{
  "type": "Feature",
  "properties": {
    "gn:country":"CH",
    "gn:fcode":"PPL",
    "gn:population":35,
    "iso:country":"CH",
    "qs_pg:aaroncc":"CH",
    "qs_pg:gn_country":"CH",
    "qs_pg:gn_fcode":"PPL",
    "qs_pg:gn_pop":35,
    "qs_pg:name":"Sedel",
    "qs_pg:name_adm0":"Schweiz",
    "qs_pg:name_adm1":"Kanton Luzern",
    "qs_pg:photos_9k":1,
    "qs_pg:photos_9r":4,
    "qs_pg:photos_all":184,
    "qs_pg:photos_sr":0,
    "qs_pg:pop_sr":1,
    "qs_pg:qs_pg_placetype":"locality",
    "qs_pg:qs_pg_placetype_gp":"Town",
    "qs_pg:woe_adm0":23424957,
    "woe:adm0_id":23424957,
    "woe:name_adm0":"Schweiz",
    "woe:name_adm1":"Kanton Luzern",
    "woe:placetype":"Town",
    "wof:name":"Sedel",
    "wof:placetype":"neighbourhood",
    "wof:population":35
},
  "geometry": {"coordinates":[8.65517,47.18105],"type":"Point"}
}