{
  "type": "Feature",
  "properties": {
    "gn:gn_country":"CH",
    "gn:gn_fcode":"PPL",
    "gn:gn_pop":849,
    "gn:population":849,
    "iso:country":"CH",
    "name:cat_x_preferred":[
        "Schlossrued"
    ],
    "name:ces_x_preferred":[
        "Schlossrued"
    ],
    "name:cym_x_preferred":[
        "Schlossrued"
    ],
    "name:deu_x_preferred":[
        "Schlossrued"
    ],
    "name:eng_x_preferred":[
        "Schlossrued"
    ],
    "name:epo_x_preferred":[
        "Schlossrued"
    ],
    "name:eus_x_preferred":[
        "Schlossrued"
    ],
    "name:fra_x_preferred":[
        "Schlossrued"
    ],
    "name:glg_x_preferred":[
        "Schlossrued"
    ],
    "name:gsw_x_preferred":[
        "Schlossrued"
    ],
    "name:hun_x_preferred":[
        "Schlossrued"
    ],
    "name:ita_x_preferred":[
        "Schlossrued"
    ],
    "name:kaz_x_preferred":[
        "\u0428\u043b\u043e\u0441\u0440\u044e\u0434"
    ],
    "name:lmo_x_preferred":[
        "Schlossrued"
    ],
    "name:msa_x_preferred":[
        "Schlossrued"
    ],
    "name:nld_x_preferred":[
        "Schlossrued"
    ],
    "name:nno_x_preferred":[
        "Schlossrued"
    ],
    "name:oci_x_preferred":[
        "Schlossrued"
    ],
    "name:pms_x_preferred":[
        "Schlossrued"
    ],
    "name:pol_x_preferred":[
        "Schlossrued"
    ],
    "name:por_x_preferred":[
        "Schlossrued"
    ],
    "name:rus_x_preferred":[
        "\u0428\u043b\u043e\u0441\u0440\u044e\u0434"
    ],
    "name:spa_x_preferred":[
        "Schlossrued"
    ],
    "name:sqi_x_preferred":[
        "Schlossrued"
    ],
    "name:swe_x_preferred":[
        "Schlossrued"
    ],
    "name:uzb_x_preferred":[
        "Schlossrued"
    ],
    "name:vol_x_preferred":[
        "Schlossrued"
    ],
    "name:war_x_preferred":[
        "Schlossrued"
    ],
    "name:zho_x_preferred":[
        "\u65bd\u6d1b\u65af\u5442\u5fb7"
    ],
    "qs_pg:aaroncc":"CH",
    "qs_pg:gn_country":"CH",
    "qs_pg:gn_fcode":"PPL",
    "qs_pg:gn_pop":849,
    "qs_pg:name":"Schlossrued",
    "qs_pg:photos_9r":0,
    "qs_pg:photos_sr":0,
    "qs_pg:pop_sr":2,
    "qs_pg:qs_pg_placetype":"locality",
    "wof:name":"Schlossrued",
    "wof:placetype":"locality",
    "wof:population":849
},
  "geometry": {"coordinates":[8.0884,47.29119],"type":"Point"}
}