{
  "type": "Feature",
  "properties": {
    "gn:gn_country":"CH",
    "gn:gn_fcode":"PPL",
    "gn:gn_pop":0,
    "iso:country":"CH",
    "name:cat_x_preferred":[
        "Trin"
    ],
    "name:deu_x_preferred":[
        "Trin"
    ],
    "name:eng_x_preferred":[
        "Trin"
    ],
    "name:epo_x_preferred":[
        "Trin"
    ],
    "name:eus_x_preferred":[
        "Trin"
    ],
    "name:fra_x_preferred":[
        "Trin"
    ],
    "name:hun_x_preferred":[
        "Trin"
    ],
    "name:ita_x_preferred":[
        "Trin"
    ],
    "name:kaz_x_preferred":[
        "\u0422\u0440\u0438\u043d"
    ],
    "name:lat_x_preferred":[
        "Turunnius"
    ],
    "name:lmo_x_preferred":[
        "Trin"
    ],
    "name:msa_x_preferred":[
        "Trin"
    ],
    "name:nld_x_preferred":[
        "Trin"
    ],
    "name:nno_x_preferred":[
        "Trin"
    ],
    "name:oci_x_preferred":[
        "Trin"
    ],
    "name:pms_x_preferred":[
        "Trin"
    ],
    "name:por_x_preferred":[
        "Trin"
    ],
    "name:roh_x_preferred":[
        "Trin"
    ],
    "name:rus_x_preferred":[
        "\u0422\u0440\u0438\u043d"
    ],
    "name:spa_x_preferred":[
        "Trin"
    ],
    "name:sqi_x_preferred":[
        "Trin"
    ],
    "name:swe_x_preferred":[
        "Trin"
    ],
    "name:unk_x_variant":[
        "Trins Dorf"
    ],
    "name:uzb_x_preferred":[
        "Trin"
    ],
    "name:vol_x_preferred":[
        "Trin"
    ],
    "name:war_x_preferred":[
        "Trin"
    ],
    "name:zho_x_preferred":[
        "\u7279\u6797"
    ],
    "qs_pg:aaroncc":"CH",
    "qs_pg:gn_country":"CH",
    "qs_pg:gn_fcode":"PPL",
    "qs_pg:gn_pop":0,
    "qs_pg:name":"Trins",
    "qs_pg:name_adm0":"Schweiz",
    "qs_pg:name_adm1":"Kanton Graub\u00fcnden",
    "qs_pg:photos":120,
    "qs_pg:photos_1k":24,
    "qs_pg:photos_9k":1,
    "qs_pg:photos_9r":3,
    "qs_pg:photos_all":120,
    "qs_pg:photos_sr":3,
    "qs_pg:pop_sr":0,
    "qs_pg:qs_pg_placetype":"locality",
    "qs_pg:qs_pg_placetype_gp":"Town",
    "qs_pg:woe_adm0":23424957,
    "woe:adm0_id":23424957,
    "woe:name_adm0":"Schweiz",
    "woe:name_adm1":"Kanton Graub\u00fcnden",
    "woe:placetype":"Town",
    "wof:name":"Trins",
    "wof:placetype":"locality"
},
  "geometry": {"coordinates":[9.36164,46.82834],"type":"Point"}
}