{
  "type": "Feature",
  "properties": {
    "gn:admin1_code":"BE",
    "gn:admin2_code":"244.0",
    "gn:admin3_code":"341.0",
    "gn:asciiname":"Cholrueti",
    "gn:country_code":"CH",
    "gn:dem":430,
    "gn:feature_class":"P",
    "gn:feature_code":"PPLL",
    "gn:name":"Cholr\u00fcti",
    "gn:population":0,
    "gn:timezone":"Europe/Zurich",
    "iso:country":"CH",
    "name:deu_x_preferred":[
        "Cholr\u00fcti"
    ],
    "wof:name":"Cholrueti",
    "wof:placetype":"neighbourhood"
},
  "geometry": {"coordinates":[7.75923,47.25516],"type":"Point"}
}