{
  "type": "Feature",
  "properties": {
    "gn:admin1_code":"VD",
    "gn:admin2_code":"2224.0",
    "gn:admin3_code":"5568.0",
    "gn:asciiname":"La Chaux",
    "gn:country_code":"CH",
    "gn:dem":1086,
    "gn:elevation":"1086.0",
    "gn:feature_class":"P",
    "gn:feature_code":"PPL",
    "gn:name":"La Chaux",
    "gn:population":0,
    "gn:timezone":"Europe/Zurich",
    "iso:country":"CH",
    "name:bre_x_preferred":[
        "La Chaux"
    ],
    "name:ceb_x_preferred":[
        "La Chaux"
    ],
    "name:fra_x_preferred":[
        "La Chaux"
    ],
    "name:ita_x_preferred":[
        "La Chaux"
    ],
    "name:nld_x_preferred":[
        "La Chaux"
    ],
    "name:pms_x_preferred":[
        "La Chaux"
    ],
    "name:pol_x_preferred":[
        "La Chaux"
    ],
    "name:por_x_preferred":[
        "La Chaux"
    ],
    "name:slk_x_preferred":[
        "La Chaux"
    ],
    "name:spa_x_preferred":[
        "La Chaux"
    ],
    "name:swe_x_preferred":[
        "La Chaux"
    ],
    "name:ukr_x_preferred":[
        "\u041b\u0430-\u0428\u043e"
    ],
    "wof:name":"La Chaux",
    "wof:placetype":"neighbourhood"
},
  "geometry": {"coordinates":[6.47966,46.83273],"type":"Point"}
}