{
  "type": "Feature",
  "properties": {
    "gn:admin1_code":"TI",
    "gn:admin2_code":"2105.0",
    "gn:admin3_code":"5197.0",
    "gn:asciiname":"Sovaglia",
    "gn:country_code":"CH",
    "gn:dem":291,
    "gn:feature_class":"P",
    "gn:feature_code":"PPL",
    "gn:name":"Sovaglia",
    "gn:population":0,
    "gn:timezone":"Europe/Zurich",
    "iso:country":"CH",
    "name:ita_x_preferred":[
        "Sovaglia"
    ],
    "wof:name":"Sovaglia",
    "wof:placetype":"neighbourhood"
},
  "geometry": {"coordinates":[8.9816,45.92758],"type":"Point"}
}