{
  "type": "Feature",
  "properties": {
    "gn:admin1_code":"TI",
    "gn:admin2_code":"2105.0",
    "gn:admin3_code":"5202.0",
    "gn:asciiname":"Bruciata",
    "gn:country_code":"CH",
    "gn:dem":295,
    "gn:feature_class":"P",
    "gn:feature_code":"PPL",
    "gn:name":"Bruciata",
    "gn:population":0,
    "gn:timezone":"Europe/Rome",
    "iso:country":"CH",
    "name:ita_x_preferred":[
        "Bruciata"
    ],
    "wof:name":"Bruciata",
    "wof:placetype":"neighbourhood"
},
  "geometry": {"coordinates":[8.82251,45.99362],"type":"Point"}
}