{
  "type": "Feature",
  "properties": {
    "gn:admin1_code":"TG",
    "gn:admin2_code":"2012.0",
    "gn:admin3_code":"4831.0",
    "gn:asciiname":"Tonisbaerg",
    "gn:country_code":"CH",
    "gn:dem":503,
    "gn:feature_class":"P",
    "gn:feature_code":"PPLL",
    "gn:name":"Tonisb\u00e4rg",
    "gn:population":0,
    "gn:timezone":"Europe/Zurich",
    "iso:country":"CH",
    "name:deu_x_preferred":[
        "Tonisb\u00e4rg"
    ],
    "wof:name":"Tonisbaerg",
    "wof:placetype":"locality"
},
  "geometry": {"coordinates":[9.01398,47.61783],"type":"Point"}
}