{
  "type": "Feature",
  "properties": {
    "gn:admin1_code":"SG",
    "gn:admin2_code":"1726.0",
    "gn:admin3_code":"3342.0",
    "gn:asciiname":"Walde",
    "gn:country_code":"CH",
    "gn:dem":863,
    "gn:elevation":"838.0",
    "gn:feature_class":"P",
    "gn:feature_code":"PPL",
    "gn:name":"Walde",
    "gn:population":0,
    "gn:timezone":"Europe/Zurich",
    "iso:country":"CH",
    "name:deu_x_preferred":[
        "Walde SG"
    ],
    "wof:name":"Walde",
    "wof:placetype":"locality"
},
  "geometry": {"coordinates":[9.01222,47.27176],"type":"Point"}
}