{
  "type": "Feature",
  "properties": {
    "gn:admin1_code":"AG",
    "gn:admin2_code":"1911.0",
    "gn:admin3_code":"4309.0",
    "gn:asciiname":"Propstberg",
    "gn:country_code":"CH",
    "gn:dem":455,
    "gn:feature_class":"P",
    "gn:feature_code":"PPLL",
    "gn:name":"Propstberg",
    "gn:population":0,
    "gn:timezone":"Europe/Zurich",
    "iso:country":"CH",
    "name:deu_x_preferred":[
        "Propstberg"
    ],
    "wof:name":"Propstberg",
    "wof:placetype":"neighbourhood"
},
  "geometry": {"coordinates":[8.26629,47.57811],"type":"Point"}
}