{
  "type": "Feature",
  "properties": {
    "gn:admin1_code":"VS",
    "gn:admin2_code":"2302.0",
    "gn:admin3_code":"6023.0",
    "gn:asciiname":"Erde",
    "gn:country_code":"CH",
    "gn:dem":834,
    "gn:feature_class":"P",
    "gn:feature_code":"PPL",
    "gn:name":"Erde",
    "gn:population":0,
    "gn:timezone":"Europe/Zurich",
    "iso:country":"CH",
    "wof:name":"Erde",
    "wof:placetype":"locality"
},
  "geometry": {"coordinates":[7.28763,46.23881],"type":"Point"}
}