{
  "type": "Feature",
  "properties": {
    "gn:gn_country":"CH",
    "gn:gn_fcode":"ADM3",
    "gn:gn_pop":366,
    "gn:population":386,
    "iso:country":"CH",
    "name:alb_x_preferred":[
        "R\u00fcmlingen"
    ],
    "name:baq_x_preferred":[
        "R\u00fcmlingen"
    ],
    "name:cat_x_preferred":[
        "R\u00fcmlingen"
    ],
    "name:chi_x_preferred":[
        "\u5442\u59c6\u6797\u6839"
    ],
    "name:chv_x_preferred":[
        "\u0420\u044e\u043c\u043b\u0438\u043d\u0433\u0435\u043d"
    ],
    "name:dut_x_preferred":[
        "R\u00fcmlingen"
    ],
    "name:eng_x_preferred":[
        "R\u00fcmlingen"
    ],
    "name:epo_x_preferred":[
        "R\u00fcmlingen"
    ],
    "name:fre_x_preferred":[
        "R\u00fcmlingen"
    ],
    "name:ger_x_preferred":[
        "R\u00fcmlingen"
    ],
    "name:gsw_x_preferred":[
        "R\u00fcmlike"
    ],
    "name:hun_x_preferred":[
        "R\u00fcmlingen"
    ],
    "name:ita_x_preferred":[
        "R\u00fcmlingen"
    ],
    "name:kaz_x_preferred":[
        "\u0420\u044e\u043c\u043b\u0438\u043d\u0433\u0435\u043d"
    ],
    "name:lmo_x_preferred":[
        "R\u00fcmlingen"
    ],
    "name:may_x_preferred":[
        "R\u00fcmlingen"
    ],
    "name:nno_x_preferred":[
        "R\u00fcmlingen"
    ],
    "name:oci_x_preferred":[
        "R\u00fcmlingen"
    ],
    "name:rus_x_preferred":[
        "\u0420\u044e\u043c\u043b\u0438\u043d\u0433\u0435\u043d"
    ],
    "name:spa_x_preferred":[
        "R\u00fcmlingen"
    ],
    "name:swe_x_preferred":[
        "R\u00fcmlingen"
    ],
    "name:uzb_x_preferred":[
        "R\u00fcmlingen"
    ],
    "name:vol_x_preferred":[
        "R\u00fcmlingen"
    ],
    "name:war_x_preferred":[
        "R\u00fcmlingen"
    ],
    "qs_pg:aaroncc":"CH",
    "qs_pg:gn_country":"CH",
    "qs_pg:gn_fcode":"ADM3",
    "qs_pg:gn_pop":366,
    "qs_pg:name":"R\u00fcmlingen",
    "qs_pg:name_adm0":"Schweiz",
    "qs_pg:name_adm1":"Kanton Basel-Land",
    "qs_pg:photos":19,
    "qs_pg:photos_1k":4,
    "qs_pg:photos_9k":1,
    "qs_pg:photos_9r":1,
    "qs_pg:photos_all":19,
    "qs_pg:photos_sr":1,
    "qs_pg:pop_sr":2,
    "qs_pg:qs_pg_placetype":"locality",
    "qs_pg:qs_pg_placetype_gp":"Town",
    "qs_pg:woe_adm0":23424957,
    "woe:adm0_id":23424957,
    "woe:name_adm0":"Schweiz",
    "woe:name_adm1":"Kanton Basel-Land",
    "woe:placetype":"Town",
    "wof:name":"R\u00fcmlingen",
    "wof:placetype":"locality",
    "wof:population":386
},
  "geometry": {"coordinates":[7.85671,47.42712],"type":"Point"}
}