{
  "type": "Feature",
  "properties": {
    "gn:admin1_code":"AG",
    "gn:admin2_code":"1908.0",
    "gn:admin3_code":"4224.0",
    "gn:asciiname":"Brunnwil",
    "gn:country_code":"CH",
    "gn:dem":702,
    "gn:elevation":"719.0",
    "gn:feature_class":"P",
    "gn:feature_code":"PPL",
    "gn:name":"Brunnwil",
    "gn:population":0,
    "gn:timezone":"Europe/Zurich",
    "iso:country":"CH",
    "wof:name":"Brunnwil",
    "wof:placetype":"neighbourhood"
},
  "geometry": {"coordinates":[8.32936,47.23335],"type":"Point"}
}