{
  "type": "Feature",
  "properties": {
    "gn:admin1_code":"VD",
    "gn:admin2_code":"2222.0",
    "gn:admin3_code":"5688.0",
    "gn:asciiname":"Syens",
    "gn:country_code":"CH",
    "gn:dem":593,
    "gn:feature_class":"P",
    "gn:feature_code":"PPL",
    "gn:name":"Syens",
    "gn:population":0,
    "gn:timezone":"Europe/Zurich",
    "iso:country":"CH",
    "name:zho_x_preferred":[
        "\u897f\u626c"
    ],
    "wof:name":"Syens",
    "wof:placetype":"locality"
},
  "geometry": {"coordinates":[6.77689,46.64406],"type":"Point"}
}