{
  "type": "Feature",
  "properties": {
    "gn:admin1_code":"LU",
    "gn:admin2_code":"315.0",
    "gn:admin3_code":"1128.0",
    "gn:asciiname":"Altkidli",
    "gn:country_code":"CH",
    "gn:dem":624,
    "gn:feature_class":"P",
    "gn:feature_code":"PPLL",
    "gn:name":"Altkidli",
    "gn:population":0,
    "gn:timezone":"Europe/Zurich",
    "iso:country":"CH",
    "name:deu_x_preferred":[
        "Altkidli"
    ],
    "wof:name":"Altkidli",
    "wof:placetype":"neighbourhood"
},
  "geometry": {"coordinates":[8.05622,47.16228],"type":"Point"}
}