{
  "type": "Feature",
  "properties": {
    "gn:admin1_code":"TG",
    "gn:admin2_code":"2015.0",
    "gn:admin3_code":"4881.0",
    "gn:asciiname":"Wolfikon (TG)",
    "gn:country_code":"CH",
    "gn:dem":603,
    "gn:elevation":"607.0",
    "gn:feature_class":"P",
    "gn:feature_code":"PPL",
    "gn:name":"Wolfikon (TG)",
    "gn:population":0,
    "gn:timezone":"Europe/Zurich",
    "iso:country":"CH",
    "name:eng_x_preferred":[
        "Wolfikon"
    ],
    "wof:name":"Wolfikon",
    "wof:placetype":"neighbourhood"
},
  "geometry": {"coordinates":[9.01011,47.55038],"type":"Point"}
}