{
  "type": "Feature",
  "properties": {
    "gn:admin1_code":"BL",
    "gn:admin2_code":"1305.0",
    "gn:admin3_code":"2888.0",
    "gn:asciiname":"Baerenwil",
    "gn:country_code":"CH",
    "gn:dem":792,
    "gn:elevation":"778.0",
    "gn:feature_class":"P",
    "gn:feature_code":"PPL",
    "gn:name":"B\u00e4renwil",
    "gn:population":0,
    "gn:timezone":"Europe/Zurich",
    "iso:country":"CH",
    "wof:name":"Baerenwil",
    "wof:placetype":"neighbourhood"
},
  "geometry": {"coordinates":[7.78951,47.3407],"type":"Point"}
}