{
  "type": "Feature",
  "properties": {
    "gn:admin1_code":"VD",
    "gn:admin2_code":"2225.0",
    "gn:admin3_code":"5586.0",
    "gn:asciiname":"La Vulliette",
    "gn:country_code":"CH",
    "gn:dem":838,
    "gn:feature_class":"P",
    "gn:feature_code":"PPL",
    "gn:name":"La Vulliette",
    "gn:population":0,
    "gn:timezone":"Europe/Zurich",
    "iso:country":"CH",
    "wof:name":"La Vulliette",
    "wof:placetype":"neighbourhood"
},
  "geometry": {"coordinates":[6.68303,46.55734],"type":"Point"}
}