{
  "type": "Feature",
  "properties": {
    "gn:admin1_code":"TI",
    "gn:admin2_code":"2105.0",
    "gn:admin3_code":"5236.0",
    "gn:asciiname":"Casaccia",
    "gn:country_code":"CH",
    "gn:dem":282,
    "gn:feature_class":"P",
    "gn:feature_code":"PPL",
    "gn:name":"Casaccia",
    "gn:population":0,
    "gn:timezone":"Europe/Zurich",
    "iso:country":"CH",
    "name:ita_x_preferred":[
        "Casaccia"
    ],
    "wof:name":"Casaccia",
    "wof:placetype":"locality"
},
  "geometry": {"coordinates":[8.90026,45.9649],"type":"Point"}
}