{
  "type": "Feature",
  "properties": {
    "gn:admin1_code":"LU",
    "gn:admin2_code":"315.0",
    "gn:admin3_code":"1135.0",
    "gn:asciiname":"Sonnsite",
    "gn:country_code":"CH",
    "gn:dem":990,
    "gn:feature_class":"P",
    "gn:feature_code":"PPLL",
    "gn:name":"Sonnsite",
    "gn:population":0,
    "gn:timezone":"Europe/Zurich",
    "iso:country":"CH",
    "name:deu_x_preferred":[
        "Sonnsite"
    ],
    "wof:lang_x_official":[
        "deu",
        "fra",
        "gsw",
        "ita"
    ],
    "wof:lang_x_spoken":[
        "deu",
        "fra",
        "gsw",
        "ita",
        "roh"
    ],
    "wof:name":"Sonnsite",
    "wof:placetype":"neighbourhood"
},
  "geometry": {"coordinates":[7.91114,47.0368],"type":"Point"}
}