{
  "type": "Feature",
  "properties": {
    "gn:admin1_code":"SH",
    "gn:admin2_code":"1403.0",
    "gn:admin3_code":"2938.0",
    "gn:asciiname":"Sandgruben",
    "gn:country_code":"CH",
    "gn:dem":404,
    "gn:feature_class":"P",
    "gn:feature_code":"PPLL",
    "gn:name":"Sandgruben",
    "gn:population":0,
    "gn:timezone":"Europe/Zurich",
    "iso:country":"CH",
    "name:deu_x_preferred":[
        "Sandgruben"
    ],
    "wof:name":"Sandgruben",
    "wof:placetype":"locality"
},
  "geometry": {"coordinates":[8.5676,47.58754],"type":"Point"}
}