{
  "type": "Feature",
  "properties": {
    "gn:admin1_code":"JU",
    "gn:admin2_code":"2602.0",
    "gn:admin3_code":"6751.0",
    "gn:asciiname":"Les Sairains",
    "gn:country_code":"CH",
    "gn:dem":953,
    "gn:elevation":"935.0",
    "gn:feature_class":"P",
    "gn:feature_code":"PPL",
    "gn:name":"Les Sairains",
    "gn:population":0,
    "gn:timezone":"Europe/Zurich",
    "iso:country":"CH",
    "wof:lang_x_official":[
        "deu",
        "fra",
        "gsw",
        "ita"
    ],
    "wof:lang_x_spoken":[
        "deu",
        "fra",
        "gsw",
        "ita",
        "roh"
    ],
    "wof:name":"Les Sairains",
    "wof:placetype":"neighbourhood"
},
  "geometry": {"coordinates":[7.08318,47.29782],"type":"Point"}
}