{
  "type": "Feature",
  "properties": {
    "gn:gn_country":"CH",
    "gn:gn_fcode":"PPL",
    "gn:gn_pop":436,
    "gn:population":436,
    "iso:country":"CH",
    "name:bul_x_preferred":[
        "\u0412\u0438\u0441\u043e\u0438\u0435"
    ],
    "name:deu_x_preferred":[
        "Vissoie"
    ],
    "name:eng_x_preferred":[
        "Vissoie"
    ],
    "name:fra_x_preferred":[
        "Vissoie"
    ],
    "name:frp_x_preferred":[
        "Viss\u00f4ye"
    ],
    "name:ita_x_preferred":[
        "Vissoie"
    ],
    "name:nld_x_preferred":[
        "Vissoie"
    ],
    "name:pms_x_preferred":[
        "Vissoie"
    ],
    "name:por_x_preferred":[
        "Vissoie"
    ],
    "name:roh_x_preferred":[
        "Vissoie"
    ],
    "name:swe_x_preferred":[
        "Vissoie"
    ],
    "name:unk_x_variant":[
        "Vissoye"
    ],
    "name:vol_x_preferred":[
        "Vissoie"
    ],
    "qs_pg:aaroncc":"CH",
    "qs_pg:gn_country":"CH",
    "qs_pg:gn_fcode":"PPL",
    "qs_pg:gn_pop":436,
    "qs_pg:name":"Vissoie",
    "qs_pg:name_adm0":"Schweiz",
    "qs_pg:name_adm1":"Canton de Valais",
    "qs_pg:photos_9k":1,
    "qs_pg:photos_9r":1,
    "qs_pg:photos_all":2,
    "qs_pg:photos_sr":0,
    "qs_pg:pop_sr":2,
    "qs_pg:qs_pg_placetype":"locality",
    "qs_pg:qs_pg_placetype_gp":"Town",
    "qs_pg:woe_adm0":23424957,
    "woe:adm0_id":23424957,
    "woe:name_adm0":"Schweiz",
    "woe:name_adm1":"Canton de Valais",
    "woe:placetype":"Town",
    "wof:name":"Vissoie",
    "wof:placetype":"locality",
    "wof:population":436
},
  "geometry": {"coordinates":[7.58544,46.21633],"type":"Point"}
}