{
  "type": "Feature",
  "properties": {
    "gn:country":"CH",
    "gn:fcode":"PPLL",
    "gn:population":9,
    "iso:country":"CH",
    "name:ceb_x_preferred":[
        "Tobel"
    ],
    "name:deu_x_preferred":[
        "Tobel"
    ],
    "name:epo_x_preferred":[
        "Tobel"
    ],
    "qs_pg:aaroncc":"CH",
    "qs_pg:gn_country":"CH",
    "qs_pg:gn_fcode":"PPLL",
    "qs_pg:gn_pop":9,
    "qs_pg:name":"Tobel",
    "qs_pg:photos_9r":0,
    "qs_pg:photos_sr":0,
    "qs_pg:pop_sr":1,
    "qs_pg:qs_pg_placetype":"locality",
    "wof:lang_x_official":[
        "deu",
        "fra",
        "gsw",
        "ita"
    ],
    "wof:lang_x_spoken":[
        "deu",
        "fra",
        "gsw",
        "ita",
        "roh"
    ],
    "wof:name":"Tobel",
    "wof:placetype":"neighbourhood",
    "wof:population":9
},
  "geometry": {"coordinates":[8.54284,47.27456],"type":"Point"}
}