{
  "type": "Feature",
  "properties": {
    "gn:admin1_code":"BE",
    "gn:admin2_code":"243.0",
    "gn:admin3_code":"310.0",
    "gn:asciiname":"Wierezwil",
    "gn:country_code":"CH",
    "gn:dem":516,
    "gn:elevation":"521.0",
    "gn:feature_class":"P",
    "gn:feature_code":"PPL",
    "gn:name":"Wierezwil",
    "gn:population":0,
    "gn:timezone":"Europe/Zurich",
    "iso:country":"CH",
    "wof:name":"Wierezwil",
    "wof:placetype":"locality"
},
  "geometry": {"coordinates":[7.39394,47.05982],"type":"Point"}
}