{
  "type": "Feature",
  "properties": {
    "gn:admin1_code":"LU",
    "gn:admin2_code":"313.0",
    "gn:admin3_code":"1041.0",
    "gn:asciiname":"Ober-Schongau",
    "gn:country_code":"CH",
    "gn:dem":741,
    "gn:feature_class":"P",
    "gn:feature_code":"PPL",
    "gn:name":"Ober-Schongau",
    "gn:population":0,
    "gn:timezone":"Europe/Zurich",
    "iso:country":"CH",
    "wof:name":"Ober-Schongau",
    "wof:placetype":"neighbourhood"
},
  "geometry": {"coordinates":[8.27657,47.27256],"type":"Point"}
}