{
  "type": "Feature",
  "properties": {
    "iso:country":"CH",
    "name:alb_x_preferred":[
        "D\u00f6ttingen"
    ],
    "name:als_x_preferred":[
        "D\u00f6ttingen"
    ],
    "name:als_x_variant":[
        "D\u00f6ttingen AG"
    ],
    "name:cat_x_preferred":[
        "D\u00f6ttingen"
    ],
    "name:chi_x_preferred":[
        "\u5fb7\u5ef7\u6839"
    ],
    "name:deu_x_colloquial":[
        "Doettingen",
        "Dottingen"
    ],
    "name:deu_x_preferred":[
        "D\u00f6ttingen"
    ],
    "name:deu_x_variant":[
        "D\u00f6ttingen AG"
    ],
    "name:dut_x_preferred":[
        "D\u00f6ttingen"
    ],
    "name:eng_x_preferred":[
        "D\u00f6ttingen"
    ],
    "name:epo_x_preferred":[
        "D\u00f6ttingen"
    ],
    "name:epo_x_variant":[
        "D\u00f6ttingen AG"
    ],
    "name:eus_x_preferred":[
        "D\u00f6ttingen"
    ],
    "name:fre_x_preferred":[
        "D\u00f6ttingen"
    ],
    "name:ger_x_preferred":[
        "D\u00f6ttingen AG"
    ],
    "name:gre_x_preferred":[
        "\u039d\u03a4\u039f\u03a4\u03a4\u0399\u039d\u0393\u039a\u0395\u039d"
    ],
    "name:gsw_x_preferred":[
        "D\u00f6ttige AG"
    ],
    "name:hun_x_preferred":[
        "D\u00f6ttingen"
    ],
    "name:ita_x_preferred":[
        "D\u00f6ttingen"
    ],
    "name:kaz_x_preferred":[
        "\u0414\u0451\u0442\u0442\u0438\u043d\u0433\u0435\u043d"
    ],
    "name:lmo_x_preferred":[
        "D\u00f6ttingen"
    ],
    "name:may_x_preferred":[
        "D\u00f6ttingen"
    ],
    "name:nno_x_preferred":[
        "D\u00f6ttingen i Sveits"
    ],
    "name:oci_x_preferred":[
        "D\u00f6ttingen"
    ],
    "name:roh_x_preferred":[
        "D\u00f6ttingen"
    ],
    "name:rus_x_preferred":[
        "\u0414\u0451\u0442\u0442\u0438\u043d\u0433\u0435\u043d"
    ],
    "name:spa_x_preferred":[
        "D\u00f6ttingen"
    ],
    "name:swe_x_preferred":[
        "D\u00f6ttingen"
    ],
    "name:ukr_x_preferred":[
        "\u0414\u044c\u043e\u0442\u0442\u0456\u043d\u0433\u0435\u043d"
    ],
    "name:uzb_x_preferred":[
        "D\u00f6ttingen"
    ],
    "name:vie_x_preferred":[
        "D\u00f6ttingen"
    ],
    "name:vol_x_preferred":[
        "D\u00f6ttingen"
    ],
    "name:war_x_preferred":[
        "D\u00f6ttingen"
    ],
    "qs:a0":"Schweiz#Suisse#Svizzera#Svizra",
    "qs:a1":"*Aargau",
    "qs:a1r":"0",
    "qs:adm0":"Schweiz#Suisse#Svizzera#Svizra",
    "qs:la_lc":"*",
    "qs:level":"locality",
    "qs:loc":"D\u00f6ttingen",
    "qs:loc_alt":"Doettingen",
    "qs:pop":0,
    "qs:type":"buffered point",
    "wd:wordcount":28,
    "wof:lang":[
        "ger"
    ],
    "wof:name":"D\u00f6ttingen",
    "wof:placetype":"locality"
},
  "geometry": {"coordinates":[8.256001,47.573822],"type":"Point"}
}