{
  "type": "Feature",
  "properties": {
    "gn:admin1_code":"SG",
    "gn:admin2_code":"1725.0",
    "gn:admin3_code":"3296.0",
    "gn:asciiname":"Prod",
    "gn:country_code":"CH",
    "gn:dem":645,
    "gn:elevation":"626.0",
    "gn:feature_class":"P",
    "gn:feature_code":"PPL",
    "gn:name":"Prod",
    "gn:population":0,
    "gn:timezone":"Europe/Zurich",
    "iso:country":"CH",
    "wof:lang_x_official":[
        "deu",
        "fra",
        "gsw",
        "ita"
    ],
    "wof:lang_x_spoken":[
        "deu",
        "fra",
        "gsw",
        "ita",
        "roh"
    ],
    "wof:name":"Prod",
    "wof:placetype":"neighbourhood"
},
  "geometry": {"coordinates":[9.43886,47.05512],"type":"Point"}
}