{
  "type": "Feature",
  "properties": {
    "gn:admin1_code":"AG",
    "gn:admin2_code":"1902.0",
    "gn:admin3_code":"4039.0",
    "gn:asciiname":"Busslingen",
    "gn:country_code":"CH",
    "gn:dem":418,
    "gn:elevation":"410.0",
    "gn:feature_class":"P",
    "gn:feature_code":"PPL",
    "gn:name":"Busslingen",
    "gn:population":0,
    "gn:timezone":"Europe/Zurich",
    "iso:country":"CH",
    "wof:lang_x_official":[
        "deu",
        "fra",
        "gsw",
        "ita"
    ],
    "wof:lang_x_spoken":[
        "deu",
        "fra",
        "gsw",
        "ita",
        "roh"
    ],
    "wof:name":"Busslingen",
    "wof:placetype":"neighbourhood"
},
  "geometry": {"coordinates":[8.31779,47.40948],"type":"Point"}
}