{
  "type": "Feature",
  "properties": {
    "gn:admin1_code":"GE",
    "gn:admin2_code":"2500.0",
    "gn:admin3_code":"6638.0",
    "gn:asciiname":"Peney",
    "gn:country_code":"CH",
    "gn:dem":388,
    "gn:elevation":"372.0",
    "gn:feature_class":"P",
    "gn:feature_code":"PPL",
    "gn:name":"Peney",
    "gn:population":0,
    "gn:timezone":"Europe/Zurich",
    "iso:country":"CH",
    "wof:name":"Peney",
    "wof:placetype":"neighbourhood"
},
  "geometry": {"coordinates":[6.04083,46.20185],"type":"Point"}
}