{
  "type": "Feature",
  "properties": {
    "iso:country":"CH",
    "name:alb_x_preferred":[
        "Castaneda"
    ],
    "name:baq_x_preferred":[
        "Castaneda"
    ],
    "name:cat_x_preferred":[
        "Castaneda"
    ],
    "name:chi_x_preferred":[
        "\u5361\u65af\u5854\u6d85\u9054"
    ],
    "name:dut_x_preferred":[
        "Castaneda"
    ],
    "name:eng_x_preferred":[
        "Castaneda"
    ],
    "name:epo_x_preferred":[
        "Castaneda GR"
    ],
    "name:fre_x_preferred":[
        "Castaneda"
    ],
    "name:ger_x_preferred":[
        "Castaneda"
    ],
    "name:hun_x_preferred":[
        "Castaneda"
    ],
    "name:ind_x_preferred":[
        "Castaneda"
    ],
    "name:ita_x_preferred":[
        "Castaneda"
    ],
    "name:kaz_x_preferred":[
        "\u041a\u0430\u0441\u0442\u0430\u043d\u0435\u0434\u0430"
    ],
    "name:lmo_x_preferred":[
        "Castaneda"
    ],
    "name:may_x_preferred":[
        "Castaneda"
    ],
    "name:nno_x_preferred":[
        "Castaneda i Sveits"
    ],
    "name:pms_x_preferred":[
        "Castaneda"
    ],
    "name:por_x_preferred":[
        "Castaneda"
    ],
    "name:roh_x_preferred":[
        "Castaneda"
    ],
    "name:rus_x_preferred":[
        "\u041a\u0430\u0441\u0442\u0430\u043d\u0435\u0434\u0430"
    ],
    "name:spa_x_preferred":[
        "Castaneda"
    ],
    "name:swe_x_preferred":[
        "Castaneda"
    ],
    "name:uzb_x_preferred":[
        "Castaneda"
    ],
    "name:vol_x_preferred":[
        "Castaneda"
    ],
    "name:war_x_preferred":[
        "Castaneda"
    ],
    "qs_pg:aaroncc":"CH",
    "qs_pg:name":"Castaneda",
    "qs_pg:name_adm0":"Schweiz",
    "qs_pg:name_adm1":"Kanton Graub\u00fcnden",
    "qs_pg:photos":70,
    "qs_pg:photos_1k":14,
    "qs_pg:photos_9k":1,
    "qs_pg:photos_9r":2,
    "qs_pg:photos_all":70,
    "qs_pg:photos_sr":2,
    "qs_pg:pop_sr":0,
    "qs_pg:qs_pg_placetype":"locality",
    "qs_pg:qs_pg_placetype_gp":"Town",
    "qs_pg:woe_adm0":23424957,
    "woe:adm0_id":23424957,
    "woe:name_adm0":"Schweiz",
    "woe:name_adm1":"Kanton Graub\u00fcnden",
    "woe:placetype":"Town",
    "wof:name":"Castaneda",
    "wof:placetype":"locality"
},
  "geometry": {"coordinates":[9.129445,46.253873],"type":"Point"}
}