{
  "type": "Feature",
  "properties": {
    "gn:admin1_code":"LU",
    "gn:admin2_code":"313.0",
    "gn:admin3_code":"1024.0",
    "gn:asciiname":"Gerliswil",
    "gn:country_code":"CH",
    "gn:dem":498,
    "gn:feature_class":"P",
    "gn:feature_code":"PPL",
    "gn:name":"Gerliswil",
    "gn:population":0,
    "gn:timezone":"Europe/Zurich",
    "iso:country":"CH",
    "wof:name":"Gerliswil",
    "wof:placetype":"locality"
},
  "geometry": {"coordinates":[8.26607,47.07885],"type":"Point"}
}