{
  "type": "Feature",
  "properties": {
    "gn:admin1_code":"NW",
    "gn:admin2_code":"700.0",
    "gn:admin3_code":"1502.0",
    "gn:asciiname":"Faden",
    "gn:country_code":"CH",
    "gn:dem":465,
    "gn:feature_class":"P",
    "gn:feature_code":"PPL",
    "gn:name":"Faden",
    "gn:population":0,
    "gn:timezone":"Europe/Zurich",
    "iso:country":"CH",
    "wof:name":"Faden",
    "wof:placetype":"locality"
},
  "geometry": {"coordinates":[8.40489,46.96863],"type":"Point"}
}