{
  "type": "Feature",
  "properties": {
    "gn:admin1_code":"FR",
    "gn:admin2_code":"1003.0",
    "gn:admin3_code":"2163.0",
    "gn:asciiname":"La Monse",
    "gn:country_code":"CH",
    "gn:dem":982,
    "gn:feature_class":"P",
    "gn:feature_code":"PPL",
    "gn:name":"La Monse",
    "gn:population":0,
    "gn:timezone":"Europe/Zurich",
    "iso:country":"CH",
    "name:fra_x_preferred":[
        "La Monse"
    ],
    "wof:name":"La Monse",
    "wof:placetype":"neighbourhood"
},
  "geometry": {"coordinates":[7.15672,46.60982],"type":"Point"}
}