{
  "type": "Feature",
  "properties": {
    "gn:country":"CH",
    "gn:fcode":"PPLX",
    "gn:population":1583,
    "iso:country":"CH",
    "name:eng_x_preferred":[
        "D\u00e4llikon (Dorf)"
    ],
    "name:eng_x_variant":[
        "D\u00e4llikon / D\u00e4llikon (Dorf)"
    ],
    "qs_pg:aaroncc":"CH",
    "qs_pg:gn_country":"CH",
    "qs_pg:gn_fcode":"PPLX",
    "qs_pg:gn_pop":1583,
    "qs_pg:name":"D\u00e4llikon / D\u00e4llikon (Dorf)",
    "qs_pg:photos_9r":0,
    "qs_pg:photos_sr":0,
    "qs_pg:pop_sr":3,
    "qs_pg:qs_pg_placetype":"neighbourhood",
    "wof:lang_x_official":[
        "deu",
        "fra",
        "gsw",
        "ita"
    ],
    "wof:lang_x_spoken":[
        "deu",
        "fra",
        "gsw",
        "ita",
        "roh"
    ],
    "wof:name":"D\u00e4llikon (Dorf)",
    "wof:placetype":"neighbourhood",
    "wof:population":1583
},
  "geometry": {"coordinates":[8.43813,47.43983],"type":"Point"}
}