{
  "type": "Feature",
  "properties": {
    "gn:gn_country":"CH",
    "gn:gn_fcode":"PPL",
    "gn:gn_pop":31,
    "gn:population":31,
    "iso:country":"CH",
    "qs_pg:aaroncc":"CH",
    "qs_pg:gn_country":"CH",
    "qs_pg:gn_fcode":"PPL",
    "qs_pg:gn_pop":31,
    "qs_pg:name":"Ober-Chr\u00fczlen",
    "qs_pg:photos_9r":0,
    "qs_pg:photos_sr":0,
    "qs_pg:pop_sr":1,
    "qs_pg:qs_pg_placetype":"locality",
    "wof:name":"Ober-Chr\u00fczlen",
    "wof:placetype":"neighbourhood",
    "wof:population":31
},
  "geometry": {"coordinates":[8.70168,47.27441],"type":"Point"}
}