{
  "type": "Feature",
  "properties": {
    "iso:country":"CH",
    "name:fra_x_preferred":[
        "Plage de Vidy"
    ],
    "qs:gn_adm0_cc":"CH",
    "qs:gn_local":2659994,
    "qs:gn_nam_loc":"Lausanne, Lausanne, Canton de Vaud, CH",
    "qs:gn_namadm1":"VD",
    "qs:local_max":7240,
    "qs:local_sum":38363,
    "qs:localhoods":45,
    "qs:name":"Plage de Vidy",
    "qs:name_adm0":"Schweiz",
    "qs:name_adm1":"Canton de Vaud",
    "qs:name_adm2":"Lausanne",
    "qs:name_lau":"Lausanne",
    "qs:name_local":"Lausanne",
    "qs:photo_max":161,
    "qs:photo_sum":468,
    "qs:placetype":"Suburb",
    "qs:quad_count":17,
    "qs:woe_adm0":23424957,
    "qs:woe_adm1":2347105,
    "qs:woe_adm2":12593172,
    "qs:woe_lau":12682890,
    "qs:woe_local":783058,
    "qs:woe_ver":"7.10.0",
    "wof:lang_x_official":[
        "deu",
        "fra",
        "gsw",
        "ita"
    ],
    "wof:lang_x_spoken":[
        "deu",
        "fra",
        "gsw",
        "ita",
        "roh"
    ],
    "wof:name":"Plage de Vidy",
    "wof:placetype":"neighbourhood"
},
  "geometry": {"coordinates":[6.589837,46.518093],"type":"Point"}
}