{
  "type": "Feature",
  "properties": {
    "gn:admin1_code":"GR",
    "gn:admin2_code":"1850.0",
    "gn:admin3_code":"3618.0",
    "gn:asciiname":"Uors",
    "gn:country_code":"CH",
    "gn:dem":920,
    "gn:feature_class":"P",
    "gn:feature_code":"PPL",
    "gn:name":"Uors",
    "gn:population":0,
    "gn:timezone":"Europe/Zurich",
    "iso:country":"CH",
    "name:deu_x_preferred":[
        "Furth"
    ],
    "name:und_x_variant":[
        "Uors (Lumnezia)"
    ],
    "wof:name":"Uors",
    "wof:placetype":"locality"
},
  "geometry": {"coordinates":[9.18343,46.70202000000001],"type":"Point"}
}