{
  "type": "Feature",
  "properties": {
    "gn:admin1_code":"BE",
    "gn:admin2_code":"245.0",
    "gn:admin3_code":"901.0",
    "gn:asciiname":"AEschaubad",
    "gn:country_code":"CH",
    "gn:dem":924,
    "gn:feature_class":"P",
    "gn:feature_code":"PPLL",
    "gn:name":"\u00c4schaubad",
    "gn:population":0,
    "gn:timezone":"Europe/Zurich",
    "iso:country":"CH",
    "name:deu_x_preferred":[
        "\u00c4schaubad"
    ],
    "wof:name":"AEschaubad",
    "wof:placetype":"neighbourhood"
},
  "geometry": {"coordinates":[7.78638,46.9142],"type":"Point"}
}