{
  "type": "Feature",
  "properties": {
    "gn:gn_country":"CH",
    "gn:gn_fcode":"PPLX",
    "gn:gn_pop":80,
    "gn:population":80,
    "iso:country":"CH",
    "name:eng_x_preferred":[
        "Haldenacher"
    ],
    "name:eng_x_variant":[
        "Birmensdorf / Haldenacher"
    ],
    "name:unk_x_variant":[
        "Haldenacher"
    ],
    "qs_pg:aaroncc":"CH",
    "qs_pg:gn_country":"CH",
    "qs_pg:gn_fcode":"PPLX",
    "qs_pg:gn_pop":80,
    "qs_pg:name":"Birmensdorf / Haldenacher",
    "qs_pg:photos_9r":0,
    "qs_pg:photos_sr":0,
    "qs_pg:pop_sr":1,
    "qs_pg:qs_pg_placetype":"neighbourhood",
    "wof:name":"Haldenacher",
    "wof:placetype":"neighbourhood",
    "wof:population":80
},
  "geometry": {"coordinates":[8.43956,47.35634],"type":"Point"}
}