{
  "type": "Feature",
  "properties": {
    "gn:admin1_code":"TG",
    "gn:admin2_code":"2012.0",
    "gn:admin3_code":"4816.0",
    "gn:asciiname":"Goetschenhaeusli",
    "gn:country_code":"CH",
    "gn:dem":550,
    "gn:feature_class":"P",
    "gn:feature_code":"PPLL",
    "gn:name":"G\u00f6tschenh\u00e4usli",
    "gn:population":0,
    "gn:timezone":"Europe/Zurich",
    "iso:country":"CH",
    "name:deu_x_preferred":[
        "G\u00f6tschenh\u00e4usli"
    ],
    "wof:name":"Goetschenhaeusli",
    "wof:placetype":"neighbourhood"
},
  "geometry": {"coordinates":[8.97972,47.64506],"type":"Point"}
}