{
  "type": "Feature",
  "properties": {
    "gn:admin1_code":"LU",
    "gn:admin2_code":"314.0",
    "gn:admin3_code":"1084.0",
    "gn:asciiname":"Hellacher",
    "gn:country_code":"CH",
    "gn:dem":685,
    "gn:feature_class":"P",
    "gn:feature_code":"PPLL",
    "gn:name":"Hellacher",
    "gn:population":0,
    "gn:timezone":"Europe/Zurich",
    "iso:country":"CH",
    "name:deu_x_preferred":[
        "Hellacher"
    ],
    "wof:name":"Hellacher",
    "wof:placetype":"neighbourhood"
},
  "geometry": {"coordinates":[8.18227,47.16119000000001],"type":"Point"}
}