{
  "type": "Feature",
  "properties": {
    "iso:country":"CH",
    "name:bre_x_preferred":[
        "Beaulieu"
    ],
    "name:cat_x_preferred":[
        "Beaulieu"
    ],
    "name:ceb_x_preferred":[
        "Beaulieu"
    ],
    "name:deu_x_preferred":[
        "Beaulieu"
    ],
    "name:epo_x_preferred":[
        "Beaulieu"
    ],
    "name:fra_x_preferred":[
        "Beaulieu"
    ],
    "name:ind_x_preferred":[
        "Beaulieu"
    ],
    "name:ita_x_preferred":[
        "Beaulieu"
    ],
    "name:jpn_x_preferred":[
        "\u30dc\u30fc\u30ea\u30e5\u30fc"
    ],
    "name:lmo_x_preferred":[
        "Beaulieu"
    ],
    "name:nds_x_preferred":[
        "Beaulieu"
    ],
    "name:nld_x_preferred":[
        "Beaulieu"
    ],
    "name:oci_x_preferred":[
        "Beaulieu"
    ],
    "name:pms_x_preferred":[
        "Beaulieu"
    ],
    "name:pol_x_preferred":[
        "Beaulieu"
    ],
    "name:por_x_preferred":[
        "Beaulieu"
    ],
    "name:ron_x_preferred":[
        "Beaulieu"
    ],
    "name:rus_x_preferred":[
        "\u0411\u043e\u043b\u044c\u0451"
    ],
    "name:sco_x_preferred":[
        "Beaulieu"
    ],
    "name:slk_x_preferred":[
        "Beaulieu"
    ],
    "name:spa_x_preferred":[
        "Beaulieu"
    ],
    "name:sqi_x_preferred":[
        "Beaulieu"
    ],
    "name:srp_x_preferred":[
        "\u0411\u043e\u043b\u0438\u0458\u0435"
    ],
    "name:swe_x_preferred":[
        "Beaulieu"
    ],
    "name:ukr_x_preferred":[
        "\u0411\u043e\u043b\u044c\u0454"
    ],
    "name:vec_x_preferred":[
        "Beaulieu"
    ],
    "wof:name":"Beaulieu",
    "wof:placetype":"neighbourhood"
},
  "geometry": {"coordinates":[6.137041,46.215253],"type":"Point"}
}