{
  "type": "Feature",
  "properties": {
    "gn:admin1_code":"BE",
    "gn:admin2_code":"246.0",
    "gn:admin3_code":"620.0",
    "gn:asciiname":"Alterswil",
    "gn:country_code":"CH",
    "gn:dem":844,
    "gn:feature_class":"P",
    "gn:feature_code":"PPLL",
    "gn:name":"Alterswil",
    "gn:population":0,
    "gn:timezone":"Europe/Zurich",
    "iso:country":"CH",
    "name:als_x_preferred":[
        "Alterswil"
    ],
    "name:cat_x_preferred":[
        "Alterswil"
    ],
    "name:ceb_x_preferred":[
        "Alterswil"
    ],
    "name:deu_x_preferred":[
        "Alterswil"
    ],
    "name:epo_x_preferred":[
        "Alterswil"
    ],
    "name:eus_x_preferred":[
        "Alterswil"
    ],
    "name:fra_x_preferred":[
        "Alterswil"
    ],
    "name:ita_x_preferred":[
        "Alterswil"
    ],
    "name:lmo_x_preferred":[
        "Alterswil"
    ],
    "name:msa_x_preferred":[
        "Alterswil"
    ],
    "name:nld_x_preferred":[
        "Alterswil"
    ],
    "name:nno_x_preferred":[
        "Alterswil"
    ],
    "name:pms_x_preferred":[
        "Alterswil"
    ],
    "name:por_x_preferred":[
        "Alterswil"
    ],
    "name:roh_x_preferred":[
        "Alterswil"
    ],
    "name:spa_x_preferred":[
        "Alterswil"
    ],
    "name:sqi_x_preferred":[
        "Alterswil"
    ],
    "name:swe_x_preferred":[
        "Alterswil"
    ],
    "name:vol_x_preferred":[
        "Alterswil"
    ],
    "name:war_x_preferred":[
        "Alterswil"
    ],
    "name:zho_x_preferred":[
        "\u963f\u723e\u7279\u65af\u7dad\u723e"
    ],
    "wof:name":"Alterswil",
    "wof:placetype":"neighbourhood"
},
  "geometry": {"coordinates":[7.66386,46.91507],"type":"Point"}
}