{
  "type": "Feature",
  "properties": {
    "gn:gn_country":"CH",
    "gn:gn_fcode":"PPL",
    "gn:gn_pop":0,
    "iso:country":"CH",
    "name:dut_x_preferred":[
        "Les Haud\u00e8res"
    ],
    "name:eng_x_preferred":[
        "Les Haud\u00e8res"
    ],
    "name:ger_x_preferred":[
        "Les Haud\u00e8res"
    ],
    "name:unk_x_variant":[
        "Les Haud\u00e8res"
    ],
    "qs_pg:aaroncc":"CH",
    "qs_pg:gn_country":"CH",
    "qs_pg:gn_fcode":"PPL",
    "qs_pg:gn_pop":0,
    "qs_pg:name":"Haud\u00e8res",
    "qs_pg:name_adm0":"Schweiz",
    "qs_pg:name_adm1":"Canton de Valais",
    "qs_pg:photos_9r":0,
    "qs_pg:photos_sr":0,
    "qs_pg:pop_sr":0,
    "qs_pg:qs_pg_placetype":"locality",
    "qs_pg:qs_pg_placetype_gp":"Town",
    "qs_pg:woe_adm0":23424957,
    "woe:adm0_id":23424957,
    "woe:name_adm0":"Schweiz",
    "woe:name_adm1":"Canton de Valais",
    "woe:placetype":"Town",
    "wof:name":"Haud\u00e8res",
    "wof:placetype":"locality"
},
  "geometry": {"coordinates":[7.50815,46.08398],"type":"Point"}
}