{
  "type": "Feature",
  "properties": {
    "gn:admin1_code":"ZG",
    "gn:admin2_code":"900.0",
    "gn:admin3_code":"1706.0",
    "gn:asciiname":"Bietenberg",
    "gn:country_code":"CH",
    "gn:dem":916,
    "gn:feature_class":"P",
    "gn:feature_code":"PPLL",
    "gn:name":"Bietenberg",
    "gn:population":0,
    "gn:timezone":"Europe/Zurich",
    "iso:country":"CH",
    "name:deu_x_preferred":[
        "Bietenberg"
    ],
    "wof:name":"Bietenberg",
    "wof:placetype":"locality"
},
  "geometry": {"coordinates":[8.64772,47.11984],"type":"Point"}
}