{
  "type": "Feature",
  "properties": {
    "gn:admin1_code":"BE",
    "gn:admin2_code":"246.0",
    "gn:admin3_code":"627.0",
    "gn:asciiname":"Vielbringen",
    "gn:country_code":"CH",
    "gn:dem":590,
    "gn:elevation":"579.0",
    "gn:feature_class":"P",
    "gn:feature_code":"PPL",
    "gn:name":"Vielbringen",
    "gn:population":0,
    "gn:timezone":"Europe/Zurich",
    "iso:country":"CH",
    "name:und_x_variant":[
        "Vielbringen b. Worb"
    ],
    "wof:name":"Vielbringen",
    "wof:placetype":"locality"
},
  "geometry": {"coordinates":[7.54896,46.91523],"type":"Point"}
}