{
  "type": "Feature",
  "properties": {
    "gn:gn_country":"CH",
    "gn:gn_fcode":"PPL",
    "gn:gn_pop":343,
    "gn:population":343,
    "iso:country":"CH",
    "name:cat_x_preferred":[
        "Grandfontaine"
    ],
    "name:deu_x_preferred":[
        "Grandfontaine JU"
    ],
    "name:eng_x_preferred":[
        "Grandfontaine"
    ],
    "name:epo_x_preferred":[
        "Grandfontaine JU"
    ],
    "name:fra_x_preferred":[
        "Grandfontaine"
    ],
    "name:gsw_x_preferred":[
        "Grandfontaine"
    ],
    "name:hun_x_preferred":[
        "Grandfontaine"
    ],
    "name:ita_x_preferred":[
        "Grandfontaine"
    ],
    "name:lmo_x_preferred":[
        "Grandfontaine"
    ],
    "name:msa_x_preferred":[
        "Grandfontaine"
    ],
    "name:nld_x_preferred":[
        "Grandfontaine"
    ],
    "name:nno_x_preferred":[
        "Grandfontaine i Sveits"
    ],
    "name:oci_x_preferred":[
        "Grandfontaine"
    ],
    "name:roh_x_preferred":[
        "Grandfontaine"
    ],
    "name:spa_x_preferred":[
        "Grandfontaine"
    ],
    "name:sqi_x_preferred":[
        "Grandfontaine"
    ],
    "name:vol_x_preferred":[
        "Grandfontaine"
    ],
    "name:war_x_preferred":[
        "Grandfontaine"
    ],
    "name:zho_x_preferred":[
        "\u683c\u862d\u5fb7\u8c50\u5766"
    ],
    "qs_pg:aaroncc":"CH",
    "qs_pg:gn_country":"CH",
    "qs_pg:gn_fcode":"PPL",
    "qs_pg:gn_pop":343,
    "qs_pg:name":"Grandfontaine",
    "qs_pg:name_adm0":"Schweiz",
    "qs_pg:name_adm1":"Canton de Jura",
    "qs_pg:photos":13,
    "qs_pg:photos_1k":3,
    "qs_pg:photos_9k":1,
    "qs_pg:photos_9r":1,
    "qs_pg:photos_all":13,
    "qs_pg:photos_sr":1,
    "qs_pg:pop_sr":2,
    "qs_pg:qs_pg_placetype":"locality",
    "qs_pg:qs_pg_placetype_gp":"Town",
    "qs_pg:woe_adm0":23424957,
    "woe:adm0_id":23424957,
    "woe:name_adm0":"Schweiz",
    "woe:name_adm1":"Canton de Jura",
    "woe:placetype":"Town",
    "wof:name":"Grandfontaine",
    "wof:placetype":"locality",
    "wof:population":343
},
  "geometry": {"coordinates":[6.93952,47.3917],"type":"Point"}
}