{
  "type": "Feature",
  "properties": {
    "gn:admin1_code":"VD",
    "gn:admin2_code":"2228.0",
    "gn:admin3_code":"5856.0",
    "gn:asciiname":"Bugnaux",
    "gn:country_code":"CH",
    "gn:dem":642,
    "gn:elevation":"599.0",
    "gn:feature_class":"P",
    "gn:feature_code":"PPL",
    "gn:name":"Bugnaux",
    "gn:population":0,
    "gn:timezone":"Europe/Zurich",
    "iso:country":"CH",
    "wof:name":"Bugnaux",
    "wof:placetype":"locality"
},
  "geometry": {"coordinates":[6.31971,46.47476],"type":"Point"}
}