{
  "type": "Feature",
  "properties": {
    "gn:country":"CH",
    "gn:fcode":"PPL",
    "gn:population":0,
    "iso:country":"CH",
    "name:und_x_variant":[
        "Aelggi Alm"
    ],
    "qs_pg:aaroncc":"CH",
    "qs_pg:gn_country":"CH",
    "qs_pg:gn_fcode":"PPL",
    "qs_pg:gn_pop":0,
    "qs_pg:name":"Aelggi Alp",
    "qs_pg:name_adm0":"Schweiz",
    "qs_pg:name_adm1":"Kanton Obwalden",
    "qs_pg:photos":1131,
    "qs_pg:photos_1k":229,
    "qs_pg:photos_9k":5,
    "qs_pg:photos_9r":7,
    "qs_pg:photos_all":1131,
    "qs_pg:photos_sr":11,
    "qs_pg:pop_sr":0,
    "qs_pg:qs_pg_placetype":"locality",
    "qs_pg:qs_pg_placetype_gp":"Town",
    "qs_pg:woe_adm0":23424957,
    "woe:adm0_id":23424957,
    "woe:name_adm0":"Schweiz",
    "woe:name_adm1":"Kanton Obwalden",
    "woe:placetype":"Town",
    "wof:name":"Aelggi Alp",
    "wof:placetype":"neighbourhood"
},
  "geometry": {"coordinates":[8.2375,46.79686],"type":"Point"}
}