{
  "type": "Feature",
  "properties": {
    "gn:admin1_code":"GR",
    "gn:admin2_code":"1849.0",
    "gn:admin3_code":"3871.0",
    "gn:asciiname":"Selfranga",
    "gn:country_code":"CH",
    "gn:dem":1225,
    "gn:feature_class":"P",
    "gn:feature_code":"PPL",
    "gn:name":"Selfranga",
    "gn:population":0,
    "gn:timezone":"Europe/Zurich",
    "iso:country":"CH",
    "wof:name":"Selfranga",
    "wof:placetype":"neighbourhood"
},
  "geometry": {"coordinates":[9.88416,46.86143],"type":"Point"}
}