{
  "type": "Feature",
  "properties": {
    "gn:admin1_code":"AG",
    "gn:admin2_code":"1905.0",
    "gn:admin3_code":"4141.0",
    "gn:asciiname":"Galli",
    "gn:country_code":"CH",
    "gn:dem":634,
    "gn:feature_class":"P",
    "gn:feature_code":"PPLL",
    "gn:name":"Galli",
    "gn:population":0,
    "gn:timezone":"Europe/Zurich",
    "iso:country":"CH",
    "name:cat_x_preferred":[
        "Gallus"
    ],
    "name:deu_x_preferred":[
        "Galli"
    ],
    "name:deu_x_variant":[
        "Galloi"
    ],
    "name:ell_x_preferred":[
        "\u0393\u03ac\u03bb\u03bb\u03bf\u03b9"
    ],
    "name:fra_x_preferred":[
        "Galle"
    ],
    "name:ita_x_preferred":[
        "Gallo"
    ],
    "name:jpn_x_preferred":[
        "\u30ac\u30c3\u30e9\u30a4"
    ],
    "name:kor_x_preferred":[
        "\uac08\ub8e8\uc2a4"
    ],
    "name:lat_x_preferred":[
        "Galli"
    ],
    "name:nld_x_preferred":[
        "Galli"
    ],
    "name:por_x_preferred":[
        "Galo"
    ],
    "name:rus_x_preferred":[
        "\u0413\u0430\u043b\u043b"
    ],
    "name:spa_x_preferred":[
        "Gallo"
    ],
    "name:srp_x_preferred":[
        "\u0413\u0430\u043b\u0438"
    ],
    "name:swe_x_preferred":[
        "Gallus"
    ],
    "wof:lang_x_official":[
        "deu",
        "fra",
        "gsw",
        "ita"
    ],
    "wof:lang_x_spoken":[
        "deu",
        "fra",
        "gsw",
        "ita",
        "roh"
    ],
    "wof:name":"Galli",
    "wof:placetype":"neighbourhood"
},
  "geometry": {"coordinates":[8.16174,47.2529],"type":"Point"}
}