{
  "type": "Feature",
  "properties": {
    "gn:gn_country":"CH",
    "gn:gn_fcode":"PPL",
    "gn:gn_pop":5341,
    "gn:population":5341,
    "iso:country":"CH",
    "name:cat_x_preferred":[
        "Buchrain"
    ],
    "name:deu_x_preferred":[
        "Buchrain"
    ],
    "name:eng_x_preferred":[
        "Buchrain"
    ],
    "name:epo_x_preferred":[
        "Buchrain"
    ],
    "name:eus_x_preferred":[
        "Buchrain"
    ],
    "name:fra_x_preferred":[
        "Buchrain"
    ],
    "name:gsw_x_preferred":[
        "Bueri"
    ],
    "name:hun_x_preferred":[
        "Buchrain"
    ],
    "name:ita_x_preferred":[
        "Buchrain"
    ],
    "name:kaz_x_preferred":[
        "\u0411\u0443\u0445\u0440\u0430\u0439\u043d"
    ],
    "name:lmo_x_preferred":[
        "Buchrain"
    ],
    "name:msa_x_preferred":[
        "Buchrain"
    ],
    "name:nld_x_preferred":[
        "Buchrain"
    ],
    "name:nno_x_preferred":[
        "Buchrain"
    ],
    "name:oci_x_preferred":[
        "Buchrain"
    ],
    "name:pms_x_preferred":[
        "Buchrain"
    ],
    "name:por_x_preferred":[
        "Buchrain"
    ],
    "name:roh_x_preferred":[
        "Buchrain"
    ],
    "name:rus_x_preferred":[
        "\u0411\u0443\u0445\u0440\u0430\u0439\u043d"
    ],
    "name:spa_x_preferred":[
        "Buchrain"
    ],
    "name:sqi_x_preferred":[
        "Buchrain"
    ],
    "name:swe_x_preferred":[
        "Buchrain"
    ],
    "name:ukr_x_preferred":[
        "\u0411\u0443\u0445\u0440\u0430\u0439\u043d"
    ],
    "name:uzb_x_preferred":[
        "Buchrain"
    ],
    "name:vol_x_preferred":[
        "Buchrain"
    ],
    "name:war_x_preferred":[
        "Buchrain"
    ],
    "name:zho_x_preferred":[
        "\u5e03\u8d6b\u8cf4\u56e0"
    ],
    "qs_pg:aaroncc":"CH",
    "qs_pg:gn_country":"CH",
    "qs_pg:gn_fcode":"PPL",
    "qs_pg:gn_pop":5341,
    "qs_pg:name":"Buchrain",
    "qs_pg:name_adm0":"Schweiz",
    "qs_pg:name_adm1":"Kanton Luzern",
    "qs_pg:photos":49,
    "qs_pg:photos_1k":10,
    "qs_pg:photos_9k":1,
    "qs_pg:photos_9r":2,
    "qs_pg:photos_all":49,
    "qs_pg:photos_sr":2,
    "qs_pg:pop_sr":5,
    "qs_pg:qs_pg_placetype":"locality",
    "qs_pg:qs_pg_placetype_gp":"Town",
    "qs_pg:woe_adm0":23424957,
    "woe:adm0_id":23424957,
    "woe:name_adm0":"Schweiz",
    "woe:name_adm1":"Kanton Luzern",
    "woe:placetype":"Town",
    "wof:name":"Buchrain",
    "wof:placetype":"locality",
    "wof:population":5341
},
  "geometry": {"coordinates":[8.34621,47.08602],"type":"Point"}
}