{
  "type": "Feature",
  "properties": {
    "gn:admin1_code":"FR",
    "gn:admin2_code":"1002.0",
    "gn:admin3_code":"2114.0",
    "gn:asciiname":"Villargiroud",
    "gn:country_code":"CH",
    "gn:dem":782,
    "gn:elevation":"788.0",
    "gn:feature_class":"P",
    "gn:feature_code":"PPL",
    "gn:name":"Villargiroud",
    "gn:population":0,
    "gn:timezone":"Europe/Zurich",
    "iso:country":"CH",
    "wof:name":"Villargiroud",
    "wof:placetype":"locality"
},
  "geometry": {"coordinates":[7.00224,46.70546],"type":"Point"}
}