{
  "type": "Feature",
  "properties": {
    "gn:admin1_code":"BL",
    "gn:admin2_code":"1305.0",
    "gn:admin3_code":"2885.0",
    "gn:asciiname":"Ober Hasel",
    "gn:country_code":"CH",
    "gn:dem":608,
    "gn:feature_class":"P",
    "gn:feature_code":"PPLL",
    "gn:name":"Ober Hasel",
    "gn:population":0,
    "gn:timezone":"Europe/Zurich",
    "iso:country":"CH",
    "name:deu_x_preferred":[
        "Ober Hasel"
    ],
    "wof:name":"Ober Hasel",
    "wof:placetype":"neighbourhood"
},
  "geometry": {"coordinates":[7.80507,47.39034],"type":"Point"}
}