{
  "type": "Feature",
  "properties": {
    "gn:gn_country":"CH",
    "gn:gn_fcode":"PPL",
    "gn:gn_pop":1036,
    "gn:population":1036,
    "iso:country":"CH",
    "name:cat_x_preferred":[
        "B\u00e4riswil"
    ],
    "name:deu_x_preferred":[
        "B\u00e4riswil"
    ],
    "name:eng_x_preferred":[
        "B\u00e4riswil"
    ],
    "name:epo_x_preferred":[
        "B\u00e4riswil BE"
    ],
    "name:eus_x_preferred":[
        "B\u00e4riswil"
    ],
    "name:fra_x_preferred":[
        "B\u00e4riswil"
    ],
    "name:gsw_x_preferred":[
        "B\u00e4riswiu"
    ],
    "name:hun_x_preferred":[
        "B\u00e4riswil"
    ],
    "name:ita_x_preferred":[
        "B\u00e4riswil"
    ],
    "name:lmo_x_preferred":[
        "B\u00e4riswil"
    ],
    "name:msa_x_preferred":[
        "B\u00e4riswil"
    ],
    "name:nld_x_preferred":[
        "B\u00e4riswil"
    ],
    "name:nno_x_preferred":[
        "B\u00e4riswil"
    ],
    "name:oci_x_preferred":[
        "B\u00e4riswil"
    ],
    "name:spa_x_preferred":[
        "B\u00e4riswil"
    ],
    "name:sqi_x_preferred":[
        "B\u00e4riswil"
    ],
    "name:swe_x_preferred":[
        "B\u00e4riswil"
    ],
    "name:vie_x_preferred":[
        "B\u00e4riswil"
    ],
    "name:vol_x_preferred":[
        "B\u00e4riswil"
    ],
    "name:war_x_preferred":[
        "B\u00e4riswil"
    ],
    "name:zho_x_preferred":[
        "\u8c9d\u91cc\u65af\u7dad\u723e"
    ],
    "qs_pg:aaroncc":"CH",
    "qs_pg:gn_country":"CH",
    "qs_pg:gn_fcode":"PPL",
    "qs_pg:gn_pop":1036,
    "qs_pg:name":"B\u00e4riswil",
    "qs_pg:name_adm0":"Schweiz",
    "qs_pg:name_adm1":"Kanton Bern",
    "qs_pg:photos":8,
    "qs_pg:photos_1k":2,
    "qs_pg:photos_9k":1,
    "qs_pg:photos_9r":1,
    "qs_pg:photos_all":8,
    "qs_pg:photos_sr":1,
    "qs_pg:pop_sr":3,
    "qs_pg:qs_pg_placetype":"locality",
    "qs_pg:qs_pg_placetype_gp":"Town",
    "qs_pg:woe_adm0":23424957,
    "woe:adm0_id":23424957,
    "woe:name_adm0":"Schweiz",
    "woe:name_adm1":"Kanton Bern",
    "woe:placetype":"Town",
    "wof:name":"B\u00e4riswil",
    "wof:placetype":"locality",
    "wof:population":1036
},
  "geometry": {"coordinates":[7.52709,47.01947],"type":"Point"}
}