{
  "type": "Feature",
  "properties": {
    "gn:gn_country":"CH",
    "gn:gn_fcode":"PPL",
    "gn:gn_pop":1218,
    "gn:population":1218,
    "iso:country":"CH",
    "name:cat_x_preferred":[
        "Radelfingen"
    ],
    "name:chv_x_preferred":[
        "\u0420\u0430\u0434\u0435\u043b\u044c\u0444\u0438\u043d\u0433\u0435\u043d"
    ],
    "name:deu_x_preferred":[
        "Radelfingen"
    ],
    "name:deu_x_variant":[
        "Radelfingen b. Aarberg"
    ],
    "name:eng_x_preferred":[
        "Radelfingen"
    ],
    "name:epo_x_preferred":[
        "Radelfingen BE"
    ],
    "name:eus_x_preferred":[
        "Radelfingen"
    ],
    "name:fra_x_preferred":[
        "Radelfingen"
    ],
    "name:gsw_x_preferred":[
        "Radufinge"
    ],
    "name:hun_x_preferred":[
        "Radelfingen"
    ],
    "name:ita_x_preferred":[
        "Radelfingen"
    ],
    "name:kaz_x_preferred":[
        "\u0420\u0430\u0434\u0435\u043b\u044c\u0444\u0438\u043d\u0433\u0435\u043d"
    ],
    "name:lmo_x_preferred":[
        "Radelfingen"
    ],
    "name:msa_x_preferred":[
        "Radelfingen"
    ],
    "name:nld_x_preferred":[
        "Radelfingen"
    ],
    "name:nno_x_preferred":[
        "Radelfingen"
    ],
    "name:oci_x_preferred":[
        "Radelfingen"
    ],
    "name:por_x_preferred":[
        "Radelfingen"
    ],
    "name:rus_x_preferred":[
        "\u0420\u0430\u0434\u0435\u043b\u044c\u0444\u0438\u043d\u0433\u0435\u043d"
    ],
    "name:spa_x_preferred":[
        "Radelfingen"
    ],
    "name:sqi_x_preferred":[
        "Radelfingen"
    ],
    "name:swe_x_preferred":[
        "Radelfingen"
    ],
    "name:vol_x_preferred":[
        "Radelfingen"
    ],
    "name:war_x_preferred":[
        "Radelfingen"
    ],
    "name:zho_x_preferred":[
        "\u62c9\u5fb7\u723e\u82ac\u6839"
    ],
    "qs_pg:aaroncc":"CH",
    "qs_pg:gn_country":"CH",
    "qs_pg:gn_fcode":"PPL",
    "qs_pg:gn_pop":1218,
    "qs_pg:name":"Radelfingen",
    "qs_pg:name_adm0":"Schweiz",
    "qs_pg:name_adm1":"Kanton Bern",
    "qs_pg:photos_9k":1,
    "qs_pg:photos_9r":1,
    "qs_pg:photos_all":2,
    "qs_pg:photos_sr":0,
    "qs_pg:pop_sr":3,
    "qs_pg:qs_pg_placetype":"locality",
    "qs_pg:qs_pg_placetype_gp":"Town",
    "qs_pg:woe_adm0":23424957,
    "woe:adm0_id":23424957,
    "woe:name_adm0":"Schweiz",
    "woe:name_adm1":"Kanton Bern",
    "woe:placetype":"Town",
    "wof:name":"Radelfingen",
    "wof:placetype":"locality",
    "wof:population":1218
},
  "geometry": {"coordinates":[7.27178,47.02146],"type":"Point"}
}