{
  "type": "Feature",
  "properties": {
    "gn:admin1_code":"TG",
    "gn:admin2_code":"2015.0",
    "gn:admin3_code":"4476.0",
    "gn:asciiname":"Engishofen",
    "gn:country_code":"CH",
    "gn:dem":443,
    "gn:elevation":"441.0",
    "gn:feature_class":"P",
    "gn:feature_code":"PPL",
    "gn:name":"Engishofen",
    "gn:population":0,
    "gn:timezone":"Europe/Zurich",
    "iso:country":"CH",
    "wof:name":"Engishofen",
    "wof:placetype":"locality"
},
  "geometry": {"coordinates":[9.25277,47.55863],"type":"Point"}
}