{
  "type": "Feature",
  "properties": {
    "gn:admin1_code":"TI",
    "gn:admin2_code":"2108.0",
    "gn:admin3_code":"5310.0",
    "gn:asciiname":"Corte Grande",
    "gn:country_code":"CH",
    "gn:dem":1899,
    "gn:feature_class":"P",
    "gn:feature_code":"PPL",
    "gn:name":"Corte Grande",
    "gn:population":0,
    "gn:timezone":"Europe/Zurich",
    "iso:country":"CH",
    "wof:name":"Corte Grande",
    "wof:placetype":"neighbourhood"
},
  "geometry": {"coordinates":[8.5013,46.40121],"type":"Point"}
}