{
  "type": "Feature",
  "properties": {
    "gn:gn_country":"CH",
    "gn:gn_fcode":"PPL",
    "gn:gn_pop":1304,
    "gn:population":1304,
    "iso:country":"CH",
    "name:cat_x_preferred":[
        "Boncourt"
    ],
    "name:deu_x_preferred":[
        "Boncourt JU"
    ],
    "name:eng_x_preferred":[
        "Boncourt"
    ],
    "name:epo_x_preferred":[
        "Boncourt JU"
    ],
    "name:eus_x_preferred":[
        "Boncourt"
    ],
    "name:fra_x_preferred":[
        "Boncourt"
    ],
    "name:gsw_x_preferred":[
        "Boncourt"
    ],
    "name:hun_x_preferred":[
        "Boncourt"
    ],
    "name:ita_x_preferred":[
        "Boncourt"
    ],
    "name:lmo_x_preferred":[
        "Boncourt"
    ],
    "name:msa_x_preferred":[
        "Boncourt"
    ],
    "name:nld_x_preferred":[
        "Boncourt"
    ],
    "name:nno_x_preferred":[
        "Boncourt i Sveits"
    ],
    "name:oci_x_preferred":[
        "Boncourt"
    ],
    "name:roh_x_preferred":[
        "Boncourt"
    ],
    "name:spa_x_preferred":[
        "Boncourt"
    ],
    "name:sqi_x_preferred":[
        "Boncourt"
    ],
    "name:swe_x_preferred":[
        "Boncourt"
    ],
    "name:vol_x_preferred":[
        "Boncourt"
    ],
    "name:war_x_preferred":[
        "Boncourt"
    ],
    "name:zho_x_preferred":[
        "\u90a6\u5eab\u723e"
    ],
    "qs_pg:aaroncc":"CH",
    "qs_pg:gn_country":"CH",
    "qs_pg:gn_fcode":"PPL",
    "qs_pg:gn_pop":1304,
    "qs_pg:name":"Boncourt",
    "qs_pg:name_adm0":"Schweiz",
    "qs_pg:name_adm1":"Canton de Jura",
    "qs_pg:photos":117,
    "qs_pg:photos_1k":24,
    "qs_pg:photos_9k":1,
    "qs_pg:photos_9r":3,
    "qs_pg:photos_all":117,
    "qs_pg:photos_sr":3,
    "qs_pg:pop_sr":3,
    "qs_pg:qs_pg_placetype":"locality",
    "qs_pg:qs_pg_placetype_gp":"Town",
    "qs_pg:woe_adm0":23424957,
    "woe:adm0_id":23424957,
    "woe:name_adm0":"Schweiz",
    "woe:name_adm1":"Canton de Jura",
    "woe:placetype":"Town",
    "wof:name":"Boncourt",
    "wof:placetype":"locality",
    "wof:population":1304
},
  "geometry": {"coordinates":[7.01423,47.4956],"type":"Point"}
}