{
  "type": "Feature",
  "properties": {
    "gn:gn_country":"CH",
    "gn:gn_fcode":"PPL",
    "gn:gn_pop":833,
    "gn:population":833,
    "iso:country":"CH",
    "name:baq_x_preferred":[
        "Borex"
    ],
    "name:cat_x_preferred":[
        "Borex"
    ],
    "name:chi_x_preferred":[
        "\u535a\u96f7"
    ],
    "name:dut_x_preferred":[
        "Borex"
    ],
    "name:eng_x_preferred":[
        "Borex"
    ],
    "name:epo_x_preferred":[
        "Borex"
    ],
    "name:fre_x_preferred":[
        "Borex"
    ],
    "name:ger_x_preferred":[
        "Borex"
    ],
    "name:gsw_x_preferred":[
        "Borex"
    ],
    "name:hun_x_preferred":[
        "Borex"
    ],
    "name:ita_x_preferred":[
        "Borex"
    ],
    "name:lmo_x_preferred":[
        "Borex"
    ],
    "name:ltz_x_preferred":[
        "Borex"
    ],
    "name:may_x_preferred":[
        "Borex"
    ],
    "name:nno_x_preferred":[
        "Borex"
    ],
    "name:oci_x_preferred":[
        "Borex"
    ],
    "name:por_x_preferred":[
        "Borex"
    ],
    "name:roh_x_preferred":[
        "Borex"
    ],
    "name:spa_x_preferred":[
        "Borex"
    ],
    "name:swe_x_preferred":[
        "Borex"
    ],
    "name:vol_x_preferred":[
        "Borex"
    ],
    "name:war_x_preferred":[
        "Borex"
    ],
    "qs_pg:aaroncc":"CH",
    "qs_pg:gn_country":"CH",
    "qs_pg:gn_fcode":"PPL",
    "qs_pg:gn_pop":833,
    "qs_pg:name":"Borex",
    "qs_pg:name_adm0":"Schweiz",
    "qs_pg:name_adm1":"Canton de Vaud",
    "qs_pg:photos_9k":1,
    "qs_pg:photos_9r":3,
    "qs_pg:photos_all":127,
    "qs_pg:photos_sr":0,
    "qs_pg:pop_sr":2,
    "qs_pg:qs_pg_placetype":"locality",
    "qs_pg:qs_pg_placetype_gp":"Town",
    "qs_pg:woe_adm0":23424957,
    "woe:adm0_id":23424957,
    "woe:name_adm0":"Schweiz",
    "woe:name_adm1":"Canton de Vaud",
    "woe:placetype":"Town",
    "wof:name":"Borex",
    "wof:placetype":"locality",
    "wof:population":833
},
  "geometry": {"coordinates":[6.1762,46.37891],"type":"Point"}
}