{
  "type": "Feature",
  "properties": {
    "gn:admin1_code":"FR",
    "gn:admin2_code":"1002.0",
    "gn:admin3_code":"2113.0",
    "gn:asciiname":"Lieffrens",
    "gn:country_code":"CH",
    "gn:dem":860,
    "gn:elevation":"862.0",
    "gn:feature_class":"P",
    "gn:feature_code":"PPL",
    "gn:name":"Lieffrens",
    "gn:population":0,
    "gn:timezone":"Europe/Zurich",
    "iso:country":"CH",
    "wof:name":"Lieffrens",
    "wof:placetype":"locality"
},
  "geometry": {"coordinates":[6.90167,46.63799],"type":"Point"}
}