{
  "type": "Feature",
  "properties": {
    "gn:admin1_code":"NE",
    "gn:admin2_code":"2406.0",
    "gn:admin3_code":"6512.0",
    "gn:asciiname":"Huttenberg",
    "gn:country_code":"CH",
    "gn:dem":1150,
    "gn:feature_class":"P",
    "gn:feature_code":"PPL",
    "gn:name":"H\u00fcttenberg",
    "gn:population":0,
    "gn:timezone":"Europe/Zurich",
    "iso:country":"CH",
    "wof:name":"Huttenberg",
    "wof:placetype":"locality"
},
  "geometry": {"coordinates":[6.53333,46.93333],"type":"Point"}
}