{
  "type": "Feature",
  "properties": {
    "gn:elevation":500,
    "iso:country":"CH",
    "name:deu_x_preferred":[
        "Ittigen"
    ],
    "name:fas_x_preferred":[
        "\u0627\u06cc\u062a\u06cc\u0698\u0627\u0646"
    ],
    "name:kaz_x_preferred":[
        "\u0418\u0442\u0442\u0438\u0433\u0435\u043d"
    ],
    "name:rus_x_preferred":[
        "\u0418\u0442\u0442\u0438\u0433\u0435\u043d"
    ],
    "name:unk_x_variant":[
        "Ittigen"
    ],
    "name:zho_x_preferred":[
        "\u4f0a\u8482\u6839"
    ],
    "qs:gn_adm0_cc":"CH",
    "qs:gn_fcode":"PPL",
    "qs:gn_local":2661552,
    "qs:gn_nam_loc":"Bern",
    "qs:gn_namadm1":"BE",
    "qs:gn_name":"Ittigen",
    "qs:local_max":19074,
    "qs:local_sum":54499,
    "qs:localhoods":30,
    "qs:name":"Ittigen",
    "qs:name_adm0":"Schweiz",
    "qs:name_adm1":"Kanton Bern",
    "qs:name_adm2":"Bern-Mittelland",
    "qs:name_lau":"Ittigen",
    "qs:name_local":"Bern",
    "qs:photo_max":2004,
    "qs:photo_sum":2215,
    "qs:placetype":"Suburb",
    "qs:quad_count":17,
    "qs:woe_adm0":23424957,
    "qs:woe_adm1":2347087,
    "qs:woe_adm2":56558125,
    "qs:woe_lau":12683428,
    "qs:woe_local":781788,
    "qs:woe_ver":"7.10.0",
    "wd:wordcount":2305,
    "wof:lang":[
        "ger"
    ],
    "wof:name":"Ittigen",
    "wof:placetype":"neighbourhood"
},
  "geometry": {"coordinates":[7.485412,46.972201],"type":"Point"}
}