{
  "type": "Feature",
  "properties": {
    "gn:gn_country":"CH",
    "gn:gn_fcode":"PPL",
    "gn:gn_pop":344,
    "gn:population":344,
    "iso:country":"CH",
    "name:cat_x_preferred":[
        "Matt"
    ],
    "name:deu_x_preferred":[
        "Matt GL"
    ],
    "name:eng_x_preferred":[
        "Matt"
    ],
    "name:epo_x_preferred":[
        "Matt GL"
    ],
    "name:fra_x_preferred":[
        "Matt"
    ],
    "name:ita_x_preferred":[
        "Matt"
    ],
    "name:kaz_x_preferred":[
        "\u041c\u0430\u0442\u0442"
    ],
    "name:lmo_x_preferred":[
        "Matt"
    ],
    "name:nld_x_preferred":[
        "Matt"
    ],
    "name:pms_x_preferred":[
        "Matt"
    ],
    "name:pnb_x_preferred":[
        "\u0645\u0627\u0679"
    ],
    "name:por_x_preferred":[
        "Matt"
    ],
    "name:rus_x_preferred":[
        "\u041c\u0430\u0442\u0442"
    ],
    "name:spa_x_preferred":[
        "Matt"
    ],
    "name:swe_x_preferred":[
        "Matt"
    ],
    "name:uzb_x_preferred":[
        "Matt"
    ],
    "name:vol_x_preferred":[
        "Matt"
    ],
    "name:war_x_preferred":[
        "Matt"
    ],
    "qs_pg:aaroncc":"CH",
    "qs_pg:gn_country":"CH",
    "qs_pg:gn_fcode":"PPL",
    "qs_pg:gn_pop":344,
    "qs_pg:name":"Matt",
    "qs_pg:name_adm0":"Schweiz",
    "qs_pg:name_adm1":"Kanton Glarus",
    "qs_pg:photos":70,
    "qs_pg:photos_1k":14,
    "qs_pg:photos_9k":1,
    "qs_pg:photos_9r":2,
    "qs_pg:photos_all":70,
    "qs_pg:photos_sr":2,
    "qs_pg:pop_sr":2,
    "qs_pg:qs_pg_placetype":"locality",
    "qs_pg:qs_pg_placetype_gp":"Town",
    "qs_pg:woe_adm0":23424957,
    "woe:adm0_id":23424957,
    "woe:name_adm0":"Schweiz",
    "woe:name_adm1":"Kanton Glarus",
    "woe:placetype":"Town",
    "wof:name":"Matt",
    "wof:placetype":"locality",
    "wof:population":344
},
  "geometry": {"coordinates":[9.1712,46.95949],"type":"Point"}
}