{
  "type": "Feature",
  "properties": {
    "gn:admin1_code":"BE",
    "gn:admin2_code":"246.0",
    "gn:admin3_code":"668.0",
    "gn:asciiname":"Buech",
    "gn:country_code":"CH",
    "gn:dem":641,
    "gn:elevation":"634.0",
    "gn:feature_class":"P",
    "gn:feature_code":"PPL",
    "gn:name":"Buech",
    "gn:population":0,
    "gn:timezone":"Europe/Zurich",
    "iso:country":"CH",
    "wof:name":"Buech",
    "wof:placetype":"locality"
},
  "geometry": {"coordinates":[7.27007,46.95137],"type":"Point"}
}