{
  "type": "Feature",
  "properties": {
    "gn:admin1_code":"ZH",
    "gn:admin2_code":"102.0",
    "gn:admin3_code":"33.0",
    "gn:asciiname":"Im Buck",
    "gn:country_code":"CH",
    "gn:dem":411,
    "gn:feature_class":"P",
    "gn:feature_code":"PPLL",
    "gn:name":"Im Buck",
    "gn:population":0,
    "gn:timezone":"Europe/Zurich",
    "iso:country":"CH",
    "name:deu_x_preferred":[
        "Im Buck"
    ],
    "wof:lang_x_official":[
        "deu",
        "fra",
        "gsw",
        "ita"
    ],
    "wof:lang_x_spoken":[
        "deu",
        "fra",
        "gsw",
        "ita",
        "roh"
    ],
    "wof:name":"Im Buck",
    "wof:placetype":"neighbourhood"
},
  "geometry": {"coordinates":[8.68549,47.62059],"type":"Point"}
}