{
  "type": "Feature",
  "properties": {
    "gn:admin1_code":"TI",
    "gn:admin2_code":"2101.0",
    "gn:admin3_code":"5018.0",
    "gn:asciiname":"Monti Moneda",
    "gn:country_code":"CH",
    "gn:dem":929,
    "gn:feature_class":"P",
    "gn:feature_code":"PPL",
    "gn:name":"Monti Moneda",
    "gn:population":0,
    "gn:timezone":"Europe/Zurich",
    "iso:country":"CH",
    "name:und_x_variant":[
        "Monti di Moneda",
        "Monti Moneda"
    ],
    "wof:name":"Monti Moneda",
    "wof:placetype":"neighbourhood"
},
  "geometry": {"coordinates":[9.07094,46.16232],"type":"Point"}
}