{
  "type": "Feature",
  "properties": {
    "gn:gn_country":"CH",
    "gn:gn_fcode":"PPL",
    "gn:gn_pop":918,
    "gn:population":918,
    "iso:country":"CH",
    "name:alb_x_preferred":[
        "Is\u00e9rables"
    ],
    "name:baq_x_preferred":[
        "Is\u00e9rables"
    ],
    "name:cat_x_preferred":[
        "Is\u00e9rables"
    ],
    "name:chi_x_preferred":[
        "\u4f0a\u585e\u62c9\u5e03\u52d2"
    ],
    "name:dut_x_preferred":[
        "Is\u00e9rables"
    ],
    "name:eng_x_preferred":[
        "Is\u00e9rables"
    ],
    "name:epo_x_preferred":[
        "Is\u00e9rables"
    ],
    "name:fre_x_preferred":[
        "Is\u00e9rables"
    ],
    "name:frp_x_preferred":[
        "Iser\u00e2blos"
    ],
    "name:ger_x_preferred":[
        "Is\u00e9rables"
    ],
    "name:hun_x_preferred":[
        "Is\u00e9rables"
    ],
    "name:ita_x_preferred":[
        "Is\u00e9rables"
    ],
    "name:lmo_x_preferred":[
        "Is\u00e9rables"
    ],
    "name:may_x_preferred":[
        "Is\u00e9rables"
    ],
    "name:nno_x_preferred":[
        "Is\u00e9rables"
    ],
    "name:oci_x_preferred":[
        "Is\u00e9rables"
    ],
    "name:roh_x_preferred":[
        "Is\u00e9rables"
    ],
    "name:spa_x_preferred":[
        "Is\u00e9rables"
    ],
    "name:swe_x_preferred":[
        "Is\u00e9rables"
    ],
    "name:unk_x_variant":[
        "Iserables"
    ],
    "name:vol_x_preferred":[
        "Is\u00e9rables"
    ],
    "name:war_x_preferred":[
        "Is\u00e9rables"
    ],
    "qs_pg:aaroncc":"CH",
    "qs_pg:gn_country":"CH",
    "qs_pg:gn_fcode":"PPL",
    "qs_pg:gn_pop":918,
    "qs_pg:name":"Is\u00e9rables",
    "qs_pg:name_adm0":"Schweiz",
    "qs_pg:name_adm1":"Canton de Valais",
    "qs_pg:photos":153,
    "qs_pg:photos_1k":31,
    "qs_pg:photos_9k":1,
    "qs_pg:photos_9r":4,
    "qs_pg:photos_all":153,
    "qs_pg:photos_sr":4,
    "qs_pg:pop_sr":2,
    "qs_pg:qs_pg_placetype":"locality",
    "qs_pg:qs_pg_placetype_gp":"Town",
    "qs_pg:woe_adm0":23424957,
    "woe:adm0_id":23424957,
    "woe:name_adm0":"Schweiz",
    "woe:name_adm1":"Canton de Valais",
    "woe:placetype":"Town",
    "wof:name":"Is\u00e9rables",
    "wof:placetype":"locality",
    "wof:population":918
},
  "geometry": {"coordinates":[7.24474,46.16228],"type":"Point"}
}