{
  "type": "Feature",
  "properties": {
    "gn:gn_country":"CH",
    "gn:gn_fcode":"PPL",
    "gn:gn_pop":1099,
    "gn:population":1099,
    "iso:country":"CH",
    "name:cat_x_preferred":[
        "Oberschrot"
    ],
    "name:deu_x_preferred":[
        "Oberschrot"
    ],
    "name:eng_x_preferred":[
        "Oberschrot"
    ],
    "name:epo_x_preferred":[
        "Oberschrot"
    ],
    "name:eus_x_preferred":[
        "Oberschrot"
    ],
    "name:fra_x_preferred":[
        "Oberschrot"
    ],
    "name:gsw_x_preferred":[
        "Oberschrot"
    ],
    "name:hun_x_preferred":[
        "Oberschrot"
    ],
    "name:ita_x_preferred":[
        "Oberschrot"
    ],
    "name:lmo_x_preferred":[
        "Oberschrot"
    ],
    "name:msa_x_preferred":[
        "Oberschrot"
    ],
    "name:nld_x_preferred":[
        "Oberschrot"
    ],
    "name:nno_x_preferred":[
        "Oberschrot"
    ],
    "name:oci_x_preferred":[
        "Oberschrot"
    ],
    "name:pms_x_preferred":[
        "Oberschrot"
    ],
    "name:por_x_preferred":[
        "Oberschrot"
    ],
    "name:roh_x_preferred":[
        "Oberschrot"
    ],
    "name:spa_x_preferred":[
        "Oberschrot"
    ],
    "name:sqi_x_preferred":[
        "Oberschrot"
    ],
    "name:swe_x_preferred":[
        "Oberschrot"
    ],
    "name:vol_x_preferred":[
        "Oberschrot"
    ],
    "name:war_x_preferred":[
        "Oberschrot"
    ],
    "name:zho_x_preferred":[
        "\u4e0a\u65bd\u7f85\u7279"
    ],
    "qs_pg:aaroncc":"CH",
    "qs_pg:gn_country":"CH",
    "qs_pg:gn_fcode":"PPL",
    "qs_pg:gn_pop":1099,
    "qs_pg:name":"Oberschrot",
    "qs_pg:name_adm0":"Schweiz",
    "qs_pg:name_adm1":"Canton de Fribourg",
    "qs_pg:photos_9k":1,
    "qs_pg:photos_9r":1,
    "qs_pg:photos_all":4,
    "qs_pg:photos_sr":0,
    "qs_pg:pop_sr":3,
    "qs_pg:qs_pg_placetype":"locality",
    "qs_pg:qs_pg_placetype_gp":"Town",
    "qs_pg:woe_adm0":23424957,
    "woe:adm0_id":23424957,
    "woe:name_adm0":"Schweiz",
    "woe:name_adm1":"Canton de Fribourg",
    "woe:placetype":"Town",
    "wof:name":"Oberschrot",
    "wof:placetype":"locality",
    "wof:population":1099
},
  "geometry": {"coordinates":[7.26896,46.73979],"type":"Point"}
}