{
  "type": "Feature",
  "properties": {
    "gn:gn_country":"CH",
    "gn:gn_fcode":"PPL",
    "gn:gn_pop":609,
    "gn:population":609,
    "iso:country":"CH",
    "name:deu_x_preferred":[
        "Goumoens-la-Ville"
    ],
    "name:eng_x_preferred":[
        "Goumoens-la-Ville"
    ],
    "name:fra_x_preferred":[
        "Goumoens-la-Ville"
    ],
    "name:hun_x_preferred":[
        "Goumoens-la-Ville"
    ],
    "name:ita_x_preferred":[
        "Goumoens-la-Ville"
    ],
    "name:lmo_x_preferred":[
        "Goumoens-la-Ville"
    ],
    "name:nld_x_preferred":[
        "Goumoens-la-Ville"
    ],
    "name:roh_x_preferred":[
        "Goumoens-la-Ville"
    ],
    "name:swe_x_preferred":[
        "Goumoens-la-Ville"
    ],
    "name:vol_x_preferred":[
        "Goumoens-la-Ville"
    ],
    "name:war_x_preferred":[
        "Goumoens-la-Ville"
    ],
    "qs_pg:aaroncc":"CH",
    "qs_pg:gn_country":"CH",
    "qs_pg:gn_fcode":"PPL",
    "qs_pg:gn_pop":609,
    "qs_pg:name":"Goumoens-la-Ville",
    "qs_pg:name_adm0":"Schweiz",
    "qs_pg:name_adm1":"Canton de Vaud",
    "qs_pg:photos_9k":1,
    "qs_pg:photos_9r":1,
    "qs_pg:photos_all":2,
    "qs_pg:photos_sr":0,
    "qs_pg:pop_sr":2,
    "qs_pg:qs_pg_placetype":"locality",
    "qs_pg:qs_pg_placetype_gp":"Town",
    "qs_pg:woe_adm0":23424957,
    "woe:adm0_id":23424957,
    "woe:name_adm0":"Schweiz",
    "woe:name_adm1":"Canton de Vaud",
    "woe:placetype":"Town",
    "wof:name":"Goumoens-la-Ville",
    "wof:placetype":"locality",
    "wof:population":609
},
  "geometry": {"coordinates":[6.60398,46.65922],"type":"Point"}
}