{
  "type": "Feature",
  "properties": {
    "gn:country":"CH",
    "gn:fcode":"PPLL",
    "gn:population":12,
    "iso:country":"CH",
    "name:als_x_preferred":[
        "Oberhof"
    ],
    "name:ceb_x_preferred":[
        "Oberhof"
    ],
    "name:deu_x_preferred":[
        "Oberhof"
    ],
    "name:epo_x_preferred":[
        "Oberhof"
    ],
    "name:eus_x_preferred":[
        "Oberhof"
    ],
    "name:fra_x_preferred":[
        "Oberhof"
    ],
    "name:ita_x_preferred":[
        "Oberhof"
    ],
    "name:lmo_x_preferred":[
        "Oberhof"
    ],
    "name:nld_x_preferred":[
        "Oberhof"
    ],
    "name:pol_x_preferred":[
        "Oberhof"
    ],
    "name:rus_x_preferred":[
        "\u041e\u0431\u0435\u0440\u0445\u043e\u0444"
    ],
    "name:swe_x_preferred":[
        "Oberhof"
    ],
    "name:vol_x_preferred":[
        "Oberhof"
    ],
    "qs_pg:aaroncc":"CH",
    "qs_pg:gn_country":"CH",
    "qs_pg:gn_fcode":"PPLL",
    "qs_pg:gn_pop":12,
    "qs_pg:name":"Oberhof",
    "qs_pg:photos_9r":0,
    "qs_pg:photos_sr":0,
    "qs_pg:pop_sr":1,
    "qs_pg:qs_pg_placetype":"locality",
    "wof:lang_x_official":[
        "deu",
        "fra",
        "gsw",
        "ita"
    ],
    "wof:lang_x_spoken":[
        "deu",
        "fra",
        "gsw",
        "ita",
        "roh"
    ],
    "wof:name":"Oberhof",
    "wof:placetype":"neighbourhood",
    "wof:population":12
},
  "geometry": {"coordinates":[8.8837,47.48894],"type":"Point"}
}