{
  "type": "Feature",
  "properties": {
    "gn:population":3754,
    "iso:country":"CH",
    "name:alb_x_preferred":[
        "Sempach"
    ],
    "name:als_x_preferred":[
        "Sempach"
    ],
    "name:baq_x_preferred":[
        "Sempach"
    ],
    "name:bel_x_preferred":[
        "\u0417\u0435\u043c\u043f\u0430\u0445"
    ],
    "name:bul_x_preferred":[
        "\u0417\u0435\u043c\u043f\u0430\u0445"
    ],
    "name:cat_x_preferred":[
        "Sempach"
    ],
    "name:ceb_x_preferred":[
        "Sempach"
    ],
    "name:chi_x_preferred":[
        "\u68ee\u5e15\u8d6b"
    ],
    "name:chv_x_preferred":[
        "\u0417\u0435\u043c\u043f\u0430\u0445"
    ],
    "name:deu_x_preferred":[
        "Sempach"
    ],
    "name:dut_x_preferred":[
        "Sempach"
    ],
    "name:eng_x_preferred":[
        "Sempach"
    ],
    "name:epo_x_preferred":[
        "Sempach"
    ],
    "name:eus_x_preferred":[
        "Sempach"
    ],
    "name:fas_x_preferred":[
        "\u0633\u0627\u0645\u067e\u06a9"
    ],
    "name:fin_x_preferred":[
        "Sempach"
    ],
    "name:fra_x_preferred":[
        "Sempach"
    ],
    "name:fre_x_preferred":[
        "Sempach"
    ],
    "name:ger_x_preferred":[
        "Sempach"
    ],
    "name:gsw_x_preferred":[
        "Sempach"
    ],
    "name:heb_x_preferred":[
        "\u05d6\u05de\u05e4\u05d0\u05da"
    ],
    "name:hun_x_preferred":[
        "Sempach"
    ],
    "name:ita_x_preferred":[
        "Sempach"
    ],
    "name:kaz_x_preferred":[
        "\u0417\u0435\u043c\u043f\u0430\u0445"
    ],
    "name:lmo_x_preferred":[
        "Sempach"
    ],
    "name:may_x_preferred":[
        "Sempach"
    ],
    "name:msa_x_preferred":[
        "Sempach"
    ],
    "name:nld_x_preferred":[
        "Sempach"
    ],
    "name:nno_x_preferred":[
        "Sempach"
    ],
    "name:oci_x_preferred":[
        "Sempach"
    ],
    "name:per_x_preferred":[
        "\u0633\u0627\u0645\u067e\u06a9"
    ],
    "name:pms_x_preferred":[
        "Sempach"
    ],
    "name:pol_x_preferred":[
        "Sempach"
    ],
    "name:por_x_preferred":[
        "Sempach"
    ],
    "name:roh_x_preferred":[
        "Sempach"
    ],
    "name:rus_x_preferred":[
        "\u0417\u0435\u043c\u043f\u0430\u0445"
    ],
    "name:slv_x_preferred":[
        "Sempach"
    ],
    "name:spa_x_preferred":[
        "Sempach"
    ],
    "name:sqi_x_preferred":[
        "Sempach"
    ],
    "name:ukr_x_preferred":[
        "\u0417\u0435\u043c\u043f\u0430\u0445"
    ],
    "name:uzb_x_preferred":[
        "Sempach"
    ],
    "name:vol_x_preferred":[
        "Sempach"
    ],
    "name:war_x_preferred":[
        "Sempach"
    ],
    "name:zho_x_preferred":[
        "\u68ee\u5e15\u8d6b"
    ],
    "qs:a0":"Schweiz#Suisse#Svizzera#Svizra",
    "qs:a1":"*Luzern",
    "qs:a1r":"0",
    "qs:adm0":"Schweiz#Suisse#Svizzera#Svizra",
    "qs:la_lc":"*",
    "qs:level":"locality",
    "qs:loc":"Sempach",
    "qs:loc_alt":"Sempach",
    "qs:pop":0,
    "qs:type":"buffered point",
    "wd:wordcount":1207,
    "wof:lang":[
        "ger"
    ],
    "wof:name":"Sempach",
    "wof:placetype":"locality",
    "wof:population":3754
},
  "geometry": {"coordinates":[8.191292,47.136814],"type":"Point"}
}