{
  "type": "Feature",
  "properties": {
    "gn:admin1_code":"TI",
    "gn:admin2_code":"2104.0",
    "gn:admin3_code":"5398.0",
    "gn:asciiname":"Alpe Cedullo",
    "gn:country_code":"CH",
    "gn:dem":1277,
    "gn:feature_class":"P",
    "gn:feature_code":"PPL",
    "gn:name":"Alpe Cedullo",
    "gn:population":0,
    "gn:timezone":"Europe/Zurich",
    "iso:country":"CH",
    "name:ita_x_preferred":[
        "Alpe Cedullo"
    ],
    "wof:name":"Alpe Cedullo",
    "wof:placetype":"neighbourhood"
},
  "geometry": {"coordinates":[8.81621,46.10962],"type":"Point"}
}