{
  "type": "Feature",
  "properties": {
    "gn:gn_country":"CH",
    "gn:gn_fcode":"PPL",
    "gn:gn_pop":142,
    "gn:population":142,
    "iso:country":"CH",
    "name:alb_x_preferred":[
        "Stierva"
    ],
    "name:cat_x_preferred":[
        "Stierva"
    ],
    "name:chi_x_preferred":[
        "\u65af\u8482\u723e\u74e6"
    ],
    "name:chv_x_preferred":[
        "\u0428\u0442\u0438\u0440\u0432\u0430"
    ],
    "name:deu_x_preferred":[
        "St\u00fcrvis"
    ],
    "name:dut_x_preferred":[
        "Stierva"
    ],
    "name:eng_x_preferred":[
        "Stierva"
    ],
    "name:epo_x_preferred":[
        "Stierva"
    ],
    "name:fre_x_preferred":[
        "Stierva"
    ],
    "name:ger_x_preferred":[
        "Stierva"
    ],
    "name:hun_x_preferred":[
        "Stierva"
    ],
    "name:ita_x_preferred":[
        "Stierva"
    ],
    "name:kaz_x_preferred":[
        "\u0428\u0442\u0438\u0440\u0432\u0430"
    ],
    "name:lat_x_preferred":[
        "Seturius"
    ],
    "name:lmo_x_preferred":[
        "Stierva"
    ],
    "name:may_x_preferred":[
        "Stierva"
    ],
    "name:nno_x_preferred":[
        "Stierva"
    ],
    "name:oci_x_preferred":[
        "Stierva"
    ],
    "name:pms_x_preferred":[
        "Stierva"
    ],
    "name:por_x_preferred":[
        "Stierva"
    ],
    "name:roh_x_preferred":[
        "Stierva"
    ],
    "name:rus_x_preferred":[
        "\u0428\u0442\u0438\u0440\u0432\u0430"
    ],
    "name:spa_x_preferred":[
        "Stierva"
    ],
    "name:swe_x_preferred":[
        "Stierva"
    ],
    "name:uzb_x_preferred":[
        "Stierva"
    ],
    "name:vol_x_preferred":[
        "Stierva"
    ],
    "name:war_x_preferred":[
        "Stierva"
    ],
    "qs_pg:aaroncc":"CH",
    "qs_pg:gn_country":"CH",
    "qs_pg:gn_fcode":"PPL",
    "qs_pg:gn_pop":142,
    "qs_pg:name":"Stierva",
    "qs_pg:name_adm0":"Schweiz",
    "qs_pg:name_adm1":"Kanton Graub\u00fcnden",
    "qs_pg:photos_9k":1,
    "qs_pg:photos_9r":2,
    "qs_pg:photos_all":27,
    "qs_pg:photos_sr":0,
    "qs_pg:pop_sr":1,
    "qs_pg:qs_pg_placetype":"locality",
    "qs_pg:qs_pg_placetype_gp":"Town",
    "qs_pg:woe_adm0":23424957,
    "woe:adm0_id":23424957,
    "woe:name_adm0":"Schweiz",
    "woe:name_adm1":"Kanton Graub\u00fcnden",
    "woe:placetype":"Town",
    "wof:name":"Stierva",
    "wof:placetype":"locality",
    "wof:population":142
},
  "geometry": {"coordinates":[9.54238,46.66333],"type":"Point"}
}