{
  "type": "Feature",
  "properties": {
    "gn:admin1_code":"FR",
    "gn:admin2_code":"1003.0",
    "gn:admin3_code":"2160.0",
    "gn:asciiname":"Pra au Favre",
    "gn:country_code":"CH",
    "gn:dem":880,
    "gn:feature_class":"P",
    "gn:feature_code":"PPL",
    "gn:name":"Pra au Favre",
    "gn:population":0,
    "gn:timezone":"Europe/Zurich",
    "iso:country":"CH",
    "name:fra_x_preferred":[
        "Pra au Favre"
    ],
    "wof:name":"Pra au Favre",
    "wof:placetype":"neighbourhood"
},
  "geometry": {"coordinates":[6.98117,46.60838],"type":"Point"}
}