{
  "type": "Feature",
  "properties": {
    "gn:admin1_code":"NW",
    "gn:admin2_code":"700.0",
    "gn:admin3_code":"1502.0",
    "gn:asciiname":"Loren",
    "gn:country_code":"CH",
    "gn:dem":470,
    "gn:feature_class":"P",
    "gn:feature_code":"PPL",
    "gn:name":"Loren",
    "gn:population":0,
    "gn:timezone":"Europe/Zurich",
    "iso:country":"CH",
    "name:fra_x_preferred":[
        "Loren"
    ],
    "name:und_x_variant":[
        "Lohren"
    ],
    "wof:name":"Loren",
    "wof:placetype":"neighbourhood"
},
  "geometry": {"coordinates":[8.44278,46.97149],"type":"Point"}
}