{
  "type": "Feature",
  "properties": {
    "gn:admin1_code":"SZ",
    "gn:admin2_code":"506.0",
    "gn:admin3_code":"1367.0",
    "gn:asciiname":"Hinterthal",
    "gn:country_code":"CH",
    "gn:dem":629,
    "gn:elevation":"624.0",
    "gn:feature_class":"P",
    "gn:feature_code":"PPL",
    "gn:name":"Hinterthal",
    "gn:population":0,
    "gn:timezone":"Europe/Zurich",
    "iso:country":"CH",
    "name:swe_x_preferred":[
        "Hinterthal"
    ],
    "wof:name":"Hinterthal",
    "wof:placetype":"neighbourhood"
},
  "geometry": {"coordinates":[8.7725,46.9736],"type":"Point"}
}