{
  "type": "Feature",
  "properties": {
    "gn:population":2900,
    "iso:country":"CH",
    "name:als_x_preferred":[
        "Netstal"
    ],
    "name:bul_x_preferred":[
        "\u041d\u0435\u0446\u0442\u0430\u043b"
    ],
    "name:cat_x_preferred":[
        "Netstal"
    ],
    "name:ceb_x_preferred":[
        "Netstal"
    ],
    "name:chv_x_preferred":[
        "\u041d\u0435\u0442\u0448\u0442\u0430\u043b\u044c"
    ],
    "name:deu_x_preferred":[
        "Netstal"
    ],
    "name:eng_x_preferred":[
        "Netstal"
    ],
    "name:epo_x_preferred":[
        "Netstal"
    ],
    "name:fra_x_preferred":[
        "Netstal"
    ],
    "name:gsw_x_preferred":[
        "Netstal"
    ],
    "name:ita_x_preferred":[
        "Netstal"
    ],
    "name:kaz_x_preferred":[
        "\u041d\u0435\u0442\u0448\u0442\u0430\u043b\u044c"
    ],
    "name:lmo_x_preferred":[
        "Netstal"
    ],
    "name:nld_x_preferred":[
        "Netstal"
    ],
    "name:pms_x_preferred":[
        "Netstal"
    ],
    "name:por_x_preferred":[
        "Netstal"
    ],
    "name:rus_x_preferred":[
        "\u041d\u0435\u0442\u0448\u0442\u0430\u043b\u044c"
    ],
    "name:spa_x_preferred":[
        "Netstal"
    ],
    "name:swe_x_preferred":[
        "Netstal"
    ],
    "name:uzb_x_preferred":[
        "Netstal"
    ],
    "name:vol_x_preferred":[
        "Netstal"
    ],
    "name:war_x_preferred":[
        "Netstal"
    ],
    "qs:a0":"Schweiz#Suisse#Svizzera#Svizra",
    "qs:a1":"*Glarus",
    "qs:a1r":"0",
    "qs:adm0":"Schweiz#Suisse#Svizzera#Svizra",
    "qs:la_lc":"*",
    "qs:level":"locality",
    "qs:loc":"Netstal",
    "qs:loc_alt":"Netstal",
    "qs:pop":0,
    "qs:type":"buffered point",
    "wd:elevation":464.0,
    "wd:wordcount":454,
    "wof:lang":[
        "ger"
    ],
    "wof:name":"Netstal",
    "wof:placetype":"locality",
    "wof:population":2900
},
  "geometry": {"coordinates":[9.059308,47.064193],"type":"Point"}
}