{
  "type": "Feature",
  "properties": {
    "gn:admin1_code":"TG",
    "gn:admin2_code":"2015.0",
    "gn:admin3_code":"4941.0",
    "gn:asciiname":"Hinterruberbaum",
    "gn:country_code":"CH",
    "gn:dem":505,
    "gn:feature_class":"P",
    "gn:feature_code":"PPLL",
    "gn:name":"Hinterruberbaum",
    "gn:population":0,
    "gn:timezone":"Europe/Zurich",
    "iso:country":"CH",
    "name:deu_x_preferred":[
        "Hinterruberbaum"
    ],
    "wof:name":"Hinterruberbaum",
    "wof:placetype":"locality"
},
  "geometry": {"coordinates":[9.08343,47.59049],"type":"Point"}
}