{
  "type": "Feature",
  "properties": {
    "gn:admin1_code":"ZH",
    "gn:admin2_code":"102.0",
    "gn:admin3_code":"36.0",
    "gn:asciiname":"Wangenbuehl",
    "gn:country_code":"CH",
    "gn:dem":545,
    "gn:feature_class":"P",
    "gn:feature_code":"PPLL",
    "gn:name":"Wangenb\u00fchl",
    "gn:population":0,
    "gn:timezone":"Europe/Zurich",
    "iso:country":"CH",
    "name:deu_x_preferred":[
        "Wangenb\u00fchl"
    ],
    "wof:name":"Wangenbuehl",
    "wof:placetype":"neighbourhood"
},
  "geometry": {"coordinates":[8.81674,47.63427],"type":"Point"}
}