{
  "type": "Feature",
  "properties": {
    "gn:gn_country":"CH",
    "gn:gn_fcode":"PPLX",
    "gn:gn_pop":73,
    "gn:population":73,
    "iso:country":"CH",
    "name:unk_x_variant":[
        "Oberm\u00fcli"
    ],
    "qs_pg:aaroncc":"CH",
    "qs_pg:gn_country":"CH",
    "qs_pg:gn_fcode":"PPLX",
    "qs_pg:gn_pop":73,
    "qs_pg:name":"Meilen / Oberm\u00fcli",
    "qs_pg:photos_9r":0,
    "qs_pg:photos_sr":0,
    "qs_pg:pop_sr":1,
    "qs_pg:qs_pg_placetype":"neighbourhood",
    "wof:name":"Meilen / Oberm\u00fcli",
    "wof:placetype":"neighbourhood",
    "wof:population":73
},
  "geometry": {"coordinates":[8.63991,47.27106],"type":"Point"}
}