{
  "type": "Feature",
  "properties": {
    "gn:country":"CH",
    "gn:fcode":"PPLX",
    "gn:population":37,
    "iso:country":"CH",
    "name:als_x_preferred":[
        "Wil"
    ],
    "name:ara_x_preferred":[
        "\u0648\u064a\u0644"
    ],
    "name:azb_x_preferred":[
        "\u0648\u06cc\u0644"
    ],
    "name:azb_x_variant":[
        "\u0648\u06cc\u0644\u060c \u0633\u0646\u200c\u06af\u0644\u0627\u0646"
    ],
    "name:cat_x_preferred":[
        "Wil"
    ],
    "name:dan_x_preferred":[
        "Wil"
    ],
    "name:deu_x_preferred":[
        "Wil"
    ],
    "name:eng_x_preferred":[
        "Wil"
    ],
    "name:eng_x_variant":[
        "D\u00fcbendorf / Wil"
    ],
    "name:epo_x_preferred":[
        "Wil"
    ],
    "name:eus_x_preferred":[
        "Wil"
    ],
    "name:fas_x_preferred":[
        "\u0648\u06cc\u0644"
    ],
    "name:fin_x_preferred":[
        "Wil"
    ],
    "name:fra_x_preferred":[
        "Wil"
    ],
    "name:gle_x_preferred":[
        "Wil"
    ],
    "name:ind_x_preferred":[
        "Wil"
    ],
    "name:ita_x_preferred":[
        "Wil"
    ],
    "name:kaz_x_preferred":[
        "\u0412\u0438\u043b\u044c"
    ],
    "name:kor_x_preferred":[
        "\ube4c"
    ],
    "name:lit_x_preferred":[
        "Vilis"
    ],
    "name:lmo_x_preferred":[
        "Wil"
    ],
    "name:msa_x_preferred":[
        "Wil"
    ],
    "name:nld_x_preferred":[
        "Wil"
    ],
    "name:nno_x_preferred":[
        "Wil"
    ],
    "name:pms_x_preferred":[
        "Wil"
    ],
    "name:pol_x_preferred":[
        "Wil"
    ],
    "name:por_x_preferred":[
        "Wil"
    ],
    "name:que_x_preferred":[
        "Wil"
    ],
    "name:rus_x_preferred":[
        "\u0412\u0438\u043b\u044c"
    ],
    "name:spa_x_preferred":[
        "Wil"
    ],
    "name:sqi_x_preferred":[
        "Wil"
    ],
    "name:srp_x_preferred":[
        "\u0412\u0438\u043b"
    ],
    "name:swe_x_preferred":[
        "Wil"
    ],
    "name:tur_x_preferred":[
        "Wil"
    ],
    "name:ukr_x_preferred":[
        "\u0412\u0456\u043b\u044c"
    ],
    "name:uzb_x_preferred":[
        "Wil"
    ],
    "name:vec_x_preferred":[
        "Wil"
    ],
    "name:vol_x_preferred":[
        "Wil"
    ],
    "name:war_x_preferred":[
        "Wil"
    ],
    "qs_pg:aaroncc":"CH",
    "qs_pg:gn_country":"CH",
    "qs_pg:gn_fcode":"PPLX",
    "qs_pg:gn_pop":37,
    "qs_pg:name":"D\u00fcbendorf / Wil",
    "qs_pg:photos_9r":0,
    "qs_pg:photos_sr":0,
    "qs_pg:pop_sr":1,
    "qs_pg:qs_pg_placetype":"neighbourhood",
    "wof:name":"Wil",
    "wof:placetype":"neighbourhood",
    "wof:population":37
},
  "geometry": {"coordinates":[8.61874,47.39036],"type":"Point"}
}