{
  "type": "Feature",
  "properties": {
    "gn:admin1_code":"LU",
    "gn:admin2_code":"316.0",
    "gn:admin3_code":"1010.0",
    "gn:asciiname":"Unterziegerhuetten",
    "gn:country_code":"CH",
    "gn:dem":1039,
    "gn:feature_class":"P",
    "gn:feature_code":"PPLL",
    "gn:name":"Unterziegerh\u00fctten",
    "gn:population":0,
    "gn:timezone":"Europe/Zurich",
    "iso:country":"CH",
    "name:deu_x_preferred":[
        "Unterziegerh\u00fctten"
    ],
    "wof:name":"Unterziegerhuetten",
    "wof:placetype":"locality"
},
  "geometry": {"coordinates":[7.94973,46.90101],"type":"Point"}
}