{
  "type": "Feature",
  "properties": {
    "iso:country":"CH",
    "name:als_x_preferred":[
        "Saint-Imier"
    ],
    "name:cat_x_preferred":[
        "Saint-Imier"
    ],
    "name:ceb_x_preferred":[
        "Saint-Imier"
    ],
    "name:chv_x_preferred":[
        "\u0421\u0435\u043d\u0442-\u0418\u043c\u044c\u0435"
    ],
    "name:dan_x_preferred":[
        "Saint-Imier"
    ],
    "name:deu_x_preferred":[
        "Saint-Imier"
    ],
    "name:deu_x_variant":[
        "Sankt Immer"
    ],
    "name:eng_x_preferred":[
        "Saint-Imier"
    ],
    "name:epo_x_preferred":[
        "Saint-Imier"
    ],
    "name:eus_x_preferred":[
        "Saint-Imier"
    ],
    "name:fin_x_preferred":[
        "Saint-Imier"
    ],
    "name:fra_x_preferred":[
        "Saint-Imier"
    ],
    "name:gsw_x_preferred":[
        "Saint-Imier"
    ],
    "name:hun_x_preferred":[
        "Saint-Imier"
    ],
    "name:ita_x_preferred":[
        "Saint-Imier"
    ],
    "name:jpn_x_preferred":[
        "\u30b5\u30f3\u30fb\u30c6\u30a3\u30df\u30a8"
    ],
    "name:kaz_x_preferred":[
        "\u0421\u0435\u043d\u0442-\u0418\u043c\u044c\u0435"
    ],
    "name:lmo_x_preferred":[
        "Saint-Imier"
    ],
    "name:msa_x_preferred":[
        "Saint-Imier"
    ],
    "name:nld_x_preferred":[
        "Saint-Imier"
    ],
    "name:nno_x_preferred":[
        "Saint-Imier"
    ],
    "name:oci_x_preferred":[
        "Saint-Imier"
    ],
    "name:por_x_preferred":[
        "Saint-Imier"
    ],
    "name:rus_x_preferred":[
        "\u0421\u0435\u043d\u0442-\u0418\u043c\u044c\u0435"
    ],
    "name:spa_x_preferred":[
        "Saint-Imier"
    ],
    "name:sqi_x_preferred":[
        "Saint-Imier"
    ],
    "name:swe_x_preferred":[
        "Saint-Imier"
    ],
    "name:vie_x_preferred":[
        "Saint-Imier"
    ],
    "name:vol_x_preferred":[
        "Saint-Imier"
    ],
    "name:war_x_preferred":[
        "Saint-Imier"
    ],
    "name:zho_x_preferred":[
        "\u8056\u4f0a\u7c73\u8036"
    ],
    "qs:a0":"Schweiz#Suisse#Svizzera#Svizra",
    "qs:a1":"*Bern",
    "qs:a1r":"0",
    "qs:adm0":"Schweiz#Suisse#Svizzera#Svizra",
    "qs:la_lc":"*",
    "qs:level":"locality",
    "qs:loc":"St-Imier",
    "qs:loc_alt":"St-Imier",
    "qs:pop":0,
    "qs:type":"buffered point",
    "wd:wordcount":2691,
    "wof:name":"St-Imier",
    "wof:placetype":"locality"
},
  "geometry": {"coordinates":[7.003455,47.154206],"type":"Point"}
}