{
  "type": "Feature",
  "properties": {
    "gn:admin1_code":"FR",
    "gn:admin2_code":"1003.0",
    "gn:admin3_code":"2155.0",
    "gn:asciiname":"Le Diron",
    "gn:country_code":"CH",
    "gn:dem":836,
    "gn:feature_class":"P",
    "gn:feature_code":"PPL",
    "gn:name":"Le Diron",
    "gn:population":0,
    "gn:timezone":"Europe/Zurich",
    "iso:country":"CH",
    "name:fra_x_preferred":[
        "Le Diron"
    ],
    "wof:name":"Le Diron",
    "wof:placetype":"neighbourhood"
},
  "geometry": {"coordinates":[6.97806,46.61252],"type":"Point"}
}