{
  "type": "Feature",
  "properties": {
    "gn:admin1_code":"SG",
    "gn:admin2_code":"1726.0",
    "gn:admin3_code":"3342.0",
    "gn:asciiname":"Breitenholz",
    "gn:country_code":"CH",
    "gn:dem":662,
    "gn:feature_class":"P",
    "gn:feature_code":"PPLL",
    "gn:name":"Breitenholz",
    "gn:population":0,
    "gn:timezone":"Europe/Zurich",
    "iso:country":"CH",
    "name:deu_x_preferred":[
        "Breitenholz"
    ],
    "wof:name":"Breitenholz",
    "wof:placetype":"neighbourhood"
},
  "geometry": {"coordinates":[8.98297,47.25542],"type":"Point"}
}