{
  "type": "Feature",
  "properties": {
    "gn:gn_country":"CH",
    "gn:gn_fcode":"PPL",
    "gn:gn_pop":2536,
    "gn:population":2536,
    "iso:country":"CH",
    "name:alb_x_preferred":[
        "Flims"
    ],
    "name:baq_x_preferred":[
        "Flims"
    ],
    "name:cat_x_preferred":[
        "Flims"
    ],
    "name:chi_x_preferred":[
        "\u5f17\u5229\u59c6\u65af"
    ],
    "name:deu_x_preferred":[
        "Flims"
    ],
    "name:dut_x_preferred":[
        "Flims"
    ],
    "name:eng_x_preferred":[
        "Flims"
    ],
    "name:epo_x_preferred":[
        "Flims"
    ],
    "name:fra_x_preferred":[
        "Flims"
    ],
    "name:fre_x_preferred":[
        "Flims"
    ],
    "name:ger_x_preferred":[
        "Flims"
    ],
    "name:gre_x_preferred":[
        "\u03a6\u03bb\u03b9\u03bc\u03c2"
    ],
    "name:gsw_x_preferred":[
        "Flims"
    ],
    "name:hun_x_preferred":[
        "Flims"
    ],
    "name:ind_x_preferred":[
        "Flims"
    ],
    "name:ita_x_preferred":[
        "Flims"
    ],
    "name:kaz_x_preferred":[
        "\u0424\u043b\u0438\u043c\u0441"
    ],
    "name:lat_x_preferred":[
        "Flemme"
    ],
    "name:lmo_x_preferred":[
        "Flims"
    ],
    "name:ltz_x_preferred":[
        "Flims"
    ],
    "name:may_x_preferred":[
        "Flims"
    ],
    "name:nno_x_preferred":[
        "Flims"
    ],
    "name:nob_x_preferred":[
        "Flims"
    ],
    "name:oci_x_preferred":[
        "Flims"
    ],
    "name:pms_x_preferred":[
        "Flims"
    ],
    "name:por_x_preferred":[
        "Flims"
    ],
    "name:roh_x_preferred":[
        "Flem"
    ],
    "name:rus_x_preferred":[
        "\u0424\u043b\u0438\u043c\u0441"
    ],
    "name:spa_x_preferred":[
        "Flims"
    ],
    "name:swe_x_preferred":[
        "Flims"
    ],
    "name:unk_x_variant":[
        "Flims Dorf"
    ],
    "name:uzb_x_preferred":[
        "Flims"
    ],
    "name:vol_x_preferred":[
        "Flims"
    ],
    "name:war_x_preferred":[
        "Flims"
    ],
    "name:zho_x_preferred":[
        "\u5f17\u5229\u59c6\u65af"
    ],
    "qs_pg:aaroncc":"CH",
    "qs_pg:gn_country":"CH",
    "qs_pg:gn_fcode":"PPL",
    "qs_pg:gn_pop":2536,
    "qs_pg:name":"Flims",
    "qs_pg:name_adm0":"Schweiz",
    "qs_pg:name_adm1":"Kanton Graub\u00fcnden",
    "qs_pg:photos":842,
    "qs_pg:photos_1k":171,
    "qs_pg:photos_9k":4,
    "qs_pg:photos_9r":6,
    "qs_pg:photos_all":842,
    "qs_pg:photos_sr":9,
    "qs_pg:pop_sr":4,
    "qs_pg:qs_pg_placetype":"locality",
    "qs_pg:qs_pg_placetype_gp":"Town",
    "qs_pg:woe_adm0":23424957,
    "woe:adm0_id":23424957,
    "woe:name_adm0":"Schweiz",
    "woe:name_adm1":"Kanton Graub\u00fcnden",
    "woe:placetype":"Town",
    "wof:name":"Flims",
    "wof:placetype":"locality",
    "wof:population":2536
},
  "geometry": {"coordinates":[9.28458,46.83705],"type":"Point"}
}