{
  "type": "Feature",
  "properties": {
    "gn:gn_country":"CH",
    "gn:gn_fcode":"PPL",
    "gn:gn_pop":0,
    "iso:country":"CH",
    "name:alb_x_preferred":[
        "Quinto"
    ],
    "name:baq_x_preferred":[
        "Quinto"
    ],
    "name:cat_x_preferred":[
        "Quinto"
    ],
    "name:chi_x_preferred":[
        "\u6606\u6258"
    ],
    "name:deu_x_preferred":[
        "Quinto TI"
    ],
    "name:dut_x_preferred":[
        "Quinto"
    ],
    "name:eng_x_preferred":[
        "Quinto"
    ],
    "name:epo_x_preferred":[
        "Quinto TI"
    ],
    "name:fin_x_preferred":[
        "Quinto"
    ],
    "name:fre_x_preferred":[
        "Quinto"
    ],
    "name:ger_x_preferred":[
        "Quinto"
    ],
    "name:gsw_x_preferred":[
        "Quinto"
    ],
    "name:hun_x_preferred":[
        "Quinto"
    ],
    "name:ita_x_preferred":[
        "Quinto"
    ],
    "name:lmo_x_preferred":[
        "Quint"
    ],
    "name:ltz_x_preferred":[
        "Quinto"
    ],
    "name:may_x_preferred":[
        "Quinto"
    ],
    "name:nno_x_preferred":[
        "Quinto i Sveits"
    ],
    "name:oci_x_preferred":[
        "Quinto"
    ],
    "name:por_x_preferred":[
        "Quinto"
    ],
    "name:roh_x_preferred":[
        "Quinto"
    ],
    "name:spa_x_preferred":[
        "Quinto"
    ],
    "name:vol_x_preferred":[
        "Quinto"
    ],
    "name:war_x_preferred":[
        "Quinto"
    ],
    "name:zho_x_preferred":[
        "\u6606\u6258"
    ],
    "qs_pg:aaroncc":"CH",
    "qs_pg:gn_country":"CH",
    "qs_pg:gn_fcode":"PPL",
    "qs_pg:gn_pop":0,
    "qs_pg:name":"Quinto",
    "qs_pg:name_adm0":"Schweiz",
    "qs_pg:name_adm1":"Cantone Ticino",
    "qs_pg:photos":107,
    "qs_pg:photos_1k":22,
    "qs_pg:photos_9k":1,
    "qs_pg:photos_9r":3,
    "qs_pg:photos_all":107,
    "qs_pg:photos_sr":3,
    "qs_pg:pop_sr":0,
    "qs_pg:qs_pg_placetype":"locality",
    "qs_pg:qs_pg_placetype_gp":"Town",
    "qs_pg:woe_adm0":23424957,
    "woe:adm0_id":23424957,
    "woe:name_adm0":"Schweiz",
    "woe:name_adm1":"Cantone Ticino",
    "woe:placetype":"Town",
    "wof:name":"Quinto",
    "wof:placetype":"locality"
},
  "geometry": {"coordinates":[8.71131,46.51027],"type":"Point"}
}