{
  "type": "Feature",
  "properties": {
    "gn:gn_country":"CH",
    "gn:gn_fcode":"PPL",
    "gn:gn_pop":3655,
    "gn:population":3655,
    "iso:country":"CH",
    "name:cat_x_preferred":[
        "Caslano"
    ],
    "name:deu_x_preferred":[
        "Caslano"
    ],
    "name:eng_x_preferred":[
        "Caslano"
    ],
    "name:epo_x_preferred":[
        "Caslano"
    ],
    "name:eus_x_preferred":[
        "Caslano"
    ],
    "name:fra_x_preferred":[
        "Caslano"
    ],
    "name:gsw_x_preferred":[
        "Caslano"
    ],
    "name:hun_x_preferred":[
        "Caslano"
    ],
    "name:ita_x_preferred":[
        "Caslano"
    ],
    "name:kor_x_preferred":[
        "\uce74\uc2ac\ub77c\ub178"
    ],
    "name:lmo_x_preferred":[
        "Caslan"
    ],
    "name:msa_x_preferred":[
        "Caslano"
    ],
    "name:nld_x_preferred":[
        "Caslano"
    ],
    "name:nno_x_preferred":[
        "Caslano"
    ],
    "name:oci_x_preferred":[
        "Caslano"
    ],
    "name:por_x_preferred":[
        "Caslano"
    ],
    "name:roh_x_preferred":[
        "Caslano"
    ],
    "name:spa_x_preferred":[
        "Caslano"
    ],
    "name:sqi_x_preferred":[
        "Caslano"
    ],
    "name:vie_x_preferred":[
        "Caslano"
    ],
    "name:vol_x_preferred":[
        "Caslano"
    ],
    "name:war_x_preferred":[
        "Caslano"
    ],
    "name:zho_x_preferred":[
        "\u5361\u65af\u62c9\u8afe"
    ],
    "qs_pg:aaroncc":"CH",
    "qs_pg:gn_country":"CH",
    "qs_pg:gn_fcode":"PPL",
    "qs_pg:gn_pop":3655,
    "qs_pg:name":"Caslano",
    "qs_pg:name_adm0":"Schweiz",
    "qs_pg:name_adm1":"Cantone Ticino",
    "qs_pg:photos":492,
    "qs_pg:photos_1k":100,
    "qs_pg:photos_9k":2,
    "qs_pg:photos_9r":5,
    "qs_pg:photos_all":492,
    "qs_pg:photos_sr":7,
    "qs_pg:pop_sr":4,
    "qs_pg:qs_pg_placetype":"locality",
    "qs_pg:qs_pg_placetype_gp":"Town",
    "qs_pg:woe_adm0":23424957,
    "woe:adm0_id":23424957,
    "woe:name_adm0":"Schweiz",
    "woe:name_adm1":"Cantone Ticino",
    "woe:placetype":"Town",
    "wof:name":"Caslano",
    "wof:placetype":"locality",
    "wof:population":3655
},
  "geometry": {"coordinates":[8.88261,45.97153],"type":"Point"}
}