{
  "type": "Feature",
  "properties": {
    "gn:population":3767,
    "iso:country":"CH",
    "name:als_x_preferred":[
        "Fehraltorf"
    ],
    "name:ara_x_preferred":[
        "\u0641\u064a\u0631\u0627\u0644\u062a\u0648\u0641"
    ],
    "name:baq_x_preferred":[
        "Fehraltorf"
    ],
    "name:cat_x_preferred":[
        "Fehraltorf"
    ],
    "name:ceb_x_preferred":[
        "Fehraltorf"
    ],
    "name:chi_x_preferred":[
        "\u8cbb\u62c9\u723e\u6258\u592b"
    ],
    "name:chv_x_preferred":[
        "\u0424\u0435\u0440\u0430\u043b\u044c\u0442\u043e\u0440\u0444"
    ],
    "name:deu_x_preferred":[
        "Fehraltorf"
    ],
    "name:dut_x_preferred":[
        "Fehraltorf"
    ],
    "name:eng_x_preferred":[
        "Fehraltorf"
    ],
    "name:epo_x_preferred":[
        "Fehraltorf"
    ],
    "name:eus_x_preferred":[
        "Fehraltorf"
    ],
    "name:fra_x_preferred":[
        "Fehraltorf"
    ],
    "name:fre_x_preferred":[
        "Fehraltorf"
    ],
    "name:ger_x_preferred":[
        "Fehraltorf"
    ],
    "name:gsw_x_preferred":[
        "Feeraltoorf"
    ],
    "name:hun_x_preferred":[
        "Fehraltorf"
    ],
    "name:ita_x_preferred":[
        "Fehraltorf"
    ],
    "name:kaz_x_preferred":[
        "\u0424\u0435\u0440\u0430\u043b\u044c\u0442\u043e\u0440\u0444"
    ],
    "name:lmo_x_preferred":[
        "Fehraltorf"
    ],
    "name:may_x_preferred":[
        "Fehraltorf"
    ],
    "name:msa_x_preferred":[
        "Fehraltorf"
    ],
    "name:nld_x_preferred":[
        "Fehraltorf"
    ],
    "name:nno_x_preferred":[
        "Fehraltorf"
    ],
    "name:oci_x_preferred":[
        "Fehraltorf"
    ],
    "name:por_x_preferred":[
        "Fehraltorf"
    ],
    "name:rus_x_preferred":[
        "\u0424\u0435\u0440\u0430\u043b\u044c\u0442\u043e\u0440\u0444"
    ],
    "name:spa_x_preferred":[
        "Fehraltorf"
    ],
    "name:uzb_x_preferred":[
        "Fehraltorf"
    ],
    "name:vec_x_preferred":[
        "Fehraltorf"
    ],
    "name:vol_x_preferred":[
        "Fehraltorf"
    ],
    "name:war_x_preferred":[
        "Fehraltorf"
    ],
    "name:zho_x_preferred":[
        "\u8cbb\u62c9\u723e\u6258\u592b"
    ],
    "qs:a0":"Schweiz#Suisse#Svizzera#Svizra",
    "qs:a1":"*Z\u00fcrich",
    "qs:a1r":"0",
    "qs:adm0":"Schweiz#Suisse#Svizzera#Svizra",
    "qs:la_lc":"*",
    "qs:level":"locality",
    "qs:loc":"Fehraltorf",
    "qs:loc_alt":"Fehraltorf",
    "qs:pop":0,
    "qs:type":"buffered point",
    "wd:wordcount":648,
    "wof:lang":[
        "ger"
    ],
    "wof:name":"Fehraltorf",
    "wof:placetype":"locality",
    "wof:population":3767
},
  "geometry": {"coordinates":[8.748033,47.39027],"type":"Point"}
}