{
  "type": "Feature",
  "properties": {
    "gn:admin1_code":"BE",
    "gn:admin2_code":"245.0",
    "gn:admin3_code":"909.0",
    "gn:asciiname":"Vorderschwendestalden",
    "gn:country_code":"CH",
    "gn:dem":857,
    "gn:feature_class":"P",
    "gn:feature_code":"PPLL",
    "gn:name":"Vorderschwendestalden",
    "gn:population":0,
    "gn:timezone":"Europe/Zurich",
    "iso:country":"CH",
    "name:deu_x_preferred":[
        "Vorderschwendestalden"
    ],
    "wof:name":"Vorderschwendestalden",
    "wof:placetype":"neighbourhood"
},
  "geometry": {"coordinates":[7.8209,46.91452],"type":"Point"}
}