{
  "type": "Feature",
  "properties": {
    "gn:admin1_code":"VD",
    "gn:admin2_code":"2224.0",
    "gn:admin3_code":"5571.0",
    "gn:asciiname":"Fontanezier",
    "gn:country_code":"CH",
    "gn:dem":862,
    "gn:feature_class":"P",
    "gn:feature_code":"PPL",
    "gn:name":"Fontanezier",
    "gn:population":0,
    "gn:timezone":"Europe/Zurich",
    "iso:country":"CH",
    "wof:name":"Fontanezier",
    "wof:placetype":"locality"
},
  "geometry": {"coordinates":[6.65589,46.8547],"type":"Point"}
}