{
  "type": "Feature",
  "properties": {
    "gn:admin1_code":"FR",
    "gn:admin2_code":"1007.0",
    "gn:admin3_code":"2325.0",
    "gn:asciiname":"Les Rosalys",
    "gn:country_code":"CH",
    "gn:dem":1142,
    "gn:feature_class":"P",
    "gn:feature_code":"PPL",
    "gn:name":"Les Rosalys",
    "gn:population":0,
    "gn:timezone":"Europe/Zurich",
    "iso:country":"CH",
    "wof:name":"Les Rosalys",
    "wof:placetype":"neighbourhood"
},
  "geometry": {"coordinates":[6.96168,46.51696],"type":"Point"}
}