{
  "type": "Feature",
  "properties": {
    "gn:admin1_code":"TG",
    "gn:admin2_code":"2012.0",
    "gn:admin3_code":"4816.0",
    "gn:asciiname":"Brathaus",
    "gn:country_code":"CH",
    "gn:dem":589,
    "gn:feature_class":"P",
    "gn:feature_code":"PPLL",
    "gn:name":"Brathaus",
    "gn:population":0,
    "gn:timezone":"Europe/Zurich",
    "iso:country":"CH",
    "name:deu_x_preferred":[
        "Brathaus"
    ],
    "wof:name":"Brathaus",
    "wof:placetype":"neighbourhood"
},
  "geometry": {"coordinates":[9.01153,47.63277],"type":"Point"}
}