{
  "type": "Feature",
  "properties": {
    "gn:admin1_code":"VS",
    "gn:admin2_code":"2312.0",
    "gn:admin3_code":"6266.0",
    "gn:asciiname":"Crete-a-l'Oeil (Les Agettes)",
    "gn:country_code":"CH",
    "gn:dem":981,
    "gn:feature_class":"P",
    "gn:feature_code":"PPL",
    "gn:name":"Cr\u00eate-\u00e0-l'Oeil (Les Agettes)",
    "gn:population":0,
    "gn:timezone":"Europe/Zurich",
    "iso:country":"CH",
    "name:und_x_variant":[
        "Cr\u00eate-\u00e0-l'Oeil (Les Agettes)"
    ],
    "wof:name":"Crete-a-l'Oeil (Les Agettes)",
    "wof:placetype":"locality"
},
  "geometry": {"coordinates":[7.37147,46.21198],"type":"Point"}
}