{
  "type": "Feature",
  "properties": {
    "gn:admin1_code":"ZG",
    "gn:admin2_code":"900.0",
    "gn:admin3_code":"1710.0",
    "gn:asciiname":"Oberbossen",
    "gn:country_code":"CH",
    "gn:dem":592,
    "gn:feature_class":"P",
    "gn:feature_code":"PPLL",
    "gn:name":"Oberbossen",
    "gn:population":0,
    "gn:timezone":"Europe/Zurich",
    "iso:country":"CH",
    "name:deu_x_preferred":[
        "Oberbossen"
    ],
    "wof:name":"Oberbossen",
    "wof:placetype":"neighbourhood"
},
  "geometry": {"coordinates":[8.50924,47.11776],"type":"Point"}
}