{
  "type": "Feature",
  "properties": {
    "gn:admin1_code":"FR",
    "gn:admin2_code":"1006.0",
    "gn:admin3_code":"2293.0",
    "gn:asciiname":"Uebewil",
    "gn:country_code":"CH",
    "gn:dem":671,
    "gn:elevation":"654.0",
    "gn:feature_class":"P",
    "gn:feature_code":"PPL",
    "gn:name":"Uebewil",
    "gn:population":0,
    "gn:timezone":"Europe/Zurich",
    "iso:country":"CH",
    "wof:lang_x_official":[
        "deu",
        "fra",
        "gsw",
        "ita"
    ],
    "wof:lang_x_spoken":[
        "deu",
        "fra",
        "gsw",
        "ita",
        "roh"
    ],
    "wof:name":"Uebewil",
    "wof:placetype":"neighbourhood"
},
  "geometry": {"coordinates":[7.17823,46.81506],"type":"Point"}
}