{
  "type": "Feature",
  "properties": {
    "iso:country":"CH",
    "wof:name":"Beundenfeld",
    "wof:placetype":"neighbourhood"
},
  "geometry": {"coordinates":[7.47052450622369,46.95821405119531],"type":"Point"}
}