{
  "type": "Feature",
  "properties": {
    "gn:admin1_code":"BE",
    "gn:admin2_code":"243.0",
    "gn:admin3_code":"734.0",
    "gn:asciiname":"Buehl b. Aarberg",
    "gn:country_code":"CH",
    "gn:dem":452,
    "gn:feature_class":"P",
    "gn:feature_code":"PPL",
    "gn:name":"B\u00fchl b. Aarberg",
    "gn:population":0,
    "gn:timezone":"Europe/Zurich",
    "iso:country":"CH",
    "wof:name":"Buehl b. Aarberg",
    "wof:placetype":"locality"
},
  "geometry": {"coordinates":[7.24544,47.07076],"type":"Point"}
}