{
  "type": "Feature",
  "properties": {
    "gn:admin1_code":"BE",
    "gn:admin2_code":"243.0",
    "gn:admin3_code":"309.0",
    "gn:asciiname":"Oltigen",
    "gn:country_code":"CH",
    "gn:dem":480,
    "gn:elevation":"462.0",
    "gn:feature_class":"P",
    "gn:feature_code":"PPL",
    "gn:name":"Oltigen",
    "gn:population":0,
    "gn:timezone":"Europe/Zurich",
    "iso:country":"CH",
    "wof:name":"Oltigen",
    "wof:placetype":"neighbourhood"
},
  "geometry": {"coordinates":[7.25821,46.98875],"type":"Point"}
}