{
  "type": "Feature",
  "properties": {
    "gn:admin1_code":"TG",
    "gn:admin2_code":"2015.0",
    "gn:admin3_code":"4951.0",
    "gn:asciiname":"Haeusern",
    "gn:country_code":"CH",
    "gn:dem":411,
    "gn:feature_class":"P",
    "gn:feature_code":"PPLL",
    "gn:name":"H\u00e4usern",
    "gn:population":0,
    "gn:timezone":"Europe/Zurich",
    "iso:country":"CH",
    "name:deu_x_preferred":[
        "H\u00e4usern"
    ],
    "wof:name":"Haeusern",
    "wof:placetype":"neighbourhood"
},
  "geometry": {"coordinates":[9.02467,47.58448],"type":"Point"}
}