{
  "type": "Feature",
  "properties": {
    "gn:admin1_code":"BE",
    "gn:admin2_code":"244.0",
    "gn:admin3_code":"329.0",
    "gn:asciiname":"Chlyrot",
    "gn:country_code":"CH",
    "gn:dem":534,
    "gn:elevation":"552.0",
    "gn:feature_class":"P",
    "gn:feature_code":"PPL",
    "gn:name":"Chlyrot",
    "gn:population":0,
    "gn:timezone":"Europe/Zurich",
    "iso:country":"CH",
    "wof:name":"Chlyrot",
    "wof:placetype":"neighbourhood"
},
  "geometry": {"coordinates":[7.84743,47.20177],"type":"Point"}
}