{
  "type": "Feature",
  "properties": {
    "gn:admin1_code":"LU",
    "gn:admin2_code":"312.0",
    "gn:admin3_code":"1069.0",
    "gn:asciiname":"Farmhuette",
    "gn:country_code":"CH",
    "gn:dem":952,
    "gn:feature_class":"P",
    "gn:feature_code":"PPLL",
    "gn:name":"Farmh\u00fctte",
    "gn:population":0,
    "gn:timezone":"Europe/Zurich",
    "iso:country":"CH",
    "name:deu_x_preferred":[
        "Farmh\u00fctte"
    ],
    "wof:name":"Farmhuette",
    "wof:placetype":"locality"
},
  "geometry": {"coordinates":[8.45527,47.03737],"type":"Point"}
}