{
  "type": "Feature",
  "properties": {
    "gn:admin1_code":"NW",
    "gn:admin2_code":"700.0",
    "gn:admin3_code":"1508.0",
    "gn:asciiname":"Schloh",
    "gn:country_code":"CH",
    "gn:dem":615,
    "gn:feature_class":"P",
    "gn:feature_code":"PPL",
    "gn:name":"Schloh",
    "gn:population":0,
    "gn:timezone":"Europe/Zurich",
    "iso:country":"CH",
    "name:deu_x_preferred":[
        "Schloh"
    ],
    "wof:name":"Schloh",
    "wof:placetype":"locality"
},
  "geometry": {"coordinates":[8.39827,46.95367],"type":"Point"}
}