{
  "type": "Feature",
  "properties": {
    "gn:admin1_code":"JU",
    "gn:admin2_code":"2601.0",
    "gn:admin3_code":"6709.0",
    "gn:asciiname":"Bellerive",
    "gn:country_code":"CH",
    "gn:dem":399,
    "gn:feature_class":"P",
    "gn:feature_code":"PPLL",
    "gn:name":"Bellerive",
    "gn:population":0,
    "gn:timezone":"Europe/Zurich",
    "iso:country":"CH",
    "name:fra_x_preferred":[
        "Bellerive"
    ],
    "wof:name":"Bellerive",
    "wof:placetype":"neighbourhood"
},
  "geometry": {"coordinates":[7.36472,47.38461],"type":"Point"}
}