{
  "type": "Feature",
  "properties": {
    "gn:admin1_code":"JU",
    "gn:admin2_code":"2601.0",
    "gn:admin3_code":"6709.0",
    "gn:asciiname":"Courcelon",
    "gn:country_code":"CH",
    "gn:dem":429,
    "gn:elevation":"426.0",
    "gn:feature_class":"P",
    "gn:feature_code":"PPL",
    "gn:name":"Courcelon",
    "gn:population":0,
    "gn:timezone":"Europe/Zurich",
    "iso:country":"CH",
    "wof:name":"Courcelon",
    "wof:placetype":"locality"
},
  "geometry": {"coordinates":[7.3918,47.363],"type":"Point"}
}