{
  "type": "Feature",
  "properties": {
    "gn:gn_country":"CH",
    "gn:gn_fcode":"PPL",
    "gn:gn_pop":152,
    "gn:population":152,
    "iso:country":"CH",
    "name:cat_x_preferred":[
        "Alvaschein"
    ],
    "name:chv_x_preferred":[
        "\u0410\u043b\u044c\u0432\u0430\u0448\u0430\u0439\u043d"
    ],
    "name:deu_x_preferred":[
        "Alvaschein"
    ],
    "name:eng_x_preferred":[
        "Alvaschein"
    ],
    "name:epo_x_preferred":[
        "Alvaschein"
    ],
    "name:fra_x_preferred":[
        "Alvaschein"
    ],
    "name:hun_x_preferred":[
        "Alvaschein"
    ],
    "name:ind_x_preferred":[
        "Alvaschein"
    ],
    "name:ita_x_preferred":[
        "Alvaschein"
    ],
    "name:kaz_x_preferred":[
        "\u0410\u043b\u044c\u0432\u0430\u0448\u0430\u0439\u043d"
    ],
    "name:lat_x_preferred":[
        "Alvisinis"
    ],
    "name:lmo_x_preferred":[
        "Alvaschein"
    ],
    "name:msa_x_preferred":[
        "Alvaschein"
    ],
    "name:nld_x_preferred":[
        "Alvaschein"
    ],
    "name:nno_x_preferred":[
        "Alvaschein"
    ],
    "name:oci_x_preferred":[
        "Alvaschein"
    ],
    "name:pms_x_preferred":[
        "Alvaschein"
    ],
    "name:por_x_preferred":[
        "Alvaschein"
    ],
    "name:roh_x_preferred":[
        "Alvaschagn"
    ],
    "name:rus_x_preferred":[
        "\u0410\u043b\u044c\u0432\u0430\u0448\u0430\u0439\u043d"
    ],
    "name:spa_x_preferred":[
        "Alvaschein"
    ],
    "name:sqi_x_preferred":[
        "Alvaschein"
    ],
    "name:swe_x_preferred":[
        "Alvaschein"
    ],
    "name:uzb_x_preferred":[
        "Alvaschein"
    ],
    "name:vol_x_preferred":[
        "Alvaschein"
    ],
    "name:war_x_preferred":[
        "Alvaschein"
    ],
    "name:zho_x_preferred":[
        "\u963f\u723e\u74e6\u6c99\u56e0"
    ],
    "qs_pg:aaroncc":"CH",
    "qs_pg:gn_country":"CH",
    "qs_pg:gn_fcode":"PPL",
    "qs_pg:gn_pop":152,
    "qs_pg:name":"Alvaschein",
    "qs_pg:name_adm0":"Schweiz",
    "qs_pg:name_adm1":"Kanton Graub\u00fcnden",
    "qs_pg:photos":26,
    "qs_pg:photos_1k":5,
    "qs_pg:photos_9k":1,
    "qs_pg:photos_9r":2,
    "qs_pg:photos_all":26,
    "qs_pg:photos_sr":2,
    "qs_pg:pop_sr":1,
    "qs_pg:qs_pg_placetype":"locality",
    "qs_pg:qs_pg_placetype_gp":"Town",
    "qs_pg:woe_adm0":23424957,
    "woe:adm0_id":23424957,
    "woe:name_adm0":"Schweiz",
    "woe:name_adm1":"Kanton Graub\u00fcnden",
    "woe:placetype":"Town",
    "wof:name":"Alvaschein",
    "wof:placetype":"locality",
    "wof:population":152
},
  "geometry": {"coordinates":[9.55051,46.67488],"type":"Point"}
}