{
  "type": "Feature",
  "properties": {
    "gn:admin1_code":"SG",
    "gn:admin2_code":"1724.0",
    "gn:admin3_code":"3273.0",
    "gn:asciiname":"Hoehi",
    "gn:country_code":"CH",
    "gn:dem":1217,
    "gn:feature_class":"P",
    "gn:feature_code":"PPLL",
    "gn:name":"H\u00f6hi",
    "gn:population":0,
    "gn:timezone":"Europe/Zurich",
    "iso:country":"CH",
    "name:deu_x_preferred":[
        "H\u00f6hi"
    ],
    "wof:name":"Hoehi",
    "wof:placetype":"neighbourhood"
},
  "geometry": {"coordinates":[9.38232,47.16485],"type":"Point"}
}