{
  "type": "Feature",
  "properties": {
    "gn:country":"CH",
    "gn:fcode":"PPLL",
    "gn:population":12,
    "iso:country":"CH",
    "name:und_x_variant":[
        "Riedenholz"
    ],
    "qs_pg:aaroncc":"CH",
    "qs_pg:gn_country":"CH",
    "qs_pg:gn_fcode":"PPLL",
    "qs_pg:gn_pop":12,
    "qs_pg:name":"Z\u00fcrich (Kreis 11) / Riedenholz",
    "qs_pg:photos_9r":0,
    "qs_pg:photos_sr":0,
    "qs_pg:pop_sr":1,
    "qs_pg:qs_pg_placetype":"locality",
    "wof:name":"Riedenholz",
    "wof:placetype":"neighbourhood",
    "wof:population":12
},
  "geometry": {"coordinates":[8.52949,47.43154],"type":"Point"}
}