{
  "type": "Feature",
  "properties": {
    "gn:country":"CH",
    "gn:fcode":"PPLX",
    "gn:population":98,
    "iso:country":"CH",
    "name:eng_x_preferred":[
        "Lauferweg"
    ],
    "name:eng_x_variant":[
        "Uhwiesen / Lauferweg"
    ],
    "qs_pg:aaroncc":"CH",
    "qs_pg:gn_country":"CH",
    "qs_pg:gn_fcode":"PPLX",
    "qs_pg:gn_pop":98,
    "qs_pg:name":"Uhwiesen / Lauferweg",
    "qs_pg:photos_9r":0,
    "qs_pg:photos_sr":0,
    "qs_pg:pop_sr":1,
    "qs_pg:qs_pg_placetype":"neighbourhood",
    "wof:lang_x_official":[
        "deu",
        "fra",
        "gsw",
        "ita"
    ],
    "wof:lang_x_spoken":[
        "deu",
        "fra",
        "gsw",
        "ita",
        "roh"
    ],
    "wof:name":"Lauferweg",
    "wof:placetype":"neighbourhood",
    "wof:population":98
},
  "geometry": {"coordinates":[8.62869,47.67226],"type":"Point"}
}