{
  "type": "Feature",
  "properties": {
    "gn:gn_country":"CH",
    "gn:gn_fcode":"PPL",
    "gn:gn_pop":856,
    "gn:population":856,
    "iso:country":"CH",
    "name:alb_x_preferred":[
        "Tecknau"
    ],
    "name:baq_x_preferred":[
        "Tecknau"
    ],
    "name:cat_x_preferred":[
        "Tecknau"
    ],
    "name:chi_x_preferred":[
        "\u7279\u514b\u7459"
    ],
    "name:chv_x_preferred":[
        "\u0422\u0435\u043a\u043d\u0430\u0443"
    ],
    "name:dut_x_preferred":[
        "Tecknau"
    ],
    "name:eng_x_preferred":[
        "Tecknau"
    ],
    "name:epo_x_preferred":[
        "Tecknau"
    ],
    "name:fre_x_preferred":[
        "Tecknau"
    ],
    "name:ger_x_preferred":[
        "Tecknau"
    ],
    "name:gsw_x_preferred":[
        "D\u00e4ggnau"
    ],
    "name:hun_x_preferred":[
        "Tecknau"
    ],
    "name:ita_x_preferred":[
        "Tecknau"
    ],
    "name:kaz_x_preferred":[
        "\u0422\u0435\u043a\u043d\u0430\u0443"
    ],
    "name:lmo_x_preferred":[
        "Tecknau"
    ],
    "name:may_x_preferred":[
        "Tecknau"
    ],
    "name:nno_x_preferred":[
        "Tecknau"
    ],
    "name:oci_x_preferred":[
        "Tecknau"
    ],
    "name:rus_x_preferred":[
        "\u0422\u0435\u043a\u043d\u0430\u0443"
    ],
    "name:spa_x_preferred":[
        "Tecknau"
    ],
    "name:swe_x_preferred":[
        "Tecknau"
    ],
    "name:uzb_x_preferred":[
        "Tecknau"
    ],
    "name:vol_x_preferred":[
        "Tecknau"
    ],
    "name:war_x_preferred":[
        "Tecknau"
    ],
    "name:zho_x_preferred":[
        "\u7279\u514b\u7459"
    ],
    "qs_pg:aaroncc":"CH",
    "qs_pg:gn_country":"CH",
    "qs_pg:gn_fcode":"PPL",
    "qs_pg:gn_pop":856,
    "qs_pg:name":"Tecknau",
    "qs_pg:name_adm0":"Schweiz",
    "qs_pg:name_adm1":"Kanton Basel-Land",
    "qs_pg:photos_9k":1,
    "qs_pg:photos_9r":1,
    "qs_pg:photos_all":2,
    "qs_pg:photos_sr":0,
    "qs_pg:pop_sr":2,
    "qs_pg:qs_pg_placetype":"locality",
    "qs_pg:qs_pg_placetype_gp":"Town",
    "qs_pg:woe_adm0":23424957,
    "woe:adm0_id":23424957,
    "woe:name_adm0":"Schweiz",
    "woe:name_adm1":"Kanton Basel-Land",
    "woe:placetype":"Town",
    "wof:name":"Tecknau",
    "wof:placetype":"locality",
    "wof:population":856
},
  "geometry": {"coordinates":[7.88399,47.45132],"type":"Point"}
}