{
  "type": "Feature",
  "properties": {
    "gn:admin1_code":"UR",
    "gn:admin2_code":"400.0",
    "gn:admin3_code":"1210.0",
    "gn:asciiname":"Zumdorf",
    "gn:country_code":"CH",
    "gn:dem":1497,
    "gn:feature_class":"P",
    "gn:feature_code":"PPL",
    "gn:name":"Zumdorf",
    "gn:population":0,
    "gn:timezone":"Europe/Zurich",
    "iso:country":"CH",
    "name:deu_x_preferred":[
        "Zumdorf"
    ],
    "wof:name":"Zumdorf",
    "wof:placetype":"neighbourhood"
},
  "geometry": {"coordinates":[8.53714,46.61151],"type":"Point"}
}