{
  "type": "Feature",
  "properties": {
    "gn:gn_country":"CH",
    "gn:gn_fcode":"PPL",
    "gn:gn_pop":7408,
    "gn:population":7408,
    "iso:country":"CH",
    "name:baq_x_preferred":[
        "Bussigny"
    ],
    "name:bul_x_preferred":[
        "\u0411\u0443\u0441\u0438\u0433\u043d\u0439"
    ],
    "name:cat_x_preferred":[
        "Bussigny-pr\u00e8s-Lausanne"
    ],
    "name:chi_x_preferred":[
        "\u6d1b\u6851\u9644\u8fd1\u6bd4\u897f\u5c3c"
    ],
    "name:dut_x_preferred":[
        "Bussigny-pr\u00e8s-Lausanne"
    ],
    "name:eng_x_preferred":[
        "Bussigny-pr\u00e8s-Lausanne"
    ],
    "name:epo_x_preferred":[
        "Bussigny-pr\u00e8s-Lausanne"
    ],
    "name:fre_x_preferred":[
        "Bussigny"
    ],
    "name:ger_x_preferred":[
        "Bussigny"
    ],
    "name:gsw_x_preferred":[
        "Bussigny-pr\u00e8s-Lausanne"
    ],
    "name:hun_x_preferred":[
        "Bussigny-pr\u00e8s-Lausanne"
    ],
    "name:ita_x_preferred":[
        "Bussigny-pr\u00e8s-Lausanne"
    ],
    "name:lit_x_preferred":[
        "Busignis"
    ],
    "name:lmo_x_preferred":[
        "Bussigny-pr\u00e8s-Lausanne"
    ],
    "name:may_x_preferred":[
        "Bussigny-pr\u00e8s-Lausanne"
    ],
    "name:nno_x_preferred":[
        "Bussigny-pr\u00e8s-Lausanne"
    ],
    "name:oci_x_preferred":[
        "Bussigny-pr\u00e8s-Lausanne"
    ],
    "name:roh_x_preferred":[
        "Bussigny"
    ],
    "name:spa_x_preferred":[
        "Bussigny-pr\u00e8s-Lausanne"
    ],
    "name:swe_x_preferred":[
        "Bussigny-pr\u00e8s-Lausanne"
    ],
    "name:vol_x_preferred":[
        "Bussigny-pr\u00e8s-Lausanne"
    ],
    "name:war_x_preferred":[
        "Bussigny-pr\u00e8s-Lausanne"
    ],
    "qs_pg:aaroncc":"CH",
    "qs_pg:gn_country":"CH",
    "qs_pg:gn_fcode":"PPL",
    "qs_pg:gn_pop":7408,
    "qs_pg:name":"Bussigny",
    "qs_pg:name_adm0":"Schweiz",
    "qs_pg:name_adm1":"Canton de Vaud",
    "qs_pg:photos":219,
    "qs_pg:photos_1k":44,
    "qs_pg:photos_9k":1,
    "qs_pg:photos_9r":4,
    "qs_pg:photos_all":219,
    "qs_pg:photos_sr":4,
    "qs_pg:pop_sr":5,
    "qs_pg:qs_pg_placetype":"locality",
    "qs_pg:qs_pg_placetype_gp":"Town",
    "qs_pg:woe_adm0":23424957,
    "woe:adm0_id":23424957,
    "woe:name_adm0":"Schweiz",
    "woe:name_adm1":"Canton de Vaud",
    "woe:placetype":"Town",
    "wof:name":"Bussigny",
    "wof:placetype":"locality",
    "wof:population":7408
},
  "geometry": {"coordinates":[6.55597,46.5511],"type":"Point"}
}