{
  "type": "Feature",
  "properties": {
    "gn:admin1_code":"SO",
    "gn:admin2_code":"1104.0",
    "gn:admin3_code":"2480.0",
    "gn:asciiname":"Seewen SO",
    "gn:country_code":"CH",
    "gn:dem":564,
    "gn:feature_class":"P",
    "gn:feature_code":"PPL",
    "gn:name":"Seewen SO",
    "gn:population":0,
    "gn:timezone":"Europe/Zurich",
    "iso:country":"CH",
    "wof:name":"Seewen SO",
    "wof:placetype":"locality"
},
  "geometry": {"coordinates":[7.6615,47.43738],"type":"Point"}
}