{
  "type": "Feature",
  "properties": {
    "gn:admin1_code":"VD",
    "gn:admin2_code":"2223.0",
    "gn:admin3_code":"5514.0",
    "gn:asciiname":"La Rusteriaz",
    "gn:country_code":"CH",
    "gn:dem":777,
    "gn:feature_class":"P",
    "gn:feature_code":"PPL",
    "gn:name":"La Rust\u00e9riaz",
    "gn:population":0,
    "gn:timezone":"Europe/Zurich",
    "iso:country":"CH",
    "name:fra_x_preferred":[
        "La Rust\u00e9riaz"
    ],
    "wof:name":"La Rusteriaz",
    "wof:placetype":"neighbourhood"
},
  "geometry": {"coordinates":[6.668,46.60702],"type":"Point"}
}