{
  "type": "Feature",
  "properties": {
    "gn:admin1_code":"BE",
    "gn:admin2_code":"243.0",
    "gn:admin3_code":"496.0",
    "gn:asciiname":"Lindenhof",
    "gn:country_code":"CH",
    "gn:dem":431,
    "gn:feature_class":"P",
    "gn:feature_code":"PPL",
    "gn:name":"Lindenhof",
    "gn:population":0,
    "gn:timezone":"Europe/Zurich",
    "iso:country":"CH",
    "name:deu_x_preferred":[
        "Lindenhof"
    ],
    "name:lat_x_preferred":[
        "Lindenhof"
    ],
    "name:pol_x_preferred":[
        "Lindenhof"
    ],
    "name:rus_x_preferred":[
        "\u041b\u0438\u043d\u0434\u0435\u043d\u0445\u043e\u0444"
    ],
    "name:tur_x_preferred":[
        "Lindenhof"
    ],
    "wof:lang_x_official":[
        "deu",
        "fra",
        "gsw",
        "ita"
    ],
    "wof:lang_x_spoken":[
        "deu",
        "fra",
        "gsw",
        "ita",
        "roh"
    ],
    "wof:name":"Lindenhof",
    "wof:placetype":"neighbourhood"
},
  "geometry": {"coordinates":[7.05833,46.98827],"type":"Point"}
}