{
  "type": "Feature",
  "properties": {
    "gn:admin1_code":"BE",
    "gn:admin2_code":"243.0",
    "gn:admin3_code":"496.0",
    "gn:asciiname":"Lindenhof",
    "gn:country_code":"CH",
    "gn:dem":431,
    "gn:feature_class":"P",
    "gn:feature_code":"PPL",
    "gn:name":"Lindenhof",
    "gn:population":0,
    "gn:timezone":"Europe/Zurich",
    "iso:country":"CH",
    "wof:name":"Lindenhof",
    "wof:placetype":"neighbourhood"
},
  "geometry": {"coordinates":[7.05833,46.98827],"type":"Point"}
}