{
  "type": "Feature",
  "properties": {
    "gn:admin1_code":"ZG",
    "gn:admin2_code":"900.0",
    "gn:admin3_code":"1704.0",
    "gn:asciiname":"Innerblack",
    "gn:country_code":"CH",
    "gn:dem":846,
    "gn:feature_class":"P",
    "gn:feature_code":"PPLL",
    "gn:name":"Innerblack",
    "gn:population":0,
    "gn:timezone":"Europe/Zurich",
    "iso:country":"CH",
    "name:deu_x_preferred":[
        "Innerblack"
    ],
    "wof:name":"Innerblack",
    "wof:placetype":"neighbourhood"
},
  "geometry": {"coordinates":[8.61635,47.16214],"type":"Point"}
}