{
  "type": "Feature",
  "properties": {
    "iso:country":"CH",
    "name:als_x_preferred":[
        "Saint-Cergue"
    ],
    "name:cat_x_preferred":[
        "Saint-Cergue"
    ],
    "name:ceb_x_preferred":[
        "Saint-Cergue"
    ],
    "name:deu_x_preferred":[
        "Saint-Cergue"
    ],
    "name:eng_x_preferred":[
        "Saint-Cergue"
    ],
    "name:epo_x_preferred":[
        "Saint-Cergue"
    ],
    "name:eus_x_preferred":[
        "Saint-Cergue"
    ],
    "name:fra_x_preferred":[
        "Saint-Cergue"
    ],
    "name:gsw_x_preferred":[
        "Saint-Cergue"
    ],
    "name:hun_x_preferred":[
        "Saint-Cergue"
    ],
    "name:ita_x_preferred":[
        "Saint-Cergue"
    ],
    "name:lmo_x_preferred":[
        "Saint-Cergue"
    ],
    "name:ltz_x_preferred":[
        "Saint-Cergue"
    ],
    "name:msa_x_preferred":[
        "Saint-Cergue"
    ],
    "name:nld_x_preferred":[
        "Saint-Cergue"
    ],
    "name:nno_x_preferred":[
        "Saint-Cergue"
    ],
    "name:oci_x_preferred":[
        "Saint-Cergue"
    ],
    "name:por_x_preferred":[
        "Saint-Cergue"
    ],
    "name:roh_x_preferred":[
        "Saint-Cergue"
    ],
    "name:spa_x_preferred":[
        "Saint-Cergue"
    ],
    "name:swe_x_preferred":[
        "Saint-Cergue"
    ],
    "name:unk_x_variant":[
        "Saint-Cergue"
    ],
    "name:vol_x_preferred":[
        "Saint-Cergue"
    ],
    "name:war_x_preferred":[
        "Saint-Cergue"
    ],
    "name:zho_x_preferred":[
        "\u5723\u585e\u5c14\u683c"
    ],
    "qs:a0":"Schweiz#Suisse#Svizzera#Svizra",
    "qs:a1":"*Vaud",
    "qs:a1r":"0",
    "qs:adm0":"Schweiz#Suisse#Svizzera#Svizra",
    "qs:la_lc":"*",
    "qs:level":"locality",
    "qs:loc":"St-Cergue",
    "qs:loc_alt":"St-Cergue",
    "qs:pop":0,
    "qs:type":"buffered point",
    "wd:wordcount":1892,
    "wof:name":"St-Cergue",
    "wof:placetype":"locality"
},
  "geometry": {"coordinates":[6.1578,46.445865],"type":"Point"}
}