{
  "type": "Feature",
  "properties": {
    "gn:admin1_code":"TI",
    "gn:admin2_code":"2105.0",
    "gn:admin3_code":"5226.0",
    "gn:asciiname":"Corte Foan",
    "gn:country_code":"CH",
    "gn:dem":964,
    "gn:feature_class":"P",
    "gn:feature_code":"PPL",
    "gn:name":"Corte Foan",
    "gn:population":0,
    "gn:timezone":"Europe/Zurich",
    "iso:country":"CH",
    "name:ita_x_preferred":[
        "Corte Foan"
    ],
    "wof:name":"Corte Foan",
    "wof:placetype":"neighbourhood"
},
  "geometry": {"coordinates":[8.94535,46.08919],"type":"Point"}
}