{
  "type": "Feature",
  "properties": {
    "gn:admin1_code":"TG",
    "gn:admin2_code":"2015.0",
    "gn:admin3_code":"4951.0",
    "gn:asciiname":"Ziegelhuette",
    "gn:country_code":"CH",
    "gn:dem":474,
    "gn:feature_class":"P",
    "gn:feature_code":"PPLL",
    "gn:name":"Ziegelh\u00fctte",
    "gn:population":0,
    "gn:timezone":"Europe/Zurich",
    "iso:country":"CH",
    "name:deu_x_preferred":[
        "Ziegelh\u00fctte"
    ],
    "wof:name":"Ziegelhuette",
    "wof:placetype":"neighbourhood"
},
  "geometry": {"coordinates":[9.098,47.60522],"type":"Point"}
}