{
  "type": "Feature",
  "properties": {
    "gn:admin1_code":"SG",
    "gn:admin2_code":"1723.0",
    "gn:admin3_code":"3251.0",
    "gn:asciiname":"Borueti",
    "gn:country_code":"CH",
    "gn:dem":745,
    "gn:feature_class":"P",
    "gn:feature_code":"PPLL",
    "gn:name":"Bor\u00fcti",
    "gn:population":0,
    "gn:timezone":"Europe/Zurich",
    "iso:country":"CH",
    "name:deu_x_preferred":[
        "Bor\u00fcti"
    ],
    "wof:name":"Borueti",
    "wof:placetype":"neighbourhood"
},
  "geometry": {"coordinates":[9.53007,47.39083],"type":"Point"}
}