{
  "type": "Feature",
  "properties": {
    "gn:population":2339,
    "iso:country":"CH",
    "name:als_x_preferred":[
        "Krauchthal"
    ],
    "name:cat_x_preferred":[
        "Krauchthal"
    ],
    "name:ceb_x_preferred":[
        "Krauchthal"
    ],
    "name:chv_x_preferred":[
        "\u041a\u0440\u0430\u0443\u0445\u0442\u0430\u043b\u044c"
    ],
    "name:deu_x_preferred":[
        "Krauchthal"
    ],
    "name:eng_x_preferred":[
        "Krauchtal"
    ],
    "name:epo_x_preferred":[
        "Krauchthal"
    ],
    "name:eus_x_preferred":[
        "Krauchthal"
    ],
    "name:fra_x_preferred":[
        "Krauchthal"
    ],
    "name:gsw_x_preferred":[
        "Chrouchtu"
    ],
    "name:hun_x_preferred":[
        "Krauchthal"
    ],
    "name:ita_x_preferred":[
        "Krauchthal"
    ],
    "name:kaz_x_preferred":[
        "\u041a\u0440\u0430\u0443\u0445\u0442\u0430\u043b\u044c"
    ],
    "name:lmo_x_preferred":[
        "Krauchthal"
    ],
    "name:msa_x_preferred":[
        "Krauchthal"
    ],
    "name:nld_x_preferred":[
        "Krauchthal"
    ],
    "name:nno_x_preferred":[
        "Krauchthal"
    ],
    "name:oci_x_preferred":[
        "Krauchthal"
    ],
    "name:rus_x_preferred":[
        "\u041a\u0440\u0430\u0443\u0445\u0442\u0430\u043b\u044c"
    ],
    "name:spa_x_preferred":[
        "Krauchthal"
    ],
    "name:sqi_x_preferred":[
        "Krauchthal"
    ],
    "name:swe_x_preferred":[
        "Krauchthal"
    ],
    "name:unk_x_variant":[
        "Krauchtal"
    ],
    "name:vie_x_preferred":[
        "Krauchthal"
    ],
    "name:vol_x_preferred":[
        "Krauchthal"
    ],
    "name:war_x_preferred":[
        "Krauchthal"
    ],
    "name:zho_x_preferred":[
        "\u514b\u52de\u8d6b\u5854\u723e"
    ],
    "qs:a0":"Schweiz#Suisse#Svizzera#Svizra",
    "qs:a1":"*Bern",
    "qs:a1r":"0",
    "qs:adm0":"Schweiz#Suisse#Svizzera#Svizra",
    "qs:la_lc":"*",
    "qs:level":"locality",
    "qs:loc":"Krauchthal",
    "qs:loc_alt":"Krauchthal",
    "qs:pop":0,
    "qs:type":"buffered point",
    "wd:wordcount":2137,
    "wof:lang":[
        "ger"
    ],
    "wof:name":"Krauchthal",
    "wof:placetype":"locality",
    "wof:population":2339
},
  "geometry": {"coordinates":[7.566613,47.010315],"type":"Point"}
}