{
  "type": "Feature",
  "properties": {
    "gn:gn_country":"CH",
    "gn:gn_fcode":"PPL",
    "gn:gn_pop":179,
    "gn:population":179,
    "iso:country":"CH",
    "name:alb_x_preferred":[
        "Dalpe"
    ],
    "name:baq_x_preferred":[
        "Dalpe"
    ],
    "name:cat_x_preferred":[
        "Dalpe"
    ],
    "name:chi_x_preferred":[
        "\u9054\u723e\u4f69"
    ],
    "name:dut_x_preferred":[
        "Dalpe"
    ],
    "name:eng_x_preferred":[
        "Dalpe"
    ],
    "name:epo_x_preferred":[
        "Dalpe"
    ],
    "name:fre_x_preferred":[
        "Dalpe"
    ],
    "name:ger_x_preferred":[
        "Dalpe"
    ],
    "name:gsw_x_preferred":[
        "Dalpe"
    ],
    "name:hun_x_preferred":[
        "Dalpe"
    ],
    "name:ita_x_preferred":[
        "Dalpe"
    ],
    "name:lmo_x_preferred":[
        "Dalp"
    ],
    "name:may_x_preferred":[
        "Dalpe"
    ],
    "name:nno_x_preferred":[
        "Dalpe"
    ],
    "name:oci_x_preferred":[
        "Dalpe"
    ],
    "name:por_x_preferred":[
        "Dalpe"
    ],
    "name:roh_x_preferred":[
        "Dalpe"
    ],
    "name:spa_x_preferred":[
        "Dalpe"
    ],
    "name:swe_x_preferred":[
        "Dalpe"
    ],
    "name:vol_x_preferred":[
        "Dalpe"
    ],
    "name:war_x_preferred":[
        "Dalpe"
    ],
    "name:zho_x_preferred":[
        "\u9054\u723e\u4f69"
    ],
    "qs_pg:aaroncc":"CH",
    "qs_pg:gn_country":"CH",
    "qs_pg:gn_fcode":"PPL",
    "qs_pg:gn_pop":179,
    "qs_pg:name":"Dalpe",
    "qs_pg:name_adm0":"Schweiz",
    "qs_pg:name_adm1":"Cantone Ticino",
    "qs_pg:photos":32,
    "qs_pg:photos_1k":6,
    "qs_pg:photos_9k":1,
    "qs_pg:photos_9r":2,
    "qs_pg:photos_all":32,
    "qs_pg:photos_sr":2,
    "qs_pg:pop_sr":1,
    "qs_pg:qs_pg_placetype":"locality",
    "qs_pg:qs_pg_placetype_gp":"Town",
    "qs_pg:woe_adm0":23424957,
    "woe:adm0_id":23424957,
    "woe:name_adm0":"Schweiz",
    "woe:name_adm1":"Cantone Ticino",
    "woe:placetype":"Town",
    "wof:name":"Dalpe",
    "wof:placetype":"locality",
    "wof:population":179
},
  "geometry": {"coordinates":[8.77494,46.47292],"type":"Point"}
}