{
  "type": "Feature",
  "properties": {
    "gn:admin1_code":"VD",
    "gn:admin2_code":"2222.0",
    "gn:admin3_code":"5692.0",
    "gn:asciiname":"Vucherens",
    "gn:country_code":"CH",
    "gn:dem":691,
    "gn:feature_class":"P",
    "gn:feature_code":"PPL",
    "gn:name":"Vucherens",
    "gn:population":0,
    "gn:timezone":"Europe/Zurich",
    "iso:country":"CH",
    "name:zho_x_preferred":[
        "\u7ef4\u820d\u6717"
    ],
    "wof:name":"Vucherens",
    "wof:placetype":"locality"
},
  "geometry": {"coordinates":[6.77987,46.62319],"type":"Point"}
}