{
  "type": "Feature",
  "properties": {
    "gn:admin1_code":"TG",
    "gn:admin2_code":"2013.0",
    "gn:admin3_code":"4666.0",
    "gn:asciiname":"Lippoldswilen",
    "gn:country_code":"CH",
    "gn:dem":519,
    "gn:elevation":"508.0",
    "gn:feature_class":"P",
    "gn:feature_code":"PPL",
    "gn:name":"Lippoldswilen",
    "gn:population":0,
    "gn:timezone":"Europe/Zurich",
    "iso:country":"CH",
    "wof:name":"Lippoldswilen",
    "wof:placetype":"locality"
},
  "geometry": {"coordinates":[9.11274,47.61229],"type":"Point"}
}