{
  "type": "Feature",
  "properties": {
    "gn:admin1_code":"VD",
    "gn:admin2_code":"2228.0",
    "gn:admin3_code":"5858.0",
    "gn:asciiname":"Luins",
    "gn:country_code":"CH",
    "gn:dem":440,
    "gn:feature_class":"P",
    "gn:feature_code":"PPL",
    "gn:name":"Luins",
    "gn:population":0,
    "gn:timezone":"Europe/Zurich",
    "iso:country":"CH",
    "wof:name":"Luins",
    "wof:placetype":"locality"
},
  "geometry": {"coordinates":[6.27275,46.44203],"type":"Point"}
}