{
  "type": "Feature",
  "properties": {
    "gn:admin1_code":"GL",
    "gn:admin2_code":"800.0",
    "gn:admin3_code":"1632.0",
    "gn:asciiname":"Rhodannenberg",
    "gn:country_code":"CH",
    "gn:dem":862,
    "gn:feature_class":"P",
    "gn:feature_code":"PPLL",
    "gn:name":"Rhodannenberg",
    "gn:population":0,
    "gn:timezone":"Europe/Zurich",
    "iso:country":"CH",
    "name:deu_x_preferred":[
        "Rhodannenberg"
    ],
    "wof:name":"Rhodannenberg",
    "wof:placetype":"neighbourhood"
},
  "geometry": {"coordinates":[9.00464,47.03636],"type":"Point"}
}