{
  "type": "Feature",
  "properties": {
    "gn:admin1_code":"NW",
    "gn:admin2_code":"700.0",
    "gn:admin3_code":"1510.0",
    "gn:asciiname":"Diethelm",
    "gn:country_code":"CH",
    "gn:dem":672,
    "gn:feature_class":"P",
    "gn:feature_code":"PPL",
    "gn:name":"Diethelm",
    "gn:population":0,
    "gn:timezone":"Europe/Zurich",
    "iso:country":"CH",
    "name:deu_x_preferred":[
        "Diethelm"
    ],
    "name:fra_x_preferred":[
        "Diethelm"
    ],
    "wof:name":"Diethelm",
    "wof:placetype":"neighbourhood"
},
  "geometry": {"coordinates":[8.35147,46.98071],"type":"Point"}
}