{
  "type": "Feature",
  "properties": {
    "gn:gn_country":"CH",
    "gn:gn_fcode":"PPL",
    "gn:gn_pop":1545,
    "gn:population":1545,
    "iso:country":"CH",
    "name:ara_x_preferred":[
        "\u0643\u0627\u0644\u0646\u0627\u062e"
    ],
    "name:cat_x_preferred":[
        "Kallnach"
    ],
    "name:chv_x_preferred":[
        "\u041a\u0430\u043b\u044c\u043d\u0430\u0445"
    ],
    "name:deu_x_preferred":[
        "Kallnach"
    ],
    "name:eng_x_preferred":[
        "Kallnach"
    ],
    "name:epo_x_preferred":[
        "Kallnach"
    ],
    "name:eus_x_preferred":[
        "Kallnach"
    ],
    "name:fra_x_preferred":[
        "Kallnach"
    ],
    "name:gsw_x_preferred":[
        "Chaunech"
    ],
    "name:hun_x_preferred":[
        "Kallnach"
    ],
    "name:ita_x_preferred":[
        "Kallnach"
    ],
    "name:kaz_x_preferred":[
        "\u041a\u0430\u043b\u044c\u043d\u0430\u0445"
    ],
    "name:lmo_x_preferred":[
        "Kallnach"
    ],
    "name:msa_x_preferred":[
        "Kallnach"
    ],
    "name:nld_x_preferred":[
        "Kallnach"
    ],
    "name:nno_x_preferred":[
        "Kallnach"
    ],
    "name:oci_x_preferred":[
        "Kallnach"
    ],
    "name:por_x_preferred":[
        "Kallnach"
    ],
    "name:rus_x_preferred":[
        "\u041a\u0430\u043b\u044c\u043d\u0430\u0445"
    ],
    "name:spa_x_preferred":[
        "Kallnach"
    ],
    "name:sqi_x_preferred":[
        "Kallnach"
    ],
    "name:swe_x_preferred":[
        "Kallnach"
    ],
    "name:vie_x_preferred":[
        "Kallnach"
    ],
    "name:vol_x_preferred":[
        "Kallnach"
    ],
    "name:war_x_preferred":[
        "Kallnach"
    ],
    "name:zho_x_preferred":[
        "\u5361\u723e\u7d0d\u8d6b"
    ],
    "qs_pg:aaroncc":"CH",
    "qs_pg:gn_country":"CH",
    "qs_pg:gn_fcode":"PPL",
    "qs_pg:gn_pop":1545,
    "qs_pg:name":"Kallnach",
    "qs_pg:name_adm0":"Schweiz",
    "qs_pg:name_adm1":"Kanton Bern",
    "qs_pg:photos":62,
    "qs_pg:photos_1k":13,
    "qs_pg:photos_9k":1,
    "qs_pg:photos_9r":2,
    "qs_pg:photos_all":62,
    "qs_pg:photos_sr":2,
    "qs_pg:pop_sr":3,
    "qs_pg:qs_pg_placetype":"locality",
    "qs_pg:qs_pg_placetype_gp":"Town",
    "qs_pg:woe_adm0":23424957,
    "woe:adm0_id":23424957,
    "woe:name_adm0":"Schweiz",
    "woe:name_adm1":"Kanton Bern",
    "woe:placetype":"Town",
    "wof:name":"Kallnach",
    "wof:placetype":"locality",
    "wof:population":1545
},
  "geometry": {"coordinates":[7.23545,47.02032],"type":"Point"}
}