{
  "type": "Feature",
  "properties": {
    "gn:admin1_code":"AG",
    "gn:admin2_code":"1905.0",
    "gn:admin3_code":"4135.0",
    "gn:asciiname":"AEusserer Schwarzenberg",
    "gn:country_code":"CH",
    "gn:dem":621,
    "gn:feature_class":"P",
    "gn:feature_code":"PPLL",
    "gn:name":"\u00c4usserer Schwarzenberg",
    "gn:population":0,
    "gn:timezone":"Europe/Zurich",
    "iso:country":"CH",
    "name:deu_x_preferred":[
        "\u00c4usserer Schwarzenberg"
    ],
    "wof:name":"AEusserer Schwarzenberg",
    "wof:placetype":"neighbourhood"
},
  "geometry": {"coordinates":[8.13886,47.25235],"type":"Point"}
}