{
  "type": "Feature",
  "properties": {
    "gn:gn_country":"CH",
    "gn:gn_fcode":"PPLX",
    "gn:gn_pop":151,
    "gn:population":151,
    "iso:country":"CH",
    "name:unk_x_variant":[
        "Gerimoos"
    ],
    "qs_pg:aaroncc":"CH",
    "qs_pg:gn_country":"CH",
    "qs_pg:gn_fcode":"PPLX",
    "qs_pg:gn_pop":151,
    "qs_pg:name":"R\u00fcschlikon / Gerimoos",
    "qs_pg:photos_9r":0,
    "qs_pg:photos_sr":0,
    "qs_pg:pop_sr":1,
    "qs_pg:qs_pg_placetype":"neighbourhood",
    "wof:name":"R\u00fcschlikon / Gerimoos",
    "wof:placetype":"neighbourhood",
    "wof:population":151
},
  "geometry": {"coordinates":[8.54837,47.3099],"type":"Point"}
}