{
  "type": "Feature",
  "properties": {
    "gn:gn_country":"CH",
    "gn:gn_fcode":"PPL",
    "gn:gn_pop":990,
    "gn:population":990,
    "iso:country":"CH",
    "name:ara_x_preferred":[
        "\u0644\u0648\u0645\u064a"
    ],
    "name:baq_x_preferred":[
        "Lommis"
    ],
    "name:cat_x_preferred":[
        "Lommis"
    ],
    "name:chi_x_preferred":[
        "\u6d1b\u7c73\u65af"
    ],
    "name:dut_x_preferred":[
        "Lommis"
    ],
    "name:eng_x_preferred":[
        "Lommis"
    ],
    "name:epo_x_preferred":[
        "Lommis"
    ],
    "name:fre_x_preferred":[
        "Lommis"
    ],
    "name:ger_x_preferred":[
        "Lommis"
    ],
    "name:gsw_x_preferred":[
        "Lommis"
    ],
    "name:hun_x_preferred":[
        "Lommis"
    ],
    "name:ita_x_preferred":[
        "Lommis"
    ],
    "name:kaz_x_preferred":[
        "\u041b\u043e\u043c\u043c\u0438\u0441"
    ],
    "name:lmo_x_preferred":[
        "Lommis"
    ],
    "name:may_x_preferred":[
        "Lommis"
    ],
    "name:nno_x_preferred":[
        "Lommis"
    ],
    "name:oci_x_preferred":[
        "Lommis"
    ],
    "name:pms_x_preferred":[
        "Lommis"
    ],
    "name:por_x_preferred":[
        "Lommis"
    ],
    "name:rus_x_preferred":[
        "\u041b\u043e\u043c\u043c\u0438\u0441"
    ],
    "name:spa_x_preferred":[
        "Lommis"
    ],
    "name:swe_x_preferred":[
        "Lommis"
    ],
    "name:uzb_x_preferred":[
        "Lommis"
    ],
    "name:vec_x_preferred":[
        "Lommis"
    ],
    "name:vol_x_preferred":[
        "Lommis"
    ],
    "name:war_x_preferred":[
        "Lommis"
    ],
    "name:zho_x_preferred":[
        "\u6d1b\u7c73\u65af"
    ],
    "qs_pg:aaroncc":"CH",
    "qs_pg:gn_country":"CH",
    "qs_pg:gn_fcode":"PPL",
    "qs_pg:gn_pop":990,
    "qs_pg:name":"Lommis",
    "qs_pg:name_adm0":"Schweiz",
    "qs_pg:name_adm1":"Kanton Thurgau",
    "qs_pg:photos_9k":1,
    "qs_pg:photos_9r":1,
    "qs_pg:photos_all":10,
    "qs_pg:photos_sr":0,
    "qs_pg:pop_sr":2,
    "qs_pg:qs_pg_placetype":"locality",
    "qs_pg:qs_pg_placetype_gp":"Town",
    "qs_pg:woe_adm0":23424957,
    "woe:adm0_id":23424957,
    "woe:name_adm0":"Schweiz",
    "woe:name_adm1":"Kanton Thurgau",
    "woe:placetype":"Town",
    "wof:name":"Lommis",
    "wof:placetype":"locality",
    "wof:population":990
},
  "geometry": {"coordinates":[8.99554,47.517],"type":"Point"}
}