{
  "type": "Feature",
  "properties": {
    "gn:admin1_code":"SG",
    "gn:admin2_code":"1721.0",
    "gn:admin3_code":"3444.0",
    "gn:asciiname":"Loch",
    "gn:country_code":"CH",
    "gn:dem":588,
    "gn:feature_class":"P",
    "gn:feature_code":"PPLL",
    "gn:name":"Loch",
    "gn:population":0,
    "gn:timezone":"Europe/Zurich",
    "iso:country":"CH",
    "name:afr_x_preferred":[
        "Loch"
    ],
    "name:ast_x_preferred":[
        "Loch"
    ],
    "name:bar_x_preferred":[
        "Loch"
    ],
    "name:bre_x_preferred":[
        "Loc'h"
    ],
    "name:cat_x_preferred":[
        "Loch"
    ],
    "name:deu_x_preferred":[
        "Loch"
    ],
    "name:epo_x_preferred":[
        "Lo\u0125o"
    ],
    "name:eus_x_preferred":[
        "Loch"
    ],
    "name:fra_x_preferred":[
        "Loch"
    ],
    "name:gla_x_preferred":[
        "Loch"
    ],
    "name:glg_x_preferred":[
        "Loch"
    ],
    "name:heb_x_preferred":[
        "\u05dc\u05d5\u05da"
    ],
    "name:ind_x_preferred":[
        "Loch"
    ],
    "name:ita_x_preferred":[
        "Lough"
    ],
    "name:jpn_x_preferred":[
        "\u30ed\u30c3\u30db"
    ],
    "name:kor_x_preferred":[
        "\ub85c\ud06c"
    ],
    "name:lim_x_preferred":[
        "Loch"
    ],
    "name:mkd_x_preferred":[
        "\u041b\u043e\u0445"
    ],
    "name:nld_x_preferred":[
        "Loch"
    ],
    "name:nno_x_preferred":[
        "Loch"
    ],
    "name:nor_x_preferred":[
        "Loch"
    ],
    "name:pol_x_preferred":[
        "Loch"
    ],
    "name:rus_x_preferred":[
        "\u041b\u043e\u0445"
    ],
    "name:spa_x_preferred":[
        "Loch"
    ],
    "name:ukr_x_preferred":[
        "\u041b\u043e\u0445"
    ],
    "wof:name":"Loch",
    "wof:placetype":"neighbourhood"
},
  "geometry": {"coordinates":[9.24804,47.45904],"type":"Point"}
}