{
  "type": "Feature",
  "properties": {
    "gn:admin1_code":"SG",
    "gn:admin2_code":"1721.0",
    "gn:admin3_code":"3444.0",
    "gn:asciiname":"Loch",
    "gn:country_code":"CH",
    "gn:dem":588,
    "gn:feature_class":"P",
    "gn:feature_code":"PPLL",
    "gn:name":"Loch",
    "gn:population":0,
    "gn:timezone":"Europe/Zurich",
    "iso:country":"CH",
    "name:deu_x_preferred":[
        "Loch"
    ],
    "wof:name":"Loch",
    "wof:placetype":"neighbourhood"
},
  "geometry": {"coordinates":[9.24804,47.45904],"type":"Point"}
}