{
  "type": "Feature",
  "properties": {
    "gn:admin1_code":"TG",
    "gn:admin2_code":"2015.0",
    "gn:admin3_code":"4511.0",
    "gn:asciiname":"Sittertal",
    "gn:country_code":"CH",
    "gn:dem":472,
    "gn:elevation":"470.0",
    "gn:feature_class":"P",
    "gn:feature_code":"PPL",
    "gn:name":"Sittertal",
    "gn:population":0,
    "gn:timezone":"Europe/Zurich",
    "iso:country":"CH",
    "wof:name":"Sittertal",
    "wof:placetype":"neighbourhood"
},
  "geometry": {"coordinates":[9.24184,47.49938],"type":"Point"}
}