{
  "type": "Feature",
  "properties": {
    "gn:admin1_code":"SG",
    "gn:admin2_code":"1721.0",
    "gn:admin3_code":"3444.0",
    "gn:asciiname":"Schoental",
    "gn:country_code":"CH",
    "gn:dem":599,
    "gn:feature_class":"P",
    "gn:feature_code":"PPLL",
    "gn:name":"Sch\u00f6ntal",
    "gn:population":0,
    "gn:timezone":"Europe/Zurich",
    "iso:country":"CH",
    "name:deu_x_preferred":[
        "Sch\u00f6ntal"
    ],
    "wof:lang_x_official":[
        "deu",
        "fra",
        "gsw",
        "ita"
    ],
    "wof:lang_x_spoken":[
        "deu",
        "fra",
        "gsw",
        "ita",
        "roh"
    ],
    "wof:name":"Schoental",
    "wof:placetype":"neighbourhood"
},
  "geometry": {"coordinates":[9.35446,47.46094],"type":"Point"}
}