{
  "type": "Feature",
  "properties": {
    "gn:gn_country":"CH",
    "gn:gn_fcode":"ADM3",
    "gn:gn_pop":326,
    "gn:population":323,
    "iso:country":"CH",
    "name:alb_x_preferred":[
        "Biezwil"
    ],
    "name:baq_x_preferred":[
        "Biezwil"
    ],
    "name:cat_x_preferred":[
        "Biezwil"
    ],
    "name:chi_x_preferred":[
        "\u6bd4\u8328\u7dad\u723e"
    ],
    "name:chv_x_preferred":[
        "\u0411\u0438\u0446\u0432\u0438\u043b\u044c"
    ],
    "name:dut_x_preferred":[
        "Biezwil"
    ],
    "name:eng_x_preferred":[
        "Biezwil"
    ],
    "name:epo_x_preferred":[
        "Biezwil"
    ],
    "name:fre_x_preferred":[
        "Biezwil"
    ],
    "name:ger_x_preferred":[
        "Biezwil"
    ],
    "name:gsw_x_preferred":[
        "Biezwiu"
    ],
    "name:hun_x_preferred":[
        "Biezwil"
    ],
    "name:ita_x_preferred":[
        "Biezwil"
    ],
    "name:kaz_x_preferred":[
        "\u0411\u0438\u0446\u0432\u0438\u043b\u044c"
    ],
    "name:lmo_x_preferred":[
        "Biezwil"
    ],
    "name:may_x_preferred":[
        "Biezwil"
    ],
    "name:nno_x_preferred":[
        "Biezwil"
    ],
    "name:nob_x_preferred":[
        "Biezwil"
    ],
    "name:oci_x_preferred":[
        "Biezwil"
    ],
    "name:rus_x_preferred":[
        "\u0411\u0438\u0446\u0432\u0438\u043b\u044c"
    ],
    "name:spa_x_preferred":[
        "Biezwil"
    ],
    "name:swe_x_preferred":[
        "Biezwil"
    ],
    "name:uzb_x_preferred":[
        "Biezwil"
    ],
    "name:vol_x_preferred":[
        "Biezwil"
    ],
    "name:war_x_preferred":[
        "Biezwil"
    ],
    "qs_pg:aaroncc":"CH",
    "qs_pg:gn_country":"CH",
    "qs_pg:gn_fcode":"ADM3",
    "qs_pg:gn_pop":326,
    "qs_pg:name":"Biezwil",
    "qs_pg:name_adm0":"Schweiz",
    "qs_pg:name_adm1":"Kanton Solothurn",
    "qs_pg:photos_9k":1,
    "qs_pg:photos_9r":1,
    "qs_pg:photos_all":10,
    "qs_pg:photos_sr":0,
    "qs_pg:pop_sr":2,
    "qs_pg:qs_pg_placetype":"locality",
    "qs_pg:qs_pg_placetype_gp":"Town",
    "qs_pg:woe_adm0":23424957,
    "woe:adm0_id":23424957,
    "woe:name_adm0":"Schweiz",
    "woe:name_adm1":"Kanton Solothurn",
    "woe:placetype":"Town",
    "wof:name":"Biezwil",
    "wof:placetype":"locality",
    "wof:population":323
},
  "geometry": {"coordinates":[7.41908,47.11178],"type":"Point"}
}