{
  "type": "Feature",
  "properties": {
    "gn:gn_country":"CH",
    "gn:gn_fcode":"ADM3",
    "gn:gn_pop":170,
    "gn:population":168,
    "iso:country":"CH",
    "name:alb_x_preferred":[
        "Avers"
    ],
    "name:baq_x_preferred":[
        "Avers"
    ],
    "name:cat_x_preferred":[
        "Avers"
    ],
    "name:chi_x_preferred":[
        "\u963f\u97cb\u723e\u65af"
    ],
    "name:dut_x_preferred":[
        "Avers"
    ],
    "name:eng_x_preferred":[
        "Avers"
    ],
    "name:epo_x_preferred":[
        "Avers"
    ],
    "name:fre_x_preferred":[
        "Avers"
    ],
    "name:ger_x_preferred":[
        "Avers"
    ],
    "name:hun_x_preferred":[
        "Avers"
    ],
    "name:ind_x_preferred":[
        "Avers"
    ],
    "name:ita_x_preferred":[
        "Avers"
    ],
    "name:kaz_x_preferred":[
        "\u0410\u0432\u0435\u0440\u0441"
    ],
    "name:lmo_x_preferred":[
        "Avers"
    ],
    "name:may_x_preferred":[
        "Avers"
    ],
    "name:nno_x_preferred":[
        "Avers"
    ],
    "name:oci_x_preferred":[
        "Avers"
    ],
    "name:pms_x_preferred":[
        "Avers"
    ],
    "name:por_x_preferred":[
        "Avers"
    ],
    "name:roh_x_preferred":[
        "Avras"
    ],
    "name:rus_x_preferred":[
        "\u0410\u0432\u0435\u0440\u0441"
    ],
    "name:spa_x_preferred":[
        "Avers"
    ],
    "name:swe_x_preferred":[
        "Avers"
    ],
    "name:ukr_x_preferred":[
        "\u0410\u0432\u0435\u0440\u0441"
    ],
    "name:uzb_x_preferred":[
        "Avers"
    ],
    "name:vol_x_preferred":[
        "Avers"
    ],
    "name:war_x_preferred":[
        "Avers"
    ],
    "qs_pg:aaroncc":"CH",
    "qs_pg:gn_country":"CH",
    "qs_pg:gn_fcode":"ADM3",
    "qs_pg:gn_pop":170,
    "qs_pg:name":"Avers",
    "qs_pg:name_adm0":"Schweiz",
    "qs_pg:name_adm1":"Kanton Graub\u00fcnden",
    "qs_pg:photos_9k":1,
    "qs_pg:photos_9r":1,
    "qs_pg:photos_all":3,
    "qs_pg:photos_sr":0,
    "qs_pg:pop_sr":1,
    "qs_pg:qs_pg_placetype":"locality",
    "qs_pg:qs_pg_placetype_gp":"Town",
    "qs_pg:woe_adm0":23424957,
    "woe:adm0_id":23424957,
    "woe:name_adm0":"Schweiz",
    "woe:name_adm1":"Kanton Graub\u00fcnden",
    "woe:placetype":"Town",
    "wof:name":"Avers",
    "wof:placetype":"locality",
    "wof:population":168
},
  "geometry": {"coordinates":[9.53056,46.44685],"type":"Point"}
}