{
  "type": "Feature",
  "properties": {
    "gn:admin1_code":"SG",
    "gn:admin2_code":"1724.0",
    "gn:admin3_code":"3275.0",
    "gn:asciiname":"Kleinberg",
    "gn:country_code":"CH",
    "gn:dem":633,
    "gn:feature_class":"P",
    "gn:feature_code":"PPLL",
    "gn:name":"Kleinberg",
    "gn:population":0,
    "gn:timezone":"Europe/Zurich",
    "iso:country":"CH",
    "name:ceb_x_preferred":[
        "Kleinberg"
    ],
    "name:deu_x_preferred":[
        "Kleinberg"
    ],
    "name:swe_x_preferred":[
        "Kleinberg"
    ],
    "wof:name":"Kleinberg",
    "wof:placetype":"neighbourhood"
},
  "geometry": {"coordinates":[9.47655,47.11952],"type":"Point"}
}