{
  "type": "Feature",
  "properties": {
    "gn:country":"CH",
    "gn:fcode":"PPLX",
    "gn:population":2632,
    "iso:country":"CH",
    "name:ceb_x_preferred":[
        "Seen"
    ],
    "name:deu_x_preferred":[
        "B\u00fcelwiesen"
    ],
    "name:eng_x_preferred":[
        "B\u00fcelwiesen"
    ],
    "name:swe_x_preferred":[
        "B\u00fcelwiesen"
    ],
    "qs_pg:aaroncc":"CH",
    "qs_pg:gn_country":"CH",
    "qs_pg:gn_fcode":"PPLX",
    "qs_pg:gn_pop":2632,
    "qs_pg:name":"Seen (Kreis 3) / B\u00fcelwiesen",
    "qs_pg:photos_9r":0,
    "qs_pg:photos_sr":0,
    "qs_pg:pop_sr":4,
    "qs_pg:qs_pg_placetype":"neighbourhood",
    "wof:name":"B\u00fcelwiesen",
    "wof:placetype":"neighbourhood",
    "wof:population":2632
},
  "geometry": {"coordinates":[8.76517,47.48446],"type":"Point"}
}