{
  "type": "Feature",
  "properties": {
    "gn:admin1_code":"LU",
    "gn:admin2_code":"313.0",
    "gn:admin3_code":"1023.0",
    "gn:asciiname":"Wald",
    "gn:country_code":"CH",
    "gn:dem":479,
    "gn:elevation":"475.0",
    "gn:feature_class":"P",
    "gn:feature_code":"PPL",
    "gn:name":"Wald",
    "gn:population":0,
    "gn:timezone":"Europe/Zurich",
    "iso:country":"CH",
    "name:als_x_preferred":[
        "Wald"
    ],
    "name:ceb_x_preferred":[
        "Wald"
    ],
    "name:ces_x_preferred":[
        "Wald"
    ],
    "name:deu_x_preferred":[
        "Wald"
    ],
    "name:epo_x_preferred":[
        "Wald"
    ],
    "name:eus_x_preferred":[
        "Wald"
    ],
    "name:fra_x_preferred":[
        "Wald"
    ],
    "name:hye_x_preferred":[
        "\u054e\u0561\u056c\u0564"
    ],
    "name:ita_x_preferred":[
        "Wald"
    ],
    "name:jpn_x_preferred":[
        "\u30f4\u30a1\u30eb\u30c8"
    ],
    "name:kaz_x_preferred":[
        "\u0412\u0430\u043b\u044c\u0434"
    ],
    "name:kir_x_preferred":[
        "\u0412\u0430\u043b\u044c\u0434"
    ],
    "name:lmo_x_preferred":[
        "Wald"
    ],
    "name:nld_x_preferred":[
        "Wald"
    ],
    "name:nno_x_preferred":[
        "Wald"
    ],
    "name:pol_x_preferred":[
        "Wald"
    ],
    "name:por_x_preferred":[
        "Wald"
    ],
    "name:rus_x_preferred":[
        "\u0412\u0430\u043b\u044c\u0434"
    ],
    "name:slv_x_preferred":[
        "Wald"
    ],
    "name:spa_x_preferred":[
        "Wald"
    ],
    "name:srp_x_preferred":[
        "\u0412\u0430\u043b\u0434"
    ],
    "name:swe_x_preferred":[
        "Wald"
    ],
    "name:vol_x_preferred":[
        "Wald"
    ],
    "name:zho_x_preferred":[
        "\u74e6\u723e\u5fb7"
    ],
    "wof:name":"Wald",
    "wof:placetype":"neighbourhood"
},
  "geometry": {"coordinates":[8.3472,47.14054],"type":"Point"}
}