{
  "type": "Feature",
  "properties": {
    "gn:admin1_code":"VD",
    "gn:admin2_code":"2227.0",
    "gn:admin3_code":"5499.0",
    "gn:asciiname":"Soveillame",
    "gn:country_code":"CH",
    "gn:dem":555,
    "gn:feature_class":"P",
    "gn:feature_code":"PPL",
    "gn:name":"Soveillame",
    "gn:population":0,
    "gn:timezone":"Europe/Zurich",
    "iso:country":"CH",
    "name:fra_x_preferred":[
        "Soveillame"
    ],
    "wof:name":"Soveillame",
    "wof:placetype":"neighbourhood"
},
  "geometry": {"coordinates":[6.4874,46.59388],"type":"Point"}
}