{
  "type": "Feature",
  "properties": {
    "gn:admin1_code":"SZ",
    "gn:admin2_code":"502.0",
    "gn:admin3_code":"1311.0",
    "gn:asciiname":"Unter Raengg",
    "gn:country_code":"CH",
    "gn:dem":727,
    "gn:feature_class":"P",
    "gn:feature_code":"PPL",
    "gn:name":"Unter R\u00e4ngg",
    "gn:population":0,
    "gn:timezone":"Europe/Zurich",
    "iso:country":"CH",
    "name:und_x_variant":[
        "Unter R\u00e4ngg",
        "Rengg"
    ],
    "wof:name":"Unter Raengg",
    "wof:placetype":"locality"
},
  "geometry": {"coordinates":[8.5007,46.99546],"type":"Point"}
}