{
  "type": "Feature",
  "properties": {
    "gn:admin1_code":"TI",
    "gn:admin2_code":"2105.0",
    "gn:admin3_code":"5171.0",
    "gn:asciiname":"Piatta",
    "gn:country_code":"CH",
    "gn:dem":321,
    "gn:feature_class":"P",
    "gn:feature_code":"PPL",
    "gn:name":"Piatta",
    "gn:population":0,
    "gn:timezone":"Europe/Rome",
    "iso:country":"CH",
    "name:ita_x_preferred":[
        "Piatta"
    ],
    "wof:lang_x_official":[
        "deu",
        "fra",
        "gsw",
        "ita"
    ],
    "wof:lang_x_spoken":[
        "deu",
        "fra",
        "gsw",
        "ita",
        "roh"
    ],
    "wof:name":"Piatta",
    "wof:placetype":"neighbourhood"
},
  "geometry": {"coordinates":[8.87835,45.95943],"type":"Point"}
}