{
  "type": "Feature",
  "properties": {
    "gn:gn_country":"CH",
    "gn:gn_fcode":"PPLL",
    "gn:gn_pop":5,
    "gn:population":5,
    "iso:country":"CH",
    "qs_pg:aaroncc":"CH",
    "qs_pg:gn_country":"CH",
    "qs_pg:gn_fcode":"PPLL",
    "qs_pg:gn_pop":5,
    "qs_pg:name":"M\u00fchliwis",
    "qs_pg:photos_9r":0,
    "qs_pg:photos_sr":0,
    "qs_pg:pop_sr":1,
    "qs_pg:qs_pg_placetype":"locality",
    "wof:name":"M\u00fchliwis",
    "wof:placetype":"neighbourhood",
    "wof:population":5
},
  "geometry": {"coordinates":[8.65538,47.62222],"type":"Point"}
}