{
  "type": "Feature",
  "properties": {
    "gn:admin1_code":"LU",
    "gn:admin2_code":"314.0",
    "gn:admin3_code":"1091.0",
    "gn:asciiname":"Bergfeld",
    "gn:country_code":"CH",
    "gn:dem":605,
    "gn:feature_class":"P",
    "gn:feature_code":"PPLL",
    "gn:name":"Bergfeld",
    "gn:population":0,
    "gn:timezone":"Europe/Zurich",
    "iso:country":"CH",
    "name:deu_x_preferred":[
        "Bergfeld"
    ],
    "wof:name":"Bergfeld",
    "wof:placetype":"neighbourhood"
},
  "geometry": {"coordinates":[8.0642,47.16324],"type":"Point"}
}