{
  "type": "Feature",
  "properties": {
    "gn:admin1_code":"LU",
    "gn:admin2_code":"316.0",
    "gn:admin3_code":"1107.0",
    "gn:asciiname":"Vordermuehleacher",
    "gn:country_code":"CH",
    "gn:dem":624,
    "gn:feature_class":"P",
    "gn:feature_code":"PPLL",
    "gn:name":"Vorderm\u00fchleacher",
    "gn:population":0,
    "gn:timezone":"Europe/Zurich",
    "iso:country":"CH",
    "name:deu_x_preferred":[
        "Vorderm\u00fchleacher"
    ],
    "wof:name":"Vordermuehleacher",
    "wof:placetype":"neighbourhood"
},
  "geometry": {"coordinates":[8.06091,47.03077],"type":"Point"}
}