{
  "type": "Feature",
  "properties": {
    "gn:admin1_code":"ZH",
    "gn:admin2_code":"102.0",
    "gn:admin3_code":"44.0",
    "gn:asciiname":"Halden",
    "gn:country_code":"CH",
    "gn:dem":456,
    "gn:feature_class":"P",
    "gn:feature_code":"PPLL",
    "gn:name":"Halden",
    "gn:population":0,
    "gn:timezone":"Europe/Zurich",
    "iso:country":"CH",
    "name:deu_x_preferred":[
        "Halden"
    ],
    "wof:name":"Halden",
    "wof:placetype":"neighbourhood"
},
  "geometry": {"coordinates":[8.7743,47.61818],"type":"Point"}
}