{
  "type": "Feature",
  "properties": {
    "gn:admin1_code":"TG",
    "gn:admin2_code":"2012.0",
    "gn:admin3_code":"4816.0",
    "gn:asciiname":"Freieck",
    "gn:country_code":"CH",
    "gn:dem":580,
    "gn:feature_class":"P",
    "gn:feature_code":"PPLL",
    "gn:name":"Freieck",
    "gn:population":0,
    "gn:timezone":"Europe/Zurich",
    "iso:country":"CH",
    "name:deu_x_preferred":[
        "Freieck"
    ],
    "wof:name":"Freieck",
    "wof:placetype":"neighbourhood"
},
  "geometry": {"coordinates":[8.95906,47.64498],"type":"Point"}
}