{
  "type": "Feature",
  "properties": {
    "gn:admin1_code":"LU",
    "gn:admin2_code":"315.0",
    "gn:admin3_code":"1135.0",
    "gn:asciiname":"Unterscheidegg",
    "gn:country_code":"CH",
    "gn:dem":946,
    "gn:feature_class":"P",
    "gn:feature_code":"PPLL",
    "gn:name":"Unterscheidegg",
    "gn:population":0,
    "gn:timezone":"Europe/Zurich",
    "iso:country":"CH",
    "name:deu_x_preferred":[
        "Unterscheidegg"
    ],
    "wof:name":"Unterscheidegg",
    "wof:placetype":"locality"
},
  "geometry": {"coordinates":[7.90438,47.03612],"type":"Point"}
}