{
  "type": "Feature",
  "properties": {
    "gn:admin1_code":"BE",
    "gn:admin2_code":"245.0",
    "gn:admin3_code":"407.0",
    "gn:asciiname":"Wirtenmoos",
    "gn:country_code":"CH",
    "gn:dem":644,
    "gn:feature_class":"P",
    "gn:feature_code":"PPLL",
    "gn:name":"Wirtenmoos",
    "gn:population":0,
    "gn:timezone":"Europe/Zurich",
    "iso:country":"CH",
    "name:deu_x_preferred":[
        "Wirtenmoos"
    ],
    "wof:name":"Wirtenmoos",
    "wof:placetype":"neighbourhood"
},
  "geometry": {"coordinates":[7.64549,47.03346],"type":"Point"}
}