{
  "type": "Feature",
  "properties": {
    "gn:admin1_code":"VD",
    "gn:admin2_code":"2224.0",
    "gn:admin3_code":"5938.0",
    "gn:asciiname":"Gressy",
    "gn:country_code":"CH",
    "gn:dem":502,
    "gn:feature_class":"P",
    "gn:feature_code":"PPL",
    "gn:name":"Gressy",
    "gn:population":0,
    "gn:timezone":"Europe/Zurich",
    "iso:country":"CH",
    "wof:name":"Gressy",
    "wof:placetype":"locality"
},
  "geometry": {"coordinates":[6.63644,46.75021],"type":"Point"}
}