{
  "type": "Feature",
  "properties": {
    "gn:admin1_code":"FR",
    "gn:admin2_code":"1004.0",
    "gn:admin3_code":"2183.0",
    "gn:asciiname":"Chesopelloz",
    "gn:country_code":"CH",
    "gn:dem":623,
    "gn:feature_class":"P",
    "gn:feature_code":"PPL",
    "gn:name":"Ch\u00e9sopelloz",
    "gn:population":0,
    "gn:timezone":"Europe/Zurich",
    "iso:country":"CH",
    "name:und_x_variant":[
        "Ch\u00e9sopelloz"
    ],
    "name:zho_x_preferred":[
        "\u8b1d\u7d22\u4f69\u6d1b"
    ],
    "wof:name":"Chesopelloz",
    "wof:placetype":"locality"
},
  "geometry": {"coordinates":[7.078,46.8081],"type":"Point"}
}