{
  "type": "Feature",
  "properties": {
    "gn:admin1_code":"NW",
    "gn:admin2_code":"700.0",
    "gn:admin3_code":"1508.0",
    "gn:asciiname":"Grummelen",
    "gn:country_code":"CH",
    "gn:dem":460,
    "gn:feature_class":"P",
    "gn:feature_code":"PPL",
    "gn:name":"Grummelen",
    "gn:population":0,
    "gn:timezone":"Europe/Zurich",
    "iso:country":"CH",
    "wof:name":"Grummelen",
    "wof:placetype":"neighbourhood"
},
  "geometry": {"coordinates":[8.37868,46.95137],"type":"Point"}
}