{
  "type": "Feature",
  "properties": {
    "gn:admin1_code":"TI",
    "gn:admin2_code":"2104.0",
    "gn:admin3_code":"5097.0",
    "gn:asciiname":"Pensevrone",
    "gn:country_code":"CH",
    "gn:dem":1211,
    "gn:feature_class":"P",
    "gn:feature_code":"PPL",
    "gn:name":"Pensevrone",
    "gn:population":0,
    "gn:timezone":"Europe/Rome",
    "iso:country":"CH",
    "name:ita_x_preferred":[
        "Pensevrone"
    ],
    "wof:name":"Pensevrone",
    "wof:placetype":"neighbourhood"
},
  "geometry": {"coordinates":[8.67812,46.11584000000001],"type":"Point"}
}