{
  "type": "Feature",
  "properties": {
    "gn:admin1_code":"FR",
    "gn:admin2_code":"1003.0",
    "gn:admin3_code":"2138.0",
    "gn:asciiname":"Perlersweid",
    "gn:country_code":"CH",
    "gn:dem":1091,
    "gn:feature_class":"P",
    "gn:feature_code":"PPL",
    "gn:name":"Perlersweid",
    "gn:population":0,
    "gn:timezone":"Europe/Zurich",
    "iso:country":"CH",
    "name:deu_x_preferred":[
        "Perlersweid"
    ],
    "wof:name":"Perlersweid",
    "wof:placetype":"neighbourhood"
},
  "geometry": {"coordinates":[7.22586,46.60175],"type":"Point"}
}