{
  "type": "Feature",
  "properties": {
    "gn:admin1_code":"BE",
    "gn:admin2_code":"245.0",
    "gn:admin3_code":"418.0",
    "gn:asciiname":"Blattenfeld",
    "gn:country_code":"CH",
    "gn:dem":668,
    "gn:feature_class":"P",
    "gn:feature_code":"PPLL",
    "gn:name":"Blattenfeld",
    "gn:population":0,
    "gn:timezone":"Europe/Zurich",
    "iso:country":"CH",
    "name:deu_x_preferred":[
        "Blattenfeld"
    ],
    "wof:name":"Blattenfeld",
    "wof:placetype":"neighbourhood"
},
  "geometry": {"coordinates":[7.61891,47.02978],"type":"Point"}
}