{
  "type": "Feature",
  "properties": {
    "gn:admin1_code":"SZ",
    "gn:admin2_code":"501.0",
    "gn:admin3_code":"1301.0",
    "gn:asciiname":"Burg",
    "gn:country_code":"CH",
    "gn:dem":903,
    "gn:feature_class":"P",
    "gn:feature_code":"PPLL",
    "gn:name":"Burg",
    "gn:population":0,
    "gn:timezone":"Europe/Zurich",
    "iso:country":"CH",
    "name:deu_x_preferred":[
        "Burg"
    ],
    "wof:name":"Burg",
    "wof:placetype":"neighbourhood"
},
  "geometry": {"coordinates":[8.73614,47.11521],"type":"Point"}
}