{
  "type": "Feature",
  "properties": {
    "gn:admin1_code":"SZ",
    "gn:admin2_code":"501.0",
    "gn:admin3_code":"1301.0",
    "gn:asciiname":"Burg",
    "gn:country_code":"CH",
    "gn:dem":903,
    "gn:feature_class":"P",
    "gn:feature_code":"PPLL",
    "gn:name":"Burg",
    "gn:population":0,
    "gn:timezone":"Europe/Zurich",
    "iso:country":"CH",
    "name:als_x_preferred":[
        "Burg"
    ],
    "name:arg_x_preferred":[
        "Burg"
    ],
    "name:bel_x_preferred":[
        "\u0411\u0443\u0440\u0433"
    ],
    "name:cat_x_preferred":[
        "Burg"
    ],
    "name:ceb_x_preferred":[
        "Burg"
    ],
    "name:dan_x_preferred":[
        "Burg"
    ],
    "name:deu_x_preferred":[
        "Burg"
    ],
    "name:epo_x_preferred":[
        "Burg"
    ],
    "name:fra_x_preferred":[
        "Burg"
    ],
    "name:heb_x_preferred":[
        "\u05d1\u05d5\u05e8\u05d2"
    ],
    "name:ita_x_preferred":[
        "Burg"
    ],
    "name:jpn_x_preferred":[
        "\u30d6\u30eb\u30af"
    ],
    "name:mkd_x_preferred":[
        "\u0411\u0443\u0440\u0433"
    ],
    "name:nld_x_preferred":[
        "Burg"
    ],
    "name:pms_x_preferred":[
        "Burg"
    ],
    "name:pol_x_preferred":[
        "Burg"
    ],
    "name:por_x_preferred":[
        "Burg"
    ],
    "name:rus_x_preferred":[
        "\u0411\u0443\u0440\u0433"
    ],
    "name:spa_x_preferred":[
        "Burg"
    ],
    "name:srp_x_preferred":[
        "Burg"
    ],
    "name:swe_x_preferred":[
        "Burg"
    ],
    "name:ukr_x_preferred":[
        "\u0411\u0443\u0440\u0433"
    ],
    "name:vls_x_preferred":[
        "Burg"
    ],
    "name:vol_x_preferred":[
        "Burg"
    ],
    "wof:name":"Burg",
    "wof:placetype":"neighbourhood"
},
  "geometry": {"coordinates":[8.73614,47.11521],"type":"Point"}
}