{
  "type": "Feature",
  "properties": {
    "gn:gn_country":"CH",
    "gn:gn_fcode":"PPL",
    "gn:gn_pop":55,
    "gn:population":55,
    "iso:country":"CH",
    "name:deu_x_preferred":[
        "Rossura"
    ],
    "name:eng_x_preferred":[
        "Rossura"
    ],
    "name:fra_x_preferred":[
        "Rossura"
    ],
    "name:ita_x_preferred":[
        "Rossura"
    ],
    "name:lmo_x_preferred":[
        "Rossura"
    ],
    "name:nld_x_preferred":[
        "Rossura"
    ],
    "name:por_x_preferred":[
        "Rossura"
    ],
    "qs_pg:aaroncc":"CH",
    "qs_pg:gn_country":"CH",
    "qs_pg:gn_fcode":"PPL",
    "qs_pg:gn_pop":55,
    "qs_pg:name":"Rossura",
    "qs_pg:name_adm0":"Schweiz",
    "qs_pg:name_adm1":"Cantone Ticino",
    "qs_pg:photos":7,
    "qs_pg:photos_1k":1,
    "qs_pg:photos_9k":1,
    "qs_pg:photos_9r":1,
    "qs_pg:photos_all":7,
    "qs_pg:photos_sr":1,
    "qs_pg:pop_sr":1,
    "qs_pg:qs_pg_placetype":"locality",
    "qs_pg:qs_pg_placetype_gp":"Town",
    "qs_pg:woe_adm0":23424957,
    "woe:adm0_id":23424957,
    "woe:name_adm0":"Schweiz",
    "woe:name_adm1":"Cantone Ticino",
    "woe:placetype":"Town",
    "wof:name":"Rossura",
    "wof:placetype":"locality",
    "wof:population":55
},
  "geometry": {"coordinates":[8.82288,46.47534],"type":"Point"}
}