{
  "type": "Feature",
  "properties": {
    "gn:admin1_code":"BE",
    "gn:admin2_code":"244.0",
    "gn:admin3_code":"983.0",
    "gn:asciiname":"Schatteberg",
    "gn:country_code":"CH",
    "gn:dem":471,
    "gn:feature_class":"P",
    "gn:feature_code":"PPLL",
    "gn:name":"Schatteberg",
    "gn:population":0,
    "gn:timezone":"Europe/Zurich",
    "iso:country":"CH",
    "name:deu_x_preferred":[
        "Schatteberg"
    ],
    "wof:name":"Schatteberg",
    "wof:placetype":"neighbourhood"
},
  "geometry": {"coordinates":[7.68452,47.25247],"type":"Point"}
}