{
  "type": "Feature",
  "properties": {
    "gn:admin1_code":"BE",
    "gn:admin2_code":"248.0",
    "gn:admin3_code":"791.0",
    "gn:asciiname":"Chline Baeder",
    "gn:country_code":"CH",
    "gn:dem":1658,
    "gn:feature_class":"P",
    "gn:feature_code":"PPL",
    "gn:name":"Chline B\u00e4der",
    "gn:population":0,
    "gn:timezone":"Europe/Zurich",
    "iso:country":"CH",
    "name:deu_x_preferred":[
        "Chline B\u00e4der"
    ],
    "wof:name":"Chline Baeder",
    "wof:placetype":"locality"
},
  "geometry": {"coordinates":[7.32011,46.60401],"type":"Point"}
}