{
  "type": "Feature",
  "properties": {
    "gn:admin1_code":"TI",
    "gn:admin2_code":"2105.0",
    "gn:admin3_code":"5192.0",
    "gn:asciiname":"Antei",
    "gn:country_code":"CH",
    "gn:dem":707,
    "gn:feature_class":"P",
    "gn:feature_code":"PPL",
    "gn:name":"Antei",
    "gn:population":0,
    "gn:timezone":"Europe/Zurich",
    "iso:country":"CH",
    "name:ita_x_preferred":[
        "Antei"
    ],
    "wof:name":"Antei",
    "wof:placetype":"neighbourhood"
},
  "geometry": {"coordinates":[9.01002,46.06438],"type":"Point"}
}