{
  "type": "Feature",
  "properties": {
    "gn:admin1_code":"TI",
    "gn:admin2_code":"2104.0",
    "gn:admin3_code":"5398.0",
    "gn:asciiname":"Monti di Fosano",
    "gn:country_code":"CH",
    "gn:dem":669,
    "gn:feature_class":"P",
    "gn:feature_code":"PPL",
    "gn:name":"Monti di Fosano",
    "gn:population":0,
    "gn:timezone":"Europe/Zurich",
    "iso:country":"CH",
    "name:ita_x_preferred":[
        "Monti di Fosano"
    ],
    "wof:name":"Monti di Fosano",
    "wof:placetype":"neighbourhood"
},
  "geometry": {"coordinates":[8.83839,46.13164],"type":"Point"}
}