{
  "type": "Feature",
  "properties": {
    "gn:gn_country":"CH",
    "gn:gn_fcode":"PPLX",
    "gn:gn_pop":147,
    "gn:population":147,
    "iso:country":"CH",
    "name:eng_x_preferred":[
        "Chramen"
    ],
    "name:eng_x_variant":[
        "Hombrechtikon / Chramen"
    ],
    "name:unk_x_variant":[
        "Chramen"
    ],
    "qs_pg:aaroncc":"CH",
    "qs_pg:gn_country":"CH",
    "qs_pg:gn_fcode":"PPLX",
    "qs_pg:gn_pop":147,
    "qs_pg:name":"Hombrechtikon / Chramen",
    "qs_pg:photos_9r":0,
    "qs_pg:photos_sr":0,
    "qs_pg:pop_sr":1,
    "qs_pg:qs_pg_placetype":"neighbourhood",
    "wof:name":"Chramen",
    "wof:placetype":"neighbourhood",
    "wof:population":147
},
  "geometry": {"coordinates":[8.7824,47.25601],"type":"Point"}
}