{
  "type": "Feature",
  "properties": {
    "gn:admin1_code":"FR",
    "gn:admin2_code":"1007.0",
    "gn:admin3_code":"2338.0",
    "gn:asciiname":"Les Chupiailles",
    "gn:country_code":"CH",
    "gn:dem":853,
    "gn:feature_class":"P",
    "gn:feature_code":"PPL",
    "gn:name":"Les Chupiailles",
    "gn:population":0,
    "gn:timezone":"Europe/Zurich",
    "iso:country":"CH",
    "name:fra_x_preferred":[
        "Les Chupiailles"
    ],
    "wof:lang_x_official":[
        "deu",
        "fra",
        "gsw",
        "ita"
    ],
    "wof:lang_x_spoken":[
        "deu",
        "fra",
        "gsw",
        "ita",
        "roh"
    ],
    "wof:name":"Les Chupiailles",
    "wof:placetype":"neighbourhood"
},
  "geometry": {"coordinates":[6.94432,46.59855],"type":"Point"}
}