{
  "type": "Feature",
  "properties": {
    "iso:country":"CH",
    "wof:name":"Muesmatt",
    "wof:placetype":"neighbourhood"
},
  "geometry": {"coordinates":[7.42749469941691,46.95316598126587],"type":"Point"}
}