{
  "type": "Feature",
  "properties": {
    "gn:admin1_code":"TI",
    "gn:admin2_code":"2104.0",
    "gn:admin3_code":"5397.0",
    "gn:asciiname":"Calezzo",
    "gn:country_code":"CH",
    "gn:dem":524,
    "gn:feature_class":"P",
    "gn:feature_code":"PPL",
    "gn:name":"Calezzo",
    "gn:population":0,
    "gn:timezone":"Europe/Zurich",
    "iso:country":"CH",
    "wof:name":"Calezzo",
    "wof:placetype":"locality"
},
  "geometry": {"coordinates":[8.68645,46.17424000000001],"type":"Point"}
}