{
  "type": "Feature",
  "properties": {
    "gn:admin1_code":"BE",
    "gn:admin2_code":"244.0",
    "gn:admin3_code":"977.0",
    "gn:asciiname":"Roethenbach Herzogenbuchsee",
    "gn:country_code":"CH",
    "gn:dem":461,
    "gn:feature_class":"P",
    "gn:feature_code":"PPL",
    "gn:name":"R\u00f6thenbach Herzogenbuchsee",
    "gn:population":0,
    "gn:timezone":"Europe/Zurich",
    "iso:country":"CH",
    "wof:name":"Roethenbach Herzogenbuchsee",
    "wof:placetype":"locality"
},
  "geometry": {"coordinates":[7.68159,47.20641],"type":"Point"}
}