{
  "type": "Feature",
  "properties": {
    "gn:country":"CH",
    "gn:fcode":"PPLX",
    "gn:population":226,
    "iso:country":"CH",
    "name:eng_x_preferred":[
        "D\u00f6rnler"
    ],
    "name:eng_x_variant":[
        "Sulz / D\u00f6rnler"
    ],
    "qs_pg:aaroncc":"CH",
    "qs_pg:gn_country":"CH",
    "qs_pg:gn_fcode":"PPLX",
    "qs_pg:gn_pop":226,
    "qs_pg:name":"Sulz / D\u00f6rnler",
    "qs_pg:photos_9r":0,
    "qs_pg:photos_sr":0,
    "qs_pg:pop_sr":2,
    "qs_pg:qs_pg_placetype":"neighbourhood",
    "wof:lang_x_official":[
        "deu",
        "fra",
        "gsw",
        "ita"
    ],
    "wof:lang_x_spoken":[
        "deu",
        "fra",
        "gsw",
        "ita",
        "roh"
    ],
    "wof:name":"D\u00f6rnler",
    "wof:placetype":"neighbourhood",
    "wof:population":226
},
  "geometry": {"coordinates":[8.79143,47.53672],"type":"Point"}
}