{
  "type": "Feature",
  "properties": {
    "gn:gn_country":"CH",
    "gn:gn_fcode":"PPL",
    "gn:gn_pop":2479,
    "gn:population":2479,
    "iso:country":"CH",
    "name:bel_x_preferred":[
        "\u041c\u0435\u0440\u044d\u043d\u0448\u0432\u0430\u043d\u0434"
    ],
    "name:cat_x_preferred":[
        "Merenschwand"
    ],
    "name:ces_x_preferred":[
        "Merenschwand"
    ],
    "name:deu_x_preferred":[
        "Merenschwand"
    ],
    "name:eng_x_preferred":[
        "Merenschwand"
    ],
    "name:epo_x_preferred":[
        "Merenschwand"
    ],
    "name:eus_x_preferred":[
        "Merenschwand"
    ],
    "name:fra_x_preferred":[
        "Merenschwand"
    ],
    "name:gsw_x_preferred":[
        "Merischwand"
    ],
    "name:hun_x_preferred":[
        "Merenschwand"
    ],
    "name:ita_x_preferred":[
        "Merenschwand"
    ],
    "name:kaz_x_preferred":[
        "\u041c\u0435\u0440\u0435\u043d\u0448\u0432\u0430\u043d\u0434"
    ],
    "name:lmo_x_preferred":[
        "Merenschwand"
    ],
    "name:msa_x_preferred":[
        "Merenschwand"
    ],
    "name:nld_x_preferred":[
        "Merenschwand"
    ],
    "name:nno_x_preferred":[
        "Merenschwand"
    ],
    "name:oci_x_preferred":[
        "Merenschwand"
    ],
    "name:pms_x_preferred":[
        "Merenschwand"
    ],
    "name:pol_x_preferred":[
        "Merenschwand"
    ],
    "name:por_x_preferred":[
        "Merenschwand"
    ],
    "name:rus_x_preferred":[
        "\u041c\u0435\u0440\u0435\u043d\u0448\u0432\u0430\u043d\u0434"
    ],
    "name:spa_x_preferred":[
        "Merenschwand"
    ],
    "name:sqi_x_preferred":[
        "Merenschwand"
    ],
    "name:swe_x_preferred":[
        "Merenschwand"
    ],
    "name:uzb_x_preferred":[
        "Merenschwand"
    ],
    "name:vie_x_preferred":[
        "Merenschwand"
    ],
    "name:vol_x_preferred":[
        "Merenschwand"
    ],
    "name:war_x_preferred":[
        "Merenschwand"
    ],
    "name:zho_x_preferred":[
        "\u6885\u502b\u4ec0\u842c\u5fb7"
    ],
    "qs_pg:aaroncc":"CH",
    "qs_pg:gn_country":"CH",
    "qs_pg:gn_fcode":"PPL",
    "qs_pg:gn_pop":2479,
    "qs_pg:name":"Merenschwand",
    "qs_pg:name_adm0":"Schweiz",
    "qs_pg:name_adm1":"Kanton Aargau",
    "qs_pg:photos_9k":1,
    "qs_pg:photos_9r":2,
    "qs_pg:photos_all":31,
    "qs_pg:photos_sr":0,
    "qs_pg:pop_sr":4,
    "qs_pg:qs_pg_placetype":"locality",
    "qs_pg:qs_pg_placetype_gp":"Town",
    "qs_pg:woe_adm0":23424957,
    "woe:adm0_id":23424957,
    "woe:name_adm0":"Schweiz",
    "woe:name_adm1":"Kanton Aargau",
    "woe:placetype":"Town",
    "wof:name":"Merenschwand",
    "wof:placetype":"locality",
    "wof:population":2479
},
  "geometry": {"coordinates":[8.37532,47.2587],"type":"Point"}
}