{
  "type": "Feature",
  "properties": {
    "gn:admin1_code":"GR",
    "gn:admin2_code":"1843.0",
    "gn:admin3_code":"3762.0",
    "gn:asciiname":"Pradella",
    "gn:country_code":"CH",
    "gn:dem":1185,
    "gn:feature_class":"P",
    "gn:feature_code":"PPL",
    "gn:name":"Pradella",
    "gn:population":0,
    "gn:timezone":"Europe/Zurich",
    "iso:country":"CH",
    "wof:name":"Pradella",
    "wof:placetype":"neighbourhood"
},
  "geometry": {"coordinates":[10.323,46.80118],"type":"Point"}
}