{
  "type": "Feature",
  "properties": {
    "gn:admin1_code":"ZH",
    "gn:admin2_code":"105.0",
    "gn:admin3_code":"118.0",
    "gn:asciiname":"Chueeweid",
    "gn:country_code":"CH",
    "gn:dem":536,
    "gn:feature_class":"P",
    "gn:feature_code":"PPLL",
    "gn:name":"Ch\u00fceweid",
    "gn:population":0,
    "gn:timezone":"Europe/Zurich",
    "iso:country":"CH",
    "name:deu_x_preferred":[
        "Ch\u00fceweid"
    ],
    "wof:lang_x_official":[
        "deu",
        "fra",
        "gsw",
        "ita"
    ],
    "wof:lang_x_spoken":[
        "deu",
        "fra",
        "gsw",
        "ita",
        "roh"
    ],
    "wof:name":"Chueeweid",
    "wof:placetype":"neighbourhood"
},
  "geometry": {"coordinates":[8.8715,47.2561],"type":"Point"}
}