{
  "type": "Feature",
  "properties": {
    "gn:admin1_code":"TI",
    "gn:admin2_code":"2105.0",
    "gn:admin3_code":"5226.0",
    "gn:asciiname":"Picchetta",
    "gn:country_code":"CH",
    "gn:dem":995,
    "gn:feature_class":"P",
    "gn:feature_code":"PPL",
    "gn:name":"Picchetta",
    "gn:population":0,
    "gn:timezone":"Europe/Zurich",
    "iso:country":"CH",
    "name:ita_x_preferred":[
        "Picchetta"
    ],
    "wof:name":"Picchetta",
    "wof:placetype":"neighbourhood"
},
  "geometry": {"coordinates":[8.97704,46.09916],"type":"Point"}
}