{
  "type": "Feature",
  "properties": {
    "gn:admin1_code":"FR",
    "gn:admin2_code":"1002.0",
    "gn:admin3_code":"2066.0",
    "gn:asciiname":"Chapelle (Glane)",
    "gn:country_code":"CH",
    "gn:dem":749,
    "gn:feature_class":"P",
    "gn:feature_code":"PPL",
    "gn:name":"Chapelle (Gl\u00e2ne)",
    "gn:population":0,
    "gn:timezone":"Europe/Zurich",
    "iso:country":"CH",
    "name:und_x_variant":[
        "Chapelle (Gl\u00e2ne)"
    ],
    "wof:name":"Chapelle (Glane)",
    "wof:placetype":"locality"
},
  "geometry": {"coordinates":[6.83718,46.58873],"type":"Point"}
}