{
  "type": "Feature",
  "properties": {
    "gn:gn_country":"CH",
    "gn:gn_fcode":"PPL",
    "gn:gn_pop":1199,
    "gn:population":1199,
    "iso:country":"CH",
    "name:bul_x_preferred":[
        "\u0413\u043b\u043e\u0432\u0435\u043b\u0438\u0435\u0440"
    ],
    "name:cat_x_preferred":[
        "Glovelier"
    ],
    "name:deu_x_preferred":[
        "Glovelier"
    ],
    "name:eng_x_preferred":[
        "Glovelier"
    ],
    "name:epo_x_preferred":[
        "Glovelier"
    ],
    "name:fra_x_preferred":[
        "Glovelier"
    ],
    "name:hun_x_preferred":[
        "Glovelier"
    ],
    "name:ita_x_preferred":[
        "Glovelier"
    ],
    "name:lmo_x_preferred":[
        "Glovelier"
    ],
    "name:msa_x_preferred":[
        "Glovelier"
    ],
    "name:nld_x_preferred":[
        "Glovelier"
    ],
    "name:nno_x_preferred":[
        "Glovelier"
    ],
    "name:oci_x_preferred":[
        "Glovelier"
    ],
    "name:roh_x_preferred":[
        "Glovelier"
    ],
    "name:spa_x_preferred":[
        "Glovelier"
    ],
    "name:sqi_x_preferred":[
        "Glovelier"
    ],
    "name:swe_x_preferred":[
        "Glovelier"
    ],
    "name:vol_x_preferred":[
        "Glovelier"
    ],
    "name:war_x_preferred":[
        "Glovelier"
    ],
    "name:zho_x_preferred":[
        "\u683c\u6d1b\u97cb\u5229\u8036"
    ],
    "qs_pg:aaroncc":"CH",
    "qs_pg:gn_country":"CH",
    "qs_pg:gn_fcode":"PPL",
    "qs_pg:gn_pop":1199,
    "qs_pg:name":"Glovelier",
    "qs_pg:name_adm0":"Schweiz",
    "qs_pg:name_adm1":"Canton de Jura",
    "qs_pg:photos":132,
    "qs_pg:photos_1k":27,
    "qs_pg:photos_9k":1,
    "qs_pg:photos_9r":3,
    "qs_pg:photos_all":132,
    "qs_pg:photos_sr":3,
    "qs_pg:pop_sr":3,
    "qs_pg:qs_pg_placetype":"locality",
    "qs_pg:qs_pg_placetype_gp":"Town",
    "qs_pg:woe_adm0":23424957,
    "woe:adm0_id":23424957,
    "woe:name_adm0":"Schweiz",
    "woe:name_adm1":"Canton de Jura",
    "woe:placetype":"Town",
    "wof:name":"Glovelier",
    "wof:placetype":"locality",
    "wof:population":1199
},
  "geometry": {"coordinates":[7.20544,47.33466],"type":"Point"}
}