{
  "type": "Feature",
  "properties": {
    "gn:admin1_code":"JU",
    "gn:admin2_code":"2603.0",
    "gn:admin3_code":"6809.0",
    "gn:asciiname":"Reclere",
    "gn:country_code":"CH",
    "gn:dem":599,
    "gn:feature_class":"P",
    "gn:feature_code":"PPL",
    "gn:name":"R\u00e9cl\u00e8re",
    "gn:population":0,
    "gn:timezone":"Europe/Zurich",
    "iso:country":"CH",
    "wof:name":"Reclere",
    "wof:placetype":"locality"
},
  "geometry": {"coordinates":[6.91898,47.37557],"type":"Point"}
}