{
  "type": "Feature",
  "properties": {
    "gn:gn_country":"CH",
    "gn:gn_fcode":"PPL",
    "gn:gn_pop":2700,
    "gn:population":2700,
    "iso:country":"CH",
    "name:cat_x_preferred":[
        "Lauperswil"
    ],
    "name:chv_x_preferred":[
        "\u041b\u0430\u0443\u043f\u0435\u0440\u0441\u0432\u0438\u043b\u044c"
    ],
    "name:deu_x_preferred":[
        "Lauperswil"
    ],
    "name:eng_x_preferred":[
        "Lauperswil"
    ],
    "name:epo_x_preferred":[
        "Lauperswil"
    ],
    "name:eus_x_preferred":[
        "Lauperswil"
    ],
    "name:fra_x_preferred":[
        "Lauperswil"
    ],
    "name:gsw_x_preferred":[
        "Luperschwiu"
    ],
    "name:hun_x_preferred":[
        "Lauperswil"
    ],
    "name:ita_x_preferred":[
        "Lauperswil"
    ],
    "name:kaz_x_preferred":[
        "\u041b\u0430\u0443\u043f\u0435\u0440\u0441\u0432\u0438\u043b\u044c"
    ],
    "name:lmo_x_preferred":[
        "Lauperswil"
    ],
    "name:msa_x_preferred":[
        "Lauperswil"
    ],
    "name:nld_x_preferred":[
        "Lauperswil"
    ],
    "name:nno_x_preferred":[
        "Lauperswil"
    ],
    "name:oci_x_preferred":[
        "Lauperswil"
    ],
    "name:rus_x_preferred":[
        "\u041b\u0430\u0443\u043f\u0435\u0440\u0441\u0432\u0438\u043b\u044c"
    ],
    "name:spa_x_preferred":[
        "Lauperswil"
    ],
    "name:sqi_x_preferred":[
        "Lauperswil"
    ],
    "name:swe_x_preferred":[
        "Lauperswil"
    ],
    "name:vie_x_preferred":[
        "Lauperswil"
    ],
    "name:vol_x_preferred":[
        "Lauperswil"
    ],
    "name:war_x_preferred":[
        "Lauperswil"
    ],
    "name:zho_x_preferred":[
        "\u52de\u73c0\u65af\u7dad\u723e"
    ],
    "qs_pg:aaroncc":"CH",
    "qs_pg:gn_country":"CH",
    "qs_pg:gn_fcode":"PPL",
    "qs_pg:gn_pop":2700,
    "qs_pg:name":"Lauperswil",
    "qs_pg:name_adm0":"Schweiz",
    "qs_pg:name_adm1":"Kanton Bern",
    "qs_pg:photos_9k":1,
    "qs_pg:photos_9r":1,
    "qs_pg:photos_all":1,
    "qs_pg:photos_sr":0,
    "qs_pg:pop_sr":4,
    "qs_pg:qs_pg_placetype":"locality",
    "qs_pg:qs_pg_placetype_gp":"Town",
    "qs_pg:woe_adm0":23424957,
    "woe:adm0_id":23424957,
    "woe:name_adm0":"Schweiz",
    "woe:name_adm1":"Kanton Bern",
    "woe:placetype":"Town",
    "wof:name":"Lauperswil",
    "wof:placetype":"locality",
    "wof:population":2700
},
  "geometry": {"coordinates":[7.74197,46.96544],"type":"Point"}
}