{
  "type": "Feature",
  "properties": {
    "gn:gn_country":"CH",
    "gn:gn_fcode":"PPL",
    "gn:gn_pop":0,
    "iso:country":"CH",
    "name:cat_x_preferred":[
        "Grandvaux"
    ],
    "name:deu_x_preferred":[
        "Grandvaux VD"
    ],
    "name:eng_x_preferred":[
        "Grandvaux"
    ],
    "name:epo_x_preferred":[
        "Grandvaux VD"
    ],
    "name:fra_x_preferred":[
        "Grandvaux"
    ],
    "name:hun_x_preferred":[
        "Grandvaux"
    ],
    "name:ita_x_preferred":[
        "Grandvaux"
    ],
    "name:lmo_x_preferred":[
        "Grandvaux"
    ],
    "name:nld_x_preferred":[
        "Grandvaux"
    ],
    "name:roh_x_preferred":[
        "Grandvaux"
    ],
    "name:spa_x_preferred":[
        "Grandvaux"
    ],
    "name:swe_x_preferred":[
        "Grandvaux"
    ],
    "name:vol_x_preferred":[
        "Grandvaux"
    ],
    "name:zho_x_preferred":[
        "\u683c\u6717\u6c83"
    ],
    "qs_pg:aaroncc":"CH",
    "qs_pg:gn_country":"CH",
    "qs_pg:gn_fcode":"PPL",
    "qs_pg:gn_pop":0,
    "qs_pg:name":"Grandvaux",
    "qs_pg:name_adm0":"Schweiz",
    "qs_pg:name_adm1":"Canton de Vaud",
    "qs_pg:photos":778,
    "qs_pg:photos_1k":158,
    "qs_pg:photos_9k":3,
    "qs_pg:photos_9r":6,
    "qs_pg:photos_all":778,
    "qs_pg:photos_sr":9,
    "qs_pg:pop_sr":0,
    "qs_pg:qs_pg_placetype":"locality",
    "qs_pg:qs_pg_placetype_gp":"Town",
    "qs_pg:woe_adm0":23424957,
    "woe:adm0_id":23424957,
    "woe:name_adm0":"Schweiz",
    "woe:name_adm1":"Canton de Vaud",
    "woe:placetype":"Town",
    "wof:name":"Grandvaux",
    "wof:placetype":"locality"
},
  "geometry": {"coordinates":[6.71611,46.49381],"type":"Point"}
}