{
  "type": "Feature",
  "properties": {
    "gn:gn_country":"CH",
    "gn:gn_fcode":"PPL",
    "gn:gn_pop":278,
    "gn:population":278,
    "iso:country":"CH",
    "name:alb_x_preferred":[
        "Langwies"
    ],
    "name:cat_x_preferred":[
        "Langwies"
    ],
    "name:chi_x_preferred":[
        "\u6717\u7dad\u65af"
    ],
    "name:dut_x_preferred":[
        "Langwies"
    ],
    "name:eng_x_preferred":[
        "Langwies"
    ],
    "name:epo_x_preferred":[
        "Langwies"
    ],
    "name:fre_x_preferred":[
        "Langwies"
    ],
    "name:ger_x_preferred":[
        "Langwies"
    ],
    "name:hun_x_preferred":[
        "Langwies"
    ],
    "name:ind_x_preferred":[
        "Langwies"
    ],
    "name:ita_x_preferred":[
        "Langwies"
    ],
    "name:kaz_x_preferred":[
        "\u041b\u0430\u043d\u0433\u0432\u0438\u0441"
    ],
    "name:lmo_x_preferred":[
        "Langwies"
    ],
    "name:may_x_preferred":[
        "Langwies"
    ],
    "name:nno_x_preferred":[
        "Langwies"
    ],
    "name:oci_x_preferred":[
        "Langwies"
    ],
    "name:pms_x_preferred":[
        "Langwies"
    ],
    "name:por_x_preferred":[
        "Langwies"
    ],
    "name:roh_x_preferred":[
        "Langwies"
    ],
    "name:rus_x_preferred":[
        "\u041b\u0430\u043d\u0433\u0432\u0438\u0441"
    ],
    "name:spa_x_preferred":[
        "Langwies"
    ],
    "name:swe_x_preferred":[
        "Langwies"
    ],
    "name:uzb_x_preferred":[
        "Langwies"
    ],
    "name:vol_x_preferred":[
        "Langwies"
    ],
    "name:war_x_preferred":[
        "Langwies"
    ],
    "name:zho_x_preferred":[
        "\u6717\u7dad\u65af"
    ],
    "qs_pg:aaroncc":"CH",
    "qs_pg:gn_country":"CH",
    "qs_pg:gn_fcode":"PPL",
    "qs_pg:gn_pop":278,
    "qs_pg:name":"Langwies",
    "qs_pg:name_adm0":"Schweiz",
    "qs_pg:name_adm1":"Kanton Graub\u00fcnden",
    "qs_pg:photos":153,
    "qs_pg:photos_1k":31,
    "qs_pg:photos_9k":1,
    "qs_pg:photos_9r":4,
    "qs_pg:photos_all":153,
    "qs_pg:photos_sr":4,
    "qs_pg:pop_sr":2,
    "qs_pg:qs_pg_placetype":"locality",
    "qs_pg:qs_pg_placetype_gp":"Town",
    "qs_pg:woe_adm0":23424957,
    "woe:adm0_id":23424957,
    "woe:name_adm0":"Schweiz",
    "woe:name_adm1":"Kanton Graub\u00fcnden",
    "woe:placetype":"Town",
    "wof:name":"Langwies",
    "wof:placetype":"locality",
    "wof:population":278
},
  "geometry": {"coordinates":[9.70938,46.81925],"type":"Point"}
}