{
  "type": "Feature",
  "properties": {
    "gn:admin1_code":"FR",
    "gn:admin2_code":"1003.0",
    "gn:admin3_code":"2138.0",
    "gn:asciiname":"Vorsatzli",
    "gn:country_code":"CH",
    "gn:dem":973,
    "gn:feature_class":"P",
    "gn:feature_code":"PPL",
    "gn:name":"Vorsatzli",
    "gn:population":0,
    "gn:timezone":"Europe/Zurich",
    "iso:country":"CH",
    "name:deu_x_preferred":[
        "Vorsatzli"
    ],
    "wof:name":"Vorsatzli",
    "wof:placetype":"neighbourhood"
},
  "geometry": {"coordinates":[7.23257,46.60074],"type":"Point"}
}