{
  "type": "Feature",
  "properties": {
    "gn:admin1_code":"AG",
    "gn:admin2_code":"1908.0",
    "gn:admin3_code":"4222.0",
    "gn:asciiname":"Althaeusern",
    "gn:country_code":"CH",
    "gn:dem":413,
    "gn:elevation":"418.0",
    "gn:feature_class":"P",
    "gn:feature_code":"PPL",
    "gn:name":"Alth\u00e4usern",
    "gn:population":0,
    "gn:timezone":"Europe/Zurich",
    "iso:country":"CH",
    "wof:name":"Althaeusern",
    "wof:placetype":"neighbourhood"
},
  "geometry": {"coordinates":[8.36101,47.2956],"type":"Point"}
}