{
  "type": "Feature",
  "properties": {
    "gn:admin1_code":"TI",
    "gn:admin2_code":"2105.0",
    "gn:admin3_code":"5195.0",
    "gn:asciiname":"Madonna della Cintola",
    "gn:country_code":"CH",
    "gn:dem":301,
    "gn:feature_class":"P",
    "gn:feature_code":"PPL",
    "gn:name":"Madonna della Cintola",
    "gn:population":0,
    "gn:timezone":"Europe/Zurich",
    "iso:country":"CH",
    "name:ita_x_preferred":[
        "Madonna della Cintola"
    ],
    "name:ita_x_variant":[
        "La Madonna"
    ],
    "wof:lang_x_official":[
        "deu",
        "fra",
        "gsw",
        "ita"
    ],
    "wof:lang_x_spoken":[
        "deu",
        "fra",
        "gsw",
        "ita",
        "roh"
    ],
    "wof:name":"Madonna della Cintola",
    "wof:placetype":"neighbourhood"
},
  "geometry": {"coordinates":[8.96744,45.93932],"type":"Point"}
}