{
  "type": "Feature",
  "properties": {
    "gn:gn_country":"CH",
    "gn:gn_fcode":"PPL",
    "gn:gn_pop":1278,
    "gn:population":1278,
    "iso:country":"CH",
    "name:cat_x_preferred":[
        "Les Ponts-de-Martel"
    ],
    "name:deu_x_preferred":[
        "Les Ponts-de-Martel"
    ],
    "name:eng_x_preferred":[
        "Les Ponts-de-Martel"
    ],
    "name:epo_x_preferred":[
        "Les Ponts-de-Martel"
    ],
    "name:eus_x_preferred":[
        "Les Ponts-de-Martel"
    ],
    "name:fra_x_preferred":[
        "Les Ponts-de-Martel"
    ],
    "name:gsw_x_preferred":[
        "Les Ponts-de-Martel"
    ],
    "name:hun_x_preferred":[
        "Les Ponts-de-Martel"
    ],
    "name:ita_x_preferred":[
        "Les Ponts-de-Martel"
    ],
    "name:jpn_x_preferred":[
        "\u30ec\u30fb\u30dd\u30f3\uff1d\u30c9\uff1d\u30de\u30eb\u30c6\u30eb"
    ],
    "name:lmo_x_preferred":[
        "Les Ponts-de-Martel"
    ],
    "name:msa_x_preferred":[
        "Les Ponts-de-Martel"
    ],
    "name:nld_x_preferred":[
        "Les Ponts-de-Martel"
    ],
    "name:nno_x_preferred":[
        "Les Ponts-de-Martel"
    ],
    "name:oci_x_preferred":[
        "Les Ponts-de-Martel"
    ],
    "name:spa_x_preferred":[
        "Les Ponts-de-Martel"
    ],
    "name:swe_x_preferred":[
        "Les Ponts-de-Martel"
    ],
    "name:unk_x_variant":[
        "Les Ponts-Martel"
    ],
    "name:vol_x_preferred":[
        "Les Ponts-de-Martel"
    ],
    "name:war_x_preferred":[
        "Les Ponts-de-Martel"
    ],
    "name:zho_x_preferred":[
        "\u840a\u84ec\u5fb7\u99ac\u723e\u6cf0\u52d2"
    ],
    "qs_pg:aaroncc":"CH",
    "qs_pg:gn_country":"CH",
    "qs_pg:gn_fcode":"PPL",
    "qs_pg:gn_pop":1278,
    "qs_pg:name":"Les Ponts-de-Martel",
    "qs_pg:name_adm0":"Schweiz",
    "qs_pg:name_adm1":"Canton de Neuch\u00e2tel",
    "qs_pg:photos":69,
    "qs_pg:photos_1k":14,
    "qs_pg:photos_9k":1,
    "qs_pg:photos_9r":2,
    "qs_pg:photos_all":69,
    "qs_pg:photos_sr":2,
    "qs_pg:pop_sr":3,
    "qs_pg:qs_pg_placetype":"locality",
    "qs_pg:qs_pg_placetype_gp":"Town",
    "qs_pg:woe_adm0":23424957,
    "woe:adm0_id":23424957,
    "woe:name_adm0":"Schweiz",
    "woe:name_adm1":"Canton de Neuch\u00e2tel",
    "woe:placetype":"Town",
    "wof:name":"Les Ponts-de-Martel",
    "wof:placetype":"locality",
    "wof:population":1278
},
  "geometry": {"coordinates":[6.73356,46.99925],"type":"Point"}
}