{
  "type": "Feature",
  "properties": {
    "gn:admin1_code":"LU",
    "gn:admin2_code":"314.0",
    "gn:admin3_code":"1094.0",
    "gn:asciiname":"Mittelhupraechtigen",
    "gn:country_code":"CH",
    "gn:dem":676,
    "gn:feature_class":"P",
    "gn:feature_code":"PPLL",
    "gn:name":"Mittelhupr\u00e4chtigen",
    "gn:population":0,
    "gn:timezone":"Europe/Zurich",
    "iso:country":"CH",
    "name:deu_x_preferred":[
        "Mittelhupr\u00e4chtigen"
    ],
    "wof:lang_x_official":[
        "deu",
        "fra",
        "gsw",
        "ita"
    ],
    "wof:lang_x_spoken":[
        "deu",
        "fra",
        "gsw",
        "ita",
        "roh"
    ],
    "wof:name":"Mittelhupraechtigen",
    "wof:placetype":"neighbourhood"
},
  "geometry": {"coordinates":[8.14979,47.11643],"type":"Point"}
}