{
  "type": "Feature",
  "properties": {
    "iso:country":"CH",
    "wof:name":"Les Philosophes",
    "wof:placetype":"neighbourhood"
},
  "geometry": {"coordinates":[6.14432233114935,46.19628458924377],"type":"Point"}
}