{
  "type": "Feature",
  "properties": {
    "gn:gn_country":"CH",
    "gn:gn_fcode":"ADM3",
    "gn:gn_pop":570,
    "gn:population":590,
    "iso:country":"CH",
    "name:alb_x_preferred":[
        "Pont-la-Ville"
    ],
    "name:cat_x_preferred":[
        "Pont-la-Ville"
    ],
    "name:chi_x_preferred":[
        "\u84ec\u62c9\u7ef4\u5c14"
    ],
    "name:dut_x_preferred":[
        "Pont-la-Ville"
    ],
    "name:eng_x_preferred":[
        "Pont-la-Ville"
    ],
    "name:epo_x_preferred":[
        "Pont-la-Ville"
    ],
    "name:fre_x_preferred":[
        "Pont-la-Ville"
    ],
    "name:ger_x_preferred":[
        "Pont-la-Ville FR"
    ],
    "name:hun_x_preferred":[
        "Pont-la-Ville"
    ],
    "name:ita_x_preferred":[
        "Pont-la-Ville"
    ],
    "name:lmo_x_preferred":[
        "Pont-la-Ville"
    ],
    "name:may_x_preferred":[
        "Pont-la-Ville"
    ],
    "name:nno_x_preferred":[
        "Pont-la-Ville"
    ],
    "name:oci_x_preferred":[
        "Pont-la-Ville"
    ],
    "name:pms_x_preferred":[
        "Pont-la-Ville"
    ],
    "name:por_x_preferred":[
        "Pont-la-Ville"
    ],
    "name:roh_x_preferred":[
        "Pont-la-Ville"
    ],
    "name:spa_x_preferred":[
        "Pont-la-Ville"
    ],
    "name:swe_x_preferred":[
        "Pont-la-Ville"
    ],
    "name:vol_x_preferred":[
        "Pont-la-Ville"
    ],
    "name:war_x_preferred":[
        "Pont-la-Ville"
    ],
    "qs_pg:aaroncc":"CH",
    "qs_pg:gn_country":"CH",
    "qs_pg:gn_fcode":"ADM3",
    "qs_pg:gn_pop":570,
    "qs_pg:name":"Pont-la-Ville",
    "qs_pg:name_adm0":"Schweiz",
    "qs_pg:name_adm1":"Canton de Fribourg",
    "qs_pg:photos":243,
    "qs_pg:photos_1k":49,
    "qs_pg:photos_9k":1,
    "qs_pg:photos_9r":4,
    "qs_pg:photos_all":243,
    "qs_pg:photos_sr":4,
    "qs_pg:pop_sr":2,
    "qs_pg:qs_pg_placetype":"locality",
    "qs_pg:qs_pg_placetype_gp":"Town",
    "qs_pg:woe_adm0":23424957,
    "woe:adm0_id":23424957,
    "woe:name_adm0":"Schweiz",
    "woe:name_adm1":"Canton de Fribourg",
    "woe:placetype":"Town",
    "wof:name":"Pont-la-Ville",
    "wof:placetype":"locality",
    "wof:population":590
},
  "geometry": {"coordinates":[7.11365,46.7037],"type":"Point"}
}