{
  "type": "Feature",
  "properties": {
    "gn:admin1_code":"BE",
    "gn:admin2_code":"249.0",
    "gn:admin3_code":"762.0",
    "gn:asciiname":"Enetgraben",
    "gn:country_code":"CH",
    "gn:dem":1120,
    "gn:feature_class":"P",
    "gn:feature_code":"PPL",
    "gn:name":"Enetgraben",
    "gn:population":0,
    "gn:timezone":"Europe/Zurich",
    "iso:country":"CH",
    "name:deu_x_preferred":[
        "Enetgraben"
    ],
    "wof:name":"Enetgraben",
    "wof:placetype":"neighbourhood"
},
  "geometry": {"coordinates":[7.51887,46.61186],"type":"Point"}
}