{
  "type": "Feature",
  "properties": {
    "gn:admin1_code":"OW",
    "gn:admin2_code":"600.0",
    "gn:admin3_code":"1404.0",
    "gn:asciiname":"Feltschi",
    "gn:country_code":"CH",
    "gn:dem":1128,
    "gn:feature_class":"P",
    "gn:feature_code":"PPLL",
    "gn:name":"Feltschi",
    "gn:population":0,
    "gn:timezone":"Europe/Zurich",
    "iso:country":"CH",
    "name:deu_x_preferred":[
        "Feltschi"
    ],
    "wof:lang_x_official":[
        "deu",
        "fra",
        "gsw",
        "ita"
    ],
    "wof:lang_x_spoken":[
        "deu",
        "fra",
        "gsw",
        "ita",
        "roh"
    ],
    "wof:name":"Feltschi",
    "wof:placetype":"neighbourhood"
},
  "geometry": {"coordinates":[8.32978,46.91429],"type":"Point"}
}