{
  "type": "Feature",
  "properties": {
    "gn:gn_country":"CH",
    "gn:gn_fcode":"PPLX",
    "gn:gn_pop":1502,
    "gn:population":1502,
    "iso:country":"CH",
    "name:deu_x_preferred":[
        "Hittnau (Dorf)"
    ],
    "name:deu_x_variant":[
        "Hittnau"
    ],
    "name:eng_x_preferred":[
        "Hittnau (Dorf)"
    ],
    "name:eng_x_variant":[
        "Hittnau / Hittnau (Dorf)"
    ],
    "qs_pg:aaroncc":"CH",
    "qs_pg:gn_country":"CH",
    "qs_pg:gn_fcode":"PPLX",
    "qs_pg:gn_pop":1502,
    "qs_pg:name":"Hittnau / Hittnau (Dorf)",
    "qs_pg:photos_9r":0,
    "qs_pg:photos_sr":0,
    "qs_pg:pop_sr":3,
    "qs_pg:qs_pg_placetype":"neighbourhood",
    "wof:name":"Hittnau (Dorf)",
    "wof:placetype":"neighbourhood",
    "wof:population":1502
},
  "geometry": {"coordinates":[8.82418,47.36334],"type":"Point"}
}