{
  "type": "Feature",
  "properties": {
    "gn:admin1_code":"SZ",
    "gn:admin2_code":"505.0",
    "gn:admin3_code":"1345.0",
    "gn:asciiname":"Blattli",
    "gn:country_code":"CH",
    "gn:dem":516,
    "gn:feature_class":"P",
    "gn:feature_code":"PPLL",
    "gn:name":"Blattli",
    "gn:population":0,
    "gn:timezone":"Europe/Zurich",
    "iso:country":"CH",
    "name:deu_x_preferred":[
        "Blattli"
    ],
    "wof:name":"Blattli",
    "wof:placetype":"neighbourhood"
},
  "geometry": {"coordinates":[8.96565,47.16497],"type":"Point"}
}