{
  "type": "Feature",
  "properties": {
    "gn:gn_country":"CH",
    "gn:gn_fcode":"PPL",
    "gn:gn_pop":1243,
    "gn:population":1243,
    "iso:country":"CH",
    "name:cat_x_preferred":[
        "Gr\u00fcsch"
    ],
    "name:deu_x_preferred":[
        "Gr\u00fcsch"
    ],
    "name:eng_x_preferred":[
        "Gr\u00fcsch"
    ],
    "name:epo_x_preferred":[
        "Gr\u00fcsch"
    ],
    "name:eus_x_preferred":[
        "Gr\u00fcsch"
    ],
    "name:fra_x_preferred":[
        "Gr\u00fcsch"
    ],
    "name:hun_x_preferred":[
        "Gr\u00fcsch"
    ],
    "name:ind_x_preferred":[
        "Gr\u00fcsch"
    ],
    "name:ita_x_preferred":[
        "Gr\u00fcsch"
    ],
    "name:kaz_x_preferred":[
        "\u0413\u0440\u044e\u0448"
    ],
    "name:lmo_x_preferred":[
        "Gr\u00fcsch"
    ],
    "name:msa_x_preferred":[
        "Gr\u00fcsch"
    ],
    "name:nld_x_preferred":[
        "Gr\u00fcsch"
    ],
    "name:nno_x_preferred":[
        "Gr\u00fcsch"
    ],
    "name:oci_x_preferred":[
        "Gr\u00fcsch"
    ],
    "name:pms_x_preferred":[
        "Gr\u00fcsch"
    ],
    "name:por_x_preferred":[
        "Gr\u00fcsch"
    ],
    "name:roh_x_preferred":[
        "Crusch"
    ],
    "name:rus_x_preferred":[
        "\u0413\u0440\u044e\u0448"
    ],
    "name:spa_x_preferred":[
        "Gr\u00fcsch"
    ],
    "name:sqi_x_preferred":[
        "Gr\u00fcsch"
    ],
    "name:swe_x_preferred":[
        "Gr\u00fcsch"
    ],
    "name:uzb_x_preferred":[
        "Gr\u00fcsch"
    ],
    "name:vol_x_preferred":[
        "Gr\u00fcsch"
    ],
    "name:war_x_preferred":[
        "Gr\u00fcsch"
    ],
    "name:zho_x_preferred":[
        "\u683c\u5442\u65bd"
    ],
    "qs_pg:aaroncc":"CH",
    "qs_pg:gn_country":"CH",
    "qs_pg:gn_fcode":"PPL",
    "qs_pg:gn_pop":1243,
    "qs_pg:name":"Gr\u00fcsch",
    "qs_pg:name_adm0":"Schweiz",
    "qs_pg:name_adm1":"Kanton Graub\u00fcnden",
    "qs_pg:photos":17,
    "qs_pg:photos_1k":3,
    "qs_pg:photos_9k":1,
    "qs_pg:photos_9r":1,
    "qs_pg:photos_all":17,
    "qs_pg:photos_sr":1,
    "qs_pg:pop_sr":3,
    "qs_pg:qs_pg_placetype":"locality",
    "qs_pg:qs_pg_placetype_gp":"Town",
    "qs_pg:woe_adm0":23424957,
    "woe:adm0_id":23424957,
    "woe:name_adm0":"Schweiz",
    "woe:name_adm1":"Kanton Graub\u00fcnden",
    "woe:placetype":"Town",
    "wof:name":"Gr\u00fcsch",
    "wof:placetype":"locality",
    "wof:population":1243
},
  "geometry": {"coordinates":[9.64639,46.97965],"type":"Point"}
}