{
  "type": "Feature",
  "properties": {
    "gn:admin1_code":"GR",
    "gn:admin2_code":"1841.0",
    "gn:admin3_code":"3543.0",
    "gn:asciiname":"Salaschigns",
    "gn:country_code":"CH",
    "gn:dem":1479,
    "gn:feature_class":"P",
    "gn:feature_code":"PPL",
    "gn:name":"Salaschigns",
    "gn:population":0,
    "gn:timezone":"Europe/Zurich",
    "iso:country":"CH",
    "name:roh_x_preferred":[
        "Salaschigns"
    ],
    "wof:name":"Salaschigns",
    "wof:placetype":"neighbourhood"
},
  "geometry": {"coordinates":[9.56221,46.61456],"type":"Point"}
}