{
  "type": "Feature",
  "properties": {
    "gn:admin1_code":"NW",
    "gn:admin2_code":"700.0",
    "gn:admin3_code":"1501.0",
    "gn:asciiname":"Isenringen",
    "gn:country_code":"CH",
    "gn:dem":433,
    "gn:feature_class":"P",
    "gn:feature_code":"PPL",
    "gn:name":"Isenringen",
    "gn:population":0,
    "gn:timezone":"Europe/Zurich",
    "iso:country":"CH",
    "wof:name":"Isenringen",
    "wof:placetype":"neighbourhood"
},
  "geometry": {"coordinates":[8.47293,46.96892],"type":"Point"}
}