{
  "type": "Feature",
  "properties": {
    "gn:admin1_code":"TG",
    "gn:admin2_code":"2012.0",
    "gn:admin3_code":"4546.0",
    "gn:asciiname":"Schlatt",
    "gn:country_code":"CH",
    "gn:dem":416,
    "gn:feature_class":"P",
    "gn:feature_code":"PPL",
    "gn:name":"Schlatt",
    "gn:population":0,
    "gn:timezone":"Europe/Zurich",
    "iso:country":"CH",
    "name:als_x_preferred":[
        "Schlatt TG"
    ],
    "name:deu_x_preferred":[
        "Schlatt TG"
    ],
    "name:eng_x_preferred":[
        "Schlatt bei Diessenhofen"
    ],
    "name:epo_x_preferred":[
        "Schlatt TG"
    ],
    "name:kaz_x_preferred":[
        "\u0428\u043b\u0430\u0442"
    ],
    "name:nno_x_preferred":[
        "Schlatt bei Diessenhofen"
    ],
    "name:rus_x_preferred":[
        "\u0428\u043b\u0430\u0442"
    ],
    "name:war_x_preferred":[
        "Schlatt bei Diessenhofen"
    ],
    "name:zho_x_preferred":[
        "\u8fea\u68ee\u970d\u82ac\u9644\u8fd1\u65bd\u62c9\u7279"
    ],
    "wof:name":"Schlatt",
    "wof:placetype":"locality"
},
  "geometry": {"coordinates":[8.70332,47.66134],"type":"Point"}
}