{
  "type": "Feature",
  "properties": {
    "iso:country":"CH",
    "qs_pg:aaroncc":"CH",
    "qs_pg:name":"Geneve Airport",
    "qs_pg:name_adm0":"Schweiz",
    "qs_pg:name_adm1":"Canton de Gen\u00e8ve",
    "qs_pg:photos":1556,
    "qs_pg:photos_1k":315,
    "qs_pg:photos_9k":7,
    "qs_pg:photos_9r":8,
    "qs_pg:photos_all":1556,
    "qs_pg:photos_sr":13,
    "qs_pg:pop_sr":0,
    "qs_pg:qs_pg_placetype":"locality",
    "qs_pg:qs_pg_placetype_gp":"Town",
    "qs_pg:woe_adm0":23424957,
    "woe:adm0_id":23424957,
    "woe:name_adm0":"Schweiz",
    "woe:name_adm1":"Canton de Gen\u00e8ve",
    "woe:placetype":"Town",
    "wof:name":"Geneve Airport",
    "wof:placetype":"neighbourhood"
},
  "geometry": {"coordinates":[6.106595,46.233468],"type":"Point"}
}