{
  "type": "Feature",
  "properties": {
    "gn:admin1_code":"SG",
    "gn:admin2_code":"1727.0",
    "gn:admin3_code":"3352.0",
    "gn:asciiname":"Niderwies",
    "gn:country_code":"CH",
    "gn:dem":900,
    "gn:feature_class":"P",
    "gn:feature_code":"PPLL",
    "gn:name":"Niderwies",
    "gn:population":0,
    "gn:timezone":"Europe/Zurich",
    "iso:country":"CH",
    "name:deu_x_preferred":[
        "Niderwies"
    ],
    "wof:name":"Niderwies",
    "wof:placetype":"neighbourhood"
},
  "geometry": {"coordinates":[9.10341,47.25721],"type":"Point"}
}