{
  "type": "Feature",
  "properties": {
    "gn:population":4732,
    "iso:country":"CH",
    "name:als_x_preferred":[
        "Sch\u00f6nenwerd"
    ],
    "name:cat_x_preferred":[
        "Sch\u00f6nenwerd"
    ],
    "name:ceb_x_preferred":[
        "Sch\u00f6nenwerd"
    ],
    "name:deu_x_colloquial":[
        "Schoenenwerd",
        "Schonenwerd"
    ],
    "name:deu_x_preferred":[
        "Sch\u00f6nenwerd"
    ],
    "name:eng_x_preferred":[
        "Sch\u00f6nenwerd"
    ],
    "name:epo_x_preferred":[
        "Sch\u00f6nenwerd"
    ],
    "name:eus_x_preferred":[
        "Sch\u00f6nenwerd"
    ],
    "name:fra_x_preferred":[
        "Sch\u00f6nenwerd"
    ],
    "name:gsw_x_preferred":[
        "Sch\u00f6newerd"
    ],
    "name:hun_x_preferred":[
        "Sch\u00f6nenwerd"
    ],
    "name:ita_x_preferred":[
        "Sch\u00f6nenwerd"
    ],
    "name:kaz_x_preferred":[
        "\u0428\u0451\u043d\u0435\u043d\u0432\u0435\u0440\u0434"
    ],
    "name:lmo_x_preferred":[
        "Sch\u00f6nenwerd"
    ],
    "name:msa_x_preferred":[
        "Sch\u00f6nenwerd"
    ],
    "name:nld_x_preferred":[
        "Sch\u00f6nenwerd"
    ],
    "name:nno_x_preferred":[
        "Sch\u00f6nenwerd"
    ],
    "name:oci_x_preferred":[
        "Sch\u00f6nenwerd"
    ],
    "name:pms_x_preferred":[
        "Sch\u00f6nenwerd"
    ],
    "name:por_x_preferred":[
        "Sch\u00f6nenwerd"
    ],
    "name:rus_x_preferred":[
        "\u0428\u0451\u043d\u0435\u043d\u0432\u0435\u0440\u0434"
    ],
    "name:spa_x_preferred":[
        "Sch\u00f6nenwerd"
    ],
    "name:sqi_x_preferred":[
        "Sch\u00f6nenwerd"
    ],
    "name:uzb_x_preferred":[
        "Sch\u00f6nenwerd"
    ],
    "name:vol_x_preferred":[
        "Sch\u00f6nenwerd"
    ],
    "name:war_x_preferred":[
        "Sch\u00f6nenwerd"
    ],
    "name:zho_x_preferred":[
        "\u820d\u5ae9\u97cb\u5fb7"
    ],
    "qs:a0":"Schweiz#Suisse#Svizzera#Svizra",
    "qs:a1":"*Solothurn",
    "qs:a1r":"0",
    "qs:adm0":"Schweiz#Suisse#Svizzera#Svizra",
    "qs:la_lc":"*",
    "qs:level":"locality",
    "qs:loc":"Sch\u00f6nenwerd",
    "qs:loc_alt":"Schoenenwerd",
    "qs:pop":0,
    "qs:type":"buffered point",
    "wd:wordcount":2088,
    "wof:lang":[
        "ger"
    ],
    "wof:name":"Sch\u00f6nenwerd",
    "wof:placetype":"locality",
    "wof:population":4732
},
  "geometry": {"coordinates":[7.999553,47.370563],"type":"Point"}
}