{
  "type": "Feature",
  "properties": {
    "gn:admin1_code":"TG",
    "gn:admin2_code":"2015.0",
    "gn:admin3_code":"4951.0",
    "gn:asciiname":"Koenigsgut",
    "gn:country_code":"CH",
    "gn:dem":439,
    "gn:feature_class":"P",
    "gn:feature_code":"PPLL",
    "gn:name":"K\u00f6nigsgut",
    "gn:population":0,
    "gn:timezone":"Europe/Zurich",
    "iso:country":"CH",
    "name:deu_x_preferred":[
        "K\u00f6nigsgut"
    ],
    "wof:name":"Koenigsgut",
    "wof:placetype":"neighbourhood"
},
  "geometry": {"coordinates":[9.04696,47.60429],"type":"Point"}
}