{
  "type": "Feature",
  "properties": {
    "gn:admin1_code":"BE",
    "gn:admin2_code":"245.0",
    "gn:admin3_code":"956.0",
    "gn:asciiname":"Zweimatt",
    "gn:country_code":"CH",
    "gn:dem":665,
    "gn:feature_class":"P",
    "gn:feature_code":"PPLL",
    "gn:name":"Zweimatt",
    "gn:population":0,
    "gn:timezone":"Europe/Zurich",
    "iso:country":"CH",
    "name:deu_x_preferred":[
        "Zweimatt"
    ],
    "wof:name":"Zweimatt",
    "wof:placetype":"neighbourhood"
},
  "geometry": {"coordinates":[7.69406,47.03604],"type":"Point"}
}