{
  "type": "Feature",
  "properties": {
    "gn:admin1_code":"TG",
    "gn:admin2_code":"2012.0",
    "gn:admin3_code":"4601.0",
    "gn:asciiname":"Kreuzstrasse",
    "gn:country_code":"CH",
    "gn:dem":515,
    "gn:feature_class":"P",
    "gn:feature_code":"PPLL",
    "gn:name":"Kreuzstrasse",
    "gn:population":0,
    "gn:timezone":"Europe/Zurich",
    "iso:country":"CH",
    "name:deu_x_preferred":[
        "Kreuzstrasse"
    ],
    "wof:name":"Kreuzstrasse",
    "wof:placetype":"locality"
},
  "geometry": {"coordinates":[8.80247,47.60085],"type":"Point"}
}