{
  "type": "Feature",
  "properties": {
    "gn:admin1_code":"GE",
    "gn:admin2_code":"2500.0",
    "gn:admin3_code":"6626.0",
    "gn:asciiname":"Lullier",
    "gn:country_code":"CH",
    "gn:dem":467,
    "gn:elevation":"464.0",
    "gn:feature_class":"P",
    "gn:feature_code":"PPL",
    "gn:name":"Lullier",
    "gn:population":0,
    "gn:timezone":"Europe/Zurich",
    "iso:country":"CH",
    "wof:name":"Lullier",
    "wof:placetype":"neighbourhood"
},
  "geometry": {"coordinates":[6.25729,46.22885],"type":"Point"}
}