{
  "type": "Feature",
  "properties": {
    "gn:admin1_code":"AR",
    "gn:admin2_code":"1502.0",
    "gn:admin3_code":"3025.0",
    "gn:asciiname":"Grueb",
    "gn:country_code":"CH",
    "gn:dem":968,
    "gn:feature_class":"P",
    "gn:feature_code":"PPLL",
    "gn:name":"Grueb",
    "gn:population":0,
    "gn:timezone":"Europe/Zurich",
    "iso:country":"CH",
    "name:deu_x_preferred":[
        "Grueb"
    ],
    "wof:name":"Grueb",
    "wof:placetype":"neighbourhood"
},
  "geometry": {"coordinates":[9.47448,47.39045],"type":"Point"}
}