{
  "type": "Feature",
  "properties": {
    "gn:admin1_code":"BE",
    "gn:admin2_code":"245.0",
    "gn:admin3_code":"956.0",
    "gn:asciiname":"Widithub",
    "gn:country_code":"CH",
    "gn:dem":750,
    "gn:feature_class":"P",
    "gn:feature_code":"PPLL",
    "gn:name":"Widithub",
    "gn:population":0,
    "gn:timezone":"Europe/Zurich",
    "iso:country":"CH",
    "name:deu_x_preferred":[
        "Widithub"
    ],
    "wof:name":"Widithub",
    "wof:placetype":"neighbourhood"
},
  "geometry": {"coordinates":[7.67933,47.03527],"type":"Point"}
}