{
  "type": "Feature",
  "properties": {
    "gn:admin1_code":"TG",
    "gn:admin2_code":"2013.0",
    "gn:admin3_code":"4666.0",
    "gn:asciiname":"Ellighausen",
    "gn:country_code":"CH",
    "gn:dem":523,
    "gn:elevation":"516.0",
    "gn:feature_class":"P",
    "gn:feature_code":"PPL",
    "gn:name":"Ellighausen",
    "gn:population":0,
    "gn:timezone":"Europe/Zurich",
    "iso:country":"CH",
    "wof:name":"Ellighausen",
    "wof:placetype":"locality"
},
  "geometry": {"coordinates":[9.13688,47.61491],"type":"Point"}
}