{
  "type": "Feature",
  "properties": {
    "gn:admin1_code":"SG",
    "gn:admin2_code":"1725.0",
    "gn:admin3_code":"3294.0",
    "gn:asciiname":"Furggels",
    "gn:country_code":"CH",
    "gn:dem":1168,
    "gn:elevation":"1197.0",
    "gn:feature_class":"P",
    "gn:feature_code":"PPL",
    "gn:name":"Furggels",
    "gn:population":0,
    "gn:timezone":"Europe/Zurich",
    "iso:country":"CH",
    "wof:name":"Furggels",
    "wof:placetype":"neighbourhood"
},
  "geometry": {"coordinates":[9.51219,46.98047],"type":"Point"}
}