{
  "type": "Feature",
  "properties": {
    "gn:admin1_code":"TG",
    "gn:admin2_code":"2012.0",
    "gn:admin3_code":"4811.0",
    "gn:asciiname":"Liebenfels",
    "gn:country_code":"CH",
    "gn:dem":564,
    "gn:feature_class":"P",
    "gn:feature_code":"PPLL",
    "gn:name":"Liebenfels",
    "gn:population":0,
    "gn:timezone":"Europe/Zurich",
    "iso:country":"CH",
    "name:deu_x_preferred":[
        "Liebenfels"
    ],
    "wof:name":"Liebenfels",
    "wof:placetype":"locality"
},
  "geometry": {"coordinates":[8.9266,47.63077],"type":"Point"}
}