{
  "type": "Feature",
  "properties": {
    "gn:admin1_code":"GL",
    "gn:admin2_code":"800.0",
    "gn:admin3_code":"1631.0",
    "gn:asciiname":"Moldboden",
    "gn:country_code":"CH",
    "gn:dem":1208,
    "gn:feature_class":"P",
    "gn:feature_code":"PPLL",
    "gn:name":"Moldboden",
    "gn:population":0,
    "gn:timezone":"Europe/Zurich",
    "iso:country":"CH",
    "name:deu_x_preferred":[
        "Moldboden"
    ],
    "wof:name":"Moldboden",
    "wof:placetype":"locality"
},
  "geometry": {"coordinates":[9.15789,46.91553],"type":"Point"}
}