{
  "type": "Feature",
  "properties": {
    "gn:country":"CH",
    "gn:fcode":"PPLL",
    "gn:population":13,
    "iso:country":"CH",
    "name:cat_x_preferred":[
        "Waldhof"
    ],
    "name:deu_x_preferred":[
        "Waldhof"
    ],
    "name:epo_x_preferred":[
        "Waldhof"
    ],
    "name:ltz_x_preferred":[
        "Waldhaff"
    ],
    "name:nld_x_preferred":[
        "Waldhof"
    ],
    "name:pol_x_preferred":[
        "Waldhof"
    ],
    "qs_pg:aaroncc":"CH",
    "qs_pg:gn_country":"CH",
    "qs_pg:gn_fcode":"PPLL",
    "qs_pg:gn_pop":13,
    "qs_pg:name":"Waldhof",
    "qs_pg:photos_9r":0,
    "qs_pg:photos_sr":0,
    "qs_pg:pop_sr":1,
    "qs_pg:qs_pg_placetype":"locality",
    "wof:lang_x_official":[
        "deu",
        "fra",
        "gsw",
        "ita"
    ],
    "wof:lang_x_spoken":[
        "deu",
        "fra",
        "gsw",
        "ita",
        "roh"
    ],
    "wof:name":"Waldhof",
    "wof:placetype":"neighbourhood",
    "wof:population":13
},
  "geometry": {"coordinates":[8.62234,47.23102],"type":"Point"}
}