{
  "type": "Feature",
  "properties": {
    "iso:country":"CH",
    "name:alb_x_preferred":[
        "Farnern"
    ],
    "name:baq_x_preferred":[
        "Farnern"
    ],
    "name:bul_x_preferred":[
        "\u0424\u0430\u0440\u043d\u0435\u0440\u043d"
    ],
    "name:cat_x_preferred":[
        "Farnern"
    ],
    "name:chi_x_preferred":[
        "\u6cd5\u723e\u5167\u6069"
    ],
    "name:dut_x_preferred":[
        "Farnern"
    ],
    "name:eng_x_preferred":[
        "Farnern"
    ],
    "name:epo_x_preferred":[
        "Farnern"
    ],
    "name:fre_x_preferred":[
        "Farnern"
    ],
    "name:ger_x_preferred":[
        "Farnern"
    ],
    "name:gsw_x_preferred":[
        "Faarnere"
    ],
    "name:hun_x_preferred":[
        "Farnern"
    ],
    "name:ita_x_preferred":[
        "Farnern"
    ],
    "name:lmo_x_preferred":[
        "Farnern"
    ],
    "name:may_x_preferred":[
        "Farnern"
    ],
    "name:nno_x_preferred":[
        "Farnern"
    ],
    "name:oci_x_preferred":[
        "Farnern"
    ],
    "name:rus_x_preferred":[
        "\u0424\u0430\u0440\u043d\u0435\u0440\u043d"
    ],
    "name:spa_x_preferred":[
        "Farnern"
    ],
    "name:swe_x_preferred":[
        "Farnern"
    ],
    "name:vie_x_preferred":[
        "Farnern"
    ],
    "name:vol_x_preferred":[
        "Farnern"
    ],
    "name:war_x_preferred":[
        "Farnern"
    ],
    "qs_pg:aaroncc":"CH",
    "qs_pg:name":"Farnern",
    "qs_pg:name_adm0":"Schweiz",
    "qs_pg:name_adm1":"Kanton Bern",
    "qs_pg:photos":2,
    "qs_pg:photos_1k":1,
    "qs_pg:photos_9k":1,
    "qs_pg:photos_9r":1,
    "qs_pg:photos_all":2,
    "qs_pg:photos_sr":1,
    "qs_pg:pop_sr":0,
    "qs_pg:qs_pg_placetype":"locality",
    "qs_pg:qs_pg_placetype_gp":"Town",
    "qs_pg:woe_adm0":23424957,
    "woe:adm0_id":23424957,
    "woe:name_adm0":"Schweiz",
    "woe:name_adm1":"Kanton Bern",
    "woe:placetype":"Town",
    "wof:name":"Farnern",
    "wof:placetype":"locality"
},
  "geometry": {"coordinates":[7.6153275,47.270282],"type":"Point"}
}