{
  "type": "Feature",
  "properties": {
    "gn:admin1_code":"VS",
    "gn:admin2_code":"2305.0",
    "gn:admin3_code":"6084.0",
    "gn:asciiname":"Mache",
    "gn:country_code":"CH",
    "gn:dem":1298,
    "gn:elevation":"1310.0",
    "gn:feature_class":"P",
    "gn:feature_code":"PPL",
    "gn:name":"M\u00e2che",
    "gn:population":0,
    "gn:timezone":"Europe/Zurich",
    "iso:country":"CH",
    "name:ceb_x_preferred":[
        "Mache"
    ],
    "name:deu_x_preferred":[
        "Mache"
    ],
    "name:fra_x_preferred":[
        "Mache"
    ],
    "name:hat_x_preferred":[
        "Mache"
    ],
    "name:nld_x_preferred":[
        "Mache"
    ],
    "name:spa_x_preferred":[
        "Mache"
    ],
    "name:swe_x_preferred":[
        "Mache"
    ],
    "wof:name":"Mache",
    "wof:placetype":"neighbourhood"
},
  "geometry": {"coordinates":[7.39267,46.15665],"type":"Point"}
}