{
  "type": "Feature",
  "properties": {
    "gn:admin1_code":"TI",
    "gn:admin2_code":"2105.0",
    "gn:admin3_code":"5192.0",
    "gn:asciiname":"Alpe Bolla",
    "gn:country_code":"CH",
    "gn:dem":1148,
    "gn:feature_class":"P",
    "gn:feature_code":"PPL",
    "gn:name":"Alpe Bolla",
    "gn:population":0,
    "gn:timezone":"Europe/Zurich",
    "iso:country":"CH",
    "name:ita_x_preferred":[
        "Alpe Bolla"
    ],
    "wof:name":"Alpe Bolla",
    "wof:placetype":"neighbourhood"
},
  "geometry": {"coordinates":[9.00738,46.03678],"type":"Point"}
}