{
  "type": "Feature",
  "properties": {
    "iso:country":"CH",
    "name:alb_x_preferred":[
        "Scharans"
    ],
    "name:baq_x_preferred":[
        "Scharans"
    ],
    "name:cat_x_preferred":[
        "Scharans"
    ],
    "name:chi_x_preferred":[
        "\u6c99\u862d\u65af"
    ],
    "name:cze_x_preferred":[
        "Scharans"
    ],
    "name:dut_x_preferred":[
        "Scharans"
    ],
    "name:eng_x_preferred":[
        "Scharans"
    ],
    "name:epo_x_preferred":[
        "Scharans"
    ],
    "name:fre_x_preferred":[
        "Scharans"
    ],
    "name:ger_x_preferred":[
        "Scharans"
    ],
    "name:gsw_x_preferred":[
        "Scharans"
    ],
    "name:hun_x_preferred":[
        "Scharans"
    ],
    "name:ita_x_preferred":[
        "Scharans"
    ],
    "name:kaz_x_preferred":[
        "\u0428\u0430\u0440\u0430\u043d\u0441"
    ],
    "name:lat_x_preferred":[
        "Schraunis"
    ],
    "name:lmo_x_preferred":[
        "Scharans"
    ],
    "name:may_x_preferred":[
        "Scharans"
    ],
    "name:nno_x_preferred":[
        "Scharans"
    ],
    "name:oci_x_preferred":[
        "Scharans"
    ],
    "name:pms_x_preferred":[
        "Scharans"
    ],
    "name:por_x_preferred":[
        "Scharans"
    ],
    "name:roh_x_preferred":[
        "Scharons"
    ],
    "name:rus_x_preferred":[
        "\u0428\u0430\u0440\u0430\u043d\u0441"
    ],
    "name:spa_x_preferred":[
        "Scharans"
    ],
    "name:swe_x_preferred":[
        "Scharans"
    ],
    "name:uzb_x_preferred":[
        "Scharans"
    ],
    "name:vol_x_preferred":[
        "Scharans"
    ],
    "name:war_x_preferred":[
        "Scharans"
    ],
    "qs_pg:aaroncc":"CH",
    "qs_pg:name":"Scharans",
    "qs_pg:name_adm0":"Schweiz",
    "qs_pg:name_adm1":"Kanton Graub\u00fcnden",
    "qs_pg:photos":24,
    "qs_pg:photos_1k":5,
    "qs_pg:photos_9k":1,
    "qs_pg:photos_9r":1,
    "qs_pg:photos_all":24,
    "qs_pg:photos_sr":1,
    "qs_pg:pop_sr":0,
    "qs_pg:qs_pg_placetype":"locality",
    "qs_pg:qs_pg_placetype_gp":"Town",
    "qs_pg:woe_adm0":23424957,
    "woe:adm0_id":23424957,
    "woe:name_adm0":"Schweiz",
    "woe:name_adm1":"Kanton Graub\u00fcnden",
    "woe:placetype":"Town",
    "wof:name":"Scharans",
    "wof:placetype":"locality"
},
  "geometry": {"coordinates":[9.458541,46.718269],"type":"Point"}
}