{
  "type": "Feature",
  "properties": {
    "gn:admin1_code":"TG",
    "gn:admin2_code":"2012.0",
    "gn:admin3_code":"4864.0",
    "gn:asciiname":"Im Laendli",
    "gn:country_code":"CH",
    "gn:dem":516,
    "gn:feature_class":"P",
    "gn:feature_code":"PPLL",
    "gn:name":"Im L\u00e4ndli",
    "gn:population":0,
    "gn:timezone":"Europe/Zurich",
    "iso:country":"CH",
    "name:deu_x_preferred":[
        "Im L\u00e4ndli"
    ],
    "wof:name":"Im Laendli",
    "wof:placetype":"locality"
},
  "geometry": {"coordinates":[8.98059,47.65439],"type":"Point"}
}