{
  "type": "Feature",
  "properties": {
    "gn:admin1_code":"NW",
    "gn:admin2_code":"700.0",
    "gn:admin3_code":"1502.0",
    "gn:asciiname":"Baechli",
    "gn:country_code":"CH",
    "gn:dem":548,
    "gn:feature_class":"P",
    "gn:feature_code":"PPL",
    "gn:name":"B\u00e4chli",
    "gn:population":0,
    "gn:timezone":"Europe/Zurich",
    "iso:country":"CH",
    "wof:name":"Baechli",
    "wof:placetype":"neighbourhood"
},
  "geometry": {"coordinates":[8.41225,46.96516],"type":"Point"}
}