{
  "type": "Feature",
  "properties": {
    "gn:admin1_code":"TI",
    "gn:admin2_code":"2103.0",
    "gn:admin3_code":"5063.0",
    "gn:asciiname":"All'Acqua",
    "gn:country_code":"CH",
    "gn:dem":1613,
    "gn:feature_class":"P",
    "gn:feature_code":"PPL",
    "gn:name":"All\u2019Acqua",
    "gn:population":0,
    "gn:timezone":"Europe/Zurich",
    "iso:country":"CH",
    "name:und_x_variant":[
        "All\u2019Acqua Ospizio",
        "All\u2019Acqua"
    ],
    "wof:name":"All'Acqua",
    "wof:placetype":"neighbourhood"
},
  "geometry": {"coordinates":[8.47515,46.48653],"type":"Point"}
}