{
  "type": "Feature",
  "properties": {
    "gn:country":"CH",
    "gn:fcode":"PPLX",
    "gn:population":195,
    "iso:country":"CH",
    "name:eng_x_preferred":[
        "Libellenweg"
    ],
    "name:eng_x_variant":[
        "D\u00fcbendorf / Libellenweg"
    ],
    "qs_pg:aaroncc":"CH",
    "qs_pg:gn_country":"CH",
    "qs_pg:gn_fcode":"PPLX",
    "qs_pg:gn_pop":195,
    "qs_pg:name":"D\u00fcbendorf / Libellenweg",
    "qs_pg:photos_9r":0,
    "qs_pg:photos_sr":0,
    "qs_pg:pop_sr":1,
    "qs_pg:qs_pg_placetype":"neighbourhood",
    "wof:lang_x_official":[
        "deu",
        "fra",
        "gsw",
        "ita"
    ],
    "wof:lang_x_spoken":[
        "deu",
        "fra",
        "gsw",
        "ita",
        "roh"
    ],
    "wof:name":"Libellenweg",
    "wof:placetype":"neighbourhood",
    "wof:population":195
},
  "geometry": {"coordinates":[8.62374,47.40586],"type":"Point"}
}