{
  "type": "Feature",
  "properties": {
    "gn:admin1_code":"TG",
    "gn:admin2_code":"2013.0",
    "gn:admin3_code":"4666.0",
    "gn:asciiname":"Geboltshausen",
    "gn:country_code":"CH",
    "gn:dem":536,
    "gn:feature_class":"P",
    "gn:feature_code":"PPLL",
    "gn:name":"Geboltshausen",
    "gn:population":0,
    "gn:timezone":"Europe/Zurich",
    "iso:country":"CH",
    "name:deu_x_preferred":[
        "Geboltshausen"
    ],
    "wof:name":"Geboltshausen",
    "wof:placetype":"neighbourhood"
},
  "geometry": {"coordinates":[9.14377,47.61934],"type":"Point"}
}