{
  "type": "Feature",
  "properties": {
    "gn:admin1_code":"ZH",
    "gn:admin2_code":"110.0",
    "gn:admin3_code":"211.0",
    "gn:asciiname":"Binz",
    "gn:country_code":"CH",
    "gn:dem":449,
    "gn:feature_class":"P",
    "gn:feature_code":"PPLL",
    "gn:name":"Binz",
    "gn:population":0,
    "gn:timezone":"Europe/Zurich",
    "iso:country":"CH",
    "name:deu_x_preferred":[
        "Binz"
    ],
    "wof:name":"Binz",
    "wof:placetype":"neighbourhood"
},
  "geometry": {"coordinates":[8.78362,47.56749],"type":"Point"}
}