{
  "type": "Feature",
  "properties": {
    "gn:gn_country":"CH",
    "gn:gn_fcode":"PPL",
    "gn:gn_pop":28,
    "gn:population":28,
    "iso:country":"CH",
    "name:deu_x_preferred":[
        "Mutzmalen"
    ],
    "name:eng_x_preferred":[
        "Mutzmalen"
    ],
    "name:fra_x_preferred":[
        "Mutzmalen"
    ],
    "name:nld_x_preferred":[
        "Mutzmalen"
    ],
    "name:roh_x_preferred":[
        "Mutzmalen"
    ],
    "qs_pg:aaroncc":"CH",
    "qs_pg:gn_country":"CH",
    "qs_pg:gn_fcode":"PPL",
    "qs_pg:gn_pop":28,
    "qs_pg:name":"Mutzmalen",
    "qs_pg:photos_9r":0,
    "qs_pg:photos_sr":0,
    "qs_pg:pop_sr":1,
    "qs_pg:qs_pg_placetype":"locality",
    "wof:name":"Mutzmalen",
    "wof:placetype":"neighbourhood",
    "wof:population":28
},
  "geometry": {"coordinates":[8.71287,47.2481],"type":"Point"}
}