{
  "type": "Feature",
  "properties": {
    "gn:admin1_code":"LU",
    "gn:admin2_code":"316.0",
    "gn:admin3_code":"1002.0",
    "gn:asciiname":"Breitwang",
    "gn:country_code":"CH",
    "gn:dem":1475,
    "gn:feature_class":"P",
    "gn:feature_code":"PPLL",
    "gn:name":"Breitwang",
    "gn:population":0,
    "gn:timezone":"Europe/Zurich",
    "iso:country":"CH",
    "name:deu_x_preferred":[
        "Breitwang"
    ],
    "wof:name":"Breitwang",
    "wof:placetype":"neighbourhood"
},
  "geometry": {"coordinates":[8.09054,46.91543],"type":"Point"}
}