{
  "type": "Feature",
  "properties": {
    "gn:admin1_code":"GE",
    "gn:admin2_code":"2500.0",
    "gn:admin3_code":"6615.0",
    "gn:asciiname":"Bossy",
    "gn:country_code":"CH",
    "gn:dem":459,
    "gn:elevation":"462.0",
    "gn:feature_class":"P",
    "gn:feature_code":"PPL",
    "gn:name":"Bossy",
    "gn:population":0,
    "gn:timezone":"Europe/Zurich",
    "iso:country":"CH",
    "name:deu_x_preferred":[
        "Bossy"
    ],
    "name:fra_x_preferred":[
        "Bossy"
    ],
    "name:ita_x_preferred":[
        "Bossy"
    ],
    "wof:lang_x_official":[
        "deu",
        "fra",
        "gsw",
        "ita"
    ],
    "wof:lang_x_spoken":[
        "deu",
        "fra",
        "gsw",
        "ita",
        "roh"
    ],
    "wof:name":"Bossy",
    "wof:placetype":"neighbourhood"
},
  "geometry": {"coordinates":[6.11484,46.28091],"type":"Point"}
}