{
  "type": "Feature",
  "properties": {
    "iso:country":"CH",
    "name:deu_x_preferred":[
        "Flugplatz Triengen"
    ],
    "name:eng_x_preferred":[
        "Triengen Airport"
    ],
    "name:msa_x_preferred":[
        "Lapangan Terbang Triengen"
    ],
    "name:ron_x_preferred":[
        "Aeroportul Triengen"
    ],
    "oa:elevation_ft":"1594",
    "oa:type":"small_airport",
    "woe:hierarchy":{
        "country_id":23424957,
        "county_id":12593207,
        "localadmin_id":12684517,
        "planet_id":1,
        "state_id":2347093
    },
    "wof:name":"Flugplatz Triengen",
    "wof:placetype":"campus"
},
  "geometry": {"coordinates":[8.078056,47.226667],"type":"Point"}
}