{
  "type": "Feature",
  "properties": {
    "gn:admin1_code":"BE",
    "gn:admin2_code":"250.0",
    "gn:admin3_code":"576.0",
    "gn:asciiname":"Rauft",
    "gn:country_code":"CH",
    "gn:dem":1517,
    "gn:feature_class":"P",
    "gn:feature_code":"PPL",
    "gn:name":"Rauft",
    "gn:population":0,
    "gn:timezone":"Europe/Zurich",
    "iso:country":"CH",
    "name:deu_x_preferred":[
        "Rauft"
    ],
    "wof:name":"Rauft",
    "wof:placetype":"locality"
},
  "geometry": {"coordinates":[7.98233,46.61936],"type":"Point"}
}