{
  "type": "Feature",
  "properties": {
    "gn:admin1_code":"GR",
    "gn:admin2_code":"1841.0",
    "gn:admin3_code":"3543.0",
    "gn:asciiname":"Tussagn",
    "gn:country_code":"CH",
    "gn:dem":1818,
    "gn:feature_class":"P",
    "gn:feature_code":"PPL",
    "gn:name":"Tussagn",
    "gn:population":0,
    "gn:timezone":"Europe/Zurich",
    "iso:country":"CH",
    "name:roh_x_preferred":[
        "Tussagn"
    ],
    "wof:name":"Tussagn",
    "wof:placetype":"neighbourhood"
},
  "geometry": {"coordinates":[9.61813,46.5994],"type":"Point"}
}