{
  "type": "Feature",
  "properties": {
    "gn:admin1_code":"BL",
    "gn:admin2_code":"1305.0",
    "gn:admin3_code":"2885.0",
    "gn:asciiname":"Hinterbirch",
    "gn:country_code":"CH",
    "gn:dem":783,
    "gn:feature_class":"P",
    "gn:feature_code":"PPLL",
    "gn:name":"Hinterbirch",
    "gn:population":0,
    "gn:timezone":"Europe/Zurich",
    "iso:country":"CH",
    "name:deu_x_preferred":[
        "Hinterbirch"
    ],
    "wof:name":"Hinterbirch",
    "wof:placetype":"locality"
},
  "geometry": {"coordinates":[7.79462,47.38199],"type":"Point"}
}