{
  "type": "Feature",
  "properties": {
    "gn:admin1_code":"BE",
    "gn:admin2_code":"245.0",
    "gn:admin3_code":"423.0",
    "gn:asciiname":"Willadingen",
    "gn:country_code":"CH",
    "gn:dem":462,
    "gn:feature_class":"P",
    "gn:feature_code":"PPL",
    "gn:name":"Willadingen",
    "gn:population":0,
    "gn:timezone":"Europe/Zurich",
    "iso:country":"CH",
    "wof:name":"Willadingen",
    "wof:placetype":"locality"
},
  "geometry": {"coordinates":[7.61112,47.14667],"type":"Point"}
}