{
  "type": "Feature",
  "properties": {
    "gn:admin1_code":"AR",
    "gn:admin2_code":"1501.0",
    "gn:admin3_code":"3001.0",
    "gn:asciiname":"Flue",
    "gn:country_code":"CH",
    "gn:dem":871,
    "gn:feature_class":"P",
    "gn:feature_code":"PPLL",
    "gn:name":"Flue",
    "gn:population":0,
    "gn:timezone":"Europe/Zurich",
    "iso:country":"CH",
    "name:deu_x_preferred":[
        "Flue"
    ],
    "name:deu_x_variant":[
        "Rauchfang"
    ],
    "name:rus_x_preferred":[
        "\u0414\u044b\u043c\u043e\u0433\u0430\u0440\u043d\u044b\u0435 \u0442\u0440\u0443\u0431\u044b"
    ],
    "name:ukr_x_preferred":[
        "\u0414\u0438\u043c\u043e\u0433\u0430\u0440\u043d\u0456 \u0442\u0440\u0443\u0431\u0438"
    ],
    "wof:name":"Flue",
    "wof:placetype":"neighbourhood"
},
  "geometry": {"coordinates":[9.25352,47.38406],"type":"Point"}
}