{
  "type": "Feature",
  "properties": {
    "gn:admin1_code":"TI",
    "gn:admin2_code":"2104.0",
    "gn:admin3_code":"5398.0",
    "gn:asciiname":"Campiscioni",
    "gn:country_code":"CH",
    "gn:dem":197,
    "gn:feature_class":"P",
    "gn:feature_code":"PPL",
    "gn:name":"Campiscioni",
    "gn:population":0,
    "gn:timezone":"Europe/Zurich",
    "iso:country":"CH",
    "name:ita_x_preferred":[
        "Campiscioni"
    ],
    "wof:name":"Campiscioni",
    "wof:placetype":"locality"
},
  "geometry": {"coordinates":[8.88828,46.15389],"type":"Point"}
}