{
  "type": "Feature",
  "properties": {
    "gn:gn_country":"CH",
    "gn:gn_fcode":"PPL",
    "gn:gn_pop":31,
    "gn:population":31,
    "iso:country":"CH",
    "name:als_x_preferred":[
        "Brunegg"
    ],
    "name:ast_x_preferred":[
        "Brunegg"
    ],
    "name:ceb_x_preferred":[
        "Brunegg"
    ],
    "name:deu_x_preferred":[
        "Brunegg"
    ],
    "name:epo_x_preferred":[
        "Brunegg"
    ],
    "name:eus_x_preferred":[
        "Brunegg"
    ],
    "name:fra_x_preferred":[
        "Brunegg"
    ],
    "name:ita_x_preferred":[
        "Brunegg"
    ],
    "name:kaz_x_preferred":[
        "\u0411\u0440\u0443\u043d\u0435\u0433"
    ],
    "name:lmo_x_preferred":[
        "Brunegg"
    ],
    "name:msa_x_preferred":[
        "Brunegg"
    ],
    "name:nld_x_preferred":[
        "Brunegg"
    ],
    "name:nno_x_preferred":[
        "Brunegg"
    ],
    "name:pms_x_preferred":[
        "Brunegg"
    ],
    "name:pol_x_preferred":[
        "Brunegg"
    ],
    "name:por_x_preferred":[
        "Brunegg"
    ],
    "name:rus_x_preferred":[
        "\u0411\u0440\u0443\u043d\u0435\u0433\u0433"
    ],
    "name:spa_x_preferred":[
        "Brunegg"
    ],
    "name:sqi_x_preferred":[
        "Brunegg"
    ],
    "name:swe_x_preferred":[
        "Brunegg"
    ],
    "name:uzb_x_preferred":[
        "Brunegg"
    ],
    "name:vol_x_preferred":[
        "Brunegg"
    ],
    "name:war_x_preferred":[
        "Brunegg"
    ],
    "name:zho_x_preferred":[
        "\u5e03\u9b6f\u5167\u683c"
    ],
    "qs_pg:aaroncc":"CH",
    "qs_pg:gn_country":"CH",
    "qs_pg:gn_fcode":"PPL",
    "qs_pg:gn_pop":31,
    "qs_pg:name":"Brunegg",
    "qs_pg:photos_9r":0,
    "qs_pg:photos_sr":0,
    "qs_pg:pop_sr":1,
    "qs_pg:qs_pg_placetype":"locality",
    "wof:name":"Brunegg",
    "wof:placetype":"neighbourhood",
    "wof:population":31
},
  "geometry": {"coordinates":[8.77171,47.24257],"type":"Point"}
}