{
  "type": "Feature",
  "properties": {
    "gn:gn_country":"CH",
    "gn:gn_fcode":"PPLX",
    "gn:gn_pop":36,
    "gn:population":36,
    "iso:country":"CH",
    "name:eng_x_preferred":[
        "Diebis"
    ],
    "name:eng_x_variant":[
        "Sellenb\u00fcren / Diebis"
    ],
    "name:unk_x_variant":[
        "Diebis"
    ],
    "qs_pg:aaroncc":"CH",
    "qs_pg:gn_country":"CH",
    "qs_pg:gn_fcode":"PPLX",
    "qs_pg:gn_pop":36,
    "qs_pg:name":"Sellenb\u00fcren / Diebis",
    "qs_pg:photos_9r":0,
    "qs_pg:photos_sr":0,
    "qs_pg:pop_sr":1,
    "qs_pg:qs_pg_placetype":"neighbourhood",
    "wof:name":"Diebis",
    "wof:placetype":"neighbourhood",
    "wof:population":36
},
  "geometry": {"coordinates":[8.47604,47.35063],"type":"Point"}
}