{
  "type": "Feature",
  "properties": {
    "gn:admin1_code":"BE",
    "gn:admin2_code":"245.0",
    "gn:admin3_code":"908.0",
    "gn:asciiname":"Haemelbach",
    "gn:country_code":"CH",
    "gn:dem":758,
    "gn:feature_class":"P",
    "gn:feature_code":"PPLL",
    "gn:name":"H\u00e4melbach",
    "gn:population":0,
    "gn:timezone":"Europe/Zurich",
    "iso:country":"CH",
    "name:deu_x_preferred":[
        "H\u00e4melbach"
    ],
    "wof:name":"Haemelbach",
    "wof:placetype":"neighbourhood"
},
  "geometry": {"coordinates":[7.86805,46.91639],"type":"Point"}
}