{
  "type": "Feature",
  "properties": {
    "gn:admin1_code":"VS",
    "gn:admin2_code":"2301.0",
    "gn:admin3_code":"6009.0",
    "gn:asciiname":"Gabi (Simplon)",
    "gn:country_code":"CH",
    "gn:dem":1231,
    "gn:feature_class":"P",
    "gn:feature_code":"PPL",
    "gn:name":"Gabi (Simplon)",
    "gn:population":0,
    "gn:timezone":"Europe/Zurich",
    "iso:country":"CH",
    "wof:name":"Gabi (Simplon)",
    "wof:placetype":"locality"
},
  "geometry": {"coordinates":[8.07306,46.18373],"type":"Point"}
}