{
  "type": "Feature",
  "properties": {
    "gn:gn_country":"CH",
    "gn:gn_fcode":"PPLX",
    "gn:gn_pop":699,
    "gn:population":699,
    "iso:country":"CH",
    "name:eng_x_preferred":[
        "Chropfacher"
    ],
    "name:eng_x_variant":[
        "Schwerzenbach / Chropfacher"
    ],
    "name:unk_x_variant":[
        "Chropfacher"
    ],
    "qs_pg:aaroncc":"CH",
    "qs_pg:gn_country":"CH",
    "qs_pg:gn_fcode":"PPLX",
    "qs_pg:gn_pop":699,
    "qs_pg:name":"Schwerzenbach / Chropfacher",
    "qs_pg:photos_9r":0,
    "qs_pg:photos_sr":0,
    "qs_pg:pop_sr":2,
    "qs_pg:qs_pg_placetype":"neighbourhood",
    "wof:name":"Chropfacher",
    "wof:placetype":"neighbourhood",
    "wof:population":699
},
  "geometry": {"coordinates":[8.65677,47.38387],"type":"Point"}
}