{
  "type": "Feature",
  "properties": {
    "gn:admin1_code":"TG",
    "gn:admin2_code":"2015.0",
    "gn:admin3_code":"4921.0",
    "gn:asciiname":"Stehrenberg",
    "gn:country_code":"CH",
    "gn:dem":571,
    "gn:feature_class":"P",
    "gn:feature_code":"PPL",
    "gn:name":"Stehrenberg",
    "gn:population":0,
    "gn:timezone":"Europe/Zurich",
    "iso:country":"CH",
    "wof:name":"Stehrenberg",
    "wof:placetype":"locality"
},
  "geometry": {"coordinates":[9.08974,47.52335],"type":"Point"}
}