{
  "type": "Feature",
  "properties": {
    "gn:admin1_code":"SG",
    "gn:admin2_code":"1728.0",
    "gn:admin3_code":"3407.0",
    "gn:asciiname":"Riggenschwil",
    "gn:country_code":"CH",
    "gn:dem":639,
    "gn:elevation":"650.0",
    "gn:feature_class":"P",
    "gn:feature_code":"PPL",
    "gn:name":"Riggenschwil",
    "gn:population":0,
    "gn:timezone":"Europe/Zurich",
    "iso:country":"CH",
    "wof:name":"Riggenschwil",
    "wof:placetype":"neighbourhood"
},
  "geometry": {"coordinates":[9.15445,47.41922],"type":"Point"}
}