{
  "type": "Feature",
  "properties": {
    "gn:country":"CH",
    "gn:fcode":"PPLX",
    "gn:population":143,
    "iso:country":"CH",
    "name:eng_x_preferred":[
        "Churfirstenstrasse"
    ],
    "name:eng_x_variant":[
        "D\u00fcbendorf / Churfirstenstrasse"
    ],
    "qs_pg:aaroncc":"CH",
    "qs_pg:gn_country":"CH",
    "qs_pg:gn_fcode":"PPLX",
    "qs_pg:gn_pop":143,
    "qs_pg:name":"D\u00fcbendorf / Churfirstenstrasse",
    "qs_pg:photos_9r":0,
    "qs_pg:photos_sr":0,
    "qs_pg:pop_sr":1,
    "qs_pg:qs_pg_placetype":"neighbourhood",
    "wof:name":"Churfirstenstrasse",
    "wof:placetype":"neighbourhood",
    "wof:population":143
},
  "geometry": {"coordinates":[8.62898,47.39717],"type":"Point"}
}