{
  "type": "Feature",
  "properties": {
    "gn:gn_country":"CH",
    "gn:gn_fcode":"PPL",
    "gn:gn_pop":1094,
    "gn:population":1094,
    "iso:country":"CH",
    "name:ara_x_preferred":[
        "\u0643\u0644\u0627\u064a\u0646\u0623\u0646\u062f\u0644\u0641\u064a\u0646\u063a\u0646"
    ],
    "name:cat_x_preferred":[
        "Kleinandelfingen"
    ],
    "name:chv_x_preferred":[
        "\u041a\u043b\u0430\u0439\u043d\u0430\u043d\u0434\u0435\u043b\u044c\u0444\u0438\u043d\u0433\u0435\u043d"
    ],
    "name:deu_x_preferred":[
        "Kleinandelfingen"
    ],
    "name:eng_x_preferred":[
        "Kleinandelfingen"
    ],
    "name:epo_x_preferred":[
        "Kleinandelfingen"
    ],
    "name:eus_x_preferred":[
        "Kleinandelfingen"
    ],
    "name:fra_x_preferred":[
        "Kleinandelfingen"
    ],
    "name:gsw_x_preferred":[
        "Chliiandelfinge"
    ],
    "name:hun_x_preferred":[
        "Kleinandelfingen"
    ],
    "name:ita_x_preferred":[
        "Kleinandelfingen"
    ],
    "name:kaz_x_preferred":[
        "\u041a\u043b\u0430\u0439\u043d\u0430\u043d\u0434\u0435\u043b\u044c\u0444\u0438\u043d\u0433\u0435\u043d"
    ],
    "name:lmo_x_preferred":[
        "Kleinandelfingen"
    ],
    "name:msa_x_preferred":[
        "Kleinandelfingen"
    ],
    "name:nld_x_preferred":[
        "Kleinandelfingen"
    ],
    "name:nno_x_preferred":[
        "Kleinandelfingen"
    ],
    "name:oci_x_preferred":[
        "Kleinandelfingen"
    ],
    "name:rus_x_preferred":[
        "\u041a\u043b\u0430\u0439\u043d\u0430\u043d\u0434\u0435\u043b\u044c\u0444\u0438\u043d\u0433\u0435\u043d"
    ],
    "name:uzb_x_preferred":[
        "Kleinandelfingen"
    ],
    "name:vec_x_preferred":[
        "Kleinandelfingen"
    ],
    "name:vol_x_preferred":[
        "Kleinandelfingen"
    ],
    "name:war_x_preferred":[
        "Kleinandelfingen"
    ],
    "name:zho_x_preferred":[
        "\u514b\u840a\u5357\u5fb7\u82ac\u6839"
    ],
    "qs_pg:aaroncc":"CH",
    "qs_pg:gn_country":"CH",
    "qs_pg:gn_fcode":"PPL",
    "qs_pg:gn_pop":1094,
    "qs_pg:name":"Kleinandelfingen",
    "qs_pg:name_adm0":"Schweiz",
    "qs_pg:name_adm1":"Kanton Z\u00fcrich",
    "qs_pg:photos":75,
    "qs_pg:photos_1k":15,
    "qs_pg:photos_9k":1,
    "qs_pg:photos_9r":2,
    "qs_pg:photos_all":75,
    "qs_pg:photos_sr":2,
    "qs_pg:pop_sr":3,
    "qs_pg:qs_pg_placetype":"locality",
    "qs_pg:qs_pg_placetype_gp":"Town",
    "qs_pg:woe_adm0":23424957,
    "woe:adm0_id":23424957,
    "woe:name_adm0":"Schweiz",
    "woe:name_adm1":"Kanton Z\u00fcrich",
    "woe:placetype":"Town",
    "wof:name":"Kleinandelfingen",
    "wof:placetype":"locality",
    "wof:population":1094
},
  "geometry": {"coordinates":[8.68362,47.60058],"type":"Point"}
}