{
  "type": "Feature",
  "properties": {
    "gn:gn_country":"CH",
    "gn:gn_fcode":"ADM3",
    "gn:gn_pop":1123,
    "gn:population":1189,
    "iso:country":"CH",
    "name:cat_x_preferred":[
        "Le Gl\u00e8be"
    ],
    "name:deu_x_preferred":[
        "Le Gl\u00e8be"
    ],
    "name:eng_x_preferred":[
        "Le Gl\u00e8be"
    ],
    "name:epo_x_preferred":[
        "Le Gl\u00e8be"
    ],
    "name:fra_x_preferred":[
        "Le Gl\u00e8be"
    ],
    "name:hun_x_preferred":[
        "Le Gl\u00e8be"
    ],
    "name:ita_x_preferred":[
        "Le Gl\u00e8be"
    ],
    "name:lmo_x_preferred":[
        "Le Gl\u00e8be"
    ],
    "name:msa_x_preferred":[
        "Le Gl\u00e8be"
    ],
    "name:nld_x_preferred":[
        "Le Gl\u00e8be"
    ],
    "name:nno_x_preferred":[
        "Le Gl\u00e8be"
    ],
    "name:oci_x_preferred":[
        "Le Gl\u00e8be"
    ],
    "name:pms_x_preferred":[
        "Le Gl\u00e8be"
    ],
    "name:por_x_preferred":[
        "Le Gl\u00e8be"
    ],
    "name:roh_x_preferred":[
        "Le Gl\u00e8be"
    ],
    "name:spa_x_preferred":[
        "Le Gl\u00e8be"
    ],
    "name:sqi_x_preferred":[
        "Le Gl\u00e8be"
    ],
    "name:swe_x_preferred":[
        "Le Gl\u00e8be"
    ],
    "name:vie_x_preferred":[
        "Le Gl\u00e8be"
    ],
    "name:vol_x_preferred":[
        "Le Gl\u00e8be"
    ],
    "name:war_x_preferred":[
        "Le Gl\u00e8be"
    ],
    "name:zho_x_preferred":[
        "\u840a\u683c\u840a\u5e03"
    ],
    "qs_pg:aaroncc":"CH",
    "qs_pg:gn_country":"CH",
    "qs_pg:gn_fcode":"ADM3",
    "qs_pg:gn_pop":1123,
    "qs_pg:name":"Le Gl\u00e8be",
    "qs_pg:name_adm0":"Schweiz",
    "qs_pg:name_adm1":"Canton de Fribourg",
    "qs_pg:photos_9k":1,
    "qs_pg:photos_9r":1,
    "qs_pg:photos_all":1,
    "qs_pg:photos_sr":0,
    "qs_pg:pop_sr":3,
    "qs_pg:qs_pg_placetype":"locality",
    "qs_pg:qs_pg_placetype_gp":"Town",
    "qs_pg:woe_adm0":23424957,
    "woe:adm0_id":23424957,
    "woe:name_adm0":"Schweiz",
    "woe:name_adm1":"Canton de Fribourg",
    "woe:placetype":"Town",
    "wof:name":"Le Gl\u00e8be",
    "wof:placetype":"neighbourhood",
    "wof:population":1189
},
  "geometry": {"coordinates":[7.02824,46.71134],"type":"Point"}
}