{
  "type": "Feature",
  "properties": {
    "gn:admin1_code":"TG",
    "gn:admin2_code":"2014.0",
    "gn:admin3_code":"4726.0",
    "gn:asciiname":"Hinteranderwil",
    "gn:country_code":"CH",
    "gn:dem":749,
    "gn:feature_class":"P",
    "gn:feature_code":"PPLL",
    "gn:name":"Hinteranderwil",
    "gn:population":0,
    "gn:timezone":"Europe/Zurich",
    "iso:country":"CH",
    "name:deu_x_preferred":[
        "Hinteranderwil"
    ],
    "wof:name":"Hinteranderwil",
    "wof:placetype":"locality"
},
  "geometry": {"coordinates":[8.95456,47.39181],"type":"Point"}
}