{
  "type": "Feature",
  "properties": {
    "gn:admin1_code":"FR",
    "gn:admin2_code":"1001.0",
    "gn:admin3_code":"2054.0",
    "gn:asciiname":"Autavaux",
    "gn:country_code":"CH",
    "gn:dem":471,
    "gn:elevation":"475.0",
    "gn:feature_class":"P",
    "gn:feature_code":"PPL",
    "gn:name":"Autavaux",
    "gn:population":0,
    "gn:timezone":"Europe/Zurich",
    "iso:country":"CH",
    "wof:name":"Autavaux",
    "wof:placetype":"locality"
},
  "geometry": {"coordinates":[6.87821,46.86661],"type":"Point"}
}