{
  "type": "Feature",
  "properties": {
    "gn:gn_country":"CH",
    "gn:gn_fcode":"PPLX",
    "gn:gn_pop":1125,
    "gn:population":1125,
    "iso:country":"CH",
    "name:unk_x_variant":[
        "Tal"
    ],
    "qs_pg:aaroncc":"CH",
    "qs_pg:gn_country":"CH",
    "qs_pg:gn_fcode":"PPLX",
    "qs_pg:gn_pop":1125,
    "qs_pg:name":"Adliswil / Tal",
    "qs_pg:photos_9r":0,
    "qs_pg:photos_sr":0,
    "qs_pg:pop_sr":3,
    "qs_pg:qs_pg_placetype":"neighbourhood",
    "wof:name":"Adliswil / Tal",
    "wof:placetype":"neighbourhood",
    "wof:population":1125
},
  "geometry": {"coordinates":[8.53446,47.31142],"type":"Point"}
}