{
  "type": "Feature",
  "properties": {
    "gn:population":3300,
    "iso:country":"CH",
    "name:als_x_preferred":[
        "Dagmersellen"
    ],
    "name:cat_x_preferred":[
        "Dagmersellen"
    ],
    "name:ceb_x_preferred":[
        "Dagmersellen"
    ],
    "name:chv_x_preferred":[
        "\u0414\u0430\u0433\u043c\u0435\u0440\u0437\u0435\u043b\u043b\u0435\u043d"
    ],
    "name:deu_x_preferred":[
        "Dagmersellen"
    ],
    "name:eng_x_preferred":[
        "Dagmersellen"
    ],
    "name:epo_x_preferred":[
        "Dagmersellen"
    ],
    "name:eus_x_preferred":[
        "Dagmersellen"
    ],
    "name:fra_x_preferred":[
        "Dagmersellen"
    ],
    "name:gsw_x_preferred":[
        "Dagmersellen"
    ],
    "name:hun_x_preferred":[
        "Dagmersellen"
    ],
    "name:ita_x_preferred":[
        "Dagmersellen"
    ],
    "name:kaz_x_preferred":[
        "\u0414\u0430\u0433\u043c\u0435\u0440\u0437\u0435\u043b\u043b\u0435\u043d"
    ],
    "name:lmo_x_preferred":[
        "Dagmersellen"
    ],
    "name:msa_x_preferred":[
        "Dagmersellen"
    ],
    "name:nld_x_preferred":[
        "Dagmersellen"
    ],
    "name:nno_x_preferred":[
        "Dagmersellen"
    ],
    "name:oci_x_preferred":[
        "Dagmersellen"
    ],
    "name:pms_x_preferred":[
        "Dagmersellen"
    ],
    "name:por_x_preferred":[
        "Dagmersellen"
    ],
    "name:rus_x_preferred":[
        "\u0414\u0430\u0433\u043c\u0435\u0440\u0437\u0435\u043b\u043b\u0435\u043d"
    ],
    "name:spa_x_preferred":[
        "Dagmersellen"
    ],
    "name:sqi_x_preferred":[
        "Dagmersellen"
    ],
    "name:srp_x_preferred":[
        "\u0414\u0430\u0433\u043c\u0435\u0440\u0437\u0435\u043b\u0435\u043d"
    ],
    "name:uzb_x_preferred":[
        "Dagmersellen"
    ],
    "name:vie_x_preferred":[
        "Dagmersellen"
    ],
    "name:vol_x_preferred":[
        "Dagmersellen"
    ],
    "name:war_x_preferred":[
        "Dagmersellen"
    ],
    "name:zho_x_preferred":[
        "\u9054\u683c\u9ed8\u585e\u502b"
    ],
    "qs:a0":"Schweiz#Suisse#Svizzera#Svizra",
    "qs:a1":"*Luzern",
    "qs:a1r":"0",
    "qs:adm0":"Schweiz#Suisse#Svizzera#Svizra",
    "qs:la_lc":"*",
    "qs:level":"locality",
    "qs:loc":"Dagmersellen",
    "qs:loc_alt":"Dagmersellen",
    "qs:pop":0,
    "qs:type":"buffered point",
    "wd:wordcount":858,
    "wof:lang":[
        "ger"
    ],
    "wof:name":"Dagmersellen",
    "wof:placetype":"locality",
    "wof:population":3300
},
  "geometry": {"coordinates":[7.988863,47.213142],"type":"Point"}
}