{
  "type": "Feature",
  "properties": {
    "gn:gn_country":"CH",
    "gn:gn_fcode":"PPL",
    "gn:gn_pop":639,
    "gn:population":639,
    "iso:country":"CH",
    "name:als_x_preferred":[
        "Walterswil BE"
    ],
    "name:deu_x_preferred":[
        "Walterswil BE"
    ],
    "name:epo_x_preferred":[
        "Walterswil BE"
    ],
    "name:kaz_x_preferred":[
        "\u0412\u0430\u043b\u044c\u0442\u0435\u0440\u0441\u0432\u0438\u043b\u044c"
    ],
    "name:nno_x_preferred":[
        "Walterswil i Bern"
    ],
    "name:rus_x_preferred":[
        "\u0412\u0430\u043b\u044c\u0442\u0435\u0440\u0441\u0432\u0438\u043b\u044c"
    ],
    "name:war_x_preferred":[
        "Walterswil BE"
    ],
    "name:zho_x_preferred":[
        "\u74e6\u723e\u7279\u65af\u7dad\u723e"
    ],
    "qs_pg:aaroncc":"CH",
    "qs_pg:gn_country":"CH",
    "qs_pg:gn_fcode":"PPL",
    "qs_pg:gn_pop":639,
    "qs_pg:name":"Walterswil",
    "qs_pg:name_adm0":"Schweiz",
    "qs_pg:name_adm1":"Kanton Solothurn",
    "qs_pg:photos":4,
    "qs_pg:photos_1k":1,
    "qs_pg:photos_9k":1,
    "qs_pg:photos_9r":1,
    "qs_pg:photos_all":4,
    "qs_pg:photos_sr":1,
    "qs_pg:pop_sr":2,
    "qs_pg:qs_pg_placetype":"locality",
    "qs_pg:qs_pg_placetype_gp":"Town",
    "qs_pg:woe_adm0":23424957,
    "woe:adm0_id":23424957,
    "woe:name_adm0":"Schweiz",
    "woe:name_adm1":"Kanton Solothurn",
    "woe:placetype":"Town",
    "wof:name":"Walterswil",
    "wof:placetype":"locality",
    "wof:population":639
},
  "geometry": {"coordinates":[7.77798,47.1122],"type":"Point"}
}