{
  "type": "Feature",
  "properties": {
    "gn:gn_country":"CH",
    "gn:gn_fcode":"ADM3",
    "gn:gn_pop":1667,
    "gn:population":1820,
    "iso:country":"CH",
    "name:cat_x_preferred":[
        "Winznau"
    ],
    "name:chv_x_preferred":[
        "\u0412\u0438\u043d\u0446\u043d\u0430\u0443"
    ],
    "name:deu_x_preferred":[
        "Winznau"
    ],
    "name:eng_x_preferred":[
        "Winznau"
    ],
    "name:epo_x_preferred":[
        "Winznau"
    ],
    "name:eus_x_preferred":[
        "Winznau"
    ],
    "name:fra_x_preferred":[
        "Winznau"
    ],
    "name:gsw_x_preferred":[
        "Winznau"
    ],
    "name:hun_x_preferred":[
        "Winznau"
    ],
    "name:ita_x_preferred":[
        "Winznau"
    ],
    "name:kaz_x_preferred":[
        "\u0412\u0438\u043d\u0446\u043d\u0430\u0443"
    ],
    "name:lmo_x_preferred":[
        "Winznau"
    ],
    "name:msa_x_preferred":[
        "Winznau"
    ],
    "name:nld_x_preferred":[
        "Winznau"
    ],
    "name:nno_x_preferred":[
        "Winznau"
    ],
    "name:oci_x_preferred":[
        "Winznau"
    ],
    "name:pms_x_preferred":[
        "Winznau"
    ],
    "name:por_x_preferred":[
        "Winznau"
    ],
    "name:rus_x_preferred":[
        "\u0412\u0438\u043d\u0446\u043d\u0430\u0443"
    ],
    "name:spa_x_preferred":[
        "Winznau"
    ],
    "name:sqi_x_preferred":[
        "Winznau"
    ],
    "name:swe_x_preferred":[
        "Winznau"
    ],
    "name:uzb_x_preferred":[
        "Winznau"
    ],
    "name:vol_x_preferred":[
        "Winznau"
    ],
    "name:war_x_preferred":[
        "Winznau"
    ],
    "name:zho_x_preferred":[
        "\u6eab\u8328\u7459"
    ],
    "qs_pg:aaroncc":"CH",
    "qs_pg:gn_country":"CH",
    "qs_pg:gn_fcode":"ADM3",
    "qs_pg:gn_pop":1667,
    "qs_pg:name":"Winznau",
    "qs_pg:name_adm0":"Schweiz",
    "qs_pg:name_adm1":"Kanton Solothurn",
    "qs_pg:photos":42,
    "qs_pg:photos_1k":9,
    "qs_pg:photos_9k":1,
    "qs_pg:photos_9r":2,
    "qs_pg:photos_all":42,
    "qs_pg:photos_sr":2,
    "qs_pg:pop_sr":3,
    "qs_pg:qs_pg_placetype":"locality",
    "qs_pg:qs_pg_placetype_gp":"Town",
    "qs_pg:woe_adm0":23424957,
    "woe:adm0_id":23424957,
    "woe:name_adm0":"Schweiz",
    "woe:name_adm1":"Kanton Solothurn",
    "woe:placetype":"Town",
    "wof:name":"Winznau",
    "wof:placetype":"locality",
    "wof:population":1820
},
  "geometry": {"coordinates":[7.92471,47.36982],"type":"Point"}
}