{
  "type": "Feature",
  "properties": {
    "gn:admin1_code":"GL",
    "gn:admin2_code":"800.0",
    "gn:admin3_code":"1632.0",
    "gn:asciiname":"Ennetbuehls",
    "gn:country_code":"CH",
    "gn:dem":551,
    "gn:elevation":"472.0",
    "gn:feature_class":"P",
    "gn:feature_code":"PPL",
    "gn:name":"Ennetb\u00fchls",
    "gn:population":0,
    "gn:timezone":"Europe/Zurich",
    "iso:country":"CH",
    "wof:name":"Ennetbuehls",
    "wof:placetype":"neighbourhood"
},
  "geometry": {"coordinates":[9.07494,47.04424],"type":"Point"}
}