{
  "type": "Feature",
  "properties": {
    "gn:admin1_code":"AR",
    "gn:admin2_code":"1502.0",
    "gn:admin3_code":"3024.0",
    "gn:asciiname":"Schloessli",
    "gn:country_code":"CH",
    "gn:dem":990,
    "gn:feature_class":"P",
    "gn:feature_code":"PPLL",
    "gn:name":"Schl\u00f6ssli",
    "gn:population":0,
    "gn:timezone":"Europe/Zurich",
    "iso:country":"CH",
    "name:deu_x_preferred":[
        "Schl\u00f6ssli"
    ],
    "wof:name":"Schloessli",
    "wof:placetype":"neighbourhood"
},
  "geometry": {"coordinates":[9.42766,47.39031],"type":"Point"}
}