{
  "type": "Feature",
  "properties": {
    "gn:gn_country":"CH",
    "gn:gn_fcode":"PPL",
    "gn:gn_pop":428,
    "gn:population":428,
    "iso:country":"CH",
    "name:alb_x_preferred":[
        "Lumbrein"
    ],
    "name:bul_x_preferred":[
        "\u041b\u0443\u043c\u0431\u0440\u0435\u0438\u043d"
    ],
    "name:cat_x_preferred":[
        "Lumbrein"
    ],
    "name:chi_x_preferred":[
        "\u502b\u5e03\u8cf4\u6069"
    ],
    "name:dut_x_preferred":[
        "Lumbrein"
    ],
    "name:eng_x_preferred":[
        "Lumbrein"
    ],
    "name:epo_x_preferred":[
        "Lumbrein"
    ],
    "name:fre_x_preferred":[
        "Lumbrein"
    ],
    "name:ger_x_preferred":[
        "Lumbrein"
    ],
    "name:hun_x_preferred":[
        "Lumbrein"
    ],
    "name:ind_x_preferred":[
        "Lumbrein"
    ],
    "name:ita_x_preferred":[
        "Lumbrein"
    ],
    "name:kaz_x_preferred":[
        "\u041b\u0443\u043c\u0431\u0440\u0430\u0439\u043d"
    ],
    "name:lmo_x_preferred":[
        "Lumbrein"
    ],
    "name:may_x_preferred":[
        "Lumbrein"
    ],
    "name:nno_x_preferred":[
        "Lumbrein"
    ],
    "name:oci_x_preferred":[
        "Lumbrein"
    ],
    "name:pms_x_preferred":[
        "Lumbrein"
    ],
    "name:por_x_preferred":[
        "Lumbrein"
    ],
    "name:roh_x_preferred":[
        "Lumbrein"
    ],
    "name:rus_x_preferred":[
        "\u041b\u0443\u043c\u0431\u0440\u0430\u0439\u043d"
    ],
    "name:spa_x_preferred":[
        "Lumbrein"
    ],
    "name:swe_x_preferred":[
        "Lumbrein"
    ],
    "name:uzb_x_preferred":[
        "Lumbrein"
    ],
    "name:vol_x_preferred":[
        "Lumbrein"
    ],
    "name:war_x_preferred":[
        "Lumbrein"
    ],
    "name:zho_x_preferred":[
        "\u502b\u5e03\u8cf4\u6069"
    ],
    "qs_pg:aaroncc":"CH",
    "qs_pg:gn_country":"CH",
    "qs_pg:gn_fcode":"PPL",
    "qs_pg:gn_pop":428,
    "qs_pg:name":"Lumbrein",
    "qs_pg:name_adm0":"Schweiz",
    "qs_pg:name_adm1":"Kanton Graub\u00fcnden",
    "qs_pg:photos":24,
    "qs_pg:photos_1k":5,
    "qs_pg:photos_9k":1,
    "qs_pg:photos_9r":1,
    "qs_pg:photos_all":24,
    "qs_pg:photos_sr":1,
    "qs_pg:pop_sr":2,
    "qs_pg:qs_pg_placetype":"locality",
    "qs_pg:qs_pg_placetype_gp":"Town",
    "qs_pg:woe_adm0":23424957,
    "woe:adm0_id":23424957,
    "woe:name_adm0":"Schweiz",
    "woe:name_adm1":"Kanton Graub\u00fcnden",
    "woe:placetype":"Town",
    "wof:name":"Lumbrein",
    "wof:placetype":"locality",
    "wof:population":428
},
  "geometry": {"coordinates":[9.13618,46.68343],"type":"Point"}
}