{
  "type": "Feature",
  "properties": {
    "gn:admin1_code":"VS",
    "gn:admin2_code":"2305.0",
    "gn:admin3_code":"6083.0",
    "gn:asciiname":"Vernec",
    "gn:country_code":"CH",
    "gn:dem":1864,
    "gn:feature_class":"P",
    "gn:feature_code":"PPL",
    "gn:name":"Vernec",
    "gn:population":0,
    "gn:timezone":"Europe/Zurich",
    "iso:country":"CH",
    "wof:name":"Vernec",
    "wof:placetype":"neighbourhood"
},
  "geometry": {"coordinates":[7.46166,46.11515],"type":"Point"}
}