{
  "type": "Feature",
  "properties": {
    "gn:admin1_code":"TG",
    "gn:admin2_code":"2012.0",
    "gn:admin3_code":"4821.0",
    "gn:asciiname":"Neumuehle",
    "gn:country_code":"CH",
    "gn:dem":430,
    "gn:feature_class":"P",
    "gn:feature_code":"PPLL",
    "gn:name":"Neum\u00fchle",
    "gn:population":0,
    "gn:timezone":"Europe/Zurich",
    "iso:country":"CH",
    "name:deu_x_preferred":[
        "Neum\u00fchle"
    ],
    "wof:name":"Neumuehle",
    "wof:placetype":"neighbourhood"
},
  "geometry": {"coordinates":[8.88274,47.60023],"type":"Point"}
}