{
  "type": "Feature",
  "properties": {
    "gn:gn_country":"CH",
    "gn:gn_fcode":"PPLL",
    "gn:gn_pop":14,
    "gn:population":14,
    "iso:country":"CH",
    "name:alb_x_preferred":[
        "Rain"
    ],
    "name:baq_x_preferred":[
        "Rain"
    ],
    "name:cat_x_preferred":[
        "Rain"
    ],
    "name:chi_x_preferred":[
        "Rain"
    ],
    "name:dut_x_preferred":[
        "Rain"
    ],
    "name:eng_x_preferred":[
        "Rain"
    ],
    "name:epo_x_preferred":[
        "Rain"
    ],
    "name:fre_x_preferred":[
        "Rain"
    ],
    "name:ger_x_preferred":[
        "Rain"
    ],
    "name:gsw_x_preferred":[
        "Rain LU"
    ],
    "name:hun_x_preferred":[
        "Rain"
    ],
    "name:ita_x_preferred":[
        "Rain"
    ],
    "name:kaz_x_preferred":[
        "\u0420\u0430\u0439\u043d"
    ],
    "name:lmo_x_preferred":[
        "Rain"
    ],
    "name:may_x_preferred":[
        "Rain"
    ],
    "name:nno_x_preferred":[
        "Rain"
    ],
    "name:oci_x_preferred":[
        "Rain"
    ],
    "name:roh_x_preferred":[
        "Rain"
    ],
    "name:rum_x_preferred":[
        "Rain"
    ],
    "name:rus_x_preferred":[
        "\u0420\u0430\u0439\u043d"
    ],
    "name:spa_x_preferred":[
        "Rain"
    ],
    "name:swe_x_preferred":[
        "Rain"
    ],
    "name:uzb_x_preferred":[
        "Rain"
    ],
    "name:vol_x_preferred":[
        "Rain"
    ],
    "name:war_x_preferred":[
        "Rain"
    ],
    "qs_pg:aaroncc":"CH",
    "qs_pg:gn_country":"CH",
    "qs_pg:gn_fcode":"PPLL",
    "qs_pg:gn_pop":14,
    "qs_pg:name":"Rain",
    "qs_pg:photos_9r":0,
    "qs_pg:photos_sr":0,
    "qs_pg:pop_sr":1,
    "qs_pg:qs_pg_placetype":"locality",
    "wof:name":"Rain",
    "wof:placetype":"locality",
    "wof:population":14
},
  "geometry": {"coordinates":[8.63196,47.1871],"type":"Point"}
}