{
  "type": "Feature",
  "properties": {
    "gn:admin1_code":"TG",
    "gn:admin2_code":"2013.0",
    "gn:admin3_code":"4666.0",
    "gn:asciiname":"Breitewiese",
    "gn:country_code":"CH",
    "gn:dem":520,
    "gn:feature_class":"P",
    "gn:feature_code":"PPLL",
    "gn:name":"Breitewiese",
    "gn:population":0,
    "gn:timezone":"Europe/Zurich",
    "iso:country":"CH",
    "name:deu_x_preferred":[
        "Breitewiese"
    ],
    "wof:name":"Breitewiese",
    "wof:placetype":"neighbourhood"
},
  "geometry": {"coordinates":[9.12684,47.59852],"type":"Point"}
}