{
  "type": "Feature",
  "properties": {
    "iso:country":"CH",
    "name:fra_x_preferred":[
        "Les Pierrettes"
    ],
    "qs:gn_adm0_cc":"CH",
    "qs:gn_local":2658860,
    "qs:gn_nam_loc":"auxon-dessous",
    "qs:gn_namadm1":"VD",
    "qs:local_max":2987,
    "qs:local_sum":2987,
    "qs:localhoods":1,
    "qs:name":"Les Pierrettes",
    "qs:name_adm0":"Schweiz",
    "qs:name_adm1":"Canton de Vaud",
    "qs:name_adm2":"Morges",
    "qs:name_lau":"St.-Sulpice",
    "qs:name_local":"St.-Sulpice",
    "qs:photo_max":571,
    "qs:photo_sum":2987,
    "qs:placetype":"Suburb",
    "qs:quad_count":81,
    "qs:woe_adm0":23424957,
    "qs:woe_adm1":2347105,
    "qs:woe_adm2":12593230,
    "qs:woe_lau":12683410,
    "qs:woe_local":784275,
    "qs:woe_ver":"7.10.0",
    "wof:name":"Les Pierrettes",
    "wof:placetype":"neighbourhood"
},
  "geometry": {"coordinates":[6.566888,46.517884],"type":"Point"}
}