{
  "type": "Feature",
  "properties": {
    "gn:admin1_code":"LU",
    "gn:admin2_code":"315.0",
    "gn:admin3_code":"1132.0",
    "gn:asciiname":"Krieshuetten",
    "gn:country_code":"CH",
    "gn:dem":949,
    "gn:feature_class":"P",
    "gn:feature_code":"PPLL",
    "gn:name":"Kriesh\u00fctten",
    "gn:population":0,
    "gn:timezone":"Europe/Zurich",
    "iso:country":"CH",
    "name:deu_x_preferred":[
        "Kriesh\u00fctten"
    ],
    "wof:name":"Krieshuetten",
    "wof:placetype":"neighbourhood"
},
  "geometry": {"coordinates":[7.94044,47.03556],"type":"Point"}
}