{
  "type": "Feature",
  "properties": {
    "gn:admin1_code":"BE",
    "gn:admin2_code":"245.0",
    "gn:admin3_code":"902.0",
    "gn:asciiname":"Bueelti",
    "gn:country_code":"CH",
    "gn:dem":1030,
    "gn:feature_class":"P",
    "gn:feature_code":"PPLL",
    "gn:name":"B\u00fcelti",
    "gn:population":0,
    "gn:timezone":"Europe/Zurich",
    "iso:country":"CH",
    "name:deu_x_preferred":[
        "B\u00fcelti"
    ],
    "wof:name":"Bueelti",
    "wof:placetype":"neighbourhood"
},
  "geometry": {"coordinates":[7.79558,46.91451],"type":"Point"}
}