{
  "type": "Feature",
  "properties": {
    "gn:gn_country":"CH",
    "gn:gn_fcode":"PPL",
    "gn:gn_pop":1145,
    "gn:population":1145,
    "iso:country":"CH",
    "name:cat_x_preferred":[
        "Ganterschwil"
    ],
    "name:deu_x_preferred":[
        "Ganterschwil"
    ],
    "name:eng_x_preferred":[
        "Ganterschwil"
    ],
    "name:epo_x_preferred":[
        "Ganterschwil"
    ],
    "name:fra_x_preferred":[
        "Ganterschwil"
    ],
    "name:gsw_x_preferred":[
        "Ganterschwil"
    ],
    "name:hun_x_preferred":[
        "Ganterschwil"
    ],
    "name:ita_x_preferred":[
        "Ganterschwil"
    ],
    "name:kaz_x_preferred":[
        "\u0413\u0430\u043d\u0442\u0435\u0440\u0448\u0432\u0438\u043b\u044c"
    ],
    "name:lmo_x_preferred":[
        "Ganterschwil"
    ],
    "name:msa_x_preferred":[
        "Ganterschwil"
    ],
    "name:nld_x_preferred":[
        "Ganterschwil"
    ],
    "name:nno_x_preferred":[
        "Ganterschwil"
    ],
    "name:oci_x_preferred":[
        "Ganterschwil"
    ],
    "name:pms_x_preferred":[
        "Ganterschwil"
    ],
    "name:por_x_preferred":[
        "Ganterschwil"
    ],
    "name:rus_x_preferred":[
        "\u0413\u0430\u043d\u0442\u0435\u0440\u0448\u0432\u0438\u043b\u044c"
    ],
    "name:spa_x_preferred":[
        "Ganterschwil"
    ],
    "name:swe_x_preferred":[
        "Ganterschwil"
    ],
    "name:unk_x_variant":[
        "Ganterschwil"
    ],
    "name:uzb_x_preferred":[
        "Ganterschwil"
    ],
    "name:vol_x_preferred":[
        "Ganterschwil"
    ],
    "name:war_x_preferred":[
        "Ganterschwil"
    ],
    "name:zho_x_preferred":[
        "\u7518\u7279\u65bd\u7dad\u723e"
    ],
    "qs_pg:aaroncc":"CH",
    "qs_pg:gn_country":"CH",
    "qs_pg:gn_fcode":"PPL",
    "qs_pg:gn_pop":1145,
    "qs_pg:name":"Winterschwil",
    "qs_pg:name_adm0":"Schweiz",
    "qs_pg:name_adm1":"Kanton Aargau",
    "qs_pg:photos_9k":1,
    "qs_pg:photos_9r":1,
    "qs_pg:photos_all":6,
    "qs_pg:photos_sr":0,
    "qs_pg:pop_sr":3,
    "qs_pg:qs_pg_placetype":"locality",
    "qs_pg:qs_pg_placetype_gp":"Town",
    "qs_pg:woe_adm0":23424957,
    "woe:adm0_id":23424957,
    "woe:name_adm0":"Schweiz",
    "woe:name_adm1":"Kanton Aargau",
    "woe:placetype":"Town",
    "wof:name":"Winterschwil",
    "wof:placetype":"neighbourhood",
    "wof:population":1145
},
  "geometry": {"coordinates":[9.09239,47.38103],"type":"Point"}
}