{
  "type": "Feature",
  "properties": {
    "gn:admin1_code":"ZH",
    "gn:admin2_code":"102.0",
    "gn:admin3_code":"22.0",
    "gn:asciiname":"Guggeeren",
    "gn:country_code":"CH",
    "gn:dem":500,
    "gn:feature_class":"P",
    "gn:feature_code":"PPLL",
    "gn:name":"Guggeeren",
    "gn:population":0,
    "gn:timezone":"Europe/Zurich",
    "iso:country":"CH",
    "name:deu_x_preferred":[
        "Guggeeren"
    ],
    "wof:name":"Guggeeren",
    "wof:placetype":"locality"
},
  "geometry": {"coordinates":[8.65479,47.65822],"type":"Point"}
}