{
  "type": "Feature",
  "properties": {
    "gn:admin1_code":"GR",
    "gn:admin2_code":"1850.0",
    "gn:admin3_code":"3603.0",
    "gn:asciiname":"Leis",
    "gn:country_code":"CH",
    "gn:dem":1527,
    "gn:feature_class":"P",
    "gn:feature_code":"PPL",
    "gn:name":"Leis",
    "gn:population":0,
    "gn:timezone":"Europe/Zurich",
    "iso:country":"CH",
    "name:deu_x_preferred":[
        "Leis"
    ],
    "wof:name":"Leis",
    "wof:placetype":"locality"
},
  "geometry": {"coordinates":[9.16494,46.60914],"type":"Point"}
}