{
  "type": "Feature",
  "properties": {
    "gn:admin1_code":"BL",
    "gn:admin2_code":"1305.0",
    "gn:admin3_code":"2889.0",
    "gn:asciiname":"Langacker",
    "gn:country_code":"CH",
    "gn:dem":680,
    "gn:feature_class":"P",
    "gn:feature_code":"PPLL",
    "gn:name":"Langacker",
    "gn:population":0,
    "gn:timezone":"Europe/Zurich",
    "iso:country":"CH",
    "name:deu_x_preferred":[
        "Langacker"
    ],
    "wof:name":"Langacker",
    "wof:placetype":"neighbourhood"
},
  "geometry": {"coordinates":[7.67014,47.38939],"type":"Point"}
}