{
  "type": "Feature",
  "properties": {
    "gn:admin1_code":"TG",
    "gn:admin2_code":"2013.0",
    "gn:admin3_code":"4666.0",
    "gn:asciiname":"Mannenmuehle",
    "gn:country_code":"CH",
    "gn:dem":470,
    "gn:feature_class":"P",
    "gn:feature_code":"PPLL",
    "gn:name":"Mannenm\u00fchle",
    "gn:population":0,
    "gn:timezone":"Europe/Zurich",
    "iso:country":"CH",
    "name:deu_x_preferred":[
        "Mannenm\u00fchle"
    ],
    "wof:name":"Mannenmuehle",
    "wof:placetype":"neighbourhood"
},
  "geometry": {"coordinates":[9.11495,47.60598],"type":"Point"}
}