{
  "type": "Feature",
  "properties": {
    "gn:gn_country":"CH",
    "gn:gn_fcode":"PPL",
    "gn:gn_pop":775,
    "gn:population":775,
    "iso:country":"CH",
    "name:als_x_preferred":[
        "Cartigny GE"
    ],
    "name:cat_x_preferred":[
        "Cartigny"
    ],
    "name:cym_x_preferred":[
        "Cartigny"
    ],
    "name:deu_x_preferred":[
        "Cartigny GE"
    ],
    "name:eng_x_preferred":[
        "Cartigny"
    ],
    "name:epo_x_preferred":[
        "Cartigny"
    ],
    "name:eus_x_preferred":[
        "Cartigny"
    ],
    "name:fra_x_preferred":[
        "Cartigny"
    ],
    "name:gsw_x_preferred":[
        "Cartigny GE"
    ],
    "name:hun_x_preferred":[
        "Cartigny"
    ],
    "name:ita_x_preferred":[
        "Cartigny"
    ],
    "name:jpn_x_preferred":[
        "\u30ab\u30eb\u30c6\u30a3\u30cb\u30fc"
    ],
    "name:lat_x_preferred":[
        "Cartiniacum"
    ],
    "name:lmo_x_preferred":[
        "Cartigny"
    ],
    "name:msa_x_preferred":[
        "Cartigny"
    ],
    "name:nld_x_preferred":[
        "Cartigny"
    ],
    "name:nno_x_preferred":[
        "Cartigny i Sveits"
    ],
    "name:oci_x_preferred":[
        "Cartigny"
    ],
    "name:por_x_preferred":[
        "Cartigny"
    ],
    "name:roh_x_preferred":[
        "Cartigny"
    ],
    "name:rus_x_preferred":[
        "\u041a\u0430\u0440\u0442\u0438\u043d\u0438"
    ],
    "name:spa_x_preferred":[
        "Cartigny"
    ],
    "name:swe_x_preferred":[
        "Cartigny"
    ],
    "name:unk_x_variant":[
        "Cartygny"
    ],
    "name:vie_x_preferred":[
        "Cartigny"
    ],
    "name:vol_x_preferred":[
        "Cartigny"
    ],
    "name:war_x_preferred":[
        "Cartigny"
    ],
    "name:zho_x_preferred":[
        "\u5361\u5c14\u8482\u5c3c"
    ],
    "qs_pg:aaroncc":"CH",
    "qs_pg:gn_country":"CH",
    "qs_pg:gn_fcode":"PPL",
    "qs_pg:gn_pop":775,
    "qs_pg:name":"Cartigny",
    "qs_pg:name_adm0":"Schweiz",
    "qs_pg:name_adm1":"Canton de Gen\u00e8ve",
    "qs_pg:photos":503,
    "qs_pg:photos_1k":102,
    "qs_pg:photos_9k":2,
    "qs_pg:photos_9r":5,
    "qs_pg:photos_all":503,
    "qs_pg:photos_sr":7,
    "qs_pg:pop_sr":2,
    "qs_pg:qs_pg_placetype":"locality",
    "qs_pg:qs_pg_placetype_gp":"Town",
    "qs_pg:woe_adm0":23424957,
    "woe:adm0_id":23424957,
    "woe:name_adm0":"Schweiz",
    "woe:name_adm1":"Canton de Gen\u00e8ve",
    "woe:placetype":"Town",
    "wof:name":"Cartigny",
    "wof:placetype":"locality",
    "wof:population":775
},
  "geometry": {"coordinates":[6.01982,46.17412],"type":"Point"}
}