{
  "type": "Feature",
  "properties": {
    "gn:admin1_code":"SG",
    "gn:admin2_code":"1727.0",
    "gn:admin3_code":"3393.0",
    "gn:asciiname":"Unterrindal",
    "gn:country_code":"CH",
    "gn:dem":645,
    "gn:elevation":"585.0",
    "gn:feature_class":"P",
    "gn:feature_code":"PPL",
    "gn:name":"Unterrindal",
    "gn:population":0,
    "gn:timezone":"Europe/Zurich",
    "iso:country":"CH",
    "wof:name":"Unterrindal",
    "wof:placetype":"locality"
},
  "geometry": {"coordinates":[9.09109,47.41061],"type":"Point"}
}