{
  "type": "Feature",
  "properties": {
    "gn:admin1_code":"BL",
    "gn:admin2_code":"1304.0",
    "gn:admin3_code":"2846.0",
    "gn:asciiname":"AErntholden",
    "gn:country_code":"CH",
    "gn:dem":528,
    "gn:feature_class":"P",
    "gn:feature_code":"PPLL",
    "gn:name":"\u00c4rntholden",
    "gn:population":0,
    "gn:timezone":"Europe/Zurich",
    "iso:country":"CH",
    "name:deu_x_preferred":[
        "\u00c4rntholden"
    ],
    "wof:name":"AErntholden",
    "wof:placetype":"neighbourhood"
},
  "geometry": {"coordinates":[7.8794,47.46104],"type":"Point"}
}