{
  "type": "Feature",
  "properties": {
    "gn:admin1_code":"BE",
    "gn:admin2_code":"249.0",
    "gn:admin3_code":"762.0",
    "gn:asciiname":"Schwenden im Diemtigtal",
    "gn:country_code":"CH",
    "gn:dem":1164,
    "gn:feature_class":"P",
    "gn:feature_code":"PPL",
    "gn:name":"Schwenden im Diemtigtal",
    "gn:population":0,
    "gn:timezone":"Europe/Zurich",
    "iso:country":"CH",
    "wof:name":"Schwenden im Diemtigtal",
    "wof:placetype":"locality"
},
  "geometry": {"coordinates":[7.49062,46.58007],"type":"Point"}
}