{
  "type": "Feature",
  "properties": {
    "gn:admin1_code":"AR",
    "gn:admin2_code":"1503.0",
    "gn:admin3_code":"3038.0",
    "gn:asciiname":"Vorderhasli",
    "gn:country_code":"CH",
    "gn:dem":528,
    "gn:feature_class":"P",
    "gn:feature_code":"PPLL",
    "gn:name":"Vorderhasli",
    "gn:population":0,
    "gn:timezone":"Europe/Zurich",
    "iso:country":"CH",
    "name:deu_x_preferred":[
        "Vorderhasli"
    ],
    "wof:lang_x_official":[
        "deu",
        "fra",
        "gsw",
        "ita"
    ],
    "wof:lang_x_spoken":[
        "deu",
        "fra",
        "gsw",
        "ita",
        "roh"
    ],
    "wof:name":"Vorderhasli",
    "wof:placetype":"neighbourhood"
},
  "geometry": {"coordinates":[9.55737,47.46119],"type":"Point"}
}