{
  "type": "Feature",
  "properties": {
    "gn:gn_country":"CH",
    "gn:gn_fcode":"PPLA3",
    "gn:gn_pop":2616,
    "gn:population":2616,
    "iso:country":"CH",
    "name:cat_x_preferred":[
        "Schenkon"
    ],
    "name:chv_x_preferred":[
        "\u0428\u0435\u043d\u043a\u043e\u043d"
    ],
    "name:deu_x_preferred":[
        "Schenkon"
    ],
    "name:eng_x_preferred":[
        "Schenkon"
    ],
    "name:epo_x_preferred":[
        "Schenkon"
    ],
    "name:eus_x_preferred":[
        "Schenkon"
    ],
    "name:fra_x_preferred":[
        "Schenkon"
    ],
    "name:gsw_x_preferred":[
        "Sch\u00e4nke"
    ],
    "name:hun_x_preferred":[
        "Schenkon"
    ],
    "name:ita_x_preferred":[
        "Schenkon"
    ],
    "name:kaz_x_preferred":[
        "\u0428\u0435\u043d\u043a\u043e\u043d"
    ],
    "name:lmo_x_preferred":[
        "Schenkon"
    ],
    "name:msa_x_preferred":[
        "Schenkon"
    ],
    "name:nld_x_preferred":[
        "Schenkon"
    ],
    "name:nno_x_preferred":[
        "Schenkon"
    ],
    "name:oci_x_preferred":[
        "Schenkon"
    ],
    "name:pms_x_preferred":[
        "Schenkon"
    ],
    "name:por_x_preferred":[
        "Schenkon"
    ],
    "name:roh_x_preferred":[
        "Schenkon"
    ],
    "name:rus_x_preferred":[
        "\u0428\u0435\u043d\u043a\u043e\u043d"
    ],
    "name:spa_x_preferred":[
        "Schenkon"
    ],
    "name:sqi_x_preferred":[
        "Schenkon"
    ],
    "name:uzb_x_preferred":[
        "Schenkon"
    ],
    "name:vol_x_preferred":[
        "Schenkon"
    ],
    "name:war_x_preferred":[
        "Schenkon"
    ],
    "name:zho_x_preferred":[
        "\u7533\u5b54"
    ],
    "qs_pg:aaroncc":"CH",
    "qs_pg:gn_country":"CH",
    "qs_pg:gn_fcode":"PPLA3",
    "qs_pg:gn_pop":2616,
    "qs_pg:name":"Schenkon",
    "qs_pg:name_adm0":"Schweiz",
    "qs_pg:name_adm1":"Kanton Luzern",
    "qs_pg:photos":48,
    "qs_pg:photos_1k":10,
    "qs_pg:photos_9k":1,
    "qs_pg:photos_9r":2,
    "qs_pg:photos_all":48,
    "qs_pg:photos_sr":2,
    "qs_pg:pop_sr":4,
    "qs_pg:qs_pg_placetype":"locality",
    "qs_pg:qs_pg_placetype_gp":"Town",
    "qs_pg:woe_adm0":23424957,
    "woe:adm0_id":23424957,
    "woe:name_adm0":"Schweiz",
    "woe:name_adm1":"Kanton Luzern",
    "woe:placetype":"Town",
    "wof:name":"Schenkon",
    "wof:placetype":"locality",
    "wof:population":2616
},
  "geometry": {"coordinates":[8.14384,47.1683],"type":"Point"}
}