{
  "type": "Feature",
  "properties": {
    "gn:admin1_code":"BE",
    "gn:admin2_code":"249.0",
    "gn:admin3_code":"761.0",
    "gn:asciiname":"Ramsli",
    "gn:country_code":"CH",
    "gn:dem":1751,
    "gn:feature_class":"P",
    "gn:feature_code":"PPL",
    "gn:name":"Ramsli",
    "gn:population":0,
    "gn:timezone":"Europe/Zurich",
    "iso:country":"CH",
    "name:deu_x_preferred":[
        "Ramsli"
    ],
    "wof:lang_x_official":[
        "deu",
        "fra",
        "gsw",
        "ita"
    ],
    "wof:lang_x_spoken":[
        "deu",
        "fra",
        "gsw",
        "ita",
        "roh"
    ],
    "wof:name":"Ramsli",
    "wof:placetype":"neighbourhood"
},
  "geometry": {"coordinates":[7.46774,46.62099],"type":"Point"}
}