{
  "type": "Feature",
  "properties": {
    "gn:admin1_code":"BE",
    "gn:admin2_code":"245.0",
    "gn:admin3_code":"956.0",
    "gn:asciiname":"Rueegsbach",
    "gn:country_code":"CH",
    "gn:dem":620,
    "gn:elevation":"617.0",
    "gn:feature_class":"P",
    "gn:feature_code":"PPL",
    "gn:name":"R\u00fcegsbach",
    "gn:population":0,
    "gn:timezone":"Europe/Zurich",
    "iso:country":"CH",
    "wof:name":"Rueegsbach",
    "wof:placetype":"locality"
},
  "geometry": {"coordinates":[7.69029,47.03541],"type":"Point"}
}