{
  "type": "Feature",
  "properties": {
    "gn:gn_country":"CH",
    "gn:gn_fcode":"PPL",
    "gn:gn_pop":1252,
    "gn:population":1252,
    "iso:country":"CH",
    "name:cat_x_preferred":[
        "Laax"
    ],
    "name:deu_x_preferred":[
        "Laax"
    ],
    "name:eng_x_preferred":[
        "Laax"
    ],
    "name:epo_x_preferred":[
        "Laax"
    ],
    "name:eus_x_preferred":[
        "Laax"
    ],
    "name:fra_x_preferred":[
        "Laax"
    ],
    "name:hun_x_preferred":[
        "Laax"
    ],
    "name:ind_x_preferred":[
        "Laax"
    ],
    "name:ita_x_preferred":[
        "Laax"
    ],
    "name:kaz_x_preferred":[
        "\u041b\u0430\u043a\u0441"
    ],
    "name:kor_x_preferred":[
        "\ub77d\uc2a4"
    ],
    "name:lmo_x_preferred":[
        "Laax"
    ],
    "name:msa_x_preferred":[
        "Laax"
    ],
    "name:nld_x_preferred":[
        "Laax"
    ],
    "name:nno_x_preferred":[
        "Laax"
    ],
    "name:nob_x_preferred":[
        "Laax"
    ],
    "name:oci_x_preferred":[
        "Laax"
    ],
    "name:pms_x_preferred":[
        "Laax"
    ],
    "name:pol_x_preferred":[
        "Laax"
    ],
    "name:por_x_preferred":[
        "Laax"
    ],
    "name:roh_x_preferred":[
        "Laax"
    ],
    "name:rus_x_preferred":[
        "\u041b\u0430\u043a\u0441"
    ],
    "name:spa_x_preferred":[
        "Laax"
    ],
    "name:sqi_x_preferred":[
        "Laax"
    ],
    "name:swe_x_preferred":[
        "Laax"
    ],
    "name:unk_x_variant":[
        "Laax bei Ilanz"
    ],
    "name:uzb_x_preferred":[
        "Laax"
    ],
    "name:vol_x_preferred":[
        "Laax"
    ],
    "name:war_x_preferred":[
        "Laax"
    ],
    "name:zho_x_preferred":[
        "\u62c9\u514b\u65af"
    ],
    "qs_pg:aaroncc":"CH",
    "qs_pg:gn_country":"CH",
    "qs_pg:gn_fcode":"PPL",
    "qs_pg:gn_pop":1252,
    "qs_pg:name":"Laax",
    "qs_pg:name_adm0":"Schweiz",
    "qs_pg:name_adm1":"Kanton Graub\u00fcnden",
    "qs_pg:photos":1082,
    "qs_pg:photos_1k":219,
    "qs_pg:photos_9k":5,
    "qs_pg:photos_9r":7,
    "qs_pg:photos_all":1082,
    "qs_pg:photos_sr":11,
    "qs_pg:pop_sr":3,
    "qs_pg:qs_pg_placetype":"locality",
    "qs_pg:qs_pg_placetype_gp":"Town",
    "qs_pg:woe_adm0":23424957,
    "woe:adm0_id":23424957,
    "woe:name_adm0":"Schweiz",
    "woe:name_adm1":"Kanton Graub\u00fcnden",
    "woe:placetype":"Town",
    "wof:name":"Laax",
    "wof:placetype":"locality",
    "wof:population":1252
},
  "geometry": {"coordinates":[9.25787,46.80452],"type":"Point"}
}