{
  "type": "Feature",
  "properties": {
    "gn:admin1_code":"AR",
    "gn:admin2_code":"1501.0",
    "gn:admin3_code":"3006.0",
    "gn:asciiname":"Zuerchersmuehle",
    "gn:country_code":"CH",
    "gn:dem":810,
    "gn:feature_class":"P",
    "gn:feature_code":"PPL",
    "gn:name":"Z\u00fcrchersm\u00fchle",
    "gn:population":0,
    "gn:timezone":"Europe/Zurich",
    "iso:country":"CH",
    "name:deu_x_preferred":[
        "Z\u00fcrchersm\u00fchle"
    ],
    "wof:name":"Zuerchersmuehle",
    "wof:placetype":"neighbourhood"
},
  "geometry": {"coordinates":[9.29362,47.33019],"type":"Point"}
}