{
  "type": "Feature",
  "properties": {
    "gn:admin1_code":"FR",
    "gn:admin2_code":"1003.0",
    "gn:admin3_code":"2160.0",
    "gn:asciiname":"La Magnenetta",
    "gn:country_code":"CH",
    "gn:dem":882,
    "gn:feature_class":"P",
    "gn:feature_code":"PPL",
    "gn:name":"La Magnenetta",
    "gn:population":0,
    "gn:timezone":"Europe/Zurich",
    "iso:country":"CH",
    "name:fra_x_preferred":[
        "La Magnenetta"
    ],
    "wof:name":"La Magnenetta",
    "wof:placetype":"neighbourhood"
},
  "geometry": {"coordinates":[7.01174,46.60542],"type":"Point"}
}