{
  "type": "Feature",
  "properties": {
    "gn:country":"CH",
    "gn:fcode":"PPLX",
    "gn:population":1107,
    "iso:country":"CH",
    "name:eng_x_preferred":[
        "Kindhausen (Dorf)"
    ],
    "name:eng_x_variant":[
        "Kindhausen / Kindhausen (Dorf)"
    ],
    "qs_pg:aaroncc":"CH",
    "qs_pg:gn_country":"CH",
    "qs_pg:gn_fcode":"PPLX",
    "qs_pg:gn_pop":1107,
    "qs_pg:name":"Kindhausen / Kindhausen (Dorf)",
    "qs_pg:photos_9r":0,
    "qs_pg:photos_sr":0,
    "qs_pg:pop_sr":3,
    "qs_pg:qs_pg_placetype":"neighbourhood",
    "wof:name":"Kindhausen (Dorf)",
    "wof:placetype":"neighbourhood",
    "wof:population":1107
},
  "geometry": {"coordinates":[8.68296,47.40644],"type":"Point"}
}