{
  "type": "Feature",
  "properties": {
    "gn:gn_country":"CH",
    "gn:gn_fcode":"PPL",
    "gn:gn_pop":0,
    "iso:country":"CH",
    "name:ces_x_preferred":[
        "Clarens"
    ],
    "name:cym_x_preferred":[
        "Clarens"
    ],
    "name:dan_x_preferred":[
        "Clarens"
    ],
    "name:deu_x_preferred":[
        "Clarens VD"
    ],
    "name:ell_x_preferred":[
        "\u039a\u03bb\u03ac\u03c1\u03b5\u03bd\u03c2"
    ],
    "name:eng_x_preferred":[
        "Clarens"
    ],
    "name:epo_x_preferred":[
        "Clarens"
    ],
    "name:fra_x_preferred":[
        "Clarens"
    ],
    "name:fry_x_preferred":[
        "Clarens"
    ],
    "name:glg_x_preferred":[
        "Clarens"
    ],
    "name:hye_x_preferred":[
        "\u053f\u056c\u0561\u0580\u0561\u0576\u057d"
    ],
    "name:ita_x_preferred":[
        "Clarens"
    ],
    "name:jpn_x_preferred":[
        "\u30af\u30e9\u30ec\u30f3\u30b9"
    ],
    "name:nld_x_preferred":[
        "Clarens"
    ],
    "name:nob_x_preferred":[
        "Clarens"
    ],
    "name:pnb_x_preferred":[
        "\u06a9\u0644\u0627\u0631\u0646\u0632"
    ],
    "name:roh_x_preferred":[
        "Clarens"
    ],
    "name:rus_x_preferred":[
        "\u041a\u043b\u0430\u0440\u0430\u043d\u0441"
    ],
    "name:slv_x_preferred":[
        "Clarens"
    ],
    "name:spa_x_preferred":[
        "Clarens"
    ],
    "name:swe_x_preferred":[
        "Clarens"
    ],
    "name:tur_x_preferred":[
        "Clarens"
    ],
    "name:zho_x_preferred":[
        "\u514b\u62c9\u502b\u65af"
    ],
    "qs_pg:aaroncc":"CH",
    "qs_pg:gn_country":"CH",
    "qs_pg:gn_fcode":"PPL",
    "qs_pg:gn_pop":0,
    "qs_pg:name":"Clarens",
    "qs_pg:name_adm0":"Schweiz",
    "qs_pg:name_adm1":"Canton de Vaud",
    "qs_pg:photos":288,
    "qs_pg:photos_1k":58,
    "qs_pg:photos_9k":1,
    "qs_pg:photos_9r":4,
    "qs_pg:photos_all":288,
    "qs_pg:photos_sr":5,
    "qs_pg:pop_sr":0,
    "qs_pg:qs_pg_placetype":"locality",
    "qs_pg:qs_pg_placetype_gp":"Town",
    "qs_pg:woe_adm0":23424957,
    "woe:adm0_id":23424957,
    "woe:name_adm0":"Schweiz",
    "woe:name_adm1":"Canton de Vaud",
    "woe:placetype":"Town",
    "wof:name":"Clarens",
    "wof:placetype":"locality"
},
  "geometry": {"coordinates":[6.89233,46.44055],"type":"Point"}
}