{
  "type": "Feature",
  "properties": {
    "gn:admin1_code":"AG",
    "gn:admin2_code":"1908.0",
    "gn:admin3_code":"4239.0",
    "gn:asciiname":"Aettenschwil",
    "gn:country_code":"CH",
    "gn:dem":490,
    "gn:feature_class":"P",
    "gn:feature_code":"PPL",
    "gn:name":"Aettenschwil",
    "gn:population":0,
    "gn:timezone":"Europe/Zurich",
    "iso:country":"CH",
    "wof:name":"Aettenschwil",
    "wof:placetype":"locality"
},
  "geometry": {"coordinates":[8.37185,47.18356],"type":"Point"}
}