{
  "type": "Feature",
  "properties": {
    "gn:country":"CH",
    "gn:fcode":"PPLL",
    "gn:population":20,
    "iso:country":"CH",
    "name:deu_x_preferred":[
        "Rosenberg"
    ],
    "name:eng_x_preferred":[
        "Rosenberg"
    ],
    "name:eng_x_variant":[
        [
            "Rosenberg"
        ],
        "Feldbach / Rosenberg"
    ],
    "qs_pg:aaroncc":"CH",
    "qs_pg:gn_country":"CH",
    "qs_pg:gn_fcode":"PPLL",
    "qs_pg:gn_pop":20,
    "qs_pg:name":"Feldbach / Rosenberg",
    "qs_pg:photos_9r":0,
    "qs_pg:photos_sr":0,
    "qs_pg:pop_sr":1,
    "qs_pg:qs_pg_placetype":"locality",
    "wof:name":"Rosenberg",
    "wof:placetype":"neighbourhood",
    "wof:population":20
},
  "geometry": {"coordinates":[8.78179,47.23767],"type":"Point"}
}