{
  "type": "Feature",
  "properties": {
    "gn:admin1_code":"BE",
    "gn:admin2_code":"248.0",
    "gn:admin3_code":"791.0",
    "gn:asciiname":"Sommerau",
    "gn:country_code":"CH",
    "gn:dem":1281,
    "gn:feature_class":"P",
    "gn:feature_code":"PPL",
    "gn:name":"Sommerau",
    "gn:population":0,
    "gn:timezone":"Europe/Zurich",
    "iso:country":"CH",
    "name:deu_x_preferred":[
        "Sommerau"
    ],
    "wof:name":"Sommerau",
    "wof:placetype":"locality"
},
  "geometry": {"coordinates":[7.35598,46.59517],"type":"Point"}
}