{
  "type": "Feature",
  "properties": {
    "gn:admin1_code":"FR",
    "gn:admin2_code":"1003.0",
    "gn:admin3_code":"2163.0",
    "gn:asciiname":"Petits Fornis",
    "gn:country_code":"CH",
    "gn:dem":955,
    "gn:feature_class":"P",
    "gn:feature_code":"PPL",
    "gn:name":"Petits Fornis",
    "gn:population":0,
    "gn:timezone":"Europe/Zurich",
    "iso:country":"CH",
    "name:fra_x_preferred":[
        "Petits Fornis"
    ],
    "wof:name":"Petits Fornis",
    "wof:placetype":"neighbourhood"
},
  "geometry": {"coordinates":[7.20482,46.60722],"type":"Point"}
}