{
  "type": "Feature",
  "properties": {
    "gn:admin1_code":"TI",
    "gn:admin2_code":"2106.0",
    "gn:admin3_code":"5249.0",
    "gn:asciiname":"Moieta",
    "gn:country_code":"CH",
    "gn:dem":492,
    "gn:feature_class":"P",
    "gn:feature_code":"PPL",
    "gn:name":"Moieta",
    "gn:population":0,
    "gn:timezone":"Europe/Zurich",
    "iso:country":"CH",
    "name:ita_x_preferred":[
        "Moieta"
    ],
    "wof:name":"Moieta",
    "wof:placetype":"neighbourhood"
},
  "geometry": {"coordinates":[9.02647,45.87594],"type":"Point"}
}