{
  "type": "Feature",
  "properties": {
    "gn:admin1_code":"TG",
    "gn:admin2_code":"2015.0",
    "gn:admin3_code":"4881.0",
    "gn:asciiname":"Strohwilen",
    "gn:country_code":"CH",
    "gn:dem":584,
    "gn:elevation":"584.0",
    "gn:feature_class":"P",
    "gn:feature_code":"PPL",
    "gn:name":"Strohwilen",
    "gn:population":0,
    "gn:timezone":"Europe/Zurich",
    "iso:country":"CH",
    "name:ara_x_preferred":[
        "\u0633\u062a\u0631\u0648\u0644\u064a\u0646"
    ],
    "name:deu_x_preferred":[
        "Strohwilen"
    ],
    "name:ita_x_preferred":[
        "Strohwilen"
    ],
    "wof:name":"Strohwilen",
    "wof:placetype":"neighbourhood"
},
  "geometry": {"coordinates":[9.01629,47.55345],"type":"Point"}
}