{
  "type": "Feature",
  "properties": {
    "gn:gn_country":"CH",
    "gn:gn_fcode":"PPL",
    "gn:gn_pop":1975,
    "gn:population":1975,
    "iso:country":"CH",
    "name:ara_x_preferred":[
        "\u0641\u0627\u064a\u0633\u0644\u0646\u063a\u0646"
    ],
    "name:cat_x_preferred":[
        "Weisslingen"
    ],
    "name:chv_x_preferred":[
        "\u0412\u0430\u0439\u0441\u043b\u0438\u043d\u0433\u0435\u043d"
    ],
    "name:deu_x_preferred":[
        "Weisslingen"
    ],
    "name:eng_x_preferred":[
        "Weisslingen"
    ],
    "name:epo_x_preferred":[
        "Weisslingen"
    ],
    "name:eus_x_preferred":[
        "Weisslingen"
    ],
    "name:fra_x_preferred":[
        "Weisslingen"
    ],
    "name:gsw_x_preferred":[
        "Wislig"
    ],
    "name:hun_x_preferred":[
        "Weisslingen"
    ],
    "name:ita_x_preferred":[
        "Weisslingen"
    ],
    "name:kaz_x_preferred":[
        "\u0412\u0430\u0439\u0441\u043b\u0438\u043d\u0433\u0435\u043d"
    ],
    "name:lmo_x_preferred":[
        "Weisslingen"
    ],
    "name:msa_x_preferred":[
        "Weisslingen"
    ],
    "name:nld_x_preferred":[
        "Weisslingen"
    ],
    "name:nno_x_preferred":[
        "Weisslingen"
    ],
    "name:oci_x_preferred":[
        "Weisslingen"
    ],
    "name:pms_x_preferred":[
        "Weisslingen"
    ],
    "name:por_x_preferred":[
        "Weisslingen"
    ],
    "name:rus_x_preferred":[
        "\u0412\u0430\u0439\u0441\u043b\u0438\u043d\u0433\u0435\u043d"
    ],
    "name:uzb_x_preferred":[
        "Weisslingen"
    ],
    "name:vec_x_preferred":[
        "Weisslingen"
    ],
    "name:vol_x_preferred":[
        "Weisslingen"
    ],
    "name:war_x_preferred":[
        "Weisslingen"
    ],
    "name:zho_x_preferred":[
        "\u9b4f\u65af\u6797\u6839"
    ],
    "qs_pg:aaroncc":"CH",
    "qs_pg:gn_country":"CH",
    "qs_pg:gn_fcode":"PPL",
    "qs_pg:gn_pop":1975,
    "qs_pg:name":"Weisslingen",
    "qs_pg:name_adm0":"Schweiz",
    "qs_pg:name_adm1":"Kanton Z\u00fcrich",
    "qs_pg:photos_9k":1,
    "qs_pg:photos_9r":1,
    "qs_pg:photos_all":3,
    "qs_pg:photos_sr":0,
    "qs_pg:pop_sr":3,
    "qs_pg:qs_pg_placetype":"locality",
    "qs_pg:qs_pg_placetype_gp":"Town",
    "qs_pg:woe_adm0":23424957,
    "woe:adm0_id":23424957,
    "woe:name_adm0":"Schweiz",
    "woe:name_adm1":"Kanton Z\u00fcrich",
    "woe:placetype":"Town",
    "wof:name":"Weisslingen",
    "wof:placetype":"locality",
    "wof:population":1975
},
  "geometry": {"coordinates":[8.76787,47.43063],"type":"Point"}
}