{
  "type": "Feature",
  "properties": {
    "gn:admin1_code":"TI",
    "gn:admin2_code":"2105.0",
    "gn:admin3_code":"5236.0",
    "gn:asciiname":"Laghetto",
    "gn:country_code":"CH",
    "gn:dem":342,
    "gn:feature_class":"P",
    "gn:feature_code":"PPL",
    "gn:name":"Laghetto",
    "gn:population":0,
    "gn:timezone":"Europe/Zurich",
    "iso:country":"CH",
    "name:ita_x_preferred":[
        "Laghetto"
    ],
    "wof:name":"Laghetto",
    "wof:placetype":"locality"
},
  "geometry": {"coordinates":[8.92941,45.99495],"type":"Point"}
}