{
  "type": "Feature",
  "properties": {
    "gn:admin1_code":"LU",
    "gn:admin2_code":"312.0",
    "gn:admin3_code":"1062.0",
    "gn:asciiname":"Untersiten",
    "gn:country_code":"CH",
    "gn:dem":725,
    "gn:feature_class":"P",
    "gn:feature_code":"PPLL",
    "gn:name":"Untersiten",
    "gn:population":0,
    "gn:timezone":"Europe/Zurich",
    "iso:country":"CH",
    "name:deu_x_preferred":[
        "Untersiten"
    ],
    "wof:name":"Untersiten",
    "wof:placetype":"neighbourhood"
},
  "geometry": {"coordinates":[8.19066,47.02906],"type":"Point"}
}