{
  "type": "Feature",
  "properties": {
    "gn:admin1_code":"AR",
    "gn:admin2_code":"1502.0",
    "gn:admin3_code":"3022.0",
    "gn:asciiname":"Kellersegg",
    "gn:country_code":"CH",
    "gn:dem":1162,
    "gn:feature_class":"P",
    "gn:feature_code":"PPLL",
    "gn:name":"Kellersegg",
    "gn:population":0,
    "gn:timezone":"Europe/Zurich",
    "iso:country":"CH",
    "name:deu_x_preferred":[
        "Kellersegg"
    ],
    "wof:name":"Kellersegg",
    "wof:placetype":"neighbourhood"
},
  "geometry": {"coordinates":[9.48332,47.38332],"type":"Point"}
}