{
  "type": "Feature",
  "properties": {
    "gn:admin1_code":"TI",
    "gn:admin2_code":"2106.0",
    "gn:admin3_code":"5254.0",
    "gn:asciiname":"Fornace",
    "gn:country_code":"CH",
    "gn:dem":521,
    "gn:feature_class":"P",
    "gn:feature_code":"PPL",
    "gn:name":"Fornace",
    "gn:population":0,
    "gn:timezone":"Europe/Zurich",
    "iso:country":"CH",
    "name:azb_x_preferred":[
        "\u0641\u0648\u0631\u0646\u0627\u0686\u0647"
    ],
    "name:bul_x_preferred":[
        "\u0424\u043e\u0440\u043d\u0430\u0447\u0435"
    ],
    "name:cat_x_preferred":[
        "Fornace"
    ],
    "name:ceb_x_preferred":[
        "Fornace"
    ],
    "name:deu_x_preferred":[
        "Fornace"
    ],
    "name:epo_x_preferred":[
        "Fornace"
    ],
    "name:est_x_preferred":[
        "Fornace"
    ],
    "name:eus_x_preferred":[
        "Fornace"
    ],
    "name:fas_x_preferred":[
        "\u0641\u0648\u0631\u0646\u0627\u0686\u0647"
    ],
    "name:fra_x_preferred":[
        "Fornace"
    ],
    "name:hun_x_preferred":[
        "Fornace"
    ],
    "name:hye_x_preferred":[
        "\u0556\u0578\u0580\u0576\u0561\u0579\u0565"
    ],
    "name:ind_x_preferred":[
        "Fornace"
    ],
    "name:ita_x_preferred":[
        "Fornace"
    ],
    "name:jpn_x_preferred":[
        "\u30d5\u30a9\u30eb\u30ca\u30fc\u30c1\u30a7"
    ],
    "name:lat_x_preferred":[
        "Fornaces"
    ],
    "name:lmo_x_preferred":[
        "Fornace"
    ],
    "name:msa_x_preferred":[
        "Fornace"
    ],
    "name:nap_x_preferred":[
        "Fornace"
    ],
    "name:nld_x_preferred":[
        "Fornace"
    ],
    "name:pms_x_preferred":[
        "Fornace"
    ],
    "name:pol_x_preferred":[
        "Fornace"
    ],
    "name:por_x_preferred":[
        "Fornace"
    ],
    "name:ron_x_preferred":[
        "Fornace"
    ],
    "name:rus_x_preferred":[
        "\u0424\u043e\u0440\u043d\u0430\u0447\u0435"
    ],
    "name:scn_x_preferred":[
        "Fornace"
    ],
    "name:spa_x_preferred":[
        "Fornace"
    ],
    "name:srp_x_preferred":[
        "\u0424\u043e\u0440\u043d\u0430\u0447\u0435"
    ],
    "name:swe_x_preferred":[
        "Fornace"
    ],
    "name:tgl_x_preferred":[
        "Fornace"
    ],
    "name:ukr_x_preferred":[
        "\u0424\u043e\u0440\u043d\u0430\u0447\u0435"
    ],
    "name:uzb_x_preferred":[
        "Fornace"
    ],
    "name:vec_x_preferred":[
        "Fornaxa"
    ],
    "name:vie_x_preferred":[
        "Fornace"
    ],
    "name:vol_x_preferred":[
        "Fornace"
    ],
    "name:war_x_preferred":[
        "Fornace"
    ],
    "name:zho_x_preferred":[
        "\u798f\u5c14\u7eb3\u5207"
    ],
    "wof:lang_x_official":[
        "deu",
        "fra",
        "gsw",
        "ita"
    ],
    "wof:lang_x_spoken":[
        "deu",
        "fra",
        "gsw",
        "ita",
        "roh"
    ],
    "wof:name":"Fornace",
    "wof:placetype":"neighbourhood"
},
  "geometry": {"coordinates":[8.95007,45.87969],"type":"Point"}
}