{
  "type": "Feature",
  "properties": {
    "gn:admin1_code":"TG",
    "gn:admin2_code":"2012.0",
    "gn:admin3_code":"4546.0",
    "gn:asciiname":"Riederen",
    "gn:country_code":"CH",
    "gn:dem":450,
    "gn:feature_class":"P",
    "gn:feature_code":"PPLL",
    "gn:name":"Riederen",
    "gn:population":0,
    "gn:timezone":"Europe/Zurich",
    "iso:country":"CH",
    "name:deu_x_preferred":[
        "Riederen"
    ],
    "wof:lang_x_official":[
        "deu",
        "fra",
        "gsw",
        "ita"
    ],
    "wof:lang_x_spoken":[
        "deu",
        "fra",
        "gsw",
        "ita",
        "roh"
    ],
    "wof:name":"Riederen",
    "wof:placetype":"neighbourhood"
},
  "geometry": {"coordinates":[8.71502,47.66318],"type":"Point"}
}