{
  "type": "Feature",
  "properties": {
    "iso:country":"CH",
    "wof:name":"De Beaumont",
    "wof:placetype":"neighbourhood"
},
  "geometry": {"coordinates":[6.15606683626516,46.1973539799354],"type":"Point"}
}