{
  "type": "Feature",
  "properties": {
    "iso:country":"CH",
    "name:bre_x_preferred":[
        "Beaulieu"
    ],
    "name:cat_x_preferred":[
        "Beaulieu"
    ],
    "name:ceb_x_preferred":[
        "Beaulieu"
    ],
    "name:deu_x_preferred":[
        "Beaulieu"
    ],
    "name:fra_x_preferred":[
        "Beaulieu"
    ],
    "name:ind_x_preferred":[
        "Beaulieu"
    ],
    "name:ita_x_preferred":[
        "Beaulieu"
    ],
    "name:jpn_x_preferred":[
        "\u30dc\u30fc\u30ea\u30e5\u30fc"
    ],
    "name:lmo_x_preferred":[
        "Beaulieu"
    ],
    "name:nds_x_preferred":[
        "Beaulieu"
    ],
    "name:nld_x_preferred":[
        "Beaulieu"
    ],
    "name:oci_x_preferred":[
        "Beaulieu"
    ],
    "name:pms_x_preferred":[
        "Beaulieu"
    ],
    "name:pol_x_preferred":[
        "Beaulieu"
    ],
    "name:por_x_preferred":[
        "Beaulieu"
    ],
    "name:ron_x_preferred":[
        "Beaulieu"
    ],
    "name:rus_x_preferred":[
        "\u0411\u043e\u043b\u044c\u0451"
    ],
    "name:sco_x_preferred":[
        "Beaulieu"
    ],
    "name:slk_x_preferred":[
        "Beaulieu"
    ],
    "name:spa_x_preferred":[
        "Beaulieu"
    ],
    "name:sqi_x_preferred":[
        "Beaulieu"
    ],
    "name:srp_x_preferred":[
        "\u0411\u043e\u043b\u0438\u0458\u0435"
    ],
    "name:swe_x_preferred":[
        "Beaulieu"
    ],
    "name:ukr_x_preferred":[
        "\u0411\u043e\u043b\u044c\u0454"
    ],
    "qs:gn_adm0_cc":"CH",
    "qs:gn_local":2659994,
    "qs:gn_nam_loc":"Lausanne, Lausanne, Canton de Vaud, CH",
    "qs:gn_namadm1":"VD",
    "qs:local_max":7240,
    "qs:local_sum":38363,
    "qs:localhoods":45,
    "qs:name":"Beaulieu",
    "qs:name_adm0":"Schweiz",
    "qs:name_adm1":"Canton de Vaud",
    "qs:name_adm2":"Lausanne",
    "qs:name_lau":"Lausanne",
    "qs:name_local":"Lausanne",
    "qs:photo_max":823,
    "qs:photo_sum":1792,
    "qs:placetype":"Suburb",
    "qs:quad_count":14,
    "qs:woe_adm0":23424957,
    "qs:woe_adm1":2347105,
    "qs:woe_adm2":12593172,
    "qs:woe_lau":12682890,
    "qs:woe_local":783058,
    "qs:woe_ver":"7.10.0",
    "wof:lang":[
        "fre"
    ],
    "wof:name":"Beaulieu",
    "wof:placetype":"neighbourhood"
},
  "geometry": {"coordinates":[6.626827,46.534117],"type":"Point"}
}