{
  "type": "Feature",
  "properties": {
    "iso:country":"CH",
    "name:fra_x_preferred":[
        "Beaulieu"
    ],
    "name:unk_x_variant":[
        "Beaulieu"
    ],
    "qs:gn_adm0_cc":"CH",
    "qs:gn_local":2659994,
    "qs:gn_nam_loc":"Lausanne, Lausanne, Canton de Vaud, CH",
    "qs:gn_namadm1":"VD",
    "qs:local_max":7240,
    "qs:local_sum":38363,
    "qs:localhoods":45,
    "qs:name":"Beaulieu",
    "qs:name_adm0":"Schweiz",
    "qs:name_adm1":"Canton de Vaud",
    "qs:name_adm2":"Lausanne",
    "qs:name_lau":"Lausanne",
    "qs:name_local":"Lausanne",
    "qs:photo_max":823,
    "qs:photo_sum":1792,
    "qs:placetype":"Suburb",
    "qs:quad_count":14,
    "qs:woe_adm0":23424957,
    "qs:woe_adm1":2347105,
    "qs:woe_adm2":12593172,
    "qs:woe_lau":12682890,
    "qs:woe_local":783058,
    "qs:woe_ver":"7.10.0",
    "wof:lang":[
        "fre"
    ],
    "wof:name":"Beaulieu",
    "wof:placetype":"neighbourhood"
},
  "geometry": {"coordinates":[6.626827,46.534117],"type":"Point"}
}