{
  "type": "Feature",
  "properties": {
    "gn:gn_country":"CH",
    "gn:gn_fcode":"PPL",
    "gn:gn_pop":19,
    "gn:population":19,
    "iso:country":"CH",
    "name:deu_x_preferred":[
        "L\u00f6ffler"
    ],
    "name:hsb_x_preferred":[
        "L\u00f6ffler"
    ],
    "qs_pg:aaroncc":"CH",
    "qs_pg:gn_country":"CH",
    "qs_pg:gn_fcode":"PPL",
    "qs_pg:gn_pop":19,
    "qs_pg:name":"L\u00f6ffler",
    "qs_pg:photos_9r":0,
    "qs_pg:photos_sr":0,
    "qs_pg:pop_sr":1,
    "qs_pg:qs_pg_placetype":"locality",
    "wof:name":"L\u00f6ffler",
    "wof:placetype":"neighbourhood",
    "wof:population":19
},
  "geometry": {"coordinates":[8.43063,47.35036],"type":"Point"}
}