{
  "type": "Feature",
  "properties": {
    "gn:admin1_code":"GR",
    "gn:admin2_code":"1843.0",
    "gn:admin3_code":"3847.0",
    "gn:asciiname":"Alp Sprella",
    "gn:country_code":"CH",
    "gn:dem":2127,
    "gn:feature_class":"P",
    "gn:feature_code":"PPL",
    "gn:name":"Alp Sprella",
    "gn:population":0,
    "gn:timezone":"Europe/Zurich",
    "iso:country":"CH",
    "name:roh_x_preferred":[
        "Alp Sprella"
    ],
    "wof:name":"Alp Sprella",
    "wof:placetype":"neighbourhood"
},
  "geometry": {"coordinates":[10.30004,46.5918],"type":"Point"}
}