{
  "type": "Feature",
  "properties": {
    "gn:admin1_code":"GR",
    "gn:admin2_code":"1843.0",
    "gn:admin3_code":"3847.0",
    "gn:asciiname":"Pizzet",
    "gn:country_code":"CH",
    "gn:dem":1414,
    "gn:feature_class":"P",
    "gn:feature_code":"PPL",
    "gn:name":"Pizzet",
    "gn:population":0,
    "gn:timezone":"Europe/Zurich",
    "iso:country":"CH",
    "name:roh_x_preferred":[
        "Pizzet"
    ],
    "wof:name":"Pizzet",
    "wof:placetype":"neighbourhood"
},
  "geometry": {"coordinates":[10.42658,46.6112],"type":"Point"}
}