{
  "type": "Feature",
  "properties": {
    "gn:admin1_code":"GR",
    "gn:admin2_code":"1849.0",
    "gn:admin3_code":"3851.0",
    "gn:asciiname":"Sertig Doefli",
    "gn:country_code":"CH",
    "gn:dem":1869,
    "gn:feature_class":"P",
    "gn:feature_code":"PPL",
    "gn:name":"Sertig D\u00f6fli",
    "gn:population":0,
    "gn:timezone":"Europe/Zurich",
    "iso:country":"CH",
    "wof:name":"Sertig Doefli",
    "wof:placetype":"locality"
},
  "geometry": {"coordinates":[9.84843,46.72635],"type":"Point"}
}