{
  "type": "Feature",
  "properties": {
    "gn:admin1_code":"SG",
    "gn:admin2_code":"1726.0",
    "gn:admin3_code":"3340.0",
    "gn:asciiname":"Busskirch",
    "gn:country_code":"CH",
    "gn:dem":404,
    "gn:feature_class":"P",
    "gn:feature_code":"PPL",
    "gn:name":"Busskirch",
    "gn:population":0,
    "gn:timezone":"Europe/Zurich",
    "iso:country":"CH",
    "name:deu_x_preferred":[
        "Busskirch"
    ],
    "name:pnb_x_preferred":[
        "\u0628\u0633\u06a9\u0631\u062e"
    ],
    "wof:lang_x_official":[
        "deu",
        "fra",
        "gsw",
        "ita"
    ],
    "wof:lang_x_spoken":[
        "deu",
        "fra",
        "gsw",
        "ita",
        "roh"
    ],
    "wof:name":"Busskirch",
    "wof:placetype":"neighbourhood"
},
  "geometry": {"coordinates":[8.83369,47.2177],"type":"Point"}
}