{
  "type": "Feature",
  "properties": {
    "gn:admin1_code":"GR",
    "gn:admin2_code":"1849.0",
    "gn:admin3_code":"3891.0",
    "gn:asciiname":"Castels",
    "gn:country_code":"CH",
    "gn:dem":1450,
    "gn:feature_class":"P",
    "gn:feature_code":"PPL",
    "gn:name":"Castels",
    "gn:population":0,
    "gn:timezone":"Europe/Zurich",
    "iso:country":"CH",
    "name:bug_x_preferred":[
        "Castels"
    ],
    "name:cat_x_preferred":[
        "Cast\u00e8l"
    ],
    "name:ceb_x_preferred":[
        "Castels"
    ],
    "name:che_x_preferred":[
        "\u041a\u0430\u0441\u0442\u0435\u043b\u044c"
    ],
    "name:deu_x_preferred":[
        "Castels"
    ],
    "name:eus_x_preferred":[
        "Cast\u00e8l"
    ],
    "name:fra_x_preferred":[
        "Castels"
    ],
    "name:hun_x_preferred":[
        "Castels"
    ],
    "name:ita_x_preferred":[
        "Castels"
    ],
    "name:kaz_x_preferred":[
        "\u041a\u0430\u0441\u0442\u0435\u043b\u044c"
    ],
    "name:lat_x_preferred":[
        "Castels"
    ],
    "name:ltz_x_preferred":[
        "Castels"
    ],
    "name:mlg_x_preferred":[
        "Castels"
    ],
    "name:msa_x_preferred":[
        "Castels"
    ],
    "name:nld_x_preferred":[
        "Castels"
    ],
    "name:oci_x_preferred":[
        "Cast\u00e8ls"
    ],
    "name:pms_x_preferred":[
        "Castels"
    ],
    "name:pol_x_preferred":[
        "Castels"
    ],
    "name:por_x_preferred":[
        "Castels"
    ],
    "name:ron_x_preferred":[
        "Castels"
    ],
    "name:slk_x_preferred":[
        "Castels"
    ],
    "name:spa_x_preferred":[
        "Castels"
    ],
    "name:srp_x_preferred":[
        "\u041a\u0430\u0441\u0442\u0435\u043b"
    ],
    "name:swe_x_preferred":[
        "Castels"
    ],
    "name:ukr_x_preferred":[
        "\u041a\u0430\u0441\u0442\u0435\u043b\u044c"
    ],
    "name:uzb_x_preferred":[
        "Castels"
    ],
    "name:vie_x_preferred":[
        "Castels"
    ],
    "name:vol_x_preferred":[
        "Castels"
    ],
    "name:war_x_preferred":[
        "Castels"
    ],
    "name:zho_x_preferred":[
        "\u5361\u65af\u6cf0\u5c14"
    ],
    "wof:name":"Castels",
    "wof:placetype":"neighbourhood"
},
  "geometry": {"coordinates":[9.81667,46.96667],"type":"Point"}
}