{
  "type": "Feature",
  "properties": {
    "gn:country":"CH",
    "gn:fcode":"PPLX",
    "gn:population":850,
    "iso:country":"CH",
    "name:ceb_x_preferred":[
        "Seen"
    ],
    "name:deu_x_preferred":[
        "Waldegg bei Uitikon"
    ],
    "name:deu_x_variant":[
        "Waldegg"
    ],
    "name:eng_x_preferred":[
        "Waldegg"
    ],
    "name:swe_x_preferred":[
        "Seen"
    ],
    "qs_pg:aaroncc":"CH",
    "qs_pg:gn_country":"CH",
    "qs_pg:gn_fcode":"PPLX",
    "qs_pg:gn_pop":850,
    "qs_pg:name":"Waldegg bei Uitikon",
    "qs_pg:name_adm0":"Schweiz",
    "qs_pg:name_adm1":"Kanton Z\u00fcrich",
    "qs_pg:photos":302,
    "qs_pg:photos_1k":61,
    "qs_pg:photos_9k":1,
    "qs_pg:photos_9r":5,
    "qs_pg:photos_all":302,
    "qs_pg:photos_sr":5,
    "qs_pg:pop_sr":2,
    "qs_pg:qs_pg_placetype":"neighbourhood",
    "qs_pg:qs_pg_placetype_gp":"Suburb",
    "qs_pg:woe_adm0":23424957,
    "woe:adm0_id":23424957,
    "woe:name_adm0":"Schweiz",
    "woe:name_adm1":"Kanton Z\u00fcrich",
    "woe:placetype":"Suburb",
    "wof:lang_x_official":[
        "deu",
        "fra",
        "gsw",
        "ita"
    ],
    "wof:lang_x_spoken":[
        "deu",
        "fra",
        "gsw",
        "ita",
        "roh"
    ],
    "wof:name":"Waldegg bei Uitikon",
    "wof:placetype":"neighbourhood",
    "wof:population":850
},
  "geometry": {"coordinates":[8.46444,47.36332],"type":"Point"}
}