{
  "type": "Feature",
  "properties": {
    "gn:gn_country":"CH",
    "gn:gn_fcode":"PPLL",
    "gn:gn_pop":16,
    "gn:population":16,
    "iso:country":"CH",
    "qs_pg:aaroncc":"CH",
    "qs_pg:gn_country":"CH",
    "qs_pg:gn_fcode":"PPLL",
    "qs_pg:gn_pop":16,
    "qs_pg:name":"T\u00f6ssegg",
    "qs_pg:name_adm0":"Schweiz",
    "qs_pg:name_adm1":"Kanton Z\u00fcrich",
    "qs_pg:photos_9r":0,
    "qs_pg:photos_sr":0,
    "qs_pg:pop_sr":1,
    "qs_pg:qs_pg_placetype":"locality",
    "qs_pg:qs_pg_placetype_gp":"Town",
    "qs_pg:woe_adm0":23424957,
    "woe:adm0_id":23424957,
    "woe:name_adm0":"Schweiz",
    "woe:name_adm1":"Kanton Z\u00fcrich",
    "woe:placetype":"Town",
    "wof:name":"T\u00f6ssegg",
    "wof:placetype":"neighbourhood",
    "wof:population":16
},
  "geometry": {"coordinates":[8.83802,47.43709],"type":"Point"}
}