{
  "type": "Feature",
  "properties": {
    "gn:admin1_code":"VD",
    "gn:admin2_code":"2222.0",
    "gn:admin3_code":"5675.0",
    "gn:asciiname":"Forel",
    "gn:country_code":"CH",
    "gn:dem":675,
    "gn:feature_class":"P",
    "gn:feature_code":"PPL",
    "gn:name":"Forel",
    "gn:population":0,
    "gn:timezone":"Europe/Zurich",
    "iso:country":"CH",
    "name:und_x_variant":[
        "Forel-sur-Lucens"
    ],
    "wof:name":"Forel",
    "wof:placetype":"locality"
},
  "geometry": {"coordinates":[6.82374,46.72887],"type":"Point"}
}