{
  "type": "Feature",
  "properties": {
    "gn:admin1_code":"BE",
    "gn:admin2_code":"241.0",
    "gn:admin3_code":"700.0",
    "gn:asciiname":"Graitery",
    "gn:country_code":"CH",
    "gn:dem":1191,
    "gn:feature_class":"P",
    "gn:feature_code":"PPLL",
    "gn:name":"Graitery",
    "gn:population":0,
    "gn:timezone":"Europe/Zurich",
    "iso:country":"CH",
    "name:fra_x_preferred":[
        "Graitery"
    ],
    "wof:name":"Graitery",
    "wof:placetype":"neighbourhood"
},
  "geometry": {"coordinates":[7.38419,47.25786],"type":"Point"}
}