{
  "type": "Feature",
  "properties": {
    "gn:gn_country":"CH",
    "gn:gn_fcode":"PPL",
    "gn:gn_pop":0,
    "iso:country":"CH",
    "name:eng_x_preferred":[
        "Les Charbonni\u00e8res"
    ],
    "name:fra_x_preferred":[
        "Les Charbonni\u00e8res"
    ],
    "name:jpn_x_preferred":[
        "\u30ec\u30fb\u30b7\u30e3\u30eb\u30dc\u30cb\u30a8\u30fc\u30eb"
    ],
    "name:nld_x_preferred":[
        "Les Charbonni\u00e8res"
    ],
    "qs_pg:aaroncc":"CH",
    "qs_pg:gn_country":"CH",
    "qs_pg:gn_fcode":"PPL",
    "qs_pg:gn_pop":0,
    "qs_pg:name":"Les Charbonni\u00e8res",
    "qs_pg:name_adm0":"Schweiz",
    "qs_pg:name_adm1":"Canton de Vaud",
    "qs_pg:photos":52,
    "qs_pg:photos_1k":11,
    "qs_pg:photos_9k":1,
    "qs_pg:photos_9r":2,
    "qs_pg:photos_all":52,
    "qs_pg:photos_sr":2,
    "qs_pg:pop_sr":0,
    "qs_pg:qs_pg_placetype":"locality",
    "qs_pg:qs_pg_placetype_gp":"Town",
    "qs_pg:woe_adm0":23424957,
    "woe:adm0_id":23424957,
    "woe:name_adm0":"Schweiz",
    "woe:name_adm1":"Canton de Vaud",
    "woe:placetype":"Town",
    "wof:name":"Les Charbonni\u00e8res",
    "wof:placetype":"locality"
},
  "geometry": {"coordinates":[6.31337,46.66748],"type":"Point"}
}