{
  "type": "Feature",
  "properties": {
    "gn:gn_country":"CH",
    "gn:gn_fcode":"PPL",
    "gn:gn_pop":1169,
    "gn:population":1169,
    "iso:country":"CH",
    "name:baq_x_preferred":[
        "Les Brenets"
    ],
    "name:cat_x_preferred":[
        "Les Brenets"
    ],
    "name:chi_x_preferred":[
        "\u840a\u5e03\u96f7\u5167"
    ],
    "name:dut_x_preferred":[
        "Les Brenets"
    ],
    "name:eng_x_preferred":[
        "Les Brenets"
    ],
    "name:epo_x_preferred":[
        "Les Brenets"
    ],
    "name:fre_x_preferred":[
        "Les Brenets"
    ],
    "name:ger_x_preferred":[
        "Les Brenets"
    ],
    "name:gsw_x_preferred":[
        "Les Brenets"
    ],
    "name:hun_x_preferred":[
        "Les Brenets"
    ],
    "name:ita_x_preferred":[
        "Les Brenets"
    ],
    "name:jpn_x_preferred":[
        "\u30ec\u30fb\u30d6\u30eb\u30cd"
    ],
    "name:lmo_x_preferred":[
        "Les Brenets"
    ],
    "name:may_x_preferred":[
        "Les Brenets"
    ],
    "name:nno_x_preferred":[
        "Les Brenets"
    ],
    "name:oci_x_preferred":[
        "Les Brenets"
    ],
    "name:spa_x_preferred":[
        "Les Brenets"
    ],
    "name:swe_x_preferred":[
        "Les Brenets"
    ],
    "name:vol_x_preferred":[
        "Les Brenets"
    ],
    "name:war_x_preferred":[
        "Les Brenets"
    ],
    "name:zho_x_preferred":[
        "\u840a\u5e03\u96f7\u5167"
    ],
    "qs_pg:aaroncc":"CH",
    "qs_pg:gn_country":"CH",
    "qs_pg:gn_fcode":"PPL",
    "qs_pg:gn_pop":1169,
    "qs_pg:name":"Les Brenets",
    "qs_pg:name_adm0":"Schweiz",
    "qs_pg:name_adm1":"Canton de Neuch\u00e2tel",
    "qs_pg:photos":299,
    "qs_pg:photos_1k":61,
    "qs_pg:photos_9k":1,
    "qs_pg:photos_9r":4,
    "qs_pg:photos_all":299,
    "qs_pg:photos_sr":5,
    "qs_pg:pop_sr":3,
    "qs_pg:qs_pg_placetype":"locality",
    "qs_pg:qs_pg_placetype_gp":"Town",
    "qs_pg:woe_adm0":23424957,
    "woe:adm0_id":23424957,
    "woe:name_adm0":"Schweiz",
    "woe:name_adm1":"Canton de Neuch\u00e2tel",
    "woe:placetype":"Town",
    "wof:name":"Les Brenets",
    "wof:placetype":"locality",
    "wof:population":1169
},
  "geometry": {"coordinates":[6.70727,47.06708],"type":"Point"}
}