{
  "type": "Feature",
  "properties": {
    "gn:gn_country":"CH",
    "gn:gn_fcode":"PPL",
    "gn:gn_pop":1647,
    "gn:population":1647,
    "iso:country":"CH",
    "name:bul_x_preferred":[
        "\u0424\u043e\u043d\u0442\u0430\u0438\u043d\u0435\u043c\u0435\u043b\u043e\u043d"
    ],
    "name:cat_x_preferred":[
        "Fontainemelon"
    ],
    "name:chi_x_preferred":[
        "\u8c50\u6cf0\u5167\u6885\u9686"
    ],
    "name:dut_x_preferred":[
        "Fontainemelon"
    ],
    "name:eng_x_preferred":[
        "Fontainemelon"
    ],
    "name:epo_x_preferred":[
        "Fontainemelon"
    ],
    "name:fre_x_preferred":[
        "Fontainemelon"
    ],
    "name:ger_x_preferred":[
        "Fontainemelon"
    ],
    "name:gsw_x_preferred":[
        "Fontainemelon"
    ],
    "name:hun_x_preferred":[
        "Fontainemelon"
    ],
    "name:ita_x_preferred":[
        "Fontainemelon"
    ],
    "name:lmo_x_preferred":[
        "Fontainemelon"
    ],
    "name:may_x_preferred":[
        "Fontainemelon"
    ],
    "name:nno_x_preferred":[
        "Fontainemelon"
    ],
    "name:oci_x_preferred":[
        "Fontainemelon"
    ],
    "name:spa_x_preferred":[
        "Fontainemelon"
    ],
    "name:swe_x_preferred":[
        "Fontainemelon"
    ],
    "name:vol_x_preferred":[
        "Fontainemelon"
    ],
    "name:war_x_preferred":[
        "Fontainemelon"
    ],
    "name:zho_x_preferred":[
        "\u8c50\u6cf0\u5167\u6885\u9686"
    ],
    "qs_pg:aaroncc":"CH",
    "qs_pg:gn_country":"CH",
    "qs_pg:gn_fcode":"PPL",
    "qs_pg:gn_pop":1647,
    "qs_pg:name":"Fontainemelon",
    "qs_pg:name_adm0":"Schweiz",
    "qs_pg:name_adm1":"Canton de Neuch\u00e2tel",
    "qs_pg:photos_9k":1,
    "qs_pg:photos_9r":4,
    "qs_pg:photos_all":173,
    "qs_pg:photos_sr":0,
    "qs_pg:pop_sr":3,
    "qs_pg:qs_pg_placetype":"locality",
    "qs_pg:qs_pg_placetype_gp":"Town",
    "qs_pg:woe_adm0":23424957,
    "woe:adm0_id":23424957,
    "woe:name_adm0":"Schweiz",
    "woe:name_adm1":"Canton de Neuch\u00e2tel",
    "woe:placetype":"Town",
    "wof:name":"Fontainemelon",
    "wof:placetype":"locality",
    "wof:population":1647
},
  "geometry": {"coordinates":[6.8868,47.05495],"type":"Point"}
}