{
  "type": "Feature",
  "properties": {
    "gn:admin1_code":"GR",
    "gn:admin2_code":"1849.0",
    "gn:admin3_code":"3851.0",
    "gn:asciiname":"Unter-Laret",
    "gn:country_code":"CH",
    "gn:dem":1507,
    "gn:feature_class":"P",
    "gn:feature_code":"PPL",
    "gn:name":"Unter-Laret",
    "gn:population":0,
    "gn:timezone":"Europe/Zurich",
    "iso:country":"CH",
    "wof:name":"Unter-Laret",
    "wof:placetype":"neighbourhood"
},
  "geometry": {"coordinates":[9.86914,46.84221],"type":"Point"}
}