{
  "type": "Feature",
  "properties": {
    "gn:gn_country":"CH",
    "gn:gn_fcode":"PPL",
    "gn:gn_pop":327,
    "gn:population":327,
    "iso:country":"CH",
    "qs_pg:aaroncc":"CH",
    "qs_pg:gn_country":"CH",
    "qs_pg:gn_fcode":"PPL",
    "qs_pg:gn_pop":327,
    "qs_pg:name":"Charmoille",
    "qs_pg:name_adm0":"Schweiz",
    "qs_pg:name_adm1":"Canton de Jura",
    "qs_pg:photos_9k":1,
    "qs_pg:photos_9r":2,
    "qs_pg:photos_all":73,
    "qs_pg:photos_sr":0,
    "qs_pg:pop_sr":2,
    "qs_pg:qs_pg_placetype":"locality",
    "qs_pg:qs_pg_placetype_gp":"Town",
    "qs_pg:woe_adm0":23424957,
    "woe:adm0_id":23424957,
    "woe:name_adm0":"Schweiz",
    "woe:name_adm1":"Canton de Jura",
    "woe:placetype":"Town",
    "wof:name":"Charmoille",
    "wof:placetype":"locality",
    "wof:population":327
},
  "geometry": {"coordinates":[7.20757,47.42375],"type":"Point"}
}