{
  "type": "Feature",
  "properties": {
    "gn:admin1_code":"VD",
    "gn:admin2_code":"2224.0",
    "gn:admin3_code":"5872.0",
    "gn:asciiname":"Piece chez Marc",
    "gn:country_code":"CH",
    "gn:dem":1272,
    "gn:feature_class":"P",
    "gn:feature_code":"PPL",
    "gn:name":"Pi\u00e8ce chez Marc",
    "gn:population":0,
    "gn:timezone":"Europe/Zurich",
    "iso:country":"CH",
    "name:fra_x_preferred":[
        "Pi\u00e8ce chez Marc"
    ],
    "wof:name":"Piece chez Marc",
    "wof:placetype":"neighbourhood"
},
  "geometry": {"coordinates":[6.26466,46.60327],"type":"Point"}
}