{
  "type": "Feature",
  "properties": {
    "gn:admin1_code":"SZ",
    "gn:admin2_code":"505.0",
    "gn:admin3_code":"1345.0",
    "gn:asciiname":"Beier",
    "gn:country_code":"CH",
    "gn:dem":529,
    "gn:feature_class":"P",
    "gn:feature_code":"PPLL",
    "gn:name":"Beier",
    "gn:population":0,
    "gn:timezone":"Europe/Zurich",
    "iso:country":"CH",
    "name:deu_x_preferred":[
        "Beier"
    ],
    "wof:name":"Beier",
    "wof:placetype":"locality"
},
  "geometry": {"coordinates":[8.97743,47.16192],"type":"Point"}
}