{
  "type": "Feature",
  "properties": {
    "gn:country":"CH",
    "gn:fcode":"PPLX",
    "gn:population":264,
    "iso:country":"CH",
    "name:als_x_preferred":[
        "Dorf"
    ],
    "name:ceb_x_preferred":[
        "Dorf"
    ],
    "name:dan_x_preferred":[
        "Dorf"
    ],
    "name:deu_x_preferred":[
        "Dorf"
    ],
    "name:eng_x_preferred":[
        "Dorf"
    ],
    "name:eng_x_variant":[
        "Otelfingen / Dorf"
    ],
    "name:epo_x_preferred":[
        "Dorf"
    ],
    "name:fra_x_preferred":[
        "Dorf"
    ],
    "name:ita_x_preferred":[
        "Dorf"
    ],
    "name:pol_x_preferred":[
        "Dorf"
    ],
    "name:rus_x_preferred":[
        "\u0414\u043e\u0440\u0444"
    ],
    "name:swe_x_preferred":[
        "Dorf"
    ],
    "qs_pg:aaroncc":"CH",
    "qs_pg:gn_country":"CH",
    "qs_pg:gn_fcode":"PPLX",
    "qs_pg:gn_pop":264,
    "qs_pg:name":"Otelfingen / Dorf",
    "qs_pg:photos_9r":0,
    "qs_pg:photos_sr":0,
    "qs_pg:pop_sr":2,
    "qs_pg:qs_pg_placetype":"neighbourhood",
    "wof:name":"Dorf",
    "wof:placetype":"neighbourhood",
    "wof:population":264
},
  "geometry": {"coordinates":[8.38672,47.46167],"type":"Point"}
}