{
  "type": "Feature",
  "properties": {
    "gn:gn_country":"CH",
    "gn:gn_fcode":"PPLX",
    "gn:gn_pop":264,
    "gn:population":264,
    "iso:country":"CH",
    "name:eng_x_preferred":[
        "Dorf"
    ],
    "name:eng_x_variant":[
        "Otelfingen / Dorf"
    ],
    "name:unk_x_variant":[
        "Dorf"
    ],
    "qs_pg:aaroncc":"CH",
    "qs_pg:gn_country":"CH",
    "qs_pg:gn_fcode":"PPLX",
    "qs_pg:gn_pop":264,
    "qs_pg:name":"Otelfingen / Dorf",
    "qs_pg:photos_9r":0,
    "qs_pg:photos_sr":0,
    "qs_pg:pop_sr":2,
    "qs_pg:qs_pg_placetype":"neighbourhood",
    "wof:name":"Dorf",
    "wof:placetype":"neighbourhood",
    "wof:population":264
},
  "geometry": {"coordinates":[8.38672,47.46167],"type":"Point"}
}