{
  "type": "Feature",
  "properties": {
    "gn:admin1_code":"VD",
    "gn:admin2_code":"2227.0",
    "gn:admin3_code":"5492.0",
    "gn:asciiname":"Le Risel",
    "gn:country_code":"CH",
    "gn:dem":1473,
    "gn:feature_class":"P",
    "gn:feature_code":"PPL",
    "gn:name":"Le Risel",
    "gn:population":0,
    "gn:timezone":"Europe/Zurich",
    "iso:country":"CH",
    "name:fra_x_preferred":[
        "Le Risel"
    ],
    "wof:lang_x_official":[
        "deu",
        "fra",
        "gsw",
        "ita"
    ],
    "wof:lang_x_spoken":[
        "deu",
        "fra",
        "gsw",
        "ita",
        "roh"
    ],
    "wof:name":"Le Risel",
    "wof:placetype":"neighbourhood"
},
  "geometry": {"coordinates":[6.33992,46.61572],"type":"Point"}
}