{
  "type": "Feature",
  "properties": {
    "gn:gn_country":"CH",
    "gn:gn_fcode":"PPL",
    "gn:gn_pop":529,
    "gn:population":529,
    "iso:country":"CH",
    "name:deu_x_preferred":[
        "Hauteville FR"
    ],
    "name:eng_x_preferred":[
        "Hauteville"
    ],
    "name:epo_x_preferred":[
        "Hauteville FR"
    ],
    "name:fra_x_preferred":[
        "Hauteville"
    ],
    "name:hun_x_preferred":[
        "Hauteville"
    ],
    "name:ita_x_preferred":[
        "Hauteville"
    ],
    "name:lmo_x_preferred":[
        "Hauteville"
    ],
    "name:msa_x_preferred":[
        "Hauteville"
    ],
    "name:nld_x_preferred":[
        "Hauteville"
    ],
    "name:nno_x_preferred":[
        "Hauteville i Fribourg"
    ],
    "name:pms_x_preferred":[
        "Hauteville"
    ],
    "name:por_x_preferred":[
        "Altavila"
    ],
    "name:roh_x_preferred":[
        "Hauteville"
    ],
    "name:spa_x_preferred":[
        "Hauteville"
    ],
    "name:sqi_x_preferred":[
        "Hauteville"
    ],
    "name:swe_x_preferred":[
        "Hauteville"
    ],
    "name:vol_x_preferred":[
        "Hauteville"
    ],
    "name:war_x_preferred":[
        "Hauteville"
    ],
    "name:zho_x_preferred":[
        "\u5967\u7279\u7dad\u723e"
    ],
    "qs_pg:aaroncc":"CH",
    "qs_pg:gn_country":"CH",
    "qs_pg:gn_fcode":"PPL",
    "qs_pg:gn_pop":529,
    "qs_pg:name":"Hauteville",
    "qs_pg:name_adm0":"Schweiz",
    "qs_pg:name_adm1":"Canton de Vaud",
    "qs_pg:photos_9k":1,
    "qs_pg:photos_9r":4,
    "qs_pg:photos_all":163,
    "qs_pg:photos_sr":0,
    "qs_pg:pop_sr":2,
    "qs_pg:qs_pg_placetype":"locality",
    "qs_pg:qs_pg_placetype_gp":"Town",
    "qs_pg:woe_adm0":23424957,
    "woe:adm0_id":23424957,
    "woe:name_adm0":"Schweiz",
    "woe:name_adm1":"Canton de Vaud",
    "woe:placetype":"Town",
    "wof:name":"Hauteville",
    "wof:placetype":"locality",
    "wof:population":529
},
  "geometry": {"coordinates":[7.10774,46.67022],"type":"Point"}
}