{
  "type": "Feature",
  "properties": {
    "gn:admin1_code":"SZ",
    "gn:admin2_code":"506.0",
    "gn:admin3_code":"1362.0",
    "gn:asciiname":"Baendli",
    "gn:country_code":"CH",
    "gn:dem":647,
    "gn:feature_class":"P",
    "gn:feature_code":"PPLL",
    "gn:name":"B\u00e4ndli",
    "gn:population":0,
    "gn:timezone":"Europe/Zurich",
    "iso:country":"CH",
    "name:deu_x_preferred":[
        "B\u00e4ndli"
    ],
    "wof:name":"Baendli",
    "wof:placetype":"neighbourhood"
},
  "geometry": {"coordinates":[8.5456,47.0381],"type":"Point"}
}