{
  "type": "Feature",
  "properties": {
    "gn:admin1_code":"ZH",
    "gn:admin2_code":"101.0",
    "gn:admin3_code":"9.0",
    "gn:asciiname":"Flaedermus",
    "gn:country_code":"CH",
    "gn:dem":618,
    "gn:feature_class":"P",
    "gn:feature_code":"PPLL",
    "gn:name":"Fl\u00e4dermus",
    "gn:population":0,
    "gn:timezone":"Europe/Zurich",
    "iso:country":"CH",
    "name:deu_x_preferred":[
        "Fl\u00e4dermus"
    ],
    "wof:name":"Flaedermus",
    "wof:placetype":"locality"
},
  "geometry": {"coordinates":[8.4771,47.25706],"type":"Point"}
}