{
  "type": "Feature",
  "properties": {
    "gn:admin1_code":"TI",
    "gn:admin2_code":"2105.0",
    "gn:admin3_code":"5226.0",
    "gn:asciiname":"Sarino",
    "gn:country_code":"CH",
    "gn:dem":769,
    "gn:feature_class":"P",
    "gn:feature_code":"PPL",
    "gn:name":"Sarino",
    "gn:population":0,
    "gn:timezone":"Europe/Zurich",
    "iso:country":"CH",
    "name:ita_x_preferred":[
        "Sarino"
    ],
    "wof:name":"Sarino",
    "wof:placetype":"neighbourhood"
},
  "geometry": {"coordinates":[8.97676,46.07835],"type":"Point"}
}