{
  "type": "Feature",
  "properties": {
    "gn:gn_country":"CH",
    "gn:gn_fcode":"PPL",
    "gn:gn_pop":1458,
    "gn:population":1458,
    "iso:country":"CH",
    "name:cat_x_preferred":[
        "Les Geneveys-sur-Coffrane"
    ],
    "name:dut_x_preferred":[
        "Les Geneveys-sur-Coffrane"
    ],
    "name:eng_x_preferred":[
        "Les Geneveys-sur-Coffrane"
    ],
    "name:epo_x_preferred":[
        "Les Geneveys-sur-Coffrane"
    ],
    "name:fre_x_preferred":[
        "Les Geneveys-sur-Coffrane"
    ],
    "name:ger_x_preferred":[
        "Les Geneveys-sur-Coffrane"
    ],
    "name:gsw_x_preferred":[
        "Les Geneveys-sur-Coffrane"
    ],
    "name:hun_x_preferred":[
        "Les Geneveys-sur-Coffrane"
    ],
    "name:ita_x_preferred":[
        "Les Geneveys-sur-Coffrane"
    ],
    "name:lmo_x_preferred":[
        "Les Geneveys-sur-Coffrane"
    ],
    "name:may_x_preferred":[
        "Les Geneveys-sur-Coffrane"
    ],
    "name:nno_x_preferred":[
        "Les Geneveys-sur-Coffrane"
    ],
    "name:oci_x_preferred":[
        "Les Geneveys-sur-Coffrane"
    ],
    "name:spa_x_preferred":[
        "Les Geneveys-sur-Coffrane"
    ],
    "name:swe_x_preferred":[
        "Les Geneveys-sur-Coffrane"
    ],
    "name:vol_x_preferred":[
        "Les Geneveys-sur-Coffrane"
    ],
    "name:war_x_preferred":[
        "Les Geneveys-sur-Coffrane"
    ],
    "qs_pg:aaroncc":"CH",
    "qs_pg:gn_country":"CH",
    "qs_pg:gn_fcode":"PPL",
    "qs_pg:gn_pop":1458,
    "qs_pg:name":"Les Geneveys-sur-Coffrane",
    "qs_pg:name_adm0":"Schweiz",
    "qs_pg:name_adm1":"Canton de Neuch\u00e2tel",
    "qs_pg:photos":236,
    "qs_pg:photos_1k":48,
    "qs_pg:photos_9k":1,
    "qs_pg:photos_9r":4,
    "qs_pg:photos_all":236,
    "qs_pg:photos_sr":4,
    "qs_pg:pop_sr":3,
    "qs_pg:qs_pg_placetype":"locality",
    "qs_pg:qs_pg_placetype_gp":"Town",
    "qs_pg:woe_adm0":23424957,
    "woe:adm0_id":23424957,
    "woe:name_adm0":"Schweiz",
    "woe:name_adm1":"Canton de Neuch\u00e2tel",
    "woe:placetype":"Town",
    "wof:name":"Les Geneveys-sur-Coffrane",
    "wof:placetype":"locality",
    "wof:population":1458
},
  "geometry": {"coordinates":[6.85253,47.014],"type":"Point"}
}