{
  "type": "Feature",
  "properties": {
    "gn:gn_country":"CH",
    "gn:gn_fcode":"PPL",
    "gn:gn_pop":0,
    "iso:country":"CH",
    "name:bul_x_preferred":[
        "\u0425\u0443\u0440\u0434\u0435\u043d"
    ],
    "name:dut_x_preferred":[
        "Hurden"
    ],
    "name:eng_x_preferred":[
        "Hurden"
    ],
    "name:fre_x_preferred":[
        "Hurden"
    ],
    "name:ger_x_preferred":[
        "Hurden"
    ],
    "name:gre_x_preferred":[
        "\u03a7\u03ad\u03c1\u03bd\u03c4\u03b5\u03bd"
    ],
    "name:gsw_x_preferred":[
        "Hurde"
    ],
    "name:heb_x_preferred":[
        "\u05d4\u05d5\u05e8\u05d3\u05df"
    ],
    "name:pnb_x_preferred":[
        "\u06c1\u0631\u0688\u0646"
    ],
    "name:rus_x_preferred":[
        "\u0425\u0443\u0440\u0434\u0435\u043d"
    ],
    "name:swe_x_preferred":[
        "Hurden"
    ],
    "name:ukr_x_preferred":[
        "\u0425\u0443\u0440\u0434\u0435\u043d"
    ],
    "name:uzb_x_preferred":[
        "Hurden"
    ],
    "qs_pg:aaroncc":"CH",
    "qs_pg:gn_country":"CH",
    "qs_pg:gn_fcode":"PPL",
    "qs_pg:gn_pop":0,
    "qs_pg:name":"Hurden",
    "qs_pg:name_adm0":"Schweiz",
    "qs_pg:name_adm1":"Kanton Schwyz",
    "qs_pg:photos":43,
    "qs_pg:photos_1k":9,
    "qs_pg:photos_9k":1,
    "qs_pg:photos_9r":2,
    "qs_pg:photos_all":43,
    "qs_pg:photos_sr":2,
    "qs_pg:pop_sr":0,
    "qs_pg:qs_pg_placetype":"locality",
    "qs_pg:qs_pg_placetype_gp":"Town",
    "qs_pg:woe_adm0":23424957,
    "woe:adm0_id":23424957,
    "woe:name_adm0":"Schweiz",
    "woe:name_adm1":"Kanton Schwyz",
    "woe:placetype":"Town",
    "wof:name":"Hurden",
    "wof:placetype":"locality"
},
  "geometry": {"coordinates":[8.80403,47.21378],"type":"Point"}
}