{
  "type": "Feature",
  "properties": {
    "gn:country":"CH",
    "gn:fcode":"PPLL",
    "gn:population":9,
    "iso:country":"CH",
    "name:eng_x_preferred":[
        "Brugglen"
    ],
    "name:eng_x_variant":[
        "Volketswil / Brugglen"
    ],
    "qs_pg:aaroncc":"CH",
    "qs_pg:gn_country":"CH",
    "qs_pg:gn_fcode":"PPLL",
    "qs_pg:gn_pop":9,
    "qs_pg:name":"Volketswil / Brugglen",
    "qs_pg:photos_9r":0,
    "qs_pg:photos_sr":0,
    "qs_pg:pop_sr":1,
    "qs_pg:qs_pg_placetype":"locality",
    "wof:name":"Brugglen",
    "wof:placetype":"neighbourhood",
    "wof:population":9
},
  "geometry": {"coordinates":[8.69507,47.39703],"type":"Point"}
}