{
  "type": "Feature",
  "properties": {
    "gn:admin1_code":"NE",
    "gn:admin2_code":"2404.0",
    "gn:admin3_code":"6451.0",
    "gn:asciiname":"Thielle",
    "gn:country_code":"CH",
    "gn:dem":435,
    "gn:feature_class":"P",
    "gn:feature_code":"PPL",
    "gn:name":"Thielle",
    "gn:population":0,
    "gn:timezone":"Europe/Zurich",
    "iso:country":"CH",
    "name:fra_x_preferred":[
        "Thielle-Wavre"
    ],
    "wof:name":"Thielle",
    "wof:placetype":"locality"
},
  "geometry": {"coordinates":[7.02921,47.02154],"type":"Point"}
}