{
  "type": "Feature",
  "properties": {
    "gn:admin1_code":"AR",
    "gn:admin2_code":"1503.0",
    "gn:admin3_code":"3037.0",
    "gn:asciiname":"Lachen",
    "gn:country_code":"CH",
    "gn:dem":832,
    "gn:elevation":"849.0",
    "gn:feature_class":"P",
    "gn:feature_code":"PPL",
    "gn:name":"Lachen",
    "gn:population":0,
    "gn:timezone":"Europe/Zurich",
    "iso:country":"CH",
    "name:als_x_preferred":[
        "Lachen"
    ],
    "name:ceb_x_preferred":[
        "Lachen"
    ],
    "name:ces_x_preferred":[
        "Lachen"
    ],
    "name:deu_x_preferred":[
        "Lachen"
    ],
    "name:epo_x_preferred":[
        "Lachen"
    ],
    "name:eus_x_preferred":[
        "Lachen"
    ],
    "name:fra_x_preferred":[
        "Lachen"
    ],
    "name:ita_x_preferred":[
        "Lachen"
    ],
    "name:nld_x_preferred":[
        "Lachen"
    ],
    "name:pol_x_preferred":[
        "Lachen"
    ],
    "name:swe_x_preferred":[
        "Lachen"
    ],
    "name:vol_x_preferred":[
        "Lachen"
    ],
    "wof:name":"Lachen",
    "wof:placetype":"neighbourhood"
},
  "geometry": {"coordinates":[9.58479,47.44245],"type":"Point"}
}