{
  "type": "Feature",
  "properties": {
    "gn:admin1_code":"GR",
    "gn:admin2_code":"1851.0",
    "gn:admin3_code":"3681.0",
    "gn:asciiname":"Puert",
    "gn:country_code":"CH",
    "gn:dem":1927,
    "gn:feature_class":"P",
    "gn:feature_code":"PPL",
    "gn:name":"P\u00fcrt",
    "gn:population":0,
    "gn:timezone":"Europe/Zurich",
    "iso:country":"CH",
    "name:deu_x_preferred":[
        "P\u00fcrt"
    ],
    "wof:name":"Puert",
    "wof:placetype":"neighbourhood"
},
  "geometry": {"coordinates":[9.52568,46.46505],"type":"Point"}
}