{
  "type": "Feature",
  "properties": {
    "gn:admin1_code":"BE",
    "gn:admin2_code":"249.0",
    "gn:admin3_code":"763.0",
    "gn:asciiname":"Ringoldingen",
    "gn:country_code":"CH",
    "gn:dem":753,
    "gn:feature_class":"P",
    "gn:feature_code":"PPL",
    "gn:name":"Ringoldingen",
    "gn:population":0,
    "gn:timezone":"Europe/Zurich",
    "iso:country":"CH",
    "wof:name":"Ringoldingen",
    "wof:placetype":"locality"
},
  "geometry": {"coordinates":[7.52483,46.65971],"type":"Point"}
}