{
  "type": "Feature",
  "properties": {
    "gn:admin1_code":"VD",
    "gn:admin2_code":"2230.0",
    "gn:admin3_code":"5841.0",
    "gn:asciiname":"Ciernes-Picat",
    "gn:country_code":"CH",
    "gn:dem":1156,
    "gn:feature_class":"P",
    "gn:feature_code":"PPL",
    "gn:name":"Ciernes-Picat",
    "gn:population":0,
    "gn:timezone":"Europe/Zurich",
    "iso:country":"CH",
    "name:und_x_variant":[
        "Les Siernes-Picats",
        "Siernes Picats",
        "Ciernes-Picat"
    ],
    "wof:name":"Ciernes-Picat",
    "wof:placetype":"neighbourhood"
},
  "geometry": {"coordinates":[7.17031,46.50529],"type":"Point"}
}