{
  "type": "Feature",
  "properties": {
    "gn:admin1_code":"ZH",
    "gn:admin2_code":"102.0",
    "gn:admin3_code":"36.0",
    "gn:asciiname":"OElenberg",
    "gn:country_code":"CH",
    "gn:dem":473,
    "gn:feature_class":"P",
    "gn:feature_code":"PPLL",
    "gn:name":"\u00d6lenberg",
    "gn:population":0,
    "gn:timezone":"Europe/Zurich",
    "iso:country":"CH",
    "name:deu_x_preferred":[
        "\u00d6lenberg"
    ],
    "wof:name":"OElenberg",
    "wof:placetype":"locality"
},
  "geometry": {"coordinates":[8.80925,47.62965],"type":"Point"}
}