{
  "type": "Feature",
  "properties": {
    "gn:admin1_code":"TI",
    "gn:admin2_code":"2105.0",
    "gn:admin3_code":"5192.0",
    "gn:asciiname":"Marseta",
    "gn:country_code":"CH",
    "gn:dem":1044,
    "gn:feature_class":"P",
    "gn:feature_code":"PPL",
    "gn:name":"Mars\u00e8ta",
    "gn:population":0,
    "gn:timezone":"Europe/Zurich",
    "iso:country":"CH",
    "name:ita_x_preferred":[
        "Mars\u00e8ta"
    ],
    "wof:name":"Marseta",
    "wof:placetype":"neighbourhood"
},
  "geometry": {"coordinates":[9.02864,46.08936],"type":"Point"}
}