{
  "type": "Feature",
  "properties": {
    "gn:population":7553,
    "iso:country":"CH",
    "name:alb_x_preferred":[
        "Oberentfelden"
    ],
    "name:baq_x_preferred":[
        "Oberentfelden"
    ],
    "name:cat_x_preferred":[
        "Oberentfelden"
    ],
    "name:ceb_x_preferred":[
        "Oberentfelden"
    ],
    "name:chi_x_preferred":[
        "\u4e0a\u6069\u7279\u8cbb\u723e\u767b"
    ],
    "name:deu_x_preferred":[
        "Oberentfelden"
    ],
    "name:dut_x_preferred":[
        "Oberentfelden"
    ],
    "name:eng_x_preferred":[
        "Entfelden"
    ],
    "name:epo_x_preferred":[
        "Oberentfelden"
    ],
    "name:eus_x_preferred":[
        "Oberentfelden"
    ],
    "name:fra_x_preferred":[
        "Oberentfelden"
    ],
    "name:fre_x_preferred":[
        "Oberentfelden"
    ],
    "name:ger_x_preferred":[
        "Oberentfelden"
    ],
    "name:hun_x_preferred":[
        "Oberentfelden"
    ],
    "name:ita_x_preferred":[
        "Oberentfelden"
    ],
    "name:kaz_x_preferred":[
        "\u041e\u0431\u0435\u0440\u0435\u043d\u0442\u0444\u0435\u043b\u044c\u0434\u0435\u043d"
    ],
    "name:lmo_x_preferred":[
        "Oberentfelden"
    ],
    "name:may_x_preferred":[
        "Oberentfelden"
    ],
    "name:msa_x_preferred":[
        "Oberentfelden"
    ],
    "name:nld_x_preferred":[
        "Oberentfelden"
    ],
    "name:nno_x_preferred":[
        "Oberentfelden"
    ],
    "name:oci_x_preferred":[
        "Oberentfelden"
    ],
    "name:pms_x_preferred":[
        "Oberentfelden"
    ],
    "name:pol_x_preferred":[
        "Oberentfelden"
    ],
    "name:por_x_preferred":[
        "Oberentfelden"
    ],
    "name:roh_x_preferred":[
        "Oberentfelden"
    ],
    "name:rus_x_preferred":[
        "\u041e\u0431\u0435\u0440\u0435\u043d\u0442\u0444\u0435\u043b\u044c\u0434\u0435\u043d"
    ],
    "name:spa_x_preferred":[
        "Oberentfelden"
    ],
    "name:sqi_x_preferred":[
        "Oberentfelden"
    ],
    "name:swe_x_preferred":[
        "Oberentfelden"
    ],
    "name:unk_x_variant":[
        "Entfelden"
    ],
    "name:uzb_x_preferred":[
        "Oberentfelden"
    ],
    "name:vol_x_preferred":[
        "Oberentfelden"
    ],
    "name:war_x_preferred":[
        "Oberentfelden"
    ],
    "name:zho_x_preferred":[
        "\u4e0a\u6069\u7279\u8cbb\u723e\u767b"
    ],
    "qs:a0":"Schweiz#Suisse#Svizzera#Svizra",
    "qs:a1":"*Aargau",
    "qs:a1r":"0",
    "qs:adm0":"Schweiz#Suisse#Svizzera#Svizra",
    "qs:la_lc":"*",
    "qs:level":"locality",
    "qs:loc":"Oberentfelden",
    "qs:loc_alt":"Oberentfelden",
    "qs:pop":0,
    "qs:type":"buffered point",
    "wd:wordcount":896,
    "wof:lang":[
        "ger"
    ],
    "wof:name":"Oberentfelden",
    "wof:placetype":"locality",
    "wof:population":7553
},
  "geometry": {"coordinates":[8.046238,47.356693],"type":"Point"}
}