{
  "type": "Feature",
  "properties": {
    "gn:admin1_code":"TI",
    "gn:admin2_code":"2104.0",
    "gn:admin3_code":"5398.0",
    "gn:asciiname":"Pezze",
    "gn:country_code":"CH",
    "gn:dem":1030,
    "gn:feature_class":"P",
    "gn:feature_code":"PPL",
    "gn:name":"Pezze",
    "gn:population":0,
    "gn:timezone":"Europe/Zurich",
    "iso:country":"CH",
    "name:ita_x_preferred":[
        "Pezze"
    ],
    "wof:name":"Pezze",
    "wof:placetype":"neighbourhood"
},
  "geometry": {"coordinates":[8.8315,46.09867],"type":"Point"}
}