{
  "type": "Feature",
  "properties": {
    "iso:country":"CH",
    "wof:name":"Rues-Basses",
    "wof:placetype":"neighbourhood"
},
  "geometry": {"coordinates":[6.14915746236633,46.2035322742205],"type":"Point"}
}