{
  "type": "Feature",
  "properties": {
    "gn:admin1_code":"FR",
    "gn:admin2_code":"1001.0",
    "gn:admin3_code":"2050.0",
    "gn:asciiname":"Frasses",
    "gn:country_code":"CH",
    "gn:dem":484,
    "gn:elevation":"482.0",
    "gn:feature_class":"P",
    "gn:feature_code":"PPL",
    "gn:name":"Frasses",
    "gn:population":0,
    "gn:timezone":"Europe/Zurich",
    "iso:country":"CH",
    "wof:name":"Frasses",
    "wof:placetype":"locality"
},
  "geometry": {"coordinates":[6.86442,46.82817],"type":"Point"}
}