{
  "type": "Feature",
  "properties": {
    "gn:country":"CH",
    "gn:fcode":"PPLX",
    "gn:population":895,
    "iso:country":"CH",
    "name:eng_x_preferred":[
        "Fadmatt"
    ],
    "name:eng_x_variant":[
        "Urdorf / Fadmatt"
    ],
    "qs_pg:aaroncc":"CH",
    "qs_pg:gn_country":"CH",
    "qs_pg:gn_fcode":"PPLX",
    "qs_pg:gn_pop":895,
    "qs_pg:name":"Urdorf / Fadmatt",
    "qs_pg:photos_9r":0,
    "qs_pg:photos_sr":0,
    "qs_pg:pop_sr":2,
    "qs_pg:qs_pg_placetype":"neighbourhood",
    "wof:name":"Fadmatt",
    "wof:placetype":"neighbourhood",
    "wof:population":895
},
  "geometry": {"coordinates":[8.42845,47.3821],"type":"Point"}
}