{
  "type": "Feature",
  "properties": {
    "gn:admin1_code":"UR",
    "gn:admin2_code":"400.0",
    "gn:admin3_code":"1217.0",
    "gn:asciiname":"Stock",
    "gn:country_code":"CH",
    "gn:dem":1706,
    "gn:feature_class":"P",
    "gn:feature_code":"PPL",
    "gn:name":"Stock",
    "gn:population":0,
    "gn:timezone":"Europe/Zurich",
    "iso:country":"CH",
    "wof:name":"Stock",
    "wof:placetype":"neighbourhood"
},
  "geometry": {"coordinates":[8.64839,46.93409000000001],"type":"Point"}
}