{
  "type": "Feature",
  "properties": {
    "gn:admin1_code":"UR",
    "gn:admin2_code":"400.0",
    "gn:admin3_code":"1217.0",
    "gn:asciiname":"Stock",
    "gn:country_code":"CH",
    "gn:dem":1706,
    "gn:feature_class":"P",
    "gn:feature_code":"PPL",
    "gn:name":"Stock",
    "gn:population":0,
    "gn:timezone":"Europe/Zurich",
    "iso:country":"CH",
    "name:ara_x_preferred":[
        "\u0633\u0647\u0645"
    ],
    "name:cdo_x_preferred":[
        "G\u016b-pi\u00e9u"
    ],
    "name:fas_x_preferred":[
        "\u0633\u0647\u0627\u0645 \u0633\u0631\u0645\u0627\u06cc\u0647"
    ],
    "name:hin_x_preferred":[
        "\u0938\u094d\u091f\u0949\u0915"
    ],
    "name:ido_x_preferred":[
        "Stoko"
    ],
    "name:isl_x_preferred":[
        "Hlutabr\u00e9f"
    ],
    "name:kan_x_preferred":[
        "\u0cb8\u0ccd\u0c9f\u0cbe\u0c95\u0cc1"
    ],
    "name:mya_x_preferred":[
        "\u1005\u1010\u1031\u102c\u1037\u1001\u103a"
    ],
    "name:pus_x_preferred":[
        "\u0648\u0646\u0689\u0647"
    ],
    "name:tam_x_preferred":[
        "\u0bae\u0bc2\u0bb2\u0ba4\u0ba9\u0baa\u0bcd \u0baa\u0b99\u0bcd\u0b95\u0bc1"
    ],
    "name:tha_x_preferred":[
        "\u0e2b\u0e38\u0e49\u0e19"
    ],
    "name:tur_x_preferred":[
        "Stok"
    ],
    "name:urd_x_preferred":[
        "\u0633\u0679\u0627\u06a9"
    ],
    "name:vie_x_preferred":[
        "C\u1ed5 phi\u1ebfu"
    ],
    "name:yid_x_preferred":[
        "\u05e1\u05d8\u05d0\u05e7\u05e1"
    ],
    "wof:lang_x_official":[
        "deu",
        "fra",
        "gsw",
        "ita"
    ],
    "wof:lang_x_spoken":[
        "deu",
        "fra",
        "gsw",
        "ita",
        "roh"
    ],
    "wof:name":"Stock",
    "wof:placetype":"neighbourhood"
},
  "geometry": {"coordinates":[8.64839,46.93409],"type":"Point"}
}