{
  "type": "Feature",
  "properties": {
    "gn:gn_country":"CH",
    "gn:gn_fcode":"PPL",
    "gn:gn_pop":1209,
    "gn:population":1209,
    "iso:country":"CH",
    "name:deu_x_preferred":[
        "Pal\u00e9zieux"
    ],
    "name:eng_x_preferred":[
        "Pal\u00e9zieux"
    ],
    "name:fra_x_preferred":[
        "Pal\u00e9zieux"
    ],
    "name:frp_x_preferred":[
        "Pal\u00e8zi\u0153x"
    ],
    "name:hun_x_preferred":[
        "Pal\u00e9zieux"
    ],
    "name:ita_x_preferred":[
        "Pal\u00e9zieux"
    ],
    "name:lmo_x_preferred":[
        "Pal\u00e9zieux"
    ],
    "name:msa_x_preferred":[
        "Pal\u00e9zieux"
    ],
    "name:nld_x_preferred":[
        "Pal\u00e9zieux"
    ],
    "name:roh_x_preferred":[
        "Pal\u00e9zieux"
    ],
    "name:spa_x_preferred":[
        "Pal\u00e9zieux"
    ],
    "name:swe_x_preferred":[
        "Pal\u00e9zieux"
    ],
    "name:vec_x_preferred":[
        "Pal\u00e9zieux"
    ],
    "name:vol_x_preferred":[
        "Pal\u00e9zieux"
    ],
    "name:war_x_preferred":[
        "Pal\u00e9zieux"
    ],
    "qs_pg:aaroncc":"CH",
    "qs_pg:gn_country":"CH",
    "qs_pg:gn_fcode":"PPL",
    "qs_pg:gn_pop":1209,
    "qs_pg:name":"Pal\u00e9zieux",
    "qs_pg:name_adm0":"Schweiz",
    "qs_pg:name_adm1":"Canton de Vaud",
    "qs_pg:photos_9k":1,
    "qs_pg:photos_9r":1,
    "qs_pg:photos_all":1,
    "qs_pg:photos_sr":0,
    "qs_pg:pop_sr":3,
    "qs_pg:qs_pg_placetype":"locality",
    "qs_pg:qs_pg_placetype_gp":"Town",
    "qs_pg:woe_adm0":23424957,
    "woe:adm0_id":23424957,
    "woe:name_adm0":"Schweiz",
    "woe:name_adm1":"Canton de Vaud",
    "woe:placetype":"Town",
    "wof:name":"Pal\u00e9zieux",
    "wof:placetype":"locality",
    "wof:population":1209
},
  "geometry": {"coordinates":[6.8325,46.54543],"type":"Point"}
}