{
  "type": "Feature",
  "properties": {
    "gn:admin1_code":"TI",
    "gn:admin2_code":"2105.0",
    "gn:admin3_code":"5161.0",
    "gn:asciiname":"Lisone",
    "gn:country_code":"CH",
    "gn:dem":833,
    "gn:feature_class":"P",
    "gn:feature_code":"PPL",
    "gn:name":"Lisone",
    "gn:population":0,
    "gn:timezone":"Europe/Zurich",
    "iso:country":"CH",
    "wof:name":"Lisone",
    "wof:placetype":"neighbourhood"
},
  "geometry": {"coordinates":[8.88356,46.02354],"type":"Point"}
}