{
  "type": "Feature",
  "properties": {
    "gn:admin1_code":"SG",
    "gn:admin2_code":"1721.0",
    "gn:admin3_code":"3444.0",
    "gn:asciiname":"Moelbach",
    "gn:country_code":"CH",
    "gn:dem":636,
    "gn:feature_class":"P",
    "gn:feature_code":"PPLL",
    "gn:name":"M\u00f6lbach",
    "gn:population":0,
    "gn:timezone":"Europe/Zurich",
    "iso:country":"CH",
    "name:deu_x_preferred":[
        "M\u00f6lbach"
    ],
    "wof:name":"Moelbach",
    "wof:placetype":"locality"
},
  "geometry": {"coordinates":[9.27052,47.45992],"type":"Point"}
}