{
  "type": "Feature",
  "properties": {
    "iso:country":"CH",
    "wof:name":"Les Franchises",
    "wof:placetype":"neighbourhood"
},
  "geometry": {"coordinates":[6.11791507604121,46.21174912109677],"type":"Point"}
}