{
  "type": "Feature",
  "properties": {
    "gn:admin1_code":"VD",
    "gn:admin2_code":"2224.0",
    "gn:admin3_code":"5872.0",
    "gn:asciiname":"Le Grand Croset Dessous",
    "gn:country_code":"CH",
    "gn:dem":1321,
    "gn:feature_class":"P",
    "gn:feature_code":"PPL",
    "gn:name":"Le Grand Croset Dessous",
    "gn:population":0,
    "gn:timezone":"Europe/Zurich",
    "iso:country":"CH",
    "name:fra_x_preferred":[
        "Le Grand Croset Dessous"
    ],
    "wof:name":"Le Grand Croset Dessous",
    "wof:placetype":"locality"
},
  "geometry": {"coordinates":[6.26982,46.58968],"type":"Point"}
}