{
  "type": "Feature",
  "properties": {
    "gn:admin1_code":"VD",
    "gn:admin2_code":"2223.0",
    "gn:admin3_code":"5473.0",
    "gn:asciiname":"Boussens",
    "gn:country_code":"CH",
    "gn:dem":587,
    "gn:feature_class":"P",
    "gn:feature_code":"PPL",
    "gn:name":"Boussens",
    "gn:population":0,
    "gn:timezone":"Europe/Zurich",
    "iso:country":"CH",
    "name:als_x_preferred":[
        "Boussens VD"
    ],
    "name:deu_x_preferred":[
        "Boussens VD"
    ],
    "name:epo_x_preferred":[
        "Boussens VD"
    ],
    "name:nno_x_preferred":[
        "Boussens i Sveits"
    ],
    "name:zho_x_preferred":[
        "\u5e03\u6851"
    ],
    "wof:name":"Boussens",
    "wof:placetype":"locality"
},
  "geometry": {"coordinates":[6.58596,46.6035],"type":"Point"}
}