{
  "type": "Feature",
  "properties": {
    "gn:gn_country":"CH",
    "gn:gn_fcode":"PPL",
    "gn:gn_pop":950,
    "gn:population":950,
    "iso:country":"CH",
    "name:cat_x_preferred":[
        "Dietwil"
    ],
    "name:deu_x_preferred":[
        "Dietwil"
    ],
    "name:eng_x_preferred":[
        "Dietwil"
    ],
    "name:epo_x_preferred":[
        "Dietwil"
    ],
    "name:eus_x_preferred":[
        "Dietwil"
    ],
    "name:fra_x_preferred":[
        "Dietwil"
    ],
    "name:gsw_x_preferred":[
        "Dietel"
    ],
    "name:hun_x_preferred":[
        "Dietwil"
    ],
    "name:ita_x_preferred":[
        "Dietwil"
    ],
    "name:kaz_x_preferred":[
        "\u0414\u0438\u0442\u0432\u0438\u043b\u044c"
    ],
    "name:lmo_x_preferred":[
        "Dietwil"
    ],
    "name:msa_x_preferred":[
        "Dietwil"
    ],
    "name:nld_x_preferred":[
        "Dietwil"
    ],
    "name:nno_x_preferred":[
        "Dietwil"
    ],
    "name:oci_x_preferred":[
        "Dietwil"
    ],
    "name:pms_x_preferred":[
        "Dietwil"
    ],
    "name:por_x_preferred":[
        "Dietwil"
    ],
    "name:rus_x_preferred":[
        "\u0414\u0438\u0442\u0432\u0438\u043b\u044c"
    ],
    "name:spa_x_preferred":[
        "Dietwil"
    ],
    "name:sqi_x_preferred":[
        "Dietwil"
    ],
    "name:swe_x_preferred":[
        "Dietwil"
    ],
    "name:uzb_x_preferred":[
        "Dietwil"
    ],
    "name:vie_x_preferred":[
        "Dietwil"
    ],
    "name:vol_x_preferred":[
        "Dietwil"
    ],
    "name:war_x_preferred":[
        "Dietwil"
    ],
    "name:zho_x_preferred":[
        "\u8fea\u7279\u7dad\u723e"
    ],
    "qs_pg:aaroncc":"CH",
    "qs_pg:gn_country":"CH",
    "qs_pg:gn_fcode":"PPL",
    "qs_pg:gn_pop":950,
    "qs_pg:name":"Dingetswil",
    "qs_pg:name_adm0":"Schweiz",
    "qs_pg:name_adm1":"Kanton Thurgau",
    "qs_pg:photos_9r":0,
    "qs_pg:photos_sr":0,
    "qs_pg:pop_sr":2,
    "qs_pg:qs_pg_placetype":"locality",
    "qs_pg:qs_pg_placetype_gp":"Town",
    "qs_pg:woe_adm0":23424957,
    "woe:adm0_id":23424957,
    "woe:name_adm0":"Schweiz",
    "woe:name_adm1":"Kanton Thurgau",
    "woe:placetype":"Town",
    "wof:name":"Dingetswil",
    "wof:placetype":"locality",
    "wof:population":950
},
  "geometry": {"coordinates":[8.39355,47.14665],"type":"Point"}
}