{
  "type": "Feature",
  "properties": {
    "iso:country":"CH",
    "name:deu_x_preferred":[
        "Schwarzwaldalp"
    ],
    "name:eng_x_preferred":[
        "Schwarzwaldalp"
    ],
    "name:nld_x_preferred":[
        "Schwarzwaldalp"
    ],
    "qs_pg:aaroncc":"CH",
    "qs_pg:name":"Schwarzwaldalp",
    "qs_pg:name_adm0":"Schweiz",
    "qs_pg:name_adm1":"Kanton Bern",
    "qs_pg:photos":55,
    "qs_pg:photos_1k":11,
    "qs_pg:photos_9k":1,
    "qs_pg:photos_9r":2,
    "qs_pg:photos_all":55,
    "qs_pg:photos_sr":2,
    "qs_pg:pop_sr":0,
    "qs_pg:qs_pg_placetype":"locality",
    "qs_pg:qs_pg_placetype_gp":"Town",
    "qs_pg:woe_adm0":23424957,
    "woe:adm0_id":23424957,
    "woe:name_adm0":"Schweiz",
    "woe:name_adm1":"Kanton Bern",
    "woe:placetype":"Town",
    "wof:name":"Schwarzwaldalp",
    "wof:placetype":"neighbourhood"
},
  "geometry": {"coordinates":[8.134174,46.675001],"type":"Point"}
}