{
  "type": "Feature",
  "properties": {
    "gn:admin1_code":"LU",
    "gn:admin2_code":"315.0",
    "gn:admin3_code":"1143.0",
    "gn:asciiname":"Neuhaus",
    "gn:country_code":"CH",
    "gn:dem":709,
    "gn:feature_class":"P",
    "gn:feature_code":"PPLL",
    "gn:name":"Neuhaus",
    "gn:population":0,
    "gn:timezone":"Europe/Zurich",
    "iso:country":"CH",
    "name:deu_x_preferred":[
        "Neuhaus"
    ],
    "wof:name":"Neuhaus",
    "wof:placetype":"neighbourhood"
},
  "geometry": {"coordinates":[7.94086,47.1602],"type":"Point"}
}