{
  "type": "Feature",
  "properties": {
    "gn:admin1_code":"LU",
    "gn:admin2_code":"315.0",
    "gn:admin3_code":"1143.0",
    "gn:asciiname":"Neuhaus",
    "gn:country_code":"CH",
    "gn:dem":709,
    "gn:feature_class":"P",
    "gn:feature_code":"PPLL",
    "gn:name":"Neuhaus",
    "gn:population":0,
    "gn:timezone":"Europe/Zurich",
    "iso:country":"CH",
    "name:ceb_x_preferred":[
        "Neuhaus"
    ],
    "name:ces_x_preferred":[
        "Neuhaus"
    ],
    "name:deu_x_preferred":[
        "Neuhaus"
    ],
    "name:epo_x_preferred":[
        "Neuhaus"
    ],
    "name:fin_x_preferred":[
        "Neuhaus"
    ],
    "name:fra_x_preferred":[
        "Neuhaus"
    ],
    "name:hun_x_preferred":[
        "Neuhaus"
    ],
    "name:ita_x_preferred":[
        "Neuhaus"
    ],
    "name:jpn_x_preferred":[
        "\u30cd\u30a4\u30ac\u30a6\u30b9"
    ],
    "name:nld_x_preferred":[
        "Neuhaus"
    ],
    "name:nor_x_preferred":[
        "Neuhaus"
    ],
    "name:pol_x_preferred":[
        "Neuhaus"
    ],
    "name:ron_x_preferred":[
        "Neuhaus"
    ],
    "name:rus_x_preferred":[
        "\u041d\u043e\u0439\u0445\u0430\u0443\u0441"
    ],
    "name:swe_x_preferred":[
        "Neuhaus"
    ],
    "name:vol_x_preferred":[
        "Neuhaus"
    ],
    "wof:name":"Neuhaus",
    "wof:placetype":"neighbourhood"
},
  "geometry": {"coordinates":[7.94086,47.1602],"type":"Point"}
}