{
  "type": "Feature",
  "properties": {
    "iso:country":"CH",
    "name:deu_x_preferred":[
        "Pagig"
    ],
    "name:eng_x_preferred":[
        "Pagig"
    ],
    "name:fra_x_preferred":[
        "Pagig"
    ],
    "name:ita_x_preferred":[
        "Pagig"
    ],
    "name:nld_x_preferred":[
        "Pagig"
    ],
    "name:pms_x_preferred":[
        "Pagig"
    ],
    "name:por_x_preferred":[
        "Pagig"
    ],
    "name:roh_x_preferred":[
        "Pagig"
    ],
    "name:rus_x_preferred":[
        "\u041f\u0430\u0433\u0438\u0433"
    ],
    "name:spa_x_preferred":[
        "Pagig"
    ],
    "name:swe_x_preferred":[
        "Pagig"
    ],
    "name:uzb_x_preferred":[
        "Pagig"
    ],
    "name:vol_x_preferred":[
        "Pagig"
    ],
    "qs_pg:aaroncc":"CH",
    "qs_pg:name":"Pagig",
    "qs_pg:name_adm0":"Schweiz",
    "qs_pg:name_adm1":"Kanton Graub\u00fcnden",
    "qs_pg:photos":7,
    "qs_pg:photos_1k":1,
    "qs_pg:photos_9k":1,
    "qs_pg:photos_9r":1,
    "qs_pg:photos_all":7,
    "qs_pg:photos_sr":1,
    "qs_pg:pop_sr":0,
    "qs_pg:qs_pg_placetype":"locality",
    "qs_pg:qs_pg_placetype_gp":"Town",
    "qs_pg:woe_adm0":23424957,
    "woe:adm0_id":23424957,
    "woe:name_adm0":"Schweiz",
    "woe:name_adm1":"Kanton Graub\u00fcnden",
    "woe:placetype":"Town",
    "wof:name":"Pagig",
    "wof:placetype":"locality"
},
  "geometry": {"coordinates":[9.630718,46.828724],"type":"Point"}
}