{
  "type": "Feature",
  "properties": {
    "gn:admin1_code":"TG",
    "gn:admin2_code":"2012.0",
    "gn:admin3_code":"4546.0",
    "gn:asciiname":"Held",
    "gn:country_code":"CH",
    "gn:dem":407,
    "gn:feature_class":"P",
    "gn:feature_code":"PPLL",
    "gn:name":"Held",
    "gn:population":0,
    "gn:timezone":"Europe/Zurich",
    "iso:country":"CH",
    "name:cat_x_preferred":[
        "Held"
    ],
    "name:ces_x_preferred":[
        "Held"
    ],
    "name:deu_x_preferred":[
        "Held"
    ],
    "name:fra_x_preferred":[
        "Held"
    ],
    "name:ita_x_preferred":[
        "Held"
    ],
    "name:pol_x_preferred":[
        "Held"
    ],
    "name:rus_x_preferred":[
        "\u0425\u0435\u043b\u044c\u0434"
    ],
    "wof:name":"Held",
    "wof:placetype":"neighbourhood"
},
  "geometry": {"coordinates":[8.69478,47.67308],"type":"Point"}
}