{
  "type": "Feature",
  "properties": {
    "iso:country":"CH",
    "name:deu_x_preferred":[
        "T\u00fcscherz-Alferm\u00e9e"
    ],
    "name:eng_x_preferred":[
        "T\u00fcscherz-Alferm\u00e9e"
    ],
    "name:fra_x_preferred":[
        "Daucher-Alferm\u00e9e"
    ],
    "name:ita_x_preferred":[
        "T\u00fcscherz-Alferm\u00e9e"
    ],
    "name:nld_x_preferred":[
        "T\u00fcscherz-Alferm\u00e9e"
    ],
    "name:scn_x_preferred":[
        "T\u00fcscherz"
    ],
    "name:spa_x_preferred":[
        "T\u00fcscherz-Alferm\u00e9e"
    ],
    "name:swe_x_preferred":[
        "T\u00fcscherz-Alferm\u00e9e"
    ],
    "name:vol_x_preferred":[
        "T\u00fcscherz-Alferm\u00e9e"
    ],
    "qs_pg:aaroncc":"CH",
    "qs_pg:name":"T\u00fcscherz-Alferm\u00e9e",
    "qs_pg:name_adm0":"Schweiz",
    "qs_pg:name_adm1":"Kanton Bern",
    "qs_pg:photos":186,
    "qs_pg:photos_1k":38,
    "qs_pg:photos_9k":1,
    "qs_pg:photos_9r":4,
    "qs_pg:photos_all":186,
    "qs_pg:photos_sr":4,
    "qs_pg:pop_sr":0,
    "qs_pg:qs_pg_placetype":"locality",
    "qs_pg:qs_pg_placetype_gp":"Town",
    "qs_pg:woe_adm0":23424957,
    "woe:adm0_id":23424957,
    "woe:name_adm0":"Schweiz",
    "woe:name_adm1":"Kanton Bern",
    "woe:placetype":"Town",
    "wof:name":"T\u00fcscherz-Alferm\u00e9e",
    "wof:placetype":"locality"
},
  "geometry": {"coordinates":[7.190079,47.113685],"type":"Point"}
}