{
  "type": "Feature",
  "properties": {
    "gn:admin1_code":"TI",
    "gn:admin2_code":"2105.0",
    "gn:admin3_code":"5144.0",
    "gn:asciiname":"Vissino",
    "gn:country_code":"CH",
    "gn:dem":688,
    "gn:feature_class":"P",
    "gn:feature_code":"PPL",
    "gn:name":"Vissino",
    "gn:population":0,
    "gn:timezone":"Europe/Zurich",
    "iso:country":"CH",
    "name:ita_x_preferred":[
        "Vissino"
    ],
    "wof:name":"Vissino",
    "wof:placetype":"locality"
},
  "geometry": {"coordinates":[8.97936,45.95372],"type":"Point"}
}