{
  "type": "Feature",
  "properties": {
    "gn:country":"CH",
    "gn:fcode":"PPLX",
    "gn:population":184,
    "iso:country":"CH",
    "name:eng_x_preferred":[
        "Suntenwiese"
    ],
    "name:eng_x_variant":[
        "R\u00fcschlikon / Suntenwiese"
    ],
    "qs_pg:aaroncc":"CH",
    "qs_pg:gn_country":"CH",
    "qs_pg:gn_fcode":"PPLX",
    "qs_pg:gn_pop":184,
    "qs_pg:name":"R\u00fcschlikon / Suntenwiese",
    "qs_pg:photos_9r":0,
    "qs_pg:photos_sr":0,
    "qs_pg:pop_sr":1,
    "qs_pg:qs_pg_placetype":"neighbourhood",
    "wof:name":"Suntenwiese",
    "wof:placetype":"neighbourhood",
    "wof:population":184
},
  "geometry": {"coordinates":[8.55622,47.30675],"type":"Point"}
}