{
  "type": "Feature",
  "properties": {
    "gn:gn_country":"CH",
    "gn:gn_fcode":"PPL",
    "gn:gn_pop":2628,
    "gn:population":2628,
    "iso:country":"CH",
    "name:alb_x_preferred":[
        "Chamoson"
    ],
    "name:baq_x_preferred":[
        "Chamoson"
    ],
    "name:cat_x_preferred":[
        "Chamoson"
    ],
    "name:chi_x_preferred":[
        "\u6c99\u83ab\u677e"
    ],
    "name:dut_x_preferred":[
        "Chamoson"
    ],
    "name:eng_x_preferred":[
        "Chamoson"
    ],
    "name:epo_x_preferred":[
        "Chamoson"
    ],
    "name:fre_x_preferred":[
        "Chamoson"
    ],
    "name:ger_x_preferred":[
        "Chamoson"
    ],
    "name:glg_x_preferred":[
        "Chamoson"
    ],
    "name:hun_x_preferred":[
        "Chamoson"
    ],
    "name:ita_x_preferred":[
        "Chamoson"
    ],
    "name:lat_x_preferred":[
        "Camusia"
    ],
    "name:lmo_x_preferred":[
        "Chamoson"
    ],
    "name:may_x_preferred":[
        "Chamoson"
    ],
    "name:nno_x_preferred":[
        "Chamoson"
    ],
    "name:oci_x_preferred":[
        "Chamoson"
    ],
    "name:roh_x_preferred":[
        "Chamoson"
    ],
    "name:spa_x_preferred":[
        "Chamoson"
    ],
    "name:swe_x_preferred":[
        "Chamoson"
    ],
    "name:vec_x_preferred":[
        "Chamoson"
    ],
    "name:vol_x_preferred":[
        "Chamoson"
    ],
    "name:war_x_preferred":[
        "Chamoson"
    ],
    "name:zho_x_preferred":[
        "\u6c99\u83ab\u677e"
    ],
    "qs_pg:aaroncc":"CH",
    "qs_pg:gn_country":"CH",
    "qs_pg:gn_fcode":"PPL",
    "qs_pg:gn_pop":2628,
    "qs_pg:name":"Chamoson",
    "qs_pg:name_adm0":"Schweiz",
    "qs_pg:name_adm1":"Canton de Valais",
    "qs_pg:photos":124,
    "qs_pg:photos_1k":25,
    "qs_pg:photos_9k":1,
    "qs_pg:photos_9r":3,
    "qs_pg:photos_all":124,
    "qs_pg:photos_sr":3,
    "qs_pg:pop_sr":4,
    "qs_pg:qs_pg_placetype":"locality",
    "qs_pg:qs_pg_placetype_gp":"Town",
    "qs_pg:woe_adm0":23424957,
    "woe:adm0_id":23424957,
    "woe:name_adm0":"Schweiz",
    "woe:name_adm1":"Canton de Valais",
    "woe:placetype":"Town",
    "wof:name":"Chamoson",
    "wof:placetype":"locality",
    "wof:population":2628
},
  "geometry": {"coordinates":[7.22341,46.20104],"type":"Point"}
}