{
  "type": "Feature",
  "properties": {
    "gn:admin1_code":"BE",
    "gn:admin2_code":"250.0",
    "gn:admin3_code":"783.0",
    "gn:asciiname":"Vorder Stafel",
    "gn:country_code":"CH",
    "gn:dem":1673,
    "gn:feature_class":"P",
    "gn:feature_code":"PPL",
    "gn:name":"Vorder Stafel",
    "gn:population":0,
    "gn:timezone":"Europe/Zurich",
    "iso:country":"CH",
    "wof:name":"Vorder Stafel",
    "wof:placetype":"neighbourhood"
},
  "geometry": {"coordinates":[8.20623,46.76023],"type":"Point"}
}