{
  "type": "Feature",
  "properties": {
    "gn:admin1_code":"BE",
    "gn:admin2_code":"245.0",
    "gn:admin3_code":"908.0",
    "gn:asciiname":"Mittenbuehl",
    "gn:country_code":"CH",
    "gn:dem":898,
    "gn:feature_class":"P",
    "gn:feature_code":"PPLL",
    "gn:name":"Mittenb\u00fchl",
    "gn:population":0,
    "gn:timezone":"Europe/Zurich",
    "iso:country":"CH",
    "name:deu_x_preferred":[
        "Mittenb\u00fchl"
    ],
    "wof:name":"Mittenbuehl",
    "wof:placetype":"neighbourhood"
},
  "geometry": {"coordinates":[7.87561,46.90166],"type":"Point"}
}