{
  "type": "Feature",
  "properties": {
    "gn:admin1_code":"GR",
    "gn:admin2_code":"1851.0",
    "gn:admin3_code":"3705.0",
    "gn:asciiname":"Magun",
    "gn:country_code":"CH",
    "gn:dem":1314,
    "gn:feature_class":"P",
    "gn:feature_code":"PPL",
    "gn:name":"Magun",
    "gn:population":0,
    "gn:timezone":"Europe/Zurich",
    "iso:country":"CH",
    "name:roh_x_preferred":[
        "Magun"
    ],
    "wof:name":"Magun",
    "wof:placetype":"locality"
},
  "geometry": {"coordinates":[9.41696,46.61897],"type":"Point"}
}