{
  "type": "Feature",
  "properties": {
    "gn:country":"CH",
    "gn:fcode":"PPLL",
    "gn:population":7,
    "iso:country":"CH",
    "qs_pg:aaroncc":"CH",
    "qs_pg:gn_country":"CH",
    "qs_pg:gn_fcode":"PPLL",
    "qs_pg:gn_pop":7,
    "qs_pg:name":"Cholgrueb",
    "qs_pg:photos_9r":0,
    "qs_pg:photos_sr":0,
    "qs_pg:pop_sr":1,
    "qs_pg:qs_pg_placetype":"locality",
    "wof:name":"Cholgrueb",
    "wof:placetype":"neighbourhood",
    "wof:population":7
},
  "geometry": {"coordinates":[8.59061,47.21363],"type":"Point"}
}