{
  "type": "Feature",
  "properties": {
    "gn:admin1_code":"TI",
    "gn:admin2_code":"2105.0",
    "gn:admin3_code":"5199.0",
    "gn:asciiname":"Tortoi",
    "gn:country_code":"CH",
    "gn:dem":903,
    "gn:feature_class":"P",
    "gn:feature_code":"PPL",
    "gn:name":"Tortoi",
    "gn:population":0,
    "gn:timezone":"Europe/Zurich",
    "iso:country":"CH",
    "name:ita_x_preferred":[
        "Tortoi"
    ],
    "wof:name":"Tortoi",
    "wof:placetype":"neighbourhood"
},
  "geometry": {"coordinates":[8.90838,46.09995],"type":"Point"}
}