{
  "type": "Feature",
  "properties": {
    "gn:gn_country":"CH",
    "gn:gn_fcode":"PPLX",
    "gn:gn_pop":117,
    "gn:population":117,
    "iso:country":"CH",
    "name:eng_x_preferred":[
        "Alemannenweg"
    ],
    "name:eng_x_variant":[
        "R\u00fcschlikon / Alemannenweg"
    ],
    "name:unk_x_variant":[
        "Alemannenweg"
    ],
    "qs_pg:aaroncc":"CH",
    "qs_pg:gn_country":"CH",
    "qs_pg:gn_fcode":"PPLX",
    "qs_pg:gn_pop":117,
    "qs_pg:name":"R\u00fcschlikon / Alemannenweg",
    "qs_pg:photos_9r":0,
    "qs_pg:photos_sr":0,
    "qs_pg:pop_sr":1,
    "qs_pg:qs_pg_placetype":"neighbourhood",
    "wof:name":"Alemannenweg",
    "wof:placetype":"neighbourhood",
    "wof:population":117
},
  "geometry": {"coordinates":[8.54241,47.30909],"type":"Point"}
}