{
  "type": "Feature",
  "properties": {
    "gn:admin1_code":"AR",
    "gn:admin2_code":"1503.0",
    "gn:admin3_code":"3032.0",
    "gn:asciiname":"Schwendi",
    "gn:country_code":"CH",
    "gn:dem":673,
    "gn:feature_class":"P",
    "gn:feature_code":"PPLL",
    "gn:name":"Schwendi",
    "gn:population":0,
    "gn:timezone":"Europe/Zurich",
    "iso:country":"CH",
    "name:als_x_preferred":[
        "Schwendi"
    ],
    "name:ceb_x_preferred":[
        "Schwendi"
    ],
    "name:deu_x_preferred":[
        "Schwendi"
    ],
    "name:epo_x_preferred":[
        "Schwendi"
    ],
    "name:pol_x_preferred":[
        "Schwendi"
    ],
    "name:swe_x_preferred":[
        "Schwendi"
    ],
    "wof:lang_x_official":[
        "deu",
        "fra",
        "gsw",
        "ita"
    ],
    "wof:lang_x_spoken":[
        "deu",
        "fra",
        "gsw",
        "ita",
        "roh"
    ],
    "wof:name":"Schwendi",
    "wof:placetype":"neighbourhood"
},
  "geometry": {"coordinates":[9.53046,47.45978],"type":"Point"}
}