{
  "type": "Feature",
  "properties": {
    "gn:country":"CH",
    "gn:fcode":"PPLX",
    "gn:population":1386,
    "iso:country":"CH",
    "name:eng_x_preferred":[
        "Eichwiesen"
    ],
    "name:eng_x_variant":[
        "Dietlikon / Eichwiesen"
    ],
    "qs_pg:aaroncc":"CH",
    "qs_pg:gn_country":"CH",
    "qs_pg:gn_fcode":"PPLX",
    "qs_pg:gn_pop":1386,
    "qs_pg:name":"Dietlikon / Eichwiesen",
    "qs_pg:photos_9r":0,
    "qs_pg:photos_sr":0,
    "qs_pg:pop_sr":3,
    "qs_pg:qs_pg_placetype":"neighbourhood",
    "wof:lang_x_official":[
        "deu",
        "fra",
        "gsw",
        "ita"
    ],
    "wof:lang_x_spoken":[
        "deu",
        "fra",
        "gsw",
        "ita",
        "roh"
    ],
    "wof:name":"Eichwiesen",
    "wof:placetype":"neighbourhood",
    "wof:population":1386
},
  "geometry": {"coordinates":[8.62078,47.4191],"type":"Point"}
}