{
  "type": "Feature",
  "properties": {
    "gn:gn_country":"CH",
    "gn:gn_fcode":"ADM3",
    "gn:gn_pop":3360,
    "gn:population":3477,
    "iso:country":"CH",
    "name:ara_x_preferred":[
        "\u0647\u0627\u0648\u0632\u0646 \u0623\u0645 \u0623\u0644\u0628\u064a\u0633"
    ],
    "name:cat_x_preferred":[
        "Hausen am Albis"
    ],
    "name:chv_x_preferred":[
        "\u0425\u0430\u0443\u0437\u0435\u043d-\u0430\u043c-\u0410\u043b\u044c\u0431\u0438\u0441"
    ],
    "name:deu_x_preferred":[
        "Hausen am Albis"
    ],
    "name:eng_x_preferred":[
        "Hausen am Albis"
    ],
    "name:epo_x_preferred":[
        "Hausen \u0109e Albis"
    ],
    "name:eus_x_preferred":[
        "Hausen am Albis"
    ],
    "name:fra_x_preferred":[
        "Hausen am Albis"
    ],
    "name:gsw_x_preferred":[
        "Huuse am Albis"
    ],
    "name:hun_x_preferred":[
        "Hausen am Albis"
    ],
    "name:ita_x_preferred":[
        "Hausen am Albis"
    ],
    "name:jpn_x_preferred":[
        "\u30cf\u30a6\u30bc\u30f3\u30fb\u30a2\u30e0\u30fb\u30a2\u30eb\u30d3\u30b9"
    ],
    "name:kaz_x_preferred":[
        "\u0425\u0430\u0443\u0437\u0435\u043d-\u043d\u0430-\u0410\u043b\u044c\u0431\u0438\u0441\u0435"
    ],
    "name:lmo_x_preferred":[
        "Hausen am Albis"
    ],
    "name:msa_x_preferred":[
        "Hausen am Albis"
    ],
    "name:nld_x_preferred":[
        "Hausen am Albis"
    ],
    "name:nno_x_preferred":[
        "Hausen am Albis"
    ],
    "name:oci_x_preferred":[
        "Hausen am Albis"
    ],
    "name:pms_x_preferred":[
        "Hausen am Albis"
    ],
    "name:por_x_preferred":[
        "Hausen am Albis"
    ],
    "name:rus_x_preferred":[
        "\u0425\u0430\u0443\u0437\u0435\u043d-\u043d\u0430-\u0410\u043b\u044c\u0431\u0438\u0441\u0435"
    ],
    "name:spa_x_preferred":[
        "Hausen am Albis"
    ],
    "name:swe_x_preferred":[
        "Hausen am Albis"
    ],
    "name:uzb_x_preferred":[
        "Hausen am Albis"
    ],
    "name:vie_x_preferred":[
        "Hausen am Albis"
    ],
    "name:vol_x_preferred":[
        "Hausen am Albis"
    ],
    "name:war_x_preferred":[
        "Hausen am Albis"
    ],
    "name:zho_x_preferred":[
        "\u963f\u723e\u6bd4\u65af\u9644\u8fd1\u8c6a\u68ee"
    ],
    "qs_pg:aaroncc":"CH",
    "qs_pg:gn_country":"CH",
    "qs_pg:gn_fcode":"ADM3",
    "qs_pg:gn_pop":3360,
    "qs_pg:name":"Hausen am Albis",
    "qs_pg:name_adm0":"Schweiz",
    "qs_pg:name_adm1":"Kanton Z\u00fcrich",
    "qs_pg:photos":24,
    "qs_pg:photos_1k":5,
    "qs_pg:photos_9k":1,
    "qs_pg:photos_9r":1,
    "qs_pg:photos_all":24,
    "qs_pg:photos_sr":1,
    "qs_pg:pop_sr":4,
    "qs_pg:qs_pg_placetype":"locality",
    "qs_pg:qs_pg_placetype_gp":"Town",
    "qs_pg:woe_adm0":23424957,
    "woe:adm0_id":23424957,
    "woe:name_adm0":"Schweiz",
    "woe:name_adm1":"Kanton Z\u00fcrich",
    "woe:placetype":"Town",
    "wof:name":"Hausen am Albis",
    "wof:placetype":"locality",
    "wof:population":3477
},
  "geometry": {"coordinates":[8.53664,47.24435],"type":"Point"}
}