{
  "type": "Feature",
  "properties": {
    "gn:admin1_code":"BE",
    "gn:admin2_code":"246.0",
    "gn:admin3_code":"535.0",
    "gn:asciiname":"Deisswil bei Muenchenbuchsee",
    "gn:country_code":"CH",
    "gn:dem":539,
    "gn:feature_class":"P",
    "gn:feature_code":"PPLL",
    "gn:name":"Deisswil bei M\u00fcnchenbuchsee",
    "gn:population":0,
    "gn:timezone":"Europe/Zurich",
    "iso:country":"CH",
    "name:deu_x_preferred":[
        "Deisswil bei M\u00fcnchenbuchsee"
    ],
    "name:und_x_variant":[
        "Deisswil b. M\u00fcnchenbuchsee"
    ],
    "wof:name":"Deisswil bei Muenchenbuchsee",
    "wof:placetype":"locality"
},
  "geometry": {"coordinates":[7.45661,47.03493],"type":"Point"}
}