{
  "type": "Feature",
  "properties": {
    "gn:admin1_code":"LU",
    "gn:admin2_code":"314.0",
    "gn:admin3_code":"1095.0",
    "gn:asciiname":"Seehubel",
    "gn:country_code":"CH",
    "gn:dem":506,
    "gn:feature_class":"P",
    "gn:feature_code":"PPLL",
    "gn:name":"Seehubel",
    "gn:population":0,
    "gn:timezone":"Europe/Zurich",
    "iso:country":"CH",
    "name:deu_x_preferred":[
        "Seehubel"
    ],
    "wof:name":"Seehubel",
    "wof:placetype":"neighbourhood"
},
  "geometry": {"coordinates":[8.12125,47.16124],"type":"Point"}
}