{
  "type": "Feature",
  "properties": {
    "gn:gn_country":"CH",
    "gn:gn_fcode":"PPL",
    "gn:gn_pop":23,
    "gn:population":23,
    "iso:country":"CH",
    "qs_pg:aaroncc":"CH",
    "qs_pg:gn_country":"CH",
    "qs_pg:gn_fcode":"PPL",
    "qs_pg:gn_pop":23,
    "qs_pg:name":"Ehrenhau",
    "qs_pg:photos_9r":0,
    "qs_pg:photos_sr":0,
    "qs_pg:pop_sr":1,
    "qs_pg:qs_pg_placetype":"locality",
    "wof:name":"Ehrenhau",
    "wof:placetype":"locality",
    "wof:population":23
},
  "geometry": {"coordinates":[8.47778,47.43801],"type":"Point"}
}