{
  "type": "Feature",
  "properties": {
    "gn:gn_country":"CH",
    "gn:gn_fcode":"PPL",
    "gn:gn_pop":800,
    "gn:population":800,
    "iso:country":"CH",
    "name:cat_x_preferred":[
        "Andeer"
    ],
    "name:deu_x_preferred":[
        "Andeer"
    ],
    "name:eng_x_preferred":[
        "Andeer"
    ],
    "name:epo_x_preferred":[
        "Andeer"
    ],
    "name:eus_x_preferred":[
        "Andeer"
    ],
    "name:fra_x_preferred":[
        "Andeer"
    ],
    "name:hun_x_preferred":[
        "Andeer"
    ],
    "name:ind_x_preferred":[
        "Andeer"
    ],
    "name:ita_x_preferred":[
        "Andeer"
    ],
    "name:kaz_x_preferred":[
        "\u0410\u043d\u0434\u0435\u0440"
    ],
    "name:lat_x_preferred":[
        "Lapidaria"
    ],
    "name:lmo_x_preferred":[
        "Andeer"
    ],
    "name:msa_x_preferred":[
        "Andeer"
    ],
    "name:nld_x_preferred":[
        "Andeer"
    ],
    "name:nno_x_preferred":[
        "Andeer"
    ],
    "name:oci_x_preferred":[
        "Andeer"
    ],
    "name:pms_x_preferred":[
        "Andeer"
    ],
    "name:por_x_preferred":[
        "Andeer"
    ],
    "name:roh_x_preferred":[
        "Andeer"
    ],
    "name:rus_x_preferred":[
        "\u0410\u043d\u0434\u0435\u0440"
    ],
    "name:spa_x_preferred":[
        "Andeer"
    ],
    "name:sqi_x_preferred":[
        "Andeer"
    ],
    "name:swe_x_preferred":[
        "Andeer"
    ],
    "name:uzb_x_preferred":[
        "Andeer"
    ],
    "name:vol_x_preferred":[
        "Andeer"
    ],
    "name:war_x_preferred":[
        "Andeer"
    ],
    "name:zho_x_preferred":[
        "\u5b89\u5fb7\u723e"
    ],
    "qs_pg:aaroncc":"CH",
    "qs_pg:gn_country":"CH",
    "qs_pg:gn_fcode":"PPL",
    "qs_pg:gn_pop":800,
    "qs_pg:name":"Andeer",
    "qs_pg:name_adm0":"Schweiz",
    "qs_pg:name_adm1":"Kanton Graub\u00fcnden",
    "qs_pg:photos":220,
    "qs_pg:photos_1k":45,
    "qs_pg:photos_9k":1,
    "qs_pg:photos_9r":4,
    "qs_pg:photos_all":220,
    "qs_pg:photos_sr":4,
    "qs_pg:pop_sr":2,
    "qs_pg:qs_pg_placetype":"locality",
    "qs_pg:qs_pg_placetype_gp":"Town",
    "qs_pg:woe_adm0":23424957,
    "woe:adm0_id":23424957,
    "woe:name_adm0":"Schweiz",
    "woe:name_adm1":"Kanton Graub\u00fcnden",
    "woe:placetype":"Town",
    "wof:name":"Andeer",
    "wof:placetype":"locality",
    "wof:population":800
},
  "geometry": {"coordinates":[9.42614,46.6034],"type":"Point"}
}