{
  "type": "Feature",
  "properties": {
    "iso:country":"CH",
    "name:als_x_preferred":[
        "Urtenen-Sch\u00f6nb\u00fchl"
    ],
    "name:cat_x_preferred":[
        "Urtenen-Sch\u00f6nb\u00fchl"
    ],
    "name:ceb_x_preferred":[
        "Urtenen-Sch\u00f6nb\u00fchl"
    ],
    "name:deu_x_preferred":[
        "Urtenen-Sch\u00f6nb\u00fchl"
    ],
    "name:eng_x_preferred":[
        "Urtenen-Sch\u00f6nb\u00fchl"
    ],
    "name:epo_x_preferred":[
        "Urtenen-Sch\u00f6nb\u00fchl"
    ],
    "name:eus_x_preferred":[
        "Urtenen-Sch\u00f6nb\u00fchl"
    ],
    "name:fra_x_preferred":[
        "Urtenen-Sch\u00f6nb\u00fchl"
    ],
    "name:gsw_x_preferred":[
        "Urtene-Sch\u00f6mb\u00fceu"
    ],
    "name:hun_x_preferred":[
        "Urtenen-Sch\u00f6nb\u00fchl"
    ],
    "name:ita_x_preferred":[
        "Urtenen-Sch\u00f6nb\u00fchl"
    ],
    "name:kaz_x_preferred":[
        "\u0423\u0440\u0442\u0435\u043d\u0435\u043d-\u0428\u0451\u043d\u0431\u044e\u043b\u044c"
    ],
    "name:lmo_x_preferred":[
        "Urtenen-Sch\u00f6nb\u00fchl"
    ],
    "name:msa_x_preferred":[
        "Urtenen-Sch\u00f6nb\u00fchl"
    ],
    "name:nld_x_preferred":[
        "Urtenen-Sch\u00f6nb\u00fchl"
    ],
    "name:nno_x_preferred":[
        "Urtenen-Sch\u00f6nb\u00fchl"
    ],
    "name:oci_x_preferred":[
        "Urtenen-Sch\u00f6nb\u00fchl"
    ],
    "name:rus_x_preferred":[
        "\u0423\u0440\u0442\u0435\u043d\u0435\u043d-\u0428\u0451\u043d\u0431\u044e\u043b\u044c"
    ],
    "name:spa_x_preferred":[
        "Urtenen-Sch\u00f6nb\u00fchl"
    ],
    "name:sqi_x_preferred":[
        "Urtenen-Sch\u00f6nb\u00fchl"
    ],
    "name:swe_x_preferred":[
        "Urtenen-Sch\u00f6nb\u00fchl"
    ],
    "name:vie_x_preferred":[
        "Urtenen-Sch\u00f6nb\u00fchl"
    ],
    "name:vol_x_preferred":[
        "Urtenen-Sch\u00f6nb\u00fchl"
    ],
    "name:war_x_preferred":[
        "Urtenen-Sch\u00f6nb\u00fchl"
    ],
    "name:zho_x_preferred":[
        "\u70cf\u723e\u6ed5\u6069-\u7533\u6bd4\u723e"
    ],
    "qs:a0":"Schweiz#Suisse#Svizzera#Svizra",
    "qs:a1":"*Bern",
    "qs:a1r":"0",
    "qs:adm0":"Schweiz#Suisse#Svizzera#Svizra",
    "qs:la_lc":"*",
    "qs:level":"locality",
    "qs:loc":"Urtenen-Sch\u00f6nb\u00fchl",
    "qs:loc_alt":"Urtenen-Schoenbuehl",
    "qs:pop":0,
    "qs:type":"buffered point",
    "wd:wordcount":2089,
    "wof:name":"Urtenen-Sch\u00f6nb\u00fchl",
    "wof:placetype":"locality"
},
  "geometry": {"coordinates":[7.499529,47.021332],"type":"Point"}
}