{
  "type": "Feature",
  "properties": {
    "gn:admin1_code":"SO",
    "gn:admin2_code":"1110.0",
    "gn:admin3_code":"2614.0",
    "gn:asciiname":"Zil",
    "gn:country_code":"CH",
    "gn:dem":457,
    "gn:feature_class":"P",
    "gn:feature_code":"PPLL",
    "gn:name":"Zil",
    "gn:population":0,
    "gn:timezone":"Europe/Zurich",
    "iso:country":"CH",
    "name:deu_x_preferred":[
        "Zil"
    ],
    "wof:lang_x_official":[
        "deu",
        "fra",
        "gsw",
        "ita"
    ],
    "wof:lang_x_spoken":[
        "deu",
        "fra",
        "gsw",
        "ita",
        "roh"
    ],
    "wof:name":"Zil",
    "wof:placetype":"neighbourhood"
},
  "geometry": {"coordinates":[7.53235,47.39117],"type":"Point"}
}