{
  "type": "Feature",
  "properties": {
    "gn:admin1_code":"SG",
    "gn:admin2_code":"1724.0",
    "gn:admin3_code":"3276.0",
    "gn:asciiname":"Gretschins",
    "gn:country_code":"CH",
    "gn:dem":626,
    "gn:elevation":"602.0",
    "gn:feature_class":"P",
    "gn:feature_code":"PPL",
    "gn:name":"Gretschins",
    "gn:population":0,
    "gn:timezone":"Europe/Zurich",
    "iso:country":"CH",
    "wof:name":"Gretschins",
    "wof:placetype":"locality"
},
  "geometry": {"coordinates":[9.4868,47.09897],"type":"Point"}
}