{
  "type": "Feature",
  "properties": {
    "gn:admin1_code":"GL",
    "gn:admin2_code":"800.0",
    "gn:admin3_code":"1630.0",
    "gn:asciiname":"Walenberg",
    "gn:country_code":"CH",
    "gn:dem":435,
    "gn:feature_class":"P",
    "gn:feature_code":"PPLL",
    "gn:name":"Walenberg",
    "gn:population":0,
    "gn:timezone":"Europe/Zurich",
    "iso:country":"CH",
    "name:deu_x_preferred":[
        "Walenberg"
    ],
    "wof:name":"Walenberg",
    "wof:placetype":"neighbourhood"
},
  "geometry": {"coordinates":[9.08621,47.11752],"type":"Point"}
}