{
  "type": "Feature",
  "properties": {
    "gn:admin1_code":"TG",
    "gn:admin2_code":"2013.0",
    "gn:admin3_code":"4666.0",
    "gn:asciiname":"Lehmgrube",
    "gn:country_code":"CH",
    "gn:dem":579,
    "gn:feature_class":"P",
    "gn:feature_code":"PPLL",
    "gn:name":"Lehmgrube",
    "gn:population":0,
    "gn:timezone":"Europe/Zurich",
    "iso:country":"CH",
    "name:deu_x_preferred":[
        "Lehmgrube"
    ],
    "wof:name":"Lehmgrube",
    "wof:placetype":"neighbourhood"
},
  "geometry": {"coordinates":[9.14714,47.58952],"type":"Point"}
}