{
  "type": "Feature",
  "properties": {
    "gn:admin1_code":"TG",
    "gn:admin2_code":"2015.0",
    "gn:admin3_code":"4901.0",
    "gn:asciiname":"Eckartshausen",
    "gn:country_code":"CH",
    "gn:dem":506,
    "gn:feature_class":"P",
    "gn:feature_code":"PPLL",
    "gn:name":"Eckartshausen",
    "gn:population":0,
    "gn:timezone":"Europe/Zurich",
    "iso:country":"CH",
    "name:deu_x_preferred":[
        "Eckartshausen"
    ],
    "wof:name":"Eckartshausen",
    "wof:placetype":"neighbourhood"
},
  "geometry": {"coordinates":[9.2151,47.57266],"type":"Point"}
}