{
  "type": "Feature",
  "properties": {
    "gn:admin1_code":"TG",
    "gn:admin2_code":"2012.0",
    "gn:admin3_code":"4566.0",
    "gn:asciiname":"Horgenbach",
    "gn:country_code":"CH",
    "gn:dem":378,
    "gn:elevation":"381.0",
    "gn:feature_class":"P",
    "gn:feature_code":"PPL",
    "gn:name":"Horgenbach",
    "gn:population":0,
    "gn:timezone":"Europe/Zurich",
    "iso:country":"CH",
    "wof:name":"Horgenbach",
    "wof:placetype":"locality"
},
  "geometry": {"coordinates":[8.84414,47.57074],"type":"Point"}
}