{
  "type": "Feature",
  "properties": {
    "gn:country":"CH",
    "gn:fcode":"PPL",
    "gn:population":0,
    "iso:country":"CH",
    "name:deu_x_historical":[
        "Reams"
    ],
    "name:deu_x_preferred":[
        "Reams"
    ],
    "name:deu_x_variant":[
        "Riom"
    ],
    "name:eng_x_preferred":[
        "Riom"
    ],
    "name:fra_x_preferred":[
        "Riom"
    ],
    "name:nld_x_preferred":[
        "Riom"
    ],
    "name:roh_x_preferred":[
        "Riom"
    ],
    "qs_pg:aaroncc":"CH",
    "qs_pg:gn_country":"CH",
    "qs_pg:gn_fcode":"PPL",
    "qs_pg:gn_pop":0,
    "qs_pg:name":"Reams",
    "qs_pg:name_adm0":"Schweiz",
    "qs_pg:name_adm1":"Kanton Graub\u00fcnden",
    "qs_pg:photos_9k":1,
    "qs_pg:photos_9r":1,
    "qs_pg:photos_all":7,
    "qs_pg:photos_sr":0,
    "qs_pg:pop_sr":0,
    "qs_pg:qs_pg_placetype":"locality",
    "qs_pg:qs_pg_placetype_gp":"Town",
    "qs_pg:woe_adm0":23424957,
    "woe:adm0_id":23424957,
    "woe:name_adm0":"Schweiz",
    "woe:name_adm1":"Kanton Graub\u00fcnden",
    "woe:placetype":"Town",
    "wof:name":"Reams",
    "wof:placetype":"neighbourhood"
},
  "geometry": {"coordinates":[9.58171,46.60977],"type":"Point"}
}