{
  "type": "Feature",
  "properties": {
    "gn:gn_country":"CH",
    "gn:gn_fcode":"PPLX",
    "gn:gn_pop":321,
    "gn:population":321,
    "iso:country":"CH",
    "name:eng_x_preferred":[
        "Welbrig"
    ],
    "name:eng_x_variant":[
        "Geroldswil / Welbrig"
    ],
    "name:unk_x_variant":[
        "Welbrig"
    ],
    "qs_pg:aaroncc":"CH",
    "qs_pg:gn_country":"CH",
    "qs_pg:gn_fcode":"PPLX",
    "qs_pg:gn_pop":321,
    "qs_pg:name":"Geroldswil / Welbrig",
    "qs_pg:photos_9r":0,
    "qs_pg:photos_sr":0,
    "qs_pg:pop_sr":2,
    "qs_pg:qs_pg_placetype":"neighbourhood",
    "wof:name":"Welbrig",
    "wof:placetype":"neighbourhood",
    "wof:population":321
},
  "geometry": {"coordinates":[8.41413,47.42355],"type":"Point"}
}