{
  "type": "Feature",
  "properties": {
    "gn:gn_country":"CH",
    "gn:gn_fcode":"PPL",
    "gn:gn_pop":3403,
    "gn:population":4040,
    "iso:country":"CH",
    "name:alb_x_preferred":[
        "Schmitten"
    ],
    "name:baq_x_preferred":[
        "Schmitten"
    ],
    "name:cat_x_preferred":[
        "Schmitten"
    ],
    "name:chi_x_preferred":[
        "\u65bd\u7c73\u6ed5"
    ],
    "name:deu_x_preferred":[
        "Schmitten FR"
    ],
    "name:dut_x_preferred":[
        "Schmitten"
    ],
    "name:eng_x_preferred":[
        "Schmitten"
    ],
    "name:epo_x_preferred":[
        "Schmitten FR"
    ],
    "name:fre_x_preferred":[
        "Schmitten"
    ],
    "name:ger_x_preferred":[
        "Schmitten FR"
    ],
    "name:hun_x_preferred":[
        "Schmitten"
    ],
    "name:ita_x_preferred":[
        "Schmitten"
    ],
    "name:lmo_x_preferred":[
        "Schmitten"
    ],
    "name:may_x_preferred":[
        "Schmitten"
    ],
    "name:nno_x_preferred":[
        "Schmitten i Fribourg"
    ],
    "name:oci_x_preferred":[
        "Schmitten"
    ],
    "name:pms_x_preferred":[
        "Schmitten"
    ],
    "name:por_x_preferred":[
        "Schmitten"
    ],
    "name:roh_x_preferred":[
        "Schmitten"
    ],
    "name:spa_x_preferred":[
        "Schmitten"
    ],
    "name:swe_x_preferred":[
        "Schmitten"
    ],
    "name:war_x_preferred":[
        "Schmitten"
    ],
    "name:zho_x_preferred":[
        "\u65bd\u7c73\u6ed5"
    ],
    "qs_pg:aaroncc":"CH",
    "qs_pg:gn_country":"CH",
    "qs_pg:gn_fcode":"PPL",
    "qs_pg:gn_pop":3403,
    "qs_pg:name":"Schmitten",
    "qs_pg:name_adm0":"Schweiz",
    "qs_pg:name_adm1":"Canton de Fribourg",
    "qs_pg:photos":133,
    "qs_pg:photos_1k":27,
    "qs_pg:photos_9k":1,
    "qs_pg:photos_9r":3,
    "qs_pg:photos_all":133,
    "qs_pg:photos_sr":3,
    "qs_pg:pop_sr":4,
    "qs_pg:qs_pg_placetype":"locality",
    "qs_pg:qs_pg_placetype_gp":"Town",
    "qs_pg:woe_adm0":23424957,
    "woe:adm0_id":23424957,
    "woe:name_adm0":"Schweiz",
    "woe:name_adm1":"Canton de Fribourg",
    "woe:placetype":"Town",
    "wof:name":"Schmitten",
    "wof:placetype":"locality",
    "wof:population":4040
},
  "geometry": {"coordinates":[7.25031,46.8575],"type":"Point"}
}