{
  "type": "Feature",
  "properties": {
    "gn:admin1_code":"BL",
    "gn:admin2_code":"1305.0",
    "gn:admin3_code":"2895.0",
    "gn:asciiname":"Sennhaus",
    "gn:country_code":"CH",
    "gn:dem":638,
    "gn:feature_class":"P",
    "gn:feature_code":"PPLL",
    "gn:name":"Sennhaus",
    "gn:population":0,
    "gn:timezone":"Europe/Zurich",
    "iso:country":"CH",
    "name:deu_x_preferred":[
        "Sennhaus"
    ],
    "wof:name":"Sennhaus",
    "wof:placetype":"neighbourhood"
},
  "geometry": {"coordinates":[7.7575,47.383],"type":"Point"}
}