{
  "type": "Feature",
  "properties": {
    "gn:admin1_code":"TI",
    "gn:admin2_code":"2105.0",
    "gn:admin3_code":"5226.0",
    "gn:asciiname":"Stinche",
    "gn:country_code":"CH",
    "gn:dem":1094,
    "gn:feature_class":"P",
    "gn:feature_code":"PPL",
    "gn:name":"Stinch\u00e8",
    "gn:population":0,
    "gn:timezone":"Europe/Zurich",
    "iso:country":"CH",
    "name:ita_x_preferred":[
        "Stinch\u00e8"
    ],
    "wof:name":"Stinche",
    "wof:placetype":"locality"
},
  "geometry": {"coordinates":[8.95293,46.09509],"type":"Point"}
}