{
  "type": "Feature",
  "properties": {
    "gn:admin1_code":"SG",
    "gn:admin2_code":"1728.0",
    "gn:admin3_code":"3424.0",
    "gn:asciiname":"Grueben",
    "gn:country_code":"CH",
    "gn:dem":508,
    "gn:feature_class":"P",
    "gn:feature_code":"PPLL",
    "gn:name":"Grueben",
    "gn:population":0,
    "gn:timezone":"Europe/Zurich",
    "iso:country":"CH",
    "name:deu_x_preferred":[
        "Grueben"
    ],
    "wof:name":"Grueben",
    "wof:placetype":"locality"
},
  "geometry": {"coordinates":[9.12848,47.4592],"type":"Point"}
}