{
  "type": "Feature",
  "properties": {
    "gn:gn_country":"CH",
    "gn:gn_fcode":"PPLX",
    "gn:gn_pop":1064,
    "gn:population":1064,
    "iso:country":"CH",
    "name:eng_x_preferred":[
        "Seilerwis"
    ],
    "name:eng_x_variant":[
        "Greifensee / M\u00fcllerwis / Seilerwis"
    ],
    "name:unk_x_variant":[
        "M\u00fcllerwis / Seilerwis"
    ],
    "qs_pg:aaroncc":"CH",
    "qs_pg:gn_country":"CH",
    "qs_pg:gn_fcode":"PPLX",
    "qs_pg:gn_pop":1064,
    "qs_pg:name":"Greifensee / M\u00fcllerwis / Seilerwis",
    "qs_pg:photos_9r":0,
    "qs_pg:photos_sr":0,
    "qs_pg:pop_sr":3,
    "qs_pg:qs_pg_placetype":"neighbourhood",
    "wof:name":"Seilerwis",
    "wof:placetype":"neighbourhood",
    "wof:population":1064
},
  "geometry": {"coordinates":[8.68151,47.37042],"type":"Point"}
}