{
  "type": "Feature",
  "properties": {
    "gn:gn_country":"CH",
    "gn:gn_fcode":"PPL",
    "gn:gn_pop":9595,
    "gn:population":9595,
    "iso:country":"CH",
    "name:alb_x_preferred":[
        "Therwil"
    ],
    "name:ast_x_preferred":[
        "Therwil"
    ],
    "name:baq_x_preferred":[
        "Therwil"
    ],
    "name:cat_x_preferred":[
        "Therwil"
    ],
    "name:chi_x_preferred":[
        "\u7279\u7dad\u723e"
    ],
    "name:dut_x_preferred":[
        "Therwil"
    ],
    "name:eng_x_preferred":[
        "Therwil"
    ],
    "name:epo_x_preferred":[
        "Therwil"
    ],
    "name:fre_x_preferred":[
        "Therwil"
    ],
    "name:ger_x_preferred":[
        "Therwil"
    ],
    "name:gsw_x_preferred":[
        "D\u00e4rwil"
    ],
    "name:hun_x_preferred":[
        "Therwil"
    ],
    "name:ita_x_preferred":[
        "Therwil"
    ],
    "name:kaz_x_preferred":[
        "\u0422\u0435\u0440\u0432\u0438\u043b\u044c"
    ],
    "name:lmo_x_preferred":[
        "Therwil"
    ],
    "name:may_x_preferred":[
        "Therwil"
    ],
    "name:nno_x_preferred":[
        "Therwil"
    ],
    "name:oci_x_preferred":[
        "Therwil"
    ],
    "name:rus_x_preferred":[
        "\u0422\u0435\u0440\u0432\u0438\u043b\u044c"
    ],
    "name:spa_x_preferred":[
        "Therwil"
    ],
    "name:swe_x_preferred":[
        "Therwil"
    ],
    "name:ukr_x_preferred":[
        "\u0422\u0435\u0440\u0432\u0456\u043b\u044c"
    ],
    "name:uzb_x_preferred":[
        "Therwil"
    ],
    "name:vol_x_preferred":[
        "Therwil"
    ],
    "name:war_x_preferred":[
        "Therwil"
    ],
    "name:zho_x_preferred":[
        "\u7279\u7dad\u723e"
    ],
    "qs_pg:aaroncc":"CH",
    "qs_pg:gn_country":"CH",
    "qs_pg:gn_fcode":"PPL",
    "qs_pg:gn_pop":9595,
    "qs_pg:name":"Therwil",
    "qs_pg:name_adm0":"Schweiz",
    "qs_pg:name_adm1":"Kanton Basel-Land",
    "qs_pg:photos":79,
    "qs_pg:photos_1k":16,
    "qs_pg:photos_9k":1,
    "qs_pg:photos_9r":3,
    "qs_pg:photos_all":79,
    "qs_pg:photos_sr":3,
    "qs_pg:pop_sr":5,
    "qs_pg:qs_pg_placetype":"locality",
    "qs_pg:qs_pg_placetype_gp":"Town",
    "qs_pg:woe_adm0":23424957,
    "woe:adm0_id":23424957,
    "woe:name_adm0":"Schweiz",
    "woe:name_adm1":"Kanton Basel-Land",
    "woe:placetype":"Town",
    "wof:name":"Therwil",
    "wof:placetype":"locality",
    "wof:population":9595
},
  "geometry": {"coordinates":[7.55286,47.50117],"type":"Point"}
}