{
  "type": "Feature",
  "properties": {
    "gn:admin1_code":"VD",
    "gn:admin2_code":"2224.0",
    "gn:admin3_code":"5872.0",
    "gn:asciiname":"La Mollerie",
    "gn:country_code":"CH",
    "gn:dem":1013,
    "gn:feature_class":"P",
    "gn:feature_code":"PPL",
    "gn:name":"La Mollerie",
    "gn:population":0,
    "gn:timezone":"Europe/Zurich",
    "iso:country":"CH",
    "name:fra_x_preferred":[
        "La Mollerie"
    ],
    "wof:name":"La Mollerie",
    "wof:placetype":"neighbourhood"
},
  "geometry": {"coordinates":[6.25624,46.61202],"type":"Point"}
}