{
  "type": "Feature",
  "properties": {
    "gn:admin1_code":"TI",
    "gn:admin2_code":"2105.0",
    "gn:admin3_code":"5238.0",
    "gn:asciiname":"Canedo",
    "gn:country_code":"CH",
    "gn:dem":839,
    "gn:feature_class":"P",
    "gn:feature_code":"PPL",
    "gn:name":"Canedo",
    "gn:population":0,
    "gn:timezone":"Europe/Zurich",
    "iso:country":"CH",
    "name:cat_x_preferred":[
        "Canedo"
    ],
    "name:ceb_x_preferred":[
        "Canedo"
    ],
    "name:deu_x_preferred":[
        "Canedo"
    ],
    "name:fra_x_preferred":[
        "Canedo"
    ],
    "name:glg_x_preferred":[
        "Canedo"
    ],
    "name:ita_x_preferred":[
        "Canedo"
    ],
    "name:nds_x_preferred":[
        "Canedo"
    ],
    "name:por_x_preferred":[
        "Canedo"
    ],
    "name:rus_x_preferred":[
        "\u041a\u0430\u043d\u0435\u0434\u0443"
    ],
    "name:spa_x_preferred":[
        "Canedo"
    ],
    "name:ukr_x_preferred":[
        "\u041a\u0430\u043d\u0435\u0434\u0443"
    ],
    "wof:name":"Canedo",
    "wof:placetype":"neighbourhood"
},
  "geometry": {"coordinates":[8.95571,46.12098],"type":"Point"}
}