{
  "type": "Feature",
  "properties": {
    "gn:gn_country":"CH",
    "gn:gn_fcode":"PPLX",
    "gn:gn_pop":54,
    "gn:population":54,
    "iso:country":"CH",
    "name:unk_x_variant":[
        "Br\u00fchl"
    ],
    "qs_pg:aaroncc":"CH",
    "qs_pg:gn_country":"CH",
    "qs_pg:gn_fcode":"PPLX",
    "qs_pg:gn_pop":54,
    "qs_pg:name":"Birmensdorf / Br\u00fchl",
    "qs_pg:photos_9r":0,
    "qs_pg:photos_sr":0,
    "qs_pg:pop_sr":1,
    "qs_pg:qs_pg_placetype":"neighbourhood",
    "wof:name":"Birmensdorf / Br\u00fchl",
    "wof:placetype":"neighbourhood",
    "wof:population":54
},
  "geometry": {"coordinates":[8.43971,47.35557],"type":"Point"}
}