{
  "type": "Feature",
  "properties": {
    "gn:gn_country":"CH",
    "gn:gn_fcode":"PPL",
    "gn:gn_pop":0,
    "iso:country":"CH",
    "name:cat_x_preferred":[
        "M\u00e4genwil"
    ],
    "name:deu_x_preferred":[
        "M\u00e4genwil"
    ],
    "name:eng_x_preferred":[
        "M\u00e4genwil"
    ],
    "name:epo_x_preferred":[
        "M\u00e4genwil"
    ],
    "name:eus_x_preferred":[
        "M\u00e4genwil"
    ],
    "name:fra_x_preferred":[
        "M\u00e4genwil"
    ],
    "name:gsw_x_preferred":[
        "M\u00e4gewil"
    ],
    "name:hun_x_preferred":[
        "M\u00e4genwil"
    ],
    "name:ita_x_preferred":[
        "M\u00e4genwil"
    ],
    "name:kaz_x_preferred":[
        "\u041c\u0435\u0433\u0435\u043d\u0432\u0438\u043b\u044c"
    ],
    "name:lmo_x_preferred":[
        "M\u00e4genwil"
    ],
    "name:msa_x_preferred":[
        "M\u00e4genwil"
    ],
    "name:nld_x_preferred":[
        "M\u00e4genwil"
    ],
    "name:nno_x_preferred":[
        "M\u00e4genwil"
    ],
    "name:oci_x_preferred":[
        "M\u00e4genwil"
    ],
    "name:pms_x_preferred":[
        "M\u00e4genwil"
    ],
    "name:pol_x_preferred":[
        "M\u00e4genwil"
    ],
    "name:por_x_preferred":[
        "M\u00e4genwil"
    ],
    "name:roh_x_preferred":[
        "M\u00e4genwil"
    ],
    "name:rus_x_preferred":[
        "\u041c\u0435\u0433\u0435\u043d\u0432\u0438\u043b\u044c"
    ],
    "name:spa_x_preferred":[
        "M\u00e4genwil"
    ],
    "name:sqi_x_preferred":[
        "M\u00e4genwil"
    ],
    "name:swe_x_preferred":[
        "M\u00e4genwil"
    ],
    "name:uzb_x_preferred":[
        "M\u00e4genwil"
    ],
    "name:vol_x_preferred":[
        "M\u00e4genwil"
    ],
    "name:war_x_preferred":[
        "M\u00e4genwil"
    ],
    "name:zho_x_preferred":[
        "\u6885\u6839\u7dad\u723e"
    ],
    "qs_pg:aaroncc":"CH",
    "qs_pg:gn_country":"CH",
    "qs_pg:gn_fcode":"PPL",
    "qs_pg:gn_pop":0,
    "qs_pg:name":"M\u00e4genwil",
    "qs_pg:name_adm0":"Schweiz",
    "qs_pg:name_adm1":"Kanton Aargau",
    "qs_pg:photos":19,
    "qs_pg:photos_1k":4,
    "qs_pg:photos_9k":1,
    "qs_pg:photos_9r":1,
    "qs_pg:photos_all":19,
    "qs_pg:photos_sr":1,
    "qs_pg:pop_sr":0,
    "qs_pg:qs_pg_placetype":"locality",
    "qs_pg:qs_pg_placetype_gp":"Town",
    "qs_pg:woe_adm0":23424957,
    "woe:adm0_id":23424957,
    "woe:name_adm0":"Schweiz",
    "woe:name_adm1":"Kanton Aargau",
    "woe:placetype":"Town",
    "wof:name":"M\u00e4genwil",
    "wof:placetype":"locality"
},
  "geometry": {"coordinates":[8.23297,47.41252],"type":"Point"}
}