{
  "type": "Feature",
  "properties": {
    "gn:admin1_code":"BE",
    "gn:admin2_code":"248.0",
    "gn:admin3_code":"791.0",
    "gn:asciiname":"Farni",
    "gn:country_code":"CH",
    "gn:dem":984,
    "gn:feature_class":"P",
    "gn:feature_code":"PPL",
    "gn:name":"Farni",
    "gn:population":0,
    "gn:timezone":"Europe/Zurich",
    "iso:country":"CH",
    "name:deu_x_preferred":[
        "Farni"
    ],
    "wof:name":"Farni",
    "wof:placetype":"neighbourhood"
},
  "geometry": {"coordinates":[7.35963,46.6234],"type":"Point"}
}