{
  "type": "Feature",
  "properties": {
    "gn:gn_country":"CH",
    "gn:gn_fcode":"PPL",
    "gn:gn_pop":135,
    "gn:population":135,
    "iso:country":"CH",
    "name:bul_x_preferred":[
        "\u0414\u043e\u043d\u0430\u0442\u0439\u0440\u0435"
    ],
    "name:dut_x_preferred":[
        "Donatyre"
    ],
    "name:eng_x_preferred":[
        "Donatyre"
    ],
    "name:fre_x_preferred":[
        "Donatyre"
    ],
    "name:ger_x_preferred":[
        "Donatyre"
    ],
    "name:ita_x_preferred":[
        "Donatyre"
    ],
    "name:spa_x_preferred":[
        "Donatyre"
    ],
    "name:swe_x_preferred":[
        "Donatyre"
    ],
    "qs_pg:aaroncc":"CH",
    "qs_pg:gn_country":"CH",
    "qs_pg:gn_fcode":"PPL",
    "qs_pg:gn_pop":135,
    "qs_pg:name":"Donatyre",
    "qs_pg:name_adm0":"Schweiz",
    "qs_pg:name_adm1":"Canton de Vaud",
    "qs_pg:photos_9k":1,
    "qs_pg:photos_9r":1,
    "qs_pg:photos_all":9,
    "qs_pg:photos_sr":0,
    "qs_pg:pop_sr":1,
    "qs_pg:qs_pg_placetype":"locality",
    "qs_pg:qs_pg_placetype_gp":"Town",
    "qs_pg:woe_adm0":23424957,
    "woe:adm0_id":23424957,
    "woe:name_adm0":"Schweiz",
    "woe:name_adm1":"Canton de Vaud",
    "woe:placetype":"Town",
    "wof:name":"Donatyre",
    "wof:placetype":"locality",
    "wof:population":135
},
  "geometry": {"coordinates":[7.06086,46.87668],"type":"Point"}
}