{
  "type": "Feature",
  "properties": {
    "gn:admin1_code":"BE",
    "gn:admin2_code":"244.0",
    "gn:admin3_code":"339.0",
    "gn:asciiname":"Untermatten",
    "gn:country_code":"CH",
    "gn:dem":637,
    "gn:feature_class":"P",
    "gn:feature_code":"PPLL",
    "gn:name":"Untermatten",
    "gn:population":0,
    "gn:timezone":"Europe/Zurich",
    "iso:country":"CH",
    "name:deu_x_preferred":[
        "Untermatten"
    ],
    "wof:name":"Untermatten",
    "wof:placetype":"locality"
},
  "geometry": {"coordinates":[7.8002,47.12064],"type":"Point"}
}