{
  "type": "Feature",
  "properties": {
    "gn:country":"CH",
    "gn:fcode":"PPLX",
    "gn:population":372,
    "iso:country":"CH",
    "name:eng_x_preferred":[
        "H\u00fcbler"
    ],
    "name:eng_x_variant":[
        "Schlieren / H\u00fcbler"
    ],
    "qs_pg:aaroncc":"CH",
    "qs_pg:gn_country":"CH",
    "qs_pg:gn_fcode":"PPLX",
    "qs_pg:gn_pop":372,
    "qs_pg:name":"Schlieren / H\u00fcbler",
    "qs_pg:photos_9r":0,
    "qs_pg:photos_sr":0,
    "qs_pg:pop_sr":2,
    "qs_pg:qs_pg_placetype":"neighbourhood",
    "wof:name":"H\u00fcbler",
    "wof:placetype":"neighbourhood",
    "wof:population":372
},
  "geometry": {"coordinates":[8.46667,47.39537],"type":"Point"}
}