{
  "type": "Feature",
  "properties": {
    "gn:admin1_code":"TI",
    "gn:admin2_code":"2105.0",
    "gn:admin3_code":"5144.0",
    "gn:asciiname":"Ca Nova",
    "gn:country_code":"CH",
    "gn:dem":553,
    "gn:feature_class":"P",
    "gn:feature_code":"PPL",
    "gn:name":"Ca Nova",
    "gn:population":0,
    "gn:timezone":"Europe/Zurich",
    "iso:country":"CH",
    "name:ita_x_preferred":[
        "Ca Nova"
    ],
    "wof:name":"Ca Nova",
    "wof:placetype":"neighbourhood"
},
  "geometry": {"coordinates":[8.98759,45.95094],"type":"Point"}
}