{
  "type": "Feature",
  "properties": {
    "gn:admin1_code":"TI",
    "gn:admin2_code":"2105.0",
    "gn:admin3_code":"5192.0",
    "gn:asciiname":"Trecio",
    "gn:country_code":"CH",
    "gn:dem":869,
    "gn:feature_class":"P",
    "gn:feature_code":"PPL",
    "gn:name":"Trecio",
    "gn:population":0,
    "gn:timezone":"Europe/Zurich",
    "iso:country":"CH",
    "name:ita_x_preferred":[
        "Trecio"
    ],
    "wof:name":"Trecio",
    "wof:placetype":"neighbourhood"
},
  "geometry": {"coordinates":[9.03108,46.07926],"type":"Point"}
}