{
  "type": "Feature",
  "properties": {
    "gn:gn_country":"CH",
    "gn:gn_fcode":"PPL",
    "gn:gn_pop":79,
    "gn:population":79,
    "iso:country":"CH",
    "name:dut_x_preferred":[
        "Casima"
    ],
    "name:eng_x_preferred":[
        "Casima"
    ],
    "name:fre_x_preferred":[
        "Casima"
    ],
    "name:ger_x_preferred":[
        "Casima"
    ],
    "name:ita_x_preferred":[
        "Casima"
    ],
    "name:lmo_x_preferred":[
        "Casima"
    ],
    "qs_pg:aaroncc":"CH",
    "qs_pg:gn_country":"CH",
    "qs_pg:gn_fcode":"PPL",
    "qs_pg:gn_pop":79,
    "qs_pg:name":"Casima",
    "qs_pg:name_adm0":"Schweiz",
    "qs_pg:name_adm1":"Cantone Ticino",
    "qs_pg:photos":22,
    "qs_pg:photos_1k":4,
    "qs_pg:photos_9k":1,
    "qs_pg:photos_9r":1,
    "qs_pg:photos_all":22,
    "qs_pg:photos_sr":1,
    "qs_pg:pop_sr":1,
    "qs_pg:qs_pg_placetype":"locality",
    "qs_pg:qs_pg_placetype_gp":"Town",
    "qs_pg:woe_adm0":23424957,
    "woe:adm0_id":23424957,
    "woe:name_adm0":"Schweiz",
    "woe:name_adm1":"Cantone Ticino",
    "woe:placetype":"Town",
    "wof:name":"Casima",
    "wof:placetype":"locality",
    "wof:population":79
},
  "geometry": {"coordinates":[9.03694,45.89036],"type":"Point"}
}