{
  "type": "Feature",
  "properties": {
    "gn:gn_country":"CH",
    "gn:gn_fcode":"PPL",
    "gn:gn_pop":1040,
    "gn:population":1040,
    "iso:country":"CH",
    "name:alb_x_preferred":[
        "Tegerfelden"
    ],
    "name:baq_x_preferred":[
        "Tegerfelden"
    ],
    "name:cat_x_preferred":[
        "Tegerfelden"
    ],
    "name:chi_x_preferred":[
        "\u6cf0\u683c\u8cbb\u723e\u767b"
    ],
    "name:dut_x_preferred":[
        "Tegerfelden"
    ],
    "name:eng_x_preferred":[
        "Tegerfelden"
    ],
    "name:epo_x_preferred":[
        "Tegerfelden"
    ],
    "name:fre_x_preferred":[
        "Tegerfelden"
    ],
    "name:ger_x_preferred":[
        "Tegerfelden"
    ],
    "name:gsw_x_preferred":[
        "T\u00e4gerf\u00e4ld"
    ],
    "name:hun_x_preferred":[
        "Tegerfelden"
    ],
    "name:ita_x_preferred":[
        "Tegerfelden"
    ],
    "name:kaz_x_preferred":[
        "\u0422\u0435\u0433\u0435\u0440\u0444\u0435\u043b\u044c\u0434\u0435\u043d"
    ],
    "name:lmo_x_preferred":[
        "Tegerfelden"
    ],
    "name:may_x_preferred":[
        "Tegerfelden"
    ],
    "name:nno_x_preferred":[
        "Tegerfelden"
    ],
    "name:oci_x_preferred":[
        "Tegerfelden"
    ],
    "name:roh_x_preferred":[
        "Tegerfelden"
    ],
    "name:rus_x_preferred":[
        "\u0422\u0435\u0433\u0435\u0440\u0444\u0435\u043b\u044c\u0434\u0435\u043d"
    ],
    "name:spa_x_preferred":[
        "Tegerfelden"
    ],
    "name:swe_x_preferred":[
        "Tegerfelden"
    ],
    "name:uzb_x_preferred":[
        "Tegerfelden"
    ],
    "name:vie_x_preferred":[
        "Tegerfelden"
    ],
    "name:vol_x_preferred":[
        "Tegerfelden"
    ],
    "name:war_x_preferred":[
        "Tegerfelden"
    ],
    "name:zho_x_preferred":[
        "\u6cf0\u683c\u8cbb\u723e\u767b"
    ],
    "qs_pg:aaroncc":"CH",
    "qs_pg:gn_country":"CH",
    "qs_pg:gn_fcode":"PPL",
    "qs_pg:gn_pop":1040,
    "qs_pg:name":"Tegerfelden",
    "qs_pg:name_adm0":"Schweiz",
    "qs_pg:name_adm1":"Kanton Aargau",
    "qs_pg:photos_9k":1,
    "qs_pg:photos_9r":1,
    "qs_pg:photos_all":8,
    "qs_pg:photos_sr":0,
    "qs_pg:pop_sr":3,
    "qs_pg:qs_pg_placetype":"locality",
    "qs_pg:qs_pg_placetype_gp":"Town",
    "qs_pg:woe_adm0":23424957,
    "woe:adm0_id":23424957,
    "woe:name_adm0":"Schweiz",
    "woe:name_adm1":"Kanton Aargau",
    "woe:placetype":"Town",
    "wof:name":"Tegerfelden",
    "wof:placetype":"locality",
    "wof:population":1040
},
  "geometry": {"coordinates":[8.28914,47.55809],"type":"Point"}
}