{
  "type": "Feature",
  "properties": {
    "gn:country":"CH",
    "gn:fcode":"PPLX",
    "gn:population":286,
    "iso:country":"CH",
    "name:eng_x_preferred":[
        "St\u00fcmel"
    ],
    "name:eng_x_variant":[
        "Aeugst / St\u00fcmel"
    ],
    "qs_pg:aaroncc":"CH",
    "qs_pg:gn_country":"CH",
    "qs_pg:gn_fcode":"PPLX",
    "qs_pg:gn_pop":286,
    "qs_pg:name":"Aeugst / St\u00fcmel",
    "qs_pg:photos_9r":0,
    "qs_pg:photos_sr":0,
    "qs_pg:pop_sr":2,
    "qs_pg:qs_pg_placetype":"neighbourhood",
    "wof:lang_x_official":[
        "deu",
        "fra",
        "gsw",
        "ita"
    ],
    "wof:lang_x_spoken":[
        "deu",
        "fra",
        "gsw",
        "ita",
        "roh"
    ],
    "wof:name":"St\u00fcmel",
    "wof:placetype":"neighbourhood",
    "wof:population":286
},
  "geometry": {"coordinates":[8.48219,47.27164],"type":"Point"}
}