{
  "type": "Feature",
  "properties": {
    "gn:gn_country":"CH",
    "gn:gn_fcode":"PPL",
    "gn:gn_pop":52,
    "gn:population":52,
    "iso:country":"CH",
    "qs_pg:aaroncc":"CH",
    "qs_pg:gn_country":"CH",
    "qs_pg:gn_fcode":"PPL",
    "qs_pg:gn_pop":52,
    "qs_pg:name":"Ober-Erlosen",
    "qs_pg:photos_9r":0,
    "qs_pg:photos_sr":0,
    "qs_pg:pop_sr":1,
    "qs_pg:qs_pg_placetype":"locality",
    "wof:name":"Ober-Erlosen",
    "wof:placetype":"neighbourhood",
    "wof:population":52
},
  "geometry": {"coordinates":[8.82443,47.31081],"type":"Point"}
}