{
  "type": "Feature",
  "properties": {
    "gn:admin1_code":"TG",
    "gn:admin2_code":"2015.0",
    "gn:admin3_code":"4501.0",
    "gn:asciiname":"Buhwil",
    "gn:country_code":"CH",
    "gn:dem":450,
    "gn:elevation":"455.0",
    "gn:feature_class":"P",
    "gn:feature_code":"PPL",
    "gn:name":"Buhwil",
    "gn:population":0,
    "gn:timezone":"Europe/Zurich",
    "iso:country":"CH",
    "wof:name":"Buhwil",
    "wof:placetype":"locality"
},
  "geometry": {"coordinates":[9.16758,47.52853],"type":"Point"}
}