{
  "type": "Feature",
  "properties": {
    "gn:admin1_code":"VD",
    "gn:admin2_code":"2221.0",
    "gn:admin3_code":"5409.0",
    "gn:asciiname":"Verchiez",
    "gn:country_code":"CH",
    "gn:dem":549,
    "gn:feature_class":"P",
    "gn:feature_code":"PPL",
    "gn:name":"Verchiez",
    "gn:population":0,
    "gn:timezone":"Europe/Zurich",
    "iso:country":"CH",
    "wof:lang_x_official":[
        "deu",
        "fra",
        "gsw",
        "ita"
    ],
    "wof:lang_x_spoken":[
        "deu",
        "fra",
        "gsw",
        "ita",
        "roh"
    ],
    "wof:name":"Verchiez",
    "wof:placetype":"neighbourhood"
},
  "geometry": {"coordinates":[6.98087,46.30597],"type":"Point"}
}