{
  "type": "Feature",
  "properties": {
    "gn:admin1_code":"AG",
    "gn:admin2_code":"1910.0",
    "gn:admin3_code":"4279.0",
    "gn:asciiname":"Riken",
    "gn:country_code":"CH",
    "gn:dem":434,
    "gn:elevation":"437.0",
    "gn:feature_class":"P",
    "gn:feature_code":"PPL",
    "gn:name":"Riken",
    "gn:population":0,
    "gn:timezone":"Europe/Zurich",
    "iso:country":"CH",
    "wof:name":"Riken",
    "wof:placetype":"locality"
},
  "geometry": {"coordinates":[7.85085,47.27798],"type":"Point"}
}