{
  "type": "Feature",
  "properties": {
    "gn:gn_country":"CH",
    "gn:gn_fcode":"PPLA3",
    "gn:gn_pop":290,
    "gn:population":290,
    "iso:country":"CH",
    "name:ara_x_preferred":[
        "\u063a\u0648\u062a\u0644\u064a\u0628\u0646"
    ],
    "name:baq_x_preferred":[
        "Gottlieben"
    ],
    "name:cat_x_preferred":[
        "Gottlieben"
    ],
    "name:chi_x_preferred":[
        "\u6208\u7279\u5229\u672c"
    ],
    "name:dut_x_preferred":[
        "Gottlieben"
    ],
    "name:eng_x_preferred":[
        "Gottlieben"
    ],
    "name:epo_x_preferred":[
        "Gottlieben"
    ],
    "name:fre_x_preferred":[
        "Gottlieben"
    ],
    "name:ger_x_preferred":[
        "Gottlieben"
    ],
    "name:gsw_x_preferred":[
        "Gottlieben"
    ],
    "name:hun_x_preferred":[
        "Gottlieben"
    ],
    "name:ita_x_preferred":[
        "Gottlieben"
    ],
    "name:kaz_x_preferred":[
        "\u0413\u043e\u0442\u0442\u043b\u0438\u0431\u0435\u043d"
    ],
    "name:lmo_x_preferred":[
        "Gottlieben"
    ],
    "name:may_x_preferred":[
        "Gottlieben"
    ],
    "name:nno_x_preferred":[
        "Gottlieben"
    ],
    "name:oci_x_preferred":[
        "Gottlieben"
    ],
    "name:pms_x_preferred":[
        "Gottlieben"
    ],
    "name:por_x_preferred":[
        "Gottlieben"
    ],
    "name:rus_x_preferred":[
        "\u0413\u043e\u0442\u0442\u043b\u0438\u0431\u0435\u043d"
    ],
    "name:spa_x_preferred":[
        "Gottlieben"
    ],
    "name:uzb_x_preferred":[
        "Gottlieben"
    ],
    "name:vol_x_preferred":[
        "Gottlieben"
    ],
    "name:war_x_preferred":[
        "Gottlieben"
    ],
    "qs_pg:aaroncc":"CH",
    "qs_pg:gn_country":"CH",
    "qs_pg:gn_fcode":"PPLA3",
    "qs_pg:gn_pop":290,
    "qs_pg:name":"Gottlieben",
    "qs_pg:name_adm0":"Schweiz",
    "qs_pg:name_adm1":"Kanton Thurgau",
    "qs_pg:photos":757,
    "qs_pg:photos_1k":153,
    "qs_pg:photos_9k":3,
    "qs_pg:photos_9r":6,
    "qs_pg:photos_all":757,
    "qs_pg:photos_sr":9,
    "qs_pg:pop_sr":2,
    "qs_pg:qs_pg_placetype":"locality",
    "qs_pg:qs_pg_placetype_gp":"Town",
    "qs_pg:woe_adm0":23424957,
    "woe:adm0_id":23424957,
    "woe:name_adm0":"Schweiz",
    "woe:name_adm1":"Kanton Thurgau",
    "woe:placetype":"Town",
    "wof:name":"Gottlieben",
    "wof:placetype":"locality",
    "wof:population":290
},
  "geometry": {"coordinates":[9.13245,47.66418],"type":"Point"}
}