{
  "type": "Feature",
  "properties": {
    "gn:admin1_code":"SZ",
    "gn:admin2_code":"506.0",
    "gn:admin3_code":"1368.0",
    "gn:asciiname":"Neuberg",
    "gn:country_code":"CH",
    "gn:dem":1102,
    "gn:feature_class":"P",
    "gn:feature_code":"PPLL",
    "gn:name":"Neuberg",
    "gn:population":0,
    "gn:timezone":"Europe/Zurich",
    "iso:country":"CH",
    "name:deu_x_preferred":[
        "Neuberg"
    ],
    "wof:name":"Neuberg",
    "wof:placetype":"neighbourhood"
},
  "geometry": {"coordinates":[8.78222,47.03715],"type":"Point"}
}