{
  "type": "Feature",
  "properties": {
    "gn:admin1_code":"TG",
    "gn:admin2_code":"2015.0",
    "gn:admin3_code":"4951.0",
    "gn:asciiname":"Rueueteli",
    "gn:country_code":"CH",
    "gn:dem":481,
    "gn:feature_class":"P",
    "gn:feature_code":"PPLL",
    "gn:name":"R\u00fc\u00fcteli",
    "gn:population":0,
    "gn:timezone":"Europe/Zurich",
    "iso:country":"CH",
    "name:deu_x_preferred":[
        "R\u00fc\u00fcteli"
    ],
    "wof:name":"Rueueteli",
    "wof:placetype":"neighbourhood"
},
  "geometry": {"coordinates":[9.06098,47.60162],"type":"Point"}
}