{
  "type": "Feature",
  "properties": {
    "gn:admin1_code":"SZ",
    "gn:admin2_code":"505.0",
    "gn:admin3_code":"1348.0",
    "gn:asciiname":"Hirzen",
    "gn:country_code":"CH",
    "gn:dem":1253,
    "gn:feature_class":"P",
    "gn:feature_code":"PPLL",
    "gn:name":"Hirzen",
    "gn:population":0,
    "gn:timezone":"Europe/Zurich",
    "iso:country":"CH",
    "name:deu_x_preferred":[
        "Hirzen"
    ],
    "wof:lang_x_official":[
        "deu",
        "fra",
        "gsw",
        "ita"
    ],
    "wof:lang_x_spoken":[
        "deu",
        "fra",
        "gsw",
        "ita",
        "roh"
    ],
    "wof:name":"Hirzen",
    "wof:placetype":"neighbourhood"
},
  "geometry": {"coordinates":[8.84605,47.12007],"type":"Point"}
}