{
  "type": "Feature",
  "properties": {
    "gn:admin1_code":"VD",
    "gn:admin2_code":"2224.0",
    "gn:admin3_code":"5873.0",
    "gn:asciiname":"Le Sechey",
    "gn:country_code":"CH",
    "gn:dem":1063,
    "gn:elevation":"1037.0",
    "gn:feature_class":"P",
    "gn:feature_code":"PPL",
    "gn:name":"Le S\u00e9chey",
    "gn:population":0,
    "gn:timezone":"Europe/Zurich",
    "iso:country":"CH",
    "wof:name":"Le Sechey",
    "wof:placetype":"locality"
},
  "geometry": {"coordinates":[6.3009,46.66142],"type":"Point"}
}