{
  "type": "Feature",
  "properties": {
    "gn:admin1_code":"TI",
    "gn:admin2_code":"2106.0",
    "gn:admin3_code":"5254.0",
    "gn:asciiname":"Spinirolo",
    "gn:country_code":"CH",
    "gn:dem":617,
    "gn:feature_class":"P",
    "gn:feature_code":"PPL",
    "gn:name":"Spinirolo",
    "gn:population":0,
    "gn:timezone":"Europe/Zurich",
    "iso:country":"CH",
    "name:ita_x_preferred":[
        "Spinirolo"
    ],
    "wof:name":"Spinirolo",
    "wof:placetype":"locality"
},
  "geometry": {"coordinates":[8.94028,45.89676],"type":"Point"}
}