{
  "type": "Feature",
  "properties": {
    "gn:country":"CH",
    "gn:fcode":"PPL",
    "gn:population":481,
    "iso:country":"CH",
    "name:cat_x_preferred":[
        "Cavergno"
    ],
    "name:ceb_x_preferred":[
        "Cavergno"
    ],
    "name:deu_x_preferred":[
        "Cavergno"
    ],
    "name:eng_x_preferred":[
        "Cavergno"
    ],
    "name:fra_x_preferred":[
        "Cavergno"
    ],
    "name:gle_x_preferred":[
        "Cavergno"
    ],
    "name:gsw_x_preferred":[
        "Cavergno"
    ],
    "name:hsb_x_preferred":[
        "Cavergno"
    ],
    "name:ita_x_preferred":[
        "Cavergno"
    ],
    "name:lmo_x_preferred":[
        "Cadvergn"
    ],
    "name:nld_x_preferred":[
        "Cavergno"
    ],
    "name:nob_x_preferred":[
        "Cavergno"
    ],
    "name:oci_x_preferred":[
        "Cavergno"
    ],
    "name:por_x_preferred":[
        "Cavergno"
    ],
    "name:swe_x_preferred":[
        "Cavergno"
    ],
    "qs_pg:aaroncc":"CH",
    "qs_pg:gn_country":"CH",
    "qs_pg:gn_fcode":"PPL",
    "qs_pg:gn_pop":481,
    "qs_pg:name":"Cavrono",
    "qs_pg:name_adm0":"Italia",
    "qs_pg:name_adm1":"Lombardia",
    "qs_pg:photos":7,
    "qs_pg:photos_1k":1,
    "qs_pg:photos_9k":1,
    "qs_pg:photos_9r":1,
    "qs_pg:photos_all":7,
    "qs_pg:photos_sr":1,
    "qs_pg:pop_sr":2,
    "qs_pg:qs_pg_placetype":"locality",
    "qs_pg:qs_pg_placetype_gp":"Town",
    "qs_pg:woe_adm0":23424853,
    "woe:adm0_id":23424853,
    "woe:name_adm0":"Italia",
    "woe:name_adm1":"Lombardia",
    "woe:placetype":"Town",
    "wof:name":"Cavrono",
    "wof:placetype":"neighbourhood",
    "wof:population":481
},
  "geometry": {"coordinates":[8.6062,46.34521],"type":"Point"}
}