{
  "type": "Feature",
  "properties": {
    "gn:country":"CH",
    "gn:fcode":"PPL",
    "gn:population":0,
    "iso:country":"CH",
    "name:ceb_x_preferred":[
        "San Giuseppe"
    ],
    "name:deu_x_preferred":[
        "San Giuseppe"
    ],
    "name:fra_x_preferred":[
        "San Giuseppe"
    ],
    "name:ita_x_preferred":[
        "San Giuseppe"
    ],
    "name:nld_x_preferred":[
        "San Giuseppe"
    ],
    "name:pol_x_preferred":[
        "\u015awi\u0119ty J\u00f3zef"
    ],
    "name:por_x_preferred":[
        "San Giuseppe"
    ],
    "name:roh_x_preferred":[
        "Sogn Giusep"
    ],
    "name:rus_x_preferred":[
        "\u0421\u0432\u044f\u0442\u043e\u0439 \u0414\u0436\u0443\u0437\u0435\u043f\u043f\u0435"
    ],
    "name:srp_x_preferred":[
        "San \u0110uzepe"
    ],
    "name:swe_x_preferred":[
        "San Giuseppe"
    ],
    "name:und_x_variant":[
        "San Giusep"
    ],
    "name:vie_x_preferred":[
        "Giuse"
    ],
    "qs_pg:aaroncc":"CH",
    "qs_pg:gn_country":"CH",
    "qs_pg:gn_fcode":"PPL",
    "qs_pg:gn_pop":0,
    "qs_pg:name":"San Giuseppe",
    "qs_pg:name_adm0":"Italia",
    "qs_pg:name_adm1":"Lombardia",
    "qs_pg:photos":36,
    "qs_pg:photos_1k":7,
    "qs_pg:photos_9k":1,
    "qs_pg:photos_9r":2,
    "qs_pg:photos_all":36,
    "qs_pg:photos_sr":2,
    "qs_pg:pop_sr":0,
    "qs_pg:qs_pg_placetype":"locality",
    "qs_pg:qs_pg_placetype_gp":"Town",
    "qs_pg:woe_adm0":23424853,
    "woe:adm0_id":23424853,
    "woe:name_adm0":"Italia",
    "woe:name_adm1":"Lombardia",
    "woe:placetype":"Town",
    "wof:name":"San Giuseppe",
    "wof:placetype":"neighbourhood"
},
  "geometry": {"coordinates":[9.08166,46.64303],"type":"Point"}
}