{
  "type": "Feature",
  "properties": {
    "gn:gn_country":"CH",
    "gn:gn_fcode":"PPL",
    "gn:gn_pop":762,
    "gn:population":762,
    "iso:country":"CH",
    "name:cat_x_preferred":[
        "R\u00fcnenberg"
    ],
    "name:chv_x_preferred":[
        "\u0420\u044e\u043d\u0435\u043d\u0431\u0435\u0440\u0433"
    ],
    "name:deu_x_preferred":[
        "R\u00fcnenberg"
    ],
    "name:eng_x_preferred":[
        "R\u00fcnenberg"
    ],
    "name:epo_x_preferred":[
        "R\u00fcnenberg"
    ],
    "name:eus_x_preferred":[
        "R\u00fcnenberg"
    ],
    "name:fra_x_preferred":[
        "R\u00fcnenberg"
    ],
    "name:gsw_x_preferred":[
        "R\u00fcnebrg"
    ],
    "name:hun_x_preferred":[
        "R\u00fcnenberg"
    ],
    "name:ita_x_preferred":[
        "R\u00fcnenberg"
    ],
    "name:kaz_x_preferred":[
        "\u0420\u044e\u043d\u0435\u043d\u0431\u0435\u0440\u0433"
    ],
    "name:lmo_x_preferred":[
        "R\u00fcnenberg"
    ],
    "name:msa_x_preferred":[
        "R\u00fcnenberg"
    ],
    "name:nld_x_preferred":[
        "R\u00fcnenberg"
    ],
    "name:nno_x_preferred":[
        "R\u00fcnenberg"
    ],
    "name:oci_x_preferred":[
        "R\u00fcnenberg"
    ],
    "name:rus_x_preferred":[
        "\u0420\u044e\u043d\u0435\u043d\u0431\u0435\u0440\u0433"
    ],
    "name:spa_x_preferred":[
        "R\u00fcnenberg"
    ],
    "name:sqi_x_preferred":[
        "R\u00fcnenberg"
    ],
    "name:swe_x_preferred":[
        "R\u00fcnenberg"
    ],
    "name:uzb_x_preferred":[
        "R\u00fcnenberg"
    ],
    "name:vol_x_preferred":[
        "R\u00fcnenberg"
    ],
    "name:war_x_preferred":[
        "R\u00fcnenberg"
    ],
    "name:zho_x_preferred":[
        "\u5442\u5ae9\u4f2f\u683c"
    ],
    "qs_pg:aaroncc":"CH",
    "qs_pg:gn_country":"CH",
    "qs_pg:gn_fcode":"PPL",
    "qs_pg:gn_pop":762,
    "qs_pg:name":"R\u00fcnenberg",
    "qs_pg:name_adm0":"Schweiz",
    "qs_pg:name_adm1":"Kanton Basel-Land",
    "qs_pg:photos":22,
    "qs_pg:photos_1k":4,
    "qs_pg:photos_9k":1,
    "qs_pg:photos_9r":1,
    "qs_pg:photos_all":22,
    "qs_pg:photos_sr":1,
    "qs_pg:pop_sr":2,
    "qs_pg:qs_pg_placetype":"locality",
    "qs_pg:qs_pg_placetype_gp":"Town",
    "qs_pg:woe_adm0":23424957,
    "woe:adm0_id":23424957,
    "woe:name_adm0":"Schweiz",
    "woe:name_adm1":"Kanton Basel-Land",
    "woe:placetype":"Town",
    "wof:name":"R\u00fcnenberg",
    "wof:placetype":"locality",
    "wof:population":762
},
  "geometry": {"coordinates":[7.8829,47.43477],"type":"Point"}
}