{
  "type": "Feature",
  "properties": {
    "gn:admin1_code":"VS",
    "gn:admin2_code":"2313.0",
    "gn:admin3_code":"6297.0",
    "gn:asciiname":"Ritti",
    "gn:cc2":"CH",
    "gn:country_code":"CH",
    "gn:dem":1288,
    "gn:feature_class":"P",
    "gn:feature_code":"PPL",
    "gn:name":"Ritti",
    "gn:population":0,
    "gn:timezone":"Europe/Zurich",
    "iso:country":"CH",
    "name:und_x_variant":[
        "Riti",
        "Ritti"
    ],
    "wof:name":"Ritti",
    "wof:placetype":"neighbourhood"
},
  "geometry": {"coordinates":[7.91667,46.28333],"type":"Point"}
}