{
  "type": "Feature",
  "properties": {
    "gn:admin1_code":"GR",
    "gn:admin2_code":"1850.0",
    "gn:admin3_code":"3603.0",
    "gn:asciiname":"Lunschania",
    "gn:country_code":"CH",
    "gn:dem":1060,
    "gn:feature_class":"P",
    "gn:feature_code":"PPL",
    "gn:name":"Lunschania",
    "gn:population":0,
    "gn:timezone":"Europe/Zurich",
    "iso:country":"CH",
    "name:roh_x_preferred":[
        "Lunschania"
    ],
    "wof:name":"Lunschania",
    "wof:placetype":"neighbourhood"
},
  "geometry": {"coordinates":[9.18942,46.66038],"type":"Point"}
}