{
  "type": "Feature",
  "properties": {
    "gn:admin1_code":"GR",
    "gn:admin2_code":"1851.0",
    "gn:admin3_code":"3701.0",
    "gn:asciiname":"Cazun",
    "gn:country_code":"CH",
    "gn:dem":1754,
    "gn:feature_class":"P",
    "gn:feature_code":"PPL",
    "gn:name":"Cazun",
    "gn:population":0,
    "gn:timezone":"Europe/Zurich",
    "iso:country":"CH",
    "name:roh_x_preferred":[
        "Cazun"
    ],
    "wof:lang_x_official":[
        "deu",
        "fra",
        "gsw",
        "ita"
    ],
    "wof:lang_x_spoken":[
        "deu",
        "fra",
        "gsw",
        "ita",
        "roh"
    ],
    "wof:name":"Cazun",
    "wof:placetype":"neighbourhood"
},
  "geometry": {"coordinates":[9.40411,46.59239],"type":"Point"}
}