{
  "type": "Feature",
  "properties": {
    "gn:admin1_code":"LU",
    "gn:admin2_code":"316.0",
    "gn:admin3_code":"1009.0",
    "gn:asciiname":"Obergrabehuesli",
    "gn:country_code":"CH",
    "gn:dem":646,
    "gn:feature_class":"P",
    "gn:feature_code":"PPLL",
    "gn:name":"Obergrabeh\u00fcsli",
    "gn:population":0,
    "gn:timezone":"Europe/Zurich",
    "iso:country":"CH",
    "name:deu_x_preferred":[
        "Obergrabeh\u00fcsli"
    ],
    "wof:name":"Obergrabehuesli",
    "wof:placetype":"neighbourhood"
},
  "geometry": {"coordinates":[8.07414,47.03594],"type":"Point"}
}