{
  "type": "Feature",
  "properties": {
    "gn:admin1_code":"TG",
    "gn:admin2_code":"2012.0",
    "gn:admin3_code":"4816.0",
    "gn:asciiname":"Bethlehem",
    "gn:country_code":"CH",
    "gn:dem":516,
    "gn:feature_class":"P",
    "gn:feature_code":"PPLL",
    "gn:name":"Bethlehem",
    "gn:population":0,
    "gn:timezone":"Europe/Zurich",
    "iso:country":"CH",
    "name:hbo_x_preferred":[
        "Bethlehem"
    ],
    "wof:name":"Bethlehem",
    "wof:placetype":"neighbourhood"
},
  "geometry": {"coordinates":[8.98635,47.61799],"type":"Point"}
}