{
  "type": "Feature",
  "properties": {
    "gn:admin1_code":"BE",
    "gn:admin2_code":"244.0",
    "gn:admin3_code":"995.0",
    "gn:asciiname":"Eichholz",
    "gn:country_code":"CH",
    "gn:dem":549,
    "gn:feature_class":"P",
    "gn:feature_code":"PPLL",
    "gn:name":"Eichholz",
    "gn:population":0,
    "gn:timezone":"Europe/Zurich",
    "iso:country":"CH",
    "name:deu_x_preferred":[
        "Eichholz"
    ],
    "wof:name":"Eichholz",
    "wof:placetype":"neighbourhood"
},
  "geometry": {"coordinates":[7.62729,47.25458],"type":"Point"}
}