{
  "type": "Feature",
  "properties": {
    "gn:admin1_code":"ZH",
    "gn:admin2_code":"103.0",
    "gn:admin3_code":"67.0",
    "gn:asciiname":"Blettliacker",
    "gn:country_code":"CH",
    "gn:dem":511,
    "gn:feature_class":"P",
    "gn:feature_code":"PPLL",
    "gn:name":"Blettliacker",
    "gn:population":0,
    "gn:timezone":"Europe/Zurich",
    "iso:country":"CH",
    "name:deu_x_preferred":[
        "Blettliacker"
    ],
    "wof:name":"Blettliacker",
    "wof:placetype":"neighbourhood"
},
  "geometry": {"coordinates":[8.52808,47.62136],"type":"Point"}
}