{
  "type": "Feature",
  "properties": {
    "gn:country":"CH",
    "gn:fcode":"PPL",
    "gn:population":18,
    "iso:country":"CH",
    "name:als_x_preferred":[
        "Rain"
    ],
    "name:cat_x_preferred":[
        "Rain"
    ],
    "name:ceb_x_preferred":[
        "Rain"
    ],
    "name:chv_x_preferred":[
        "\u0420\u0430\u0439\u043d"
    ],
    "name:deu_x_preferred":[
        "Rain"
    ],
    "name:eng_ca_x_preferred":[
        "Rain"
    ],
    "name:eng_gb_x_preferred":[
        "Rain"
    ],
    "name:eng_x_preferred":[
        "Rain"
    ],
    "name:epo_x_preferred":[
        "Rain"
    ],
    "name:eus_x_preferred":[
        "Rain"
    ],
    "name:fra_x_preferred":[
        "Rain"
    ],
    "name:gsw_x_preferred":[
        "Rain LU"
    ],
    "name:gsw_x_variant":[
        "Rain"
    ],
    "name:hun_x_preferred":[
        "Rain"
    ],
    "name:ita_x_preferred":[
        "Rain"
    ],
    "name:kaz_x_preferred":[
        "\u0420\u0430\u0439\u043d"
    ],
    "name:lmo_x_preferred":[
        "Rain"
    ],
    "name:msa_x_preferred":[
        "Rain"
    ],
    "name:nld_x_preferred":[
        "Rain"
    ],
    "name:nno_x_preferred":[
        "Rain"
    ],
    "name:oci_x_preferred":[
        "Rain"
    ],
    "name:roh_x_preferred":[
        "Rain"
    ],
    "name:ron_x_preferred":[
        "Rain"
    ],
    "name:rus_x_preferred":[
        "\u0420\u0430\u0439\u043d"
    ],
    "name:spa_x_preferred":[
        "Rain"
    ],
    "name:sqi_x_preferred":[
        "Rain"
    ],
    "name:swe_x_preferred":[
        "Rain"
    ],
    "name:uzb_x_preferred":[
        "Rain"
    ],
    "name:vec_x_preferred":[
        "Rain"
    ],
    "name:vol_x_preferred":[
        "Rain"
    ],
    "name:war_x_preferred":[
        "Rain"
    ],
    "name:zho_x_preferred":[
        "Rain"
    ],
    "qs_pg:aaroncc":"CH",
    "qs_pg:gn_country":"CH",
    "qs_pg:gn_fcode":"PPL",
    "qs_pg:gn_pop":18,
    "qs_pg:name":"Rain",
    "qs_pg:photos_9r":0,
    "qs_pg:photos_sr":0,
    "qs_pg:pop_sr":1,
    "qs_pg:qs_pg_placetype":"locality",
    "wof:lang_x_official":[
        "deu",
        "fra",
        "gsw",
        "ita"
    ],
    "wof:lang_x_spoken":[
        "deu",
        "fra",
        "gsw",
        "ita",
        "roh"
    ],
    "wof:name":"Rain",
    "wof:placetype":"neighbourhood",
    "wof:population":18
},
  "geometry": {"coordinates":[8.43326,47.23258],"type":"Point"}
}