{
  "type": "Feature",
  "properties": {
    "gn:gn_country":"CH",
    "gn:gn_fcode":"PPL",
    "gn:gn_pop":896,
    "gn:population":896,
    "iso:country":"CH",
    "name:alb_x_preferred":[
        "Grono"
    ],
    "name:baq_x_preferred":[
        "Grono"
    ],
    "name:cat_x_preferred":[
        "Grono"
    ],
    "name:chi_x_preferred":[
        "\u683c\u7f85\u8afe"
    ],
    "name:dut_x_preferred":[
        "Grono"
    ],
    "name:eng_x_preferred":[
        "Grono"
    ],
    "name:epo_x_preferred":[
        "Grono"
    ],
    "name:fin_x_preferred":[
        "Grono"
    ],
    "name:fre_x_preferred":[
        "Grono"
    ],
    "name:ger_x_preferred":[
        "Grono"
    ],
    "name:hun_x_preferred":[
        "Grono"
    ],
    "name:ind_x_preferred":[
        "Grono"
    ],
    "name:ita_x_preferred":[
        "Grono"
    ],
    "name:kaz_x_preferred":[
        "\u0413\u0440\u043e\u043d\u043e"
    ],
    "name:lmo_x_preferred":[
        "Gron"
    ],
    "name:may_x_preferred":[
        "Grono"
    ],
    "name:nno_x_preferred":[
        "Grono"
    ],
    "name:oci_x_preferred":[
        "Grono"
    ],
    "name:pms_x_preferred":[
        "Grono"
    ],
    "name:pol_x_preferred":[
        "Grono"
    ],
    "name:por_x_preferred":[
        "Grono"
    ],
    "name:roh_x_preferred":[
        "Grono"
    ],
    "name:rus_x_preferred":[
        "\u0413\u0440\u043e\u043d\u043e"
    ],
    "name:slv_x_preferred":[
        "Grono"
    ],
    "name:spa_x_preferred":[
        "Grono"
    ],
    "name:swe_x_preferred":[
        "Grono"
    ],
    "name:uzb_x_preferred":[
        "Grono"
    ],
    "name:vol_x_preferred":[
        "Grono"
    ],
    "name:war_x_preferred":[
        "Grono"
    ],
    "name:zho_x_preferred":[
        "\u683c\u7f85\u8afe"
    ],
    "qs_pg:aaroncc":"CH",
    "qs_pg:gn_country":"CH",
    "qs_pg:gn_fcode":"PPL",
    "qs_pg:gn_pop":896,
    "qs_pg:name":"Grono",
    "qs_pg:name_adm0":"Schweiz",
    "qs_pg:name_adm1":"Kanton Graub\u00fcnden",
    "qs_pg:photos":206,
    "qs_pg:photos_1k":42,
    "qs_pg:photos_9k":1,
    "qs_pg:photos_9r":4,
    "qs_pg:photos_all":206,
    "qs_pg:photos_sr":4,
    "qs_pg:pop_sr":2,
    "qs_pg:qs_pg_placetype":"locality",
    "qs_pg:qs_pg_placetype_gp":"Town",
    "qs_pg:woe_adm0":23424957,
    "woe:adm0_id":23424957,
    "woe:name_adm0":"Schweiz",
    "woe:name_adm1":"Kanton Graub\u00fcnden",
    "woe:placetype":"Town",
    "wof:name":"Grono",
    "wof:placetype":"locality",
    "wof:population":896
},
  "geometry": {"coordinates":[9.14926,46.24679],"type":"Point"}
}