{
  "type": "Feature",
  "properties": {
    "gn:admin1_code":"TI",
    "gn:admin2_code":"2105.0",
    "gn:admin3_code":"5192.0",
    "gn:asciiname":"Nendum",
    "gn:country_code":"CH",
    "gn:dem":1031,
    "gn:feature_class":"P",
    "gn:feature_code":"PPL",
    "gn:name":"Nendum",
    "gn:population":0,
    "gn:timezone":"Europe/Zurich",
    "iso:country":"CH",
    "name:ita_x_preferred":[
        "Nendum"
    ],
    "wof:name":"Nendum",
    "wof:placetype":"neighbourhood"
},
  "geometry": {"coordinates":[9.05933,46.07742],"type":"Point"}
}