{
  "type": "Feature",
  "properties": {
    "gn:gn_country":"CH",
    "gn:gn_fcode":"PPLX",
    "gn:gn_pop":361,
    "gn:population":361,
    "iso:country":"CH",
    "name:deu_x_preferred":[
        "Buchs ZH"
    ],
    "name:eng_x_preferred":[
        "Buchs (Dorf)"
    ],
    "name:eng_x_variant":[
        "Buchs / Buchs (Dorf)"
    ],
    "name:unk_x_variant":[
        "Buchs (Dorf)"
    ],
    "qs_pg:aaroncc":"CH",
    "qs_pg:gn_country":"CH",
    "qs_pg:gn_fcode":"PPLX",
    "qs_pg:gn_pop":361,
    "qs_pg:name":"Buchs / Buchs (Dorf)",
    "qs_pg:photos_9r":0,
    "qs_pg:photos_sr":0,
    "qs_pg:pop_sr":2,
    "qs_pg:qs_pg_placetype":"neighbourhood",
    "wof:name":"Buchs (Dorf)",
    "wof:placetype":"neighbourhood",
    "wof:population":361
},
  "geometry": {"coordinates":[8.43661,47.45876],"type":"Point"}
}