{
  "type": "Feature",
  "properties": {
    "gn:gn_country":"CH",
    "gn:gn_fcode":"PPLX",
    "gn:gn_pop":418,
    "gn:population":418,
    "iso:country":"CH",
    "name:eng_x_preferred":[
        "Erdb\u00fcel-Halden"
    ],
    "name:eng_x_variant":[
        "Seuzach Dorf / Erdb\u00fcel-Halden"
    ],
    "name:unk_x_variant":[
        "Erdb\u00fcel-Halden"
    ],
    "qs_pg:aaroncc":"CH",
    "qs_pg:gn_country":"CH",
    "qs_pg:gn_fcode":"PPLX",
    "qs_pg:gn_pop":418,
    "qs_pg:name":"Seuzach Dorf / Erdb\u00fcel-Halden",
    "qs_pg:photos_9r":0,
    "qs_pg:photos_sr":0,
    "qs_pg:pop_sr":2,
    "qs_pg:qs_pg_placetype":"neighbourhood",
    "wof:name":"Erdb\u00fcel-Halden",
    "wof:placetype":"neighbourhood",
    "wof:population":418
},
  "geometry": {"coordinates":[8.72992,47.54132],"type":"Point"}
}