{
  "type": "Feature",
  "properties": {
    "gn:gn_country":"CH",
    "gn:gn_fcode":"PPL",
    "gn:gn_pop":0,
    "iso:country":"CH",
    "name:eng_x_preferred":[
        "Pian San Giacomo"
    ],
    "name:ita_x_preferred":[
        "Pian San Giacomo"
    ],
    "name:lmo_x_preferred":[
        "Pian San Giacom"
    ],
    "name:nld_x_preferred":[
        "Pian San Giacomo"
    ],
    "name:unk_x_variant":[
        "San Giacomo"
    ],
    "qs_pg:aaroncc":"CH",
    "qs_pg:gn_country":"CH",
    "qs_pg:gn_fcode":"PPL",
    "qs_pg:gn_pop":0,
    "qs_pg:name":"Pian San Giacomo",
    "qs_pg:name_adm0":"Schweiz",
    "qs_pg:name_adm1":"Kanton Graub\u00fcnden",
    "qs_pg:photos":80,
    "qs_pg:photos_1k":16,
    "qs_pg:photos_9k":1,
    "qs_pg:photos_9r":3,
    "qs_pg:photos_all":80,
    "qs_pg:photos_sr":3,
    "qs_pg:pop_sr":0,
    "qs_pg:qs_pg_placetype":"locality",
    "qs_pg:qs_pg_placetype_gp":"Town",
    "qs_pg:woe_adm0":23424957,
    "woe:adm0_id":23424957,
    "woe:name_adm0":"Schweiz",
    "woe:name_adm1":"Kanton Graub\u00fcnden",
    "woe:placetype":"Town",
    "wof:name":"Pian San Giacomo",
    "wof:placetype":"neighbourhood"
},
  "geometry": {"coordinates":[9.22768,46.42213],"type":"Point"}
}