{
  "type": "Feature",
  "properties": {
    "gn:admin1_code":"BE",
    "gn:admin2_code":"245.0",
    "gn:admin3_code":"907.0",
    "gn:asciiname":"Steinen",
    "gn:country_code":"CH",
    "gn:dem":710,
    "gn:elevation":"713.0",
    "gn:feature_class":"P",
    "gn:feature_code":"PPL",
    "gn:name":"Steinen",
    "gn:population":0,
    "gn:timezone":"Europe/Zurich",
    "iso:country":"CH",
    "wof:name":"Steinen",
    "wof:placetype":"neighbourhood"
},
  "geometry": {"coordinates":[7.71817,46.90694000000001],"type":"Point"}
}