{
  "type": "Feature",
  "properties": {
    "gn:gn_country":"CH",
    "gn:gn_fcode":"PPL",
    "gn:gn_pop":504,
    "gn:population":504,
    "iso:country":"CH",
    "name:alb_x_preferred":[
        "Eriz"
    ],
    "name:baq_x_preferred":[
        "Eriz"
    ],
    "name:cat_x_preferred":[
        "Eriz"
    ],
    "name:chi_x_preferred":[
        "\u57c3\u91cc\u8328"
    ],
    "name:chv_x_preferred":[
        "\u042d\u0440\u0438\u0446"
    ],
    "name:deu_x_preferred":[
        "Eriz"
    ],
    "name:dut_x_preferred":[
        "Eriz"
    ],
    "name:eng_x_preferred":[
        "Eriz"
    ],
    "name:epo_x_preferred":[
        "Eriz"
    ],
    "name:fra_x_preferred":[
        "Eriz"
    ],
    "name:fre_x_preferred":[
        "Eriz"
    ],
    "name:ger_x_preferred":[
        "Eriz"
    ],
    "name:gsw_x_preferred":[
        "Eriz"
    ],
    "name:hun_x_preferred":[
        "Eriz"
    ],
    "name:ita_x_preferred":[
        "Eriz"
    ],
    "name:kaz_x_preferred":[
        "\u042d\u0440\u0438\u0446"
    ],
    "name:lmo_x_preferred":[
        "Eriz"
    ],
    "name:may_x_preferred":[
        "Eriz"
    ],
    "name:nno_x_preferred":[
        "Eriz"
    ],
    "name:oci_x_preferred":[
        "Eriz"
    ],
    "name:pms_x_preferred":[
        "Eriz"
    ],
    "name:por_x_preferred":[
        "Eriz"
    ],
    "name:roh_x_preferred":[
        "Eriz"
    ],
    "name:rus_x_preferred":[
        "\u042d\u0440\u0438\u0446"
    ],
    "name:spa_x_preferred":[
        "Eriz"
    ],
    "name:swe_x_preferred":[
        "Eriz"
    ],
    "name:vie_x_preferred":[
        "Eriz"
    ],
    "name:vol_x_preferred":[
        "Eriz"
    ],
    "name:war_x_preferred":[
        "Eriz"
    ],
    "name:zho_x_preferred":[
        "\u57c3\u91cc\u8328"
    ],
    "qs_pg:aaroncc":"CH",
    "qs_pg:gn_country":"CH",
    "qs_pg:gn_fcode":"PPL",
    "qs_pg:gn_pop":504,
    "qs_pg:name":"Eriz",
    "qs_pg:name_adm0":"Schweiz",
    "qs_pg:name_adm1":"Kanton Bern",
    "qs_pg:photos_9k":1,
    "qs_pg:photos_9r":1,
    "qs_pg:photos_all":1,
    "qs_pg:photos_sr":0,
    "qs_pg:pop_sr":2,
    "qs_pg:qs_pg_placetype":"locality",
    "qs_pg:qs_pg_placetype_gp":"Town",
    "qs_pg:woe_adm0":23424957,
    "woe:adm0_id":23424957,
    "woe:name_adm0":"Schweiz",
    "woe:name_adm1":"Kanton Bern",
    "woe:placetype":"Town",
    "wof:name":"Eriz",
    "wof:placetype":"locality",
    "wof:population":504
},
  "geometry": {"coordinates":[7.77102,46.78773],"type":"Point"}
}