{
  "type": "Feature",
  "properties": {
    "gn:admin1_code":"SG",
    "gn:admin2_code":"1721.0",
    "gn:admin3_code":"3444.0",
    "gn:asciiname":"Schachen",
    "gn:country_code":"CH",
    "gn:dem":614,
    "gn:feature_class":"P",
    "gn:feature_code":"PPLL",
    "gn:name":"Schachen",
    "gn:population":0,
    "gn:timezone":"Europe/Zurich",
    "iso:country":"CH",
    "name:deu_x_preferred":[
        "Schachen"
    ],
    "wof:name":"Schachen",
    "wof:placetype":"neighbourhood"
},
  "geometry": {"coordinates":[9.35096,47.46089],"type":"Point"}
}