{
  "type": "Feature",
  "properties": {
    "gn:gn_country":"CH",
    "gn:gn_fcode":"PPLL",
    "gn:gn_pop":36,
    "gn:population":36,
    "iso:country":"CH",
    "name:unk_x_variant":[
        "Scheug"
    ],
    "qs_pg:aaroncc":"CH",
    "qs_pg:gn_country":"CH",
    "qs_pg:gn_fcode":"PPLL",
    "qs_pg:gn_pop":36,
    "qs_pg:name":"Uetikon / Scheug",
    "qs_pg:photos_9r":0,
    "qs_pg:photos_sr":0,
    "qs_pg:pop_sr":1,
    "qs_pg:qs_pg_placetype":"locality",
    "wof:name":"Uetikon / Scheug",
    "wof:placetype":"neighbourhood",
    "wof:population":36
},
  "geometry": {"coordinates":[8.67545,47.26505],"type":"Point"}
}