{
  "type": "Feature",
  "properties": {
    "gn:admin1_code":"GR",
    "gn:admin2_code":"1846.0",
    "gn:admin3_code":"3791.0",
    "gn:asciiname":"Hotel Castell",
    "gn:country_code":"CH",
    "gn:dem":1804,
    "gn:feature_class":"P",
    "gn:feature_code":"PPL",
    "gn:name":"Hotel Castell",
    "gn:population":0,
    "gn:timezone":"Europe/Zurich",
    "iso:country":"CH",
    "name:fra_x_preferred":[
        "Hotel Castell"
    ],
    "wof:name":"Hotel Castell",
    "wof:placetype":"locality"
},
  "geometry": {"coordinates":[9.94901,46.59853],"type":"Point"}
}