{
  "type": "Feature",
  "properties": {
    "iso:country":"CH",
    "name:baq_x_preferred":[
        "L'Abbaye"
    ],
    "name:cat_x_preferred":[
        "L'Abbaye"
    ],
    "name:chi_x_preferred":[
        "\u62c9\u62dc"
    ],
    "name:dut_x_preferred":[
        "L'Abbaye"
    ],
    "name:eng_x_preferred":[
        "L'Abbaye"
    ],
    "name:epo_x_preferred":[
        "L'Abbaye"
    ],
    "name:fre_x_preferred":[
        "L'Abbaye"
    ],
    "name:frp_x_preferred":[
        "L\u2019Abayie"
    ],
    "name:ger_x_preferred":[
        "L\u2019Abbaye"
    ],
    "name:gsw_x_preferred":[
        "L\u2019Abbaye"
    ],
    "name:hun_x_preferred":[
        "L'Abbaye"
    ],
    "name:ita_x_preferred":[
        "L'Abbaye"
    ],
    "name:lmo_x_preferred":[
        "L'Abbaye"
    ],
    "name:may_x_preferred":[
        "L'Abbaye"
    ],
    "name:nno_x_preferred":[
        "L'Abbaye"
    ],
    "name:oci_x_preferred":[
        "L'Abbaye"
    ],
    "name:pol_x_preferred":[
        "L'Abbaye"
    ],
    "name:roh_x_preferred":[
        "L'Abbaye"
    ],
    "name:rum_x_preferred":[
        "L'Abbaye"
    ],
    "name:spa_x_preferred":[
        "L'Abbaye"
    ],
    "name:vec_x_preferred":[
        "L'Abbaye"
    ],
    "name:vie_x_preferred":[
        "L'Abbaye"
    ],
    "name:vol_x_preferred":[
        "L\u2019Abbaye"
    ],
    "qs_pg:aaroncc":"CH",
    "qs_pg:name":"L'Abbaye",
    "qs_pg:name_adm0":"Schweiz",
    "qs_pg:name_adm1":"Canton de Vaud",
    "qs_pg:photos":184,
    "qs_pg:photos_1k":37,
    "qs_pg:photos_9k":1,
    "qs_pg:photos_9r":4,
    "qs_pg:photos_all":184,
    "qs_pg:photos_sr":4,
    "qs_pg:pop_sr":0,
    "qs_pg:qs_pg_placetype":"locality",
    "qs_pg:qs_pg_placetype_gp":"Town",
    "qs_pg:woe_adm0":23424957,
    "woe:adm0_id":23424957,
    "woe:name_adm0":"Schweiz",
    "woe:name_adm1":"Canton de Vaud",
    "woe:placetype":"Town",
    "wof:name":"L'Abbaye",
    "wof:placetype":"locality"
},
  "geometry": {"coordinates":[6.322271,46.652794],"type":"Point"}
}