{
  "type": "Feature",
  "properties": {
    "gn:population":5415,
    "iso:country":"CH",
    "name:cat_x_preferred":[
        "Menziken"
    ],
    "name:deu_x_preferred":[
        "Menziken"
    ],
    "name:eng_x_preferred":[
        "Menziken"
    ],
    "name:epo_x_preferred":[
        "Menziken"
    ],
    "name:eus_x_preferred":[
        "Menziken"
    ],
    "name:fra_x_preferred":[
        "Menziken"
    ],
    "name:hun_x_preferred":[
        "Menziken"
    ],
    "name:ita_x_preferred":[
        "Menziken"
    ],
    "name:kaz_x_preferred":[
        "\u041c\u0435\u043d\u0446\u0438\u043a\u0435\u043d"
    ],
    "name:lav_x_preferred":[
        "Mencikene"
    ],
    "name:lmo_x_preferred":[
        "Menziken"
    ],
    "name:mkd_x_preferred":[
        "\u041c\u0435\u043d\u0446\u0438\u043a\u0435\u043d"
    ],
    "name:msa_x_preferred":[
        "Menziken"
    ],
    "name:nld_x_preferred":[
        "Menziken"
    ],
    "name:nno_x_preferred":[
        "Menziken"
    ],
    "name:oci_x_preferred":[
        "Menziken"
    ],
    "name:pms_x_preferred":[
        "Menziken"
    ],
    "name:pol_x_preferred":[
        "Menziken"
    ],
    "name:por_x_preferred":[
        "Menziken"
    ],
    "name:ron_x_preferred":[
        "Menziken"
    ],
    "name:rus_x_preferred":[
        "\u041c\u0435\u043d\u0446\u0438\u043a\u0435\u043d"
    ],
    "name:spa_x_preferred":[
        "Menziken"
    ],
    "name:sqi_x_preferred":[
        "Menziken"
    ],
    "name:swe_x_preferred":[
        "Menziken"
    ],
    "name:uzb_x_preferred":[
        "Menziken"
    ],
    "name:vol_x_preferred":[
        "Menziken"
    ],
    "name:war_x_preferred":[
        "Menziken"
    ],
    "qs:a0":"Schweiz#Suisse#Svizzera#Svizra",
    "qs:a1":"*Aargau",
    "qs:a1r":"0",
    "qs:adm0":"Schweiz#Suisse#Svizzera#Svizra",
    "qs:la_lc":"*",
    "qs:level":"locality",
    "qs:loc":"Menziken",
    "qs:loc_alt":"Menziken",
    "qs:pop":0,
    "qs:type":"buffered point",
    "wd:wordcount":1594,
    "wof:lang":[
        "ger"
    ],
    "wof:name":"Menziken",
    "wof:placetype":"locality",
    "wof:population":5415
},
  "geometry": {"coordinates":[8.188346,47.241935],"type":"Point"}
}