{
  "type": "Feature",
  "properties": {
    "gn:admin1_code":"TG",
    "gn:admin2_code":"2012.0",
    "gn:admin3_code":"4831.0",
    "gn:asciiname":"Sonnenberg",
    "gn:country_code":"CH",
    "gn:dem":445,
    "gn:feature_class":"P",
    "gn:feature_code":"PPLL",
    "gn:name":"Sonnenberg",
    "gn:population":0,
    "gn:timezone":"Europe/Zurich",
    "iso:country":"CH",
    "name:deu_x_preferred":[
        "Sonnenberg"
    ],
    "wof:name":"Sonnenberg",
    "wof:placetype":"neighbourhood"
},
  "geometry": {"coordinates":[9.01589,47.61045],"type":"Point"}
}