{
  "type": "Feature",
  "properties": {
    "gn:country":"CH",
    "gn:fcode":"PPL",
    "gn:population":28,
    "iso:country":"CH",
    "qs_pg:aaroncc":"CH",
    "qs_pg:gn_country":"CH",
    "qs_pg:gn_fcode":"PPL",
    "qs_pg:gn_pop":28,
    "qs_pg:name":"H\u00f6h",
    "qs_pg:name_adm0":"\u00d6sterreich",
    "qs_pg:name_adm1":"Vorarlberg",
    "qs_pg:photos":67,
    "qs_pg:photos_1k":14,
    "qs_pg:photos_9k":1,
    "qs_pg:photos_9r":2,
    "qs_pg:photos_all":67,
    "qs_pg:photos_sr":2,
    "qs_pg:pop_sr":1,
    "qs_pg:qs_pg_placetype":"locality",
    "qs_pg:qs_pg_placetype_gp":"Town",
    "qs_pg:woe_adm0":23424750,
    "woe:adm0_id":23424750,
    "woe:name_adm0":"\u00d6sterreich",
    "woe:name_adm1":"Vorarlberg",
    "woe:placetype":"Town",
    "wof:name":"H\u00f6h",
    "wof:placetype":"neighbourhood",
    "wof:population":28
},
  "geometry": {"coordinates":[8.93289,47.29126],"type":"Point"}
}