{
  "type": "Feature",
  "properties": {
    "gn:admin1_code":"BE",
    "gn:admin2_code":"241.0",
    "gn:admin3_code":"692.0",
    "gn:asciiname":"Eschert",
    "gn:country_code":"CH",
    "gn:dem":612,
    "gn:feature_class":"P",
    "gn:feature_code":"PPL",
    "gn:name":"Eschert",
    "gn:population":0,
    "gn:timezone":"Europe/Zurich",
    "iso:country":"CH",
    "name:kaz_x_preferred":[
        "\u042d\u0448\u0435\u0440\u0442"
    ],
    "name:rus_x_preferred":[
        "\u042d\u0448\u0435\u0440\u0442"
    ],
    "name:zho_x_preferred":[
        "\u57c3\u65af\u6b47\u7279"
    ],
    "wof:name":"Eschert",
    "wof:placetype":"locality"
},
  "geometry": {"coordinates":[7.40334,47.27503],"type":"Point"}
}