{
  "type": "Feature",
  "properties": {
    "gn:admin1_code":"GR",
    "gn:admin2_code":"1850.0",
    "gn:admin3_code":"3986.0",
    "gn:asciiname":"Selva",
    "gn:country_code":"CH",
    "gn:dem":1542,
    "gn:elevation":"1537.0",
    "gn:feature_class":"P",
    "gn:feature_code":"PPL",
    "gn:name":"Selva",
    "gn:population":0,
    "gn:timezone":"Europe/Zurich",
    "iso:country":"CH",
    "wof:name":"Selva",
    "wof:placetype":"neighbourhood"
},
  "geometry": {"coordinates":[8.72166,46.661],"type":"Point"}
}