{
  "type": "Feature",
  "properties": {
    "gn:gn_country":"CH",
    "gn:gn_fcode":"PPL",
    "gn:gn_pop":0,
    "iso:country":"CH",
    "name:dut_x_preferred":[
        "Lustdorf"
    ],
    "name:eng_x_preferred":[
        "Lustdorf"
    ],
    "name:fre_x_preferred":[
        "Lustdorf"
    ],
    "name:ger_x_preferred":[
        "Lustdorf"
    ],
    "name:rus_x_preferred":[
        "\u041b\u0443\u0441\u0442\u0434\u043e\u0440\u0444"
    ],
    "name:uzb_x_preferred":[
        "Lustdorf"
    ],
    "qs_pg:aaroncc":"CH",
    "qs_pg:gn_country":"CH",
    "qs_pg:gn_fcode":"PPL",
    "qs_pg:gn_pop":0,
    "qs_pg:name":"Lustdorf",
    "qs_pg:name_adm0":"Schweiz",
    "qs_pg:name_adm1":"Kanton Thurgau",
    "qs_pg:photos_9r":0,
    "qs_pg:photos_sr":0,
    "qs_pg:pop_sr":0,
    "qs_pg:qs_pg_placetype":"locality",
    "qs_pg:qs_pg_placetype_gp":"Town",
    "qs_pg:woe_adm0":23424957,
    "woe:adm0_id":23424957,
    "woe:name_adm0":"Schweiz",
    "woe:name_adm1":"Kanton Thurgau",
    "woe:placetype":"Town",
    "wof:name":"Lustdorf",
    "wof:placetype":"locality"
},
  "geometry": {"coordinates":[8.98812,47.55144],"type":"Point"}
}