{
  "type": "Feature",
  "properties": {
    "gn:gn_country":"CH",
    "gn:gn_fcode":"PPL",
    "gn:gn_pop":1321,
    "gn:population":1321,
    "iso:country":"CH",
    "name:cat_x_preferred":[
        "Seeberg"
    ],
    "name:deu_x_preferred":[
        "Seeberg BE"
    ],
    "name:eng_x_preferred":[
        "Seeberg"
    ],
    "name:epo_x_preferred":[
        "Seeberg BE"
    ],
    "name:eus_x_preferred":[
        "Seeberg"
    ],
    "name:fra_x_preferred":[
        "Seeberg"
    ],
    "name:gsw_x_preferred":[
        "Seeberg"
    ],
    "name:hun_x_preferred":[
        "Seeberg"
    ],
    "name:ita_x_preferred":[
        "Seeberg"
    ],
    "name:kaz_x_preferred":[
        "\u0417\u0435\u0435\u0431\u0435\u0440\u0433"
    ],
    "name:lmo_x_preferred":[
        "Seeberg"
    ],
    "name:msa_x_preferred":[
        "Seeberg"
    ],
    "name:nld_x_preferred":[
        "Seeberg"
    ],
    "name:nno_x_preferred":[
        "Seeberg"
    ],
    "name:oci_x_preferred":[
        "Seeberg"
    ],
    "name:rus_x_preferred":[
        "\u0417\u0435\u0435\u0431\u0435\u0440\u0433"
    ],
    "name:spa_x_preferred":[
        "Seeberg"
    ],
    "name:sqi_x_preferred":[
        "Seeberg"
    ],
    "name:swe_x_preferred":[
        "Seeberg"
    ],
    "name:vol_x_preferred":[
        "Seeberg"
    ],
    "name:war_x_preferred":[
        "Seeberg BE"
    ],
    "name:zho_x_preferred":[
        "\u585e\u8c9d\u683c"
    ],
    "qs_pg:aaroncc":"CH",
    "qs_pg:gn_country":"CH",
    "qs_pg:gn_fcode":"PPL",
    "qs_pg:gn_pop":1321,
    "qs_pg:name":"Seeberg",
    "qs_pg:photos_9r":0,
    "qs_pg:photos_sr":0,
    "qs_pg:pop_sr":3,
    "qs_pg:qs_pg_placetype":"locality",
    "wof:name":"Seeberg",
    "wof:placetype":"locality",
    "wof:population":1321
},
  "geometry": {"coordinates":[7.66665,47.15505],"type":"Point"}
}