{
  "type": "Feature",
  "properties": {
    "gn:admin1_code":"VS",
    "gn:admin2_code":"2305.0",
    "gn:admin3_code":"6082.0",
    "gn:asciiname":"Blignou (Ayent)",
    "gn:country_code":"CH",
    "gn:dem":980,
    "gn:feature_class":"P",
    "gn:feature_code":"PPL",
    "gn:name":"Blignou (Ayent)",
    "gn:population":0,
    "gn:timezone":"Europe/Zurich",
    "iso:country":"CH",
    "wof:name":"Blignou (Ayent)",
    "wof:placetype":"locality"
},
  "geometry": {"coordinates":[7.40118,46.27337],"type":"Point"}
}