{
  "type": "Feature",
  "properties": {
    "gn:admin1_code":"TG",
    "gn:admin2_code":"2013.0",
    "gn:admin3_code":"4656.0",
    "gn:asciiname":"Lire",
    "gn:country_code":"CH",
    "gn:dem":448,
    "gn:feature_class":"P",
    "gn:feature_code":"PPLL",
    "gn:name":"Lire",
    "gn:population":0,
    "gn:timezone":"Europe/Zurich",
    "iso:country":"CH",
    "name:deu_x_preferred":[
        "Lire"
    ],
    "name:fra_x_preferred":[
        "Lire"
    ],
    "name:nld_x_preferred":[
        "Lire"
    ],
    "name:nor_x_preferred":[
        "Lire"
    ],
    "name:por_x_preferred":[
        "Lire"
    ],
    "name:ukr_x_preferred":[
        "\u041b\u0456\u0440\u0435"
    ],
    "wof:name":"Lire",
    "wof:placetype":"neighbourhood"
},
  "geometry": {"coordinates":[9.30204,47.59242],"type":"Point"}
}