{
  "type": "Feature",
  "properties": {
    "gn:gn_country":"CH",
    "gn:gn_fcode":"PPL",
    "gn:gn_pop":2213,
    "gn:population":2213,
    "iso:country":"CH",
    "name:bul_x_preferred":[
        "\u041c\u043e\u0433\u0435\u043b\u0441\u0431\u0435\u0440\u0433"
    ],
    "name:cat_x_preferred":[
        "Mogelsberg"
    ],
    "name:dut_x_preferred":[
        "Mogelsberg"
    ],
    "name:eng_x_preferred":[
        "Mogelsberg"
    ],
    "name:epo_x_preferred":[
        "Mogelsberg"
    ],
    "name:fre_x_preferred":[
        "Mogelsberg"
    ],
    "name:ger_x_preferred":[
        "Mogelsberg"
    ],
    "name:ita_x_preferred":[
        "Mogelsberg"
    ],
    "name:kaz_x_preferred":[
        "\u041c\u043e\u0433\u0435\u043b\u044c\u0441\u0431\u0435\u0440\u0433"
    ],
    "name:pms_x_preferred":[
        "Mogelsberg"
    ],
    "name:por_x_preferred":[
        "Mogelsberg"
    ],
    "name:rus_x_preferred":[
        "\u041c\u043e\u0433\u0435\u043b\u044c\u0441\u0431\u0435\u0440\u0433"
    ],
    "name:spa_x_preferred":[
        "Mogelsberg"
    ],
    "name:swe_x_preferred":[
        "Mogelsberg"
    ],
    "name:uzb_x_preferred":[
        "Mogelsberg"
    ],
    "name:vol_x_preferred":[
        "Mogelsberg"
    ],
    "qs_pg:aaroncc":"CH",
    "qs_pg:gn_country":"CH",
    "qs_pg:gn_fcode":"PPL",
    "qs_pg:gn_pop":2213,
    "qs_pg:name":"Mogelsberg",
    "qs_pg:name_adm0":"Schweiz",
    "qs_pg:name_adm1":"Kanton St. Gallen",
    "qs_pg:photos_9k":1,
    "qs_pg:photos_9r":1,
    "qs_pg:photos_all":1,
    "qs_pg:photos_sr":0,
    "qs_pg:pop_sr":4,
    "qs_pg:qs_pg_placetype":"locality",
    "qs_pg:qs_pg_placetype_gp":"Town",
    "qs_pg:woe_adm0":23424957,
    "woe:adm0_id":23424957,
    "woe:name_adm0":"Schweiz",
    "woe:name_adm1":"Kanton St. Gallen",
    "woe:placetype":"Town",
    "wof:name":"Mogelsberg",
    "wof:placetype":"locality",
    "wof:population":2213
},
  "geometry": {"coordinates":[9.13541,47.36222],"type":"Point"}
}