{
  "type": "Feature",
  "properties": {
    "gn:gn_country":"CH",
    "gn:gn_fcode":"PPLX",
    "gn:gn_pop":476,
    "gn:population":476,
    "iso:country":"CH",
    "name:unk_x_variant":[
        "Oberdorf"
    ],
    "qs_pg:aaroncc":"CH",
    "qs_pg:gn_country":"CH",
    "qs_pg:gn_fcode":"PPLX",
    "qs_pg:gn_pop":476,
    "qs_pg:name":"Obermeilen / Oberdorf",
    "qs_pg:photos_9r":0,
    "qs_pg:photos_sr":0,
    "qs_pg:pop_sr":2,
    "qs_pg:qs_pg_placetype":"neighbourhood",
    "wof:name":"Obermeilen / Oberdorf",
    "wof:placetype":"neighbourhood",
    "wof:population":476
},
  "geometry": {"coordinates":[8.6564,47.26698],"type":"Point"}
}