{
  "type": "Feature",
  "properties": {
    "gn:country":"CH",
    "gn:fcode":"PPLX",
    "gn:population":476,
    "iso:country":"CH",
    "name:als_x_preferred":[
        "Oberdorf"
    ],
    "name:bre_x_preferred":[
        "Oberdorf"
    ],
    "name:ceb_x_preferred":[
        "Oberdorf"
    ],
    "name:deu_x_preferred":[
        "Oberdorf"
    ],
    "name:eng_x_preferred":[
        "Oberdorf"
    ],
    "name:eng_x_variant":[
        "Obermeilen / Oberdorf"
    ],
    "name:epo_x_preferred":[
        "Oberdorf"
    ],
    "name:eus_x_preferred":[
        "Oberdorf"
    ],
    "name:fra_x_preferred":[
        "Oberdorf"
    ],
    "name:hun_x_preferred":[
        "Oberdorf"
    ],
    "name:ita_x_preferred":[
        "Oberdorf"
    ],
    "name:kor_x_preferred":[
        "\uc624\ubc84\ub3c4\ub974\ud504"
    ],
    "name:nld_x_preferred":[
        "Oberdorf"
    ],
    "name:pms_x_preferred":[
        "Oberdorf"
    ],
    "name:pol_x_preferred":[
        "Oberdorf"
    ],
    "name:por_x_preferred":[
        "Oberdorf"
    ],
    "name:ron_x_preferred":[
        "Oberdorf"
    ],
    "name:rus_x_preferred":[
        "\u041e\u0431\u0435\u0440\u0434\u043e\u0440\u0444"
    ],
    "name:spa_x_preferred":[
        "Oberdorf"
    ],
    "name:swe_x_preferred":[
        "Oberdorf"
    ],
    "qs_pg:aaroncc":"CH",
    "qs_pg:gn_country":"CH",
    "qs_pg:gn_fcode":"PPLX",
    "qs_pg:gn_pop":476,
    "qs_pg:name":"Obermeilen / Oberdorf",
    "qs_pg:photos_9r":0,
    "qs_pg:photos_sr":0,
    "qs_pg:pop_sr":2,
    "qs_pg:qs_pg_placetype":"neighbourhood",
    "wof:name":"Oberdorf",
    "wof:placetype":"neighbourhood",
    "wof:population":476
},
  "geometry": {"coordinates":[8.6564,47.26698],"type":"Point"}
}