{
  "type": "Feature",
  "properties": {
    "gn:country":"CH",
    "gn:fcode":"PPLL",
    "gn:population":8,
    "iso:country":"CH",
    "name:als_x_preferred":[
        "Rickenbach"
    ],
    "name:ceb_x_preferred":[
        "Rickenbach"
    ],
    "name:deu_x_preferred":[
        "Rickenbach"
    ],
    "name:epo_x_preferred":[
        "Rickenbach"
    ],
    "name:eus_x_preferred":[
        "Rickenbach"
    ],
    "name:fra_x_preferred":[
        "Rickenbach"
    ],
    "name:ita_x_preferred":[
        "Rickenbach"
    ],
    "name:lmo_x_preferred":[
        "Rickenbach"
    ],
    "name:nld_x_preferred":[
        "Rickenbach"
    ],
    "name:pol_x_preferred":[
        "Rickenbach"
    ],
    "name:por_x_preferred":[
        "Rickenbach"
    ],
    "name:rus_x_preferred":[
        "\u0420\u0438\u043a\u043a\u0435\u043d\u0431\u0430\u0445"
    ],
    "name:spa_x_preferred":[
        "Rickenbach"
    ],
    "name:swe_x_preferred":[
        "Rickenbach"
    ],
    "name:vol_x_preferred":[
        "Rickenbach"
    ],
    "qs_pg:aaroncc":"CH",
    "qs_pg:gn_country":"CH",
    "qs_pg:gn_fcode":"PPLL",
    "qs_pg:gn_pop":8,
    "qs_pg:name":"Rickenbach",
    "qs_pg:photos_9r":0,
    "qs_pg:photos_sr":0,
    "qs_pg:pop_sr":1,
    "qs_pg:qs_pg_placetype":"locality",
    "wof:name":"Rickenbach",
    "wof:placetype":"neighbourhood",
    "wof:population":8
},
  "geometry": {"coordinates":[8.89425,47.27779],"type":"Point"}
}