{
  "type": "Feature",
  "properties": {
    "gn:gn_country":"CH",
    "gn:gn_fcode":"PPL",
    "gn:gn_pop":753,
    "gn:population":753,
    "iso:country":"CH",
    "name:alb_x_preferred":[
        "Agarn"
    ],
    "name:baq_x_preferred":[
        "Agarn"
    ],
    "name:cat_x_preferred":[
        "Agarn"
    ],
    "name:chi_x_preferred":[
        "\u963f\u52a0\u6069"
    ],
    "name:dut_x_preferred":[
        "Agarn"
    ],
    "name:eng_x_preferred":[
        "Agarn"
    ],
    "name:epo_x_preferred":[
        "Agarn"
    ],
    "name:fre_x_preferred":[
        "Agarn"
    ],
    "name:ger_x_preferred":[
        "Agarn"
    ],
    "name:glg_x_preferred":[
        "Agarn"
    ],
    "name:gsw_x_preferred":[
        "Agarn"
    ],
    "name:hun_x_preferred":[
        "Agarn"
    ],
    "name:ita_x_preferred":[
        "Agarn"
    ],
    "name:lmo_x_preferred":[
        "Agarn"
    ],
    "name:may_x_preferred":[
        "Agarn"
    ],
    "name:nno_x_preferred":[
        "Agarn"
    ],
    "name:oci_x_preferred":[
        "Agarn"
    ],
    "name:pms_x_preferred":[
        "Agarn"
    ],
    "name:por_x_preferred":[
        "Agarn"
    ],
    "name:roh_x_preferred":[
        "Agarn"
    ],
    "name:spa_x_preferred":[
        "Agarn"
    ],
    "name:swe_x_preferred":[
        "Agarn"
    ],
    "name:vie_x_preferred":[
        "Agarn"
    ],
    "name:vol_x_preferred":[
        "Agarn"
    ],
    "name:war_x_preferred":[
        "Agarn"
    ],
    "name:zho_x_preferred":[
        "\u963f\u52a0\u6069"
    ],
    "qs_pg:aaroncc":"CH",
    "qs_pg:gn_country":"CH",
    "qs_pg:gn_fcode":"PPL",
    "qs_pg:gn_pop":753,
    "qs_pg:name":"Agarn",
    "qs_pg:name_adm0":"Schweiz",
    "qs_pg:name_adm1":"Canton de Valais",
    "qs_pg:photos":105,
    "qs_pg:photos_1k":21,
    "qs_pg:photos_9k":1,
    "qs_pg:photos_9r":3,
    "qs_pg:photos_all":105,
    "qs_pg:photos_sr":3,
    "qs_pg:pop_sr":2,
    "qs_pg:qs_pg_placetype":"locality",
    "qs_pg:qs_pg_placetype_gp":"Town",
    "qs_pg:woe_adm0":23424957,
    "woe:adm0_id":23424957,
    "woe:name_adm0":"Schweiz",
    "woe:name_adm1":"Canton de Valais",
    "woe:placetype":"Town",
    "wof:name":"Agarn",
    "wof:placetype":"locality",
    "wof:population":753
},
  "geometry": {"coordinates":[7.66322,46.29749],"type":"Point"}
}