{
  "type": "Feature",
  "properties": {
    "gn:admin1_code":"GR",
    "gn:admin2_code":"1846.0",
    "gn:admin3_code":"3791.0",
    "gn:asciiname":"Acla dal Spih",
    "gn:country_code":"CH",
    "gn:dem":1945,
    "gn:feature_class":"P",
    "gn:feature_code":"PPL",
    "gn:name":"Acla dal Spih",
    "gn:population":0,
    "gn:timezone":"Europe/Zurich",
    "iso:country":"CH",
    "name:roh_x_preferred":[
        "Acla dal Spih"
    ],
    "wof:name":"Acla dal Spih",
    "wof:placetype":"locality"
},
  "geometry": {"coordinates":[9.94917,46.6053],"type":"Point"}
}