{
  "type": "Feature",
  "properties": {
    "gn:admin1_code":"BE",
    "gn:admin2_code":"245.0",
    "gn:admin3_code":"410.0",
    "gn:asciiname":"Hoechstetten",
    "gn:country_code":"CH",
    "gn:dem":461,
    "gn:feature_class":"P",
    "gn:feature_code":"PPL",
    "gn:name":"H\u00f6chstetten",
    "gn:population":0,
    "gn:timezone":"Europe/Zurich",
    "iso:country":"CH",
    "name:und_x_variant":[
        "H\u00f6chstetten"
    ],
    "wof:name":"Hoechstetten",
    "wof:placetype":"locality"
},
  "geometry": {"coordinates":[7.63134,47.14505],"type":"Point"}
}