{
  "type": "Feature",
  "properties": {
    "iso:country":"CH",
    "name:fra_x_preferred":[
        "H\u00f4pital"
    ],
    "wof:name":"Hopital",
    "wof:placetype":"neighbourhood"
},
  "geometry": {"coordinates":[6.14964383651242,46.19380906798343],"type":"Point"}
}