{
  "type": "Feature",
  "properties": {
    "gn:admin1_code":"GR",
    "gn:admin2_code":"1849.0",
    "gn:admin3_code":"3961.0",
    "gn:asciiname":"Ueberlandquart",
    "gn:country_code":"CH",
    "gn:dem":1089,
    "gn:feature_class":"P",
    "gn:feature_code":"PPL",
    "gn:name":"Ueberlandquart",
    "gn:population":0,
    "gn:timezone":"Europe/Zurich",
    "iso:country":"CH",
    "wof:name":"Ueberlandquart",
    "wof:placetype":"neighbourhood"
},
  "geometry": {"coordinates":[9.61667,46.95],"type":"Point"}
}