{
  "type": "Feature",
  "properties": {
    "gn:admin1_code":"TI",
    "gn:admin2_code":"2105.0",
    "gn:admin3_code":"5208.0",
    "gn:asciiname":"Magi",
    "gn:country_code":"CH",
    "gn:dem":425,
    "gn:feature_class":"P",
    "gn:feature_code":"PPL",
    "gn:name":"Magi",
    "gn:population":0,
    "gn:timezone":"Europe/Zurich",
    "iso:country":"CH",
    "name:ara_x_preferred":[
        "\u0645\u0648\u063a"
    ],
    "name:aze_x_preferred":[
        "Maqlar"
    ],
    "name:cat_x_preferred":[
        "Magus"
    ],
    "name:deu_x_preferred":[
        "Magier"
    ],
    "name:fin_x_preferred":[
        "Maagi"
    ],
    "name:fra_x_preferred":[
        "Mage"
    ],
    "name:hin_x_preferred":[
        "\u092e\u093e\u0917\u0940"
    ],
    "name:hrv_x_preferred":[
        "Magi"
    ],
    "name:hun_x_preferred":[
        "M\u00e1gus"
    ],
    "name:hye_x_preferred":[
        "\u0544\u0578\u0563"
    ],
    "name:ido_x_preferred":[
        "Mago"
    ],
    "name:ind_x_preferred":[
        "Majus"
    ],
    "name:ita_x_preferred":[
        "Magi"
    ],
    "name:khm_x_preferred":[
        "\u17a0\u17c4\u179a\u17b6\u1785\u17b6\u179a\u17d2\u1799"
    ],
    "name:kur_x_preferred":[
        "Mux"
    ],
    "name:mlg_x_preferred":[
        "Magy"
    ],
    "name:msa_x_preferred":[
        "Majus"
    ],
    "name:oci_x_preferred":[
        "Mague"
    ],
    "name:pol_x_preferred":[
        "Mag"
    ],
    "name:por_x_preferred":[
        "Mago"
    ],
    "name:ron_x_preferred":[
        "Mag"
    ],
    "name:rus_x_preferred":[
        "\u041c\u0430\u0433\u0438"
    ],
    "name:scn_x_preferred":[
        "Magu"
    ],
    "name:slk_x_preferred":[
        "M\u00e1g"
    ],
    "name:swe_x_preferred":[
        "Magier"
    ],
    "name:ukr_x_preferred":[
        "\u041c\u0430\u0433"
    ],
    "wof:name":"Magi",
    "wof:placetype":"neighbourhood"
},
  "geometry": {"coordinates":[8.94117,46.04688],"type":"Point"}
}