{
  "type": "Feature",
  "properties": {
    "gn:admin1_code":"TI",
    "gn:admin2_code":"2105.0",
    "gn:admin3_code":"5208.0",
    "gn:asciiname":"Magi",
    "gn:country_code":"CH",
    "gn:dem":425,
    "gn:feature_class":"P",
    "gn:feature_code":"PPL",
    "gn:name":"Magi",
    "gn:population":0,
    "gn:timezone":"Europe/Zurich",
    "iso:country":"CH",
    "name:ita_x_preferred":[
        "Magi"
    ],
    "wof:name":"Magi",
    "wof:placetype":"neighbourhood"
},
  "geometry": {"coordinates":[8.94117,46.04688],"type":"Point"}
}