{
  "type": "Feature",
  "properties": {
    "gn:admin1_code":"ZH",
    "gn:admin2_code":"103.0",
    "gn:admin3_code":"67.0",
    "gn:asciiname":"Wisetal",
    "gn:country_code":"CH",
    "gn:dem":434,
    "gn:feature_class":"P",
    "gn:feature_code":"PPLL",
    "gn:name":"Wisetal",
    "gn:population":0,
    "gn:timezone":"Europe/Zurich",
    "iso:country":"CH",
    "name:deu_x_preferred":[
        "Wisetal"
    ],
    "wof:name":"Wisetal",
    "wof:placetype":"neighbourhood"
},
  "geometry": {"coordinates":[8.55882,47.6064],"type":"Point"}
}