{
  "type": "Feature",
  "properties": {
    "gn:gn_country":"CH",
    "gn:gn_fcode":"PPL",
    "gn:gn_pop":1221,
    "gn:population":1221,
    "iso:country":"CH",
    "name:cat_x_preferred":[
        "Wildhaus"
    ],
    "name:ces_x_preferred":[
        "Wildhaus"
    ],
    "name:cym_x_preferred":[
        "Wildhaus"
    ],
    "name:deu_x_preferred":[
        "Wildhaus SG"
    ],
    "name:deu_x_variant":[
        "Wildhaus"
    ],
    "name:eng_x_preferred":[
        "Wildhaus"
    ],
    "name:epo_x_preferred":[
        "Wildhaus"
    ],
    "name:fra_x_preferred":[
        "Wildhaus"
    ],
    "name:hye_x_preferred":[
        "\u054e\u056b\u056c\u0564\u0570\u0561\u0578\u0582\u057d"
    ],
    "name:ita_x_preferred":[
        "Wildhaus"
    ],
    "name:kaz_x_preferred":[
        "\u0412\u0438\u043b\u044c\u0434\u0445\u0430\u0443\u0441"
    ],
    "name:nld_x_preferred":[
        "Wildhaus"
    ],
    "name:nno_x_preferred":[
        "Wildhaus"
    ],
    "name:nob_x_preferred":[
        "Wildhaus"
    ],
    "name:pms_x_preferred":[
        "Wildhaus"
    ],
    "name:pnb_x_preferred":[
        "\u0648\u0627\u0626\u0644\u0688\u06c1\u0627\u0624\u0633"
    ],
    "name:pol_x_preferred":[
        "Wildhaus"
    ],
    "name:por_x_preferred":[
        "Wildhaus"
    ],
    "name:ron_x_preferred":[
        "Wildhaus"
    ],
    "name:rus_x_preferred":[
        "\u0412\u0438\u043b\u044c\u0434\u0445\u0430\u0443\u0441"
    ],
    "name:spa_x_preferred":[
        "Wildhaus"
    ],
    "name:swe_x_preferred":[
        "Wildhaus"
    ],
    "name:uzb_x_preferred":[
        "Wildhaus"
    ],
    "name:vol_x_preferred":[
        "Wildhaus"
    ],
    "name:zho_x_preferred":[
        "\u5a01\u5fb7\u8d6b\u65af\u57ce"
    ],
    "qs_pg:aaroncc":"CH",
    "qs_pg:gn_country":"CH",
    "qs_pg:gn_fcode":"PPL",
    "qs_pg:gn_pop":1221,
    "qs_pg:name":"Wildhaus",
    "qs_pg:name_adm0":"Schweiz",
    "qs_pg:name_adm1":"Kanton St. Gallen",
    "qs_pg:photos":309,
    "qs_pg:photos_1k":63,
    "qs_pg:photos_9k":1,
    "qs_pg:photos_9r":5,
    "qs_pg:photos_all":309,
    "qs_pg:photos_sr":5,
    "qs_pg:pop_sr":3,
    "qs_pg:qs_pg_placetype":"locality",
    "qs_pg:qs_pg_placetype_gp":"Town",
    "qs_pg:woe_adm0":23424957,
    "woe:adm0_id":23424957,
    "woe:name_adm0":"Schweiz",
    "woe:name_adm1":"Kanton St. Gallen",
    "woe:placetype":"Town",
    "wof:name":"Wildhaus",
    "wof:placetype":"locality",
    "wof:population":1221
},
  "geometry": {"coordinates":[9.35488,47.20148],"type":"Point"}
}