{
  "type": "Feature",
  "properties": {
    "gn:population":3636,
    "iso:country":"CH",
    "name:als_x_preferred":[
        "Kehrsatz"
    ],
    "name:cat_x_preferred":[
        "Kehrsatz"
    ],
    "name:ceb_x_preferred":[
        "Kehrsatz"
    ],
    "name:chv_x_preferred":[
        "\u041a\u0435\u0440\u0437\u0430\u0446"
    ],
    "name:deu_x_preferred":[
        "Kehrsatz"
    ],
    "name:eng_x_preferred":[
        "Kehrsatz"
    ],
    "name:epo_x_preferred":[
        "Kehrsatz"
    ],
    "name:eus_x_preferred":[
        "Kehrsatz"
    ],
    "name:fra_x_preferred":[
        "Kehrsatz"
    ],
    "name:gsw_x_preferred":[
        "Ch\u00e4sitz"
    ],
    "name:hun_x_preferred":[
        "Kehrsatz"
    ],
    "name:ita_x_preferred":[
        "Kehrsatz"
    ],
    "name:kaz_x_preferred":[
        "\u041a\u0435\u0440\u0437\u0430\u0446"
    ],
    "name:lmo_x_preferred":[
        "Kehrsatz"
    ],
    "name:msa_x_preferred":[
        "Kehrsatz"
    ],
    "name:nld_x_preferred":[
        "Kehrsatz"
    ],
    "name:nno_x_preferred":[
        "Kehrsatz"
    ],
    "name:oci_x_preferred":[
        "Kehrsatz"
    ],
    "name:pms_x_preferred":[
        "Kehrsatz"
    ],
    "name:pol_x_preferred":[
        "Kehrsatz"
    ],
    "name:por_x_preferred":[
        "Kehrsatz"
    ],
    "name:rus_x_preferred":[
        "\u041a\u0435\u0440\u0437\u0430\u0446"
    ],
    "name:spa_x_preferred":[
        "Kehrsatz"
    ],
    "name:sqi_x_preferred":[
        "Kehrsatz"
    ],
    "name:srp_x_preferred":[
        "Kerzac"
    ],
    "name:swe_x_preferred":[
        "Kehrsatz"
    ],
    "name:vie_x_preferred":[
        "Kehrsatz"
    ],
    "name:vol_x_preferred":[
        "Kehrsatz"
    ],
    "name:war_x_preferred":[
        "Kehrsatz"
    ],
    "name:zho_x_preferred":[
        "\u514b\u723e\u85a9\u8328"
    ],
    "qs:gn_adm0_cc":"CH",
    "qs:gn_fcode":"PPL",
    "qs:gn_local":2661552,
    "qs:gn_nam_loc":"Bern",
    "qs:gn_namadm1":"BE",
    "qs:gn_name":"Kehrsatz",
    "qs:local_max":19074,
    "qs:local_sum":54499,
    "qs:localhoods":30,
    "qs:name":"Kehrsatz",
    "qs:name_adm0":"Schweiz",
    "qs:name_adm1":"Kanton Bern",
    "qs:name_adm2":"Bern-Mittelland",
    "qs:name_lau":"Kehrsatz",
    "qs:name_local":"Bern",
    "qs:photo_max":51,
    "qs:photo_sum":209,
    "qs:placetype":"Suburb",
    "qs:quad_count":26,
    "qs:woe_adm0":23424957,
    "qs:woe_adm1":2347087,
    "qs:woe_adm2":56558125,
    "qs:woe_lau":12683638,
    "qs:woe_local":781788,
    "qs:woe_ver":"7.10.0",
    "wd:wordcount":2363,
    "wof:lang":[
        "ger"
    ],
    "wof:name":"Kehrsatz",
    "wof:placetype":"neighbourhood",
    "wof:population":3636
},
  "geometry": {"coordinates":[7.472014,46.898908],"type":"Point"}
}