{
  "type": "Feature",
  "properties": {
    "gn:country":"CH",
    "gn:fcode":"PPL",
    "gn:population":64,
    "iso:country":"CH",
    "name:bih_x_preferred":[
        "\u0932\u0942\u0939\u093f"
    ],
    "name:ceb_x_preferred":[
        "Loo"
    ],
    "name:ces_x_preferred":[
        "Loo"
    ],
    "name:cym_x_preferred":[
        "Loo"
    ],
    "name:deu_x_preferred":[
        "Loo"
    ],
    "name:fra_x_preferred":[
        "Loo"
    ],
    "name:rus_x_preferred":[
        "\u041b\u043e\u043e"
    ],
    "name:spa_x_preferred":[
        "Loo"
    ],
    "name:swe_x_preferred":[
        "Loo"
    ],
    "name:ukr_x_preferred":[
        "\u041b\u043e\u043e"
    ],
    "qs_pg:aaroncc":"CH",
    "qs_pg:gn_country":"CH",
    "qs_pg:gn_fcode":"PPL",
    "qs_pg:gn_pop":64,
    "qs_pg:name":"Loo",
    "qs_pg:photos_9r":0,
    "qs_pg:photos_sr":0,
    "qs_pg:pop_sr":1,
    "qs_pg:qs_pg_placetype":"locality",
    "wof:name":"Loo",
    "wof:placetype":"neighbourhood",
    "wof:population":64
},
  "geometry": {"coordinates":[8.56226,47.48322],"type":"Point"}
}