{
  "type": "Feature",
  "properties": {
    "gn:admin1_code":"GR",
    "gn:admin2_code":"1848.0",
    "gn:admin3_code":"3921.0",
    "gn:asciiname":"Doerfli",
    "gn:country_code":"CH",
    "gn:dem":1755,
    "gn:feature_class":"P",
    "gn:feature_code":"PPL",
    "gn:name":"D\u00f6rfli",
    "gn:population":0,
    "gn:timezone":"Europe/Zurich",
    "iso:country":"CH",
    "name:und_x_variant":[
        "D\u00f6rfji",
        "D\u00f6rfli"
    ],
    "wof:lang_x_official":[
        "deu",
        "fra",
        "gsw",
        "ita"
    ],
    "wof:lang_x_spoken":[
        "deu",
        "fra",
        "gsw",
        "ita",
        "roh"
    ],
    "wof:name":"Doerfli",
    "wof:placetype":"neighbourhood"
},
  "geometry": {"coordinates":[9.75268,46.81793],"type":"Point"}
}