{
  "type": "Feature",
  "properties": {
    "gn:admin1_code":"BE",
    "gn:admin2_code":"248.0",
    "gn:admin3_code":"791.0",
    "gn:asciiname":"Grosse Baeder",
    "gn:country_code":"CH",
    "gn:dem":1654,
    "gn:feature_class":"P",
    "gn:feature_code":"PPL",
    "gn:name":"Grosse B\u00e4der",
    "gn:population":0,
    "gn:timezone":"Europe/Zurich",
    "iso:country":"CH",
    "name:deu_x_preferred":[
        "Grosse B\u00e4der"
    ],
    "wof:name":"Grosse Baeder",
    "wof:placetype":"neighbourhood"
},
  "geometry": {"coordinates":[7.32667,46.60538],"type":"Point"}
}