{
  "type": "Feature",
  "properties": {
    "gn:gn_country":"CH",
    "gn:gn_fcode":"PPL",
    "gn:gn_pop":172,
    "gn:population":172,
    "iso:country":"CH",
    "qs_pg:aaroncc":"CH",
    "qs_pg:gn_country":"CH",
    "qs_pg:gn_fcode":"PPL",
    "qs_pg:gn_pop":172,
    "qs_pg:name":"H\u00e4ngerten",
    "qs_pg:photos_9r":0,
    "qs_pg:photos_sr":0,
    "qs_pg:pop_sr":1,
    "qs_pg:qs_pg_placetype":"locality",
    "wof:name":"H\u00e4ngerten",
    "wof:placetype":"neighbourhood",
    "wof:population":172
},
  "geometry": {"coordinates":[8.44479,47.41628],"type":"Point"}
}