{
  "type": "Feature",
  "properties": {
    "gn:admin1_code":"LU",
    "gn:admin2_code":"315.0",
    "gn:admin3_code":"1150.0",
    "gn:asciiname":"Schachen",
    "gn:country_code":"CH",
    "gn:dem":640,
    "gn:feature_class":"P",
    "gn:feature_code":"PPLL",
    "gn:name":"Schachen",
    "gn:population":0,
    "gn:timezone":"Europe/Zurich",
    "iso:country":"CH",
    "name:deu_x_preferred":[
        "Schachen"
    ],
    "wof:name":"Schachen",
    "wof:placetype":"neighbourhood"
},
  "geometry": {"coordinates":[7.91577,47.11871],"type":"Point"}
}