{
  "type": "Feature",
  "properties": {
    "gn:admin1_code":"BE",
    "gn:admin2_code":"245.0",
    "gn:admin3_code":"413.0",
    "gn:asciiname":"Sankt Niklaus",
    "gn:country_code":"CH",
    "gn:dem":484,
    "gn:elevation":"485.0",
    "gn:feature_class":"P",
    "gn:feature_code":"PPL",
    "gn:name":"Sankt Niklaus",
    "gn:population":0,
    "gn:timezone":"Europe/Zurich",
    "iso:country":"CH",
    "wof:name":"Sankt Niklaus",
    "wof:placetype":"neighbourhood"
},
  "geometry": {"coordinates":[7.6153,47.13212],"type":"Point"}
}