{
  "type": "Feature",
  "properties": {
    "gn:admin1_code":"GR",
    "gn:admin2_code":"1841.0",
    "gn:admin3_code":"3543.0",
    "gn:asciiname":"Som igls Mellens",
    "gn:country_code":"CH",
    "gn:dem":1950,
    "gn:feature_class":"P",
    "gn:feature_code":"PPL",
    "gn:name":"Som igls Mellens",
    "gn:population":0,
    "gn:timezone":"Europe/Zurich",
    "iso:country":"CH",
    "name:roh_x_preferred":[
        "Som igls Mellens"
    ],
    "wof:name":"Som igls Mellens",
    "wof:placetype":"neighbourhood"
},
  "geometry": {"coordinates":[9.53133,46.60593],"type":"Point"}
}