{
  "type": "Feature",
  "properties": {
    "gn:admin1_code":"GR",
    "gn:admin2_code":"1851.0",
    "gn:admin3_code":"3713.0",
    "gn:asciiname":"Starlera",
    "gn:country_code":"CH",
    "gn:dem":1750,
    "gn:feature_class":"P",
    "gn:feature_code":"PPL",
    "gn:name":"Starlera",
    "gn:population":0,
    "gn:timezone":"Europe/Zurich",
    "iso:country":"CH",
    "name:roh_x_preferred":[
        "Starlera"
    ],
    "wof:lang_x_official":[
        "deu",
        "fra",
        "gsw",
        "ita"
    ],
    "wof:lang_x_spoken":[
        "deu",
        "fra",
        "gsw",
        "ita",
        "roh"
    ],
    "wof:name":"Starlera",
    "wof:placetype":"neighbourhood"
},
  "geometry": {"coordinates":[9.46794,46.51189],"type":"Point"}
}