{
  "type": "Feature",
  "properties": {
    "gn:country":"CH",
    "gn:fcode":"PPL",
    "gn:population":160,
    "iso:country":"CH",
    "name:als_x_preferred":[
        "Aegerten"
    ],
    "name:ara_x_preferred":[
        "\u0625\u064a\u062c\u0631\u062a\u0646"
    ],
    "name:cat_x_preferred":[
        "Aegerten"
    ],
    "name:ceb_x_preferred":[
        "Aegerten"
    ],
    "name:deu_x_preferred":[
        "Aegerten"
    ],
    "name:epo_x_preferred":[
        "Aegerten"
    ],
    "name:eus_x_preferred":[
        "Aegerten"
    ],
    "name:fra_x_preferred":[
        "Aegerten"
    ],
    "name:glg_x_preferred":[
        "Aegerten"
    ],
    "name:ita_x_preferred":[
        "Aegerten"
    ],
    "name:kaz_x_preferred":[
        "\u042d\u0433\u0435\u0440\u0442\u0435\u043d"
    ],
    "name:lmo_x_preferred":[
        "Aegerten"
    ],
    "name:msa_x_preferred":[
        "Aegerten"
    ],
    "name:nld_x_preferred":[
        "Aegerten"
    ],
    "name:nno_x_preferred":[
        "Aegerten"
    ],
    "name:nor_x_preferred":[
        "Aegerten"
    ],
    "name:rus_x_preferred":[
        "\u042d\u0433\u0435\u0440\u0442\u0435\u043d"
    ],
    "name:spa_x_preferred":[
        "Aegerten"
    ],
    "name:sqi_x_preferred":[
        "Aegerten"
    ],
    "name:swe_x_preferred":[
        "Aegerten"
    ],
    "name:vec_x_preferred":[
        "Aegerten"
    ],
    "name:vie_x_preferred":[
        "Aegerten"
    ],
    "name:vol_x_preferred":[
        "Aegerten"
    ],
    "name:war_x_preferred":[
        "Aegerten"
    ],
    "name:zho_x_preferred":[
        "\u963f\u683c\u6ed5"
    ],
    "qs_pg:aaroncc":"CH",
    "qs_pg:gn_country":"CH",
    "qs_pg:gn_fcode":"PPL",
    "qs_pg:gn_pop":160,
    "qs_pg:name":"Aegerten",
    "qs_pg:name_adm0":"Schweiz",
    "qs_pg:name_adm1":"Kanton Bern",
    "qs_pg:photos_9k":1,
    "qs_pg:photos_9r":1,
    "qs_pg:photos_all":3,
    "qs_pg:photos_sr":0,
    "qs_pg:pop_sr":1,
    "qs_pg:qs_pg_placetype":"locality",
    "qs_pg:qs_pg_placetype_gp":"Town",
    "qs_pg:woe_adm0":23424957,
    "woe:adm0_id":23424957,
    "woe:name_adm0":"Schweiz",
    "woe:name_adm1":"Kanton Bern",
    "woe:placetype":"Town",
    "wof:name":"Aegerten",
    "wof:placetype":"neighbourhood",
    "wof:population":160
},
  "geometry": {"coordinates":[8.49245,47.32035],"type":"Point"}
}