{
  "type": "Feature",
  "properties": {
    "gn:gn_country":"CH",
    "gn:gn_fcode":"PPLL",
    "gn:gn_pop":9,
    "gn:population":9,
    "iso:country":"CH",
    "name:eng_x_preferred":[
        "Giessen"
    ],
    "name:eng_x_variant":[
        "Meilen / Giessen"
    ],
    "name:unk_x_variant":[
        "Giessen"
    ],
    "qs_pg:aaroncc":"CH",
    "qs_pg:gn_country":"CH",
    "qs_pg:gn_fcode":"PPLL",
    "qs_pg:gn_pop":9,
    "qs_pg:name":"Meilen / Giessen",
    "qs_pg:photos_9r":0,
    "qs_pg:photos_sr":0,
    "qs_pg:pop_sr":1,
    "qs_pg:qs_pg_placetype":"locality",
    "wof:name":"Giessen",
    "wof:placetype":"neighbourhood",
    "wof:population":9
},
  "geometry": {"coordinates":[8.65602,47.26916],"type":"Point"}
}