{
  "type": "Feature",
  "properties": {
    "gn:admin1_code":"FR",
    "gn:admin2_code":"1004.0",
    "gn:admin3_code":"2175.0",
    "gn:asciiname":"Cutterwil",
    "gn:country_code":"CH",
    "gn:dem":633,
    "gn:elevation":"633.0",
    "gn:feature_class":"P",
    "gn:feature_code":"PPL",
    "gn:name":"Cutterwil",
    "gn:population":0,
    "gn:timezone":"Europe/Zurich",
    "iso:country":"CH",
    "wof:name":"Cutterwil",
    "wof:placetype":"neighbourhood"
},
  "geometry": {"coordinates":[7.08607,46.84112],"type":"Point"}
}