{
  "type": "Feature",
  "properties": {
    "gn:gn_country":"CH",
    "gn:gn_fcode":"PPL",
    "gn:gn_pop":0,
    "iso:country":"CH",
    "name:dan_x_preferred":[
        "Anz\u00e8re"
    ],
    "name:eng_x_preferred":[
        "Anz\u00e8re"
    ],
    "name:fra_x_preferred":[
        "Anz\u00e8re"
    ],
    "name:nld_x_preferred":[
        "Anz\u00e8re"
    ],
    "name:pnb_x_preferred":[
        "\u0627\u0646\u0632\u0626\u0631"
    ],
    "name:scn_x_preferred":[
        "Anz\u00e8re"
    ],
    "qs_pg:aaroncc":"CH",
    "qs_pg:gn_country":"CH",
    "qs_pg:gn_fcode":"PPL",
    "qs_pg:gn_pop":0,
    "qs_pg:name":"Anz\u00e8re",
    "qs_pg:name_adm0":"Schweiz",
    "qs_pg:name_adm1":"Canton de Valais",
    "qs_pg:photos":403,
    "qs_pg:photos_1k":82,
    "qs_pg:photos_9k":2,
    "qs_pg:photos_9r":5,
    "qs_pg:photos_all":403,
    "qs_pg:photos_sr":6,
    "qs_pg:pop_sr":0,
    "qs_pg:qs_pg_placetype":"locality",
    "qs_pg:qs_pg_placetype_gp":"Town",
    "qs_pg:woe_adm0":23424957,
    "woe:adm0_id":23424957,
    "woe:name_adm0":"Schweiz",
    "woe:name_adm1":"Canton de Valais",
    "woe:placetype":"Town",
    "wof:name":"Anz\u00e8re",
    "wof:placetype":"locality"
},
  "geometry": {"coordinates":[7.39622,46.29561],"type":"Point"}
}