{
  "type": "Feature",
  "properties": {
    "gn:admin1_code":"GR",
    "gn:admin2_code":"1846.0",
    "gn:admin3_code":"3787.0",
    "gn:asciiname":"Suvretta",
    "gn:country_code":"CH",
    "gn:dem":1887,
    "gn:feature_class":"P",
    "gn:feature_code":"PPL",
    "gn:name":"Suvretta",
    "gn:population":0,
    "gn:timezone":"Europe/Zurich",
    "iso:country":"CH",
    "wof:lang_x_official":[
        "deu",
        "fra",
        "gsw",
        "ita"
    ],
    "wof:lang_x_spoken":[
        "deu",
        "fra",
        "gsw",
        "ita",
        "roh"
    ],
    "wof:name":"Suvretta",
    "wof:placetype":"neighbourhood"
},
  "geometry": {"coordinates":[9.81929,46.48532],"type":"Point"}
}