{
  "type": "Feature",
  "properties": {
    "gn:gn_country":"CH",
    "gn:gn_fcode":"PPL",
    "gn:gn_pop":1574,
    "gn:population":1574,
    "iso:country":"CH",
    "name:ara_x_preferred":[
        "\u0647\u064a\u0646\u063a\u0627\u0631\u062a"
    ],
    "name:cat_x_preferred":[
        "Henggart"
    ],
    "name:chv_x_preferred":[
        "\u0425\u0435\u043d\u0433\u0433\u0430\u0440\u0442"
    ],
    "name:deu_x_preferred":[
        "Henggart"
    ],
    "name:eng_x_preferred":[
        "Henggart"
    ],
    "name:epo_x_preferred":[
        "Henggart"
    ],
    "name:eus_x_preferred":[
        "Henggart"
    ],
    "name:fra_x_preferred":[
        "Henggart"
    ],
    "name:gsw_x_preferred":[
        "H\u00e4nggert"
    ],
    "name:hun_x_preferred":[
        "Henggart"
    ],
    "name:ita_x_preferred":[
        "Henggart"
    ],
    "name:kaz_x_preferred":[
        "\u0425\u0435\u043d\u0433\u0433\u0430\u0440\u0442"
    ],
    "name:lmo_x_preferred":[
        "Henggart"
    ],
    "name:msa_x_preferred":[
        "Henggart"
    ],
    "name:nld_x_preferred":[
        "Henggart"
    ],
    "name:nno_x_preferred":[
        "Henggart"
    ],
    "name:oci_x_preferred":[
        "Henggart"
    ],
    "name:pms_x_preferred":[
        "Henggart"
    ],
    "name:por_x_preferred":[
        "Henggart"
    ],
    "name:rus_x_preferred":[
        "\u0425\u0435\u043d\u0433\u0433\u0430\u0440\u0442"
    ],
    "name:uzb_x_preferred":[
        "Henggart"
    ],
    "name:vec_x_preferred":[
        "Henggart"
    ],
    "name:vol_x_preferred":[
        "Henggart"
    ],
    "name:war_x_preferred":[
        "Henggart"
    ],
    "name:zho_x_preferred":[
        "\u4ea8\u52a0\u7279"
    ],
    "qs_pg:aaroncc":"CH",
    "qs_pg:gn_country":"CH",
    "qs_pg:gn_fcode":"PPL",
    "qs_pg:gn_pop":1574,
    "qs_pg:name":"Henggart",
    "qs_pg:name_adm0":"Schweiz",
    "qs_pg:name_adm1":"Kanton Z\u00fcrich",
    "qs_pg:photos_9k":1,
    "qs_pg:photos_9r":1,
    "qs_pg:photos_all":3,
    "qs_pg:photos_sr":0,
    "qs_pg:pop_sr":3,
    "qs_pg:qs_pg_placetype":"locality",
    "qs_pg:qs_pg_placetype_gp":"Town",
    "qs_pg:woe_adm0":23424957,
    "woe:adm0_id":23424957,
    "woe:name_adm0":"Schweiz",
    "woe:name_adm1":"Kanton Z\u00fcrich",
    "woe:placetype":"Town",
    "wof:name":"Henggart",
    "wof:placetype":"locality",
    "wof:population":1574
},
  "geometry": {"coordinates":[8.68215,47.56272],"type":"Point"}
}