{
  "type": "Feature",
  "properties": {
    "iso:country":"CH",
    "name:fra_x_preferred":[
        "P\u00e2quis Temple"
    ],
    "wof:name":"Paquis Temple",
    "wof:placetype":"neighbourhood"
},
  "geometry": {"coordinates":[6.14536660505124,46.21147194629538],"type":"Point"}
}