{
  "type": "Feature",
  "properties": {
    "gn:admin1_code":"VD",
    "gn:admin2_code":"2224.0",
    "gn:admin3_code":"5743.0",
    "gn:asciiname":"Arnex-sur-Orbe",
    "gn:country_code":"CH",
    "gn:dem":543,
    "gn:feature_class":"P",
    "gn:feature_code":"PPL",
    "gn:name":"Arnex-sur-Orbe",
    "gn:population":0,
    "gn:timezone":"Europe/Zurich",
    "iso:country":"CH",
    "name:und_x_variant":[
        "Arnex"
    ],
    "wof:name":"Arnex-sur-Orbe",
    "wof:placetype":"locality"
},
  "geometry": {"coordinates":[6.51918,46.69455],"type":"Point"}
}