{
  "type": "Feature",
  "properties": {
    "gn:admin1_code":"NW",
    "gn:admin2_code":"700.0",
    "gn:admin3_code":"1509.0",
    "gn:asciiname":"Mettenweg",
    "gn:country_code":"CH",
    "gn:dem":448,
    "gn:feature_class":"P",
    "gn:feature_code":"PPL",
    "gn:name":"Mettenweg",
    "gn:population":0,
    "gn:timezone":"Europe/Zurich",
    "iso:country":"CH",
    "wof:name":"Mettenweg",
    "wof:placetype":"locality"
},
  "geometry": {"coordinates":[8.37359,46.96032],"type":"Point"}
}