{
  "type": "Feature",
  "properties": {
    "gn:admin1_code":"FR",
    "gn:admin2_code":"1007.0",
    "gn:admin3_code":"2338.0",
    "gn:asciiname":"Montesy",
    "gn:country_code":"CH",
    "gn:dem":919,
    "gn:feature_class":"P",
    "gn:feature_code":"PPL",
    "gn:name":"Mont\u00e9sy",
    "gn:population":0,
    "gn:timezone":"Europe/Zurich",
    "iso:country":"CH",
    "name:fra_x_preferred":[
        "Mont\u00e9sy"
    ],
    "wof:name":"Montesy",
    "wof:placetype":"neighbourhood"
},
  "geometry": {"coordinates":[6.90473,46.61094],"type":"Point"}
}