{
  "type": "Feature",
  "properties": {
    "gn:gn_country":"CH",
    "gn:gn_fcode":"ADM3",
    "gn:gn_pop":419,
    "gn:population":423,
    "iso:country":"CH",
    "name:ara_x_preferred":[
        "\u0628\u0648\u0644"
    ],
    "name:deu_x_preferred":[
        "B\u00fchl BE"
    ],
    "name:eng_x_preferred":[
        "B\u00fchl bei Aarberg"
    ],
    "name:epo_x_preferred":[
        "B\u00fchl BE"
    ],
    "name:eus_x_preferred":[
        "B\u00fchl"
    ],
    "name:fin_x_preferred":[
        "B\u00fchl"
    ],
    "name:fra_x_preferred":[
        "B\u00fchl"
    ],
    "name:gsw_x_preferred":[
        "B\u00fceu"
    ],
    "name:hun_x_preferred":[
        "B\u00fchl bei Aarberg"
    ],
    "name:ita_x_preferred":[
        "B\u00fchl"
    ],
    "name:kaz_x_preferred":[
        "\u0411\u044e\u043b\u044c"
    ],
    "name:lmo_x_preferred":[
        "B\u00fchl bei Aarberg"
    ],
    "name:msa_x_preferred":[
        "B\u00fchl bei Aarberg"
    ],
    "name:nld_x_preferred":[
        "B\u00fchl"
    ],
    "name:nno_x_preferred":[
        "B\u00fchl bei Aarberg"
    ],
    "name:rus_x_preferred":[
        "\u0411\u044e\u043b\u044c"
    ],
    "name:spa_x_preferred":[
        "B\u00fchl bei Aarberg"
    ],
    "name:sqi_x_preferred":[
        "B\u00fchl bei Aarberg"
    ],
    "name:swe_x_preferred":[
        "B\u00fchl"
    ],
    "name:vie_x_preferred":[
        "B\u00fchl bei Aarberg"
    ],
    "name:vol_x_preferred":[
        "B\u00fchl"
    ],
    "name:war_x_preferred":[
        "B\u00fchl BE"
    ],
    "name:zho_x_preferred":[
        "\u6bd4\u723e"
    ],
    "qs_pg:aaroncc":"CH",
    "qs_pg:gn_country":"CH",
    "qs_pg:gn_fcode":"ADM3",
    "qs_pg:gn_pop":419,
    "qs_pg:name":"B\u00fchl",
    "qs_pg:name_adm0":"Schweiz",
    "qs_pg:name_adm1":"Kanton Bern",
    "qs_pg:photos_9r":0,
    "qs_pg:photos_sr":0,
    "qs_pg:pop_sr":2,
    "qs_pg:qs_pg_placetype":"locality",
    "qs_pg:qs_pg_placetype_gp":"Town",
    "qs_pg:woe_adm0":23424957,
    "woe:adm0_id":23424957,
    "woe:name_adm0":"Schweiz",
    "woe:name_adm1":"Kanton Bern",
    "woe:placetype":"Town",
    "wof:name":"B\u00fchl",
    "wof:placetype":"locality",
    "wof:population":423
},
  "geometry": {"coordinates":[7.24659,47.06701],"type":"Point"}
}