{
  "type": "Feature",
  "properties": {
    "gn:gn_country":"CH",
    "gn:gn_fcode":"PPLX",
    "gn:gn_pop":51,
    "gn:population":51,
    "iso:country":"CH",
    "name:unk_x_variant":[
        "Tobelhus"
    ],
    "qs_pg:aaroncc":"CH",
    "qs_pg:gn_country":"CH",
    "qs_pg:gn_fcode":"PPLX",
    "qs_pg:gn_pop":51,
    "qs_pg:name":"Zumikon / Tobelhus",
    "qs_pg:photos_9r":0,
    "qs_pg:photos_sr":0,
    "qs_pg:pop_sr":1,
    "qs_pg:qs_pg_placetype":"neighbourhood",
    "wof:name":"Zumikon / Tobelhus",
    "wof:placetype":"neighbourhood",
    "wof:population":51
},
  "geometry": {"coordinates":[8.62215,47.32521],"type":"Point"}
}