{
  "type": "Feature",
  "properties": {
    "gn:population":4051,
    "iso:country":"CH",
    "name:als_x_preferred":[
        "W\u00e4ngi"
    ],
    "name:ara_x_preferred":[
        "\u0641\u064a\u0646\u063a\u064a"
    ],
    "name:baq_x_preferred":[
        "W\u00e4ngi"
    ],
    "name:cat_x_preferred":[
        "W\u00e4ngi"
    ],
    "name:ceb_x_preferred":[
        "W\u00e4ngi"
    ],
    "name:chi_x_preferred":[
        "\u6587\u5409"
    ],
    "name:chv_x_preferred":[
        "\u0412\u0435\u043d\u0433\u0438"
    ],
    "name:deu_x_colloquial":[
        "Waengi",
        "Wangi"
    ],
    "name:deu_x_preferred":[
        "W\u00e4ngi"
    ],
    "name:dut_x_preferred":[
        "W\u00e4ngi"
    ],
    "name:eng_x_preferred":[
        "W\u00e4ngi"
    ],
    "name:epo_x_preferred":[
        "W\u00e4ngi"
    ],
    "name:eus_x_preferred":[
        "W\u00e4ngi"
    ],
    "name:fra_x_preferred":[
        "W\u00e4ngi"
    ],
    "name:fre_x_preferred":[
        "W\u00e4ngi"
    ],
    "name:ger_x_preferred":[
        "W\u00e4ngi"
    ],
    "name:gsw_x_preferred":[
        "W\u00e4ngi"
    ],
    "name:hun_x_preferred":[
        "W\u00e4ngi"
    ],
    "name:ind_x_preferred":[
        "W\u00e4ngi"
    ],
    "name:ita_x_preferred":[
        "W\u00e4ngi"
    ],
    "name:kaz_x_preferred":[
        "\u0412\u0435\u043d\u0433\u0438"
    ],
    "name:lmo_x_preferred":[
        "W\u00e4ngi"
    ],
    "name:may_x_preferred":[
        "W\u00e4ngi"
    ],
    "name:nno_x_preferred":[
        "W\u00e4ngi"
    ],
    "name:oci_x_preferred":[
        "W\u00e4ngi"
    ],
    "name:pms_x_preferred":[
        "W\u00e4ngi"
    ],
    "name:por_x_preferred":[
        "W\u00e4ngi"
    ],
    "name:rus_x_preferred":[
        "\u0412\u0435\u043d\u0433\u0438"
    ],
    "name:spa_x_preferred":[
        "W\u00e4ngi"
    ],
    "name:uzb_x_preferred":[
        "W\u00e4ngi"
    ],
    "name:vec_x_preferred":[
        "W\u00e4ngi"
    ],
    "name:vol_x_preferred":[
        "W\u00e4ngi"
    ],
    "name:war_x_preferred":[
        "W\u00e4ngi"
    ],
    "name:zho_x_preferred":[
        "\u6587\u5409"
    ],
    "qs:a0":"Schweiz#Suisse#Svizzera#Svizra",
    "qs:a1":"*Thurgau",
    "qs:a1r":"0",
    "qs:adm0":"Schweiz#Suisse#Svizzera#Svizra",
    "qs:la_lc":"*",
    "qs:level":"locality",
    "qs:loc":"W\u00e4ngi",
    "qs:loc_alt":"Waengi",
    "qs:pop":0,
    "qs:type":"buffered point",
    "wd:wordcount":1811,
    "wof:lang":[
        "ger"
    ],
    "wof:name":"W\u00e4ngi",
    "wof:placetype":"locality",
    "wof:population":4051
},
  "geometry": {"coordinates":[8.954739,47.497257],"type":"Point"}
}