{
  "type": "Feature",
  "properties": {
    "gn:gn_country":"CH",
    "gn:gn_fcode":"PPL",
    "gn:gn_pop":0,
    "iso:country":"CH",
    "name:alb_x_preferred":[
        "Ipsach"
    ],
    "name:baq_x_preferred":[
        "Ipsach"
    ],
    "name:bul_x_preferred":[
        "\u0418\u043f\u0441\u0430\u0447"
    ],
    "name:cat_x_preferred":[
        "Ipsach"
    ],
    "name:chi_x_preferred":[
        "\u4f0a\u666e\u85a9\u8d6b"
    ],
    "name:dut_x_preferred":[
        "Ipsach"
    ],
    "name:eng_x_preferred":[
        "Ipsach"
    ],
    "name:epo_x_preferred":[
        "Ipsach"
    ],
    "name:fre_x_preferred":[
        "Ipsach"
    ],
    "name:ger_x_preferred":[
        "Ipsach"
    ],
    "name:gsw_x_preferred":[
        "Ipse"
    ],
    "name:hun_x_preferred":[
        "Ipsach"
    ],
    "name:ita_x_preferred":[
        "Ipsach"
    ],
    "name:kaz_x_preferred":[
        "\u0418\u043f\u0437\u0430\u0445"
    ],
    "name:lat_x_preferred":[
        "Ipzachum"
    ],
    "name:lmo_x_preferred":[
        "Ipsach"
    ],
    "name:may_x_preferred":[
        "Ipsach"
    ],
    "name:nno_x_preferred":[
        "Ipsach"
    ],
    "name:oci_x_preferred":[
        "Ipsach"
    ],
    "name:rus_x_preferred":[
        "\u0418\u043f\u0437\u0430\u0445"
    ],
    "name:scn_x_preferred":[
        "Ipsach"
    ],
    "name:spa_x_preferred":[
        "Ipsach"
    ],
    "name:swe_x_preferred":[
        "Ipsach"
    ],
    "name:vie_x_preferred":[
        "Ipsach"
    ],
    "name:vol_x_preferred":[
        "Ipsach"
    ],
    "name:war_x_preferred":[
        "Ipsach"
    ],
    "name:zho_x_preferred":[
        "\u4f0a\u666e\u85a9\u8d6b"
    ],
    "qs_pg:aaroncc":"CH",
    "qs_pg:gn_country":"CH",
    "qs_pg:gn_fcode":"PPL",
    "qs_pg:gn_pop":0,
    "qs_pg:name":"Ipsach",
    "qs_pg:name_adm0":"Schweiz",
    "qs_pg:name_adm1":"Kanton Bern",
    "qs_pg:photos":287,
    "qs_pg:photos_1k":58,
    "qs_pg:photos_9k":1,
    "qs_pg:photos_9r":4,
    "qs_pg:photos_all":287,
    "qs_pg:photos_sr":5,
    "qs_pg:pop_sr":0,
    "qs_pg:qs_pg_placetype":"locality",
    "qs_pg:qs_pg_placetype_gp":"Town",
    "qs_pg:woe_adm0":23424957,
    "woe:adm0_id":23424957,
    "woe:name_adm0":"Schweiz",
    "woe:name_adm1":"Kanton Bern",
    "woe:placetype":"Town",
    "wof:name":"Ipsach",
    "wof:placetype":"locality"
},
  "geometry": {"coordinates":[7.23029,47.11389],"type":"Point"}
}