{
  "type": "Feature",
  "properties": {
    "gn:admin1_code":"BE",
    "gn:admin2_code":"245.0",
    "gn:admin3_code":"957.0",
    "gn:asciiname":"Vorderarni",
    "gn:country_code":"CH",
    "gn:dem":1083,
    "gn:feature_class":"P",
    "gn:feature_code":"PPLL",
    "gn:name":"Vorderarni",
    "gn:population":0,
    "gn:timezone":"Europe/Zurich",
    "iso:country":"CH",
    "name:deu_x_preferred":[
        "Vorderarni"
    ],
    "wof:name":"Vorderarni",
    "wof:placetype":"neighbourhood"
},
  "geometry": {"coordinates":[7.82734,47.03039],"type":"Point"}
}