{
  "type": "Feature",
  "properties": {
    "gn:admin1_code":"FR",
    "gn:admin2_code":"1002.0",
    "gn:admin3_code":"2099.0",
    "gn:asciiname":"Chavannes-les-Forts",
    "gn:country_code":"CH",
    "gn:dem":767,
    "gn:elevation":"784.0",
    "gn:feature_class":"P",
    "gn:feature_code":"PPL",
    "gn:name":"Chavannes-les-Forts",
    "gn:population":0,
    "gn:timezone":"Europe/Zurich",
    "iso:country":"CH",
    "wof:name":"Chavannes-les-Forts",
    "wof:placetype":"locality"
},
  "geometry": {"coordinates":[6.89849,46.65302],"type":"Point"}
}