{
  "type": "Feature",
  "properties": {
    "gn:gn_country":"CH",
    "gn:gn_fcode":"PPLX",
    "gn:gn_pop":2538,
    "gn:population":2538,
    "iso:country":"CH",
    "name:unk_x_variant":[
        "Adliswil (Stadtkern)"
    ],
    "qs_pg:aaroncc":"CH",
    "qs_pg:gn_country":"CH",
    "qs_pg:gn_fcode":"PPLX",
    "qs_pg:gn_pop":2538,
    "qs_pg:name":"Adliswil / Adliswil (Stadtkern)",
    "qs_pg:photos_9r":0,
    "qs_pg:photos_sr":0,
    "qs_pg:pop_sr":4,
    "qs_pg:qs_pg_placetype":"neighbourhood",
    "wof:name":"Adliswil / Adliswil (Stadtkern)",
    "wof:placetype":"neighbourhood",
    "wof:population":2538
},
  "geometry": {"coordinates":[8.52675,47.31128],"type":"Point"}
}