{
  "type": "Feature",
  "properties": {
    "gn:admin1_code":"VS",
    "gn:admin2_code":"2306.0",
    "gn:admin3_code":"6118.0",
    "gn:asciiname":"Engersch",
    "gn:country_code":"CH",
    "gn:dem":1574,
    "gn:elevation":"1508.0",
    "gn:feature_class":"P",
    "gn:feature_code":"PPL",
    "gn:name":"Engersch",
    "gn:population":0,
    "gn:timezone":"Europe/Zurich",
    "iso:country":"CH",
    "wof:lang_x_official":[
        "deu",
        "fra",
        "gsw",
        "ita"
    ],
    "wof:lang_x_spoken":[
        "deu",
        "fra",
        "gsw",
        "ita",
        "roh"
    ],
    "wof:name":"Engersch",
    "wof:placetype":"neighbourhood"
},
  "geometry": {"coordinates":[7.71195,46.33023],"type":"Point"}
}