{
  "type": "Feature",
  "properties": {
    "gn:admin1_code":"LU",
    "gn:admin2_code":"314.0",
    "gn:admin3_code":"1093.0",
    "gn:asciiname":"Gottsmaenigen",
    "gn:country_code":"CH",
    "gn:dem":518,
    "gn:feature_class":"P",
    "gn:feature_code":"PPLL",
    "gn:name":"Gottsm\u00e4nigen",
    "gn:population":0,
    "gn:timezone":"Europe/Zurich",
    "iso:country":"CH",
    "name:deu_x_preferred":[
        "Gottsm\u00e4nigen"
    ],
    "wof:name":"Gottsmaenigen",
    "wof:placetype":"neighbourhood"
},
  "geometry": {"coordinates":[8.20467,47.11879],"type":"Point"}
}