{
  "type": "Feature",
  "properties": {
    "gn:admin1_code":"TG",
    "gn:admin2_code":"2013.0",
    "gn:admin3_code":"4646.0",
    "gn:asciiname":"Ulmberg",
    "gn:country_code":"CH",
    "gn:dem":456,
    "gn:feature_class":"P",
    "gn:feature_code":"PPLL",
    "gn:name":"Ulmberg",
    "gn:population":0,
    "gn:timezone":"Europe/Zurich",
    "iso:country":"CH",
    "name:deu_x_preferred":[
        "Ulmberg"
    ],
    "wof:lang_x_official":[
        "deu",
        "fra",
        "gsw",
        "ita"
    ],
    "wof:lang_x_spoken":[
        "deu",
        "fra",
        "gsw",
        "ita",
        "roh"
    ],
    "wof:name":"Ulmberg",
    "wof:placetype":"neighbourhood"
},
  "geometry": {"coordinates":[9.07626,47.66513],"type":"Point"}
}