{
  "type": "Feature",
  "properties": {
    "gn:admin1_code":"VD",
    "gn:admin2_code":"2227.0",
    "gn:admin3_code":"5625.0",
    "gn:asciiname":"Bussy",
    "gn:country_code":"CH",
    "gn:dem":530,
    "gn:elevation":"520.0",
    "gn:feature_class":"P",
    "gn:feature_code":"PPL",
    "gn:name":"Bussy",
    "gn:population":0,
    "gn:timezone":"Europe/Zurich",
    "iso:country":"CH",
    "name:und_x_variant":[
        "Bussy-Chardonney"
    ],
    "wof:name":"Bussy",
    "wof:placetype":"locality"
},
  "geometry": {"coordinates":[6.44254,46.53045],"type":"Point"}
}