{
  "type": "Feature",
  "properties": {
    "gn:gn_country":"CH",
    "gn:gn_fcode":"PPL",
    "gn:gn_pop":0,
    "iso:country":"CH",
    "qs_pg:aaroncc":"CH",
    "qs_pg:gn_country":"CH",
    "qs_pg:gn_fcode":"PPL",
    "qs_pg:gn_pop":0,
    "qs_pg:name":"Ifenthal",
    "qs_pg:name_adm0":"Schweiz",
    "qs_pg:name_adm1":"Kanton Solothurn",
    "qs_pg:photos":16,
    "qs_pg:photos_1k":3,
    "qs_pg:photos_9k":1,
    "qs_pg:photos_9r":1,
    "qs_pg:photos_all":16,
    "qs_pg:photos_sr":1,
    "qs_pg:pop_sr":0,
    "qs_pg:qs_pg_placetype":"locality",
    "qs_pg:qs_pg_placetype_gp":"Town",
    "qs_pg:woe_adm0":23424957,
    "woe:adm0_id":23424957,
    "woe:name_adm0":"Schweiz",
    "woe:name_adm1":"Kanton Solothurn",
    "woe:placetype":"Town",
    "wof:name":"Ifenthal",
    "wof:placetype":"locality"
},
  "geometry": {"coordinates":[7.85095,47.37363],"type":"Point"}
}