{
  "type": "Feature",
  "properties": {
    "gn:admin1_code":"BE",
    "gn:admin2_code":"245.0",
    "gn:admin3_code":"407.0",
    "gn:asciiname":"Oelbach",
    "gn:country_code":"CH",
    "gn:dem":655,
    "gn:feature_class":"P",
    "gn:feature_code":"PPLL",
    "gn:name":"Oelbach",
    "gn:population":0,
    "gn:timezone":"Europe/Zurich",
    "iso:country":"CH",
    "name:deu_x_preferred":[
        "Oelbach"
    ],
    "wof:lang_x_official":[
        "deu",
        "fra",
        "gsw",
        "ita"
    ],
    "wof:lang_x_spoken":[
        "deu",
        "fra",
        "gsw",
        "ita",
        "roh"
    ],
    "wof:name":"Oelbach",
    "wof:placetype":"neighbourhood"
},
  "geometry": {"coordinates":[7.64936,47.02978],"type":"Point"}
}