{
  "type": "Feature",
  "properties": {
    "iso:country":"CH",
    "name:ara_x_preferred":[
        "\u0631\u0627\u064a\u0646\u0627\u0648"
    ],
    "name:baq_x_preferred":[
        "Rheinau"
    ],
    "name:cat_x_preferred":[
        "Rheinau"
    ],
    "name:chi_x_preferred":[
        "\u840a\u8335\u7459"
    ],
    "name:chv_x_preferred":[
        "\u0420\u0430\u0439\u043d\u0430\u0443"
    ],
    "name:dut_x_preferred":[
        "Rheinau"
    ],
    "name:eng_x_preferred":[
        "Rheinau"
    ],
    "name:epo_x_preferred":[
        "Rejna\u016do ZH"
    ],
    "name:fre_x_preferred":[
        "Rheinau"
    ],
    "name:ger_x_preferred":[
        "Rheinau ZH"
    ],
    "name:gsw_x_preferred":[
        "Riin\u00f2u"
    ],
    "name:hun_x_preferred":[
        "Rheinau"
    ],
    "name:ita_x_preferred":[
        "Rheinau"
    ],
    "name:kaz_x_preferred":[
        "\u0420\u0430\u0439\u043d\u0430\u0443"
    ],
    "name:lmo_x_preferred":[
        "Rheinau"
    ],
    "name:may_x_preferred":[
        "Rheinau"
    ],
    "name:nno_x_preferred":[
        "Rheinau i Sveits"
    ],
    "name:oci_x_preferred":[
        "Rheinau"
    ],
    "name:per_x_preferred":[
        "\u0631\u0646\u0648\u060c \u0633\u0648\u0626\u06cc\u0633"
    ],
    "name:rus_x_preferred":[
        "\u0420\u0430\u0439\u043d\u0430\u0443"
    ],
    "name:swe_x_preferred":[
        "Rheinau"
    ],
    "name:uzb_x_preferred":[
        "Rheinau"
    ],
    "name:vol_x_preferred":[
        "Rheinau"
    ],
    "name:war_x_preferred":[
        "Rheinau"
    ],
    "qs_pg:aaroncc":"CH",
    "qs_pg:name":"Rheinau",
    "qs_pg:name_adm0":"Schweiz",
    "qs_pg:name_adm1":"Kanton Z\u00fcrich",
    "qs_pg:photos":379,
    "qs_pg:photos_1k":77,
    "qs_pg:photos_9k":2,
    "qs_pg:photos_9r":5,
    "qs_pg:photos_all":379,
    "qs_pg:photos_sr":6,
    "qs_pg:pop_sr":0,
    "qs_pg:qs_pg_placetype":"locality",
    "qs_pg:qs_pg_placetype_gp":"Town",
    "qs_pg:woe_adm0":23424957,
    "woe:adm0_id":23424957,
    "woe:name_adm0":"Schweiz",
    "woe:name_adm1":"Kanton Z\u00fcrich",
    "woe:placetype":"Town",
    "wof:name":"Rheinau",
    "wof:placetype":"locality"
},
  "geometry": {"coordinates":[8.607884,47.642612],"type":"Point"}
}