{
  "type": "Feature",
  "properties": {
    "gn:admin1_code":"TI",
    "gn:admin2_code":"2108.0",
    "gn:admin3_code":"5310.0",
    "gn:asciiname":"S. Carlo",
    "gn:country_code":"CH",
    "gn:dem":1024,
    "gn:elevation":"960.0",
    "gn:feature_class":"P",
    "gn:feature_code":"PPL",
    "gn:name":"S. Carlo",
    "gn:population":0,
    "gn:timezone":"Europe/Zurich",
    "iso:country":"CH",
    "name:und_x_variant":[
        "S. Carlo (Val Bavona)",
        "San Carlo"
    ],
    "wof:name":"S. Carlo",
    "wof:placetype":"locality"
},
  "geometry": {"coordinates":[8.52895,46.40995],"type":"Point"}
}