{
  "type": "Feature",
  "properties": {
    "gn:admin1_code":"TG",
    "gn:admin2_code":"2012.0",
    "gn:admin3_code":"4864.0",
    "gn:asciiname":"Hoefli",
    "gn:country_code":"CH",
    "gn:dem":584,
    "gn:feature_class":"P",
    "gn:feature_code":"PPLL",
    "gn:name":"H\u00f6fli",
    "gn:population":0,
    "gn:timezone":"Europe/Zurich",
    "iso:country":"CH",
    "name:deu_x_preferred":[
        "H\u00f6fli"
    ],
    "wof:name":"Hoefli",
    "wof:placetype":"neighbourhood"
},
  "geometry": {"coordinates":[9.01755,47.66169],"type":"Point"}
}