{
  "type": "Feature",
  "properties": {
    "iso:country":"CH",
    "name:als_x_preferred":[
        "Eschenbach LU"
    ],
    "name:deu_x_preferred":[
        "Eschenbach LU"
    ],
    "name:deu_x_variant":[
        "Eschenbach"
    ],
    "name:epo_x_preferred":[
        "Eschenbach LU"
    ],
    "name:eus_x_preferred":[
        "Eschenbach"
    ],
    "name:fra_x_preferred":[
        "Eschenbach"
    ],
    "name:ita_x_preferred":[
        "Eschenbach"
    ],
    "name:kaz_x_preferred":[
        "\u042d\u0448\u0435\u043d\u0431\u0430\u0445"
    ],
    "name:lmo_x_preferred":[
        "Eschenbach"
    ],
    "name:msa_x_preferred":[
        "Eschenbach"
    ],
    "name:nld_x_preferred":[
        "Eschenbach"
    ],
    "name:nno_x_preferred":[
        "Eschenbach i Luzern"
    ],
    "name:oci_x_preferred":[
        "Eschenbach LU"
    ],
    "name:pms_x_preferred":[
        "Eschenbach"
    ],
    "name:por_x_preferred":[
        "Eschenbach"
    ],
    "name:rus_x_preferred":[
        "\u042d\u0448\u0435\u043d\u0431\u0430\u0445"
    ],
    "name:spa_x_preferred":[
        "Eschenbach"
    ],
    "name:sqi_x_preferred":[
        "Eschenbach"
    ],
    "name:unk_x_variant":[
        "Eschenbach"
    ],
    "name:uzb_x_preferred":[
        "Eschenbach"
    ],
    "name:war_x_preferred":[
        "Eschenbach"
    ],
    "name:zho_x_preferred":[
        "\u57c3\u7533\u5df4\u8d6b"
    ],
    "qs:a0":"Schweiz#Suisse#Svizzera#Svizra",
    "qs:a1":"*Luzern",
    "qs:a1r":"0",
    "qs:adm0":"Schweiz#Suisse#Svizzera#Svizra",
    "qs:la_lc":"*",
    "qs:level":"locality",
    "qs:loc":"Eschenbach (LU)",
    "qs:loc_alt":"Eschenbach (LU)",
    "qs:pop":0,
    "qs:type":"buffered point",
    "wd:wordcount":787,
    "wof:lang":[
        "ger"
    ],
    "wof:name":"Eschenbach (LU)",
    "wof:placetype":"locality"
},
  "geometry": {"coordinates":[8.320174,47.132771],"type":"Point"}
}