{
  "type": "Feature",
  "properties": {
    "gn:admin1_code":"VD",
    "gn:admin2_code":"2230.0",
    "gn:admin3_code":"5886.0",
    "gn:asciiname":"Villard-sur-Chamby",
    "gn:country_code":"CH",
    "gn:dem":1010,
    "gn:feature_class":"P",
    "gn:feature_code":"PPL",
    "gn:name":"Villard-sur-Chamby",
    "gn:population":0,
    "gn:timezone":"Europe/Zurich",
    "iso:country":"CH",
    "wof:name":"Villard-sur-Chamby",
    "wof:placetype":"locality"
},
  "geometry": {"coordinates":[6.92898,46.47218],"type":"Point"}
}