{
  "type": "Feature",
  "properties": {
    "gn:admin1_code":"BE",
    "gn:admin2_code":"244.0",
    "gn:admin3_code":"336.0",
    "gn:asciiname":"Gemeindeweid",
    "gn:country_code":"CH",
    "gn:dem":705,
    "gn:feature_class":"P",
    "gn:feature_code":"PPLL",
    "gn:name":"Gemeindeweid",
    "gn:population":0,
    "gn:timezone":"Europe/Zurich",
    "iso:country":"CH",
    "name:deu_x_preferred":[
        "Gemeindeweid"
    ],
    "wof:name":"Gemeindeweid",
    "wof:placetype":"neighbourhood"
},
  "geometry": {"coordinates":[7.83606,47.16154],"type":"Point"}
}