{
  "type": "Feature",
  "properties": {
    "gn:admin1_code":"LU",
    "gn:admin2_code":"312.0",
    "gn:admin3_code":"1059.0",
    "gn:asciiname":"Laengacher",
    "gn:country_code":"CH",
    "gn:dem":581,
    "gn:feature_class":"P",
    "gn:feature_code":"PPLL",
    "gn:name":"L\u00e4ngacher",
    "gn:population":0,
    "gn:timezone":"Europe/Zurich",
    "iso:country":"CH",
    "name:deu_x_preferred":[
        "L\u00e4ngacher"
    ],
    "wof:name":"Laengacher",
    "wof:placetype":"neighbourhood"
},
  "geometry": {"coordinates":[8.24694,47.03023],"type":"Point"}
}