{
  "type": "Feature",
  "properties": {
    "gn:admin1_code":"TI",
    "gn:admin2_code":"2104.0",
    "gn:admin3_code":"5097.0",
    "gn:asciiname":"Alba Nova",
    "gn:country_code":"CH",
    "gn:dem":956,
    "gn:feature_class":"P",
    "gn:feature_code":"PPL",
    "gn:name":"Alba Nova",
    "gn:population":0,
    "gn:timezone":"Europe/Zurich",
    "iso:country":"CH",
    "name:ita_x_preferred":[
        "Alba Nova"
    ],
    "wof:name":"Alba Nova",
    "wof:placetype":"neighbourhood"
},
  "geometry": {"coordinates":[8.69572,46.13286],"type":"Point"}
}