{
  "type": "Feature",
  "properties": {
    "gn:country":"CH",
    "gn:fcode":"PPL",
    "gn:population":574,
    "iso:country":"CH",
    "name:bul_x_preferred":[
        "\u041c\u0430\u0433\u043b\u0438\u043d\u0433\u0435\u043d"
    ],
    "name:ceb_x_preferred":[
        "Magglingen"
    ],
    "name:deu_x_preferred":[
        "Magglingen"
    ],
    "name:eng_x_preferred":[
        "Magglingen"
    ],
    "name:fin_x_preferred":[
        "Magglingen"
    ],
    "name:fra_x_preferred":[
        "Macolin"
    ],
    "name:ita_x_preferred":[
        "Leubringen/Magglingen"
    ],
    "name:ita_x_variant":[
        "Magglingen"
    ],
    "name:jpn_x_preferred":[
        "\u30de\u30b0\u30b0\u30ea\u30f3\u30b2\u30f3"
    ],
    "name:lin_x_preferred":[
        "Makolini"
    ],
    "name:nld_x_preferred":[
        "Magglingen"
    ],
    "name:rus_x_preferred":[
        "\u041c\u0430\u0433\u043b\u0438\u043d\u0433\u0435\u043d"
    ],
    "name:swe_x_preferred":[
        "Magglingen"
    ],
    "qs_pg:aaroncc":"CH",
    "qs_pg:gn_country":"CH",
    "qs_pg:gn_fcode":"PPL",
    "qs_pg:gn_pop":574,
    "qs_pg:name":"Magglingen",
    "qs_pg:name_adm0":"Schweiz",
    "qs_pg:name_adm1":"Kanton Bern",
    "qs_pg:photos":39,
    "qs_pg:photos_1k":8,
    "qs_pg:photos_9k":1,
    "qs_pg:photos_9r":2,
    "qs_pg:photos_all":39,
    "qs_pg:photos_sr":2,
    "qs_pg:pop_sr":2,
    "qs_pg:qs_pg_placetype":"locality",
    "qs_pg:qs_pg_placetype_gp":"Town",
    "qs_pg:woe_adm0":23424957,
    "woe:adm0_id":23424957,
    "woe:name_adm0":"Schweiz",
    "woe:name_adm1":"Kanton Bern",
    "woe:placetype":"Town",
    "wof:name":"Magglingen",
    "wof:placetype":"neighbourhood",
    "wof:population":574
},
  "geometry": {"coordinates":[7.21407,47.139],"type":"Point"}
}