{
  "type": "Feature",
  "properties": {
    "gn:gn_country":"CH",
    "gn:gn_fcode":"PPLX",
    "gn:gn_pop":212,
    "gn:population":212,
    "iso:country":"CH",
    "name:eng_x_preferred":[
        "H\u00fcsliweg"
    ],
    "name:eng_x_variant":[
        "Niederweningen / H\u00fcsliweg"
    ],
    "name:unk_x_variant":[
        "H\u00fcsliweg"
    ],
    "qs_pg:aaroncc":"CH",
    "qs_pg:gn_country":"CH",
    "qs_pg:gn_fcode":"PPLX",
    "qs_pg:gn_pop":212,
    "qs_pg:name":"Niederweningen / H\u00fcsliweg",
    "qs_pg:photos_9r":0,
    "qs_pg:photos_sr":0,
    "qs_pg:pop_sr":2,
    "qs_pg:qs_pg_placetype":"neighbourhood",
    "wof:name":"H\u00fcsliweg",
    "wof:placetype":"neighbourhood",
    "wof:population":212
},
  "geometry": {"coordinates":[8.37707,47.511],"type":"Point"}
}