{
  "type": "Feature",
  "properties": {
    "gn:admin1_code":"FR",
    "gn:admin2_code":"1003.0",
    "gn:admin3_code":"2163.0",
    "gn:asciiname":"Le Liencon",
    "gn:country_code":"CH",
    "gn:dem":877,
    "gn:feature_class":"P",
    "gn:feature_code":"PPL",
    "gn:name":"Le Lien\u00e7on",
    "gn:population":0,
    "gn:timezone":"Europe/Zurich",
    "iso:country":"CH",
    "name:fra_x_preferred":[
        "Le Lien\u00e7on"
    ],
    "wof:name":"Le Liencon",
    "wof:placetype":"neighbourhood"
},
  "geometry": {"coordinates":[7.14616,46.61165],"type":"Point"}
}