{
  "type": "Feature",
  "properties": {
    "gn:admin1_code":"SG",
    "gn:admin2_code":"1728.0",
    "gn:admin3_code":"3422.0",
    "gn:asciiname":"Moos",
    "gn:country_code":"CH",
    "gn:dem":572,
    "gn:feature_class":"P",
    "gn:feature_code":"PPLL",
    "gn:name":"Moos",
    "gn:population":0,
    "gn:timezone":"Europe/Zurich",
    "iso:country":"CH",
    "name:deu_x_preferred":[
        "Moos"
    ],
    "wof:name":"Moos",
    "wof:placetype":"neighbourhood"
},
  "geometry": {"coordinates":[9.22791,47.45887000000001],"type":"Point"}
}