{
  "type": "Feature",
  "properties": {
    "iso:country":"CH",
    "name:cat_x_preferred":[
        "Silvaplana"
    ],
    "name:deu_x_preferred":[
        "Silvaplana"
    ],
    "name:eng_x_preferred":[
        "Silvaplana"
    ],
    "name:epo_x_preferred":[
        "Silvaplana"
    ],
    "name:eus_x_preferred":[
        "Silvaplana"
    ],
    "name:fra_x_preferred":[
        "Silvaplana"
    ],
    "name:hun_x_preferred":[
        "Silvaplana"
    ],
    "name:ita_x_preferred":[
        "Silvaplana"
    ],
    "name:jpn_x_preferred":[
        "\u30b7\u30eb\u30f4\u30a1\u30d7\u30e9\u30fc\u30ca"
    ],
    "name:kaz_x_preferred":[
        "\u0421\u0438\u043b\u044c\u0432\u0430\u043f\u043b\u0430\u043d\u0430"
    ],
    "name:lmo_x_preferred":[
        "Silvaplana"
    ],
    "name:msa_x_preferred":[
        "Silvaplana"
    ],
    "name:nld_x_preferred":[
        "Silvaplana"
    ],
    "name:nno_x_preferred":[
        "Silvaplana"
    ],
    "name:oci_x_preferred":[
        "Silvaplana"
    ],
    "name:pms_x_preferred":[
        "Silvaplana"
    ],
    "name:pol_x_preferred":[
        "Silvaplana"
    ],
    "name:por_x_preferred":[
        "Silvaplana"
    ],
    "name:roh_x_preferred":[
        "Silvaplauna"
    ],
    "name:rus_x_preferred":[
        "\u0421\u0438\u043b\u044c\u0432\u0430\u043f\u043b\u0430\u043d\u0430"
    ],
    "name:spa_x_preferred":[
        "Silvaplana"
    ],
    "name:sqi_x_preferred":[
        "Silvaplana"
    ],
    "name:swe_x_preferred":[
        "Silvaplana"
    ],
    "name:uzb_x_preferred":[
        "Silvaplana"
    ],
    "name:vol_x_preferred":[
        "Silvaplana"
    ],
    "name:war_x_preferred":[
        "Silvaplana"
    ],
    "name:zho_x_preferred":[
        "\u5e2d\u723e\u74e6\u666e\u62c9\u7d0d"
    ],
    "qs_pg:aaroncc":"CH",
    "qs_pg:name":"Silvaplana",
    "qs_pg:name_adm0":"Schweiz",
    "qs_pg:name_adm1":"Kanton Graub\u00fcnden",
    "qs_pg:photos":661,
    "qs_pg:photos_1k":134,
    "qs_pg:photos_9k":3,
    "qs_pg:photos_9r":5,
    "qs_pg:photos_all":661,
    "qs_pg:photos_sr":8,
    "qs_pg:pop_sr":0,
    "qs_pg:qs_pg_placetype":"locality",
    "qs_pg:qs_pg_placetype_gp":"Town",
    "qs_pg:woe_adm0":23424957,
    "woe:adm0_id":23424957,
    "woe:name_adm0":"Schweiz",
    "woe:name_adm1":"Kanton Graub\u00fcnden",
    "woe:placetype":"Town",
    "wof:name":"Silvaplana",
    "wof:placetype":"locality"
},
  "geometry": {"coordinates":[9.797219,46.458329],"type":"Point"}
}