{
  "type": "Feature",
  "properties": {
    "gn:admin1_code":"UR",
    "gn:admin2_code":"400.0",
    "gn:admin3_code":"1211.0",
    "gn:asciiname":"Hermisegg",
    "gn:country_code":"CH",
    "gn:dem":1016,
    "gn:feature_class":"P",
    "gn:feature_code":"PPLL",
    "gn:name":"Hermisegg",
    "gn:population":0,
    "gn:timezone":"Europe/Zurich",
    "iso:country":"CH",
    "name:deu_x_preferred":[
        "Hermisegg"
    ],
    "wof:name":"Hermisegg",
    "wof:placetype":"neighbourhood"
},
  "geometry": {"coordinates":[8.55719,46.90126],"type":"Point"}
}