{
  "type": "Feature",
  "properties": {
    "iso:country":"CH",
    "name:cat_x_preferred":[
        "\u00c9cl\u00e9pens"
    ],
    "name:deu_x_preferred":[
        "Ecl\u00e9pens"
    ],
    "name:eng_x_preferred":[
        "Ecl\u00e9pens"
    ],
    "name:epo_x_preferred":[
        "Ecl\u00e9pens"
    ],
    "name:eus_x_preferred":[
        "Ecl\u00e9pens"
    ],
    "name:fra_x_preferred":[
        "Ecl\u00e9pens"
    ],
    "name:gsw_x_preferred":[
        "Ecl\u00e9pens"
    ],
    "name:hun_x_preferred":[
        "Ecl\u00e9pens"
    ],
    "name:ita_x_preferred":[
        "Ecl\u00e9pens"
    ],
    "name:lmo_x_preferred":[
        "Ecl\u00e9pens"
    ],
    "name:msa_x_preferred":[
        "Ecl\u00e9pens"
    ],
    "name:nld_x_preferred":[
        "Ecl\u00e9pens"
    ],
    "name:nno_x_preferred":[
        "ecl\u00e9pens"
    ],
    "name:oci_x_preferred":[
        "\u00c9cl\u00e9pens"
    ],
    "name:roh_x_preferred":[
        "Ecl\u00e9pens"
    ],
    "name:spa_x_preferred":[
        "Ecl\u00e9pens"
    ],
    "name:swe_x_preferred":[
        "Ecl\u00e9pens"
    ],
    "name:vol_x_preferred":[
        "Ecl\u00e9pens"
    ],
    "name:war_x_preferred":[
        "Ecl\u00e9pens"
    ],
    "name:zho_x_preferred":[
        "\u57c3\u514b\u96f7\u5e9e"
    ],
    "qs_pg:aaroncc":"CH",
    "qs_pg:name":"Ecl\u00e9pens",
    "qs_pg:name_adm0":"Schweiz",
    "qs_pg:name_adm1":"Canton de Vaud",
    "qs_pg:photos":65,
    "qs_pg:photos_1k":13,
    "qs_pg:photos_9k":1,
    "qs_pg:photos_9r":2,
    "qs_pg:photos_all":65,
    "qs_pg:photos_sr":2,
    "qs_pg:pop_sr":0,
    "qs_pg:qs_pg_placetype":"locality",
    "qs_pg:qs_pg_placetype_gp":"Town",
    "qs_pg:woe_adm0":23424957,
    "woe:adm0_id":23424957,
    "woe:name_adm0":"Schweiz",
    "woe:name_adm1":"Canton de Vaud",
    "woe:placetype":"Town",
    "wof:name":"Ecl\u00e9pens",
    "wof:placetype":"locality"
},
  "geometry": {"coordinates":[6.537551,46.656314],"type":"Point"}
}