{
  "type": "Feature",
  "properties": {
    "iso:country":"CH",
    "qs_pg:aaroncc":"CH",
    "qs_pg:name":"Rippertschwand",
    "qs_pg:name_adm0":"Schweiz",
    "qs_pg:name_adm1":"Kanton Luzern",
    "qs_pg:photos":5,
    "qs_pg:photos_1k":1,
    "qs_pg:photos_9k":1,
    "qs_pg:photos_9r":1,
    "qs_pg:photos_all":5,
    "qs_pg:photos_sr":1,
    "qs_pg:pop_sr":0,
    "qs_pg:qs_pg_placetype":"locality",
    "qs_pg:qs_pg_placetype_gp":"Town",
    "qs_pg:woe_adm0":23424957,
    "woe:adm0_id":23424957,
    "woe:name_adm0":"Schweiz",
    "woe:name_adm1":"Kanton Luzern",
    "woe:placetype":"Town",
    "wof:name":"Rippertschwand",
    "wof:placetype":"neighbourhood"
},
  "geometry": {"coordinates":[8.239672,47.101166],"type":"Point"}
}