{
  "type": "Feature",
  "properties": {
    "gn:admin1_code":"BE",
    "gn:admin2_code":"245.0",
    "gn:admin3_code":"902.0",
    "gn:asciiname":"Unterraemis",
    "gn:country_code":"CH",
    "gn:dem":1002,
    "gn:feature_class":"P",
    "gn:feature_code":"PPLL",
    "gn:name":"Unterr\u00e4mis",
    "gn:population":0,
    "gn:timezone":"Europe/Zurich",
    "iso:country":"CH",
    "name:deu_x_preferred":[
        "Unterr\u00e4mis"
    ],
    "wof:name":"Unterraemis",
    "wof:placetype":"neighbourhood"
},
  "geometry": {"coordinates":[7.80727,46.98482],"type":"Point"}
}