{
  "type": "Feature",
  "properties": {
    "gn:gn_country":"CH",
    "gn:gn_fcode":"PPL",
    "gn:gn_pop":0,
    "iso:country":"CH",
    "name:ceb_x_preferred":[
        "Crans"
    ],
    "name:deu_x_preferred":[
        "Crans"
    ],
    "name:epo_x_preferred":[
        "Crans"
    ],
    "name:fra_x_preferred":[
        "Crans"
    ],
    "name:hun_x_preferred":[
        "Crans"
    ],
    "name:ind_x_preferred":[
        "Crans"
    ],
    "name:ita_x_preferred":[
        "Crans"
    ],
    "name:nds_x_preferred":[
        "Crans"
    ],
    "name:nld_x_preferred":[
        "Crans"
    ],
    "name:oci_x_preferred":[
        "Crans"
    ],
    "name:pol_x_preferred":[
        "Crans"
    ],
    "name:por_x_preferred":[
        "Crans"
    ],
    "name:ron_x_preferred":[
        "Crans"
    ],
    "name:scn_x_preferred":[
        "Crans"
    ],
    "name:slk_x_preferred":[
        "Crans"
    ],
    "name:spa_x_preferred":[
        "Crans"
    ],
    "name:swe_x_preferred":[
        "Crans"
    ],
    "qs_pg:aaroncc":"CH",
    "qs_pg:gn_country":"CH",
    "qs_pg:gn_fcode":"PPL",
    "qs_pg:gn_pop":0,
    "qs_pg:name":"Crans",
    "qs_pg:name_adm0":"Schweiz",
    "qs_pg:name_adm1":"Canton de Vaud",
    "qs_pg:photos":1490,
    "qs_pg:photos_1k":302,
    "qs_pg:photos_9k":7,
    "qs_pg:photos_9r":7,
    "qs_pg:photos_all":1490,
    "qs_pg:photos_sr":12,
    "qs_pg:pop_sr":0,
    "qs_pg:qs_pg_placetype":"locality",
    "qs_pg:qs_pg_placetype_gp":"Town",
    "qs_pg:woe_adm0":23424957,
    "woe:adm0_id":23424957,
    "woe:name_adm0":"Schweiz",
    "woe:name_adm1":"Canton de Vaud",
    "woe:placetype":"Town",
    "wof:name":"Crans",
    "wof:placetype":"neighbourhood"
},
  "geometry": {"coordinates":[6.20581,46.35912],"type":"Point"}
}