{
  "type": "Feature",
  "properties": {
    "gn:admin1_code":"FR",
    "gn:admin2_code":"1003.0",
    "gn:admin3_code":"2145.0",
    "gn:asciiname":"Le Carmel",
    "gn:country_code":"CH",
    "gn:dem":818,
    "gn:feature_class":"P",
    "gn:feature_code":"PPL",
    "gn:name":"Le Carmel",
    "gn:population":0,
    "gn:timezone":"Europe/Zurich",
    "iso:country":"CH",
    "name:fra_x_preferred":[
        "Le Carmel"
    ],
    "wof:name":"Le Carmel",
    "wof:placetype":"neighbourhood"
},
  "geometry": {"coordinates":[7.05526,46.58797],"type":"Point"}
}