{
  "type": "Feature",
  "properties": {
    "gn:admin1_code":"NW",
    "gn:admin2_code":"700.0",
    "gn:admin3_code":"1507.0",
    "gn:asciiname":"Renggeli",
    "gn:country_code":"CH",
    "gn:dem":838,
    "gn:feature_class":"P",
    "gn:feature_code":"PPLL",
    "gn:name":"Renggeli",
    "gn:population":0,
    "gn:timezone":"Europe/Zurich",
    "iso:country":"CH",
    "name:deu_x_preferred":[
        "Renggeli"
    ],
    "wof:name":"Renggeli",
    "wof:placetype":"neighbourhood"
},
  "geometry": {"coordinates":[8.28478,46.9835],"type":"Point"}
}