{
  "type": "Feature",
  "properties": {
    "gn:gn_country":"CH",
    "gn:gn_fcode":"PPL",
    "gn:gn_pop":0,
    "iso:country":"CH",
    "name:deu_x_preferred":[
        "Heerbrugg"
    ],
    "name:eng_x_preferred":[
        "Heerbrugg"
    ],
    "name:fra_x_preferred":[
        "Heerbrugg"
    ],
    "name:nld_x_preferred":[
        "Heerbrugg"
    ],
    "name:rus_x_preferred":[
        "\u0425\u0435\u0440\u0431\u0440\u0443\u0433"
    ],
    "name:unk_x_variant":[
        "Heerbrugge"
    ],
    "name:uzb_x_preferred":[
        "Heerbrugg"
    ],
    "qs_pg:aaroncc":"CH",
    "qs_pg:gn_country":"CH",
    "qs_pg:gn_fcode":"PPL",
    "qs_pg:gn_pop":0,
    "qs_pg:name":"Heerbrugg",
    "qs_pg:name_adm0":"Schweiz",
    "qs_pg:name_adm1":"Kanton St. Gallen",
    "qs_pg:photos":140,
    "qs_pg:photos_1k":28,
    "qs_pg:photos_9k":1,
    "qs_pg:photos_9r":3,
    "qs_pg:photos_all":140,
    "qs_pg:photos_sr":3,
    "qs_pg:pop_sr":0,
    "qs_pg:qs_pg_placetype":"locality",
    "qs_pg:qs_pg_placetype_gp":"Town",
    "qs_pg:woe_adm0":23424957,
    "woe:adm0_id":23424957,
    "woe:name_adm0":"Schweiz",
    "woe:name_adm1":"Kanton St. Gallen",
    "woe:placetype":"Town",
    "wof:name":"Heerbrugg",
    "wof:placetype":"locality"
},
  "geometry": {"coordinates":[9.62544,47.41368],"type":"Point"}
}