{
  "type": "Feature",
  "properties": {
    "gn:admin1_code":"JU",
    "gn:admin2_code":"2603.0",
    "gn:admin3_code":"6784.0",
    "gn:asciiname":"Courtemautruy",
    "gn:country_code":"CH",
    "gn:dem":545,
    "gn:elevation":"541.0",
    "gn:feature_class":"P",
    "gn:feature_code":"PPL",
    "gn:name":"Courtemautruy",
    "gn:population":0,
    "gn:timezone":"Europe/Zurich",
    "iso:country":"CH",
    "wof:name":"Courtemautruy",
    "wof:placetype":"locality"
},
  "geometry": {"coordinates":[7.13925,47.396],"type":"Point"}
}