{
  "type": "Feature",
  "properties": {
    "gn:country":"CH",
    "gn:fcode":"PPLX",
    "gn:population":1763,
    "iso:country":"CH",
    "name:eng_x_preferred":[
        "Gschwader"
    ],
    "name:eng_x_variant":[
        "Uster / Gschwader"
    ],
    "qs_pg:aaroncc":"CH",
    "qs_pg:gn_country":"CH",
    "qs_pg:gn_fcode":"PPLX",
    "qs_pg:gn_pop":1763,
    "qs_pg:name":"Uster / Gschwader",
    "qs_pg:photos_9r":0,
    "qs_pg:photos_sr":0,
    "qs_pg:pop_sr":3,
    "qs_pg:qs_pg_placetype":"neighbourhood",
    "wof:lang_x_official":[
        "deu",
        "fra",
        "gsw",
        "ita"
    ],
    "wof:lang_x_spoken":[
        "deu",
        "fra",
        "gsw",
        "ita",
        "roh"
    ],
    "wof:name":"Gschwader",
    "wof:placetype":"neighbourhood",
    "wof:population":1763
},
  "geometry": {"coordinates":[8.7139,47.36016],"type":"Point"}
}