{
  "type": "Feature",
  "properties": {
    "gn:gn_country":"CH",
    "gn:gn_fcode":"PPLX",
    "gn:gn_pop":1763,
    "gn:population":1763,
    "iso:country":"CH",
    "name:unk_x_variant":[
        "Gschwader"
    ],
    "qs_pg:aaroncc":"CH",
    "qs_pg:gn_country":"CH",
    "qs_pg:gn_fcode":"PPLX",
    "qs_pg:gn_pop":1763,
    "qs_pg:name":"Uster / Gschwader",
    "qs_pg:photos_9r":0,
    "qs_pg:photos_sr":0,
    "qs_pg:pop_sr":3,
    "qs_pg:qs_pg_placetype":"neighbourhood",
    "wof:name":"Uster / Gschwader",
    "wof:placetype":"neighbourhood",
    "wof:population":1763
},
  "geometry": {"coordinates":[8.7139,47.36016],"type":"Point"}
}