{
  "type": "Feature",
  "properties": {
    "gn:gn_country":"CH",
    "gn:gn_fcode":"PPLL",
    "gn:gn_pop":29,
    "gn:population":29,
    "iso:country":"CH",
    "name:eng_x_preferred":[
        "Unot"
    ],
    "name:eng_x_variant":[
        "Meilen / Unot"
    ],
    "name:unk_x_variant":[
        "Unot"
    ],
    "qs_pg:aaroncc":"CH",
    "qs_pg:gn_country":"CH",
    "qs_pg:gn_fcode":"PPLL",
    "qs_pg:gn_pop":29,
    "qs_pg:name":"Meilen / Unot",
    "qs_pg:photos_9r":0,
    "qs_pg:photos_sr":0,
    "qs_pg:pop_sr":1,
    "qs_pg:qs_pg_placetype":"locality",
    "wof:name":"Unot",
    "wof:placetype":"neighbourhood",
    "wof:population":29
},
  "geometry": {"coordinates":[8.65394,47.27463],"type":"Point"}
}