{
  "type": "Feature",
  "properties": {
    "gn:gn_country":"CH",
    "gn:gn_fcode":"PPL",
    "gn:gn_pop":1566,
    "gn:population":1566,
    "iso:country":"CH",
    "name:alb_x_preferred":[
        "Giffers"
    ],
    "name:baq_x_preferred":[
        "Giffers"
    ],
    "name:cat_x_preferred":[
        "Giffers"
    ],
    "name:chi_x_preferred":[
        "\u5409\u5f17\u65af"
    ],
    "name:dut_x_preferred":[
        "Giffers"
    ],
    "name:eng_x_preferred":[
        "Giffers"
    ],
    "name:epo_x_preferred":[
        "Giffers"
    ],
    "name:fre_x_preferred":[
        "Giffers"
    ],
    "name:ger_x_preferred":[
        "Giffers"
    ],
    "name:gsw_x_preferred":[
        "G\u00fcfersch"
    ],
    "name:hun_x_preferred":[
        "Giffers"
    ],
    "name:ita_x_preferred":[
        "Giffers"
    ],
    "name:lmo_x_preferred":[
        "Giffers"
    ],
    "name:may_x_preferred":[
        "Giffers"
    ],
    "name:nno_x_preferred":[
        "Giffers"
    ],
    "name:oci_x_preferred":[
        "Giffers"
    ],
    "name:pms_x_preferred":[
        "Giffers"
    ],
    "name:por_x_preferred":[
        "Giffers"
    ],
    "name:roh_x_preferred":[
        "Giffers"
    ],
    "name:spa_x_preferred":[
        "Giffers"
    ],
    "name:swe_x_preferred":[
        "Giffers"
    ],
    "name:vol_x_preferred":[
        "Giffers"
    ],
    "name:war_x_preferred":[
        "Giffers"
    ],
    "name:zho_x_preferred":[
        "\u5409\u5f17\u65af"
    ],
    "qs_pg:aaroncc":"CH",
    "qs_pg:gn_country":"CH",
    "qs_pg:gn_fcode":"PPL",
    "qs_pg:gn_pop":1566,
    "qs_pg:name":"Giffers",
    "qs_pg:name_adm0":"Schweiz",
    "qs_pg:name_adm1":"Canton de Fribourg",
    "qs_pg:photos":566,
    "qs_pg:photos_1k":115,
    "qs_pg:photos_9k":3,
    "qs_pg:photos_9r":5,
    "qs_pg:photos_all":566,
    "qs_pg:photos_sr":8,
    "qs_pg:pop_sr":3,
    "qs_pg:qs_pg_placetype":"locality",
    "qs_pg:qs_pg_placetype_gp":"Town",
    "qs_pg:woe_adm0":23424957,
    "woe:adm0_id":23424957,
    "woe:name_adm0":"Schweiz",
    "woe:name_adm1":"Canton de Fribourg",
    "woe:placetype":"Town",
    "wof:name":"Giffers",
    "wof:placetype":"locality",
    "wof:population":1566
},
  "geometry": {"coordinates":[7.20845,46.7623],"type":"Point"}
}