{
  "type": "Feature",
  "properties": {
    "gn:country":"CH",
    "gn:fcode":"PPLX",
    "gn:population":75,
    "iso:country":"CH",
    "name:und_x_variant":[
        "Wohnkolonie Hardhof"
    ],
    "qs_pg:aaroncc":"CH",
    "qs_pg:gn_country":"CH",
    "qs_pg:gn_fcode":"PPLX",
    "qs_pg:gn_pop":75,
    "qs_pg:name":"Z\u00fcrich (Kreis 9) / Wohnkolonie Hardhof",
    "qs_pg:photos_9r":0,
    "qs_pg:photos_sr":0,
    "qs_pg:pop_sr":1,
    "qs_pg:qs_pg_placetype":"neighbourhood",
    "wof:name":"Wohnkolonie Hardhof",
    "wof:placetype":"neighbourhood",
    "wof:population":75
},
  "geometry": {"coordinates":[8.49597,47.39643],"type":"Point"}
}