{
  "type": "Feature",
  "properties": {
    "gn:admin1_code":"VD",
    "gn:admin2_code":"2224.0",
    "gn:admin3_code":"5871.0",
    "gn:asciiname":"Le Bucley",
    "gn:country_code":"CH",
    "gn:dem":1434,
    "gn:feature_class":"P",
    "gn:feature_code":"PPL",
    "gn:name":"Le Bucley",
    "gn:population":0,
    "gn:timezone":"Europe/Zurich",
    "iso:country":"CH",
    "name:fra_x_preferred":[
        "Le Bucley"
    ],
    "wof:name":"Le Bucley",
    "wof:placetype":"neighbourhood"
},
  "geometry": {"coordinates":[6.3151,46.61809],"type":"Point"}
}