{
  "type": "Feature",
  "properties": {
    "gn:admin1_code":"BL",
    "gn:admin2_code":"1305.0",
    "gn:admin3_code":"2885.0",
    "gn:asciiname":"Saege",
    "gn:country_code":"CH",
    "gn:dem":547,
    "gn:feature_class":"P",
    "gn:feature_code":"PPLL",
    "gn:name":"S\u00e4ge",
    "gn:population":0,
    "gn:timezone":"Europe/Zurich",
    "iso:country":"CH",
    "name:deu_x_preferred":[
        "S\u00e4ge"
    ],
    "wof:lang_x_official":[
        "deu",
        "fra",
        "gsw",
        "ita"
    ],
    "wof:lang_x_spoken":[
        "deu",
        "fra",
        "gsw",
        "ita",
        "roh"
    ],
    "wof:name":"Saege",
    "wof:placetype":"neighbourhood"
},
  "geometry": {"coordinates":[7.8126,47.39104],"type":"Point"}
}