{
  "type": "Feature",
  "properties": {
    "gn:admin1_code":"BE",
    "gn:admin2_code":"247.0",
    "gn:admin3_code":"927.0",
    "gn:asciiname":"Schwendi",
    "gn:country_code":"CH",
    "gn:dem":1107,
    "gn:feature_class":"P",
    "gn:feature_code":"PPL",
    "gn:name":"Schwendi",
    "gn:population":0,
    "gn:timezone":"Europe/Zurich",
    "iso:country":"CH",
    "wof:name":"Schwendi",
    "wof:placetype":"neighbourhood"
},
  "geometry": {"coordinates":[7.69083,46.74932],"type":"Point"}
}