{
  "type": "Feature",
  "properties": {
    "gn:admin1_code":"SH",
    "gn:admin2_code":"1405.0",
    "gn:admin3_code":"2964.0",
    "gn:asciiname":"Faleberg",
    "gn:country_code":"CH",
    "gn:dem":537,
    "gn:feature_class":"P",
    "gn:feature_code":"PPLL",
    "gn:name":"Faleberg",
    "gn:population":0,
    "gn:timezone":"Europe/Zurich",
    "iso:country":"CH",
    "name:deu_x_preferred":[
        "Faleberg"
    ],
    "wof:name":"Faleberg",
    "wof:placetype":"neighbourhood"
},
  "geometry": {"coordinates":[8.86933,47.6694],"type":"Point"}
}