{
  "type": "Feature",
  "properties": {
    "gn:gn_country":"CH",
    "gn:gn_fcode":"PPL",
    "gn:gn_pop":10138,
    "gn:population":10138,
    "iso:country":"CH",
    "name:als_x_preferred":[
        "Aesch BL"
    ],
    "name:chv_x_preferred":[
        "\u042d\u0448"
    ],
    "name:deu_x_preferred":[
        "Aesch BL"
    ],
    "name:epo_x_preferred":[
        "Aesch BL"
    ],
    "name:nno_x_preferred":[
        "Aesch i Basel-Landschaft"
    ],
    "name:rus_x_preferred":[
        "\u042d\u0448"
    ],
    "name:zho_x_preferred":[
        "\u57c3\u65bd"
    ],
    "qs_pg:aaroncc":"CH",
    "qs_pg:gn_country":"CH",
    "qs_pg:gn_fcode":"PPL",
    "qs_pg:gn_pop":10138,
    "qs_pg:name":"Aesch",
    "qs_pg:name_adm0":"Schweiz",
    "qs_pg:name_adm1":"Kanton Basel-Land",
    "qs_pg:photos":309,
    "qs_pg:photos_1k":63,
    "qs_pg:photos_9k":1,
    "qs_pg:photos_9r":5,
    "qs_pg:photos_all":309,
    "qs_pg:photos_sr":5,
    "qs_pg:pop_sr":6,
    "qs_pg:qs_pg_placetype":"locality",
    "qs_pg:qs_pg_placetype_gp":"Town",
    "qs_pg:woe_adm0":23424957,
    "woe:adm0_id":23424957,
    "woe:name_adm0":"Schweiz",
    "woe:name_adm1":"Kanton Basel-Land",
    "woe:placetype":"Town",
    "wof:name":"Aesch",
    "wof:placetype":"locality",
    "wof:population":10138
},
  "geometry": {"coordinates":[7.5973,47.47104],"type":"Point"}
}