{
  "type": "Feature",
  "properties": {
    "gn:gn_country":"CH",
    "gn:gn_fcode":"PPL",
    "gn:gn_pop":103,
    "gn:population":103,
    "iso:country":"CH",
    "name:deu_x_preferred":[
        "Findeln"
    ],
    "qs_pg:aaroncc":"CH",
    "qs_pg:gn_country":"CH",
    "qs_pg:gn_fcode":"PPL",
    "qs_pg:gn_pop":103,
    "qs_pg:name":"Findeln",
    "qs_pg:name_adm0":"Schweiz",
    "qs_pg:name_adm1":"Canton de Valais",
    "qs_pg:photos":232,
    "qs_pg:photos_1k":47,
    "qs_pg:photos_9k":1,
    "qs_pg:photos_9r":4,
    "qs_pg:photos_all":232,
    "qs_pg:photos_sr":4,
    "qs_pg:pop_sr":1,
    "qs_pg:qs_pg_placetype":"locality",
    "qs_pg:qs_pg_placetype_gp":"Town",
    "qs_pg:woe_adm0":23424957,
    "woe:adm0_id":23424957,
    "woe:name_adm0":"Schweiz",
    "woe:name_adm1":"Canton de Valais",
    "woe:placetype":"Town",
    "wof:name":"Findeln",
    "wof:placetype":"neighbourhood",
    "wof:population":103
},
  "geometry": {"coordinates":[7.61739,46.34438],"type":"Point"}
}