{
  "type": "Feature",
  "properties": {
    "gn:admin1_code":"BE",
    "gn:admin2_code":"249.0",
    "gn:admin3_code":"567.0",
    "gn:asciiname":"Im Aabe",
    "gn:country_code":"CH",
    "gn:dem":1029,
    "gn:feature_class":"P",
    "gn:feature_code":"PPL",
    "gn:name":"Im Aabe",
    "gn:population":0,
    "gn:timezone":"Europe/Zurich",
    "iso:country":"CH",
    "name:deu_x_preferred":[
        "Im Aabe"
    ],
    "wof:name":"Im Aabe",
    "wof:placetype":"locality"
},
  "geometry": {"coordinates":[7.70883,46.61609],"type":"Point"}
}