{
  "type": "Feature",
  "properties": {
    "iso:country":"CH",
    "name:deu_x_preferred":[
        "Gurten-Kulm"
    ],
    "name:unk_x_variant":[
        "Gurten-Kulm"
    ],
    "qs:gn_local":0,
    "qs:local_max":4550,
    "qs:local_sum":6457,
    "qs:localhoods":6,
    "qs:name":"Gurten-Kulm",
    "qs:name_adm0":"Schweiz",
    "qs:name_adm1":"Kanton Bern",
    "qs:name_adm2":"Bern-Mittelland",
    "qs:name_lau":"K\u00f6niz",
    "qs:name_local":"K\u00f6niz",
    "qs:photo_max":2062,
    "qs:photo_sum":4550,
    "qs:placetype":"Suburb",
    "qs:quad_count":31,
    "qs:woe_adm0":23424957,
    "qs:woe_adm1":2347087,
    "qs:woe_adm2":56558125,
    "qs:woe_lau":12683628,
    "qs:woe_local":12683628,
    "qs:woe_ver":"7.10.0",
    "wof:lang":[
        "ger"
    ],
    "wof:name":"Gurten-Kulm",
    "wof:placetype":"neighbourhood"
},
  "geometry": {"coordinates":[7.441834,46.918515],"type":"Point"}
}