{
  "type": "Feature",
  "properties": {
    "gn:gn_country":"CH",
    "gn:gn_fcode":"PPLX",
    "gn:gn_pop":1989,
    "gn:population":1989,
    "iso:country":"CH",
    "name:eng_x_preferred":[
        "Unterdorf"
    ],
    "name:eng_x_variant":[
        "Affoltern / Unterdorf"
    ],
    "name:unk_x_variant":[
        "Unterdorf"
    ],
    "qs_pg:aaroncc":"CH",
    "qs_pg:gn_country":"CH",
    "qs_pg:gn_fcode":"PPLX",
    "qs_pg:gn_pop":1989,
    "qs_pg:name":"Affoltern / Unterdorf",
    "qs_pg:photos_9r":0,
    "qs_pg:photos_sr":0,
    "qs_pg:pop_sr":3,
    "qs_pg:qs_pg_placetype":"neighbourhood",
    "wof:name":"Unterdorf",
    "wof:placetype":"neighbourhood",
    "wof:population":1989
},
  "geometry": {"coordinates":[8.45086,47.28257],"type":"Point"}
}