{
  "type": "Feature",
  "properties": {
    "gn:admin1_code":"AG",
    "gn:admin2_code":"1903.0",
    "gn:admin3_code":"4080.0",
    "gn:asciiname":"Hilfikon",
    "gn:country_code":"CH",
    "gn:dem":538,
    "gn:feature_class":"P",
    "gn:feature_code":"PPL",
    "gn:name":"Hilfikon",
    "gn:population":0,
    "gn:timezone":"Europe/Zurich",
    "iso:country":"CH",
    "name:kaz_x_preferred":[
        "\u0425\u0438\u043b\u044c\u0444\u0438\u043a\u043e\u043d"
    ],
    "name:rus_x_preferred":[
        "\u0425\u0438\u043b\u044c\u0444\u0438\u043a\u043e\u043d"
    ],
    "wof:name":"Hilfikon",
    "wof:placetype":"locality"
},
  "geometry": {"coordinates":[8.24236,47.33135],"type":"Point"}
}