{
  "type": "Feature",
  "properties": {
    "gn:admin1_code":"LU",
    "gn:admin2_code":"313.0",
    "gn:admin3_code":"1039.0",
    "gn:asciiname":"Mur",
    "gn:country_code":"CH",
    "gn:dem":698,
    "gn:feature_class":"P",
    "gn:feature_code":"PPLL",
    "gn:name":"Mur",
    "gn:population":0,
    "gn:timezone":"Europe/Zurich",
    "iso:country":"CH",
    "name:bel_x_preferred":[
        "\u041c\u0443\u0440"
    ],
    "name:bre_x_preferred":[
        "Mur"
    ],
    "name:bul_x_preferred":[
        "\u041c\u0443\u0440"
    ],
    "name:cat_x_preferred":[
        "Mur"
    ],
    "name:ceb_x_preferred":[
        "Mur"
    ],
    "name:dan_x_preferred":[
        "Mur"
    ],
    "name:deu_x_preferred":[
        "Mur"
    ],
    "name:eus_x_preferred":[
        "Mur"
    ],
    "name:fra_x_preferred":[
        "Mur"
    ],
    "name:heb_x_preferred":[
        "\u05de\u05d5\u05e8"
    ],
    "name:hun_x_preferred":[
        "Mur"
    ],
    "name:nld_x_preferred":[
        "Mur"
    ],
    "name:nor_x_preferred":[
        "Mur"
    ],
    "name:pol_x_preferred":[
        "Mur"
    ],
    "name:por_x_preferred":[
        "Mur"
    ],
    "name:ron_x_preferred":[
        "Mur"
    ],
    "name:rus_x_preferred":[
        "\u041c\u0443\u0440"
    ],
    "name:srp_x_preferred":[
        "\u041c\u0443\u0440"
    ],
    "name:ukr_x_preferred":[
        "\u041c\u0443\u0440"
    ],
    "wof:name":"Mur",
    "wof:placetype":"neighbourhood"
},
  "geometry": {"coordinates":[8.25147,47.16142],"type":"Point"}
}