{
  "type": "Feature",
  "properties": {
    "gn:gn_country":"CH",
    "gn:gn_fcode":"ADM3",
    "gn:gn_pop":328,
    "gn:population":328,
    "iso:country":"CH",
    "name:ara_x_preferred":[
        "\u0625\u0628\u0633\u0627\u062e"
    ],
    "name:bul_x_preferred":[
        "\u0415\u043f\u0441\u0430\u0447"
    ],
    "name:cat_x_preferred":[
        "Epsach"
    ],
    "name:deu_x_preferred":[
        "Epsach"
    ],
    "name:eng_x_preferred":[
        "Epsach"
    ],
    "name:epo_x_preferred":[
        "Epsach"
    ],
    "name:eus_x_preferred":[
        "Epsach"
    ],
    "name:fra_x_preferred":[
        "Epsach"
    ],
    "name:gsw_x_preferred":[
        "Epse"
    ],
    "name:hun_x_preferred":[
        "Epsach"
    ],
    "name:ita_x_preferred":[
        "Epsach"
    ],
    "name:kaz_x_preferred":[
        "\u042d\u043f\u0437\u0430\u0445"
    ],
    "name:lat_x_preferred":[
        "Ebza"
    ],
    "name:lmo_x_preferred":[
        "Epsach"
    ],
    "name:msa_x_preferred":[
        "Epsach"
    ],
    "name:nld_x_preferred":[
        "Epsach"
    ],
    "name:nno_x_preferred":[
        "Epsach"
    ],
    "name:oci_x_preferred":[
        "Epsach"
    ],
    "name:rus_x_preferred":[
        "\u042d\u043f\u0437\u0430\u0445"
    ],
    "name:spa_x_preferred":[
        "Epsach"
    ],
    "name:sqi_x_preferred":[
        "Epsach"
    ],
    "name:swe_x_preferred":[
        "Epsach"
    ],
    "name:vie_x_preferred":[
        "Epsach"
    ],
    "name:vol_x_preferred":[
        "Epsach"
    ],
    "name:war_x_preferred":[
        "Epsach"
    ],
    "name:zho_x_preferred":[
        "\u57c3\u666e\u85a9\u8d6b"
    ],
    "qs_pg:aaroncc":"CH",
    "qs_pg:gn_country":"CH",
    "qs_pg:gn_fcode":"ADM3",
    "qs_pg:gn_pop":328,
    "qs_pg:name":"Epsach",
    "qs_pg:name_adm0":"Schweiz",
    "qs_pg:name_adm1":"Kanton Bern",
    "qs_pg:photos_9k":1,
    "qs_pg:photos_9r":1,
    "qs_pg:photos_all":1,
    "qs_pg:photos_sr":0,
    "qs_pg:pop_sr":2,
    "qs_pg:qs_pg_placetype":"locality",
    "qs_pg:qs_pg_placetype_gp":"Town",
    "qs_pg:woe_adm0":23424957,
    "woe:adm0_id":23424957,
    "woe:name_adm0":"Schweiz",
    "woe:name_adm1":"Kanton Bern",
    "woe:placetype":"Town",
    "wof:name":"Epsach",
    "wof:placetype":"locality",
    "wof:population":328
},
  "geometry": {"coordinates":[7.2201,47.07041],"type":"Point"}
}