{
  "type": "Feature",
  "properties": {
    "gn:admin1_code":"TG",
    "gn:admin2_code":"2014.0",
    "gn:admin3_code":"4551.0",
    "gn:asciiname":"Guntershausen",
    "gn:country_code":"CH",
    "gn:dem":554,
    "gn:elevation":"547.0",
    "gn:feature_class":"P",
    "gn:feature_code":"PPL",
    "gn:name":"Guntershausen",
    "gn:population":0,
    "gn:timezone":"Europe/Zurich",
    "iso:country":"CH",
    "name:deu_x_preferred":[
        "Guntershausen b. Aadorf"
    ],
    "wof:name":"Guntershausen",
    "wof:placetype":"locality"
},
  "geometry": {"coordinates":[8.91825,47.47549],"type":"Point"}
}