{
  "type": "Feature",
  "properties": {
    "iso:country":"CH",
    "name:cat_x_preferred":[
        "Sankt Ant\u00f6nien"
    ],
    "name:deu_x_preferred":[
        "St. Ant\u00f6nien"
    ],
    "name:eng_x_preferred":[
        "St. Ant\u00f6nien"
    ],
    "name:epo_x_preferred":[
        "Sankt Ant\u00f6nien"
    ],
    "name:fra_x_preferred":[
        "Sankt Ant\u00f6nien"
    ],
    "name:hun_x_preferred":[
        "St. Ant\u00f6nien"
    ],
    "name:ita_x_preferred":[
        "Sankt Ant\u00f6nien"
    ],
    "name:kaz_x_preferred":[
        "\u0421\u0430\u043d\u043a\u0442-\u0410\u043d\u0442\u0451\u043d\u0438\u0435\u043d"
    ],
    "name:lmo_x_preferred":[
        "St. Ant\u00f6nien"
    ],
    "name:msa_x_preferred":[
        "St. Ant\u00f6nien"
    ],
    "name:nld_x_preferred":[
        "Sankt Ant\u00f6nien"
    ],
    "name:nno_x_preferred":[
        "St. Ant\u00f6nien"
    ],
    "name:oci_x_preferred":[
        "Sankt Ant\u00f6nien"
    ],
    "name:pms_x_preferred":[
        "Sankt Ant\u00f6nien"
    ],
    "name:por_x_preferred":[
        "Sankt Ant\u00f6nien"
    ],
    "name:roh_x_preferred":[
        "Sontg Ant\u00f6nia"
    ],
    "name:rus_x_preferred":[
        "\u0421\u0430\u043d\u043a\u0442-\u0410\u043d\u0442\u0451\u043d\u0438\u0435\u043d"
    ],
    "name:spa_x_preferred":[
        "Sankt Ant\u00f6nien"
    ],
    "name:sqi_x_preferred":[
        "St. Ant\u00f6nien"
    ],
    "name:swe_x_preferred":[
        "Sankt Ant\u00f6nien"
    ],
    "name:uzb_x_preferred":[
        "St. Ant\u00f6nien"
    ],
    "name:vol_x_preferred":[
        "St. Ant\u00f6nien"
    ],
    "name:war_x_preferred":[
        "St. Ant\u00f6nien"
    ],
    "name:zho_x_preferred":[
        "\u8056\u5b89\u7279\u5c3c\u6069"
    ],
    "qs_pg:aaroncc":"CH",
    "qs_pg:name":"St. Ant\u00f6nien",
    "qs_pg:name_adm0":"Schweiz",
    "qs_pg:name_adm1":"Kanton Graub\u00fcnden",
    "qs_pg:photos":79,
    "qs_pg:photos_1k":16,
    "qs_pg:photos_9k":1,
    "qs_pg:photos_9r":3,
    "qs_pg:photos_all":79,
    "qs_pg:photos_sr":3,
    "qs_pg:pop_sr":0,
    "qs_pg:qs_pg_placetype":"locality",
    "qs_pg:qs_pg_placetype_gp":"Town",
    "qs_pg:woe_adm0":23424957,
    "woe:adm0_id":23424957,
    "woe:name_adm0":"Schweiz",
    "woe:name_adm1":"Kanton Graub\u00fcnden",
    "woe:placetype":"Town",
    "wof:name":"St. Ant\u00f6nien",
    "wof:placetype":"locality"
},
  "geometry": {"coordinates":[9.829673,46.973693],"type":"Point"}
}