{
  "type": "Feature",
  "properties": {
    "gn:admin1_code":"SZ",
    "gn:admin2_code":"506.0",
    "gn:admin3_code":"1367.0",
    "gn:asciiname":"Alpwirtschaft Waldi Alp",
    "gn:country_code":"CH",
    "gn:dem":1440,
    "gn:feature_class":"P",
    "gn:feature_code":"PPLL",
    "gn:name":"Alpwirtschaft Waldi Alp",
    "gn:population":0,
    "gn:timezone":"Europe/Zurich",
    "iso:country":"CH",
    "name:deu_x_preferred":[
        "Alpwirtschaft Waldi Alp"
    ],
    "wof:name":"Alpwirtschaft Waldi Alp",
    "wof:placetype":"locality"
},
  "geometry": {"coordinates":[8.83674,46.91518],"type":"Point"}
}