{
  "type": "Feature",
  "properties": {
    "gn:gn_country":"CH",
    "gn:gn_fcode":"ADM3",
    "gn:gn_pop":1306,
    "gn:population":1363,
    "iso:country":"CH",
    "name:ara_x_preferred":[
        "\u0628\u064a\u0631\u0641\u064a\u0646\u0643\u0646"
    ],
    "name:baq_x_preferred":[
        "Birwinken"
    ],
    "name:cat_x_preferred":[
        "Birwinken"
    ],
    "name:chi_x_preferred":[
        "\u6bd4\u6eab\u80af"
    ],
    "name:dut_x_preferred":[
        "Birwinken"
    ],
    "name:eng_x_preferred":[
        "Birwinken"
    ],
    "name:epo_x_preferred":[
        "Birwinken"
    ],
    "name:fre_x_preferred":[
        "Birwinken"
    ],
    "name:ger_x_preferred":[
        "Birwinken"
    ],
    "name:gsw_x_preferred":[
        "Birwinken"
    ],
    "name:hun_x_preferred":[
        "Birwinken"
    ],
    "name:ita_x_preferred":[
        "Birwinken"
    ],
    "name:kaz_x_preferred":[
        "\u0411\u0438\u0440\u0432\u0438\u043d\u043a\u0435\u043d"
    ],
    "name:lmo_x_preferred":[
        "Birwinken"
    ],
    "name:may_x_preferred":[
        "Birwinken"
    ],
    "name:nno_x_preferred":[
        "Birwinken"
    ],
    "name:oci_x_preferred":[
        "Birwinken"
    ],
    "name:pms_x_preferred":[
        "Birwinken"
    ],
    "name:por_x_preferred":[
        "Birwinken"
    ],
    "name:rus_x_preferred":[
        "\u0411\u0438\u0440\u0432\u0438\u043d\u043a\u0435\u043d"
    ],
    "name:spa_x_preferred":[
        "Birwinken"
    ],
    "name:swe_x_preferred":[
        "Birwinken"
    ],
    "name:uzb_x_preferred":[
        "Birwinken"
    ],
    "name:vec_x_preferred":[
        "Birvinken"
    ],
    "name:vol_x_preferred":[
        "Birwinken"
    ],
    "name:war_x_preferred":[
        "Birwinken"
    ],
    "qs_pg:aaroncc":"CH",
    "qs_pg:gn_country":"CH",
    "qs_pg:gn_fcode":"ADM3",
    "qs_pg:gn_pop":1306,
    "qs_pg:name":"Birwinken",
    "qs_pg:name_adm0":"Schweiz",
    "qs_pg:name_adm1":"Kanton Thurgau",
    "qs_pg:photos_9r":0,
    "qs_pg:photos_sr":0,
    "qs_pg:pop_sr":3,
    "qs_pg:qs_pg_placetype":"locality",
    "qs_pg:qs_pg_placetype_gp":"Town",
    "qs_pg:woe_adm0":23424957,
    "woe:adm0_id":23424957,
    "woe:name_adm0":"Schweiz",
    "woe:name_adm1":"Kanton Thurgau",
    "woe:placetype":"Town",
    "wof:name":"Birwinken",
    "wof:placetype":"locality",
    "wof:population":1363
},
  "geometry": {"coordinates":[9.21467,47.57648],"type":"Point"}
}