{
  "type": "Feature",
  "properties": {
    "gn:gn_country":"CH",
    "gn:gn_fcode":"PPLX",
    "gn:gn_pop":2923,
    "gn:population":2923,
    "iso:country":"CH",
    "name:eng_x_preferred":[
        "Gutschick"
    ],
    "name:ger_x_preferred":[
        "Gutschick"
    ],
    "name:swe_x_preferred":[
        "Mattenbach"
    ],
    "name:unk_x_variant":[
        "Gutschick"
    ],
    "qs_pg:aaroncc":"CH",
    "qs_pg:gn_country":"CH",
    "qs_pg:gn_fcode":"PPLX",
    "qs_pg:gn_pop":2923,
    "qs_pg:name":"Mattenbach (Kreis 7) / Gutschick",
    "qs_pg:photos_9r":0,
    "qs_pg:photos_sr":0,
    "qs_pg:pop_sr":4,
    "qs_pg:qs_pg_placetype":"neighbourhood",
    "wof:name":"Mattenbach (Kreis 7) / Gutschick",
    "wof:placetype":"neighbourhood",
    "wof:population":2923
},
  "geometry": {"coordinates":[8.75258,47.49104],"type":"Point"}
}