{
  "type": "Feature",
  "properties": {
    "gn:country":"CH",
    "gn:fcode":"PPL",
    "gn:population":37,
    "iso:country":"CH",
    "qs_pg:aaroncc":"CH",
    "qs_pg:gn_country":"CH",
    "qs_pg:gn_fcode":"PPL",
    "qs_pg:gn_pop":37,
    "qs_pg:name":"Rittweg",
    "qs_pg:photos_9r":0,
    "qs_pg:photos_sr":0,
    "qs_pg:pop_sr":1,
    "qs_pg:qs_pg_placetype":"locality",
    "wof:name":"Rittweg",
    "wof:placetype":"neighbourhood",
    "wof:population":37
},
  "geometry": {"coordinates":[8.86482,47.37853],"type":"Point"}
}