{
  "type": "Feature",
  "properties": {
    "iso:country":"CH",
    "wof:name":"Montchoisy",
    "wof:placetype":"neighbourhood"
},
  "geometry": {"coordinates":[6.16447824796807,46.20402729978824],"type":"Point"}
}