{
  "type": "Feature",
  "properties": {
    "gn:country":"CH",
    "gn:fcode":"PPLX",
    "gn:population":81,
    "iso:country":"CH",
    "name:eng_x_preferred":[
        "Industrie West"
    ],
    "name:eng_x_variant":[
        "Schlieren / Industrie West"
    ],
    "qs_pg:aaroncc":"CH",
    "qs_pg:gn_country":"CH",
    "qs_pg:gn_fcode":"PPLX",
    "qs_pg:gn_pop":81,
    "qs_pg:name":"Schlieren / Industrie West",
    "qs_pg:photos_9r":0,
    "qs_pg:photos_sr":0,
    "qs_pg:pop_sr":1,
    "qs_pg:qs_pg_placetype":"neighbourhood",
    "wof:lang_x_official":[
        "deu",
        "fra",
        "gsw",
        "ita"
    ],
    "wof:lang_x_spoken":[
        "deu",
        "fra",
        "gsw",
        "ita",
        "roh"
    ],
    "wof:name":"Industrie West",
    "wof:placetype":"neighbourhood",
    "wof:population":81
},
  "geometry": {"coordinates":[8.44159,47.40063],"type":"Point"}
}