{
  "type": "Feature",
  "properties": {
    "gn:gn_country":"CH",
    "gn:gn_fcode":"PPLX",
    "gn:gn_pop":81,
    "gn:population":81,
    "iso:country":"CH",
    "name:unk_x_variant":[
        "Industrie West"
    ],
    "qs_pg:aaroncc":"CH",
    "qs_pg:gn_country":"CH",
    "qs_pg:gn_fcode":"PPLX",
    "qs_pg:gn_pop":81,
    "qs_pg:name":"Schlieren / Industrie West",
    "qs_pg:photos_9r":0,
    "qs_pg:photos_sr":0,
    "qs_pg:pop_sr":1,
    "qs_pg:qs_pg_placetype":"neighbourhood",
    "wof:name":"Schlieren / Industrie West",
    "wof:placetype":"neighbourhood",
    "wof:population":81
},
  "geometry": {"coordinates":[8.44159,47.40063],"type":"Point"}
}