{
  "type": "Feature",
  "properties": {
    "gn:admin1_code":"JU",
    "gn:admin2_code":"2603.0",
    "gn:admin3_code":"6783.0",
    "gn:asciiname":"Mormont",
    "gn:country_code":"CH",
    "gn:dem":538,
    "gn:feature_class":"P",
    "gn:feature_code":"PPL",
    "gn:name":"Mormont",
    "gn:population":0,
    "gn:timezone":"Europe/Zurich",
    "iso:country":"CH",
    "name:deu_x_preferred":[
        "Mormont"
    ],
    "name:fra_x_preferred":[
        "Mormont"
    ],
    "name:nno_x_preferred":[
        "Mormont"
    ],
    "wof:name":"Mormont",
    "wof:placetype":"neighbourhood"
},
  "geometry": {"coordinates":[7.0387,47.43947],"type":"Point"}
}