{
  "type": "Feature",
  "properties": {
    "gn:gn_country":"CH",
    "gn:gn_fcode":"PPLL",
    "gn:gn_pop":49,
    "gn:population":49,
    "iso:country":"CH",
    "qs_pg:aaroncc":"CH",
    "qs_pg:gn_country":"CH",
    "qs_pg:gn_fcode":"PPLL",
    "qs_pg:gn_pop":49,
    "qs_pg:name":"Mettmenriet",
    "qs_pg:photos_9r":0,
    "qs_pg:photos_sr":0,
    "qs_pg:pop_sr":1,
    "qs_pg:qs_pg_placetype":"locality",
    "wof:name":"Mettmenriet",
    "wof:placetype":"neighbourhood",
    "wof:population":49
},
  "geometry": {"coordinates":[8.54572,47.5126],"type":"Point"}
}