{
  "type": "Feature",
  "properties": {
    "gn:admin1_code":"BE",
    "gn:admin2_code":"249.0",
    "gn:admin3_code":"561.0",
    "gn:asciiname":"Engstligenalp",
    "gn:country_code":"CH",
    "gn:dem":1951,
    "gn:elevation":"1964.0",
    "gn:feature_class":"P",
    "gn:feature_code":"PPLL",
    "gn:name":"Engstligenalp",
    "gn:population":0,
    "gn:timezone":"Europe/Zurich",
    "iso:country":"CH",
    "name:deu_x_preferred":[
        "Engstligenalp"
    ],
    "name:epo_x_preferred":[
        "Engstligenalpo"
    ],
    "wof:name":"Engstligenalp",
    "wof:placetype":"neighbourhood"
},
  "geometry": {"coordinates":[7.5649,46.44935],"type":"Point"}
}