{
  "type": "Feature",
  "properties": {
    "gn:admin1_code":"BE",
    "gn:admin2_code":"245.0",
    "gn:admin3_code":"908.0",
    "gn:asciiname":"Spitzenhaus",
    "gn:country_code":"CH",
    "gn:dem":955,
    "gn:feature_class":"P",
    "gn:feature_code":"PPL",
    "gn:name":"Spitzenhaus",
    "gn:population":0,
    "gn:timezone":"Europe/Zurich",
    "iso:country":"CH",
    "wof:name":"Spitzenhaus",
    "wof:placetype":"locality"
},
  "geometry": {"coordinates":[7.88333,46.96667],"type":"Point"}
}