{
  "type": "Feature",
  "properties": {
    "iso:country":"CH",
    "wof:name":"Lorraine",
    "wof:placetype":"neighbourhood"
},
  "geometry": {"coordinates":[7.44431752282276,46.95821405119531],"type":"Point"}
}