{
  "type": "Feature",
  "properties": {
    "gn:admin1_code":"NW",
    "gn:admin2_code":"700.0",
    "gn:admin3_code":"1511.0",
    "gn:asciiname":"Geren",
    "gn:country_code":"CH",
    "gn:dem":1209,
    "gn:feature_class":"P",
    "gn:feature_code":"PPL",
    "gn:name":"Geren",
    "gn:population":0,
    "gn:timezone":"Europe/Zurich",
    "iso:country":"CH",
    "name:und_x_variant":[
        "Goren"
    ],
    "wof:name":"Geren",
    "wof:placetype":"neighbourhood"
},
  "geometry": {"coordinates":[8.41604,46.8985],"type":"Point"}
}