{
  "type": "Feature",
  "properties": {
    "gn:admin1_code":"TG",
    "gn:admin2_code":"2012.0",
    "gn:admin3_code":"4821.0",
    "gn:asciiname":"Chalet Sunneschy",
    "gn:country_code":"CH",
    "gn:dem":476,
    "gn:feature_class":"P",
    "gn:feature_code":"PPLL",
    "gn:name":"Chalet Sunneschy",
    "gn:population":0,
    "gn:timezone":"Europe/Zurich",
    "iso:country":"CH",
    "name:deu_x_preferred":[
        "Chalet Sunneschy"
    ],
    "wof:name":"Chalet Sunneschy",
    "wof:placetype":"neighbourhood"
},
  "geometry": {"coordinates":[8.8845,47.60386],"type":"Point"}
}