{
  "type": "Feature",
  "properties": {
    "gn:admin1_code":"TG",
    "gn:admin2_code":"2012.0",
    "gn:admin3_code":"4871.0",
    "gn:asciiname":"Foersterhaus",
    "gn:country_code":"CH",
    "gn:dem":455,
    "gn:feature_class":"P",
    "gn:feature_code":"PPLL",
    "gn:name":"F\u00f6rsterhaus",
    "gn:population":0,
    "gn:timezone":"Europe/Zurich",
    "iso:country":"CH",
    "name:deu_x_preferred":[
        "F\u00f6rsterhaus"
    ],
    "wof:lang_x_official":[
        "deu",
        "fra",
        "gsw",
        "ita"
    ],
    "wof:lang_x_spoken":[
        "deu",
        "fra",
        "gsw",
        "ita",
        "roh"
    ],
    "wof:name":"Foersterhaus",
    "wof:placetype":"neighbourhood"
},
  "geometry": {"coordinates":[8.83121,47.65133],"type":"Point"}
}