{
  "type": "Feature",
  "properties": {
    "gn:admin1_code":"FR",
    "gn:admin2_code":"1003.0",
    "gn:admin3_code":"2125.0",
    "gn:asciiname":"Bouleyres",
    "gn:country_code":"CH",
    "gn:dem":735,
    "gn:feature_class":"P",
    "gn:feature_code":"PPL",
    "gn:name":"Bouleyres",
    "gn:population":0,
    "gn:timezone":"Europe/Zurich",
    "iso:country":"CH",
    "name:fra_x_preferred":[
        "Bouleyres"
    ],
    "wof:lang_x_official":[
        "deu",
        "fra",
        "gsw",
        "ita"
    ],
    "wof:lang_x_spoken":[
        "deu",
        "fra",
        "gsw",
        "ita",
        "roh"
    ],
    "wof:name":"Bouleyres",
    "wof:placetype":"neighbourhood"
},
  "geometry": {"coordinates":[7.08654,46.60802],"type":"Point"}
}