{
  "type": "Feature",
  "properties": {
    "gn:admin1_code":"TG",
    "gn:admin2_code":"2013.0",
    "gn:admin3_code":"4701.0",
    "gn:asciiname":"Sonterswil",
    "gn:country_code":"CH",
    "gn:dem":543,
    "gn:elevation":"530.0",
    "gn:feature_class":"P",
    "gn:feature_code":"PPL",
    "gn:name":"Sonterswil",
    "gn:population":0,
    "gn:timezone":"Europe/Zurich",
    "iso:country":"CH",
    "wof:name":"Sonterswil",
    "wof:placetype":"locality"
},
  "geometry": {"coordinates":[9.07949,47.62224000000001],"type":"Point"}
}