{
  "type": "Feature",
  "properties": {
    "gn:admin1_code":"TI",
    "gn:admin2_code":"2105.0",
    "gn:admin3_code":"5226.0",
    "gn:asciiname":"Crampa",
    "gn:country_code":"CH",
    "gn:dem":531,
    "gn:feature_class":"P",
    "gn:feature_code":"PPL",
    "gn:name":"Crampa",
    "gn:population":0,
    "gn:timezone":"Europe/Zurich",
    "iso:country":"CH",
    "name:ita_x_preferred":[
        "Crampa"
    ],
    "wof:name":"Crampa",
    "wof:placetype":"neighbourhood"
},
  "geometry": {"coordinates":[8.96954,46.05232],"type":"Point"}
}