{
  "type": "Feature",
  "properties": {
    "gn:admin1_code":"SO",
    "gn:admin2_code":"1108.0",
    "gn:admin3_code":"2580.0",
    "gn:asciiname":"Kappel",
    "gn:country_code":"CH",
    "gn:dem":423,
    "gn:feature_class":"P",
    "gn:feature_code":"PPL",
    "gn:name":"Kappel",
    "gn:population":0,
    "gn:timezone":"Europe/Zurich",
    "iso:country":"CH",
    "name:als_x_preferred":[
        "Kappel SO"
    ],
    "name:deu_x_preferred":[
        "Kappel"
    ],
    "name:deu_x_variant":[
        "Kappel SO"
    ],
    "name:epo_x_preferred":[
        "Kappel SO"
    ],
    "name:kaz_x_preferred":[
        "\u041a\u0430\u043f\u043f\u0435\u043b\u044c"
    ],
    "name:nno_x_preferred":[
        "Kappel i Sveits"
    ],
    "name:rus_x_preferred":[
        "\u041a\u0430\u043f\u043f\u0435\u043b\u044c"
    ],
    "name:zho_x_preferred":[
        "\u5361\u4f69\u723e"
    ],
    "wof:name":"Kappel",
    "wof:placetype":"locality"
},
  "geometry": {"coordinates":[7.84647,47.32475],"type":"Point"}
}