{
  "type": "Feature",
  "properties": {
    "gn:gn_country":"CH",
    "gn:gn_fcode":"PPL",
    "gn:gn_pop":0,
    "iso:country":"CH",
    "name:dut_x_preferred":[
        "Wasserauen"
    ],
    "name:eng_x_preferred":[
        "Wasserauen"
    ],
    "name:ger_x_preferred":[
        "Wasserauen"
    ],
    "name:rus_x_preferred":[
        "\u0412\u0430\u0441\u0441\u0435\u0440\u0430\u0443\u044d\u043d"
    ],
    "name:spa_x_preferred":[
        "Wasserauen"
    ],
    "qs_pg:aaroncc":"CH",
    "qs_pg:gn_country":"CH",
    "qs_pg:gn_fcode":"PPL",
    "qs_pg:gn_pop":0,
    "qs_pg:name":"Wasserauen",
    "qs_pg:name_adm0":"Schweiz",
    "qs_pg:name_adm1":"Kanton Appenzell Innerrhoden",
    "qs_pg:photos":186,
    "qs_pg:photos_1k":38,
    "qs_pg:photos_9k":1,
    "qs_pg:photos_9r":4,
    "qs_pg:photos_all":186,
    "qs_pg:photos_sr":4,
    "qs_pg:pop_sr":0,
    "qs_pg:qs_pg_placetype":"locality",
    "qs_pg:qs_pg_placetype_gp":"Town",
    "qs_pg:woe_adm0":23424957,
    "woe:adm0_id":23424957,
    "woe:name_adm0":"Schweiz",
    "woe:name_adm1":"Kanton Appenzell Innerrhoden",
    "woe:placetype":"Town",
    "wof:name":"Wasserauen",
    "wof:placetype":"locality"
},
  "geometry": {"coordinates":[9.42575,47.28342],"type":"Point"}
}