{
  "type": "Feature",
  "properties": {
    "gn:admin1_code":"BE",
    "gn:admin2_code":"249.0",
    "gn:admin3_code":"563.0",
    "gn:asciiname":"Achsete",
    "gn:country_code":"CH",
    "gn:dem":1142,
    "gn:feature_class":"P",
    "gn:feature_code":"PPL",
    "gn:name":"Achsete",
    "gn:population":0,
    "gn:timezone":"Europe/Zurich",
    "iso:country":"CH",
    "name:und_x_variant":[
        "Achseten"
    ],
    "wof:name":"Achsete",
    "wof:placetype":"locality"
},
  "geometry": {"coordinates":[7.59666,46.52766],"type":"Point"}
}