{
  "type": "Feature",
  "properties": {
    "gn:gn_country":"CH",
    "gn:gn_fcode":"PPL",
    "gn:gn_pop":6511,
    "gn:population":6511,
    "iso:country":"CH",
    "name:als_x_preferred":[
        "Kilchberg ZH"
    ],
    "name:deu_x_preferred":[
        "Kilchberg ZH"
    ],
    "name:epo_x_preferred":[
        "Kilchberg ZH"
    ],
    "name:kaz_x_preferred":[
        "\u041a\u0438\u043b\u044c\u0445\u0431\u0435\u0440\u0433"
    ],
    "name:nno_x_preferred":[
        "Kilchberg i Z\u00fcrich"
    ],
    "name:rus_x_preferred":[
        "\u041a\u0438\u043b\u044c\u0445\u0431\u0435\u0440\u0433"
    ],
    "name:zho_x_preferred":[
        "\u57fa\u5e0c\u4f2f\u683c"
    ],
    "qs_pg:aaroncc":"CH",
    "qs_pg:gn_country":"CH",
    "qs_pg:gn_fcode":"PPL",
    "qs_pg:gn_pop":6511,
    "qs_pg:name":"Kilchberg",
    "qs_pg:name_adm0":"Schweiz",
    "qs_pg:name_adm1":"Kanton Z\u00fcrich",
    "qs_pg:photos":374,
    "qs_pg:photos_1k":76,
    "qs_pg:photos_9k":2,
    "qs_pg:photos_9r":5,
    "qs_pg:photos_all":374,
    "qs_pg:photos_sr":6,
    "qs_pg:pop_sr":5,
    "qs_pg:qs_pg_placetype":"locality",
    "qs_pg:qs_pg_placetype_gp":"Town",
    "qs_pg:woe_adm0":23424957,
    "woe:adm0_id":23424957,
    "woe:name_adm0":"Schweiz",
    "woe:name_adm1":"Kanton Z\u00fcrich",
    "woe:placetype":"Town",
    "wof:name":"Kilchberg",
    "wof:placetype":"locality",
    "wof:population":6511
},
  "geometry": {"coordinates":[8.54548,47.32438],"type":"Point"}
}