{
  "type": "Feature",
  "properties": {
    "gn:gn_country":"CH",
    "gn:gn_fcode":"ADM3",
    "gn:gn_pop":379,
    "gn:population":377,
    "iso:country":"CH",
    "name:baq_x_preferred":[
        "Bussy-Chardonney"
    ],
    "name:cat_x_preferred":[
        "Bussy-Chardonney"
    ],
    "name:chi_x_preferred":[
        "\u6bd4\u897f-\u590f\u5c14\u591a\u5185"
    ],
    "name:dut_x_preferred":[
        "Bussy-Chardonney"
    ],
    "name:eng_x_preferred":[
        "Bussy-Chardonney"
    ],
    "name:epo_x_preferred":[
        "Bussy-Chardonney"
    ],
    "name:fre_x_preferred":[
        "Bussy-Chardonney"
    ],
    "name:ger_x_preferred":[
        "Bussy-Chardonney"
    ],
    "name:gsw_x_preferred":[
        "Bussy-Chardonney"
    ],
    "name:hun_x_preferred":[
        "Bussy-Chardonney"
    ],
    "name:ita_x_preferred":[
        "Bussy-Chardonney"
    ],
    "name:lmo_x_preferred":[
        "Bussy-Chardonney"
    ],
    "name:may_x_preferred":[
        "Bussy-Chardonney"
    ],
    "name:nno_x_preferred":[
        "Bussy-Chardonney"
    ],
    "name:oci_x_preferred":[
        "Bussy-Chardonney"
    ],
    "name:roh_x_preferred":[
        "Bussy-Chardonney"
    ],
    "name:spa_x_preferred":[
        "Bussy-Chardonney"
    ],
    "name:swe_x_preferred":[
        "Bussy-Chardonney"
    ],
    "name:vol_x_preferred":[
        "Bussy-Chardonney"
    ],
    "name:war_x_preferred":[
        "Bussy-Chardonney"
    ],
    "qs_pg:aaroncc":"CH",
    "qs_pg:gn_country":"CH",
    "qs_pg:gn_fcode":"ADM3",
    "qs_pg:gn_pop":379,
    "qs_pg:name":"Bussy-Chardonney",
    "qs_pg:name_adm0":"Schweiz",
    "qs_pg:name_adm1":"Canton de Vaud",
    "qs_pg:photos_9k":1,
    "qs_pg:photos_9r":1,
    "qs_pg:photos_all":2,
    "qs_pg:photos_sr":0,
    "qs_pg:pop_sr":2,
    "qs_pg:qs_pg_placetype":"locality",
    "qs_pg:qs_pg_placetype_gp":"Town",
    "qs_pg:woe_adm0":23424957,
    "woe:adm0_id":23424957,
    "woe:name_adm0":"Schweiz",
    "woe:name_adm1":"Canton de Vaud",
    "woe:placetype":"Town",
    "wof:name":"Bussy-Chardonney",
    "wof:placetype":"locality",
    "wof:population":377
},
  "geometry": {"coordinates":[6.44097,46.53086],"type":"Point"}
}