{
  "type": "Feature",
  "properties": {
    "gn:admin1_code":"LU",
    "gn:admin2_code":"314.0",
    "gn:admin3_code":"1081.0",
    "gn:asciiname":"Waldi",
    "gn:country_code":"CH",
    "gn:dem":729,
    "gn:elevation":"728.0",
    "gn:feature_class":"P",
    "gn:feature_code":"PPL",
    "gn:name":"Waldi",
    "gn:population":0,
    "gn:timezone":"Europe/Zurich",
    "iso:country":"CH",
    "name:cat_x_preferred":[
        "Waldi"
    ],
    "name:deu_x_preferred":[
        "Waldi"
    ],
    "name:ell_x_preferred":[
        "\u0392\u03ac\u03bb\u03bd\u03c4\u03b9"
    ],
    "name:eus_x_preferred":[
        "Waldi"
    ],
    "name:fra_x_preferred":[
        "Waldi"
    ],
    "name:por_x_preferred":[
        "Waldi"
    ],
    "name:rus_x_preferred":[
        "\u0422\u0430\u043a\u0441\u0430 \u0412\u0430\u043b\u044c\u0434\u0438"
    ],
    "name:sah_x_preferred":[
        "\u0412\u0430\u043b\u044c\u0434\u0438"
    ],
    "name:spa_x_preferred":[
        "Waldi"
    ],
    "wof:name":"Waldi",
    "wof:placetype":"neighbourhood"
},
  "geometry": {"coordinates":[8.16901,47.18934],"type":"Point"}
}