{
  "type": "Feature",
  "properties": {
    "gn:admin1_code":"ZG",
    "gn:admin2_code":"900.0",
    "gn:admin3_code":"1711.0",
    "gn:asciiname":"Zugerberg",
    "gn:country_code":"CH",
    "gn:dem":934,
    "gn:feature_class":"P",
    "gn:feature_code":"PPL",
    "gn:name":"Zugerberg",
    "gn:population":0,
    "gn:timezone":"Europe/Zurich",
    "iso:country":"CH",
    "wof:name":"Zugerberg",
    "wof:placetype":"locality"
},
  "geometry": {"coordinates":[8.53342,47.14338],"type":"Point"}
}