{
  "type": "Feature",
  "properties": {
    "gn:admin1_code":"TG",
    "gn:admin2_code":"2013.0",
    "gn:admin3_code":"4701.0",
    "gn:asciiname":"Schmidholz",
    "gn:country_code":"CH",
    "gn:dem":587,
    "gn:feature_class":"P",
    "gn:feature_code":"PPLL",
    "gn:name":"Schmidholz",
    "gn:population":0,
    "gn:timezone":"Europe/Zurich",
    "iso:country":"CH",
    "name:deu_x_preferred":[
        "Schmidholz"
    ],
    "wof:name":"Schmidholz",
    "wof:placetype":"neighbourhood"
},
  "geometry": {"coordinates":[9.08759,47.63208],"type":"Point"}
}