{
  "type": "Feature",
  "properties": {
    "gn:admin1_code":"BE",
    "gn:admin2_code":"246.0",
    "gn:admin3_code":"852.0",
    "gn:asciiname":"Sangernboden",
    "gn:country_code":"CH",
    "gn:dem":985,
    "gn:feature_class":"P",
    "gn:feature_code":"PPL",
    "gn:name":"Sangernboden",
    "gn:population":0,
    "gn:timezone":"Europe/Zurich",
    "iso:country":"CH",
    "wof:name":"Sangernboden",
    "wof:placetype":"locality"
},
  "geometry": {"coordinates":[7.35187,46.7133],"type":"Point"}
}