{
  "type": "Feature",
  "properties": {
    "gn:admin1_code":"LU",
    "gn:admin2_code":"312.0",
    "gn:admin3_code":"1069.0",
    "gn:asciiname":"Zinne",
    "gn:country_code":"CH",
    "gn:dem":446,
    "gn:feature_class":"P",
    "gn:feature_code":"PPLL",
    "gn:name":"Zinne",
    "gn:population":0,
    "gn:timezone":"Europe/Zurich",
    "iso:country":"CH",
    "name:deu_x_preferred":[
        "Zinne"
    ],
    "wof:name":"Zinne",
    "wof:placetype":"neighbourhood"
},
  "geometry": {"coordinates":[8.39795,47.0303],"type":"Point"}
}