{
  "type": "Feature",
  "properties": {
    "gn:admin1_code":"AG",
    "gn:admin2_code":"1901.0",
    "gn:admin3_code":"4007.0",
    "gn:asciiname":"Hirschthal",
    "gn:country_code":"CH",
    "gn:dem":446,
    "gn:feature_class":"P",
    "gn:feature_code":"PPL",
    "gn:name":"Hirschthal",
    "gn:population":0,
    "gn:timezone":"Europe/Zurich",
    "iso:country":"CH",
    "wof:name":"Hirschthal",
    "wof:placetype":"locality"
},
  "geometry": {"coordinates":[8.05638,47.31871],"type":"Point"}
}