{
  "type": "Feature",
  "properties": {
    "gn:admin1_code":"FR",
    "gn:admin2_code":"1002.0",
    "gn:admin3_code":"2102.0",
    "gn:asciiname":"Mossel",
    "gn:country_code":"CH",
    "gn:dem":820,
    "gn:feature_class":"P",
    "gn:feature_code":"PPL",
    "gn:name":"Mossel",
    "gn:population":0,
    "gn:timezone":"Europe/Zurich",
    "iso:country":"CH",
    "wof:name":"Mossel",
    "wof:placetype":"locality"
},
  "geometry": {"coordinates":[6.85165,46.60862],"type":"Point"}
}