{
  "type": "Feature",
  "properties": {
    "gn:gn_country":"CH",
    "gn:gn_fcode":"PPL",
    "gn:gn_pop":12,
    "gn:population":12,
    "iso:country":"CH",
    "qs_pg:aaroncc":"CH",
    "qs_pg:gn_country":"CH",
    "qs_pg:gn_fcode":"PPL",
    "qs_pg:gn_pop":12,
    "qs_pg:name":"B\u00f6sch",
    "qs_pg:photos_9r":0,
    "qs_pg:photos_sr":0,
    "qs_pg:pop_sr":1,
    "qs_pg:qs_pg_placetype":"locality",
    "wof:name":"B\u00f6sch",
    "wof:placetype":"neighbourhood",
    "wof:population":12
},
  "geometry": {"coordinates":[8.69742,47.36164],"type":"Point"}
}