{
  "type": "Feature",
  "properties": {
    "iso:country":"CH",
    "name:deu_x_preferred":[
        "St\u00f6ckacker"
    ],
    "wof:name":"Stoeckacker",
    "wof:placetype":"neighbourhood"
},
  "geometry": {"coordinates":[7.40275399101521,46.94482146491394],"type":"Point"}
}