{
  "type": "Feature",
  "properties": {
    "gn:gn_country":"CH",
    "gn:gn_fcode":"PPL",
    "gn:gn_pop":2241,
    "gn:population":2241,
    "iso:country":"CH",
    "name:alb_x_preferred":[
        "Nebikon"
    ],
    "name:baq_x_preferred":[
        "Nebikon"
    ],
    "name:cat_x_preferred":[
        "Nebikon"
    ],
    "name:chi_x_preferred":[
        "\u5167\u6bd4\u5b54"
    ],
    "name:chv_x_preferred":[
        "\u041d\u0435\u0431\u0438\u043a\u043e\u043d"
    ],
    "name:dut_x_preferred":[
        "Nebikon"
    ],
    "name:eng_x_preferred":[
        "Nebikon"
    ],
    "name:epo_x_preferred":[
        "Nebikon"
    ],
    "name:fre_x_preferred":[
        "Nebikon"
    ],
    "name:ger_x_preferred":[
        "Nebikon"
    ],
    "name:gsw_x_preferred":[
        "Nebikon"
    ],
    "name:heb_x_preferred":[
        "\u05e0\u05d1\u05d9\u05e7\u05d5\u05df"
    ],
    "name:hun_x_preferred":[
        "Nebikon"
    ],
    "name:ita_x_preferred":[
        "Nebikon"
    ],
    "name:jpn_x_preferred":[
        "\u30cd\u30fc\u30d3\u30b3\u30f3"
    ],
    "name:kaz_x_preferred":[
        "\u041d\u0435\u0431\u0438\u043a\u043e\u043d"
    ],
    "name:lat_x_preferred":[
        "Nevinhova"
    ],
    "name:lmo_x_preferred":[
        "Nebikon"
    ],
    "name:may_x_preferred":[
        "Nebikon"
    ],
    "name:nno_x_preferred":[
        "Nebikon"
    ],
    "name:oci_x_preferred":[
        "Nebikon"
    ],
    "name:pms_x_preferred":[
        "Nebikon"
    ],
    "name:por_x_preferred":[
        "Nebikon"
    ],
    "name:rus_x_preferred":[
        "\u041d\u0435\u0431\u0438\u043a\u043e\u043d"
    ],
    "name:spa_x_preferred":[
        "Nebikon"
    ],
    "name:uzb_x_preferred":[
        "Nebikon"
    ],
    "name:vol_x_preferred":[
        "Nebikon"
    ],
    "name:war_x_preferred":[
        "Nebikon"
    ],
    "qs_pg:aaroncc":"CH",
    "qs_pg:gn_country":"CH",
    "qs_pg:gn_fcode":"PPL",
    "qs_pg:gn_pop":2241,
    "qs_pg:name":"Nebikon",
    "qs_pg:name_adm0":"Schweiz",
    "qs_pg:name_adm1":"Kanton Luzern",
    "qs_pg:photos_9k":1,
    "qs_pg:photos_9r":1,
    "qs_pg:photos_all":2,
    "qs_pg:photos_sr":0,
    "qs_pg:pop_sr":4,
    "qs_pg:qs_pg_placetype":"locality",
    "qs_pg:qs_pg_placetype_gp":"Town",
    "qs_pg:woe_adm0":23424957,
    "woe:adm0_id":23424957,
    "woe:name_adm0":"Schweiz",
    "woe:name_adm1":"Kanton Luzern",
    "woe:placetype":"Town",
    "wof:name":"Nebikon",
    "wof:placetype":"locality",
    "wof:population":2241
},
  "geometry": {"coordinates":[7.97806,47.19257],"type":"Point"}
}