{
  "type": "Feature",
  "properties": {
    "gn:admin1_code":"VD",
    "gn:admin2_code":"2227.0",
    "gn:admin3_code":"5485.0",
    "gn:asciiname":"Le Setif",
    "gn:country_code":"CH",
    "gn:dem":596,
    "gn:feature_class":"P",
    "gn:feature_code":"PPL",
    "gn:name":"Le S\u00e9tif",
    "gn:population":0,
    "gn:timezone":"Europe/Zurich",
    "iso:country":"CH",
    "name:fra_x_preferred":[
        "Le S\u00e9tif"
    ],
    "wof:name":"Le Setif",
    "wof:placetype":"locality"
},
  "geometry": {"coordinates":[6.45365,46.60059],"type":"Point"}
}