{
  "type": "Feature",
  "properties": {
    "gn:admin1_code":"FR",
    "gn:admin2_code":"1002.0",
    "gn:admin3_code":"2099.0",
    "gn:asciiname":"Villaranon",
    "gn:country_code":"CH",
    "gn:dem":784,
    "gn:elevation":"791.0",
    "gn:feature_class":"P",
    "gn:feature_code":"PPL",
    "gn:name":"Villaranon",
    "gn:population":0,
    "gn:timezone":"Europe/Zurich",
    "iso:country":"CH",
    "wof:name":"Villaranon",
    "wof:placetype":"locality"
},
  "geometry": {"coordinates":[6.88299,46.67144],"type":"Point"}
}