{
  "type": "Feature",
  "properties": {
    "gn:gn_country":"CH",
    "gn:gn_fcode":"ADM3",
    "gn:gn_pop":2461,
    "gn:population":2536,
    "iso:country":"CH",
    "name:baq_x_preferred":[
        "Lonay"
    ],
    "name:bul_x_preferred":[
        "\u041b\u043e\u043d\u0430\u0439"
    ],
    "name:cat_x_preferred":[
        "Lonay"
    ],
    "name:chi_x_preferred":[
        "\u6d1b\u5948"
    ],
    "name:dut_x_preferred":[
        "Lonay"
    ],
    "name:eng_x_preferred":[
        "Lonay"
    ],
    "name:epo_x_preferred":[
        "Lonay"
    ],
    "name:fre_x_preferred":[
        "Lonay"
    ],
    "name:ger_x_preferred":[
        "Lonay"
    ],
    "name:gsw_x_preferred":[
        "Lonay"
    ],
    "name:hun_x_preferred":[
        "Lonay"
    ],
    "name:ita_x_preferred":[
        "Lonay"
    ],
    "name:lmo_x_preferred":[
        "Lonay"
    ],
    "name:may_x_preferred":[
        "Lonay"
    ],
    "name:nno_x_preferred":[
        "Lonay"
    ],
    "name:oci_x_preferred":[
        "Lonay"
    ],
    "name:roh_x_preferred":[
        "Lonay"
    ],
    "name:rus_x_preferred":[
        "\u041b\u043e\u043d\u0435"
    ],
    "name:slv_x_preferred":[
        "Lonay"
    ],
    "name:spa_x_preferred":[
        "Lonay"
    ],
    "name:swe_x_preferred":[
        "Lonay"
    ],
    "name:vol_x_preferred":[
        "Lonay"
    ],
    "name:war_x_preferred":[
        "Lonay"
    ],
    "qs_pg:aaroncc":"CH",
    "qs_pg:gn_country":"CH",
    "qs_pg:gn_fcode":"ADM3",
    "qs_pg:gn_pop":2461,
    "qs_pg:name":"Lonay",
    "qs_pg:name_adm0":"Schweiz",
    "qs_pg:name_adm1":"Canton de Vaud",
    "qs_pg:photos":76,
    "qs_pg:photos_1k":15,
    "qs_pg:photos_9k":1,
    "qs_pg:photos_9r":3,
    "qs_pg:photos_all":76,
    "qs_pg:photos_sr":3,
    "qs_pg:pop_sr":4,
    "qs_pg:qs_pg_placetype":"locality",
    "qs_pg:qs_pg_placetype_gp":"Town",
    "qs_pg:woe_adm0":23424957,
    "woe:adm0_id":23424957,
    "woe:name_adm0":"Schweiz",
    "woe:name_adm1":"Canton de Vaud",
    "woe:placetype":"Town",
    "wof:name":"Lonay",
    "wof:placetype":"locality",
    "wof:population":2536
},
  "geometry": {"coordinates":[6.51701,46.52986],"type":"Point"}
}