{
  "type": "Feature",
  "properties": {
    "gn:country":"CH",
    "gn:fcode":"PPLX",
    "gn:population":196,
    "iso:country":"CH",
    "name:eng_x_preferred":[
        "Alterszentrum"
    ],
    "name:eng_x_variant":[
        "D\u00fcbendorf / Alterszentrum"
    ],
    "qs_pg:aaroncc":"CH",
    "qs_pg:gn_country":"CH",
    "qs_pg:gn_fcode":"PPLX",
    "qs_pg:gn_pop":196,
    "qs_pg:name":"D\u00fcbendorf / Alterszentrum",
    "qs_pg:photos_9r":0,
    "qs_pg:photos_sr":0,
    "qs_pg:pop_sr":1,
    "qs_pg:qs_pg_placetype":"neighbourhood",
    "wof:name":"Alterszentrum",
    "wof:placetype":"neighbourhood",
    "wof:population":196
},
  "geometry": {"coordinates":[8.61983,47.3874],"type":"Point"}
}