{
  "type": "Feature",
  "properties": {
    "gn:admin1_code":"BE",
    "gn:admin2_code":"244.0",
    "gn:admin3_code":"339.0",
    "gn:asciiname":"Rohrbachgraben",
    "gn:country_code":"CH",
    "gn:dem":623,
    "gn:feature_class":"P",
    "gn:feature_code":"PPL",
    "gn:name":"Rohrbachgraben",
    "gn:population":0,
    "gn:timezone":"Europe/Zurich",
    "iso:country":"CH",
    "name:als_x_preferred":[
        "Rohrbachgraben BE"
    ],
    "name:deu_x_preferred":[
        "Rohrbachgraben BE"
    ],
    "name:kaz_x_preferred":[
        "\u0420\u043e\u0440\u0431\u0430\u0445\u0433\u0440\u0430\u0431\u0435\u043d"
    ],
    "name:rus_x_preferred":[
        "\u0420\u043e\u0440\u0431\u0430\u0445\u0433\u0440\u0430\u0431\u0435\u043d"
    ],
    "name:war_x_preferred":[
        "Rohrbachgraben BE"
    ],
    "name:zho_x_preferred":[
        "\u7f85\u723e\u5df4\u8d6b\u683c\u62c9\u672c"
    ],
    "wof:name":"Rohrbachgraben",
    "wof:placetype":"locality"
},
  "geometry": {"coordinates":[7.80044,47.11934],"type":"Point"}
}