{
  "type": "Feature",
  "properties": {
    "gn:admin1_code":"SZ",
    "gn:admin2_code":"505.0",
    "gn:admin3_code":"1342.0",
    "gn:asciiname":"Galgenen",
    "gn:country_code":"CH",
    "gn:dem":424,
    "gn:feature_class":"P",
    "gn:feature_code":"PPL",
    "gn:name":"Galgenen",
    "gn:population":0,
    "gn:timezone":"Europe/Zurich",
    "iso:country":"CH",
    "wof:name":"Galgenen",
    "wof:placetype":"locality"
},
  "geometry": {"coordinates":[8.87046,47.18226],"type":"Point"}
}