{
  "type": "Feature",
  "properties": {
    "gn:admin1_code":"FR",
    "gn:admin2_code":"1001.0",
    "gn:admin3_code":"2029.0",
    "gn:asciiname":"Mannens",
    "gn:country_code":"CH",
    "gn:dem":632,
    "gn:feature_class":"P",
    "gn:feature_code":"PPL",
    "gn:name":"Mannens",
    "gn:population":0,
    "gn:timezone":"Europe/Zurich",
    "iso:country":"CH",
    "name:fra_x_preferred":[
        "Mannens-Grandsivaz"
    ],
    "wof:name":"Mannens",
    "wof:placetype":"locality"
},
  "geometry": {"coordinates":[6.96889,46.79374],"type":"Point"}
}