{
  "type": "Feature",
  "properties": {
    "gn:admin1_code":"LU",
    "gn:admin2_code":"314.0",
    "gn:admin3_code":"1086.0",
    "gn:asciiname":"Riedmatt",
    "gn:country_code":"CH",
    "gn:dem":546,
    "gn:feature_class":"P",
    "gn:feature_code":"PPLL",
    "gn:name":"Riedmatt",
    "gn:population":0,
    "gn:timezone":"Europe/Zurich",
    "iso:country":"CH",
    "name:deu_x_preferred":[
        "Riedmatt"
    ],
    "wof:lang_x_official":[
        "deu",
        "fra",
        "gsw",
        "ita"
    ],
    "wof:lang_x_spoken":[
        "deu",
        "fra",
        "gsw",
        "ita",
        "roh"
    ],
    "wof:name":"Riedmatt",
    "wof:placetype":"neighbourhood"
},
  "geometry": {"coordinates":[8.06286,47.11927],"type":"Point"}
}