{
  "type": "Feature",
  "properties": {
    "gn:admin1_code":"ZH",
    "gn:admin2_code":"102.0",
    "gn:admin3_code":"30.0",
    "gn:asciiname":"Wehri",
    "gn:country_code":"CH",
    "gn:dem":353,
    "gn:feature_class":"P",
    "gn:feature_code":"PPLL",
    "gn:name":"Wehri",
    "gn:population":0,
    "gn:timezone":"Europe/Zurich",
    "iso:country":"CH",
    "name:deu_x_preferred":[
        "Wehri"
    ],
    "wof:name":"Wehri",
    "wof:placetype":"neighbourhood"
},
  "geometry": {"coordinates":[8.65423,47.5933],"type":"Point"}
}