{
  "type": "Feature",
  "properties": {
    "gn:country":"CH",
    "gn:fcode":"PPLX",
    "gn:population":121,
    "iso:country":"CH",
    "name:eng_x_preferred":[
        "Misleren-Ruchenacher"
    ],
    "name:eng_x_variant":[
        "Zumikon / Misleren-Ruchenacher"
    ],
    "qs_pg:aaroncc":"CH",
    "qs_pg:gn_country":"CH",
    "qs_pg:gn_fcode":"PPLX",
    "qs_pg:gn_pop":121,
    "qs_pg:name":"Zumikon / Misleren-Ruchenacher",
    "qs_pg:photos_9r":0,
    "qs_pg:photos_sr":0,
    "qs_pg:pop_sr":1,
    "qs_pg:qs_pg_placetype":"neighbourhood",
    "wof:name":"Misleren-Ruchenacher",
    "wof:placetype":"neighbourhood",
    "wof:population":121
},
  "geometry": {"coordinates":[8.63711,47.3311],"type":"Point"}
}