{
  "type": "Feature",
  "properties": {
    "gn:admin1_code":"OW",
    "gn:admin2_code":"600.0",
    "gn:admin3_code":"1404.0",
    "gn:asciiname":"Mehlbach",
    "gn:country_code":"CH",
    "gn:dem":936,
    "gn:feature_class":"P",
    "gn:feature_code":"PPLL",
    "gn:name":"Mehlbach",
    "gn:population":0,
    "gn:timezone":"Europe/Zurich",
    "iso:country":"CH",
    "name:deu_x_preferred":[
        "Mehlbach"
    ],
    "wof:name":"Mehlbach",
    "wof:placetype":"neighbourhood"
},
  "geometry": {"coordinates":[8.32345,46.91363],"type":"Point"}
}