{
  "type": "Feature",
  "properties": {
    "gn:admin1_code":"OW",
    "gn:admin2_code":"600.0",
    "gn:admin3_code":"1404.0",
    "gn:asciiname":"Mehlbach",
    "gn:country_code":"CH",
    "gn:dem":936,
    "gn:feature_class":"P",
    "gn:feature_code":"PPLL",
    "gn:name":"Mehlbach",
    "gn:population":0,
    "gn:timezone":"Europe/Zurich",
    "iso:country":"CH",
    "name:ceb_x_preferred":[
        "Mehlbach"
    ],
    "name:deu_x_preferred":[
        "Mehlbach"
    ],
    "name:epo_x_preferred":[
        "Mehlbach"
    ],
    "name:eus_x_preferred":[
        "Mehlbach"
    ],
    "name:fas_x_preferred":[
        "\u0645\u0647\u0644\u0628\u0627\u062e"
    ],
    "name:fra_x_preferred":[
        "Mehlbach"
    ],
    "name:hun_x_preferred":[
        "Mehlbach"
    ],
    "name:ita_x_preferred":[
        "Mehlbach"
    ],
    "name:kaz_x_preferred":[
        "\u041c\u0435\u043b\u044c\u0431\u0430\u0445"
    ],
    "name:kir_x_preferred":[
        "\u041c\u0435\u043b\u044c\u0431\u0430\u0445"
    ],
    "name:msa_x_preferred":[
        "Mehlbach"
    ],
    "name:nld_x_preferred":[
        "Mehlbach"
    ],
    "name:pol_x_preferred":[
        "Mehlbach"
    ],
    "name:por_x_preferred":[
        "Mehlbach"
    ],
    "name:ron_x_preferred":[
        "Mehlbach"
    ],
    "name:rus_x_preferred":[
        "\u041c\u0435\u043b\u044c\u0431\u0430\u0445"
    ],
    "name:spa_x_preferred":[
        "Mehlbach"
    ],
    "name:srp_x_preferred":[
        "\u041c\u0435\u043b\u0431\u0430\u0445"
    ],
    "name:ukr_x_preferred":[
        "\u041c\u0435\u043b\u044c\u0431\u0430\u0445"
    ],
    "name:uzb_x_preferred":[
        "Mehlbach"
    ],
    "name:vie_x_preferred":[
        "Mehlbach"
    ],
    "name:vol_x_preferred":[
        "Mehlbach"
    ],
    "name:war_x_preferred":[
        "Mehlbach"
    ],
    "name:zho_x_preferred":[
        "\u6885\u5c14\u5df4\u8d6b"
    ],
    "wof:name":"Mehlbach",
    "wof:placetype":"neighbourhood"
},
  "geometry": {"coordinates":[8.32345,46.91363],"type":"Point"}
}