{
  "type": "Feature",
  "properties": {
    "gn:country":"CH",
    "gn:fcode":"PPLX",
    "gn:population":486,
    "iso:country":"CH",
    "name:eng_x_preferred":[
        "Nauen (s\u00fcdl. Teil)"
    ],
    "name:eng_x_variant":[
        "Tann / Nauen (s\u00fcdl. Teil)"
    ],
    "qs_pg:aaroncc":"CH",
    "qs_pg:gn_country":"CH",
    "qs_pg:gn_fcode":"PPLX",
    "qs_pg:gn_pop":486,
    "qs_pg:name":"Tann / Nauen (s\u00fcdl. Teil)",
    "qs_pg:photos_9r":0,
    "qs_pg:photos_sr":0,
    "qs_pg:pop_sr":2,
    "qs_pg:qs_pg_placetype":"neighbourhood",
    "wof:name":"Nauen (s\u00fcdl. Teil)",
    "wof:placetype":"neighbourhood",
    "wof:population":486
},
  "geometry": {"coordinates":[8.85424,47.27285],"type":"Point"}
}