{
  "type": "Feature",
  "properties": {
    "gn:admin1_code":"NW",
    "gn:admin2_code":"700.0",
    "gn:admin3_code":"1511.0",
    "gn:asciiname":"Hinter Walibalm",
    "gn:country_code":"CH",
    "gn:dem":1024,
    "gn:feature_class":"P",
    "gn:feature_code":"PPL",
    "gn:name":"Hinter Walibalm",
    "gn:population":0,
    "gn:timezone":"Europe/Zurich",
    "iso:country":"CH",
    "name:und_x_variant":[
        "Wallibalin"
    ],
    "wof:name":"Hinter Walibalm",
    "wof:placetype":"locality"
},
  "geometry": {"coordinates":[8.40735,46.9072],"type":"Point"}
}