{
  "type": "Feature",
  "properties": {
    "gn:gn_country":"CH",
    "gn:gn_fcode":"PPLX",
    "gn:gn_pop":11737,
    "gn:population":11737,
    "iso:country":"CH",
    "name:dut_x_preferred":[
        "Industriequartier"
    ],
    "name:eng_x_preferred":[
        "Industriequartier"
    ],
    "name:fre_x_preferred":[
        "Industriequartier"
    ],
    "name:ger_x_preferred":[
        "Industriequartier"
    ],
    "name:lat_x_preferred":[
        "Industriequartier"
    ],
    "name:tur_x_preferred":[
        "Industriequartier"
    ],
    "qs_pg:aaroncc":"CH",
    "qs_pg:gn_country":"CH",
    "qs_pg:gn_fcode":"PPLX",
    "qs_pg:gn_pop":11737,
    "qs_pg:name":"Z\u00fcrich (Kreis 5)",
    "qs_pg:photos_9r":0,
    "qs_pg:photos_sr":0,
    "qs_pg:pop_sr":6,
    "qs_pg:qs_pg_placetype":"neighbourhood",
    "wof:name":"Z\u00fcrich (Kreis 5)",
    "wof:placetype":"neighbourhood",
    "wof:population":11737
},
  "geometry": {"coordinates":[8.52152,47.38767],"type":"Point"}
}