{
  "type": "Feature",
  "properties": {
    "gn:admin1_code":"BL",
    "gn:admin2_code":"1304.0",
    "gn:admin3_code":"2852.0",
    "gn:asciiname":"Rueti",
    "gn:country_code":"CH",
    "gn:dem":675,
    "gn:feature_class":"P",
    "gn:feature_code":"PPLL",
    "gn:name":"R\u00fcti",
    "gn:population":0,
    "gn:timezone":"Europe/Zurich",
    "iso:country":"CH",
    "name:deu_x_preferred":[
        "R\u00fcti"
    ],
    "wof:name":"Rueti",
    "wof:placetype":"neighbourhood"
},
  "geometry": {"coordinates":[7.87626,47.38991],"type":"Point"}
}