{
  "type": "Feature",
  "properties": {
    "gn:gn_country":"CH",
    "gn:gn_fcode":"ADM3",
    "gn:gn_pop":531,
    "gn:population":528,
    "iso:country":"CH",
    "name:ara_x_preferred":[
        "\u0644\u0648\u0634\u0627\u0631\u062a\u0632"
    ],
    "name:cat_x_preferred":[
        "L\u00fcscherz"
    ],
    "name:chv_x_preferred":[
        "\u041b\u044e\u0448\u0435\u0440\u0446"
    ],
    "name:deu_x_preferred":[
        "L\u00fcscherz"
    ],
    "name:ell_x_preferred":[
        "\u039b\u03bf\u03cd\u03c3\u03b5\u03c1\u03c4\u03c2"
    ],
    "name:eng_x_preferred":[
        "L\u00fcscherz"
    ],
    "name:epo_x_preferred":[
        "L\u00fcscherz"
    ],
    "name:eus_x_preferred":[
        "L\u00fcscherz"
    ],
    "name:fra_x_preferred":[
        "L\u00fcscherz"
    ],
    "name:gsw_x_preferred":[
        "L\u00fcscherz"
    ],
    "name:hun_x_preferred":[
        "L\u00fcscherz"
    ],
    "name:ita_x_preferred":[
        "L\u00fcscherz"
    ],
    "name:kaz_x_preferred":[
        "\u041b\u044e\u0448\u0435\u0440\u0446"
    ],
    "name:lmo_x_preferred":[
        "L\u00fcscherz"
    ],
    "name:msa_x_preferred":[
        "L\u00fcscherz"
    ],
    "name:nld_x_preferred":[
        "L\u00fcscherz"
    ],
    "name:nno_x_preferred":[
        "L\u00fcscherz"
    ],
    "name:oci_x_preferred":[
        "L\u00fcscherz"
    ],
    "name:rus_x_preferred":[
        "\u041b\u044e\u0448\u0435\u0440\u0446"
    ],
    "name:scn_x_preferred":[
        "L\u00fcscherz"
    ],
    "name:spa_x_preferred":[
        "L\u00fcscherz"
    ],
    "name:sqi_x_preferred":[
        "L\u00fcscherz"
    ],
    "name:swe_x_preferred":[
        "L\u00fcscherz"
    ],
    "name:vol_x_preferred":[
        "L\u00fcscherz"
    ],
    "name:war_x_preferred":[
        "L\u00fcscherz"
    ],
    "name:zho_x_preferred":[
        "\u5442\u820d\u8328"
    ],
    "qs_pg:aaroncc":"CH",
    "qs_pg:gn_country":"CH",
    "qs_pg:gn_fcode":"ADM3",
    "qs_pg:gn_pop":531,
    "qs_pg:name":"L\u00fcscherz",
    "qs_pg:name_adm0":"Schweiz",
    "qs_pg:name_adm1":"Kanton Bern",
    "qs_pg:photos_9k":1,
    "qs_pg:photos_9r":2,
    "qs_pg:photos_all":30,
    "qs_pg:photos_sr":0,
    "qs_pg:pop_sr":2,
    "qs_pg:qs_pg_placetype":"locality",
    "qs_pg:qs_pg_placetype_gp":"Town",
    "qs_pg:woe_adm0":23424957,
    "woe:adm0_id":23424957,
    "woe:name_adm0":"Schweiz",
    "woe:name_adm1":"Kanton Bern",
    "woe:placetype":"Town",
    "wof:name":"L\u00fcscherz",
    "wof:placetype":"locality",
    "wof:population":528
},
  "geometry": {"coordinates":[7.16306,47.04352],"type":"Point"}
}