{
  "type": "Feature",
  "properties": {
    "gn:gn_country":"CH",
    "gn:gn_fcode":"PPL",
    "gn:gn_pop":2876,
    "gn:population":2876,
    "iso:country":"CH",
    "name:alb_x_preferred":[
        "Reichenburg"
    ],
    "name:baq_x_preferred":[
        "Reichenburg"
    ],
    "name:cat_x_preferred":[
        "Reichenburg"
    ],
    "name:dut_x_preferred":[
        "Reichenburg"
    ],
    "name:eng_x_preferred":[
        "Reichenburg"
    ],
    "name:epo_x_preferred":[
        "Reichenburg"
    ],
    "name:fre_x_preferred":[
        "Reichenburg"
    ],
    "name:ger_x_preferred":[
        "Reichenburg"
    ],
    "name:gsw_x_preferred":[
        "Riicheburg"
    ],
    "name:hun_x_preferred":[
        "Reichenburg"
    ],
    "name:ita_x_preferred":[
        "Reichenburg"
    ],
    "name:kaz_x_preferred":[
        "\u0420\u0430\u0439\u0445\u0435\u043d\u0431\u0443\u0440\u0433"
    ],
    "name:lmo_x_preferred":[
        "Reichenburg"
    ],
    "name:nno_x_preferred":[
        "Reichenburg"
    ],
    "name:oci_x_preferred":[
        "Reichenburg"
    ],
    "name:pms_x_preferred":[
        "Reichenburg"
    ],
    "name:por_x_preferred":[
        "Reichenburg"
    ],
    "name:rus_x_preferred":[
        "\u0420\u0430\u0439\u0445\u0435\u043d\u0431\u0443\u0440\u0433"
    ],
    "name:spa_x_preferred":[
        "Reichenburg"
    ],
    "name:uzb_x_preferred":[
        "Reichenburg"
    ],
    "name:vol_x_preferred":[
        "Reichenburg"
    ],
    "name:war_x_preferred":[
        "Reichenburg"
    ],
    "qs_pg:aaroncc":"CH",
    "qs_pg:gn_country":"CH",
    "qs_pg:gn_fcode":"PPL",
    "qs_pg:gn_pop":2876,
    "qs_pg:name":"Reichenburg",
    "qs_pg:name_adm0":"Schweiz",
    "qs_pg:name_adm1":"Kanton Schwyz",
    "qs_pg:photos":99,
    "qs_pg:photos_1k":20,
    "qs_pg:photos_9k":1,
    "qs_pg:photos_9r":3,
    "qs_pg:photos_all":99,
    "qs_pg:photos_sr":3,
    "qs_pg:pop_sr":4,
    "qs_pg:qs_pg_placetype":"locality",
    "qs_pg:qs_pg_placetype_gp":"Town",
    "qs_pg:woe_adm0":23424957,
    "woe:adm0_id":23424957,
    "woe:name_adm0":"Schweiz",
    "woe:name_adm1":"Kanton Schwyz",
    "woe:placetype":"Town",
    "wof:name":"Reichenburg",
    "wof:placetype":"locality",
    "wof:population":2876
},
  "geometry": {"coordinates":[8.98304,47.16747],"type":"Point"}
}