{
  "type": "Feature",
  "properties": {
    "gn:admin1_code":"VD",
    "gn:admin2_code":"2221.0",
    "gn:admin3_code":"5406.0",
    "gn:asciiname":"Dailly",
    "gn:country_code":"CH",
    "gn:dem":1241,
    "gn:feature_class":"P",
    "gn:feature_code":"PPL",
    "gn:name":"Dailly",
    "gn:population":0,
    "gn:timezone":"Europe/Zurich",
    "iso:country":"CH",
    "name:ceb_x_preferred":[
        "Dailly"
    ],
    "name:cym_x_preferred":[
        "Dailly"
    ],
    "name:deu_x_preferred":[
        "Dailly"
    ],
    "name:eus_x_preferred":[
        "Dailly"
    ],
    "name:fas_x_preferred":[
        "\u062f\u06cc\u0644\u06cc"
    ],
    "name:ita_x_preferred":[
        "Dailly"
    ],
    "name:spa_x_preferred":[
        "Dailly"
    ],
    "name:swe_x_preferred":[
        "Dailly"
    ],
    "wof:name":"Dailly",
    "wof:placetype":"neighbourhood"
},
  "geometry": {"coordinates":[7.0286,46.20744000000001],"type":"Point"}
}