{
  "type": "Feature",
  "properties": {
    "gn:admin1_code":"FR",
    "gn:admin2_code":"1002.0",
    "gn:admin3_code":"2102.0",
    "gn:asciiname":"Fin de Vau",
    "gn:country_code":"CH",
    "gn:dem":824,
    "gn:feature_class":"P",
    "gn:feature_code":"PPL",
    "gn:name":"Fin de Vau",
    "gn:population":0,
    "gn:timezone":"Europe/Zurich",
    "iso:country":"CH",
    "name:fra_x_preferred":[
        "Fin de Vau"
    ],
    "wof:name":"Fin de Vau",
    "wof:placetype":"neighbourhood"
},
  "geometry": {"coordinates":[6.85623,46.61112],"type":"Point"}
}