{
  "type": "Feature",
  "properties": {
    "gn:admin1_code":"ZH",
    "gn:admin2_code":"102.0",
    "gn:admin3_code":"37.0",
    "gn:asciiname":"Im Lochacker",
    "gn:country_code":"CH",
    "gn:dem":407,
    "gn:feature_class":"P",
    "gn:feature_code":"PPLL",
    "gn:name":"Im Lochacker",
    "gn:population":0,
    "gn:timezone":"Europe/Zurich",
    "iso:country":"CH",
    "name:deu_x_preferred":[
        "Im Lochacker"
    ],
    "wof:name":"Im Lochacker",
    "wof:placetype":"locality"
},
  "geometry": {"coordinates":[8.70988,47.61303],"type":"Point"}
}