{
  "type": "Feature",
  "properties": {
    "gn:gn_country":"CH",
    "iso:country":"CH",
    "qs_pg:aaroncc":"CH",
    "qs_pg:gn_country":"CH",
    "qs_pg:name":"Biaufond",
    "qs_pg:name_adm0":"Schweiz",
    "qs_pg:name_adm1":"Canton de Jura",
    "qs_pg:photos":245,
    "qs_pg:photos_1k":50,
    "qs_pg:photos_9k":1,
    "qs_pg:photos_9r":4,
    "qs_pg:photos_all":245,
    "qs_pg:photos_sr":4,
    "qs_pg:pop_sr":0,
    "qs_pg:qs_pg_placetype":"locality",
    "qs_pg:qs_pg_placetype_gp":"Town",
    "qs_pg:woe_adm0":23424957,
    "woe:adm0_id":23424957,
    "woe:name_adm0":"Schweiz",
    "woe:name_adm1":"Canton de Jura",
    "woe:placetype":"Town",
    "wof:name":"Biaufond",
    "wof:placetype":"locality"
},
  "geometry": {"coordinates":[6.844461,47.155383],"type":"Point"}
}