{
  "type": "Feature",
  "properties": {
    "gn:admin1_code":"VS",
    "gn:admin2_code":"2311.0",
    "gn:admin3_code":"6252.0",
    "gn:asciiname":"Niouc",
    "gn:country_code":"CH",
    "gn:dem":1007,
    "gn:feature_class":"P",
    "gn:feature_code":"PPL",
    "gn:name":"Niouc",
    "gn:population":0,
    "gn:timezone":"Europe/Zurich",
    "iso:country":"CH",
    "wof:name":"Niouc",
    "wof:placetype":"locality"
},
  "geometry": {"coordinates":[7.55384,46.27158],"type":"Point"}
}