{
  "type": "Feature",
  "properties": {
    "gn:admin1_code":"FR",
    "gn:admin2_code":"1004.0",
    "gn:admin3_code":"2234.0",
    "gn:asciiname":"Lentigny",
    "gn:country_code":"CH",
    "gn:dem":731,
    "gn:elevation":"720.0",
    "gn:feature_class":"P",
    "gn:feature_code":"PPL",
    "gn:name":"Lentigny",
    "gn:population":0,
    "gn:timezone":"Europe/Zurich",
    "iso:country":"CH",
    "wof:name":"Lentigny",
    "wof:placetype":"locality"
},
  "geometry": {"coordinates":[7.00294,46.76106],"type":"Point"}
}