{
  "type": "Feature",
  "properties": {
    "gn:admin1_code":"TG",
    "gn:admin2_code":"2015.0",
    "gn:admin3_code":"4951.0",
    "gn:asciiname":"Brunenaecker",
    "gn:country_code":"CH",
    "gn:dem":410,
    "gn:feature_class":"P",
    "gn:feature_code":"PPLL",
    "gn:name":"Brunen\u00e4cker",
    "gn:population":0,
    "gn:timezone":"Europe/Zurich",
    "iso:country":"CH",
    "name:deu_x_preferred":[
        "Brunen\u00e4cker"
    ],
    "wof:name":"Brunenaecker",
    "wof:placetype":"neighbourhood"
},
  "geometry": {"coordinates":[9.03262,47.58682],"type":"Point"}
}