{
  "type": "Feature",
  "properties": {
    "gn:admin1_code":"VD",
    "gn:admin2_code":"2228.0",
    "gn:admin3_code":"5728.0",
    "gn:asciiname":"Avenex",
    "gn:country_code":"CH",
    "gn:dem":458,
    "gn:elevation":"455.0",
    "gn:feature_class":"P",
    "gn:feature_code":"PPL",
    "gn:name":"Avenex",
    "gn:population":0,
    "gn:timezone":"Europe/Zurich",
    "iso:country":"CH",
    "wof:name":"Avenex",
    "wof:placetype":"locality"
},
  "geometry": {"coordinates":[6.21184,46.39298],"type":"Point"}
}