{
  "type": "Feature",
  "properties": {
    "gn:admin1_code":"FR",
    "gn:admin2_code":"1003.0",
    "gn:admin3_code":"2163.0",
    "gn:asciiname":"Gros Ganet",
    "gn:country_code":"CH",
    "gn:dem":1330,
    "gn:feature_class":"P",
    "gn:feature_code":"PPL",
    "gn:name":"Gros Ganet",
    "gn:population":0,
    "gn:timezone":"Europe/Zurich",
    "iso:country":"CH",
    "name:fra_x_preferred":[
        "Gros Ganet"
    ],
    "wof:name":"Gros Ganet",
    "wof:placetype":"locality"
},
  "geometry": {"coordinates":[7.1974,46.61815],"type":"Point"}
}