{
  "type": "Feature",
  "properties": {
    "gn:gn_country":"CH",
    "gn:gn_fcode":"ADM3",
    "gn:gn_pop":120,
    "gn:population":116,
    "iso:country":"CH",
    "name:cat_x_preferred":[
        "Mont-Tramelan"
    ],
    "name:chv_x_preferred":[
        "\u041c\u043e\u043d-\u0422\u0440\u0430\u043c\u043b\u0430\u043d"
    ],
    "name:deu_x_preferred":[
        "Mont-Tramelan"
    ],
    "name:eng_x_preferred":[
        "Mont-Tramelan"
    ],
    "name:epo_x_preferred":[
        "Mont-Tramelan"
    ],
    "name:eus_x_preferred":[
        "Mont-Tramelan"
    ],
    "name:fra_x_preferred":[
        "Mont-Tramelan"
    ],
    "name:gsw_x_preferred":[
        "Mont-Tramelan"
    ],
    "name:hun_x_preferred":[
        "Mont-Tramelan"
    ],
    "name:ita_x_preferred":[
        "Mont-Tramelan"
    ],
    "name:kaz_x_preferred":[
        "\u041c\u043e\u043d-\u0422\u0440\u0430\u043c\u043b\u0430\u043d"
    ],
    "name:lmo_x_preferred":[
        "Mont-Tramelan"
    ],
    "name:msa_x_preferred":[
        "Mont-Tramelan"
    ],
    "name:nld_x_preferred":[
        "Mont-Tramelan"
    ],
    "name:nno_x_preferred":[
        "Mont-Tramelan"
    ],
    "name:oci_x_preferred":[
        "Mont-Tramelan"
    ],
    "name:por_x_preferred":[
        "Mont-Tramelan"
    ],
    "name:rus_x_preferred":[
        "\u041c\u043e\u043d-\u0422\u0440\u0430\u043c\u043b\u0430\u043d"
    ],
    "name:spa_x_preferred":[
        "Mont Tramelan"
    ],
    "name:sqi_x_preferred":[
        "Mont-Tramelan"
    ],
    "name:swe_x_preferred":[
        "Mont-Tramelan"
    ],
    "name:vie_x_preferred":[
        "Mont-Tramelan"
    ],
    "name:vol_x_preferred":[
        "Mont-Tramelan"
    ],
    "name:war_x_preferred":[
        "Mont-Tramelan"
    ],
    "name:zho_x_preferred":[
        "\u8499\u7279-\u7279\u62c9\u6885\u862d"
    ],
    "qs_pg:aaroncc":"CH",
    "qs_pg:gn_country":"CH",
    "qs_pg:gn_fcode":"ADM3",
    "qs_pg:gn_pop":120,
    "qs_pg:name":"Mont-Tramelan",
    "qs_pg:name_adm0":"Schweiz",
    "qs_pg:name_adm1":"Kanton Bern",
    "qs_pg:photos_9k":1,
    "qs_pg:photos_9r":1,
    "qs_pg:photos_all":1,
    "qs_pg:photos_sr":0,
    "qs_pg:pop_sr":1,
    "qs_pg:qs_pg_placetype":"locality",
    "qs_pg:qs_pg_placetype_gp":"Town",
    "qs_pg:woe_adm0":23424957,
    "woe:adm0_id":23424957,
    "woe:name_adm0":"Schweiz",
    "woe:name_adm1":"Kanton Bern",
    "woe:placetype":"Town",
    "wof:name":"Mont-Tramelan",
    "wof:placetype":"locality",
    "wof:population":116
},
  "geometry": {"coordinates":[7.06477,47.20999],"type":"Point"}
}