{
  "type": "Feature",
  "properties": {
    "gn:admin1_code":"TG",
    "gn:admin2_code":"2015.0",
    "gn:admin3_code":"4711.0",
    "gn:asciiname":"Zezikon",
    "gn:country_code":"CH",
    "gn:dem":511,
    "gn:elevation":"492.0",
    "gn:feature_class":"P",
    "gn:feature_code":"PPL",
    "gn:name":"Zezikon",
    "gn:population":0,
    "gn:timezone":"Europe/Zurich",
    "iso:country":"CH",
    "wof:name":"Zezikon",
    "wof:placetype":"locality"
},
  "geometry": {"coordinates":[9.0237,47.53649],"type":"Point"}
}