{
  "type": "Feature",
  "properties": {
    "gn:gn_country":"CH",
    "gn:gn_fcode":"PPLX",
    "gn:gn_pop":115,
    "gn:population":115,
    "iso:country":"CH",
    "name:eng_x_preferred":[
        "Terrassensiedlung"
    ],
    "name:eng_x_variant":[
        "Kollbrunn / Terrassensiedlung"
    ],
    "name:unk_x_variant":[
        "Terrassensiedlung"
    ],
    "qs_pg:aaroncc":"CH",
    "qs_pg:gn_country":"CH",
    "qs_pg:gn_fcode":"PPLX",
    "qs_pg:gn_pop":115,
    "qs_pg:name":"Kollbrunn / Terrassensiedlung",
    "qs_pg:photos_9r":0,
    "qs_pg:photos_sr":0,
    "qs_pg:pop_sr":1,
    "qs_pg:qs_pg_placetype":"neighbourhood",
    "wof:name":"Terrassensiedlung",
    "wof:placetype":"neighbourhood",
    "wof:population":115
},
  "geometry": {"coordinates":[8.78342,47.46095],"type":"Point"}
}