{
  "type": "Feature",
  "properties": {
    "gn:admin1_code":"LU",
    "gn:admin2_code":"316.0",
    "gn:admin3_code":"1107.0",
    "gn:asciiname":"Klungelisei",
    "gn:country_code":"CH",
    "gn:dem":614,
    "gn:feature_class":"P",
    "gn:feature_code":"PPLL",
    "gn:name":"Klungelisei",
    "gn:population":0,
    "gn:timezone":"Europe/Zurich",
    "iso:country":"CH",
    "name:deu_x_preferred":[
        "Klungelisei"
    ],
    "wof:name":"Klungelisei",
    "wof:placetype":"neighbourhood"
},
  "geometry": {"coordinates":[8.06708,47.03482],"type":"Point"}
}