{
  "type": "Feature",
  "properties": {
    "gn:gn_country":"CH",
    "gn:gn_fcode":"PPL",
    "gn:gn_pop":0,
    "iso:country":"CH",
    "name:cat_x_preferred":[
        "Neyruz"
    ],
    "name:deu_x_preferred":[
        "Neyruz FR"
    ],
    "name:eng_x_preferred":[
        "Neyruz"
    ],
    "name:epo_x_preferred":[
        "Neyruz FR"
    ],
    "name:eus_x_preferred":[
        "Neyruz"
    ],
    "name:fra_x_preferred":[
        "Neyruz"
    ],
    "name:hun_x_preferred":[
        "Neyruz"
    ],
    "name:ita_x_preferred":[
        "Neyruz"
    ],
    "name:lmo_x_preferred":[
        "Neyruz"
    ],
    "name:msa_x_preferred":[
        "Neyruz"
    ],
    "name:nld_x_preferred":[
        "Neyruz"
    ],
    "name:nno_x_preferred":[
        "Neyruz"
    ],
    "name:oci_x_preferred":[
        "Neyruz"
    ],
    "name:pms_x_preferred":[
        "Neyruz"
    ],
    "name:por_x_preferred":[
        "Neyruz"
    ],
    "name:roh_x_preferred":[
        "Neyruz"
    ],
    "name:spa_x_preferred":[
        "Neyruz"
    ],
    "name:sqi_x_preferred":[
        "Neyruz"
    ],
    "name:swe_x_preferred":[
        "Neyruz"
    ],
    "name:vie_x_preferred":[
        "Neyruz"
    ],
    "name:vol_x_preferred":[
        "Neyruz"
    ],
    "name:war_x_preferred":[
        "Neyruz"
    ],
    "name:zho_x_preferred":[
        "\u5167\u5442"
    ],
    "qs_pg:aaroncc":"CH",
    "qs_pg:gn_country":"CH",
    "qs_pg:gn_fcode":"PPL",
    "qs_pg:gn_pop":0,
    "qs_pg:name":"Neyruz",
    "qs_pg:name_adm0":"Schweiz",
    "qs_pg:name_adm1":"Canton de Fribourg",
    "qs_pg:photos":108,
    "qs_pg:photos_1k":22,
    "qs_pg:photos_9k":1,
    "qs_pg:photos_9r":3,
    "qs_pg:photos_all":108,
    "qs_pg:photos_sr":3,
    "qs_pg:pop_sr":0,
    "qs_pg:qs_pg_placetype":"locality",
    "qs_pg:qs_pg_placetype_gp":"Town",
    "qs_pg:woe_adm0":23424957,
    "woe:adm0_id":23424957,
    "woe:name_adm0":"Schweiz",
    "woe:name_adm1":"Canton de Fribourg",
    "woe:placetype":"Town",
    "wof:name":"Neyruz",
    "wof:placetype":"locality"
},
  "geometry": {"coordinates":[7.06827,46.76868],"type":"Point"}
}