{
  "type": "Feature",
  "properties": {
    "gn:gn_country":"CH",
    "gn:gn_fcode":"PPLX",
    "gn:gn_pop":179,
    "gn:population":179,
    "iso:country":"CH",
    "name:eng_x_preferred":[
        "Im J\u00f6ndler"
    ],
    "name:eng_x_variant":[
        "Oetwil / Im J\u00f6ndler"
    ],
    "name:unk_x_variant":[
        "Im J\u00f6ndler"
    ],
    "qs_pg:aaroncc":"CH",
    "qs_pg:gn_country":"CH",
    "qs_pg:gn_fcode":"PPLX",
    "qs_pg:gn_pop":179,
    "qs_pg:name":"Oetwil / Im J\u00f6ndler",
    "qs_pg:photos_9r":0,
    "qs_pg:photos_sr":0,
    "qs_pg:pop_sr":1,
    "qs_pg:qs_pg_placetype":"neighbourhood",
    "wof:name":"Im J\u00f6ndler",
    "wof:placetype":"neighbourhood",
    "wof:population":179
},
  "geometry": {"coordinates":[8.72294,47.26873],"type":"Point"}
}