{
  "type": "Feature",
  "properties": {
    "gn:admin1_code":"NE",
    "gn:admin2_code":"2405.0",
    "gn:admin3_code":"6487.0",
    "gn:asciiname":"Les Vieux-Pres",
    "gn:country_code":"CH",
    "gn:dem":1033,
    "gn:elevation":"1030.0",
    "gn:feature_class":"P",
    "gn:feature_code":"PPL",
    "gn:name":"Les Vieux-Pr\u00e9s",
    "gn:population":0,
    "gn:timezone":"Europe/Zurich",
    "iso:country":"CH",
    "wof:name":"Les Vieux-Pres",
    "wof:placetype":"locality"
},
  "geometry": {"coordinates":[6.93756,47.0836],"type":"Point"}
}