{
  "type": "Feature",
  "properties": {
    "gn:gn_country":"CH",
    "gn:gn_fcode":"PPL",
    "gn:gn_pop":226,
    "gn:population":226,
    "iso:country":"CH",
    "name:deu_x_preferred":[
        "Saint-Jean VS"
    ],
    "name:eng_x_preferred":[
        "Saint-Jean"
    ],
    "name:fra_x_preferred":[
        "Saint-Jean"
    ],
    "name:ita_x_preferred":[
        "Saint-Jean"
    ],
    "name:nld_x_preferred":[
        "Saint-Jean"
    ],
    "name:pms_x_preferred":[
        "Saint-Jean"
    ],
    "name:por_x_preferred":[
        "Saint-Jean"
    ],
    "name:roh_x_preferred":[
        "Saint-Jean"
    ],
    "name:swe_x_preferred":[
        "Saint-Jean"
    ],
    "qs_pg:aaroncc":"CH",
    "qs_pg:gn_country":"CH",
    "qs_pg:gn_fcode":"PPL",
    "qs_pg:gn_pop":226,
    "qs_pg:name":"Saint-Jean",
    "qs_pg:photos_9r":0,
    "qs_pg:photos_sr":0,
    "qs_pg:pop_sr":2,
    "qs_pg:qs_pg_placetype":"locality",
    "wof:name":"Saint-Jean",
    "wof:placetype":"neighbourhood",
    "wof:population":226
},
  "geometry": {"coordinates":[7.58662,46.19688],"type":"Point"}
}