{
  "type": "Feature",
  "properties": {
    "gn:gn_country":"CH",
    "gn:gn_fcode":"PPL",
    "gn:gn_pop":13057,
    "gn:population":13057,
    "iso:country":"CH",
    "name:ara_x_preferred":[
        "\u062b\u0648\u0646\u064a\u0643\u0633"
    ],
    "name:baq_x_preferred":[
        "Th\u00f4nex"
    ],
    "name:cat_x_preferred":[
        "Th\u00f4nex"
    ],
    "name:chi_x_preferred":[
        "\u6258\u5185"
    ],
    "name:dan_x_preferred":[
        "Th\u00f4nex"
    ],
    "name:dut_x_preferred":[
        "Th\u00f4nex"
    ],
    "name:eng_x_preferred":[
        "Th\u00f4nex"
    ],
    "name:epo_x_preferred":[
        "Th\u00f4nex"
    ],
    "name:fas_x_preferred":[
        "\u062a\u0648\u0646\u06a9\u0633"
    ],
    "name:fin_x_preferred":[
        "Th\u00f4nex"
    ],
    "name:fre_x_preferred":[
        "Th\u00f4nex"
    ],
    "name:frp_x_preferred":[
        "Toun\u00e8x"
    ],
    "name:ger_x_preferred":[
        "Th\u00f4nex"
    ],
    "name:gsw_x_preferred":[
        "Th\u00f4nex"
    ],
    "name:heb_x_preferred":[
        "\u05ea\u05d5\u05e0\u05d4"
    ],
    "name:hun_x_preferred":[
        "Th\u00f4nex"
    ],
    "name:ind_x_preferred":[
        "Th\u00f4nex"
    ],
    "name:ita_x_preferred":[
        "Th\u00f4nex"
    ],
    "name:jpn_x_preferred":[
        "\u30c8\u30cd"
    ],
    "name:lit_x_preferred":[
        "Toneksas"
    ],
    "name:lmo_x_preferred":[
        "Th\u00f4nex"
    ],
    "name:may_x_preferred":[
        "Th\u00f4nex"
    ],
    "name:nan_x_preferred":[
        "Th\u00f4nex"
    ],
    "name:nno_x_preferred":[
        "Th\u00f4nex"
    ],
    "name:oci_x_preferred":[
        "Th\u00f4nex"
    ],
    "name:per_x_preferred":[
        "\u062a\u0648\u0646\u06a9\u0633"
    ],
    "name:pol_x_preferred":[
        "Th\u00f4nex"
    ],
    "name:por_x_preferred":[
        "Th\u00f4nex"
    ],
    "name:roh_x_preferred":[
        "Th\u00f4nex"
    ],
    "name:rus_x_preferred":[
        "\u0422\u043e\u043d\u0435"
    ],
    "name:spa_x_preferred":[
        "Th\u00f4nex"
    ],
    "name:swe_x_preferred":[
        "Th\u00f4nex"
    ],
    "name:vie_x_preferred":[
        "Th\u00f4nex"
    ],
    "name:vol_x_preferred":[
        "Th\u00f4nex"
    ],
    "name:war_x_preferred":[
        "Th\u00f4nex"
    ],
    "name:zho_x_preferred":[
        "\u6258\u5185"
    ],
    "qs_pg:aaroncc":"CH",
    "qs_pg:gn_country":"CH",
    "qs_pg:gn_fcode":"PPL",
    "qs_pg:gn_pop":13057,
    "qs_pg:name":"Th\u00f4nex",
    "qs_pg:name_adm0":"Schweiz",
    "qs_pg:name_adm1":"Canton de Gen\u00e8ve",
    "qs_pg:photos":165,
    "qs_pg:photos_1k":33,
    "qs_pg:photos_9k":1,
    "qs_pg:photos_9r":4,
    "qs_pg:photos_all":165,
    "qs_pg:photos_sr":4,
    "qs_pg:pop_sr":6,
    "qs_pg:qs_pg_placetype":"locality",
    "qs_pg:qs_pg_placetype_gp":"Town",
    "qs_pg:woe_adm0":23424957,
    "woe:adm0_id":23424957,
    "woe:name_adm0":"Schweiz",
    "woe:name_adm1":"Canton de Gen\u00e8ve",
    "woe:placetype":"Town",
    "wof:name":"Th\u00f4nex",
    "wof:placetype":"locality",
    "wof:population":13057
},
  "geometry": {"coordinates":[6.19904,46.18815],"type":"Point"}
}