{
  "type": "Feature",
  "properties": {
    "gn:admin1_code":"VS",
    "gn:admin2_code":"2303.0",
    "gn:admin3_code":"6031.0",
    "gn:asciiname":"Le Chable",
    "gn:country_code":"CH",
    "gn:dem":837,
    "gn:feature_class":"P",
    "gn:feature_code":"PPL",
    "gn:name":"Le Ch\u00e2ble",
    "gn:population":0,
    "gn:timezone":"Europe/Zurich",
    "iso:country":"CH",
    "wof:name":"Le Chable",
    "wof:placetype":"locality"
},
  "geometry": {"coordinates":[7.21192,46.07978],"type":"Point"}
}