{
  "type": "Feature",
  "properties": {
    "gn:admin1_code":"BE",
    "gn:admin2_code":"242.0",
    "gn:admin3_code":"750.0",
    "gn:asciiname":"Lattrigen",
    "gn:country_code":"CH",
    "gn:dem":441,
    "gn:elevation":"447.0",
    "gn:feature_class":"P",
    "gn:feature_code":"PPL",
    "gn:name":"Lattrigen",
    "gn:population":0,
    "gn:timezone":"Europe/Zurich",
    "iso:country":"CH",
    "wof:name":"Lattrigen",
    "wof:placetype":"neighbourhood"
},
  "geometry": {"coordinates":[7.21298,47.10096],"type":"Point"}
}