{
  "type": "Feature",
  "properties": {
    "gn:country":"CH",
    "gn:fcode":"PPL",
    "gn:population":0,
    "iso:country":"CH",
    "name:cat_x_preferred":[
        "Malaval"
    ],
    "name:ceb_x_preferred":[
        "Malval"
    ],
    "name:che_x_preferred":[
        "\u041c\u0430\u043b\u044c\u0432\u0430\u043b\u044c"
    ],
    "name:deu_x_preferred":[
        "Malval"
    ],
    "name:epo_x_preferred":[
        "Malval"
    ],
    "name:eus_x_preferred":[
        "Malval"
    ],
    "name:fra_x_preferred":[
        "Malval"
    ],
    "name:hun_x_preferred":[
        "Malval"
    ],
    "name:ind_x_preferred":[
        "Malval"
    ],
    "name:ita_x_preferred":[
        "Malval"
    ],
    "name:kaz_x_preferred":[
        "\u041c\u0430\u043b\u044c\u0432\u0430\u043b\u044c"
    ],
    "name:lat_x_preferred":[
        "Malval"
    ],
    "name:msa_x_preferred":[
        "Malval"
    ],
    "name:nld_x_preferred":[
        "Malval"
    ],
    "name:oci_x_preferred":[
        "Malaval"
    ],
    "name:pms_x_preferred":[
        "Malval"
    ],
    "name:pol_x_preferred":[
        "Malval"
    ],
    "name:por_x_preferred":[
        "Malval"
    ],
    "name:ron_x_preferred":[
        "Malval"
    ],
    "name:rus_x_preferred":[
        "\u041c\u0430\u043b\u044c\u0432\u0430\u043b\u044c"
    ],
    "name:slk_x_preferred":[
        "Malval"
    ],
    "name:spa_x_preferred":[
        "Malval"
    ],
    "name:swe_x_preferred":[
        "Malval"
    ],
    "name:ukr_x_preferred":[
        "\u041c\u0430\u043b\u044c\u0432\u0430\u043b\u044c"
    ],
    "name:uzb_x_preferred":[
        "Malval"
    ],
    "name:vie_x_preferred":[
        "Malval"
    ],
    "name:vol_x_preferred":[
        "Malval"
    ],
    "name:war_x_preferred":[
        "Malval"
    ],
    "name:zho_x_preferred":[
        "\u9a6c\u5c14\u74e6"
    ],
    "qs_pg:aaroncc":"CH",
    "qs_pg:gn_country":"CH",
    "qs_pg:gn_fcode":"PPL",
    "qs_pg:gn_pop":0,
    "qs_pg:name":"Malval",
    "qs_pg:name_adm0":"Schweiz",
    "qs_pg:name_adm1":"Canton de Gen\u00e8ve",
    "qs_pg:photos":33,
    "qs_pg:photos_1k":7,
    "qs_pg:photos_9k":1,
    "qs_pg:photos_9r":2,
    "qs_pg:photos_all":33,
    "qs_pg:photos_sr":2,
    "qs_pg:pop_sr":0,
    "qs_pg:qs_pg_placetype":"locality",
    "qs_pg:qs_pg_placetype_gp":"Town",
    "qs_pg:woe_adm0":23424957,
    "woe:adm0_id":23424957,
    "woe:name_adm0":"Schweiz",
    "woe:name_adm1":"Canton de Gen\u00e8ve",
    "woe:placetype":"Town",
    "wof:name":"Malval",
    "wof:placetype":"neighbourhood"
},
  "geometry": {"coordinates":[5.99137,46.21264],"type":"Point"}
}