{
  "type": "Feature",
  "properties": {
    "gn:admin1_code":"SG",
    "gn:admin2_code":"1727.0",
    "gn:admin3_code":"3379.0",
    "gn:asciiname":"Laeui",
    "gn:country_code":"CH",
    "gn:dem":1068,
    "gn:feature_class":"P",
    "gn:feature_code":"PPLL",
    "gn:name":"L\u00e4ui",
    "gn:population":0,
    "gn:timezone":"Europe/Zurich",
    "iso:country":"CH",
    "name:deu_x_preferred":[
        "L\u00e4ui"
    ],
    "wof:name":"Laeui",
    "wof:placetype":"neighbourhood"
},
  "geometry": {"coordinates":[9.06977,47.25638],"type":"Point"}
}