{
  "type": "Feature",
  "properties": {
    "gn:gn_country":"CH",
    "gn:gn_fcode":"PPL",
    "gn:gn_pop":2201,
    "gn:population":2201,
    "iso:country":"CH",
    "name:alb_x_preferred":[
        "Pfeffingen"
    ],
    "name:als_x_preferred":[
        "Pfeffingen BL"
    ],
    "name:ast_x_preferred":[
        "Pfeffingen"
    ],
    "name:baq_x_preferred":[
        "Pfeffingen"
    ],
    "name:cat_x_preferred":[
        "Pfeffingen"
    ],
    "name:chi_x_preferred":[
        "\u666e\u8cbb\u82ac\u6839"
    ],
    "name:deu_x_preferred":[
        "Pfeffingen BL"
    ],
    "name:dut_x_preferred":[
        "Pfeffingen"
    ],
    "name:eng_x_preferred":[
        "Pfeffingen"
    ],
    "name:epo_x_preferred":[
        "Pfeffingen BL"
    ],
    "name:fre_x_preferred":[
        "Pfeffingen"
    ],
    "name:ger_x_preferred":[
        "Pfeffingen"
    ],
    "name:gsw_x_preferred":[
        "Pf\u00e4ffige BL"
    ],
    "name:hun_x_preferred":[
        "Pfeffingen"
    ],
    "name:ita_x_preferred":[
        "Pfeffingen"
    ],
    "name:kaz_x_preferred":[
        "\u041f\u0444\u0435\u0444\u0444\u0438\u043d\u0433\u0435\u043d"
    ],
    "name:lmo_x_preferred":[
        "Pfeffingen"
    ],
    "name:may_x_preferred":[
        "Pfeffingen"
    ],
    "name:nno_x_preferred":[
        "Pfeffingen"
    ],
    "name:oci_x_preferred":[
        "Pfeffingen"
    ],
    "name:rus_x_preferred":[
        "\u041f\u0444\u0435\u0444\u0444\u0438\u043d\u0433\u0435\u043d"
    ],
    "name:spa_x_preferred":[
        "Pfeffingen"
    ],
    "name:swe_x_preferred":[
        "Pfeffingen"
    ],
    "name:uzb_x_preferred":[
        "Pfeffingen"
    ],
    "name:vol_x_preferred":[
        "Pfeffingen"
    ],
    "name:war_x_preferred":[
        "Pfeffingen"
    ],
    "name:zho_x_preferred":[
        "\u666e\u8cbb\u82ac\u6839"
    ],
    "qs_pg:aaroncc":"CH",
    "qs_pg:gn_country":"CH",
    "qs_pg:gn_fcode":"PPL",
    "qs_pg:gn_pop":2201,
    "qs_pg:name":"Pfeffingen",
    "qs_pg:name_adm0":"Schweiz",
    "qs_pg:name_adm1":"Kanton Basel-Land",
    "qs_pg:photos":140,
    "qs_pg:photos_1k":28,
    "qs_pg:photos_9k":1,
    "qs_pg:photos_9r":3,
    "qs_pg:photos_all":140,
    "qs_pg:photos_sr":3,
    "qs_pg:pop_sr":4,
    "qs_pg:qs_pg_placetype":"locality",
    "qs_pg:qs_pg_placetype_gp":"Town",
    "qs_pg:woe_adm0":23424957,
    "woe:adm0_id":23424957,
    "woe:name_adm0":"Schweiz",
    "woe:name_adm1":"Kanton Basel-Land",
    "woe:placetype":"Town",
    "wof:name":"Pfeffingen",
    "wof:placetype":"locality",
    "wof:population":2201
},
  "geometry": {"coordinates":[7.58975,47.45984],"type":"Point"}
}