{
  "type": "Feature",
  "properties": {
    "gn:gn_country":"CH",
    "gn:gn_fcode":"PPL",
    "gn:gn_pop":1597,
    "gn:population":1597,
    "iso:country":"CH",
    "name:alb_x_preferred":[
        "Sattel"
    ],
    "name:als_x_preferred":[
        "Sattel SZ"
    ],
    "name:baq_x_preferred":[
        "Sattel"
    ],
    "name:cat_x_preferred":[
        "Sattel"
    ],
    "name:deu_x_preferred":[
        "Sattel SZ"
    ],
    "name:dut_x_preferred":[
        "Sattel"
    ],
    "name:eng_x_preferred":[
        "Sattel"
    ],
    "name:epo_x_preferred":[
        "Sattel SZ"
    ],
    "name:fre_x_preferred":[
        "Sattel"
    ],
    "name:ger_x_preferred":[
        "Sattel"
    ],
    "name:gsw_x_preferred":[
        "Sattel SZ"
    ],
    "name:hun_x_preferred":[
        "Sattel"
    ],
    "name:ita_x_preferred":[
        "Sattel"
    ],
    "name:kaz_x_preferred":[
        "\u0417\u0430\u0442\u0442\u0435\u043b\u044c"
    ],
    "name:lmo_x_preferred":[
        "Sattel"
    ],
    "name:nno_x_preferred":[
        "Sattel"
    ],
    "name:oci_x_preferred":[
        "Sattel"
    ],
    "name:pms_x_preferred":[
        "Sattel"
    ],
    "name:por_x_preferred":[
        "Sattel"
    ],
    "name:rus_x_preferred":[
        "\u0417\u0430\u0442\u0442\u0435\u043b\u044c"
    ],
    "name:spa_x_preferred":[
        "Sattel"
    ],
    "name:uzb_x_preferred":[
        "Sattel"
    ],
    "name:vol_x_preferred":[
        "Sattel"
    ],
    "name:war_x_preferred":[
        "Sattel"
    ],
    "qs_pg:aaroncc":"CH",
    "qs_pg:gn_country":"CH",
    "qs_pg:gn_fcode":"PPL",
    "qs_pg:gn_pop":1597,
    "qs_pg:name":"Sattel",
    "qs_pg:name_adm0":"Schweiz",
    "qs_pg:name_adm1":"Kanton Schwyz",
    "qs_pg:photos":203,
    "qs_pg:photos_1k":41,
    "qs_pg:photos_9k":1,
    "qs_pg:photos_9r":4,
    "qs_pg:photos_all":203,
    "qs_pg:photos_sr":4,
    "qs_pg:pop_sr":3,
    "qs_pg:qs_pg_placetype":"locality",
    "qs_pg:qs_pg_placetype_gp":"Town",
    "qs_pg:woe_adm0":23424957,
    "woe:adm0_id":23424957,
    "woe:name_adm0":"Schweiz",
    "woe:name_adm1":"Kanton Schwyz",
    "woe:placetype":"Town",
    "wof:name":"Sattel",
    "wof:placetype":"locality",
    "wof:population":1597
},
  "geometry": {"coordinates":[8.63565,47.08246],"type":"Point"}
}