{
  "type": "Feature",
  "properties": {
    "gn:gn_country":"CH",
    "gn:gn_fcode":"PPL",
    "gn:gn_pop":1567,
    "gn:population":1567,
    "iso:country":"CH",
    "name:ara_x_preferred":[
        "\u0645\u0627\u0631\u062a\u0627\u0644\u0646"
    ],
    "name:baq_x_preferred":[
        "Marthalen"
    ],
    "name:cat_x_preferred":[
        "Marthalen"
    ],
    "name:chi_x_preferred":[
        "\u99ac\u5854\u502b"
    ],
    "name:chv_x_preferred":[
        "\u041c\u0430\u0440\u0442\u0430\u043b\u0435\u043d"
    ],
    "name:dan_x_preferred":[
        "Marthalen"
    ],
    "name:dut_x_preferred":[
        "Marthalen"
    ],
    "name:eng_x_preferred":[
        "Marthalen"
    ],
    "name:epo_x_preferred":[
        "Marthalen"
    ],
    "name:fao_x_preferred":[
        "Marthalen"
    ],
    "name:fre_x_preferred":[
        "Marthalen"
    ],
    "name:ger_x_preferred":[
        "Marthalen"
    ],
    "name:gsw_x_preferred":[
        "Marthal\u00e4"
    ],
    "name:hun_x_preferred":[
        "Marthalen"
    ],
    "name:ita_x_preferred":[
        "Marthalen"
    ],
    "name:kal_x_preferred":[
        "Marthalen"
    ],
    "name:kaz_x_preferred":[
        "\u041c\u0430\u0440\u0442\u0430\u043b\u0435\u043d"
    ],
    "name:lat_x_preferred":[
        "Martella"
    ],
    "name:lmo_x_preferred":[
        "Marthalen"
    ],
    "name:may_x_preferred":[
        "Marthalen"
    ],
    "name:nno_x_preferred":[
        "Marthalen"
    ],
    "name:nob_x_preferred":[
        "Marthalen"
    ],
    "name:oci_x_preferred":[
        "Marthalen"
    ],
    "name:rus_x_preferred":[
        "\u041c\u0430\u0440\u0442\u0430\u043b\u0435\u043d"
    ],
    "name:spa_x_preferred":[
        "Marthalen"
    ],
    "name:swe_x_preferred":[
        "Marthalen"
    ],
    "name:uzb_x_preferred":[
        "Marthalen"
    ],
    "name:vol_x_preferred":[
        "Marthalen"
    ],
    "name:war_x_preferred":[
        "Marthalen"
    ],
    "name:zho_x_preferred":[
        "\u99ac\u5854\u502b"
    ],
    "qs_pg:aaroncc":"CH",
    "qs_pg:gn_country":"CH",
    "qs_pg:gn_fcode":"PPL",
    "qs_pg:gn_pop":1567,
    "qs_pg:name":"Marthalen",
    "qs_pg:name_adm0":"Schweiz",
    "qs_pg:name_adm1":"Kanton Z\u00fcrich",
    "qs_pg:photos":253,
    "qs_pg:photos_1k":51,
    "qs_pg:photos_9k":1,
    "qs_pg:photos_9r":4,
    "qs_pg:photos_all":253,
    "qs_pg:photos_sr":5,
    "qs_pg:pop_sr":3,
    "qs_pg:qs_pg_placetype":"locality",
    "qs_pg:qs_pg_placetype_gp":"Town",
    "qs_pg:woe_adm0":23424957,
    "woe:adm0_id":23424957,
    "woe:name_adm0":"Schweiz",
    "woe:name_adm1":"Kanton Z\u00fcrich",
    "woe:placetype":"Town",
    "wof:name":"Marthalen",
    "wof:placetype":"locality",
    "wof:population":1567
},
  "geometry": {"coordinates":[8.65326,47.62913],"type":"Point"}
}