{
  "type": "Feature",
  "properties": {
    "gn:admin1_code":"AG",
    "gn:admin2_code":"1902.0",
    "gn:admin3_code":"4038.0",
    "gn:asciiname":"Tromsberg",
    "gn:country_code":"CH",
    "gn:dem":497,
    "gn:feature_class":"P",
    "gn:feature_code":"PPLL",
    "gn:name":"Tromsberg",
    "gn:population":0,
    "gn:timezone":"Europe/Zurich",
    "iso:country":"CH",
    "wof:name":"Tromsberg",
    "wof:placetype":"neighbourhood"
},
  "geometry": {"coordinates":[8.28245,47.49876],"type":"Point"}
}