{
  "type": "Feature",
  "properties": {
    "gn:admin1_code":"SG",
    "gn:admin2_code":"1725.0",
    "gn:admin3_code":"3293.0",
    "gn:asciiname":"Gallenwerch",
    "gn:country_code":"CH",
    "gn:dem":1275,
    "gn:feature_class":"P",
    "gn:feature_code":"PPLL",
    "gn:name":"Gallenwerch",
    "gn:population":0,
    "gn:timezone":"Europe/Zurich",
    "iso:country":"CH",
    "name:deu_x_preferred":[
        "Gallenwerch"
    ],
    "wof:name":"Gallenwerch",
    "wof:placetype":"neighbourhood"
},
  "geometry": {"coordinates":[9.37557,47.03457],"type":"Point"}
}