{
  "type": "Feature",
  "properties": {
    "gn:admin1_code":"TG",
    "gn:admin2_code":"2012.0",
    "gn:admin3_code":"4590.0",
    "gn:asciiname":"Grosswies",
    "gn:country_code":"CH",
    "gn:dem":398,
    "gn:feature_class":"P",
    "gn:feature_code":"PPLL",
    "gn:name":"Grosswies",
    "gn:population":0,
    "gn:timezone":"Europe/Zurich",
    "iso:country":"CH",
    "name:deu_x_preferred":[
        "Grosswies"
    ],
    "wof:name":"Grosswies",
    "wof:placetype":"neighbourhood"
},
  "geometry": {"coordinates":[8.97117,47.58586],"type":"Point"}
}