{
  "type": "Feature",
  "properties": {
    "gn:admin1_code":"TG",
    "gn:admin2_code":"2012.0",
    "gn:admin3_code":"4536.0",
    "gn:asciiname":"Schlattingen",
    "gn:country_code":"CH",
    "gn:dem":420,
    "gn:feature_class":"P",
    "gn:feature_code":"PPL",
    "gn:name":"Schlattingen",
    "gn:population":0,
    "gn:timezone":"Europe/Zurich",
    "iso:country":"CH",
    "wof:name":"Schlattingen",
    "wof:placetype":"locality"
},
  "geometry": {"coordinates":[8.76984,47.66562],"type":"Point"}
}