{
  "type": "Feature",
  "properties": {
    "gn:admin1_code":"BE",
    "gn:admin2_code":"248.0",
    "gn:admin3_code":"794.0",
    "gn:asciiname":"Lee",
    "gn:country_code":"CH",
    "gn:dem":912,
    "gn:feature_class":"P",
    "gn:feature_code":"PPL",
    "gn:name":"Lee",
    "gn:population":0,
    "gn:timezone":"Europe/Zurich",
    "iso:country":"CH",
    "name:deu_x_preferred":[
        "Lee"
    ],
    "wof:name":"Lee",
    "wof:placetype":"locality"
},
  "geometry": {"coordinates":[7.38252,46.58272],"type":"Point"}
}