{
  "type": "Feature",
  "properties": {
    "gn:gn_country":"CH",
    "gn:gn_fcode":"PPLA3",
    "gn:gn_pop":2148,
    "gn:population":2148,
    "iso:country":"CH",
    "name:alb_x_preferred":[
        "Broc"
    ],
    "name:als_x_preferred":[
        "Broc FR"
    ],
    "name:baq_x_preferred":[
        "Broc"
    ],
    "name:cat_x_preferred":[
        "Broc"
    ],
    "name:chi_x_preferred":[
        "\u5e03\u7f57\u514b"
    ],
    "name:deu_x_preferred":[
        "Broc FR"
    ],
    "name:dut_x_preferred":[
        "Broc"
    ],
    "name:eng_x_preferred":[
        "Broc"
    ],
    "name:epo_x_preferred":[
        "Broc FR"
    ],
    "name:fin_x_preferred":[
        "Broc"
    ],
    "name:fre_x_preferred":[
        "Broc"
    ],
    "name:ger_x_preferred":[
        "Broc"
    ],
    "name:gsw_x_preferred":[
        "Broc FR"
    ],
    "name:hun_x_preferred":[
        "Broc"
    ],
    "name:ita_x_preferred":[
        "Broc"
    ],
    "name:lmo_x_preferred":[
        "Broc"
    ],
    "name:may_x_preferred":[
        "Broc"
    ],
    "name:nno_x_preferred":[
        "Broc"
    ],
    "name:oci_x_preferred":[
        "Broc"
    ],
    "name:pms_x_preferred":[
        "Broc"
    ],
    "name:pol_x_preferred":[
        "Broc"
    ],
    "name:por_x_preferred":[
        "Broc"
    ],
    "name:roh_x_preferred":[
        "Broc"
    ],
    "name:spa_x_preferred":[
        "Broc"
    ],
    "name:swe_x_preferred":[
        "Broc"
    ],
    "name:vol_x_preferred":[
        "Broc"
    ],
    "name:war_x_preferred":[
        "Broc"
    ],
    "name:zho_x_preferred":[
        "\u5e03\u7f57\u514b"
    ],
    "qs_pg:aaroncc":"CH",
    "qs_pg:gn_country":"CH",
    "qs_pg:gn_fcode":"PPLA3",
    "qs_pg:gn_pop":2148,
    "qs_pg:name":"Broc",
    "qs_pg:name_adm0":"Schweiz",
    "qs_pg:name_adm1":"Canton de Fribourg",
    "qs_pg:photos":971,
    "qs_pg:photos_1k":197,
    "qs_pg:photos_9k":4,
    "qs_pg:photos_9r":6,
    "qs_pg:photos_all":971,
    "qs_pg:photos_sr":10,
    "qs_pg:pop_sr":4,
    "qs_pg:qs_pg_placetype":"locality",
    "qs_pg:qs_pg_placetype_gp":"Town",
    "qs_pg:woe_adm0":23424957,
    "woe:adm0_id":23424957,
    "woe:name_adm0":"Schweiz",
    "woe:name_adm1":"Canton de Fribourg",
    "woe:placetype":"Town",
    "wof:name":"Broc",
    "wof:placetype":"locality",
    "wof:population":2148
},
  "geometry": {"coordinates":[7.09891,46.60514],"type":"Point"}
}