{
  "type": "Feature",
  "properties": {
    "gn:admin1_code":"VS",
    "gn:admin2_code":"2312.0",
    "gn:admin3_code":"6265.0",
    "gn:asciiname":"Granois (Saviese)",
    "gn:country_code":"CH",
    "gn:dem":857,
    "gn:feature_class":"P",
    "gn:feature_code":"PPL",
    "gn:name":"Granois (Savi\u00e8se)",
    "gn:population":0,
    "gn:timezone":"Europe/Zurich",
    "iso:country":"CH",
    "wof:name":"Granois (Saviese)",
    "wof:placetype":"neighbourhood"
},
  "geometry": {"coordinates":[7.33694,46.24886],"type":"Point"}
}