{
  "type": "Feature",
  "properties": {
    "gn:admin1_code":"SO",
    "gn:admin2_code":"1107.0",
    "gn:admin3_code":"2554.0",
    "gn:asciiname":"Winterseite",
    "gn:country_code":"CH",
    "gn:dem":575,
    "gn:feature_class":"P",
    "gn:feature_code":"PPLL",
    "gn:name":"Winterseite",
    "gn:population":0,
    "gn:timezone":"Europe/Zurich",
    "iso:country":"CH",
    "name:deu_x_preferred":[
        "Winterseite"
    ],
    "wof:name":"Winterseite",
    "wof:placetype":"neighbourhood"
},
  "geometry": {"coordinates":[7.56883,47.25377],"type":"Point"}
}