{
  "type": "Feature",
  "properties": {
    "iso:country":"CH",
    "name:deu_x_preferred":[
        "Aire"
    ],
    "name:eng_x_preferred":[
        "A\u00efre"
    ],
    "name:fra_x_preferred":[
        "A\u00efre"
    ],
    "name:nld_x_preferred":[
        "A\u00efre"
    ],
    "qs_pg:aaroncc":"CH",
    "qs_pg:name":"A\u00efre",
    "qs_pg:name_adm0":"Schweiz",
    "qs_pg:name_adm1":"Canton de Gen\u00e8ve",
    "qs_pg:photos":21,
    "qs_pg:photos_1k":4,
    "qs_pg:photos_9k":1,
    "qs_pg:photos_9r":1,
    "qs_pg:photos_all":21,
    "qs_pg:photos_sr":1,
    "qs_pg:pop_sr":0,
    "qs_pg:qs_pg_placetype":"locality",
    "qs_pg:qs_pg_placetype_gp":"Town",
    "qs_pg:woe_adm0":23424957,
    "woe:adm0_id":23424957,
    "woe:name_adm0":"Schweiz",
    "woe:name_adm1":"Canton de Gen\u00e8ve",
    "woe:placetype":"Town",
    "wof:name":"A\u00efre",
    "wof:placetype":"locality"
},
  "geometry": {"coordinates":[6.100339,46.197219],"type":"Point"}
}