{
  "type": "Feature",
  "properties": {
    "gn:country":"CH",
    "gn:fcode":"PPL",
    "gn:population":43,
    "iso:country":"CH",
    "name:cat_x_preferred":[
        "Au"
    ],
    "name:ceb_x_preferred":[
        "Au"
    ],
    "name:dan_x_preferred":[
        "Au"
    ],
    "name:deu_x_preferred":[
        "Au ZH"
    ],
    "name:deu_x_variant":[
        "Au"
    ],
    "name:ell_x_preferred":[
        "\u0386\u03bf\u03c5"
    ],
    "name:eng_x_preferred":[
        "Au"
    ],
    "name:gsw_x_preferred":[
        "Au ZH"
    ],
    "name:gsw_x_variant":[
        "Au"
    ],
    "name:jpn_x_preferred":[
        "\u30a2\u30a6"
    ],
    "name:nld_x_preferred":[
        "Au"
    ],
    "name:pnb_x_preferred":[
        "\u0622\u0624"
    ],
    "name:rus_x_preferred":[
        "\u0410\u0443"
    ],
    "name:swe_x_preferred":[
        "Au"
    ],
    "name:war_x_preferred":[
        "Au"
    ],
    "qs_pg:aaroncc":"CH",
    "qs_pg:gn_country":"CH",
    "qs_pg:gn_fcode":"PPL",
    "qs_pg:gn_pop":43,
    "qs_pg:name":"Au",
    "qs_pg:photos_9r":0,
    "qs_pg:photos_sr":0,
    "qs_pg:pop_sr":1,
    "qs_pg:qs_pg_placetype":"locality",
    "wof:name":"Au",
    "wof:placetype":"neighbourhood",
    "wof:population":43
},
  "geometry": {"coordinates":[8.65999,47.17751],"type":"Point"}
}