{
  "type": "Feature",
  "properties": {
    "gn:admin1_code":"VD",
    "gn:admin2_code":"2224.0",
    "gn:admin3_code":"5568.0",
    "gn:asciiname":"La Sagne",
    "gn:country_code":"CH",
    "gn:dem":1036,
    "gn:elevation":"1037.0",
    "gn:feature_class":"P",
    "gn:feature_code":"PPL",
    "gn:name":"La Sagne",
    "gn:population":0,
    "gn:timezone":"Europe/Zurich",
    "iso:country":"CH",
    "name:und_x_variant":[
        "La Sagne (Ste-Croix)"
    ],
    "wof:name":"La Sagne",
    "wof:placetype":"locality"
},
  "geometry": {"coordinates":[6.49931,46.81576],"type":"Point"}
}