{
  "type": "Feature",
  "properties": {
    "gn:gn_country":"CH",
    "gn:gn_fcode":"PPL",
    "gn:gn_pop":461,
    "gn:population":461,
    "iso:country":"CH",
    "name:cat_x_preferred":[
        "Paspels"
    ],
    "name:deu_x_preferred":[
        "Paspels"
    ],
    "name:eng_x_preferred":[
        "Paspels"
    ],
    "name:epo_x_preferred":[
        "Paspels"
    ],
    "name:fra_x_preferred":[
        "Paspels"
    ],
    "name:gsw_x_preferred":[
        "Paspels"
    ],
    "name:hun_x_preferred":[
        "Paspels"
    ],
    "name:ita_x_preferred":[
        "Paspels"
    ],
    "name:kaz_x_preferred":[
        "\u041f\u0430\u0441\u043f\u0435\u043b\u044c\u0441"
    ],
    "name:lmo_x_preferred":[
        "Paspels"
    ],
    "name:msa_x_preferred":[
        "Paspels"
    ],
    "name:nld_x_preferred":[
        "Paspels"
    ],
    "name:nno_x_preferred":[
        "Paspels"
    ],
    "name:oci_x_preferred":[
        "Paspels"
    ],
    "name:pms_x_preferred":[
        "Paspels"
    ],
    "name:por_x_preferred":[
        "Paspels"
    ],
    "name:roh_x_preferred":[
        "Pasqual"
    ],
    "name:rus_x_preferred":[
        "\u041f\u0430\u0441\u043f\u0435\u043b\u044c\u0441"
    ],
    "name:spa_x_preferred":[
        "Paspels"
    ],
    "name:sqi_x_preferred":[
        "Paspels"
    ],
    "name:swe_x_preferred":[
        "Paspels"
    ],
    "name:uzb_x_preferred":[
        "Paspels"
    ],
    "name:vol_x_preferred":[
        "Paspels"
    ],
    "name:war_x_preferred":[
        "Paspels"
    ],
    "name:zho_x_preferred":[
        "\u5e15\u723e\u4f69\u723e\u65af"
    ],
    "qs_pg:aaroncc":"CH",
    "qs_pg:gn_country":"CH",
    "qs_pg:gn_fcode":"PPL",
    "qs_pg:gn_pop":461,
    "qs_pg:name":"Paspels",
    "qs_pg:name_adm0":"Schweiz",
    "qs_pg:name_adm1":"Kanton Graub\u00fcnden",
    "qs_pg:photos":99,
    "qs_pg:photos_1k":20,
    "qs_pg:photos_9k":1,
    "qs_pg:photos_9r":3,
    "qs_pg:photos_all":99,
    "qs_pg:photos_sr":3,
    "qs_pg:pop_sr":2,
    "qs_pg:qs_pg_placetype":"locality",
    "qs_pg:qs_pg_placetype_gp":"Town",
    "qs_pg:woe_adm0":23424957,
    "woe:adm0_id":23424957,
    "woe:name_adm0":"Schweiz",
    "woe:name_adm1":"Kanton Graub\u00fcnden",
    "woe:placetype":"Town",
    "wof:name":"Paspels",
    "wof:placetype":"locality",
    "wof:population":461
},
  "geometry": {"coordinates":[9.4447,46.74881],"type":"Point"}
}