{
  "type": "Feature",
  "properties": {
    "gn:gn_country":"CH",
    "gn:gn_fcode":"PPL",
    "gn:gn_pop":339,
    "gn:population":339,
    "iso:country":"CH",
    "name:als_x_preferred":[
        "Hasliberg"
    ],
    "name:cat_x_preferred":[
        "Hasliberg"
    ],
    "name:ceb_x_preferred":[
        "Hasliberg"
    ],
    "name:ces_x_preferred":[
        "Hasliberg"
    ],
    "name:deu_x_preferred":[
        "Hasliberg"
    ],
    "name:epo_x_preferred":[
        "Hasliberg"
    ],
    "name:est_x_preferred":[
        "Haslibergi vald"
    ],
    "name:eus_x_preferred":[
        "Hasliberg"
    ],
    "name:fra_x_preferred":[
        "Hasliberg"
    ],
    "name:ita_x_preferred":[
        "Hasliberg"
    ],
    "name:kaz_x_preferred":[
        "\u0425\u0430\u0441\u043b\u0438\u0431\u0435\u0440\u0433"
    ],
    "name:lmo_x_preferred":[
        "Hasliberg"
    ],
    "name:msa_x_preferred":[
        "Hasliberg"
    ],
    "name:nld_x_preferred":[
        "Hasliberg"
    ],
    "name:nno_x_preferred":[
        "Hasliberg"
    ],
    "name:pms_x_preferred":[
        "Hasliberg"
    ],
    "name:pol_x_preferred":[
        "Hasliberg"
    ],
    "name:por_x_preferred":[
        "Hasliberg"
    ],
    "name:roh_x_preferred":[
        "Hasliberg"
    ],
    "name:ron_x_preferred":[
        "Hasliberg"
    ],
    "name:rus_x_preferred":[
        "\u0425\u0430\u0441\u043b\u0438\u0431\u0435\u0440\u0433"
    ],
    "name:spa_x_preferred":[
        "Hasliberg"
    ],
    "name:sqi_x_preferred":[
        "Hasliberg"
    ],
    "name:swe_x_preferred":[
        "Hasliberg"
    ],
    "name:vie_x_preferred":[
        "Hasliberg"
    ],
    "name:vol_x_preferred":[
        "Hasliberg"
    ],
    "name:war_x_preferred":[
        "Hasliberg"
    ],
    "name:zho_x_preferred":[
        "\u54c8\u65af\u5229\u8c9d\u683c"
    ],
    "qs_pg:aaroncc":"CH",
    "qs_pg:gn_country":"CH",
    "qs_pg:gn_fcode":"PPL",
    "qs_pg:gn_pop":339,
    "qs_pg:name":"Hasliberg",
    "qs_pg:name_adm0":"Schweiz",
    "qs_pg:name_adm1":"Kanton Z\u00fcrich",
    "qs_pg:photos_9r":0,
    "qs_pg:photos_sr":0,
    "qs_pg:pop_sr":2,
    "qs_pg:qs_pg_placetype":"locality",
    "qs_pg:qs_pg_placetype_gp":"Town",
    "qs_pg:woe_adm0":23424957,
    "wof:name":"Hasliberg",
    "wof:placetype":"neighbourhood",
    "wof:population":339
},
  "geometry": {"coordinates":[8.51039,47.46854],"type":"Point"}
}