{
  "type": "Feature",
  "properties": {
    "gn:gn_country":"CH",
    "gn:gn_fcode":"PPLL",
    "gn:gn_pop":3,
    "gn:population":3,
    "iso:country":"CH",
    "qs_pg:aaroncc":"CH",
    "qs_pg:gn_country":"CH",
    "qs_pg:gn_fcode":"PPLL",
    "qs_pg:gn_pop":3,
    "qs_pg:name":"Obere Langfurri",
    "qs_pg:photos_9r":0,
    "qs_pg:photos_sr":0,
    "qs_pg:pop_sr":1,
    "qs_pg:qs_pg_placetype":"locality",
    "wof:name":"Obere Langfurri",
    "wof:placetype":"neighbourhood",
    "wof:population":3
},
  "geometry": {"coordinates":[8.91523,47.38153],"type":"Point"}
}