{
  "type": "Feature",
  "properties": {
    "gn:admin1_code":"BE",
    "gn:admin2_code":"245.0",
    "gn:admin3_code":"407.0",
    "gn:asciiname":"Rotmatt",
    "gn:country_code":"CH",
    "gn:dem":740,
    "gn:feature_class":"P",
    "gn:feature_code":"PPLL",
    "gn:name":"Rotmatt",
    "gn:population":0,
    "gn:timezone":"Europe/Zurich",
    "iso:country":"CH",
    "name:deu_x_preferred":[
        "Rotmatt"
    ],
    "wof:name":"Rotmatt",
    "wof:placetype":"neighbourhood"
},
  "geometry": {"coordinates":[7.66537,47.03781],"type":"Point"}
}