{
  "type": "Feature",
  "properties": {
    "gn:admin1_code":"SG",
    "gn:admin2_code":"1725.0",
    "gn:admin3_code":"3293.0",
    "gn:asciiname":"Hienzi",
    "gn:country_code":"CH",
    "gn:dem":850,
    "gn:feature_class":"P",
    "gn:feature_code":"PPLL",
    "gn:name":"Hienzi",
    "gn:population":0,
    "gn:timezone":"Europe/Zurich",
    "iso:country":"CH",
    "name:deu_x_preferred":[
        "Hienzi"
    ],
    "wof:name":"Hienzi",
    "wof:placetype":"neighbourhood"
},
  "geometry": {"coordinates":[9.39832,47.03788],"type":"Point"}
}