{
  "type": "Feature",
  "properties": {
    "gn:gn_country":"CH",
    "gn:gn_fcode":"PPL",
    "gn:gn_pop":55,
    "gn:population":55,
    "iso:country":"CH",
    "name:cat_x_preferred":[
        "Au"
    ],
    "name:est_x_preferred":[
        "Au"
    ],
    "name:hun_x_preferred":[
        "Au"
    ],
    "qs_pg:aaroncc":"CH",
    "qs_pg:gn_country":"CH",
    "qs_pg:gn_fcode":"PPL",
    "qs_pg:gn_pop":55,
    "qs_pg:name":"Au",
    "qs_pg:photos_9r":0,
    "qs_pg:photos_sr":0,
    "qs_pg:pop_sr":1,
    "qs_pg:qs_pg_placetype":"locality",
    "wof:name":"Au",
    "wof:placetype":"neighbourhood",
    "wof:population":55
},
  "geometry": {"coordinates":[8.9353,47.26157],"type":"Point"}
}