{
  "type": "Feature",
  "properties": {
    "gn:admin1_code":"NW",
    "gn:admin2_code":"700.0",
    "gn:admin3_code":"1501.0",
    "gn:asciiname":"Hartmanix",
    "gn:country_code":"CH",
    "gn:dem":853,
    "gn:feature_class":"P",
    "gn:feature_code":"PPL",
    "gn:name":"Hartmanix",
    "gn:population":0,
    "gn:timezone":"Europe/Zurich",
    "iso:country":"CH",
    "name:und_x_variant":[
        "Hartinannix"
    ],
    "wof:name":"Hartmanix",
    "wof:placetype":"neighbourhood"
},
  "geometry": {"coordinates":[8.46989,46.95482],"type":"Point"}
}