{
  "type": "Feature",
  "properties": {
    "gn:admin1_code":"NW",
    "gn:admin2_code":"700.0",
    "gn:admin3_code":"1504.0",
    "gn:asciiname":"Schattigstock",
    "gn:country_code":"CH",
    "gn:dem":1275,
    "gn:feature_class":"P",
    "gn:feature_code":"PPL",
    "gn:name":"Schattigstock",
    "gn:population":0,
    "gn:timezone":"Europe/Zurich",
    "iso:country":"CH",
    "wof:name":"Schattigstock",
    "wof:placetype":"neighbourhood"
},
  "geometry": {"coordinates":[8.50535,46.94503],"type":"Point"}
}