{
  "type": "Feature",
  "properties": {
    "iso:country":"CH",
    "qs_pg:aaroncc":"CH",
    "qs_pg:name":"Wiestiboden",
    "qs_pg:name_adm0":"Schweiz",
    "qs_pg:name_adm1":"Canton de Valais",
    "qs_pg:photos":212,
    "qs_pg:photos_1k":43,
    "qs_pg:photos_9k":1,
    "qs_pg:photos_9r":4,
    "qs_pg:photos_all":212,
    "qs_pg:photos_sr":4,
    "qs_pg:pop_sr":0,
    "qs_pg:qs_pg_placetype":"locality",
    "qs_pg:qs_pg_placetype_gp":"Town",
    "qs_pg:woe_adm0":23424957,
    "woe:adm0_id":23424957,
    "woe:name_adm0":"Schweiz",
    "woe:name_adm1":"Canton de Valais",
    "woe:placetype":"Town",
    "wof:name":"Wiestiboden",
    "wof:placetype":"neighbourhood"
},
  "geometry": {"coordinates":[7.74811,46.01419],"type":"Point"}
}