{
  "type": "Feature",
  "properties": {
    "gn:admin1_code":"ZH",
    "gn:admin2_code":"102.0",
    "gn:admin3_code":"22.0",
    "gn:asciiname":"Im Robacker",
    "gn:country_code":"CH",
    "gn:dem":481,
    "gn:feature_class":"P",
    "gn:feature_code":"PPLL",
    "gn:name":"Im Robacker",
    "gn:population":0,
    "gn:timezone":"Europe/Zurich",
    "iso:country":"CH",
    "name:deu_x_preferred":[
        "Im Robacker"
    ],
    "wof:name":"Im Robacker",
    "wof:placetype":"neighbourhood"
},
  "geometry": {"coordinates":[8.66298,47.65513],"type":"Point"}
}