{
  "type": "Feature",
  "properties": {
    "gn:admin1_code":"NW",
    "gn:admin2_code":"700.0",
    "gn:admin3_code":"1504.0",
    "gn:asciiname":"Erlen",
    "gn:country_code":"CH",
    "gn:dem":843,
    "gn:feature_class":"P",
    "gn:feature_code":"PPL",
    "gn:name":"Erlen",
    "gn:population":0,
    "gn:timezone":"Europe/Zurich",
    "iso:country":"CH",
    "wof:name":"Erlen",
    "wof:placetype":"neighbourhood"
},
  "geometry": {"coordinates":[8.50469,46.95436],"type":"Point"}
}