{
  "type": "Feature",
  "properties": {
    "gn:admin1_code":"NW",
    "gn:admin2_code":"700.0",
    "gn:admin3_code":"1504.0",
    "gn:asciiname":"Erlen",
    "gn:country_code":"CH",
    "gn:dem":843,
    "gn:feature_class":"P",
    "gn:feature_code":"PPL",
    "gn:name":"Erlen",
    "gn:population":0,
    "gn:timezone":"Europe/Zurich",
    "iso:country":"CH",
    "name:als_x_preferred":[
        "Erlen"
    ],
    "name:ara_x_preferred":[
        "\u0625\u0631\u0644\u0646"
    ],
    "name:cat_x_preferred":[
        "Erlen"
    ],
    "name:ceb_x_preferred":[
        "Erlen"
    ],
    "name:chv_x_preferred":[
        "\u042d\u0440\u043b\u0435\u043d"
    ],
    "name:deu_x_preferred":[
        "Erlen"
    ],
    "name:epo_x_preferred":[
        "Erlen"
    ],
    "name:eus_x_preferred":[
        "Erlen"
    ],
    "name:fra_x_preferred":[
        "Erlen"
    ],
    "name:ita_x_preferred":[
        "Erlen"
    ],
    "name:kaz_x_preferred":[
        "\u042d\u0440\u043b\u0435\u043d"
    ],
    "name:lmo_x_preferred":[
        "Erlen"
    ],
    "name:msa_x_preferred":[
        "Erlen"
    ],
    "name:nld_x_preferred":[
        "Erlen"
    ],
    "name:nno_x_preferred":[
        "Erlen"
    ],
    "name:pms_x_preferred":[
        "Erlen"
    ],
    "name:pol_x_preferred":[
        "Erlen"
    ],
    "name:por_x_preferred":[
        "Erlen"
    ],
    "name:rus_x_preferred":[
        "\u042d\u0440\u043b\u0435\u043d"
    ],
    "name:spa_x_preferred":[
        "Erlen"
    ],
    "name:swe_x_preferred":[
        "Erlen"
    ],
    "name:uzb_x_preferred":[
        "Erlen"
    ],
    "name:vol_x_preferred":[
        "Erlen"
    ],
    "name:war_x_preferred":[
        "Erlen"
    ],
    "wof:name":"Erlen",
    "wof:placetype":"neighbourhood"
},
  "geometry": {"coordinates":[8.50469,46.95436],"type":"Point"}
}