{
  "type": "Feature",
  "properties": {
    "gn:gn_country":"CH",
    "gn:gn_fcode":"PPL",
    "gn:gn_pop":19344,
    "gn:population":19344,
    "iso:country":"CH",
    "name:ara_x_preferred":[
        "\u0643\u0627\u0631\u0648\u062c"
    ],
    "name:fas_x_preferred":[
        "\u06a9\u0631\u0648\u0698"
    ],
    "name:frp_x_preferred":[
        "Carroge"
    ],
    "name:heb_x_preferred":[
        "\u05e7\u05e8\u05d5\u05d6"
    ],
    "name:jpn_x_preferred":[
        "\u30ab\u30eb\u30fc\u30b8\u30e5"
    ],
    "name:kor_x_preferred":[
        "\uce74\ub8e8\uc8fc"
    ],
    "name:lat_x_preferred":[
        "Quadruvium"
    ],
    "name:lit_x_preferred":[
        "Karu\u017eas"
    ],
    "name:rus_x_preferred":[
        "\u041a\u0430\u0440\u0443\u0436"
    ],
    "name:ukr_x_preferred":[
        "\u041a\u0430\u0440\u0443\u0436"
    ],
    "name:zho_x_preferred":[
        "\u5361\u9c81\u65e5"
    ],
    "qs_pg:aaroncc":"CH",
    "qs_pg:gn_country":"CH",
    "qs_pg:gn_fcode":"PPL",
    "qs_pg:gn_pop":19344,
    "qs_pg:name":"Carouge",
    "qs_pg:name_adm0":"Schweiz",
    "qs_pg:name_adm1":"Canton de Gen\u00e8ve",
    "qs_pg:photos":227,
    "qs_pg:photos_1k":46,
    "qs_pg:photos_9k":1,
    "qs_pg:photos_9r":4,
    "qs_pg:photos_all":227,
    "qs_pg:photos_sr":4,
    "qs_pg:pop_sr":6,
    "qs_pg:qs_pg_placetype":"locality",
    "qs_pg:qs_pg_placetype_gp":"Town",
    "qs_pg:woe_adm0":23424957,
    "woe:adm0_id":23424957,
    "woe:name_adm0":"Schweiz",
    "woe:name_adm1":"Canton de Gen\u00e8ve",
    "woe:placetype":"Town",
    "wof:name":"Carouge",
    "wof:placetype":"locality",
    "wof:population":19344
},
  "geometry": {"coordinates":[6.13921,46.18096],"type":"Point"}
}