{
  "type": "Feature",
  "properties": {
    "gn:admin1_code":"BE",
    "gn:admin2_code":"250.0",
    "gn:admin3_code":"576.0",
    "gn:asciiname":"Moosgaden",
    "gn:country_code":"CH",
    "gn:dem":1161,
    "gn:feature_class":"P",
    "gn:feature_code":"PPL",
    "gn:name":"Moosgaden",
    "gn:population":0,
    "gn:timezone":"Europe/Zurich",
    "iso:country":"CH",
    "name:deu_x_preferred":[
        "Moosgaden"
    ],
    "wof:name":"Moosgaden",
    "wof:placetype":"neighbourhood"
},
  "geometry": {"coordinates":[8.00547,46.61547],"type":"Point"}
}