{
  "type": "Feature",
  "properties": {
    "gn:gn_country":"CH",
    "gn:gn_fcode":"PPLL",
    "gn:gn_pop":27291,
    "gn:population":27291,
    "iso:country":"CH",
    "name:ara_x_preferred":[
        "\u0644\u0627\u0646\u0633\u064a"
    ],
    "name:bul_x_preferred":[
        "\u041b\u0430\u043d\u0441\u0438"
    ],
    "name:cat_x_preferred":[
        "Lancy"
    ],
    "name:dan_x_preferred":[
        "Lancy"
    ],
    "name:deu_x_preferred":[
        "Lancy"
    ],
    "name:eng_x_preferred":[
        "Lancy"
    ],
    "name:epo_x_preferred":[
        "Lancy"
    ],
    "name:eus_x_preferred":[
        "Lancy"
    ],
    "name:fas_x_preferred":[
        "\u0644\u0627\u0646\u0633\u06cc"
    ],
    "name:fin_x_preferred":[
        "Lancy"
    ],
    "name:fra_x_preferred":[
        "Lancy"
    ],
    "name:frp_x_preferred":[
        "Lanci"
    ],
    "name:gle_x_preferred":[
        "Lancy"
    ],
    "name:gsw_x_preferred":[
        "Lancy"
    ],
    "name:hun_x_preferred":[
        "Lancy"
    ],
    "name:hye_x_preferred":[
        "\u053c\u0561\u0576\u057d\u056b"
    ],
    "name:ind_x_preferred":[
        "Lancy"
    ],
    "name:ita_x_preferred":[
        "Lancy"
    ],
    "name:jpn_x_preferred":[
        "\u30e9\u30f3\u30b7\u30fc"
    ],
    "name:lat_x_preferred":[
        "Lanciacus"
    ],
    "name:lit_x_preferred":[
        "Lansi"
    ],
    "name:lmo_x_preferred":[
        "Lancy"
    ],
    "name:msa_x_preferred":[
        "Lancy"
    ],
    "name:nan_x_preferred":[
        "Lancy"
    ],
    "name:nld_x_preferred":[
        "Lancy"
    ],
    "name:nno_x_preferred":[
        "Lancy"
    ],
    "name:oci_x_preferred":[
        "Lancy"
    ],
    "name:pol_x_preferred":[
        "Lancy"
    ],
    "name:por_x_preferred":[
        "Lancy"
    ],
    "name:roh_x_preferred":[
        "Lancy"
    ],
    "name:rus_x_preferred":[
        "\u041b\u0430\u043d\u0441\u0438"
    ],
    "name:slk_x_preferred":[
        "Lancy"
    ],
    "name:spa_x_preferred":[
        "Lancy"
    ],
    "name:swe_x_preferred":[
        "Lancy"
    ],
    "name:ukr_x_preferred":[
        "\u041b\u0430\u043d\u0441\u0456"
    ],
    "name:vie_x_preferred":[
        "Lancy"
    ],
    "name:vol_x_preferred":[
        "Lancy"
    ],
    "name:war_x_preferred":[
        "Lancy"
    ],
    "name:zho_x_preferred":[
        "\u6717\u897f"
    ],
    "qs_pg:aaroncc":"CH",
    "qs_pg:gn_country":"CH",
    "qs_pg:gn_fcode":"PPLL",
    "qs_pg:gn_pop":27291,
    "qs_pg:name":"Lancy",
    "qs_pg:name_adm0":"Schweiz",
    "qs_pg:name_adm1":"Canton de Gen\u00e8ve",
    "qs_pg:photos":66,
    "qs_pg:photos_1k":13,
    "qs_pg:photos_9k":1,
    "qs_pg:photos_9r":2,
    "qs_pg:photos_all":66,
    "qs_pg:photos_sr":2,
    "qs_pg:pop_sr":7,
    "qs_pg:qs_pg_placetype":"locality",
    "qs_pg:qs_pg_placetype_gp":"Town",
    "qs_pg:woe_adm0":23424957,
    "woe:adm0_id":23424957,
    "woe:name_adm0":"Schweiz",
    "woe:name_adm1":"Canton de Gen\u00e8ve",
    "woe:placetype":"Town",
    "wof:name":"Lancy",
    "wof:placetype":"neighbourhood",
    "wof:population":27291
},
  "geometry": {"coordinates":[6.11441,46.18981],"type":"Point"}
}