{
  "type": "Feature",
  "properties": {
    "gn:gn_country":"CH",
    "gn:gn_fcode":"PPL",
    "gn:gn_pop":1412,
    "gn:population":1412,
    "iso:country":"CH",
    "name:alb_x_preferred":[
        "Seltisberg"
    ],
    "name:ast_x_preferred":[
        "Seltisberg"
    ],
    "name:baq_x_preferred":[
        "Seltisberg"
    ],
    "name:cat_x_preferred":[
        "Seltisberg"
    ],
    "name:chi_x_preferred":[
        "\u745f\u8482\u65af\u4f2f\u683c"
    ],
    "name:dut_x_preferred":[
        "Seltisberg"
    ],
    "name:eng_x_preferred":[
        "Seltisberg"
    ],
    "name:epo_x_preferred":[
        "Seltisberg"
    ],
    "name:fre_x_preferred":[
        "Seltisberg"
    ],
    "name:ger_x_preferred":[
        "Seltisberg"
    ],
    "name:gsw_x_preferred":[
        "S\u00e4ltisb\u00e4rg"
    ],
    "name:hun_x_preferred":[
        "Seltisberg"
    ],
    "name:ita_x_preferred":[
        "Seltisberg"
    ],
    "name:kaz_x_preferred":[
        "\u0417\u0435\u043b\u044c\u0442\u0438\u0441\u0431\u0435\u0440\u0433"
    ],
    "name:lmo_x_preferred":[
        "Seltisberg"
    ],
    "name:may_x_preferred":[
        "Seltisberg"
    ],
    "name:nno_x_preferred":[
        "Seltisberg"
    ],
    "name:oci_x_preferred":[
        "Seltisberg"
    ],
    "name:rus_x_preferred":[
        "\u0417\u0435\u043b\u044c\u0442\u0438\u0441\u0431\u0435\u0440\u0433"
    ],
    "name:spa_x_preferred":[
        "Seltisberg"
    ],
    "name:swe_x_preferred":[
        "Seltisberg"
    ],
    "name:uzb_x_preferred":[
        "Seltisberg"
    ],
    "name:vol_x_preferred":[
        "Seltisberg"
    ],
    "name:war_x_preferred":[
        "Seltisberg"
    ],
    "qs_pg:aaroncc":"CH",
    "qs_pg:gn_country":"CH",
    "qs_pg:gn_fcode":"PPL",
    "qs_pg:gn_pop":1412,
    "qs_pg:name":"Seltisberg",
    "qs_pg:name_adm0":"Schweiz",
    "qs_pg:name_adm1":"Kanton Basel-Land",
    "qs_pg:photos_9k":1,
    "qs_pg:photos_9r":1,
    "qs_pg:photos_all":3,
    "qs_pg:photos_sr":0,
    "qs_pg:pop_sr":3,
    "qs_pg:qs_pg_placetype":"locality",
    "qs_pg:qs_pg_placetype_gp":"Town",
    "qs_pg:woe_adm0":23424957,
    "woe:adm0_id":23424957,
    "woe:name_adm0":"Schweiz",
    "woe:name_adm1":"Kanton Basel-Land",
    "woe:placetype":"Town",
    "wof:name":"Seltisberg",
    "wof:placetype":"locality",
    "wof:population":1412
},
  "geometry": {"coordinates":[7.71729,47.45947],"type":"Point"}
}