{
  "type": "Feature",
  "properties": {
    "gn:admin1_code":"ZG",
    "gn:admin2_code":"900.0",
    "gn:admin3_code":"1703.0",
    "gn:asciiname":"Rothus",
    "gn:country_code":"CH",
    "gn:dem":444,
    "gn:feature_class":"P",
    "gn:feature_code":"PPLL",
    "gn:name":"Rothus",
    "gn:population":0,
    "gn:timezone":"Europe/Zurich",
    "iso:country":"CH",
    "name:ceb_x_preferred":[
        "Rothus"
    ],
    "name:deu_x_preferred":[
        "Rothus"
    ],
    "name:fra_x_preferred":[
        "Rothus"
    ],
    "name:nld_x_preferred":[
        "Rothus"
    ],
    "name:swe_x_preferred":[
        "Rothus"
    ],
    "name:vie_x_preferred":[
        "Rothus"
    ],
    "name:war_x_preferred":[
        "Rothus"
    ],
    "wof:lang_x_official":[
        "deu",
        "fra",
        "gsw",
        "ita"
    ],
    "wof:lang_x_spoken":[
        "deu",
        "fra",
        "gsw",
        "ita",
        "roh"
    ],
    "wof:name":"Rothus",
    "wof:placetype":"neighbourhood"
},
  "geometry": {"coordinates":[8.44286,47.16023],"type":"Point"}
}