{
  "type": "Feature",
  "properties": {
    "gn:admin1_code":"GR",
    "gn:admin2_code":"1850.0",
    "gn:admin3_code":"3986.0",
    "gn:asciiname":"Camischolas",
    "gn:country_code":"CH",
    "gn:dem":1437,
    "gn:feature_class":"P",
    "gn:feature_code":"PPL",
    "gn:name":"Camischolas",
    "gn:population":0,
    "gn:timezone":"Europe/Zurich",
    "iso:country":"CH",
    "wof:name":"Camischolas",
    "wof:placetype":"locality"
},
  "geometry": {"coordinates":[8.7646,46.6806],"type":"Point"}
}