{
  "type": "Feature",
  "properties": {
    "gn:gn_country":"CH",
    "gn:gn_fcode":"PPL",
    "gn:gn_pop":20,
    "gn:population":20,
    "iso:country":"CH",
    "name:ceb_x_preferred":[
        "Z\u00fcrich"
    ],
    "name:deu_x_preferred":[
        "Hard"
    ],
    "name:eng_x_preferred":[
        "Hard"
    ],
    "name:fra_x_preferred":[
        "Hard"
    ],
    "name:lat_x_preferred":[
        "Hard"
    ],
    "name:nld_x_preferred":[
        "Hard"
    ],
    "qs_pg:aaroncc":"CH",
    "qs_pg:gn_country":"CH",
    "qs_pg:gn_fcode":"PPL",
    "qs_pg:gn_pop":20,
    "qs_pg:name":"Hard",
    "qs_pg:name_adm0":"Schweiz",
    "qs_pg:name_adm1":"Kanton Schaffhausen",
    "qs_pg:photos_9r":0,
    "qs_pg:photos_sr":0,
    "qs_pg:pop_sr":1,
    "qs_pg:qs_pg_placetype":"locality",
    "qs_pg:qs_pg_placetype_gp":"Town",
    "qs_pg:woe_adm0":23424957,
    "woe:adm0_id":23424957,
    "woe:name_adm0":"Schweiz",
    "woe:name_adm1":"Kanton Schaffhausen",
    "woe:placetype":"Town",
    "wof:name":"Hard",
    "wof:placetype":"neighbourhood",
    "wof:population":20
},
  "geometry": {"coordinates":[8.62013,47.43583],"type":"Point"}
}