{
  "type": "Feature",
  "properties": {
    "gn:admin1_code":"BE",
    "gn:admin2_code":"245.0",
    "gn:admin3_code":"906.0",
    "gn:asciiname":"Wald",
    "gn:country_code":"CH",
    "gn:dem":965,
    "gn:feature_class":"P",
    "gn:feature_code":"PPL",
    "gn:name":"Wald",
    "gn:population":0,
    "gn:timezone":"Europe/Zurich",
    "iso:country":"CH",
    "wof:name":"Wald",
    "wof:placetype":"neighbourhood"
},
  "geometry": {"coordinates":[7.87549,46.83526],"type":"Point"}
}