{
  "type": "Feature",
  "properties": {
    "gn:admin1_code":"VS",
    "gn:admin2_code":"2308.0",
    "gn:admin3_code":"6158.0",
    "gn:asciiname":"Revereulaz",
    "gn:country_code":"CH",
    "gn:dem":912,
    "gn:elevation":"992.0",
    "gn:feature_class":"P",
    "gn:feature_code":"PPL",
    "gn:name":"Revereulaz",
    "gn:population":0,
    "gn:timezone":"Europe/Zurich",
    "iso:country":"CH",
    "wof:name":"Revereulaz",
    "wof:placetype":"neighbourhood"
},
  "geometry": {"coordinates":[6.88014,46.31674],"type":"Point"}
}