{
  "type": "Feature",
  "properties": {
    "gn:admin1_code":"LU",
    "gn:admin2_code":"315.0",
    "gn:admin3_code":"1136.0",
    "gn:asciiname":"Steinhalden",
    "gn:country_code":"CH",
    "gn:dem":1022,
    "gn:feature_class":"P",
    "gn:feature_code":"PPLL",
    "gn:name":"Steinhalden",
    "gn:population":0,
    "gn:timezone":"Europe/Zurich",
    "iso:country":"CH",
    "name:deu_x_preferred":[
        "Steinhalden"
    ],
    "wof:name":"Steinhalden",
    "wof:placetype":"neighbourhood"
},
  "geometry": {"coordinates":[8.00118,47.03654],"type":"Point"}
}