{
  "type": "Feature",
  "properties": {
    "gn:admin1_code":"TI",
    "gn:admin2_code":"2103.0",
    "gn:admin3_code":"5079.0",
    "gn:asciiname":"Deggio",
    "gn:country_code":"CH",
    "gn:dem":1270,
    "gn:elevation":"1194.0",
    "gn:feature_class":"P",
    "gn:feature_code":"PPL",
    "gn:name":"Deggio",
    "gn:population":0,
    "gn:timezone":"Europe/Zurich",
    "iso:country":"CH",
    "wof:name":"Deggio",
    "wof:placetype":"neighbourhood"
},
  "geometry": {"coordinates":[8.71424,46.51543],"type":"Point"}
}