{
  "type": "Feature",
  "properties": {
    "gn:country":"CH",
    "gn:fcode":"HSE",
    "gn:population":2,
    "iso:country":"CH",
    "name:deu_x_preferred":[
        "Blumenau"
    ],
    "name:eng_x_preferred":[
        "Blumenau"
    ],
    "qs_pg:aaroncc":"CH",
    "qs_pg:gn_country":"CH",
    "qs_pg:gn_fcode":"HSE",
    "qs_pg:gn_pop":2,
    "qs_pg:name":"Blumenau",
    "qs_pg:photos_9r":0,
    "qs_pg:photos_sr":0,
    "qs_pg:pop_sr":1,
    "qs_pg:qs_pg_placetype":"locality_funky",
    "wof:name":"Blumenau",
    "wof:placetype":"neighbourhood",
    "wof:population":2
},
  "geometry": {"coordinates":[8.80786,47.495],"type":"Point"}
}