{
  "type": "Feature",
  "properties": {
    "gn:gn_country":"CH",
    "gn:gn_fcode":"PPL",
    "gn:gn_pop":2329,
    "gn:population":2329,
    "iso:country":"CH",
    "name:alb_x_preferred":[
        "R\u00fcderswil"
    ],
    "name:baq_x_preferred":[
        "R\u00fcderswil"
    ],
    "name:cat_x_preferred":[
        "R\u00fcderswil"
    ],
    "name:chi_x_preferred":[
        "\u5442\u5fb7\u65af\u7dad\u723e"
    ],
    "name:chv_x_preferred":[
        "\u0420\u044e\u0434\u0435\u0440\u0441\u0432\u0438\u043b\u044c"
    ],
    "name:dut_x_preferred":[
        "R\u00fcderswil"
    ],
    "name:eng_x_preferred":[
        "R\u00fcderswil"
    ],
    "name:epo_x_preferred":[
        "R\u00fcderswil"
    ],
    "name:fre_x_preferred":[
        "R\u00fcderswil"
    ],
    "name:ger_x_preferred":[
        "R\u00fcderswil"
    ],
    "name:gsw_x_preferred":[
        "R\u00fcderschwiu"
    ],
    "name:hun_x_preferred":[
        "R\u00fcderswil"
    ],
    "name:ita_x_preferred":[
        "R\u00fcderswil"
    ],
    "name:kaz_x_preferred":[
        "\u0420\u044e\u0434\u0435\u0440\u0441\u0432\u0438\u043b\u044c"
    ],
    "name:lmo_x_preferred":[
        "R\u00fcderswil"
    ],
    "name:may_x_preferred":[
        "R\u00fcderswil"
    ],
    "name:nno_x_preferred":[
        "R\u00fcderswil"
    ],
    "name:oci_x_preferred":[
        "R\u00fcderswil"
    ],
    "name:rus_x_preferred":[
        "\u0420\u044e\u0434\u0435\u0440\u0441\u0432\u0438\u043b\u044c"
    ],
    "name:slv_x_preferred":[
        "R\u00fcderswil"
    ],
    "name:spa_x_preferred":[
        "R\u00fcderswil"
    ],
    "name:swe_x_preferred":[
        "R\u00fcderswil"
    ],
    "name:vie_x_preferred":[
        "R\u00fcderswil"
    ],
    "name:vol_x_preferred":[
        "R\u00fcderswil"
    ],
    "name:war_x_preferred":[
        "R\u00fcderswil"
    ],
    "qs_pg:aaroncc":"CH",
    "qs_pg:gn_country":"CH",
    "qs_pg:gn_fcode":"PPL",
    "qs_pg:gn_pop":2329,
    "qs_pg:name":"R\u00fcderswil",
    "qs_pg:name_adm0":"Schweiz",
    "qs_pg:name_adm1":"Kanton Bern",
    "qs_pg:photos_9r":0,
    "qs_pg:photos_sr":0,
    "qs_pg:pop_sr":4,
    "qs_pg:qs_pg_placetype":"locality",
    "qs_pg:qs_pg_placetype_gp":"Town",
    "qs_pg:woe_adm0":23424957,
    "woe:adm0_id":23424957,
    "woe:name_adm0":"Schweiz",
    "woe:name_adm1":"Kanton Bern",
    "woe:placetype":"Town",
    "wof:name":"R\u00fcderswil",
    "wof:placetype":"locality",
    "wof:population":2329
},
  "geometry": {"coordinates":[7.72061,46.98415],"type":"Point"}
}