{
  "type": "Feature",
  "properties": {
    "gn:country":"CH",
    "gn:fcode":"PPLX",
    "gn:population":122,
    "iso:country":"CH",
    "name:eng_x_preferred":[
        "Chaibler"
    ],
    "name:eng_x_variant":[
        "Maur / Chaibler"
    ],
    "qs_pg:aaroncc":"CH",
    "qs_pg:gn_country":"CH",
    "qs_pg:gn_fcode":"PPLX",
    "qs_pg:gn_pop":122,
    "qs_pg:name":"Maur / Chaibler",
    "qs_pg:photos_9r":0,
    "qs_pg:photos_sr":0,
    "qs_pg:pop_sr":1,
    "qs_pg:qs_pg_placetype":"neighbourhood",
    "wof:name":"Chaibler",
    "wof:placetype":"neighbourhood",
    "wof:population":122
},
  "geometry": {"coordinates":[8.67495,47.33894],"type":"Point"}
}