{
  "type": "Feature",
  "properties": {
    "gn:population":10937,
    "iso:country":"CH",
    "name:alb_x_preferred":[
        "Lyss"
    ],
    "name:als_x_preferred":[
        "Lyss"
    ],
    "name:ara_x_preferred":[
        "\u0644\u0648\u0633"
    ],
    "name:baq_x_preferred":[
        "Lyss"
    ],
    "name:cat_x_preferred":[
        "Lyss"
    ],
    "name:ceb_x_preferred":[
        "Lyss"
    ],
    "name:ces_x_preferred":[
        "Lyss"
    ],
    "name:chi_x_preferred":[
        "\u5229\u65af"
    ],
    "name:chv_x_preferred":[
        "\u041b\u0438\u0441"
    ],
    "name:cze_x_preferred":[
        "Lyss"
    ],
    "name:deu_x_preferred":[
        "Lyss"
    ],
    "name:dut_x_preferred":[
        "Lyss"
    ],
    "name:eng_x_preferred":[
        "Lyss"
    ],
    "name:epo_x_preferred":[
        "Lyss"
    ],
    "name:eus_x_preferred":[
        "Lyss"
    ],
    "name:fas_x_preferred":[
        "\u0644\u06cc\u0633"
    ],
    "name:fin_x_preferred":[
        "Lyss"
    ],
    "name:fra_x_preferred":[
        "Lyss"
    ],
    "name:fre_x_preferred":[
        "Lyss"
    ],
    "name:ger_x_preferred":[
        "Lyss"
    ],
    "name:gsw_x_preferred":[
        "Liiss"
    ],
    "name:hun_x_preferred":[
        "Lyss"
    ],
    "name:ita_x_preferred":[
        "Lyss"
    ],
    "name:kaz_x_preferred":[
        "\u041b\u0438\u0441"
    ],
    "name:kor_x_preferred":[
        "\ub9ac\uc2a4"
    ],
    "name:lmo_x_preferred":[
        "Lyss"
    ],
    "name:may_x_preferred":[
        "Lyss"
    ],
    "name:msa_x_preferred":[
        "Lyss"
    ],
    "name:nan_x_preferred":[
        "Lyss"
    ],
    "name:nld_x_preferred":[
        "Lyss"
    ],
    "name:nno_x_preferred":[
        "Lyss"
    ],
    "name:oci_x_preferred":[
        "Lyss"
    ],
    "name:per_x_preferred":[
        "\u0644\u06cc\u0633"
    ],
    "name:pol_x_preferred":[
        "Lyss"
    ],
    "name:por_x_preferred":[
        "Lyss"
    ],
    "name:rus_x_preferred":[
        "\u041b\u0438\u0441"
    ],
    "name:scn_x_preferred":[
        "Lyss"
    ],
    "name:spa_x_preferred":[
        "Lyss"
    ],
    "name:sqi_x_preferred":[
        "Lyss"
    ],
    "name:swe_x_preferred":[
        "Lyss"
    ],
    "name:ukr_x_preferred":[
        "\u041b\u0456\u0441"
    ],
    "name:vol_x_preferred":[
        "Lyss"
    ],
    "name:war_x_preferred":[
        "Lyss"
    ],
    "name:zho_min_nan_x_preferred":[
        "Lyss"
    ],
    "name:zho_x_preferred":[
        "\u5229\u65af"
    ],
    "qs:a0":"Schweiz#Suisse#Svizzera#Svizra",
    "qs:a1":"*Bern",
    "qs:a1r":"0",
    "qs:adm0":"Schweiz#Suisse#Svizzera#Svizra",
    "qs:la_lc":"*",
    "qs:level":"locality",
    "qs:loc":"Lyss",
    "qs:loc_alt":"Lyss",
    "qs:pop":0,
    "qs:type":"buffered point",
    "wd:wordcount":2707,
    "wof:lang":[
        "ger"
    ],
    "wof:name":"Lyss",
    "wof:placetype":"locality",
    "wof:population":10937
},
  "geometry": {"coordinates":[7.306518,47.073977],"type":"Point"}
}