{
  "type": "Feature",
  "properties": {
    "gn:country":"CH",
    "gn:fcode":"PPLX",
    "gn:population":38,
    "iso:country":"CH",
    "name:eng_x_preferred":[
        "Frauenchammer"
    ],
    "name:eng_x_variant":[
        "Feldmeilen / Frauenchammer"
    ],
    "qs_pg:aaroncc":"CH",
    "qs_pg:gn_country":"CH",
    "qs_pg:gn_fcode":"PPLX",
    "qs_pg:gn_pop":38,
    "qs_pg:name":"Feldmeilen / Frauenchammer",
    "qs_pg:photos_9r":0,
    "qs_pg:photos_sr":0,
    "qs_pg:pop_sr":1,
    "qs_pg:qs_pg_placetype":"neighbourhood",
    "wof:lang_x_official":[
        "deu",
        "fra",
        "gsw",
        "ita"
    ],
    "wof:lang_x_spoken":[
        "deu",
        "fra",
        "gsw",
        "ita",
        "roh"
    ],
    "wof:name":"Frauenchammer",
    "wof:placetype":"neighbourhood",
    "wof:population":38
},
  "geometry": {"coordinates":[8.62418,47.27826],"type":"Point"}
}