{
  "type": "Feature",
  "properties": {
    "gn:gn_country":"CH",
    "gn:gn_fcode":"PPLX",
    "gn:gn_pop":85,
    "gn:population":85,
    "iso:country":"CH",
    "name:eng_x_preferred":[
        "Berg"
    ],
    "name:eng_x_variant":[
        "Sch\u00f6fflisdorf / Berg"
    ],
    "name:unk_x_variant":[
        "Berg"
    ],
    "qs_pg:aaroncc":"CH",
    "qs_pg:gn_country":"CH",
    "qs_pg:gn_fcode":"PPLX",
    "qs_pg:gn_pop":85,
    "qs_pg:name":"Sch\u00f6fflisdorf / Berg",
    "qs_pg:photos_9r":0,
    "qs_pg:photos_sr":0,
    "qs_pg:pop_sr":1,
    "qs_pg:qs_pg_placetype":"neighbourhood",
    "wof:name":"Berg",
    "wof:placetype":"neighbourhood",
    "wof:population":85
},
  "geometry": {"coordinates":[8.41461,47.50264],"type":"Point"}
}