{
  "type": "Feature",
  "properties": {
    "gn:country":"CH",
    "gn:fcode":"PPLX",
    "gn:population":85,
    "iso:country":"CH",
    "name:als_x_preferred":[
        "Berg"
    ],
    "name:cat_x_preferred":[
        "Berg"
    ],
    "name:ceb_x_preferred":[
        "Berg"
    ],
    "name:ces_x_preferred":[
        "Berg"
    ],
    "name:deu_x_preferred":[
        "Berg"
    ],
    "name:eng_x_preferred":[
        "Berg"
    ],
    "name:eng_x_variant":[
        "Sch\u00f6fflisdorf / Berg"
    ],
    "name:epo_x_preferred":[
        "Berg"
    ],
    "name:eus_x_preferred":[
        "Berg"
    ],
    "name:fin_x_preferred":[
        "Berg"
    ],
    "name:fra_x_preferred":[
        "Berg"
    ],
    "name:hun_x_preferred":[
        "Berg"
    ],
    "name:hye_x_preferred":[
        "\u0532\u0565\u0580\u0563"
    ],
    "name:ita_x_preferred":[
        "Berg"
    ],
    "name:jpn_x_preferred":[
        "\u30d9\u30eb\u30af"
    ],
    "name:kat_x_preferred":[
        "\u10d1\u10d4\u10e0\u10d2\u10d8"
    ],
    "name:kor_x_preferred":[
        "\ubca0\ub974\ud06c"
    ],
    "name:lim_x_preferred":[
        "Berg"
    ],
    "name:lmo_x_preferred":[
        "Berg"
    ],
    "name:nds_x_preferred":[
        "Berg"
    ],
    "name:nld_x_preferred":[
        "Berg"
    ],
    "name:nno_x_preferred":[
        "Berg"
    ],
    "name:nor_x_preferred":[
        "Berg"
    ],
    "name:pms_x_preferred":[
        "Berg"
    ],
    "name:pol_x_preferred":[
        "Berg"
    ],
    "name:por_x_preferred":[
        "Berg"
    ],
    "name:ron_x_preferred":[
        "Berg"
    ],
    "name:rus_x_preferred":[
        "\u0411\u0435\u0440\u0433"
    ],
    "name:slk_x_preferred":[
        "Berg"
    ],
    "name:spa_x_preferred":[
        "Berg"
    ],
    "name:srp_x_preferred":[
        "\u0411\u0435\u0440\u0433"
    ],
    "name:swe_x_preferred":[
        "Berg"
    ],
    "name:ukr_x_preferred":[
        "\u0411\u0435\u0440\u0433"
    ],
    "name:vol_x_preferred":[
        "Berg"
    ],
    "qs_pg:aaroncc":"CH",
    "qs_pg:gn_country":"CH",
    "qs_pg:gn_fcode":"PPLX",
    "qs_pg:gn_pop":85,
    "qs_pg:name":"Sch\u00f6fflisdorf / Berg",
    "qs_pg:photos_9r":0,
    "qs_pg:photos_sr":0,
    "qs_pg:pop_sr":1,
    "qs_pg:qs_pg_placetype":"neighbourhood",
    "wof:lang_x_official":[
        "deu",
        "fra",
        "gsw",
        "ita"
    ],
    "wof:lang_x_spoken":[
        "deu",
        "fra",
        "gsw",
        "ita",
        "roh"
    ],
    "wof:name":"Berg",
    "wof:placetype":"neighbourhood",
    "wof:population":85
},
  "geometry": {"coordinates":[8.41461,47.50264],"type":"Point"}
}