{
  "type": "Feature",
  "properties": {
    "gn:admin1_code":"BL",
    "gn:admin2_code":"1302.0",
    "gn:admin3_code":"2788.0",
    "gn:asciiname":"Rohrberg",
    "gn:country_code":"CH",
    "gn:dem":590,
    "gn:feature_class":"P",
    "gn:feature_code":"PPLL",
    "gn:name":"Rohrberg",
    "gn:population":0,
    "gn:timezone":"Europe/Zurich",
    "iso:country":"CH",
    "name:ceb_x_preferred":[
        "Rohrberg"
    ],
    "name:deu_x_preferred":[
        "Rohrberg"
    ],
    "name:epo_x_preferred":[
        "Rohrberg"
    ],
    "name:fra_x_preferred":[
        "Rohrberg"
    ],
    "name:hun_x_preferred":[
        "Rohrberg"
    ],
    "name:ita_x_preferred":[
        "Rohrberg"
    ],
    "name:lmo_x_preferred":[
        "Rohrberg"
    ],
    "name:nld_x_preferred":[
        "Rohrberg"
    ],
    "name:pol_x_preferred":[
        "Rohrberg"
    ],
    "name:rus_x_preferred":[
        "\u0420\u043e\u0440\u0431\u0435\u0440\u0433"
    ],
    "name:swe_x_preferred":[
        "Rohrberg"
    ],
    "name:vol_x_preferred":[
        "Rohrberg"
    ],
    "wof:lang_x_official":[
        "deu",
        "fra",
        "gsw",
        "ita"
    ],
    "wof:lang_x_spoken":[
        "deu",
        "fra",
        "gsw",
        "ita",
        "roh"
    ],
    "wof:name":"Rohrberg",
    "wof:placetype":"neighbourhood"
},
  "geometry": {"coordinates":[7.42249,47.38214],"type":"Point"}
}