{
  "type": "Feature",
  "properties": {
    "gn:gn_country":"CH",
    "gn:gn_fcode":"PPLX",
    "gn:gn_pop":76,
    "gn:population":76,
    "iso:country":"CH",
    "name:ara_x_preferred":[
        "\u0647\u0627\u0644\u062f\u0646"
    ],
    "name:azb_x_preferred":[
        "\u0647\u0627\u0644\u062f\u0646"
    ],
    "name:bpy_x_preferred":[
        "\u09b9\u09b2\u09a1\u09c7\u09a8"
    ],
    "name:bul_x_preferred":[
        "\u0425\u0430\u043b\u0434\u0435\u043d"
    ],
    "name:cat_x_preferred":[
        "Halden"
    ],
    "name:ceb_x_preferred":[
        "Halden"
    ],
    "name:ces_x_preferred":[
        "Halden"
    ],
    "name:dan_x_preferred":[
        "Halden"
    ],
    "name:deu_x_preferred":[
        "Halden"
    ],
    "name:eng_x_preferred":[
        "Halden"
    ],
    "name:eng_x_variant":[
        "Aesch / Halden"
    ],
    "name:epo_x_preferred":[
        "Halden"
    ],
    "name:est_x_preferred":[
        "Haldeni vald"
    ],
    "name:eus_x_preferred":[
        "Halden"
    ],
    "name:fas_x_preferred":[
        "\u0647\u0627\u0644\u062f\u0646"
    ],
    "name:fin_x_preferred":[
        "Halden"
    ],
    "name:fra_x_preferred":[
        "Halden"
    ],
    "name:ind_x_preferred":[
        "Halden"
    ],
    "name:isl_x_preferred":[
        "Halden"
    ],
    "name:ita_x_preferred":[
        "Halden"
    ],
    "name:jav_x_preferred":[
        "Halden"
    ],
    "name:jpn_x_preferred":[
        "\u30cf\u30eb\u30c7\u30f3"
    ],
    "name:kal_x_preferred":[
        "Halden"
    ],
    "name:lat_x_preferred":[
        "Fridericostadium"
    ],
    "name:lim_x_preferred":[
        "Halden"
    ],
    "name:lit_x_preferred":[
        "Haldenas"
    ],
    "name:msa_x_preferred":[
        "Halden"
    ],
    "name:nds_x_preferred":[
        "Kommun Halden"
    ],
    "name:nld_x_preferred":[
        "Halden"
    ],
    "name:nno_x_preferred":[
        "Halden kommune"
    ],
    "name:nor_x_preferred":[
        "Halden"
    ],
    "name:pol_x_preferred":[
        "Halden"
    ],
    "name:por_x_preferred":[
        "Halden"
    ],
    "name:ron_x_preferred":[
        "Halden"
    ],
    "name:rus_x_preferred":[
        "\u0425\u0430\u043b\u0434\u0435\u043d"
    ],
    "name:sme_x_preferred":[
        "Halden"
    ],
    "name:spa_x_preferred":[
        "Halden"
    ],
    "name:sqi_x_preferred":[
        "Halden"
    ],
    "name:srp_x_preferred":[
        "\u0425\u0430\u043b\u0434\u0435\u043d"
    ],
    "name:swe_x_preferred":[
        "Haldens kommun"
    ],
    "name:tha_x_preferred":[
        "\u0e2e\u0e32\u0e25\u0e40\u0e14\u0e19"
    ],
    "name:tum_x_preferred":[
        "Halden"
    ],
    "name:tur_x_preferred":[
        "Halden"
    ],
    "name:ukr_x_preferred":[
        "\u0413\u0430\u043b\u0434\u0435\u043d"
    ],
    "name:unk_x_variant":[
        "Halden"
    ],
    "name:vie_x_preferred":[
        "Halden"
    ],
    "name:war_x_preferred":[
        "Halden"
    ],
    "name:zho_x_preferred":[
        "\u54c8\u5c14\u767b"
    ],
    "qs_pg:aaroncc":"CH",
    "qs_pg:gn_country":"CH",
    "qs_pg:gn_fcode":"PPLX",
    "qs_pg:gn_pop":76,
    "qs_pg:name":"Aesch / Halden",
    "qs_pg:photos_9r":0,
    "qs_pg:photos_sr":0,
    "qs_pg:pop_sr":1,
    "qs_pg:qs_pg_placetype":"neighbourhood",
    "wof:name":"Halden",
    "wof:placetype":"neighbourhood",
    "wof:population":76
},
  "geometry": {"coordinates":[8.44396,47.33699],"type":"Point"}
}