{
  "type": "Feature",
  "properties": {
    "gn:gn_country":"CH",
    "gn:gn_fcode":"PPLX",
    "gn:gn_pop":504,
    "gn:population":504,
    "iso:country":"CH",
    "name:unk_x_variant":[
        "Widacher"
    ],
    "qs_pg:aaroncc":"CH",
    "qs_pg:gn_country":"CH",
    "qs_pg:gn_fcode":"PPLX",
    "qs_pg:gn_pop":504,
    "qs_pg:name":"Schwerzenbach / Widacher",
    "qs_pg:photos_9r":0,
    "qs_pg:photos_sr":0,
    "qs_pg:pop_sr":2,
    "qs_pg:qs_pg_placetype":"neighbourhood",
    "wof:name":"Schwerzenbach / Widacher",
    "wof:placetype":"neighbourhood",
    "wof:population":504
},
  "geometry": {"coordinates":[8.65748,47.38151],"type":"Point"}
}