{
  "type": "Feature",
  "properties": {
    "gn:admin1_code":"VD",
    "gn:admin2_code":"2222.0",
    "gn:admin3_code":"5831.0",
    "gn:asciiname":"Combremont-le-Grand",
    "gn:country_code":"CH",
    "gn:dem":672,
    "gn:feature_class":"P",
    "gn:feature_code":"PPL",
    "gn:name":"Combremont-le-Grand",
    "gn:population":0,
    "gn:timezone":"Europe/Zurich",
    "iso:country":"CH",
    "wof:name":"Combremont-le-Grand",
    "wof:placetype":"locality"
},
  "geometry": {"coordinates":[6.81818,46.76168],"type":"Point"}
}