{
  "type": "Feature",
  "properties": {
    "gn:population":3477,
    "iso:country":"CH",
    "name:alb_x_preferred":[
        "Saxon"
    ],
    "name:baq_x_preferred":[
        "Saxon"
    ],
    "name:cat_x_preferred":[
        "Saxon"
    ],
    "name:ceb_x_preferred":[
        "Saxon"
    ],
    "name:chi_x_preferred":[
        "\u85a9\u514b\u677e"
    ],
    "name:deu_x_preferred":[
        "Saxon VS"
    ],
    "name:dut_x_preferred":[
        "Saxon"
    ],
    "name:eng_x_preferred":[
        "Saxon"
    ],
    "name:epo_x_preferred":[
        "Saxon VS"
    ],
    "name:eus_x_preferred":[
        "Saxon"
    ],
    "name:fra_x_preferred":[
        "Saxon"
    ],
    "name:fre_x_preferred":[
        "Saxon"
    ],
    "name:frp_x_preferred":[
        "Sasson"
    ],
    "name:ger_x_preferred":[
        "Saxon VS"
    ],
    "name:hun_x_preferred":[
        "Saxon"
    ],
    "name:ita_x_preferred":[
        "Saxon"
    ],
    "name:lmo_x_preferred":[
        "Saxon"
    ],
    "name:may_x_preferred":[
        "Saxon"
    ],
    "name:msa_x_preferred":[
        "Saxon"
    ],
    "name:nld_x_preferred":[
        "Saxon"
    ],
    "name:nno_x_preferred":[
        "Saxon i Sveits"
    ],
    "name:oci_x_preferred":[
        "Saxon"
    ],
    "name:roh_x_preferred":[
        "Saxon"
    ],
    "name:rus_x_preferred":[
        "\u0421\u0430\u043a\u0441\u043e\u043d"
    ],
    "name:spa_x_preferred":[
        "Saxon"
    ],
    "name:sqi_x_preferred":[
        "Saxon"
    ],
    "name:swe_x_preferred":[
        "Saxon"
    ],
    "name:vol_x_preferred":[
        "Saxon"
    ],
    "name:war_x_preferred":[
        "Saxon"
    ],
    "name:zho_x_preferred":[
        "\u85a9\u514b\u677e"
    ],
    "qs:a0":"Schweiz#Suisse#Svizzera#Svizra",
    "qs:a1":"*Valais",
    "qs:a1r":"0",
    "qs:adm0":"Schweiz#Suisse#Svizzera#Svizra",
    "qs:la_lc":"*",
    "qs:level":"locality",
    "qs:loc":"Saxon",
    "qs:loc_alt":"Saxon",
    "qs:pop":0,
    "qs:type":"buffered point",
    "wd:wordcount":1489,
    "wof:name":"Saxon",
    "wof:placetype":"locality",
    "wof:population":3477
},
  "geometry": {"coordinates":[7.174381,46.150284],"type":"Point"}
}