{
  "type": "Feature",
  "properties": {
    "gn:gn_country":"CH",
    "gn:gn_fcode":"PPL",
    "gn:gn_pop":15,
    "gn:population":15,
    "iso:country":"CH",
    "name:ara_x_preferred":[
        "\u0623\u0634"
    ],
    "name:cat_x_preferred":[
        "Aesch"
    ],
    "name:ceb_x_preferred":[
        "Aesch"
    ],
    "name:chv_x_preferred":[
        "\u042d\u0448"
    ],
    "name:deu_x_preferred":[
        "Aesch ZH"
    ],
    "name:eng_x_preferred":[
        "Aesch"
    ],
    "name:epo_x_preferred":[
        "Aesch ZH"
    ],
    "name:eus_x_preferred":[
        "Aesch"
    ],
    "name:fra_x_preferred":[
        "Aesch"
    ],
    "name:gsw_x_preferred":[
        "\u00c4\u00e4sch"
    ],
    "name:hun_x_preferred":[
        "Aesch"
    ],
    "name:ita_x_preferred":[
        "Aesch bei Birmensdorf"
    ],
    "name:ita_x_variant":[
        "Aesch"
    ],
    "name:kaz_x_preferred":[
        "\u042d\u0448"
    ],
    "name:lmo_x_preferred":[
        "Aesch"
    ],
    "name:msa_x_preferred":[
        "Aesch"
    ],
    "name:nld_x_preferred":[
        "Aesch"
    ],
    "name:nno_x_preferred":[
        "Aesch i Z\u00fcrich"
    ],
    "name:nob_x_preferred":[
        "Aesch"
    ],
    "name:oci_x_preferred":[
        "Aesch"
    ],
    "name:pms_x_preferred":[
        "Aesch bei Birmensdorf"
    ],
    "name:pol_x_preferred":[
        "Aesch"
    ],
    "name:por_x_preferred":[
        "Aesch bei Birmensdorf"
    ],
    "name:rus_x_preferred":[
        "\u042d\u0448"
    ],
    "name:spa_x_preferred":[
        "Aesch"
    ],
    "name:swe_x_preferred":[
        "Aesch"
    ],
    "name:uzb_x_preferred":[
        "Aesch"
    ],
    "name:vol_x_preferred":[
        "Aesch"
    ],
    "name:war_x_preferred":[
        "Aesch"
    ],
    "name:zho_x_preferred":[
        "\u57c3\u65bd"
    ],
    "qs_pg:aaroncc":"CH",
    "qs_pg:gn_country":"CH",
    "qs_pg:gn_fcode":"PPL",
    "qs_pg:gn_pop":15,
    "qs_pg:name":"Aesch",
    "qs_pg:photos_9r":0,
    "qs_pg:photos_sr":0,
    "qs_pg:pop_sr":1,
    "qs_pg:qs_pg_placetype":"locality",
    "wof:name":"Aesch",
    "wof:placetype":"neighbourhood",
    "wof:population":15
},
  "geometry": {"coordinates":[8.6225,47.20039],"type":"Point"}
}