{
  "type": "Feature",
  "properties": {
    "gn:population":3723,
    "iso:country":"CH",
    "name:alb_x_preferred":[
        "Sch\u00fcpfheim"
    ],
    "name:als_x_preferred":[
        "Sch\u00fcpfheim LU"
    ],
    "name:baq_x_preferred":[
        "Sch\u00fcpfheim"
    ],
    "name:cat_x_preferred":[
        "Sch\u00fcpfheim"
    ],
    "name:ceb_x_preferred":[
        "Sch\u00fcpfheim"
    ],
    "name:chi_x_preferred":[
        "\u8a31\u666e\u5f17\u6d77\u59c6"
    ],
    "name:deu_x_colloquial":[
        "Schuepfheim",
        "Schupfheim"
    ],
    "name:deu_x_preferred":[
        "Sch\u00fcpfheim"
    ],
    "name:dut_x_preferred":[
        "Sch\u00fcpfheim"
    ],
    "name:eng_x_preferred":[
        "Sch\u00fcpfheim"
    ],
    "name:epo_x_preferred":[
        "Sch\u00fcpfheim LU"
    ],
    "name:eus_x_preferred":[
        "Sch\u00fcpfheim"
    ],
    "name:fra_x_preferred":[
        "Sch\u00fcpfheim"
    ],
    "name:fre_x_preferred":[
        "Sch\u00fcpfheim"
    ],
    "name:ger_x_preferred":[
        "Sch\u00fcpfheim"
    ],
    "name:gsw_x_preferred":[
        "Sch\u00fcpfheim LU"
    ],
    "name:hun_x_preferred":[
        "Sch\u00fcpfheim"
    ],
    "name:ita_x_preferred":[
        "Sch\u00fcpfheim"
    ],
    "name:kaz_x_preferred":[
        "\u0428\u044e\u043f\u0444\u0445\u0430\u0439\u043c"
    ],
    "name:lmo_x_preferred":[
        "Sch\u00fcpfheim"
    ],
    "name:may_x_preferred":[
        "Sch\u00fcpfheim"
    ],
    "name:nno_x_preferred":[
        "Sch\u00fcpfheim"
    ],
    "name:oci_x_preferred":[
        "Sch\u00fcpfheim"
    ],
    "name:pms_x_preferred":[
        "Sch\u00fcpfheim"
    ],
    "name:por_x_preferred":[
        "Sch\u00fcpfheim"
    ],
    "name:rus_x_preferred":[
        "\u0428\u044e\u043f\u0444\u0445\u0430\u0439\u043c"
    ],
    "name:spa_x_preferred":[
        "Sch\u00fcpfheim"
    ],
    "name:uzb_x_preferred":[
        "Sch\u00fcpfheim"
    ],
    "name:vol_x_preferred":[
        "Sch\u00fcpfheim"
    ],
    "name:war_x_preferred":[
        "Sch\u00fcpfheim"
    ],
    "name:zho_x_preferred":[
        "\u8a31\u666e\u5f17\u6d77\u59c6"
    ],
    "qs:a0":"Schweiz#Suisse#Svizzera#Svizra",
    "qs:a1":"*Luzern",
    "qs:a1r":"0",
    "qs:adm0":"Schweiz#Suisse#Svizzera#Svizra",
    "qs:la_lc":"*",
    "qs:level":"locality",
    "qs:loc":"Sch\u00fcpfheim",
    "qs:loc_alt":"Schuepfheim",
    "qs:pop":0,
    "qs:type":"buffered point",
    "wd:wordcount":697,
    "wof:lang":[
        "ger"
    ],
    "wof:name":"Sch\u00fcpfheim",
    "wof:placetype":"locality",
    "wof:population":3723
},
  "geometry": {"coordinates":[8.014573,46.950905],"type":"Point"}
}