{
  "type": "Feature",
  "properties": {
    "gn:country":"CH",
    "gn:fcode":"PPLX",
    "gn:population":1333,
    "iso:country":"CH",
    "name:eng_x_preferred":[
        "Bahnhofquartier"
    ],
    "name:eng_x_variant":[
        "Oberglatt / Bahnhofquartier"
    ],
    "qs_pg:aaroncc":"CH",
    "qs_pg:gn_country":"CH",
    "qs_pg:gn_fcode":"PPLX",
    "qs_pg:gn_pop":1333,
    "qs_pg:name":"Oberglatt / Bahnhofquartier",
    "qs_pg:photos_9r":0,
    "qs_pg:photos_sr":0,
    "qs_pg:pop_sr":3,
    "qs_pg:qs_pg_placetype":"neighbourhood",
    "wof:name":"Bahnhofquartier",
    "wof:placetype":"neighbourhood",
    "wof:population":1333
},
  "geometry": {"coordinates":[8.51289,47.47143],"type":"Point"}
}