{
  "type": "Feature",
  "properties": {
    "gn:admin1_code":"LU",
    "gn:admin2_code":"316.0",
    "gn:admin3_code":"1010.0",
    "gn:asciiname":"Aussergrat",
    "gn:country_code":"CH",
    "gn:dem":1034,
    "gn:feature_class":"P",
    "gn:feature_code":"PPLL",
    "gn:name":"Aussergrat",
    "gn:population":0,
    "gn:timezone":"Europe/Zurich",
    "iso:country":"CH",
    "name:deu_x_preferred":[
        "Aussergrat"
    ],
    "wof:lang_x_official":[
        "deu",
        "fra",
        "gsw",
        "ita"
    ],
    "wof:lang_x_spoken":[
        "deu",
        "fra",
        "gsw",
        "ita",
        "roh"
    ],
    "wof:name":"Aussergrat",
    "wof:placetype":"neighbourhood"
},
  "geometry": {"coordinates":[7.88704,46.91475],"type":"Point"}
}