{
  "type": "Feature",
  "properties": {
    "gn:admin1_code":"SZ",
    "gn:admin2_code":"505.0",
    "gn:admin3_code":"1342.0",
    "gn:asciiname":"Hintergschwaend",
    "gn:country_code":"CH",
    "gn:dem":922,
    "gn:feature_class":"P",
    "gn:feature_code":"PPLL",
    "gn:name":"Hintergschw\u00e4nd",
    "gn:population":0,
    "gn:timezone":"Europe/Zurich",
    "iso:country":"CH",
    "name:deu_x_preferred":[
        "Hintergschw\u00e4nd"
    ],
    "wof:name":"Hintergschwaend",
    "wof:placetype":"locality"
},
  "geometry": {"coordinates":[8.87126,47.15951],"type":"Point"}
}