{
  "type": "Feature",
  "properties": {
    "gn:admin1_code":"BE",
    "gn:admin2_code":"250.0",
    "gn:admin3_code":"571.0",
    "gn:asciiname":"Spirenwald",
    "gn:country_code":"CH",
    "gn:dem":1192,
    "gn:elevation":"1173.0",
    "gn:feature_class":"P",
    "gn:feature_code":"PPL",
    "gn:name":"Spirenwald",
    "gn:population":0,
    "gn:timezone":"Europe/Zurich",
    "iso:country":"CH",
    "wof:lang_x_official":[
        "deu",
        "fra",
        "gsw",
        "ita"
    ],
    "wof:lang_x_spoken":[
        "deu",
        "fra",
        "gsw",
        "ita",
        "roh"
    ],
    "wof:name":"Spirenwald",
    "wof:placetype":"neighbourhood"
},
  "geometry": {"coordinates":[7.80052,46.70167],"type":"Point"}
}