{
  "type": "Feature",
  "properties": {
    "gn:admin1_code":"FR",
    "gn:admin2_code":"1005.0",
    "gn:admin3_code":"2284.0",
    "gn:asciiname":"Bellechasse",
    "gn:country_code":"CH",
    "gn:dem":431,
    "gn:feature_class":"P",
    "gn:feature_code":"PPL",
    "gn:name":"Bellechasse",
    "gn:population":0,
    "gn:timezone":"Europe/Zurich",
    "iso:country":"CH",
    "name:deu_x_preferred":[
        "Bellechasse"
    ],
    "name:fra_x_preferred":[
        "Bellechasse"
    ],
    "name:spa_x_preferred":[
        "Bellechasse"
    ],
    "wof:name":"Bellechasse",
    "wof:placetype":"neighbourhood"
},
  "geometry": {"coordinates":[7.13206,46.97451],"type":"Point"}
}