{
  "type": "Feature",
  "properties": {
    "gn:admin1_code":"TI",
    "gn:admin2_code":"2105.0",
    "gn:admin3_code":"5149.0",
    "gn:asciiname":"Feredino",
    "gn:country_code":"CH",
    "gn:dem":571,
    "gn:feature_class":"P",
    "gn:feature_code":"PPL",
    "gn:name":"Feredino",
    "gn:population":0,
    "gn:timezone":"Europe/Zurich",
    "iso:country":"CH",
    "name:ita_x_preferred":[
        "Feredino"
    ],
    "wof:name":"Feredino",
    "wof:placetype":"neighbourhood"
},
  "geometry": {"coordinates":[8.84899,46.00167],"type":"Point"}
}