{
  "type": "Feature",
  "properties": {
    "gn:admin1_code":"ZH",
    "gn:admin2_code":"109.0",
    "gn:admin3_code":"195.0",
    "gn:asciiname":"Rossweid",
    "gn:country_code":"CH",
    "gn:dem":485,
    "gn:feature_class":"P",
    "gn:feature_code":"PPLL",
    "gn:name":"Rossweid",
    "gn:population":0,
    "gn:timezone":"Europe/Zurich",
    "iso:country":"CH",
    "wof:name":"Rossweid",
    "wof:placetype":"neighbourhood"
},
  "geometry": {"coordinates":[8.65911,47.34851],"type":"Point"}
}