{
  "type": "Feature",
  "properties": {
    "gn:gn_country":"CH",
    "gn:gn_fcode":"PPL",
    "gn:gn_pop":1555,
    "gn:population":1555,
    "iso:country":"CH",
    "name:bul_x_preferred":[
        "\u0410\u0443\u0432\u0435\u0440\u043d\u0438\u0435\u0440"
    ],
    "name:cat_x_preferred":[
        "Auvernier"
    ],
    "name:deu_x_preferred":[
        "Auvernier"
    ],
    "name:eng_x_preferred":[
        "Auvernier"
    ],
    "name:epo_x_preferred":[
        "Auvernier"
    ],
    "name:fra_x_preferred":[
        "Auvernier"
    ],
    "name:gsw_x_preferred":[
        "Auvernier"
    ],
    "name:hun_x_preferred":[
        "Auvernier"
    ],
    "name:ita_x_preferred":[
        "Auvernier"
    ],
    "name:lmo_x_preferred":[
        "Auvernier"
    ],
    "name:msa_x_preferred":[
        "Auvernier"
    ],
    "name:nld_x_preferred":[
        "Auvernier"
    ],
    "name:nno_x_preferred":[
        "Auvernier"
    ],
    "name:oci_x_preferred":[
        "Auvernier"
    ],
    "name:scn_x_preferred":[
        "Auvernier"
    ],
    "name:spa_x_preferred":[
        "Auvernier"
    ],
    "name:swe_x_preferred":[
        "Auvernier"
    ],
    "name:vol_x_preferred":[
        "Auvernier"
    ],
    "name:war_x_preferred":[
        "Auvernier"
    ],
    "name:zho_x_preferred":[
        "\u5967\u97cb\u5c3c\u8036"
    ],
    "qs_pg:aaroncc":"CH",
    "qs_pg:gn_country":"CH",
    "qs_pg:gn_fcode":"PPL",
    "qs_pg:gn_pop":1555,
    "qs_pg:name":"Auvernier",
    "qs_pg:name_adm0":"Schweiz",
    "qs_pg:name_adm1":"Canton de Neuch\u00e2tel",
    "qs_pg:photos":234,
    "qs_pg:photos_1k":47,
    "qs_pg:photos_9k":1,
    "qs_pg:photos_9r":4,
    "qs_pg:photos_all":234,
    "qs_pg:photos_sr":4,
    "qs_pg:pop_sr":3,
    "qs_pg:qs_pg_placetype":"locality",
    "qs_pg:qs_pg_placetype_gp":"Town",
    "qs_pg:woe_adm0":23424957,
    "woe:adm0_id":23424957,
    "woe:name_adm0":"Schweiz",
    "woe:name_adm1":"Canton de Neuch\u00e2tel",
    "woe:placetype":"Town",
    "wof:name":"Auvernier",
    "wof:placetype":"locality",
    "wof:population":1555
},
  "geometry": {"coordinates":[6.87903,46.97545],"type":"Point"}
}