{
  "type": "Feature",
  "properties": {
    "gn:country":"CH",
    "gn:fcode":"PPLL",
    "gn:population":14,
    "iso:country":"CH",
    "name:als_x_preferred":[
        "Hasel"
    ],
    "name:ceb_x_preferred":[
        "Hasel"
    ],
    "name:deu_x_preferred":[
        "Hasel"
    ],
    "name:epo_x_preferred":[
        "Hasel"
    ],
    "name:ita_x_preferred":[
        "Hasel"
    ],
    "name:nld_x_preferred":[
        "Hasel"
    ],
    "name:pol_x_preferred":[
        "Hasel"
    ],
    "name:srp_x_preferred":[
        "\u0425\u0430\u0441\u0435\u043b"
    ],
    "name:swe_x_preferred":[
        "Hasel"
    ],
    "qs_pg:aaroncc":"CH",
    "qs_pg:gn_country":"CH",
    "qs_pg:gn_fcode":"PPLL",
    "qs_pg:gn_pop":14,
    "qs_pg:name":"Hasel",
    "qs_pg:photos_9r":0,
    "qs_pg:photos_sr":0,
    "qs_pg:pop_sr":1,
    "qs_pg:qs_pg_placetype":"locality",
    "wof:lang_x_official":[
        "deu",
        "fra",
        "gsw",
        "ita"
    ],
    "wof:lang_x_spoken":[
        "deu",
        "fra",
        "gsw",
        "ita",
        "roh"
    ],
    "wof:name":"Hasel",
    "wof:placetype":"neighbourhood",
    "wof:population":14
},
  "geometry": {"coordinates":[8.7765,47.26309],"type":"Point"}
}