{
  "type": "Feature",
  "properties": {
    "gn:admin1_code":"GR",
    "gn:admin2_code":"1851.0",
    "gn:admin3_code":"3681.0",
    "gn:asciiname":"Am Bach",
    "gn:country_code":"CH",
    "gn:dem":1959,
    "gn:feature_class":"P",
    "gn:feature_code":"PPL",
    "gn:name":"Am Bach",
    "gn:population":0,
    "gn:timezone":"Europe/Zurich",
    "iso:country":"CH",
    "name:deu_x_preferred":[
        "Am Bach"
    ],
    "name:und_x_variant":[
        "Am Bach (Avers)"
    ],
    "wof:name":"Am Bach",
    "wof:placetype":"locality"
},
  "geometry": {"coordinates":[9.53743,46.45857],"type":"Point"}
}