{
  "type": "Feature",
  "properties": {
    "gn:gn_country":"CH",
    "gn:gn_fcode":"PPL",
    "gn:gn_pop":279,
    "gn:population":279,
    "iso:country":"CH",
    "name:bul_x_preferred":[
        "\u041a\u0440\u0438\u043d\u0430\u0443"
    ],
    "name:cat_x_preferred":[
        "Krinau"
    ],
    "name:dut_x_preferred":[
        "Krinau"
    ],
    "name:eng_x_preferred":[
        "Krinau"
    ],
    "name:epo_x_preferred":[
        "Krinau"
    ],
    "name:fre_x_preferred":[
        "Krinau"
    ],
    "name:ger_x_preferred":[
        "Krinau"
    ],
    "name:gsw_x_preferred":[
        "Chrinou"
    ],
    "name:hun_x_preferred":[
        "Krinau"
    ],
    "name:ita_x_preferred":[
        "Krinau"
    ],
    "name:kaz_x_preferred":[
        "\u041a\u0440\u0438\u043d\u0430\u0443"
    ],
    "name:lmo_x_preferred":[
        "Krinau"
    ],
    "name:may_x_preferred":[
        "Krinau"
    ],
    "name:nno_x_preferred":[
        "Krinau"
    ],
    "name:oci_x_preferred":[
        "Krinau"
    ],
    "name:pms_x_preferred":[
        "Krinau"
    ],
    "name:por_x_preferred":[
        "Krinau"
    ],
    "name:rus_x_preferred":[
        "\u041a\u0440\u0438\u043d\u0430\u0443"
    ],
    "name:spa_x_preferred":[
        "Krinau"
    ],
    "name:swe_x_preferred":[
        "Krinau"
    ],
    "name:uzb_x_preferred":[
        "Krinau"
    ],
    "name:vol_x_preferred":[
        "Krinau"
    ],
    "name:war_x_preferred":[
        "Krinau"
    ],
    "qs_pg:aaroncc":"CH",
    "qs_pg:gn_country":"CH",
    "qs_pg:gn_fcode":"PPL",
    "qs_pg:gn_pop":279,
    "qs_pg:name":"Krinau",
    "qs_pg:name_adm0":"Schweiz",
    "qs_pg:name_adm1":"Kanton St. Gallen",
    "qs_pg:photos":4,
    "qs_pg:photos_1k":1,
    "qs_pg:photos_9k":1,
    "qs_pg:photos_9r":1,
    "qs_pg:photos_all":4,
    "qs_pg:photos_sr":1,
    "qs_pg:pop_sr":2,
    "qs_pg:qs_pg_placetype":"locality",
    "qs_pg:qs_pg_placetype_gp":"Town",
    "qs_pg:woe_adm0":23424957,
    "woe:adm0_id":23424957,
    "woe:name_adm0":"Schweiz",
    "woe:name_adm1":"Kanton St. Gallen",
    "woe:placetype":"Town",
    "wof:name":"Krinau",
    "wof:placetype":"locality",
    "wof:population":279
},
  "geometry": {"coordinates":[9.05003,47.31756],"type":"Point"}
}