{
  "type": "Feature",
  "properties": {
    "gn:gn_country":"CH",
    "gn:gn_fcode":"PPL",
    "gn:gn_pop":660,
    "gn:population":660,
    "iso:country":"CH",
    "name:ast_x_preferred":[
        "Buckten"
    ],
    "name:cat_x_preferred":[
        "Buckten"
    ],
    "name:chv_x_preferred":[
        "\u0411\u0443\u043a\u0442\u0435\u043d"
    ],
    "name:deu_x_preferred":[
        "Buckten"
    ],
    "name:eng_x_preferred":[
        "Buckten"
    ],
    "name:epo_x_preferred":[
        "Buckten"
    ],
    "name:eus_x_preferred":[
        "Buckten"
    ],
    "name:fra_x_preferred":[
        "Buckten"
    ],
    "name:gsw_x_preferred":[
        "Buckte"
    ],
    "name:hun_x_preferred":[
        "Buckten"
    ],
    "name:ita_x_preferred":[
        "Buckten"
    ],
    "name:kaz_x_preferred":[
        "\u0411\u0443\u043a\u0442\u0435\u043d"
    ],
    "name:lmo_x_preferred":[
        "Buckten"
    ],
    "name:msa_x_preferred":[
        "Buckten"
    ],
    "name:nld_x_preferred":[
        "Buckten"
    ],
    "name:nno_x_preferred":[
        "Buckten"
    ],
    "name:oci_x_preferred":[
        "Buckten"
    ],
    "name:rus_x_preferred":[
        "\u0411\u0443\u043a\u0442\u0435\u043d"
    ],
    "name:spa_x_preferred":[
        "Buckten"
    ],
    "name:sqi_x_preferred":[
        "Buckten"
    ],
    "name:swe_x_preferred":[
        "Buckten"
    ],
    "name:uzb_x_preferred":[
        "Buckten"
    ],
    "name:vol_x_preferred":[
        "Buckten"
    ],
    "name:war_x_preferred":[
        "Buckten"
    ],
    "name:zho_x_preferred":[
        "\u5e03\u514b\u6ed5"
    ],
    "qs_pg:aaroncc":"CH",
    "qs_pg:gn_country":"CH",
    "qs_pg:gn_fcode":"PPL",
    "qs_pg:gn_pop":660,
    "qs_pg:name":"Buckten",
    "qs_pg:name_adm0":"Schweiz",
    "qs_pg:name_adm1":"Kanton Basel-Land",
    "qs_pg:photos":20,
    "qs_pg:photos_1k":4,
    "qs_pg:photos_9k":1,
    "qs_pg:photos_9r":1,
    "qs_pg:photos_all":20,
    "qs_pg:photos_sr":1,
    "qs_pg:pop_sr":2,
    "qs_pg:qs_pg_placetype":"locality",
    "qs_pg:qs_pg_placetype_gp":"Town",
    "qs_pg:woe_adm0":23424957,
    "woe:adm0_id":23424957,
    "woe:name_adm0":"Schweiz",
    "woe:name_adm1":"Kanton Basel-Land",
    "woe:placetype":"Town",
    "wof:name":"Buckten",
    "wof:placetype":"locality",
    "wof:population":660
},
  "geometry": {"coordinates":[7.84481,47.4099],"type":"Point"}
}