{
  "type": "Feature",
  "properties": {
    "gn:admin1_code":"BL",
    "gn:admin2_code":"1304.0",
    "gn:admin3_code":"2867.0",
    "gn:asciiname":"Wittinsburg",
    "gn:country_code":"CH",
    "gn:dem":576,
    "gn:feature_class":"P",
    "gn:feature_code":"PPL",
    "gn:name":"Wittinsburg",
    "gn:population":0,
    "gn:timezone":"Europe/Zurich",
    "iso:country":"CH",
    "wof:name":"Wittinsburg",
    "wof:placetype":"locality"
},
  "geometry": {"coordinates":[7.84128,47.42521],"type":"Point"}
}