{
  "type": "Feature",
  "properties": {
    "gn:admin1_code":"LU",
    "gn:admin2_code":"315.0",
    "gn:admin3_code":"1128.0",
    "gn:asciiname":"Moosmatt",
    "gn:country_code":"CH",
    "gn:dem":507,
    "gn:feature_class":"P",
    "gn:feature_code":"PPLL",
    "gn:name":"Moosmatt",
    "gn:population":0,
    "gn:timezone":"Europe/Zurich",
    "iso:country":"CH",
    "name:deu_x_preferred":[
        "Moosmatt"
    ],
    "wof:name":"Moosmatt",
    "wof:placetype":"locality"
},
  "geometry": {"coordinates":[8.03048,47.16257],"type":"Point"}
}