{
  "type": "Feature",
  "properties": {
    "gn:country":"CH",
    "gn:fcode":"PPL",
    "gn:population":19,
    "iso:country":"CH",
    "qs_pg:aaroncc":"CH",
    "qs_pg:gn_country":"CH",
    "qs_pg:gn_fcode":"PPL",
    "qs_pg:gn_pop":19,
    "qs_pg:name":"Vorder-Strahlegg",
    "qs_pg:photos_9r":0,
    "qs_pg:photos_sr":0,
    "qs_pg:pop_sr":1,
    "qs_pg:qs_pg_placetype":"locality",
    "wof:name":"Vorder-Strahlegg",
    "wof:placetype":"neighbourhood",
    "wof:population":19
},
  "geometry": {"coordinates":[8.9567,47.32653],"type":"Point"}
}