{
  "type": "Feature",
  "properties": {
    "gn:admin1_code":"TI",
    "gn:admin2_code":"2105.0",
    "gn:admin3_code":"5226.0",
    "gn:asciiname":"Lugaggia",
    "gn:country_code":"CH",
    "gn:dem":510,
    "gn:feature_class":"P",
    "gn:feature_code":"PPL",
    "gn:name":"Lugaggia",
    "gn:population":0,
    "gn:timezone":"Europe/Zurich",
    "iso:country":"CH",
    "wof:name":"Lugaggia",
    "wof:placetype":"locality"
},
  "geometry": {"coordinates":[8.97265,46.06263],"type":"Point"}
}