{
  "type": "Feature",
  "properties": {
    "gn:admin1_code":"TG",
    "gn:admin2_code":"2012.0",
    "gn:admin3_code":"4841.0",
    "gn:asciiname":"Hungerbuehl",
    "gn:country_code":"CH",
    "gn:dem":469,
    "gn:feature_class":"P",
    "gn:feature_code":"PPLL",
    "gn:name":"Hungerb\u00fchl",
    "gn:population":0,
    "gn:timezone":"Europe/Zurich",
    "iso:country":"CH",
    "name:deu_x_preferred":[
        "Hungerb\u00fchl"
    ],
    "wof:name":"Hungerbuehl",
    "wof:placetype":"neighbourhood"
},
  "geometry": {"coordinates":[8.97996,47.60865],"type":"Point"}
}