{
  "type": "Feature",
  "properties": {
    "gn:gn_country":"CH",
    "gn:gn_fcode":"PPL",
    "gn:gn_pop":0,
    "iso:country":"CH",
    "name:bul_x_preferred":[
        "\u0415\u043d\u0433\u0435\u0441"
    ],
    "name:cat_x_preferred":[
        "Enges"
    ],
    "name:deu_x_preferred":[
        "Enges"
    ],
    "name:eng_x_preferred":[
        "Enges"
    ],
    "name:epo_x_preferred":[
        "Enges"
    ],
    "name:eus_x_preferred":[
        "Enges"
    ],
    "name:fra_x_preferred":[
        "Enges"
    ],
    "name:gsw_x_preferred":[
        "Enges"
    ],
    "name:hun_x_preferred":[
        "Enges"
    ],
    "name:ita_x_preferred":[
        "Enges"
    ],
    "name:lmo_x_preferred":[
        "Enges"
    ],
    "name:msa_x_preferred":[
        "Enges"
    ],
    "name:nld_x_preferred":[
        "Enges"
    ],
    "name:nno_x_preferred":[
        "Enges"
    ],
    "name:oci_x_preferred":[
        "Enges"
    ],
    "name:spa_x_preferred":[
        "Enges"
    ],
    "name:swe_x_preferred":[
        "Enges"
    ],
    "name:vol_x_preferred":[
        "Enges"
    ],
    "name:war_x_preferred":[
        "Enges"
    ],
    "name:zho_x_preferred":[
        "\u6069\u71b1"
    ],
    "qs_pg:aaroncc":"CH",
    "qs_pg:gn_country":"CH",
    "qs_pg:gn_fcode":"PPL",
    "qs_pg:gn_pop":0,
    "qs_pg:name":"Enges",
    "qs_pg:name_adm0":"Schweiz",
    "qs_pg:name_adm1":"Canton de Neuch\u00e2tel",
    "qs_pg:photos":19,
    "qs_pg:photos_1k":4,
    "qs_pg:photos_9k":1,
    "qs_pg:photos_9r":1,
    "qs_pg:photos_all":19,
    "qs_pg:photos_sr":1,
    "qs_pg:pop_sr":0,
    "qs_pg:qs_pg_placetype":"locality",
    "qs_pg:qs_pg_placetype_gp":"Town",
    "qs_pg:woe_adm0":23424957,
    "woe:adm0_id":23424957,
    "woe:name_adm0":"Schweiz",
    "woe:name_adm1":"Canton de Neuch\u00e2tel",
    "woe:placetype":"Town",
    "wof:name":"Enges",
    "wof:placetype":"locality"
},
  "geometry": {"coordinates":[7.01657,47.06673],"type":"Point"}
}