{
  "type": "Feature",
  "properties": {
    "gn:admin1_code":"FR",
    "gn:admin2_code":"1004.0",
    "gn:admin3_code":"2236.0",
    "gn:asciiname":"Rueyres-St-Laurent",
    "gn:country_code":"CH",
    "gn:dem":778,
    "gn:feature_class":"P",
    "gn:feature_code":"PPL",
    "gn:name":"Rueyres-St-Laurent",
    "gn:population":0,
    "gn:timezone":"Europe/Zurich",
    "iso:country":"CH",
    "wof:name":"Rueyres-St-Laurent",
    "wof:placetype":"locality"
},
  "geometry": {"coordinates":[7.03614,46.71287],"type":"Point"}
}