{
  "type": "Feature",
  "properties": {
    "gn:admin1_code":"SH",
    "gn:admin2_code":"1405.0",
    "gn:admin3_code":"2963.0",
    "gn:asciiname":"Bibermuhle",
    "gn:country_code":"CH",
    "gn:dem":402,
    "gn:feature_class":"P",
    "gn:feature_code":"PPL",
    "gn:name":"Biberm\u00fchle",
    "gn:population":0,
    "gn:timezone":"Europe/Zurich",
    "iso:country":"CH",
    "name:deu_x_preferred":[
        "Biberm\u00fcli"
    ],
    "name:deu_x_variant":[
        "Biberm\u00fchle"
    ],
    "wof:name":"Bibermuhle",
    "wof:placetype":"neighbourhood"
},
  "geometry": {"coordinates":[8.80486,47.68004000000001],"type":"Point"}
}