{
  "type": "Feature",
  "properties": {
    "gn:admin1_code":"VD",
    "gn:admin2_code":"2226.0",
    "gn:admin3_code":"5590.0",
    "gn:asciiname":"Les Monts-de-Pully",
    "gn:country_code":"CH",
    "gn:dem":740,
    "gn:feature_class":"P",
    "gn:feature_code":"PPL",
    "gn:name":"Les Monts-de-Pully",
    "gn:population":0,
    "gn:timezone":"Europe/Zurich",
    "iso:country":"CH",
    "wof:name":"Les Monts-de-Pully",
    "wof:placetype":"locality"
},
  "geometry": {"coordinates":[6.68758,46.53731],"type":"Point"}
}