{
  "type": "Feature",
  "properties": {
    "gn:gn_country":"CH",
    "gn:gn_fcode":"PPL",
    "gn:gn_pop":0,
    "iso:country":"CH",
    "qs_pg:aaroncc":"CH",
    "qs_pg:gn_country":"CH",
    "qs_pg:gn_fcode":"PPL",
    "qs_pg:gn_pop":0,
    "qs_pg:name":"B\u00fcrgenstock",
    "qs_pg:name_adm0":"Schweiz",
    "qs_pg:name_adm1":"Kanton Nidwalden",
    "qs_pg:photos":96,
    "qs_pg:photos_1k":19,
    "qs_pg:photos_9k":1,
    "qs_pg:photos_9r":3,
    "qs_pg:photos_all":96,
    "qs_pg:photos_sr":3,
    "qs_pg:pop_sr":0,
    "qs_pg:qs_pg_placetype":"locality",
    "qs_pg:qs_pg_placetype_gp":"Town",
    "qs_pg:woe_adm0":23424957,
    "woe:adm0_id":23424957,
    "woe:name_adm0":"Schweiz",
    "woe:name_adm1":"Kanton Nidwalden",
    "woe:placetype":"Town",
    "wof:name":"B\u00fcrgenstock",
    "wof:placetype":"locality"
},
  "geometry": {"coordinates":[8.37484,46.99621],"type":"Point"}
}