{
  "type": "Feature",
  "properties": {
    "iso:country":"CH",
    "name:deu_x_preferred":[
        "Stuckishaus"
    ],
    "qs:gn_adm0_cc":"CH",
    "qs:gn_fcode":"PPL",
    "qs:gn_local":2661552,
    "qs:gn_nam_loc":"Bern",
    "qs:gn_namadm1":"BE",
    "qs:gn_name":"Stuckishaus",
    "qs:local_max":19074,
    "qs:local_sum":54499,
    "qs:localhoods":30,
    "qs:name":"Stuckishaus",
    "qs:name_adm0":"Schweiz",
    "qs:name_adm1":"Kanton Bern",
    "qs:name_adm2":"Bern-Mittelland",
    "qs:name_lau":"Bremgarten bei Bern",
    "qs:name_local":"Bern",
    "qs:photo_max":42,
    "qs:photo_sum":88,
    "qs:placetype":"Suburb",
    "qs:quad_count":10,
    "qs:woe_adm0":23424957,
    "qs:woe_adm1":2347087,
    "qs:woe_adm2":56558125,
    "qs:woe_lau":12683453,
    "qs:woe_local":781788,
    "qs:woe_ver":"7.10.0",
    "wof:lang":[
        "ger"
    ],
    "wof:name":"Stuckishaus",
    "wof:placetype":"neighbourhood"
},
  "geometry": {"coordinates":[7.431681,46.971471],"type":"Point"}
}