{
  "type": "Feature",
  "properties": {
    "gn:population":6576,
    "iso:country":"CH",
    "name:als_x_preferred":[
        "Visp"
    ],
    "name:bel_x_preferred":[
        "\u0424\u0456\u0441\u043f"
    ],
    "name:cat_x_preferred":[
        "Visp"
    ],
    "name:ceb_x_preferred":[
        "Visp"
    ],
    "name:ces_x_preferred":[
        "Visp"
    ],
    "name:dan_x_preferred":[
        "Visp"
    ],
    "name:deu_x_preferred":[
        "Visp"
    ],
    "name:eng_x_preferred":[
        "Visp"
    ],
    "name:epo_x_preferred":[
        "Vispo"
    ],
    "name:eus_x_preferred":[
        "Visp"
    ],
    "name:fas_x_preferred":[
        "\u0648\u06cc\u0633\u067e"
    ],
    "name:fin_x_preferred":[
        "Visp"
    ],
    "name:fra_x_preferred":[
        "Vi\u00e8ge"
    ],
    "name:gsw_x_preferred":[
        "Vischp"
    ],
    "name:heb_x_preferred":[
        "\u05d5\u05d9\u05e1\u05e4"
    ],
    "name:hun_x_preferred":[
        "Visp"
    ],
    "name:hye_x_preferred":[
        "\u054e\u056b\u057d\u057a"
    ],
    "name:ita_x_preferred":[
        "Visp"
    ],
    "name:jpn_x_preferred":[
        "\u30d5\u30a3\u30b9\u30d7"
    ],
    "name:kor_x_preferred":[
        "\ud53c\uc2a4\ud504"
    ],
    "name:lmo_x_preferred":[
        "Visp"
    ],
    "name:msa_x_preferred":[
        "Visp"
    ],
    "name:nld_x_preferred":[
        "Visp"
    ],
    "name:nno_x_preferred":[
        "Visp i Sveits"
    ],
    "name:nob_x_preferred":[
        "Visp"
    ],
    "name:nor_x_preferred":[
        "Visp"
    ],
    "name:oci_x_preferred":[
        "Visp"
    ],
    "name:pms_x_preferred":[
        "Visp"
    ],
    "name:pol_x_preferred":[
        "Visp"
    ],
    "name:por_x_preferred":[
        "Visp"
    ],
    "name:roh_x_preferred":[
        "Visp"
    ],
    "name:ron_x_preferred":[
        "Visp"
    ],
    "name:rus_x_preferred":[
        "\u0424\u0438\u0441\u043f"
    ],
    "name:scn_x_preferred":[
        "Visp"
    ],
    "name:slv_x_preferred":[
        "Visp"
    ],
    "name:spa_x_preferred":[
        "Visp"
    ],
    "name:sqi_x_preferred":[
        "Visp"
    ],
    "name:swe_x_preferred":[
        "Visp"
    ],
    "name:szl_x_preferred":[
        "Visp"
    ],
    "name:vol_x_preferred":[
        "Visp"
    ],
    "name:war_x_preferred":[
        "Visp"
    ],
    "name:zho_x_preferred":[
        "\u83f2\u65af\u666e"
    ],
    "qs:a0":"Schweiz#Suisse#Svizzera#Svizra",
    "qs:a1":"*Valais",
    "qs:a1r":"0",
    "qs:adm0":"Schweiz#Suisse#Svizzera#Svizra",
    "qs:la_lc":"*",
    "qs:level":"locality",
    "qs:loc":"Visp",
    "qs:loc_alt":"Visp",
    "qs:pop":0,
    "qs:type":"buffered point",
    "wof:name":"Visp",
    "wof:placetype":"locality",
    "wof:population":6576
},
  "geometry": {"coordinates":[7.880608,46.29496],"type":"Point"}
}