{
  "type": "Feature",
  "properties": {
    "iso:country":"CH",
    "wof:name":"Les Cropettes",
    "wof:placetype":"neighbourhood"
},
  "geometry": {"coordinates":[6.14038842261482,46.21339234297587],"type":"Point"}
}