{
  "type": "Feature",
  "properties": {
    "iso:country":"CH",
    "name:fra_x_preferred":[
        "Saint-L\u00e9ger"
    ],
    "wof:name":"Saint-Leger",
    "wof:placetype":"neighbourhood"
},
  "geometry": {"coordinates":[6.1476125091964,46.19749260313093],"type":"Point"}
}