{
  "type": "Feature",
  "properties": {
    "gn:admin1_code":"TI",
    "gn:admin2_code":"2105.0",
    "gn:admin3_code":"5146.0",
    "gn:asciiname":"Erbagni",
    "gn:country_code":"CH",
    "gn:dem":690,
    "gn:feature_class":"P",
    "gn:feature_code":"PPL",
    "gn:name":"Erbagni",
    "gn:population":0,
    "gn:timezone":"Europe/Zurich",
    "iso:country":"CH",
    "name:ita_x_preferred":[
        "Erbagni"
    ],
    "wof:name":"Erbagni",
    "wof:placetype":"neighbourhood"
},
  "geometry": {"coordinates":[8.79867,46.01125],"type":"Point"}
}