{
  "type": "Feature",
  "properties": {
    "gn:admin1_code":"TI",
    "gn:admin2_code":"2105.0",
    "gn:admin3_code":"5222.0",
    "gn:asciiname":"La Costa",
    "gn:country_code":"CH",
    "gn:dem":561,
    "gn:feature_class":"P",
    "gn:feature_code":"PPL",
    "gn:name":"La Costa",
    "gn:population":0,
    "gn:timezone":"Europe/Zurich",
    "iso:country":"CH",
    "name:ita_x_preferred":[
        "La Costa"
    ],
    "wof:name":"La Costa",
    "wof:placetype":"neighbourhood"
},
  "geometry": {"coordinates":[8.82569,46.00752],"type":"Point"}
}