{
  "type": "Feature",
  "properties": {
    "gn:admin1_code":"JU",
    "gn:admin2_code":"2601.0",
    "gn:admin3_code":"6708.0",
    "gn:asciiname":"Choindez",
    "gn:country_code":"CH",
    "gn:dem":467,
    "gn:feature_class":"P",
    "gn:feature_code":"PPL",
    "gn:name":"Choindez",
    "gn:population":0,
    "gn:timezone":"Europe/Zurich",
    "iso:country":"CH",
    "wof:name":"Choindez",
    "wof:placetype":"neighbourhood"
},
  "geometry": {"coordinates":[7.37981,47.32102],"type":"Point"}
}