{
  "type": "Feature",
  "properties": {
    "gn:admin1_code":"BE",
    "gn:admin2_code":"241.0",
    "gn:admin3_code":"434.0",
    "gn:asciiname":"La Blanche",
    "gn:country_code":"CH",
    "gn:dem":1167,
    "gn:feature_class":"P",
    "gn:feature_code":"PPLL",
    "gn:name":"La Blanche",
    "gn:population":0,
    "gn:timezone":"Europe/Zurich",
    "iso:country":"CH",
    "name:fra_x_preferred":[
        "La Blanche"
    ],
    "wof:name":"La Blanche",
    "wof:placetype":"neighbourhood"
},
  "geometry": {"coordinates":[7.07496,47.16121],"type":"Point"}
}