{
  "type": "Feature",
  "properties": {
    "gn:admin1_code":"LU",
    "gn:admin2_code":"316.0",
    "gn:admin3_code":"1009.0",
    "gn:asciiname":"Lochguet",
    "gn:country_code":"CH",
    "gn:dem":751,
    "gn:feature_class":"P",
    "gn:feature_code":"PPLL",
    "gn:name":"Lochguet",
    "gn:population":0,
    "gn:timezone":"Europe/Zurich",
    "iso:country":"CH",
    "name:deu_x_preferred":[
        "Lochguet"
    ],
    "wof:lang_x_official":[
        "deu",
        "fra",
        "gsw",
        "ita"
    ],
    "wof:lang_x_spoken":[
        "deu",
        "fra",
        "gsw",
        "ita",
        "roh"
    ],
    "wof:name":"Lochguet",
    "wof:placetype":"neighbourhood"
},
  "geometry": {"coordinates":[8.11587,47.03808],"type":"Point"}
}