{
  "type": "Feature",
  "properties": {
    "gn:gn_country":"CH",
    "gn:gn_fcode":"PPLL",
    "gn:gn_pop":8,
    "gn:population":8,
    "iso:country":"CH",
    "name:ceb_x_preferred":[
        "Buck"
    ],
    "name:ces_x_preferred":[
        "Buck"
    ],
    "name:deu_x_preferred":[
        "Buck"
    ],
    "name:fra_x_preferred":[
        "Buck"
    ],
    "name:heb_x_preferred":[
        "\u05d1\u05d0\u05e7"
    ],
    "name:ita_x_preferred":[
        "Buck"
    ],
    "name:nds_x_preferred":[
        "Buck"
    ],
    "name:nld_x_preferred":[
        "Buck"
    ],
    "name:nor_x_preferred":[
        "Buck"
    ],
    "name:pol_x_preferred":[
        "Buck"
    ],
    "name:swe_x_preferred":[
        "Buck"
    ],
    "qs_pg:aaroncc":"CH",
    "qs_pg:gn_country":"CH",
    "qs_pg:gn_fcode":"PPLL",
    "qs_pg:gn_pop":8,
    "qs_pg:name":"Buck",
    "qs_pg:photos_9r":0,
    "qs_pg:photos_sr":0,
    "qs_pg:pop_sr":1,
    "qs_pg:qs_pg_placetype":"locality",
    "wof:name":"Buck",
    "wof:placetype":"neighbourhood",
    "wof:population":8
},
  "geometry": {"coordinates":[8.71469,47.57931],"type":"Point"}
}