{
  "type": "Feature",
  "properties": {
    "gn:gn_country":"CH",
    "gn:gn_fcode":"PPL",
    "gn:gn_pop":957,
    "gn:population":957,
    "iso:country":"CH",
    "name:ara_x_preferred":[
        "\u0641\u0648\u0628\u0646\u0627\u0648"
    ],
    "name:baq_x_preferred":[
        "Wuppenau"
    ],
    "name:cat_x_preferred":[
        "Wuppenau"
    ],
    "name:chi_x_preferred":[
        "\u6b66\u73c0\u7459"
    ],
    "name:dut_x_preferred":[
        "Wuppenau"
    ],
    "name:eng_x_preferred":[
        "Wuppenau"
    ],
    "name:epo_x_preferred":[
        "Wuppenau"
    ],
    "name:fre_x_preferred":[
        "Wuppenau"
    ],
    "name:ger_x_preferred":[
        "Wuppenau"
    ],
    "name:gsw_x_preferred":[
        "Wuppenau"
    ],
    "name:hun_x_preferred":[
        "Wuppenau"
    ],
    "name:ita_x_preferred":[
        "Wuppenau"
    ],
    "name:kaz_x_preferred":[
        "\u0412\u0443\u043f\u043f\u0435\u043d\u0430\u0443"
    ],
    "name:lmo_x_preferred":[
        "Wuppenau"
    ],
    "name:may_x_preferred":[
        "Wuppenau"
    ],
    "name:nno_x_preferred":[
        "Wuppenau"
    ],
    "name:oci_x_preferred":[
        "Wuppenau"
    ],
    "name:pms_x_preferred":[
        "Wuppenau"
    ],
    "name:por_x_preferred":[
        "Wuppenau"
    ],
    "name:rus_x_preferred":[
        "\u0412\u0443\u043f\u043f\u0435\u043d\u0430\u0443"
    ],
    "name:spa_x_preferred":[
        "Wuppenau"
    ],
    "name:uzb_x_preferred":[
        "Wuppenau"
    ],
    "name:vec_x_preferred":[
        "Wuppenau"
    ],
    "name:vol_x_preferred":[
        "Wuppenau"
    ],
    "name:war_x_preferred":[
        "Wuppenau"
    ],
    "name:zho_x_preferred":[
        "\u6b66\u73c0\u7459"
    ],
    "qs_pg:aaroncc":"CH",
    "qs_pg:gn_country":"CH",
    "qs_pg:gn_fcode":"PPL",
    "qs_pg:gn_pop":957,
    "qs_pg:name":"Wuppenau",
    "qs_pg:name_adm0":"Schweiz",
    "qs_pg:name_adm1":"Kanton Thurgau",
    "qs_pg:photos_9r":0,
    "qs_pg:photos_sr":0,
    "qs_pg:pop_sr":2,
    "qs_pg:qs_pg_placetype":"locality",
    "qs_pg:qs_pg_placetype_gp":"Town",
    "qs_pg:woe_adm0":23424957,
    "woe:adm0_id":23424957,
    "woe:name_adm0":"Schweiz",
    "woe:name_adm1":"Kanton Thurgau",
    "woe:placetype":"Town",
    "wof:name":"Wuppenau",
    "wof:placetype":"locality",
    "wof:population":957
},
  "geometry": {"coordinates":[9.10904,47.49633],"type":"Point"}
}