{
  "type": "Feature",
  "properties": {
    "gn:admin1_code":"VS",
    "gn:admin2_code":"2312.0",
    "gn:admin3_code":"6266.0",
    "gn:asciiname":"La Vernaz (Les Agettes)",
    "gn:country_code":"CH",
    "gn:dem":1060,
    "gn:feature_class":"P",
    "gn:feature_code":"PPL",
    "gn:name":"La Vernaz (Les Agettes)",
    "gn:population":0,
    "gn:timezone":"Europe/Zurich",
    "iso:country":"CH",
    "wof:name":"La Vernaz (Les Agettes)",
    "wof:placetype":"locality"
},
  "geometry": {"coordinates":[7.37342,46.21022],"type":"Point"}
}