{
  "type": "Feature",
  "properties": {
    "gn:gn_country":"CH",
    "gn:gn_fcode":"PPL",
    "gn:gn_pop":1233,
    "gn:population":1233,
    "iso:country":"CH",
    "name:deu_x_preferred":[
        "Travers NE"
    ],
    "name:eng_x_preferred":[
        "Travers"
    ],
    "name:fra_x_preferred":[
        "Travers"
    ],
    "name:ita_x_preferred":[
        "Travers"
    ],
    "name:nld_x_preferred":[
        "Travers"
    ],
    "name:spa_x_preferred":[
        "Travers"
    ],
    "name:swe_x_preferred":[
        "Travers"
    ],
    "name:vol_x_preferred":[
        "Travers"
    ],
    "qs_pg:aaroncc":"CH",
    "qs_pg:gn_country":"CH",
    "qs_pg:gn_fcode":"PPL",
    "qs_pg:gn_pop":1233,
    "qs_pg:name":"Travers",
    "qs_pg:name_adm0":"Schweiz",
    "qs_pg:name_adm1":"Canton de Neuch\u00e2tel",
    "qs_pg:photos":654,
    "qs_pg:photos_1k":133,
    "qs_pg:photos_9k":3,
    "qs_pg:photos_9r":5,
    "qs_pg:photos_all":654,
    "qs_pg:photos_sr":8,
    "qs_pg:pop_sr":3,
    "qs_pg:qs_pg_placetype":"locality",
    "qs_pg:qs_pg_placetype_gp":"Town",
    "qs_pg:woe_adm0":23424957,
    "woe:adm0_id":23424957,
    "woe:name_adm0":"Schweiz",
    "woe:name_adm1":"Canton de Neuch\u00e2tel",
    "woe:placetype":"Town",
    "wof:name":"Travers",
    "wof:placetype":"locality",
    "wof:population":1233
},
  "geometry": {"coordinates":[6.67595,46.94018],"type":"Point"}
}