{
  "type": "Feature",
  "properties": {
    "gn:admin1_code":"SH",
    "gn:admin2_code":"1405.0",
    "gn:admin3_code":"2963.0",
    "gn:asciiname":"Wiesholz",
    "gn:country_code":"CH",
    "gn:dem":423,
    "gn:elevation":"426.0",
    "gn:feature_class":"P",
    "gn:feature_code":"PPL",
    "gn:name":"Wiesholz",
    "gn:population":0,
    "gn:timezone":"Europe/Zurich",
    "iso:country":"CH",
    "wof:name":"Wiesholz",
    "wof:placetype":"neighbourhood"
},
  "geometry": {"coordinates":[8.8354,47.71174],"type":"Point"}
}