{
  "type": "Feature",
  "properties": {
    "gn:admin1_code":"TI",
    "gn:admin2_code":"2105.0",
    "gn:admin3_code":"5143.0",
    "gn:asciiname":"Luscie",
    "gn:country_code":"CH",
    "gn:dem":668,
    "gn:feature_class":"P",
    "gn:feature_code":"PPL",
    "gn:name":"Lusci\u00e8",
    "gn:population":0,
    "gn:timezone":"Europe/Zurich",
    "iso:country":"CH",
    "name:ita_x_preferred":[
        "Lusci\u00e8"
    ],
    "wof:name":"Luscie",
    "wof:placetype":"neighbourhood"
},
  "geometry": {"coordinates":[8.87679,46.02834],"type":"Point"}
}