{
  "type": "Feature",
  "properties": {
    "gn:gn_country":"CH",
    "gn:gn_fcode":"PPL",
    "gn:gn_pop":408,
    "gn:population":408,
    "iso:country":"CH",
    "name:cat_x_preferred":[
        "Kriechenwil"
    ],
    "name:deu_x_preferred":[
        "Kriechenwil"
    ],
    "name:eng_x_preferred":[
        "Kriechenwil"
    ],
    "name:epo_x_preferred":[
        "Kriechenwil"
    ],
    "name:eus_x_preferred":[
        "Kriechenwil"
    ],
    "name:fra_x_preferred":[
        "Kriechenwil"
    ],
    "name:gsw_x_preferred":[
        "Chriechwiu"
    ],
    "name:hun_x_preferred":[
        "Kriechenwil"
    ],
    "name:ita_x_preferred":[
        "Kriechenwil"
    ],
    "name:kaz_x_preferred":[
        "\u041a\u0440\u0438\u0445\u0435\u043d\u0432\u0438\u043b\u044c"
    ],
    "name:lmo_x_preferred":[
        "Kriechenwil"
    ],
    "name:msa_x_preferred":[
        "Kriechenwil"
    ],
    "name:nld_x_preferred":[
        "Kriechenwil"
    ],
    "name:nno_x_preferred":[
        "Kriechenwil"
    ],
    "name:oci_x_preferred":[
        "Kriechenwil"
    ],
    "name:rus_x_preferred":[
        "\u041a\u0440\u0438\u0445\u0435\u043d\u0432\u0438\u043b\u044c"
    ],
    "name:spa_x_preferred":[
        "Kriechenwil"
    ],
    "name:sqi_x_preferred":[
        "Kriechenwil"
    ],
    "name:swe_x_preferred":[
        "Kriechenwil"
    ],
    "name:vie_x_preferred":[
        "Kriechenwil"
    ],
    "name:vol_x_preferred":[
        "Kriechenwil"
    ],
    "name:war_x_preferred":[
        "Kriechenwil"
    ],
    "name:zho_x_preferred":[
        "\u514b\u91cc\u8208\u7dad\u723e"
    ],
    "qs_pg:aaroncc":"CH",
    "qs_pg:gn_country":"CH",
    "qs_pg:gn_fcode":"PPL",
    "qs_pg:gn_pop":408,
    "qs_pg:name":"Kriechenwil",
    "qs_pg:name_adm0":"Schweiz",
    "qs_pg:name_adm1":"Kanton Bern",
    "qs_pg:photos":87,
    "qs_pg:photos_1k":18,
    "qs_pg:photos_9k":1,
    "qs_pg:photos_9r":3,
    "qs_pg:photos_all":87,
    "qs_pg:photos_sr":3,
    "qs_pg:pop_sr":2,
    "qs_pg:qs_pg_placetype":"locality",
    "qs_pg:qs_pg_placetype_gp":"Town",
    "qs_pg:woe_adm0":23424957,
    "woe:adm0_id":23424957,
    "woe:name_adm0":"Schweiz",
    "woe:name_adm1":"Kanton Bern",
    "woe:placetype":"Town",
    "wof:name":"Kriechenwil",
    "wof:placetype":"locality",
    "wof:population":408
},
  "geometry": {"coordinates":[7.21957,46.90968],"type":"Point"}
}