{
  "type": "Feature",
  "properties": {
    "gn:admin1_code":"LU",
    "gn:admin2_code":"316.0",
    "gn:admin3_code":"1004.0",
    "gn:asciiname":"Ausserlamm",
    "gn:country_code":"CH",
    "gn:dem":846,
    "gn:feature_class":"P",
    "gn:feature_code":"PPLL",
    "gn:name":"Ausserlamm",
    "gn:population":0,
    "gn:timezone":"Europe/Zurich",
    "iso:country":"CH",
    "name:deu_x_preferred":[
        "Ausserlamm"
    ],
    "wof:name":"Ausserlamm",
    "wof:placetype":"locality"
},
  "geometry": {"coordinates":[8.01272,46.91531],"type":"Point"}
}