{
  "type": "Feature",
  "properties": {
    "gn:admin1_code":"BE",
    "gn:admin2_code":"250.0",
    "gn:admin3_code":"584.0",
    "gn:asciiname":"Heimegg",
    "gn:country_code":"CH",
    "gn:dem":899,
    "gn:feature_class":"P",
    "gn:feature_code":"PPL",
    "gn:name":"Heimegg",
    "gn:population":0,
    "gn:timezone":"Europe/Zurich",
    "iso:country":"CH",
    "name:deu_x_preferred":[
        "Heimegg"
    ],
    "wof:name":"Heimegg",
    "wof:placetype":"neighbourhood"
},
  "geometry": {"coordinates":[7.91225,46.60252],"type":"Point"}
}