{
  "type": "Feature",
  "properties": {
    "gn:admin1_code":"ZH",
    "gn:admin2_code":"108.0",
    "gn:admin3_code":"173.0",
    "gn:asciiname":"Trogacher",
    "gn:country_code":"CH",
    "gn:dem":652,
    "gn:feature_class":"P",
    "gn:feature_code":"PPLL",
    "gn:name":"Trogacher",
    "gn:population":0,
    "gn:timezone":"Europe/Zurich",
    "iso:country":"CH",
    "name:deu_x_preferred":[
        "Trogacher"
    ],
    "wof:name":"Trogacher",
    "wof:placetype":"neighbourhood"
},
  "geometry": {"coordinates":[8.83355,47.38224],"type":"Point"}
}