{
  "type": "Feature",
  "properties": {
    "gn:admin1_code":"TG",
    "gn:admin2_code":"2015.0",
    "gn:admin3_code":"4946.0",
    "gn:asciiname":"Weerswilen",
    "gn:country_code":"CH",
    "gn:dem":592,
    "gn:elevation":"567.0",
    "gn:feature_class":"P",
    "gn:feature_code":"PPL",
    "gn:name":"Weerswilen",
    "gn:population":0,
    "gn:timezone":"Europe/Zurich",
    "iso:country":"CH",
    "wof:name":"Weerswilen",
    "wof:placetype":"neighbourhood"
},
  "geometry": {"coordinates":[9.13501,47.57632],"type":"Point"}
}