{
  "type": "Feature",
  "properties": {
    "gn:admin1_code":"TI",
    "gn:admin2_code":"2104.0",
    "gn:admin3_code":"5398.0",
    "gn:asciiname":"Piodaccia",
    "gn:country_code":"CH",
    "gn:dem":394,
    "gn:feature_class":"P",
    "gn:feature_code":"PPL",
    "gn:name":"Piodaccia",
    "gn:population":0,
    "gn:timezone":"Europe/Zurich",
    "iso:country":"CH",
    "name:ita_x_preferred":[
        "Piodaccia"
    ],
    "wof:name":"Piodaccia",
    "wof:placetype":"neighbourhood"
},
  "geometry": {"coordinates":[8.85704,46.14362],"type":"Point"}
}