{
  "type": "Feature",
  "properties": {
    "gn:admin1_code":"BL",
    "gn:admin2_code":"1305.0",
    "gn:admin3_code":"2889.0",
    "gn:asciiname":"Lauwilberg",
    "gn:country_code":"CH",
    "gn:dem":763,
    "gn:feature_class":"P",
    "gn:feature_code":"PPLL",
    "gn:name":"Lauwilberg",
    "gn:population":0,
    "gn:timezone":"Europe/Zurich",
    "iso:country":"CH",
    "name:deu_x_preferred":[
        "Lauwilberg"
    ],
    "wof:name":"Lauwilberg",
    "wof:placetype":"neighbourhood"
},
  "geometry": {"coordinates":[7.66883,47.38408],"type":"Point"}
}