{
  "type": "Feature",
  "properties": {
    "gn:country":"CH",
    "gn:fcode":"PPLL",
    "gn:population":9,
    "iso:country":"CH",
    "name:eng_x_preferred":[
        "Sch\u00f6rli"
    ],
    "name:eng_x_variant":[
        "D\u00fcbendorf / Sch\u00f6rli"
    ],
    "qs_pg:aaroncc":"CH",
    "qs_pg:gn_country":"CH",
    "qs_pg:gn_fcode":"PPLL",
    "qs_pg:gn_pop":9,
    "qs_pg:name":"D\u00fcbendorf / Sch\u00f6rli",
    "qs_pg:photos_9r":0,
    "qs_pg:photos_sr":0,
    "qs_pg:pop_sr":1,
    "qs_pg:qs_pg_placetype":"locality",
    "wof:lang_x_official":[
        "deu",
        "fra",
        "gsw",
        "ita"
    ],
    "wof:lang_x_spoken":[
        "deu",
        "fra",
        "gsw",
        "ita",
        "roh"
    ],
    "wof:name":"Sch\u00f6rli",
    "wof:placetype":"neighbourhood",
    "wof:population":9
},
  "geometry": {"coordinates":[8.63337,47.39586],"type":"Point"}
}