{
  "type": "Feature",
  "properties": {
    "gn:admin1_code":"ZH",
    "gn:admin2_code":"102.0",
    "gn:admin3_code":"37.0",
    "gn:asciiname":"Ziegelhuette",
    "gn:country_code":"CH",
    "gn:dem":377,
    "gn:feature_class":"P",
    "gn:feature_code":"PPLL",
    "gn:name":"Ziegelh\u00fctte",
    "gn:population":0,
    "gn:timezone":"Europe/Zurich",
    "iso:country":"CH",
    "name:deu_x_preferred":[
        "Ziegelh\u00fctte"
    ],
    "wof:name":"Ziegelhuette",
    "wof:placetype":"neighbourhood"
},
  "geometry": {"coordinates":[8.73718,47.59622],"type":"Point"}
}