{
  "type": "Feature",
  "properties": {
    "gn:admin1_code":"FR",
    "gn:admin2_code":"1002.0",
    "gn:admin3_code":"2097.0",
    "gn:asciiname":"Les Augustins",
    "gn:country_code":"CH",
    "gn:dem":665,
    "gn:feature_class":"P",
    "gn:feature_code":"PPL",
    "gn:name":"Les Augustins",
    "gn:population":0,
    "gn:timezone":"Europe/Zurich",
    "iso:country":"CH",
    "name:fra_x_preferred":[
        "Les Augustins"
    ],
    "wof:name":"Les Augustins",
    "wof:placetype":"locality"
},
  "geometry": {"coordinates":[6.83066,46.62197000000001],"type":"Point"}
}