{
  "type": "Feature",
  "properties": {
    "gn:admin1_code":"FR",
    "gn:admin2_code":"1003.0",
    "gn:admin3_code":"2124.0",
    "gn:asciiname":"Bouleyres",
    "gn:country_code":"CH",
    "gn:dem":691,
    "gn:feature_class":"P",
    "gn:feature_code":"PPL",
    "gn:name":"Bouleyres",
    "gn:population":0,
    "gn:timezone":"Europe/Zurich",
    "iso:country":"CH",
    "name:fra_x_preferred":[
        "Bouleyres"
    ],
    "wof:name":"Bouleyres",
    "wof:placetype":"neighbourhood"
},
  "geometry": {"coordinates":[7.09372,46.60292000000001],"type":"Point"}
}