{
  "type": "Feature",
  "properties": {
    "gn:gn_country":"CH",
    "gn:gn_fcode":"PPLX",
    "gn:gn_pop":25,
    "gn:population":25,
    "iso:country":"CH",
    "name:unk_x_variant":[
        "Wieshof"
    ],
    "qs_pg:aaroncc":"CH",
    "qs_pg:gn_country":"CH",
    "qs_pg:gn_fcode":"PPLX",
    "qs_pg:gn_pop":25,
    "qs_pg:name":"W\u00fclflingen (Kreis 6) / Wieshof",
    "qs_pg:photos_9r":0,
    "qs_pg:photos_sr":0,
    "qs_pg:pop_sr":1,
    "qs_pg:qs_pg_placetype":"neighbourhood",
    "wof:name":"W\u00fclflingen (Kreis 6) / Wieshof",
    "wof:placetype":"neighbourhood",
    "wof:population":25
},
  "geometry": {"coordinates":[8.67774,47.50383],"type":"Point"}
}