{
  "type": "Feature",
  "properties": {
    "gn:admin1_code":"BE",
    "gn:admin2_code":"246.0",
    "gn:admin3_code":"866.0",
    "gn:asciiname":"Saedel",
    "gn:country_code":"CH",
    "gn:dem":783,
    "gn:feature_class":"P",
    "gn:feature_code":"PPL",
    "gn:name":"S\u00e4del",
    "gn:population":0,
    "gn:timezone":"Europe/Zurich",
    "iso:country":"CH",
    "wof:name":"Saedel",
    "wof:placetype":"neighbourhood"
},
  "geometry": {"coordinates":[7.53645,46.84196],"type":"Point"}
}