{
  "type": "Feature",
  "properties": {
    "gn:admin1_code":"TG",
    "gn:admin2_code":"2015.0",
    "gn:admin3_code":"4941.0",
    "gn:asciiname":"Rossrueti",
    "gn:country_code":"CH",
    "gn:dem":498,
    "gn:feature_class":"P",
    "gn:feature_code":"PPLL",
    "gn:name":"Rossr\u00fcti",
    "gn:population":0,
    "gn:timezone":"Europe/Zurich",
    "iso:country":"CH",
    "name:deu_x_preferred":[
        "Rossr\u00fcti"
    ],
    "wof:lang_x_official":[
        "deu",
        "fra",
        "gsw",
        "ita"
    ],
    "wof:lang_x_spoken":[
        "deu",
        "fra",
        "gsw",
        "ita",
        "roh"
    ],
    "wof:name":"Rossrueti",
    "wof:placetype":"neighbourhood"
},
  "geometry": {"coordinates":[9.09315,47.59386],"type":"Point"}
}