{
  "type": "Feature",
  "properties": {
    "gn:gn_country":"CH",
    "gn:gn_fcode":"PPL",
    "gn:gn_pop":469,
    "gn:population":469,
    "iso:country":"CH",
    "name:alb_x_preferred":[
        "Cama"
    ],
    "name:baq_x_preferred":[
        "Cama"
    ],
    "name:cat_x_preferred":[
        "Cama"
    ],
    "name:chi_x_preferred":[
        "\u5361\u99ac"
    ],
    "name:dut_x_preferred":[
        "Cama"
    ],
    "name:eng_x_preferred":[
        "Cama"
    ],
    "name:epo_x_preferred":[
        "Cama"
    ],
    "name:fre_x_preferred":[
        "Cama"
    ],
    "name:ger_x_preferred":[
        "Cama"
    ],
    "name:hun_x_preferred":[
        "Cama"
    ],
    "name:ind_x_preferred":[
        "Cama"
    ],
    "name:ita_x_preferred":[
        "Cama"
    ],
    "name:kaz_x_preferred":[
        "\u041a\u0430\u043c\u0430"
    ],
    "name:lmo_x_preferred":[
        "Cama"
    ],
    "name:may_x_preferred":[
        "Cama"
    ],
    "name:nno_x_preferred":[
        "Cama i Sveits"
    ],
    "name:oci_x_preferred":[
        "Cama"
    ],
    "name:pms_x_preferred":[
        "Cama"
    ],
    "name:por_x_preferred":[
        "Cama"
    ],
    "name:roh_x_preferred":[
        "Cama"
    ],
    "name:rus_x_preferred":[
        "\u041a\u0430\u043c\u0430"
    ],
    "name:spa_x_preferred":[
        "Cama"
    ],
    "name:swe_x_preferred":[
        "Cama"
    ],
    "name:uzb_x_preferred":[
        "Cama"
    ],
    "name:vol_x_preferred":[
        "Cama"
    ],
    "name:war_x_preferred":[
        "Cama"
    ],
    "qs_pg:aaroncc":"CH",
    "qs_pg:gn_country":"CH",
    "qs_pg:gn_fcode":"PPL",
    "qs_pg:gn_pop":469,
    "qs_pg:name":"Cama",
    "qs_pg:name_adm0":"Schweiz",
    "qs_pg:name_adm1":"Kanton Graub\u00fcnden",
    "qs_pg:photos":50,
    "qs_pg:photos_1k":10,
    "qs_pg:photos_9k":1,
    "qs_pg:photos_9r":2,
    "qs_pg:photos_all":50,
    "qs_pg:photos_sr":2,
    "qs_pg:pop_sr":2,
    "qs_pg:qs_pg_placetype":"locality",
    "qs_pg:qs_pg_placetype_gp":"Town",
    "qs_pg:woe_adm0":23424957,
    "woe:adm0_id":23424957,
    "woe:name_adm0":"Schweiz",
    "woe:name_adm1":"Kanton Graub\u00fcnden",
    "woe:placetype":"Town",
    "wof:name":"Cama",
    "wof:placetype":"locality",
    "wof:population":469
},
  "geometry": {"coordinates":[9.16957,46.273],"type":"Point"}
}