{
  "type": "Feature",
  "properties": {
    "gn:admin1_code":"TI",
    "gn:admin2_code":"2108.0",
    "gn:admin3_code":"5323.0",
    "gn:asciiname":"Sambuco di Fuori",
    "gn:cc2":"CH",
    "gn:country_code":"CH",
    "gn:dem":1465,
    "gn:feature_class":"P",
    "gn:feature_code":"PPL",
    "gn:name":"Sambuco di Fuori",
    "gn:population":0,
    "gn:timezone":"Europe/Zurich",
    "iso:country":"CH",
    "name:und_x_variant":[
        "Sambuco",
        "Sambucco",
        "Sambuco di Fuori"
    ],
    "wof:lang_x_official":[
        "deu",
        "fra",
        "gsw",
        "ita"
    ],
    "wof:lang_x_spoken":[
        "deu",
        "fra",
        "gsw",
        "ita",
        "roh"
    ],
    "wof:name":"Sambuco di Fuori",
    "wof:placetype":"neighbourhood"
},
  "geometry": {"coordinates":[8.65,46.46667],"type":"Point"}
}