{
  "type": "Feature",
  "properties": {
    "gn:admin1_code":"TG",
    "gn:admin2_code":"2013.0",
    "gn:admin3_code":"4846.0",
    "gn:asciiname":"Fischbach",
    "gn:country_code":"CH",
    "gn:dem":587,
    "gn:feature_class":"P",
    "gn:feature_code":"PPLL",
    "gn:name":"Fischbach",
    "gn:population":0,
    "gn:timezone":"Europe/Zurich",
    "iso:country":"CH",
    "name:deu_x_preferred":[
        "Fischbach"
    ],
    "wof:name":"Fischbach",
    "wof:placetype":"neighbourhood"
},
  "geometry": {"coordinates":[9.05571,47.63694],"type":"Point"}
}