{
  "type": "Feature",
  "properties": {
    "gn:admin1_code":"TG",
    "gn:admin2_code":"2013.0",
    "gn:admin3_code":"4846.0",
    "gn:asciiname":"Fischbach",
    "gn:country_code":"CH",
    "gn:dem":587,
    "gn:feature_class":"P",
    "gn:feature_code":"PPLL",
    "gn:name":"Fischbach",
    "gn:population":0,
    "gn:timezone":"Europe/Zurich",
    "iso:country":"CH",
    "name:ceb_x_preferred":[
        "Fischbach"
    ],
    "name:deu_x_preferred":[
        "Fischbach"
    ],
    "name:epo_x_preferred":[
        "Fischbach"
    ],
    "name:eus_x_preferred":[
        "Fischbach"
    ],
    "name:fra_x_preferred":[
        "Fischbach"
    ],
    "name:ita_x_preferred":[
        "Fischbach"
    ],
    "name:nld_x_preferred":[
        "Fischbach"
    ],
    "name:pol_x_preferred":[
        "Fischbach"
    ],
    "name:rus_x_preferred":[
        "\u0424\u0438\u0448\u0431\u0430\u0445"
    ],
    "name:slk_x_preferred":[
        "Fischbach"
    ],
    "name:srp_x_preferred":[
        "\u0424\u0438\u0448\u0431\u0430\u0445"
    ],
    "name:swe_x_preferred":[
        "Fischbach"
    ],
    "name:vol_x_preferred":[
        "Fischbach"
    ],
    "name:zho_x_preferred":[
        "\u83f2\u65bd\u5df4\u8d6b"
    ],
    "wof:name":"Fischbach",
    "wof:placetype":"neighbourhood"
},
  "geometry": {"coordinates":[9.05571,47.63694],"type":"Point"}
}