{
  "type": "Feature",
  "properties": {
    "gn:admin1_code":"FR",
    "gn:admin2_code":"1004.0",
    "gn:admin3_code":"2236.0",
    "gn:asciiname":"Estavayer-le-Gibloux",
    "gn:country_code":"CH",
    "gn:dem":674,
    "gn:elevation":"700.0",
    "gn:feature_class":"P",
    "gn:feature_code":"PPL",
    "gn:name":"Estavayer-le-Gibloux",
    "gn:population":0,
    "gn:timezone":"Europe/Zurich",
    "iso:country":"CH",
    "wof:name":"Estavayer-le-Gibloux",
    "wof:placetype":"locality"
},
  "geometry": {"coordinates":[7.0263,46.72414000000001],"type":"Point"}
}