{
  "type": "Feature",
  "properties": {
    "gn:admin1_code":"VD",
    "gn:admin2_code":"2224.0",
    "gn:admin3_code":"5872.0",
    "gn:asciiname":"Le Planoz",
    "gn:country_code":"CH",
    "gn:dem":1034,
    "gn:feature_class":"P",
    "gn:feature_code":"PPL",
    "gn:name":"Le Planoz",
    "gn:population":0,
    "gn:timezone":"Europe/Zurich",
    "iso:country":"CH",
    "name:fra_x_preferred":[
        "Le Planoz"
    ],
    "wof:name":"Le Planoz",
    "wof:placetype":"neighbourhood"
},
  "geometry": {"coordinates":[6.20355,46.58716],"type":"Point"}
}