{
  "type": "Feature",
  "properties": {
    "gn:admin1_code":"FR",
    "gn:admin2_code":"1007.0",
    "gn:admin3_code":"2338.0",
    "gn:asciiname":"Montborget",
    "gn:country_code":"CH",
    "gn:dem":894,
    "gn:feature_class":"P",
    "gn:feature_code":"PPL",
    "gn:name":"Montborget",
    "gn:population":0,
    "gn:timezone":"Europe/Zurich",
    "iso:country":"CH",
    "name:deu_x_preferred":[
        "Montborget"
    ],
    "name:fra_x_preferred":[
        "Montborget"
    ],
    "wof:name":"Montborget",
    "wof:placetype":"neighbourhood"
},
  "geometry": {"coordinates":[6.9337,46.6119],"type":"Point"}
}