{
  "type": "Feature",
  "properties": {
    "gn:admin1_code":"AG",
    "gn:admin2_code":"1905.0",
    "gn:admin3_code":"4135.0",
    "gn:asciiname":"Schwarzenberg",
    "gn:country_code":"CH",
    "gn:dem":616,
    "gn:feature_class":"P",
    "gn:feature_code":"PPLL",
    "gn:name":"Schwarzenberg",
    "gn:population":0,
    "gn:timezone":"Europe/Zurich",
    "iso:country":"CH",
    "name:deu_x_preferred":[
        "Schwarzenberg"
    ],
    "wof:name":"Schwarzenberg",
    "wof:placetype":"neighbourhood"
},
  "geometry": {"coordinates":[8.13733,47.25606],"type":"Point"}
}