{
  "type": "Feature",
  "properties": {
    "gn:admin1_code":"AG",
    "gn:admin2_code":"1905.0",
    "gn:admin3_code":"4135.0",
    "gn:asciiname":"Schwarzenberg",
    "gn:country_code":"CH",
    "gn:dem":616,
    "gn:feature_class":"P",
    "gn:feature_code":"PPLL",
    "gn:name":"Schwarzenberg",
    "gn:population":0,
    "gn:timezone":"Europe/Zurich",
    "iso:country":"CH",
    "name:als_x_preferred":[
        "Schwarzenberg"
    ],
    "name:ceb_x_preferred":[
        "Schwarzenberg"
    ],
    "name:ces_x_preferred":[
        "Schwarzenberg"
    ],
    "name:deu_x_preferred":[
        "Schwarzenberg"
    ],
    "name:epo_x_preferred":[
        "Schwarzenberg"
    ],
    "name:eus_x_preferred":[
        "Schwarzenberg"
    ],
    "name:fra_x_preferred":[
        "Schwarzenberg"
    ],
    "name:hun_x_preferred":[
        "Schwarzenberg"
    ],
    "name:ita_x_preferred":[
        "Schwarzenberg"
    ],
    "name:jpn_x_preferred":[
        "\u30b7\u30e5\u30f4\u30a1\u30eb\u30c4\u30a7\u30f3\u30d9\u30eb\u30af"
    ],
    "name:kor_x_preferred":[
        "\uc288\ubc14\ub974\uccb8\ubca0\ub974\ud06c"
    ],
    "name:mkd_x_preferred":[
        "\u0428\u0432\u0430\u0440\u0446\u0435\u043d\u0431\u0435\u0440\u0433"
    ],
    "name:nld_x_preferred":[
        "Schwarzenberg"
    ],
    "name:pol_x_preferred":[
        "Schwarzenberg"
    ],
    "name:por_x_preferred":[
        "Schwarzenberg"
    ],
    "name:rus_x_preferred":[
        "\u0428\u0432\u0430\u0440\u0446\u0435\u043d\u0431\u0435\u0440\u0433"
    ],
    "name:swe_x_preferred":[
        "Schwarzenberg"
    ],
    "name:ukr_x_preferred":[
        "\u0428\u0432\u0430\u0440\u0446\u0435\u043d\u0431\u0435\u0440\u0433"
    ],
    "name:vol_x_preferred":[
        "Schwarzenberg"
    ],
    "wof:name":"Schwarzenberg",
    "wof:placetype":"neighbourhood"
},
  "geometry": {"coordinates":[8.13733,47.25606],"type":"Point"}
}