{
  "type": "Feature",
  "properties": {
    "gn:gn_country":"CH",
    "gn:gn_fcode":"ADM3",
    "gn:gn_pop":584,
    "gn:population":583,
    "iso:country":"CH",
    "name:alb_x_preferred":[
        "Anwil"
    ],
    "name:baq_x_preferred":[
        "Anwil"
    ],
    "name:cat_x_preferred":[
        "Anwil"
    ],
    "name:chi_x_preferred":[
        "\u5b89\u7dad\u723e"
    ],
    "name:chv_x_preferred":[
        "\u0410\u043d\u0432\u0438\u043b\u044c"
    ],
    "name:dut_x_preferred":[
        "Anwil"
    ],
    "name:eng_x_preferred":[
        "Anwil"
    ],
    "name:epo_x_preferred":[
        "Anwil"
    ],
    "name:fre_x_preferred":[
        "Anwil"
    ],
    "name:ger_x_preferred":[
        "Anwil"
    ],
    "name:gsw_x_preferred":[
        "Ammel"
    ],
    "name:hun_x_preferred":[
        "Anwil"
    ],
    "name:ita_x_preferred":[
        "Anwil"
    ],
    "name:kaz_x_preferred":[
        "\u0410\u043d\u0432\u0438\u043b\u044c"
    ],
    "name:lmo_x_preferred":[
        "Anwil"
    ],
    "name:may_x_preferred":[
        "Anwil"
    ],
    "name:nno_x_preferred":[
        "Anwil"
    ],
    "name:oci_x_preferred":[
        "Anwil"
    ],
    "name:rus_x_preferred":[
        "\u0410\u043d\u0432\u0438\u043b\u044c"
    ],
    "name:spa_x_preferred":[
        "Anwil"
    ],
    "name:swe_x_preferred":[
        "Anwil"
    ],
    "name:uzb_x_preferred":[
        "Anwil"
    ],
    "name:vol_x_preferred":[
        "Anwil"
    ],
    "name:war_x_preferred":[
        "Anwil"
    ],
    "qs_pg:aaroncc":"CH",
    "qs_pg:gn_country":"CH",
    "qs_pg:gn_fcode":"ADM3",
    "qs_pg:gn_pop":584,
    "qs_pg:name":"Anwil",
    "qs_pg:name_adm0":"Schweiz",
    "qs_pg:name_adm1":"Kanton Basel-Land",
    "qs_pg:photos":65,
    "qs_pg:photos_1k":13,
    "qs_pg:photos_9k":1,
    "qs_pg:photos_9r":2,
    "qs_pg:photos_all":65,
    "qs_pg:photos_sr":2,
    "qs_pg:pop_sr":2,
    "qs_pg:qs_pg_placetype":"locality",
    "qs_pg:qs_pg_placetype_gp":"Town",
    "qs_pg:woe_adm0":23424957,
    "woe:adm0_id":23424957,
    "woe:name_adm0":"Schweiz",
    "woe:name_adm1":"Kanton Basel-Land",
    "woe:placetype":"Town",
    "wof:name":"Anwil",
    "wof:placetype":"locality",
    "wof:population":583
},
  "geometry": {"coordinates":[7.94194,47.45298],"type":"Point"}
}