{
  "type": "Feature",
  "properties": {
    "gn:admin1_code":"FR",
    "gn:admin2_code":"1003.0",
    "gn:admin3_code":"2152.0",
    "gn:asciiname":"Treyfayes",
    "gn:country_code":"CH",
    "gn:dem":856,
    "gn:feature_class":"P",
    "gn:feature_code":"PPL",
    "gn:name":"Treyfayes",
    "gn:population":0,
    "gn:timezone":"Europe/Zurich",
    "iso:country":"CH",
    "wof:name":"Treyfayes",
    "wof:placetype":"locality"
},
  "geometry": {"coordinates":[6.95327,46.65406],"type":"Point"}
}