{
  "type": "Feature",
  "properties": {
    "gn:admin1_code":"BE",
    "gn:admin2_code":"245.0",
    "gn:admin3_code":"402.0",
    "gn:asciiname":"Tannwald",
    "gn:country_code":"CH",
    "gn:dem":492,
    "gn:feature_class":"P",
    "gn:feature_code":"PPLL",
    "gn:name":"Tannwald",
    "gn:population":0,
    "gn:timezone":"Europe/Zurich",
    "iso:country":"CH",
    "name:deu_x_preferred":[
        "Tannwald"
    ],
    "wof:name":"Tannwald",
    "wof:placetype":"neighbourhood"
},
  "geometry": {"coordinates":[7.62375,47.12224000000001],"type":"Point"}
}