{
  "type": "Feature",
  "properties": {
    "gn:admin1_code":"GR",
    "gn:admin2_code":"1844.0",
    "gn:admin3_code":"3734.0",
    "gn:asciiname":"Digg",
    "gn:country_code":"CH",
    "gn:dem":863,
    "gn:feature_class":"P",
    "gn:feature_code":"PPL",
    "gn:name":"Digg",
    "gn:population":0,
    "gn:timezone":"Europe/Zurich",
    "iso:country":"CH",
    "name:roh_x_preferred":[
        "Digg"
    ],
    "wof:name":"Digg",
    "wof:placetype":"locality"
},
  "geometry": {"coordinates":[9.35446,46.82404],"type":"Point"}
}