{
  "type": "Feature",
  "properties": {
    "gn:gn_country":"CH",
    "gn:gn_fcode":"PPL",
    "gn:gn_pop":0,
    "iso:country":"CH",
    "name:ast_x_preferred":[
        "Neggio"
    ],
    "name:cat_x_preferred":[
        "Neggio"
    ],
    "name:deu_x_preferred":[
        "Neggio"
    ],
    "name:eng_x_preferred":[
        "Neggio"
    ],
    "name:epo_x_preferred":[
        "Neggio"
    ],
    "name:eus_x_preferred":[
        "Neggio"
    ],
    "name:fra_x_preferred":[
        "Neggio"
    ],
    "name:gsw_x_preferred":[
        "Neggio"
    ],
    "name:hun_x_preferred":[
        "Neggio"
    ],
    "name:ita_x_preferred":[
        "Neggio"
    ],
    "name:lmo_x_preferred":[
        "Negg"
    ],
    "name:msa_x_preferred":[
        "Neggio"
    ],
    "name:nld_x_preferred":[
        "Neggio"
    ],
    "name:nno_x_preferred":[
        "Neggio"
    ],
    "name:oci_x_preferred":[
        "Neggio"
    ],
    "name:por_x_preferred":[
        "Neggio"
    ],
    "name:roh_x_preferred":[
        "Neggio"
    ],
    "name:spa_x_preferred":[
        "Neggio"
    ],
    "name:sqi_x_preferred":[
        "Neggio"
    ],
    "name:vie_x_preferred":[
        "Neggio"
    ],
    "name:vol_x_preferred":[
        "Neggio"
    ],
    "name:war_x_preferred":[
        "Neggio"
    ],
    "name:zho_x_preferred":[
        "\u5167\u7126"
    ],
    "qs_pg:aaroncc":"CH",
    "qs_pg:gn_country":"CH",
    "qs_pg:gn_fcode":"PPL",
    "qs_pg:gn_pop":0,
    "qs_pg:name":"Neggio",
    "qs_pg:name_adm0":"Schweiz",
    "qs_pg:name_adm1":"Cantone Ticino",
    "qs_pg:photos":44,
    "qs_pg:photos_1k":9,
    "qs_pg:photos_9k":1,
    "qs_pg:photos_9r":2,
    "qs_pg:photos_all":44,
    "qs_pg:photos_sr":2,
    "qs_pg:pop_sr":0,
    "qs_pg:qs_pg_placetype":"locality",
    "qs_pg:qs_pg_placetype_gp":"Town",
    "qs_pg:woe_adm0":23424957,
    "woe:adm0_id":23424957,
    "woe:name_adm0":"Schweiz",
    "woe:name_adm1":"Cantone Ticino",
    "woe:placetype":"Town",
    "wof:name":"Neggio",
    "wof:placetype":"locality"
},
  "geometry": {"coordinates":[8.8797,45.98709],"type":"Point"}
}