{
  "type": "Feature",
  "properties": {
    "gn:admin1_code":"TG",
    "gn:admin2_code":"2012.0",
    "gn:admin3_code":"4546.0",
    "gn:asciiname":"Schneckenacker",
    "gn:country_code":"CH",
    "gn:dem":436,
    "gn:feature_class":"P",
    "gn:feature_code":"PPLL",
    "gn:name":"Schneckenacker",
    "gn:population":0,
    "gn:timezone":"Europe/Zurich",
    "iso:country":"CH",
    "name:deu_x_preferred":[
        "Schneckenacker"
    ],
    "wof:name":"Schneckenacker",
    "wof:placetype":"locality"
},
  "geometry": {"coordinates":[8.68844,47.67147],"type":"Point"}
}