{
  "type": "Feature",
  "properties": {
    "gn:gn_country":"CH",
    "gn:gn_fcode":"PPL",
    "gn:gn_pop":649,
    "gn:population":649,
    "iso:country":"CH",
    "name:ara_x_preferred":[
        "\u0644\u0648\u0647\u0646"
    ],
    "name:cat_x_preferred":[
        "Lohn"
    ],
    "name:deu_x_preferred":[
        "Lohn SH"
    ],
    "name:eng_x_preferred":[
        "Lohn"
    ],
    "name:epo_x_preferred":[
        "Lohn SH"
    ],
    "name:eus_x_preferred":[
        "Lohn"
    ],
    "name:fra_x_preferred":[
        "Lohn"
    ],
    "name:gsw_x_preferred":[
        "Loo SH"
    ],
    "name:hun_x_preferred":[
        "Lohn"
    ],
    "name:ita_x_preferred":[
        "Lohn"
    ],
    "name:kaz_x_preferred":[
        "\u041b\u043e\u043d"
    ],
    "name:lmo_x_preferred":[
        "Lohn"
    ],
    "name:nld_x_preferred":[
        "Lohn"
    ],
    "name:nno_x_preferred":[
        "Lohn"
    ],
    "name:oci_x_preferred":[
        "Lohn"
    ],
    "name:pms_x_preferred":[
        "Lohn"
    ],
    "name:pnb_x_preferred":[
        "\u0644\u0648\u06c1\u0646"
    ],
    "name:por_x_preferred":[
        "Lohn"
    ],
    "name:rus_x_preferred":[
        "\u041b\u043e\u043d"
    ],
    "name:spa_x_preferred":[
        "Lohn"
    ],
    "name:sqi_x_preferred":[
        "Lohn"
    ],
    "name:swe_x_preferred":[
        "Lohn"
    ],
    "name:vol_x_preferred":[
        "Lohn"
    ],
    "name:war_x_preferred":[
        "Lohn"
    ],
    "qs_pg:aaroncc":"CH",
    "qs_pg:gn_country":"CH",
    "qs_pg:gn_fcode":"PPL",
    "qs_pg:gn_pop":649,
    "qs_pg:name":"Lohner",
    "qs_pg:name_adm0":"Deutschland",
    "qs_pg:name_adm1":"Baden-W\u00fcrttemberg",
    "qs_pg:photos_9r":0,
    "qs_pg:photos_sr":0,
    "qs_pg:pop_sr":2,
    "qs_pg:qs_pg_placetype":"locality",
    "qs_pg:qs_pg_placetype_gp":"Town",
    "qs_pg:woe_adm0":23424829,
    "woe:adm0_id":23424829,
    "woe:name_adm0":"Deutschland",
    "woe:name_adm1":"Baden-W\u00fcrttemberg",
    "woe:placetype":"Town",
    "wof:name":"Lohner",
    "wof:placetype":"locality",
    "wof:population":649
},
  "geometry": {"coordinates":[8.66847,47.75508],"type":"Point"}
}