{
  "type": "Feature",
  "properties": {
    "gn:admin1_code":"TI",
    "gn:admin2_code":"2102.0",
    "gn:admin3_code":"5049.0",
    "gn:asciiname":"Ponte Semina",
    "gn:country_code":"CH",
    "gn:dem":1191,
    "gn:feature_class":"P",
    "gn:feature_code":"PPL",
    "gn:name":"Ponte Semina",
    "gn:population":0,
    "gn:timezone":"Europe/Zurich",
    "iso:country":"CH",
    "name:ita_x_preferred":[
        "Ponte Semina"
    ],
    "wof:name":"Ponte Semina",
    "wof:placetype":"locality"
},
  "geometry": {"coordinates":[8.93794,46.55215],"type":"Point"}
}