{
  "type": "Feature",
  "properties": {
    "gn:admin1_code":"TI",
    "gn:admin2_code":"2102.0",
    "gn:admin3_code":"5050.0",
    "gn:asciiname":"Alpe Pulgabio",
    "gn:country_code":"CH",
    "gn:dem":1606,
    "gn:feature_class":"P",
    "gn:feature_code":"PPL",
    "gn:name":"Alpe Pulgabio",
    "gn:population":0,
    "gn:timezone":"Europe/Zurich",
    "iso:country":"CH",
    "wof:name":"Alpe Pulgabio",
    "wof:placetype":"neighbourhood"
},
  "geometry": {"coordinates":[9.05056,46.40532],"type":"Point"}
}