{
  "type": "Feature",
  "properties": {
    "gn:admin1_code":"SG",
    "gn:admin2_code":"1726.0",
    "gn:admin3_code":"3315.0",
    "gn:asciiname":"Fiderschebode",
    "gn:country_code":"CH",
    "gn:dem":1639,
    "gn:feature_class":"P",
    "gn:feature_code":"PPLL",
    "gn:name":"Fiderschebode",
    "gn:population":0,
    "gn:timezone":"Europe/Zurich",
    "iso:country":"CH",
    "name:deu_x_preferred":[
        "Fiderschebode"
    ],
    "wof:name":"Fiderschebode",
    "wof:placetype":"neighbourhood"
},
  "geometry": {"coordinates":[9.09259,47.16376],"type":"Point"}
}