{
  "type": "Feature",
  "properties": {
    "gn:gn_country":"CH",
    "gn:gn_fcode":"PPL",
    "gn:gn_pop":0,
    "iso:country":"CH",
    "name:als_x_preferred":[
        "Rengg"
    ],
    "name:deu_x_preferred":[
        "Sengg"
    ],
    "name:deu_x_variant":[
        "Rengg"
    ],
    "qs_pg:aaroncc":"CH",
    "qs_pg:gn_country":"CH",
    "qs_pg:gn_fcode":"PPL",
    "qs_pg:gn_pop":0,
    "qs_pg:name":"Rengg",
    "qs_pg:name_adm0":"Schweiz",
    "qs_pg:name_adm1":"Kanton Obwalden",
    "qs_pg:photos":22,
    "qs_pg:photos_1k":4,
    "qs_pg:photos_9k":1,
    "qs_pg:photos_9r":1,
    "qs_pg:photos_all":22,
    "qs_pg:photos_sr":1,
    "qs_pg:pop_sr":0,
    "qs_pg:qs_pg_placetype":"locality",
    "qs_pg:qs_pg_placetype_gp":"Town",
    "qs_pg:woe_adm0":23424957,
    "woe:adm0_id":23424957,
    "woe:name_adm0":"Schweiz",
    "woe:name_adm1":"Kanton Obwalden",
    "woe:placetype":"Town",
    "wof:name":"Rengg",
    "wof:placetype":"neighbourhood"
},
  "geometry": {"coordinates":[7.95096,46.70441],"type":"Point"}
}