{
  "type": "Feature",
  "properties": {
    "gn:admin1_code":"BE",
    "gn:admin2_code":"250.0",
    "gn:admin3_code":"784.0",
    "gn:asciiname":"Nessenthal",
    "gn:country_code":"CH",
    "gn:dem":932,
    "gn:feature_class":"P",
    "gn:feature_code":"PPL",
    "gn:name":"Nessenthal",
    "gn:population":0,
    "gn:timezone":"Europe/Zurich",
    "iso:country":"CH",
    "name:und_x_variant":[
        "Nessental",
        "Nessenthal"
    ],
    "wof:name":"Nessenthal",
    "wof:placetype":"neighbourhood"
},
  "geometry": {"coordinates":[8.29682,46.72044],"type":"Point"}
}