{
  "type": "Feature",
  "properties": {
    "gn:admin1_code":"BL",
    "gn:admin2_code":"1304.0",
    "gn:admin3_code":"2845.0",
    "gn:asciiname":"Diepflingen",
    "gn:country_code":"CH",
    "gn:dem":432,
    "gn:feature_class":"P",
    "gn:feature_code":"PPL",
    "gn:name":"Diepflingen",
    "gn:population":0,
    "gn:timezone":"Europe/Zurich",
    "iso:country":"CH",
    "wof:name":"Diepflingen",
    "wof:placetype":"locality"
},
  "geometry": {"coordinates":[7.8364,47.44443],"type":"Point"}
}