{
  "type": "Feature",
  "properties": {
    "gn:country":"CH",
    "gn:fcode":"PPLX",
    "gn:population":64,
    "iso:country":"CH",
    "name:eng_x_preferred":[
        "In der Farb"
    ],
    "name:eng_x_variant":[
        "Oetwil / In der Farb"
    ],
    "qs_pg:aaroncc":"CH",
    "qs_pg:gn_country":"CH",
    "qs_pg:gn_fcode":"PPLX",
    "qs_pg:gn_pop":64,
    "qs_pg:name":"Oetwil / In der Farb",
    "qs_pg:photos_9r":0,
    "qs_pg:photos_sr":0,
    "qs_pg:pop_sr":1,
    "qs_pg:qs_pg_placetype":"neighbourhood",
    "wof:name":"In der Farb",
    "wof:placetype":"neighbourhood",
    "wof:population":64
},
  "geometry": {"coordinates":[8.72315,47.26643],"type":"Point"}
}