{
  "type": "Feature",
  "properties": {
    "gn:admin1_code":"ZH",
    "gn:admin2_code":"103.0",
    "gn:admin3_code":"61.0",
    "gn:asciiname":"Bahnhof",
    "gn:country_code":"CH",
    "gn:dem":401,
    "gn:feature_class":"P",
    "gn:feature_code":"PPLL",
    "gn:name":"Bahnhof",
    "gn:population":6,
    "gn:timezone":"Europe/Zurich",
    "iso:country":"CH",
    "name:ara_x_preferred":[
        "\u0628\u0627\u0647\u0646\u0647\u0648\u0641"
    ],
    "name:deu_x_preferred":[
        "Bahnhof"
    ],
    "name:swe_x_preferred":[
        "Bahnhof"
    ],
    "wof:name":"Bahnhof",
    "wof:placetype":"neighbourhood",
    "wof:population":6
},
  "geometry": {"coordinates":[8.51268,47.58235],"type":"Point"}
}