{
  "type": "Feature",
  "properties": {
    "gn:gn_country":"CH",
    "gn:gn_fcode":"PPLX",
    "gn:gn_pop":57,
    "gn:population":57,
    "iso:country":"CH",
    "name:eng_x_preferred":[
        "Horn"
    ],
    "name:eng_x_variant":[
        "Feldmeilen / Horn"
    ],
    "name:unk_x_variant":[
        "Horn"
    ],
    "qs_pg:aaroncc":"CH",
    "qs_pg:gn_country":"CH",
    "qs_pg:gn_fcode":"PPLX",
    "qs_pg:gn_pop":57,
    "qs_pg:name":"Feldmeilen / Horn",
    "qs_pg:photos_9r":0,
    "qs_pg:photos_sr":0,
    "qs_pg:pop_sr":1,
    "qs_pg:qs_pg_placetype":"neighbourhood",
    "wof:name":"Horn",
    "wof:placetype":"neighbourhood",
    "wof:population":57
},
  "geometry": {"coordinates":[8.62997,47.27177],"type":"Point"}
}