{
  "type": "Feature",
  "properties": {
    "gn:country":"CH",
    "gn:fcode":"PPLX",
    "gn:population":57,
    "iso:country":"CH",
    "name:bos_x_preferred":[
        "Horn"
    ],
    "name:bre_x_preferred":[
        "Horn"
    ],
    "name:bul_x_preferred":[
        "\u0425\u043e\u0440\u043d"
    ],
    "name:ceb_x_preferred":[
        "Horn"
    ],
    "name:ces_x_preferred":[
        "Horn"
    ],
    "name:dan_x_preferred":[
        "Horn"
    ],
    "name:deu_x_preferred":[
        "Horn"
    ],
    "name:ell_x_preferred":[
        "\u03a7\u03bf\u03c1\u03bd"
    ],
    "name:eng_x_preferred":[
        "Horn"
    ],
    "name:eng_x_variant":[
        "Feldmeilen / Horn"
    ],
    "name:epo_x_preferred":[
        "Horn"
    ],
    "name:eus_x_preferred":[
        "Horn"
    ],
    "name:fas_x_preferred":[
        "\u0634\u0627\u062e"
    ],
    "name:fin_x_preferred":[
        "Horn"
    ],
    "name:fra_x_preferred":[
        "Horn"
    ],
    "name:heb_x_preferred":[
        "\u05d4\u05d5\u05e8\u05df"
    ],
    "name:isl_x_preferred":[
        "Horn"
    ],
    "name:ita_x_preferred":[
        "Horn"
    ],
    "name:jpn_x_preferred":[
        "\u30db\u30fc\u30f3"
    ],
    "name:lit_x_preferred":[
        "Hornas"
    ],
    "name:nld_x_preferred":[
        "Horn"
    ],
    "name:nor_x_preferred":[
        "Horn"
    ],
    "name:pol_x_preferred":[
        "Horn"
    ],
    "name:por_x_preferred":[
        "Horn"
    ],
    "name:rus_x_preferred":[
        "\u0425\u043e\u0440\u043d"
    ],
    "name:sco_x_preferred":[
        "Horn"
    ],
    "name:slk_x_preferred":[
        "Horn"
    ],
    "name:srp_x_preferred":[
        "\u0425\u043e\u0440\u043d"
    ],
    "name:swe_x_preferred":[
        "Horn"
    ],
    "name:vol_x_preferred":[
        "Horn"
    ],
    "qs_pg:aaroncc":"CH",
    "qs_pg:gn_country":"CH",
    "qs_pg:gn_fcode":"PPLX",
    "qs_pg:gn_pop":57,
    "qs_pg:name":"Feldmeilen / Horn",
    "qs_pg:photos_9r":0,
    "qs_pg:photos_sr":0,
    "qs_pg:pop_sr":1,
    "qs_pg:qs_pg_placetype":"neighbourhood",
    "wof:name":"Horn",
    "wof:placetype":"neighbourhood",
    "wof:population":57
},
  "geometry": {"coordinates":[8.62997,47.27177],"type":"Point"}
}