{
  "type": "Feature",
  "properties": {
    "gn:admin1_code":"ZH",
    "gn:admin2_code":"103.0",
    "gn:admin3_code":"55.0",
    "gn:asciiname":"Dachsberg",
    "gn:country_code":"CH",
    "gn:dem":391,
    "gn:feature_class":"P",
    "gn:feature_code":"PPLL",
    "gn:name":"Dachsberg",
    "gn:population":0,
    "gn:timezone":"Europe/Zurich",
    "iso:country":"CH",
    "name:deu_x_preferred":[
        "Dachsberg"
    ],
    "wof:name":"Dachsberg",
    "wof:placetype":"neighbourhood"
},
  "geometry": {"coordinates":[8.50959,47.57311],"type":"Point"}
}