{
  "type": "Feature",
  "properties": {
    "gn:admin1_code":"ZH",
    "gn:admin2_code":"103.0",
    "gn:admin3_code":"55.0",
    "gn:asciiname":"Dachsberg",
    "gn:country_code":"CH",
    "gn:dem":391,
    "gn:feature_class":"P",
    "gn:feature_code":"PPLL",
    "gn:name":"Dachsberg",
    "gn:population":0,
    "gn:timezone":"Europe/Zurich",
    "iso:country":"CH",
    "name:als_x_preferred":[
        "Dachsberg"
    ],
    "name:ceb_x_preferred":[
        "Dachsberg"
    ],
    "name:deu_x_preferred":[
        "Dachsberg"
    ],
    "name:epo_x_preferred":[
        "Dachsberg"
    ],
    "name:eus_x_preferred":[
        "Dachsberg"
    ],
    "name:fas_x_preferred":[
        "\u062f\u0627\u062e\u0633\u0628\u0631\u06af"
    ],
    "name:fra_x_preferred":[
        "Dachsberg"
    ],
    "name:hun_x_preferred":[
        "Dachsberg"
    ],
    "name:ita_x_preferred":[
        "Dachsberg"
    ],
    "name:kaz_x_preferred":[
        "\u0414\u0430\u0445\u0441\u0431\u0435\u0440\u0433"
    ],
    "name:kir_x_preferred":[
        "\u0414\u0430\u0445\u0441\u0431\u0435\u0440\u0433"
    ],
    "name:lat_x_preferred":[
        "Dachsberg"
    ],
    "name:lmo_x_preferred":[
        "Dachsberg"
    ],
    "name:msa_x_preferred":[
        "Dachsberg"
    ],
    "name:nld_x_preferred":[
        "Dachsberg"
    ],
    "name:pol_x_preferred":[
        "Dachsberg"
    ],
    "name:por_x_preferred":[
        "Dachsberg"
    ],
    "name:ron_x_preferred":[
        "Dachsberg"
    ],
    "name:rus_x_preferred":[
        "\u0414\u0430\u043a\u0441\u0431\u0435\u0440\u0433"
    ],
    "name:spa_x_preferred":[
        "Dachsberg"
    ],
    "name:srp_x_preferred":[
        "\u0414\u0430\u0445\u0441\u0431\u0435\u0440\u0433"
    ],
    "name:ukr_x_preferred":[
        "\u0414\u0430\u043a\u0441\u0431\u0435\u0440\u0433"
    ],
    "name:uzb_x_preferred":[
        "Dachsberg"
    ],
    "name:vie_x_preferred":[
        "Dachsberg"
    ],
    "name:vol_x_preferred":[
        "Dachsberg"
    ],
    "name:war_x_preferred":[
        "Dachsberg"
    ],
    "name:zho_x_preferred":[
        "\u8fbe\u8d6b\u65af\u8d1d\u683c"
    ],
    "wof:lang_x_official":[
        "deu",
        "fra",
        "gsw",
        "ita"
    ],
    "wof:lang_x_spoken":[
        "deu",
        "fra",
        "gsw",
        "ita",
        "roh"
    ],
    "wof:name":"Dachsberg",
    "wof:placetype":"neighbourhood"
},
  "geometry": {"coordinates":[8.50959,47.57311],"type":"Point"}
}