{
  "type": "Feature",
  "properties": {
    "gn:admin1_code":"SG",
    "gn:admin2_code":"1726.0",
    "gn:admin3_code":"3311.0",
    "gn:asciiname":"Hinteraltschen",
    "gn:country_code":"CH",
    "gn:dem":1333,
    "gn:feature_class":"P",
    "gn:feature_code":"PPLL",
    "gn:name":"Hinteraltschen",
    "gn:population":0,
    "gn:timezone":"Europe/Zurich",
    "iso:country":"CH",
    "name:deu_x_preferred":[
        "Hinteraltschen"
    ],
    "wof:name":"Hinteraltschen",
    "wof:placetype":"neighbourhood"
},
  "geometry": {"coordinates":[9.1409,47.16233],"type":"Point"}
}