{
  "type": "Feature",
  "properties": {
    "gn:admin1_code":"AR",
    "gn:admin2_code":"1502.0",
    "gn:admin3_code":"3024.0",
    "gn:asciiname":"Buchenmuehle",
    "gn:country_code":"CH",
    "gn:dem":819,
    "gn:feature_class":"P",
    "gn:feature_code":"PPLL",
    "gn:name":"Buchenm\u00fchle",
    "gn:population":0,
    "gn:timezone":"Europe/Zurich",
    "iso:country":"CH",
    "name:deu_x_preferred":[
        "Buchenm\u00fchle"
    ],
    "wof:name":"Buchenmuehle",
    "wof:placetype":"neighbourhood"
},
  "geometry": {"coordinates":[9.4033,47.38983],"type":"Point"}
}