{
  "type": "Feature",
  "properties": {
    "gn:admin1_code":"TG",
    "gn:admin2_code":"2015.0",
    "gn:admin3_code":"4791.0",
    "gn:asciiname":"Heiligkreuz",
    "gn:country_code":"CH",
    "gn:dem":634,
    "gn:elevation":"647.0",
    "gn:feature_class":"P",
    "gn:feature_code":"PPL",
    "gn:name":"Heiligkreuz",
    "gn:population":0,
    "gn:timezone":"Europe/Zurich",
    "iso:country":"CH",
    "wof:name":"Heiligkreuz",
    "wof:placetype":"neighbourhood"
},
  "geometry": {"coordinates":[9.15739,47.50073],"type":"Point"}
}