{
  "type": "Feature",
  "properties": {
    "gn:admin1_code":"FR",
    "gn:admin2_code":"1003.0",
    "gn:admin3_code":"2124.0",
    "gn:asciiname":"Les Arquinces",
    "gn:country_code":"CH",
    "gn:dem":888,
    "gn:feature_class":"P",
    "gn:feature_code":"PPL",
    "gn:name":"Les Arquinces",
    "gn:population":0,
    "gn:timezone":"Europe/Zurich",
    "iso:country":"CH",
    "name:fra_x_preferred":[
        "Les Arquinces"
    ],
    "wof:name":"Les Arquinces",
    "wof:placetype":"locality"
},
  "geometry": {"coordinates":[7.12066,46.60041],"type":"Point"}
}