{
  "type": "Feature",
  "properties": {
    "gn:admin1_code":"ZH",
    "gn:admin2_code":"102.0",
    "gn:admin3_code":"37.0",
    "gn:asciiname":"Im Schlatter",
    "gn:country_code":"CH",
    "gn:dem":436,
    "gn:feature_class":"P",
    "gn:feature_code":"PPLL",
    "gn:name":"Im Schlatter",
    "gn:population":0,
    "gn:timezone":"Europe/Zurich",
    "iso:country":"CH",
    "name:deu_x_preferred":[
        "Im Schlatter"
    ],
    "wof:lang_x_official":[
        "deu",
        "fra",
        "gsw",
        "ita"
    ],
    "wof:lang_x_spoken":[
        "deu",
        "fra",
        "gsw",
        "ita",
        "roh"
    ],
    "wof:name":"Im Schlatter",
    "wof:placetype":"neighbourhood"
},
  "geometry": {"coordinates":[8.72427,47.61623],"type":"Point"}
}