{
  "type": "Feature",
  "properties": {
    "gn:admin1_code":"SO",
    "gn:admin2_code":"1106.0",
    "gn:admin3_code":"2516.0",
    "gn:asciiname":"Wylihof",
    "gn:country_code":"CH",
    "gn:dem":424,
    "gn:feature_class":"P",
    "gn:feature_code":"PPL",
    "gn:name":"Wylihof",
    "gn:population":0,
    "gn:timezone":"Europe/Zurich",
    "iso:country":"CH",
    "wof:name":"Wylihof",
    "wof:placetype":"locality"
},
  "geometry": {"coordinates":[7.59009,47.22569],"type":"Point"}
}