{
  "type": "Feature",
  "properties": {
    "gn:gn_country":"CH",
    "gn:gn_fcode":"ADM3",
    "gn:gn_pop":250,
    "gn:population":270,
    "iso:country":"CH",
    "name:alb_x_preferred":[
        "S\u00e9vaz"
    ],
    "name:baq_x_preferred":[
        "S\u00e9vaz"
    ],
    "name:cat_x_preferred":[
        "S\u00e9vaz"
    ],
    "name:chi_x_preferred":[
        "\u585e\u74e6"
    ],
    "name:dut_x_preferred":[
        "S\u00e9vaz"
    ],
    "name:eng_x_preferred":[
        "S\u00e9vaz"
    ],
    "name:epo_x_preferred":[
        "S\u00e9vaz"
    ],
    "name:fre_x_preferred":[
        "S\u00e9vaz"
    ],
    "name:ger_x_preferred":[
        "S\u00e9vaz"
    ],
    "name:hun_x_preferred":[
        "S\u00e9vaz"
    ],
    "name:ita_x_preferred":[
        "S\u00e9vaz"
    ],
    "name:lmo_x_preferred":[
        "S\u00e9vaz"
    ],
    "name:may_x_preferred":[
        "S\u00e9vaz"
    ],
    "name:nno_x_preferred":[
        "S\u00e9vaz"
    ],
    "name:oci_x_preferred":[
        "S\u00e9vaz"
    ],
    "name:por_x_preferred":[
        "S\u00e9vaz"
    ],
    "name:roh_x_preferred":[
        "S\u00e9vaz"
    ],
    "name:spa_x_preferred":[
        "S\u00e9vaz"
    ],
    "name:swe_x_preferred":[
        "S\u00e9vaz"
    ],
    "name:vie_x_preferred":[
        "S\u00e9vaz"
    ],
    "name:vol_x_preferred":[
        "S\u00e9vaz"
    ],
    "name:war_x_preferred":[
        "S\u00e9vaz"
    ],
    "qs_pg:aaroncc":"CH",
    "qs_pg:gn_country":"CH",
    "qs_pg:gn_fcode":"ADM3",
    "qs_pg:gn_pop":250,
    "qs_pg:name":"S\u00e9vaz",
    "qs_pg:name_adm0":"Schweiz",
    "qs_pg:name_adm1":"Canton de Fribourg",
    "qs_pg:photos_9k":1,
    "qs_pg:photos_9r":1,
    "qs_pg:photos_all":4,
    "qs_pg:photos_sr":0,
    "qs_pg:pop_sr":2,
    "qs_pg:qs_pg_placetype":"locality",
    "qs_pg:qs_pg_placetype_gp":"Town",
    "qs_pg:woe_adm0":23424957,
    "woe:adm0_id":23424957,
    "woe:name_adm0":"Schweiz",
    "woe:name_adm1":"Canton de Fribourg",
    "woe:placetype":"Town",
    "wof:name":"S\u00e9vaz",
    "wof:placetype":"locality",
    "wof:population":270
},
  "geometry": {"coordinates":[6.87441,46.83946],"type":"Point"}
}