{
  "type": "Feature",
  "properties": {
    "gn:gn_country":"CH",
    "gn:gn_fcode":"PPL",
    "gn:gn_pop":0,
    "iso:country":"CH",
    "name:deu_x_preferred":[
        "Vauderens"
    ],
    "name:eng_x_preferred":[
        "Vauderens"
    ],
    "name:fra_x_preferred":[
        "Vauderens"
    ],
    "name:nld_x_preferred":[
        "Vauderens"
    ],
    "qs_pg:aaroncc":"CH",
    "qs_pg:gn_country":"CH",
    "qs_pg:gn_fcode":"PPL",
    "qs_pg:gn_pop":0,
    "qs_pg:name":"Vauderens",
    "qs_pg:name_adm0":"Schweiz",
    "qs_pg:name_adm1":"Canton de Fribourg",
    "qs_pg:photos_9k":1,
    "qs_pg:photos_9r":1,
    "qs_pg:photos_all":2,
    "qs_pg:photos_sr":0,
    "qs_pg:pop_sr":0,
    "qs_pg:qs_pg_placetype":"locality",
    "qs_pg:qs_pg_placetype_gp":"Town",
    "qs_pg:woe_adm0":23424957,
    "woe:adm0_id":23424957,
    "woe:name_adm0":"Schweiz",
    "woe:name_adm1":"Canton de Fribourg",
    "woe:placetype":"Town",
    "wof:name":"Vauderens",
    "wof:placetype":"locality"
},
  "geometry": {"coordinates":[6.85066,46.62283],"type":"Point"}
}