{
  "type": "Feature",
  "properties": {
    "gn:admin1_code":"VS",
    "gn:admin2_code":"2303.0",
    "gn:admin3_code":"6036.0",
    "gn:asciiname":"Cries (Volleges)",
    "gn:country_code":"CH",
    "gn:dem":934,
    "gn:feature_class":"P",
    "gn:feature_code":"PPL",
    "gn:name":"Cries (Voll\u00e8ges)",
    "gn:population":0,
    "gn:timezone":"Europe/Zurich",
    "iso:country":"CH",
    "name:und_x_variant":[
        "Cries (Voll\u00e8ges)"
    ],
    "wof:name":"Cries (Volleges)",
    "wof:placetype":"locality"
},
  "geometry": {"coordinates":[7.1755,46.09196],"type":"Point"}
}