{
  "type": "Feature",
  "properties": {
    "gn:gn_country":"CH",
    "gn:gn_fcode":"ADM3",
    "gn:gn_pop":113,
    "gn:population":113,
    "iso:country":"CH",
    "name:deu_x_preferred":[
        "Carabietta"
    ],
    "name:eng_x_preferred":[
        "Carabietta"
    ],
    "name:fra_x_preferred":[
        "Carabietta"
    ],
    "name:gsw_x_preferred":[
        "Carabietta"
    ],
    "name:hun_x_preferred":[
        "Carabietta"
    ],
    "name:ita_x_preferred":[
        "Carabietta"
    ],
    "name:lmo_x_preferred":[
        "Carabieta"
    ],
    "name:nld_x_preferred":[
        "Carabietta"
    ],
    "name:nno_x_preferred":[
        "Carabietta"
    ],
    "name:por_x_preferred":[
        "Carabietta"
    ],
    "name:roh_x_preferred":[
        "Carabietta"
    ],
    "name:spa_x_preferred":[
        "Carabietta"
    ],
    "name:sqi_x_preferred":[
        "Carabietta"
    ],
    "name:swe_x_preferred":[
        "Carabietta"
    ],
    "name:vol_x_preferred":[
        "Carabietta"
    ],
    "name:war_x_preferred":[
        "Carabietta"
    ],
    "qs_pg:aaroncc":"CH",
    "qs_pg:gn_country":"CH",
    "qs_pg:gn_fcode":"ADM3",
    "qs_pg:gn_pop":113,
    "qs_pg:name":"Carabietta",
    "qs_pg:name_adm0":"Schweiz",
    "qs_pg:name_adm1":"Cantone Ticino",
    "qs_pg:photos":25,
    "qs_pg:photos_1k":5,
    "qs_pg:photos_9k":1,
    "qs_pg:photos_9r":1,
    "qs_pg:photos_all":25,
    "qs_pg:photos_sr":1,
    "qs_pg:pop_sr":1,
    "qs_pg:qs_pg_placetype":"locality",
    "qs_pg:qs_pg_placetype_gp":"Town",
    "qs_pg:woe_adm0":23424957,
    "woe:adm0_id":23424957,
    "woe:name_adm0":"Schweiz",
    "woe:name_adm1":"Cantone Ticino",
    "woe:placetype":"Town",
    "wof:name":"Carabietta",
    "wof:placetype":"locality",
    "wof:population":113
},
  "geometry": {"coordinates":[8.90252,45.96884],"type":"Point"}
}