{
  "type": "Feature",
  "properties": {
    "gn:population":2813,
    "iso:country":"CH",
    "name:alb_x_preferred":[
        "Zweisimmen"
    ],
    "name:als_x_preferred":[
        "Zweisimmen"
    ],
    "name:baq_x_preferred":[
        "Zweisimmen"
    ],
    "name:cat_x_preferred":[
        "Zweisimmen"
    ],
    "name:ceb_x_preferred":[
        "Zweisimmen"
    ],
    "name:chi_x_preferred":[
        "\u8328\u97cb\u897f\u9580"
    ],
    "name:deu_x_preferred":[
        "Zweisimmen"
    ],
    "name:dut_x_preferred":[
        "Zweisimmen"
    ],
    "name:eng_x_preferred":[
        "Zweisimmen"
    ],
    "name:epo_x_preferred":[
        "Zweisimmen"
    ],
    "name:est_x_preferred":[
        "Zweisimmeni vald"
    ],
    "name:eus_x_preferred":[
        "Zweisimmen"
    ],
    "name:fra_x_preferred":[
        "Zweisimmen"
    ],
    "name:fre_x_preferred":[
        "Zweisimmen"
    ],
    "name:ger_x_preferred":[
        "Zweisimmen"
    ],
    "name:gsw_x_preferred":[
        "Zw\u00fc\u00fcsimme"
    ],
    "name:hun_x_preferred":[
        "Zweisimmen"
    ],
    "name:ita_x_preferred":[
        "Zweisimmen"
    ],
    "name:kaz_x_preferred":[
        "\u0426\u0432\u0430\u0439\u0437\u0438\u043c\u043c\u0435\u043d"
    ],
    "name:lmo_x_preferred":[
        "Zweisimmen"
    ],
    "name:may_x_preferred":[
        "Zweisimmen"
    ],
    "name:msa_x_preferred":[
        "Zweisimmen"
    ],
    "name:nld_x_preferred":[
        "Zweisimmen"
    ],
    "name:nno_x_preferred":[
        "Zweisimmen"
    ],
    "name:oci_x_preferred":[
        "Zweisimmen"
    ],
    "name:pms_x_preferred":[
        "Zweisimmen"
    ],
    "name:por_x_preferred":[
        "Zweisimmen"
    ],
    "name:rus_x_preferred":[
        "\u0426\u0432\u0430\u0439\u0437\u0438\u043c\u043c\u0435\u043d"
    ],
    "name:spa_x_preferred":[
        "Zweisimmen"
    ],
    "name:sqi_x_preferred":[
        "Zweisimmen"
    ],
    "name:swe_x_preferred":[
        "Zweisimmen"
    ],
    "name:vol_x_preferred":[
        "Zweisimmen"
    ],
    "name:war_x_preferred":[
        "Zweisimmen"
    ],
    "name:zho_x_preferred":[
        "\u8328\u97cb\u897f\u9580"
    ],
    "qs:a0":"Schweiz#Suisse#Svizzera#Svizra",
    "qs:a1":"*Bern",
    "qs:a1r":"0",
    "qs:adm0":"Schweiz#Suisse#Svizzera#Svizra",
    "qs:la_lc":"*",
    "qs:level":"locality",
    "qs:loc":"Zweisimmen",
    "qs:loc_alt":"Zweisimmen",
    "qs:pop":0,
    "qs:type":"buffered point",
    "wd:wordcount":2839,
    "wof:lang":[
        "ger"
    ],
    "wof:name":"Zweisimmen",
    "wof:placetype":"locality",
    "wof:population":2813
},
  "geometry": {"coordinates":[7.375178,46.553028],"type":"Point"}
}