{
  "type": "Feature",
  "properties": {
    "gn:admin1_code":"BE",
    "gn:admin2_code":"246.0",
    "gn:admin3_code":"878.0",
    "gn:asciiname":"Noflen",
    "gn:country_code":"CH",
    "gn:dem":639,
    "gn:feature_class":"P",
    "gn:feature_code":"PPL",
    "gn:name":"Noflen",
    "gn:population":0,
    "gn:timezone":"Europe/Zurich",
    "iso:country":"CH",
    "name:als_x_preferred":[
        "Noflen BE"
    ],
    "name:deu_x_preferred":[
        "Noflen BE"
    ],
    "name:epo_x_preferred":[
        "Noflen BE"
    ],
    "name:kaz_x_preferred":[
        "\u041d\u043e\u0444\u043b\u0435\u043d"
    ],
    "name:rus_x_preferred":[
        "\u041d\u043e\u0444\u043b\u0435\u043d"
    ],
    "name:war_x_preferred":[
        "Noflen BE"
    ],
    "name:zho_x_preferred":[
        "\u8afe\u5f17\u502b"
    ],
    "wof:name":"Noflen",
    "wof:placetype":"locality"
},
  "geometry": {"coordinates":[7.5433,46.8056],"type":"Point"}
}