{
  "type": "Feature",
  "properties": {
    "gn:admin1_code":"UR",
    "gn:admin2_code":"400.0",
    "gn:admin3_code":"1210.0",
    "gn:asciiname":"Chaemleten",
    "gn:country_code":"CH",
    "gn:dem":1655,
    "gn:feature_class":"P",
    "gn:feature_code":"PPL",
    "gn:name":"Ch\u00e4mleten",
    "gn:population":0,
    "gn:timezone":"Europe/Zurich",
    "iso:country":"CH",
    "name:deu_x_preferred":[
        "Ch\u00e4mleten"
    ],
    "wof:name":"Chaemleten",
    "wof:placetype":"locality"
},
  "geometry": {"coordinates":[8.56753,46.6144],"type":"Point"}
}