{
  "type": "Feature",
  "properties": {
    "gn:gn_country":"CH",
    "gn:gn_fcode":"PPL",
    "gn:gn_pop":1779,
    "gn:population":1779,
    "iso:country":"CH",
    "name:cat_x_preferred":[
        "Rehetobel"
    ],
    "name:chv_x_preferred":[
        "\u0420\u0435\u044d\u0442\u043e\u0431\u0435\u043b\u044c"
    ],
    "name:deu_x_preferred":[
        "Rehetobel"
    ],
    "name:eng_x_preferred":[
        "Rehetobel"
    ],
    "name:epo_x_preferred":[
        "Rehetobel"
    ],
    "name:eus_x_preferred":[
        "Rehetobel"
    ],
    "name:fra_x_preferred":[
        "Rehetobel"
    ],
    "name:gsw_x_preferred":[
        "Rechtobel"
    ],
    "name:hun_x_preferred":[
        "Rehetobel"
    ],
    "name:ita_x_preferred":[
        "Rehetobel"
    ],
    "name:kaz_x_preferred":[
        "\u0420\u0435\u044d\u0442\u043e\u0431\u0435\u043b\u044c"
    ],
    "name:lmo_x_preferred":[
        "Rehetobel"
    ],
    "name:nld_x_preferred":[
        "Rehetobel"
    ],
    "name:nno_x_preferred":[
        "Rehetobel"
    ],
    "name:oci_x_preferred":[
        "Rehetobel"
    ],
    "name:pms_x_preferred":[
        "Rehetobel"
    ],
    "name:pol_x_preferred":[
        "Rehetobel"
    ],
    "name:por_x_preferred":[
        "Rehetobel"
    ],
    "name:ron_x_preferred":[
        "Rehetobel"
    ],
    "name:rus_x_preferred":[
        "\u0420\u0435\u044d\u0442\u043e\u0431\u0435\u043b\u044c"
    ],
    "name:spa_x_preferred":[
        "Rehetobel"
    ],
    "name:sqi_x_preferred":[
        "Rehetobel"
    ],
    "name:swe_x_preferred":[
        "Rehetobel"
    ],
    "name:uzb_x_preferred":[
        "Rehetobel"
    ],
    "name:vol_x_preferred":[
        "Rehetobel"
    ],
    "name:war_x_preferred":[
        "Rehetobel"
    ],
    "qs_pg:aaroncc":"CH",
    "qs_pg:gn_country":"CH",
    "qs_pg:gn_fcode":"PPL",
    "qs_pg:gn_pop":1779,
    "qs_pg:name":"Rehetobel",
    "qs_pg:name_adm0":"Schweiz",
    "qs_pg:name_adm1":"Kanton Appenzell Ausserrhoden",
    "qs_pg:photos":8,
    "qs_pg:photos_1k":2,
    "qs_pg:photos_9k":1,
    "qs_pg:photos_9r":1,
    "qs_pg:photos_all":8,
    "qs_pg:photos_sr":1,
    "qs_pg:pop_sr":3,
    "qs_pg:qs_pg_placetype":"locality",
    "qs_pg:qs_pg_placetype_gp":"Town",
    "qs_pg:woe_adm0":23424957,
    "woe:adm0_id":23424957,
    "woe:name_adm0":"Schweiz",
    "woe:name_adm1":"Kanton Appenzell Ausserrhoden",
    "woe:placetype":"Town",
    "wof:name":"Rehetobel",
    "wof:placetype":"locality",
    "wof:population":1779
},
  "geometry": {"coordinates":[9.483,47.42611],"type":"Point"}
}