{
  "type": "Feature",
  "properties": {
    "gn:admin1_code":"SH",
    "gn:admin2_code":"1402.0",
    "gn:admin3_code":"2920.0",
    "gn:asciiname":"Haeldeli",
    "gn:country_code":"CH",
    "gn:dem":582,
    "gn:feature_class":"P",
    "gn:feature_code":"PPLL",
    "gn:name":"H\u00e4ldeli",
    "gn:population":0,
    "gn:timezone":"Europe/Zurich",
    "iso:country":"CH",
    "name:deu_x_preferred":[
        "H\u00e4ldeli"
    ],
    "wof:name":"Haeldeli",
    "wof:placetype":"locality"
},
  "geometry": {"coordinates":[8.65357,47.78868],"type":"Point"}
}