{
  "type": "Feature",
  "properties": {
    "gn:admin1_code":"TG",
    "gn:admin2_code":"2012.0",
    "gn:admin3_code":"4816.0",
    "gn:asciiname":"Helmetshausen",
    "gn:country_code":"CH",
    "gn:dem":576,
    "gn:feature_class":"P",
    "gn:feature_code":"PPLL",
    "gn:name":"Helmetshausen",
    "gn:population":0,
    "gn:timezone":"Europe/Zurich",
    "iso:country":"CH",
    "name:deu_x_preferred":[
        "Helmetshausen"
    ],
    "wof:name":"Helmetshausen",
    "wof:placetype":"neighbourhood"
},
  "geometry": {"coordinates":[8.96052,47.63963],"type":"Point"}
}