{
  "type": "Feature",
  "properties": {
    "gn:admin1_code":"BE",
    "gn:admin2_code":"244.0",
    "gn:admin3_code":"339.0",
    "gn:asciiname":"Wil",
    "gn:country_code":"CH",
    "gn:dem":623,
    "gn:feature_class":"P",
    "gn:feature_code":"PPLL",
    "gn:name":"Wil",
    "gn:population":0,
    "gn:timezone":"Europe/Zurich",
    "iso:country":"CH",
    "name:deu_x_preferred":[
        "Wil"
    ],
    "wof:name":"Wil",
    "wof:placetype":"neighbourhood"
},
  "geometry": {"coordinates":[7.80308,47.12123],"type":"Point"}
}