{
  "type": "Feature",
  "properties": {
    "iso:country":"CH",
    "name:als_x_preferred":[
        "Clara"
    ],
    "name:cat_x_preferred":[
        "Clara"
    ],
    "name:ceb_x_preferred":[
        "Clara"
    ],
    "name:deu_x_preferred":[
        "Clara"
    ],
    "name:est_x_preferred":[
        "Clara"
    ],
    "name:fas_x_preferred":[
        "\u06a9\u0644\u0627\u0631\u0627"
    ],
    "name:fra_x_preferred":[
        "Clara"
    ],
    "name:glg_x_preferred":[
        "Clara"
    ],
    "name:ita_x_preferred":[
        "Clara"
    ],
    "name:jpn_x_preferred":[
        "\u30af\u30e9\u30e9"
    ],
    "name:kor_x_preferred":[
        "\ud074\ub77c\ub77c"
    ],
    "name:nld_x_preferred":[
        "Clara"
    ],
    "name:pol_x_preferred":[
        "Clara"
    ],
    "name:ron_x_preferred":[
        "Clara"
    ],
    "name:rus_x_preferred":[
        "\u041a\u043b\u0430\u0440\u0430"
    ],
    "name:spa_x_preferred":[
        "Clara"
    ],
    "name:swe_x_preferred":[
        "Clara"
    ],
    "name:ukr_x_preferred":[
        "\u041a\u043b\u0430\u0440\u0430"
    ],
    "name:vie_x_preferred":[
        "Clara"
    ],
    "wof:name":"Clara",
    "wof:placetype":"neighbourhood"
},
  "geometry": {"coordinates":[7.59663846127972,47.56344693277015],"type":"Point"}
}