{
  "type": "Feature",
  "properties": {
    "iso:country":"CH",
    "wof:name":"Clara",
    "wof:placetype":"neighbourhood"
},
  "geometry": {"coordinates":[7.59663846127972,47.56344693277015],"type":"Point"}
}