{
  "type": "Feature",
  "properties": {
    "gn:gn_country":"CH",
    "gn:gn_fcode":"PPLL",
    "gn:gn_pop":8,
    "gn:population":8,
    "iso:country":"CH",
    "name:unk_x_variant":[
        "Maas"
    ],
    "qs_pg:aaroncc":"CH",
    "qs_pg:gn_country":"CH",
    "qs_pg:gn_fcode":"PPLL",
    "qs_pg:gn_pop":8,
    "qs_pg:name":"Oberwinterthur (Kreis 2) / Maas",
    "qs_pg:photos_9r":0,
    "qs_pg:photos_sr":0,
    "qs_pg:pop_sr":1,
    "qs_pg:qs_pg_placetype":"locality",
    "wof:name":"Oberwinterthur (Kreis 2) / Maas",
    "wof:placetype":"locality",
    "wof:population":8
},
  "geometry": {"coordinates":[8.80342,47.48832],"type":"Point"}
}