{
  "type": "Feature",
  "properties": {
    "gn:gn_country":"CH",
    "gn:gn_fcode":"PPLX",
    "gn:gn_pop":346,
    "gn:population":346,
    "iso:country":"CH",
    "name:eng_x_preferred":[
        "B\u00fchlhof"
    ],
    "name:eng_x_variant":[
        "Wolfhausen / B\u00fchlhof"
    ],
    "name:unk_x_variant":[
        "B\u00fchlhof"
    ],
    "qs_pg:aaroncc":"CH",
    "qs_pg:gn_country":"CH",
    "qs_pg:gn_fcode":"PPLX",
    "qs_pg:gn_pop":346,
    "qs_pg:name":"Wolfhausen / B\u00fchlhof",
    "qs_pg:photos_9r":0,
    "qs_pg:photos_sr":0,
    "qs_pg:pop_sr":2,
    "qs_pg:qs_pg_placetype":"neighbourhood",
    "wof:name":"B\u00fchlhof",
    "wof:placetype":"neighbourhood",
    "wof:population":346
},
  "geometry": {"coordinates":[8.79696,47.25925],"type":"Point"}
}