{
  "type": "Feature",
  "properties": {
    "gn:admin1_code":"VD",
    "gn:admin2_code":"2222.0",
    "gn:admin3_code":"5669.0",
    "gn:asciiname":"Curtilles",
    "gn:country_code":"CH",
    "gn:dem":514,
    "gn:feature_class":"P",
    "gn:feature_code":"PPL",
    "gn:name":"Curtilles",
    "gn:population":0,
    "gn:timezone":"Europe/Zurich",
    "iso:country":"CH",
    "name:zho_x_preferred":[
        "\u5c45\u5c14\u8482\u8036"
    ],
    "wof:name":"Curtilles",
    "wof:placetype":"locality"
},
  "geometry": {"coordinates":[6.84505,46.70108],"type":"Point"}
}