{
  "type": "Feature",
  "properties": {
    "gn:admin1_code":"TG",
    "gn:admin2_code":"2013.0",
    "gn:admin3_code":"4666.0",
    "gn:asciiname":"Gaisbuehl",
    "gn:country_code":"CH",
    "gn:dem":556,
    "gn:feature_class":"P",
    "gn:feature_code":"PPLL",
    "gn:name":"Gaisb\u00fchl",
    "gn:population":0,
    "gn:timezone":"Europe/Zurich",
    "iso:country":"CH",
    "name:deu_x_preferred":[
        "Gaisb\u00fchl"
    ],
    "wof:lang_x_official":[
        "deu",
        "fra",
        "gsw",
        "ita"
    ],
    "wof:lang_x_spoken":[
        "deu",
        "fra",
        "gsw",
        "ita",
        "roh"
    ],
    "wof:name":"Gaisbuehl",
    "wof:placetype":"neighbourhood"
},
  "geometry": {"coordinates":[9.17492,47.60832],"type":"Point"}
}