{
  "type": "Feature",
  "properties": {
    "gn:gn_country":"CH",
    "gn:gn_fcode":"PPL",
    "gn:gn_pop":147,
    "gn:population":147,
    "iso:country":"CH",
    "name:bul_x_preferred":[
        "\u041c\u0443\u0433\u0435\u043d\u0430"
    ],
    "name:dut_x_preferred":[
        "Mugena"
    ],
    "name:eng_x_preferred":[
        "Mugena"
    ],
    "name:fre_x_preferred":[
        "Mugena"
    ],
    "name:ger_x_preferred":[
        "Mugena"
    ],
    "name:ita_x_preferred":[
        "Arosio-Mugena"
    ],
    "name:ita_x_variant":[
        "Mugena"
    ],
    "name:lmo_x_preferred":[
        "Musgena"
    ],
    "name:por_x_preferred":[
        "Mugena"
    ],
    "qs_pg:aaroncc":"CH",
    "qs_pg:gn_country":"CH",
    "qs_pg:gn_fcode":"PPL",
    "qs_pg:gn_pop":147,
    "qs_pg:name":"Mugena",
    "qs_pg:name_adm0":"Schweiz",
    "qs_pg:name_adm1":"Cantone Ticino",
    "qs_pg:photos":15,
    "qs_pg:photos_1k":3,
    "qs_pg:photos_9k":1,
    "qs_pg:photos_9r":1,
    "qs_pg:photos_all":15,
    "qs_pg:photos_sr":1,
    "qs_pg:pop_sr":1,
    "qs_pg:qs_pg_placetype":"locality",
    "qs_pg:qs_pg_placetype_gp":"Town",
    "qs_pg:woe_adm0":23424957,
    "woe:adm0_id":23424957,
    "woe:name_adm0":"Schweiz",
    "woe:name_adm1":"Cantone Ticino",
    "woe:placetype":"Town",
    "wof:name":"Mugena",
    "wof:placetype":"locality",
    "wof:population":147
},
  "geometry": {"coordinates":[8.88931,46.04863],"type":"Point"}
}