{
  "type": "Feature",
  "properties": {
    "gn:admin1_code":"FR",
    "gn:admin2_code":"1003.0",
    "gn:admin3_code":"2162.0",
    "gn:asciiname":"Villars-sous-Mont",
    "gn:country_code":"CH",
    "gn:dem":747,
    "gn:elevation":"758.0",
    "gn:feature_class":"P",
    "gn:feature_code":"PPL",
    "gn:name":"Villars-sous-Mont",
    "gn:population":0,
    "gn:timezone":"Europe/Zurich",
    "iso:country":"CH",
    "wof:name":"Villars-sous-Mont",
    "wof:placetype":"locality"
},
  "geometry": {"coordinates":[7.07035,46.54119],"type":"Point"}
}