{
  "type": "Feature",
  "properties": {
    "gn:gn_country":"CH",
    "gn:gn_fcode":"PPL",
    "gn:gn_pop":1058,
    "gn:population":1058,
    "iso:country":"CH",
    "name:alb_x_preferred":[
        "Rechthalten"
    ],
    "name:baq_x_preferred":[
        "Rechthalten"
    ],
    "name:cat_x_preferred":[
        "Rechthalten"
    ],
    "name:chi_x_preferred":[
        "\u96f7\u8d6b\u5854\u723e\u6ed5"
    ],
    "name:dut_x_preferred":[
        "Rechthalten"
    ],
    "name:eng_x_preferred":[
        "Rechthalten"
    ],
    "name:epo_x_preferred":[
        "Rechthalten"
    ],
    "name:fre_x_preferred":[
        "Rechthalten"
    ],
    "name:ger_x_preferred":[
        "Rechthalten"
    ],
    "name:gsw_x_preferred":[
        "R\u00e4chthaute"
    ],
    "name:hun_x_preferred":[
        "Rechthalten"
    ],
    "name:ita_x_preferred":[
        "Rechthalten"
    ],
    "name:lmo_x_preferred":[
        "Rechthalten"
    ],
    "name:may_x_preferred":[
        "Rechthalten"
    ],
    "name:nno_x_preferred":[
        "Rechthalten"
    ],
    "name:oci_x_preferred":[
        "Rechthalten"
    ],
    "name:pms_x_preferred":[
        "Rechthalten"
    ],
    "name:por_x_preferred":[
        "Rechthalten"
    ],
    "name:roh_x_preferred":[
        "Rechthalten"
    ],
    "name:spa_x_preferred":[
        "Rechthalten"
    ],
    "name:swe_x_preferred":[
        "Rechthalten"
    ],
    "name:vol_x_preferred":[
        "Rechthalten"
    ],
    "name:war_x_preferred":[
        "Rechthalten"
    ],
    "name:zho_x_preferred":[
        "\u96f7\u8d6b\u5854\u723e\u6ed5"
    ],
    "qs_pg:aaroncc":"CH",
    "qs_pg:gn_country":"CH",
    "qs_pg:gn_fcode":"PPL",
    "qs_pg:gn_pop":1058,
    "qs_pg:name":"Rechthalten",
    "qs_pg:name_adm0":"Schweiz",
    "qs_pg:name_adm1":"Canton de Fribourg",
    "qs_pg:photos_9k":1,
    "qs_pg:photos_9r":2,
    "qs_pg:photos_all":55,
    "qs_pg:photos_sr":0,
    "qs_pg:pop_sr":3,
    "qs_pg:qs_pg_placetype":"locality",
    "qs_pg:qs_pg_placetype_gp":"Town",
    "qs_pg:woe_adm0":23424957,
    "woe:adm0_id":23424957,
    "woe:name_adm0":"Schweiz",
    "woe:name_adm1":"Canton de Fribourg",
    "woe:placetype":"Town",
    "wof:name":"Rechthalten",
    "wof:placetype":"locality",
    "wof:population":1058
},
  "geometry": {"coordinates":[7.24028,46.76766],"type":"Point"}
}