{
  "type": "Feature",
  "properties": {
    "gn:admin1_code":"TI",
    "gn:admin2_code":"2105.0",
    "gn:admin3_code":"5226.0",
    "gn:asciiname":"Sore",
    "gn:country_code":"CH",
    "gn:dem":999,
    "gn:feature_class":"P",
    "gn:feature_code":"PPL",
    "gn:name":"Sor\u00e8",
    "gn:population":0,
    "gn:timezone":"Europe/Zurich",
    "iso:country":"CH",
    "name:ceb_x_preferred":[
        "Sore"
    ],
    "name:deu_x_preferred":[
        "Sore"
    ],
    "name:fra_x_preferred":[
        "Sore"
    ],
    "name:ind_x_preferred":[
        "Sore"
    ],
    "name:ita_x_preferred":[
        "Sor\u00e8"
    ],
    "name:slk_x_preferred":[
        "Sore"
    ],
    "name:swe_x_preferred":[
        "Sore"
    ],
    "wof:lang_x_official":[
        "deu",
        "fra",
        "gsw",
        "ita"
    ],
    "wof:lang_x_spoken":[
        "deu",
        "fra",
        "gsw",
        "ita",
        "roh"
    ],
    "wof:name":"Sore",
    "wof:placetype":"neighbourhood"
},
  "geometry": {"coordinates":[8.97897,46.09514],"type":"Point"}
}