{
  "type": "Feature",
  "properties": {
    "gn:gn_country":"CH",
    "gn:gn_fcode":"PPL",
    "gn:gn_pop":953,
    "gn:population":953,
    "iso:country":"CH",
    "name:alb_x_preferred":[
        "Birrwil"
    ],
    "name:ast_x_preferred":[
        "Birrwil"
    ],
    "name:baq_x_preferred":[
        "Birrwil"
    ],
    "name:cat_x_preferred":[
        "Birrwil"
    ],
    "name:chi_x_preferred":[
        "\u6bd4\u723e\u7dad\u723e"
    ],
    "name:dut_x_preferred":[
        "Birrwil"
    ],
    "name:eng_x_preferred":[
        "Birrwil"
    ],
    "name:epo_x_preferred":[
        "Birrwil"
    ],
    "name:fre_x_preferred":[
        "Birrwil"
    ],
    "name:ger_x_preferred":[
        "Birrwil"
    ],
    "name:gsw_x_preferred":[
        "Birrbu"
    ],
    "name:hun_x_preferred":[
        "Birrwil"
    ],
    "name:ita_x_preferred":[
        "Birrwil"
    ],
    "name:kaz_x_preferred":[
        "\u0411\u0438\u0440\u0440\u0432\u0438\u043b\u044c"
    ],
    "name:lmo_x_preferred":[
        "Birrwil"
    ],
    "name:may_x_preferred":[
        "Birrwil"
    ],
    "name:nno_x_preferred":[
        "Birrwil"
    ],
    "name:oci_x_preferred":[
        "Birrwil"
    ],
    "name:pms_x_preferred":[
        "Birrwil"
    ],
    "name:pol_x_preferred":[
        "Birrwil"
    ],
    "name:por_x_preferred":[
        "Birrwil"
    ],
    "name:rus_x_preferred":[
        "\u0411\u0438\u0440\u0440\u0432\u0438\u043b\u044c"
    ],
    "name:spa_x_preferred":[
        "Birrwil"
    ],
    "name:swe_x_preferred":[
        "Birrwil"
    ],
    "name:uzb_x_preferred":[
        "Birrwil"
    ],
    "name:vol_x_preferred":[
        "Birrwil"
    ],
    "name:war_x_preferred":[
        "Birrwil"
    ],
    "name:zho_x_preferred":[
        "\u6bd4\u723e\u7dad\u723e"
    ],
    "qs_pg:aaroncc":"CH",
    "qs_pg:gn_country":"CH",
    "qs_pg:gn_fcode":"PPL",
    "qs_pg:gn_pop":953,
    "qs_pg:name":"Birrwil",
    "qs_pg:name_adm0":"Schweiz",
    "qs_pg:name_adm1":"Kanton Aargau",
    "qs_pg:photos":19,
    "qs_pg:photos_1k":4,
    "qs_pg:photos_9k":1,
    "qs_pg:photos_9r":1,
    "qs_pg:photos_all":19,
    "qs_pg:photos_sr":1,
    "qs_pg:pop_sr":2,
    "qs_pg:qs_pg_placetype":"locality",
    "qs_pg:qs_pg_placetype_gp":"Town",
    "qs_pg:woe_adm0":23424957,
    "woe:adm0_id":23424957,
    "woe:name_adm0":"Schweiz",
    "woe:name_adm1":"Kanton Aargau",
    "woe:placetype":"Town",
    "wof:name":"Birrwil",
    "wof:placetype":"locality",
    "wof:population":953
},
  "geometry": {"coordinates":[8.20004,47.2886],"type":"Point"}
}