{
  "type": "Feature",
  "properties": {
    "gn:gn_country":"CH",
    "gn:gn_fcode":"PPLX",
    "gn:gn_pop":130,
    "gn:population":130,
    "iso:country":"CH",
    "name:eng_x_preferred":[
        "Schwerzgrub"
    ],
    "name:eng_x_variant":[
        "Uitikon / Schwerzgrub"
    ],
    "name:unk_x_variant":[
        "Schwerzgrub"
    ],
    "qs_pg:aaroncc":"CH",
    "qs_pg:gn_country":"CH",
    "qs_pg:gn_fcode":"PPLX",
    "qs_pg:gn_pop":130,
    "qs_pg:name":"Uitikon / Schwerzgrub",
    "qs_pg:photos_9r":0,
    "qs_pg:photos_sr":0,
    "qs_pg:pop_sr":1,
    "qs_pg:qs_pg_placetype":"neighbourhood",
    "wof:name":"Schwerzgrub",
    "wof:placetype":"neighbourhood",
    "wof:population":130
},
  "geometry": {"coordinates":[8.4611,47.36873],"type":"Point"}
}