{
  "type": "Feature",
  "properties": {
    "gn:gn_country":"CH",
    "gn:gn_fcode":"PPL",
    "gn:gn_pop":624,
    "gn:population":624,
    "iso:country":"CH",
    "name:alb_x_preferred":[
        "Cresciano"
    ],
    "name:baq_x_preferred":[
        "Cresciano"
    ],
    "name:cat_x_preferred":[
        "Cresciano"
    ],
    "name:chi_x_preferred":[
        "\u514b\u96f7\u65af\u6070\u8afe"
    ],
    "name:dut_x_preferred":[
        "Cresciano"
    ],
    "name:eng_x_preferred":[
        "Cresciano"
    ],
    "name:epo_x_preferred":[
        "Cresciano"
    ],
    "name:fre_x_preferred":[
        "Cresciano"
    ],
    "name:ger_x_preferred":[
        "Cresciano"
    ],
    "name:gsw_x_preferred":[
        "Cresciano"
    ],
    "name:hun_x_preferred":[
        "Cresciano"
    ],
    "name:ita_x_preferred":[
        "Cresciano"
    ],
    "name:lmo_x_preferred":[
        "Carsc\u00e8i"
    ],
    "name:may_x_preferred":[
        "Cresciano"
    ],
    "name:nno_x_preferred":[
        "Cresciano"
    ],
    "name:oci_x_preferred":[
        "Cresciano"
    ],
    "name:por_x_preferred":[
        "Cresciano"
    ],
    "name:roh_x_preferred":[
        "Cresciano"
    ],
    "name:spa_x_preferred":[
        "Cresciano"
    ],
    "name:vol_x_preferred":[
        "Cresciano"
    ],
    "name:war_x_preferred":[
        "Cresciano"
    ],
    "name:zho_x_preferred":[
        "\u514b\u96f7\u65af\u6070\u8afe"
    ],
    "qs_pg:aaroncc":"CH",
    "qs_pg:gn_country":"CH",
    "qs_pg:gn_fcode":"PPL",
    "qs_pg:gn_pop":624,
    "qs_pg:name":"Cresciano",
    "qs_pg:name_adm0":"Schweiz",
    "qs_pg:name_adm1":"Cantone Ticino",
    "qs_pg:photos":95,
    "qs_pg:photos_1k":19,
    "qs_pg:photos_9k":1,
    "qs_pg:photos_9r":3,
    "qs_pg:photos_all":95,
    "qs_pg:photos_sr":3,
    "qs_pg:pop_sr":2,
    "qs_pg:qs_pg_placetype":"locality",
    "qs_pg:qs_pg_placetype_gp":"Town",
    "qs_pg:woe_adm0":23424957,
    "woe:adm0_id":23424957,
    "woe:name_adm0":"Schweiz",
    "woe:name_adm1":"Cantone Ticino",
    "woe:placetype":"Town",
    "wof:name":"Cresciano",
    "wof:placetype":"locality",
    "wof:population":624
},
  "geometry": {"coordinates":[9.00261,46.27875],"type":"Point"}
}