{
  "type": "Feature",
  "properties": {
    "gn:admin1_code":"VS",
    "gn:admin2_code":"2309.0",
    "gn:admin3_code":"6192.0",
    "gn:asciiname":"Guggistafel",
    "gn:country_code":"CH",
    "gn:dem":1926,
    "gn:feature_class":"P",
    "gn:feature_code":"PPL",
    "gn:name":"Guggistafel",
    "gn:population":0,
    "gn:timezone":"Europe/Zurich",
    "iso:country":"CH",
    "name:deu_x_preferred":[
        "Guggistafel"
    ],
    "wof:lang_x_official":[
        "deu",
        "fra",
        "gsw",
        "ita"
    ],
    "wof:lang_x_spoken":[
        "deu",
        "fra",
        "gsw",
        "ita",
        "roh"
    ],
    "wof:name":"Guggistafel",
    "wof:placetype":"neighbourhood"
},
  "geometry": {"coordinates":[7.86885,46.43947],"type":"Point"}
}