{
  "type": "Feature",
  "properties": {
    "gn:gn_country":"CH",
    "gn:gn_fcode":"PPL",
    "gn:gn_pop":1080,
    "gn:population":1080,
    "iso:country":"CH",
    "name:cat_x_preferred":[
        "Wegenstetten"
    ],
    "name:deu_x_preferred":[
        "Wegenstetten"
    ],
    "name:eng_x_preferred":[
        "Wegenstetten"
    ],
    "name:epo_x_preferred":[
        "Wegenstetten"
    ],
    "name:eus_x_preferred":[
        "Wegenstetten"
    ],
    "name:fra_x_preferred":[
        "Wegenstetten"
    ],
    "name:gsw_x_preferred":[
        "W\u00e4gestette"
    ],
    "name:hun_x_preferred":[
        "Wegenstetten"
    ],
    "name:ita_x_preferred":[
        "Wegenstetten"
    ],
    "name:kaz_x_preferred":[
        "\u0412\u0435\u0433\u0435\u043d\u0448\u0442\u0435\u0442\u0442\u0435\u043d"
    ],
    "name:lmo_x_preferred":[
        "Wegenstetten"
    ],
    "name:msa_x_preferred":[
        "Wegenstetten"
    ],
    "name:nld_x_preferred":[
        "Wegenstetten"
    ],
    "name:nno_x_preferred":[
        "Wegenstetten"
    ],
    "name:oci_x_preferred":[
        "Wegenstetten"
    ],
    "name:rus_x_preferred":[
        "\u0412\u0435\u0433\u0435\u043d\u0448\u0442\u0435\u0442\u0442\u0435\u043d"
    ],
    "name:spa_x_preferred":[
        "Wegenstetten"
    ],
    "name:sqi_x_preferred":[
        "Wegenstetten"
    ],
    "name:swe_x_preferred":[
        "Wegenstetten"
    ],
    "name:uzb_x_preferred":[
        "Wegenstetten"
    ],
    "name:vol_x_preferred":[
        "Wegenstetten"
    ],
    "name:war_x_preferred":[
        "Wegenstetten"
    ],
    "name:zho_x_preferred":[
        "\u97cb\u6839\u65bd\u6cf0\u6ed5"
    ],
    "qs_pg:aaroncc":"CH",
    "qs_pg:gn_country":"CH",
    "qs_pg:gn_fcode":"PPL",
    "qs_pg:gn_pop":1080,
    "qs_pg:name":"Wegenstetten",
    "qs_pg:name_adm0":"Schweiz",
    "qs_pg:name_adm1":"Kanton Aargau",
    "qs_pg:photos":89,
    "qs_pg:photos_1k":18,
    "qs_pg:photos_9k":1,
    "qs_pg:photos_9r":3,
    "qs_pg:photos_all":89,
    "qs_pg:photos_sr":3,
    "qs_pg:pop_sr":3,
    "qs_pg:qs_pg_placetype":"locality",
    "qs_pg:qs_pg_placetype_gp":"Town",
    "qs_pg:woe_adm0":23424957,
    "woe:adm0_id":23424957,
    "woe:name_adm0":"Schweiz",
    "woe:name_adm1":"Kanton Aargau",
    "woe:placetype":"Town",
    "wof:name":"Wegenstetten",
    "wof:placetype":"locality",
    "wof:population":1080
},
  "geometry": {"coordinates":[7.93159,47.49794],"type":"Point"}
}