{
  "type": "Feature",
  "properties": {
    "gn:gn_country":"CH",
    "gn:gn_fcode":"PPL",
    "gn:gn_pop":910,
    "gn:population":910,
    "iso:country":"CH",
    "name:alb_x_preferred":[
        "W\u00f6lflinswil"
    ],
    "name:baq_x_preferred":[
        "W\u00f6lflinswil"
    ],
    "name:cat_x_preferred":[
        "W\u00f6lflinswil"
    ],
    "name:chi_x_preferred":[
        "\u97cb\u592b\u6797\u65af\u7dad\u723e"
    ],
    "name:dut_x_preferred":[
        "W\u00f6lflinswil"
    ],
    "name:eng_x_preferred":[
        "W\u00f6lflinswil"
    ],
    "name:epo_x_preferred":[
        "W\u00f6lflinswil"
    ],
    "name:fre_x_preferred":[
        "W\u00f6lflinswil"
    ],
    "name:ger_x_preferred":[
        "W\u00f6lflinswil"
    ],
    "name:gsw_x_preferred":[
        "W\u00f6lflinswil"
    ],
    "name:hun_x_preferred":[
        "W\u00f6lflinswil"
    ],
    "name:ita_x_preferred":[
        "W\u00f6lflinswil"
    ],
    "name:kaz_x_preferred":[
        "\u0412\u0451\u043b\u044c\u0444\u043b\u0438\u043d\u0441\u0432\u0438\u043b\u044c"
    ],
    "name:lmo_x_preferred":[
        "W\u00f6lflinswil"
    ],
    "name:may_x_preferred":[
        "W\u00f6lflinswil"
    ],
    "name:nno_x_preferred":[
        "W\u00f6lflinswil"
    ],
    "name:oci_x_preferred":[
        "W\u00f6lflinswil"
    ],
    "name:rus_x_preferred":[
        "\u0412\u0451\u043b\u044c\u0444\u043b\u0438\u043d\u0441\u0432\u0438\u043b\u044c"
    ],
    "name:spa_x_preferred":[
        "W\u00f6lflinswil"
    ],
    "name:swe_x_preferred":[
        "W\u00f6lflinswil"
    ],
    "name:uzb_x_preferred":[
        "W\u00f6lflinswil"
    ],
    "name:vol_x_preferred":[
        "W\u00f6lflinswil"
    ],
    "name:war_x_preferred":[
        "W\u00f6lflinswil"
    ],
    "name:zho_x_preferred":[
        "\u97cb\u592b\u6797\u65af\u7dad\u723e"
    ],
    "qs_pg:aaroncc":"CH",
    "qs_pg:gn_country":"CH",
    "qs_pg:gn_fcode":"PPL",
    "qs_pg:gn_pop":910,
    "qs_pg:name":"W\u00f6lflinswil",
    "qs_pg:name_adm0":"Schweiz",
    "qs_pg:name_adm1":"Kanton Aargau",
    "qs_pg:photos_9k":1,
    "qs_pg:photos_9r":1,
    "qs_pg:photos_all":4,
    "qs_pg:photos_sr":0,
    "qs_pg:pop_sr":2,
    "qs_pg:qs_pg_placetype":"locality",
    "qs_pg:qs_pg_placetype_gp":"Town",
    "qs_pg:woe_adm0":23424957,
    "woe:adm0_id":23424957,
    "woe:name_adm0":"Schweiz",
    "woe:name_adm1":"Kanton Aargau",
    "woe:placetype":"Town",
    "wof:name":"W\u00f6lflinswil",
    "wof:placetype":"locality",
    "wof:population":910
},
  "geometry": {"coordinates":[7.99965,47.45811],"type":"Point"}
}