{
  "type": "Feature",
  "properties": {
    "gn:admin1_code":"AG",
    "gn:admin2_code":"1901.0",
    "gn:admin3_code":"4004.0",
    "gn:asciiname":"Herzberg",
    "gn:country_code":"CH",
    "gn:dem":694,
    "gn:feature_class":"P",
    "gn:feature_code":"PPL",
    "gn:name":"Herzberg",
    "gn:population":0,
    "gn:timezone":"Europe/Zurich",
    "iso:country":"CH",
    "wof:name":"Herzberg",
    "wof:placetype":"neighbourhood"
},
  "geometry": {"coordinates":[8.04697,47.43648],"type":"Point"}
}