{
  "type": "Feature",
  "properties": {
    "gn:admin1_code":"BE",
    "gn:admin2_code":"245.0",
    "gn:admin3_code":"901.0",
    "gn:asciiname":"Oberdornacker",
    "gn:country_code":"CH",
    "gn:dem":784,
    "gn:feature_class":"P",
    "gn:feature_code":"PPLL",
    "gn:name":"Oberdornacker",
    "gn:population":0,
    "gn:timezone":"Europe/Zurich",
    "iso:country":"CH",
    "name:deu_x_preferred":[
        "Oberdornacker"
    ],
    "wof:lang_x_official":[
        "deu",
        "fra",
        "gsw",
        "ita"
    ],
    "wof:lang_x_spoken":[
        "deu",
        "fra",
        "gsw",
        "ita",
        "roh"
    ],
    "wof:name":"Oberdornacker",
    "wof:placetype":"neighbourhood"
},
  "geometry": {"coordinates":[7.77135,46.9139],"type":"Point"}
}