{
  "type": "Feature",
  "properties": {
    "gn:gn_country":"CH",
    "gn:gn_fcode":"PPL",
    "gn:gn_pop":658,
    "gn:population":658,
    "iso:country":"CH",
    "name:dut_x_preferred":[
        "Liebistorf"
    ],
    "name:eng_x_preferred":[
        "Liebistorf"
    ],
    "name:fre_x_preferred":[
        "Liebistorf"
    ],
    "name:ger_x_preferred":[
        "Liebistorf"
    ],
    "qs_pg:aaroncc":"CH",
    "qs_pg:gn_country":"CH",
    "qs_pg:gn_fcode":"PPL",
    "qs_pg:gn_pop":658,
    "qs_pg:name":"Liebistorf",
    "qs_pg:name_adm0":"Schweiz",
    "qs_pg:name_adm1":"Canton de Fribourg",
    "qs_pg:photos_9k":1,
    "qs_pg:photos_9r":1,
    "qs_pg:photos_all":2,
    "qs_pg:photos_sr":0,
    "qs_pg:pop_sr":2,
    "qs_pg:qs_pg_placetype":"locality",
    "qs_pg:qs_pg_placetype_gp":"Town",
    "qs_pg:woe_adm0":23424957,
    "woe:adm0_id":23424957,
    "woe:name_adm0":"Schweiz",
    "woe:name_adm1":"Canton de Fribourg",
    "woe:placetype":"Town",
    "wof:name":"Liebistorf",
    "wof:placetype":"locality",
    "wof:population":658
},
  "geometry": {"coordinates":[7.19636,46.90881],"type":"Point"}
}