{
  "type": "Feature",
  "properties": {
    "gn:elevation":569,
    "iso:country":"CH",
    "name:deu_x_preferred":[
        "Niederwangen"
    ],
    "name:eng_x_preferred":[
        "Niederwargen"
    ],
    "name:eng_x_variant":[
        "Niederwargen"
    ],
    "name:unk_x_variant":[
        "Niederwangen"
    ],
    "qs:gn_fcode":"PPL",
    "qs:gn_local":0,
    "qs:gn_namadm1":"BE",
    "qs:gn_name":"Niederwangen",
    "qs:local_max":4550,
    "qs:local_sum":6457,
    "qs:localhoods":6,
    "qs:name":"Niederwangen",
    "qs:name_adm0":"Schweiz",
    "qs:name_adm1":"Kanton Bern",
    "qs:name_adm2":"Bern-Mittelland",
    "qs:name_en":"Niederwargen",
    "qs:name_lau":"K\u00f6niz",
    "qs:name_local":"K\u00f6niz",
    "qs:photo_max":23,
    "qs:photo_sum":55,
    "qs:placetype":"Suburb",
    "qs:quad_count":11,
    "qs:woe_adm0":23424957,
    "qs:woe_adm1":2347087,
    "qs:woe_adm2":56558125,
    "qs:woe_lau":12683628,
    "qs:woe_local":12683628,
    "qs:woe_ver":"7.10.0",
    "wof:lang":[
        "ger"
    ],
    "wof:name":"Niederwangen",
    "wof:placetype":"neighbourhood"
},
  "geometry": {"coordinates":[7.375746,46.924536],"type":"Point"}
}