{
  "type": "Feature",
  "properties": {
    "gn:admin1_code":"ZG",
    "gn:admin2_code":"900.0",
    "gn:admin3_code":"1701.0",
    "gn:asciiname":"Unterstock",
    "gn:country_code":"CH",
    "gn:dem":750,
    "gn:feature_class":"P",
    "gn:feature_code":"PPLL",
    "gn:name":"Unterstock",
    "gn:population":0,
    "gn:timezone":"Europe/Zurich",
    "iso:country":"CH",
    "name:deu_x_preferred":[
        "Unterstock"
    ],
    "wof:name":"Unterstock",
    "wof:placetype":"neighbourhood"
},
  "geometry": {"coordinates":[8.5536,47.16036],"type":"Point"}
}