{
  "type": "Feature",
  "properties": {
    "gn:gn_country":"CH",
    "gn:gn_fcode":"PPL",
    "gn:gn_pop":641,
    "gn:population":641,
    "iso:country":"CH",
    "name:alb_x_preferred":[
        "Ochlenberg"
    ],
    "name:baq_x_preferred":[
        "Ochlenberg"
    ],
    "name:cat_x_preferred":[
        "Ochlenberg"
    ],
    "name:chi_x_preferred":[
        "\u5967\u8d6b\u502b\u8c9d\u683c"
    ],
    "name:dut_x_preferred":[
        "Ochlenberg"
    ],
    "name:eng_x_preferred":[
        "Ochlenberg"
    ],
    "name:epo_x_preferred":[
        "Ochlenberg"
    ],
    "name:fre_x_preferred":[
        "Ochlenberg"
    ],
    "name:ger_x_preferred":[
        "Ochlenberg"
    ],
    "name:gsw_x_preferred":[
        "Ochleberg"
    ],
    "name:hun_x_preferred":[
        "Ochlenberg"
    ],
    "name:ita_x_preferred":[
        "Ochlenberg"
    ],
    "name:kaz_x_preferred":[
        "\u041e\u0445\u043b\u0435\u043d\u0431\u0435\u0440\u0433"
    ],
    "name:lmo_x_preferred":[
        "Ochlenberg"
    ],
    "name:may_x_preferred":[
        "Ochlenberg"
    ],
    "name:nno_x_preferred":[
        "Ochlenberg"
    ],
    "name:oci_x_preferred":[
        "Ochlenberg"
    ],
    "name:pol_x_preferred":[
        "Ochlenberg"
    ],
    "name:rus_x_preferred":[
        "\u041e\u0445\u043b\u0435\u043d\u0431\u0435\u0440\u0433"
    ],
    "name:spa_x_preferred":[
        "Ochlenberg"
    ],
    "name:swe_x_preferred":[
        "Ochlenberg"
    ],
    "name:vie_x_preferred":[
        "Ochlenberg"
    ],
    "name:vol_x_preferred":[
        "Ochlenberg"
    ],
    "name:war_x_preferred":[
        "Ochlenberg"
    ],
    "qs_pg:aaroncc":"CH",
    "qs_pg:gn_country":"CH",
    "qs_pg:gn_fcode":"PPL",
    "qs_pg:gn_pop":641,
    "qs_pg:name":"Ochlenberg",
    "qs_pg:name_adm0":"Schweiz",
    "qs_pg:name_adm1":"Kanton Bern",
    "qs_pg:photos_9r":0,
    "qs_pg:photos_sr":0,
    "qs_pg:pop_sr":2,
    "qs_pg:qs_pg_placetype":"locality",
    "qs_pg:qs_pg_placetype_gp":"Town",
    "qs_pg:woe_adm0":23424957,
    "woe:adm0_id":23424957,
    "woe:name_adm0":"Schweiz",
    "woe:name_adm1":"Kanton Bern",
    "woe:placetype":"Town",
    "wof:name":"Ochlenberg",
    "wof:placetype":"locality",
    "wof:population":641
},
  "geometry": {"coordinates":[7.73603,47.14953],"type":"Point"}
}