{
  "type": "Feature",
  "properties": {
    "gn:gn_country":"CH",
    "gn:gn_fcode":"PPL",
    "gn:gn_pop":2321,
    "gn:population":2321,
    "iso:country":"CH",
    "name:cat_x_preferred":[
        "Ilanz"
    ],
    "name:ceb_x_preferred":[
        "Ilanz"
    ],
    "name:deu_x_preferred":[
        "Ilanz/Glion"
    ],
    "name:deu_x_variant":[
        "Ilanz"
    ],
    "name:epo_x_preferred":[
        "Ilanz"
    ],
    "name:fas_x_preferred":[
        "\u0627\u06cc\u0644\u0627\u0646\u0632"
    ],
    "name:fra_x_preferred":[
        "Ilanz"
    ],
    "name:ind_x_preferred":[
        "Ilanz"
    ],
    "name:ita_x_preferred":[
        "Ilanz"
    ],
    "name:kaz_x_preferred":[
        "\u0418\u043b\u0430\u043d\u0446"
    ],
    "name:lat_x_preferred":[
        "Iliande"
    ],
    "name:lmo_x_preferred":[
        "Ilanz"
    ],
    "name:msa_x_preferred":[
        "Ilanz"
    ],
    "name:nld_x_preferred":[
        "Ilanz/Glion"
    ],
    "name:nno_x_preferred":[
        "Ilanz"
    ],
    "name:pms_x_preferred":[
        "Ilanz"
    ],
    "name:por_x_preferred":[
        "Ilanz"
    ],
    "name:roh_x_preferred":[
        "Glion"
    ],
    "name:rus_x_preferred":[
        "\u0418\u043b\u0430\u043d\u0446"
    ],
    "name:spa_x_preferred":[
        "Ilanz"
    ],
    "name:sqi_x_preferred":[
        "Ilanz"
    ],
    "name:swe_x_preferred":[
        "Ilanz/Glion"
    ],
    "name:uzb_x_preferred":[
        "Ilanz"
    ],
    "name:vol_x_preferred":[
        "Ilanz"
    ],
    "name:war_x_preferred":[
        "Ilanz"
    ],
    "name:zho_x_preferred":[
        "\u4f0a\u5170\u8328"
    ],
    "qs:a0":"Schweiz#Suisse#Svizzera#Svizra",
    "qs:a1":"*Graub\u00fcnden",
    "qs:a1r":"0",
    "qs:adm0":"Schweiz#Suisse#Svizzera#Svizra",
    "qs:la_lc":"*",
    "qs:level":"locality",
    "qs:loc":"Ilanz",
    "qs:loc_alt":"Ilanz",
    "qs:pop":0,
    "qs:type":"buffered point",
    "qs_pg:aaroncc":"CH",
    "qs_pg:gn_country":"CH",
    "qs_pg:gn_fcode":"PPL",
    "qs_pg:gn_pop":2321,
    "qs_pg:name":"Ilanz",
    "qs_pg:name_adm0":"Schweiz",
    "qs_pg:name_adm1":"Kanton Graub\u00fcnden",
    "qs_pg:photos":245,
    "qs_pg:photos_1k":50,
    "qs_pg:photos_9k":1,
    "qs_pg:photos_9r":4,
    "qs_pg:photos_all":245,
    "qs_pg:photos_sr":4,
    "qs_pg:pop_sr":4,
    "qs_pg:qs_pg_placetype":"locality",
    "qs_pg:qs_pg_placetype_gp":"Town",
    "qs_pg:woe_adm0":23424957,
    "wd:wordcount":1414,
    "wof:name":"Ilanz",
    "wof:placetype":"locality",
    "wof:population":2321
},
  "geometry": {"coordinates":[9.208291,46.77555],"type":"Point"}
}