{
  "type": "Feature",
  "properties": {
    "gn:population":2559,
    "iso:country":"CH",
    "name:alb_x_preferred":[
        "Eggiwil"
    ],
    "name:als_x_preferred":[
        "Eggiwil"
    ],
    "name:baq_x_preferred":[
        "Eggiwil"
    ],
    "name:cat_x_preferred":[
        "Eggiwil"
    ],
    "name:ceb_x_preferred":[
        "Eggiwil"
    ],
    "name:chi_x_preferred":[
        "\u57c3\u5409\u7dad\u723e"
    ],
    "name:chv_x_preferred":[
        "\u042d\u0433\u0433\u0438\u0432\u0438\u043b\u044c"
    ],
    "name:deu_x_preferred":[
        "Eggiwil"
    ],
    "name:dut_x_preferred":[
        "Eggiwil"
    ],
    "name:eng_x_preferred":[
        "Eggiwil"
    ],
    "name:epo_x_preferred":[
        "Eggiwil"
    ],
    "name:eus_x_preferred":[
        "Eggiwil"
    ],
    "name:fra_x_preferred":[
        "Eggiwil"
    ],
    "name:fre_x_preferred":[
        "Eggiwil"
    ],
    "name:ger_x_preferred":[
        "Eggiwil"
    ],
    "name:gsw_x_preferred":[
        "Eggiwiu"
    ],
    "name:hun_x_preferred":[
        "Eggiwil"
    ],
    "name:ita_x_preferred":[
        "Eggiwil"
    ],
    "name:kaz_x_preferred":[
        "\u042d\u0433\u0433\u0438\u0432\u0438\u043b\u044c"
    ],
    "name:lmo_x_preferred":[
        "Eggiwil"
    ],
    "name:may_x_preferred":[
        "Eggiwil"
    ],
    "name:msa_x_preferred":[
        "Eggiwil"
    ],
    "name:nld_x_preferred":[
        "Eggiwil"
    ],
    "name:nno_x_preferred":[
        "Eggiwil"
    ],
    "name:oci_x_preferred":[
        "Eggiwil"
    ],
    "name:rus_x_preferred":[
        "\u042d\u0433\u0433\u0438\u0432\u0438\u043b\u044c"
    ],
    "name:spa_x_preferred":[
        "Eggiwil"
    ],
    "name:sqi_x_preferred":[
        "Eggiwil"
    ],
    "name:swe_x_preferred":[
        "Eggiwil"
    ],
    "name:vie_x_preferred":[
        "Eggiwil"
    ],
    "name:vol_x_preferred":[
        "Eggiwil"
    ],
    "name:war_x_preferred":[
        "Eggiwil"
    ],
    "name:zho_x_preferred":[
        "\u57c3\u5409\u7dad\u723e"
    ],
    "qs:a0":"Schweiz#Suisse#Svizzera#Svizra",
    "qs:a1":"*Bern",
    "qs:a1r":"0",
    "qs:adm0":"Schweiz#Suisse#Svizzera#Svizra",
    "qs:la_lc":"*",
    "qs:level":"locality",
    "qs:loc":"Eggiwil",
    "qs:loc_alt":"Eggiwil",
    "qs:pop":0,
    "qs:type":"buffered point",
    "wd:wordcount":2316,
    "wof:lang":[
        "ger"
    ],
    "wof:name":"Eggiwil",
    "wof:placetype":"locality",
    "wof:population":2559
},
  "geometry": {"coordinates":[7.795894,46.875782],"type":"Point"}
}