{
  "type": "Feature",
  "properties": {
    "gn:admin1_code":"TG",
    "gn:admin2_code":"2012.0",
    "gn:admin3_code":"4811.0",
    "gn:asciiname":"Meienberg",
    "gn:country_code":"CH",
    "gn:dem":586,
    "gn:feature_class":"P",
    "gn:feature_code":"PPLL",
    "gn:name":"Meienberg",
    "gn:population":0,
    "gn:timezone":"Europe/Zurich",
    "iso:country":"CH",
    "name:deu_x_preferred":[
        "Meienberg"
    ],
    "wof:name":"Meienberg",
    "wof:placetype":"neighbourhood"
},
  "geometry": {"coordinates":[8.92669,47.62637],"type":"Point"}
}