{
  "type": "Feature",
  "properties": {
    "gn:gn_country":"CH",
    "gn:gn_fcode":"PPL",
    "gn:gn_pop":2841,
    "gn:population":2841,
    "iso:country":"CH",
    "name:als_x_preferred":[
        "Chavornay VD"
    ],
    "name:baq_x_preferred":[
        "Chavornay"
    ],
    "name:chi_x_preferred":[
        "\u6c99\u6c83\u5c14\u5948"
    ],
    "name:cze_x_preferred":[
        "Chavornay"
    ],
    "name:deu_x_preferred":[
        "Chavornay VD"
    ],
    "name:dut_x_preferred":[
        "Chavornay"
    ],
    "name:eng_x_preferred":[
        "Chavornay"
    ],
    "name:epo_x_preferred":[
        "Chavornay VD"
    ],
    "name:fre_x_preferred":[
        "Chavornay"
    ],
    "name:ger_x_preferred":[
        "Chavornay"
    ],
    "name:gsw_x_preferred":[
        "Chavornay VD"
    ],
    "name:hun_x_preferred":[
        "Chavornay"
    ],
    "name:ita_x_preferred":[
        "Chavornay"
    ],
    "name:lmo_x_preferred":[
        "Chavornay"
    ],
    "name:may_x_preferred":[
        "Chavornay"
    ],
    "name:nno_x_preferred":[
        "Chavornay i Vaud"
    ],
    "name:roh_x_preferred":[
        "Chavornay"
    ],
    "name:slo_x_preferred":[
        "Chavornay"
    ],
    "name:spa_x_preferred":[
        "Chavornay"
    ],
    "name:vie_x_preferred":[
        "Chavornay"
    ],
    "name:vol_x_preferred":[
        "Chavornay"
    ],
    "name:zho_x_preferred":[
        "\u6c99\u6c83\u5c14\u5948"
    ],
    "qs_pg:aaroncc":"CH",
    "qs_pg:gn_country":"CH",
    "qs_pg:gn_fcode":"PPL",
    "qs_pg:gn_pop":2841,
    "qs_pg:name":"Chavornay",
    "qs_pg:name_adm0":"Schweiz",
    "qs_pg:name_adm1":"Canton de Vaud",
    "qs_pg:photos":54,
    "qs_pg:photos_1k":11,
    "qs_pg:photos_9k":1,
    "qs_pg:photos_9r":2,
    "qs_pg:photos_all":54,
    "qs_pg:photos_sr":2,
    "qs_pg:pop_sr":4,
    "qs_pg:qs_pg_placetype":"locality",
    "qs_pg:qs_pg_placetype_gp":"Town",
    "qs_pg:woe_adm0":23424957,
    "woe:adm0_id":23424957,
    "woe:name_adm0":"Schweiz",
    "woe:name_adm1":"Canton de Vaud",
    "woe:placetype":"Town",
    "wof:name":"Chavornay",
    "wof:placetype":"locality",
    "wof:population":2841
},
  "geometry": {"coordinates":[6.5694,46.70244],"type":"Point"}
}