{
  "type": "Feature",
  "properties": {
    "gn:admin1_code":"NW",
    "gn:admin2_code":"700.0",
    "gn:admin3_code":"1511.0",
    "gn:asciiname":"Huiterdorf",
    "gn:country_code":"CH",
    "gn:dem":530,
    "gn:feature_class":"P",
    "gn:feature_code":"PPL",
    "gn:name":"Huiterdorf",
    "gn:population":0,
    "gn:timezone":"Europe/Zurich",
    "iso:country":"CH",
    "wof:name":"Huiterdorf",
    "wof:placetype":"neighbourhood"
},
  "geometry": {"coordinates":[8.39241,46.89697],"type":"Point"}
}