{
  "type": "Feature",
  "properties": {
    "gn:gn_country":"CH",
    "gn:gn_fcode":"PPL",
    "gn:gn_pop":153,
    "gn:population":153,
    "iso:country":"CH",
    "qs_pg:aaroncc":"CH",
    "qs_pg:gn_country":"CH",
    "qs_pg:gn_fcode":"PPL",
    "qs_pg:gn_pop":153,
    "qs_pg:name":"B\u00f6nler",
    "qs_pg:photos_9r":0,
    "qs_pg:photos_sr":0,
    "qs_pg:pop_sr":1,
    "qs_pg:qs_pg_placetype":"locality",
    "wof:name":"B\u00f6nler",
    "wof:placetype":"neighbourhood",
    "wof:population":153
},
  "geometry": {"coordinates":[8.79033,47.30611],"type":"Point"}
}