{
  "type": "Feature",
  "properties": {
    "gn:admin1_code":"ZH",
    "gn:admin2_code":"105.0",
    "gn:admin3_code":"114.0",
    "gn:asciiname":"Goggelswald",
    "gn:country_code":"CH",
    "gn:dem":982,
    "gn:feature_class":"P",
    "gn:feature_code":"PPLL",
    "gn:name":"Goggelswald",
    "gn:population":0,
    "gn:timezone":"Europe/Zurich",
    "iso:country":"CH",
    "wof:name":"Goggelswald",
    "wof:placetype":"neighbourhood"
},
  "geometry": {"coordinates":[8.94835,47.35857],"type":"Point"}
}