{
  "type": "Feature",
  "properties": {
    "gn:admin1_code":"TG",
    "gn:admin2_code":"2012.0",
    "gn:admin3_code":"4811.0",
    "gn:asciiname":"Eggmuehle",
    "gn:country_code":"CH",
    "gn:dem":546,
    "gn:feature_class":"P",
    "gn:feature_code":"PPLL",
    "gn:name":"Eggm\u00fchle",
    "gn:population":0,
    "gn:timezone":"Europe/Zurich",
    "iso:country":"CH",
    "name:deu_x_preferred":[
        "Eggm\u00fchle"
    ],
    "wof:name":"Eggmuehle",
    "wof:placetype":"locality"
},
  "geometry": {"coordinates":[8.91272,47.62928],"type":"Point"}
}