{
  "type": "Feature",
  "properties": {
    "gn:gn_country":"CH",
    "gn:gn_fcode":"PPLX",
    "gn:gn_pop":13,
    "gn:population":13,
    "iso:country":"CH",
    "name:unk_x_variant":[
        "Schweikhof"
    ],
    "qs_pg:aaroncc":"CH",
    "qs_pg:gn_country":"CH",
    "qs_pg:gn_fcode":"PPLX",
    "qs_pg:gn_pop":13,
    "qs_pg:name":"W\u00fclflingen (Kreis 6) / Schweikhof",
    "qs_pg:photos_9r":0,
    "qs_pg:photos_sr":0,
    "qs_pg:pop_sr":1,
    "qs_pg:qs_pg_placetype":"neighbourhood",
    "wof:name":"W\u00fclflingen (Kreis 6) / Schweikhof",
    "wof:placetype":"neighbourhood",
    "wof:population":13
},
  "geometry": {"coordinates":[8.67443,47.50191],"type":"Point"}
}