{
  "type": "Feature",
  "properties": {
    "gn:admin1_code":"VD",
    "gn:admin2_code":"2228.0",
    "gn:admin3_code":"5715.0",
    "gn:asciiname":"Changins",
    "gn:country_code":"CH",
    "gn:dem":438,
    "gn:feature_class":"P",
    "gn:feature_code":"PPL",
    "gn:name":"Changins",
    "gn:population":0,
    "gn:timezone":"Europe/Zurich",
    "iso:country":"CH",
    "wof:name":"Changins",
    "wof:placetype":"locality"
},
  "geometry": {"coordinates":[6.2327,46.39894],"type":"Point"}
}