{
  "type": "Feature",
  "properties": {
    "gn:admin1_code":"GR",
    "gn:admin2_code":"1848.0",
    "gn:admin3_code":"3921.0",
    "gn:asciiname":"Lueen",
    "gn:country_code":"CH",
    "gn:dem":996,
    "gn:feature_class":"P",
    "gn:feature_code":"PPL",
    "gn:name":"L\u00fcen",
    "gn:population":0,
    "gn:timezone":"Europe/Zurich",
    "iso:country":"CH",
    "name:kaz_x_preferred":[
        "\u041b\u044e\u044d\u043d"
    ],
    "name:rus_x_preferred":[
        "\u041b\u044e\u044d\u043d"
    ],
    "name:und_x_variant":[
        "L\u00fcen"
    ],
    "name:zho_x_preferred":[
        "\u5442\u6069"
    ],
    "wof:name":"Lueen",
    "wof:placetype":"locality"
},
  "geometry": {"coordinates":[9.61417,46.83314],"type":"Point"}
}