{
  "type": "Feature",
  "properties": {
    "gn:gn_country":"CH",
    "gn:gn_fcode":"PPLX",
    "gn:gn_pop":37,
    "gn:population":37,
    "iso:country":"CH",
    "name:unk_x_variant":[
        "Sch\u00e4llen"
    ],
    "qs_pg:aaroncc":"CH",
    "qs_pg:gn_country":"CH",
    "qs_pg:gn_fcode":"PPLX",
    "qs_pg:gn_pop":37,
    "qs_pg:name":"Meilen / Sch\u00e4llen",
    "qs_pg:photos_9r":0,
    "qs_pg:photos_sr":0,
    "qs_pg:pop_sr":1,
    "qs_pg:qs_pg_placetype":"neighbourhood",
    "wof:name":"Meilen / Sch\u00e4llen",
    "wof:placetype":"neighbourhood",
    "wof:population":37
},
  "geometry": {"coordinates":[8.64936,47.26745],"type":"Point"}
}