{
  "type": "Feature",
  "properties": {
    "gn:gn_country":"CH",
    "gn:gn_fcode":"PPL",
    "gn:gn_pop":157,
    "gn:population":157,
    "iso:country":"CH",
    "name:cat_x_preferred":[
        "Verdabbio"
    ],
    "name:deu_x_preferred":[
        "Verdabbio"
    ],
    "name:eng_x_preferred":[
        "Verdabbio"
    ],
    "name:epo_x_preferred":[
        "Verdabbio"
    ],
    "name:eus_x_preferred":[
        "Verdabbio"
    ],
    "name:fra_x_preferred":[
        "Verdabbio"
    ],
    "name:hun_x_preferred":[
        "Verdabbio"
    ],
    "name:ita_x_preferred":[
        "Verdabbio"
    ],
    "name:kaz_x_preferred":[
        "\u0412\u0435\u0440\u0434\u0430\u0431\u0431\u0438\u043e"
    ],
    "name:lmo_x_preferred":[
        "Verdabi"
    ],
    "name:msa_x_preferred":[
        "Verdabbio"
    ],
    "name:nld_x_preferred":[
        "Verdabbio"
    ],
    "name:nno_x_preferred":[
        "Verdabbio"
    ],
    "name:oci_x_preferred":[
        "Verdabbio"
    ],
    "name:pms_x_preferred":[
        "Verdabbio"
    ],
    "name:por_x_preferred":[
        "Verdabbio"
    ],
    "name:roh_x_preferred":[
        "Verdabbio"
    ],
    "name:rus_x_preferred":[
        "\u0412\u0435\u0440\u0434\u0430\u0431\u0431\u0438\u043e"
    ],
    "name:spa_x_preferred":[
        "Verdabbio"
    ],
    "name:sqi_x_preferred":[
        "Verdabbio"
    ],
    "name:swe_x_preferred":[
        "Verdabbio"
    ],
    "name:uzb_x_preferred":[
        "Verdabbio"
    ],
    "name:vol_x_preferred":[
        "Verdabbio"
    ],
    "name:war_x_preferred":[
        "Verdabbio"
    ],
    "name:zho_x_preferred":[
        "\u97cb\u723e\u9054\u6bd4\u5967"
    ],
    "qs_pg:aaroncc":"CH",
    "qs_pg:gn_country":"CH",
    "qs_pg:gn_fcode":"PPL",
    "qs_pg:gn_pop":157,
    "qs_pg:name":"Verdabbio",
    "qs_pg:name_adm0":"Schweiz",
    "qs_pg:name_adm1":"Kanton Graub\u00fcnden",
    "qs_pg:photos":4,
    "qs_pg:photos_1k":1,
    "qs_pg:photos_9k":1,
    "qs_pg:photos_9r":1,
    "qs_pg:photos_all":4,
    "qs_pg:photos_sr":1,
    "qs_pg:pop_sr":1,
    "qs_pg:qs_pg_placetype":"locality",
    "qs_pg:qs_pg_placetype_gp":"Town",
    "qs_pg:woe_adm0":23424957,
    "woe:adm0_id":23424957,
    "woe:name_adm0":"Schweiz",
    "woe:name_adm1":"Kanton Graub\u00fcnden",
    "woe:placetype":"Town",
    "wof:name":"Verdabbio",
    "wof:placetype":"locality",
    "wof:population":157
},
  "geometry": {"coordinates":[9.15806,46.26832],"type":"Point"}
}