{
  "type": "Feature",
  "properties": {
    "iso:country":"CH",
    "name:cat_x_preferred":[
        "La Muraz"
    ],
    "name:ceb_x_preferred":[
        "La Muraz"
    ],
    "name:che_x_preferred":[
        "\u041b\u0430-\u041c\u044e\u0440\u0430"
    ],
    "name:deu_x_preferred":[
        "La Muraz"
    ],
    "name:diq_x_preferred":[
        "La Muraz"
    ],
    "name:epo_x_preferred":[
        "La Muraz"
    ],
    "name:eus_x_preferred":[
        "La Muraz"
    ],
    "name:fra_x_preferred":[
        "La Muraz"
    ],
    "name:hun_x_preferred":[
        "La Muraz"
    ],
    "name:ita_x_preferred":[
        "La Muraz"
    ],
    "name:lat_x_preferred":[
        "Murata"
    ],
    "name:lmo_x_preferred":[
        "La Muraz"
    ],
    "name:ltz_x_preferred":[
        "La Muraz"
    ],
    "name:mlg_x_preferred":[
        "La Muraz"
    ],
    "name:msa_x_preferred":[
        "La Muraz"
    ],
    "name:nld_x_preferred":[
        "La Muraz"
    ],
    "name:oci_x_preferred":[
        "La Muraz"
    ],
    "name:pol_x_preferred":[
        "La Muraz"
    ],
    "name:ron_x_preferred":[
        "La Muraz"
    ],
    "name:slk_x_preferred":[
        "La Muraz"
    ],
    "name:spa_x_preferred":[
        "La Muraz"
    ],
    "name:swe_x_preferred":[
        "La Muraz"
    ],
    "name:ukr_x_preferred":[
        "\u041b\u0430-\u041c\u044e\u0440\u0430"
    ],
    "name:urd_x_preferred":[
        "\u0644\u0627 \u0645\u0648\u0631\u0627\u0632"
    ],
    "name:uzb_x_preferred":[
        "La Muraz"
    ],
    "name:vec_x_preferred":[
        "La Muraz"
    ],
    "name:vie_x_preferred":[
        "La Muraz"
    ],
    "name:vol_x_preferred":[
        "La Muraz"
    ],
    "name:war_x_preferred":[
        "La Muraz"
    ],
    "qs_pg:aaroncc":"CH",
    "qs_pg:name":"La Muraz",
    "qs_pg:name_adm0":"Schweiz",
    "qs_pg:name_adm1":"Canton de Valais",
    "qs_pg:photos":71,
    "qs_pg:photos_1k":14,
    "qs_pg:photos_9k":1,
    "qs_pg:photos_9r":2,
    "qs_pg:photos_all":71,
    "qs_pg:photos_sr":2,
    "qs_pg:pop_sr":0,
    "qs_pg:qs_pg_placetype":"locality",
    "qs_pg:qs_pg_placetype_gp":"Town",
    "qs_pg:woe_adm0":23424957,
    "woe:adm0_id":23424957,
    "woe:name_adm0":"Schweiz",
    "woe:name_adm1":"Canton de Valais",
    "woe:placetype":"Town",
    "wof:name":"La Muraz",
    "wof:placetype":"neighbourhood"
},
  "geometry": {"coordinates":[7.336421,46.233201],"type":"Point"}
}