{
  "type": "Feature",
  "properties": {
    "gn:admin1_code":"TI",
    "gn:admin2_code":"2105.0",
    "gn:admin3_code":"5238.0",
    "gn:asciiname":"Corte di Sopra",
    "gn:country_code":"CH",
    "gn:dem":1524,
    "gn:feature_class":"P",
    "gn:feature_code":"PPL",
    "gn:name":"Corte di Sopra",
    "gn:population":0,
    "gn:timezone":"Europe/Zurich",
    "iso:country":"CH",
    "name:ita_x_preferred":[
        "Corte di Sopra"
    ],
    "wof:name":"Corte di Sopra",
    "wof:placetype":"neighbourhood"
},
  "geometry": {"coordinates":[8.89337,46.11711],"type":"Point"}
}