{
  "type": "Feature",
  "properties": {
    "gn:admin1_code":"BE",
    "gn:admin2_code":"245.0",
    "gn:admin3_code":"956.0",
    "gn:asciiname":"Neuegg",
    "gn:country_code":"CH",
    "gn:dem":814,
    "gn:feature_class":"P",
    "gn:feature_code":"PPLL",
    "gn:name":"Neuegg",
    "gn:population":0,
    "gn:timezone":"Europe/Zurich",
    "iso:country":"CH",
    "name:deu_x_preferred":[
        "Neuegg"
    ],
    "wof:name":"Neuegg",
    "wof:placetype":"neighbourhood"
},
  "geometry": {"coordinates":[7.72246,47.03882],"type":"Point"}
}