{
  "type": "Feature",
  "properties": {
    "gn:country":"CH",
    "gn:fcode":"PPL",
    "gn:population":221,
    "iso:country":"CH",
    "name:cat_x_preferred":[
        "Sevgein"
    ],
    "name:ceb_x_preferred":[
        "Seewis"
    ],
    "name:deu_x_preferred":[
        "Sevgein"
    ],
    "name:eng_x_preferred":[
        "Sevgein"
    ],
    "name:epo_x_preferred":[
        "Sevgein"
    ],
    "name:fra_x_preferred":[
        "Sevgein"
    ],
    "name:hun_x_preferred":[
        "Sevgein"
    ],
    "name:ita_x_preferred":[
        "Sevgein"
    ],
    "name:kaz_x_preferred":[
        "\u0421\u0435\u0432\u0433\u0430\u0439\u043d"
    ],
    "name:lmo_x_preferred":[
        "Sevgein"
    ],
    "name:msa_x_preferred":[
        "Sevgein"
    ],
    "name:nld_x_preferred":[
        "Sevgein"
    ],
    "name:nno_x_preferred":[
        "Sevgein"
    ],
    "name:oci_x_preferred":[
        "Sevgein"
    ],
    "name:pms_x_preferred":[
        "Sevgein"
    ],
    "name:por_x_preferred":[
        "Sevgein"
    ],
    "name:roh_x_preferred":[
        "Sevgein"
    ],
    "name:rus_x_preferred":[
        "\u0421\u0435\u0432\u0433\u0430\u0439\u043d"
    ],
    "name:spa_x_preferred":[
        "Sevgein"
    ],
    "name:sqi_x_preferred":[
        "Sevgein"
    ],
    "name:swe_x_preferred":[
        "Sevgein"
    ],
    "name:und_x_variant":[
        "Seewis im Oberland"
    ],
    "name:uzb_x_preferred":[
        "Sevgein"
    ],
    "name:vol_x_preferred":[
        "Sevgein"
    ],
    "name:war_x_preferred":[
        "Sevgein"
    ],
    "name:zho_x_preferred":[
        "\u585e\u5f17\u84cb\u56e0"
    ],
    "qs_pg:aaroncc":"CH",
    "qs_pg:gn_country":"CH",
    "qs_pg:gn_fcode":"PPL",
    "qs_pg:gn_pop":221,
    "qs_pg:name":"Seewis",
    "qs_pg:name_adm0":"Schweiz",
    "qs_pg:name_adm1":"Kanton Graub\u00fcnden",
    "qs_pg:photos_9k":1,
    "qs_pg:photos_9r":1,
    "qs_pg:photos_all":1,
    "qs_pg:photos_sr":0,
    "qs_pg:pop_sr":2,
    "qs_pg:qs_pg_placetype":"locality",
    "qs_pg:qs_pg_placetype_gp":"Town",
    "qs_pg:woe_adm0":23424957,
    "woe:adm0_id":23424957,
    "woe:name_adm0":"Schweiz",
    "woe:name_adm1":"Kanton Graub\u00fcnden",
    "woe:placetype":"Town",
    "wof:name":"Seewis",
    "wof:placetype":"neighbourhood",
    "wof:population":221
},
  "geometry": {"coordinates":[9.21998,46.76553],"type":"Point"}
}