{
  "type": "Feature",
  "properties": {
    "gn:population":2193,
    "iso:country":"CH",
    "name:ara_x_preferred":[
        "\u062f\u064a\u0633\u064a\u0646\u062a\u064a\u0633"
    ],
    "name:bul_x_preferred":[
        "\u0414\u0438\u0441\u0435\u043d\u0442\u0438\u0441"
    ],
    "name:cat_x_preferred":[
        "Disentis/Must\u00e9r"
    ],
    "name:deu_x_preferred":[
        "Disentis"
    ],
    "name:deu_x_variant":[
        "Disentis/Must\u00e9r"
    ],
    "name:eng_x_preferred":[
        "Disentis/Must\u00e9r"
    ],
    "name:epo_x_preferred":[
        "Disentis/Must\u00e9r"
    ],
    "name:eus_x_preferred":[
        "Disentis/Must\u00e9r"
    ],
    "name:fin_x_preferred":[
        "Disentis/Must\u00e9r"
    ],
    "name:fra_x_preferred":[
        "Disentis/Must\u00e9r"
    ],
    "name:hun_x_preferred":[
        "Disentis/Must\u00e9r"
    ],
    "name:ind_x_preferred":[
        "Disentis/Must\u00e9r"
    ],
    "name:ita_x_preferred":[
        "Disentis/Must\u00e9r"
    ],
    "name:jpn_x_preferred":[
        "\u30c7\u30a3\u30bc\u30f3\u30c6\u30a3\u30b9"
    ],
    "name:kat_x_preferred":[
        "\u10d3\u10d8\u10e1\u10d4\u10dc\u10e2\u10d8\u10e1\u10d8"
    ],
    "name:kaz_x_preferred":[
        "\u0414\u0438\u0441\u0435\u043d\u0442\u0438\u0441"
    ],
    "name:lat_x_preferred":[
        "Desertina"
    ],
    "name:lmo_x_preferred":[
        "Disentis/Must\u00e9r"
    ],
    "name:msa_x_preferred":[
        "Disentis/Must\u00e9r"
    ],
    "name:nld_x_preferred":[
        "Disentis"
    ],
    "name:nno_x_preferred":[
        "Disentis/Must\u00e9r"
    ],
    "name:nob_x_preferred":[
        "Disentis/Must\u00e9r"
    ],
    "name:oci_x_preferred":[
        "Disentis/Must\u00e9r"
    ],
    "name:pms_x_preferred":[
        "Disentis"
    ],
    "name:por_x_preferred":[
        "Disentis/Must\u00e9r"
    ],
    "name:roh_x_preferred":[
        "Must\u00e9r"
    ],
    "name:ron_x_preferred":[
        "Disentis/Must\u00e9r"
    ],
    "name:rus_x_preferred":[
        "\u0414\u0438\u0441\u0435\u043d\u0442\u0438\u0441"
    ],
    "name:spa_x_preferred":[
        "Disentis/Must\u00e9r"
    ],
    "name:sqi_x_preferred":[
        "Disentis/Must\u00e9r"
    ],
    "name:swe_x_preferred":[
        "Disentis/Must\u00e9r"
    ],
    "name:uzb_x_preferred":[
        "Disentis/Must\u00e9r"
    ],
    "name:vol_x_preferred":[
        "Disentis"
    ],
    "name:war_x_preferred":[
        "Disentis/Must\u00e9r"
    ],
    "name:zho_x_preferred":[
        "\u8fea\u68ee\u8482\u65af"
    ],
    "qs:a0":"Schweiz#Suisse#Svizzera#Svizra",
    "qs:a1":"*Graub\u00fcnden",
    "qs:a1r":"0",
    "qs:adm0":"Schweiz#Suisse#Svizzera#Svizra",
    "qs:la_lc":"*",
    "qs:level":"locality",
    "qs:loc":"Disentis/Must\u00e9r",
    "qs:loc_alt":"Disentis/Muster",
    "qs:pop":0,
    "qs:type":"buffered point",
    "wof:name":"Disentis/Must\u00e9r",
    "wof:placetype":"locality",
    "wof:population":2193
},
  "geometry": {"coordinates":[8.856038,46.704754],"type":"Point"}
}