{
  "type": "Feature",
  "properties": {
    "gn:admin1_code":"GR",
    "gn:admin2_code":"1851.0",
    "gn:admin3_code":"3681.0",
    "gn:asciiname":"Hohenhaus",
    "gn:cc2":"CH",
    "gn:country_code":"CH",
    "gn:dem":2336,
    "gn:feature_class":"P",
    "gn:feature_code":"PPL",
    "gn:name":"Hohenhaus",
    "gn:population":0,
    "gn:timezone":"Europe/Zurich",
    "iso:country":"CH",
    "name:und_x_variant":[
        "Beim Hohenhaus",
        "Hohenhaus"
    ],
    "wof:name":"Hohenhaus",
    "wof:placetype":"neighbourhood"
},
  "geometry": {"coordinates":[9.46667,46.45],"type":"Point"}
}