{
  "type": "Feature",
  "properties": {
    "gn:admin1_code":"SG",
    "gn:admin2_code":"1727.0",
    "gn:admin3_code":"3378.0",
    "gn:asciiname":"Dicken",
    "gn:country_code":"CH",
    "gn:dem":818,
    "gn:elevation":"816.0",
    "gn:feature_class":"P",
    "gn:feature_code":"PPL",
    "gn:name":"Dicken",
    "gn:population":0,
    "gn:timezone":"Europe/Zurich",
    "iso:country":"CH",
    "wof:name":"Dicken",
    "wof:placetype":"locality"
},
  "geometry": {"coordinates":[9.19168,47.33789],"type":"Point"}
}