{
  "type": "Feature",
  "properties": {
    "gn:country":"CH",
    "gn:fcode":"HSE",
    "gn:population":2,
    "iso:country":"CH",
    "name:ceb_x_preferred":[
        "Z\u00fcrich"
    ],
    "name:deu_x_preferred":[
        "Lindenhof"
    ],
    "name:eng_x_preferred":[
        "Lindenhof"
    ],
    "name:fra_x_preferred":[
        "Lindenhof"
    ],
    "name:jpn_x_preferred":[
        "\u30ea\u30f3\u30c7\u30f3\u30db\u30fc\u30d5"
    ],
    "name:lat_x_preferred":[
        "Lindenhof"
    ],
    "name:nld_x_preferred":[
        "Lindenhof"
    ],
    "name:pol_x_preferred":[
        "Lindenhof"
    ],
    "name:rus_x_preferred":[
        "\u041b\u0438\u043d\u0434\u0435\u043d\u0445\u043e\u0444"
    ],
    "name:tur_x_preferred":[
        "Lindenhof"
    ],
    "name:zho_x_preferred":[
        "\u6797\u767b\u970d\u592b"
    ],
    "qs_pg:aaroncc":"CH",
    "qs_pg:gn_country":"CH",
    "qs_pg:gn_fcode":"HSE",
    "qs_pg:gn_pop":2,
    "qs_pg:name":"Lindenhof",
    "qs_pg:photos_9r":0,
    "qs_pg:photos_sr":0,
    "qs_pg:pop_sr":1,
    "qs_pg:qs_pg_placetype":"locality_funky",
    "wof:lang_x_official":[
        "deu",
        "fra",
        "gsw",
        "ita"
    ],
    "wof:lang_x_spoken":[
        "deu",
        "fra",
        "gsw",
        "ita",
        "roh"
    ],
    "wof:name":"Lindenhof",
    "wof:placetype":"neighbourhood",
    "wof:population":2
},
  "geometry": {"coordinates":[8.92721,47.38393],"type":"Point"}
}