{
  "type": "Feature",
  "properties": {
    "gn:gn_country":"CH",
    "gn:gn_fcode":"PPL",
    "gn:gn_pop":3050,
    "gn:population":3050,
    "iso:country":"CH",
    "name:cat_x_preferred":[
        "Beckenried"
    ],
    "name:deu_x_preferred":[
        "Beckenried"
    ],
    "name:eng_x_preferred":[
        "Beckenried"
    ],
    "name:epo_x_preferred":[
        "Beckenried"
    ],
    "name:eus_x_preferred":[
        "Beckenried"
    ],
    "name:fra_x_preferred":[
        "Beckenried"
    ],
    "name:hrv_x_preferred":[
        "Beckenried"
    ],
    "name:hun_x_preferred":[
        "Beckenried"
    ],
    "name:ita_x_preferred":[
        "Beckenried"
    ],
    "name:kaz_x_preferred":[
        "\u0411\u0435\u043a\u043a\u0435\u043d\u0440\u0438\u0434"
    ],
    "name:lat_x_preferred":[
        "Beckenried"
    ],
    "name:lmo_x_preferred":[
        "Beckenried"
    ],
    "name:nld_x_preferred":[
        "Beckenried"
    ],
    "name:nno_x_preferred":[
        "Beckenried"
    ],
    "name:oci_x_preferred":[
        "Beckenried"
    ],
    "name:pms_x_preferred":[
        "Beckenried"
    ],
    "name:pol_x_preferred":[
        "Beckenried"
    ],
    "name:por_x_preferred":[
        "Beckenried"
    ],
    "name:ron_x_preferred":[
        "Beckenried"
    ],
    "name:rus_x_preferred":[
        "\u0411\u0435\u043a\u043a\u0435\u043d\u0440\u0438\u0434"
    ],
    "name:spa_x_preferred":[
        "Beckenried"
    ],
    "name:sqi_x_preferred":[
        "Beckenried"
    ],
    "name:uzb_x_preferred":[
        "Beckenried"
    ],
    "name:vol_x_preferred":[
        "Beckenried"
    ],
    "name:war_x_preferred":[
        "Beckenried"
    ],
    "qs_pg:aaroncc":"CH",
    "qs_pg:gn_country":"CH",
    "qs_pg:gn_fcode":"PPL",
    "qs_pg:gn_pop":3050,
    "qs_pg:name":"Beckenried",
    "qs_pg:name_adm0":"Schweiz",
    "qs_pg:name_adm1":"Kanton Nidwalden",
    "qs_pg:photos":348,
    "qs_pg:photos_1k":71,
    "qs_pg:photos_9k":2,
    "qs_pg:photos_9r":5,
    "qs_pg:photos_all":348,
    "qs_pg:photos_sr":5,
    "qs_pg:pop_sr":4,
    "qs_pg:qs_pg_placetype":"locality",
    "qs_pg:qs_pg_placetype_gp":"Town",
    "qs_pg:woe_adm0":23424957,
    "woe:adm0_id":23424957,
    "woe:name_adm0":"Schweiz",
    "woe:name_adm1":"Kanton Nidwalden",
    "woe:placetype":"Town",
    "wof:name":"Beckenried",
    "wof:placetype":"locality",
    "wof:population":3050
},
  "geometry": {"coordinates":[8.47394,46.96476],"type":"Point"}
}