{
  "type": "Feature",
  "properties": {
    "gn:admin1_code":"AR",
    "gn:admin2_code":"1503.0",
    "gn:admin3_code":"3037.0",
    "gn:asciiname":"Schutz",
    "gn:country_code":"CH",
    "gn:dem":567,
    "gn:feature_class":"P",
    "gn:feature_code":"PPLL",
    "gn:name":"Schutz",
    "gn:population":0,
    "gn:timezone":"Europe/Zurich",
    "iso:country":"CH",
    "name:deu_x_preferred":[
        "Schutz"
    ],
    "wof:name":"Schutz",
    "wof:placetype":"locality"
},
  "geometry": {"coordinates":[9.59354,47.45783],"type":"Point"}
}