{
  "type": "Feature",
  "properties": {
    "gn:gn_country":"CH",
    "gn:gn_fcode":"PPL",
    "gn:gn_pop":40,
    "gn:population":40,
    "iso:country":"CH",
    "name:deu_x_preferred":[
        "Indemini"
    ],
    "name:eng_x_preferred":[
        "Indemini"
    ],
    "name:fra_x_preferred":[
        "Indemini"
    ],
    "name:ita_x_preferred":[
        "Indemini"
    ],
    "name:lmo_x_preferred":[
        "Indemen"
    ],
    "name:nld_x_preferred":[
        "Indemini"
    ],
    "name:por_x_preferred":[
        "Indemini"
    ],
    "name:roh_x_preferred":[
        "Indemini"
    ],
    "name:spa_x_preferred":[
        "Indemini"
    ],
    "name:vol_x_preferred":[
        "Indemini"
    ],
    "qs_pg:aaroncc":"CH",
    "qs_pg:gn_country":"CH",
    "qs_pg:gn_fcode":"PPL",
    "qs_pg:gn_pop":40,
    "qs_pg:name":"Indemini",
    "qs_pg:name_adm0":"Schweiz",
    "qs_pg:name_adm1":"Cantone Ticino",
    "qs_pg:photos":98,
    "qs_pg:photos_1k":20,
    "qs_pg:photos_9k":1,
    "qs_pg:photos_9r":3,
    "qs_pg:photos_all":98,
    "qs_pg:photos_sr":3,
    "qs_pg:pop_sr":1,
    "qs_pg:qs_pg_placetype":"locality",
    "qs_pg:qs_pg_placetype_gp":"Town",
    "qs_pg:woe_adm0":23424957,
    "woe:adm0_id":23424957,
    "woe:name_adm0":"Schweiz",
    "woe:name_adm1":"Cantone Ticino",
    "woe:placetype":"Town",
    "wof:name":"Indemini",
    "wof:placetype":"locality",
    "wof:population":40
},
  "geometry": {"coordinates":[8.82575,46.09425],"type":"Point"}
}