{
  "type": "Feature",
  "properties": {
    "iso:country":"CH",
    "qs_pg:aaroncc":"CH",
    "qs_pg:name":"Artore",
    "qs_pg:name_adm0":"Schweiz",
    "qs_pg:name_adm1":"Cantone Ticino",
    "qs_pg:photos":10,
    "qs_pg:photos_1k":2,
    "qs_pg:photos_9k":1,
    "qs_pg:photos_9r":1,
    "qs_pg:photos_all":10,
    "qs_pg:photos_sr":1,
    "qs_pg:pop_sr":0,
    "qs_pg:qs_pg_placetype":"locality",
    "qs_pg:qs_pg_placetype_gp":"Town",
    "qs_pg:woe_adm0":23424957,
    "woe:adm0_id":23424957,
    "woe:name_adm0":"Schweiz",
    "woe:name_adm1":"Cantone Ticino",
    "woe:placetype":"Town",
    "wof:name":"Artore",
    "wof:placetype":"neighbourhood"
},
  "geometry": {"coordinates":[9.030971,46.1903745],"type":"Point"}
}