{
  "type": "Feature",
  "properties": {
    "gn:population":3099,
    "iso:country":"CH",
    "name:alb_x_preferred":[
        "Unterkulm"
    ],
    "name:baq_x_preferred":[
        "Unterkulm"
    ],
    "name:cat_x_preferred":[
        "Unterkulm"
    ],
    "name:ceb_x_preferred":[
        "Unterkulm"
    ],
    "name:chi_x_preferred":[
        "\u4e0b\u5eab\u723e\u59c6"
    ],
    "name:deu_x_preferred":[
        "Unterkulm"
    ],
    "name:dut_x_preferred":[
        "Unterkulm"
    ],
    "name:eng_x_preferred":[
        "Kulm"
    ],
    "name:epo_x_preferred":[
        "Unterkulm"
    ],
    "name:eus_x_preferred":[
        "Unterkulm"
    ],
    "name:fra_x_preferred":[
        "Unterkulm"
    ],
    "name:fre_x_preferred":[
        "Unterkulm"
    ],
    "name:ger_x_preferred":[
        "Unterkulm"
    ],
    "name:hun_x_preferred":[
        "Unterkulm"
    ],
    "name:ita_x_preferred":[
        "Unterkulm"
    ],
    "name:kaz_x_preferred":[
        "\u0423\u043d\u0442\u0435\u0440\u043a\u0443\u043b\u044c\u043c"
    ],
    "name:lmo_x_preferred":[
        "Unterkulm"
    ],
    "name:may_x_preferred":[
        "Unterkulm"
    ],
    "name:msa_x_preferred":[
        "Unterkulm"
    ],
    "name:nld_x_preferred":[
        "Unterkulm"
    ],
    "name:nno_x_preferred":[
        "Unterkulm"
    ],
    "name:oci_x_preferred":[
        "Unterkulm"
    ],
    "name:pms_x_preferred":[
        "Unterkulm"
    ],
    "name:pol_x_preferred":[
        "Unterkulm"
    ],
    "name:por_x_preferred":[
        "Unterkulm"
    ],
    "name:rus_x_preferred":[
        "\u0423\u043d\u0442\u0435\u0440\u043a\u0443\u043b\u044c\u043c"
    ],
    "name:spa_x_preferred":[
        "Unterkulm"
    ],
    "name:sqi_x_preferred":[
        "Unterkulm"
    ],
    "name:swe_x_preferred":[
        "Unterkulm"
    ],
    "name:unk_x_variant":[
        "Kulm"
    ],
    "name:uzb_x_preferred":[
        "Unterkulm"
    ],
    "name:vol_x_preferred":[
        "Unterkulm"
    ],
    "name:war_x_preferred":[
        "Unterkulm"
    ],
    "name:zho_x_preferred":[
        "\u4e0b\u5eab\u723e\u59c6"
    ],
    "qs:a0":"Schweiz#Suisse#Svizzera#Svizra",
    "qs:a1":"*Aargau",
    "qs:a1r":"0",
    "qs:adm0":"Schweiz#Suisse#Svizzera#Svizra",
    "qs:la_lc":"*",
    "qs:level":"locality",
    "qs:loc":"Unterkulm",
    "qs:loc_alt":"Unterkulm",
    "qs:pop":0,
    "qs:type":"buffered point",
    "wd:wordcount":1456,
    "wof:lang":[
        "ger"
    ],
    "wof:name":"Unterkulm",
    "wof:placetype":"locality",
    "wof:population":3099
},
  "geometry": {"coordinates":[8.114553,47.310559],"type":"Point"}
}