{
  "type": "Feature",
  "properties": {
    "gn:admin1_code":"BE",
    "gn:admin2_code":"244.0",
    "gn:admin3_code":"341.0",
    "gn:asciiname":"Rufshausen",
    "gn:country_code":"CH",
    "gn:dem":424,
    "gn:feature_class":"P",
    "gn:feature_code":"PPLL",
    "gn:name":"Rufshausen",
    "gn:population":0,
    "gn:timezone":"Europe/Zurich",
    "iso:country":"CH",
    "name:deu_x_preferred":[
        "Rufshausen"
    ],
    "wof:lang_x_official":[
        "deu",
        "fra",
        "gsw",
        "ita"
    ],
    "wof:lang_x_spoken":[
        "deu",
        "fra",
        "gsw",
        "ita",
        "roh"
    ],
    "wof:name":"Rufshausen",
    "wof:placetype":"neighbourhood"
},
  "geometry": {"coordinates":[7.77523,47.25228],"type":"Point"}
}