{
  "type": "Feature",
  "properties": {
    "gn:admin1_code":"VD",
    "gn:admin2_code":"2227.0",
    "gn:admin3_code":"5493.0",
    "gn:asciiname":"Orny",
    "gn:country_code":"CH",
    "gn:dem":466,
    "gn:feature_class":"P",
    "gn:feature_code":"PPLA3",
    "gn:name":"Orny",
    "gn:population":0,
    "gn:timezone":"Europe/Zurich",
    "iso:country":"CH",
    "name:als_x_preferred":[
        "Orny VD"
    ],
    "name:deu_x_preferred":[
        "Orny VD"
    ],
    "name:epo_x_preferred":[
        "Orny VD"
    ],
    "name:nno_x_preferred":[
        "Orny i Sveits"
    ],
    "name:war_x_preferred":[
        "Orny VD"
    ],
    "name:zho_x_preferred":[
        "\u5965\u5c14\u5c3c"
    ],
    "wof:name":"Orny",
    "wof:placetype":"locality"
},
  "geometry": {"coordinates":[6.52639,46.66758],"type":"Point"}
}