{
  "type": "Feature",
  "properties": {
    "gn:admin1_code":"FR",
    "gn:admin2_code":"1006.0",
    "gn:admin3_code":"2309.0",
    "gn:asciiname":"Dietisberg",
    "gn:country_code":"CH",
    "gn:dem":648,
    "gn:elevation":"651.0",
    "gn:feature_class":"P",
    "gn:feature_code":"PPL",
    "gn:name":"Dietisberg",
    "gn:population":0,
    "gn:timezone":"Europe/Zurich",
    "iso:country":"CH",
    "wof:name":"Dietisberg",
    "wof:placetype":"locality"
},
  "geometry": {"coordinates":[7.28061,46.8666],"type":"Point"}
}