{
  "type": "Feature",
  "properties": {
    "gn:admin1_code":"BE",
    "gn:admin2_code":"249.0",
    "gn:admin3_code":"762.0",
    "gn:asciiname":"Gsaessweid",
    "gn:country_code":"CH",
    "gn:dem":1353,
    "gn:feature_class":"P",
    "gn:feature_code":"PPL",
    "gn:name":"Gs\u00e4ssweid",
    "gn:population":0,
    "gn:timezone":"Europe/Zurich",
    "iso:country":"CH",
    "name:deu_x_preferred":[
        "Gs\u00e4ssweid"
    ],
    "wof:name":"Gsaessweid",
    "wof:placetype":"neighbourhood"
},
  "geometry": {"coordinates":[7.57756,46.62007],"type":"Point"}
}