{
  "type": "Feature",
  "properties": {
    "gn:admin1_code":"BE",
    "gn:admin2_code":"246.0",
    "gn:admin3_code":"359.0",
    "gn:asciiname":"Utzigen",
    "gn:country_code":"CH",
    "gn:dem":720,
    "gn:elevation":"691.0",
    "gn:feature_class":"P",
    "gn:feature_code":"PPL",
    "gn:name":"Utzigen",
    "gn:population":0,
    "gn:timezone":"Europe/Zurich",
    "iso:country":"CH",
    "wof:name":"Utzigen",
    "wof:placetype":"locality"
},
  "geometry": {"coordinates":[7.56568,46.96211],"type":"Point"}
}