{
  "type": "Feature",
  "properties": {
    "gn:admin1_code":"BE",
    "gn:admin2_code":"245.0",
    "gn:admin3_code":"418.0",
    "gn:asciiname":"Gansern",
    "gn:country_code":"CH",
    "gn:dem":562,
    "gn:feature_class":"P",
    "gn:feature_code":"PPLL",
    "gn:name":"Gansern",
    "gn:population":0,
    "gn:timezone":"Europe/Zurich",
    "iso:country":"CH",
    "name:deu_x_preferred":[
        "Gansern"
    ],
    "wof:name":"Gansern",
    "wof:placetype":"neighbourhood"
},
  "geometry": {"coordinates":[7.60768,47.03821],"type":"Point"}
}