{
  "type": "Feature",
  "properties": {
    "gn:gn_country":"CH",
    "gn:gn_fcode":"PPL",
    "gn:gn_pop":2,
    "gn:population":2,
    "iso:country":"CH",
    "qs_pg:aaroncc":"CH",
    "qs_pg:gn_country":"CH",
    "qs_pg:gn_fcode":"PPL",
    "qs_pg:gn_pop":2,
    "qs_pg:name":"Waldegg",
    "qs_pg:name_adm0":"Schweiz",
    "qs_pg:name_adm1":"Kanton Bern",
    "qs_pg:photos":174,
    "qs_pg:photos_1k":35,
    "qs_pg:photos_9k":1,
    "qs_pg:photos_9r":4,
    "qs_pg:photos_all":174,
    "qs_pg:photos_sr":4,
    "qs_pg:pop_sr":1,
    "qs_pg:qs_pg_placetype":"locality",
    "qs_pg:qs_pg_placetype_gp":"Town",
    "qs_pg:woe_adm0":23424957,
    "woe:adm0_id":23424957,
    "woe:name_adm0":"Schweiz",
    "woe:name_adm1":"Kanton Bern",
    "woe:placetype":"Town",
    "wof:name":"Waldegg",
    "wof:placetype":"locality",
    "wof:population":2
},
  "geometry": {"coordinates":[7.16128,46.84289],"type":"Point"}
}