{
  "type": "Feature",
  "properties": {
    "gn:admin1_code":"GL",
    "gn:admin2_code":"800.0",
    "gn:admin3_code":"1631.0",
    "gn:asciiname":"Steinibach",
    "gn:country_code":"CH",
    "gn:dem":1117,
    "gn:feature_class":"P",
    "gn:feature_code":"PPL",
    "gn:name":"Steinibach",
    "gn:population":0,
    "gn:timezone":"Europe/Zurich",
    "iso:country":"CH",
    "wof:name":"Steinibach",
    "wof:placetype":"locality"
},
  "geometry": {"coordinates":[9.14547,46.90821],"type":"Point"}
}