{
  "type": "Feature",
  "properties": {
    "gn:admin1_code":"LU",
    "gn:admin2_code":"312.0",
    "gn:admin3_code":"1062.0",
    "gn:asciiname":"Islern",
    "gn:country_code":"CH",
    "gn:dem":529,
    "gn:feature_class":"P",
    "gn:feature_code":"PPLL",
    "gn:name":"Islern",
    "gn:population":0,
    "gn:timezone":"Europe/Zurich",
    "iso:country":"CH",
    "name:deu_x_preferred":[
        "Islern"
    ],
    "wof:name":"Islern",
    "wof:placetype":"neighbourhood"
},
  "geometry": {"coordinates":[8.14842,47.03322],"type":"Point"}
}