{
  "type": "Feature",
  "properties": {
    "gn:country":"CH",
    "gn:fcode":"PPLX",
    "gn:population":24,
    "iso:country":"CH",
    "name:und_x_variant":[
        "Sch\u00fctzenhaus"
    ],
    "qs_pg:aaroncc":"CH",
    "qs_pg:gn_country":"CH",
    "qs_pg:gn_fcode":"PPLX",
    "qs_pg:gn_pop":24,
    "qs_pg:name":"T\u00f6ss (Kreis 4) / Sch\u00fctzenhaus",
    "qs_pg:photos_9r":0,
    "qs_pg:photos_sr":0,
    "qs_pg:pop_sr":1,
    "qs_pg:qs_pg_placetype":"neighbourhood",
    "wof:lang_x_official":[
        "deu",
        "fra",
        "gsw",
        "ita"
    ],
    "wof:lang_x_spoken":[
        "deu",
        "fra",
        "gsw",
        "ita",
        "roh"
    ],
    "wof:name":"Sch\u00fctzenhaus",
    "wof:placetype":"neighbourhood",
    "wof:population":24
},
  "geometry": {"coordinates":[8.70354,47.47806],"type":"Point"}
}