{
  "type": "Feature",
  "properties": {
    "gn:admin1_code":"FR",
    "gn:admin2_code":"1003.0",
    "gn:admin3_code":"2152.0",
    "gn:asciiname":"Grange Neuve",
    "gn:country_code":"CH",
    "gn:dem":861,
    "gn:feature_class":"P",
    "gn:feature_code":"PPL",
    "gn:name":"Grange Neuve",
    "gn:population":0,
    "gn:timezone":"Europe/Zurich",
    "iso:country":"CH",
    "name:fra_x_preferred":[
        "Grange Neuve"
    ],
    "wof:name":"Grange Neuve",
    "wof:placetype":"locality"
},
  "geometry": {"coordinates":[6.95867,46.61897],"type":"Point"}
}