{
  "type": "Feature",
  "properties": {
    "iso:country":"CH",
    "name:deu_x_preferred":[
        "Engstlenalp"
    ],
    "name:eng_x_preferred":[
        "Engstlenalp"
    ],
    "name:nld_x_preferred":[
        "Engstlenalp"
    ],
    "name:rus_x_preferred":[
        "\u042d\u043d\u0433\u0441\u0442\u043b\u0435\u043d\u0430\u043b\u044c\u043f"
    ],
    "qs_pg:aaroncc":"CH",
    "qs_pg:name":"Engstlenalp",
    "qs_pg:name_adm0":"Schweiz",
    "qs_pg:name_adm1":"Kanton Bern",
    "qs_pg:photos":266,
    "qs_pg:photos_1k":54,
    "qs_pg:photos_9k":1,
    "qs_pg:photos_9r":4,
    "qs_pg:photos_all":266,
    "qs_pg:photos_sr":5,
    "qs_pg:pop_sr":0,
    "qs_pg:qs_pg_placetype":"locality",
    "qs_pg:qs_pg_placetype_gp":"Town",
    "qs_pg:woe_adm0":23424957,
    "woe:adm0_id":23424957,
    "woe:name_adm0":"Schweiz",
    "woe:name_adm1":"Kanton Bern",
    "woe:placetype":"Town",
    "wof:name":"Engstlenalp",
    "wof:placetype":"neighbourhood"
},
  "geometry": {"coordinates":[8.347549,46.77645],"type":"Point"}
}