{
  "type": "Feature",
  "properties": {
    "gn:admin1_code":"LU",
    "gn:admin2_code":"312.0",
    "gn:admin3_code":"1064.0",
    "gn:asciiname":"Sonderi",
    "gn:country_code":"CH",
    "gn:dem":688,
    "gn:feature_class":"P",
    "gn:feature_code":"PPLL",
    "gn:name":"Sonderi",
    "gn:population":0,
    "gn:timezone":"Europe/Zurich",
    "iso:country":"CH",
    "name:deu_x_preferred":[
        "Sonderi"
    ],
    "wof:name":"Sonderi",
    "wof:placetype":"neighbourhood"
},
  "geometry": {"coordinates":[8.41762,47.12019],"type":"Point"}
}