{
  "type": "Feature",
  "properties": {
    "iso:country":"CH",
    "wof:name":"Felsenau",
    "wof:placetype":"neighbourhood"
},
  "geometry": {"coordinates":[7.4435164359939,46.97232073356173],"type":"Point"}
}