{
  "type": "Feature",
  "properties": {
    "gn:gn_country":"CH",
    "gn:gn_fcode":"ADM3",
    "gn:gn_pop":1047,
    "gn:population":1054,
    "iso:country":"CH",
    "name:alb_x_preferred":[
        "Remigen"
    ],
    "name:baq_x_preferred":[
        "Remigen"
    ],
    "name:bul_x_preferred":[
        "\u0420\u0435\u043c\u0438\u0433\u0435\u043d"
    ],
    "name:cat_x_preferred":[
        "Remigen"
    ],
    "name:chi_x_preferred":[
        "\u96f7\u7c73\u6839"
    ],
    "name:dut_x_preferred":[
        "Remigen"
    ],
    "name:eng_x_preferred":[
        "Remigen"
    ],
    "name:epo_x_preferred":[
        "Remigen"
    ],
    "name:fre_x_preferred":[
        "Remigen"
    ],
    "name:ger_x_preferred":[
        "Remigen"
    ],
    "name:gsw_x_preferred":[
        "Remige"
    ],
    "name:hun_x_preferred":[
        "Remigen"
    ],
    "name:ita_x_preferred":[
        "Remigen"
    ],
    "name:kaz_x_preferred":[
        "\u0420\u0435\u043c\u0438\u0433\u0435\u043d"
    ],
    "name:lmo_x_preferred":[
        "Remigen"
    ],
    "name:may_x_preferred":[
        "Remigen"
    ],
    "name:nno_x_preferred":[
        "Remigen"
    ],
    "name:oci_x_preferred":[
        "Remigen"
    ],
    "name:pol_x_preferred":[
        "Remigen"
    ],
    "name:rus_x_preferred":[
        "\u0420\u0435\u043c\u0438\u0433\u0435\u043d"
    ],
    "name:spa_x_preferred":[
        "Remigen"
    ],
    "name:swe_x_preferred":[
        "Remigen"
    ],
    "name:uzb_x_preferred":[
        "Remigen"
    ],
    "name:vol_x_preferred":[
        "Remigen"
    ],
    "name:war_x_preferred":[
        "Remigen"
    ],
    "qs_pg:aaroncc":"CH",
    "qs_pg:gn_country":"CH",
    "qs_pg:gn_fcode":"ADM3",
    "qs_pg:gn_pop":1047,
    "qs_pg:name":"Remigen",
    "qs_pg:name_adm0":"Schweiz",
    "qs_pg:name_adm1":"Kanton Aargau",
    "qs_pg:photos":58,
    "qs_pg:photos_1k":12,
    "qs_pg:photos_9k":1,
    "qs_pg:photos_9r":2,
    "qs_pg:photos_all":58,
    "qs_pg:photos_sr":2,
    "qs_pg:pop_sr":3,
    "qs_pg:qs_pg_placetype":"locality",
    "qs_pg:qs_pg_placetype_gp":"Town",
    "qs_pg:woe_adm0":23424957,
    "woe:adm0_id":23424957,
    "woe:name_adm0":"Schweiz",
    "woe:name_adm1":"Kanton Aargau",
    "woe:placetype":"Town",
    "wof:name":"Remigen",
    "wof:placetype":"locality",
    "wof:population":1054
},
  "geometry": {"coordinates":[8.17615,47.51756],"type":"Point"}
}