{
  "type": "Feature",
  "properties": {
    "iso:country":"CH",
    "oa:elevation_ft":"1837",
    "oa:type":"small_airport",
    "woe:hierarchy":{
        "country_id":23424957,
        "county_id":12593111,
        "localadmin_id":12682752,
        "planet_id":1,
        "state_id":2347087
    },
    "wof:name":"Flugplatz Thun",
    "wof:placetype":"campus"
},
  "geometry": {"coordinates":[7.600555,46.756388],"type":"Point"}
}