{
  "type": "Feature",
  "properties": {
    "iso:country":"CH",
    "name:deu_x_preferred":[
        "Milit\u00e4rflugplatz Thun"
    ],
    "name:eng_x_preferred":[
        "Thun Airport"
    ],
    "name:msa_x_preferred":[
        "Lapangan Terbang Thun"
    ],
    "name:ron_x_preferred":[
        "Aeroportul Thun"
    ],
    "oa:elevation_ft":"1837",
    "oa:type":"small_airport",
    "woe:hierarchy":{
        "country_id":23424957,
        "county_id":12593111,
        "localadmin_id":12682752,
        "planet_id":1,
        "state_id":2347087
    },
    "wof:lang_x_official":[
        "deu",
        "fra",
        "gsw",
        "ita"
    ],
    "wof:lang_x_spoken":[
        "deu",
        "fra",
        "gsw",
        "ita",
        "roh"
    ],
    "wof:name":"Flugplatz Thun",
    "wof:placetype":"campus"
},
  "geometry": {"coordinates":[7.600555,46.756388],"type":"Point"}
}