{
  "type": "Feature",
  "properties": {
    "gn:admin1_code":"FR",
    "gn:admin2_code":"1001.0",
    "gn:admin3_code":"2054.0",
    "gn:asciiname":"Forel",
    "gn:country_code":"CH",
    "gn:dem":455,
    "gn:elevation":"465.0",
    "gn:feature_class":"P",
    "gn:feature_code":"PPL",
    "gn:name":"Forel",
    "gn:population":0,
    "gn:timezone":"Europe/Zurich",
    "iso:country":"CH",
    "name:deu_x_preferred":[
        "Forel"
    ],
    "name:epo_x_preferred":[
        "Forel"
    ],
    "name:fra_x_preferred":[
        "Forel"
    ],
    "name:ita_x_preferred":[
        "Forel"
    ],
    "name:lmo_x_preferred":[
        "Forel"
    ],
    "name:nds_x_preferred":[
        "Forel"
    ],
    "name:nld_x_preferred":[
        "Forel"
    ],
    "name:pol_x_preferred":[
        "Forel"
    ],
    "name:roh_x_preferred":[
        "Forel"
    ],
    "name:swe_x_preferred":[
        "Forel"
    ],
    "wof:lang_x_official":[
        "deu",
        "fra",
        "gsw",
        "ita"
    ],
    "wof:lang_x_spoken":[
        "deu",
        "fra",
        "gsw",
        "ita",
        "roh"
    ],
    "wof:name":"Forel",
    "wof:placetype":"neighbourhood"
},
  "geometry": {"coordinates":[6.88911,46.87736],"type":"Point"}
}