{
  "type": "Feature",
  "properties": {
    "gn:country":"CH",
    "gn:fcode":"PPL",
    "gn:population":0,
    "iso:country":"CH",
    "name:als_x_preferred":[
        "Burg"
    ],
    "name:arg_x_preferred":[
        "Burg"
    ],
    "name:bel_x_preferred":[
        "\u0411\u0443\u0440\u0433"
    ],
    "name:cat_x_preferred":[
        "Burg"
    ],
    "name:ceb_x_preferred":[
        "Burg"
    ],
    "name:dan_x_preferred":[
        "Burg"
    ],
    "name:deu_x_preferred":[
        "Burg im Leimental"
    ],
    "name:deu_x_variant":[
        "Burg"
    ],
    "name:epo_x_preferred":[
        "Burg"
    ],
    "name:fra_x_preferred":[
        "Burg"
    ],
    "name:heb_x_preferred":[
        "\u05d1\u05d5\u05e8\u05d2"
    ],
    "name:hun_x_preferred":[
        "Burg"
    ],
    "name:ita_x_preferred":[
        "Burg"
    ],
    "name:jpn_x_preferred":[
        "\u30d6\u30eb\u30af"
    ],
    "name:lmo_x_preferred":[
        "Burg"
    ],
    "name:mkd_x_preferred":[
        "\u0411\u0443\u0440\u0433"
    ],
    "name:nld_x_preferred":[
        "Burg"
    ],
    "name:pms_x_preferred":[
        "Burg"
    ],
    "name:pol_x_preferred":[
        "Burg"
    ],
    "name:por_x_preferred":[
        "Burg"
    ],
    "name:rus_x_preferred":[
        "\u0411\u0443\u0440\u0433"
    ],
    "name:spa_x_preferred":[
        "Burg"
    ],
    "name:srp_x_preferred":[
        "Burg"
    ],
    "name:swe_x_preferred":[
        "Burg"
    ],
    "name:ukr_x_preferred":[
        "\u0411\u0443\u0440\u0433"
    ],
    "name:vls_x_preferred":[
        "Burg"
    ],
    "name:vol_x_preferred":[
        "Burg"
    ],
    "qs_pg:aaroncc":"CH",
    "qs_pg:gn_country":"CH",
    "qs_pg:gn_fcode":"PPL",
    "qs_pg:gn_pop":0,
    "qs_pg:name":"Burg",
    "qs_pg:name_adm0":"Schweiz",
    "qs_pg:name_adm1":"Kanton Basel-Land",
    "qs_pg:photos":8,
    "qs_pg:photos_1k":2,
    "qs_pg:photos_9k":1,
    "qs_pg:photos_9r":1,
    "qs_pg:photos_all":8,
    "qs_pg:photos_sr":1,
    "qs_pg:pop_sr":0,
    "qs_pg:qs_pg_placetype":"locality",
    "qs_pg:qs_pg_placetype_gp":"Town",
    "qs_pg:woe_adm0":23424957,
    "woe:adm0_id":23424957,
    "woe:name_adm0":"Schweiz",
    "woe:name_adm1":"Kanton Basel-Land",
    "woe:placetype":"Town",
    "wof:name":"Burg",
    "wof:placetype":"neighbourhood"
},
  "geometry": {"coordinates":[7.43808,47.45957],"type":"Point"}
}