{
  "type": "Feature",
  "properties": {
    "gn:gn_country":"CH",
    "gn:gn_fcode":"ADM3",
    "gn:gn_pop":303,
    "gn:population":317,
    "iso:country":"CH",
    "name:alb_x_preferred":[
        "Mandach"
    ],
    "name:baq_x_preferred":[
        "Mandach"
    ],
    "name:bul_x_preferred":[
        "\u041c\u0430\u043d\u0434\u0430\u0447"
    ],
    "name:cat_x_preferred":[
        "Mandach"
    ],
    "name:chi_x_preferred":[
        "\u66fc\u9054\u8d6b"
    ],
    "name:dut_x_preferred":[
        "Mandach"
    ],
    "name:eng_x_preferred":[
        "Mandach"
    ],
    "name:epo_x_preferred":[
        "Mandach"
    ],
    "name:fre_x_preferred":[
        "Mandach"
    ],
    "name:ger_x_preferred":[
        "Mandach"
    ],
    "name:gsw_x_preferred":[
        "Mandach"
    ],
    "name:hun_x_preferred":[
        "Mandach"
    ],
    "name:ita_x_preferred":[
        "Mandach"
    ],
    "name:kaz_x_preferred":[
        "\u041c\u0430\u043d\u0434\u0430\u0445"
    ],
    "name:lmo_x_preferred":[
        "Mandach"
    ],
    "name:may_x_preferred":[
        "Mandach"
    ],
    "name:nno_x_preferred":[
        "Mandach"
    ],
    "name:oci_x_preferred":[
        "Mandach"
    ],
    "name:pol_x_preferred":[
        "Mandach"
    ],
    "name:rus_x_preferred":[
        "\u041c\u0430\u043d\u0434\u0430\u0445"
    ],
    "name:spa_x_preferred":[
        "Mandach"
    ],
    "name:swe_x_preferred":[
        "Mandach"
    ],
    "name:uzb_x_preferred":[
        "Mandach"
    ],
    "name:vol_x_preferred":[
        "Mandach"
    ],
    "name:war_x_preferred":[
        "Mandach"
    ],
    "qs_pg:aaroncc":"CH",
    "qs_pg:gn_country":"CH",
    "qs_pg:gn_fcode":"ADM3",
    "qs_pg:gn_pop":303,
    "qs_pg:name":"Mandach",
    "qs_pg:name_adm0":"Schweiz",
    "qs_pg:name_adm1":"Kanton Aargau",
    "qs_pg:photos":48,
    "qs_pg:photos_1k":10,
    "qs_pg:photos_9k":1,
    "qs_pg:photos_9r":2,
    "qs_pg:photos_all":48,
    "qs_pg:photos_sr":2,
    "qs_pg:pop_sr":2,
    "qs_pg:qs_pg_placetype":"locality",
    "qs_pg:qs_pg_placetype_gp":"Town",
    "qs_pg:woe_adm0":23424957,
    "woe:adm0_id":23424957,
    "woe:name_adm0":"Schweiz",
    "woe:name_adm1":"Kanton Aargau",
    "woe:placetype":"Town",
    "wof:name":"Mandach",
    "wof:placetype":"locality",
    "wof:population":317
},
  "geometry": {"coordinates":[8.18769,47.55152],"type":"Point"}
}