{
  "type": "Feature",
  "properties": {
    "gn:admin1_code":"AG",
    "gn:admin2_code":"1911.0",
    "gn:admin3_code":"4311.0",
    "gn:asciiname":"Aspen",
    "gn:country_code":"CH",
    "gn:dem":338,
    "gn:feature_class":"P",
    "gn:feature_code":"PPLL",
    "gn:name":"Aspen",
    "gn:population":0,
    "gn:timezone":"Europe/Zurich",
    "iso:country":"CH",
    "name:deu_x_preferred":[
        "Aspen"
    ],
    "wof:name":"Aspen",
    "wof:placetype":"neighbourhood"
},
  "geometry": {"coordinates":[8.17957,47.5888],"type":"Point"}
}