{
  "type": "Feature",
  "properties": {
    "gn:gn_country":"CH",
    "gn:gn_fcode":"PPL",
    "gn:gn_pop":728,
    "gn:population":728,
    "iso:country":"CH",
    "name:alb_x_preferred":[
        "Liddes"
    ],
    "name:baq_x_preferred":[
        "Liddes"
    ],
    "name:cat_x_preferred":[
        "Liddes"
    ],
    "name:chi_x_preferred":[
        "\u5229\u5fb7"
    ],
    "name:dut_x_preferred":[
        "Liddes"
    ],
    "name:eng_x_preferred":[
        "Liddes"
    ],
    "name:epo_x_preferred":[
        "Liddes"
    ],
    "name:fre_x_preferred":[
        "Liddes"
    ],
    "name:ger_x_preferred":[
        "Liddes"
    ],
    "name:gsw_x_preferred":[
        "Liddes"
    ],
    "name:hun_x_preferred":[
        "Liddes"
    ],
    "name:ita_x_preferred":[
        "Liddes"
    ],
    "name:lmo_x_preferred":[
        "Liddes"
    ],
    "name:may_x_preferred":[
        "Liddes"
    ],
    "name:nno_x_preferred":[
        "Liddes"
    ],
    "name:oci_x_preferred":[
        "Liddes"
    ],
    "name:roh_x_preferred":[
        "Liddes"
    ],
    "name:spa_x_preferred":[
        "Liddes"
    ],
    "name:swe_x_preferred":[
        "Liddes"
    ],
    "name:vol_x_preferred":[
        "Liddes"
    ],
    "name:war_x_preferred":[
        "Liddes"
    ],
    "qs_pg:aaroncc":"CH",
    "qs_pg:gn_country":"CH",
    "qs_pg:gn_fcode":"PPL",
    "qs_pg:gn_pop":728,
    "qs_pg:name":"Liddes",
    "qs_pg:name_adm0":"Schweiz",
    "qs_pg:name_adm1":"Canton de Valais",
    "qs_pg:photos":652,
    "qs_pg:photos_1k":132,
    "qs_pg:photos_9k":3,
    "qs_pg:photos_9r":5,
    "qs_pg:photos_all":652,
    "qs_pg:photos_sr":8,
    "qs_pg:pop_sr":2,
    "qs_pg:qs_pg_placetype":"locality",
    "qs_pg:qs_pg_placetype_gp":"Town",
    "qs_pg:woe_adm0":23424957,
    "woe:adm0_id":23424957,
    "woe:name_adm0":"Schweiz",
    "woe:name_adm1":"Canton de Valais",
    "woe:placetype":"Town",
    "wof:name":"Liddes",
    "wof:placetype":"locality",
    "wof:population":728
},
  "geometry": {"coordinates":[7.18729,45.99249],"type":"Point"}
}