{
  "type": "Feature",
  "properties": {
    "gn:admin1_code":"BE",
    "gn:admin2_code":"249.0",
    "gn:admin3_code":"762.0",
    "gn:asciiname":"Tubelfaerrich",
    "gn:country_code":"CH",
    "gn:dem":1723,
    "gn:feature_class":"P",
    "gn:feature_code":"PPL",
    "gn:name":"Tubelf\u00e4rrich",
    "gn:population":0,
    "gn:timezone":"Europe/Zurich",
    "iso:country":"CH",
    "name:deu_x_preferred":[
        "Tubelf\u00e4rrich"
    ],
    "wof:name":"Tubelfaerrich",
    "wof:placetype":"neighbourhood"
},
  "geometry": {"coordinates":[7.54131,46.587],"type":"Point"}
}