{
  "type": "Feature",
  "properties": {
    "gn:gn_country":"CH",
    "gn:gn_fcode":"PPL",
    "gn:gn_pop":20,
    "gn:population":20,
    "iso:country":"CH",
    "name:deu_x_preferred":[
        "Allenwinden"
    ],
    "name:eng_x_preferred":[
        "Allenwinden"
    ],
    "name:nld_x_preferred":[
        "Allenwinden"
    ],
    "qs_pg:aaroncc":"CH",
    "qs_pg:gn_country":"CH",
    "qs_pg:gn_fcode":"PPL",
    "qs_pg:gn_pop":20,
    "qs_pg:name":"Allenwinden",
    "qs_pg:photos_9r":0,
    "qs_pg:photos_sr":0,
    "qs_pg:pop_sr":1,
    "qs_pg:qs_pg_placetype":"locality",
    "wof:name":"Allenwinden",
    "wof:placetype":"neighbourhood",
    "wof:population":20
},
  "geometry": {"coordinates":[8.78145,47.30403],"type":"Point"}
}