{
  "type": "Feature",
  "properties": {
    "gn:gn_country":"CH",
    "gn:gn_fcode":"PPL",
    "gn:gn_pop":967,
    "gn:population":967,
    "iso:country":"CH",
    "name:cat_x_preferred":[
        "M\u00fchlau"
    ],
    "name:deu_x_preferred":[
        "M\u00fchlau"
    ],
    "name:eng_x_preferred":[
        "M\u00fchlau"
    ],
    "name:epo_x_preferred":[
        "M\u00fchlau AG"
    ],
    "name:eus_x_preferred":[
        "M\u00fchlau"
    ],
    "name:fra_x_preferred":[
        "M\u00fchlau"
    ],
    "name:gsw_x_preferred":[
        "M\u00fclau"
    ],
    "name:hun_x_preferred":[
        "M\u00fchlau"
    ],
    "name:ita_x_preferred":[
        "M\u00fchlau"
    ],
    "name:kaz_x_preferred":[
        "\u041c\u044e\u043b\u0430\u0443"
    ],
    "name:lmo_x_preferred":[
        "M\u00fchlau"
    ],
    "name:msa_x_preferred":[
        "M\u00fchlau"
    ],
    "name:nld_x_preferred":[
        "M\u00fchlau"
    ],
    "name:nno_x_preferred":[
        "M\u00fchlau"
    ],
    "name:oci_x_preferred":[
        "M\u00fchlau"
    ],
    "name:pms_x_preferred":[
        "M\u00fchlau"
    ],
    "name:por_x_preferred":[
        "M\u00fchlau"
    ],
    "name:rus_x_preferred":[
        "\u041c\u044e\u043b\u0430\u0443"
    ],
    "name:spa_x_preferred":[
        "M\u00fchlau"
    ],
    "name:sqi_x_preferred":[
        "M\u00fchlau"
    ],
    "name:swe_x_preferred":[
        "M\u00fchlau"
    ],
    "name:uzb_x_preferred":[
        "M\u00fchlau"
    ],
    "name:vie_x_preferred":[
        "M\u00fchlau"
    ],
    "name:vol_x_preferred":[
        "M\u00fchlau"
    ],
    "name:war_x_preferred":[
        "M\u00fchlau"
    ],
    "name:zho_x_preferred":[
        "\u7c73\u8d6b\u52b3"
    ],
    "qs_pg:aaroncc":"CH",
    "qs_pg:gn_country":"CH",
    "qs_pg:gn_fcode":"PPL",
    "qs_pg:gn_pop":967,
    "qs_pg:name":"M\u00fchlau",
    "qs_pg:name_adm0":"Schweiz",
    "qs_pg:name_adm1":"Kanton Aargau",
    "qs_pg:photos":53,
    "qs_pg:photos_1k":11,
    "qs_pg:photos_9k":1,
    "qs_pg:photos_9r":2,
    "qs_pg:photos_all":53,
    "qs_pg:photos_sr":2,
    "qs_pg:pop_sr":2,
    "qs_pg:qs_pg_placetype":"locality",
    "qs_pg:qs_pg_placetype_gp":"Town",
    "qs_pg:woe_adm0":23424957,
    "woe:adm0_id":23424957,
    "woe:name_adm0":"Schweiz",
    "woe:name_adm1":"Kanton Aargau",
    "woe:placetype":"Town",
    "wof:name":"M\u00fchlau",
    "wof:placetype":"locality",
    "wof:population":967
},
  "geometry": {"coordinates":[8.38965,47.23035],"type":"Point"}
}