{
  "type": "Feature",
  "properties": {
    "gn:gn_country":"CH",
    "gn:gn_fcode":"PPL",
    "gn:gn_pop":0,
    "gn:population":2610,
    "iso:country":"CH",
    "name:bul_x_preferred":[
        "\u041b\u0435\u043d\u0446\u0435\u0440\u0445\u0430\u0439\u0434\u0435"
    ],
    "name:ces_x_preferred":[
        "Lenzerheide"
    ],
    "name:deu_x_preferred":[
        "Lenzerheide"
    ],
    "name:deu_x_variant":[
        "Lenzerheide/Lai"
    ],
    "name:eng_x_preferred":[
        "Lenzerheide"
    ],
    "name:fin_x_preferred":[
        "Lenzerheide"
    ],
    "name:fra_x_preferred":[
        "Lenzerheide"
    ],
    "name:gsw_x_preferred":[
        "Lenzerhaid"
    ],
    "name:heb_x_preferred":[
        "\u05dc\u05e0\u05e6\u05e8\u05d4\u05d9\u05d9\u05d3\u05d4"
    ],
    "name:ita_x_preferred":[
        "Lenzerheide"
    ],
    "name:lav_x_preferred":[
        "Lencerheide"
    ],
    "name:nld_x_preferred":[
        "Lenzerheide"
    ],
    "name:nob_x_preferred":[
        "Lenzerheide"
    ],
    "name:pol_x_preferred":[
        "Lenzerheide"
    ],
    "name:roh_x_preferred":[
        "Lai"
    ],
    "name:rus_x_preferred":[
        "\u041b\u0435\u043d\u0446\u0435\u0440\u0445\u0430\u0439\u0434\u0435"
    ],
    "name:slk_x_preferred":[
        "Lenzerheide"
    ],
    "name:srp_x_preferred":[
        "\u041b\u0435\u043d\u0446\u0435\u0440\u0445\u0430\u0458\u0434\u0435"
    ],
    "name:swe_x_preferred":[
        "Lenzerheide"
    ],
    "name:ukr_x_preferred":[
        "\u041b\u0435\u043d\u0446\u0435\u0440\u0445\u0430\u0439\u0434\u0435"
    ],
    "name:uzb_x_preferred":[
        "Lenzerheide"
    ],
    "qs_pg:aaroncc":"CH",
    "qs_pg:gn_country":"CH",
    "qs_pg:gn_fcode":"PPL",
    "qs_pg:gn_pop":0,
    "qs_pg:name":"Lenzerheide",
    "qs_pg:name_adm0":"Schweiz",
    "qs_pg:name_adm1":"Kanton Graub\u00fcnden",
    "qs_pg:photos":447,
    "qs_pg:photos_1k":91,
    "qs_pg:photos_9k":2,
    "qs_pg:photos_9r":5,
    "qs_pg:photos_all":447,
    "qs_pg:photos_sr":6,
    "qs_pg:pop_sr":0,
    "qs_pg:qs_pg_placetype":"locality",
    "qs_pg:qs_pg_placetype_gp":"Town",
    "qs_pg:woe_adm0":23424957,
    "woe:adm0_id":23424957,
    "woe:name_adm0":"Schweiz",
    "woe:name_adm1":"Kanton Graub\u00fcnden",
    "woe:placetype":"Town",
    "wof:name":"Lenzerheide",
    "wof:placetype":"neighbourhood",
    "wof:population":2610
},
  "geometry": {"coordinates":[9.55905,46.72215],"type":"Point"}
}