{
  "type": "Feature",
  "properties": {
    "gn:country":"CH",
    "gn:fcode":"PPLX",
    "gn:population":1212,
    "iso:country":"CH",
    "name:eng_x_preferred":[
        "Freiestrasse"
    ],
    "name:eng_x_variant":[
        "Schlieren / Freiestrasse"
    ],
    "qs_pg:aaroncc":"CH",
    "qs_pg:gn_country":"CH",
    "qs_pg:gn_fcode":"PPLX",
    "qs_pg:gn_pop":1212,
    "qs_pg:name":"Schlieren / Freiestrasse",
    "qs_pg:photos_9r":0,
    "qs_pg:photos_sr":0,
    "qs_pg:pop_sr":3,
    "qs_pg:qs_pg_placetype":"neighbourhood",
    "wof:name":"Freiestrasse",
    "wof:placetype":"neighbourhood",
    "wof:population":1212
},
  "geometry": {"coordinates":[8.44202,47.39598],"type":"Point"}
}