{
  "type": "Feature",
  "properties": {
    "gn:admin1_code":"TG",
    "gn:admin2_code":"2015.0",
    "gn:admin3_code":"4471.0",
    "gn:asciiname":"Schweizersholz",
    "gn:country_code":"CH",
    "gn:dem":570,
    "gn:feature_class":"P",
    "gn:feature_code":"PPL",
    "gn:name":"Schweizersholz",
    "gn:population":0,
    "gn:timezone":"Europe/Zurich",
    "iso:country":"CH",
    "wof:name":"Schweizersholz",
    "wof:placetype":"locality"
},
  "geometry": {"coordinates":[9.19628,47.50277],"type":"Point"}
}