{
  "type": "Feature",
  "properties": {
    "gn:admin1_code":"LU",
    "gn:admin2_code":"313.0",
    "gn:admin3_code":"1040.0",
    "gn:asciiname":"Sueesstannen",
    "gn:country_code":"CH",
    "gn:dem":583,
    "gn:feature_class":"P",
    "gn:feature_code":"PPLL",
    "gn:name":"S\u00fcesstannen",
    "gn:population":0,
    "gn:timezone":"Europe/Zurich",
    "iso:country":"CH",
    "name:deu_x_preferred":[
        "S\u00fcesstannen"
    ],
    "wof:lang_x_official":[
        "deu",
        "fra",
        "gsw",
        "ita"
    ],
    "wof:lang_x_spoken":[
        "deu",
        "fra",
        "gsw",
        "ita",
        "roh"
    ],
    "wof:name":"Sueesstannen",
    "wof:placetype":"neighbourhood"
},
  "geometry": {"coordinates":[8.24653,47.11757],"type":"Point"}
}