{
  "type": "Feature",
  "properties": {
    "gn:gn_country":"CH",
    "gn:gn_fcode":"PPL",
    "gn:gn_pop":444,
    "gn:population":444,
    "iso:country":"CH",
    "name:cat_x_preferred":[
        "Vaulion"
    ],
    "name:deu_x_preferred":[
        "Vaulion"
    ],
    "name:eng_x_preferred":[
        "Vaulion"
    ],
    "name:epo_x_preferred":[
        "Vaulion"
    ],
    "name:eus_x_preferred":[
        "Vaulion"
    ],
    "name:fra_x_preferred":[
        "Vaulion"
    ],
    "name:gsw_x_preferred":[
        "Vaulion"
    ],
    "name:hun_x_preferred":[
        "Vaulion"
    ],
    "name:ita_x_preferred":[
        "Vaulion"
    ],
    "name:lmo_x_preferred":[
        "Vaulion"
    ],
    "name:msa_x_preferred":[
        "Vaulion"
    ],
    "name:nld_x_preferred":[
        "Vaulion"
    ],
    "name:nno_x_preferred":[
        "Vaulion"
    ],
    "name:oci_x_preferred":[
        "Vaulion"
    ],
    "name:roh_x_preferred":[
        "Vaulion"
    ],
    "name:spa_x_preferred":[
        "Vaulion"
    ],
    "name:vie_x_preferred":[
        "Vaulion"
    ],
    "name:vol_x_preferred":[
        "Vaulion"
    ],
    "qs_pg:aaroncc":"CH",
    "qs_pg:gn_country":"CH",
    "qs_pg:gn_fcode":"PPL",
    "qs_pg:gn_pop":444,
    "qs_pg:name":"Vaulion",
    "qs_pg:name_adm0":"Schweiz",
    "qs_pg:name_adm1":"Canton de Vaud",
    "qs_pg:photos":66,
    "qs_pg:photos_1k":13,
    "qs_pg:photos_9k":1,
    "qs_pg:photos_9r":2,
    "qs_pg:photos_all":66,
    "qs_pg:photos_sr":2,
    "qs_pg:pop_sr":2,
    "qs_pg:qs_pg_placetype":"locality",
    "qs_pg:qs_pg_placetype_gp":"Town",
    "qs_pg:woe_adm0":23424957,
    "woe:adm0_id":23424957,
    "woe:name_adm0":"Schweiz",
    "woe:name_adm1":"Canton de Vaud",
    "woe:placetype":"Town",
    "wof:name":"Vaulion",
    "wof:placetype":"locality",
    "wof:population":444
},
  "geometry": {"coordinates":[6.38941,46.68913],"type":"Point"}
}