{
  "type": "Feature",
  "properties": {
    "gn:population":2788,
    "iso:country":"CH",
    "name:als_x_preferred":[
        "Wattenwil"
    ],
    "name:cat_x_preferred":[
        "Wattenwil"
    ],
    "name:ceb_x_preferred":[
        "Wattenwil"
    ],
    "name:chv_x_preferred":[
        "\u0412\u0430\u0442\u0442\u0435\u043d\u0432\u0438\u043b\u044c"
    ],
    "name:deu_x_preferred":[
        "Wattenwil"
    ],
    "name:eng_x_preferred":[
        "Wattenwil"
    ],
    "name:epo_x_preferred":[
        "Wattenwil BE"
    ],
    "name:eus_x_preferred":[
        "Wattenwil"
    ],
    "name:fra_x_preferred":[
        "Wattenwil"
    ],
    "name:gsw_x_preferred":[
        "Wattewiu"
    ],
    "name:hun_x_preferred":[
        "Wattenwil"
    ],
    "name:ita_x_preferred":[
        "Wattenwil"
    ],
    "name:kaz_x_preferred":[
        "\u0412\u0430\u0442\u0442\u0435\u043d\u0432\u0438\u043b\u044c"
    ],
    "name:lmo_x_preferred":[
        "Wattenwil"
    ],
    "name:msa_x_preferred":[
        "Wattenwil"
    ],
    "name:nld_x_preferred":[
        "Wattenwil"
    ],
    "name:nno_x_preferred":[
        "Wattenwil"
    ],
    "name:oci_x_preferred":[
        "Wattenwil"
    ],
    "name:pms_x_preferred":[
        "Wattenwil"
    ],
    "name:por_x_preferred":[
        "Wattenwil"
    ],
    "name:rus_x_preferred":[
        "\u0412\u0430\u0442\u0442\u0435\u043d\u0432\u0438\u043b\u044c"
    ],
    "name:spa_x_preferred":[
        "Wattenwil"
    ],
    "name:sqi_x_preferred":[
        "Wattenwil"
    ],
    "name:swe_x_preferred":[
        "Wattenwil"
    ],
    "name:vie_x_preferred":[
        "Wattenwil"
    ],
    "name:vol_x_preferred":[
        "Wattenwil"
    ],
    "name:war_x_preferred":[
        "Wattenwil"
    ],
    "name:zho_x_preferred":[
        "\u74e6\u6ed5\u7dad\u723e"
    ],
    "qs:a0":"Schweiz#Suisse#Svizzera#Svizra",
    "qs:a1":"*Bern",
    "qs:a1r":"0",
    "qs:adm0":"Schweiz#Suisse#Svizzera#Svizra",
    "qs:la_lc":"*",
    "qs:level":"locality",
    "qs:loc":"Wattenwil",
    "qs:loc_alt":"Wattenwil",
    "qs:pop":0,
    "qs:type":"buffered point",
    "wd:wordcount":2382,
    "wof:lang":[
        "ger"
    ],
    "wof:name":"Wattenwil",
    "wof:placetype":"neighbourhood",
    "wof:population":2788
},
  "geometry": {"coordinates":[7.509766,46.770001],"type":"Point"}
}