{
  "type": "Feature",
  "properties": {
    "gn:admin1_code":"LU",
    "gn:admin2_code":"314.0",
    "gn:admin3_code":"1104.0",
    "gn:asciiname":"Marchstein",
    "gn:country_code":"CH",
    "gn:dem":498,
    "gn:feature_class":"P",
    "gn:feature_code":"PPLL",
    "gn:name":"Marchstein",
    "gn:population":0,
    "gn:timezone":"Europe/Zurich",
    "iso:country":"CH",
    "name:deu_x_preferred":[
        "Marchstein"
    ],
    "wof:name":"Marchstein",
    "wof:placetype":"neighbourhood"
},
  "geometry": {"coordinates":[8.06657,47.25314],"type":"Point"}
}