{
  "type": "Feature",
  "properties": {
    "gn:gn_country":"CH",
    "gn:gn_fcode":"PPL",
    "gn:gn_pop":492,
    "gn:population":492,
    "iso:country":"CH",
    "name:unk_x_variant":[
        "Niedersommeri"
    ],
    "qs_pg:aaroncc":"CH",
    "qs_pg:gn_country":"CH",
    "qs_pg:gn_fcode":"PPL",
    "qs_pg:gn_pop":492,
    "qs_pg:name":"Sommeri",
    "qs_pg:name_adm0":"Schweiz",
    "qs_pg:name_adm1":"Kanton Thurgau",
    "qs_pg:photos_9r":0,
    "qs_pg:photos_sr":0,
    "qs_pg:pop_sr":2,
    "qs_pg:qs_pg_placetype":"locality",
    "qs_pg:qs_pg_placetype_gp":"Town",
    "qs_pg:woe_adm0":23424957,
    "woe:adm0_id":23424957,
    "woe:name_adm0":"Schweiz",
    "woe:name_adm1":"Kanton Thurgau",
    "woe:placetype":"Town",
    "wof:name":"Sommeri",
    "wof:placetype":"locality",
    "wof:population":492
},
  "geometry": {"coordinates":[9.28919,47.5675],"type":"Point"}
}