{
  "type": "Feature",
  "properties": {
    "gn:admin1_code":"VD",
    "gn:admin2_code":"2223.0",
    "gn:admin3_code":"5533.0",
    "gn:asciiname":"La Tuiliere",
    "gn:country_code":"CH",
    "gn:dem":830,
    "gn:feature_class":"P",
    "gn:feature_code":"PPL",
    "gn:name":"La Tuili\u00e8re",
    "gn:population":0,
    "gn:timezone":"Europe/Zurich",
    "iso:country":"CH",
    "name:fra_x_preferred":[
        "La Tuili\u00e8re"
    ],
    "wof:name":"La Tuiliere",
    "wof:placetype":"neighbourhood"
},
  "geometry": {"coordinates":[6.68992,46.61198],"type":"Point"}
}