{
  "type": "Feature",
  "properties": {
    "gn:gn_country":"CH",
    "gn:gn_fcode":"PPL",
    "gn:gn_pop":620,
    "gn:population":620,
    "iso:country":"CH",
    "name:deu_x_preferred":[
        "Zwillikon"
    ],
    "name:eng_x_preferred":[
        "Zwillikon"
    ],
    "name:nld_x_preferred":[
        "Zwillikon"
    ],
    "name:rus_x_preferred":[
        "\u0426\u0432\u0438\u043b\u043b\u0438\u043a\u043e\u043d"
    ],
    "name:swe_x_preferred":[
        "Zwillikon"
    ],
    "name:uzb_x_preferred":[
        "Zwillikon"
    ],
    "qs_pg:aaroncc":"CH",
    "qs_pg:gn_country":"CH",
    "qs_pg:gn_fcode":"PPL",
    "qs_pg:gn_pop":620,
    "qs_pg:name":"Zwillikon",
    "qs_pg:name_adm0":"Schweiz",
    "qs_pg:name_adm1":"Kanton Z\u00fcrich",
    "qs_pg:photos_9k":1,
    "qs_pg:photos_9r":1,
    "qs_pg:photos_all":12,
    "qs_pg:photos_sr":0,
    "qs_pg:pop_sr":2,
    "qs_pg:qs_pg_placetype":"locality",
    "qs_pg:qs_pg_placetype_gp":"Town",
    "qs_pg:woe_adm0":23424957,
    "woe:adm0_id":23424957,
    "woe:name_adm0":"Schweiz",
    "woe:name_adm1":"Kanton Z\u00fcrich",
    "woe:placetype":"Town",
    "wof:name":"Zwillikon",
    "wof:placetype":"locality",
    "wof:population":620
},
  "geometry": {"coordinates":[8.43124,47.28833],"type":"Point"}
}