{
  "type": "Feature",
  "properties": {
    "gn:admin1_code":"TG",
    "gn:admin2_code":"2012.0",
    "gn:admin3_code":"4536.0",
    "gn:asciiname":"Chalchofe",
    "gn:country_code":"CH",
    "gn:dem":426,
    "gn:feature_class":"P",
    "gn:feature_code":"PPLL",
    "gn:name":"Chalchofe",
    "gn:population":0,
    "gn:timezone":"Europe/Zurich",
    "iso:country":"CH",
    "name:deu_x_preferred":[
        "Chalchofe"
    ],
    "wof:name":"Chalchofe",
    "wof:placetype":"neighbourhood"
},
  "geometry": {"coordinates":[8.7443,47.66105],"type":"Point"}
}