{
  "type": "Feature",
  "properties": {
    "gn:admin1_code":"TI",
    "gn:admin2_code":"2104.0",
    "gn:admin3_code":"5097.0",
    "gn:asciiname":"Borgna",
    "gn:country_code":"CH",
    "gn:dem":807,
    "gn:feature_class":"P",
    "gn:feature_code":"PPL",
    "gn:name":"Borgna",
    "gn:population":0,
    "gn:timezone":"Europe/Zurich",
    "iso:country":"CH",
    "name:ita_x_preferred":[
        "Borgna"
    ],
    "wof:name":"Borgna",
    "wof:placetype":"neighbourhood"
},
  "geometry": {"coordinates":[8.7075,46.1363],"type":"Point"}
}