{
  "type": "Feature",
  "properties": {
    "gn:admin1_code":"TI",
    "gn:admin2_code":"2104.0",
    "gn:admin3_code":"5398.0",
    "gn:asciiname":"Ranzo",
    "gn:country_code":"CH",
    "gn:dem":237,
    "gn:elevation":"208.0",
    "gn:feature_class":"P",
    "gn:feature_code":"PPL",
    "gn:name":"Ranzo",
    "gn:population":0,
    "gn:timezone":"Europe/Zurich",
    "iso:country":"CH",
    "wof:name":"Ranzo",
    "wof:placetype":"locality"
},
  "geometry": {"coordinates":[8.77371,46.11463],"type":"Point"}
}