{
  "type": "Feature",
  "properties": {
    "gn:admin1_code":"SG",
    "gn:admin2_code":"1728.0",
    "gn:admin3_code":"3402.0",
    "gn:asciiname":"Egg",
    "gn:country_code":"CH",
    "gn:dem":750,
    "gn:elevation":"750.0",
    "gn:feature_class":"P",
    "gn:feature_code":"PPL",
    "gn:name":"Egg",
    "gn:population":0,
    "gn:timezone":"Europe/Zurich",
    "iso:country":"CH",
    "name:deu_x_preferred":[
        "Egg (Flawil)"
    ],
    "wof:name":"Egg",
    "wof:placetype":"locality"
},
  "geometry": {"coordinates":[9.2276,47.39313],"type":"Point"}
}