{
  "type": "Feature",
  "properties": {
    "gn:gn_country":"CH",
    "gn:gn_fcode":"PPLX",
    "gn:gn_pop":207,
    "gn:population":207,
    "iso:country":"CH",
    "name:eng_x_preferred":[
        "Wullikon"
    ],
    "name:eng_x_variant":[
        "Birmensdorf / Wullikon"
    ],
    "name:unk_x_variant":[
        "Wullikon"
    ],
    "qs_pg:aaroncc":"CH",
    "qs_pg:gn_country":"CH",
    "qs_pg:gn_fcode":"PPLX",
    "qs_pg:gn_pop":207,
    "qs_pg:name":"Birmensdorf / Wullikon",
    "qs_pg:photos_9r":0,
    "qs_pg:photos_sr":0,
    "qs_pg:pop_sr":2,
    "qs_pg:qs_pg_placetype":"neighbourhood",
    "wof:name":"Wullikon",
    "wof:placetype":"neighbourhood",
    "wof:population":207
},
  "geometry": {"coordinates":[8.43493,47.35278],"type":"Point"}
}