{
  "type": "Feature",
  "properties": {
    "gn:gn_country":"CH",
    "gn:gn_fcode":"PPL",
    "gn:gn_pop":0,
    "iso:country":"CH",
    "name:alb_x_preferred":[
        "Tschappina"
    ],
    "name:baq_x_preferred":[
        "Tschappina"
    ],
    "name:cat_x_preferred":[
        "Tschappina"
    ],
    "name:chi_x_preferred":[
        "\u8328\u5bdf\u76ae\u7d0d"
    ],
    "name:dut_x_preferred":[
        "Tschappina"
    ],
    "name:eng_x_preferred":[
        "Tschappina"
    ],
    "name:epo_x_preferred":[
        "Tschappina GR"
    ],
    "name:fre_x_preferred":[
        "Tschappina"
    ],
    "name:ger_x_preferred":[
        "Tschappina"
    ],
    "name:hun_x_preferred":[
        "Tschappina"
    ],
    "name:ita_x_preferred":[
        "Tschappina"
    ],
    "name:kaz_x_preferred":[
        "\u0427\u0430\u043f\u043f\u0438\u043d\u0430"
    ],
    "name:lmo_x_preferred":[
        "Tschappina"
    ],
    "name:may_x_preferred":[
        "Tschappina"
    ],
    "name:nno_x_preferred":[
        "Tschappina"
    ],
    "name:oci_x_preferred":[
        "Tschappina"
    ],
    "name:pms_x_preferred":[
        "Tschappina"
    ],
    "name:por_x_preferred":[
        "Tschappina"
    ],
    "name:roh_x_preferred":[
        "Tschappina"
    ],
    "name:rus_x_preferred":[
        "\u0427\u0430\u043f\u043f\u0438\u043d\u0430"
    ],
    "name:spa_x_preferred":[
        "Tschappina"
    ],
    "name:swe_x_preferred":[
        "Tschappina"
    ],
    "name:uzb_x_preferred":[
        "Tschappina"
    ],
    "name:vol_x_preferred":[
        "Tschappina"
    ],
    "name:war_x_preferred":[
        "Tschappina"
    ],
    "name:zho_x_preferred":[
        "\u8328\u5bdf\u76ae\u7d0d"
    ],
    "qs_pg:aaroncc":"CH",
    "qs_pg:gn_country":"CH",
    "qs_pg:gn_fcode":"PPL",
    "qs_pg:gn_pop":0,
    "qs_pg:name":"Tschappina",
    "qs_pg:name_adm0":"Schweiz",
    "qs_pg:name_adm1":"Kanton Graub\u00fcnden",
    "qs_pg:photos":39,
    "qs_pg:photos_1k":8,
    "qs_pg:photos_9k":1,
    "qs_pg:photos_9r":2,
    "qs_pg:photos_all":39,
    "qs_pg:photos_sr":2,
    "qs_pg:pop_sr":0,
    "qs_pg:qs_pg_placetype":"locality",
    "qs_pg:qs_pg_placetype_gp":"Town",
    "qs_pg:woe_adm0":23424957,
    "woe:adm0_id":23424957,
    "woe:name_adm0":"Schweiz",
    "woe:name_adm1":"Kanton Graub\u00fcnden",
    "woe:placetype":"Town",
    "wof:name":"Tschappina",
    "wof:placetype":"locality"
},
  "geometry": {"coordinates":[9.38035,46.68754],"type":"Point"}
}