{
  "type": "Feature",
  "properties": {
    "gn:country":"CH",
    "gn:fcode":"PPL",
    "gn:population":0,
    "iso:country":"CH",
    "name:fra_x_preferred":[
        "Soussillon"
    ],
    "qs_pg:aaroncc":"CH",
    "qs_pg:gn_country":"CH",
    "qs_pg:gn_fcode":"PPL",
    "qs_pg:gn_pop":0,
    "qs_pg:name":"Soussillon",
    "qs_pg:name_adm0":"Schweiz",
    "qs_pg:name_adm1":"Canton de Valais",
    "qs_pg:photos":13,
    "qs_pg:photos_1k":3,
    "qs_pg:photos_9k":1,
    "qs_pg:photos_9r":1,
    "qs_pg:photos_all":13,
    "qs_pg:photos_sr":1,
    "qs_pg:pop_sr":0,
    "qs_pg:qs_pg_placetype":"locality",
    "qs_pg:qs_pg_placetype_gp":"Town",
    "qs_pg:woe_adm0":23424957,
    "woe:adm0_id":23424957,
    "woe:name_adm0":"Schweiz",
    "woe:name_adm1":"Canton de Valais",
    "woe:placetype":"Town",
    "wof:lang_x_official":[
        "deu",
        "fra",
        "gsw",
        "ita"
    ],
    "wof:lang_x_spoken":[
        "deu",
        "fra",
        "gsw",
        "ita",
        "roh"
    ],
    "wof:name":"Soussillon",
    "wof:placetype":"neighbourhood"
},
  "geometry": {"coordinates":[7.57609,46.26003],"type":"Point"}
}