{
  "type": "Feature",
  "properties": {
    "gn:gn_country":"CH",
    "gn:gn_fcode":"PPLX",
    "gn:gn_pop":36,
    "gn:population":36,
    "iso:country":"CH",
    "name:unk_x_variant":[
        "Hochbord"
    ],
    "qs_pg:aaroncc":"CH",
    "qs_pg:gn_country":"CH",
    "qs_pg:gn_fcode":"PPLX",
    "qs_pg:gn_pop":36,
    "qs_pg:name":"D\u00fcbendorf / Hochbord",
    "qs_pg:photos_9r":0,
    "qs_pg:photos_sr":0,
    "qs_pg:pop_sr":1,
    "qs_pg:qs_pg_placetype":"neighbourhood",
    "wof:name":"D\u00fcbendorf / Hochbord",
    "wof:placetype":"neighbourhood",
    "wof:population":36
},
  "geometry": {"coordinates":[8.60263,47.39905],"type":"Point"}
}