{
  "type": "Feature",
  "properties": {
    "gn:population":2192,
    "iso:country":"CH",
    "name:als_x_preferred":[
        "Lucens"
    ],
    "name:cat_x_preferred":[
        "Lucens"
    ],
    "name:ceb_x_preferred":[
        "Lucens"
    ],
    "name:deu_x_preferred":[
        "Lucens"
    ],
    "name:eng_x_preferred":[
        "Lucens"
    ],
    "name:epo_x_preferred":[
        "Lucens"
    ],
    "name:eus_x_preferred":[
        "Lucens"
    ],
    "name:fra_x_preferred":[
        "Lucens"
    ],
    "name:gsw_x_preferred":[
        "Lucens"
    ],
    "name:hun_x_preferred":[
        "Lucens"
    ],
    "name:ita_x_preferred":[
        "Lucens"
    ],
    "name:lmo_x_preferred":[
        "Lucens"
    ],
    "name:msa_x_preferred":[
        "Lucens"
    ],
    "name:nld_x_preferred":[
        "Lucens"
    ],
    "name:nno_x_preferred":[
        "Lucens"
    ],
    "name:oci_x_preferred":[
        "Lucens"
    ],
    "name:pol_x_preferred":[
        "Lucens"
    ],
    "name:roh_x_preferred":[
        "Lucens"
    ],
    "name:spa_x_preferred":[
        "Lucens"
    ],
    "name:vol_x_preferred":[
        "Lucens"
    ],
    "name:war_x_preferred":[
        "Lucens"
    ],
    "name:zho_x_preferred":[
        "\u5415\u6851"
    ],
    "qs:a0":"Schweiz#Suisse#Svizzera#Svizra",
    "qs:a1":"*Vaud",
    "qs:a1r":"0",
    "qs:adm0":"Schweiz#Suisse#Svizzera#Svizra",
    "qs:la_lc":"*",
    "qs:level":"locality",
    "qs:loc":"Lucens",
    "qs:loc_alt":"Lucens",
    "qs:pop":0,
    "qs:type":"buffered point",
    "wd:wordcount":2230,
    "wof:name":"Lucens",
    "wof:placetype":"locality",
    "wof:population":2192
},
  "geometry": {"coordinates":[6.839144,46.708237],"type":"Point"}
}