{
  "type": "Feature",
  "properties": {
    "gn:admin1_code":"UR",
    "gn:admin2_code":"400.0",
    "gn:admin3_code":"1211.0",
    "gn:asciiname":"Hinterbaerchi",
    "gn:country_code":"CH",
    "gn:dem":927,
    "gn:feature_class":"P",
    "gn:feature_code":"PPLL",
    "gn:name":"Hinterb\u00e4rchi",
    "gn:population":0,
    "gn:timezone":"Europe/Zurich",
    "iso:country":"CH",
    "name:deu_x_preferred":[
        "Hinterb\u00e4rchi"
    ],
    "wof:name":"Hinterbaerchi",
    "wof:placetype":"locality"
},
  "geometry": {"coordinates":[8.58079,46.91641],"type":"Point"}
}