{
  "type": "Feature",
  "properties": {
    "gn:admin1_code":"GR",
    "gn:admin2_code":"1849.0",
    "gn:admin3_code":"3891.0",
    "gn:asciiname":"Dalfazza",
    "gn:country_code":"CH",
    "gn:dem":800,
    "gn:feature_class":"P",
    "gn:feature_code":"PPLL",
    "gn:name":"Dalfazza",
    "gn:population":0,
    "gn:timezone":"Europe/Zurich",
    "iso:country":"CH",
    "name:roh_x_preferred":[
        "Dalfazza"
    ],
    "wof:lang_x_official":[
        "deu",
        "fra",
        "gsw",
        "ita"
    ],
    "wof:lang_x_spoken":[
        "deu",
        "fra",
        "gsw",
        "ita",
        "roh"
    ],
    "wof:name":"Dalfazza",
    "wof:placetype":"neighbourhood"
},
  "geometry": {"coordinates":[9.76567,46.91436],"type":"Point"}
}