{
  "type": "Feature",
  "properties": {
    "gn:admin1_code":"BE",
    "gn:admin2_code":"249.0",
    "gn:admin3_code":"766.0",
    "gn:asciiname":"Waldried",
    "gn:country_code":"CH",
    "gn:dem":1012,
    "gn:elevation":"990.0",
    "gn:feature_class":"P",
    "gn:feature_code":"PPL",
    "gn:name":"Waldried",
    "gn:population":0,
    "gn:timezone":"Europe/Zurich",
    "iso:country":"CH",
    "wof:name":"Waldried",
    "wof:placetype":"locality"
},
  "geometry": {"coordinates":[7.41501,46.65639],"type":"Point"}
}