{
  "type": "Feature",
  "properties": {
    "gn:admin1_code":"TG",
    "gn:admin2_code":"2013.0",
    "gn:admin3_code":"4683.0",
    "gn:asciiname":"Hohenegg",
    "gn:country_code":"CH",
    "gn:dem":553,
    "gn:feature_class":"P",
    "gn:feature_code":"PPLL",
    "gn:name":"Hohenegg",
    "gn:population":0,
    "gn:timezone":"Europe/Zurich",
    "iso:country":"CH",
    "name:deu_x_preferred":[
        "Hohenegg"
    ],
    "wof:lang_x_official":[
        "deu",
        "fra",
        "gsw",
        "ita"
    ],
    "wof:lang_x_spoken":[
        "deu",
        "fra",
        "gsw",
        "ita",
        "roh"
    ],
    "wof:name":"Hohenegg",
    "wof:placetype":"neighbourhood"
},
  "geometry": {"coordinates":[9.19485,47.60965],"type":"Point"}
}