{
  "type": "Feature",
  "properties": {
    "iso:country":"CH",
    "name:deu_x_preferred":[
        "Carasso TI"
    ],
    "name:deu_x_variant":[
        "Carasso"
    ],
    "name:eng_x_preferred":[
        "Carasso"
    ],
    "name:fra_x_preferred":[
        "Carasso"
    ],
    "name:ita_x_preferred":[
        "Carasso"
    ],
    "name:lmo_x_preferred":[
        "Carass"
    ],
    "name:nld_x_preferred":[
        "Carasso"
    ],
    "qs_pg:aaroncc":"CH",
    "qs_pg:name":"Carasso",
    "qs_pg:name_adm0":"Schweiz",
    "qs_pg:name_adm1":"Cantone Ticino",
    "qs_pg:photos":18,
    "qs_pg:photos_1k":4,
    "qs_pg:photos_9k":1,
    "qs_pg:photos_9r":1,
    "qs_pg:photos_all":18,
    "qs_pg:photos_sr":1,
    "qs_pg:pop_sr":0,
    "qs_pg:qs_pg_placetype":"locality",
    "qs_pg:qs_pg_placetype_gp":"Town",
    "qs_pg:woe_adm0":23424957,
    "woe:adm0_id":23424957,
    "woe:name_adm0":"Schweiz",
    "woe:name_adm1":"Cantone Ticino",
    "woe:placetype":"Town",
    "wof:lang_x_official":[
        "deu",
        "fra",
        "gsw",
        "ita"
    ],
    "wof:lang_x_spoken":[
        "deu",
        "fra",
        "gsw",
        "ita",
        "roh"
    ],
    "wof:name":"Carasso",
    "wof:placetype":"neighbourhood"
},
  "geometry": {"coordinates":[9.016342,46.204985],"type":"Point"}
}