{
  "type": "Feature",
  "properties": {
    "gn:country":"CH",
    "gn:fcode":"PPLX",
    "gn:population":46,
    "iso:country":"CH",
    "name:und_x_variant":[
        "Unter Ricketwil"
    ],
    "qs_pg:aaroncc":"CH",
    "qs_pg:gn_country":"CH",
    "qs_pg:gn_fcode":"PPLX",
    "qs_pg:gn_pop":46,
    "qs_pg:name":"Oberwinterthur (Kreis 2) / Unter Ricketwil",
    "qs_pg:photos_9r":0,
    "qs_pg:photos_sr":0,
    "qs_pg:pop_sr":1,
    "qs_pg:qs_pg_placetype":"neighbourhood",
    "wof:lang_x_official":[
        "deu",
        "fra",
        "gsw",
        "ita"
    ],
    "wof:lang_x_spoken":[
        "deu",
        "fra",
        "gsw",
        "ita",
        "roh"
    ],
    "wof:name":"Unter Ricketwil",
    "wof:placetype":"neighbourhood",
    "wof:population":46
},
  "geometry": {"coordinates":[8.79748,47.48656],"type":"Point"}
}