{
  "type": "Feature",
  "properties": {
    "gn:admin1_code":"BE",
    "gn:admin2_code":"245.0",
    "gn:admin3_code":"424.0",
    "gn:asciiname":"Wil",
    "gn:country_code":"CH",
    "gn:dem":687,
    "gn:feature_class":"P",
    "gn:feature_code":"PPLL",
    "gn:name":"Wil",
    "gn:population":0,
    "gn:timezone":"Europe/Zurich",
    "iso:country":"CH",
    "name:deu_x_preferred":[
        "Wil"
    ],
    "wof:name":"Wil",
    "wof:placetype":"neighbourhood"
},
  "geometry": {"coordinates":[7.70308,47.11551],"type":"Point"}
}