{
  "type": "Feature",
  "properties": {
    "gn:admin1_code":"BE",
    "gn:admin2_code":"245.0",
    "gn:admin3_code":"424.0",
    "gn:asciiname":"Wil",
    "gn:country_code":"CH",
    "gn:dem":687,
    "gn:feature_class":"P",
    "gn:feature_code":"PPLL",
    "gn:name":"Wil",
    "gn:population":0,
    "gn:timezone":"Europe/Zurich",
    "iso:country":"CH",
    "name:als_x_preferred":[
        "Wil"
    ],
    "name:ara_x_preferred":[
        "\u0648\u064a\u0644"
    ],
    "name:azb_x_preferred":[
        "\u0648\u06cc\u0644"
    ],
    "name:cat_x_preferred":[
        "Wil"
    ],
    "name:dan_x_preferred":[
        "Wil"
    ],
    "name:deu_x_preferred":[
        "Wil"
    ],
    "name:epo_x_preferred":[
        "Wil"
    ],
    "name:eus_x_preferred":[
        "Wil"
    ],
    "name:fas_x_preferred":[
        "\u0648\u06cc\u0644"
    ],
    "name:fin_x_preferred":[
        "Wil"
    ],
    "name:fra_x_preferred":[
        "Wil"
    ],
    "name:gle_x_preferred":[
        "Wil"
    ],
    "name:ind_x_preferred":[
        "Wil"
    ],
    "name:ita_x_preferred":[
        "Wil"
    ],
    "name:kaz_x_preferred":[
        "\u0412\u0438\u043b\u044c"
    ],
    "name:kor_x_preferred":[
        "\ube4c"
    ],
    "name:lit_x_preferred":[
        "Vilis"
    ],
    "name:lmo_x_preferred":[
        "Wil"
    ],
    "name:msa_x_preferred":[
        "Wil"
    ],
    "name:nld_x_preferred":[
        "Wil"
    ],
    "name:nno_x_preferred":[
        "Wil"
    ],
    "name:pms_x_preferred":[
        "Wil"
    ],
    "name:pol_x_preferred":[
        "Wil"
    ],
    "name:por_x_preferred":[
        "Wil"
    ],
    "name:que_x_preferred":[
        "Wil"
    ],
    "name:rus_x_preferred":[
        "\u0412\u0438\u043b\u044c"
    ],
    "name:spa_x_preferred":[
        "Wil"
    ],
    "name:sqi_x_preferred":[
        "Wil"
    ],
    "name:srp_x_preferred":[
        "\u0412\u0438\u043b"
    ],
    "name:swe_x_preferred":[
        "Wil"
    ],
    "name:tur_x_preferred":[
        "Wil"
    ],
    "name:ukr_x_preferred":[
        "\u0412\u0456\u043b\u044c"
    ],
    "name:uzb_x_preferred":[
        "Wil"
    ],
    "name:vec_x_preferred":[
        "Wil"
    ],
    "name:war_x_preferred":[
        "Wil"
    ],
    "wof:name":"Wil",
    "wof:placetype":"neighbourhood"
},
  "geometry": {"coordinates":[7.70308,47.11551],"type":"Point"}
}