{
  "type": "Feature",
  "properties": {
    "gn:admin1_code":"TI",
    "gn:admin2_code":"2105.0",
    "gn:admin3_code":"5226.0",
    "gn:asciiname":"Favessa",
    "gn:country_code":"CH",
    "gn:dem":566,
    "gn:feature_class":"P",
    "gn:feature_code":"PPL",
    "gn:name":"Favessa",
    "gn:population":0,
    "gn:timezone":"Europe/Zurich",
    "iso:country":"CH",
    "name:ita_x_preferred":[
        "Favessa"
    ],
    "wof:name":"Favessa",
    "wof:placetype":"neighbourhood"
},
  "geometry": {"coordinates":[8.95056,46.06827],"type":"Point"}
}