{
  "type": "Feature",
  "properties": {
    "gn:gn_country":"CH",
    "gn:gn_fcode":"PPLX",
    "gn:gn_pop":93,
    "gn:population":93,
    "iso:country":"CH",
    "name:ceb_x_preferred":[
        "Seen"
    ],
    "name:deu_x_preferred":[
        "Sonnenberg"
    ],
    "name:eng_x_preferred":[
        "Sonnenberg"
    ],
    "name:eng_x_variant":[
        [
            "Sonnenberg"
        ],
        "Sch\u00f6fflisdorf / Sonnenberg"
    ],
    "name:swe_x_preferred":[
        "Seen"
    ],
    "name:unk_x_variant":[
        "Sonnenberg"
    ],
    "qs_pg:aaroncc":"CH",
    "qs_pg:gn_country":"CH",
    "qs_pg:gn_fcode":"PPLX",
    "qs_pg:gn_pop":93,
    "qs_pg:name":"Sch\u00f6fflisdorf / Sonnenberg",
    "qs_pg:photos_9r":0,
    "qs_pg:photos_sr":0,
    "qs_pg:pop_sr":1,
    "qs_pg:qs_pg_placetype":"neighbourhood",
    "wof:name":"Sonnenberg",
    "wof:placetype":"neighbourhood",
    "wof:population":93
},
  "geometry": {"coordinates":[8.41934,47.50174],"type":"Point"}
}