{
  "type": "Feature",
  "properties": {
    "gn:gn_country":"CH",
    "gn:gn_fcode":"PPL",
    "gn:gn_pop":1661,
    "gn:population":1661,
    "iso:country":"CH",
    "name:cat_x_preferred":[
        "Vordemwald"
    ],
    "name:deu_x_preferred":[
        "Vordemwald"
    ],
    "name:eng_x_preferred":[
        "Vordemwald"
    ],
    "name:epo_x_preferred":[
        "Vordemwald"
    ],
    "name:eus_x_preferred":[
        "Vordemwald"
    ],
    "name:fra_x_preferred":[
        "Vordemwald"
    ],
    "name:hun_x_preferred":[
        "Vordemwald"
    ],
    "name:ita_x_preferred":[
        "Vordemwald"
    ],
    "name:kaz_x_preferred":[
        "\u0424\u043e\u0440\u0434\u0435\u043c\u0432\u0430\u043b\u044c\u0434"
    ],
    "name:lmo_x_preferred":[
        "Vordemwald"
    ],
    "name:msa_x_preferred":[
        "Vordemwald"
    ],
    "name:nld_x_preferred":[
        "Vordemwald"
    ],
    "name:nno_x_preferred":[
        "Vordemwald"
    ],
    "name:oci_x_preferred":[
        "Vordemwald"
    ],
    "name:pms_x_preferred":[
        "Vordemwald"
    ],
    "name:por_x_preferred":[
        "Vordemwald"
    ],
    "name:roh_x_preferred":[
        "Vordemwald"
    ],
    "name:rus_x_preferred":[
        "\u0424\u043e\u0440\u0434\u0435\u043c\u0432\u0430\u043b\u044c\u0434"
    ],
    "name:spa_x_preferred":[
        "Vordemwald"
    ],
    "name:sqi_x_preferred":[
        "Vordemwald"
    ],
    "name:swe_x_preferred":[
        "Vordemwald"
    ],
    "name:uzb_x_preferred":[
        "Vordemwald"
    ],
    "name:vie_x_preferred":[
        "Vordemwald"
    ],
    "name:vol_x_preferred":[
        "Vordemwald"
    ],
    "name:war_x_preferred":[
        "Vordemwald"
    ],
    "name:zho_x_preferred":[
        "\u6c83\u5fb7\u59c6\u74e6\u5fb7"
    ],
    "qs_pg:aaroncc":"CH",
    "qs_pg:gn_country":"CH",
    "qs_pg:gn_fcode":"PPL",
    "qs_pg:gn_pop":1661,
    "qs_pg:name":"Vordemwald",
    "qs_pg:name_adm0":"Schweiz",
    "qs_pg:name_adm1":"Kanton Aargau",
    "qs_pg:photos_9k":1,
    "qs_pg:photos_9r":1,
    "qs_pg:photos_all":2,
    "qs_pg:photos_sr":0,
    "qs_pg:pop_sr":3,
    "qs_pg:qs_pg_placetype":"locality",
    "qs_pg:qs_pg_placetype_gp":"Town",
    "qs_pg:woe_adm0":23424957,
    "woe:adm0_id":23424957,
    "woe:name_adm0":"Schweiz",
    "woe:name_adm1":"Kanton Aargau",
    "woe:placetype":"Town",
    "wof:name":"Vordemwald",
    "wof:placetype":"locality",
    "wof:population":1661
},
  "geometry": {"coordinates":[7.90114,47.27585],"type":"Point"}
}