{
  "type": "Feature",
  "properties": {
    "gn:country":"CH",
    "gn:fcode":"PPLX",
    "gn:population":413,
    "iso:country":"CH",
    "name:eng_x_preferred":[
        "Unterdorf"
    ],
    "name:eng_x_variant":[
        "R\u00fcschlikon / Unterdorf"
    ],
    "qs_pg:aaroncc":"CH",
    "qs_pg:gn_country":"CH",
    "qs_pg:gn_fcode":"PPLX",
    "qs_pg:gn_pop":413,
    "qs_pg:name":"R\u00fcschlikon / Unterdorf",
    "qs_pg:photos_9r":0,
    "qs_pg:photos_sr":0,
    "qs_pg:pop_sr":2,
    "qs_pg:qs_pg_placetype":"neighbourhood",
    "wof:name":"Unterdorf",
    "wof:placetype":"neighbourhood",
    "wof:population":413
},
  "geometry": {"coordinates":[8.55608,47.3093],"type":"Point"}
}