{
  "type": "Feature",
  "properties": {
    "gn:admin1_code":"BE",
    "gn:admin2_code":"250.0",
    "gn:admin3_code":"576.0",
    "gn:asciiname":"Rotsteckli",
    "gn:country_code":"CH",
    "gn:dem":2095,
    "gn:feature_class":"P",
    "gn:feature_code":"PPL",
    "gn:name":"Rotsteckli",
    "gn:population":0,
    "gn:timezone":"Europe/Zurich",
    "iso:country":"CH",
    "name:deu_x_preferred":[
        "Rotsteckli"
    ],
    "wof:lang_x_official":[
        "deu",
        "fra",
        "gsw",
        "ita"
    ],
    "wof:lang_x_spoken":[
        "deu",
        "fra",
        "gsw",
        "ita",
        "roh"
    ],
    "wof:name":"Rotsteckli",
    "wof:placetype":"neighbourhood"
},
  "geometry": {"coordinates":[7.96055,46.58935],"type":"Point"}
}