{
  "type": "Feature",
  "properties": {
    "gn:admin1_code":"BE",
    "gn:admin2_code":"246.0",
    "gn:admin3_code":"670.0",
    "gn:asciiname":"Sueri",
    "gn:country_code":"CH",
    "gn:dem":594,
    "gn:elevation":"597.0",
    "gn:feature_class":"P",
    "gn:feature_code":"PPL",
    "gn:name":"S\u00fcri",
    "gn:population":0,
    "gn:timezone":"Europe/Zurich",
    "iso:country":"CH",
    "wof:name":"Sueri",
    "wof:placetype":"neighbourhood"
},
  "geometry": {"coordinates":[7.26945,46.92067],"type":"Point"}
}