{
  "type": "Feature",
  "properties": {
    "gn:country":"CH",
    "gn:fcode":"PPLX",
    "gn:population":504,
    "iso:country":"CH",
    "name:eng_x_preferred":[
        "P\u00fcnten-Ifang"
    ],
    "name:eng_x_variant":[
        "Seuzach Dorf / P\u00fcnten-Ifang"
    ],
    "qs_pg:aaroncc":"CH",
    "qs_pg:gn_country":"CH",
    "qs_pg:gn_fcode":"PPLX",
    "qs_pg:gn_pop":504,
    "qs_pg:name":"Seuzach Dorf / P\u00fcnten-Ifang",
    "qs_pg:photos_9r":0,
    "qs_pg:photos_sr":0,
    "qs_pg:pop_sr":2,
    "qs_pg:qs_pg_placetype":"neighbourhood",
    "wof:name":"P\u00fcnten-Ifang",
    "wof:placetype":"neighbourhood",
    "wof:population":504
},
  "geometry": {"coordinates":[8.72915,47.53743],"type":"Point"}
}