{
  "type": "Feature",
  "properties": {
    "gn:country":"CH",
    "gn:fcode":"PPLX",
    "gn:population":420,
    "iso:country":"CH",
    "name:eng_x_preferred":[
        "Thesenacher"
    ],
    "name:eng_x_variant":[
        "Zumikon / Thesenacher"
    ],
    "qs_pg:aaroncc":"CH",
    "qs_pg:gn_country":"CH",
    "qs_pg:gn_fcode":"PPLX",
    "qs_pg:gn_pop":420,
    "qs_pg:name":"Zumikon / Thesenacher",
    "qs_pg:photos_9r":0,
    "qs_pg:photos_sr":0,
    "qs_pg:pop_sr":2,
    "qs_pg:qs_pg_placetype":"neighbourhood",
    "wof:lang_x_official":[
        "deu",
        "fra",
        "gsw",
        "ita"
    ],
    "wof:lang_x_spoken":[
        "deu",
        "fra",
        "gsw",
        "ita",
        "roh"
    ],
    "wof:name":"Thesenacher",
    "wof:placetype":"neighbourhood",
    "wof:population":420
},
  "geometry": {"coordinates":[8.6295,47.32762],"type":"Point"}
}