{
  "type": "Feature",
  "properties": {
    "gn:admin1_code":"BE",
    "gn:admin2_code":"245.0",
    "gn:admin3_code":"956.0",
    "gn:asciiname":"Scheuer",
    "gn:country_code":"CH",
    "gn:dem":686,
    "gn:feature_class":"P",
    "gn:feature_code":"PPLL",
    "gn:name":"Scheuer",
    "gn:population":0,
    "gn:timezone":"Europe/Zurich",
    "iso:country":"CH",
    "name:deu_x_preferred":[
        "Scheuer"
    ],
    "wof:name":"Scheuer",
    "wof:placetype":"neighbourhood"
},
  "geometry": {"coordinates":[7.69622,47.03831],"type":"Point"}
}