{
  "type": "Feature",
  "properties": {
    "gn:admin1_code":"SG",
    "gn:admin2_code":"1722.0",
    "gn:admin3_code":"3218.0",
    "gn:asciiname":"Tuebach",
    "gn:country_code":"CH",
    "gn:dem":416,
    "gn:feature_class":"P",
    "gn:feature_code":"PPL",
    "gn:name":"T\u00fcbach",
    "gn:population":0,
    "gn:timezone":"Europe/Zurich",
    "iso:country":"CH",
    "name:kaz_x_preferred":[
        "\u0422\u044e\u0431\u0430\u0445"
    ],
    "name:rus_x_preferred":[
        "\u0422\u044e\u0431\u0430\u0445"
    ],
    "name:und_x_variant":[
        "T\u00fcbach"
    ],
    "name:zho_x_preferred":[
        "\u8482\u5df4\u8d6b"
    ],
    "wof:name":"Tuebach",
    "wof:placetype":"locality"
},
  "geometry": {"coordinates":[9.45462,47.48678],"type":"Point"}
}