{
  "type": "Feature",
  "properties": {
    "gn:admin1_code":"FR",
    "gn:admin2_code":"1005.0",
    "gn:admin3_code":"2284.0",
    "gn:asciiname":"Nant",
    "gn:country_code":"CH",
    "gn:dem":437,
    "gn:elevation":"434.0",
    "gn:feature_class":"P",
    "gn:feature_code":"PPL",
    "gn:name":"Nant",
    "gn:population":0,
    "gn:timezone":"Europe/Zurich",
    "iso:country":"CH",
    "wof:lang_x_official":[
        "deu",
        "fra",
        "gsw",
        "ita"
    ],
    "wof:lang_x_spoken":[
        "deu",
        "fra",
        "gsw",
        "ita",
        "roh"
    ],
    "wof:name":"Nant",
    "wof:placetype":"neighbourhood"
},
  "geometry": {"coordinates":[7.10707,46.95799],"type":"Point"}
}