{
  "type": "Feature",
  "properties": {
    "gn:gn_country":"CH",
    "gn:gn_fcode":"PPLX",
    "gn:gn_pop":1568,
    "gn:population":1568,
    "iso:country":"CH",
    "name:eng_x_preferred":[
        "Berg"
    ],
    "name:eng_x_variant":[
        "Thalwil / Berg"
    ],
    "name:unk_x_variant":[
        "Berg"
    ],
    "qs_pg:aaroncc":"CH",
    "qs_pg:gn_country":"CH",
    "qs_pg:gn_fcode":"PPLX",
    "qs_pg:gn_pop":1568,
    "qs_pg:name":"Thalwil / Berg",
    "qs_pg:photos_9r":0,
    "qs_pg:photos_sr":0,
    "qs_pg:pop_sr":3,
    "qs_pg:qs_pg_placetype":"neighbourhood",
    "wof:name":"Berg",
    "wof:placetype":"neighbourhood",
    "wof:population":1568
},
  "geometry": {"coordinates":[8.55602,47.29178],"type":"Point"}
}