{
  "type": "Feature",
  "properties": {
    "gn:admin1_code":"BE",
    "gn:admin2_code":"246.0",
    "gn:admin3_code":"861.0",
    "gn:asciiname":"Schliermatt",
    "gn:country_code":"CH",
    "gn:dem":573,
    "gn:feature_class":"P",
    "gn:feature_code":"PPLL",
    "gn:name":"Schliermatt",
    "gn:population":0,
    "gn:timezone":"Europe/Zurich",
    "iso:country":"CH",
    "name:deu_x_preferred":[
        "Schliermatt"
    ],
    "wof:name":"Schliermatt",
    "wof:placetype":"locality"
},
  "geometry": {"coordinates":[7.48304,46.90179000000001],"type":"Point"}
}