{
  "type": "Feature",
  "properties": {
    "gn:admin1_code":"TG",
    "gn:admin2_code":"2015.0",
    "gn:admin3_code":"4946.0",
    "gn:asciiname":"Schlipfenberg",
    "gn:country_code":"CH",
    "gn:dem":499,
    "gn:feature_class":"P",
    "gn:feature_code":"PPLL",
    "gn:name":"Schlipfenberg",
    "gn:population":0,
    "gn:timezone":"Europe/Zurich",
    "iso:country":"CH",
    "name:deu_x_preferred":[
        "Schlipfenberg"
    ],
    "wof:name":"Schlipfenberg",
    "wof:placetype":"neighbourhood"
},
  "geometry": {"coordinates":[9.11388,47.57196],"type":"Point"}
}