{
  "type": "Feature",
  "properties": {
    "gn:admin1_code":"AG",
    "gn:admin2_code":"1911.0",
    "gn:admin3_code":"4322.0",
    "gn:asciiname":"Wislikofen",
    "gn:country_code":"CH",
    "gn:dem":422,
    "gn:feature_class":"P",
    "gn:feature_code":"PPL",
    "gn:name":"Wislikofen",
    "gn:population":0,
    "gn:timezone":"Europe/Zurich",
    "iso:country":"CH",
    "name:kaz_x_preferred":[
        "\u0412\u0438\u0441\u043b\u0438\u043a\u043e\u0444\u0435\u043d"
    ],
    "name:rus_x_preferred":[
        "\u0412\u0438\u0441\u043b\u0438\u043a\u043e\u0444\u0435\u043d"
    ],
    "name:zho_x_preferred":[
        "\u7dad\u65af\u5229\u79d1\u82ac"
    ],
    "wof:name":"Wislikofen",
    "wof:placetype":"locality"
},
  "geometry": {"coordinates":[8.36389,47.55833],"type":"Point"}
}