{
  "type": "Feature",
  "properties": {
    "gn:admin1_code":"UR",
    "gn:admin2_code":"400.0",
    "gn:admin3_code":"1207.0",
    "gn:asciiname":"Steinrustig",
    "gn:country_code":"CH",
    "gn:dem":1554,
    "gn:feature_class":"P",
    "gn:feature_code":"PPLL",
    "gn:name":"Steinrustig",
    "gn:population":0,
    "gn:timezone":"Europe/Zurich",
    "iso:country":"CH",
    "name:deu_x_preferred":[
        "Steinrustig"
    ],
    "wof:name":"Steinrustig",
    "wof:placetype":"neighbourhood"
},
  "geometry": {"coordinates":[8.66247,46.91608],"type":"Point"}
}