{
  "type": "Feature",
  "properties": {
    "gn:admin1_code":"ZH",
    "gn:admin2_code":"102.0",
    "gn:admin3_code":"36.0",
    "gn:asciiname":"Uf Poeschen",
    "gn:country_code":"CH",
    "gn:dem":426,
    "gn:feature_class":"P",
    "gn:feature_code":"PPLL",
    "gn:name":"Uf P\u00f6schen",
    "gn:population":0,
    "gn:timezone":"Europe/Zurich",
    "iso:country":"CH",
    "name:deu_x_preferred":[
        "Uf P\u00f6schen"
    ],
    "wof:name":"Uf Poeschen",
    "wof:placetype":"locality"
},
  "geometry": {"coordinates":[8.78201,47.62432],"type":"Point"}
}