{
  "type": "Feature",
  "properties": {
    "gn:gn_country":"CH",
    "gn:gn_fcode":"PPL",
    "gn:gn_pop":263,
    "gn:population":263,
    "iso:country":"CH",
    "name:cat_x_preferred":[
        "Albinen"
    ],
    "name:deu_x_preferred":[
        "Albinen"
    ],
    "name:eng_x_preferred":[
        "Albinen"
    ],
    "name:epo_x_preferred":[
        "Albinen"
    ],
    "name:eus_x_preferred":[
        "Albinen"
    ],
    "name:fra_x_preferred":[
        "Albinen"
    ],
    "name:glg_x_preferred":[
        "Albinen"
    ],
    "name:hun_x_preferred":[
        "Albinen"
    ],
    "name:ita_x_preferred":[
        "Albinen"
    ],
    "name:lmo_x_preferred":[
        "Albinen"
    ],
    "name:msa_x_preferred":[
        "Albinen"
    ],
    "name:nld_x_preferred":[
        "Albinen"
    ],
    "name:nno_x_preferred":[
        "Albinen"
    ],
    "name:oci_x_preferred":[
        "Albinen"
    ],
    "name:pms_x_preferred":[
        "Albinen"
    ],
    "name:por_x_preferred":[
        "Albinen"
    ],
    "name:roh_x_preferred":[
        "Albinen"
    ],
    "name:spa_x_preferred":[
        "Albinen"
    ],
    "name:sqi_x_preferred":[
        "Albinen"
    ],
    "name:swe_x_preferred":[
        "Albinen"
    ],
    "name:vie_x_preferred":[
        "Albinen"
    ],
    "name:vol_x_preferred":[
        "Albinen"
    ],
    "name:war_x_preferred":[
        "Albinen"
    ],
    "name:zho_x_preferred":[
        "\u963f\u723e\u8cd3\u6069"
    ],
    "qs_pg:aaroncc":"CH",
    "qs_pg:gn_country":"CH",
    "qs_pg:gn_fcode":"PPL",
    "qs_pg:gn_pop":263,
    "qs_pg:name":"Albinen",
    "qs_pg:name_adm0":"Schweiz",
    "qs_pg:name_adm1":"Canton de Valais",
    "qs_pg:photos":109,
    "qs_pg:photos_1k":22,
    "qs_pg:photos_9k":1,
    "qs_pg:photos_9r":3,
    "qs_pg:photos_all":109,
    "qs_pg:photos_sr":3,
    "qs_pg:pop_sr":2,
    "qs_pg:qs_pg_placetype":"locality",
    "qs_pg:qs_pg_placetype_gp":"Town",
    "qs_pg:woe_adm0":23424957,
    "woe:adm0_id":23424957,
    "woe:name_adm0":"Schweiz",
    "woe:name_adm1":"Canton de Valais",
    "woe:placetype":"Town",
    "wof:name":"Albinen",
    "wof:placetype":"locality",
    "wof:population":263
},
  "geometry": {"coordinates":[7.63318,46.34071],"type":"Point"}
}