{
  "type": "Feature",
  "properties": {
    "gn:gn_country":"CH",
    "iso:country":"CH",
    "qs_pg:aaroncc":"CH",
    "qs_pg:gn_country":"CH",
    "qs_pg:name":"Moillesulaz",
    "qs_pg:name_adm0":"Schweiz",
    "qs_pg:name_adm1":"Canton de Gen\u00e8ve",
    "qs_pg:photos":7,
    "qs_pg:photos_1k":1,
    "qs_pg:photos_9k":1,
    "qs_pg:photos_9r":1,
    "qs_pg:photos_all":7,
    "qs_pg:photos_sr":1,
    "qs_pg:pop_sr":0,
    "qs_pg:qs_pg_placetype":"locality",
    "qs_pg:qs_pg_placetype_gp":"Town",
    "qs_pg:woe_adm0":23424957,
    "woe:adm0_id":23424957,
    "woe:name_adm0":"Schweiz",
    "woe:name_adm1":"Canton de Gen\u00e8ve",
    "woe:placetype":"Town",
    "wof:name":"Moillesulaz",
    "wof:placetype":"locality"
},
  "geometry": {"coordinates":[6.205773,46.192487],"type":"Point"}
}