{
  "type": "Feature",
  "properties": {
    "gn:admin1_code":"LU",
    "gn:admin2_code":"314.0",
    "gn:admin3_code":"1093.0",
    "gn:asciiname":"Wartensee",
    "gn:country_code":"CH",
    "gn:dem":558,
    "gn:feature_class":"P",
    "gn:feature_code":"PPLL",
    "gn:name":"Wartensee",
    "gn:population":0,
    "gn:timezone":"Europe/Zurich",
    "iso:country":"CH",
    "name:deu_x_preferred":[
        "Wartensee"
    ],
    "wof:name":"Wartensee",
    "wof:placetype":"neighbourhood"
},
  "geometry": {"coordinates":[8.17293,47.11609],"type":"Point"}
}