{
  "type": "Feature",
  "properties": {
    "gn:admin1_code":"SG",
    "gn:admin2_code":"1721.0",
    "gn:admin3_code":"3202.0",
    "gn:asciiname":"Rotzenwil",
    "gn:country_code":"CH",
    "gn:dem":522,
    "gn:elevation":"531.0",
    "gn:feature_class":"P",
    "gn:feature_code":"PPL",
    "gn:name":"Rotzenwil",
    "gn:population":0,
    "gn:timezone":"Europe/Zurich",
    "iso:country":"CH",
    "wof:name":"Rotzenwil",
    "wof:placetype":"neighbourhood"
},
  "geometry": {"coordinates":[9.29804,47.51634],"type":"Point"}
}