{
  "type": "Feature",
  "properties": {
    "gn:country":"CH",
    "gn:fcode":"PPLL",
    "gn:population":14,
    "iso:country":"CH",
    "name:hun_x_preferred":[
        "Steinberg"
    ],
    "name:jpn_x_preferred":[
        "\u30b9\u30bf\u30a4\u30f3\u30d0\u30fc\u30b0"
    ],
    "name:kor_x_preferred":[
        "\uc2a4\ud14c\uc778\ubc84\uadf8"
    ],
    "name:nld_x_preferred":[
        "Steinberg"
    ],
    "name:por_x_preferred":[
        "Steinberg"
    ],
    "name:spa_x_preferred":[
        "Steinberg"
    ],
    "name:swe_x_preferred":[
        "Steinberg"
    ],
    "name:tha_x_preferred":[
        "\u0e2a\u0e44\u0e15\u0e19\u0e4c\u0e40\u0e1a\u0e34\u0e23\u0e4c\u0e01"
    ],
    "name:tha_x_variant":[
        "\u0e0a\u0e44\u0e15\u0e19\u0e4c\u0e41\u0e1a\u0e23\u0e4c\u0e04"
    ],
    "name:tur_x_preferred":[
        "Steinberg"
    ],
    "name:ukr_x_preferred":[
        "Steinberg"
    ],
    "name:zho_x_preferred":[
        "Steinberg"
    ],
    "qs_pg:aaroncc":"CH",
    "qs_pg:gn_country":"CH",
    "qs_pg:gn_fcode":"PPLL",
    "qs_pg:gn_pop":14,
    "qs_pg:name":"Steinberg",
    "qs_pg:photos_9r":0,
    "qs_pg:photos_sr":0,
    "qs_pg:pop_sr":1,
    "qs_pg:qs_pg_placetype":"locality",
    "wof:name":"Steinberg",
    "wof:placetype":"neighbourhood",
    "wof:population":14
},
  "geometry": {"coordinates":[8.7744,47.33755],"type":"Point"}
}