{
  "type": "Feature",
  "properties": {
    "gn:admin1_code":"ZH",
    "gn:admin2_code":"102.0",
    "gn:admin3_code":"40.0",
    "gn:asciiname":"Hebsack",
    "gn:country_code":"CH",
    "gn:dem":504,
    "gn:feature_class":"P",
    "gn:feature_code":"PPLL",
    "gn:name":"Hebsack",
    "gn:population":0,
    "gn:timezone":"Europe/Zurich",
    "iso:country":"CH",
    "name:deu_x_preferred":[
        "Hebsack"
    ],
    "wof:lang_x_official":[
        "deu",
        "fra",
        "gsw",
        "ita"
    ],
    "wof:lang_x_spoken":[
        "deu",
        "fra",
        "gsw",
        "ita",
        "roh"
    ],
    "wof:name":"Hebsack",
    "wof:placetype":"neighbourhood"
},
  "geometry": {"coordinates":[8.68534,47.6507],"type":"Point"}
}