{
  "type": "Feature",
  "properties": {
    "gn:gn_country":"CH",
    "gn:gn_fcode":"ADM3",
    "gn:gn_pop":1706,
    "gn:population":1775,
    "iso:country":"CH",
    "name:alb_x_preferred":[
        "Wolfhalden"
    ],
    "name:baq_x_preferred":[
        "Wolfhalden"
    ],
    "name:cat_x_preferred":[
        "Wolfhalden"
    ],
    "name:chv_x_preferred":[
        "\u0412\u043e\u043b\u044c\u0444\u0445\u0430\u043b\u044c\u0434\u0435\u043d"
    ],
    "name:dut_x_preferred":[
        "Wolfhalden"
    ],
    "name:eng_x_preferred":[
        "Wolfhalden"
    ],
    "name:epo_x_preferred":[
        "Wolfhalden"
    ],
    "name:fre_x_preferred":[
        "Wolfhalden"
    ],
    "name:ger_x_preferred":[
        "Wolfhalden"
    ],
    "name:hun_x_preferred":[
        "Wolfhalden"
    ],
    "name:ita_x_preferred":[
        "Wolfhalden"
    ],
    "name:kaz_x_preferred":[
        "\u0412\u043e\u043b\u044c\u0444\u0445\u0430\u043b\u044c\u0434\u0435\u043d"
    ],
    "name:lmo_x_preferred":[
        "Wolfhalden"
    ],
    "name:nno_x_preferred":[
        "Wolfhalden"
    ],
    "name:pms_x_preferred":[
        "Wolfhalden"
    ],
    "name:pnb_x_preferred":[
        "\u0648\u0648\u0644\u0641\u06c1\u0627\u0644\u062f\u0646"
    ],
    "name:pol_x_preferred":[
        "Wolfhalden"
    ],
    "name:por_x_preferred":[
        "Wolfhalden"
    ],
    "name:rum_x_preferred":[
        "Wolfhalden"
    ],
    "name:rus_x_preferred":[
        "\u0412\u043e\u043b\u044c\u0444\u0445\u0430\u043b\u044c\u0434\u0435\u043d"
    ],
    "name:spa_x_preferred":[
        "Wolfhalden"
    ],
    "name:swe_x_preferred":[
        "Wolfhalden"
    ],
    "name:uzb_x_preferred":[
        "Wolfhalden"
    ],
    "name:vol_x_preferred":[
        "Wolfhalden"
    ],
    "name:war_x_preferred":[
        "Wolfhalden"
    ],
    "qs_pg:aaroncc":"CH",
    "qs_pg:gn_country":"CH",
    "qs_pg:gn_fcode":"ADM3",
    "qs_pg:gn_pop":1706,
    "qs_pg:name":"Wolfhalden",
    "qs_pg:name_adm0":"Schweiz",
    "qs_pg:name_adm1":"Kanton Appenzell Ausserrhoden",
    "qs_pg:photos":12,
    "qs_pg:photos_1k":2,
    "qs_pg:photos_9k":1,
    "qs_pg:photos_9r":1,
    "qs_pg:photos_all":12,
    "qs_pg:photos_sr":1,
    "qs_pg:pop_sr":3,
    "qs_pg:qs_pg_placetype":"locality",
    "qs_pg:qs_pg_placetype_gp":"Town",
    "qs_pg:woe_adm0":23424957,
    "woe:adm0_id":23424957,
    "woe:name_adm0":"Schweiz",
    "woe:name_adm1":"Kanton Appenzell Ausserrhoden",
    "woe:placetype":"Town",
    "wof:name":"Wolfhalden",
    "wof:placetype":"locality",
    "wof:population":1775
},
  "geometry": {"coordinates":[9.5606,47.44969],"type":"Point"}
}