{
  "type": "Feature",
  "properties": {
    "gn:gn_country":"CH",
    "gn:gn_fcode":"PPL",
    "gn:gn_pop":451,
    "gn:population":451,
    "iso:country":"CH",
    "name:ara_x_preferred":[
        "\u0647\u0648\u062a\u0646"
    ],
    "name:cat_x_preferred":[
        "H\u00fctten"
    ],
    "name:chv_x_preferred":[
        "\u0425\u044e\u0442\u0442\u0435\u043d"
    ],
    "name:deu_x_preferred":[
        "H\u00fctten ZH"
    ],
    "name:eng_x_preferred":[
        "H\u00fctten"
    ],
    "name:epo_x_preferred":[
        "H\u00fctten ZH"
    ],
    "name:eus_x_preferred":[
        "H\u00fctten"
    ],
    "name:fra_x_preferred":[
        "H\u00fctten"
    ],
    "name:gsw_x_preferred":[
        "H\u00fctte"
    ],
    "name:hun_x_preferred":[
        "H\u00fctten"
    ],
    "name:ita_x_preferred":[
        "H\u00fctten"
    ],
    "name:kaz_x_preferred":[
        "\u0425\u044e\u0442\u0442\u0435\u043d"
    ],
    "name:lmo_x_preferred":[
        "H\u00fctten"
    ],
    "name:msa_x_preferred":[
        "H\u00fctten"
    ],
    "name:nld_x_preferred":[
        "H\u00fctten"
    ],
    "name:nno_x_preferred":[
        "H\u00fctten i Sveits"
    ],
    "name:oci_x_preferred":[
        "H\u00fctten"
    ],
    "name:pms_x_preferred":[
        "H\u00fctten"
    ],
    "name:por_x_preferred":[
        "H\u00fctten"
    ],
    "name:rus_x_preferred":[
        "\u0425\u044e\u0442\u0442\u0435\u043d"
    ],
    "name:spa_x_preferred":[
        "H\u00fctten"
    ],
    "name:uzb_x_preferred":[
        "H\u00fctten"
    ],
    "name:vol_x_preferred":[
        "H\u00fctten"
    ],
    "name:war_x_preferred":[
        "H\u00fctten"
    ],
    "name:zho_x_preferred":[
        "\u8a31\u6ed5"
    ],
    "qs_pg:aaroncc":"CH",
    "qs_pg:gn_country":"CH",
    "qs_pg:gn_fcode":"PPL",
    "qs_pg:gn_pop":451,
    "qs_pg:name":"H\u00fctten",
    "qs_pg:name_adm0":"Schweiz",
    "qs_pg:name_adm1":"Kanton Z\u00fcrich",
    "qs_pg:photos":38,
    "qs_pg:photos_1k":8,
    "qs_pg:photos_9k":1,
    "qs_pg:photos_9r":2,
    "qs_pg:photos_all":38,
    "qs_pg:photos_sr":2,
    "qs_pg:pop_sr":2,
    "qs_pg:qs_pg_placetype":"locality",
    "qs_pg:qs_pg_placetype_gp":"Town",
    "qs_pg:woe_adm0":23424957,
    "woe:adm0_id":23424957,
    "woe:name_adm0":"Schweiz",
    "woe:name_adm1":"Kanton Z\u00fcrich",
    "woe:placetype":"Town",
    "wof:name":"H\u00fctten",
    "wof:placetype":"locality",
    "wof:population":451
},
  "geometry": {"coordinates":[8.66655,47.17573],"type":"Point"}
}