{
  "type": "Feature",
  "properties": {
    "gn:gn_country":"CH",
    "gn:gn_fcode":"PPL",
    "gn:gn_pop":1130,
    "gn:population":1130,
    "iso:country":"CH",
    "name:cat_x_preferred":[
        "Jenaz"
    ],
    "name:deu_x_preferred":[
        "Jenaz"
    ],
    "name:eng_x_preferred":[
        "Jenaz"
    ],
    "name:epo_x_preferred":[
        "Jenaz"
    ],
    "name:eus_x_preferred":[
        "Jenaz"
    ],
    "name:fra_x_preferred":[
        "Jenaz"
    ],
    "name:hun_x_preferred":[
        "Jenaz"
    ],
    "name:ind_x_preferred":[
        "Jenaz"
    ],
    "name:ita_x_preferred":[
        "Jenaz"
    ],
    "name:kaz_x_preferred":[
        "\u0415\u043d\u0430\u0446"
    ],
    "name:lmo_x_preferred":[
        "Jenaz"
    ],
    "name:msa_x_preferred":[
        "Jenaz"
    ],
    "name:nld_x_preferred":[
        "Jenaz"
    ],
    "name:nno_x_preferred":[
        "Jenaz"
    ],
    "name:oci_x_preferred":[
        "Jenaz"
    ],
    "name:pms_x_preferred":[
        "Jenaz"
    ],
    "name:por_x_preferred":[
        "Jenaz"
    ],
    "name:roh_x_preferred":[
        "Gianatsch"
    ],
    "name:rus_x_preferred":[
        "\u0415\u043d\u0430\u0446"
    ],
    "name:spa_x_preferred":[
        "Jenaz"
    ],
    "name:sqi_x_preferred":[
        "Jenaz"
    ],
    "name:swe_x_preferred":[
        "Jenaz"
    ],
    "name:uzb_x_preferred":[
        "Jenaz"
    ],
    "name:vol_x_preferred":[
        "Jenaz"
    ],
    "name:war_x_preferred":[
        "Jenaz"
    ],
    "name:zho_x_preferred":[
        "\u8036\u7d0d\u8328"
    ],
    "qs_pg:aaroncc":"CH",
    "qs_pg:gn_country":"CH",
    "qs_pg:gn_fcode":"PPL",
    "qs_pg:gn_pop":1130,
    "qs_pg:name":"Jenaz",
    "qs_pg:photos_9r":0,
    "qs_pg:photos_sr":0,
    "qs_pg:pop_sr":3,
    "qs_pg:qs_pg_placetype":"locality",
    "wof:name":"Jenaz",
    "wof:placetype":"locality",
    "wof:population":1130
},
  "geometry": {"coordinates":[9.71275,46.92892],"type":"Point"}
}