{
  "type": "Feature",
  "properties": {
    "gn:population":1618,
    "iso:country":"CH",
    "name:als_x_preferred":[
        "Trogen AR"
    ],
    "name:ara_x_preferred":[
        "\u062a\u0648\u0631\u063a\u064a\u0646"
    ],
    "name:cat_x_preferred":[
        "Trogen"
    ],
    "name:chv_x_preferred":[
        "\u0422\u0440\u043e\u0433\u0435\u043d"
    ],
    "name:deu_x_preferred":[
        "Trogen AR"
    ],
    "name:deu_x_variant":[
        "Trogen"
    ],
    "name:eng_x_preferred":[
        "Trogen"
    ],
    "name:epo_x_preferred":[
        "Trogen AR"
    ],
    "name:eus_x_preferred":[
        "Trogen"
    ],
    "name:fin_x_preferred":[
        "Trogen"
    ],
    "name:fra_x_preferred":[
        "Trogen"
    ],
    "name:gsw_x_preferred":[
        "Troge"
    ],
    "name:hbs_x_preferred":[
        "Trogen"
    ],
    "name:hrv_x_preferred":[
        "Trogen"
    ],
    "name:hun_x_preferred":[
        "Trogen"
    ],
    "name:ind_x_preferred":[
        "Trogen"
    ],
    "name:ita_x_preferred":[
        "Trogen"
    ],
    "name:jpn_x_preferred":[
        "\u30c8\u30ed\u30fc\u30b2\u30f3"
    ],
    "name:kaz_x_preferred":[
        "\u0422\u0440\u043e\u0433\u0435\u043d"
    ],
    "name:kor_x_preferred":[
        "\ud2b8\ub85c\uac90"
    ],
    "name:lmo_x_preferred":[
        "Trogen"
    ],
    "name:nld_x_preferred":[
        "Trogen"
    ],
    "name:nno_x_preferred":[
        "Trogen"
    ],
    "name:nob_x_preferred":[
        "Trogen"
    ],
    "name:oci_x_preferred":[
        "Trogen"
    ],
    "name:pms_x_preferred":[
        "Trogen"
    ],
    "name:pol_x_preferred":[
        "Trogen"
    ],
    "name:por_x_preferred":[
        "Trogen"
    ],
    "name:roh_x_preferred":[
        "Trogen"
    ],
    "name:ron_x_preferred":[
        "Trogen"
    ],
    "name:rus_x_preferred":[
        "\u0422\u0440\u043e\u0433\u0435\u043d"
    ],
    "name:spa_x_preferred":[
        "Trogen"
    ],
    "name:sqi_x_preferred":[
        "Trogen"
    ],
    "name:swe_x_preferred":[
        "Trogen"
    ],
    "name:ukr_x_preferred":[
        "\u0422\u0440\u043e\u0433\u0435\u043d"
    ],
    "name:uzb_x_preferred":[
        "Trogen"
    ],
    "name:vol_x_preferred":[
        "Trogen"
    ],
    "name:war_x_preferred":[
        "Trogen"
    ],
    "name:zho_x_preferred":[
        "\u7279\u7f85\u6839"
    ],
    "qs:a0":"Schweiz#Suisse#Svizzera#Svizra",
    "qs:a1":"*Appenzell Ausserrhoden",
    "qs:a1r":"0",
    "qs:adm0":"Schweiz#Suisse#Svizzera#Svizra",
    "qs:la_lc":"*",
    "qs:level":"locality",
    "qs:loc":"Trogen",
    "qs:loc_alt":"Trogen",
    "qs:pop":0,
    "qs:type":"buffered point",
    "wd:wordcount":821,
    "wof:lang":[
        "ger"
    ],
    "wof:name":"Trogen",
    "wof:placetype":"locality",
    "wof:population":1618
},
  "geometry": {"coordinates":[9.464306,47.409958],"type":"Point"}
}