{
  "type": "Feature",
  "properties": {
    "gn:admin1_code":"TG",
    "gn:admin2_code":"2013.0",
    "gn:admin3_code":"4683.0",
    "gn:asciiname":"Illighausen",
    "gn:country_code":"CH",
    "gn:dem":559,
    "gn:feature_class":"P",
    "gn:feature_code":"PPL",
    "gn:name":"Illighausen",
    "gn:population":0,
    "gn:timezone":"Europe/Zurich",
    "iso:country":"CH",
    "wof:name":"Illighausen",
    "wof:placetype":"locality"
},
  "geometry": {"coordinates":[9.20983,47.6031],"type":"Point"}
}