{
  "type": "Feature",
  "properties": {
    "gn:admin1_code":"BE",
    "gn:admin2_code":"244.0",
    "gn:admin3_code":"335.0",
    "gn:asciiname":"Hinterstampbach",
    "gn:country_code":"CH",
    "gn:dem":763,
    "gn:feature_class":"P",
    "gn:feature_code":"PPLL",
    "gn:name":"Hinterstampbach",
    "gn:population":0,
    "gn:timezone":"Europe/Zurich",
    "iso:country":"CH",
    "name:deu_x_preferred":[
        "Hinterstampbach"
    ],
    "wof:name":"Hinterstampbach",
    "wof:placetype":"neighbourhood"
},
  "geometry": {"coordinates":[7.73515,47.11561],"type":"Point"}
}