{
  "type": "Feature",
  "properties": {
    "gn:admin1_code":"SZ",
    "gn:admin2_code":"506.0",
    "gn:admin3_code":"1372.0",
    "gn:asciiname":"Oberschonenbuch",
    "gn:country_code":"CH",
    "gn:dem":536,
    "gn:feature_class":"P",
    "gn:feature_code":"PPL",
    "gn:name":"Obersch\u00f6nenbuch",
    "gn:population":0,
    "gn:timezone":"Europe/Zurich",
    "iso:country":"CH",
    "wof:name":"Oberschonenbuch",
    "wof:placetype":"neighbourhood"
},
  "geometry": {"coordinates":[8.64651,46.99648],"type":"Point"}
}