{
  "type": "Feature",
  "properties": {
    "gn:country":"CH",
    "gn:fcode":"PPLX",
    "gn:population":538,
    "iso:country":"CH",
    "name:eng_x_preferred":[
        "Gr\u00fczenstrasse"
    ],
    "name:eng_x_variant":[
        "D\u00fcbendorf / Gr\u00fczenstrasse"
    ],
    "qs_pg:aaroncc":"CH",
    "qs_pg:gn_country":"CH",
    "qs_pg:gn_fcode":"PPLX",
    "qs_pg:gn_pop":538,
    "qs_pg:name":"D\u00fcbendorf / Gr\u00fczenstrasse",
    "qs_pg:photos_9r":0,
    "qs_pg:photos_sr":0,
    "qs_pg:pop_sr":2,
    "qs_pg:qs_pg_placetype":"neighbourhood",
    "wof:name":"Gr\u00fczenstrasse",
    "wof:placetype":"neighbourhood",
    "wof:population":538
},
  "geometry": {"coordinates":[8.61978,47.39263],"type":"Point"}
}