{
  "type": "Feature",
  "properties": {
    "gn:admin1_code":"SG",
    "gn:admin2_code":"1723.0",
    "gn:admin3_code":"3236.0",
    "gn:asciiname":"Weinberg",
    "gn:country_code":"CH",
    "gn:dem":558,
    "gn:feature_class":"P",
    "gn:feature_code":"PPLL",
    "gn:name":"Weinberg",
    "gn:population":0,
    "gn:timezone":"Europe/Zurich",
    "iso:country":"CH",
    "name:deu_x_preferred":[
        "Weinberg"
    ],
    "wof:name":"Weinberg",
    "wof:placetype":"neighbourhood"
},
  "geometry": {"coordinates":[9.60351,47.45616],"type":"Point"}
}