{
  "type": "Feature",
  "properties": {
    "gn:admin1_code":"SG",
    "gn:admin2_code":"1723.0",
    "gn:admin3_code":"3236.0",
    "gn:asciiname":"Weinberg",
    "gn:country_code":"CH",
    "gn:dem":558,
    "gn:feature_class":"P",
    "gn:feature_code":"PPLL",
    "gn:name":"Weinberg",
    "gn:population":0,
    "gn:timezone":"Europe/Zurich",
    "iso:country":"CH",
    "name:ceb_x_preferred":[
        "Weinberg"
    ],
    "name:ces_x_preferred":[
        "Weinberg"
    ],
    "name:deu_x_preferred":[
        "Weinberg"
    ],
    "name:epo_x_preferred":[
        "Weinberg"
    ],
    "name:fra_x_preferred":[
        "Weinberg"
    ],
    "name:heb_x_preferred":[
        "\u05d5\u05d9\u05d9\u05e0\u05d1\u05e8\u05d2"
    ],
    "name:ita_x_preferred":[
        "Weinberg"
    ],
    "name:jpn_x_preferred":[
        "\u30ef\u30a4\u30f3\u30d0\u30fc\u30b0"
    ],
    "name:nld_x_preferred":[
        "Weinberg"
    ],
    "name:pol_x_preferred":[
        "Weinberg"
    ],
    "name:ron_x_preferred":[
        "Weinberg"
    ],
    "name:rus_x_preferred":[
        "\u0412\u0430\u0439\u043d\u0431\u0435\u0440\u0433"
    ],
    "name:swe_x_preferred":[
        "Weinberg"
    ],
    "name:ukr_x_preferred":[
        "\u0412\u0430\u0439\u043d\u0431\u0435\u0440\u0433"
    ],
    "wof:name":"Weinberg",
    "wof:placetype":"neighbourhood"
},
  "geometry": {"coordinates":[9.60351,47.45616],"type":"Point"}
}