{
  "type": "Feature",
  "properties": {
    "gn:admin1_code":"TG",
    "gn:admin2_code":"2012.0",
    "gn:admin3_code":"4826.0",
    "gn:asciiname":"Guldifuss",
    "gn:country_code":"CH",
    "gn:dem":402,
    "gn:feature_class":"P",
    "gn:feature_code":"PPLL",
    "gn:name":"Guldifuss",
    "gn:population":0,
    "gn:timezone":"Europe/Zurich",
    "iso:country":"CH",
    "name:deu_x_preferred":[
        "Guldifuss"
    ],
    "wof:name":"Guldifuss",
    "wof:placetype":"neighbourhood"
},
  "geometry": {"coordinates":[8.92397,47.64639],"type":"Point"}
}