{
  "type": "Feature",
  "properties": {
    "gn:admin1_code":"TG",
    "gn:admin2_code":"2015.0",
    "gn:admin3_code":"4911.0",
    "gn:asciiname":"Istighofen",
    "gn:country_code":"CH",
    "gn:dem":439,
    "gn:elevation":"441.0",
    "gn:feature_class":"P",
    "gn:feature_code":"PPL",
    "gn:name":"Istighofen",
    "gn:population":0,
    "gn:timezone":"Europe/Zurich",
    "iso:country":"CH",
    "wof:name":"Istighofen",
    "wof:placetype":"locality"
},
  "geometry": {"coordinates":[9.14994,47.54232],"type":"Point"}
}