{
  "type": "Feature",
  "properties": {
    "gn:admin1_code":"UR",
    "gn:admin2_code":"400.0",
    "gn:admin3_code":"1212.0",
    "gn:asciiname":"Schweig",
    "gn:country_code":"CH",
    "gn:dem":1742,
    "gn:feature_class":"P",
    "gn:feature_code":"PPL",
    "gn:name":"Schweig",
    "gn:population":0,
    "gn:timezone":"Europe/Zurich",
    "iso:country":"CH",
    "name:deu_x_preferred":[
        "Schweig"
    ],
    "wof:name":"Schweig",
    "wof:placetype":"locality"
},
  "geometry": {"coordinates":[8.49354,46.57923],"type":"Point"}
}