{
  "type": "Feature",
  "properties": {
    "gn:admin1_code":"FR",
    "gn:admin2_code":"1001.0",
    "gn:admin3_code":"2029.0",
    "gn:asciiname":"Grandsivaz",
    "gn:country_code":"CH",
    "gn:dem":626,
    "gn:feature_class":"P",
    "gn:feature_code":"PPL",
    "gn:name":"Grandsivaz",
    "gn:population":0,
    "gn:timezone":"Europe/Zurich",
    "iso:country":"CH",
    "wof:name":"Grandsivaz",
    "wof:placetype":"locality"
},
  "geometry": {"coordinates":[6.98085,46.78502],"type":"Point"}
}