{
  "type": "Feature",
  "properties": {
    "gn:admin1_code":"SG",
    "gn:admin2_code":"1726.0",
    "gn:admin3_code":"3341.0",
    "gn:asciiname":"Rietmatt",
    "gn:country_code":"CH",
    "gn:dem":679,
    "gn:feature_class":"P",
    "gn:feature_code":"PPLL",
    "gn:name":"Rietmatt",
    "gn:population":0,
    "gn:timezone":"Europe/Zurich",
    "iso:country":"CH",
    "name:deu_x_preferred":[
        "Rietmatt"
    ],
    "wof:name":"Rietmatt",
    "wof:placetype":"locality"
},
  "geometry": {"coordinates":[8.99792,47.25346],"type":"Point"}
}