{
  "type": "Feature",
  "properties": {
    "gn:gn_country":"CH",
    "gn:gn_fcode":"PPL",
    "gn:gn_pop":406,
    "gn:population":406,
    "iso:country":"CH",
    "name:deu_x_preferred":[
        "Nax"
    ],
    "name:eng_x_preferred":[
        "Nax"
    ],
    "name:fra_x_preferred":[
        "Nax"
    ],
    "name:frp_x_preferred":[
        "N\u00e2x"
    ],
    "name:ita_x_preferred":[
        "Nax"
    ],
    "name:lmo_x_preferred":[
        "Nax"
    ],
    "name:msa_x_preferred":[
        "Nax"
    ],
    "name:nld_x_preferred":[
        "Nax"
    ],
    "name:pms_x_preferred":[
        "Nax"
    ],
    "name:pnb_x_preferred":[
        "\u0646\u0627\u06a9\u0633"
    ],
    "name:por_x_preferred":[
        "Nax"
    ],
    "name:roh_x_preferred":[
        "Nax"
    ],
    "name:spa_x_preferred":[
        "Nax"
    ],
    "name:swe_x_preferred":[
        "Nax"
    ],
    "name:vol_x_preferred":[
        "Nax"
    ],
    "name:war_x_preferred":[
        "Nax"
    ],
    "name:zho_x_preferred":[
        "\u7d0d\u514b\u65af"
    ],
    "qs_pg:aaroncc":"CH",
    "qs_pg:gn_country":"CH",
    "qs_pg:gn_fcode":"PPL",
    "qs_pg:gn_pop":406,
    "qs_pg:name":"Nax",
    "qs_pg:name_adm0":"Schweiz",
    "qs_pg:name_adm1":"Canton de Valais",
    "qs_pg:photos":64,
    "qs_pg:photos_1k":13,
    "qs_pg:photos_9k":1,
    "qs_pg:photos_9r":2,
    "qs_pg:photos_all":64,
    "qs_pg:photos_sr":2,
    "qs_pg:pop_sr":2,
    "qs_pg:qs_pg_placetype":"locality",
    "qs_pg:qs_pg_placetype_gp":"Town",
    "qs_pg:woe_adm0":23424957,
    "woe:adm0_id":23424957,
    "woe:name_adm0":"Schweiz",
    "woe:name_adm1":"Canton de Valais",
    "woe:placetype":"Town",
    "wof:name":"Nax",
    "wof:placetype":"locality",
    "wof:population":406
},
  "geometry": {"coordinates":[7.42798,46.22847],"type":"Point"}
}