{
  "type": "Feature",
  "properties": {
    "gn:admin1_code":"VS",
    "gn:admin2_code":"2302.0",
    "gn:admin3_code":"6025.0",
    "gn:asciiname":"Magnot",
    "gn:country_code":"CH",
    "gn:dem":487,
    "gn:feature_class":"P",
    "gn:feature_code":"PPL",
    "gn:name":"Magnot",
    "gn:population":0,
    "gn:timezone":"Europe/Zurich",
    "iso:country":"CH",
    "wof:name":"Magnot",
    "wof:placetype":"neighbourhood"
},
  "geometry": {"coordinates":[7.26557,46.21952],"type":"Point"}
}