{
  "type": "Feature",
  "properties": {
    "gn:gn_country":"CH",
    "gn:gn_fcode":"PPL",
    "gn:gn_pop":3174,
    "gn:population":3174,
    "iso:country":"CH",
    "name:deu_x_preferred":[
        "Schindellegi"
    ],
    "name:eng_x_preferred":[
        "Schindellegi"
    ],
    "name:epo_x_preferred":[
        "Schindellegi"
    ],
    "name:fra_x_preferred":[
        "Schindellegi"
    ],
    "name:gsw_x_preferred":[
        "Schindellegi"
    ],
    "name:hun_x_preferred":[
        "Schindellegi"
    ],
    "name:nld_x_preferred":[
        "Schindellegi"
    ],
    "name:pol_x_preferred":[
        "Schindellegi"
    ],
    "qs_pg:aaroncc":"CH",
    "qs_pg:gn_country":"CH",
    "qs_pg:gn_fcode":"PPL",
    "qs_pg:gn_pop":3174,
    "qs_pg:name":"Schindellegi",
    "qs_pg:name_adm0":"Schweiz",
    "qs_pg:name_adm1":"Kanton Schwyz",
    "qs_pg:photos":122,
    "qs_pg:photos_1k":25,
    "qs_pg:photos_9k":1,
    "qs_pg:photos_9r":3,
    "qs_pg:photos_all":122,
    "qs_pg:photos_sr":3,
    "qs_pg:pop_sr":4,
    "qs_pg:qs_pg_placetype":"locality",
    "qs_pg:qs_pg_placetype_gp":"Town",
    "qs_pg:woe_adm0":23424957,
    "woe:adm0_id":23424957,
    "woe:name_adm0":"Schweiz",
    "woe:name_adm1":"Kanton Schwyz",
    "woe:placetype":"Town",
    "wof:name":"Schindellegi",
    "wof:placetype":"locality",
    "wof:population":3174
},
  "geometry": {"coordinates":[8.71345,47.1746],"type":"Point"}
}