{
  "type": "Feature",
  "properties": {
    "gn:country":"CH",
    "gn:fcode":"PPLL",
    "gn:population":7,
    "iso:country":"CH",
    "name:ceb_x_preferred":[
        "Weid"
    ],
    "name:deu_x_preferred":[
        "Weid"
    ],
    "name:epo_x_preferred":[
        "Weid"
    ],
    "name:nds_x_preferred":[
        "Weid"
    ],
    "qs_pg:aaroncc":"CH",
    "qs_pg:gn_country":"CH",
    "qs_pg:gn_fcode":"PPLL",
    "qs_pg:gn_pop":7,
    "qs_pg:name":"Weid",
    "qs_pg:photos_9r":0,
    "qs_pg:photos_sr":0,
    "qs_pg:pop_sr":1,
    "qs_pg:qs_pg_placetype":"locality",
    "wof:name":"Weid",
    "wof:placetype":"neighbourhood",
    "wof:population":7
},
  "geometry": {"coordinates":[8.42349,47.23998],"type":"Point"}
}