{
  "type": "Feature",
  "properties": {
    "gn:admin1_code":"BE",
    "gn:admin2_code":"241.0",
    "gn:admin3_code":"433.0",
    "gn:asciiname":"Haut de la Montagne",
    "gn:country_code":"CH",
    "gn:dem":1180,
    "gn:feature_class":"P",
    "gn:feature_code":"PPLL",
    "gn:name":"Haut de la Montagne",
    "gn:population":0,
    "gn:timezone":"Europe/Zurich",
    "iso:country":"CH",
    "name:fra_x_preferred":[
        "Haut de la Montagne"
    ],
    "wof:name":"Haut de la Montagne",
    "wof:placetype":"neighbourhood"
},
  "geometry": {"coordinates":[7.11149,47.16241],"type":"Point"}
}