{
  "type": "Feature",
  "properties": {
    "gn:admin1_code":"BE",
    "gn:admin2_code":"246.0",
    "gn:admin3_code":"360.0",
    "gn:asciiname":"Birchi",
    "gn:country_code":"CH",
    "gn:dem":619,
    "gn:feature_class":"P",
    "gn:feature_code":"PPL",
    "gn:name":"Birchi",
    "gn:population":0,
    "gn:timezone":"Europe/Zurich",
    "iso:country":"CH",
    "wof:name":"Birchi",
    "wof:placetype":"neighbourhood"
},
  "geometry": {"coordinates":[7.34925,46.99518],"type":"Point"}
}