{
  "type": "Feature",
  "properties": {
    "gn:admin1_code":"BE",
    "gn:admin2_code":"250.0",
    "gn:admin3_code":"571.0",
    "gn:asciiname":"Beatenberg-Waldegg",
    "gn:country_code":"CH",
    "gn:dem":1236,
    "gn:elevation":"1202.0",
    "gn:feature_class":"P",
    "gn:feature_code":"PPL",
    "gn:name":"Beatenberg-Waldegg",
    "gn:population":0,
    "gn:timezone":"Europe/Zurich",
    "iso:country":"CH",
    "wof:lang_x_official":[
        "deu",
        "fra",
        "gsw",
        "ita"
    ],
    "wof:lang_x_spoken":[
        "deu",
        "fra",
        "gsw",
        "ita",
        "roh"
    ],
    "wof:name":"Beatenberg-Waldegg",
    "wof:placetype":"neighbourhood"
},
  "geometry": {"coordinates":[7.81372,46.70288],"type":"Point"}
}