{
  "type": "Feature",
  "properties": {
    "gn:admin1_code":"TI",
    "gn:admin2_code":"2105.0",
    "gn:admin3_code":"5178.0",
    "gn:asciiname":"Madonnone",
    "gn:country_code":"CH",
    "gn:dem":294,
    "gn:feature_class":"P",
    "gn:feature_code":"PPL",
    "gn:name":"Madonnone",
    "gn:population":0,
    "gn:timezone":"Europe/Rome",
    "iso:country":"CH",
    "name:ita_x_preferred":[
        "Madonnone"
    ],
    "wof:name":"Madonnone",
    "wof:placetype":"neighbourhood"
},
  "geometry": {"coordinates":[8.8474,45.97717],"type":"Point"}
}