{
  "type": "Feature",
  "properties": {
    "gn:admin1_code":"TI",
    "gn:admin2_code":"2101.0",
    "gn:admin3_code":"5017.0",
    "gn:asciiname":"Mondo",
    "gn:country_code":"CH",
    "gn:dem":307,
    "gn:feature_class":"P",
    "gn:feature_code":"PPL",
    "gn:name":"Mond\u00f2",
    "gn:population":0,
    "gn:timezone":"Europe/Zurich",
    "iso:country":"CH",
    "name:ceb_x_preferred":[
        "Mondo"
    ],
    "name:deu_x_preferred":[
        "Mondo"
    ],
    "name:fin_x_preferred":[
        "Mondo"
    ],
    "name:fra_x_preferred":[
        "Mondo"
    ],
    "name:ita_x_preferred":[
        "Mond\u00f2"
    ],
    "name:ita_x_variant":[
        "Mondo"
    ],
    "name:rus_x_preferred":[
        "\u041c\u043e\u043d\u0434\u043e"
    ],
    "name:spa_x_preferred":[
        "Mondo"
    ],
    "name:swa_x_preferred":[
        "Mondo"
    ],
    "name:swe_x_preferred":[
        "Mondo"
    ],
    "wof:name":"Mondo",
    "wof:placetype":"neighbourhood"
},
  "geometry": {"coordinates":[8.9833,46.15204],"type":"Point"}
}