{
  "type": "Feature",
  "properties": {
    "gn:gn_country":"CH",
    "gn:gn_fcode":"PPLX",
    "gn:gn_pop":317,
    "gn:population":317,
    "iso:country":"CH",
    "name:eng_x_preferred":[
        "Lindenmoos"
    ],
    "name:eng_x_variant":[
        "Affoltern / Lindenmoos"
    ],
    "name:unk_x_variant":[
        "Lindenmoos"
    ],
    "qs_pg:aaroncc":"CH",
    "qs_pg:gn_country":"CH",
    "qs_pg:gn_fcode":"PPLX",
    "qs_pg:gn_pop":317,
    "qs_pg:name":"Affoltern / Lindenmoos",
    "qs_pg:photos_9r":0,
    "qs_pg:photos_sr":0,
    "qs_pg:pop_sr":2,
    "qs_pg:qs_pg_placetype":"neighbourhood",
    "wof:name":"Lindenmoos",
    "wof:placetype":"neighbourhood",
    "wof:population":317
},
  "geometry": {"coordinates":[8.44301,47.27242],"type":"Point"}
}