{
  "type": "Feature",
  "properties": {
    "gn:admin1_code":"SO",
    "gn:admin2_code":"1103.0",
    "gn:admin3_code":"2464.0",
    "gn:asciiname":"Nennigkofen",
    "gn:country_code":"CH",
    "gn:dem":459,
    "gn:feature_class":"P",
    "gn:feature_code":"PPL",
    "gn:name":"Nennigkofen",
    "gn:population":0,
    "gn:timezone":"Europe/Zurich",
    "iso:country":"CH",
    "name:deu_x_preferred":[
        "L\u00fcsslingen-Nennigkofen"
    ],
    "name:kaz_x_preferred":[
        "\u041d\u0435\u043d\u043d\u0438\u0433\u043e\u0444\u0435\u043d"
    ],
    "name:rus_x_preferred":[
        "\u041d\u0435\u043d\u043d\u0438\u0433\u043e\u0444\u0435\u043d"
    ],
    "name:zho_x_preferred":[
        "\u5ae9\u5c3c\u683c\u79d1\u82ac"
    ],
    "wof:name":"Nennigkofen",
    "wof:placetype":"locality"
},
  "geometry": {"coordinates":[7.49516,47.18633],"type":"Point"}
}