{
  "type": "Feature",
  "properties": {
    "gn:gn_country":"CH",
    "gn:gn_fcode":"ADM3",
    "gn:gn_pop":2294,
    "gn:population":2305,
    "iso:country":"CH",
    "name:ara_x_preferred":[
        "\u0641\u062e\u0627\u064a\u0646\u0634\u062a\u0627\u064a\u0646-\u062a\u0648\u064a\u0641\u0646"
    ],
    "name:cat_x_preferred":[
        "Freienstein-Teufen"
    ],
    "name:ceb_x_preferred":[
        "Freienstein-Teufen"
    ],
    "name:chv_x_preferred":[
        "\u0424\u0440\u0430\u0439\u0435\u043d\u0448\u0442\u0430\u0439\u043d-\u0422\u043e\u0439\u0444\u0435\u043d"
    ],
    "name:deu_x_preferred":[
        "Freienstein-Teufen"
    ],
    "name:eng_x_preferred":[
        "Freienstein-Teufen"
    ],
    "name:epo_x_preferred":[
        "Freienstein-Teufen"
    ],
    "name:eus_x_preferred":[
        "Freienstein-Teufen"
    ],
    "name:fra_x_preferred":[
        "Freienstein-Teufen"
    ],
    "name:gsw_x_preferred":[
        "Freyescht\u00e4i-T\u00fc\u00fcffe"
    ],
    "name:hun_x_preferred":[
        "Freienstein-Teufen"
    ],
    "name:ita_x_preferred":[
        "Freienstein-Teufen"
    ],
    "name:kaz_x_preferred":[
        "\u0424\u0440\u0430\u0439\u0435\u043d\u0448\u0442\u0430\u0439\u043d-\u0422\u043e\u0439\u0444\u0435\u043d"
    ],
    "name:lmo_x_preferred":[
        "Freienstein-Teufen"
    ],
    "name:msa_x_preferred":[
        "Freienstein-Teufen"
    ],
    "name:nld_x_preferred":[
        "Freienstein-Teufen"
    ],
    "name:nno_x_preferred":[
        "Freienstein-Teufen"
    ],
    "name:oci_x_preferred":[
        "Freienstein-Teufen"
    ],
    "name:pol_x_preferred":[
        "Freienstein-Teufen"
    ],
    "name:rus_x_preferred":[
        "\u0424\u0440\u0430\u0439\u0435\u043d\u0448\u0442\u0430\u0439\u043d-\u0422\u043e\u0439\u0444\u0435\u043d"
    ],
    "name:spa_x_preferred":[
        "Freienstein-Teufen"
    ],
    "name:swe_x_preferred":[
        "Freienstein-Teufen"
    ],
    "name:uzb_x_preferred":[
        "Freienstein-Teufen"
    ],
    "name:vie_x_preferred":[
        "Freienstein-Teufen"
    ],
    "name:vol_x_preferred":[
        "Freienstein-Teufen"
    ],
    "name:war_x_preferred":[
        "Freienstein-Teufen"
    ],
    "name:zho_x_preferred":[
        "\u5f17\u8cf4\u6069\u65af\u6cf0\u56e0-\u6258\u4f0a\u82ac"
    ],
    "qs_pg:aaroncc":"CH",
    "qs_pg:gn_country":"CH",
    "qs_pg:gn_fcode":"ADM3",
    "qs_pg:gn_pop":2294,
    "qs_pg:name":"Freienstein-Teufen",
    "qs_pg:name_adm0":"Schweiz",
    "qs_pg:name_adm1":"Kanton Z\u00fcrich",
    "qs_pg:photos_9r":0,
    "qs_pg:photos_sr":0,
    "qs_pg:pop_sr":4,
    "qs_pg:qs_pg_placetype":"locality",
    "qs_pg:qs_pg_placetype_gp":"Town",
    "qs_pg:woe_adm0":23424957,
    "woe:adm0_id":23424957,
    "woe:name_adm0":"Schweiz",
    "woe:name_adm1":"Kanton Z\u00fcrich",
    "woe:placetype":"Town",
    "wof:name":"Freienstein-Teufen",
    "wof:placetype":"neighbourhood",
    "wof:population":2305
},
  "geometry": {"coordinates":[8.55,47.55],"type":"Point"}
}