{
  "type": "Feature",
  "properties": {
    "gn:gn_country":"CH",
    "gn:gn_fcode":"PPL",
    "gn:gn_pop":2715,
    "gn:population":2715,
    "iso:country":"CH",
    "name:baq_x_preferred":[
        "Quarten"
    ],
    "name:cat_x_preferred":[
        "Quarten"
    ],
    "name:chi_x_preferred":[
        "\u5938\u723e\u6ed5"
    ],
    "name:dut_x_preferred":[
        "Quarten"
    ],
    "name:eng_x_preferred":[
        "Quarten"
    ],
    "name:epo_x_preferred":[
        "Quarten"
    ],
    "name:fre_x_preferred":[
        "Quarten"
    ],
    "name:ger_x_preferred":[
        "Quarten"
    ],
    "name:hun_x_preferred":[
        "Quarten"
    ],
    "name:ita_x_preferred":[
        "Quarten"
    ],
    "name:kaz_x_preferred":[
        "\u041a\u0432\u0430\u0440\u0442\u0435\u043d"
    ],
    "name:lat_x_preferred":[
        "Quartus"
    ],
    "name:lmo_x_preferred":[
        "Quarten"
    ],
    "name:ltz_x_preferred":[
        "Quarten"
    ],
    "name:may_x_preferred":[
        "Quarten"
    ],
    "name:nno_x_preferred":[
        "Quarten"
    ],
    "name:oci_x_preferred":[
        "Quarten"
    ],
    "name:pms_x_preferred":[
        "Quarten"
    ],
    "name:por_x_preferred":[
        "Quarten"
    ],
    "name:rus_x_preferred":[
        "\u041a\u0432\u0430\u0440\u0442\u0435\u043d"
    ],
    "name:spa_x_preferred":[
        "Quarten"
    ],
    "name:uzb_x_preferred":[
        "Quarten"
    ],
    "name:vol_x_preferred":[
        "Quarten"
    ],
    "name:war_x_preferred":[
        "Quarten"
    ],
    "name:zho_x_preferred":[
        "\u5938\u723e\u6ed5"
    ],
    "qs_pg:aaroncc":"CH",
    "qs_pg:gn_country":"CH",
    "qs_pg:gn_fcode":"PPL",
    "qs_pg:gn_pop":2715,
    "qs_pg:name":"Quarten",
    "qs_pg:photos_9r":0,
    "qs_pg:photos_sr":0,
    "qs_pg:pop_sr":4,
    "qs_pg:qs_pg_placetype":"locality",
    "wof:name":"Quarten",
    "wof:placetype":"locality",
    "wof:population":2715
},
  "geometry": {"coordinates":[9.23401,47.10016],"type":"Point"}
}