{
  "type": "Feature",
  "properties": {
    "gn:admin1_code":"LU",
    "gn:admin2_code":"312.0",
    "gn:admin3_code":"1062.0",
    "gn:asciiname":"Glattacher",
    "gn:country_code":"CH",
    "gn:dem":513,
    "gn:feature_class":"P",
    "gn:feature_code":"PPLL",
    "gn:name":"Glattacher",
    "gn:population":0,
    "gn:timezone":"Europe/Zurich",
    "iso:country":"CH",
    "name:deu_x_preferred":[
        "Glattacher"
    ],
    "wof:name":"Glattacher",
    "wof:placetype":"neighbourhood"
},
  "geometry": {"coordinates":[8.15184,47.0383],"type":"Point"}
}