{
  "type": "Feature",
  "properties": {
    "gn:admin1_code":"SO",
    "gn:admin2_code":"1108.0",
    "gn:admin3_code":"2572.0",
    "gn:asciiname":"Eich",
    "gn:country_code":"CH",
    "gn:dem":437,
    "gn:elevation":"433.0",
    "gn:feature_class":"P",
    "gn:feature_code":"PPL",
    "gn:name":"Eich",
    "gn:population":0,
    "gn:timezone":"Europe/Zurich",
    "iso:country":"CH",
    "name:ceb_x_preferred":[
        "Eich"
    ],
    "name:deu_x_preferred":[
        "Eich"
    ],
    "name:epo_x_preferred":[
        "Eich"
    ],
    "name:fra_x_preferred":[
        "Eich"
    ],
    "name:ita_x_preferred":[
        "Eich"
    ],
    "name:nld_x_preferred":[
        "Eich"
    ],
    "name:pol_x_preferred":[
        "Eich"
    ],
    "name:swe_x_preferred":[
        "Eich"
    ],
    "name:vol_x_preferred":[
        "Eich"
    ],
    "wof:name":"Eich",
    "wof:placetype":"neighbourhood"
},
  "geometry": {"coordinates":[7.98798,47.34931],"type":"Point"}
}