{
  "type": "Feature",
  "properties": {
    "gn:admin1_code":"TI",
    "gn:admin2_code":"2106.0",
    "gn:admin3_code":"5260.0",
    "gn:asciiname":"Loi",
    "gn:country_code":"CH",
    "gn:dem":348,
    "gn:feature_class":"P",
    "gn:feature_code":"PPL",
    "gn:name":"Loi",
    "gn:population":0,
    "gn:timezone":"Europe/Zurich",
    "iso:country":"CH",
    "name:ara_x_preferred":[
        "\u0644\u0648\u064a"
    ],
    "name:ita_x_preferred":[
        "Loi"
    ],
    "wof:lang_x_official":[
        "deu",
        "fra",
        "gsw",
        "ita"
    ],
    "wof:lang_x_spoken":[
        "deu",
        "fra",
        "gsw",
        "ita",
        "roh"
    ],
    "wof:name":"Loi",
    "wof:placetype":"neighbourhood"
},
  "geometry": {"coordinates":[8.97054,45.851],"type":"Point"}
}