{
  "type": "Feature",
  "properties": {
    "gn:admin1_code":"SZ",
    "gn:admin2_code":"506.0",
    "gn:admin3_code":"1372.0",
    "gn:asciiname":"Hunghafen",
    "gn:country_code":"CH",
    "gn:dem":645,
    "gn:feature_class":"P",
    "gn:feature_code":"PPLL",
    "gn:name":"Hunghafen",
    "gn:population":0,
    "gn:timezone":"Europe/Zurich",
    "iso:country":"CH",
    "name:deu_x_preferred":[
        "Hunghafen"
    ],
    "wof:name":"Hunghafen",
    "wof:placetype":"neighbourhood"
},
  "geometry": {"coordinates":[8.64537,47.03719],"type":"Point"}
}