{
  "type": "Feature",
  "properties": {
    "gn:gn_country":"CH",
    "gn:gn_fcode":"PPL",
    "gn:gn_pop":1835,
    "gn:population":1835,
    "iso:country":"CH",
    "name:ast_x_preferred":[
        "Vuadens"
    ],
    "name:cat_x_preferred":[
        "Vuadens"
    ],
    "name:deu_x_preferred":[
        "Vuadens"
    ],
    "name:eng_x_preferred":[
        "Vuadens"
    ],
    "name:epo_x_preferred":[
        "Vuadens"
    ],
    "name:eus_x_preferred":[
        "Vuadens"
    ],
    "name:fra_x_preferred":[
        "Vuadens"
    ],
    "name:hun_x_preferred":[
        "Vuadens"
    ],
    "name:ita_x_preferred":[
        "Vuadens"
    ],
    "name:lmo_x_preferred":[
        "Vuadens"
    ],
    "name:msa_x_preferred":[
        "Vuadens"
    ],
    "name:nld_x_preferred":[
        "Vuadens"
    ],
    "name:nno_x_preferred":[
        "Vuadens"
    ],
    "name:oci_x_preferred":[
        "Vuadens"
    ],
    "name:pms_x_preferred":[
        "Vuadens"
    ],
    "name:por_x_preferred":[
        "Vuadens"
    ],
    "name:roh_x_preferred":[
        "Vuadens"
    ],
    "name:spa_x_preferred":[
        "Vuadens"
    ],
    "name:sqi_x_preferred":[
        "Vuadens"
    ],
    "name:swe_x_preferred":[
        "Vuadens"
    ],
    "name:unk_x_variant":[
        "W\u00fcadingen"
    ],
    "name:vol_x_preferred":[
        "Vuadens"
    ],
    "name:war_x_preferred":[
        "Vuadens"
    ],
    "name:zho_x_preferred":[
        "\u7dad\u963f\u7576"
    ],
    "qs_pg:aaroncc":"CH",
    "qs_pg:gn_country":"CH",
    "qs_pg:gn_fcode":"PPL",
    "qs_pg:gn_pop":1835,
    "qs_pg:name":"Vuadens",
    "qs_pg:name_adm0":"Schweiz",
    "qs_pg:name_adm1":"Canton de Fribourg",
    "qs_pg:photos_9k":1,
    "qs_pg:photos_9r":1,
    "qs_pg:photos_all":4,
    "qs_pg:photos_sr":0,
    "qs_pg:pop_sr":3,
    "qs_pg:qs_pg_placetype":"locality",
    "qs_pg:qs_pg_placetype_gp":"Town",
    "qs_pg:woe_adm0":23424957,
    "woe:adm0_id":23424957,
    "woe:name_adm0":"Schweiz",
    "woe:name_adm1":"Canton de Fribourg",
    "woe:placetype":"Town",
    "wof:name":"Vuadens",
    "wof:placetype":"locality",
    "wof:population":1835
},
  "geometry": {"coordinates":[7.02052,46.61731],"type":"Point"}
}