{
  "type": "Feature",
  "properties": {
    "gn:admin1_code":"ZG",
    "gn:admin2_code":"900.0",
    "gn:admin3_code":"1710.0",
    "gn:asciiname":"Schwaendi",
    "gn:country_code":"CH",
    "gn:dem":924,
    "gn:feature_class":"P",
    "gn:feature_code":"PPLL",
    "gn:name":"Schw\u00e4ndi",
    "gn:population":0,
    "gn:timezone":"Europe/Zurich",
    "iso:country":"CH",
    "name:deu_x_preferred":[
        "Schw\u00e4ndi"
    ],
    "wof:name":"Schwaendi",
    "wof:placetype":"neighbourhood"
},
  "geometry": {"coordinates":[8.52342,47.11666],"type":"Point"}
}