{
  "type": "Feature",
  "properties": {
    "gn:admin1_code":"TG",
    "gn:admin2_code":"2012.0",
    "gn:admin3_code":"4841.0",
    "gn:asciiname":"Steinbach",
    "gn:country_code":"CH",
    "gn:dem":421,
    "gn:feature_class":"P",
    "gn:feature_code":"PPLL",
    "gn:name":"Steinbach",
    "gn:population":0,
    "gn:timezone":"Europe/Zurich",
    "iso:country":"CH",
    "name:deu_x_preferred":[
        "Steinbach"
    ],
    "wof:name":"Steinbach",
    "wof:placetype":"neighbourhood"
},
  "geometry": {"coordinates":[8.94187,47.59723],"type":"Point"}
}