{
  "type": "Feature",
  "properties": {
    "gn:admin1_code":"TG",
    "gn:admin2_code":"2015.0",
    "gn:admin3_code":"4951.0",
    "gn:asciiname":"Moesli",
    "gn:country_code":"CH",
    "gn:dem":483,
    "gn:feature_class":"P",
    "gn:feature_code":"PPLL",
    "gn:name":"M\u00f6sli",
    "gn:population":0,
    "gn:timezone":"Europe/Zurich",
    "iso:country":"CH",
    "name:deu_x_preferred":[
        "M\u00f6sli"
    ],
    "wof:name":"Moesli",
    "wof:placetype":"neighbourhood"
},
  "geometry": {"coordinates":[9.04868,47.61776],"type":"Point"}
}