{
  "type": "Feature",
  "properties": {
    "gn:admin1_code":"SZ",
    "gn:admin2_code":"502.0",
    "gn:admin3_code":"1311.0",
    "gn:asciiname":"Ober Rotschuo",
    "gn:country_code":"CH",
    "gn:dem":462,
    "gn:feature_class":"P",
    "gn:feature_code":"PPL",
    "gn:name":"Ober Rotschuo",
    "gn:population":0,
    "gn:timezone":"Europe/Zurich",
    "iso:country":"CH",
    "name:und_x_variant":[
        "Rotschuh"
    ],
    "wof:name":"Ober Rotschuo",
    "wof:placetype":"neighbourhood"
},
  "geometry": {"coordinates":[8.49086,46.99277],"type":"Point"}
}