{
  "type": "Feature",
  "properties": {
    "gn:admin1_code":"FR",
    "gn:admin2_code":"1003.0",
    "gn:admin3_code":"2143.0",
    "gn:asciiname":"Les Cheseaux",
    "gn:country_code":"CH",
    "gn:dem":709,
    "gn:feature_class":"P",
    "gn:feature_code":"PPL",
    "gn:name":"Les Ch\u00e9seaux",
    "gn:population":0,
    "gn:timezone":"Europe/Zurich",
    "iso:country":"CH",
    "name:fra_x_preferred":[
        "Les Ch\u00e9seaux"
    ],
    "wof:name":"Les Cheseaux",
    "wof:placetype":"neighbourhood"
},
  "geometry": {"coordinates":[7.09143,46.6157],"type":"Point"}
}