{
  "type": "Feature",
  "properties": {
    "gn:admin1_code":"TI",
    "gn:admin2_code":"2103.0",
    "gn:admin3_code":"5073.0",
    "gn:asciiname":"Cagnago",
    "gn:country_code":"CH",
    "gn:dem":342,
    "gn:feature_class":"P",
    "gn:feature_code":"PPL",
    "gn:name":"Cagnago",
    "gn:population":0,
    "gn:timezone":"Europe/Zurich",
    "iso:country":"CH",
    "wof:name":"Cagnago",
    "wof:placetype":"locality"
},
  "geometry": {"coordinates":[8.89326,46.38543],"type":"Point"}
}