{
  "type": "Feature",
  "properties": {
    "gn:admin1_code":"GR",
    "gn:admin2_code":"1849.0",
    "gn:admin3_code":"3851.0",
    "gn:asciiname":"Oberalp",
    "gn:country_code":"CH",
    "gn:dem":1890,
    "gn:feature_class":"P",
    "gn:feature_code":"PPL",
    "gn:name":"Oberalp",
    "gn:population":0,
    "gn:timezone":"Europe/Zurich",
    "iso:country":"CH",
    "wof:name":"Oberalp",
    "wof:placetype":"neighbourhood"
},
  "geometry": {"coordinates":[9.78868,46.70813],"type":"Point"}
}