{
  "type": "Feature",
  "properties": {
    "gn:country":"CH",
    "gn:fcode":"PPL",
    "gn:population":26,
    "iso:country":"CH",
    "name:arz_x_preferred":[
        "\u062c\u0628\u0644 \u0631\u0648\u062a\u064a\u0646\u0641\u0644\u0648\u0647"
    ],
    "name:deu_x_preferred":[
        "Rotenfluh"
    ],
    "name:jpn_x_preferred":[
        "\u30ed\u30fc\u30c6\u30f3\u30d5\u30eb\u30fc\u5c71"
    ],
    "name:zho_x_preferred":[
        "\u7f85\u6ed5\u5f17\u76e7\u8d6b\u5c71"
    ],
    "qs_pg:aaroncc":"CH",
    "qs_pg:gn_country":"CH",
    "qs_pg:gn_fcode":"PPL",
    "qs_pg:gn_pop":26,
    "qs_pg:name":"Rotenfluh",
    "qs_pg:photos_9r":0,
    "qs_pg:photos_sr":0,
    "qs_pg:pop_sr":1,
    "qs_pg:qs_pg_placetype":"locality",
    "wof:name":"Rotenfluh",
    "wof:placetype":"neighbourhood",
    "wof:population":26
},
  "geometry": {"coordinates":[8.62835,47.49409],"type":"Point"}
}