{
  "type": "Feature",
  "properties": {
    "gn:gn_country":"CH",
    "gn:gn_fcode":"PPL",
    "gn:gn_pop":3800,
    "gn:population":3800,
    "iso:country":"CH",
    "qs_pg:aaroncc":"CH",
    "qs_pg:gn_country":"CH",
    "qs_pg:gn_fcode":"PPL",
    "qs_pg:gn_pop":3800,
    "qs_pg:name":"Rudolfstetten",
    "qs_pg:name_adm0":"Schweiz",
    "qs_pg:name_adm1":"Kanton Aargau",
    "qs_pg:photos":138,
    "qs_pg:photos_1k":28,
    "qs_pg:photos_9k":1,
    "qs_pg:photos_9r":3,
    "qs_pg:photos_all":138,
    "qs_pg:photos_sr":3,
    "qs_pg:pop_sr":4,
    "qs_pg:qs_pg_placetype":"locality",
    "qs_pg:qs_pg_placetype_gp":"Town",
    "qs_pg:woe_adm0":23424957,
    "woe:adm0_id":23424957,
    "woe:name_adm0":"Schweiz",
    "woe:name_adm1":"Kanton Aargau",
    "woe:placetype":"Town",
    "wof:name":"Rudolfstetten",
    "wof:placetype":"locality",
    "wof:population":3800
},
  "geometry": {"coordinates":[8.38083,47.37101],"type":"Point"}
}