{
  "type": "Feature",
  "properties": {
    "gn:admin1_code":"VD",
    "gn:admin2_code":"2228.0",
    "gn:admin3_code":"5855.0",
    "gn:asciiname":"Dully",
    "gn:country_code":"CH",
    "gn:dem":415,
    "gn:feature_class":"P",
    "gn:feature_code":"PPL",
    "gn:name":"Dully",
    "gn:population":0,
    "gn:timezone":"Europe/Zurich",
    "iso:country":"CH",
    "wof:name":"Dully",
    "wof:placetype":"locality"
},
  "geometry": {"coordinates":[6.29461,46.43143],"type":"Point"}
}