{
  "type": "Feature",
  "properties": {
    "gn:gn_country":"CH",
    "gn:gn_fcode":"PPL",
    "gn:gn_pop":961,
    "gn:population":961,
    "iso:country":"CH",
    "name:alb_x_preferred":[
        "Savognin"
    ],
    "name:cat_x_preferred":[
        "Savognin"
    ],
    "name:chi_x_preferred":[
        "\u85a9\u6c83\u5be7"
    ],
    "name:chv_x_preferred":[
        "\u0421\u0430\u0432\u043e\u043d\u044c\u0438\u043d"
    ],
    "name:dut_x_preferred":[
        "Savognin"
    ],
    "name:eng_x_preferred":[
        "Savognin"
    ],
    "name:epo_x_preferred":[
        "Savognin"
    ],
    "name:fre_x_preferred":[
        "Savognin"
    ],
    "name:ger_x_preferred":[
        "Savognin"
    ],
    "name:gsw_x_preferred":[
        "Savognin"
    ],
    "name:hun_x_preferred":[
        "Savognin"
    ],
    "name:ita_x_preferred":[
        "Savognin"
    ],
    "name:kaz_x_preferred":[
        "\u0421\u0430\u0432\u043e\u043d\u044c\u0438\u043d"
    ],
    "name:lmo_x_preferred":[
        "Savognin"
    ],
    "name:may_x_preferred":[
        "Savognin"
    ],
    "name:nno_x_preferred":[
        "Savognin"
    ],
    "name:oci_x_preferred":[
        "Savognin"
    ],
    "name:pms_x_preferred":[
        "Savognin"
    ],
    "name:por_x_preferred":[
        "Savognin"
    ],
    "name:roh_x_preferred":[
        "Savognin"
    ],
    "name:rus_x_preferred":[
        "\u0421\u0430\u0432\u043e\u043d\u044c\u0438\u043d"
    ],
    "name:sco_x_preferred":[
        "Savognin"
    ],
    "name:spa_x_preferred":[
        "Savognin"
    ],
    "name:swe_x_preferred":[
        "Savognin"
    ],
    "name:uzb_x_preferred":[
        "Savognin"
    ],
    "name:vol_x_preferred":[
        "Savognin"
    ],
    "name:war_x_preferred":[
        "Savognin"
    ],
    "name:zho_x_preferred":[
        "\u85a9\u6c83\u5be7"
    ],
    "qs_pg:aaroncc":"CH",
    "qs_pg:gn_country":"CH",
    "qs_pg:gn_fcode":"PPL",
    "qs_pg:gn_pop":961,
    "qs_pg:name":"Savognin",
    "qs_pg:name_adm0":"Schweiz",
    "qs_pg:name_adm1":"Kanton Graub\u00fcnden",
    "qs_pg:photos":571,
    "qs_pg:photos_1k":116,
    "qs_pg:photos_9k":3,
    "qs_pg:photos_9r":5,
    "qs_pg:photos_all":571,
    "qs_pg:photos_sr":8,
    "qs_pg:pop_sr":2,
    "qs_pg:qs_pg_placetype":"locality",
    "qs_pg:qs_pg_placetype_gp":"Town",
    "qs_pg:woe_adm0":23424957,
    "woe:adm0_id":23424957,
    "woe:name_adm0":"Schweiz",
    "woe:name_adm1":"Kanton Graub\u00fcnden",
    "woe:placetype":"Town",
    "wof:name":"Savognin",
    "wof:placetype":"locality",
    "wof:population":961
},
  "geometry": {"coordinates":[9.59825,46.59636],"type":"Point"}
}