{
  "type": "Feature",
  "properties": {
    "gn:gn_country":"CH",
    "gn:gn_fcode":"PPL",
    "gn:gn_pop":2336,
    "gn:population":2336,
    "iso:country":"CH",
    "name:cat_x_preferred":[
        "Monte Carasso"
    ],
    "name:deu_x_preferred":[
        "Monte Carasso"
    ],
    "name:eng_x_preferred":[
        "Monte Carasso"
    ],
    "name:epo_x_preferred":[
        "Monte Carasso"
    ],
    "name:eus_x_preferred":[
        "Monte Carasso"
    ],
    "name:fra_x_preferred":[
        "Monte Carasso"
    ],
    "name:gsw_x_preferred":[
        "Monte Carasso"
    ],
    "name:hun_x_preferred":[
        "Monte Carasso"
    ],
    "name:ita_x_preferred":[
        "Monte Carasso"
    ],
    "name:jpn_x_preferred":[
        "\u30e2\u30f3\u30c6\u30fb\u30ab\u30e9\u30c3\u30bd"
    ],
    "name:lmo_x_preferred":[
        "Mont Carass"
    ],
    "name:msa_x_preferred":[
        "Monte Carasso"
    ],
    "name:nld_x_preferred":[
        "Monte Carasso"
    ],
    "name:nno_x_preferred":[
        "Monte Carasso"
    ],
    "name:oci_x_preferred":[
        "Monte Carasso"
    ],
    "name:pol_x_preferred":[
        "Monte Carasso"
    ],
    "name:por_x_preferred":[
        "Monte Carasso"
    ],
    "name:roh_x_preferred":[
        "Monte Carasso"
    ],
    "name:spa_x_preferred":[
        "Monte Carasso"
    ],
    "name:sqi_x_preferred":[
        "Monte Carasso"
    ],
    "name:unk_x_variant":[
        "Monte Carasso-Sementina"
    ],
    "name:vol_x_preferred":[
        "Monte Carasso"
    ],
    "name:war_x_preferred":[
        "Monte Carasso"
    ],
    "name:zho_x_preferred":[
        "\u8499\u6cf0\u5361\u62c9\u7d22"
    ],
    "qs_pg:aaroncc":"CH",
    "qs_pg:gn_country":"CH",
    "qs_pg:gn_fcode":"PPL",
    "qs_pg:gn_pop":2336,
    "qs_pg:name":"Monte Carasso",
    "qs_pg:name_adm0":"Schweiz",
    "qs_pg:name_adm1":"Cantone Ticino",
    "qs_pg:photos":309,
    "qs_pg:photos_1k":63,
    "qs_pg:photos_9k":1,
    "qs_pg:photos_9r":5,
    "qs_pg:photos_all":309,
    "qs_pg:photos_sr":5,
    "qs_pg:pop_sr":4,
    "qs_pg:qs_pg_placetype":"locality",
    "qs_pg:qs_pg_placetype_gp":"Town",
    "qs_pg:woe_adm0":23424957,
    "woe:adm0_id":23424957,
    "woe:name_adm0":"Schweiz",
    "woe:name_adm1":"Cantone Ticino",
    "woe:placetype":"Town",
    "wof:name":"Monte Carasso",
    "wof:placetype":"locality",
    "wof:population":2336
},
  "geometry": {"coordinates":[8.99892,46.18649],"type":"Point"}
}