{
  "type": "Feature",
  "properties": {
    "gn:admin1_code":"SG",
    "gn:admin2_code":"1726.0",
    "gn:admin3_code":"3342.0",
    "gn:asciiname":"Lindenbaechli",
    "gn:country_code":"CH",
    "gn:dem":680,
    "gn:feature_class":"P",
    "gn:feature_code":"PPLL",
    "gn:name":"Lindenb\u00e4chli",
    "gn:population":0,
    "gn:timezone":"Europe/Zurich",
    "iso:country":"CH",
    "name:deu_x_preferred":[
        "Lindenb\u00e4chli"
    ],
    "wof:name":"Lindenbaechli",
    "wof:placetype":"locality"
},
  "geometry": {"coordinates":[8.98163,47.25782],"type":"Point"}
}