{
  "type": "Feature",
  "properties": {
    "gn:admin1_code":"FR",
    "gn:admin2_code":"1003.0",
    "gn:admin3_code":"2152.0",
    "gn:asciiname":"La Gisetta",
    "gn:country_code":"CH",
    "gn:dem":855,
    "gn:feature_class":"P",
    "gn:feature_code":"PPL",
    "gn:name":"La Gisetta",
    "gn:population":0,
    "gn:timezone":"Europe/Zurich",
    "iso:country":"CH",
    "name:fra_x_preferred":[
        "La Gisetta"
    ],
    "wof:name":"La Gisetta",
    "wof:placetype":"locality"
},
  "geometry": {"coordinates":[6.95182,46.60397],"type":"Point"}
}