{
  "type": "Feature",
  "properties": {
    "gn:gn_country":"CH",
    "gn:gn_fcode":"PPL",
    "gn:gn_pop":754,
    "gn:population":754,
    "iso:country":"CH",
    "name:baq_x_preferred":[
        "Grandcour"
    ],
    "name:cat_x_preferred":[
        "Grandcour"
    ],
    "name:chi_x_preferred":[
        "\u683c\u6717\u5e93\u5c14"
    ],
    "name:dut_x_preferred":[
        "Grandcour"
    ],
    "name:eng_x_preferred":[
        "Grandcour"
    ],
    "name:epo_x_preferred":[
        "Grandcour"
    ],
    "name:fas_x_preferred":[
        "\u06af\u0631\u0627\u0646\u062f\u06a9\u0648\u0631"
    ],
    "name:fre_x_preferred":[
        "Grandcour"
    ],
    "name:ger_x_preferred":[
        "Grandcour"
    ],
    "name:gsw_x_preferred":[
        "Grandcour"
    ],
    "name:hun_x_preferred":[
        "Grandcour"
    ],
    "name:ita_x_preferred":[
        "Grandcour"
    ],
    "name:lmo_x_preferred":[
        "Grandcour"
    ],
    "name:may_x_preferred":[
        "Grandcour"
    ],
    "name:nno_x_preferred":[
        "Grandcour"
    ],
    "name:oci_x_preferred":[
        "Grandcour"
    ],
    "name:per_x_preferred":[
        "\u06af\u0631\u0627\u0646\u062f\u06a9\u0648\u0631"
    ],
    "name:roh_x_preferred":[
        "Grandcour"
    ],
    "name:spa_x_preferred":[
        "Grandcour"
    ],
    "name:vol_x_preferred":[
        "Grandcour"
    ],
    "name:zho_x_preferred":[
        "\u683c\u6717\u5e93\u5c14"
    ],
    "qs_pg:aaroncc":"CH",
    "qs_pg:gn_country":"CH",
    "qs_pg:gn_fcode":"PPL",
    "qs_pg:gn_pop":754,
    "qs_pg:name":"Grandcour",
    "qs_pg:name_adm0":"Schweiz",
    "qs_pg:name_adm1":"Canton de Vaud",
    "qs_pg:photos":50,
    "qs_pg:photos_1k":10,
    "qs_pg:photos_9k":1,
    "qs_pg:photos_9r":2,
    "qs_pg:photos_all":50,
    "qs_pg:photos_sr":2,
    "qs_pg:pop_sr":2,
    "qs_pg:qs_pg_placetype":"locality",
    "qs_pg:qs_pg_placetype_gp":"Town",
    "qs_pg:woe_adm0":23424957,
    "woe:adm0_id":23424957,
    "woe:name_adm0":"Schweiz",
    "woe:name_adm1":"Canton de Vaud",
    "woe:placetype":"Town",
    "wof:name":"Grandcour",
    "wof:placetype":"locality",
    "wof:population":754
},
  "geometry": {"coordinates":[6.9284,46.87185],"type":"Point"}
}