{
  "type": "Feature",
  "properties": {
    "gn:gn_country":"CH",
    "gn:gn_fcode":"PPL",
    "gn:gn_pop":0,
    "iso:country":"CH",
    "name:alb_x_preferred":[
        "Birrhard"
    ],
    "name:baq_x_preferred":[
        "Birrhard"
    ],
    "name:bul_x_preferred":[
        "\u0411\u0438\u0440\u0445\u0430\u0440\u0434"
    ],
    "name:cat_x_preferred":[
        "Birrhard"
    ],
    "name:chi_x_preferred":[
        "\u6bd4\u723e\u963f\u723e\u5fb7"
    ],
    "name:dut_x_preferred":[
        "Birrhard"
    ],
    "name:eng_x_preferred":[
        "Birrhard"
    ],
    "name:epo_x_preferred":[
        "Birrhard"
    ],
    "name:fre_x_preferred":[
        "Birrhard"
    ],
    "name:ger_x_preferred":[
        "Birrhard"
    ],
    "name:gsw_x_preferred":[
        "Birret"
    ],
    "name:hun_x_preferred":[
        "Birrhard"
    ],
    "name:ita_x_preferred":[
        "Birrhard"
    ],
    "name:kaz_x_preferred":[
        "\u0411\u0438\u0440\u0445\u0430\u0440\u0434"
    ],
    "name:lmo_x_preferred":[
        "Birrhard"
    ],
    "name:may_x_preferred":[
        "Birrhard"
    ],
    "name:nno_x_preferred":[
        "Birrhard"
    ],
    "name:oci_x_preferred":[
        "Birrhard"
    ],
    "name:pms_x_preferred":[
        "Birrhard"
    ],
    "name:pol_x_preferred":[
        "Birrhard"
    ],
    "name:por_x_preferred":[
        "Birrhard"
    ],
    "name:rus_x_preferred":[
        "\u0411\u0438\u0440\u0445\u0430\u0440\u0434"
    ],
    "name:spa_x_preferred":[
        "Birrhard"
    ],
    "name:swe_x_preferred":[
        "Birrhard"
    ],
    "name:uzb_x_preferred":[
        "Birrhard"
    ],
    "name:vol_x_preferred":[
        "Birrhard"
    ],
    "name:war_x_preferred":[
        "Birrhard"
    ],
    "name:zho_x_preferred":[
        "\u6bd4\u723e\u963f\u723e\u5fb7"
    ],
    "qs_pg:aaroncc":"CH",
    "qs_pg:gn_country":"CH",
    "qs_pg:gn_fcode":"PPL",
    "qs_pg:gn_pop":0,
    "qs_pg:name":"Birrhard",
    "qs_pg:name_adm0":"Schweiz",
    "qs_pg:name_adm1":"Kanton Aargau",
    "qs_pg:photos":17,
    "qs_pg:photos_1k":3,
    "qs_pg:photos_9k":1,
    "qs_pg:photos_9r":1,
    "qs_pg:photos_all":17,
    "qs_pg:photos_sr":1,
    "qs_pg:pop_sr":0,
    "qs_pg:qs_pg_placetype":"locality",
    "qs_pg:qs_pg_placetype_gp":"Town",
    "qs_pg:woe_adm0":23424957,
    "woe:adm0_id":23424957,
    "woe:name_adm0":"Schweiz",
    "woe:name_adm1":"Kanton Aargau",
    "woe:placetype":"Town",
    "wof:name":"Birrhard",
    "wof:placetype":"locality"
},
  "geometry": {"coordinates":[8.24498,47.43285],"type":"Point"}
}