{
  "type": "Feature",
  "properties": {
    "gn:admin1_code":"NW",
    "gn:admin2_code":"700.0",
    "gn:admin3_code":"1503.0",
    "gn:asciiname":"Haechlisberg",
    "gn:country_code":"CH",
    "gn:dem":731,
    "gn:feature_class":"P",
    "gn:feature_code":"PPL",
    "gn:name":"H\u00e4chlisberg",
    "gn:population":0,
    "gn:timezone":"Europe/Zurich",
    "iso:country":"CH",
    "wof:name":"Haechlisberg",
    "wof:placetype":"neighbourhood"
},
  "geometry": {"coordinates":[8.37908,46.92157],"type":"Point"}
}