{
  "type": "Feature",
  "properties": {
    "gn:admin1_code":"JU",
    "gn:admin2_code":"2601.0",
    "gn:admin3_code":"6721.0",
    "gn:asciiname":"Rossemaison",
    "gn:country_code":"CH",
    "gn:dem":444,
    "gn:feature_class":"P",
    "gn:feature_code":"PPL",
    "gn:name":"Rossemaison",
    "gn:population":0,
    "gn:timezone":"Europe/Zurich",
    "iso:country":"CH",
    "name:zho_x_preferred":[
        "\u7f85\u745f\u9081\u677e"
    ],
    "wof:name":"Rossemaison",
    "wof:placetype":"locality"
},
  "geometry": {"coordinates":[7.3409,47.34434],"type":"Point"}
}