{
  "type": "Feature",
  "properties": {
    "gn:admin1_code":"FR",
    "gn:admin2_code":"1002.0",
    "gn:admin3_code":"2099.0",
    "gn:asciiname":"Prez-vers-Siviriez",
    "gn:country_code":"CH",
    "gn:dem":759,
    "gn:feature_class":"P",
    "gn:feature_code":"PPL",
    "gn:name":"Prez-vers-Siviriez",
    "gn:population":0,
    "gn:timezone":"Europe/Zurich",
    "iso:country":"CH",
    "wof:name":"Prez-vers-Siviriez",
    "wof:placetype":"locality"
},
  "geometry": {"coordinates":[6.87478,46.63965],"type":"Point"}
}