{
  "type": "Feature",
  "properties": {
    "gn:country":"CH",
    "gn:fcode":"PPL",
    "gn:population":0,
    "iso:country":"CH",
    "name:bre_x_preferred":[
        "Ried-Brig"
    ],
    "name:cat_x_preferred":[
        "Ried-Brig"
    ],
    "name:ceb_x_preferred":[
        "Ried-Brig"
    ],
    "name:cym_x_preferred":[
        "Ried-Brig"
    ],
    "name:deu_x_preferred":[
        "Ried-Brig"
    ],
    "name:eng_x_preferred":[
        "Ried-Brig"
    ],
    "name:epo_x_preferred":[
        "Ried-Brig"
    ],
    "name:eus_x_preferred":[
        "Ried-Brig"
    ],
    "name:fra_x_preferred":[
        "Ried-Brig"
    ],
    "name:frp_x_preferred":[
        "Ried-Brega"
    ],
    "name:gle_x_preferred":[
        "Ried-Brig"
    ],
    "name:gsw_x_preferred":[
        "Ried-Brig"
    ],
    "name:hsb_x_preferred":[
        "Ried-Brig"
    ],
    "name:hun_x_preferred":[
        "Ried-Brig"
    ],
    "name:ita_x_preferred":[
        "Ried-Briga"
    ],
    "name:lmo_x_preferred":[
        "Ried-Brig"
    ],
    "name:msa_x_preferred":[
        "Ried-Brig"
    ],
    "name:nld_x_preferred":[
        "Ried-Brig"
    ],
    "name:nno_x_preferred":[
        "Ried-Brig"
    ],
    "name:nob_x_preferred":[
        "Ried-Brig"
    ],
    "name:oci_x_preferred":[
        "Ried-Brig"
    ],
    "name:pms_x_preferred":[
        "Ried-Brig"
    ],
    "name:por_x_preferred":[
        "Ried-Brig"
    ],
    "name:roh_x_preferred":[
        "Ried-Brig"
    ],
    "name:rus_x_preferred":[
        "\u0420\u0438\u0434-\u0411\u0440\u0438\u0433"
    ],
    "name:spa_x_preferred":[
        "Ried-Brig"
    ],
    "name:sqi_x_preferred":[
        "Ried-Brig"
    ],
    "name:swe_x_preferred":[
        "Ried-Brig"
    ],
    "name:ukr_x_preferred":[
        "\u0420\u0456\u0434-\u0411\u0440\u0456\u0433"
    ],
    "name:vec_x_preferred":[
        "Ried-Briga"
    ],
    "name:vol_x_preferred":[
        "Ried-Brig"
    ],
    "name:war_x_preferred":[
        "Ried-Brig"
    ],
    "name:zho_x_preferred":[
        "\u91cc\u5fb7\u5e03\u91cc\u683c"
    ],
    "qs_pg:aaroncc":"CH",
    "qs_pg:gn_country":"CH",
    "qs_pg:gn_fcode":"PPL",
    "qs_pg:gn_pop":0,
    "qs_pg:name":"Ried",
    "qs_pg:name_adm0":"Schweiz",
    "qs_pg:name_adm1":"Canton de Valais",
    "qs_pg:photos":30,
    "qs_pg:photos_1k":6,
    "qs_pg:photos_9k":1,
    "qs_pg:photos_9r":2,
    "qs_pg:photos_all":30,
    "qs_pg:photos_sr":2,
    "qs_pg:pop_sr":0,
    "qs_pg:qs_pg_placetype":"locality",
    "qs_pg:qs_pg_placetype_gp":"Town",
    "qs_pg:woe_adm0":23424957,
    "woe:adm0_id":23424957,
    "woe:name_adm0":"Schweiz",
    "woe:name_adm1":"Canton de Valais",
    "woe:placetype":"Town",
    "wof:name":"Ried",
    "wof:placetype":"neighbourhood"
},
  "geometry": {"coordinates":[8.01752,46.31376],"type":"Point"}
}