{
  "type": "Feature",
  "properties": {
    "gn:admin1_code":"BE",
    "gn:admin2_code":"245.0",
    "gn:admin3_code":"409.0",
    "gn:asciiname":"Wiler",
    "gn:country_code":"CH",
    "gn:dem":532,
    "gn:feature_class":"P",
    "gn:feature_code":"PPLL",
    "gn:name":"Wiler",
    "gn:population":0,
    "gn:timezone":"Europe/Zurich",
    "iso:country":"CH",
    "name:deu_x_preferred":[
        "Wiler"
    ],
    "wof:name":"Wiler",
    "wof:placetype":"neighbourhood"
},
  "geometry": {"coordinates":[7.54422,47.03511],"type":"Point"}
}