{
  "type": "Feature",
  "properties": {
    "gn:admin1_code":"BE",
    "gn:admin2_code":"245.0",
    "gn:admin3_code":"409.0",
    "gn:asciiname":"Wiler",
    "gn:country_code":"CH",
    "gn:dem":532,
    "gn:feature_class":"P",
    "gn:feature_code":"PPLL",
    "gn:name":"Wiler",
    "gn:population":0,
    "gn:timezone":"Europe/Zurich",
    "iso:country":"CH",
    "name:als_x_preferred":[
        "Wiler"
    ],
    "name:cat_x_preferred":[
        "Wiler"
    ],
    "name:ceb_x_preferred":[
        "Wiler"
    ],
    "name:deu_x_preferred":[
        "Wiler"
    ],
    "name:epo_x_preferred":[
        "Wiler"
    ],
    "name:eus_x_preferred":[
        "Wiler"
    ],
    "name:fra_x_preferred":[
        "Wiler"
    ],
    "name:ita_x_preferred":[
        "Wiler"
    ],
    "name:lmo_x_preferred":[
        "Wiler"
    ],
    "name:msa_x_preferred":[
        "Wiler"
    ],
    "name:nld_x_preferred":[
        "Wiler"
    ],
    "name:nno_x_preferred":[
        "Wiler"
    ],
    "name:pms_x_preferred":[
        "Wiler"
    ],
    "name:por_x_preferred":[
        "Wiler"
    ],
    "name:roh_x_preferred":[
        "Wiler"
    ],
    "name:spa_x_preferred":[
        "Wiler"
    ],
    "name:sqi_x_preferred":[
        "Wiler"
    ],
    "name:swe_x_preferred":[
        "Wiler"
    ],
    "name:vec_x_preferred":[
        "Wiler"
    ],
    "name:vol_x_preferred":[
        "Wiler"
    ],
    "name:war_x_preferred":[
        "Wiler"
    ],
    "name:zho_x_preferred":[
        "\u7dad\u52d2"
    ],
    "wof:lang_x_official":[
        "deu",
        "fra",
        "gsw",
        "ita"
    ],
    "wof:lang_x_spoken":[
        "deu",
        "fra",
        "gsw",
        "ita",
        "roh"
    ],
    "wof:name":"Wiler",
    "wof:placetype":"neighbourhood"
},
  "geometry": {"coordinates":[7.54422,47.03511],"type":"Point"}
}