{
  "type": "Feature",
  "properties": {
    "gn:admin1_code":"ZH",
    "gn:admin2_code":"111.0",
    "gn:admin3_code":"243.0",
    "gn:asciiname":"Dietikon / Industrie",
    "gn:country_code":"CH",
    "gn:dem":385,
    "gn:feature_class":"P",
    "gn:feature_code":"PPL",
    "gn:name":"Dietikon / Industrie",
    "gn:population":0,
    "gn:timezone":"Europe/Zurich",
    "iso:country":"CH",
    "name:eng_x_preferred":[
        "Industrie"
    ],
    "name:eng_x_variant":[
        "Dietikon / Industrie"
    ],
    "wof:name":"Industrie",
    "wof:placetype":"neighbourhood"
},
  "geometry": {"coordinates":[8.4016,47.4122],"type":"Point"}
}