{
  "type": "Feature",
  "properties": {
    "gn:admin1_code":"VD",
    "gn:admin2_code":"2228.0",
    "gn:admin3_code":"5702.0",
    "gn:asciiname":"Le Muids",
    "gn:country_code":"CH",
    "gn:dem":703,
    "gn:elevation":"696.0",
    "gn:feature_class":"P",
    "gn:feature_code":"PPL",
    "gn:name":"Le Muids",
    "gn:population":0,
    "gn:timezone":"Europe/Zurich",
    "iso:country":"CH",
    "wof:lang_x_official":[
        "deu",
        "fra",
        "gsw",
        "ita"
    ],
    "wof:lang_x_spoken":[
        "deu",
        "fra",
        "gsw",
        "ita",
        "roh"
    ],
    "wof:name":"Le Muids",
    "wof:placetype":"neighbourhood"
},
  "geometry": {"coordinates":[6.22035,46.45559],"type":"Point"}
}