{
  "type": "Feature",
  "properties": {
    "gn:gn_country":"CH",
    "gn:gn_fcode":"PPL",
    "gn:gn_pop":848,
    "gn:population":848,
    "iso:country":"CH",
    "name:alb_x_preferred":[
        "Sent"
    ],
    "name:bre_x_preferred":[
        "Sent"
    ],
    "name:cat_x_preferred":[
        "Sent"
    ],
    "name:chi_x_preferred":[
        "\u68ee\u7279"
    ],
    "name:deu_x_preferred":[
        "Sins GR"
    ],
    "name:deu_x_variant":[
        "Sent",
        "Sent GR"
    ],
    "name:dut_x_preferred":[
        "Sent"
    ],
    "name:eng_x_preferred":[
        "Sent"
    ],
    "name:epo_x_preferred":[
        "Sent"
    ],
    "name:fre_x_preferred":[
        "Sent"
    ],
    "name:ger_x_preferred":[
        "Sent"
    ],
    "name:hun_x_preferred":[
        "Sent"
    ],
    "name:ita_x_preferred":[
        "Sent"
    ],
    "name:kaz_x_preferred":[
        "\u0417\u0435\u043d\u0442"
    ],
    "name:lat_x_preferred":[
        "Sindes"
    ],
    "name:lmo_x_preferred":[
        "Sent"
    ],
    "name:may_x_preferred":[
        "Sent"
    ],
    "name:nno_x_preferred":[
        "Sent"
    ],
    "name:oci_x_preferred":[
        "Sent"
    ],
    "name:pms_x_preferred":[
        "Sent"
    ],
    "name:por_x_preferred":[
        "Sent"
    ],
    "name:roh_x_preferred":[
        "Sent"
    ],
    "name:rus_x_preferred":[
        "\u0417\u0435\u043d\u0442"
    ],
    "name:spa_x_preferred":[
        "Sent"
    ],
    "name:swe_x_preferred":[
        "Sent"
    ],
    "name:tur_x_preferred":[
        "Sent GR"
    ],
    "name:uzb_x_preferred":[
        "Sent"
    ],
    "name:vol_x_preferred":[
        "Sent"
    ],
    "name:war_x_preferred":[
        "Sent"
    ],
    "name:zho_x_preferred":[
        "\u68ee\u7279"
    ],
    "qs_pg:aaroncc":"CH",
    "qs_pg:gn_country":"CH",
    "qs_pg:gn_fcode":"PPL",
    "qs_pg:gn_pop":848,
    "qs_pg:name":"Sent",
    "qs_pg:name_adm0":"Schweiz",
    "qs_pg:name_adm1":"Kanton Graub\u00fcnden",
    "qs_pg:photos":370,
    "qs_pg:photos_1k":75,
    "qs_pg:photos_9k":2,
    "qs_pg:photos_9r":5,
    "qs_pg:photos_all":370,
    "qs_pg:photos_sr":6,
    "qs_pg:pop_sr":2,
    "qs_pg:qs_pg_placetype":"locality",
    "qs_pg:qs_pg_placetype_gp":"Town",
    "qs_pg:woe_adm0":23424957,
    "woe:adm0_id":23424957,
    "woe:name_adm0":"Schweiz",
    "woe:name_adm1":"Kanton Graub\u00fcnden",
    "woe:placetype":"Town",
    "wof:name":"Sent",
    "wof:placetype":"locality",
    "wof:population":848
},
  "geometry": {"coordinates":[10.33683,46.81717],"type":"Point"}
}