{
  "type": "Feature",
  "properties": {
    "gn:admin1_code":"AG",
    "gn:admin2_code":"1911.0",
    "gn:admin3_code":"4323.0",
    "gn:asciiname":"Barz",
    "gn:country_code":"CH",
    "gn:dem":319,
    "gn:feature_class":"P",
    "gn:feature_code":"PPLL",
    "gn:name":"Barz",
    "gn:population":0,
    "gn:timezone":"Europe/Zurich",
    "iso:country":"CH",
    "name:deu_x_preferred":[
        "Barz"
    ],
    "wof:name":"Barz",
    "wof:placetype":"neighbourhood"
},
  "geometry": {"coordinates":[8.29607,47.60452],"type":"Point"}
}