{
  "type": "Feature",
  "properties": {
    "gn:admin1_code":"GR",
    "gn:admin2_code":"1849.0",
    "gn:admin3_code":"3851.0",
    "gn:asciiname":"Buenda",
    "gn:country_code":"CH",
    "gn:dem":1564,
    "gn:feature_class":"P",
    "gn:feature_code":"PPL",
    "gn:name":"B\u00fcnda",
    "gn:population":0,
    "gn:timezone":"Europe/Zurich",
    "iso:country":"CH",
    "wof:name":"Buenda",
    "wof:placetype":"locality"
},
  "geometry": {"coordinates":[9.84446,46.81095],"type":"Point"}
}