{
  "type": "Feature",
  "properties": {
    "gn:gn_country":"CH",
    "gn:gn_fcode":"ADM3",
    "gn:gn_pop":1552,
    "gn:population":1539,
    "iso:country":"CH",
    "name:alb_x_preferred":[
        "Matran"
    ],
    "name:baq_x_preferred":[
        "Matran"
    ],
    "name:bul_x_preferred":[
        "\u041c\u0430\u0442\u0440\u0430\u043d"
    ],
    "name:cat_x_preferred":[
        "Matran"
    ],
    "name:chi_x_preferred":[
        "\u99ac\u7279\u6717"
    ],
    "name:dut_x_preferred":[
        "Matran"
    ],
    "name:eng_x_preferred":[
        "Matran"
    ],
    "name:epo_x_preferred":[
        "Matran"
    ],
    "name:fre_x_preferred":[
        "Matran"
    ],
    "name:ger_x_preferred":[
        "Matran"
    ],
    "name:hun_x_preferred":[
        "Matran"
    ],
    "name:ita_x_preferred":[
        "Matran"
    ],
    "name:lmo_x_preferred":[
        "Matran"
    ],
    "name:may_x_preferred":[
        "Matran"
    ],
    "name:nno_x_preferred":[
        "Matran"
    ],
    "name:oci_x_preferred":[
        "Matran"
    ],
    "name:pms_x_preferred":[
        "Matran"
    ],
    "name:por_x_preferred":[
        "Matran"
    ],
    "name:roh_x_preferred":[
        "Matran"
    ],
    "name:spa_x_preferred":[
        "Matran"
    ],
    "name:swe_x_preferred":[
        "Matran"
    ],
    "name:vie_x_preferred":[
        "Matran"
    ],
    "name:vol_x_preferred":[
        "Matran"
    ],
    "name:war_x_preferred":[
        "Matran"
    ],
    "qs_pg:aaroncc":"CH",
    "qs_pg:gn_country":"CH",
    "qs_pg:gn_fcode":"ADM3",
    "qs_pg:gn_pop":1552,
    "qs_pg:name":"Matran",
    "qs_pg:name_adm0":"Schweiz",
    "qs_pg:name_adm1":"Canton de Fribourg",
    "qs_pg:photos":206,
    "qs_pg:photos_1k":42,
    "qs_pg:photos_9k":1,
    "qs_pg:photos_9r":4,
    "qs_pg:photos_all":206,
    "qs_pg:photos_sr":4,
    "qs_pg:pop_sr":3,
    "qs_pg:qs_pg_placetype":"locality",
    "qs_pg:qs_pg_placetype_gp":"Town",
    "qs_pg:woe_adm0":23424957,
    "woe:adm0_id":23424957,
    "woe:name_adm0":"Schweiz",
    "woe:name_adm1":"Canton de Fribourg",
    "woe:placetype":"Town",
    "wof:name":"Matran",
    "wof:placetype":"locality",
    "wof:population":1539
},
  "geometry": {"coordinates":[7.09101,46.78391],"type":"Point"}
}