{
  "type": "Feature",
  "properties": {
    "gn:admin1_code":"TI",
    "gn:admin2_code":"2105.0",
    "gn:admin3_code":"5236.0",
    "gn:asciiname":"Bigogno",
    "gn:country_code":"CH",
    "gn:dem":544,
    "gn:feature_class":"P",
    "gn:feature_code":"PPL",
    "gn:name":"Bigogno",
    "gn:population":0,
    "gn:timezone":"Europe/Zurich",
    "iso:country":"CH",
    "wof:name":"Bigogno",
    "wof:placetype":"neighbourhood"
},
  "geometry": {"coordinates":[8.91498,45.97367],"type":"Point"}
}