{
  "type": "Feature",
  "properties": {
    "gn:gn_country":"CH",
    "gn:gn_fcode":"PPL",
    "gn:gn_pop":885,
    "gn:population":885,
    "iso:country":"CH",
    "name:baq_x_preferred":[
        "Yvorne"
    ],
    "name:cat_x_preferred":[
        "Yvorne"
    ],
    "name:chi_x_preferred":[
        "\u4f0a\u6c83\u5c14\u8bb7"
    ],
    "name:dut_x_preferred":[
        "Yvorne"
    ],
    "name:eng_x_preferred":[
        "Yvorne"
    ],
    "name:epo_x_preferred":[
        "Yvorne"
    ],
    "name:fre_x_preferred":[
        "Yvorne"
    ],
    "name:ger_x_preferred":[
        "Yvorne"
    ],
    "name:gsw_x_preferred":[
        "Yvorne"
    ],
    "name:heb_x_preferred":[
        "\u05d0\u05d9\u05d5\u05d5\u05e8\u05df"
    ],
    "name:hun_x_preferred":[
        "Yvorne"
    ],
    "name:ita_x_preferred":[
        "Yvorne"
    ],
    "name:lmo_x_preferred":[
        "Yvorne"
    ],
    "name:may_x_preferred":[
        "Yvorne"
    ],
    "name:nno_x_preferred":[
        "Yvorne"
    ],
    "name:oci_x_preferred":[
        "Yvorne"
    ],
    "name:pol_x_preferred":[
        "Yvorne"
    ],
    "name:roh_x_preferred":[
        "Yvorne"
    ],
    "name:rum_x_preferred":[
        "Yvorne"
    ],
    "name:spa_x_preferred":[
        "Yvorne"
    ],
    "name:vol_x_preferred":[
        "Yvorne"
    ],
    "name:war_x_preferred":[
        "Yvorne"
    ],
    "qs_pg:aaroncc":"CH",
    "qs_pg:gn_country":"CH",
    "qs_pg:gn_fcode":"PPL",
    "qs_pg:gn_pop":885,
    "qs_pg:name":"Yvorne",
    "qs_pg:name_adm0":"Schweiz",
    "qs_pg:name_adm1":"Canton de Vaud",
    "qs_pg:photos":346,
    "qs_pg:photos_1k":70,
    "qs_pg:photos_9k":2,
    "qs_pg:photos_9r":5,
    "qs_pg:photos_all":346,
    "qs_pg:photos_sr":5,
    "qs_pg:pop_sr":2,
    "qs_pg:qs_pg_placetype":"locality",
    "qs_pg:qs_pg_placetype_gp":"Town",
    "qs_pg:woe_adm0":23424957,
    "woe:adm0_id":23424957,
    "woe:name_adm0":"Schweiz",
    "woe:name_adm1":"Canton de Vaud",
    "woe:placetype":"Town",
    "wof:name":"Yvorne",
    "wof:placetype":"locality",
    "wof:population":885
},
  "geometry": {"coordinates":[6.95872,46.33122],"type":"Point"}
}