{
  "type": "Feature",
  "properties": {
    "gn:admin1_code":"LU",
    "gn:admin2_code":"315.0",
    "gn:admin3_code":"1140.0",
    "gn:asciiname":"Boelletal",
    "gn:country_code":"CH",
    "gn:dem":477,
    "gn:feature_class":"P",
    "gn:feature_code":"PPLL",
    "gn:name":"B\u00f6lletal",
    "gn:population":0,
    "gn:timezone":"Europe/Zurich",
    "iso:country":"CH",
    "name:deu_x_preferred":[
        "B\u00f6lletal"
    ],
    "wof:name":"Boelletal",
    "wof:placetype":"neighbourhood"
},
  "geometry": {"coordinates":[7.97831,47.25322],"type":"Point"}
}