{
  "type": "Feature",
  "properties": {
    "gn:admin1_code":"TG",
    "gn:admin2_code":"2012.0",
    "gn:admin3_code":"4816.0",
    "gn:asciiname":"Unterkappel",
    "gn:country_code":"CH",
    "gn:dem":556,
    "gn:feature_class":"P",
    "gn:feature_code":"PPLL",
    "gn:name":"Unterkappel",
    "gn:population":0,
    "gn:timezone":"Europe/Zurich",
    "iso:country":"CH",
    "name:deu_x_preferred":[
        "Unterkappel"
    ],
    "wof:lang_x_official":[
        "deu",
        "fra",
        "gsw",
        "ita"
    ],
    "wof:lang_x_spoken":[
        "deu",
        "fra",
        "gsw",
        "ita",
        "roh"
    ],
    "wof:name":"Unterkappel",
    "wof:placetype":"neighbourhood"
},
  "geometry": {"coordinates":[8.99445,47.62431],"type":"Point"}
}