{
  "type": "Feature",
  "properties": {
    "gn:admin1_code":"TI",
    "gn:admin2_code":"2108.0",
    "gn:admin3_code":"5323.0",
    "gn:asciiname":"Sornico",
    "gn:country_code":"CH",
    "gn:dem":756,
    "gn:feature_class":"P",
    "gn:feature_code":"PPL",
    "gn:name":"Sornico",
    "gn:population":0,
    "gn:timezone":"Europe/Zurich",
    "iso:country":"CH",
    "wof:name":"Sornico",
    "wof:placetype":"locality"
},
  "geometry": {"coordinates":[8.65363,46.39841],"type":"Point"}
}