{
  "type": "Feature",
  "properties": {
    "gn:country":"CH",
    "gn:fcode":"PPLX",
    "gn:population":312,
    "iso:country":"CH",
    "name:eng_x_preferred":[
        "Hohenstieglen"
    ],
    "name:eng_x_variant":[
        "Glattbrugg / Hohenstieglen"
    ],
    "qs_pg:aaroncc":"CH",
    "qs_pg:gn_country":"CH",
    "qs_pg:gn_fcode":"PPLX",
    "qs_pg:gn_pop":312,
    "qs_pg:name":"Glattbrugg / Hohenstieglen",
    "qs_pg:photos_9r":0,
    "qs_pg:photos_sr":0,
    "qs_pg:pop_sr":2,
    "qs_pg:qs_pg_placetype":"neighbourhood",
    "wof:lang_x_official":[
        "deu",
        "fra",
        "gsw",
        "ita"
    ],
    "wof:lang_x_spoken":[
        "deu",
        "fra",
        "gsw",
        "ita",
        "roh"
    ],
    "wof:name":"Hohenstieglen",
    "wof:placetype":"neighbourhood",
    "wof:population":312
},
  "geometry": {"coordinates":[8.55799,47.42758],"type":"Point"}
}