{
  "type": "Feature",
  "properties": {
    "gn:gn_country":"CH",
    "gn:gn_fcode":"PPL",
    "gn:gn_pop":9032,
    "gn:population":9032,
    "iso:country":"CH",
    "name:alb_x_preferred":[
        "H\u00fcnenberg"
    ],
    "name:baq_x_preferred":[
        "H\u00fcnenberg"
    ],
    "name:cat_x_preferred":[
        "H\u00fcnenberg"
    ],
    "name:chi_x_preferred":[
        "\u4f11\u502b\u5821"
    ],
    "name:chv_x_preferred":[
        "\u0425\u044e\u043d\u0435\u043d\u0431\u0435\u0440\u0433"
    ],
    "name:deu_x_preferred":[
        "H\u00fcnenberg ZG"
    ],
    "name:dut_x_preferred":[
        "H\u00fcnenberg"
    ],
    "name:eng_x_preferred":[
        "H\u00fcnenberg"
    ],
    "name:epo_x_preferred":[
        "H\u00fcnenberg"
    ],
    "name:fre_x_preferred":[
        "H\u00fcnenberg"
    ],
    "name:ger_x_preferred":[
        "H\u00fcnenberg"
    ],
    "name:hun_x_preferred":[
        "H\u00fcnenberg"
    ],
    "name:ita_x_preferred":[
        "H\u00fcnenberg"
    ],
    "name:jpn_x_preferred":[
        "\u30d2\u30e5\u30cd\u30f3\u30d9\u30eb\u30af"
    ],
    "name:kaz_x_preferred":[
        "\u0425\u044e\u043d\u0435\u043d\u0431\u0435\u0440\u0433"
    ],
    "name:lmo_x_preferred":[
        "H\u00fcnenberg"
    ],
    "name:nno_x_preferred":[
        "H\u00fcnenberg"
    ],
    "name:oci_x_preferred":[
        "H\u00fcnenberg"
    ],
    "name:pms_x_preferred":[
        "H\u00fcnenberg"
    ],
    "name:por_x_preferred":[
        "H\u00fcnenberg"
    ],
    "name:rus_x_preferred":[
        "\u0425\u044e\u043d\u0435\u043d\u0431\u0435\u0440\u0433"
    ],
    "name:spa_x_preferred":[
        "H\u00fcnenberg"
    ],
    "name:vol_x_preferred":[
        "H\u00fcnenberg"
    ],
    "name:war_x_preferred":[
        "H\u00fcnenberg"
    ],
    "name:zho_x_preferred":[
        "\u4f11\u502b\u5821"
    ],
    "qs_pg:aaroncc":"CH",
    "qs_pg:gn_country":"CH",
    "qs_pg:gn_fcode":"PPL",
    "qs_pg:gn_pop":9032,
    "qs_pg:name":"H\u00fcnenberg",
    "qs_pg:name_adm0":"Schweiz",
    "qs_pg:name_adm1":"Kanton Zug",
    "qs_pg:photos":221,
    "qs_pg:photos_1k":45,
    "qs_pg:photos_9k":1,
    "qs_pg:photos_9r":4,
    "qs_pg:photos_all":221,
    "qs_pg:photos_sr":4,
    "qs_pg:pop_sr":5,
    "qs_pg:qs_pg_placetype":"locality",
    "qs_pg:qs_pg_placetype_gp":"Town",
    "qs_pg:woe_adm0":23424957,
    "woe:adm0_id":23424957,
    "woe:name_adm0":"Schweiz",
    "woe:name_adm1":"Kanton Zug",
    "woe:placetype":"Town",
    "wof:name":"H\u00fcnenberg",
    "wof:placetype":"locality",
    "wof:population":9032
},
  "geometry": {"coordinates":[8.42497,47.17536],"type":"Point"}
}