{
  "type": "Feature",
  "properties": {
    "gn:admin1_code":"ZH",
    "gn:admin2_code":"110.0",
    "gn:admin3_code":"211.0",
    "gn:asciiname":"Binz",
    "gn:country":"CH",
    "gn:country_code":"CH",
    "gn:dem":449,
    "gn:fcode":"HSE",
    "gn:feature_class":"P",
    "gn:feature_code":"PPLL",
    "gn:name":"Binz",
    "gn:population":1,
    "gn:timezone":"Europe/Zurich",
    "iso:country":"CH",
    "name:cat_x_preferred":[
        "Binz"
    ],
    "name:ceb_x_preferred":[
        "Binz"
    ],
    "name:ces_x_preferred":[
        "Binz"
    ],
    "name:dan_x_preferred":[
        "Binz"
    ],
    "name:deu_x_preferred":[
        "Binz"
    ],
    "name:eng_x_preferred":[
        "Binz"
    ],
    "name:epo_x_preferred":[
        "Binz"
    ],
    "name:fas_x_preferred":[
        "\u0628\u06cc\u0646\u062a\u0633"
    ],
    "name:fin_x_preferred":[
        "Binz"
    ],
    "name:fra_x_preferred":[
        "Binz"
    ],
    "name:hun_x_preferred":[
        "Binz"
    ],
    "name:ita_x_preferred":[
        "Binz"
    ],
    "name:mkd_x_preferred":[
        "\u0411\u0438\u043d\u0446"
    ],
    "name:msa_x_preferred":[
        "Binz"
    ],
    "name:nld_x_preferred":[
        "Binz"
    ],
    "name:pms_x_preferred":[
        "Binz"
    ],
    "name:pol_x_preferred":[
        "Binz"
    ],
    "name:por_x_preferred":[
        "Binz"
    ],
    "name:ron_x_preferred":[
        "Binz"
    ],
    "name:rus_x_preferred":[
        "\u0411\u0438\u043d\u0446"
    ],
    "name:slk_x_preferred":[
        "Binz"
    ],
    "name:spa_x_preferred":[
        "Binz"
    ],
    "name:srp_x_preferred":[
        "\u0411\u0438\u043d\u0446"
    ],
    "name:swe_x_preferred":[
        "Binz"
    ],
    "name:ukr_x_preferred":[
        "\u0411\u0456\u043d\u0446"
    ],
    "name:urd_x_preferred":[
        "\u0628\u0646\u0632"
    ],
    "name:uzb_x_preferred":[
        "Binz"
    ],
    "name:vie_x_preferred":[
        "Binz"
    ],
    "name:vol_x_preferred":[
        "Binz"
    ],
    "name:war_x_preferred":[
        "Binz"
    ],
    "qs_pg:aaroncc":"CH",
    "qs_pg:gn_country":"CH",
    "qs_pg:gn_fcode":"HSE",
    "qs_pg:gn_pop":1,
    "qs_pg:name":"Binz",
    "qs_pg:photos_9r":0,
    "qs_pg:photos_sr":0,
    "qs_pg:pop_sr":1,
    "qs_pg:qs_pg_placetype":"locality_funky",
    "wof:name":"Binz",
    "wof:placetype":"neighbourhood",
    "wof:population":1
},
  "geometry": {"coordinates":[8.78363,47.56714],"type":"Point"}
}