{
  "type": "Feature",
  "properties": {
    "gn:country":"CH",
    "gn:fcode":"HSE",
    "gn:population":1,
    "iso:country":"CH",
    "name:ces_x_preferred":[
        "Binz"
    ],
    "name:deu_x_preferred":[
        "Binz"
    ],
    "name:eng_x_preferred":[
        "Binz"
    ],
    "name:fra_x_preferred":[
        "Binz"
    ],
    "name:nld_x_preferred":[
        "Binz"
    ],
    "name:rus_x_preferred":[
        "\u0411\u0438\u043d\u0446"
    ],
    "name:slk_x_preferred":[
        "Binz"
    ],
    "name:uzb_x_preferred":[
        "Binz"
    ],
    "qs_pg:aaroncc":"CH",
    "qs_pg:gn_country":"CH",
    "qs_pg:gn_fcode":"HSE",
    "qs_pg:gn_pop":1,
    "qs_pg:name":"Binz",
    "qs_pg:photos_9r":0,
    "qs_pg:photos_sr":0,
    "qs_pg:pop_sr":1,
    "qs_pg:qs_pg_placetype":"locality_funky",
    "wof:lang_x_official":[
        "deu",
        "fra",
        "gsw",
        "ita"
    ],
    "wof:lang_x_spoken":[
        "deu",
        "fra",
        "gsw",
        "ita",
        "roh"
    ],
    "wof:name":"Binz",
    "wof:placetype":"neighbourhood",
    "wof:population":1
},
  "geometry": {"coordinates":[8.78363,47.56714],"type":"Point"}
}