{
  "type": "Feature",
  "properties": {
    "gn:admin1_code":"BE",
    "gn:admin2_code":"245.0",
    "gn:admin3_code":"907.0",
    "gn:asciiname":"Tanne",
    "gn:country_code":"CH",
    "gn:dem":731,
    "gn:feature_class":"P",
    "gn:feature_code":"PPLL",
    "gn:name":"Tanne",
    "gn:population":0,
    "gn:timezone":"Europe/Zurich",
    "iso:country":"CH",
    "name:deu_x_preferred":[
        "Tanne"
    ],
    "name:epo_x_preferred":[
        "Tanne"
    ],
    "name:fra_x_preferred":[
        "Tanne"
    ],
    "wof:name":"Tanne",
    "wof:placetype":"neighbourhood"
},
  "geometry": {"coordinates":[7.73866,46.91593],"type":"Point"}
}