{
  "type": "Feature",
  "properties": {
    "gn:gn_country":"CH",
    "gn:gn_fcode":"PPL",
    "gn:gn_pop":2000,
    "gn:population":2000,
    "iso:country":"CH",
    "name:cat_x_preferred":[
        "Hallau"
    ],
    "name:deu_x_preferred":[
        "Hallau"
    ],
    "name:eng_x_preferred":[
        "Hallau"
    ],
    "name:epo_x_preferred":[
        "Hallau"
    ],
    "name:eus_x_preferred":[
        "Hallau"
    ],
    "name:fra_x_preferred":[
        "Hallau"
    ],
    "name:gsw_x_preferred":[
        "Halau"
    ],
    "name:hrv_x_preferred":[
        "Hallau"
    ],
    "name:hun_x_preferred":[
        "Hallau"
    ],
    "name:ita_x_preferred":[
        "Hallau"
    ],
    "name:kaz_x_preferred":[
        "\u0425\u0430\u043b\u043b\u0430\u0443"
    ],
    "name:lmo_x_preferred":[
        "Hallau"
    ],
    "name:nld_x_preferred":[
        "Hallau"
    ],
    "name:nno_x_preferred":[
        "Hallau"
    ],
    "name:oci_x_preferred":[
        "Hallau"
    ],
    "name:pms_x_preferred":[
        "Hallau"
    ],
    "name:por_x_preferred":[
        "Hallau"
    ],
    "name:rus_x_preferred":[
        "\u0425\u0430\u043b\u043b\u0430\u0443"
    ],
    "name:spa_x_preferred":[
        "Hallau"
    ],
    "name:sqi_x_preferred":[
        "Hallau"
    ],
    "name:vol_x_preferred":[
        "Hallau"
    ],
    "name:war_x_preferred":[
        "Hallau"
    ],
    "qs_pg:aaroncc":"CH",
    "qs_pg:gn_country":"CH",
    "qs_pg:gn_fcode":"PPL",
    "qs_pg:gn_pop":2000,
    "qs_pg:name":"Hallau",
    "qs_pg:name_adm0":"Schweiz",
    "qs_pg:name_adm1":"Kanton Schaffhausen",
    "qs_pg:photos":82,
    "qs_pg:photos_1k":17,
    "qs_pg:photos_9k":1,
    "qs_pg:photos_9r":3,
    "qs_pg:photos_all":82,
    "qs_pg:photos_sr":3,
    "qs_pg:pop_sr":3,
    "qs_pg:qs_pg_placetype":"locality",
    "qs_pg:qs_pg_placetype_gp":"Town",
    "qs_pg:woe_adm0":23424957,
    "woe:adm0_id":23424957,
    "woe:name_adm0":"Schweiz",
    "woe:name_adm1":"Kanton Schaffhausen",
    "woe:placetype":"Town",
    "wof:name":"Hallau",
    "wof:placetype":"locality",
    "wof:population":2000
},
  "geometry": {"coordinates":[8.45827,47.69648],"type":"Point"}
}