{
  "type": "Feature",
  "properties": {
    "gn:admin1_code":"VD",
    "gn:admin2_code":"2224.0",
    "gn:admin3_code":"5938.0",
    "gn:asciiname":"Sermuz",
    "gn:country_code":"CH",
    "gn:dem":490,
    "gn:elevation":"488.0",
    "gn:feature_class":"P",
    "gn:feature_code":"PPL",
    "gn:name":"Sermuz",
    "gn:population":0,
    "gn:timezone":"Europe/Zurich",
    "iso:country":"CH",
    "wof:name":"Sermuz",
    "wof:placetype":"neighbourhood"
},
  "geometry": {"coordinates":[6.64731,46.75668],"type":"Point"}
}