{
  "type": "Feature",
  "properties": {
    "iso:country":"CH",
    "qs_pg:aaroncc":"CH",
    "qs_pg:name":"Klewenalp",
    "qs_pg:name_adm0":"Schweiz",
    "qs_pg:name_adm1":"Kanton Nidwalden",
    "qs_pg:photos":93,
    "qs_pg:photos_1k":19,
    "qs_pg:photos_9k":1,
    "qs_pg:photos_9r":3,
    "qs_pg:photos_all":93,
    "qs_pg:photos_sr":3,
    "qs_pg:pop_sr":0,
    "qs_pg:qs_pg_placetype":"locality",
    "qs_pg:qs_pg_placetype_gp":"Town",
    "qs_pg:woe_adm0":23424957,
    "woe:adm0_id":23424957,
    "woe:name_adm0":"Schweiz",
    "woe:name_adm1":"Kanton Nidwalden",
    "woe:placetype":"Town",
    "wof:name":"Klewenalp",
    "wof:placetype":"neighbourhood"
},
  "geometry": {"coordinates":[8.474407,46.939],"type":"Point"}
}