{
  "type": "Feature",
  "properties": {
    "gn:country":"CH",
    "gn:fcode":"PPLX",
    "gn:population":546,
    "iso:country":"CH",
    "name:eng_x_preferred":[
        "Alte Landstrasse"
    ],
    "name:eng_x_variant":[
        "R\u00fcschlikon / Alte Landstrasse"
    ],
    "qs_pg:aaroncc":"CH",
    "qs_pg:gn_country":"CH",
    "qs_pg:gn_fcode":"PPLX",
    "qs_pg:gn_pop":546,
    "qs_pg:name":"R\u00fcschlikon / Alte Landstrasse",
    "qs_pg:photos_9r":0,
    "qs_pg:photos_sr":0,
    "qs_pg:pop_sr":2,
    "qs_pg:qs_pg_placetype":"neighbourhood",
    "wof:name":"Alte Landstrasse",
    "wof:placetype":"neighbourhood",
    "wof:population":546
},
  "geometry": {"coordinates":[8.55427,47.30378],"type":"Point"}
}