{
  "type": "Feature",
  "properties": {
    "gn:admin1_code":"FR",
    "gn:admin2_code":"1002.0",
    "gn:admin3_code":"2113.0",
    "gn:asciiname":"La Joux",
    "gn:country_code":"CH",
    "gn:dem":846,
    "gn:elevation":"858.0",
    "gn:feature_class":"P",
    "gn:feature_code":"PPL",
    "gn:name":"La Joux",
    "gn:population":0,
    "gn:timezone":"Europe/Zurich",
    "iso:country":"CH",
    "wof:name":"La Joux",
    "wof:placetype":"locality"
},
  "geometry": {"coordinates":[6.94015,46.63064],"type":"Point"}
}