{
  "type": "Feature",
  "properties": {
    "gn:gn_country":"CH",
    "gn:gn_fcode":"PPL",
    "gn:gn_pop":294,
    "gn:population":294,
    "iso:country":"CH",
    "name:dut_x_preferred":[
        "Breno"
    ],
    "name:eng_x_preferred":[
        "Breno"
    ],
    "name:fre_x_preferred":[
        "Breno"
    ],
    "name:ger_x_preferred":[
        "Breno"
    ],
    "name:ita_x_preferred":[
        "Breno"
    ],
    "name:lmo_x_preferred":[
        "Bren"
    ],
    "name:por_x_preferred":[
        "Breno"
    ],
    "qs_pg:aaroncc":"CH",
    "qs_pg:gn_country":"CH",
    "qs_pg:gn_fcode":"PPL",
    "qs_pg:gn_pop":294,
    "qs_pg:name":"Breno",
    "qs_pg:name_adm0":"Schweiz",
    "qs_pg:name_adm1":"Cantone Ticino",
    "qs_pg:photos":149,
    "qs_pg:photos_1k":30,
    "qs_pg:photos_9k":1,
    "qs_pg:photos_9r":3,
    "qs_pg:photos_all":149,
    "qs_pg:photos_sr":3,
    "qs_pg:pop_sr":2,
    "qs_pg:qs_pg_placetype":"locality",
    "qs_pg:qs_pg_placetype_gp":"Town",
    "qs_pg:woe_adm0":23424957,
    "woe:adm0_id":23424957,
    "woe:name_adm0":"Schweiz",
    "woe:name_adm1":"Cantone Ticino",
    "woe:placetype":"Town",
    "wof:name":"Breno",
    "wof:placetype":"locality",
    "wof:population":294
},
  "geometry": {"coordinates":[8.87,46.03225],"type":"Point"}
}