{
  "type": "Feature",
  "properties": {
    "gn:country":"CH",
    "gn:fcode":"PPL",
    "gn:population":14,
    "iso:country":"CH",
    "name:ara_x_preferred":[
        "\u0633\u0644"
    ],
    "name:bre_x_preferred":[
        "Zell"
    ],
    "name:cat_x_preferred":[
        "Zell"
    ],
    "name:ceb_x_preferred":[
        "Zell"
    ],
    "name:chv_x_preferred":[
        "\u0426\u0435\u043b\u043b\u044c"
    ],
    "name:cym_x_preferred":[
        "Zell"
    ],
    "name:deu_x_preferred":[
        "Zell ZH"
    ],
    "name:deu_x_variant":[
        "Zell"
    ],
    "name:eng_x_preferred":[
        "Zell"
    ],
    "name:epo_x_preferred":[
        "Zell ZH"
    ],
    "name:epo_x_variant":[
        "Zell"
    ],
    "name:eus_x_preferred":[
        "Zell"
    ],
    "name:fra_x_preferred":[
        "Zell"
    ],
    "name:gle_x_preferred":[
        "Zell"
    ],
    "name:gsw_x_preferred":[
        "Z\u00e4ll"
    ],
    "name:hsb_x_preferred":[
        "Zell"
    ],
    "name:hun_x_preferred":[
        "Zell"
    ],
    "name:ita_x_preferred":[
        "Zell"
    ],
    "name:kaz_x_preferred":[
        "\u0426\u0435\u043b\u043b\u044c"
    ],
    "name:lmo_x_preferred":[
        "Zell"
    ],
    "name:msa_x_preferred":[
        "Zell"
    ],
    "name:nld_x_preferred":[
        "Zell"
    ],
    "name:nno_x_preferred":[
        "Zell i Z\u00fcrich"
    ],
    "name:oci_x_preferred":[
        "Zell"
    ],
    "name:pms_x_preferred":[
        "Zell"
    ],
    "name:pol_x_preferred":[
        "Zell"
    ],
    "name:por_x_preferred":[
        "Zell"
    ],
    "name:ron_x_preferred":[
        "Zell ZH"
    ],
    "name:ron_x_variant":[
        "Zell"
    ],
    "name:rus_x_preferred":[
        "\u0426\u0435\u043b\u043b\u044c"
    ],
    "name:spa_x_preferred":[
        "Zell"
    ],
    "name:swe_x_preferred":[
        "Zell"
    ],
    "name:ukr_x_preferred":[
        "\u0426\u0435\u043b\u043b\u044c"
    ],
    "name:uzb_x_preferred":[
        "Zell"
    ],
    "name:vec_x_preferred":[
        "Zell"
    ],
    "name:vol_x_preferred":[
        "Zell"
    ],
    "name:war_x_preferred":[
        "Zell"
    ],
    "name:zho_x_preferred":[
        "\u7b56\u723e"
    ],
    "name:zho_x_variant":[
        "\u91c7\u5c14"
    ],
    "qs_pg:aaroncc":"CH",
    "qs_pg:gn_country":"CH",
    "qs_pg:gn_fcode":"PPL",
    "qs_pg:gn_pop":14,
    "qs_pg:name":"Zell",
    "qs_pg:photos_9r":0,
    "qs_pg:photos_sr":0,
    "qs_pg:pop_sr":1,
    "qs_pg:qs_pg_placetype":"locality",
    "wof:name":"Zell",
    "wof:placetype":"neighbourhood",
    "wof:population":14
},
  "geometry": {"coordinates":[8.82137,47.26013],"type":"Point"}
}