{
  "type": "Feature",
  "properties": {
    "gn:gn_country":"CH",
    "gn:gn_fcode":"PPL",
    "gn:gn_pop":1218,
    "gn:population":1218,
    "iso:country":"CH",
    "name:alb_x_preferred":[
        "Wikon"
    ],
    "name:arm_x_preferred":[
        "\u054e\u056b\u056f\u0578\u0576"
    ],
    "name:baq_x_preferred":[
        "Wikon"
    ],
    "name:cat_x_preferred":[
        "Wikon"
    ],
    "name:chi_x_preferred":[
        "\u7dad\u5b54"
    ],
    "name:chv_x_preferred":[
        "\u0412\u0438\u043a\u043e\u043d"
    ],
    "name:cze_x_preferred":[
        "Adelboden"
    ],
    "name:dut_x_preferred":[
        "Wikon"
    ],
    "name:eng_x_preferred":[
        "Wikon"
    ],
    "name:epo_x_preferred":[
        "Wikon"
    ],
    "name:fre_x_preferred":[
        "Wikon"
    ],
    "name:geo_x_preferred":[
        "\u10d5\u10d8\u10d9\u10dd\u10dc\u10d8"
    ],
    "name:ger_x_preferred":[
        "Wikon"
    ],
    "name:gsw_x_preferred":[
        "Wikon"
    ],
    "name:hun_x_preferred":[
        "Wikon"
    ],
    "name:ita_x_preferred":[
        "Wikon"
    ],
    "name:kaz_x_preferred":[
        "\u0412\u0438\u043a\u043e\u043d"
    ],
    "name:lmo_x_preferred":[
        "Wikon"
    ],
    "name:may_x_preferred":[
        "Wikon"
    ],
    "name:nno_x_preferred":[
        "Wikon"
    ],
    "name:oci_x_preferred":[
        "Wikon"
    ],
    "name:pms_x_preferred":[
        "Wikon"
    ],
    "name:por_x_preferred":[
        "Wikon"
    ],
    "name:rus_x_preferred":[
        "\u0412\u0438\u043a\u043e\u043d"
    ],
    "name:spa_x_preferred":[
        "Wikon"
    ],
    "name:uzb_x_preferred":[
        "Wikon"
    ],
    "name:vol_x_preferred":[
        "Wikon"
    ],
    "name:war_x_preferred":[
        "Wikon"
    ],
    "qs_pg:aaroncc":"CH",
    "qs_pg:gn_country":"CH",
    "qs_pg:gn_fcode":"PPL",
    "qs_pg:gn_pop":1218,
    "qs_pg:name":"Wikon",
    "qs_pg:name_adm0":"Schweiz",
    "qs_pg:name_adm1":"Kanton Luzern",
    "qs_pg:photos":10,
    "qs_pg:photos_1k":2,
    "qs_pg:photos_9k":1,
    "qs_pg:photos_9r":1,
    "qs_pg:photos_all":10,
    "qs_pg:photos_sr":1,
    "qs_pg:pop_sr":3,
    "qs_pg:qs_pg_placetype":"locality",
    "qs_pg:qs_pg_placetype_gp":"Town",
    "qs_pg:woe_adm0":23424957,
    "woe:adm0_id":23424957,
    "woe:name_adm0":"Schweiz",
    "woe:name_adm1":"Kanton Luzern",
    "woe:placetype":"Town",
    "wof:name":"Wikon",
    "wof:placetype":"locality",
    "wof:population":1218
},
  "geometry": {"coordinates":[7.96801,47.26339],"type":"Point"}
}