{
  "type": "Feature",
  "properties": {
    "iso:country":"CH",
    "name:dut_x_preferred":[
        "Gentilino"
    ],
    "name:eng_x_preferred":[
        "Gentilino"
    ],
    "name:fre_x_preferred":[
        "Gentilino"
    ],
    "name:ger_x_preferred":[
        "Gentilino"
    ],
    "name:ita_x_preferred":[
        "Gentilino"
    ],
    "name:lmo_x_preferred":[
        "Gentirin"
    ],
    "name:pnb_x_preferred":[
        "\u06af\u0646\u0679\u06cc\u0644\u06cc\u0646\u0648"
    ],
    "qs_pg:aaroncc":"CH",
    "qs_pg:name":"Gentilino",
    "qs_pg:name_adm0":"Schweiz",
    "qs_pg:name_adm1":"Cantone Ticino",
    "qs_pg:photos":452,
    "qs_pg:photos_1k":92,
    "qs_pg:photos_9k":2,
    "qs_pg:photos_9r":5,
    "qs_pg:photos_all":452,
    "qs_pg:photos_sr":7,
    "qs_pg:pop_sr":0,
    "qs_pg:qs_pg_placetype":"locality",
    "qs_pg:qs_pg_placetype_gp":"Town",
    "qs_pg:woe_adm0":23424957,
    "woe:adm0_id":23424957,
    "woe:name_adm0":"Schweiz",
    "woe:name_adm1":"Cantone Ticino",
    "woe:placetype":"Town",
    "wof:name":"Gentilino",
    "wof:placetype":"locality"
},
  "geometry": {"coordinates":[8.927807,45.992213],"type":"Point"}
}