{
  "type": "Feature",
  "properties": {
    "gn:gn_country":"CH",
    "gn:gn_fcode":"PPL",
    "gn:gn_pop":1232,
    "gn:population":1232,
    "iso:country":"CH",
    "name:cat_x_preferred":[
        "Stalden"
    ],
    "name:deu_x_preferred":[
        "Stalden VS"
    ],
    "name:deu_x_variant":[
        "Stalden"
    ],
    "name:eng_x_preferred":[
        "Stalden"
    ],
    "name:epo_x_preferred":[
        "Stalden VS"
    ],
    "name:eus_x_preferred":[
        "Stalden"
    ],
    "name:fra_x_preferred":[
        "Stalden"
    ],
    "name:hun_x_preferred":[
        "Stalden"
    ],
    "name:ita_x_preferred":[
        "Stalden"
    ],
    "name:lmo_x_preferred":[
        "Stalden"
    ],
    "name:msa_x_preferred":[
        "Stalden"
    ],
    "name:nld_x_preferred":[
        "Stalden"
    ],
    "name:nno_x_preferred":[
        "Stalden"
    ],
    "name:oci_x_preferred":[
        "Stalden"
    ],
    "name:pms_x_preferred":[
        "Stalden"
    ],
    "name:por_x_preferred":[
        "Stalden"
    ],
    "name:roh_x_preferred":[
        "Stalden"
    ],
    "name:spa_x_preferred":[
        "Stalden"
    ],
    "name:sqi_x_preferred":[
        "Stalden"
    ],
    "name:swe_x_preferred":[
        "Stalden"
    ],
    "name:vol_x_preferred":[
        "Stalden"
    ],
    "name:war_x_preferred":[
        "Stalden"
    ],
    "name:zho_x_preferred":[
        "\u65bd\u5854\u723e\u767b"
    ],
    "qs_pg:aaroncc":"CH",
    "qs_pg:gn_country":"CH",
    "qs_pg:gn_fcode":"PPL",
    "qs_pg:gn_pop":1232,
    "qs_pg:name":"Stalden",
    "qs_pg:name_adm0":"Schweiz",
    "qs_pg:name_adm1":"Canton de Valais",
    "qs_pg:photos":330,
    "qs_pg:photos_1k":67,
    "qs_pg:photos_9k":1,
    "qs_pg:photos_9r":5,
    "qs_pg:photos_all":330,
    "qs_pg:photos_sr":5,
    "qs_pg:pop_sr":3,
    "qs_pg:qs_pg_placetype":"locality",
    "qs_pg:qs_pg_placetype_gp":"Town",
    "qs_pg:woe_adm0":23424957,
    "woe:adm0_id":23424957,
    "woe:name_adm0":"Schweiz",
    "woe:name_adm1":"Canton de Valais",
    "woe:placetype":"Town",
    "wof:name":"Stalden",
    "wof:placetype":"locality",
    "wof:population":1232
},
  "geometry": {"coordinates":[7.87273,46.23341],"type":"Point"}
}