{
  "type": "Feature",
  "properties": {
    "gn:admin1_code":"AR",
    "gn:admin2_code":"1501.0",
    "gn:admin3_code":"3005.0",
    "gn:asciiname":"Nord",
    "gn:country_code":"CH",
    "gn:dem":797,
    "gn:feature_class":"P",
    "gn:feature_code":"PPLL",
    "gn:name":"Nord",
    "gn:population":0,
    "gn:timezone":"Europe/Zurich",
    "iso:country":"CH",
    "name:deu_x_preferred":[
        "Nord"
    ],
    "wof:name":"Nord",
    "wof:placetype":"neighbourhood"
},
  "geometry": {"coordinates":[9.33242,47.38352],"type":"Point"}
}