{
  "type": "Feature",
  "properties": {
    "iso:country":"CH",
    "name:deu_x_preferred":[
        "Herrenschwanden"
    ],
    "qs:gn_fcode":"PPL",
    "qs:gn_local":0,
    "qs:gn_namadm1":"BE",
    "qs:gn_name":"Herrenschwanden",
    "qs:local_max":130,
    "qs:local_sum":130,
    "qs:localhoods":1,
    "qs:name":"Herrenschwanden",
    "qs:name_adm0":"Schweiz",
    "qs:name_adm1":"Kanton Bern",
    "qs:name_adm2":"Bern-Mittelland",
    "qs:name_lau":"Kirchlindach",
    "qs:name_local":"Kirchlindach",
    "qs:photo_max":78,
    "qs:photo_sum":130,
    "qs:placetype":"Suburb",
    "qs:quad_count":14,
    "qs:woe_adm0":23424957,
    "qs:woe_adm1":2347087,
    "qs:woe_adm2":56558125,
    "qs:woe_lau":12683041,
    "qs:woe_local":12683041,
    "qs:woe_ver":"7.10.0",
    "wof:name":"Herrenschwanden",
    "wof:placetype":"neighbourhood"
},
  "geometry": {"coordinates":[7.414926,46.979532],"type":"Point"}
}