{
  "type": "Feature",
  "properties": {
    "gn:gn_country":"CH",
    "gn:gn_fcode":"PPL",
    "gn:gn_pop":0,
    "iso:country":"CH",
    "name:deu_x_preferred":[
        "Niederwil SG"
    ],
    "name:unk_x_variant":[
        "Niederwil"
    ],
    "qs_pg:aaroncc":"CH",
    "qs_pg:gn_country":"CH",
    "qs_pg:gn_fcode":"PPL",
    "qs_pg:gn_pop":0,
    "qs_pg:name":"Niederwil bei Gossau",
    "qs_pg:name_adm0":"Schweiz",
    "qs_pg:name_adm1":"Kanton St. Gallen",
    "qs_pg:photos":38,
    "qs_pg:photos_1k":8,
    "qs_pg:photos_9k":1,
    "qs_pg:photos_9r":2,
    "qs_pg:photos_all":38,
    "qs_pg:photos_sr":2,
    "qs_pg:pop_sr":0,
    "qs_pg:qs_pg_placetype":"locality",
    "qs_pg:qs_pg_placetype_gp":"Town",
    "qs_pg:woe_adm0":23424957,
    "woe:adm0_id":23424957,
    "woe:name_adm0":"Schweiz",
    "woe:name_adm1":"Kanton St. Gallen",
    "woe:placetype":"Town",
    "wof:name":"Niederwil bei Gossau",
    "wof:placetype":"neighbourhood"
},
  "geometry": {"coordinates":[9.19917,47.43957],"type":"Point"}
}