{
  "type": "Feature",
  "properties": {
    "gn:admin1_code":"BE",
    "gn:admin2_code":"245.0",
    "gn:admin3_code":"957.0",
    "gn:asciiname":"Buchegghaus",
    "gn:country_code":"CH",
    "gn:dem":1035,
    "gn:feature_class":"P",
    "gn:feature_code":"PPLL",
    "gn:name":"Buchegghaus",
    "gn:population":0,
    "gn:timezone":"Europe/Zurich",
    "iso:country":"CH",
    "name:deu_x_preferred":[
        "Buchegghaus"
    ],
    "wof:name":"Buchegghaus",
    "wof:placetype":"neighbourhood"
},
  "geometry": {"coordinates":[7.87164,47.03699],"type":"Point"}
}