{
  "type": "Feature",
  "properties": {
    "gn:gn_country":"CH",
    "gn:gn_fcode":"PPL",
    "gn:gn_pop":897,
    "gn:population":897,
    "iso:country":"CH",
    "name:ara_x_preferred":[
        "\u0641\u0627\u064a\u062a\u0627\u062e"
    ],
    "name:cat_x_preferred":[
        "Weiach"
    ],
    "name:chv_x_preferred":[
        "\u0412\u0430\u0439\u0430\u0445"
    ],
    "name:deu_x_preferred":[
        "Weiach"
    ],
    "name:eng_x_preferred":[
        "Weiach"
    ],
    "name:epo_x_preferred":[
        "Weiach"
    ],
    "name:eus_x_preferred":[
        "Weiach"
    ],
    "name:fra_x_preferred":[
        "Weiach"
    ],
    "name:gsw_x_preferred":[
        "Weich"
    ],
    "name:hun_x_preferred":[
        "Weiach"
    ],
    "name:ita_x_preferred":[
        "Weiach"
    ],
    "name:kaz_x_preferred":[
        "\u0412\u0430\u0439\u0430\u0445"
    ],
    "name:lmo_x_preferred":[
        "Weiach"
    ],
    "name:msa_x_preferred":[
        "Weiach"
    ],
    "name:nld_x_preferred":[
        "Weiach"
    ],
    "name:nno_x_preferred":[
        "Weiach"
    ],
    "name:oci_x_preferred":[
        "Weiach"
    ],
    "name:pol_x_preferred":[
        "Weiach"
    ],
    "name:ron_x_preferred":[
        "Weiach"
    ],
    "name:rus_x_preferred":[
        "\u0412\u0430\u0439\u0430\u0445"
    ],
    "name:uzb_x_preferred":[
        "Weiach"
    ],
    "name:vol_x_preferred":[
        "Weiach"
    ],
    "name:war_x_preferred":[
        "Weiach"
    ],
    "name:zho_x_preferred":[
        "\u9b4f\u963f\u8d6b"
    ],
    "qs_pg:aaroncc":"CH",
    "qs_pg:gn_country":"CH",
    "qs_pg:gn_fcode":"PPL",
    "qs_pg:gn_pop":897,
    "qs_pg:name":"Weiach",
    "qs_pg:name_adm0":"Schweiz",
    "qs_pg:name_adm1":"Kanton Z\u00fcrich",
    "qs_pg:photos":164,
    "qs_pg:photos_1k":33,
    "qs_pg:photos_9k":1,
    "qs_pg:photos_9r":4,
    "qs_pg:photos_all":164,
    "qs_pg:photos_sr":4,
    "qs_pg:pop_sr":2,
    "qs_pg:qs_pg_placetype":"locality",
    "qs_pg:qs_pg_placetype_gp":"Town",
    "qs_pg:woe_adm0":23424957,
    "woe:adm0_id":23424957,
    "woe:name_adm0":"Schweiz",
    "woe:name_adm1":"Kanton Z\u00fcrich",
    "woe:placetype":"Town",
    "wof:name":"Weiach",
    "wof:placetype":"locality",
    "wof:population":897
},
  "geometry": {"coordinates":[8.43344,47.55908],"type":"Point"}
}