{
  "type": "Feature",
  "properties": {
    "gn:admin1_code":"AG",
    "gn:admin2_code":"1911.0",
    "gn:admin3_code":"4323.0",
    "gn:asciiname":"Achenberg",
    "gn:country_code":"CH",
    "gn:dem":507,
    "gn:feature_class":"P",
    "gn:feature_code":"PPL",
    "gn:name":"Achenberg",
    "gn:population":0,
    "gn:timezone":"Europe/Zurich",
    "iso:country":"CH",
    "name:deu_x_preferred":[
        "Acheberg"
    ],
    "wof:name":"Achenberg",
    "wof:placetype":"locality"
},
  "geometry": {"coordinates":[8.27558,47.58518],"type":"Point"}
}