{
  "type": "Feature",
  "properties": {
    "gn:gn_country":"CH",
    "gn:gn_fcode":"PPL",
    "gn:gn_pop":1100,
    "gn:population":1100,
    "iso:country":"CH",
    "name:baq_x_preferred":[
        "Aire-la-Ville"
    ],
    "name:cat_x_preferred":[
        "Aire-la-Ville"
    ],
    "name:chi_x_preferred":[
        "\u827e\u5c14\u62c9\u7ef4\u5c14"
    ],
    "name:dut_x_preferred":[
        "Aire-la-Ville"
    ],
    "name:eng_x_preferred":[
        "Aire-la-Ville"
    ],
    "name:epo_x_preferred":[
        "Aire-la-Ville"
    ],
    "name:fre_x_preferred":[
        "Aire-la-Ville"
    ],
    "name:ger_x_preferred":[
        "Aire-la-Ville"
    ],
    "name:gsw_x_preferred":[
        "Aire-la-Ville"
    ],
    "name:hun_x_preferred":[
        "Aire-la-Ville"
    ],
    "name:ita_x_preferred":[
        "Aire-la-Ville"
    ],
    "name:jpn_x_preferred":[
        "\u30a8\u30eb\uff1d\u30e9\uff1d\u30f4\u30a3\u30eb"
    ],
    "name:lat_x_preferred":[
        "Aeria Villa"
    ],
    "name:lmo_x_preferred":[
        "Aire-la-Ville"
    ],
    "name:may_x_preferred":[
        "Aire-la-Ville"
    ],
    "name:nno_x_preferred":[
        "Aire-la-Ville"
    ],
    "name:oci_x_preferred":[
        "Aire-la-Ville"
    ],
    "name:por_x_preferred":[
        "Aire-la-Ville"
    ],
    "name:roh_x_preferred":[
        "Aire-la-Ville"
    ],
    "name:rus_x_preferred":[
        "\u042d\u0440-\u043b\u0430-\u0412\u0438\u043b\u044c"
    ],
    "name:spa_x_preferred":[
        "Aire-la-Ville"
    ],
    "name:swe_x_preferred":[
        "Aire-la-Ville"
    ],
    "name:vie_x_preferred":[
        "Aire-la-Ville"
    ],
    "name:vol_x_preferred":[
        "Aire-la-Ville"
    ],
    "name:war_x_preferred":[
        "Aire-la-Ville"
    ],
    "name:zho_x_preferred":[
        "\u827e\u5c14\u62c9\u7ef4\u5c14"
    ],
    "qs_pg:aaroncc":"CH",
    "qs_pg:gn_country":"CH",
    "qs_pg:gn_fcode":"PPL",
    "qs_pg:gn_pop":1100,
    "qs_pg:name":"Aire-la-Ville",
    "qs_pg:name_adm0":"Schweiz",
    "qs_pg:name_adm1":"Canton de Gen\u00e8ve",
    "qs_pg:photos":359,
    "qs_pg:photos_1k":73,
    "qs_pg:photos_9k":2,
    "qs_pg:photos_9r":5,
    "qs_pg:photos_all":359,
    "qs_pg:photos_sr":6,
    "qs_pg:pop_sr":3,
    "qs_pg:qs_pg_placetype":"locality",
    "qs_pg:qs_pg_placetype_gp":"Town",
    "qs_pg:woe_adm0":23424957,
    "woe:adm0_id":23424957,
    "woe:name_adm0":"Schweiz",
    "woe:name_adm1":"Canton de Gen\u00e8ve",
    "woe:placetype":"Town",
    "wof:name":"Aire-la-Ville",
    "wof:placetype":"locality",
    "wof:population":1100
},
  "geometry": {"coordinates":[6.04287,46.19057],"type":"Point"}
}