{
  "type": "Feature",
  "properties": {
    "gn:admin1_code":"SG",
    "gn:admin2_code":"1722.0",
    "gn:admin3_code":"3214.0",
    "gn:asciiname":"Hueb",
    "gn:country_code":"CH",
    "gn:dem":551,
    "gn:elevation":"548.0",
    "gn:feature_class":"P",
    "gn:feature_code":"PPL",
    "gn:name":"Hueb",
    "gn:population":0,
    "gn:timezone":"Europe/Zurich",
    "iso:country":"CH",
    "wof:name":"Hueb",
    "wof:placetype":"neighbourhood"
},
  "geometry": {"coordinates":[9.41713,47.47467],"type":"Point"}
}