{
  "type": "Feature",
  "properties": {
    "gn:admin1_code":"TI",
    "gn:admin2_code":"2105.0",
    "gn:admin3_code":"5202.0",
    "gn:asciiname":"Genestraio",
    "gn:country_code":"CH",
    "gn:dem":308,
    "gn:feature_class":"P",
    "gn:feature_code":"PPL",
    "gn:name":"Genestraio",
    "gn:population":0,
    "gn:timezone":"Europe/Rome",
    "iso:country":"CH",
    "name:ita_x_preferred":[
        "Genestraio"
    ],
    "wof:name":"Genestraio",
    "wof:placetype":"locality"
},
  "geometry": {"coordinates":[8.80063,45.99341],"type":"Point"}
}