{
  "type": "Feature",
  "properties": {
    "gn:admin1_code":"SG",
    "gn:admin2_code":"1725.0",
    "gn:admin3_code":"3293.0",
    "gn:asciiname":"Weisstannen",
    "gn:country_code":"CH",
    "gn:dem":997,
    "gn:feature_class":"P",
    "gn:feature_code":"PPL",
    "gn:name":"Weisstannen",
    "gn:population":0,
    "gn:timezone":"Europe/Zurich",
    "iso:country":"CH",
    "wof:name":"Weisstannen",
    "wof:placetype":"locality"
},
  "geometry": {"coordinates":[9.34258,46.99108],"type":"Point"}
}