{
  "type": "Feature",
  "properties": {
    "gn:gn_country":"CH",
    "gn:gn_fcode":"PPL",
    "gn:gn_pop":0,
    "iso:country":"CH",
    "name:ita_x_preferred":[
        "S. Antonio (Val Morobbia)"
    ],
    "name:unk_x_variant":[
        "Sant\u2019Antonio"
    ],
    "qs_pg:aaroncc":"CH",
    "qs_pg:gn_country":"CH",
    "qs_pg:gn_fcode":"PPL",
    "qs_pg:gn_pop":0,
    "qs_pg:name":"Sant'antonio",
    "qs_pg:name_adm0":"Italia",
    "qs_pg:name_adm1":"Lombardia",
    "qs_pg:photos":42,
    "qs_pg:photos_1k":9,
    "qs_pg:photos_9k":1,
    "qs_pg:photos_9r":2,
    "qs_pg:photos_all":42,
    "qs_pg:photos_sr":2,
    "qs_pg:pop_sr":0,
    "qs_pg:qs_pg_placetype":"locality",
    "qs_pg:qs_pg_placetype_gp":"Town",
    "qs_pg:woe_adm0":23424853,
    "woe:adm0_id":23424853,
    "woe:name_adm0":"Italia",
    "woe:name_adm1":"Lombardia",
    "woe:placetype":"Town",
    "wof:name":"Sant'antonio",
    "wof:placetype":"locality"
},
  "geometry": {"coordinates":[9.08078,46.17022],"type":"Point"}
}