{
  "type": "Feature",
  "properties": {
    "gn:admin1_code":"TI",
    "gn:admin2_code":"2105.0",
    "gn:admin3_code":"5226.0",
    "gn:asciiname":"Rove",
    "gn:country_code":"CH",
    "gn:dem":985,
    "gn:feature_class":"P",
    "gn:feature_code":"PPL",
    "gn:name":"Rov\u00e8",
    "gn:population":0,
    "gn:timezone":"Europe/Zurich",
    "iso:country":"CH",
    "name:ita_x_preferred":[
        "Rov\u00e8"
    ],
    "wof:name":"Rove",
    "wof:placetype":"neighbourhood"
},
  "geometry": {"coordinates":[8.9615,46.09815],"type":"Point"}
}