{
  "type": "Feature",
  "properties": {
    "gn:admin1_code":"TI",
    "gn:admin2_code":"2105.0",
    "gn:admin3_code":"5226.0",
    "gn:asciiname":"Rove",
    "gn:country_code":"CH",
    "gn:dem":985,
    "gn:feature_class":"P",
    "gn:feature_code":"PPL",
    "gn:name":"Rov\u00e8",
    "gn:population":0,
    "gn:timezone":"Europe/Zurich",
    "iso:country":"CH",
    "name:bos_x_preferred":[
        "Rove"
    ],
    "name:ceb_x_preferred":[
        "Rove"
    ],
    "name:deu_x_preferred":[
        "Rove"
    ],
    "name:fra_x_preferred":[
        "Rove"
    ],
    "name:heb_x_preferred":[
        "\u05e8\u05d5\u05d1"
    ],
    "name:hrv_x_preferred":[
        "Rove"
    ],
    "name:ita_x_preferred":[
        "Rov\u00e8"
    ],
    "name:nld_x_preferred":[
        "Rove"
    ],
    "name:rus_x_preferred":[
        "\u0420\u043e\u0443\u0432"
    ],
    "name:slv_x_preferred":[
        "Rove"
    ],
    "wof:lang_x_official":[
        "deu",
        "fra",
        "gsw",
        "ita"
    ],
    "wof:lang_x_spoken":[
        "deu",
        "fra",
        "gsw",
        "ita",
        "roh"
    ],
    "wof:name":"Rove",
    "wof:placetype":"neighbourhood"
},
  "geometry": {"coordinates":[8.9615,46.09815],"type":"Point"}
}