{
  "type": "Feature",
  "properties": {
    "gn:admin1_code":"BE",
    "gn:admin2_code":"245.0",
    "gn:admin3_code":"424.0",
    "gn:asciiname":"Hubli",
    "gn:country_code":"CH",
    "gn:dem":681,
    "gn:feature_class":"P",
    "gn:feature_code":"PPLL",
    "gn:name":"Hubli",
    "gn:population":0,
    "gn:timezone":"Europe/Zurich",
    "iso:country":"CH",
    "name:deu_x_preferred":[
        "Hubli"
    ],
    "wof:name":"Hubli",
    "wof:placetype":"neighbourhood"
},
  "geometry": {"coordinates":[7.69691,47.11561],"type":"Point"}
}