{
  "type": "Feature",
  "properties": {
    "gn:admin1_code":"BE",
    "gn:admin2_code":"245.0",
    "gn:admin3_code":"424.0",
    "gn:asciiname":"Hubli",
    "gn:country_code":"CH",
    "gn:dem":681,
    "gn:feature_class":"P",
    "gn:feature_code":"PPLL",
    "gn:name":"Hubli",
    "gn:population":0,
    "gn:timezone":"Europe/Zurich",
    "iso:country":"CH",
    "name:afr_x_preferred":[
        "Hubli-Dharwad"
    ],
    "name:ara_x_preferred":[
        "\u0647\u0648\u0628\u0644\u064a"
    ],
    "name:azb_x_preferred":[
        "\u0647\u0648\u0628\u0644\u06cc -\u062f\u0627\u0631\u0648\u062f\u0627"
    ],
    "name:ben_x_preferred":[
        "\u09b9\u09c1\u09ac\u09b2\u09bf"
    ],
    "name:bpy_x_preferred":[
        "\u09b9\u09c1\u09ac\u09b2\u09bf-\u09a7\u09be\u09b0\u09f1\u09be\u09a6"
    ],
    "name:cat_x_preferred":[
        "Huballi"
    ],
    "name:ceb_x_preferred":[
        "Hubli"
    ],
    "name:ces_x_preferred":[
        "Hubl\u00ed-Dh\u00e1rv\u00e1d"
    ],
    "name:deu_x_preferred":[
        "Hubli"
    ],
    "name:deu_x_variant":[
        "Hubli-Dharwad"
    ],
    "name:epo_x_preferred":[
        "Hubli"
    ],
    "name:fas_x_preferred":[
        "\u0647\u0648\u0628\u0644\u06cc -\u062f\u0627\u0631\u0648\u062f\u0627"
    ],
    "name:hin_x_preferred":[
        "\u0939\u0941\u092c\u0932\u0940"
    ],
    "name:hun_x_preferred":[
        "Hubli"
    ],
    "name:ita_x_preferred":[
        "Hubli-Dharwad"
    ],
    "name:kan_x_preferred":[
        "\u0cb9\u0cc1\u0cac\u0ccd\u0cac\u0cb3\u0ccd\u0cb3\u0cbf"
    ],
    "name:kat_x_preferred":[
        "\u10f0\u10e3\u10d1\u10da\u10d8"
    ],
    "name:kor_x_preferred":[
        "\ud6c4\ube14\ub9ac"
    ],
    "name:mal_x_preferred":[
        "\u0d39\u0d41\u0d2c\u0d4d\u0d32\u0d3f"
    ],
    "name:mar_x_preferred":[
        "\u0939\u0941\u092c\u0933\u0940"
    ],
    "name:nep_x_preferred":[
        "\u0939\u0941\u092c\u0932\u0940"
    ],
    "name:new_x_preferred":[
        "\u0939\u0941\u092c\u094d\u0932\u0940-\u0927\u093e\u0930\u0935\u093e\u0926"
    ],
    "name:nor_x_preferred":[
        "Hubli-Dharwad"
    ],
    "name:ori_x_preferred":[
        "\u0b39\u0b41\u0b2c\u0b33\u0b3f"
    ],
    "name:pam_x_preferred":[
        "Hubballi"
    ],
    "name:pnb_x_preferred":[
        "\u06c1\u0628\u0644\u06cc"
    ],
    "name:pol_x_preferred":[
        "Hubballi-Dharwar"
    ],
    "name:por_x_preferred":[
        "Hubli"
    ],
    "name:ron_x_preferred":[
        "Hubli-Dharwad"
    ],
    "name:rus_x_preferred":[
        "\u0425\u0443\u0431\u043b\u0438-\u0414\u0445\u0430\u0440\u0432\u0430\u0434"
    ],
    "name:san_x_preferred":[
        "\u0939\u0941\u092c\u094d\u092c\u0933\u094d\u0933\u0940"
    ],
    "name:spa_x_preferred":[
        "Hubli"
    ],
    "name:srp_x_preferred":[
        "\u0425\u0443\u0431\u043b\u0438-\u0414\u0430\u0440\u0432\u0430\u0434"
    ],
    "name:swe_x_preferred":[
        "Hubballi-Dharwad"
    ],
    "name:tam_x_preferred":[
        "\u0bb9\u0bc2\u0baa\u0bcd\u0bb3\u0bbf"
    ],
    "name:tel_x_preferred":[
        "\u0c39\u0c41\u0c2c\u0c4d\u0c2c\u0c33\u0c4d\u0c32\u0c3f"
    ],
    "name:urd_x_preferred":[
        "\u06c1\u0648\u0628\u0644\u06cc"
    ],
    "name:vie_x_preferred":[
        "Hubli"
    ],
    "name:war_x_preferred":[
        "Hubli-Dharwad"
    ],
    "name:zho_x_preferred":[
        "\u80e1\u5e03\u5229"
    ],
    "wof:name":"Hubli",
    "wof:placetype":"neighbourhood"
},
  "geometry": {"coordinates":[7.69691,47.11561],"type":"Point"}
}