{
  "type": "Feature",
  "properties": {
    "gn:country":"CH",
    "gn:fcode":"PPLL",
    "gn:population":11,
    "iso:country":"CH",
    "qs_pg:aaroncc":"CH",
    "qs_pg:gn_country":"CH",
    "qs_pg:gn_fcode":"PPLL",
    "qs_pg:gn_pop":11,
    "qs_pg:name":"Tobelm\u00fcli",
    "qs_pg:photos_9r":0,
    "qs_pg:photos_sr":0,
    "qs_pg:pop_sr":1,
    "qs_pg:qs_pg_placetype":"locality",
    "wof:name":"Tobelm\u00fcli",
    "wof:placetype":"neighbourhood",
    "wof:population":11
},
  "geometry": {"coordinates":[8.62979,47.3212],"type":"Point"}
}