{
  "type": "Feature",
  "properties": {
    "gn:admin1_code":"GR",
    "gn:admin2_code":"1850.0",
    "gn:admin3_code":"3672.0",
    "gn:asciiname":"Piaenetsch",
    "gn:country_code":"CH",
    "gn:dem":2050,
    "gn:feature_class":"P",
    "gn:feature_code":"PPL",
    "gn:name":"Pi\u00e4netsch",
    "gn:population":0,
    "gn:timezone":"Europe/Zurich",
    "iso:country":"CH",
    "name:roh_x_preferred":[
        "Pi\u00e4netsch"
    ],
    "wof:lang_x_official":[
        "deu",
        "fra",
        "gsw",
        "ita"
    ],
    "wof:lang_x_spoken":[
        "deu",
        "fra",
        "gsw",
        "ita",
        "roh"
    ],
    "wof:name":"Piaenetsch",
    "wof:placetype":"neighbourhood"
},
  "geometry": {"coordinates":[9.27284,46.60166],"type":"Point"}
}