{
  "type": "Feature",
  "properties": {
    "gn:admin1_code":"BE",
    "gn:admin2_code":"249.0",
    "gn:admin3_code":"762.0",
    "gn:asciiname":"Schwarzeberg",
    "gn:country_code":"CH",
    "gn:dem":1491,
    "gn:feature_class":"P",
    "gn:feature_code":"PPL",
    "gn:name":"Schwarzeberg",
    "gn:population":0,
    "gn:timezone":"Europe/Zurich",
    "iso:country":"CH",
    "name:deu_x_preferred":[
        "Schwarzeberg"
    ],
    "wof:name":"Schwarzeberg",
    "wof:placetype":"neighbourhood"
},
  "geometry": {"coordinates":[7.54491,46.59885],"type":"Point"}
}