{
  "type": "Feature",
  "properties": {
    "gn:admin1_code":"BE",
    "gn:admin2_code":"250.0",
    "gn:admin3_code":"584.0",
    "gn:asciiname":"Schmitsmatte",
    "gn:country_code":"CH",
    "gn:dem":740,
    "gn:feature_class":"P",
    "gn:feature_code":"PPL",
    "gn:name":"Schmitsmatte",
    "gn:population":0,
    "gn:timezone":"Europe/Zurich",
    "iso:country":"CH",
    "name:deu_x_preferred":[
        "Schmitsmatte"
    ],
    "wof:name":"Schmitsmatte",
    "wof:placetype":"neighbourhood"
},
  "geometry": {"coordinates":[7.90505,46.60646],"type":"Point"}
}