{
  "type": "Feature",
  "properties": {
    "gn:country":"CH",
    "gn:fcode":"PPLX",
    "gn:population":10428,
    "iso:country":"CH",
    "name:eng_x_preferred":[
        "Kirch-Uster"
    ],
    "name:eng_x_variant":[
        "Uster / Kirch-Uster"
    ],
    "qs_pg:aaroncc":"CH",
    "qs_pg:gn_country":"CH",
    "qs_pg:gn_fcode":"PPLX",
    "qs_pg:gn_pop":10428,
    "qs_pg:name":"Uster / Kirch-Uster",
    "qs_pg:photos_9r":0,
    "qs_pg:photos_sr":0,
    "qs_pg:pop_sr":6,
    "qs_pg:qs_pg_placetype":"neighbourhood",
    "wof:lang_x_official":[
        "deu",
        "fra",
        "gsw",
        "ita"
    ],
    "wof:lang_x_spoken":[
        "deu",
        "fra",
        "gsw",
        "ita",
        "roh"
    ],
    "wof:name":"Kirch-Uster",
    "wof:placetype":"neighbourhood",
    "wof:population":10428
},
  "geometry": {"coordinates":[8.71839,47.34579],"type":"Point"}
}