{
  "type": "Feature",
  "properties": {
    "gn:gn_country":"CH",
    "gn:gn_fcode":"PPLX",
    "gn:gn_pop":10428,
    "gn:population":10428,
    "iso:country":"CH",
    "name:unk_x_variant":[
        "Kirch-Uster"
    ],
    "qs_pg:aaroncc":"CH",
    "qs_pg:gn_country":"CH",
    "qs_pg:gn_fcode":"PPLX",
    "qs_pg:gn_pop":10428,
    "qs_pg:name":"Uster / Kirch-Uster",
    "qs_pg:photos_9r":0,
    "qs_pg:photos_sr":0,
    "qs_pg:pop_sr":6,
    "qs_pg:qs_pg_placetype":"neighbourhood",
    "wof:name":"Uster / Kirch-Uster",
    "wof:placetype":"neighbourhood",
    "wof:population":10428
},
  "geometry": {"coordinates":[8.71839,47.34579],"type":"Point"}
}