{
  "type": "Feature",
  "properties": {
    "gn:admin1_code":"AG",
    "gn:admin2_code":"1908.0",
    "gn:admin3_code":"4229.0",
    "gn:asciiname":"Buenzen",
    "gn:country_code":"CH",
    "gn:dem":439,
    "gn:feature_class":"P",
    "gn:feature_code":"PPL",
    "gn:name":"B\u00fcnzen",
    "gn:population":0,
    "gn:timezone":"Europe/Zurich",
    "iso:country":"CH",
    "wof:name":"Buenzen",
    "wof:placetype":"locality"
},
  "geometry": {"coordinates":[8.32384,47.30977],"type":"Point"}
}