{
  "type": "Feature",
  "properties": {
    "gn:admin1_code":"SG",
    "gn:admin2_code":"1725.0",
    "gn:admin3_code":"3298.0",
    "gn:asciiname":"Buechel",
    "gn:country_code":"CH",
    "gn:dem":1487,
    "gn:feature_class":"P",
    "gn:feature_code":"PPLL",
    "gn:name":"B\u00fcchel",
    "gn:population":0,
    "gn:timezone":"Europe/Zurich",
    "iso:country":"CH",
    "name:ceb_x_preferred":[
        "Buechel"
    ],
    "name:deu_x_preferred":[
        "B\u00fcchel"
    ],
    "name:swe_x_preferred":[
        "Buechel"
    ],
    "wof:name":"Buechel",
    "wof:placetype":"neighbourhood"
},
  "geometry": {"coordinates":[9.36249,47.11792],"type":"Point"}
}