{
  "type": "Feature",
  "properties": {
    "gn:gn_country":"CH",
    "gn:gn_fcode":"PPL",
    "gn:gn_pop":0,
    "iso:country":"CH",
    "name:alb_x_preferred":[
        "Venth\u00f4ne"
    ],
    "name:baq_x_preferred":[
        "Venth\u00f4ne"
    ],
    "name:cat_x_preferred":[
        "Venth\u00f4ne"
    ],
    "name:chi_x_preferred":[
        "\u65fa\u6258\u8a25"
    ],
    "name:dut_x_preferred":[
        "Venth\u00f4ne"
    ],
    "name:eng_x_preferred":[
        "Venth\u00f4ne"
    ],
    "name:epo_x_preferred":[
        "Venth\u00f4ne"
    ],
    "name:fre_x_preferred":[
        "Venth\u00f4ne"
    ],
    "name:ger_x_preferred":[
        "Venth\u00f4ne"
    ],
    "name:hun_x_preferred":[
        "Venth\u00f4ne"
    ],
    "name:ita_x_preferred":[
        "Venth\u00f4ne"
    ],
    "name:lmo_x_preferred":[
        "Venth\u00f4ne"
    ],
    "name:may_x_preferred":[
        "Venth\u00f4ne"
    ],
    "name:nno_x_preferred":[
        "Venth\u00f4ne"
    ],
    "name:oci_x_preferred":[
        "Venth\u00f4ne"
    ],
    "name:pms_x_preferred":[
        "Venth\u00f4ne"
    ],
    "name:por_x_preferred":[
        "Venth\u00f4ne"
    ],
    "name:roh_x_preferred":[
        "Venth\u00f4ne"
    ],
    "name:spa_x_preferred":[
        "Venth\u00f4ne"
    ],
    "name:swe_x_preferred":[
        "Venth\u00f4ne"
    ],
    "name:vol_x_preferred":[
        "Venth\u00f4ne"
    ],
    "name:war_x_preferred":[
        "Venth\u00f4ne"
    ],
    "qs_pg:aaroncc":"CH",
    "qs_pg:gn_country":"CH",
    "qs_pg:gn_fcode":"PPL",
    "qs_pg:gn_pop":0,
    "qs_pg:name":"Venth\u00f4ne",
    "qs_pg:name_adm0":"Schweiz",
    "qs_pg:name_adm1":"Canton de Valais",
    "qs_pg:photos":40,
    "qs_pg:photos_1k":8,
    "qs_pg:photos_9k":1,
    "qs_pg:photos_9r":2,
    "qs_pg:photos_all":40,
    "qs_pg:photos_sr":2,
    "qs_pg:pop_sr":0,
    "qs_pg:qs_pg_placetype":"locality",
    "qs_pg:qs_pg_placetype_gp":"Town",
    "qs_pg:woe_adm0":23424957,
    "woe:adm0_id":23424957,
    "woe:name_adm0":"Schweiz",
    "woe:name_adm1":"Canton de Valais",
    "woe:placetype":"Town",
    "wof:name":"Venth\u00f4ne",
    "wof:placetype":"locality"
},
  "geometry": {"coordinates":[7.52924,46.30665],"type":"Point"}
}