{
  "type": "Feature",
  "properties": {
    "gn:admin1_code":"TI",
    "gn:admin2_code":"2105.0",
    "gn:admin3_code":"5178.0",
    "gn:asciiname":"Purasca",
    "gn:country_code":"CH",
    "gn:dem":354,
    "gn:feature_class":"P",
    "gn:feature_code":"PPL",
    "gn:name":"Purasca",
    "gn:population":0,
    "gn:timezone":"Europe/Zurich",
    "iso:country":"CH",
    "wof:name":"Purasca",
    "wof:placetype":"locality"
},
  "geometry": {"coordinates":[8.85101,45.97745],"type":"Point"}
}