{
  "type": "Feature",
  "properties": {
    "gn:country":"CH",
    "gn:fcode":"PPLL",
    "gn:population":12,
    "iso:country":"CH",
    "name:ara_x_preferred":[
        "\u0647\u064a\u0646\u062a\u064a\u0631\u064a\u063a"
    ],
    "name:ceb_x_preferred":[
        "Hinteregg"
    ],
    "name:swe_x_preferred":[
        "Hinteregg"
    ],
    "qs_pg:aaroncc":"CH",
    "qs_pg:gn_country":"CH",
    "qs_pg:gn_fcode":"PPLL",
    "qs_pg:gn_pop":12,
    "qs_pg:name":"Hinteregg",
    "qs_pg:photos_9r":0,
    "qs_pg:photos_sr":0,
    "qs_pg:pop_sr":1,
    "qs_pg:qs_pg_placetype":"locality",
    "wof:name":"Hinteregg",
    "wof:placetype":"neighbourhood",
    "wof:population":12
},
  "geometry": {"coordinates":[8.79006,47.53335],"type":"Point"}
}