{
  "type": "Feature",
  "properties": {
    "gn:admin1_code":"SG",
    "gn:admin2_code":"1727.0",
    "gn:admin3_code":"3359.0",
    "gn:asciiname":"Starkenbach",
    "gn:country_code":"CH",
    "gn:dem":888,
    "gn:elevation":"891.0",
    "gn:feature_class":"P",
    "gn:feature_code":"PPL",
    "gn:name":"Starkenbach",
    "gn:population":0,
    "gn:timezone":"Europe/Zurich",
    "iso:country":"CH",
    "wof:name":"Starkenbach",
    "wof:placetype":"neighbourhood"
},
  "geometry": {"coordinates":[9.25134,47.18699],"type":"Point"}
}