{
  "type": "Feature",
  "properties": {
    "gn:admin1_code":"FR",
    "gn:admin2_code":"1003.0",
    "gn:admin3_code":"2135.0",
    "gn:asciiname":"Beauregard",
    "gn:country_code":"CH",
    "gn:dem":957,
    "gn:feature_class":"P",
    "gn:feature_code":"PPL",
    "gn:name":"Beauregard",
    "gn:population":0,
    "gn:timezone":"Europe/Zurich",
    "iso:country":"CH",
    "name:fra_x_preferred":[
        "Beauregard"
    ],
    "wof:name":"Beauregard",
    "wof:placetype":"locality"
},
  "geometry": {"coordinates":[7.02001,46.59797],"type":"Point"}
}