{
  "type": "Feature",
  "properties": {
    "gn:country":"CH",
    "gn:fcode":"PPLX",
    "gn:population":18,
    "iso:country":"CH",
    "name:eng_x_preferred":[
        "Gfenn"
    ],
    "name:eng_x_variant":[
        "Hegnau / Gfenn"
    ],
    "qs_pg:aaroncc":"CH",
    "qs_pg:gn_country":"CH",
    "qs_pg:gn_fcode":"PPLX",
    "qs_pg:gn_pop":18,
    "qs_pg:name":"Hegnau / Gfenn",
    "qs_pg:photos_9r":0,
    "qs_pg:photos_sr":0,
    "qs_pg:pop_sr":1,
    "qs_pg:qs_pg_placetype":"neighbourhood",
    "wof:name":"Gfenn",
    "wof:placetype":"neighbourhood",
    "wof:population":18
},
  "geometry": {"coordinates":[8.65594,47.39405],"type":"Point"}
}