{
  "type": "Feature",
  "properties": {
    "gn:gn_country":"CH",
    "gn:gn_fcode":"PPL",
    "gn:gn_pop":539,
    "gn:population":539,
    "iso:country":"CH",
    "name:deu_x_preferred":[
        "Enney"
    ],
    "name:eng_x_preferred":[
        "Enney"
    ],
    "name:fra_x_preferred":[
        "Enney"
    ],
    "name:nld_x_preferred":[
        "Enney"
    ],
    "name:swe_x_preferred":[
        "Enney"
    ],
    "qs_pg:aaroncc":"CH",
    "qs_pg:gn_country":"CH",
    "qs_pg:gn_fcode":"PPL",
    "qs_pg:gn_pop":539,
    "qs_pg:name":"Enney",
    "qs_pg:name_adm0":"Schweiz",
    "qs_pg:name_adm1":"Canton de Fribourg",
    "qs_pg:photos":27,
    "qs_pg:photos_1k":5,
    "qs_pg:photos_9k":1,
    "qs_pg:photos_9r":2,
    "qs_pg:photos_all":27,
    "qs_pg:photos_sr":2,
    "qs_pg:pop_sr":2,
    "qs_pg:qs_pg_placetype":"locality",
    "qs_pg:qs_pg_placetype_gp":"Town",
    "qs_pg:woe_adm0":23424957,
    "woe:adm0_id":23424957,
    "woe:name_adm0":"Schweiz",
    "woe:name_adm1":"Canton de Fribourg",
    "woe:placetype":"Town",
    "wof:name":"Enney",
    "wof:placetype":"locality",
    "wof:population":539
},
  "geometry": {"coordinates":[7.08418,46.56625],"type":"Point"}
}