{
  "type": "Feature",
  "properties": {
    "gn:admin1_code":"SG",
    "gn:admin2_code":"1725.0",
    "gn:admin3_code":"3298.0",
    "gn:asciiname":"Malun",
    "gn:country_code":"CH",
    "gn:dem":1654,
    "gn:feature_class":"P",
    "gn:feature_code":"PPLL",
    "gn:name":"Malun",
    "gn:population":0,
    "gn:timezone":"Europe/Zurich",
    "iso:country":"CH",
    "name:roh_x_preferred":[
        "Malun"
    ],
    "wof:name":"Malun",
    "wof:placetype":"neighbourhood"
},
  "geometry": {"coordinates":[9.39356,47.11566],"type":"Point"}
}