{
  "type": "Feature",
  "properties": {
    "gn:country":"CH",
    "gn:fcode":"PPLX",
    "gn:population":222,
    "iso:country":"CH",
    "name:eng_x_preferred":[
        "Ruggen"
    ],
    "name:eng_x_variant":[
        "Birmensdorf / Ruggen"
    ],
    "qs_pg:aaroncc":"CH",
    "qs_pg:gn_country":"CH",
    "qs_pg:gn_fcode":"PPLX",
    "qs_pg:gn_pop":222,
    "qs_pg:name":"Birmensdorf / Ruggen",
    "qs_pg:photos_9r":0,
    "qs_pg:photos_sr":0,
    "qs_pg:pop_sr":2,
    "qs_pg:qs_pg_placetype":"neighbourhood",
    "wof:lang_x_official":[
        "deu",
        "fra",
        "gsw",
        "ita"
    ],
    "wof:lang_x_spoken":[
        "deu",
        "fra",
        "gsw",
        "ita",
        "roh"
    ],
    "wof:name":"Ruggen",
    "wof:placetype":"neighbourhood",
    "wof:population":222
},
  "geometry": {"coordinates":[8.4439,47.3501],"type":"Point"}
}