{
  "type": "Feature",
  "properties": {
    "iso:country":"CH",
    "name:bre_x_preferred":[
        "T\u00f6ss"
    ],
    "name:ceb_x_preferred":[
        "T\u00f6ss"
    ],
    "name:ces_x_preferred":[
        "T\u00f6ss"
    ],
    "name:deu_x_colloquial":[
        "Toess",
        "Toss",
        "Winterthur Toess",
        "Winterthur Toss"
    ],
    "name:deu_x_preferred":[
        "T\u00f6ss"
    ],
    "name:deu_x_variant":[
        "Winterthur T\u00f6ss"
    ],
    "name:eng_x_preferred":[
        "T\u00f6ss"
    ],
    "name:fas_x_preferred":[
        "\u062a\u0648\u0633\u060c \u0628\u062e\u0634 \u0633\u0648\u0626\u06cc\u0633"
    ],
    "name:fas_x_variant":[
        "\u062a\u0648\u0633"
    ],
    "name:fra_x_preferred":[
        "T\u00f6ss"
    ],
    "name:ita_x_preferred":[
        "T\u00f6ss"
    ],
    "name:nld_x_preferred":[
        "T\u00f6ss"
    ],
    "name:nob_x_preferred":[
        "T\u00f6ss"
    ],
    "name:rus_x_preferred":[
        "\u0422\u0451\u0441\u0441"
    ],
    "name:swe_x_preferred":[
        "T\u00f6ss"
    ],
    "name:zho_x_preferred":[
        "\u6258\u65af"
    ],
    "qs:gn_adm0_cc":"CH",
    "qs:gn_local":2657970,
    "qs:gn_nam_loc":"Winterthur, Winterthur, Winterthur, Kanton Z\u00fcrich, CH",
    "qs:gn_namadm1":"ZH",
    "qs:local_max":4892,
    "qs:local_sum":5989,
    "qs:localhoods":2,
    "qs:name":"T\u00f6ss",
    "qs:name_adm0":"Schweiz",
    "qs:name_adm1":"Kanton Z\u00fcrich",
    "qs:name_adm2":"Winterthur",
    "qs:name_lau":"Winterthur",
    "qs:name_local":"Winterthur",
    "qs:photo_max":289,
    "qs:photo_sum":4892,
    "qs:placetype":"Suburb",
    "qs:quad_count":158,
    "qs:woe_adm0":23424957,
    "qs:woe_adm1":2347107,
    "qs:woe_adm2":12593177,
    "qs:woe_lau":12683652,
    "qs:woe_local":784723,
    "qs:woe_ver":"7.10.0",
    "wd:wordcount":79,
    "wof:name":"T\u00f6ss",
    "wof:placetype":"neighbourhood"
},
  "geometry": {"coordinates":[8.72158,47.495422],"type":"Point"}
}