{
  "type": "Feature",
  "properties": {
    "gn:admin1_code":"ZH",
    "gn:admin2_code":"102.0",
    "gn:admin3_code":"40.0",
    "gn:asciiname":"Sunnacker",
    "gn:country_code":"CH",
    "gn:dem":470,
    "gn:feature_class":"P",
    "gn:feature_code":"PPLL",
    "gn:name":"Sunnacker",
    "gn:population":0,
    "gn:timezone":"Europe/Zurich",
    "iso:country":"CH",
    "name:deu_x_preferred":[
        "Sunnacker"
    ],
    "wof:name":"Sunnacker",
    "wof:placetype":"neighbourhood"
},
  "geometry": {"coordinates":[8.71225,47.63843],"type":"Point"}
}