{
  "type": "Feature",
  "properties": {
    "gn:admin1_code":"SZ",
    "gn:admin2_code":"501.0",
    "gn:admin3_code":"1301.0",
    "gn:asciiname":"In den Baechen",
    "gn:country_code":"CH",
    "gn:dem":1036,
    "gn:feature_class":"P",
    "gn:feature_code":"PPLL",
    "gn:name":"In den B\u00e4chen",
    "gn:population":0,
    "gn:timezone":"Europe/Zurich",
    "iso:country":"CH",
    "name:deu_x_preferred":[
        "In den B\u00e4chen"
    ],
    "wof:lang_x_official":[
        "deu",
        "fra",
        "gsw",
        "ita"
    ],
    "wof:lang_x_spoken":[
        "deu",
        "fra",
        "gsw",
        "ita",
        "roh"
    ],
    "wof:name":"In den Baechen",
    "wof:placetype":"neighbourhood"
},
  "geometry": {"coordinates":[8.80579,47.15998],"type":"Point"}
}