{
  "type": "Feature",
  "properties": {
    "gn:admin1_code":"SG",
    "gn:admin2_code":"1727.0",
    "gn:admin3_code":"3352.0",
    "gn:asciiname":"Steintal",
    "gn:country_code":"CH",
    "gn:dem":870,
    "gn:elevation":"829.0",
    "gn:feature_class":"P",
    "gn:feature_code":"PPL",
    "gn:name":"Steintal",
    "gn:population":0,
    "gn:timezone":"Europe/Zurich",
    "iso:country":"CH",
    "wof:name":"Steintal",
    "wof:placetype":"neighbourhood"
},
  "geometry": {"coordinates":[9.13865,47.23012],"type":"Point"}
}