{
  "type": "Feature",
  "properties": {
    "gn:admin1_code":"SZ",
    "gn:admin2_code":"506.0",
    "gn:admin3_code":"1370.0",
    "gn:asciiname":"Mittlere Altmatt",
    "gn:country_code":"CH",
    "gn:dem":930,
    "gn:feature_class":"P",
    "gn:feature_code":"PPLL",
    "gn:name":"Mittlere Altmatt",
    "gn:population":0,
    "gn:timezone":"Europe/Zurich",
    "iso:country":"CH",
    "name:deu_x_preferred":[
        "Mittlere Altmatt"
    ],
    "wof:lang_x_official":[
        "deu",
        "fra",
        "gsw",
        "ita"
    ],
    "wof:lang_x_spoken":[
        "deu",
        "fra",
        "gsw",
        "ita",
        "roh"
    ],
    "wof:name":"Mittlere Altmatt",
    "wof:placetype":"neighbourhood"
},
  "geometry": {"coordinates":[8.68556,47.11881],"type":"Point"}
}