{
  "type": "Feature",
  "properties": {
    "iso:country":"CH",
    "name:fra_x_preferred":[
        "La Gravi\u00e8re"
    ],
    "wof:lang_x_official":[
        "deu",
        "fra",
        "gsw",
        "ita"
    ],
    "wof:lang_x_spoken":[
        "deu",
        "fra",
        "gsw",
        "ita",
        "roh"
    ],
    "wof:name":"La Graviere",
    "wof:placetype":"neighbourhood"
},
  "geometry": {"coordinates":[6.12924473262065,46.19753220969403],"type":"Point"}
}