{
  "type": "Feature",
  "properties": {
    "gn:admin1_code":"TG",
    "gn:admin2_code":"2013.0",
    "gn:admin3_code":"4701.0",
    "gn:asciiname":"Schmeckwies",
    "gn:country_code":"CH",
    "gn:dem":569,
    "gn:feature_class":"P",
    "gn:feature_code":"PPLL",
    "gn:name":"Schmeckwies",
    "gn:population":0,
    "gn:timezone":"Europe/Zurich",
    "iso:country":"CH",
    "name:deu_x_preferred":[
        "Schmeckwies"
    ],
    "wof:name":"Schmeckwies",
    "wof:placetype":"locality"
},
  "geometry": {"coordinates":[9.0921,47.62685],"type":"Point"}
}