{
  "type": "Feature",
  "properties": {
    "gn:country":"CH",
    "gn:fcode":"PPLX",
    "gn:population":1120,
    "iso:country":"CH",
    "name:eng_x_preferred":[
        "Rikon"
    ],
    "name:eng_x_variant":[
        "Effretikon / Rikon"
    ],
    "name:jpn_x_preferred":[
        "\u96e2\u5a5a"
    ],
    "qs_pg:aaroncc":"CH",
    "qs_pg:gn_country":"CH",
    "qs_pg:gn_fcode":"PPLX",
    "qs_pg:gn_pop":1120,
    "qs_pg:name":"Effretikon / Rikon",
    "qs_pg:photos_9r":0,
    "qs_pg:photos_sr":0,
    "qs_pg:pop_sr":3,
    "qs_pg:qs_pg_placetype":"neighbourhood",
    "wof:lang_x_official":[
        "deu",
        "fra",
        "gsw",
        "ita"
    ],
    "wof:lang_x_spoken":[
        "deu",
        "fra",
        "gsw",
        "ita",
        "roh"
    ],
    "wof:name":"Rikon",
    "wof:placetype":"neighbourhood",
    "wof:population":1120
},
  "geometry": {"coordinates":[8.79528,47.44674],"type":"Point"}
}