{
  "type": "Feature",
  "properties": {
    "iso:country":"CH",
    "name:cat_x_preferred":[
        "San Salvatore"
    ],
    "name:ceb_x_preferred":[
        "San Salvatore"
    ],
    "name:deu_x_preferred":[
        "San Salvatore"
    ],
    "name:fra_x_preferred":[
        "San Salvatore"
    ],
    "name:ita_x_preferred":[
        "San Salvatore"
    ],
    "name:por_x_preferred":[
        "San Salvatore"
    ],
    "name:rus_x_preferred":[
        "\u0421\u0430\u043d-\u0421\u0430\u043b\u044c\u0432\u0430\u0442\u043e\u0440\u0435"
    ],
    "name:srp_x_preferred":[
        "San Salvatore"
    ],
    "name:swe_x_preferred":[
        "San Salvatore"
    ],
    "qs_pg:aaroncc":"CH",
    "qs_pg:name":"San Salvatore",
    "qs_pg:name_adm0":"Schweiz",
    "qs_pg:name_adm1":"Cantone Ticino",
    "qs_pg:photos":283,
    "qs_pg:photos_1k":57,
    "qs_pg:photos_9k":1,
    "qs_pg:photos_9r":4,
    "qs_pg:photos_all":283,
    "qs_pg:photos_sr":5,
    "qs_pg:pop_sr":0,
    "qs_pg:qs_pg_placetype":"locality",
    "qs_pg:qs_pg_placetype_gp":"Town",
    "qs_pg:woe_adm0":23424957,
    "woe:adm0_id":23424957,
    "woe:name_adm0":"Schweiz",
    "woe:name_adm1":"Cantone Ticino",
    "woe:placetype":"Town",
    "wof:name":"San Salvatore",
    "wof:placetype":"neighbourhood"
},
  "geometry": {"coordinates":[8.9458,45.976779],"type":"Point"}
}