{
  "type": "Feature",
  "properties": {
    "gn:country":"CH",
    "gn:fcode":"PPL",
    "gn:population":0,
    "iso:country":"CH",
    "name:cat_x_preferred":[
        "Vals"
    ],
    "name:ceb_x_preferred":[
        "Vals"
    ],
    "name:deu_x_preferred":[
        "Vals"
    ],
    "name:eng_x_preferred":[
        "Vals"
    ],
    "name:epo_x_preferred":[
        "Vals GR"
    ],
    "name:eus_x_preferred":[
        "Vals"
    ],
    "name:fin_x_preferred":[
        "Vals"
    ],
    "name:fra_x_preferred":[
        "Vals"
    ],
    "name:gsw_x_preferred":[
        "Wals"
    ],
    "name:hun_x_preferred":[
        "Vals"
    ],
    "name:ita_x_preferred":[
        "Vals"
    ],
    "name:kaz_x_preferred":[
        "\u0412\u0430\u043b\u044c\u0441"
    ],
    "name:lmo_x_preferred":[
        "Vals"
    ],
    "name:msa_x_preferred":[
        "Vals"
    ],
    "name:nld_x_preferred":[
        "Vals"
    ],
    "name:nno_x_preferred":[
        "Vals i Sveits"
    ],
    "name:oci_x_preferred":[
        "Vals"
    ],
    "name:pms_x_preferred":[
        "Vals"
    ],
    "name:pol_x_preferred":[
        "Vals"
    ],
    "name:por_x_preferred":[
        "Vals"
    ],
    "name:roh_x_preferred":[
        "Val"
    ],
    "name:rus_x_preferred":[
        "\u0412\u0430\u043b\u044c\u0441"
    ],
    "name:spa_x_preferred":[
        "Vals"
    ],
    "name:sqi_x_preferred":[
        "Vals"
    ],
    "name:swe_x_preferred":[
        "Vals"
    ],
    "name:uzb_x_preferred":[
        "Vals"
    ],
    "name:vol_x_preferred":[
        "Vals"
    ],
    "name:war_x_preferred":[
        "Vals"
    ],
    "name:zho_x_preferred":[
        "\u74e6\u723e\u65af"
    ],
    "qs_pg:aaroncc":"CH",
    "qs_pg:gn_country":"CH",
    "qs_pg:gn_fcode":"PPL",
    "qs_pg:gn_pop":0,
    "qs_pg:name":"Vals Platz",
    "qs_pg:name_adm0":"Schweiz",
    "qs_pg:name_adm1":"Kanton Graub\u00fcnden",
    "qs_pg:photos":142,
    "qs_pg:photos_1k":29,
    "qs_pg:photos_9k":1,
    "qs_pg:photos_9r":3,
    "qs_pg:photos_all":142,
    "qs_pg:photos_sr":3,
    "qs_pg:pop_sr":0,
    "qs_pg:qs_pg_placetype":"locality",
    "qs_pg:qs_pg_placetype_gp":"Town",
    "qs_pg:woe_adm0":23424957,
    "woe:adm0_id":23424957,
    "woe:name_adm0":"Schweiz",
    "woe:name_adm1":"Kanton Graub\u00fcnden",
    "woe:placetype":"Town",
    "wof:name":"Vals Platz",
    "wof:placetype":"neighbourhood",
    "wof:population":1006
},
  "geometry": {"coordinates":[9.18025,46.61647],"type":"Point"}
}