{
  "type": "Feature",
  "properties": {
    "gn:admin1_code":"BE",
    "gn:admin2_code":"245.0",
    "gn:admin3_code":"418.0",
    "gn:asciiname":"Leimern",
    "gn:country_code":"CH",
    "gn:dem":594,
    "gn:feature_class":"P",
    "gn:feature_code":"PPLL",
    "gn:name":"Leimern",
    "gn:population":0,
    "gn:timezone":"Europe/Zurich",
    "iso:country":"CH",
    "name:deu_x_preferred":[
        "Leimern"
    ],
    "wof:name":"Leimern",
    "wof:placetype":"locality"
},
  "geometry": {"coordinates":[7.62601,47.0321],"type":"Point"}
}