{
  "type": "Feature",
  "properties": {
    "gn:admin1_code":"NW",
    "gn:admin2_code":"700.0",
    "gn:admin3_code":"1508.0",
    "gn:asciiname":"Winterswil",
    "gn:country_code":"CH",
    "gn:dem":713,
    "gn:feature_class":"P",
    "gn:feature_code":"PPL",
    "gn:name":"Winterswil",
    "gn:population":0,
    "gn:timezone":"Europe/Zurich",
    "iso:country":"CH",
    "name:deu_x_preferred":[
        "Winterswil"
    ],
    "wof:lang_x_official":[
        "deu",
        "fra",
        "gsw",
        "ita"
    ],
    "wof:lang_x_spoken":[
        "deu",
        "fra",
        "gsw",
        "ita",
        "roh"
    ],
    "wof:name":"Winterswil",
    "wof:placetype":"neighbourhood"
},
  "geometry": {"coordinates":[8.40474,46.9558],"type":"Point"}
}