{
  "type": "Feature",
  "properties": {
    "gn:country":"CH",
    "gn:fcode":"PPL",
    "gn:population":12598,
    "iso:country":"CH",
    "name:ceb_x_preferred":[
        "W\u00fclflingen"
    ],
    "name:cym_x_preferred":[
        "W\u00fclflingen"
    ],
    "name:deu_x_preferred":[
        "W\u00fclflingen"
    ],
    "name:eng_x_preferred":[
        "W\u00fclflingen"
    ],
    "name:fra_x_preferred":[
        "W\u00fclflingen"
    ],
    "name:ita_x_preferred":[
        "W\u00fclflingen"
    ],
    "name:nld_x_preferred":[
        "W\u00fclflingen"
    ],
    "name:swe_x_preferred":[
        "W\u00fclflingen"
    ],
    "qs_pg:aaroncc":"CH",
    "qs_pg:gn_country":"CH",
    "qs_pg:gn_fcode":"PPL",
    "qs_pg:gn_pop":12598,
    "qs_pg:name":"W\u00fclflingen (Kreis 6)",
    "qs_pg:photos_9r":0,
    "qs_pg:photos_sr":0,
    "qs_pg:pop_sr":6,
    "qs_pg:qs_pg_placetype":"locality",
    "wof:lang_x_official":[
        "deu",
        "fra",
        "gsw",
        "ita"
    ],
    "wof:lang_x_spoken":[
        "deu",
        "fra",
        "gsw",
        "ita",
        "roh"
    ],
    "wof:name":"W\u00fclflingen (Kreis 6)",
    "wof:placetype":"neighbourhood",
    "wof:population":12598
},
  "geometry": {"coordinates":[8.68333,47.51036],"type":"Point"}
}