{
  "type": "Feature",
  "properties": {
    "gn:country":"CH",
    "gn:fcode":"PPLX",
    "gn:population":409,
    "iso:country":"CH",
    "name:eng_x_preferred":[
        "Dielsdorfer-/Kr\u00e4hstelstr."
    ],
    "name:eng_x_variant":[
        "Buchs / Dielsdorfer-/Kr\u00e4hstelstr."
    ],
    "qs_pg:aaroncc":"CH",
    "qs_pg:gn_country":"CH",
    "qs_pg:gn_fcode":"PPLX",
    "qs_pg:gn_pop":409,
    "qs_pg:name":"Buchs / Dielsdorfer-/Kr\u00e4hstelstr.",
    "qs_pg:photos_9r":0,
    "qs_pg:photos_sr":0,
    "qs_pg:pop_sr":2,
    "qs_pg:qs_pg_placetype":"neighbourhood",
    "wof:name":"Dielsdorfer-/Kr\u00e4hstelstr.",
    "wof:placetype":"neighbourhood",
    "wof:population":409
},
  "geometry": {"coordinates":[8.44184,47.45967],"type":"Point"}
}