{
  "type": "Feature",
  "properties": {
    "gn:admin1_code":"GR",
    "gn:admin2_code":"1850.0",
    "gn:admin3_code":"3603.0",
    "gn:asciiname":"Guraletsch",
    "gn:cc2":"CH",
    "gn:country_code":"CH",
    "gn:dem":1804,
    "gn:feature_class":"P",
    "gn:feature_code":"PPL",
    "gn:name":"Guraletsch",
    "gn:population":0,
    "gn:timezone":"Europe/Zurich",
    "iso:country":"CH",
    "name:und_x_variant":[
        "Alt Guraletsch",
        "Guraletsch"
    ],
    "wof:name":"Guraletsch",
    "wof:placetype":"neighbourhood"
},
  "geometry": {"coordinates":[9.13333,46.58333],"type":"Point"}
}