{
  "type": "Feature",
  "properties": {
    "gn:gn_country":"CH",
    "gn:gn_fcode":"PPL",
    "gn:gn_pop":806,
    "gn:population":806,
    "iso:country":"CH",
    "name:chi_x_preferred":[
        "\u9f4a\u7f8e\u723e\u74e6\u723e\u5fb7"
    ],
    "name:dut_x_preferred":[
        "Zimmerwald"
    ],
    "name:eng_x_preferred":[
        "Zimmerwald"
    ],
    "name:fre_x_preferred":[
        "Zimmerwald"
    ],
    "name:ger_x_preferred":[
        "Zimmerwald"
    ],
    "name:jpn_x_preferred":[
        "\u30c4\u30a3\u30f3\u30de\u30fc\u30f4\u30a1\u30eb\u30c8"
    ],
    "name:por_x_preferred":[
        "Zimmerwald"
    ],
    "name:swe_x_preferred":[
        "Zimmerwald"
    ],
    "qs_pg:aaroncc":"CH",
    "qs_pg:gn_country":"CH",
    "qs_pg:gn_fcode":"PPL",
    "qs_pg:gn_pop":806,
    "qs_pg:name":"Zimmerwald",
    "qs_pg:name_adm0":"Schweiz",
    "qs_pg:name_adm1":"Kanton Bern",
    "qs_pg:photos_9k":1,
    "qs_pg:photos_9r":1,
    "qs_pg:photos_all":1,
    "qs_pg:photos_sr":0,
    "qs_pg:pop_sr":2,
    "qs_pg:qs_pg_placetype":"locality",
    "qs_pg:qs_pg_placetype_gp":"Town",
    "qs_pg:woe_adm0":23424957,
    "woe:adm0_id":23424957,
    "woe:name_adm0":"Schweiz",
    "woe:name_adm1":"Kanton Bern",
    "woe:placetype":"Town",
    "wof:name":"Zimmerwald",
    "wof:placetype":"locality",
    "wof:population":806
},
  "geometry": {"coordinates":[7.47712,46.88091],"type":"Point"}
}