{
  "type": "Feature",
  "properties": {
    "gn:gn_country":"CH",
    "gn:gn_fcode":"PPL",
    "gn:gn_pop":103,
    "gn:population":103,
    "iso:country":"CH",
    "name:ara_x_preferred":[
        "\u0625\u0634\u0644\u064a\u0643\u0648\u0646"
    ],
    "name:baq_x_preferred":[
        "Eschlikon"
    ],
    "name:cat_x_preferred":[
        "Eschlikon"
    ],
    "name:chi_x_preferred":[
        "\u57c3\u65bd\u5229\u5b54"
    ],
    "name:cze_x_preferred":[
        "Eschlikon"
    ],
    "name:dut_x_preferred":[
        "Eschlikon"
    ],
    "name:eng_x_preferred":[
        "Eschlikon"
    ],
    "name:epo_x_preferred":[
        "Eschlikon TG"
    ],
    "name:fre_x_preferred":[
        "Eschlikon"
    ],
    "name:ger_x_preferred":[
        "Eschlikon"
    ],
    "name:gsw_x_preferred":[
        "Eschlikon"
    ],
    "name:hun_x_preferred":[
        "Eschlikon"
    ],
    "name:ita_x_preferred":[
        "Eschlikon"
    ],
    "name:kaz_x_preferred":[
        "\u042d\u0448\u043b\u0438\u043a\u043e\u043d"
    ],
    "name:lmo_x_preferred":[
        "Eschlikon"
    ],
    "name:may_x_preferred":[
        "Eschlikon"
    ],
    "name:nno_x_preferred":[
        "Eschlikon"
    ],
    "name:oci_x_preferred":[
        "Eschlikon"
    ],
    "name:pms_x_preferred":[
        "Eschlikon"
    ],
    "name:por_x_preferred":[
        "Eschlikon"
    ],
    "name:rus_x_preferred":[
        "\u042d\u0448\u043b\u0438\u043a\u043e\u043d"
    ],
    "name:spa_x_preferred":[
        "Eschlikon"
    ],
    "name:swe_x_preferred":[
        "Eschlikon"
    ],
    "name:uzb_x_preferred":[
        "Eschlikon"
    ],
    "name:vec_x_preferred":[
        "Eschlikon"
    ],
    "name:vol_x_preferred":[
        "Eschlikon"
    ],
    "name:war_x_preferred":[
        "Eschlikon"
    ],
    "qs_pg:aaroncc":"CH",
    "qs_pg:gn_country":"CH",
    "qs_pg:gn_fcode":"PPL",
    "qs_pg:gn_pop":103,
    "qs_pg:name":"Eschlikon",
    "qs_pg:name_adm0":"Schweiz",
    "qs_pg:name_adm1":"Kanton Z\u00fcrich",
    "qs_pg:photos_9r":0,
    "qs_pg:photos_sr":0,
    "qs_pg:pop_sr":1,
    "qs_pg:qs_pg_placetype":"locality",
    "qs_pg:qs_pg_placetype_gp":"Town",
    "qs_pg:woe_adm0":23424957,
    "woe:adm0_id":23424957,
    "woe:name_adm0":"Schweiz",
    "woe:name_adm1":"Kanton Z\u00fcrich",
    "woe:placetype":"Town",
    "wof:name":"Eschlikon",
    "wof:placetype":"locality",
    "wof:population":103
},
  "geometry": {"coordinates":[8.75372,47.5649],"type":"Point"}
}