{
  "type": "Feature",
  "properties": {
    "gn:country":"CH",
    "gn:fcode":"PPLX",
    "gn:population":34,
    "iso:country":"CH",
    "name:und_x_variant":[
        "Lantig"
    ],
    "qs_pg:aaroncc":"CH",
    "qs_pg:gn_country":"CH",
    "qs_pg:gn_fcode":"PPLX",
    "qs_pg:gn_pop":34,
    "qs_pg:name":"W\u00fclflingen (Kreis 6) / Lantig",
    "qs_pg:photos_9r":0,
    "qs_pg:photos_sr":0,
    "qs_pg:pop_sr":1,
    "qs_pg:qs_pg_placetype":"neighbourhood",
    "wof:lang_x_official":[
        "deu",
        "fra",
        "gsw",
        "ita"
    ],
    "wof:lang_x_spoken":[
        "deu",
        "fra",
        "gsw",
        "ita",
        "roh"
    ],
    "wof:name":"Lantig",
    "wof:placetype":"neighbourhood",
    "wof:population":34
},
  "geometry": {"coordinates":[8.69613,47.52199],"type":"Point"}
}