{
  "type": "Feature",
  "properties": {
    "iso:country":"CH",
    "name:cat_x_preferred":[
        "Mitl\u00f6di"
    ],
    "name:chv_x_preferred":[
        "\u041c\u0438\u0442\u043b\u0451\u0434\u0438"
    ],
    "name:dut_x_preferred":[
        "Mitl\u00f6di"
    ],
    "name:eng_x_preferred":[
        "Mitl\u00f6di"
    ],
    "name:epo_x_preferred":[
        "Mitl\u00f6di"
    ],
    "name:fre_x_preferred":[
        "Mitl\u00f6di"
    ],
    "name:ger_x_preferred":[
        "Mitl\u00f6di"
    ],
    "name:ita_x_preferred":[
        "Mitl\u00f6di"
    ],
    "name:kaz_x_preferred":[
        "\u041c\u0438\u0442\u043b\u0451\u0434\u0438"
    ],
    "name:lmo_x_preferred":[
        "Mitl\u00f6di"
    ],
    "name:pms_x_preferred":[
        "Mitl\u00f6di"
    ],
    "name:pnb_x_preferred":[
        "\u0645\u0679\u0644\u0648\u0688\u06cc"
    ],
    "name:por_x_preferred":[
        "Mitl\u00f6di"
    ],
    "name:rus_x_preferred":[
        "\u041c\u0438\u0442\u043b\u0451\u0434\u0438"
    ],
    "name:spa_x_preferred":[
        "Mitl\u00f6di"
    ],
    "name:swe_x_preferred":[
        "Mitl\u00f6di"
    ],
    "name:uzb_x_preferred":[
        "Mitl\u00f6di"
    ],
    "name:vol_x_preferred":[
        "Mitl\u00f6di"
    ],
    "name:war_x_preferred":[
        "Mitl\u00f6di"
    ],
    "qs_pg:aaroncc":"CH",
    "qs_pg:name":"Mitl\u00f6di",
    "qs_pg:name_adm0":"Schweiz",
    "qs_pg:name_adm1":"Kanton Glarus",
    "qs_pg:photos":7,
    "qs_pg:photos_1k":1,
    "qs_pg:photos_9k":1,
    "qs_pg:photos_9r":1,
    "qs_pg:photos_all":7,
    "qs_pg:photos_sr":1,
    "qs_pg:pop_sr":0,
    "qs_pg:qs_pg_placetype":"locality",
    "qs_pg:qs_pg_placetype_gp":"Town",
    "qs_pg:woe_adm0":23424957,
    "woe:adm0_id":23424957,
    "woe:name_adm0":"Schweiz",
    "woe:name_adm1":"Kanton Glarus",
    "woe:placetype":"Town",
    "wof:name":"Mitl\u00f6di",
    "wof:placetype":"locality"
},
  "geometry": {"coordinates":[9.073784,47.007635],"type":"Point"}
}