{
  "type": "Feature",
  "properties": {
    "gn:admin1_code":"SG",
    "gn:admin2_code":"1727.0",
    "gn:admin3_code":"3352.0",
    "gn:asciiname":"Relis",
    "gn:country_code":"CH",
    "gn:dem":838,
    "gn:feature_class":"P",
    "gn:feature_code":"PPLL",
    "gn:name":"Relis",
    "gn:population":0,
    "gn:timezone":"Europe/Zurich",
    "iso:country":"CH",
    "name:deu_x_preferred":[
        "Relis"
    ],
    "wof:name":"Relis",
    "wof:placetype":"neighbourhood"
},
  "geometry": {"coordinates":[9.10922,47.25623],"type":"Point"}
}