{
  "type": "Feature",
  "properties": {
    "gn:gn_country":"CH",
    "gn:gn_fcode":"PPLL",
    "gn:gn_pop":12,
    "gn:population":12,
    "iso:country":"CH",
    "name:deu_x_preferred":[
        "Eichm\u00fchle"
    ],
    "qs_pg:aaroncc":"CH",
    "qs_pg:gn_country":"CH",
    "qs_pg:gn_fcode":"PPLL",
    "qs_pg:gn_pop":12,
    "qs_pg:name":"Eichm\u00fchle",
    "qs_pg:photos_9r":0,
    "qs_pg:photos_sr":0,
    "qs_pg:pop_sr":1,
    "qs_pg:qs_pg_placetype":"locality",
    "wof:name":"Eichm\u00fchle",
    "wof:placetype":"neighbourhood",
    "wof:population":12
},
  "geometry": {"coordinates":[8.71579,47.55027],"type":"Point"}
}