{
  "type": "Feature",
  "properties": {
    "gn:gn_country":"CH",
    "gn:gn_fcode":"PPLX",
    "gn:gn_pop":46,
    "gn:population":46,
    "iso:country":"CH",
    "name:eng_x_preferred":[
        "Ober-Rennweg"
    ],
    "name:eng_x_variant":[
        "Wolfhausen / Ober-Rennweg"
    ],
    "name:unk_x_variant":[
        "Ober-Rennweg"
    ],
    "qs_pg:aaroncc":"CH",
    "qs_pg:gn_country":"CH",
    "qs_pg:gn_fcode":"PPLX",
    "qs_pg:gn_pop":46,
    "qs_pg:name":"Wolfhausen / Ober-Rennweg",
    "qs_pg:photos_9r":0,
    "qs_pg:photos_sr":0,
    "qs_pg:pop_sr":1,
    "qs_pg:qs_pg_placetype":"neighbourhood",
    "wof:name":"Ober-Rennweg",
    "wof:placetype":"neighbourhood",
    "wof:population":46
},
  "geometry": {"coordinates":[8.79026,47.25582],"type":"Point"}
}