{
  "type": "Feature",
  "properties": {
    "gn:admin1_code":"VD",
    "gn:admin2_code":"2223.0",
    "gn:admin3_code":"5503.0",
    "gn:asciiname":"Vufflens-la-Ville",
    "gn:country_code":"CH",
    "gn:dem":464,
    "gn:feature_class":"P",
    "gn:feature_code":"PPL",
    "gn:name":"Vufflens-la-Ville",
    "gn:population":0,
    "gn:timezone":"Europe/Zurich",
    "iso:country":"CH",
    "name:zho_x_preferred":[
        "\u7ef4\u592b\u6717\u62c9\u7ef4\u5c14"
    ],
    "wof:name":"Vufflens-la-Ville",
    "wof:placetype":"locality"
},
  "geometry": {"coordinates":[6.53716,46.57515],"type":"Point"}
}