{
  "type": "Feature",
  "properties": {
    "gn:gn_country":"CH",
    "gn:gn_fcode":"PPL",
    "gn:gn_pop":535,
    "gn:population":535,
    "iso:country":"CH",
    "name:dut_x_preferred":[
        "Bironico"
    ],
    "name:eng_x_preferred":[
        "Bironico"
    ],
    "name:fre_x_preferred":[
        "Bironico"
    ],
    "name:ger_x_preferred":[
        "Bironico"
    ],
    "name:ita_x_preferred":[
        "Bironico"
    ],
    "name:lmo_x_preferred":[
        "Bironich"
    ],
    "name:por_x_preferred":[
        "Bironico"
    ],
    "name:roh_x_preferred":[
        "Bironico"
    ],
    "name:spa_x_preferred":[
        "Bironico"
    ],
    "name:swe_x_preferred":[
        "Bironico"
    ],
    "name:unk_x_variant":[
        "Rivera-Bironico"
    ],
    "name:vol_x_preferred":[
        "Bironico"
    ],
    "name:war_x_preferred":[
        "Bironico"
    ],
    "qs_pg:aaroncc":"CH",
    "qs_pg:gn_country":"CH",
    "qs_pg:gn_fcode":"PPL",
    "qs_pg:gn_pop":535,
    "qs_pg:name":"Bironico",
    "qs_pg:name_adm0":"Schweiz",
    "qs_pg:name_adm1":"Cantone Ticino",
    "qs_pg:photos":56,
    "qs_pg:photos_1k":11,
    "qs_pg:photos_9k":1,
    "qs_pg:photos_9r":2,
    "qs_pg:photos_all":56,
    "qs_pg:photos_sr":2,
    "qs_pg:pop_sr":2,
    "qs_pg:qs_pg_placetype":"locality",
    "qs_pg:qs_pg_placetype_gp":"Town",
    "qs_pg:woe_adm0":23424957,
    "woe:adm0_id":23424957,
    "woe:name_adm0":"Schweiz",
    "woe:name_adm1":"Cantone Ticino",
    "woe:placetype":"Town",
    "wof:name":"Bironico",
    "wof:placetype":"locality",
    "wof:population":535
},
  "geometry": {"coordinates":[8.93314,46.11038],"type":"Point"}
}