{
  "type": "Feature",
  "properties": {
    "gn:gn_country":"CH",
    "gn:gn_fcode":"PPL",
    "gn:gn_pop":0,
    "iso:country":"CH",
    "name:dut_x_preferred":[
        "Billens"
    ],
    "name:eng_x_preferred":[
        "Billens"
    ],
    "name:fre_x_preferred":[
        "Billens"
    ],
    "name:ger_x_preferred":[
        "Billens"
    ],
    "qs_pg:aaroncc":"CH",
    "qs_pg:gn_country":"CH",
    "qs_pg:gn_fcode":"PPL",
    "qs_pg:gn_pop":0,
    "qs_pg:name":"Billens",
    "qs_pg:name_adm0":"Schweiz",
    "qs_pg:name_adm1":"Canton de Fribourg",
    "qs_pg:photos":5000,
    "qs_pg:photos_1k":1000,
    "qs_pg:photos_9k":22,
    "qs_pg:photos_9r":14,
    "qs_pg:photos_all":5000,
    "qs_pg:photos_sr":24,
    "qs_pg:pop_sr":0,
    "qs_pg:qs_pg_placetype":"locality",
    "qs_pg:qs_pg_placetype_gp":"Town",
    "qs_pg:woe_adm0":23424957,
    "woe:adm0_id":23424957,
    "woe:name_adm0":"Schweiz",
    "woe:name_adm1":"Canton de Fribourg",
    "woe:placetype":"Town",
    "wof:name":"Billens",
    "wof:placetype":"locality"
},
  "geometry": {"coordinates":[6.9008,46.69218],"type":"Point"}
}