{
  "type": "Feature",
  "properties": {
    "gn:admin1_code":"TI",
    "gn:admin2_code":"2104.0",
    "gn:admin3_code":"5097.0",
    "gn:asciiname":"Bassuno",
    "gn:country_code":"CH",
    "gn:dem":869,
    "gn:feature_class":"P",
    "gn:feature_code":"PPL",
    "gn:name":"Bassuno",
    "gn:population":0,
    "gn:timezone":"Europe/Zurich",
    "iso:country":"CH",
    "name:ita_x_preferred":[
        "Bassuno"
    ],
    "wof:name":"Bassuno",
    "wof:placetype":"neighbourhood"
},
  "geometry": {"coordinates":[8.69881,46.13094],"type":"Point"}
}