{
  "type": "Feature",
  "properties": {
    "gn:gn_country":"CH",
    "gn:gn_fcode":"PPL",
    "gn:gn_pop":362,
    "gn:population":362,
    "iso:country":"CH",
    "name:cat_x_preferred":[
        "Waltensburg/Vuorz"
    ],
    "name:deu_x_preferred":[
        "Waltensburg Dorf"
    ],
    "name:deu_x_variant":[
        "Waltensburg",
        "Waltensburg/Vuorz"
    ],
    "name:eng_x_preferred":[
        "Waltensburg/Vuorz"
    ],
    "name:epo_x_preferred":[
        "Waltensburg/Vuorz"
    ],
    "name:eus_x_preferred":[
        "Waltensburg/Vuorz"
    ],
    "name:fra_x_preferred":[
        "Waltensburg/Vuorz"
    ],
    "name:hun_x_preferred":[
        "Waltensburg/Vuorz"
    ],
    "name:ita_x_preferred":[
        "Waltensburg/Vuorz"
    ],
    "name:kaz_x_preferred":[
        "\u0412\u0430\u043b\u044c\u0442\u0435\u043d\u0441\u0431\u0443\u0440\u0433"
    ],
    "name:lmo_x_preferred":[
        "Waltensburg/Vuorz"
    ],
    "name:msa_x_preferred":[
        "Waltensburg/Vuorz"
    ],
    "name:nld_x_preferred":[
        "Waltensburg/Vuorz"
    ],
    "name:nno_x_preferred":[
        "Waltensburg/Vuorz"
    ],
    "name:oci_x_preferred":[
        "Waltensburg/Vuorz"
    ],
    "name:pms_x_preferred":[
        "Waltensburg/Vuorz"
    ],
    "name:por_x_preferred":[
        "Waltensburg/Vuorz"
    ],
    "name:roh_x_preferred":[
        "Vuorz"
    ],
    "name:rus_x_preferred":[
        "\u0412\u0430\u043b\u044c\u0442\u0435\u043d\u0441\u0431\u0443\u0440\u0433"
    ],
    "name:spa_x_preferred":[
        "Waltensburg/Vuorz"
    ],
    "name:sqi_x_preferred":[
        "Waltensburg/Vuorz"
    ],
    "name:swe_x_preferred":[
        "Waltensburg/Vuorz"
    ],
    "name:unk_x_variant":[
        "Waltensburg/Vuorz"
    ],
    "name:uzb_x_preferred":[
        "Waltensburg/Vuorz"
    ],
    "name:vol_x_preferred":[
        "Waltensburg/Vuorz"
    ],
    "name:war_x_preferred":[
        "Waltensburg/Vuorz"
    ],
    "name:zho_x_preferred":[
        "\u74e6\u723e\u6ed5\u65af\u5821"
    ],
    "qs_pg:aaroncc":"CH",
    "qs_pg:gn_country":"CH",
    "qs_pg:gn_fcode":"PPL",
    "qs_pg:gn_pop":362,
    "qs_pg:name":"Waltensburg",
    "qs_pg:name_adm0":"Schweiz",
    "qs_pg:name_adm1":"Kanton Graub\u00fcnden",
    "qs_pg:photos":21,
    "qs_pg:photos_1k":4,
    "qs_pg:photos_9k":1,
    "qs_pg:photos_9r":1,
    "qs_pg:photos_all":21,
    "qs_pg:photos_sr":1,
    "qs_pg:pop_sr":2,
    "qs_pg:qs_pg_placetype":"locality",
    "qs_pg:qs_pg_placetype_gp":"Town",
    "qs_pg:woe_adm0":23424957,
    "woe:adm0_id":23424957,
    "woe:name_adm0":"Schweiz",
    "woe:name_adm1":"Kanton Graub\u00fcnden",
    "woe:placetype":"Town",
    "wof:name":"Waltensburg",
    "wof:placetype":"neighbourhood",
    "wof:population":362
},
  "geometry": {"coordinates":[9.1085,46.77368],"type":"Point"}
}