{
  "type": "Feature",
  "properties": {
    "gn:admin1_code":"TI",
    "gn:admin2_code":"2105.0",
    "gn:admin3_code":"5227.0",
    "gn:asciiname":"Monticello",
    "gn:country_code":"CH",
    "gn:dem":842,
    "gn:feature_class":"P",
    "gn:feature_code":"PPL",
    "gn:name":"Monticello",
    "gn:population":0,
    "gn:timezone":"Europe/Zurich",
    "iso:country":"CH",
    "name:ita_x_preferred":[
        "Monticello"
    ],
    "wof:name":"Monticello",
    "wof:placetype":"neighbourhood"
},
  "geometry": {"coordinates":[8.90875,46.07127],"type":"Point"}
}