{
  "type": "Feature",
  "properties": {
    "gn:admin1_code":"AG",
    "gn:admin2_code":"1911.0",
    "gn:admin3_code":"4313.0",
    "gn:asciiname":"Leuggern",
    "gn:country_code":"CH",
    "gn:dem":324,
    "gn:feature_class":"P",
    "gn:feature_code":"PPL",
    "gn:name":"Leuggern",
    "gn:population":0,
    "gn:timezone":"Europe/Zurich",
    "iso:country":"CH",
    "name:kaz_x_preferred":[
        "\u041b\u043e\u0439\u0433\u0435\u0440\u043d"
    ],
    "name:rus_x_preferred":[
        "\u041b\u043e\u0439\u0433\u0433\u0435\u0440\u043d"
    ],
    "name:zho_x_preferred":[
        "\u6d1b\u4f0a\u683c\u723e\u6069"
    ],
    "wof:name":"Leuggern",
    "wof:placetype":"locality"
},
  "geometry": {"coordinates":[8.21945,47.58195],"type":"Point"}
}