{
  "type": "Feature",
  "properties": {
    "gn:admin1_code":"BE",
    "gn:admin2_code":"242.0",
    "gn:admin3_code":"731.0",
    "gn:asciiname":"Aegerten",
    "gn:country_code":"CH",
    "gn:dem":432,
    "gn:feature_class":"P",
    "gn:feature_code":"PPL",
    "gn:name":"Aegerten",
    "gn:population":0,
    "gn:timezone":"Europe/Zurich",
    "iso:country":"CH",
    "name:epo_x_preferred":[
        "Aegerten BE"
    ],
    "name:kaz_x_preferred":[
        "\u042d\u0433\u0435\u0440\u0442\u0435\u043d"
    ],
    "name:rus_x_preferred":[
        "\u042d\u0433\u0435\u0440\u0442\u0435\u043d"
    ],
    "name:zho_x_preferred":[
        "\u963f\u683c\u6ed5"
    ],
    "wof:name":"Aegerten",
    "wof:placetype":"locality"
},
  "geometry": {"coordinates":[7.29164,47.12115],"type":"Point"}
}