{
  "type": "Feature",
  "properties": {
    "gn:admin1_code":"ZH",
    "gn:admin2_code":"101.0",
    "gn:admin3_code":"10.0",
    "gn:asciiname":"Lunnerfeld",
    "gn:country_code":"CH",
    "gn:dem":406,
    "gn:feature_class":"P",
    "gn:feature_code":"PPLL",
    "gn:name":"Lunnerfeld",
    "gn:population":0,
    "gn:timezone":"Europe/Zurich",
    "iso:country":"CH",
    "name:deu_x_preferred":[
        "Lunnerfeld"
    ],
    "wof:name":"Lunnerfeld",
    "wof:placetype":"locality"
},
  "geometry": {"coordinates":[8.41139,47.25603],"type":"Point"}
}