{
  "type": "Feature",
  "properties": {
    "gn:admin1_code":"UR",
    "gn:admin2_code":"400.0",
    "gn:admin3_code":"1205.0",
    "gn:asciiname":"Hinterste Huetten",
    "gn:country_code":"CH",
    "gn:dem":1494,
    "gn:feature_class":"P",
    "gn:feature_code":"PPLL",
    "gn:name":"Hinterste H\u00fctten",
    "gn:population":0,
    "gn:timezone":"Europe/Zurich",
    "iso:country":"CH",
    "name:deu_x_preferred":[
        "Hinterste H\u00fctten"
    ],
    "wof:lang_x_official":[
        "deu",
        "fra",
        "gsw",
        "ita"
    ],
    "wof:lang_x_spoken":[
        "deu",
        "fra",
        "gsw",
        "ita",
        "roh"
    ],
    "wof:name":"Hinterste Huetten",
    "wof:placetype":"neighbourhood"
},
  "geometry": {"coordinates":[8.75793,46.91452],"type":"Point"}
}