{
  "type": "Feature",
  "properties": {
    "gn:gn_country":"CH",
    "gn:gn_fcode":"PPL",
    "gn:gn_pop":662,
    "gn:population":662,
    "iso:country":"CH",
    "name:cat_x_preferred":[
        "Engi"
    ],
    "name:chv_x_preferred":[
        "\u042d\u043d\u0433\u0438"
    ],
    "name:deu_x_preferred":[
        "Engi GL"
    ],
    "name:dut_x_preferred":[
        "Engi"
    ],
    "name:eng_x_preferred":[
        "Engi"
    ],
    "name:epo_x_preferred":[
        "Engi"
    ],
    "name:fre_x_preferred":[
        "Engi"
    ],
    "name:ger_x_preferred":[
        "Engi GL"
    ],
    "name:ita_x_preferred":[
        "Engi"
    ],
    "name:kaz_x_preferred":[
        "\u042d\u043d\u0433\u0438"
    ],
    "name:lmo_x_preferred":[
        "Engi"
    ],
    "name:pms_x_preferred":[
        "Engi"
    ],
    "name:pnb_x_preferred":[
        "\u0627\u0646\u06af\u06cc"
    ],
    "name:por_x_preferred":[
        "Engi"
    ],
    "name:rus_x_preferred":[
        "\u042d\u043d\u0433\u0438"
    ],
    "name:spa_x_preferred":[
        "Engi"
    ],
    "name:swe_x_preferred":[
        "Engi"
    ],
    "name:uzb_x_preferred":[
        "Engi"
    ],
    "name:vol_x_preferred":[
        "Engi"
    ],
    "name:war_x_preferred":[
        "Engi"
    ],
    "qs_pg:aaroncc":"CH",
    "qs_pg:gn_country":"CH",
    "qs_pg:gn_fcode":"PPL",
    "qs_pg:gn_pop":662,
    "qs_pg:name":"Engi",
    "qs_pg:name_adm0":"Schweiz",
    "qs_pg:name_adm1":"Kanton Glarus",
    "qs_pg:photos":210,
    "qs_pg:photos_1k":43,
    "qs_pg:photos_9k":1,
    "qs_pg:photos_9r":4,
    "qs_pg:photos_all":210,
    "qs_pg:photos_sr":4,
    "qs_pg:pop_sr":2,
    "qs_pg:qs_pg_placetype":"locality",
    "qs_pg:qs_pg_placetype_gp":"Town",
    "qs_pg:woe_adm0":23424957,
    "woe:adm0_id":23424957,
    "woe:name_adm0":"Schweiz",
    "woe:name_adm1":"Kanton Glarus",
    "woe:placetype":"Town",
    "wof:name":"Engi",
    "wof:placetype":"locality",
    "wof:population":662
},
  "geometry": {"coordinates":[9.15311,46.98239],"type":"Point"}
}