{
  "type": "Feature",
  "properties": {
    "gn:admin1_code":"LU",
    "gn:admin2_code":"312.0",
    "gn:admin3_code":"1062.0",
    "gn:asciiname":"Ennigen",
    "gn:country_code":"CH",
    "gn:dem":515,
    "gn:feature_class":"P",
    "gn:feature_code":"PPL",
    "gn:name":"Ennigen",
    "gn:population":0,
    "gn:timezone":"Europe/Zurich",
    "iso:country":"CH",
    "wof:name":"Ennigen",
    "wof:placetype":"neighbourhood"
},
  "geometry": {"coordinates":[8.15503,47.03497],"type":"Point"}
}