{
  "type": "Feature",
  "properties": {
    "gn:admin1_code":"GR",
    "gn:admin2_code":"1851.0",
    "gn:admin3_code":"3661.0",
    "gn:asciiname":"Summaprada",
    "gn:country_code":"CH",
    "gn:dem":681,
    "gn:feature_class":"P",
    "gn:feature_code":"PPL",
    "gn:name":"Summaprada",
    "gn:population":0,
    "gn:timezone":"Europe/Zurich",
    "iso:country":"CH",
    "wof:name":"Summaprada",
    "wof:placetype":"locality"
},
  "geometry": {"coordinates":[9.43305,46.71474],"type":"Point"}
}