{
  "type": "Feature",
  "properties": {
    "iso:country":"CH",
    "wof:name":"St Jakob",
    "wof:placetype":"neighbourhood"
},
  "geometry": {"coordinates":[7.6093557146877,47.54435037479335],"type":"Point"}
}