{
  "type": "Feature",
  "properties": {
    "gn:admin1_code":"SG",
    "gn:admin2_code":"1726.0",
    "gn:admin3_code":"3342.0",
    "gn:asciiname":"Letzi",
    "gn:country_code":"CH",
    "gn:dem":615,
    "gn:feature_class":"P",
    "gn:feature_code":"PPLL",
    "gn:name":"Letzi",
    "gn:population":0,
    "gn:timezone":"Europe/Zurich",
    "iso:country":"CH",
    "name:als_x_preferred":[
        "Letzi"
    ],
    "name:deu_x_preferred":[
        "Letzi"
    ],
    "name:deu_x_variant":[
        "Talsperre"
    ],
    "name:slv_x_preferred":[
        "Dolinska pregrada"
    ],
    "wof:lang_x_official":[
        "deu",
        "fra",
        "gsw",
        "ita"
    ],
    "wof:lang_x_spoken":[
        "deu",
        "fra",
        "gsw",
        "ita",
        "roh"
    ],
    "wof:name":"Letzi",
    "wof:placetype":"neighbourhood"
},
  "geometry": {"coordinates":[8.94468,47.25481],"type":"Point"}
}