{
  "type": "Feature",
  "properties": {
    "gn:admin1_code":"FR",
    "gn:admin2_code":"1002.0",
    "gn:admin3_code":"2113.0",
    "gn:asciiname":"Le Sapaley",
    "gn:country_code":"CH",
    "gn:dem":903,
    "gn:feature_class":"P",
    "gn:feature_code":"PPL",
    "gn:name":"Le Sapaley",
    "gn:population":0,
    "gn:timezone":"Europe/Zurich",
    "iso:country":"CH",
    "name:fra_x_preferred":[
        "Le Sapaley"
    ],
    "wof:name":"Le Sapaley",
    "wof:placetype":"neighbourhood"
},
  "geometry": {"coordinates":[6.93691,46.62066],"type":"Point"}
}