{
  "type": "Feature",
  "properties": {
    "gn:admin1_code":"FR",
    "gn:admin2_code":"1002.0",
    "gn:admin3_code":"2102.0",
    "gn:asciiname":"Pra Jordan",
    "gn:country_code":"CH",
    "gn:dem":829,
    "gn:feature_class":"P",
    "gn:feature_code":"PPL",
    "gn:name":"Pra Jordan",
    "gn:population":0,
    "gn:timezone":"Europe/Zurich",
    "iso:country":"CH",
    "name:fra_x_preferred":[
        "Pra Jordan"
    ],
    "wof:name":"Pra Jordan",
    "wof:placetype":"neighbourhood"
},
  "geometry": {"coordinates":[6.86484,46.62044],"type":"Point"}
}