{
  "type": "Feature",
  "properties": {
    "iso:country":"CH",
    "wof:name":"Iselin",
    "wof:placetype":"neighbourhood"
},
  "geometry": {"coordinates":[7.56483817519878,47.56163219084914],"type":"Point"}
}