{
  "type": "Feature",
  "properties": {
    "gn:admin1_code":"SG",
    "gn:admin2_code":"1724.0",
    "gn:admin3_code":"3273.0",
    "gn:asciiname":"Ober Stofel",
    "gn:country_code":"CH",
    "gn:dem":1200,
    "gn:feature_class":"P",
    "gn:feature_code":"PPLL",
    "gn:name":"Ober Stofel",
    "gn:population":0,
    "gn:timezone":"Europe/Zurich",
    "iso:country":"CH",
    "name:deu_x_preferred":[
        "Ober Stofel"
    ],
    "wof:name":"Ober Stofel",
    "wof:placetype":"neighbourhood"
},
  "geometry": {"coordinates":[9.37708,47.16111],"type":"Point"}
}