{
  "type": "Feature",
  "properties": {
    "gn:admin1_code":"FR",
    "gn:admin2_code":"1007.0",
    "gn:admin3_code":"2335.0",
    "gn:asciiname":"Les Preises",
    "gn:country_code":"CH",
    "gn:dem":902,
    "gn:feature_class":"P",
    "gn:feature_code":"PPL",
    "gn:name":"Les Preises",
    "gn:population":0,
    "gn:timezone":"Europe/Zurich",
    "iso:country":"CH",
    "name:fra_x_preferred":[
        "Les Preises"
    ],
    "wof:name":"Les Preises",
    "wof:placetype":"neighbourhood"
},
  "geometry": {"coordinates":[6.88893,46.59258],"type":"Point"}
}