{
  "type": "Feature",
  "properties": {
    "gn:admin1_code":"GR",
    "gn:admin2_code":"1841.0",
    "gn:admin3_code":"3521.0",
    "gn:asciiname":"Tuors Davant",
    "gn:country_code":"CH",
    "gn:dem":1717,
    "gn:feature_class":"P",
    "gn:feature_code":"PPL",
    "gn:name":"Tuors Davant",
    "gn:population":0,
    "gn:timezone":"Europe/Zurich",
    "iso:country":"CH",
    "name:roh_x_preferred":[
        "Tuors Davant"
    ],
    "wof:lang_x_official":[
        "deu",
        "fra",
        "gsw",
        "ita"
    ],
    "wof:lang_x_spoken":[
        "deu",
        "fra",
        "gsw",
        "ita",
        "roh"
    ],
    "wof:name":"Tuors Davant",
    "wof:placetype":"neighbourhood"
},
  "geometry": {"coordinates":[9.80197,46.64337],"type":"Point"}
}