{
  "type": "Feature",
  "properties": {
    "gn:admin1_code":"ZH",
    "gn:admin2_code":"110.0",
    "gn:admin3_code":"222.0",
    "gn:asciiname":"Schauenberg",
    "gn:country_code":"CH",
    "gn:dem":861,
    "gn:feature_class":"P",
    "gn:feature_code":"PPLL",
    "gn:name":"Schauenberg",
    "gn:population":0,
    "gn:timezone":"Europe/Zurich",
    "iso:country":"CH",
    "name:deu_x_preferred":[
        "Schauenberg"
    ],
    "wof:name":"Schauenberg",
    "wof:placetype":"neighbourhood"
},
  "geometry": {"coordinates":[8.86683,47.46111],"type":"Point"}
}