{
  "type": "Feature",
  "properties": {
    "gn:admin1_code":"LU",
    "gn:admin2_code":"315.0",
    "gn:admin3_code":"1135.0",
    "gn:asciiname":"Mittelhumbel",
    "gn:country_code":"CH",
    "gn:dem":942,
    "gn:feature_class":"P",
    "gn:feature_code":"PPLL",
    "gn:name":"Mittelhumbel",
    "gn:population":0,
    "gn:timezone":"Europe/Zurich",
    "iso:country":"CH",
    "name:deu_x_preferred":[
        "Mittelhumbel"
    ],
    "wof:name":"Mittelhumbel",
    "wof:placetype":"neighbourhood"
},
  "geometry": {"coordinates":[7.91646,47.03361],"type":"Point"}
}