{
  "type": "Feature",
  "properties": {
    "gn:gn_country":"CH",
    "gn:gn_fcode":"PPL",
    "gn:gn_pop":1158,
    "gn:population":1158,
    "iso:country":"CH",
    "name:alb_x_preferred":[
        "Baltschieder"
    ],
    "name:baq_x_preferred":[
        "Baltschieder"
    ],
    "name:cat_x_preferred":[
        "Baltschieder"
    ],
    "name:chi_x_preferred":[
        "\u5df4\u723e\u5947\u5fb7\u723e"
    ],
    "name:dut_x_preferred":[
        "Baltschieder"
    ],
    "name:eng_x_preferred":[
        "Baltschieder"
    ],
    "name:epo_x_preferred":[
        "Baltschieder"
    ],
    "name:fre_x_preferred":[
        "Baltschieder"
    ],
    "name:ger_x_preferred":[
        "Baltschieder"
    ],
    "name:glg_x_preferred":[
        "Baltschieder"
    ],
    "name:hun_x_preferred":[
        "Baltschieder"
    ],
    "name:ita_x_preferred":[
        "Baltschieder"
    ],
    "name:lat_x_preferred":[
        "Ponczirrum"
    ],
    "name:lmo_x_preferred":[
        "Baltschieder"
    ],
    "name:may_x_preferred":[
        "Baltschieder"
    ],
    "name:nno_x_preferred":[
        "Baltschieder"
    ],
    "name:oci_x_preferred":[
        "Baltschieder"
    ],
    "name:pms_x_preferred":[
        "Baltschieder"
    ],
    "name:por_x_preferred":[
        "Baltschieder"
    ],
    "name:roh_x_preferred":[
        "Baltschieder"
    ],
    "name:spa_x_preferred":[
        "Baltschieder"
    ],
    "name:swe_x_preferred":[
        "Baltschieder"
    ],
    "name:vol_x_preferred":[
        "Baltschieder"
    ],
    "name:war_x_preferred":[
        "Baltschieder"
    ],
    "name:zho_x_preferred":[
        "\u5df4\u723e\u5947\u5fb7\u723e"
    ],
    "qs_pg:aaroncc":"CH",
    "qs_pg:gn_country":"CH",
    "qs_pg:gn_fcode":"PPL",
    "qs_pg:gn_pop":1158,
    "qs_pg:name":"Baltschieder",
    "qs_pg:name_adm0":"Schweiz",
    "qs_pg:name_adm1":"Canton de Valais",
    "qs_pg:photos":49,
    "qs_pg:photos_1k":10,
    "qs_pg:photos_9k":1,
    "qs_pg:photos_9r":2,
    "qs_pg:photos_all":49,
    "qs_pg:photos_sr":2,
    "qs_pg:pop_sr":3,
    "qs_pg:qs_pg_placetype":"locality",
    "qs_pg:qs_pg_placetype_gp":"Town",
    "qs_pg:woe_adm0":23424957,
    "woe:adm0_id":23424957,
    "woe:name_adm0":"Schweiz",
    "woe:name_adm1":"Canton de Valais",
    "woe:placetype":"Town",
    "wof:name":"Baltschieder",
    "wof:placetype":"locality",
    "wof:population":1158
},
  "geometry": {"coordinates":[7.8657,46.30888],"type":"Point"}
}