{
  "type": "Feature",
  "properties": {
    "gn:admin1_code":"BL",
    "gn:admin2_code":"1303.0",
    "gn:admin3_code":"2830.0",
    "gn:asciiname":"Lupsingen",
    "gn:country_code":"CH",
    "gn:dem":474,
    "gn:feature_class":"P",
    "gn:feature_code":"PPL",
    "gn:name":"Lupsingen",
    "gn:population":0,
    "gn:timezone":"Europe/Zurich",
    "iso:country":"CH",
    "name:kaz_x_preferred":[
        "\u041b\u0443\u043f\u0437\u0438\u043d\u0433\u0435\u043d"
    ],
    "name:rus_x_preferred":[
        "\u041b\u0443\u043f\u0437\u0438\u043d\u0433\u0435\u043d"
    ],
    "name:zho_x_preferred":[
        "\u76e7\u666e\u8f9b\u6839"
    ],
    "wof:name":"Lupsingen",
    "wof:placetype":"locality"
},
  "geometry": {"coordinates":[7.69574,47.44433],"type":"Point"}
}