{
  "type": "Feature",
  "properties": {
    "gn:admin1_code":"BE",
    "gn:admin2_code":"243.0",
    "gn:admin3_code":"302.0",
    "gn:asciiname":"Aspi",
    "gn:country_code":"CH",
    "gn:dem":443,
    "gn:feature_class":"P",
    "gn:feature_code":"PPLL",
    "gn:name":"Aspi",
    "gn:population":0,
    "gn:timezone":"Europe/Zurich",
    "iso:country":"CH",
    "name:deu_x_preferred":[
        "Aspi"
    ],
    "wof:name":"Aspi",
    "wof:placetype":"neighbourhood"
},
  "geometry": {"coordinates":[7.23039,47.03548],"type":"Point"}
}