{
  "type": "Feature",
  "properties": {
    "gn:admin1_code":"TI",
    "gn:admin2_code":"2103.0",
    "gn:admin3_code":"5079.0",
    "gn:asciiname":"Catto",
    "gn:country_code":"CH",
    "gn:dem":1283,
    "gn:elevation":"1241.0",
    "gn:feature_class":"P",
    "gn:feature_code":"PPL",
    "gn:name":"Catto",
    "gn:population":0,
    "gn:timezone":"Europe/Zurich",
    "iso:country":"CH",
    "name:ita_x_preferred":[
        "Catto"
    ],
    "wof:lang_x_official":[
        "deu",
        "fra",
        "gsw",
        "ita"
    ],
    "wof:lang_x_spoken":[
        "deu",
        "fra",
        "gsw",
        "ita",
        "roh"
    ],
    "wof:name":"Catto",
    "wof:placetype":"neighbourhood"
},
  "geometry": {"coordinates":[8.73642,46.50475],"type":"Point"}
}