{
  "type": "Feature",
  "properties": {
    "gn:admin1_code":"AR",
    "gn:admin2_code":"1501.0",
    "gn:admin3_code":"3005.0",
    "gn:asciiname":"Altberg",
    "gn:country_code":"CH",
    "gn:dem":814,
    "gn:feature_class":"P",
    "gn:feature_code":"PPLL",
    "gn:name":"Altberg",
    "gn:population":0,
    "gn:timezone":"Europe/Zurich",
    "iso:country":"CH",
    "name:deu_x_preferred":[
        "Altberg"
    ],
    "wof:name":"Altberg",
    "wof:placetype":"locality"
},
  "geometry": {"coordinates":[9.34119,47.38308],"type":"Point"}
}