{
  "type": "Feature",
  "properties": {
    "gn:admin1_code":"AR",
    "gn:admin2_code":"1501.0",
    "gn:admin3_code":"3001.0",
    "gn:asciiname":"Flue",
    "gn:country_code":"CH",
    "gn:dem":871,
    "gn:feature_class":"P",
    "gn:feature_code":"PPLL",
    "gn:name":"Flue",
    "gn:population":0,
    "gn:timezone":"Europe/Zurich",
    "iso:country":"CH",
    "name:deu_x_preferred":[
        "Flue"
    ],
    "wof:name":"Flue",
    "wof:placetype":"locality"
},
  "geometry": {"coordinates":[9.25352,47.38406],"type":"Point"}
}