{
  "type": "Feature",
  "properties": {
    "gn:gn_country":"CH",
    "gn:gn_fcode":"PPL",
    "gn:gn_pop":179,
    "gn:population":179,
    "iso:country":"CH",
    "name:deu_x_preferred":[
        "Castasegna"
    ],
    "name:eng_x_preferred":[
        "Castasegna"
    ],
    "name:fra_x_preferred":[
        "Castasegna"
    ],
    "name:ita_x_preferred":[
        "Castasegna"
    ],
    "name:kaz_x_preferred":[
        "\u041a\u0430\u0441\u0442\u0430\u0437\u0435\u043d\u044c\u044f"
    ],
    "name:lat_x_preferred":[
        "Castexegnia"
    ],
    "name:lmo_x_preferred":[
        "Castascegna"
    ],
    "name:nld_x_preferred":[
        "Castasegna"
    ],
    "name:pms_x_preferred":[
        "Castasegna"
    ],
    "name:pnb_x_preferred":[
        "\u06a9\u0627\u0633\u0679\u0627\u0633\u06af\u0646\u0627"
    ],
    "name:pol_x_preferred":[
        "Castasegna"
    ],
    "name:por_x_preferred":[
        "Castasegna"
    ],
    "name:roh_x_preferred":[
        "Castasegna"
    ],
    "name:rus_x_preferred":[
        "\u041a\u0430\u0441\u0442\u0430\u0437\u0435\u043d\u044c\u044f"
    ],
    "name:spa_x_preferred":[
        "Castasegna"
    ],
    "name:swe_x_preferred":[
        "Castasegna"
    ],
    "name:uzb_x_preferred":[
        "Castasegna"
    ],
    "name:vec_x_preferred":[
        "Castaxegna"
    ],
    "name:vol_x_preferred":[
        "Castasegna"
    ],
    "qs_pg:aaroncc":"CH",
    "qs_pg:gn_country":"CH",
    "qs_pg:gn_fcode":"PPL",
    "qs_pg:gn_pop":179,
    "qs_pg:name":"Castasegna",
    "qs_pg:name_adm0":"Schweiz",
    "qs_pg:name_adm1":"Kanton Graub\u00fcnden",
    "qs_pg:photos":92,
    "qs_pg:photos_1k":19,
    "qs_pg:photos_9k":1,
    "qs_pg:photos_9r":3,
    "qs_pg:photos_all":92,
    "qs_pg:photos_sr":3,
    "qs_pg:pop_sr":1,
    "qs_pg:qs_pg_placetype":"locality",
    "qs_pg:qs_pg_placetype_gp":"Town",
    "qs_pg:woe_adm0":23424957,
    "woe:adm0_id":23424957,
    "woe:name_adm0":"Schweiz",
    "woe:name_adm1":"Kanton Graub\u00fcnden",
    "woe:placetype":"Town",
    "wof:name":"Castasegna",
    "wof:placetype":"locality",
    "wof:population":179
},
  "geometry": {"coordinates":[9.51785,46.33392],"type":"Point"}
}