{
  "type": "Feature",
  "properties": {
    "gn:admin1_code":"TI",
    "gn:admin2_code":"2102.0",
    "gn:admin3_code":"5048.0",
    "gn:asciiname":"Negrentino",
    "gn:country_code":"CH",
    "gn:dem":840,
    "gn:feature_class":"P",
    "gn:feature_code":"PPL",
    "gn:name":"Negrentino",
    "gn:population":0,
    "gn:timezone":"Europe/Zurich",
    "iso:country":"CH",
    "wof:name":"Negrentino",
    "wof:placetype":"neighbourhood"
},
  "geometry": {"coordinates":[8.92274,46.46499],"type":"Point"}
}