{
  "type": "Feature",
  "properties": {
    "gn:admin1_code":"GR",
    "gn:admin2_code":"1850.0",
    "gn:admin3_code":"3603.0",
    "gn:asciiname":"Travisasch",
    "gn:country_code":"CH",
    "gn:dem":1672,
    "gn:feature_class":"P",
    "gn:feature_code":"PPL",
    "gn:name":"Travisasch",
    "gn:population":0,
    "gn:timezone":"Europe/Zurich",
    "iso:country":"CH",
    "name:und_x_variant":[
        "Travesasch",
        "Travisasch"
    ],
    "wof:lang_x_official":[
        "deu",
        "fra",
        "gsw",
        "ita"
    ],
    "wof:lang_x_spoken":[
        "deu",
        "fra",
        "gsw",
        "ita",
        "roh"
    ],
    "wof:name":"Travisasch",
    "wof:placetype":"neighbourhood"
},
  "geometry": {"coordinates":[9.20471,46.66535],"type":"Point"}
}