{
  "type": "Feature",
  "properties": {
    "gn:gn_country":"CH",
    "gn:gn_fcode":"PPL",
    "gn:gn_pop":849,
    "gn:population":849,
    "iso:country":"CH",
    "name:baq_x_preferred":[
        "Ballaigues"
    ],
    "name:bel_x_preferred":[
        "\u0411\u0430\u043b\u0435\u0433"
    ],
    "name:cat_x_preferred":[
        "Ballaigues"
    ],
    "name:chi_x_preferred":[
        "\u5df4\u83b1\u683c"
    ],
    "name:dut_x_preferred":[
        "Ballaigues"
    ],
    "name:eng_x_preferred":[
        "Ballaigues"
    ],
    "name:epo_x_preferred":[
        "Ballaigues"
    ],
    "name:fre_x_preferred":[
        "Ballaigues"
    ],
    "name:ger_x_preferred":[
        "Ballaigues"
    ],
    "name:gsw_x_preferred":[
        "Ballaigues"
    ],
    "name:hun_x_preferred":[
        "Ballaigues"
    ],
    "name:ita_x_preferred":[
        "Ballaigues"
    ],
    "name:lmo_x_preferred":[
        "Ballaigues"
    ],
    "name:may_x_preferred":[
        "Ballaigues"
    ],
    "name:nno_x_preferred":[
        "Ballaigues"
    ],
    "name:oci_x_preferred":[
        "Ballaigues"
    ],
    "name:roh_x_preferred":[
        "Ballaigues"
    ],
    "name:unk_x_variant":[
        "Baillaigues"
    ],
    "name:vie_x_preferred":[
        "Ballaigues"
    ],
    "name:vol_x_preferred":[
        "Ballaigues"
    ],
    "name:zho_x_preferred":[
        "\u5df4\u83b1\u683c"
    ],
    "qs_pg:aaroncc":"CH",
    "qs_pg:gn_country":"CH",
    "qs_pg:gn_fcode":"PPL",
    "qs_pg:gn_pop":849,
    "qs_pg:name":"Ballaigues",
    "qs_pg:name_adm0":"Schweiz",
    "qs_pg:name_adm1":"Canton de Vaud",
    "qs_pg:photos":56,
    "qs_pg:photos_1k":11,
    "qs_pg:photos_9k":1,
    "qs_pg:photos_9r":2,
    "qs_pg:photos_all":56,
    "qs_pg:photos_sr":2,
    "qs_pg:pop_sr":2,
    "qs_pg:qs_pg_placetype":"locality",
    "qs_pg:qs_pg_placetype_gp":"Town",
    "qs_pg:woe_adm0":23424957,
    "woe:adm0_id":23424957,
    "woe:name_adm0":"Schweiz",
    "woe:name_adm1":"Canton de Vaud",
    "woe:placetype":"Town",
    "wof:name":"Ballaigues",
    "wof:placetype":"locality",
    "wof:population":849
},
  "geometry": {"coordinates":[6.41556,46.73055],"type":"Point"}
}