{
  "type": "Feature",
  "properties": {
    "gn:gn_country":"CH",
    "gn:gn_fcode":"PPLX",
    "gn:gn_pop":33820,
    "gn:population":33820,
    "iso:country":"CH",
    "qs_pg:aaroncc":"CH",
    "qs_pg:gn_country":"CH",
    "qs_pg:gn_fcode":"PPLX",
    "qs_pg:gn_pop":33820,
    "qs_pg:name":"Z\u00fcrich (Kreis 7)",
    "qs_pg:photos_9r":0,
    "qs_pg:photos_sr":0,
    "qs_pg:pop_sr":7,
    "qs_pg:qs_pg_placetype":"neighbourhood",
    "wof:name":"Z\u00fcrich (Kreis 7)",
    "wof:placetype":"neighbourhood",
    "wof:population":33820
},
  "geometry": {"coordinates":[8.58038,47.37328],"type":"Point"}
}