{
  "type": "Feature",
  "properties": {
    "gn:gn_country":"CH",
    "gn:gn_fcode":"PPL",
    "gn:gn_pop":473,
    "gn:population":473,
    "iso:country":"CH",
    "name:alb_x_preferred":[
        "Sch\u00f6nengrund"
    ],
    "name:baq_x_preferred":[
        "Sch\u00f6nengrund"
    ],
    "name:cat_x_preferred":[
        "Sch\u00f6nengrund"
    ],
    "name:chv_x_preferred":[
        "\u0428\u0451\u043d\u0435\u043d\u0433\u0440\u0443\u043d\u0434"
    ],
    "name:deu_x_preferred":[
        "Sch\u00f6nengrund"
    ],
    "name:dut_x_preferred":[
        "Sch\u00f6nengrund"
    ],
    "name:eng_x_preferred":[
        "Sch\u00f6nengrund"
    ],
    "name:epo_x_preferred":[
        "Sch\u00f6nengrund"
    ],
    "name:fra_x_preferred":[
        "Sch\u00f6nengrund"
    ],
    "name:fre_x_preferred":[
        "Sch\u00f6nengrund"
    ],
    "name:ger_x_preferred":[
        "Sch\u00f6nengrund"
    ],
    "name:gsw_x_preferred":[
        "Sch\u00f6negrond"
    ],
    "name:hun_x_preferred":[
        "Sch\u00f6nengrund"
    ],
    "name:ita_x_preferred":[
        "Sch\u00f6nengrund"
    ],
    "name:kaz_x_preferred":[
        "\u0428\u0451\u043d\u0435\u043d\u0433\u0440\u0443\u043d\u0434"
    ],
    "name:lmo_x_preferred":[
        "Sch\u00f6nengrund"
    ],
    "name:nno_x_preferred":[
        "Sch\u00f6nengrund"
    ],
    "name:oci_x_preferred":[
        "Sch\u00f6nengrund"
    ],
    "name:pms_x_preferred":[
        "Sch\u00f6nengrund"
    ],
    "name:pol_x_preferred":[
        "Sch\u00f6nengrund"
    ],
    "name:por_x_preferred":[
        "Sch\u00f6nengrund"
    ],
    "name:ron_x_preferred":[
        "Sch\u00f6nengrund"
    ],
    "name:rum_x_preferred":[
        "Sch\u00f6nengrund"
    ],
    "name:rus_x_preferred":[
        "\u0428\u0451\u043d\u0435\u043d\u0433\u0440\u0443\u043d\u0434"
    ],
    "name:spa_x_preferred":[
        "Sch\u00f6nengrund"
    ],
    "name:swe_x_preferred":[
        "Sch\u00f6nengrund"
    ],
    "name:uzb_x_preferred":[
        "Sch\u00f6nengrund"
    ],
    "name:vol_x_preferred":[
        "Sch\u00f6nengrund"
    ],
    "name:war_x_preferred":[
        "Sch\u00f6nengrund"
    ],
    "qs_pg:aaroncc":"CH",
    "qs_pg:gn_country":"CH",
    "qs_pg:gn_fcode":"PPL",
    "qs_pg:gn_pop":473,
    "qs_pg:name":"Sch\u00f6nengrund",
    "qs_pg:name_adm0":"Schweiz",
    "qs_pg:name_adm1":"Kanton Appenzell Ausserrhoden",
    "qs_pg:photos":2,
    "qs_pg:photos_1k":1,
    "qs_pg:photos_9k":1,
    "qs_pg:photos_9r":1,
    "qs_pg:photos_all":2,
    "qs_pg:photos_sr":1,
    "qs_pg:pop_sr":2,
    "qs_pg:qs_pg_placetype":"locality",
    "qs_pg:qs_pg_placetype_gp":"Town",
    "qs_pg:woe_adm0":23424957,
    "woe:adm0_id":23424957,
    "woe:name_adm0":"Schweiz",
    "woe:name_adm1":"Kanton Appenzell Ausserrhoden",
    "woe:placetype":"Town",
    "wof:name":"Sch\u00f6nengrund",
    "wof:placetype":"locality",
    "wof:population":473
},
  "geometry": {"coordinates":[9.2269,47.32786],"type":"Point"}
}