{
  "type": "Feature",
  "properties": {
    "gn:admin1_code":"BE",
    "gn:admin2_code":"248.0",
    "gn:admin3_code":"791.0",
    "gn:asciiname":"Bleiki",
    "gn:country_code":"CH",
    "gn:dem":1054,
    "gn:feature_class":"P",
    "gn:feature_code":"PPL",
    "gn:name":"Bleiki",
    "gn:population":0,
    "gn:timezone":"Europe/Zurich",
    "iso:country":"CH",
    "name:deu_x_preferred":[
        "Bleiki"
    ],
    "wof:name":"Bleiki",
    "wof:placetype":"locality"
},
  "geometry": {"coordinates":[7.36428,46.61536],"type":"Point"}
}