{
  "type": "Feature",
  "properties": {
    "gn:gn_country":"CH",
    "gn:gn_fcode":"PPL",
    "gn:gn_pop":1386,
    "gn:population":1386,
    "iso:country":"CH",
    "name:bul_x_preferred":[
        "\u0413\u0430\u043c\u043f\u0435\u043b"
    ],
    "name:deu_x_preferred":[
        "Gampel"
    ],
    "name:eng_x_preferred":[
        "Gampel"
    ],
    "name:fra_x_preferred":[
        "Gampel"
    ],
    "name:ita_x_preferred":[
        "Gampel"
    ],
    "name:lmo_x_preferred":[
        "Gampel"
    ],
    "name:nld_x_preferred":[
        "Gampel"
    ],
    "name:pms_x_preferred":[
        "Gampel"
    ],
    "name:por_x_preferred":[
        "Gampel"
    ],
    "name:roh_x_preferred":[
        "Gampel"
    ],
    "name:swe_x_preferred":[
        "Gampel"
    ],
    "name:vol_x_preferred":[
        "Gampel"
    ],
    "qs_pg:aaroncc":"CH",
    "qs_pg:gn_country":"CH",
    "qs_pg:gn_fcode":"PPL",
    "qs_pg:gn_pop":1386,
    "qs_pg:name":"Gampel",
    "qs_pg:name_adm0":"Schweiz",
    "qs_pg:name_adm1":"Canton de Valais",
    "qs_pg:photos":822,
    "qs_pg:photos_1k":167,
    "qs_pg:photos_9k":4,
    "qs_pg:photos_9r":6,
    "qs_pg:photos_all":822,
    "qs_pg:photos_sr":9,
    "qs_pg:pop_sr":3,
    "qs_pg:qs_pg_placetype":"locality",
    "qs_pg:qs_pg_placetype_gp":"Town",
    "qs_pg:woe_adm0":23424957,
    "woe:adm0_id":23424957,
    "woe:name_adm0":"Schweiz",
    "woe:name_adm1":"Canton de Valais",
    "woe:placetype":"Town",
    "wof:name":"Gampel",
    "wof:placetype":"locality",
    "wof:population":1386
},
  "geometry": {"coordinates":[7.7421,46.31599],"type":"Point"}
}