{
  "type": "Feature",
  "properties": {
    "gn:gn_country":"CH",
    "gn:gn_fcode":"PPL",
    "gn:gn_pop":417,
    "gn:population":417,
    "iso:country":"CH",
    "name:bul_x_preferred":[
        "\u0410\u0443\u0440\u0438\u0433\u0435\u043d\u043e"
    ],
    "name:dut_x_preferred":[
        "Aurigeno"
    ],
    "name:eng_x_preferred":[
        "Aurigeno"
    ],
    "name:fre_x_preferred":[
        "Aurigeno"
    ],
    "name:ger_x_preferred":[
        "Aurigeno"
    ],
    "name:hrv_x_preferred":[
        "Aurigeno"
    ],
    "name:ita_x_preferred":[
        "Aurigeno"
    ],
    "name:lmo_x_preferred":[
        "Aurigen"
    ],
    "name:roh_x_preferred":[
        "Aurigeno"
    ],
    "name:swe_x_preferred":[
        "Aurigeno"
    ],
    "qs_pg:aaroncc":"CH",
    "qs_pg:gn_country":"CH",
    "qs_pg:gn_fcode":"PPL",
    "qs_pg:gn_pop":417,
    "qs_pg:name":"Aurigeno",
    "qs_pg:name_adm0":"Schweiz",
    "qs_pg:name_adm1":"Cantone Ticino",
    "qs_pg:photos":40,
    "qs_pg:photos_1k":8,
    "qs_pg:photos_9k":1,
    "qs_pg:photos_9r":2,
    "qs_pg:photos_all":40,
    "qs_pg:photos_sr":2,
    "qs_pg:pop_sr":2,
    "qs_pg:qs_pg_placetype":"locality",
    "qs_pg:qs_pg_placetype_gp":"Town",
    "qs_pg:woe_adm0":23424957,
    "woe:adm0_id":23424957,
    "woe:name_adm0":"Schweiz",
    "woe:name_adm1":"Cantone Ticino",
    "woe:placetype":"Town",
    "wof:name":"Aurigeno",
    "wof:placetype":"locality",
    "wof:population":417
},
  "geometry": {"coordinates":[8.71222,46.23199],"type":"Point"}
}