{
  "type": "Feature",
  "properties": {
    "gn:country":"CH",
    "gn:fcode":"PPLX",
    "gn:population":211,
    "iso:country":"CH",
    "name:eng_x_preferred":[
        "B\u00fcel"
    ],
    "name:eng_x_variant":[
        "Sellenb\u00fcren / B\u00fcel"
    ],
    "qs_pg:aaroncc":"CH",
    "qs_pg:gn_country":"CH",
    "qs_pg:gn_fcode":"PPLX",
    "qs_pg:gn_pop":211,
    "qs_pg:name":"Sellenb\u00fcren / B\u00fcel",
    "qs_pg:photos_9r":0,
    "qs_pg:photos_sr":0,
    "qs_pg:pop_sr":2,
    "qs_pg:qs_pg_placetype":"neighbourhood",
    "wof:lang_x_official":[
        "deu",
        "fra",
        "gsw",
        "ita"
    ],
    "wof:lang_x_spoken":[
        "deu",
        "fra",
        "gsw",
        "ita",
        "roh"
    ],
    "wof:name":"B\u00fcel",
    "wof:placetype":"neighbourhood",
    "wof:population":211
},
  "geometry": {"coordinates":[8.48172,47.34656],"type":"Point"}
}