{
  "type": "Feature",
  "properties": {
    "gn:admin1_code":"VD",
    "gn:admin2_code":"2227.0",
    "gn:admin3_code":"5426.0",
    "gn:asciiname":"Bougy-Villars",
    "gn:country_code":"CH",
    "gn:dem":613,
    "gn:feature_class":"P",
    "gn:feature_code":"PPL",
    "gn:name":"Bougy-Villars",
    "gn:population":0,
    "gn:timezone":"Europe/Zurich",
    "iso:country":"CH",
    "wof:name":"Bougy-Villars",
    "wof:placetype":"locality"
},
  "geometry": {"coordinates":[6.35359,46.48188],"type":"Point"}
}