{
  "type": "Feature",
  "properties": {
    "gn:gn_country":"CH",
    "gn:gn_fcode":"PPLX",
    "gn:gn_pop":1391,
    "gn:population":1391,
    "iso:country":"CH",
    "name:eng_x_preferred":[
        "Horainli"
    ],
    "name:eng_x_variant":[
        "Kloten / Horainli"
    ],
    "name:unk_x_variant":[
        "Horainli"
    ],
    "qs_pg:aaroncc":"CH",
    "qs_pg:gn_country":"CH",
    "qs_pg:gn_fcode":"PPLX",
    "qs_pg:gn_pop":1391,
    "qs_pg:name":"Kloten / Horainli",
    "qs_pg:photos_9r":0,
    "qs_pg:photos_sr":0,
    "qs_pg:pop_sr":3,
    "qs_pg:qs_pg_placetype":"neighbourhood",
    "wof:name":"Horainli",
    "wof:placetype":"neighbourhood",
    "wof:population":1391
},
  "geometry": {"coordinates":[8.58306,47.45399],"type":"Point"}
}