{
  "type": "Feature",
  "properties": {
    "gn:admin1_code":"TG",
    "gn:admin2_code":"2013.0",
    "gn:admin3_code":"4671.0",
    "gn:asciiname":"Mellgenten",
    "gn:country_code":"CH",
    "gn:dem":482,
    "gn:feature_class":"P",
    "gn:feature_code":"PPLL",
    "gn:name":"Mellgenten",
    "gn:population":0,
    "gn:timezone":"Europe/Zurich",
    "iso:country":"CH",
    "name:deu_x_preferred":[
        "Mellgenten"
    ],
    "wof:name":"Mellgenten",
    "wof:placetype":"neighbourhood"
},
  "geometry": {"coordinates":[9.19258,47.63279],"type":"Point"}
}