{
  "type": "Feature",
  "properties": {
    "gn:admin1_code":"NW",
    "gn:admin2_code":"700.0",
    "gn:admin3_code":"1511.0",
    "gn:asciiname":"Hinter Diegisbalm",
    "gn:country_code":"CH",
    "gn:dem":950,
    "gn:feature_class":"P",
    "gn:feature_code":"PPL",
    "gn:name":"Hinter Diegisbalm",
    "gn:population":0,
    "gn:timezone":"Europe/Zurich",
    "iso:country":"CH",
    "wof:name":"Hinter Diegisbalm",
    "wof:placetype":"neighbourhood"
},
  "geometry": {"coordinates":[8.37342,46.89417],"type":"Point"}
}