{
  "type": "Feature",
  "properties": {
    "gn:admin1_code":"GE",
    "gn:admin2_code":"2500.0",
    "gn:admin3_code":"6604.0",
    "gn:asciiname":"Sezegnin",
    "gn:country_code":"CH",
    "gn:dem":419,
    "gn:feature_class":"P",
    "gn:feature_code":"PPL",
    "gn:name":"S\u00e9zegnin",
    "gn:population":0,
    "gn:timezone":"Europe/Paris",
    "iso:country":"CH",
    "name:und_x_variant":[
        "S\u00e9zegnin"
    ],
    "wof:name":"Sezegnin",
    "wof:placetype":"neighbourhood"
},
  "geometry": {"coordinates":[6.00672,46.14485],"type":"Point"}
}