{
  "type": "Feature",
  "properties": {
    "gn:admin1_code":"JU",
    "gn:admin2_code":"2601.0",
    "gn:admin3_code":"6729.0",
    "gn:asciiname":"Sceut",
    "gn:country_code":"CH",
    "gn:dem":882,
    "gn:elevation":"870.0",
    "gn:feature_class":"P",
    "gn:feature_code":"PPL",
    "gn:name":"Sceut",
    "gn:population":0,
    "gn:timezone":"Europe/Zurich",
    "iso:country":"CH",
    "wof:lang_x_official":[
        "deu",
        "fra",
        "gsw",
        "ita"
    ],
    "wof:lang_x_spoken":[
        "deu",
        "fra",
        "gsw",
        "ita",
        "roh"
    ],
    "wof:name":"Sceut",
    "wof:placetype":"neighbourhood"
},
  "geometry": {"coordinates":[7.15303,47.31844],"type":"Point"}
}