{
  "type": "Feature",
  "properties": {
    "gn:gn_country":"CH",
    "gn:gn_fcode":"PPL",
    "gn:gn_pop":15230,
    "gn:population":15230,
    "iso:country":"CH",
    "name:ara_x_preferred":[
        "\u0623\u062f\u0644\u064a\u0633\u0648\u064a\u0644"
    ],
    "name:cat_x_preferred":[
        "Adliswil"
    ],
    "name:ces_x_preferred":[
        "Adliswil"
    ],
    "name:chv_x_preferred":[
        "\u0410\u0434\u043b\u0438\u0441\u0432\u0438\u043b\u044c"
    ],
    "name:dan_x_preferred":[
        "Adliswil"
    ],
    "name:deu_x_preferred":[
        "Adliswil"
    ],
    "name:eng_x_preferred":[
        "Adliswil"
    ],
    "name:epo_x_preferred":[
        "Adliswil"
    ],
    "name:eus_x_preferred":[
        "Adliswil"
    ],
    "name:fas_x_preferred":[
        "\u0627\u062f\u0644\u06cc\u0632\u0648\u06cc\u0644"
    ],
    "name:fra_x_preferred":[
        "Adliswil"
    ],
    "name:gsw_x_preferred":[
        "Adlischwiil"
    ],
    "name:hun_x_preferred":[
        "Adliswil"
    ],
    "name:ind_x_preferred":[
        "Adliswil"
    ],
    "name:ita_x_preferred":[
        "Adliswil"
    ],
    "name:jav_x_preferred":[
        "Adliswil"
    ],
    "name:jpn_x_preferred":[
        "\u30a2\u30c9\u30eb\u30b9\u30f4\u30a3\u30eb"
    ],
    "name:kaz_x_preferred":[
        "\u0410\u0434\u043b\u0438\u0441\u0432\u0438\u043b\u044c"
    ],
    "name:lit_x_preferred":[
        "Adlisvilas"
    ],
    "name:lmo_x_preferred":[
        "Adliswil"
    ],
    "name:msa_x_preferred":[
        "Adliswil"
    ],
    "name:nan_x_preferred":[
        "Adliswil"
    ],
    "name:nld_x_preferred":[
        "Adliswil"
    ],
    "name:nno_x_preferred":[
        "Adliswil"
    ],
    "name:nob_x_preferred":[
        "Adliswil"
    ],
    "name:oci_x_preferred":[
        "Adliswil"
    ],
    "name:pms_x_preferred":[
        "Adliswil"
    ],
    "name:pol_x_preferred":[
        "Adliswil"
    ],
    "name:por_x_preferred":[
        "Adliswil"
    ],
    "name:rus_x_preferred":[
        "\u0410\u0434\u043b\u0438\u0441\u0432\u0438\u043b\u044c"
    ],
    "name:spa_x_preferred":[
        "Adliswil"
    ],
    "name:swe_x_preferred":[
        "Adliswil"
    ],
    "name:ukr_x_preferred":[
        "\u0410\u0434\u043b\u0456\u0441\u0432\u0456\u043b\u044c"
    ],
    "name:uzb_x_preferred":[
        "Adliswil"
    ],
    "name:vec_x_preferred":[
        "Adliswil"
    ],
    "name:vol_x_preferred":[
        "Adliswil"
    ],
    "name:war_x_preferred":[
        "Adliswil"
    ],
    "name:zho_x_preferred":[
        "\u963f\u5fb7\u5229\u65af\u7dad\u723e"
    ],
    "qs_pg:aaroncc":"CH",
    "qs_pg:gn_country":"CH",
    "qs_pg:gn_fcode":"PPL",
    "qs_pg:gn_pop":15230,
    "qs_pg:name":"Adliswil",
    "qs_pg:name_adm0":"Schweiz",
    "qs_pg:name_adm1":"Kanton Z\u00fcrich",
    "qs_pg:photos":168,
    "qs_pg:photos_1k":34,
    "qs_pg:photos_9k":1,
    "qs_pg:photos_9r":4,
    "qs_pg:photos_all":168,
    "qs_pg:photos_sr":4,
    "qs_pg:pop_sr":6,
    "qs_pg:qs_pg_placetype":"locality",
    "qs_pg:qs_pg_placetype_gp":"Town",
    "qs_pg:woe_adm0":23424957,
    "woe:adm0_id":23424957,
    "woe:name_adm0":"Schweiz",
    "woe:name_adm1":"Kanton Z\u00fcrich",
    "woe:placetype":"Town",
    "wof:name":"Adliswil",
    "wof:placetype":"locality",
    "wof:population":15230
},
  "geometry": {"coordinates":[8.52462,47.30997],"type":"Point"}
}