{
  "type": "Feature",
  "properties": {
    "gn:gn_country":"CH",
    "gn:gn_fcode":"PPL",
    "gn:gn_pop":344,
    "gn:population":344,
    "iso:country":"CH",
    "name:ara_x_preferred":[
        "\u0641\u064a\u0644\u062f\u0628\u0631\u063a"
    ],
    "name:baq_x_preferred":[
        "Wildberg"
    ],
    "name:cat_x_preferred":[
        "Wildberg"
    ],
    "name:chi_x_preferred":[
        "\u7dad\u5fb7\u4f2f\u683c"
    ],
    "name:chv_x_preferred":[
        "\u0412\u0438\u043b\u044c\u0434\u0431\u0435\u0440\u0433"
    ],
    "name:dut_x_preferred":[
        "Wildberg"
    ],
    "name:eng_x_preferred":[
        "Wildberg"
    ],
    "name:epo_x_preferred":[
        "Wildberg ZH"
    ],
    "name:fre_x_preferred":[
        "Wildberg"
    ],
    "name:ger_x_preferred":[
        "Wildberg"
    ],
    "name:gsw_x_preferred":[
        "Wildb\u00e8\u00e8rg"
    ],
    "name:hun_x_preferred":[
        "Wildberg"
    ],
    "name:ita_x_preferred":[
        "Wildberg"
    ],
    "name:kaz_x_preferred":[
        "\u0412\u0438\u043b\u044c\u0434\u0431\u0435\u0440\u0433"
    ],
    "name:lmo_x_preferred":[
        "Wildberg"
    ],
    "name:may_x_preferred":[
        "Wildberg"
    ],
    "name:nno_x_preferred":[
        "Wildberg i Sveits"
    ],
    "name:oci_x_preferred":[
        "Wildberg"
    ],
    "name:pms_x_preferred":[
        "Wildberg"
    ],
    "name:por_x_preferred":[
        "Wildberg"
    ],
    "name:rus_x_preferred":[
        "\u0412\u0438\u043b\u044c\u0434\u0431\u0435\u0440\u0433"
    ],
    "name:uzb_x_preferred":[
        "Wildberg"
    ],
    "name:vol_x_preferred":[
        "Wildberg"
    ],
    "name:war_x_preferred":[
        "Wildberg"
    ],
    "qs_pg:aaroncc":"CH",
    "qs_pg:gn_country":"CH",
    "qs_pg:gn_fcode":"PPL",
    "qs_pg:gn_pop":344,
    "qs_pg:name":"Wildberg",
    "qs_pg:name_adm0":"Schweiz",
    "qs_pg:name_adm1":"Kanton Z\u00fcrich",
    "qs_pg:photos_9k":1,
    "qs_pg:photos_9r":1,
    "qs_pg:photos_all":24,
    "qs_pg:photos_sr":0,
    "qs_pg:pop_sr":2,
    "qs_pg:qs_pg_placetype":"locality",
    "qs_pg:qs_pg_placetype_gp":"Town",
    "qs_pg:woe_adm0":23424957,
    "woe:adm0_id":23424957,
    "woe:name_adm0":"Schweiz",
    "woe:name_adm1":"Kanton Z\u00fcrich",
    "woe:placetype":"Town",
    "wof:name":"Wildberg",
    "wof:placetype":"locality",
    "wof:population":344
},
  "geometry": {"coordinates":[8.81669,47.42585],"type":"Point"}
}