{
  "type": "Feature",
  "properties": {
    "iso:country":"CH",
    "name:dan_x_preferred":[
        "M\u00e5tte"
    ],
    "name:deu_x_preferred":[
        "Matte"
    ],
    "name:deu_x_variant":[
        "Mattequartier",
        "Schwarzes Quartier"
    ],
    "name:eng_x_preferred":[
        "Mattequartier"
    ],
    "name:epo_x_preferred":[
        "Matte"
    ],
    "name:fra_x_preferred":[
        "Matte"
    ],
    "name:swe_x_preferred":[
        "Matte"
    ],
    "qs:gn_adm0_cc":"CH",
    "qs:gn_local":2661552,
    "qs:gn_nam_loc":"Bern",
    "qs:gn_namadm1":"BE",
    "qs:local_max":19074,
    "qs:local_sum":54499,
    "qs:localhoods":30,
    "qs:name":"Matte",
    "qs:name_adm0":"Schweiz",
    "qs:name_adm1":"Kanton Bern",
    "qs:name_adm2":"Bern-Mittelland",
    "qs:name_lau":"Bern",
    "qs:name_local":"Bern",
    "qs:photo_max":4893,
    "qs:photo_sum":19074,
    "qs:placetype":"Suburb",
    "qs:quad_count":68,
    "qs:woe_adm0":23424957,
    "qs:woe_adm1":2347087,
    "qs:woe_adm2":56558125,
    "qs:woe_lau":12682693,
    "qs:woe_local":781788,
    "qs:woe_ver":"7.10.0",
    "wd:wordcount":213,
    "wof:lang":[
        "ger"
    ],
    "wof:name":"Matte",
    "wof:placetype":"neighbourhood"
},
  "geometry": {"coordinates":[7.456079,46.946495],"type":"Point"}
}