{
  "type": "Feature",
  "properties": {
    "gn:admin1_code":"FR",
    "gn:admin2_code":"1002.0",
    "gn:admin3_code":"2086.0",
    "gn:asciiname":"Massonnens",
    "gn:country_code":"CH",
    "gn:dem":758,
    "gn:feature_class":"P",
    "gn:feature_code":"PPL",
    "gn:name":"Massonnens",
    "gn:population":0,
    "gn:timezone":"Europe/Zurich",
    "iso:country":"CH",
    "wof:name":"Massonnens",
    "wof:placetype":"locality"
},
  "geometry": {"coordinates":[6.97396,46.69822],"type":"Point"}
}