{
  "type": "Feature",
  "properties": {
    "gn:gn_country":"CH",
    "gn:gn_fcode":"PPL",
    "gn:gn_pop":1006,
    "gn:population":1006,
    "iso:country":"CH",
    "name:alb_x_preferred":[
        "Vorderthal"
    ],
    "name:baq_x_preferred":[
        "Vorderthal"
    ],
    "name:cat_x_preferred":[
        "Vorderthal"
    ],
    "name:deu_x_preferred":[
        "Vorderthal"
    ],
    "name:dut_x_preferred":[
        "Vorderthal"
    ],
    "name:eng_x_preferred":[
        "Vorderthal"
    ],
    "name:epo_x_preferred":[
        "Vorderthal"
    ],
    "name:fre_x_preferred":[
        "Vorderthal"
    ],
    "name:ger_x_preferred":[
        "Vorderthal"
    ],
    "name:hun_x_preferred":[
        "Vorderthal"
    ],
    "name:ita_x_preferred":[
        "Vorderthal"
    ],
    "name:kaz_x_preferred":[
        "\u0424\u043e\u0440\u0434\u0435\u0440\u0442\u0430\u043b\u044c"
    ],
    "name:lmo_x_preferred":[
        "Vorderthal"
    ],
    "name:nno_x_preferred":[
        "Vorderthal"
    ],
    "name:oci_x_preferred":[
        "Vorderthal"
    ],
    "name:pms_x_preferred":[
        "Vorderthal"
    ],
    "name:por_x_preferred":[
        "Vorderthal"
    ],
    "name:rus_x_preferred":[
        "\u0424\u043e\u0440\u0434\u0435\u0440\u0442\u0430\u043b\u044c"
    ],
    "name:spa_x_preferred":[
        "Vorderthal"
    ],
    "name:unk_x_variant":[
        "Vordertal"
    ],
    "name:uzb_x_preferred":[
        "Vorderthal"
    ],
    "name:vol_x_preferred":[
        "Vorderthal"
    ],
    "name:war_x_preferred":[
        "Vorderthal"
    ],
    "qs_pg:aaroncc":"CH",
    "qs_pg:gn_country":"CH",
    "qs_pg:gn_fcode":"PPL",
    "qs_pg:gn_pop":1006,
    "qs_pg:name":"Vorderthal",
    "qs_pg:name_adm0":"Schweiz",
    "qs_pg:name_adm1":"Kanton Schwyz",
    "qs_pg:photos_9k":1,
    "qs_pg:photos_9r":1,
    "qs_pg:photos_all":2,
    "qs_pg:photos_sr":0,
    "qs_pg:pop_sr":3,
    "qs_pg:qs_pg_placetype":"locality",
    "qs_pg:qs_pg_placetype_gp":"Town",
    "qs_pg:woe_adm0":23424957,
    "woe:adm0_id":23424957,
    "woe:name_adm0":"Schweiz",
    "woe:name_adm1":"Kanton Schwyz",
    "woe:placetype":"Town",
    "wof:name":"Vorderthal",
    "wof:placetype":"locality",
    "wof:population":1006
},
  "geometry": {"coordinates":[8.90185,47.12092],"type":"Point"}
}