{
  "type": "Feature",
  "properties": {
    "gn:admin1_code":"LU",
    "gn:admin2_code":"313.0",
    "gn:admin3_code":"1033.0",
    "gn:asciiname":"Heitermatt",
    "gn:country_code":"CH",
    "gn:dem":416,
    "gn:feature_class":"P",
    "gn:feature_code":"PPLL",
    "gn:name":"Heitermatt",
    "gn:population":0,
    "gn:timezone":"Europe/Zurich",
    "iso:country":"CH",
    "name:deu_x_preferred":[
        "Heitermatt"
    ],
    "wof:name":"Heitermatt",
    "wof:placetype":"neighbourhood"
},
  "geometry": {"coordinates":[8.356,47.11928],"type":"Point"}
}