{
  "type": "Feature",
  "properties": {
    "gn:admin1_code":"BE",
    "gn:admin2_code":"246.0",
    "gn:admin3_code":"622.0",
    "gn:asciiname":"Oppligen",
    "gn:country_code":"CH",
    "gn:dem":570,
    "gn:feature_class":"P",
    "gn:feature_code":"PPL",
    "gn:name":"Oppligen",
    "gn:population":0,
    "gn:timezone":"Europe/Zurich",
    "iso:country":"CH",
    "wof:name":"Oppligen",
    "wof:placetype":"locality"
},
  "geometry": {"coordinates":[7.60074,46.81839],"type":"Point"}
}