{
  "type": "Feature",
  "properties": {
    "gn:country":"CH",
    "gn:fcode":"PPL",
    "gn:population":0,
    "iso:country":"CH",
    "name:deu_x_preferred":[
        "Branson"
    ],
    "name:epo_x_preferred":[
        "Branson"
    ],
    "name:fra_x_preferred":[
        "Branson"
    ],
    "name:ita_x_preferred":[
        "Branson"
    ],
    "name:jpn_x_preferred":[
        "\u30d6\u30e9\u30f3\u30bd\u30f3"
    ],
    "name:kor_x_preferred":[
        "\ube0c\ub79c\uc2a8"
    ],
    "name:nds_x_preferred":[
        "Branson"
    ],
    "name:nld_x_preferred":[
        "Branson"
    ],
    "name:pol_x_preferred":[
        "Branson"
    ],
    "name:por_x_preferred":[
        "Branson"
    ],
    "name:rus_x_preferred":[
        "\u0411\u0440\u044d\u043d\u0441\u043e\u043d"
    ],
    "name:swe_x_preferred":[
        "Branson"
    ],
    "name:szl_x_preferred":[
        "Branson"
    ],
    "name:ukr_x_preferred":[
        "\u0411\u0440\u0430\u043d\u0441\u043e\u043d"
    ],
    "name:vol_x_preferred":[
        "Branson"
    ],
    "qs_pg:aaroncc":"CH",
    "qs_pg:gn_country":"CH",
    "qs_pg:gn_fcode":"PPL",
    "qs_pg:gn_pop":0,
    "qs_pg:name":"Branson",
    "qs_pg:name_adm0":"Schweiz",
    "qs_pg:name_adm1":"Canton de Valais",
    "qs_pg:photos":56,
    "qs_pg:photos_1k":11,
    "qs_pg:photos_9k":1,
    "qs_pg:photos_9r":2,
    "qs_pg:photos_all":56,
    "qs_pg:photos_sr":2,
    "qs_pg:pop_sr":0,
    "qs_pg:qs_pg_placetype":"locality",
    "qs_pg:qs_pg_placetype_gp":"Town",
    "qs_pg:woe_adm0":23424957,
    "woe:adm0_id":23424957,
    "woe:name_adm0":"Schweiz",
    "woe:name_adm1":"Canton de Valais",
    "woe:placetype":"Town",
    "wof:lang_x_official":[
        "deu",
        "fra",
        "gsw",
        "ita"
    ],
    "wof:lang_x_spoken":[
        "deu",
        "fra",
        "gsw",
        "ita",
        "roh"
    ],
    "wof:name":"Branson",
    "wof:placetype":"neighbourhood"
},
  "geometry": {"coordinates":[7.0923,46.13089],"type":"Point"}
}