{
  "type": "Feature",
  "properties": {
    "gn:gn_country":"CH",
    "gn:gn_fcode":"PPL",
    "gn:gn_pop":3419,
    "gn:population":3419,
    "iso:country":"CH",
    "name:alb_x_preferred":[
        "Muhen"
    ],
    "name:baq_x_preferred":[
        "Muhen"
    ],
    "name:cat_x_preferred":[
        "Muhen"
    ],
    "name:chi_x_preferred":[
        "\u7a46\u4ea8"
    ],
    "name:dut_x_preferred":[
        "Muhen"
    ],
    "name:eng_x_preferred":[
        "Muhen"
    ],
    "name:epo_x_preferred":[
        "Muhen"
    ],
    "name:fre_x_preferred":[
        "Muhen"
    ],
    "name:ger_x_preferred":[
        "Muhen"
    ],
    "name:hun_x_preferred":[
        "Muhen"
    ],
    "name:ita_x_preferred":[
        "Muhen"
    ],
    "name:kaz_x_preferred":[
        "\u041c\u0443\u044d\u043d"
    ],
    "name:lmo_x_preferred":[
        "Muhen"
    ],
    "name:may_x_preferred":[
        "Muhen"
    ],
    "name:nno_x_preferred":[
        "Muhen"
    ],
    "name:oci_x_preferred":[
        "Muhen"
    ],
    "name:pms_x_preferred":[
        "Muhen"
    ],
    "name:pol_x_preferred":[
        "Muhen"
    ],
    "name:por_x_preferred":[
        "Muhen"
    ],
    "name:roh_x_preferred":[
        "Muhen"
    ],
    "name:rus_x_preferred":[
        "\u041c\u0443\u044d\u043d"
    ],
    "name:spa_x_preferred":[
        "Muhen"
    ],
    "name:swe_x_preferred":[
        "Muhen"
    ],
    "name:unk_x_variant":[
        "Mittel-Muhen"
    ],
    "name:uzb_x_preferred":[
        "Muhen"
    ],
    "name:vol_x_preferred":[
        "Muhen"
    ],
    "name:war_x_preferred":[
        "Muhen"
    ],
    "name:zho_x_preferred":[
        "\u7a46\u4ea8"
    ],
    "qs_pg:aaroncc":"CH",
    "qs_pg:gn_country":"CH",
    "qs_pg:gn_fcode":"PPL",
    "qs_pg:gn_pop":3419,
    "qs_pg:name":"Muhen",
    "qs_pg:name_adm0":"Schweiz",
    "qs_pg:name_adm1":"Kanton Aargau",
    "qs_pg:photos_9k":1,
    "qs_pg:photos_9r":1,
    "qs_pg:photos_all":7,
    "qs_pg:photos_sr":0,
    "qs_pg:pop_sr":4,
    "qs_pg:qs_pg_placetype":"locality",
    "qs_pg:qs_pg_placetype_gp":"Town",
    "qs_pg:woe_adm0":23424957,
    "woe:adm0_id":23424957,
    "woe:name_adm0":"Schweiz",
    "woe:name_adm1":"Kanton Aargau",
    "woe:placetype":"Town",
    "wof:name":"Muhen",
    "wof:placetype":"locality",
    "wof:population":3419
},
  "geometry": {"coordinates":[8.05408,47.33671],"type":"Point"}
}