{
  "type": "Feature",
  "properties": {
    "gn:admin1_code":"FR",
    "gn:admin2_code":"1005.0",
    "gn:admin3_code":"2275.0",
    "gn:asciiname":"Salvenach",
    "gn:country_code":"CH",
    "gn:dem":565,
    "gn:feature_class":"P",
    "gn:feature_code":"PPL",
    "gn:name":"Salvenach",
    "gn:population":0,
    "gn:timezone":"Europe/Zurich",
    "iso:country":"CH",
    "wof:name":"Salvenach",
    "wof:placetype":"locality"
},
  "geometry": {"coordinates":[7.15107,46.91289],"type":"Point"}
}