{
  "type": "Feature",
  "properties": {
    "gn:admin1_code":"TI",
    "gn:admin2_code":"2105.0",
    "gn:admin3_code":"5149.0",
    "gn:asciiname":"Banco",
    "gn:country_code":"CH",
    "gn:dem":577,
    "gn:feature_class":"P",
    "gn:feature_code":"PPL",
    "gn:name":"Banco",
    "gn:population":0,
    "gn:timezone":"Europe/Zurich",
    "iso:country":"CH",
    "name:ita_x_preferred":[
        "Banco"
    ],
    "wof:name":"Banco",
    "wof:placetype":"locality"
},
  "geometry": {"coordinates":[8.84522,46.00941],"type":"Point"}
}