{
  "type": "Feature",
  "properties": {
    "gn:gn_country":"CH",
    "gn:gn_fcode":"PPL",
    "gn:gn_pop":2252,
    "gn:population":2252,
    "iso:country":"CH",
    "name:alb_x_preferred":[
        "Udligenswil"
    ],
    "name:baq_x_preferred":[
        "Udligenswil"
    ],
    "name:cat_x_preferred":[
        "Udligenswil"
    ],
    "name:chi_x_preferred":[
        "\u70cf\u5fb7\u5229\u6839\u65af\u7dad\u723e"
    ],
    "name:dut_x_preferred":[
        "Udligenswil"
    ],
    "name:eng_x_preferred":[
        "Udligenswil"
    ],
    "name:epo_x_preferred":[
        "Udligenswil"
    ],
    "name:fre_x_preferred":[
        "Udligenswil"
    ],
    "name:ger_x_preferred":[
        "Udligenswil"
    ],
    "name:gsw_x_preferred":[
        "Udligenswil"
    ],
    "name:hun_x_preferred":[
        "Udligenswil"
    ],
    "name:ita_x_preferred":[
        "Udligenswil"
    ],
    "name:kaz_x_preferred":[
        "\u0423\u0434\u043b\u0438\u0433\u0435\u043d\u0441\u0432\u0438\u043b\u044c"
    ],
    "name:lmo_x_preferred":[
        "Udligenswil"
    ],
    "name:may_x_preferred":[
        "Udligenswil"
    ],
    "name:nno_x_preferred":[
        "Udligenswil"
    ],
    "name:oci_x_preferred":[
        "Udligenswil"
    ],
    "name:pms_x_preferred":[
        "Udligenswil"
    ],
    "name:por_x_preferred":[
        "Udligenswil"
    ],
    "name:rus_x_preferred":[
        "\u0423\u0434\u043b\u0438\u0433\u0435\u043d\u0441\u0432\u0438\u043b\u044c"
    ],
    "name:spa_x_preferred":[
        "Udligenswil"
    ],
    "name:uzb_x_preferred":[
        "Udligenswil"
    ],
    "name:vol_x_preferred":[
        "Udligenswil"
    ],
    "name:war_x_preferred":[
        "Udligenswil"
    ],
    "qs_pg:aaroncc":"CH",
    "qs_pg:gn_country":"CH",
    "qs_pg:gn_fcode":"PPL",
    "qs_pg:gn_pop":2252,
    "qs_pg:name":"Udligenswil",
    "qs_pg:name_adm0":"Schweiz",
    "qs_pg:name_adm1":"Kanton Luzern",
    "qs_pg:photos":12,
    "qs_pg:photos_1k":2,
    "qs_pg:photos_9k":1,
    "qs_pg:photos_9r":1,
    "qs_pg:photos_all":12,
    "qs_pg:photos_sr":1,
    "qs_pg:pop_sr":4,
    "qs_pg:qs_pg_placetype":"locality",
    "qs_pg:qs_pg_placetype_gp":"Town",
    "qs_pg:woe_adm0":23424957,
    "woe:adm0_id":23424957,
    "woe:name_adm0":"Schweiz",
    "woe:name_adm1":"Kanton Luzern",
    "woe:placetype":"Town",
    "wof:name":"Udligenswil",
    "wof:placetype":"locality",
    "wof:population":2252
},
  "geometry": {"coordinates":[8.40335,47.09005],"type":"Point"}
}