{
  "type": "Feature",
  "properties": {
    "gn:admin1_code":"TG",
    "gn:admin2_code":"2014.0",
    "gn:admin3_code":"4726.0",
    "gn:asciiname":"Hinterschwendi",
    "gn:country_code":"CH",
    "gn:dem":809,
    "gn:feature_class":"P",
    "gn:feature_code":"PPLL",
    "gn:name":"Hinterschwendi",
    "gn:population":0,
    "gn:timezone":"Europe/Zurich",
    "iso:country":"CH",
    "name:deu_x_preferred":[
        "Hinterschwendi"
    ],
    "wof:name":"Hinterschwendi",
    "wof:placetype":"neighbourhood"
},
  "geometry": {"coordinates":[8.94336,47.39084],"type":"Point"}
}