{
  "type": "Feature",
  "properties": {
    "gn:admin1_code":"BE",
    "gn:admin2_code":"250.0",
    "gn:admin3_code":"576.0",
    "gn:asciiname":"Brandegg",
    "gn:country_code":"CH",
    "gn:dem":1348,
    "gn:feature_class":"P",
    "gn:feature_code":"PPL",
    "gn:name":"Brandegg",
    "gn:population":0,
    "gn:timezone":"Europe/Zurich",
    "iso:country":"CH",
    "name:deu_x_preferred":[
        "Brandegg"
    ],
    "wof:name":"Brandegg",
    "wof:placetype":"neighbourhood"
},
  "geometry": {"coordinates":[8.01116,46.60869],"type":"Point"}
}