{
  "type": "Feature",
  "properties": {
    "gn:country":"CH",
    "gn:fcode":"PPLX",
    "gn:population":356,
    "iso:country":"CH",
    "name:eng_x_preferred":[
        "Heugarten"
    ],
    "name:eng_x_variant":[
        "M\u00f6nchaltorf / Heugarten"
    ],
    "qs_pg:aaroncc":"CH",
    "qs_pg:gn_country":"CH",
    "qs_pg:gn_fcode":"PPLX",
    "qs_pg:gn_pop":356,
    "qs_pg:name":"M\u00f6nchaltorf / Heugarten",
    "qs_pg:photos_9r":0,
    "qs_pg:photos_sr":0,
    "qs_pg:pop_sr":2,
    "qs_pg:qs_pg_placetype":"neighbourhood",
    "wof:name":"Heugarten",
    "wof:placetype":"neighbourhood",
    "wof:population":356
},
  "geometry": {"coordinates":[8.72693,47.30876],"type":"Point"}
}