{
  "type": "Feature",
  "properties": {
    "gn:gn_country":"CH",
    "gn:gn_fcode":"PPL",
    "gn:gn_pop":3288,
    "gn:population":3288,
    "iso:country":"CH",
    "name:alb_x_preferred":[
        "Seengen"
    ],
    "name:baq_x_preferred":[
        "Seengen"
    ],
    "name:cat_x_preferred":[
        "Seengen"
    ],
    "name:chi_x_preferred":[
        "\u68ee\u6839"
    ],
    "name:dut_x_preferred":[
        "Seengen"
    ],
    "name:eng_x_preferred":[
        "Seengen"
    ],
    "name:epo_x_preferred":[
        "Seengen"
    ],
    "name:fre_x_preferred":[
        "Seengen"
    ],
    "name:ger_x_preferred":[
        "Seengen"
    ],
    "name:gre_x_preferred":[
        "\u0396\u03b5\u03ad\u03bd\u03b3\u03ba\u03b5\u03bd"
    ],
    "name:hun_x_preferred":[
        "Seengen"
    ],
    "name:ita_x_preferred":[
        "Seengen"
    ],
    "name:kaz_x_preferred":[
        "\u0417\u0435\u0435\u043d\u0433\u0435\u043d"
    ],
    "name:lmo_x_preferred":[
        "Seengen"
    ],
    "name:may_x_preferred":[
        "Seengen"
    ],
    "name:nno_x_preferred":[
        "Seengen"
    ],
    "name:oci_x_preferred":[
        "Seengen"
    ],
    "name:pms_x_preferred":[
        "Seengen"
    ],
    "name:por_x_preferred":[
        "Seengen"
    ],
    "name:rus_x_preferred":[
        "\u0417\u0435\u043d\u0433\u0435\u043d"
    ],
    "name:spa_x_preferred":[
        "Seengen"
    ],
    "name:swe_x_preferred":[
        "Seengen"
    ],
    "name:uzb_x_preferred":[
        "Seengen"
    ],
    "name:vol_x_preferred":[
        "Seengen"
    ],
    "name:war_x_preferred":[
        "Seengen"
    ],
    "name:zho_x_preferred":[
        "\u68ee\u6839"
    ],
    "qs_pg:aaroncc":"CH",
    "qs_pg:gn_country":"CH",
    "qs_pg:gn_fcode":"PPL",
    "qs_pg:gn_pop":3288,
    "qs_pg:name":"Seengen",
    "qs_pg:name_adm0":"Schweiz",
    "qs_pg:name_adm1":"Kanton Aargau",
    "qs_pg:photos":139,
    "qs_pg:photos_1k":28,
    "qs_pg:photos_9k":1,
    "qs_pg:photos_9r":3,
    "qs_pg:photos_all":139,
    "qs_pg:photos_sr":3,
    "qs_pg:pop_sr":4,
    "qs_pg:qs_pg_placetype":"locality",
    "qs_pg:qs_pg_placetype_gp":"Town",
    "qs_pg:woe_adm0":23424957,
    "woe:adm0_id":23424957,
    "woe:name_adm0":"Schweiz",
    "woe:name_adm1":"Kanton Aargau",
    "woe:placetype":"Town",
    "wof:name":"Seengen",
    "wof:placetype":"locality",
    "wof:population":3288
},
  "geometry": {"coordinates":[8.20509,47.32852],"type":"Point"}
}