{
  "type": "Feature",
  "properties": {
    "gn:admin1_code":"AG",
    "gn:admin2_code":"1911.0",
    "gn:admin3_code":"4312.0",
    "gn:asciiname":"Lengnau",
    "gn:country_code":"CH",
    "gn:dem":426,
    "gn:feature_class":"P",
    "gn:feature_code":"PPL",
    "gn:name":"Lengnau",
    "gn:population":0,
    "gn:timezone":"Europe/Zurich",
    "iso:country":"CH",
    "name:als_x_preferred":[
        "Lengnau AG"
    ],
    "name:deu_x_preferred":[
        "Lengnau AG"
    ],
    "name:epo_x_preferred":[
        "Lengnau AG"
    ],
    "name:heb_x_preferred":[
        "\u05dc\u05e0\u05d2\u05e0\u05d0\u05d5"
    ],
    "name:kaz_x_preferred":[
        "\u041b\u0435\u043d\u0433\u043d\u0430\u0443"
    ],
    "name:nno_x_preferred":[
        "Lengnau i Aargau"
    ],
    "name:rus_x_preferred":[
        "\u041b\u0435\u043d\u0433\u043d\u0430\u0443"
    ],
    "name:zho_x_preferred":[
        "\u502b\u7459"
    ],
    "wof:name":"Lengnau",
    "wof:placetype":"locality"
},
  "geometry": {"coordinates":[8.33056,47.52222],"type":"Point"}
}