{
  "type": "Feature",
  "properties": {
    "gn:admin1_code":"TG",
    "gn:admin2_code":"2012.0",
    "gn:admin3_code":"4536.0",
    "gn:asciiname":"Tegerbuch",
    "gn:country_code":"CH",
    "gn:dem":438,
    "gn:feature_class":"P",
    "gn:feature_code":"PPLL",
    "gn:name":"Tegerbuch",
    "gn:population":0,
    "gn:timezone":"Europe/Zurich",
    "iso:country":"CH",
    "name:deu_x_preferred":[
        "Tegerbuch"
    ],
    "wof:name":"Tegerbuch",
    "wof:placetype":"neighbourhood"
},
  "geometry": {"coordinates":[8.73603,47.65291],"type":"Point"}
}