{
  "type": "Feature",
  "properties": {
    "gn:admin1_code":"TG",
    "gn:admin2_code":"2013.0",
    "gn:admin3_code":"4701.0",
    "gn:asciiname":"Hefenhausen",
    "gn:country_code":"CH",
    "gn:dem":507,
    "gn:feature_class":"P",
    "gn:feature_code":"PPLL",
    "gn:name":"Hefenhausen",
    "gn:population":0,
    "gn:timezone":"Europe/Zurich",
    "iso:country":"CH",
    "name:deu_x_preferred":[
        "Hefenhausen"
    ],
    "wof:name":"Hefenhausen",
    "wof:placetype":"locality"
},
  "geometry": {"coordinates":[9.06488,47.61713],"type":"Point"}
}