{
  "type": "Feature",
  "properties": {
    "gn:admin1_code":"VD",
    "gn:admin2_code":"2228.0",
    "gn:admin3_code":"5722.0",
    "gn:asciiname":"Grens",
    "gn:country_code":"CH",
    "gn:dem":500,
    "gn:feature_class":"P",
    "gn:feature_code":"PPL",
    "gn:name":"Grens",
    "gn:population":0,
    "gn:timezone":"Europe/Zurich",
    "iso:country":"CH",
    "wof:name":"Grens",
    "wof:placetype":"locality"
},
  "geometry": {"coordinates":[6.19114,46.39401],"type":"Point"}
}