{
  "type": "Feature",
  "properties": {
    "gn:admin1_code":"TG",
    "gn:admin2_code":"2011.0",
    "gn:admin3_code":"4446.0",
    "gn:asciiname":"Scheidweg",
    "gn:country_code":"CH",
    "gn:dem":488,
    "gn:feature_class":"P",
    "gn:feature_code":"PPLL",
    "gn:name":"Scheidweg",
    "gn:population":0,
    "gn:timezone":"Europe/Zurich",
    "iso:country":"CH",
    "name:deu_x_preferred":[
        "Scheidweg"
    ],
    "wof:name":"Scheidweg",
    "wof:placetype":"neighbourhood"
},
  "geometry": {"coordinates":[9.26994,47.57359],"type":"Point"}
}