{
  "type": "Feature",
  "properties": {
    "gn:admin1_code":"TG",
    "gn:admin2_code":"2012.0",
    "gn:admin3_code":"4821.0",
    "gn:asciiname":"Rossbuck",
    "gn:country_code":"CH",
    "gn:dem":575,
    "gn:feature_class":"P",
    "gn:feature_code":"PPLL",
    "gn:name":"Rossbuck",
    "gn:population":0,
    "gn:timezone":"Europe/Zurich",
    "iso:country":"CH",
    "name:deu_x_preferred":[
        "Rossbuck"
    ],
    "wof:name":"Rossbuck",
    "wof:placetype":"neighbourhood"
},
  "geometry": {"coordinates":[8.8308,47.63156],"type":"Point"}
}