{
  "type": "Feature",
  "properties": {
    "iso:country":"CH",
    "wof:lang_x_official":[
        "deu",
        "fra",
        "gsw",
        "ita"
    ],
    "wof:lang_x_spoken":[
        "deu",
        "fra",
        "gsw",
        "ita",
        "roh"
    ],
    "wof:name":"La Forence",
    "wof:placetype":"neighbourhood"
},
  "geometry": {"coordinates":[6.16751093382015,46.19347238847771],"type":"Point"}
}