{
  "type": "Feature",
  "properties": {
    "gn:admin1_code":"TI",
    "gn:admin2_code":"2105.0",
    "gn:admin3_code":"5238.0",
    "gn:asciiname":"Tornago",
    "gn:country_code":"CH",
    "gn:dem":815,
    "gn:feature_class":"P",
    "gn:feature_code":"PPL",
    "gn:name":"Tornago",
    "gn:population":0,
    "gn:timezone":"Europe/Zurich",
    "iso:country":"CH",
    "name:ita_x_preferred":[
        "Tornago"
    ],
    "wof:name":"Tornago",
    "wof:placetype":"neighbourhood"
},
  "geometry": {"coordinates":[8.90594,46.12941],"type":"Point"}
}