{
  "type": "Feature",
  "properties": {
    "gn:admin1_code":"SG",
    "gn:admin2_code":"1726.0",
    "gn:admin3_code":"3342.0",
    "gn:asciiname":"Neuhaus",
    "gn:country_code":"CH",
    "gn:dem":520,
    "gn:elevation":"502.0",
    "gn:feature_class":"P",
    "gn:feature_code":"PPL",
    "gn:name":"Neuhaus",
    "gn:population":0,
    "gn:timezone":"Europe/Zurich",
    "iso:country":"CH",
    "name:deu_x_preferred":[
        "Neuhaus SG"
    ],
    "wof:name":"Neuhaus",
    "wof:placetype":"locality"
},
  "geometry": {"coordinates":[8.94822,47.24434],"type":"Point"}
}