{
  "type": "Feature",
  "properties": {
    "gn:gn_country":"CH",
    "gn:gn_fcode":"PPLX",
    "gn:gn_pop":296,
    "gn:population":296,
    "iso:country":"CH",
    "name:unk_x_variant":[
        "Oberdorf"
    ],
    "qs_pg:aaroncc":"CH",
    "qs_pg:gn_country":"CH",
    "qs_pg:gn_fcode":"PPLX",
    "qs_pg:gn_pop":296,
    "qs_pg:name":"Birmensdorf / Oberdorf",
    "qs_pg:photos_9r":0,
    "qs_pg:photos_sr":0,
    "qs_pg:pop_sr":2,
    "qs_pg:qs_pg_placetype":"neighbourhood",
    "wof:name":"Birmensdorf / Oberdorf",
    "wof:placetype":"neighbourhood",
    "wof:population":296
},
  "geometry": {"coordinates":[8.43927,47.35151],"type":"Point"}
}