{
  "type": "Feature",
  "properties": {
    "gn:gn_country":"CH",
    "gn:gn_fcode":"PPL",
    "gn:gn_pop":1251,
    "gn:population":1251,
    "iso:country":"CH",
    "name:alb_x_preferred":[
        "Wyssachen"
    ],
    "name:baq_x_preferred":[
        "Wyssachen"
    ],
    "name:cat_x_preferred":[
        "Wyssachen"
    ],
    "name:chi_x_preferred":[
        "\u7dad\u85a9\u8208"
    ],
    "name:chv_x_preferred":[
        "\u0412\u0438\u0441\u0430\u0445\u0435\u043d"
    ],
    "name:dut_x_preferred":[
        "Wyssachen"
    ],
    "name:eng_x_preferred":[
        "Wyssachen"
    ],
    "name:epo_x_preferred":[
        "Wyssachen"
    ],
    "name:fre_x_preferred":[
        "Wyssachen"
    ],
    "name:ger_x_preferred":[
        "Wyssachen"
    ],
    "name:gsw_x_preferred":[
        "Wiisseche"
    ],
    "name:hun_x_preferred":[
        "Wyssachen"
    ],
    "name:ita_x_preferred":[
        "Wyssachen"
    ],
    "name:kaz_x_preferred":[
        "\u0412\u0438\u0441\u0430\u0445\u0435\u043d"
    ],
    "name:lmo_x_preferred":[
        "Wyssachen"
    ],
    "name:may_x_preferred":[
        "Wyssachen"
    ],
    "name:nno_x_preferred":[
        "Wyssachen"
    ],
    "name:oci_x_preferred":[
        "Wyssachen"
    ],
    "name:rus_x_preferred":[
        "\u0412\u0438\u0441\u0430\u0445\u0435\u043d"
    ],
    "name:spa_x_preferred":[
        "Wyssachen"
    ],
    "name:swe_x_preferred":[
        "Wyssachen"
    ],
    "name:vie_x_preferred":[
        "Wyssachen"
    ],
    "name:vol_x_preferred":[
        "Wyssachen"
    ],
    "name:war_x_preferred":[
        "Wyssachen"
    ],
    "name:zho_x_preferred":[
        "\u7dad\u85a9\u8208"
    ],
    "qs_pg:aaroncc":"CH",
    "qs_pg:gn_country":"CH",
    "qs_pg:gn_fcode":"PPL",
    "qs_pg:gn_pop":1251,
    "qs_pg:name":"Wyssachen",
    "qs_pg:name_adm0":"Schweiz",
    "qs_pg:name_adm1":"Kanton Bern",
    "qs_pg:photos_9k":1,
    "qs_pg:photos_9r":1,
    "qs_pg:photos_all":2,
    "qs_pg:photos_sr":0,
    "qs_pg:pop_sr":3,
    "qs_pg:qs_pg_placetype":"locality",
    "qs_pg:qs_pg_placetype_gp":"Town",
    "qs_pg:woe_adm0":23424957,
    "woe:adm0_id":23424957,
    "woe:name_adm0":"Schweiz",
    "woe:name_adm1":"Kanton Bern",
    "woe:placetype":"Town",
    "wof:name":"Wyssachen",
    "wof:placetype":"locality",
    "wof:population":1251
},
  "geometry": {"coordinates":[7.82922,47.07851],"type":"Point"}
}