{
  "type": "Feature",
  "properties": {
    "gn:admin1_code":"TG",
    "gn:admin2_code":"2013.0",
    "gn:admin3_code":"4671.0",
    "gn:asciiname":"Langhalde",
    "gn:country_code":"CH",
    "gn:dem":473,
    "gn:feature_class":"P",
    "gn:feature_code":"PPLL",
    "gn:name":"Langhalde",
    "gn:population":0,
    "gn:timezone":"Europe/Zurich",
    "iso:country":"CH",
    "name:deu_x_preferred":[
        "Langhalde"
    ],
    "wof:name":"Langhalde",
    "wof:placetype":"locality"
},
  "geometry": {"coordinates":[9.18587,47.63415],"type":"Point"}
}