{
  "type": "Feature",
  "properties": {
    "gn:population":4767,
    "iso:country":"CH",
    "name:als_x_preferred":[
        "Hombrechtikon"
    ],
    "name:ara_x_preferred":[
        "\u0647\u0648\u0645\u0628\u0631\u064a\u0643\u062a\u064a\u0643\u0648\u0646"
    ],
    "name:baq_x_preferred":[
        "Hombrechtikon"
    ],
    "name:cat_x_preferred":[
        "Hombrechtikon"
    ],
    "name:ceb_x_preferred":[
        "Hombrechtikon"
    ],
    "name:chi_x_preferred":[
        "\u6d2a\u5e03\u96f7\u5e03\u8482\u5b54"
    ],
    "name:chv_x_preferred":[
        "\u0425\u043e\u043c\u0431\u0440\u0435\u0445\u0442\u0438\u043a\u043e\u043d"
    ],
    "name:deu_x_preferred":[
        "Hombrechtikon"
    ],
    "name:dut_x_preferred":[
        "Hombrechtikon"
    ],
    "name:eng_x_preferred":[
        "Hombrechtikon"
    ],
    "name:epo_x_preferred":[
        "Hombrechtikon"
    ],
    "name:eus_x_preferred":[
        "Hombrechtikon"
    ],
    "name:fra_x_preferred":[
        "Hombrechtikon"
    ],
    "name:fre_x_preferred":[
        "Hombrechtikon"
    ],
    "name:ger_x_preferred":[
        "Hombrechtikon"
    ],
    "name:gsw_x_preferred":[
        "Humbr\u00e4chtike"
    ],
    "name:hun_x_preferred":[
        "Hombrechtikon"
    ],
    "name:ita_x_preferred":[
        "Hombrechtikon"
    ],
    "name:kaz_x_preferred":[
        "\u0425\u043e\u043c\u0431\u0440\u0435\u0445\u0442\u0438\u043a\u043e\u043d"
    ],
    "name:lmo_x_preferred":[
        "Hombrechtikon"
    ],
    "name:may_x_preferred":[
        "Hombrechtikon"
    ],
    "name:msa_x_preferred":[
        "Hombrechtikon"
    ],
    "name:nld_x_preferred":[
        "Hombrechtikon"
    ],
    "name:nno_x_preferred":[
        "Hombrechtikon"
    ],
    "name:oci_x_preferred":[
        "Hombrechtikon"
    ],
    "name:pms_x_preferred":[
        "Hombrechtikon"
    ],
    "name:por_x_preferred":[
        "Hombrechtikon"
    ],
    "name:rus_x_preferred":[
        "\u0425\u043e\u043c\u0431\u0440\u0435\u0445\u0442\u0438\u043a\u043e\u043d"
    ],
    "name:spa_x_preferred":[
        "Hombrechtikon"
    ],
    "name:ukr_x_preferred":[
        "\u0425\u043e\u043c\u0431\u0440\u0435\u0445\u0442\u0456\u043a\u043e\u043d"
    ],
    "name:uzb_x_preferred":[
        "Hombrechtikon"
    ],
    "name:vol_x_preferred":[
        "Hombrechtikon"
    ],
    "name:war_x_preferred":[
        "Hombrechtikon"
    ],
    "name:zho_x_preferred":[
        "\u6d2a\u5e03\u96f7\u5e03\u8482\u5b54"
    ],
    "qs:a0":"Schweiz#Suisse#Svizzera#Svizra",
    "qs:a1":"*Z\u00fcrich",
    "qs:a1r":"0",
    "qs:adm0":"Schweiz#Suisse#Svizzera#Svizra",
    "qs:la_lc":"*",
    "qs:level":"locality",
    "qs:loc":"Hombrechtikon",
    "qs:loc_alt":"Hombrechtikon",
    "qs:pop":0,
    "qs:type":"buffered point",
    "wd:wordcount":851,
    "wof:name":"Hombrechtikon",
    "wof:placetype":"locality",
    "wof:population":4767
},
  "geometry": {"coordinates":[8.765929,47.252125],"type":"Point"}
}