{
  "type": "Feature",
  "properties": {
    "gn:admin1_code":"NW",
    "gn:admin2_code":"700.0",
    "gn:admin3_code":"1505.0",
    "gn:asciiname":"Kleinbiel",
    "gn:country_code":"CH",
    "gn:dem":747,
    "gn:feature_class":"P",
    "gn:feature_code":"PPL",
    "gn:name":"Kleinbiel",
    "gn:population":0,
    "gn:timezone":"Europe/Zurich",
    "iso:country":"CH",
    "name:deu_x_preferred":[
        "Kleinbiel"
    ],
    "name:und_x_variant":[
        "Chlei B\u00fcel",
        "Kleinb\u00fchl"
    ],
    "wof:name":"Kleinbiel",
    "wof:placetype":"locality"
},
  "geometry": {"coordinates":[8.40125,46.9901],"type":"Point"}
}