{
  "type": "Feature",
  "properties": {
    "gn:gn_country":"CH",
    "gn:gn_fcode":"PPL",
    "gn:gn_pop":61,
    "gn:population":61,
    "iso:country":"CH",
    "qs_pg:aaroncc":"CH",
    "qs_pg:gn_country":"CH",
    "qs_pg:gn_fcode":"PPL",
    "qs_pg:gn_pop":61,
    "qs_pg:name":"M\u00fcliweid",
    "qs_pg:photos_9r":0,
    "qs_pg:photos_sr":0,
    "qs_pg:pop_sr":1,
    "qs_pg:qs_pg_placetype":"locality",
    "wof:name":"M\u00fcliweid",
    "wof:placetype":"locality",
    "wof:population":61
},
  "geometry": {"coordinates":[8.66942,47.26298],"type":"Point"}
}