{
  "type": "Feature",
  "properties": {
    "gn:country":"CH",
    "gn:fcode":"PPLX",
    "gn:population":20,
    "iso:country":"CH",
    "name:eng_x_preferred":[
        "Alpenblick"
    ],
    "name:eng_x_variant":[
        "Ottikon / Alpenblick"
    ],
    "qs_pg:aaroncc":"CH",
    "qs_pg:gn_country":"CH",
    "qs_pg:gn_fcode":"PPLX",
    "qs_pg:gn_pop":20,
    "qs_pg:name":"Ottikon / Alpenblick",
    "qs_pg:photos_9r":0,
    "qs_pg:photos_sr":0,
    "qs_pg:pop_sr":1,
    "qs_pg:qs_pg_placetype":"neighbourhood",
    "wof:name":"Alpenblick",
    "wof:placetype":"neighbourhood",
    "wof:population":20
},
  "geometry": {"coordinates":[8.7146,47.43802],"type":"Point"}
}