{
  "type": "Feature",
  "properties": {
    "gn:country":"CH",
    "gn:fcode":"PPLX",
    "gn:population":2032,
    "iso:country":"CH",
    "name:deu_x_preferred":[
        "Irgenhausen"
    ],
    "name:eng_x_preferred":[
        "Irgenhausen"
    ],
    "name:fra_x_preferred":[
        "Irgenhausen"
    ],
    "name:nld_x_preferred":[
        "Irgenhausen"
    ],
    "name:pnb_x_preferred":[
        "\u0627\u0631\u06af\u0646\u06c1\u0627\u0624\u0633\u0646"
    ],
    "name:rus_x_preferred":[
        "\u0418\u0440\u0433\u0435\u043d\u0445\u0430\u0443\u0437\u0435\u043d"
    ],
    "name:swe_x_preferred":[
        "Pf\u00e4ffikon / Irgenhausen"
    ],
    "name:und_x_variant":[
        "Irgenhusen"
    ],
    "qs_pg:aaroncc":"CH",
    "qs_pg:gn_country":"CH",
    "qs_pg:gn_fcode":"PPLX",
    "qs_pg:gn_pop":2032,
    "qs_pg:name":"Irgenhausen",
    "qs_pg:name_adm0":"Schweiz",
    "qs_pg:name_adm1":"Kanton Z\u00fcrich",
    "qs_pg:photos_9k":1,
    "qs_pg:photos_9r":1,
    "qs_pg:photos_all":12,
    "qs_pg:photos_sr":0,
    "qs_pg:pop_sr":4,
    "qs_pg:qs_pg_placetype":"locality_gp_neighbourhood_gn",
    "qs_pg:qs_pg_placetype_gp":"Town",
    "qs_pg:woe_adm0":23424957,
    "woe:adm0_id":23424957,
    "woe:name_adm0":"Schweiz",
    "woe:name_adm1":"Kanton Z\u00fcrich",
    "woe:placetype":"Town",
    "wof:name":"Irgenhausen",
    "wof:placetype":"neighbourhood",
    "wof:population":2032
},
  "geometry": {"coordinates":[8.79265,47.3624],"type":"Point"}
}