{
  "type": "Feature",
  "properties": {
    "gn:admin1_code":"SZ",
    "gn:admin2_code":"506.0",
    "gn:admin3_code":"1375.0",
    "gn:asciiname":"Vordertwingi",
    "gn:country_code":"CH",
    "gn:dem":948,
    "gn:feature_class":"P",
    "gn:feature_code":"PPLL",
    "gn:name":"Vordertwingi",
    "gn:population":0,
    "gn:timezone":"Europe/Zurich",
    "iso:country":"CH",
    "name:deu_x_preferred":[
        "Vordertwingi"
    ],
    "wof:name":"Vordertwingi",
    "wof:placetype":"neighbourhood"
},
  "geometry": {"coordinates":[8.80537,47.03547],"type":"Point"}
}