{
  "type": "Feature",
  "properties": {
    "gn:admin1_code":"AG",
    "gn:admin2_code":"1903.0",
    "gn:admin3_code":"4062.0",
    "gn:asciiname":"Mutschellen",
    "gn:country_code":"CH",
    "gn:dem":553,
    "gn:elevation":"556.0",
    "gn:feature_class":"P",
    "gn:feature_code":"PPL",
    "gn:name":"Mutschellen",
    "gn:population":0,
    "gn:timezone":"Europe/Zurich",
    "iso:country":"CH",
    "name:als_x_preferred":[
        "Mutschellen"
    ],
    "name:ceb_x_preferred":[
        "Mutschellen"
    ],
    "name:deu_x_preferred":[
        "Mutschellen"
    ],
    "name:lat_x_preferred":[
        "Mutschellen"
    ],
    "name:swe_x_preferred":[
        "Mutschellen"
    ],
    "wof:name":"Mutschellen",
    "wof:placetype":"neighbourhood"
},
  "geometry": {"coordinates":[8.36789,47.36044],"type":"Point"}
}