{
  "type": "Feature",
  "properties": {
    "gn:admin1_code":"TG",
    "gn:admin2_code":"2011.0",
    "gn:admin3_code":"4451.0",
    "gn:asciiname":"Kreuzen",
    "gn:country_code":"CH",
    "gn:dem":418,
    "gn:feature_class":"P",
    "gn:feature_code":"PPLL",
    "gn:name":"Kreuzen",
    "gn:population":0,
    "gn:timezone":"Europe/Zurich",
    "iso:country":"CH",
    "name:deu_x_preferred":[
        "Kreuzen"
    ],
    "wof:name":"Kreuzen",
    "wof:placetype":"neighbourhood"
},
  "geometry": {"coordinates":[9.35041,47.57987],"type":"Point"}
}