{
  "type": "Feature",
  "properties": {
    "gn:population":7423,
    "iso:country":"CH",
    "name:alb_x_preferred":[
        "Rothrist"
    ],
    "name:baq_x_preferred":[
        "Rothrist"
    ],
    "name:cat_x_preferred":[
        "Rothrist"
    ],
    "name:ceb_x_preferred":[
        "Rothrist"
    ],
    "name:chi_x_preferred":[
        "\u7f85\u7279\u91cc\u65af\u7279"
    ],
    "name:deu_x_preferred":[
        "Rothrist"
    ],
    "name:deu_x_variant":[
        "Rothrist-Dorf"
    ],
    "name:dut_x_preferred":[
        "Rothrist"
    ],
    "name:eng_x_preferred":[
        "Rothrist-Dorf"
    ],
    "name:epo_x_preferred":[
        "Rothrist"
    ],
    "name:eus_x_preferred":[
        "Rothrist"
    ],
    "name:fra_x_preferred":[
        "Rothrist"
    ],
    "name:fre_x_preferred":[
        "Rothrist"
    ],
    "name:ger_x_preferred":[
        "Rothrist"
    ],
    "name:hun_x_preferred":[
        "Rothrist"
    ],
    "name:ita_x_preferred":[
        "Rothrist"
    ],
    "name:kaz_x_preferred":[
        "\u0420\u043e\u0442\u0440\u0438\u0441\u0442"
    ],
    "name:lmo_x_preferred":[
        "Rothrist"
    ],
    "name:may_x_preferred":[
        "Rothrist"
    ],
    "name:msa_x_preferred":[
        "Rothrist"
    ],
    "name:nld_x_preferred":[
        "Rothrist"
    ],
    "name:nno_x_preferred":[
        "Rothrist"
    ],
    "name:oci_x_preferred":[
        "Rothrist"
    ],
    "name:pms_x_preferred":[
        "Rothrist"
    ],
    "name:por_x_preferred":[
        "Rothrist"
    ],
    "name:roh_x_preferred":[
        "Rothrist"
    ],
    "name:rus_x_preferred":[
        "\u0420\u043e\u0442\u0440\u0438\u0441\u0442"
    ],
    "name:spa_x_preferred":[
        "Rothrist"
    ],
    "name:sqi_x_preferred":[
        "Rothrist"
    ],
    "name:swe_x_preferred":[
        "Rothrist"
    ],
    "name:uzb_x_preferred":[
        "Rothrist"
    ],
    "name:vie_x_preferred":[
        "Rothrist"
    ],
    "name:vol_x_preferred":[
        "Rothrist"
    ],
    "name:war_x_preferred":[
        "Rothrist"
    ],
    "name:zho_x_preferred":[
        "\u7f85\u7279\u91cc\u65af\u7279"
    ],
    "qs:a0":"Schweiz#Suisse#Svizzera#Svizra",
    "qs:a1":"*Aargau",
    "qs:a1r":"0",
    "qs:adm0":"Schweiz#Suisse#Svizzera#Svizra",
    "qs:la_lc":"*",
    "qs:level":"locality",
    "qs:loc":"Rothrist",
    "qs:loc_alt":"Rothrist",
    "qs:pop":0,
    "qs:type":"buffered point",
    "wd:wordcount":1462,
    "wof:lang":[
        "ger"
    ],
    "wof:name":"Rothrist",
    "wof:placetype":"locality",
    "wof:population":7423
},
  "geometry": {"coordinates":[7.877597,47.30619],"type":"Point"}
}