{
  "type": "Feature",
  "properties": {
    "gn:admin1_code":"TG",
    "gn:admin2_code":"2015.0",
    "gn:admin3_code":"4506.0",
    "gn:asciiname":"Goetighofen",
    "gn:country_code":"CH",
    "gn:dem":510,
    "gn:elevation":"508.0",
    "gn:feature_class":"P",
    "gn:feature_code":"PPL",
    "gn:name":"G\u00f6tighofen",
    "gn:population":0,
    "gn:timezone":"Europe/Zurich",
    "iso:country":"CH",
    "wof:name":"Goetighofen",
    "wof:placetype":"locality"
},
  "geometry": {"coordinates":[9.21734,47.53603],"type":"Point"}
}