{
  "type": "Feature",
  "properties": {
    "gn:gn_country":"CH",
    "gn:gn_fcode":"PPL",
    "gn:gn_pop":973,
    "gn:population":973,
    "iso:country":"CH",
    "name:cat_x_preferred":[
        "Spiringen"
    ],
    "name:deu_x_preferred":[
        "Spiringen"
    ],
    "name:eng_x_preferred":[
        "Spiringen"
    ],
    "name:epo_x_preferred":[
        "Spiringen"
    ],
    "name:eus_x_preferred":[
        "Spiringen"
    ],
    "name:fra_x_preferred":[
        "Spiringen"
    ],
    "name:gsw_x_preferred":[
        "Spiringen"
    ],
    "name:hun_x_preferred":[
        "Spiringen"
    ],
    "name:ita_x_preferred":[
        "Spiringen"
    ],
    "name:kaz_x_preferred":[
        "\u0428\u043f\u0438\u0440\u0438\u043d\u0433\u0435\u043d"
    ],
    "name:lmo_x_preferred":[
        "Spiringen"
    ],
    "name:nld_x_preferred":[
        "Spiringen"
    ],
    "name:nno_x_preferred":[
        "Spiringen"
    ],
    "name:oci_x_preferred":[
        "Spiringen"
    ],
    "name:pms_x_preferred":[
        "Spiringen"
    ],
    "name:pnb_x_preferred":[
        "\u0633\u067e\u0631\u0646\u06af\u0646"
    ],
    "name:por_x_preferred":[
        "Spiringen"
    ],
    "name:rus_x_preferred":[
        "\u0428\u043f\u0438\u0440\u0438\u043d\u0433\u0435\u043d"
    ],
    "name:spa_x_preferred":[
        "Spiringen"
    ],
    "name:sqi_x_preferred":[
        "Spiringen"
    ],
    "name:uzb_x_preferred":[
        "Spiringen"
    ],
    "name:vol_x_preferred":[
        "Spiringen"
    ],
    "name:war_x_preferred":[
        "Spiringen"
    ],
    "qs_pg:aaroncc":"CH",
    "qs_pg:gn_country":"CH",
    "qs_pg:gn_fcode":"PPL",
    "qs_pg:gn_pop":973,
    "qs_pg:name":"Spiringen",
    "qs_pg:name_adm0":"Schweiz",
    "qs_pg:name_adm1":"Kanton Uri",
    "qs_pg:photos":21,
    "qs_pg:photos_1k":4,
    "qs_pg:photos_9k":1,
    "qs_pg:photos_9r":1,
    "qs_pg:photos_all":21,
    "qs_pg:photos_sr":1,
    "qs_pg:pop_sr":2,
    "qs_pg:qs_pg_placetype":"locality",
    "qs_pg:qs_pg_placetype_gp":"Town",
    "qs_pg:woe_adm0":23424957,
    "woe:adm0_id":23424957,
    "woe:name_adm0":"Schweiz",
    "woe:name_adm1":"Kanton Uri",
    "woe:placetype":"Town",
    "wof:name":"Spiringen",
    "wof:placetype":"locality",
    "wof:population":973
},
  "geometry": {"coordinates":[8.73017,46.87259],"type":"Point"}
}