{
  "type": "Feature",
  "properties": {
    "gn:admin1_code":"NW",
    "gn:admin2_code":"700.0",
    "gn:admin3_code":"1505.0",
    "gn:asciiname":"Raegenrueti",
    "gn:country_code":"CH",
    "gn:dem":463,
    "gn:feature_class":"P",
    "gn:feature_code":"PPL",
    "gn:name":"R\u00e4genr\u00fcti",
    "gn:population":0,
    "gn:timezone":"Europe/Zurich",
    "iso:country":"CH",
    "name:und_x_variant":[
        "R\u00e4genr\u00fcti",
        "Regenr\u00fcti"
    ],
    "wof:name":"Raegenrueti",
    "wof:placetype":"neighbourhood"
},
  "geometry": {"coordinates":[8.43397,46.99237],"type":"Point"}
}