{
  "type": "Feature",
  "properties": {
    "gn:country":"CH",
    "gn:fcode":"PPL",
    "gn:population":30,
    "iso:country":"CH",
    "name:als_x_preferred":[
        "Berg"
    ],
    "name:cat_x_preferred":[
        "Berg"
    ],
    "name:ceb_x_preferred":[
        "Berg"
    ],
    "name:ces_x_preferred":[
        "Berg"
    ],
    "name:deu_x_preferred":[
        "Berg"
    ],
    "name:epo_x_preferred":[
        "Berg"
    ],
    "name:eus_x_preferred":[
        "Berg"
    ],
    "name:fin_x_preferred":[
        "Berg"
    ],
    "name:fra_x_preferred":[
        "Berg"
    ],
    "name:hun_x_preferred":[
        "Berg"
    ],
    "name:hye_x_preferred":[
        "\u0532\u0565\u0580\u0563"
    ],
    "name:ita_x_preferred":[
        "Berg"
    ],
    "name:jpn_x_preferred":[
        "\u30d9\u30eb\u30af"
    ],
    "name:kat_x_preferred":[
        "\u10d1\u10d4\u10e0\u10d2\u10d8"
    ],
    "name:kor_x_preferred":[
        "\ubca0\ub974\ud06c"
    ],
    "name:lim_x_preferred":[
        "Berg"
    ],
    "name:lmo_x_preferred":[
        "Berg"
    ],
    "name:nds_x_preferred":[
        "Berg"
    ],
    "name:nld_x_preferred":[
        "Berg"
    ],
    "name:nno_x_preferred":[
        "Berg"
    ],
    "name:nor_x_preferred":[
        "Berg"
    ],
    "name:pms_x_preferred":[
        "Berg"
    ],
    "name:pol_x_preferred":[
        "Berg"
    ],
    "name:por_x_preferred":[
        "Berg"
    ],
    "name:ron_x_preferred":[
        "Berg"
    ],
    "name:rus_x_preferred":[
        "\u0411\u0435\u0440\u0433"
    ],
    "name:slk_x_preferred":[
        "Berg"
    ],
    "name:spa_x_preferred":[
        "Berg"
    ],
    "name:srp_x_preferred":[
        "\u0411\u0435\u0440\u0433"
    ],
    "name:swe_x_preferred":[
        "Berg"
    ],
    "name:ukr_x_preferred":[
        "\u0411\u0435\u0440\u0433"
    ],
    "name:vol_x_preferred":[
        "Berg"
    ],
    "qs_pg:aaroncc":"CH",
    "qs_pg:gn_country":"CH",
    "qs_pg:gn_fcode":"PPL",
    "qs_pg:gn_pop":30,
    "qs_pg:name":"Berg",
    "qs_pg:name_adm0":"Schweiz",
    "qs_pg:name_adm1":"Kanton Z\u00fcrich",
    "qs_pg:photos_9r":0,
    "qs_pg:photos_sr":0,
    "qs_pg:pop_sr":1,
    "qs_pg:qs_pg_placetype":"locality",
    "qs_pg:qs_pg_placetype_gp":"Town",
    "qs_pg:woe_adm0":23424957,
    "woe:adm0_id":23424957,
    "woe:name_adm0":"Schweiz",
    "woe:name_adm1":"Kanton Z\u00fcrich",
    "woe:placetype":"Town",
    "wof:name":"Berg",
    "wof:placetype":"neighbourhood",
    "wof:population":30
},
  "geometry": {"coordinates":[8.88577,47.41927],"type":"Point"}
}