{
  "type": "Feature",
  "properties": {
    "gn:gn_country":"CH",
    "gn:gn_fcode":"PPL",
    "gn:gn_pop":142,
    "gn:population":142,
    "iso:country":"CH",
    "qs_pg:aaroncc":"CH",
    "qs_pg:gn_country":"CH",
    "qs_pg:gn_fcode":"PPL",
    "qs_pg:gn_pop":142,
    "qs_pg:name":"Hohlgass",
    "qs_pg:photos_9r":0,
    "qs_pg:photos_sr":0,
    "qs_pg:pop_sr":1,
    "qs_pg:qs_pg_placetype":"locality",
    "wof:name":"Hohlgass",
    "wof:placetype":"neighbourhood",
    "wof:population":142
},
  "geometry": {"coordinates":[8.55523,47.28481],"type":"Point"}
}