{
  "type": "Feature",
  "properties": {
    "gn:gn_country":"CH",
    "gn:gn_fcode":"PPL",
    "gn:gn_pop":1160,
    "gn:population":1160,
    "iso:country":"CH",
    "name:ast_x_preferred":[
        "Tamins"
    ],
    "name:cat_x_preferred":[
        "Tamins"
    ],
    "name:deu_x_preferred":[
        "Tamins"
    ],
    "name:eng_x_preferred":[
        "Tamins"
    ],
    "name:epo_x_preferred":[
        "Tamins"
    ],
    "name:eus_x_preferred":[
        "Tamins"
    ],
    "name:fra_x_preferred":[
        "Tamins"
    ],
    "name:gsw_x_preferred":[
        "Tamins"
    ],
    "name:hun_x_preferred":[
        "Tamins"
    ],
    "name:ita_x_preferred":[
        "Tamins"
    ],
    "name:kaz_x_preferred":[
        "\u0422\u0430\u043c\u0438\u043d\u0441"
    ],
    "name:lmo_x_preferred":[
        "Tamins"
    ],
    "name:msa_x_preferred":[
        "Tamins"
    ],
    "name:nld_x_preferred":[
        "Tamins"
    ],
    "name:nno_x_preferred":[
        "Tamins"
    ],
    "name:oci_x_preferred":[
        "Tamins"
    ],
    "name:pms_x_preferred":[
        "Tamins"
    ],
    "name:por_x_preferred":[
        "Tamins"
    ],
    "name:roh_x_preferred":[
        "Tumein"
    ],
    "name:rus_x_preferred":[
        "\u0422\u0430\u043c\u0438\u043d\u0441"
    ],
    "name:spa_x_preferred":[
        "Tamins"
    ],
    "name:sqi_x_preferred":[
        "Tamins"
    ],
    "name:swe_x_preferred":[
        "Tamins"
    ],
    "name:uzb_x_preferred":[
        "Tamins"
    ],
    "name:vol_x_preferred":[
        "Tamins"
    ],
    "name:war_x_preferred":[
        "Tamins"
    ],
    "name:zho_x_preferred":[
        "\u5854\u660e\u65af"
    ],
    "qs_pg:aaroncc":"CH",
    "qs_pg:gn_country":"CH",
    "qs_pg:gn_fcode":"PPL",
    "qs_pg:gn_pop":1160,
    "qs_pg:name":"Tamins",
    "qs_pg:name_adm0":"Schweiz",
    "qs_pg:name_adm1":"Kanton Graub\u00fcnden",
    "qs_pg:photos":252,
    "qs_pg:photos_1k":51,
    "qs_pg:photos_9k":1,
    "qs_pg:photos_9r":4,
    "qs_pg:photos_all":252,
    "qs_pg:photos_sr":5,
    "qs_pg:pop_sr":3,
    "qs_pg:qs_pg_placetype":"locality",
    "qs_pg:qs_pg_placetype_gp":"Town",
    "qs_pg:woe_adm0":23424957,
    "woe:adm0_id":23424957,
    "woe:name_adm0":"Schweiz",
    "woe:name_adm1":"Kanton Graub\u00fcnden",
    "woe:placetype":"Town",
    "wof:name":"Tamins",
    "wof:placetype":"locality",
    "wof:population":1160
},
  "geometry": {"coordinates":[9.40648,46.82964],"type":"Point"}
}