{
  "type": "Feature",
  "properties": {
    "gn:country":"CH",
    "gn:fcode":"PPL",
    "gn:population":180,
    "iso:country":"CH",
    "name:ceb_x_preferred":[
        "Sankt Peter"
    ],
    "name:ces_x_preferred":[
        "Sankt Peter"
    ],
    "name:deu_x_preferred":[
        "St. Peter-Pagig"
    ],
    "name:deu_x_variant":[
        "Sankt Peter"
    ],
    "name:fra_x_preferred":[
        "Sankt Peter"
    ],
    "name:ita_x_preferred":[
        "Sankt Peter"
    ],
    "name:nld_x_preferred":[
        "Sankt Peter"
    ],
    "name:pol_x_preferred":[
        "Sankt Peter"
    ],
    "name:por_x_preferred":[
        "Sankt Peter"
    ],
    "name:rus_x_preferred":[
        "\u0421\u0430\u043d\u043a\u0442-\u041f\u0435\u0442\u0435\u0440"
    ],
    "name:sco_x_preferred":[
        "Sankt Peter"
    ],
    "name:swe_x_preferred":[
        "Sankt Peter"
    ],
    "name:und_x_variant":[
        "Saint Peter"
    ],
    "qs_pg:aaroncc":"CH",
    "qs_pg:gn_country":"CH",
    "qs_pg:gn_fcode":"PPL",
    "qs_pg:gn_pop":180,
    "qs_pg:name":"Sankt Peter",
    "qs_pg:photos_9r":0,
    "qs_pg:photos_sr":0,
    "qs_pg:pop_sr":1,
    "qs_pg:qs_pg_placetype":"locality",
    "wof:lang_x_official":[
        "deu",
        "fra",
        "gsw",
        "ita"
    ],
    "wof:lang_x_spoken":[
        "deu",
        "fra",
        "gsw",
        "ita",
        "roh"
    ],
    "wof:name":"Sankt Peter",
    "wof:placetype":"neighbourhood",
    "wof:population":180
},
  "geometry": {"coordinates":[9.65091,46.83304],"type":"Point"}
}