{
  "type": "Feature",
  "properties": {
    "gn:population":3305,
    "iso:country":"CH",
    "name:alb_x_preferred":[
        "Bassecourt"
    ],
    "name:als_x_preferred":[
        "Bassecourt"
    ],
    "name:cat_x_preferred":[
        "Bassecourt"
    ],
    "name:ceb_x_preferred":[
        "Bassecourt"
    ],
    "name:chi_x_preferred":[
        "\u5df4\u65af\u5eab\u723e"
    ],
    "name:deu_x_preferred":[
        "Bassecourt"
    ],
    "name:dut_x_preferred":[
        "Bassecourt"
    ],
    "name:eng_x_preferred":[
        "Bassecourt"
    ],
    "name:epo_x_preferred":[
        "Bassecourt"
    ],
    "name:fra_x_preferred":[
        "Bassecourt"
    ],
    "name:fre_x_preferred":[
        "Bassecourt"
    ],
    "name:ger_x_preferred":[
        "Bassecourt"
    ],
    "name:gsw_x_preferred":[
        "Bassecourt"
    ],
    "name:hun_x_preferred":[
        "Bassecourt"
    ],
    "name:ita_x_preferred":[
        "Bassecourt"
    ],
    "name:lmo_x_preferred":[
        "Bassecourt"
    ],
    "name:may_x_preferred":[
        "Bassecourt"
    ],
    "name:msa_x_preferred":[
        "Bassecourt"
    ],
    "name:nld_x_preferred":[
        "Bassecourt"
    ],
    "name:nno_x_preferred":[
        "Bassecourt"
    ],
    "name:oci_x_preferred":[
        "Bassecourt"
    ],
    "name:pol_x_preferred":[
        "Bassecourt"
    ],
    "name:roh_x_preferred":[
        "Bassecourt"
    ],
    "name:spa_x_preferred":[
        "Bassecourt"
    ],
    "name:sqi_x_preferred":[
        "Bassecourt"
    ],
    "name:swe_x_preferred":[
        "Bassecourt"
    ],
    "name:vol_x_preferred":[
        "Bassecourt"
    ],
    "name:war_x_preferred":[
        "Bassecourt"
    ],
    "name:zho_x_preferred":[
        "\u5df4\u65af\u5eab\u723e"
    ],
    "qs:a0":"Schweiz#Suisse#Svizzera#Svizra",
    "qs:a1":"*Jura",
    "qs:a1r":"0",
    "qs:adm0":"Schweiz#Suisse#Svizzera#Svizra",
    "qs:la_lc":"*",
    "qs:level":"locality",
    "qs:loc":"Bassecourt",
    "qs:loc_alt":"Bassecourt",
    "qs:pop":0,
    "qs:type":"buffered point",
    "wd:elevation":477.0,
    "wd:wordcount":1746,
    "wof:name":"Bassecourt",
    "wof:placetype":"locality",
    "wof:population":3305
},
  "geometry": {"coordinates":[7.247119,47.336365],"type":"Point"}
}