{
  "type": "Feature",
  "properties": {
    "gn:population":3862,
    "iso:country":"CH",
    "name:als_x_preferred":[
        "Niederbipp"
    ],
    "name:cat_x_preferred":[
        "Niederbipp"
    ],
    "name:ceb_x_preferred":[
        "Niederbipp"
    ],
    "name:cym_x_preferred":[
        "Niederbipp"
    ],
    "name:deu_x_preferred":[
        "Niederbipp"
    ],
    "name:eng_x_preferred":[
        "Niederbipp"
    ],
    "name:epo_x_preferred":[
        "Niederbipp"
    ],
    "name:eus_x_preferred":[
        "Niederbipp"
    ],
    "name:fra_x_preferred":[
        "Niederbipp"
    ],
    "name:gsw_x_preferred":[
        "Niderbipp"
    ],
    "name:hrv_x_preferred":[
        "Niederbipp"
    ],
    "name:hun_x_preferred":[
        "Niederbipp"
    ],
    "name:ita_x_preferred":[
        "Niederbipp"
    ],
    "name:kaz_x_preferred":[
        "\u041d\u0438\u0434\u0435\u0440\u0431\u0438\u043f"
    ],
    "name:lmo_x_preferred":[
        "Niederbipp"
    ],
    "name:msa_x_preferred":[
        "Niederbipp"
    ],
    "name:nld_x_preferred":[
        "Niederbipp"
    ],
    "name:nno_x_preferred":[
        "Niederbipp"
    ],
    "name:oci_x_preferred":[
        "Niederbipp"
    ],
    "name:rus_x_preferred":[
        "\u041d\u0438\u0434\u0435\u0440\u0431\u0438\u043f\u043f"
    ],
    "name:spa_x_preferred":[
        "Niederbipp"
    ],
    "name:sqi_x_preferred":[
        "Niederbipp"
    ],
    "name:swe_x_preferred":[
        "Niederbipp"
    ],
    "name:vie_x_preferred":[
        "Niederbipp"
    ],
    "name:vol_x_preferred":[
        "Niederbipp"
    ],
    "name:war_x_preferred":[
        "Niederbipp"
    ],
    "name:zho_x_preferred":[
        "\u4e0b\u6bd4\u666e"
    ],
    "qs:a0":"Schweiz#Suisse#Svizzera#Svizra",
    "qs:a1":"*Bern",
    "qs:a1r":"0",
    "qs:adm0":"Schweiz#Suisse#Svizzera#Svizra",
    "qs:la_lc":"*",
    "qs:level":"locality",
    "qs:loc":"Niederbipp",
    "qs:loc_alt":"Niederbipp",
    "qs:pop":0,
    "qs:type":"buffered point",
    "wd:wordcount":631,
    "wof:name":"Niederbipp",
    "wof:placetype":"locality",
    "wof:population":3862
},
  "geometry": {"coordinates":[7.691716,47.268432],"type":"Point"}
}