{
  "type": "Feature",
  "properties": {
    "gn:admin1_code":"VS",
    "gn:admin2_code":"2312.0",
    "gn:admin3_code":"6265.0",
    "gn:asciiname":"Tramillau",
    "gn:country_code":"CH",
    "gn:dem":1292,
    "gn:feature_class":"P",
    "gn:feature_code":"PPL",
    "gn:name":"Tramillau",
    "gn:population":0,
    "gn:timezone":"Europe/Zurich",
    "iso:country":"CH",
    "wof:name":"Tramillau",
    "wof:placetype":"neighbourhood"
},
  "geometry": {"coordinates":[7.35779,46.27251],"type":"Point"}
}