{
  "type": "Feature",
  "properties": {
    "gn:country":"CH",
    "gn:fcode":"PPLL",
    "gn:population":10,
    "iso:country":"CH",
    "name:ceb_x_preferred":[
        "Neuhof"
    ],
    "name:deu_x_preferred":[
        "Neuhof"
    ],
    "name:epo_x_preferred":[
        "Neuhof"
    ],
    "name:eus_x_preferred":[
        "Neuhof"
    ],
    "name:fra_x_preferred":[
        "Neuhof"
    ],
    "name:hun_x_preferred":[
        "Neuhof"
    ],
    "name:ita_x_preferred":[
        "Neuhof"
    ],
    "name:jpn_x_preferred":[
        "\u30ce\u30a4\u30db\u30fc\u30d5"
    ],
    "name:lav_x_preferred":[
        "Neuhof"
    ],
    "name:mkd_x_preferred":[
        "\u041d\u043e\u0458\u0445\u043e\u0444"
    ],
    "name:nld_x_preferred":[
        "Neuhof"
    ],
    "name:pol_x_preferred":[
        "Neuhof"
    ],
    "name:rus_x_preferred":[
        "\u041d\u0435\u0439\u0433\u043e\u0444"
    ],
    "name:srp_x_preferred":[
        "\u041d\u043e\u0458\u0445\u043e\u0444"
    ],
    "name:swe_x_preferred":[
        "Neuhof"
    ],
    "name:vol_x_preferred":[
        "Neuhof"
    ],
    "qs_pg:aaroncc":"CH",
    "qs_pg:gn_country":"CH",
    "qs_pg:gn_fcode":"PPLL",
    "qs_pg:gn_pop":10,
    "qs_pg:name":"Neuhof",
    "qs_pg:photos_9r":0,
    "qs_pg:photos_sr":0,
    "qs_pg:pop_sr":1,
    "qs_pg:qs_pg_placetype":"locality",
    "wof:name":"Neuhof",
    "wof:placetype":"neighbourhood",
    "wof:population":10
},
  "geometry": {"coordinates":[8.65638,47.22176],"type":"Point"}
}