{
  "type": "Feature",
  "properties": {
    "gn:admin1_code":"VD",
    "gn:admin2_code":"2221.0",
    "gn:admin3_code":"5409.0",
    "gn:asciiname":"Exergillod",
    "gn:country_code":"CH",
    "gn:dem":885,
    "gn:feature_class":"P",
    "gn:feature_code":"PPL",
    "gn:name":"Exergillod",
    "gn:population":0,
    "gn:timezone":"Europe/Zurich",
    "iso:country":"CH",
    "name:fra_x_preferred":[
        "Exergillod"
    ],
    "wof:name":"Exergillod",
    "wof:placetype":"neighbourhood"
},
  "geometry": {"coordinates":[7.03932,46.33678],"type":"Point"}
}