{
  "type": "Feature",
  "properties": {
    "gn:admin1_code":"BE",
    "gn:admin2_code":"246.0",
    "gn:admin3_code":"360.0",
    "gn:asciiname":"Unter-Wohlen",
    "gn:country_code":"CH",
    "gn:dem":545,
    "gn:feature_class":"P",
    "gn:feature_code":"PPL",
    "gn:name":"Unter-Wohlen",
    "gn:population":0,
    "gn:timezone":"Europe/Zurich",
    "iso:country":"CH",
    "wof:name":"Unter-Wohlen",
    "wof:placetype":"locality"
},
  "geometry": {"coordinates":[7.35526,46.97082],"type":"Point"}
}