{
  "type": "Feature",
  "properties": {
    "gn:gn_country":"CH",
    "gn:gn_fcode":"PPL",
    "gn:gn_pop":1722,
    "gn:population":1722,
    "iso:country":"CH",
    "name:alb_x_preferred":[
        "Knutwil"
    ],
    "name:baq_x_preferred":[
        "Knutwil"
    ],
    "name:cat_x_preferred":[
        "Knutwil"
    ],
    "name:chi_x_preferred":[
        "\u514b\u52aa\u7279\u7dad\u723e"
    ],
    "name:chv_x_preferred":[
        "\u041a\u043d\u0443\u0442\u0432\u0438\u043b\u044c"
    ],
    "name:dut_x_preferred":[
        "Knutwil"
    ],
    "name:eng_x_preferred":[
        "Knutwil"
    ],
    "name:epo_x_preferred":[
        "Knutwil"
    ],
    "name:fre_x_preferred":[
        "Knutwil"
    ],
    "name:ger_x_preferred":[
        "Knutwil"
    ],
    "name:gsw_x_preferred":[
        "Knutwil"
    ],
    "name:hun_x_preferred":[
        "Knutwil"
    ],
    "name:ita_x_preferred":[
        "Knutwil"
    ],
    "name:kaz_x_preferred":[
        "\u041a\u043d\u0443\u0442\u0432\u0438\u043b\u044c"
    ],
    "name:lmo_x_preferred":[
        "Knutwil"
    ],
    "name:may_x_preferred":[
        "Knutwil"
    ],
    "name:nno_x_preferred":[
        "Knutwil"
    ],
    "name:nob_x_preferred":[
        "Knutwil"
    ],
    "name:oci_x_preferred":[
        "Knutwil"
    ],
    "name:pms_x_preferred":[
        "Knutwil"
    ],
    "name:por_x_preferred":[
        "Knutwil"
    ],
    "name:roh_x_preferred":[
        "Knutwil"
    ],
    "name:rus_x_preferred":[
        "\u041a\u043d\u0443\u0442\u0432\u0438\u043b\u044c"
    ],
    "name:spa_x_preferred":[
        "Knutwil"
    ],
    "name:uzb_x_preferred":[
        "Knutwil"
    ],
    "name:vol_x_preferred":[
        "Knutwil"
    ],
    "name:war_x_preferred":[
        "Knutwil"
    ],
    "name:zho_x_preferred":[
        "\u514b\u52aa\u7279\u7dad\u723e"
    ],
    "qs_pg:aaroncc":"CH",
    "qs_pg:gn_country":"CH",
    "qs_pg:gn_fcode":"PPL",
    "qs_pg:gn_pop":1722,
    "qs_pg:name":"Knutwil",
    "qs_pg:name_adm0":"Schweiz",
    "qs_pg:name_adm1":"Kanton Luzern",
    "qs_pg:photos":34,
    "qs_pg:photos_1k":7,
    "qs_pg:photos_9k":1,
    "qs_pg:photos_9r":2,
    "qs_pg:photos_all":34,
    "qs_pg:photos_sr":2,
    "qs_pg:pop_sr":3,
    "qs_pg:qs_pg_placetype":"locality",
    "qs_pg:qs_pg_placetype_gp":"Town",
    "qs_pg:woe_adm0":23424957,
    "woe:adm0_id":23424957,
    "woe:name_adm0":"Schweiz",
    "woe:name_adm1":"Kanton Luzern",
    "woe:placetype":"Town",
    "wof:name":"Knutwil",
    "wof:placetype":"locality",
    "wof:population":1722
},
  "geometry": {"coordinates":[8.07315,47.19953],"type":"Point"}
}