{
  "type": "Feature",
  "properties": {
    "gn:gn_country":"CH",
    "gn:gn_fcode":"PPL",
    "gn:gn_pop":1277,
    "gn:population":1277,
    "iso:country":"CH",
    "name:alb_x_preferred":[
        "Opfikon"
    ],
    "name:ara_x_preferred":[
        "\u0623\u0648\u0628\u0641\u064a\u0643\u0648\u0646"
    ],
    "name:baq_x_preferred":[
        "Opfikon"
    ],
    "name:cat_x_preferred":[
        "Opfikon"
    ],
    "name:chi_x_preferred":[
        "\u5967\u666e\u83f2\u5b54"
    ],
    "name:chv_x_preferred":[
        "\u041e\u043f\u0444\u0438\u043a\u043e\u043d"
    ],
    "name:dut_x_preferred":[
        "Opfikon"
    ],
    "name:eng_x_preferred":[
        "Opfikon"
    ],
    "name:epo_x_preferred":[
        "Opfikon-Glattbrugg"
    ],
    "name:fas_x_preferred":[
        "\u0627\u0648\u067e\u0641\u06cc\u06a9\u0648\u0646"
    ],
    "name:fre_x_preferred":[
        "Opfikon"
    ],
    "name:ger_x_preferred":[
        "Opfikon"
    ],
    "name:gsw_x_preferred":[
        "Opfike"
    ],
    "name:hun_x_preferred":[
        "Opfikon"
    ],
    "name:ita_x_preferred":[
        "Opfikon"
    ],
    "name:kaz_x_preferred":[
        "\u041e\u043f\u0444\u0438\u043a\u043e\u043d"
    ],
    "name:lat_x_preferred":[
        "Opfikon"
    ],
    "name:lit_x_preferred":[
        "Opfikonas"
    ],
    "name:lmo_x_preferred":[
        "Opfikon"
    ],
    "name:may_x_preferred":[
        "Opfikon"
    ],
    "name:nan_x_preferred":[
        "Opfikon"
    ],
    "name:nno_x_preferred":[
        "Opfikon"
    ],
    "name:oci_x_preferred":[
        "Opfikon"
    ],
    "name:per_x_preferred":[
        "\u0627\u0648\u067e\u0641\u06cc\u06a9\u0648\u0646"
    ],
    "name:pol_x_preferred":[
        "Opfikon"
    ],
    "name:rus_x_preferred":[
        "\u041e\u043f\u0444\u0438\u043a\u043e\u043d"
    ],
    "name:spa_x_preferred":[
        "Opfikon"
    ],
    "name:swe_x_preferred":[
        "Opfikon"
    ],
    "name:ukr_x_preferred":[
        "\u041e\u043f\u0444\u0456\u043a\u043e\u043d"
    ],
    "name:uzb_x_preferred":[
        "Opfikon"
    ],
    "name:vie_x_preferred":[
        "Opfikon"
    ],
    "name:vol_x_preferred":[
        "Opfikon"
    ],
    "name:war_x_preferred":[
        "Opfikon"
    ],
    "name:zho_x_preferred":[
        "\u5967\u666e\u83f2\u5b54"
    ],
    "qs_pg:aaroncc":"CH",
    "qs_pg:gn_country":"CH",
    "qs_pg:gn_fcode":"PPL",
    "qs_pg:gn_pop":1277,
    "qs_pg:name":"Opfikon",
    "qs_pg:name_adm0":"Schweiz",
    "qs_pg:name_adm1":"Kanton Z\u00fcrich",
    "qs_pg:photos":131,
    "qs_pg:photos_1k":27,
    "qs_pg:photos_9k":1,
    "qs_pg:photos_9r":3,
    "qs_pg:photos_all":131,
    "qs_pg:photos_sr":3,
    "qs_pg:pop_sr":3,
    "qs_pg:qs_pg_placetype":"locality",
    "qs_pg:qs_pg_placetype_gp":"Town",
    "qs_pg:woe_adm0":23424957,
    "woe:adm0_id":23424957,
    "woe:name_adm0":"Schweiz",
    "woe:name_adm1":"Kanton Z\u00fcrich",
    "woe:placetype":"Town",
    "wof:name":"Opfikon",
    "wof:placetype":"locality",
    "wof:population":1277
},
  "geometry": {"coordinates":[8.57588,47.43169],"type":"Point"}
}