{
  "type": "Feature",
  "properties": {
    "gn:admin1_code":"AG",
    "gn:admin2_code":"1902.0",
    "gn:admin3_code":"4031.0",
    "gn:asciiname":"Sulz",
    "gn:country_code":"CH",
    "gn:dem":372,
    "gn:elevation":"363.0",
    "gn:feature_class":"P",
    "gn:feature_code":"PPL",
    "gn:name":"Sulz",
    "gn:population":0,
    "gn:timezone":"Europe/Zurich",
    "iso:country":"CH",
    "wof:name":"Sulz",
    "wof:placetype":"neighbourhood"
},
  "geometry": {"coordinates":[8.324,47.38312],"type":"Point"}
}