{
  "type": "Feature",
  "properties": {
    "gn:admin1_code":"AG",
    "gn:admin2_code":"1902.0",
    "gn:admin3_code":"4031.0",
    "gn:asciiname":"Sulz",
    "gn:country_code":"CH",
    "gn:dem":372,
    "gn:elevation":"363.0",
    "gn:feature_class":"P",
    "gn:feature_code":"PPL",
    "gn:name":"Sulz",
    "gn:population":0,
    "gn:timezone":"Europe/Zurich",
    "iso:country":"CH",
    "name:als_x_preferred":[
        "Sulz"
    ],
    "name:ceb_x_preferred":[
        "Sulz"
    ],
    "name:deu_x_preferred":[
        "Sulz"
    ],
    "name:epo_x_preferred":[
        "Sulz"
    ],
    "name:fra_x_preferred":[
        "Sulz"
    ],
    "name:ita_x_preferred":[
        "Sulz"
    ],
    "name:nld_x_preferred":[
        "Sulz"
    ],
    "name:pol_x_preferred":[
        "Sulz"
    ],
    "name:por_x_preferred":[
        "Sulz"
    ],
    "name:rus_x_preferred":[
        "\u0417\u0443\u043b\u044c\u0446"
    ],
    "name:swe_x_preferred":[
        "Sulz"
    ],
    "name:ukr_x_preferred":[
        "\u0417\u0443\u043b\u044c\u0446"
    ],
    "name:vol_x_preferred":[
        "Sulz"
    ],
    "wof:name":"Sulz",
    "wof:placetype":"neighbourhood"
},
  "geometry": {"coordinates":[8.324,47.38312],"type":"Point"}
}