{
  "type": "Feature",
  "properties": {
    "gn:admin1_code":"TI",
    "gn:admin2_code":"2104.0",
    "gn:admin3_code":"5097.0",
    "gn:asciiname":"Gerbio",
    "gn:country_code":"CH",
    "gn:dem":732,
    "gn:feature_class":"P",
    "gn:feature_code":"PPL",
    "gn:name":"Gerbio",
    "gn:population":0,
    "gn:timezone":"Europe/Rome",
    "iso:country":"CH",
    "name:ita_x_preferred":[
        "Gerbio"
    ],
    "wof:name":"Gerbio",
    "wof:placetype":"neighbourhood"
},
  "geometry": {"coordinates":[8.68908,46.1091],"type":"Point"}
}