{
  "type": "Feature",
  "properties": {
    "gn:admin1_code":"BE",
    "gn:admin2_code":"246.0",
    "gn:admin3_code":"620.0",
    "gn:asciiname":"Chaenelthal",
    "gn:country_code":"CH",
    "gn:dem":892,
    "gn:feature_class":"P",
    "gn:feature_code":"PPLL",
    "gn:name":"Ch\u00e4nelthal",
    "gn:population":0,
    "gn:timezone":"Europe/Zurich",
    "iso:country":"CH",
    "name:deu_x_preferred":[
        "Ch\u00e4nelthal"
    ],
    "wof:name":"Chaenelthal",
    "wof:placetype":"neighbourhood"
},
  "geometry": {"coordinates":[7.68001,46.91523],"type":"Point"}
}