{
  "type": "Feature",
  "properties": {
    "gn:country":"CH",
    "gn:fcode":"PPLL",
    "gn:population":6,
    "iso:country":"CH",
    "name:ceb_x_preferred":[
        "Grund"
    ],
    "name:ces_x_preferred":[
        "Grund"
    ],
    "name:dan_x_preferred":[
        "Grund"
    ],
    "name:deu_x_preferred":[
        "Grund"
    ],
    "name:epo_x_preferred":[
        "Grund"
    ],
    "name:fas_x_preferred":[
        "\u06af\u0631\u0648\u0646\u062f"
    ],
    "name:hun_x_preferred":[
        "Grund"
    ],
    "name:isl_x_preferred":[
        "Grund"
    ],
    "name:ita_x_preferred":[
        "Grund"
    ],
    "name:nld_x_preferred":[
        "Grund"
    ],
    "name:pol_x_preferred":[
        "Grund"
    ],
    "name:swe_x_preferred":[
        "Grund"
    ],
    "qs_pg:aaroncc":"CH",
    "qs_pg:gn_country":"CH",
    "qs_pg:gn_fcode":"PPLL",
    "qs_pg:gn_pop":6,
    "qs_pg:name":"Grund",
    "qs_pg:photos_9r":0,
    "qs_pg:photos_sr":0,
    "qs_pg:pop_sr":1,
    "qs_pg:qs_pg_placetype":"locality",
    "wof:name":"Grund",
    "wof:placetype":"neighbourhood",
    "wof:population":6
},
  "geometry": {"coordinates":[8.47048,47.31118],"type":"Point"}
}