{
  "type": "Feature",
  "properties": {
    "gn:country":"CH",
    "gn:fcode":"PPLX",
    "gn:population":164,
    "iso:country":"CH",
    "name:eng_x_preferred":[
        "Brunnenb\u00fchl"
    ],
    "name:eng_x_variant":[
        "Tann / Brunnenb\u00fchl"
    ],
    "qs_pg:aaroncc":"CH",
    "qs_pg:gn_country":"CH",
    "qs_pg:gn_fcode":"PPLX",
    "qs_pg:gn_pop":164,
    "qs_pg:name":"Tann / Brunnenb\u00fchl",
    "qs_pg:photos_9r":0,
    "qs_pg:photos_sr":0,
    "qs_pg:pop_sr":1,
    "qs_pg:qs_pg_placetype":"neighbourhood",
    "wof:name":"Brunnenb\u00fchl",
    "wof:placetype":"neighbourhood",
    "wof:population":164
},
  "geometry": {"coordinates":[8.85461,47.26945],"type":"Point"}
}