{
  "type": "Feature",
  "properties": {
    "iso:country":"CH",
    "name:als_x_preferred":[
        "Moiry"
    ],
    "name:deu_x_preferred":[
        "Moiry"
    ],
    "name:epo_x_preferred":[
        "Moiry"
    ],
    "name:eus_x_preferred":[
        "Moiry"
    ],
    "name:fra_x_preferred":[
        "Moiry"
    ],
    "name:hye_x_preferred":[
        "\u053c\u0561\u0584\u0565\u057d\u056b\u057d"
    ],
    "name:ita_x_preferred":[
        "Moiry"
    ],
    "name:ltz_x_preferred":[
        "Moiry"
    ],
    "name:nld_x_preferred":[
        "Moiry"
    ],
    "name:rus_x_preferred":[
        "\u041c\u0443\u0430\u0440\u0438"
    ],
    "name:slk_x_preferred":[
        "Moiry"
    ],
    "name:sqi_x_preferred":[
        "Moiry"
    ],
    "name:swe_x_preferred":[
        "Moiry"
    ],
    "qs_pg:aaroncc":"CH",
    "qs_pg:name":"Moiry",
    "qs_pg:name_adm0":"Schweiz",
    "qs_pg:name_adm1":"Canton de Valais",
    "qs_pg:photos":254,
    "qs_pg:photos_1k":51,
    "qs_pg:photos_9k":1,
    "qs_pg:photos_9r":4,
    "qs_pg:photos_all":254,
    "qs_pg:photos_sr":5,
    "qs_pg:pop_sr":0,
    "qs_pg:qs_pg_placetype":"locality",
    "qs_pg:qs_pg_placetype_gp":"Town",
    "qs_pg:woe_adm0":23424957,
    "woe:adm0_id":23424957,
    "woe:name_adm0":"Schweiz",
    "woe:name_adm1":"Canton de Valais",
    "woe:placetype":"Town",
    "wof:name":"Moiry",
    "wof:placetype":"neighbourhood"
},
  "geometry": {"coordinates":[7.572841,46.1380355],"type":"Point"}
}