{
  "type": "Feature",
  "properties": {
    "gn:admin1_code":"VS",
    "gn:admin2_code":"2312.0",
    "gn:admin3_code":"6263.0",
    "gn:asciiname":"Champlan",
    "gn:country_code":"CH",
    "gn:dem":722,
    "gn:feature_class":"P",
    "gn:feature_code":"PPL",
    "gn:name":"Champlan",
    "gn:population":0,
    "gn:timezone":"Europe/Zurich",
    "iso:country":"CH",
    "name:und_x_variant":[
        "Champlan (Grimisuat)"
    ],
    "wof:name":"Champlan",
    "wof:placetype":"locality"
},
  "geometry": {"coordinates":[7.37294,46.24712],"type":"Point"}
}