{
  "type": "Feature",
  "properties": {
    "gn:admin1_code":"LU",
    "gn:admin2_code":"314.0",
    "gn:admin3_code":"1083.0",
    "gn:asciiname":"Meienberg",
    "gn:country_code":"CH",
    "gn:dem":670,
    "gn:feature_class":"P",
    "gn:feature_code":"PPLL",
    "gn:name":"Meienberg",
    "gn:population":0,
    "gn:timezone":"Europe/Zurich",
    "iso:country":"CH",
    "name:deu_x_preferred":[
        "Meienberg"
    ],
    "wof:name":"Meienberg",
    "wof:placetype":"neighbourhood"
},
  "geometry": {"coordinates":[8.12221,47.11949],"type":"Point"}
}