{
  "type": "Feature",
  "properties": {
    "gn:gn_country":"CH",
    "gn:gn_fcode":"PPLL",
    "gn:gn_pop":11,
    "gn:population":11,
    "iso:country":"CH",
    "qs_pg:aaroncc":"CH",
    "qs_pg:gn_country":"CH",
    "qs_pg:gn_fcode":"PPLL",
    "qs_pg:gn_pop":11,
    "qs_pg:name":"Bollenr\u00fcti",
    "qs_pg:photos_9r":0,
    "qs_pg:photos_sr":0,
    "qs_pg:pop_sr":1,
    "qs_pg:qs_pg_placetype":"locality",
    "wof:name":"Bollenr\u00fcti",
    "wof:placetype":"locality",
    "wof:population":11
},
  "geometry": {"coordinates":[8.62574,47.37718],"type":"Point"}
}