{
  "type": "Feature",
  "properties": {
    "gn:admin1_code":"TG",
    "gn:admin2_code":"2014.0",
    "gn:admin3_code":"4721.0",
    "gn:asciiname":"Rietwies",
    "gn:country_code":"CH",
    "gn:dem":561,
    "gn:feature_class":"P",
    "gn:feature_code":"PPLL",
    "gn:name":"Rietwies",
    "gn:population":0,
    "gn:timezone":"Europe/Zurich",
    "iso:country":"CH",
    "name:deu_x_preferred":[
        "Rietwies"
    ],
    "wof:name":"Rietwies",
    "wof:placetype":"neighbourhood"
},
  "geometry": {"coordinates":[8.9425,47.4594],"type":"Point"}
}