{
  "type": "Feature",
  "properties": {
    "iso:country":"CH",
    "name:fra_x_preferred":[
        "La Petite-Boissi\u00e8re"
    ],
    "wof:name":"La Petite-Boissiere",
    "wof:placetype":"neighbourhood"
},
  "geometry": {"coordinates":[6.16928476894117,46.19727476620975],"type":"Point"}
}