{
  "type": "Feature",
  "properties": {
    "gn:country":"CH",
    "gn:fcode":"PPLX",
    "gn:population":123,
    "iso:country":"CH",
    "name:eng_x_preferred":[
        "Reithalle-Pilgerweg"
    ],
    "name:eng_x_variant":[
        "R\u00fcschlikon / Reithalle-Pilgerweg"
    ],
    "qs_pg:aaroncc":"CH",
    "qs_pg:gn_country":"CH",
    "qs_pg:gn_fcode":"PPLX",
    "qs_pg:gn_pop":123,
    "qs_pg:name":"R\u00fcschlikon / Reithalle-Pilgerweg",
    "qs_pg:photos_9r":0,
    "qs_pg:photos_sr":0,
    "qs_pg:pop_sr":1,
    "qs_pg:qs_pg_placetype":"neighbourhood",
    "wof:lang_x_official":[
        "deu",
        "fra",
        "gsw",
        "ita"
    ],
    "wof:lang_x_spoken":[
        "deu",
        "fra",
        "gsw",
        "ita",
        "roh"
    ],
    "wof:name":"Reithalle-Pilgerweg",
    "wof:placetype":"neighbourhood",
    "wof:population":123
},
  "geometry": {"coordinates":[8.55425,47.31169],"type":"Point"}
}