{
  "type": "Feature",
  "properties": {
    "gn:admin1_code":"LU",
    "gn:admin2_code":"315.0",
    "gn:admin3_code":"1132.0",
    "gn:asciiname":"Grausschuer",
    "gn:country_code":"CH",
    "gn:dem":839,
    "gn:feature_class":"P",
    "gn:feature_code":"PPLL",
    "gn:name":"Graussch\u00fcr",
    "gn:population":0,
    "gn:timezone":"Europe/Zurich",
    "iso:country":"CH",
    "name:deu_x_preferred":[
        "Graussch\u00fcr"
    ],
    "wof:lang_x_official":[
        "deu",
        "fra",
        "gsw",
        "ita"
    ],
    "wof:lang_x_spoken":[
        "deu",
        "fra",
        "gsw",
        "ita",
        "roh"
    ],
    "wof:name":"Grausschuer",
    "wof:placetype":"neighbourhood"
},
  "geometry": {"coordinates":[7.95326,47.03822],"type":"Point"}
}