{
  "type": "Feature",
  "properties": {
    "gn:gn_country":"CH",
    "gn:gn_fcode":"PPL",
    "gn:gn_pop":0,
    "iso:country":"CH",
    "name:deu_x_historical":[
        "Cierfs"
    ],
    "name:deu_x_preferred":[
        "Cierfs"
    ],
    "name:deu_x_variant":[
        "Tschierv"
    ],
    "name:eng_x_preferred":[
        "Tschierv"
    ],
    "name:fra_x_preferred":[
        "Tschierv"
    ],
    "name:ita_x_preferred":[
        "Tschierv"
    ],
    "name:kaz_x_preferred":[
        "\u0427\u0438\u0440\u0444"
    ],
    "name:nld_x_preferred":[
        "Tschierv"
    ],
    "name:pms_x_preferred":[
        "Tschierv"
    ],
    "name:por_x_preferred":[
        "Tschierv"
    ],
    "name:roh_x_preferred":[
        "Tschierv"
    ],
    "name:rus_x_preferred":[
        "\u0427\u0438\u0440\u0444"
    ],
    "name:spa_x_preferred":[
        "Tschierv"
    ],
    "name:swe_x_preferred":[
        "Tschierv"
    ],
    "name:unk_x_variant":[
        "Orasom Cierfs"
    ],
    "name:uzb_x_preferred":[
        "Tschierv"
    ],
    "name:vol_x_preferred":[
        "Tschierv"
    ],
    "qs_pg:aaroncc":"CH",
    "qs_pg:gn_country":"CH",
    "qs_pg:gn_fcode":"PPL",
    "qs_pg:gn_pop":0,
    "qs_pg:name":"Cierfs",
    "qs_pg:name_adm0":"Schweiz",
    "qs_pg:name_adm1":"Kanton Graub\u00fcnden",
    "qs_pg:photos":165,
    "qs_pg:photos_1k":33,
    "qs_pg:photos_9k":1,
    "qs_pg:photos_9r":4,
    "qs_pg:photos_all":165,
    "qs_pg:photos_sr":4,
    "qs_pg:pop_sr":0,
    "qs_pg:qs_pg_placetype":"locality",
    "qs_pg:qs_pg_placetype_gp":"Town",
    "qs_pg:woe_adm0":23424957,
    "woe:adm0_id":23424957,
    "woe:name_adm0":"Schweiz",
    "woe:name_adm1":"Kanton Graub\u00fcnden",
    "woe:placetype":"Town",
    "wof:name":"Cierfs",
    "wof:placetype":"neighbourhood"
},
  "geometry": {"coordinates":[10.33333,46.63333],"type":"Point"}
}