{
  "type": "Feature",
  "properties": {
    "gn:gn_country":"CH",
    "gn:gn_fcode":"PPL",
    "gn:gn_pop":2548,
    "gn:population":2548,
    "iso:country":"CH",
    "name:als_x_preferred":[
        "Fischingen TG"
    ],
    "name:ara_x_preferred":[
        "\u0641\u064a\u0634\u0646\u063a\u0646"
    ],
    "name:cat_x_preferred":[
        "Fischingen"
    ],
    "name:deu_x_preferred":[
        "Fischingen TG"
    ],
    "name:deu_x_variant":[
        "Fischingen"
    ],
    "name:eng_x_preferred":[
        "Fischingen"
    ],
    "name:epo_x_preferred":[
        "Fischingen TG"
    ],
    "name:eus_x_preferred":[
        "Fischingen"
    ],
    "name:fra_x_preferred":[
        "Fischingen"
    ],
    "name:gsw_x_preferred":[
        "Fischingen TG"
    ],
    "name:hun_x_preferred":[
        "Fischingen"
    ],
    "name:ita_x_preferred":[
        "Fischingen"
    ],
    "name:kaz_x_preferred":[
        "\u0424\u0438\u0448\u0438\u043d\u0433\u0435\u043d"
    ],
    "name:lmo_x_preferred":[
        "Fischingen"
    ],
    "name:msa_x_preferred":[
        "Fischingen"
    ],
    "name:nld_x_preferred":[
        "Fischingen"
    ],
    "name:nno_x_preferred":[
        "Fischingen"
    ],
    "name:oci_x_preferred":[
        "Fischingen"
    ],
    "name:pms_x_preferred":[
        "Fischingen"
    ],
    "name:por_x_preferred":[
        "Fischingen"
    ],
    "name:rus_x_preferred":[
        "\u0424\u0438\u0448\u0438\u043d\u0433\u0435\u043d"
    ],
    "name:spa_x_preferred":[
        "Fischingen"
    ],
    "name:uzb_x_preferred":[
        "Fischingen"
    ],
    "name:vec_x_preferred":[
        "Fischingen"
    ],
    "name:vol_x_preferred":[
        "Fischingen"
    ],
    "name:war_x_preferred":[
        "Fischingen"
    ],
    "name:zho_x_preferred":[
        "\u83f2\u6b23\u6839"
    ],
    "qs_pg:aaroncc":"CH",
    "qs_pg:gn_country":"CH",
    "qs_pg:gn_fcode":"PPL",
    "qs_pg:gn_pop":2548,
    "qs_pg:name":"Fischingen",
    "qs_pg:name_adm0":"Schweiz",
    "qs_pg:name_adm1":"Kanton Thurgau",
    "qs_pg:photos":3,
    "qs_pg:photos_1k":1,
    "qs_pg:photos_9k":1,
    "qs_pg:photos_9r":1,
    "qs_pg:photos_all":3,
    "qs_pg:photos_sr":1,
    "qs_pg:pop_sr":4,
    "qs_pg:qs_pg_placetype":"locality",
    "qs_pg:qs_pg_placetype_gp":"Town",
    "qs_pg:woe_adm0":23424957,
    "woe:adm0_id":23424957,
    "woe:name_adm0":"Schweiz",
    "woe:name_adm1":"Kanton Thurgau",
    "woe:placetype":"Town",
    "wof:name":"Fischingen",
    "wof:placetype":"locality",
    "wof:population":2548
},
  "geometry": {"coordinates":[8.96914,47.41428],"type":"Point"}
}