{
  "type": "Feature",
  "properties": {
    "gn:admin1_code":"NW",
    "gn:admin2_code":"700.0",
    "gn:admin3_code":"1511.0",
    "gn:asciiname":"Bannalp",
    "gn:country_code":"CH",
    "gn:dem":1662,
    "gn:feature_class":"P",
    "gn:feature_code":"PPL",
    "gn:name":"Bannalp",
    "gn:population":0,
    "gn:timezone":"Europe/Zurich",
    "iso:country":"CH",
    "wof:name":"Bannalp",
    "wof:placetype":"neighbourhood"
},
  "geometry": {"coordinates":[8.43398,46.86993],"type":"Point"}
}