{
  "type": "Feature",
  "properties": {
    "gn:gn_country":"CH",
    "gn:gn_fcode":"PPL",
    "gn:gn_pop":0,
    "iso:country":"CH",
    "name:als_x_preferred":[
        "Etoy VD"
    ],
    "name:baq_x_preferred":[
        "\u00c9toy"
    ],
    "name:bul_x_preferred":[
        "\u0415\u0442\u043e\u0439"
    ],
    "name:cat_x_preferred":[
        "Etoy"
    ],
    "name:chi_x_preferred":[
        "\u57c3\u6258\u74e6"
    ],
    "name:deu_x_preferred":[
        "Etoy VD"
    ],
    "name:dut_x_preferred":[
        "Etoy"
    ],
    "name:eng_x_preferred":[
        "\u00c9toy"
    ],
    "name:epo_x_preferred":[
        "Etoy"
    ],
    "name:fra_x_preferred":[
        "\u00c9toy"
    ],
    "name:fre_x_preferred":[
        "Etoy"
    ],
    "name:ger_x_preferred":[
        "Etoy VD"
    ],
    "name:gsw_x_preferred":[
        "Etoy VD"
    ],
    "name:hun_x_preferred":[
        "Etoy"
    ],
    "name:ita_x_preferred":[
        "Etoy"
    ],
    "name:lmo_x_preferred":[
        "Etoy"
    ],
    "name:may_x_preferred":[
        "Etoy"
    ],
    "name:nno_x_preferred":[
        "etoy"
    ],
    "name:oci_x_preferred":[
        "\u00c9toy"
    ],
    "name:pol_x_preferred":[
        "Etoy"
    ],
    "name:roh_x_preferred":[
        "Etoy"
    ],
    "name:rum_x_preferred":[
        "Etoy"
    ],
    "name:spa_x_preferred":[
        "Etoy"
    ],
    "name:swe_x_preferred":[
        "Etoy"
    ],
    "name:vol_x_preferred":[
        "Etoy"
    ],
    "name:war_x_preferred":[
        "Etoy VD"
    ],
    "name:zho_x_preferred":[
        "\u57c3\u6258\u74e6"
    ],
    "qs_pg:aaroncc":"CH",
    "qs_pg:gn_country":"CH",
    "qs_pg:gn_fcode":"PPL",
    "qs_pg:gn_pop":0,
    "qs_pg:name":"Etoy",
    "qs_pg:name_adm0":"Schweiz",
    "qs_pg:name_adm1":"Canton de Vaud",
    "qs_pg:photos":73,
    "qs_pg:photos_1k":15,
    "qs_pg:photos_9k":1,
    "qs_pg:photos_9r":2,
    "qs_pg:photos_all":73,
    "qs_pg:photos_sr":2,
    "qs_pg:pop_sr":0,
    "qs_pg:qs_pg_placetype":"locality",
    "qs_pg:qs_pg_placetype_gp":"Town",
    "qs_pg:woe_adm0":23424957,
    "woe:adm0_id":23424957,
    "woe:name_adm0":"Schweiz",
    "woe:name_adm1":"Canton de Vaud",
    "woe:placetype":"Town",
    "wof:name":"Etoy",
    "wof:placetype":"locality"
},
  "geometry": {"coordinates":[6.41816,46.48587],"type":"Point"}
}