{
  "type": "Feature",
  "properties": {
    "gn:gn_country":"CH",
    "gn:gn_fcode":"PPL",
    "gn:gn_pop":72,
    "gn:population":72,
    "iso:country":"CH",
    "name:deu_x_preferred":[
        "M\u00fchlebach"
    ],
    "name:dut_x_preferred":[
        "M\u00fchlebach"
    ],
    "name:eng_x_preferred":[
        "M\u00fchlebach"
    ],
    "name:fre_x_preferred":[
        "M\u00fchlebach VS"
    ],
    "name:ger_x_preferred":[
        "M\u00fchlebach VS"
    ],
    "name:nno_x_preferred":[
        "M\u00fchlebach"
    ],
    "name:nob_x_preferred":[
        "M\u00fchlebach"
    ],
    "name:slv_x_preferred":[
        "M\u00fchlebach"
    ],
    "qs_pg:aaroncc":"CH",
    "qs_pg:gn_country":"CH",
    "qs_pg:gn_fcode":"PPL",
    "qs_pg:gn_pop":72,
    "qs_pg:name":"M\u00fchlebach",
    "qs_pg:name_adm0":"Schweiz",
    "qs_pg:name_adm1":"Canton de Valais",
    "qs_pg:photos":46,
    "qs_pg:photos_1k":9,
    "qs_pg:photos_9k":1,
    "qs_pg:photos_9r":2,
    "qs_pg:photos_all":46,
    "qs_pg:photos_sr":2,
    "qs_pg:pop_sr":1,
    "qs_pg:qs_pg_placetype":"locality",
    "qs_pg:qs_pg_placetype_gp":"Town",
    "qs_pg:woe_adm0":23424957,
    "woe:adm0_id":23424957,
    "woe:name_adm0":"Schweiz",
    "woe:name_adm1":"Canton de Valais",
    "woe:placetype":"Town",
    "wof:name":"M\u00fchlebach",
    "wof:placetype":"locality",
    "wof:population":72
},
  "geometry": {"coordinates":[8.15716,46.40776],"type":"Point"}
}