{
  "type": "Feature",
  "properties": {
    "gn:gn_country":"CH",
    "gn:gn_fcode":"PPL",
    "gn:gn_pop":0,
    "iso:country":"CH",
    "name:deu_x_preferred":[
        "Gimmelwald"
    ],
    "name:eng_x_preferred":[
        "Gimmelwald"
    ],
    "name:fra_x_preferred":[
        "Gimmelwald"
    ],
    "name:nld_x_preferred":[
        "Gimmelwald"
    ],
    "name:swe_x_preferred":[
        "Gimmelwald"
    ],
    "name:vie_x_preferred":[
        "Gimmelwald"
    ],
    "qs_pg:aaroncc":"CH",
    "qs_pg:gn_country":"CH",
    "qs_pg:gn_fcode":"PPL",
    "qs_pg:gn_pop":0,
    "qs_pg:name":"Gimmelwald",
    "qs_pg:name_adm0":"Schweiz",
    "qs_pg:name_adm1":"Kanton Bern",
    "qs_pg:photos":1596,
    "qs_pg:photos_1k":323,
    "qs_pg:photos_9k":7,
    "qs_pg:photos_9r":8,
    "qs_pg:photos_all":1596,
    "qs_pg:photos_sr":13,
    "qs_pg:pop_sr":0,
    "qs_pg:qs_pg_placetype":"locality",
    "qs_pg:qs_pg_placetype_gp":"Town",
    "qs_pg:woe_adm0":23424957,
    "woe:adm0_id":23424957,
    "woe:name_adm0":"Schweiz",
    "woe:name_adm1":"Kanton Bern",
    "woe:placetype":"Town",
    "wof:name":"Gimmelwald",
    "wof:placetype":"locality"
},
  "geometry": {"coordinates":[7.89149,46.546],"type":"Point"}
}