{
  "type": "Feature",
  "properties": {
    "gn:admin1_code":"TI",
    "gn:admin2_code":"2106.0",
    "gn:admin3_code":"5260.0",
    "gn:asciiname":"Pauzella",
    "gn:country_code":"CH",
    "gn:dem":475,
    "gn:feature_class":"P",
    "gn:feature_code":"PPL",
    "gn:name":"Pauzella",
    "gn:population":0,
    "gn:timezone":"Europe/Rome",
    "iso:country":"CH",
    "name:ita_x_preferred":[
        "Pauzella"
    ],
    "wof:name":"Pauzella",
    "wof:placetype":"neighbourhood"
},
  "geometry": {"coordinates":[8.971,45.83328],"type":"Point"}
}