{
  "type": "Feature",
  "properties": {
    "gn:admin1_code":"SG",
    "gn:admin2_code":"1726.0",
    "gn:admin3_code":"3342.0",
    "gn:asciiname":"Hinterbergen",
    "gn:country_code":"CH",
    "gn:dem":669,
    "gn:feature_class":"P",
    "gn:feature_code":"PPLL",
    "gn:name":"Hinterbergen",
    "gn:population":0,
    "gn:timezone":"Europe/Zurich",
    "iso:country":"CH",
    "name:deu_x_preferred":[
        "Hinterbergen"
    ],
    "wof:name":"Hinterbergen",
    "wof:placetype":"locality"
},
  "geometry": {"coordinates":[8.9471,47.25758],"type":"Point"}
}