{
  "type": "Feature",
  "properties": {
    "gn:admin1_code":"TI",
    "gn:admin2_code":"2102.0",
    "gn:admin3_code":"5049.0",
    "gn:asciiname":"Anveuda",
    "gn:country_code":"CH",
    "gn:dem":1679,
    "gn:feature_class":"P",
    "gn:feature_code":"PPL",
    "gn:name":"Anv\u00e9uda",
    "gn:population":0,
    "gn:timezone":"Europe/Zurich",
    "iso:country":"CH",
    "name:und_x_variant":[
        "Monti Anvedua",
        "Anv\u00e9uda"
    ],
    "wof:name":"Anveuda",
    "wof:placetype":"neighbourhood"
},
  "geometry": {"coordinates":[8.90101,46.54065],"type":"Point"}
}