{
  "type": "Feature",
  "properties": {
    "gn:admin1_code":"BE",
    "gn:admin2_code":"250.0",
    "gn:admin3_code":"576.0",
    "gn:asciiname":"Maennlichen",
    "gn:country_code":"CH",
    "gn:dem":2213,
    "gn:feature_class":"P",
    "gn:feature_code":"PPL",
    "gn:name":"M\u00e4nnlichen",
    "gn:population":0,
    "gn:timezone":"Europe/Zurich",
    "iso:country":"CH",
    "name:deu_x_preferred":[
        "M\u00e4nnlichen"
    ],
    "wof:name":"Maennlichen",
    "wof:placetype":"locality"
},
  "geometry": {"coordinates":[7.9421,46.61218],"type":"Point"}
}