{
  "type": "Feature",
  "properties": {
    "gn:admin1_code":"FR",
    "gn:admin2_code":"1004.0",
    "gn:admin3_code":"2216.0",
    "gn:asciiname":"Villars-sur-Marly",
    "gn:country_code":"CH",
    "gn:dem":724,
    "gn:feature_class":"P",
    "gn:feature_code":"PPL",
    "gn:name":"Villars-sur-Marly",
    "gn:population":0,
    "gn:timezone":"Europe/Zurich",
    "iso:country":"CH",
    "wof:lang_x_official":[
        "deu",
        "fra",
        "gsw",
        "ita"
    ],
    "wof:lang_x_spoken":[
        "deu",
        "fra",
        "gsw",
        "ita",
        "roh"
    ],
    "wof:name":"Villars-sur-Marly",
    "wof:placetype":"neighbourhood"
},
  "geometry": {"coordinates":[7.18581,46.77485],"type":"Point"}
}