{
  "type": "Feature",
  "properties": {
    "gn:admin1_code":"VS",
    "gn:admin2_code":"2304.0",
    "gn:admin3_code":"6054.0",
    "gn:asciiname":"Faeld",
    "gn:country_code":"CH",
    "gn:dem":1604,
    "gn:elevation":"1547.0",
    "gn:feature_class":"P",
    "gn:feature_code":"PPL",
    "gn:name":"F\u00e4ld",
    "gn:population":0,
    "gn:timezone":"Europe/Zurich",
    "iso:country":"CH",
    "wof:name":"Faeld",
    "wof:placetype":"neighbourhood"
},
  "geometry": {"coordinates":[8.21368,46.37168],"type":"Point"}
}