{
  "type": "Feature",
  "properties": {
    "gn:admin1_code":"BL",
    "gn:admin2_code":"1303.0",
    "gn:admin3_code":"2833.0",
    "gn:asciiname":"Galms",
    "gn:country_code":"CH",
    "gn:dem":497,
    "gn:feature_class":"P",
    "gn:feature_code":"PPLL",
    "gn:name":"Galms",
    "gn:population":0,
    "gn:timezone":"Europe/Zurich",
    "iso:country":"CH",
    "name:deu_x_preferred":[
        "Galms"
    ],
    "wof:name":"Galms",
    "wof:placetype":"neighbourhood"
},
  "geometry": {"coordinates":[7.72338,47.46138],"type":"Point"}
}