{
  "type": "Feature",
  "properties": {
    "gn:admin1_code":"VD",
    "gn:admin2_code":"2221.0",
    "gn:admin3_code":"5402.0",
    "gn:asciiname":"Le Bevieux",
    "gn:country_code":"CH",
    "gn:dem":485,
    "gn:elevation":"485.0",
    "gn:feature_class":"P",
    "gn:feature_code":"PPL",
    "gn:name":"Le B\u00e9vieux",
    "gn:population":0,
    "gn:timezone":"Europe/Zurich",
    "iso:country":"CH",
    "wof:name":"Le Bevieux",
    "wof:placetype":"neighbourhood"
},
  "geometry": {"coordinates":[7.03114,46.25923],"type":"Point"}
}