{
  "type": "Feature",
  "properties": {
    "gn:admin1_code":"GR",
    "gn:admin2_code":"1845.0",
    "gn:admin3_code":"3946.0",
    "gn:asciiname":"Jeli",
    "gn:country_code":"CH",
    "gn:dem":1225,
    "gn:feature_class":"P",
    "gn:feature_code":"PPL",
    "gn:name":"Jeli",
    "gn:population":0,
    "gn:timezone":"Europe/Zurich",
    "iso:country":"CH",
    "wof:lang_x_official":[
        "deu",
        "fra",
        "gsw",
        "ita"
    ],
    "wof:lang_x_spoken":[
        "deu",
        "fra",
        "gsw",
        "ita",
        "roh"
    ],
    "wof:name":"Jeli",
    "wof:placetype":"neighbourhood"
},
  "geometry": {"coordinates":[9.5124,46.93311],"type":"Point"}
}