{
  "type": "Feature",
  "properties": {
    "gn:gn_country":"CH",
    "gn:gn_fcode":"PPL",
    "gn:gn_pop":680,
    "gn:population":680,
    "iso:country":"CH",
    "name:als_x_preferred":[
        "Champagne VD"
    ],
    "name:deu_x_preferred":[
        "Champagne VD"
    ],
    "name:epo_x_preferred":[
        "Champagne VD"
    ],
    "name:jpn_x_preferred":[
        "\u30b7\u30e3\u30f3\u30d1\u30fc\u30cb\u30e5"
    ],
    "name:ltz_x_preferred":[
        "Champagne VD"
    ],
    "name:nno_x_preferred":[
        "Champagne i Sveits"
    ],
    "name:zho_x_preferred":[
        "\u5c1a\u5df4\u6d85"
    ],
    "qs_pg:aaroncc":"CH",
    "qs_pg:gn_country":"CH",
    "qs_pg:gn_fcode":"PPL",
    "qs_pg:gn_pop":680,
    "qs_pg:name":"Champagne",
    "qs_pg:photos_9r":0,
    "qs_pg:photos_sr":0,
    "qs_pg:pop_sr":2,
    "qs_pg:qs_pg_placetype":"locality",
    "wof:name":"Champagne",
    "wof:placetype":"locality",
    "wof:population":680
},
  "geometry": {"coordinates":[6.65977,46.83213],"type":"Point"}
}