{
  "type": "Feature",
  "properties": {
    "gn:admin1_code":"LU",
    "gn:admin2_code":"316.0",
    "gn:admin3_code":"1007.0",
    "gn:asciiname":"Ennetegg",
    "gn:country_code":"CH",
    "gn:dem":759,
    "gn:feature_class":"P",
    "gn:feature_code":"PPL",
    "gn:name":"Ennetegg",
    "gn:population":0,
    "gn:timezone":"Europe/Zurich",
    "iso:country":"CH",
    "wof:name":"Ennetegg",
    "wof:placetype":"neighbourhood"
},
  "geometry": {"coordinates":[8.01667,46.98333],"type":"Point"}
}