{
  "type": "Feature",
  "properties": {
    "gn:admin1_code":"LU",
    "gn:admin2_code":"314.0",
    "gn:admin3_code":"1086.0",
    "gn:asciiname":"Rueezligen",
    "gn:country_code":"CH",
    "gn:dem":565,
    "gn:feature_class":"P",
    "gn:feature_code":"PPLL",
    "gn:name":"R\u00fcezligen",
    "gn:population":0,
    "gn:timezone":"Europe/Zurich",
    "iso:country":"CH",
    "name:deu_x_preferred":[
        "R\u00fcezligen"
    ],
    "wof:name":"Rueezligen",
    "wof:placetype":"neighbourhood"
},
  "geometry": {"coordinates":[8.05442,47.1158],"type":"Point"}
}