{
  "type": "Feature",
  "properties": {
    "gn:gn_country":"CH",
    "gn:gn_fcode":"PPL",
    "gn:gn_pop":0,
    "iso:country":"CH",
    "name:cat_x_preferred":[
        "Chavannes-de-Bogis"
    ],
    "name:deu_x_preferred":[
        "Chavannes-de-Bogis"
    ],
    "name:eng_x_preferred":[
        "Chavannes-de-Bogis"
    ],
    "name:epo_x_preferred":[
        "Chavannes-de-Bogis"
    ],
    "name:eus_x_preferred":[
        "Chavannes-de-Bogis"
    ],
    "name:fra_x_preferred":[
        "Chavannes-de-Bogis"
    ],
    "name:gsw_x_preferred":[
        "Chavannes-de-Bogis"
    ],
    "name:hun_x_preferred":[
        "Chavannes-de-Bogis"
    ],
    "name:ita_x_preferred":[
        "Chavannes-de-Bogis"
    ],
    "name:lit_x_preferred":[
        "\u0160avanas prie Bogio"
    ],
    "name:lmo_x_preferred":[
        "Chavannes-de-Bogis"
    ],
    "name:ltz_x_preferred":[
        "Chavannes-de-Bogis"
    ],
    "name:msa_x_preferred":[
        "Chavannes-de-Bogis"
    ],
    "name:nld_x_preferred":[
        "Chavannes-de-Bogis"
    ],
    "name:nno_x_preferred":[
        "Chavannes-de-Bogis"
    ],
    "name:oci_x_preferred":[
        "Chavannes-de-Bogis"
    ],
    "name:por_x_preferred":[
        "Chavannes-de-Bogis"
    ],
    "name:roh_x_preferred":[
        "Chavannes-de-Bogis"
    ],
    "name:spa_x_preferred":[
        "Chavannes-de-Bogis"
    ],
    "name:swe_x_preferred":[
        "Chavannes-de-Bogis"
    ],
    "name:vol_x_preferred":[
        "Chavannes-de-Bogis"
    ],
    "name:war_x_preferred":[
        "Chavannes-de-Bogis"
    ],
    "name:zho_x_preferred":[
        "\u6c99\u74e6\u8bb7\u5fb7\u535a\u5409"
    ],
    "qs_pg:aaroncc":"CH",
    "qs_pg:gn_country":"CH",
    "qs_pg:gn_fcode":"PPL",
    "qs_pg:gn_pop":0,
    "qs_pg:name":"Chavannes-de-Bogis",
    "qs_pg:name_adm0":"Schweiz",
    "qs_pg:name_adm1":"Canton de Vaud",
    "qs_pg:photos":26,
    "qs_pg:photos_1k":5,
    "qs_pg:photos_9k":1,
    "qs_pg:photos_9r":2,
    "qs_pg:photos_all":26,
    "qs_pg:photos_sr":2,
    "qs_pg:pop_sr":0,
    "qs_pg:qs_pg_placetype":"locality",
    "qs_pg:qs_pg_placetype_gp":"Town",
    "qs_pg:woe_adm0":23424957,
    "woe:adm0_id":23424957,
    "woe:name_adm0":"Schweiz",
    "woe:name_adm1":"Canton de Vaud",
    "woe:placetype":"Town",
    "wof:name":"Chavannes-de-Bogis",
    "wof:placetype":"locality"
},
  "geometry": {"coordinates":[6.16204,46.34539],"type":"Point"}
}