{
  "type": "Feature",
  "properties": {
    "gn:admin1_code":"SG",
    "gn:admin2_code":"1727.0",
    "gn:admin3_code":"3352.0",
    "gn:asciiname":"Brandholz",
    "gn:country_code":"CH",
    "gn:dem":688,
    "gn:feature_class":"P",
    "gn:feature_code":"PPLL",
    "gn:name":"Brandholz",
    "gn:population":0,
    "gn:timezone":"Europe/Zurich",
    "iso:country":"CH",
    "name:deu_x_preferred":[
        "Brandholz"
    ],
    "wof:name":"Brandholz",
    "wof:placetype":"neighbourhood"
},
  "geometry": {"coordinates":[9.14272,47.25399],"type":"Point"}
}