{
  "type": "Feature",
  "properties": {
    "gn:admin1_code":"TG",
    "gn:admin2_code":"2012.0",
    "gn:admin3_code":"4841.0",
    "gn:asciiname":"Saentisblick",
    "gn:country_code":"CH",
    "gn:dem":440,
    "gn:feature_class":"P",
    "gn:feature_code":"PPLL",
    "gn:name":"S\u00e4ntisblick",
    "gn:population":0,
    "gn:timezone":"Europe/Zurich",
    "iso:country":"CH",
    "name:deu_x_preferred":[
        "S\u00e4ntisblick"
    ],
    "wof:name":"Saentisblick",
    "wof:placetype":"locality"
},
  "geometry": {"coordinates":[8.97259,47.60446],"type":"Point"}
}