{
  "type": "Feature",
  "properties": {
    "gn:gn_country":"CH",
    "gn:gn_fcode":"PPL",
    "gn:gn_pop":4022,
    "gn:population":4022,
    "iso:country":"CH",
    "name:alb_x_preferred":[
        "Niederlenz"
    ],
    "name:ast_x_preferred":[
        "Niederlenz"
    ],
    "name:baq_x_preferred":[
        "Niederlenz"
    ],
    "name:cat_x_preferred":[
        "Niederlenz"
    ],
    "name:chi_x_preferred":[
        "\u4e0b\u502b\u8328"
    ],
    "name:dut_x_preferred":[
        "Niederlenz"
    ],
    "name:eng_x_preferred":[
        "Niederlenz"
    ],
    "name:epo_x_preferred":[
        "Niederlenz"
    ],
    "name:fre_x_preferred":[
        "Niederlenz"
    ],
    "name:ger_x_preferred":[
        "Niederlenz"
    ],
    "name:gsw_x_preferred":[
        "Niederlenz"
    ],
    "name:hun_x_preferred":[
        "Niederlenz"
    ],
    "name:ita_x_preferred":[
        "Niederlenz"
    ],
    "name:kaz_x_preferred":[
        "\u041d\u0438\u0434\u0435\u0440\u043b\u0435\u043d\u0446"
    ],
    "name:lmo_x_preferred":[
        "Niederlenz"
    ],
    "name:may_x_preferred":[
        "Niederlenz"
    ],
    "name:nno_x_preferred":[
        "Niederlenz"
    ],
    "name:oci_x_preferred":[
        "Niederlenz"
    ],
    "name:pms_x_preferred":[
        "Niederlenz"
    ],
    "name:por_x_preferred":[
        "Niederlenz"
    ],
    "name:rus_x_preferred":[
        "\u041d\u0438\u0434\u0435\u0440\u043b\u0435\u043d\u0446"
    ],
    "name:spa_x_preferred":[
        "Niederlenz"
    ],
    "name:swe_x_preferred":[
        "Niederlenz"
    ],
    "name:uzb_x_preferred":[
        "Niederlenz"
    ],
    "name:vol_x_preferred":[
        "Niederlenz"
    ],
    "name:war_x_preferred":[
        "Niederlenz"
    ],
    "name:zho_x_preferred":[
        "\u4e0b\u502b\u8328"
    ],
    "qs_pg:aaroncc":"CH",
    "qs_pg:gn_country":"CH",
    "qs_pg:gn_fcode":"PPL",
    "qs_pg:gn_pop":4022,
    "qs_pg:name":"Niederlenz",
    "qs_pg:name_adm0":"Schweiz",
    "qs_pg:name_adm1":"Kanton Aargau",
    "qs_pg:photos":76,
    "qs_pg:photos_1k":15,
    "qs_pg:photos_9k":1,
    "qs_pg:photos_9r":3,
    "qs_pg:photos_all":76,
    "qs_pg:photos_sr":3,
    "qs_pg:pop_sr":4,
    "qs_pg:qs_pg_placetype":"locality",
    "qs_pg:qs_pg_placetype_gp":"Town",
    "qs_pg:woe_adm0":23424957,
    "woe:adm0_id":23424957,
    "woe:name_adm0":"Schweiz",
    "woe:name_adm1":"Kanton Aargau",
    "woe:placetype":"Town",
    "wof:name":"Niederlenz",
    "wof:placetype":"locality",
    "wof:population":4022
},
  "geometry": {"coordinates":[8.1764,47.40079],"type":"Point"}
}