{
  "type": "Feature",
  "properties": {
    "gn:admin1_code":"SG",
    "gn:admin2_code":"1727.0",
    "gn:admin3_code":"3352.0",
    "gn:asciiname":"Kappel",
    "gn:country_code":"CH",
    "gn:dem":632,
    "gn:elevation":"630.0",
    "gn:feature_class":"P",
    "gn:feature_code":"PPL",
    "gn:name":"Kappel",
    "gn:population":0,
    "gn:timezone":"Europe/Zurich",
    "iso:country":"CH",
    "wof:name":"Kappel",
    "wof:placetype":"neighbourhood"
},
  "geometry": {"coordinates":[9.11622,47.26891],"type":"Point"}
}