{
  "type": "Feature",
  "properties": {
    "gn:admin1_code":"SG",
    "gn:admin2_code":"1727.0",
    "gn:admin3_code":"3352.0",
    "gn:asciiname":"Kappel",
    "gn:country_code":"CH",
    "gn:dem":632,
    "gn:elevation":"630.0",
    "gn:feature_class":"P",
    "gn:feature_code":"PPL",
    "gn:name":"Kappel",
    "gn:population":0,
    "gn:timezone":"Europe/Zurich",
    "iso:country":"CH",
    "name:als_x_preferred":[
        "Kappel"
    ],
    "name:ceb_x_preferred":[
        "Kappel"
    ],
    "name:deu_x_preferred":[
        "Kappel"
    ],
    "name:epo_x_preferred":[
        "Kappel"
    ],
    "name:fra_x_preferred":[
        "Kappel"
    ],
    "name:ita_x_preferred":[
        "Kappel"
    ],
    "name:nld_x_preferred":[
        "Kappel"
    ],
    "name:pol_x_preferred":[
        "Kappel"
    ],
    "name:spa_x_preferred":[
        "Kappel"
    ],
    "name:swe_x_preferred":[
        "Kappel"
    ],
    "name:vol_x_preferred":[
        "Kappel"
    ],
    "wof:lang_x_official":[
        "deu",
        "fra",
        "gsw",
        "ita"
    ],
    "wof:lang_x_spoken":[
        "deu",
        "fra",
        "gsw",
        "ita",
        "roh"
    ],
    "wof:name":"Kappel",
    "wof:placetype":"neighbourhood"
},
  "geometry": {"coordinates":[9.11622,47.26891],"type":"Point"}
}