{
  "type": "Feature",
  "properties": {
    "gn:admin1_code":"BE",
    "gn:admin2_code":"250.0",
    "gn:admin3_code":"579.0",
    "gn:asciiname":"Speicher",
    "gn:country_code":"CH",
    "gn:dem":1684,
    "gn:feature_class":"P",
    "gn:feature_code":"PPL",
    "gn:name":"Speicher",
    "gn:population":0,
    "gn:timezone":"Europe/Zurich",
    "iso:country":"CH",
    "name:ceb_x_preferred":[
        "Speicher"
    ],
    "name:deu_x_preferred":[
        "Speicher"
    ],
    "name:epo_x_preferred":[
        "Speicher"
    ],
    "name:fra_x_preferred":[
        "Speicher"
    ],
    "name:ita_x_preferred":[
        "Speicher"
    ],
    "name:nld_x_preferred":[
        "Speicher"
    ],
    "name:pol_x_preferred":[
        "Speicher"
    ],
    "name:rus_x_preferred":[
        "\u0428\u043f\u0430\u0439\u0445\u0435\u0440"
    ],
    "name:swe_x_preferred":[
        "Speicher"
    ],
    "name:vol_x_preferred":[
        "Speicher"
    ],
    "wof:lang_x_official":[
        "deu",
        "fra",
        "gsw",
        "ita"
    ],
    "wof:lang_x_spoken":[
        "deu",
        "fra",
        "gsw",
        "ita",
        "roh"
    ],
    "wof:name":"Speicher",
    "wof:placetype":"neighbourhood"
},
  "geometry": {"coordinates":[7.88879,46.76308],"type":"Point"}
}