{
  "type": "Feature",
  "properties": {
    "gn:admin1_code":"TG",
    "gn:admin2_code":"2015.0",
    "gn:admin3_code":"4941.0",
    "gn:asciiname":"Ruberbaum",
    "gn:country_code":"CH",
    "gn:dem":461,
    "gn:feature_class":"P",
    "gn:feature_code":"PPLL",
    "gn:name":"Ruberbaum",
    "gn:population":0,
    "gn:timezone":"Europe/Zurich",
    "iso:country":"CH",
    "name:deu_x_preferred":[
        "Ruberbaum"
    ],
    "wof:name":"Ruberbaum",
    "wof:placetype":"neighbourhood"
},
  "geometry": {"coordinates":[9.07875,47.58872],"type":"Point"}
}