{
  "type": "Feature",
  "properties": {
    "gn:admin1_code":"VD",
    "gn:admin2_code":"2224.0",
    "gn:admin3_code":"5910.0",
    "gn:asciiname":"La Rupe",
    "gn:country_code":"CH",
    "gn:dem":560,
    "gn:feature_class":"P",
    "gn:feature_code":"PPL",
    "gn:name":"La Rupe",
    "gn:population":0,
    "gn:timezone":"Europe/Zurich",
    "iso:country":"CH",
    "wof:name":"La Rupe",
    "wof:placetype":"locality"
},
  "geometry": {"coordinates":[6.70012,46.7508],"type":"Point"}
}