{
  "type": "Feature",
  "properties": {
    "gn:admin1_code":"VD",
    "gn:admin2_code":"2222.0",
    "gn:admin3_code":"5692.0",
    "gn:asciiname":"La Gotte",
    "gn:country_code":"CH",
    "gn:dem":741,
    "gn:feature_class":"P",
    "gn:feature_code":"PPL",
    "gn:name":"La Gotte",
    "gn:population":0,
    "gn:timezone":"Europe/Zurich",
    "iso:country":"CH",
    "name:fra_x_preferred":[
        "La Gotte"
    ],
    "wof:name":"La Gotte",
    "wof:placetype":"neighbourhood"
},
  "geometry": {"coordinates":[6.77163,46.6191],"type":"Point"}
}