{
  "type": "Feature",
  "properties": {
    "gn:admin1_code":"TG",
    "gn:admin2_code":"2013.0",
    "gn:admin3_code":"4846.0",
    "gn:asciiname":"Rennental",
    "gn:country_code":"CH",
    "gn:dem":695,
    "gn:feature_class":"P",
    "gn:feature_code":"PPLL",
    "gn:name":"Rennental",
    "gn:population":0,
    "gn:timezone":"Europe/Zurich",
    "iso:country":"CH",
    "name:deu_x_preferred":[
        "Rennental"
    ],
    "wof:name":"Rennental",
    "wof:placetype":"locality"
},
  "geometry": {"coordinates":[9.04003,47.65182],"type":"Point"}
}