{
  "type": "Feature",
  "properties": {
    "gn:gn_country":"CH",
    "gn:gn_fcode":"PPL",
    "gn:gn_pop":477,
    "gn:population":477,
    "iso:country":"CH",
    "name:ces_x_preferred":[
        "M\u00f6rel"
    ],
    "name:deu_x_preferred":[
        "M\u00f6rel VS"
    ],
    "name:eng_x_preferred":[
        "M\u00f6rel"
    ],
    "name:fra_x_preferred":[
        "M\u00f6rel"
    ],
    "name:nld_x_preferred":[
        "M\u00f6rel"
    ],
    "name:pms_x_preferred":[
        "M\u00f6rel"
    ],
    "name:por_x_preferred":[
        "M\u00f6rel"
    ],
    "name:roh_x_preferred":[
        "M\u00f6rel"
    ],
    "name:ron_x_preferred":[
        "M\u00f6rel"
    ],
    "name:swe_x_preferred":[
        "M\u00f6rel"
    ],
    "name:vol_x_preferred":[
        "M\u00f6rel"
    ],
    "name:zho_x_preferred":[
        "\u9ed8\u96f7\u5c14"
    ],
    "qs_pg:aaroncc":"CH",
    "qs_pg:gn_country":"CH",
    "qs_pg:gn_fcode":"PPL",
    "qs_pg:gn_pop":477,
    "qs_pg:name":"M\u00f6rel",
    "qs_pg:name_adm0":"Schweiz",
    "qs_pg:name_adm1":"Canton de Valais",
    "qs_pg:photos_9k":1,
    "qs_pg:photos_9r":1,
    "qs_pg:photos_all":3,
    "qs_pg:photos_sr":0,
    "qs_pg:pop_sr":2,
    "qs_pg:qs_pg_placetype":"locality",
    "qs_pg:qs_pg_placetype_gp":"Town",
    "qs_pg:woe_adm0":23424957,
    "woe:adm0_id":23424957,
    "woe:name_adm0":"Schweiz",
    "woe:name_adm1":"Canton de Valais",
    "woe:placetype":"Town",
    "wof:name":"M\u00f6rel",
    "wof:placetype":"locality",
    "wof:population":477
},
  "geometry": {"coordinates":[8.04332,46.35499],"type":"Point"}
}