{
  "type": "Feature",
  "properties": {
    "gn:population":3066,
    "iso:country":"CH",
    "name:als_x_preferred":[
        "Leysin"
    ],
    "name:bel_x_preferred":[
        "\u041b\u0435\u0437\u044d\u043d"
    ],
    "name:cat_x_preferred":[
        "Leysin"
    ],
    "name:ceb_x_preferred":[
        "Leysin"
    ],
    "name:ces_x_preferred":[
        "Leysin"
    ],
    "name:cym_x_preferred":[
        "Leysin"
    ],
    "name:deu_x_preferred":[
        "Leysin"
    ],
    "name:eng_x_preferred":[
        "Leysin"
    ],
    "name:epo_x_preferred":[
        "Leysin"
    ],
    "name:est_x_preferred":[
        "Leysini vald"
    ],
    "name:eus_x_preferred":[
        "Leysin"
    ],
    "name:fin_x_preferred":[
        "Leysin"
    ],
    "name:fra_x_preferred":[
        "Leysin"
    ],
    "name:frp_x_preferred":[
        "L\u00easin"
    ],
    "name:gsw_x_preferred":[
        "Leysin"
    ],
    "name:heb_x_preferred":[
        "\u05dc\u05d6\u05d0\u05df"
    ],
    "name:hun_x_preferred":[
        "Leysin"
    ],
    "name:ita_x_preferred":[
        "Leysin"
    ],
    "name:jpn_x_preferred":[
        "\u30ec\u30b6\u30f3"
    ],
    "name:lav_x_preferred":[
        "Lez\u0113na"
    ],
    "name:lit_x_preferred":[
        "Leisenas"
    ],
    "name:lmo_x_preferred":[
        "Leysin"
    ],
    "name:mkd_x_preferred":[
        "\u041b\u0435\u0437\u0435\u043d"
    ],
    "name:msa_x_preferred":[
        "Leysin"
    ],
    "name:nld_x_preferred":[
        "Leysin"
    ],
    "name:nno_x_preferred":[
        "Leysin"
    ],
    "name:nob_x_preferred":[
        "Leysin"
    ],
    "name:oci_x_preferred":[
        "Leysin"
    ],
    "name:pol_x_preferred":[
        "Leysin"
    ],
    "name:por_x_preferred":[
        "Leysin"
    ],
    "name:roh_x_preferred":[
        "Leysin"
    ],
    "name:ron_x_preferred":[
        "Leysin"
    ],
    "name:rus_x_preferred":[
        "\u041b\u0435\u0437\u0435\u043d"
    ],
    "name:spa_x_preferred":[
        "Leysin"
    ],
    "name:swe_x_preferred":[
        "Leysin"
    ],
    "name:vol_x_preferred":[
        "Leysin"
    ],
    "name:war_x_preferred":[
        "Leysin"
    ],
    "name:zho_x_preferred":[
        "\u83b1\u68ee"
    ],
    "qs:a0":"Schweiz#Suisse#Svizzera#Svizra",
    "qs:a1":"*Vaud",
    "qs:a1r":"0",
    "qs:adm0":"Schweiz#Suisse#Svizzera#Svizra",
    "qs:la_lc":"*",
    "qs:level":"locality",
    "qs:loc":"Leysin",
    "qs:loc_alt":"Leysin",
    "qs:pop":0,
    "qs:type":"buffered point",
    "wd:wordcount":2403,
    "wof:lang":[
        "fre"
    ],
    "wof:name":"Leysin",
    "wof:placetype":"locality",
    "wof:population":3066
},
  "geometry": {"coordinates":[7.008003,46.343136],"type":"Point"}
}