{
  "type": "Feature",
  "properties": {
    "gn:admin1_code":"AR",
    "gn:admin2_code":"1503.0",
    "gn:admin3_code":"3038.0",
    "gn:asciiname":"Muehltobel",
    "gn:country_code":"CH",
    "gn:dem":644,
    "gn:feature_class":"P",
    "gn:feature_code":"PPL",
    "gn:name":"M\u00fchltobel",
    "gn:population":0,
    "gn:timezone":"Europe/Zurich",
    "iso:country":"CH",
    "wof:name":"Muehltobel",
    "wof:placetype":"neighbourhood"
},
  "geometry": {"coordinates":[9.5657,47.45585],"type":"Point"}
}