{
  "type": "Feature",
  "properties": {
    "gn:admin1_code":"TG",
    "gn:admin2_code":"2015.0",
    "gn:admin3_code":"4511.0",
    "gn:asciiname":"Zihlschlacht",
    "gn:country_code":"CH",
    "gn:dem":529,
    "gn:feature_class":"P",
    "gn:feature_code":"PPL",
    "gn:name":"Zihlschlacht",
    "gn:population":0,
    "gn:timezone":"Europe/Zurich",
    "iso:country":"CH",
    "wof:name":"Zihlschlacht",
    "wof:placetype":"locality"
},
  "geometry": {"coordinates":[9.25736,47.52065],"type":"Point"}
}