{
  "type": "Feature",
  "properties": {
    "gn:gn_country":"CH",
    "gn:gn_fcode":"PPLL",
    "gn:gn_pop":9,
    "gn:population":9,
    "iso:country":"CH",
    "name:deu_x_preferred":[
        "Lindenhof"
    ],
    "name:lat_x_preferred":[
        "Lindenhof"
    ],
    "name:pol_x_preferred":[
        "Lindenhof"
    ],
    "name:rus_x_preferred":[
        "\u041b\u0438\u043d\u0434\u0435\u043d\u0445\u043e\u0444"
    ],
    "name:tur_x_preferred":[
        "Lindenhof"
    ],
    "qs_pg:aaroncc":"CH",
    "qs_pg:gn_country":"CH",
    "qs_pg:gn_fcode":"PPLL",
    "qs_pg:gn_pop":9,
    "qs_pg:name":"Lindenhof",
    "qs_pg:photos_9r":0,
    "qs_pg:photos_sr":0,
    "qs_pg:pop_sr":1,
    "qs_pg:qs_pg_placetype":"locality",
    "wof:name":"Lindenhof",
    "wof:placetype":"neighbourhood",
    "wof:population":9
},
  "geometry": {"coordinates":[8.81092,47.62487],"type":"Point"}
}