{
  "type": "Feature",
  "properties": {
    "gn:gn_country":"CH",
    "gn:gn_fcode":"PPL",
    "gn:gn_pop":513,
    "gn:population":513,
    "iso:country":"CH",
    "name:cat_x_preferred":[
        "Eischoll"
    ],
    "name:deu_x_preferred":[
        "Eischoll"
    ],
    "name:eng_x_preferred":[
        "Eischoll"
    ],
    "name:epo_x_preferred":[
        "Eischoll"
    ],
    "name:eus_x_preferred":[
        "Eischoll"
    ],
    "name:fra_x_preferred":[
        "Eischoll"
    ],
    "name:hun_x_preferred":[
        "Eischoll"
    ],
    "name:ita_x_preferred":[
        "Eischoll"
    ],
    "name:lmo_x_preferred":[
        "Eischoll"
    ],
    "name:msa_x_preferred":[
        "Eischoll"
    ],
    "name:nld_x_preferred":[
        "Eischoll"
    ],
    "name:nno_x_preferred":[
        "Eischoll"
    ],
    "name:oci_x_preferred":[
        "Eischoll"
    ],
    "name:pms_x_preferred":[
        "Eischoll"
    ],
    "name:por_x_preferred":[
        "Eischoll"
    ],
    "name:roh_x_preferred":[
        "Eischoll"
    ],
    "name:spa_x_preferred":[
        "Eischoll"
    ],
    "name:sqi_x_preferred":[
        "Eischoll"
    ],
    "name:swe_x_preferred":[
        "Eischoll"
    ],
    "name:unk_x_variant":[
        "Eischol"
    ],
    "name:vol_x_preferred":[
        "Eischoll"
    ],
    "name:war_x_preferred":[
        "Eischoll"
    ],
    "name:zho_x_preferred":[
        "\u827e\u7d39\u723e"
    ],
    "qs_pg:aaroncc":"CH",
    "qs_pg:gn_country":"CH",
    "qs_pg:gn_fcode":"PPL",
    "qs_pg:gn_pop":513,
    "qs_pg:name":"Eischoll",
    "qs_pg:name_adm0":"Schweiz",
    "qs_pg:name_adm1":"Canton de Valais",
    "qs_pg:photos":53,
    "qs_pg:photos_1k":11,
    "qs_pg:photos_9k":1,
    "qs_pg:photos_9r":2,
    "qs_pg:photos_all":53,
    "qs_pg:photos_sr":2,
    "qs_pg:pop_sr":2,
    "qs_pg:qs_pg_placetype":"locality",
    "qs_pg:qs_pg_placetype_gp":"Town",
    "qs_pg:woe_adm0":23424957,
    "woe:adm0_id":23424957,
    "woe:name_adm0":"Schweiz",
    "woe:name_adm1":"Canton de Valais",
    "woe:placetype":"Town",
    "wof:name":"Eischoll",
    "wof:placetype":"locality",
    "wof:population":513
},
  "geometry": {"coordinates":[7.77995,46.29352],"type":"Point"}
}