{
  "type": "Feature",
  "properties": {
    "gn:gn_country":"CH",
    "gn:gn_fcode":"PPL",
    "gn:gn_pop":2369,
    "gn:population":2369,
    "iso:country":"CH",
    "name:ara_x_preferred":[
        "\u0641\u0648\u0646\u063a\u0646"
    ],
    "name:cat_x_preferred":[
        "Pfungen"
    ],
    "name:chv_x_preferred":[
        "\u041f\u0444\u0443\u043d\u0433\u0435\u043d"
    ],
    "name:deu_x_preferred":[
        "Pfungen"
    ],
    "name:eng_x_preferred":[
        "Pfungen"
    ],
    "name:epo_x_preferred":[
        "Pfungen"
    ],
    "name:eus_x_preferred":[
        "Pfungen"
    ],
    "name:fra_x_preferred":[
        "Pfungen"
    ],
    "name:gsw_x_preferred":[
        "Pfunge"
    ],
    "name:hun_x_preferred":[
        "Pfungen"
    ],
    "name:ita_x_preferred":[
        "Pfungen"
    ],
    "name:kaz_x_preferred":[
        "\u041f\u0444\u0443\u043d\u0433\u0435\u043d"
    ],
    "name:lat_x_preferred":[
        "Funginga"
    ],
    "name:lmo_x_preferred":[
        "Pfungen"
    ],
    "name:msa_x_preferred":[
        "Pfungen"
    ],
    "name:nld_x_preferred":[
        "Pfungen"
    ],
    "name:nno_x_preferred":[
        "Pfungen"
    ],
    "name:oci_x_preferred":[
        "Pfungen"
    ],
    "name:pms_x_preferred":[
        "Pfungen"
    ],
    "name:por_x_preferred":[
        "Pfungen"
    ],
    "name:rus_x_preferred":[
        "\u041f\u0444\u0443\u043d\u0433\u0435\u043d"
    ],
    "name:spa_x_preferred":[
        "Pfungen"
    ],
    "name:uzb_x_preferred":[
        "Pfungen"
    ],
    "name:vec_x_preferred":[
        "Pfungen"
    ],
    "name:vol_x_preferred":[
        "Pfungen"
    ],
    "name:war_x_preferred":[
        "Pfungen"
    ],
    "name:zho_x_preferred":[
        "\u666e\u8c50\u6839"
    ],
    "qs_pg:aaroncc":"CH",
    "qs_pg:gn_country":"CH",
    "qs_pg:gn_fcode":"PPL",
    "qs_pg:gn_pop":2369,
    "qs_pg:name":"Pfungen",
    "qs_pg:name_adm0":"Schweiz",
    "qs_pg:name_adm1":"Kanton Z\u00fcrich",
    "qs_pg:photos":17,
    "qs_pg:photos_1k":3,
    "qs_pg:photos_9k":1,
    "qs_pg:photos_9r":1,
    "qs_pg:photos_all":17,
    "qs_pg:photos_sr":1,
    "qs_pg:pop_sr":4,
    "qs_pg:qs_pg_placetype":"locality",
    "qs_pg:qs_pg_placetype_gp":"Town",
    "qs_pg:woe_adm0":23424957,
    "woe:adm0_id":23424957,
    "woe:name_adm0":"Schweiz",
    "woe:name_adm1":"Kanton Z\u00fcrich",
    "woe:placetype":"Town",
    "wof:name":"Pfungen",
    "wof:placetype":"locality",
    "wof:population":2369
},
  "geometry": {"coordinates":[8.6423,47.51394],"type":"Point"}
}