{
  "type": "Feature",
  "properties": {
    "gn:admin1_code":"SG",
    "gn:admin2_code":"1725.0",
    "gn:admin3_code":"3298.0",
    "gn:asciiname":"Schwamm",
    "gn:country_code":"CH",
    "gn:dem":1464,
    "gn:feature_class":"P",
    "gn:feature_code":"PPLL",
    "gn:name":"Schwamm",
    "gn:population":0,
    "gn:timezone":"Europe/Zurich",
    "iso:country":"CH",
    "name:deu_x_preferred":[
        "Schwamm"
    ],
    "wof:name":"Schwamm",
    "wof:placetype":"neighbourhood"
},
  "geometry": {"coordinates":[9.38054,47.11671],"type":"Point"}
}