{
  "type": "Feature",
  "properties": {
    "gn:gn_country":"CH",
    "gn:gn_fcode":"PPL",
    "gn:gn_pop":259,
    "gn:population":259,
    "iso:country":"CH",
    "name:alb_x_preferred":[
        "Zeneggen"
    ],
    "name:baq_x_preferred":[
        "Zeneggen"
    ],
    "name:cat_x_preferred":[
        "Zeneggen"
    ],
    "name:chi_x_preferred":[
        "\u7b56\u5167\u6839"
    ],
    "name:dut_x_preferred":[
        "Zeneggen"
    ],
    "name:eng_x_preferred":[
        "Zeneggen"
    ],
    "name:epo_x_preferred":[
        "Zeneggen"
    ],
    "name:fre_x_preferred":[
        "Zeneggen"
    ],
    "name:ger_x_preferred":[
        "Zeneggen"
    ],
    "name:hun_x_preferred":[
        "Zeneggen"
    ],
    "name:ita_x_preferred":[
        "Zeneggen"
    ],
    "name:lmo_x_preferred":[
        "Zeneggen"
    ],
    "name:may_x_preferred":[
        "Zeneggen"
    ],
    "name:nno_x_preferred":[
        "Zeneggen"
    ],
    "name:oci_x_preferred":[
        "Zeneggen"
    ],
    "name:pms_x_preferred":[
        "Zeneggen"
    ],
    "name:por_x_preferred":[
        "Zeneggen"
    ],
    "name:roh_x_preferred":[
        "Zeneggen"
    ],
    "name:spa_x_preferred":[
        "Zeneggen"
    ],
    "name:swe_x_preferred":[
        "Zeneggen"
    ],
    "name:vol_x_preferred":[
        "Zeneggen"
    ],
    "name:war_x_preferred":[
        "Zeneggen"
    ],
    "name:zho_x_preferred":[
        "\u7b56\u5167\u6839"
    ],
    "qs_pg:aaroncc":"CH",
    "qs_pg:gn_country":"CH",
    "qs_pg:gn_fcode":"PPL",
    "qs_pg:gn_pop":259,
    "qs_pg:name":"Zeneggen",
    "qs_pg:name_adm0":"Schweiz",
    "qs_pg:name_adm1":"Canton de Valais",
    "qs_pg:photos":117,
    "qs_pg:photos_1k":24,
    "qs_pg:photos_9k":1,
    "qs_pg:photos_9r":3,
    "qs_pg:photos_all":117,
    "qs_pg:photos_sr":3,
    "qs_pg:pop_sr":2,
    "qs_pg:qs_pg_placetype":"locality",
    "qs_pg:qs_pg_placetype_gp":"Town",
    "qs_pg:woe_adm0":23424957,
    "woe:adm0_id":23424957,
    "woe:name_adm0":"Schweiz",
    "woe:name_adm1":"Canton de Valais",
    "woe:placetype":"Town",
    "wof:name":"Zeneggen",
    "wof:placetype":"locality",
    "wof:population":259
},
  "geometry": {"coordinates":[7.86535,46.27341],"type":"Point"}
}