{
  "type": "Feature",
  "properties": {
    "gn:admin1_code":"BE",
    "gn:admin2_code":"246.0",
    "gn:admin3_code":"855.0",
    "gn:asciiname":"AEckematt",
    "gn:country_code":"CH",
    "gn:dem":658,
    "gn:elevation":"663.0",
    "gn:feature_class":"P",
    "gn:feature_code":"PPL",
    "gn:name":"\u00c4ckematt",
    "gn:population":0,
    "gn:timezone":"Europe/Zurich",
    "iso:country":"CH",
    "wof:name":"AEckematt",
    "wof:placetype":"locality"
},
  "geometry": {"coordinates":[7.36425,46.85909],"type":"Point"}
}