{
  "type": "Feature",
  "properties": {
    "gn:gn_country":"CH",
    "gn:gn_fcode":"PPLX",
    "gn:gn_pop":377,
    "gn:population":377,
    "iso:country":"CH",
    "name:eng_x_preferred":[
        "Isleren"
    ],
    "name:eng_x_variant":[
        "Zumikon / Isleren"
    ],
    "name:unk_x_variant":[
        "Isleren"
    ],
    "qs_pg:aaroncc":"CH",
    "qs_pg:gn_country":"CH",
    "qs_pg:gn_fcode":"PPLX",
    "qs_pg:gn_pop":377,
    "qs_pg:name":"Zumikon / Isleren",
    "qs_pg:photos_9r":0,
    "qs_pg:photos_sr":0,
    "qs_pg:pop_sr":2,
    "qs_pg:qs_pg_placetype":"neighbourhood",
    "wof:name":"Isleren",
    "wof:placetype":"neighbourhood",
    "wof:population":377
},
  "geometry": {"coordinates":[8.61335,47.33396],"type":"Point"}
}