{
  "type": "Feature",
  "properties": {
    "gn:admin1_code":"SG",
    "gn:admin2_code":"1725.0",
    "gn:admin3_code":"3292.0",
    "gn:asciiname":"Portels",
    "gn:country_code":"CH",
    "gn:dem":664,
    "gn:elevation":"721.0",
    "gn:feature_class":"P",
    "gn:feature_code":"PPL",
    "gn:name":"Portels",
    "gn:population":0,
    "gn:timezone":"Europe/Zurich",
    "iso:country":"CH",
    "name:deu_x_preferred":[
        "Flumserberg Portels"
    ],
    "wof:lang_x_official":[
        "deu",
        "fra",
        "gsw",
        "ita"
    ],
    "wof:lang_x_spoken":[
        "deu",
        "fra",
        "gsw",
        "ita",
        "roh"
    ],
    "wof:name":"Portels",
    "wof:placetype":"neighbourhood"
},
  "geometry": {"coordinates":[9.33721,47.08402],"type":"Point"}
}