{
  "type": "Feature",
  "properties": {
    "gn:population":3600,
    "iso:country":"CH",
    "name:cat_x_preferred":[
        "Sins"
    ],
    "name:deu_x_preferred":[
        "Sins"
    ],
    "name:eng_x_preferred":[
        "Sins"
    ],
    "name:epo_x_preferred":[
        "Sins"
    ],
    "name:eus_x_preferred":[
        "Sins"
    ],
    "name:fra_x_preferred":[
        "Sins"
    ],
    "name:gsw_x_preferred":[
        "Seis"
    ],
    "name:hun_x_preferred":[
        "Sins"
    ],
    "name:ita_x_preferred":[
        "Sins"
    ],
    "name:kaz_x_preferred":[
        "\u0417\u0438\u043d\u0441"
    ],
    "name:kor_x_preferred":[
        "\uc2e0\uc2a4"
    ],
    "name:lmo_x_preferred":[
        "Sins"
    ],
    "name:msa_x_preferred":[
        "Sins"
    ],
    "name:nld_x_preferred":[
        "Sins"
    ],
    "name:nno_x_preferred":[
        "Sins"
    ],
    "name:oci_x_preferred":[
        "Sins"
    ],
    "name:pms_x_preferred":[
        "Sins"
    ],
    "name:por_x_preferred":[
        "Sins"
    ],
    "name:rus_x_preferred":[
        "\u0417\u0438\u043d\u0441"
    ],
    "name:spa_x_preferred":[
        "Sins"
    ],
    "name:sqi_x_preferred":[
        "Sins"
    ],
    "name:swe_x_preferred":[
        "Sins"
    ],
    "name:uzb_x_preferred":[
        "Sins"
    ],
    "name:vie_x_preferred":[
        "Sins"
    ],
    "name:vol_x_preferred":[
        "Sins"
    ],
    "name:war_x_preferred":[
        "Sins"
    ],
    "name:zho_x_preferred":[
        "\u8f9b\u65af"
    ],
    "qs:a0":"Schweiz#Suisse#Svizzera#Svizra",
    "qs:a1":"*Aargau",
    "qs:a1r":"0",
    "qs:adm0":"Schweiz#Suisse#Svizzera#Svizra",
    "qs:la_lc":"*",
    "qs:level":"locality",
    "qs:loc":"Sins",
    "qs:loc_alt":"Sins",
    "qs:pop":0,
    "qs:type":"buffered point",
    "wd:wordcount":2976,
    "wof:lang":[
        "ger"
    ],
    "wof:name":"Sins",
    "wof:placetype":"locality",
    "wof:population":3600
},
  "geometry": {"coordinates":[8.395746,47.191826],"type":"Point"}
}