{
  "type": "Feature",
  "properties": {
    "gn:admin1_code":"TG",
    "gn:admin2_code":"2012.0",
    "gn:admin3_code":"4864.0",
    "gn:asciiname":"Feldbach",
    "gn:country_code":"CH",
    "gn:dem":400,
    "gn:feature_class":"P",
    "gn:feature_code":"PPL",
    "gn:name":"Feldbach",
    "gn:population":0,
    "gn:timezone":"Europe/Zurich",
    "iso:country":"CH",
    "name:als_x_preferred":[
        "Feldbach"
    ],
    "name:bos_x_preferred":[
        "Feldbach"
    ],
    "name:ceb_x_preferred":[
        "Feldbach"
    ],
    "name:deu_x_preferred":[
        "Feldbach"
    ],
    "name:fra_x_preferred":[
        "Feldbach"
    ],
    "name:ita_x_preferred":[
        "Feldbach"
    ],
    "name:nld_x_preferred":[
        "Feldbach"
    ],
    "name:pnb_x_preferred":[
        "\u0641\u0644\u0688\u0628\u0627\u062e"
    ],
    "name:pol_x_preferred":[
        "Feldbach"
    ],
    "name:rus_x_preferred":[
        "\u0424\u0435\u043b\u044c\u0434\u0431\u0430\u0445"
    ],
    "name:slk_x_preferred":[
        "Feldbach"
    ],
    "name:swe_x_preferred":[
        "Feldbach"
    ],
    "name:ukr_x_preferred":[
        "\u0424\u0435\u043b\u044c\u0434\u0431\u0430\u0445"
    ],
    "name:vol_x_preferred":[
        "Feldbach"
    ],
    "wof:name":"Feldbach",
    "wof:placetype":"neighbourhood"
},
  "geometry": {"coordinates":[8.97515,47.66388],"type":"Point"}
}