{
  "type": "Feature",
  "properties": {
    "gn:admin1_code":"BE",
    "gn:admin2_code":"241.0",
    "gn:admin3_code":"450.0",
    "gn:asciiname":"Rondchatel",
    "gn:country_code":"CH",
    "gn:dem":609,
    "gn:feature_class":"P",
    "gn:feature_code":"PPL",
    "gn:name":"Rondch\u00e2tel",
    "gn:population":0,
    "gn:timezone":"Europe/Zurich",
    "iso:country":"CH",
    "wof:name":"Rondchatel",
    "wof:placetype":"neighbourhood"
},
  "geometry": {"coordinates":[7.24651,47.17677],"type":"Point"}
}