{
  "type": "Feature",
  "properties": {
    "gn:admin1_code":"SZ",
    "gn:admin2_code":"506.0",
    "gn:admin3_code":"1372.0",
    "gn:asciiname":"Bol",
    "gn:country_code":"CH",
    "gn:dem":559,
    "gn:feature_class":"P",
    "gn:feature_code":"PPLL",
    "gn:name":"Bol",
    "gn:population":0,
    "gn:timezone":"Europe/Zurich",
    "iso:country":"CH",
    "name:bel_x_preferred":[
        "\u0411\u043e\u043b"
    ],
    "name:bos_x_preferred":[
        "Bol"
    ],
    "name:ceb_x_preferred":[
        "Bol"
    ],
    "name:dan_x_preferred":[
        "B\u00f8l"
    ],
    "name:deu_x_preferred":[
        "Bol"
    ],
    "name:fin_x_preferred":[
        "Bol"
    ],
    "name:fra_x_preferred":[
        "Bol"
    ],
    "name:hrv_x_preferred":[
        "Bol"
    ],
    "name:hye_x_preferred":[
        "\u0532\u0578\u056c"
    ],
    "name:nds_x_preferred":[
        "Bol"
    ],
    "name:nld_x_preferred":[
        "Bol"
    ],
    "name:nor_x_preferred":[
        "Bol"
    ],
    "name:oss_x_preferred":[
        "\u0411\u043e\u043b"
    ],
    "name:pol_x_preferred":[
        "Bol"
    ],
    "name:rus_x_preferred":[
        "\u0411\u043e\u043b"
    ],
    "name:slk_x_preferred":[
        "Bol"
    ],
    "name:swe_x_preferred":[
        "Bol"
    ],
    "name:ukr_x_preferred":[
        "\u0411\u043e\u043b"
    ],
    "wof:name":"Bol",
    "wof:placetype":"neighbourhood"
},
  "geometry": {"coordinates":[8.63824,47.0383],"type":"Point"}
}