{
  "type": "Feature",
  "properties": {
    "gn:gn_country":"CH",
    "gn:gn_fcode":"PPL",
    "gn:gn_pop":1515,
    "gn:population":1515,
    "iso:country":"CH",
    "name:cat_x_preferred":[
        "Attinghausen"
    ],
    "name:deu_x_preferred":[
        "Attinghausen"
    ],
    "name:eng_x_preferred":[
        "Attinghausen"
    ],
    "name:epo_x_preferred":[
        "Attinghausen"
    ],
    "name:eus_x_preferred":[
        "Attinghausen"
    ],
    "name:fra_x_preferred":[
        "Attinghausen"
    ],
    "name:gsw_x_preferred":[
        "\u00c4ttigh\u00fc\u00fcs\u00e4"
    ],
    "name:hun_x_preferred":[
        "Attinghausen"
    ],
    "name:ita_x_preferred":[
        "Attinghausen"
    ],
    "name:jpn_x_preferred":[
        "\u30a2\u30c6\u30a3\u30f3\u30b0\u30cf\u30a6\u30bc\u30f3"
    ],
    "name:kaz_x_preferred":[
        "\u0410\u0442\u0442\u0438\u043d\u0433\u0445\u0430\u0443\u0437\u0435\u043d"
    ],
    "name:lit_x_preferred":[
        "Atinghauzenas"
    ],
    "name:lmo_x_preferred":[
        "Attinghausen"
    ],
    "name:ltz_x_preferred":[
        "Attinghausen"
    ],
    "name:nld_x_preferred":[
        "Attinghausen"
    ],
    "name:nno_x_preferred":[
        "Attinghausen"
    ],
    "name:oci_x_preferred":[
        "Attinghausen"
    ],
    "name:pms_x_preferred":[
        "Attinghausen"
    ],
    "name:por_x_preferred":[
        "Attinghausen"
    ],
    "name:roh_x_preferred":[
        "Attinghausen"
    ],
    "name:rus_x_preferred":[
        "\u0410\u0442\u0442\u0438\u043d\u0433\u0445\u0430\u0443\u0437\u0435\u043d"
    ],
    "name:spa_x_preferred":[
        "Attinghausen"
    ],
    "name:sqi_x_preferred":[
        "Attinghausen"
    ],
    "name:uzb_x_preferred":[
        "Attinghausen"
    ],
    "name:vol_x_preferred":[
        "Attinghausen"
    ],
    "name:war_x_preferred":[
        "Attinghausen"
    ],
    "qs_pg:aaroncc":"CH",
    "qs_pg:gn_country":"CH",
    "qs_pg:gn_fcode":"PPL",
    "qs_pg:gn_pop":1515,
    "qs_pg:name":"Attinghausen",
    "qs_pg:name_adm0":"Schweiz",
    "qs_pg:name_adm1":"Kanton Uri",
    "qs_pg:photos":124,
    "qs_pg:photos_1k":25,
    "qs_pg:photos_9k":1,
    "qs_pg:photos_9r":3,
    "qs_pg:photos_all":124,
    "qs_pg:photos_sr":3,
    "qs_pg:pop_sr":3,
    "qs_pg:qs_pg_placetype":"locality",
    "qs_pg:qs_pg_placetype_gp":"Town",
    "qs_pg:woe_adm0":23424957,
    "woe:adm0_id":23424957,
    "woe:name_adm0":"Schweiz",
    "woe:name_adm1":"Kanton Uri",
    "woe:placetype":"Town",
    "wof:name":"Attinghausen",
    "wof:placetype":"locality",
    "wof:population":1515
},
  "geometry": {"coordinates":[8.63036,46.86255],"type":"Point"}
}