{
  "type": "Feature",
  "properties": {
    "gn:admin1_code":"SO",
    "gn:admin2_code":"1103.0",
    "gn:admin3_code":"2465.0",
    "gn:asciiname":"Muehledorf",
    "gn:country_code":"CH",
    "gn:dem":564,
    "gn:feature_class":"P",
    "gn:feature_code":"PPL",
    "gn:name":"M\u00fchledorf",
    "gn:population":0,
    "gn:timezone":"Europe/Zurich",
    "iso:country":"CH",
    "name:als_x_preferred":[
        "M\u00fchledorf SO"
    ],
    "name:deu_x_preferred":[
        "M\u00fchledorf SO"
    ],
    "name:epo_x_preferred":[
        "M\u00fchledorf SO"
    ],
    "name:kaz_x_preferred":[
        "\u041c\u044e\u043b\u0435\u0434\u043e\u0440\u0444"
    ],
    "name:nno_x_preferred":[
        "M\u00fchledorf i Solothurn"
    ],
    "name:rus_x_preferred":[
        "\u041c\u044e\u043b\u0435\u0434\u043e\u0440\u0444"
    ],
    "name:zho_x_preferred":[
        "\u7c73\u52d2\u591a\u592b"
    ],
    "wof:name":"Muehledorf",
    "wof:placetype":"locality"
},
  "geometry": {"coordinates":[7.47663,47.13462],"type":"Point"}
}