{
  "type": "Feature",
  "properties": {
    "gn:admin1_code":"SG",
    "gn:admin2_code":"1722.0",
    "gn:admin3_code":"3237.0",
    "gn:asciiname":"Am Rhein",
    "gn:country_code":"CH",
    "gn:dem":396,
    "gn:feature_class":"P",
    "gn:feature_code":"PPL",
    "gn:name":"Am Rhein",
    "gn:population":0,
    "gn:timezone":"Europe/Zurich",
    "iso:country":"CH",
    "wof:lang_x_official":[
        "deu",
        "fra",
        "gsw",
        "ita"
    ],
    "wof:lang_x_spoken":[
        "deu",
        "fra",
        "gsw",
        "ita",
        "roh"
    ],
    "wof:name":"Am Rhein",
    "wof:placetype":"neighbourhood"
},
  "geometry": {"coordinates":[9.56411,47.49122],"type":"Point"}
}