{
  "type": "Feature",
  "properties": {
    "gn:gn_country":"CH",
    "gn:gn_fcode":"PPL",
    "gn:gn_pop":4226,
    "gn:population":4226,
    "iso:country":"CH",
    "name:cat_x_preferred":[
        "Zuzwil"
    ],
    "name:deu_x_preferred":[
        "Zuzwil SG"
    ],
    "name:eng_x_preferred":[
        "Zuzwil"
    ],
    "name:epo_x_preferred":[
        "Zuzwil SG"
    ],
    "name:eus_x_preferred":[
        "Zuzwil"
    ],
    "name:fra_x_preferred":[
        "Zuzwil"
    ],
    "name:hun_x_preferred":[
        "Zuzwil"
    ],
    "name:ita_x_preferred":[
        "Zuzwil"
    ],
    "name:kaz_x_preferred":[
        "\u0426\u0443\u0446\u0432\u0438\u043b\u044c"
    ],
    "name:lmo_x_preferred":[
        "Zuzwil"
    ],
    "name:msa_x_preferred":[
        "Zuzwil"
    ],
    "name:nld_x_preferred":[
        "Zuzwil"
    ],
    "name:nno_x_preferred":[
        "Zuzwil i St. Gallen"
    ],
    "name:oci_x_preferred":[
        "Zuzwil"
    ],
    "name:pms_x_preferred":[
        "Zuzwil"
    ],
    "name:por_x_preferred":[
        "Zuzwil"
    ],
    "name:rus_x_preferred":[
        "\u0426\u0443\u0446\u0432\u0438\u043b\u044c"
    ],
    "name:spa_x_preferred":[
        "Zuzwil"
    ],
    "name:uzb_x_preferred":[
        "Zuzwil"
    ],
    "name:vol_x_preferred":[
        "Zuzwil"
    ],
    "name:war_x_preferred":[
        "Zuzwil"
    ],
    "name:zho_x_preferred":[
        "\u695a\u8328\u7dad\u723e"
    ],
    "qs_pg:aaroncc":"CH",
    "qs_pg:gn_country":"CH",
    "qs_pg:gn_fcode":"PPL",
    "qs_pg:gn_pop":4226,
    "qs_pg:name":"Zuzwil",
    "qs_pg:name_adm0":"Schweiz",
    "qs_pg:name_adm1":"Kanton St. Gallen",
    "qs_pg:photos":29,
    "qs_pg:photos_1k":6,
    "qs_pg:photos_9k":1,
    "qs_pg:photos_9r":2,
    "qs_pg:photos_all":29,
    "qs_pg:photos_sr":2,
    "qs_pg:pop_sr":4,
    "qs_pg:qs_pg_placetype":"locality",
    "qs_pg:qs_pg_placetype_gp":"Town",
    "qs_pg:woe_adm0":23424957,
    "woe:adm0_id":23424957,
    "woe:name_adm0":"Schweiz",
    "woe:name_adm1":"Kanton St. Gallen",
    "woe:placetype":"Town",
    "wof:name":"Zuzwil",
    "wof:placetype":"locality",
    "wof:population":4226
},
  "geometry": {"coordinates":[9.11196,47.47452],"type":"Point"}
}