{
  "type": "Feature",
  "properties": {
    "gn:gn_country":"CH",
    "gn:gn_fcode":"PPL",
    "gn:gn_pop":239,
    "gn:population":239,
    "iso:country":"CH",
    "name:bul_x_preferred":[
        "\u041b\u043e\u0434\u0430\u043d\u043e"
    ],
    "name:deu_x_preferred":[
        "Lodano"
    ],
    "name:eng_x_preferred":[
        "Lodano"
    ],
    "name:fra_x_preferred":[
        "Lodano"
    ],
    "name:ita_x_preferred":[
        "Lodano"
    ],
    "name:lmo_x_preferred":[
        "Loeuden"
    ],
    "name:nld_x_preferred":[
        "Lodano"
    ],
    "name:roh_x_preferred":[
        "Lodano"
    ],
    "name:swe_x_preferred":[
        "Lodano"
    ],
    "qs_pg:aaroncc":"CH",
    "qs_pg:gn_country":"CH",
    "qs_pg:gn_fcode":"PPL",
    "qs_pg:gn_pop":239,
    "qs_pg:name":"Lodano",
    "qs_pg:name_adm0":"Schweiz",
    "qs_pg:name_adm1":"Cantone Ticino",
    "qs_pg:photos":40,
    "qs_pg:photos_1k":8,
    "qs_pg:photos_9k":1,
    "qs_pg:photos_9r":2,
    "qs_pg:photos_all":40,
    "qs_pg:photos_sr":2,
    "qs_pg:pop_sr":2,
    "qs_pg:qs_pg_placetype":"locality",
    "qs_pg:qs_pg_placetype_gp":"Town",
    "qs_pg:woe_adm0":23424957,
    "woe:adm0_id":23424957,
    "woe:name_adm0":"Schweiz",
    "woe:name_adm1":"Cantone Ticino",
    "woe:placetype":"Town",
    "wof:name":"Lodano",
    "wof:placetype":"locality",
    "wof:population":239
},
  "geometry": {"coordinates":[8.68522,46.25837],"type":"Point"}
}