{
  "type": "Feature",
  "properties": {
    "gn:population":5873,
    "iso:country":"CH",
    "name:als_x_preferred":[
        "Sissach"
    ],
    "name:ast_x_preferred":[
        "Sissach"
    ],
    "name:cat_x_preferred":[
        "Sissach"
    ],
    "name:ceb_x_preferred":[
        "Sissach"
    ],
    "name:chv_x_preferred":[
        "\u0417\u0438\u0441\u0441\u0430\u0445"
    ],
    "name:deu_x_preferred":[
        "Sissach"
    ],
    "name:eng_x_preferred":[
        "Sissach"
    ],
    "name:epo_x_preferred":[
        "Sissach"
    ],
    "name:eus_x_preferred":[
        "Sissach"
    ],
    "name:fra_x_preferred":[
        "Sissach"
    ],
    "name:gsw_x_preferred":[
        "Sissech"
    ],
    "name:hun_x_preferred":[
        "Sissach"
    ],
    "name:ita_x_preferred":[
        "Sissach"
    ],
    "name:kaz_x_preferred":[
        "\u0417\u0438\u0441\u0441\u0430\u0445"
    ],
    "name:lmo_x_preferred":[
        "Sissach"
    ],
    "name:msa_x_preferred":[
        "Sissach"
    ],
    "name:nld_x_preferred":[
        "Sissach"
    ],
    "name:nno_x_preferred":[
        "Sissach"
    ],
    "name:nob_x_preferred":[
        "Sissach"
    ],
    "name:oci_x_preferred":[
        "Sissach"
    ],
    "name:pol_x_preferred":[
        "Sissach"
    ],
    "name:rus_x_preferred":[
        "\u0417\u0438\u0441\u0441\u0430\u0445"
    ],
    "name:spa_x_preferred":[
        "Sissach"
    ],
    "name:sqi_x_preferred":[
        "Sissach"
    ],
    "name:swe_x_preferred":[
        "Sissach"
    ],
    "name:ukr_x_preferred":[
        "\u0417\u0456\u0441\u0441\u0430\u0445"
    ],
    "name:uzb_x_preferred":[
        "Sissach"
    ],
    "name:vol_x_preferred":[
        "Sissach"
    ],
    "name:war_x_preferred":[
        "Sissach"
    ],
    "name:zho_x_preferred":[
        "\u932b\u85a9\u8d6b"
    ],
    "qs:a0":"Schweiz#Suisse#Svizzera#Svizra",
    "qs:a1":"*Basel-Landschaft",
    "qs:a1r":"0",
    "qs:adm0":"Schweiz#Suisse#Svizzera#Svizra",
    "qs:la_lc":"*",
    "qs:level":"locality",
    "qs:loc":"Sissach",
    "qs:loc_alt":"Sissach",
    "qs:pop":0,
    "qs:type":"buffered point",
    "wof:lang":[
        "ger"
    ],
    "wof:name":"Sissach",
    "wof:placetype":"locality",
    "wof:population":5873
},
  "geometry": {"coordinates":[7.810092,47.464451],"type":"Point"}
}