{
  "type": "Feature",
  "properties": {
    "iso:country":"CH",
    "name:bul_x_preferred":[
        "\u0413\u0435\u043b\u0442\u0435\u0440\u0444\u0438\u043d\u0433\u0435\u043d"
    ],
    "name:cat_x_preferred":[
        "Gelterfingen"
    ],
    "name:chv_x_preferred":[
        "\u0413\u0435\u043b\u044c\u0442\u0435\u0440\u0444\u0438\u043d\u0433\u0435\u043d"
    ],
    "name:deu_x_preferred":[
        "Gelterfingen"
    ],
    "name:eng_x_preferred":[
        "Gelterfingen"
    ],
    "name:epo_x_preferred":[
        "Gelterfingen"
    ],
    "name:eus_x_preferred":[
        "Gelterfingen"
    ],
    "name:fra_x_preferred":[
        "Gelterfingen"
    ],
    "name:gsw_x_preferred":[
        "G\u00e4uterfinge"
    ],
    "name:hun_x_preferred":[
        "Gelterfingen"
    ],
    "name:ita_x_preferred":[
        "Gelterfingen"
    ],
    "name:kaz_x_preferred":[
        "\u0413\u0435\u043b\u044c\u0442\u0435\u0440\u0444\u0438\u043d\u0433\u0435\u043d"
    ],
    "name:lmo_x_preferred":[
        "Gelterfingen"
    ],
    "name:msa_x_preferred":[
        "Gelterfingen"
    ],
    "name:nld_x_preferred":[
        "Gelterfingen"
    ],
    "name:nno_x_preferred":[
        "Gelterfingen"
    ],
    "name:oci_x_preferred":[
        "Gelterfingen"
    ],
    "name:pms_x_preferred":[
        "Gelterfingen"
    ],
    "name:por_x_preferred":[
        "Gelterfingen"
    ],
    "name:rus_x_preferred":[
        "\u0413\u0435\u043b\u044c\u0442\u0435\u0440\u0444\u0438\u043d\u0433\u0435\u043d"
    ],
    "name:spa_x_preferred":[
        "Gelterfingen"
    ],
    "name:sqi_x_preferred":[
        "Gelterfingen"
    ],
    "name:swe_x_preferred":[
        "Gelterfingen"
    ],
    "name:vie_x_preferred":[
        "Gelterfingen"
    ],
    "name:vol_x_preferred":[
        "Gelterfingen"
    ],
    "name:war_x_preferred":[
        "Gelterfingen"
    ],
    "name:zho_x_preferred":[
        "\u683c\u723e\u7279\u82ac\u6839"
    ],
    "qs_pg:aaroncc":"CH",
    "qs_pg:name":"Gelterfingen",
    "qs_pg:name_adm0":"Schweiz",
    "qs_pg:name_adm1":"Kanton Bern",
    "qs_pg:photos":187,
    "qs_pg:photos_1k":38,
    "qs_pg:photos_9k":1,
    "qs_pg:photos_9r":4,
    "qs_pg:photos_all":187,
    "qs_pg:photos_sr":4,
    "qs_pg:pop_sr":0,
    "qs_pg:qs_pg_placetype":"locality",
    "qs_pg:qs_pg_placetype_gp":"Town",
    "qs_pg:woe_adm0":23424957,
    "woe:adm0_id":23424957,
    "woe:name_adm0":"Schweiz",
    "woe:name_adm1":"Kanton Bern",
    "woe:placetype":"Town",
    "wof:name":"Gelterfingen",
    "wof:placetype":"locality"
},
  "geometry": {"coordinates":[7.505872,46.835418],"type":"Point"}
}