{
  "type": "Feature",
  "properties": {
    "iso:country":"CH",
    "name:cat_x_preferred":[
        "Le Mouret"
    ],
    "name:ceb_x_preferred":[
        "Le Mouret"
    ],
    "name:deu_x_preferred":[
        "Le Mouret"
    ],
    "name:eng_x_preferred":[
        "Le Mouret"
    ],
    "name:epo_x_preferred":[
        "Le Mouret"
    ],
    "name:eus_x_preferred":[
        "Le Mouret"
    ],
    "name:fra_x_preferred":[
        "Le Mouret"
    ],
    "name:gsw_x_preferred":[
        "Le Mouret"
    ],
    "name:hun_x_preferred":[
        "Le Mouret"
    ],
    "name:ita_x_preferred":[
        "Le Mouret"
    ],
    "name:lmo_x_preferred":[
        "Le Mouret"
    ],
    "name:msa_x_preferred":[
        "Le Mouret"
    ],
    "name:nld_x_preferred":[
        "Le Mouret"
    ],
    "name:nno_x_preferred":[
        "Le Mouret"
    ],
    "name:oci_x_preferred":[
        "Le Mouret"
    ],
    "name:pms_x_preferred":[
        "Le Mouret"
    ],
    "name:por_x_preferred":[
        "Le Mouret"
    ],
    "name:roh_x_preferred":[
        "Le Mouret"
    ],
    "name:spa_x_preferred":[
        "Le Mouret"
    ],
    "name:sqi_x_preferred":[
        "Le Mouret"
    ],
    "name:swe_x_preferred":[
        "Le Mouret"
    ],
    "name:unk_x_variant":[
        "Le Mouret"
    ],
    "name:vie_x_preferred":[
        "Le Mouret"
    ],
    "name:vol_x_preferred":[
        "Le Mouret"
    ],
    "name:war_x_preferred":[
        "Le Mouret"
    ],
    "name:zho_x_preferred":[
        "\u840a\u7a46\u96f7"
    ],
    "qs:gn_adm0_cc":"CH",
    "qs:gn_local":7285810,
    "qs:gn_nam_loc":"Ferpicloz, Ferpicloz, La Sarine, Canton de Fribourg, CH",
    "qs:gn_namadm1":"FR",
    "qs:local_max":147,
    "qs:local_sum":147,
    "qs:localhoods":1,
    "qs:name":"Le Mouret",
    "qs:name_adm0":"Schweiz",
    "qs:name_adm1":"Canton de Fribourg",
    "qs:name_adm2":"La Sarine",
    "qs:name_lau":"Le Mouret",
    "qs:name_local":"Ferpicloz",
    "qs:photo_max":119,
    "qs:photo_sum":147,
    "qs:placetype":"Suburb",
    "qs:quad_count":20,
    "qs:woe_adm0":23424957,
    "qs:woe_adm1":2347088,
    "qs:woe_adm2":12593162,
    "qs:woe_lau":24544637,
    "qs:woe_local":20101705,
    "qs:woe_ver":"7.10.0",
    "wd:wordcount":1784,
    "wof:lang":[
        "fre"
    ],
    "wof:name":"Le Mouret",
    "wof:placetype":"neighbourhood"
},
  "geometry": {"coordinates":[7.194186,46.766556],"type":"Point"}
}