{
  "type": "Feature",
  "properties": {
    "gn:admin1_code":"OW",
    "gn:admin2_code":"600.0",
    "gn:admin3_code":"1402.0",
    "gn:asciiname":"Fuerenalp",
    "gn:country_code":"CH",
    "gn:dem":1822,
    "gn:feature_class":"P",
    "gn:feature_code":"PPL",
    "gn:name":"F\u00fcrenalp",
    "gn:population":0,
    "gn:timezone":"Europe/Zurich",
    "iso:country":"CH",
    "wof:lang_x_official":[
        "deu",
        "fra",
        "gsw",
        "ita"
    ],
    "wof:lang_x_spoken":[
        "deu",
        "fra",
        "gsw",
        "ita",
        "roh"
    ],
    "wof:name":"Fuerenalp",
    "wof:placetype":"neighbourhood"
},
  "geometry": {"coordinates":[8.46814,46.8017],"type":"Point"}
}