{
  "type": "Feature",
  "properties": {
    "gn:gn_country":"CH",
    "gn:gn_fcode":"PPL",
    "gn:gn_pop":0,
    "iso:country":"CH",
    "name:dut_x_preferred":[
        "Valchava"
    ],
    "name:eng_x_preferred":[
        "Valchava"
    ],
    "name:fre_x_preferred":[
        "Valchava"
    ],
    "name:ger_x_preferred":[
        "Valchava"
    ],
    "name:ita_x_preferred":[
        "Valchava"
    ],
    "name:kaz_x_preferred":[
        "\u0412\u0430\u043b\u044c\u043a\u0430\u0432\u0430"
    ],
    "name:pms_x_preferred":[
        "Valchava"
    ],
    "name:por_x_preferred":[
        "Valchava"
    ],
    "name:roh_x_preferred":[
        "Valchava"
    ],
    "name:rus_x_preferred":[
        "\u0412\u0430\u043b\u044c\u043a\u0430\u0432\u0430"
    ],
    "name:spa_x_preferred":[
        "Valchava"
    ],
    "name:swe_x_preferred":[
        "Valchava"
    ],
    "name:unk_x_variant":[
        "Valcava"
    ],
    "name:uzb_x_preferred":[
        "Valchava"
    ],
    "name:vol_x_preferred":[
        "Valchava"
    ],
    "qs_pg:aaroncc":"CH",
    "qs_pg:gn_country":"CH",
    "qs_pg:gn_fcode":"PPL",
    "qs_pg:gn_pop":0,
    "qs_pg:name":"Valchava",
    "qs_pg:name_adm0":"Schweiz",
    "qs_pg:name_adm1":"Kanton Graub\u00fcnden",
    "qs_pg:photos":165,
    "qs_pg:photos_1k":33,
    "qs_pg:photos_9k":1,
    "qs_pg:photos_9r":4,
    "qs_pg:photos_all":165,
    "qs_pg:photos_sr":4,
    "qs_pg:pop_sr":0,
    "qs_pg:qs_pg_placetype":"locality",
    "qs_pg:qs_pg_placetype_gp":"Town",
    "qs_pg:woe_adm0":23424957,
    "woe:adm0_id":23424957,
    "woe:name_adm0":"Schweiz",
    "woe:name_adm1":"Kanton Graub\u00fcnden",
    "woe:placetype":"Town",
    "wof:name":"Valchava",
    "wof:placetype":"locality"
},
  "geometry": {"coordinates":[10.40752,46.60073],"type":"Point"}
}