{
  "type": "Feature",
  "properties": {
    "gn:admin1_code":"TI",
    "gn:admin2_code":"2106.0",
    "gn:admin3_code":"5254.0",
    "gn:asciiname":"Prella",
    "gn:country_code":"CH",
    "gn:dem":369,
    "gn:feature_class":"P",
    "gn:feature_code":"PPL",
    "gn:name":"Prella",
    "gn:population":0,
    "gn:timezone":"Europe/Rome",
    "iso:country":"CH",
    "name:ita_x_preferred":[
        "Prella"
    ],
    "wof:name":"Prella",
    "wof:placetype":"locality"
},
  "geometry": {"coordinates":[8.95493,45.8451],"type":"Point"}
}