{
  "type": "Feature",
  "properties": {
    "gn:admin1_code":"BE",
    "gn:admin2_code":"250.0",
    "gn:admin3_code":"584.0",
    "gn:asciiname":"Inhalte",
    "gn:country_code":"CH",
    "gn:dem":1298,
    "gn:feature_class":"P",
    "gn:feature_code":"PPL",
    "gn:name":"Inhalte",
    "gn:population":0,
    "gn:timezone":"Europe/Zurich",
    "iso:country":"CH",
    "name:deu_x_preferred":[
        "Inhalte"
    ],
    "wof:name":"Inhalte",
    "wof:placetype":"neighbourhood"
},
  "geometry": {"coordinates":[7.88664,46.61029],"type":"Point"}
}