{
  "type": "Feature",
  "properties": {
    "gn:country":"CH",
    "gn:fcode":"PPL",
    "gn:population":13,
    "iso:country":"CH",
    "name:bul_x_preferred":[
        "\u041d\u043e\u0439\u0431\u0435\u0440\u0433"
    ],
    "name:ceb_x_preferred":[
        "Neuberg"
    ],
    "name:deu_x_preferred":[
        "Neuberg"
    ],
    "name:epo_x_preferred":[
        "Neuberg"
    ],
    "name:fra_x_preferred":[
        "Neuberg"
    ],
    "name:hrv_x_preferred":[
        "Neuberg"
    ],
    "name:ita_x_preferred":[
        "Neuberg"
    ],
    "name:jpn_x_preferred":[
        "\u30ce\u30a4\u30d9\u30eb\u30af"
    ],
    "name:nld_x_preferred":[
        "Neuberg"
    ],
    "name:pol_x_preferred":[
        "Neuberg"
    ],
    "name:rus_x_preferred":[
        "\u041d\u043e\u0439\u0431\u0435\u0440\u0433"
    ],
    "name:swe_x_preferred":[
        "Neuberg"
    ],
    "name:zho_x_preferred":[
        "\u8bfa\u4f0a\u8d1d\u683c"
    ],
    "qs_pg:aaroncc":"CH",
    "qs_pg:gn_country":"CH",
    "qs_pg:gn_fcode":"PPL",
    "qs_pg:gn_pop":13,
    "qs_pg:name":"Neuberg",
    "qs_pg:name_adm0":"Deutschland",
    "qs_pg:name_adm1":"Baden-W\u00fcrttemberg",
    "qs_pg:photos_9r":0,
    "qs_pg:photos_sr":0,
    "qs_pg:pop_sr":1,
    "qs_pg:qs_pg_placetype":"locality",
    "qs_pg:qs_pg_placetype_gp":"Town",
    "qs_pg:woe_adm0":23424829,
    "woe:adm0_id":23424829,
    "woe:name_adm0":"Deutschland",
    "woe:name_adm1":"Baden-W\u00fcrttemberg",
    "woe:placetype":"Town",
    "wof:name":"Neuberg",
    "wof:placetype":"neighbourhood",
    "wof:population":13
},
  "geometry": {"coordinates":[8.66737,47.31603],"type":"Point"}
}