{
  "type": "Feature",
  "properties": {
    "gn:admin1_code":"BE",
    "gn:admin2_code":"246.0",
    "gn:admin3_code":"546.0",
    "gn:asciiname":"Moosrain",
    "gn:country_code":"CH",
    "gn:dem":541,
    "gn:feature_class":"P",
    "gn:feature_code":"PPLL",
    "gn:name":"Moosrain",
    "gn:population":0,
    "gn:timezone":"Europe/Zurich",
    "iso:country":"CH",
    "name:deu_x_preferred":[
        "Moosrain"
    ],
    "wof:name":"Moosrain",
    "wof:placetype":"locality"
},
  "geometry": {"coordinates":[7.43225,47.02901],"type":"Point"}
}