{
  "type": "Feature",
  "properties": {
    "gn:gn_country":"CH",
    "gn:gn_fcode":"ADM3",
    "gn:gn_pop":581,
    "gn:population":566,
    "iso:country":"CH",
    "name:cat_x_preferred":[
        "Villars-sous-Yens"
    ],
    "name:deu_x_preferred":[
        "Villars-sous-Yens"
    ],
    "name:eng_x_preferred":[
        "Villars-sous-Yens"
    ],
    "name:epo_x_preferred":[
        "Villars-sous-Yens"
    ],
    "name:eus_x_preferred":[
        "Villars-sous-Yens"
    ],
    "name:fra_x_preferred":[
        "Villars-sous-Yens"
    ],
    "name:gsw_x_preferred":[
        "Villars-sous-Yens"
    ],
    "name:hun_x_preferred":[
        "Villars-sous-Yens"
    ],
    "name:ita_x_preferred":[
        "Villars-sous-Yens"
    ],
    "name:lmo_x_preferred":[
        "Villars-sous-Yens"
    ],
    "name:msa_x_preferred":[
        "Villars-sous-Yens"
    ],
    "name:nld_x_preferred":[
        "Villars-sous-Yens"
    ],
    "name:nno_x_preferred":[
        "Villars-sous-Yens"
    ],
    "name:oci_x_preferred":[
        "Villars-sous-Yens"
    ],
    "name:roh_x_preferred":[
        "Villars-sous-Yens"
    ],
    "name:spa_x_preferred":[
        "Villars-sous-Yens"
    ],
    "name:swe_x_preferred":[
        "Villars-sous-Yens"
    ],
    "name:vol_x_preferred":[
        "Villars-sous-Yens"
    ],
    "name:war_x_preferred":[
        "Villars-sous-Yens"
    ],
    "name:zho_x_preferred":[
        "\u626c\u6751\u4e0b\u7ef4\u62c9\u5c14"
    ],
    "qs_pg:aaroncc":"CH",
    "qs_pg:gn_country":"CH",
    "qs_pg:gn_fcode":"ADM3",
    "qs_pg:gn_pop":581,
    "qs_pg:name":"Villars-sous-Yens",
    "qs_pg:name_adm0":"Schweiz",
    "qs_pg:name_adm1":"Canton de Vaud",
    "qs_pg:photos_9k":1,
    "qs_pg:photos_9r":1,
    "qs_pg:photos_all":1,
    "qs_pg:photos_sr":0,
    "qs_pg:pop_sr":2,
    "qs_pg:qs_pg_placetype":"locality",
    "qs_pg:qs_pg_placetype_gp":"Town",
    "qs_pg:woe_adm0":23424957,
    "woe:adm0_id":23424957,
    "woe:name_adm0":"Schweiz",
    "woe:name_adm1":"Canton de Vaud",
    "woe:placetype":"Town",
    "wof:name":"Villars-sous-Yens",
    "wof:placetype":"locality",
    "wof:population":566
},
  "geometry": {"coordinates":[6.43015,46.50694],"type":"Point"}
}