{
  "type": "Feature",
  "properties": {
    "iso:country":"CH",
    "wof:name":"Parc-des-Sports",
    "wof:placetype":"neighbourhood"
},
  "geometry": {"coordinates":[6.11697093799292,46.20927429657309],"type":"Point"}
}