{
  "type": "Feature",
  "properties": {
    "gn:admin1_code":"ZH",
    "gn:admin2_code":"105.0",
    "gn:admin3_code":"112.0",
    "gn:asciiname":"Widerzell",
    "gn:country_code":"CH",
    "gn:dem":503,
    "gn:feature_class":"P",
    "gn:feature_code":"PPLL",
    "gn:name":"Widerzell",
    "gn:population":0,
    "gn:timezone":"Europe/Zurich",
    "iso:country":"CH",
    "name:deu_x_preferred":[
        "Widerzell"
    ],
    "wof:name":"Widerzell",
    "wof:placetype":"neighbourhood"
},
  "geometry": {"coordinates":[8.8155,47.25453],"type":"Point"}
}