{
  "type": "Feature",
  "properties": {
    "gn:admin1_code":"TG",
    "gn:admin2_code":"2013.0",
    "gn:admin3_code":"4846.0",
    "gn:asciiname":"Bueren",
    "gn:country_code":"CH",
    "gn:dem":642,
    "gn:elevation":"641.0",
    "gn:feature_class":"P",
    "gn:feature_code":"PPL",
    "gn:name":"B\u00fcren",
    "gn:population":0,
    "gn:timezone":"Europe/Zurich",
    "iso:country":"CH",
    "wof:name":"Bueren",
    "wof:placetype":"neighbourhood"
},
  "geometry": {"coordinates":[9.04634,47.64532],"type":"Point"}
}