{
  "type": "Feature",
  "properties": {
    "gn:admin1_code":"AG",
    "gn:admin2_code":"1904.0",
    "gn:admin3_code":"4112.0",
    "gn:asciiname":"Ruefenach",
    "gn:country_code":"CH",
    "gn:dem":373,
    "gn:feature_class":"P",
    "gn:feature_code":"PPL",
    "gn:name":"R\u00fcfenach",
    "gn:population":0,
    "gn:timezone":"Europe/Zurich",
    "iso:country":"CH",
    "name:kaz_x_preferred":[
        "\u0420\u044e\u0444\u0435\u043d\u0430\u0445"
    ],
    "name:rus_x_preferred":[
        "\u0420\u044e\u0444\u0435\u043d\u0430\u0445"
    ],
    "name:und_x_variant":[
        "R\u00fcfenach"
    ],
    "name:zho_x_preferred":[
        "\u5442\u8cbb\u7d0d\u8d6b"
    ],
    "wof:name":"Ruefenach",
    "wof:placetype":"locality"
},
  "geometry": {"coordinates":[8.20903,47.50712],"type":"Point"}
}