{
  "type": "Feature",
  "properties": {
    "gn:admin1_code":"NW",
    "gn:admin2_code":"700.0",
    "gn:admin3_code":"1503.0",
    "gn:asciiname":"Rietli",
    "gn:country_code":"CH",
    "gn:dem":508,
    "gn:feature_class":"P",
    "gn:feature_code":"PPL",
    "gn:name":"Rietli",
    "gn:population":0,
    "gn:timezone":"Europe/Zurich",
    "iso:country":"CH",
    "wof:name":"Rietli",
    "wof:placetype":"neighbourhood"
},
  "geometry": {"coordinates":[8.39285,46.91781],"type":"Point"}
}