{
  "type": "Feature",
  "properties": {
    "gn:admin1_code":"TG",
    "gn:admin2_code":"2015.0",
    "gn:admin3_code":"4891.0",
    "gn:asciiname":"Guntershausen",
    "gn:country_code":"CH",
    "gn:dem":503,
    "gn:elevation":"504.0",
    "gn:feature_class":"P",
    "gn:feature_code":"PPL",
    "gn:name":"Guntershausen",
    "gn:population":0,
    "gn:timezone":"Europe/Zurich",
    "iso:country":"CH",
    "name:und_x_variant":[
        "Guntershausen b. Berg"
    ],
    "wof:name":"Guntershausen",
    "wof:placetype":"locality"
},
  "geometry": {"coordinates":[9.18974,47.5736],"type":"Point"}
}