{
  "type": "Feature",
  "properties": {
    "gn:admin1_code":"FR",
    "gn:admin2_code":"1003.0",
    "gn:admin3_code":"2138.0",
    "gn:asciiname":"Untere Muencheberg",
    "gn:country_code":"CH",
    "gn:dem":1348,
    "gn:feature_class":"P",
    "gn:feature_code":"PPL",
    "gn:name":"Untere M\u00fcncheberg",
    "gn:population":0,
    "gn:timezone":"Europe/Zurich",
    "iso:country":"CH",
    "name:deu_x_preferred":[
        "Untere M\u00fcncheberg"
    ],
    "wof:name":"Untere Muencheberg",
    "wof:placetype":"neighbourhood"
},
  "geometry": {"coordinates":[7.30406,46.62216],"type":"Point"}
}