{
  "type": "Feature",
  "properties": {
    "gn:admin1_code":"SO",
    "gn:admin2_code":"1106.0",
    "gn:admin3_code":"2523.0",
    "gn:asciiname":"Horriwil",
    "gn:country_code":"CH",
    "gn:dem":457,
    "gn:feature_class":"P",
    "gn:feature_code":"PPL",
    "gn:name":"Horriwil",
    "gn:population":0,
    "gn:timezone":"Europe/Zurich",
    "iso:country":"CH",
    "name:kaz_x_preferred":[
        "\u0425\u043e\u0440\u0440\u0438\u0432\u0438\u043b\u044c"
    ],
    "name:rus_x_preferred":[
        "\u0425\u043e\u0440\u0440\u0438\u0432\u0438\u043b\u044c"
    ],
    "name:zho_x_preferred":[
        "\u970d\u91cc\u7dad\u723e"
    ],
    "wof:name":"Horriwil",
    "wof:placetype":"locality"
},
  "geometry": {"coordinates":[7.62185,47.1823],"type":"Point"}
}