{
  "type": "Feature",
  "properties": {
    "gn:admin1_code":"SG",
    "gn:admin2_code":"1726.0",
    "gn:admin3_code":"3313.0",
    "gn:asciiname":"Steinenbrugg",
    "gn:country_code":"CH",
    "gn:dem":453,
    "gn:elevation":"450.0",
    "gn:feature_class":"P",
    "gn:feature_code":"PPL",
    "gn:name":"Steinenbrugg",
    "gn:population":0,
    "gn:timezone":"Europe/Zurich",
    "iso:country":"CH",
    "wof:name":"Steinenbrugg",
    "wof:placetype":"locality"
},
  "geometry": {"coordinates":[9.03821,47.20788],"type":"Point"}
}