{
  "type": "Feature",
  "properties": {
    "gn:gn_country":"CH",
    "gn:gn_fcode":"PPL",
    "gn:gn_pop":722,
    "gn:population":722,
    "iso:country":"CH",
    "name:alb_x_preferred":[
        "Fahrni"
    ],
    "name:baq_x_preferred":[
        "Fahrni"
    ],
    "name:cat_x_preferred":[
        "Fahrni"
    ],
    "name:chi_x_preferred":[
        "\u6cd5\u723e\u5c3c"
    ],
    "name:chv_x_preferred":[
        "\u0424\u0430\u0440\u043d\u0438"
    ],
    "name:deu_x_preferred":[
        "Fahrni"
    ],
    "name:deu_x_variant":[
        "Fahrni b. Thun"
    ],
    "name:dut_x_preferred":[
        "Fahrni"
    ],
    "name:eng_x_preferred":[
        "Fahrni"
    ],
    "name:epo_x_preferred":[
        "Fahrni"
    ],
    "name:fra_x_preferred":[
        "Fahrni"
    ],
    "name:fre_x_preferred":[
        "Fahrni"
    ],
    "name:ger_x_preferred":[
        "Fahrni"
    ],
    "name:gsw_x_preferred":[
        "Faarni"
    ],
    "name:hun_x_preferred":[
        "Fahrni"
    ],
    "name:ita_x_preferred":[
        "Fahrni"
    ],
    "name:kaz_x_preferred":[
        "\u0424\u0430\u0440\u043d\u0438"
    ],
    "name:lmo_x_preferred":[
        "Fahrni"
    ],
    "name:may_x_preferred":[
        "Fahrni"
    ],
    "name:nno_x_preferred":[
        "Fahrni"
    ],
    "name:oci_x_preferred":[
        "Fahrni"
    ],
    "name:pms_x_preferred":[
        "Fahrni"
    ],
    "name:por_x_preferred":[
        "Fahrni"
    ],
    "name:roh_x_preferred":[
        "Fahrni"
    ],
    "name:rus_x_preferred":[
        "\u0424\u0430\u0440\u043d\u0438"
    ],
    "name:spa_x_preferred":[
        "Fahrni"
    ],
    "name:swe_x_preferred":[
        "Fahrni"
    ],
    "name:vie_x_preferred":[
        "Fahrni"
    ],
    "name:vol_x_preferred":[
        "Fahrni"
    ],
    "name:war_x_preferred":[
        "Fahrni"
    ],
    "name:zho_x_preferred":[
        "\u6cd5\u723e\u5c3c"
    ],
    "qs_pg:aaroncc":"CH",
    "qs_pg:gn_country":"CH",
    "qs_pg:gn_fcode":"PPL",
    "qs_pg:gn_pop":722,
    "qs_pg:name":"Fahrni",
    "qs_pg:name_adm0":"Schweiz",
    "qs_pg:name_adm1":"Kanton Bern",
    "qs_pg:photos_9k":1,
    "qs_pg:photos_9r":1,
    "qs_pg:photos_all":2,
    "qs_pg:photos_sr":0,
    "qs_pg:pop_sr":2,
    "qs_pg:qs_pg_placetype":"locality",
    "qs_pg:qs_pg_placetype_gp":"Town",
    "qs_pg:woe_adm0":23424957,
    "woe:adm0_id":23424957,
    "woe:name_adm0":"Schweiz",
    "woe:name_adm1":"Kanton Bern",
    "woe:placetype":"Town",
    "wof:name":"Fahrni",
    "wof:placetype":"locality",
    "wof:population":722
},
  "geometry": {"coordinates":[7.66971,46.79671],"type":"Point"}
}