{
  "type": "Feature",
  "properties": {
    "gn:admin1_code":"TG",
    "gn:admin2_code":"2013.0",
    "gn:admin3_code":"4641.0",
    "gn:asciiname":"Seealp",
    "gn:country_code":"CH",
    "gn:dem":406,
    "gn:feature_class":"P",
    "gn:feature_code":"PPLL",
    "gn:name":"Seealp",
    "gn:population":0,
    "gn:timezone":"Europe/Zurich",
    "iso:country":"CH",
    "name:deu_x_preferred":[
        "Seealp"
    ],
    "wof:name":"Seealp",
    "wof:placetype":"locality"
},
  "geometry": {"coordinates":[9.27511,47.61858],"type":"Point"}
}