{
  "type": "Feature",
  "properties": {
    "gn:admin1_code":"TG",
    "gn:admin2_code":"2013.0",
    "gn:admin3_code":"4656.0",
    "gn:asciiname":"Hoheneich",
    "gn:country_code":"CH",
    "gn:dem":478,
    "gn:feature_class":"P",
    "gn:feature_code":"PPLL",
    "gn:name":"Hoheneich",
    "gn:population":0,
    "gn:timezone":"Europe/Zurich",
    "iso:country":"CH",
    "name:ceb_x_preferred":[
        "Hoheneich"
    ],
    "name:ces_x_preferred":[
        "Hoheneich"
    ],
    "name:deu_x_preferred":[
        "Hoheneich"
    ],
    "name:epo_x_preferred":[
        "Hoheneich"
    ],
    "name:fas_x_preferred":[
        "\u0647\u0648\u0647\u0646\u06cc\u0634"
    ],
    "name:fra_x_preferred":[
        "Hoheneich"
    ],
    "name:hun_x_preferred":[
        "Hoheneich"
    ],
    "name:ita_x_preferred":[
        "Hoheneich"
    ],
    "name:kaz_x_preferred":[
        "\u0425\u043e\u044d\u043d\u0430\u0439\u0445"
    ],
    "name:nld_x_preferred":[
        "Hoheneich"
    ],
    "name:pol_x_preferred":[
        "Hoheneich"
    ],
    "name:por_x_preferred":[
        "Hoheneich"
    ],
    "name:rus_x_preferred":[
        "\u0425\u043e\u044d\u043d\u0430\u0439\u0445"
    ],
    "name:slk_x_preferred":[
        "Hoheneich"
    ],
    "name:spa_x_preferred":[
        "Hoheneich"
    ],
    "name:swe_x_preferred":[
        "Hoheneich"
    ],
    "name:uzb_x_preferred":[
        "Hoheneich"
    ],
    "name:vie_x_preferred":[
        "Hoheneich"
    ],
    "name:vol_x_preferred":[
        "Hoheneich"
    ],
    "name:war_x_preferred":[
        "Hoheneich"
    ],
    "name:zho_x_preferred":[
        "\u970d\u8d6b\u5948\u5e0c"
    ],
    "wof:name":"Hoheneich",
    "wof:placetype":"neighbourhood"
},
  "geometry": {"coordinates":[9.29557,47.58938],"type":"Point"}
}