{
  "type": "Feature",
  "properties": {
    "gn:admin1_code":"TG",
    "gn:admin2_code":"2014.0",
    "gn:admin3_code":"4761.0",
    "gn:asciiname":"Wiezikon",
    "gn:country_code":"CH",
    "gn:dem":572,
    "gn:elevation":"565.0",
    "gn:feature_class":"P",
    "gn:feature_code":"PPL",
    "gn:name":"Wiezikon",
    "gn:population":0,
    "gn:timezone":"Europe/Zurich",
    "iso:country":"CH",
    "name:deu_x_preferred":[
        "Wiezikon b Sirnach"
    ],
    "wof:name":"Wiezikon",
    "wof:placetype":"locality"
},
  "geometry": {"coordinates":[8.98748,47.45132],"type":"Point"}
}