{
  "type": "Feature",
  "properties": {
    "gn:admin1_code":"NW",
    "gn:admin2_code":"700.0",
    "gn:admin3_code":"1503.0",
    "gn:asciiname":"Unter Wissiflueeli",
    "gn:country_code":"CH",
    "gn:dem":597,
    "gn:feature_class":"P",
    "gn:feature_code":"PPL",
    "gn:name":"Unter Wissifl\u00fceli",
    "gn:population":0,
    "gn:timezone":"Europe/Zurich",
    "iso:country":"CH",
    "name:und_x_variant":[
        "Unter Wissifl\u00fceli",
        "Unter Wyssifl\u00fceli"
    ],
    "wof:name":"Unter Wissiflueeli",
    "wof:placetype":"locality"
},
  "geometry": {"coordinates":[8.38894,46.91862],"type":"Point"}
}