{
  "type": "Feature",
  "properties": {
    "gn:country":"CH",
    "gn:fcode":"PPLX",
    "gn:population":5031,
    "iso:country":"CH",
    "name:eng_x_preferred":[
        "Wallisellen-Ost"
    ],
    "name:eng_x_variant":[
        "Wallisellen / Wallisellen-Ost"
    ],
    "qs_pg:aaroncc":"CH",
    "qs_pg:gn_country":"CH",
    "qs_pg:gn_fcode":"PPLX",
    "qs_pg:gn_pop":5031,
    "qs_pg:name":"Wallisellen / Wallisellen-Ost",
    "qs_pg:photos_9r":0,
    "qs_pg:photos_sr":0,
    "qs_pg:pop_sr":5,
    "qs_pg:qs_pg_placetype":"neighbourhood",
    "wof:name":"Wallisellen-Ost",
    "wof:placetype":"neighbourhood",
    "wof:population":5031
},
  "geometry": {"coordinates":[8.59727,47.41446],"type":"Point"}
}