{
  "type": "Feature",
  "properties": {
    "gn:gn_country":"CH",
    "gn:gn_fcode":"PPL",
    "gn:gn_pop":437,
    "gn:population":437,
    "iso:country":"CH",
    "name:bul_x_preferred":[
        "\u0412\u0430\u0443\u0444\u0435\u043b\u0438\u043d"
    ],
    "name:cat_x_preferred":[
        "Vauffelin"
    ],
    "name:chv_x_preferred":[
        "\u0412\u043e\u0444\u043b\u0435\u043d"
    ],
    "name:deu_x_preferred":[
        "Vauffelin"
    ],
    "name:eng_x_preferred":[
        "Vauffelin"
    ],
    "name:epo_x_preferred":[
        "Vauffelin"
    ],
    "name:fra_x_preferred":[
        "Vauffelin"
    ],
    "name:gsw_x_preferred":[
        "Vauffelin"
    ],
    "name:hun_x_preferred":[
        "Vauffelin"
    ],
    "name:ita_x_preferred":[
        "Vauffelin"
    ],
    "name:kaz_x_preferred":[
        "\u0412\u043e\u0444\u043b\u0435\u043d"
    ],
    "name:lmo_x_preferred":[
        "Vauffelin"
    ],
    "name:msa_x_preferred":[
        "Vauffelin"
    ],
    "name:nld_x_preferred":[
        "Vauffelin"
    ],
    "name:nno_x_preferred":[
        "Vauffelin"
    ],
    "name:oci_x_preferred":[
        "Vauffelin"
    ],
    "name:por_x_preferred":[
        "Vauffelin"
    ],
    "name:rus_x_preferred":[
        "\u0412\u043e\u0444\u043b\u0435\u043d"
    ],
    "name:spa_x_preferred":[
        "Vauffelin"
    ],
    "name:sqi_x_preferred":[
        "Vauffelin"
    ],
    "name:swe_x_preferred":[
        "Vauffelin"
    ],
    "name:vie_x_preferred":[
        "Vauffelin"
    ],
    "name:vol_x_preferred":[
        "Vauffelin"
    ],
    "name:war_x_preferred":[
        "Vauffelin"
    ],
    "name:zho_x_preferred":[
        "\u798f\u5f17\u6797"
    ],
    "qs_pg:aaroncc":"CH",
    "qs_pg:gn_country":"CH",
    "qs_pg:gn_fcode":"PPL",
    "qs_pg:gn_pop":437,
    "qs_pg:name":"Vauffelin",
    "qs_pg:name_adm0":"Schweiz",
    "qs_pg:name_adm1":"Kanton Bern",
    "qs_pg:photos_9k":1,
    "qs_pg:photos_9r":1,
    "qs_pg:photos_all":3,
    "qs_pg:photos_sr":0,
    "qs_pg:pop_sr":2,
    "qs_pg:qs_pg_placetype":"locality",
    "qs_pg:qs_pg_placetype_gp":"Town",
    "qs_pg:woe_adm0":23424957,
    "woe:adm0_id":23424957,
    "woe:name_adm0":"Schweiz",
    "woe:name_adm1":"Kanton Bern",
    "woe:placetype":"Town",
    "wof:name":"Vauffelin",
    "wof:placetype":"locality",
    "wof:population":437
},
  "geometry": {"coordinates":[7.3001,47.18731],"type":"Point"}
}