{
  "type": "Feature",
  "properties": {
    "gn:admin1_code":"TI",
    "gn:admin2_code":"2105.0",
    "gn:admin3_code":"5144.0",
    "gn:asciiname":"Grumo",
    "gn:country_code":"CH",
    "gn:dem":717,
    "gn:feature_class":"P",
    "gn:feature_code":"PPL",
    "gn:name":"Grumo",
    "gn:population":0,
    "gn:timezone":"Europe/Zurich",
    "iso:country":"CH",
    "name:ita_x_preferred":[
        "Grumo"
    ],
    "wof:name":"Grumo",
    "wof:placetype":"neighbourhood"
},
  "geometry": {"coordinates":[8.99648,45.95666],"type":"Point"}
}