{
  "type": "Feature",
  "properties": {
    "gn:admin1_code":"BE",
    "gn:admin2_code":"245.0",
    "gn:admin3_code":"955.0",
    "gn:asciiname":"Hofgraben",
    "gn:country_code":"CH",
    "gn:dem":738,
    "gn:feature_class":"P",
    "gn:feature_code":"PPLL",
    "gn:name":"Hofgraben",
    "gn:population":0,
    "gn:timezone":"Europe/Zurich",
    "iso:country":"CH",
    "name:deu_x_preferred":[
        "Hofgraben"
    ],
    "wof:name":"Hofgraben",
    "wof:placetype":"neighbourhood"
},
  "geometry": {"coordinates":[7.71743,47.03629],"type":"Point"}
}