{
  "type": "Feature",
  "properties": {
    "gn:country":"CH",
    "gn:fcode":"PPLL",
    "gn:population":9,
    "iso:country":"CH",
    "name:deu_x_preferred":[
        "Scheller"
    ],
    "name:fra_x_preferred":[
        "Scheller"
    ],
    "name:nds_x_preferred":[
        "Scheller"
    ],
    "name:rus_x_preferred":[
        "\u0428\u0435\u043b\u043b\u0435\u0440"
    ],
    "name:swe_x_preferred":[
        "Scheller"
    ],
    "qs_pg:aaroncc":"CH",
    "qs_pg:gn_country":"CH",
    "qs_pg:gn_fcode":"PPLL",
    "qs_pg:gn_pop":9,
    "qs_pg:name":"Scheller",
    "qs_pg:photos_9r":0,
    "qs_pg:photos_sr":0,
    "qs_pg:pop_sr":1,
    "qs_pg:qs_pg_placetype":"locality",
    "wof:lang_x_official":[
        "deu",
        "fra",
        "gsw",
        "ita"
    ],
    "wof:lang_x_spoken":[
        "deu",
        "fra",
        "gsw",
        "ita",
        "roh"
    ],
    "wof:name":"Scheller",
    "wof:placetype":"neighbourhood",
    "wof:population":9
},
  "geometry": {"coordinates":[8.48728,47.29034],"type":"Point"}
}