{
  "type": "Feature",
  "properties": {
    "gn:admin1_code":"SG",
    "gn:admin2_code":"1727.0",
    "gn:admin3_code":"3374.0",
    "gn:asciiname":"St. Loretto",
    "gn:country_code":"CH",
    "gn:dem":632,
    "gn:elevation":"629.0",
    "gn:feature_class":"P",
    "gn:feature_code":"PPL",
    "gn:name":"St. Loretto",
    "gn:population":0,
    "gn:timezone":"Europe/Zurich",
    "iso:country":"CH",
    "wof:lang_x_official":[
        "deu",
        "fra",
        "gsw",
        "ita"
    ],
    "wof:lang_x_spoken":[
        "deu",
        "fra",
        "gsw",
        "ita",
        "roh"
    ],
    "wof:name":"St. Loretto",
    "wof:placetype":"neighbourhood"
},
  "geometry": {"coordinates":[9.08594,47.3328],"type":"Point"}
}