{
  "type": "Feature",
  "properties": {
    "gn:gn_country":"CH",
    "gn:gn_fcode":"PPL",
    "gn:gn_pop":1104,
    "gn:population":1104,
    "iso:country":"CH",
    "name:baq_x_preferred":[
        "Le Vaud"
    ],
    "name:cat_x_preferred":[
        "Le Vaud"
    ],
    "name:chi_x_preferred":[
        "\u52d2\u6c83"
    ],
    "name:dut_x_preferred":[
        "Le Vaud"
    ],
    "name:eng_x_preferred":[
        "Le Vaud"
    ],
    "name:epo_x_preferred":[
        "Le Vaud"
    ],
    "name:fre_x_preferred":[
        "Le Vaud"
    ],
    "name:ger_x_preferred":[
        "Le Vaud"
    ],
    "name:gsw_x_preferred":[
        "Le Vaud"
    ],
    "name:hun_x_preferred":[
        "Le Vaud"
    ],
    "name:ita_x_preferred":[
        "Le Vaud"
    ],
    "name:lmo_x_preferred":[
        "Le Vaud"
    ],
    "name:ltz_x_preferred":[
        "Le Vaud"
    ],
    "name:may_x_preferred":[
        "Le Vaud"
    ],
    "name:nno_x_preferred":[
        "Le Vaud"
    ],
    "name:oci_x_preferred":[
        "Le Vaud"
    ],
    "name:roh_x_preferred":[
        "Le Vaud"
    ],
    "name:spa_x_preferred":[
        "Le Vaud"
    ],
    "name:unk_x_variant":[
        "Vaud"
    ],
    "name:vol_x_preferred":[
        "Le Vaud"
    ],
    "name:war_x_preferred":[
        "Le Vaud"
    ],
    "qs_pg:aaroncc":"CH",
    "qs_pg:gn_country":"CH",
    "qs_pg:gn_fcode":"PPL",
    "qs_pg:gn_pop":1104,
    "qs_pg:name":"Le Vaud",
    "qs_pg:name_adm0":"Schweiz",
    "qs_pg:name_adm1":"Canton de Vaud",
    "qs_pg:photos":170,
    "qs_pg:photos_1k":34,
    "qs_pg:photos_9k":1,
    "qs_pg:photos_9r":4,
    "qs_pg:photos_all":170,
    "qs_pg:photos_sr":4,
    "qs_pg:pop_sr":3,
    "qs_pg:qs_pg_placetype":"locality",
    "qs_pg:qs_pg_placetype_gp":"Town",
    "qs_pg:woe_adm0":23424957,
    "woe:adm0_id":23424957,
    "woe:name_adm0":"Schweiz",
    "woe:name_adm1":"Canton de Vaud",
    "woe:placetype":"Town",
    "wof:name":"Le Vaud",
    "wof:placetype":"locality",
    "wof:population":1104
},
  "geometry": {"coordinates":[6.23603,46.47753],"type":"Point"}
}