{
  "type": "Feature",
  "properties": {
    "gn:admin1_code":"BE",
    "gn:admin2_code":"250.0",
    "gn:admin3_code":"584.0",
    "gn:asciiname":"Boden",
    "gn:country_code":"CH",
    "gn:dem":1466,
    "gn:feature_class":"P",
    "gn:feature_code":"PPL",
    "gn:name":"Boden",
    "gn:population":0,
    "gn:timezone":"Europe/Zurich",
    "iso:country":"CH",
    "name:ceb_x_preferred":[
        "Boden"
    ],
    "name:deu_x_preferred":[
        "Boden"
    ],
    "name:epo_x_preferred":[
        "Boden"
    ],
    "name:est_x_preferred":[
        "Boden"
    ],
    "name:fin_x_preferred":[
        "Boden"
    ],
    "name:fra_x_preferred":[
        "Boden"
    ],
    "name:heb_x_preferred":[
        "\u05d1\u05d5\u05d3\u05df"
    ],
    "name:hrv_x_preferred":[
        "Boden"
    ],
    "name:ita_x_preferred":[
        "Boden"
    ],
    "name:nld_x_preferred":[
        "Boden"
    ],
    "name:pol_x_preferred":[
        "Boden"
    ],
    "name:rus_x_preferred":[
        "\u0411\u0443\u0434\u0435\u043d"
    ],
    "name:swe_x_preferred":[
        "Boden"
    ],
    "name:ukr_x_preferred":[
        "\u0411\u0443\u0434\u0435\u043d"
    ],
    "wof:name":"Boden",
    "wof:placetype":"neighbourhood"
},
  "geometry": {"coordinates":[7.92845,46.58878],"type":"Point"}
}