{
  "type": "Feature",
  "properties": {
    "gn:gn_country":"CH",
    "gn:gn_fcode":"PPLX",
    "gn:gn_pop":977,
    "gn:population":977,
    "iso:country":"CH",
    "name:eng_x_preferred":[
        "Butzen"
    ],
    "name:eng_x_variant":[
        "Affoltern / Butzen"
    ],
    "name:unk_x_variant":[
        "Butzen"
    ],
    "qs_pg:aaroncc":"CH",
    "qs_pg:gn_country":"CH",
    "qs_pg:gn_fcode":"PPLX",
    "qs_pg:gn_pop":977,
    "qs_pg:name":"Affoltern / Butzen",
    "qs_pg:photos_9r":0,
    "qs_pg:photos_sr":0,
    "qs_pg:pop_sr":2,
    "qs_pg:qs_pg_placetype":"neighbourhood",
    "wof:name":"Butzen",
    "wof:placetype":"neighbourhood",
    "wof:population":977
},
  "geometry": {"coordinates":[8.45737,47.27669],"type":"Point"}
}