{
  "type": "Feature",
  "properties": {
    "gn:gn_country":"CH",
    "gn:gn_fcode":"PPL",
    "gn:gn_pop":0,
    "iso:country":"CH",
    "name:deu_x_preferred":[
        "Gwatt (Thun)"
    ],
    "qs_pg:aaroncc":"CH",
    "qs_pg:gn_country":"CH",
    "qs_pg:gn_fcode":"PPL",
    "qs_pg:gn_pop":0,
    "qs_pg:name":"Gwatt",
    "qs_pg:name_adm0":"Schweiz",
    "qs_pg:name_adm1":"Kanton Bern",
    "qs_pg:photos":339,
    "qs_pg:photos_1k":69,
    "qs_pg:photos_9k":2,
    "qs_pg:photos_9r":5,
    "qs_pg:photos_all":339,
    "qs_pg:photos_sr":5,
    "qs_pg:pop_sr":0,
    "qs_pg:qs_pg_placetype":"locality",
    "qs_pg:qs_pg_placetype_gp":"Town",
    "qs_pg:woe_adm0":23424957,
    "woe:adm0_id":23424957,
    "woe:name_adm0":"Schweiz",
    "woe:name_adm1":"Kanton Bern",
    "woe:placetype":"Town",
    "wof:name":"Gwatt",
    "wof:placetype":"locality"
},
  "geometry": {"coordinates":[7.62226,46.72044],"type":"Point"}
}