{
  "type": "Feature",
  "properties": {
    "gn:gn_country":"CH",
    "gn:gn_fcode":"PPL",
    "gn:gn_pop":264,
    "gn:population":264,
    "iso:country":"CH",
    "name:cat_x_preferred":[
        "L\u00fctschental"
    ],
    "name:ceb_x_preferred":[
        "L\u00fctschental"
    ],
    "name:chv_x_preferred":[
        "\u041b\u044e\u0447\u0435\u043d\u0442\u0430\u043b\u044c"
    ],
    "name:deu_x_preferred":[
        "L\u00fctschental"
    ],
    "name:eng_x_preferred":[
        "L\u00fctschental"
    ],
    "name:epo_x_preferred":[
        "L\u00fctschental"
    ],
    "name:eus_x_preferred":[
        "L\u00fctschental"
    ],
    "name:fin_x_preferred":[
        "L\u00fctschental"
    ],
    "name:fra_x_preferred":[
        "L\u00fctschental"
    ],
    "name:gsw_x_preferred":[
        "Litschitaal"
    ],
    "name:hun_x_preferred":[
        "L\u00fctschental"
    ],
    "name:ita_x_preferred":[
        "L\u00fctschental"
    ],
    "name:kaz_x_preferred":[
        "\u041b\u044e\u0447\u0435\u043d\u0442\u0430\u043b\u044c"
    ],
    "name:lmo_x_preferred":[
        "L\u00fctschental"
    ],
    "name:msa_x_preferred":[
        "L\u00fctschental"
    ],
    "name:nld_x_preferred":[
        "L\u00fctschental"
    ],
    "name:nno_x_preferred":[
        "L\u00fctschental"
    ],
    "name:oci_x_preferred":[
        "L\u00fctschental"
    ],
    "name:pms_x_preferred":[
        "L\u00fctschental"
    ],
    "name:pol_x_preferred":[
        "L\u00fctschental"
    ],
    "name:por_x_preferred":[
        "L\u00fctschental"
    ],
    "name:roh_x_preferred":[
        "L\u00fctschental"
    ],
    "name:rus_x_preferred":[
        "\u041b\u044e\u0447\u0435\u043d\u0442\u0430\u043b\u044c"
    ],
    "name:spa_x_preferred":[
        "L\u00fctschental"
    ],
    "name:sqi_x_preferred":[
        "L\u00fctschental"
    ],
    "name:swe_x_preferred":[
        "L\u00fctschental"
    ],
    "name:vie_x_preferred":[
        "L\u00fctschental"
    ],
    "name:vol_x_preferred":[
        "L\u00fctschental"
    ],
    "name:war_x_preferred":[
        "L\u00fctschental"
    ],
    "name:zho_x_preferred":[
        "\u5442\u8fb0\u5854\u723e"
    ],
    "qs_pg:aaroncc":"CH",
    "qs_pg:gn_country":"CH",
    "qs_pg:gn_fcode":"PPL",
    "qs_pg:gn_pop":264,
    "qs_pg:name":"L\u00fctschental",
    "qs_pg:photos_9r":0,
    "qs_pg:photos_sr":0,
    "qs_pg:pop_sr":2,
    "qs_pg:qs_pg_placetype":"locality",
    "wof:name":"L\u00fctschental",
    "wof:placetype":"neighbourhood",
    "wof:population":264
},
  "geometry": {"coordinates":[8.03689,46.6989],"type":"Point"}
}