{
  "type": "Feature",
  "properties": {
    "gn:admin1_code":"GR",
    "gn:admin2_code":"1847.0",
    "gn:admin3_code":"3823.0",
    "gn:asciiname":"Alpe di Boggio",
    "gn:country_code":"CH",
    "gn:dem":1551,
    "gn:feature_class":"P",
    "gn:feature_code":"PPL",
    "gn:name":"Alpe di Boggio",
    "gn:population":0,
    "gn:timezone":"Europe/Zurich",
    "iso:country":"CH",
    "wof:name":"Alpe di Boggio",
    "wof:placetype":"neighbourhood"
},
  "geometry": {"coordinates":[9.18333,46.35],"type":"Point"}
}